"type";"unit_name";"on_building";"total_supply";"supply"
"Unit";"Overlord";"Larva";13;0
"Building";"SpawningPool";NA;19;0
"Building";"Hatchery";NA;17;0
"Building";"Extractor";NA;23;0
"Unit";"Zergling";"Larva";24;1
"Unit";"Zergling";"Larva";24;1
"Unit";"Zergling";"Larva";24;1
"Unit";"Zergling";"Larva";24;1
"Unit";"Queen";"Hatchery";23;2
"Unit";"Overlord";"Larva";24;0
"Unit";"Overlord";"Larva";24;0
"Unit";"Queen";"Hatchery";24;2
"Building";"Hatchery";NA;23;0
"Unit";"Queen";"Hatchery";37;2
"Unit";"Overlord";"Larva";47;0
"Unit";"Overlord";"Larva";48;0
"Building";"SporeCrawler";NA;53;0
"Building";"SporeCrawler";NA;53;0
"Unit";"Zergling";"Larva";53;1
"Unit";"Zergling";"Larva";53;1
"Unit";"Zergling";"Larva";53;1
"Unit";"Zergling";"Larva";53;1
"Unit";"Zergling";"Larva";55;1
"Unit";"Zergling";"Larva";55;1
"Unit";"Zergling";"Larva";55;1
"Unit";"Zergling";"Larva";55;1
"Unit";"Zergling";"Larva";55;1
"Unit";"Zergling";"Larva";55;1
"Unit";"Zergling";"Larva";55;1
"Unit";"Zergling";"Larva";55;1
"Building";"SporeCrawler";NA;55;0
"Unit";"Zergling";"Larva";68;1
"Unit";"Zergling";"Larva";68;1
"Unit";"Zergling";"Larva";68;1
"Unit";"Zergling";"Larva";68;1
"Unit";"Zergling";"Larva";68;1
"Unit";"Zergling";"Larva";68;1
"Unit";"Zergling";"Larva";68;1
"Unit";"Zergling";"Larva";68;1
"Unit";"Zergling";"Larva";68;1
"Unit";"Zergling";"Larva";68;1
"Unit";"Zergling";"Larva";68;1
"Unit";"Zergling";"Larva";68;1
"Building";"BanelingNest";NA;55;0
"Unit";"Queen";"Hatchery";59;2
"Unit";"Queen";"Hatchery";59;2
"Building";"CreepTumorQueen";NA;94;0
"Building";"CreepTumorQueen";NA;94;0
"Building";"CreepTumorQueen";NA;94;0
"Building";"CreepTumorQueen";NA;94;0
"Building";"CreepTumorQueen";NA;94;0
"Building";"CreepTumorQueen";NA;94;0
"Unit";"Baneling";"Zergling";94;0
"Unit";"Baneling";"Zergling";94;0
"Unit";"Overlord";"Larva";98;0
"Unit";"Overlord";"Larva";98;0
"Building";"CreepTumor";NA;99;0
"Building";"CreepTumor";NA;99;0
"Building";"CreepTumor";NA;99;0
"Building";"CreepTumor";NA;99;0
"Building";"CreepTumor";NA;99;0
"Building";"CreepTumor";NA;99;0
"Unit";"Queen";"Hatchery";98;2
"Unit";"Zergling";"Larva";99;1
"Unit";"Zergling";"Larva";99;1
"Unit";"Zergling";"Larva";99;1
"Unit";"Zergling";"Larva";99;1
"Unit";"Zergling";"Larva";99;1
"Unit";"Zergling";"Larva";99;1
"Unit";"Zergling";"Larva";99;1
"Unit";"Zergling";"Larva";99;1
"Unit";"Zergling";"Larva";99;1
"Unit";"Zergling";"Larva";99;1
"Building";"CreepTumorQueen";NA;99;0
"Building";"CreepTumorQueen";NA;99;0
"Unit";"Queen";"Hatchery";99;2
"Building";"CreepTumor";NA;122;0
"Building";"CreepTumor";NA;122;0
"Building";"Extractor";NA;119;0
"Building";"CreepTumor";NA;122;0
"Building";"Extractor";NA;119;0
"Building";"CreepTumor";NA;122;0
"Building";"CreepTumor";NA;122;0
"Building";"CreepTumor";NA;122;0
"Building";"Extractor";NA;119;0
"Building";"Extractor";NA;119;0
"Building";"CreepTumorQueen";NA;122;0
"Unit";"Overlord";"Larva";125;0
"Building";"RoachWarren";NA;119;0
"Unit";"Overlord";"Larva";130;0
"Unit";"Overlord";"Larva";130;0
"Building";"EvolutionChamber";NA;130;0
"Building";"CreepTumor";NA;131;0
"Building";"CreepTumor";NA;131;0
"Building";"CreepTumor";NA;131;0
"Building";"CreepTumor";NA;131;0
"Building";"EvolutionChamber";NA;130;0
"Building";"CreepTumor";NA;131;0
"Building";"HydraliskDen";NA;130;0
"Building";"CreepTumorQueen";NA;141;0
"Building";"CreepTumorQueen";NA;141;0
"Building";"CreepTumorQueen";NA;141;0
"Building";"CreepTumorQueen";NA;141;0
"Building";"CreepTumorQueen";NA;141;0
"Building";"CreepTumor";NA;141;0
"Building";"Hatchery";NA;122;0
"Building";"CreepTumor";NA;141;0
"Unit";"Overlord";"Larva";141;0
"Building";"Extractor";NA;141;0
"Building";"SporeCrawler";NA;141;0
"Building";"CreepTumorQueen";NA;151;0
"Building";"CreepTumorQueen";NA;151;0
"Building";"CreepTumorQueen";NA;151;0
"Building";"CreepTumor";NA;151;0
"Building";"CreepTumor";NA;151;0
"Building";"CreepTumor";NA;151;0
"Building";"CreepTumor";NA;151;0
"Building";"CreepTumor";NA;151;0
"Building";"CreepTumor";NA;151;0
"Building";"CreepTumor";NA;157;0
"Building";"CreepTumor";NA;157;0
"Building";"CreepTumor";NA;157;0
"Building";"CreepTumor";NA;161;0
"Unit";"Overlord";"Larva";161;0
"Unit";"Overlord";"Larva";161;0
"Unit";"Overlord";"Larva";161;0
"Building";"CreepTumor";NA;161;0
"Building";"SporeCrawler";NA;161;0
"Building";"CreepTumor";NA;161;0
"Building";"CreepTumor";NA;161;0
"Building";"CreepTumor";NA;161;0
"Unit";"Queen";"Hatchery";159;2
"Unit";"Hydralisk";"Larva";161;2
"Unit";"Hydralisk";"Larva";161;2
"Unit";"Hydralisk";"Larva";161;2
"Unit";"Hydralisk";"Larva";161;2
"Unit";"Hydralisk";"Larva";161;2
"Unit";"Overlord";"Larva";161;0
"Unit";"Overlord";"Larva";161;0
"Unit";"Overlord";"Larva";161;0
"Unit";"Overlord";"Larva";161;0
"Building";"Hatchery";NA;141;0
"Building";"CreepTumor";NA;173;0
"Building";"CreepTumor";NA;173;0
"Unit";"Zergling";"Larva";161;1
"Unit";"Zergling";"Larva";161;1
"Unit";"Overlord";"Larva";161;0
"Unit";"Overlord";"Larva";161;0
"Unit";"Zergling";"Larva";161;1
"Unit";"Zergling";"Larva";161;1
"Unit";"Zergling";"Larva";161;1
"Unit";"Zergling";"Larva";161;1
"Unit";"Zergling";"Larva";161;1
"Unit";"Zergling";"Larva";161;1
"Unit";"Zergling";"Larva";161;1
"Unit";"Zergling";"Larva";161;1
"Unit";"Zergling";"Larva";161;1
"Unit";"Zergling";"Larva";161;1
"Building";"CreepTumorQueen";NA;173;0
"Building";"SporeCrawler";NA;161;0
"Building";"CreepTumor";NA;173;0
"Building";"CreepTumor";NA;173;0
"Building";"CreepTumor";NA;173;0
"Unit";"Zergling";"Larva";173;1
"Unit";"Zergling";"Larva";173;1
"Unit";"Zergling";"Larva";173;1
"Unit";"Zergling";"Larva";173;1
"Unit";"Zergling";"Larva";173;1
"Unit";"Zergling";"Larva";173;1
"Unit";"Zergling";"Larva";173;1
"Unit";"Zergling";"Larva";173;1
"Unit";"Zergling";"Larva";173;1
"Unit";"Zergling";"Larva";173;1
"Unit";"Zergling";"Larva";173;1
"Unit";"Zergling";"Larva";173;1
"Unit";"Zergling";"Larva";173;1
"Unit";"Zergling";"Larva";173;1
"Unit";"Zergling";"Larva";173;1
"Unit";"Zergling";"Larva";173;1
"Unit";"Zergling";"Larva";173;1
"Unit";"Zergling";"Larva";173;1
"Unit";"Zergling";"Larva";173;1
"Unit";"Zergling";"Larva";173;1
"Unit";"Zergling";"Larva";173;1
"Unit";"Zergling";"Larva";173;1
"Upgrade";"ZergGroundArmorsLevel1";"EvolutionChamber";151;0
"Upgrade";"ZergMeleeWeaponsLevel1";"EvolutionChamber";151;0
"Unit";"Queen";"Hatchery";173;2
"Unit";"Baneling";"Zergling";207;0
"Unit";"Baneling";"Zergling";207;0
"Unit";"Baneling";"Zergling";207;0
"Unit";"Baneling";"Zergling";207;0
"Unit";"Baneling";"Zergling";207;0
"Unit";"Baneling";"Zergling";207;0
"Unit";"Baneling";"Zergling";207;0
"Unit";"Baneling";"Zergling";207;0
"Unit";"Baneling";"Zergling";207;0
"Unit";"Baneling";"Zergling";207;0
"Unit";"Baneling";"Zergling";207;0
"Unit";"Baneling";"Zergling";207;0
"Unit";"Baneling";"Zergling";207;0
"Unit";"Baneling";"Zergling";207;0
"Upgrade";"EvolveGroovedSpines";"HydraliskDen";161;0
"Unit";"Baneling";"Zergling";207;0
"Unit";"Baneling";"Zergling";207;0
"Unit";"Baneling";"Zergling";207;0
"Unit";"Baneling";"Zergling";207;0
"Unit";"Zergling";"Larva";207;1
"Unit";"Zergling";"Larva";207;1
"Unit";"Zergling";"Larva";207;1
"Unit";"Zergling";"Larva";207;1
"Unit";"Zergling";"Larva";207;1
"Unit";"Zergling";"Larva";207;1
"Unit";"Zergling";"Larva";207;1
"Unit";"Zergling";"Larva";207;1
"Unit";"Zergling";"Larva";207;1
"Unit";"Zergling";"Larva";207;1
"Unit";"Zergling";"Larva";207;1
"Unit";"Zergling";"Larva";207;1
"Unit";"Zergling";"Larva";207;1
"Unit";"Zergling";"Larva";207;1
"Unit";"Zergling";"Larva";207;1
"Unit";"Zergling";"Larva";207;1
"Unit";"Zergling";"Larva";207;1
"Unit";"Zergling";"Larva";207;1
"Unit";"Zergling";"Larva";207;1
"Unit";"Zergling";"Larva";207;1
"Unit";"Zergling";"Larva";207;1
"Unit";"Zergling";"Larva";207;1
"Unit";"Zergling";"Larva";207;1
"Unit";"Zergling";"Larva";207;1
"Building";"InfestationPit";NA;185;0
"Unit";"Zergling";"Larva";209;1
"Unit";"Zergling";"Larva";209;1
"Unit";"Zergling";"Larva";209;1
"Unit";"Zergling";"Larva";209;1
"Unit";"Zergling";"Larva";209;1
"Unit";"Zergling";"Larva";209;1
"Unit";"Zergling";"Larva";209;1
"Unit";"Zergling";"Larva";209;1
"Unit";"Zergling";"Larva";209;1
"Unit";"Zergling";"Larva";209;1
"Unit";"Zergling";"Larva";209;1
"Unit";"Zergling";"Larva";209;1
"Unit";"Zergling";"Larva";209;1
"Unit";"Zergling";"Larva";209;1
"Unit";"Zergling";"Larva";209;1
"Unit";"Zergling";"Larva";209;1
"Unit";"Zergling";"Larva";211;1
"Unit";"Zergling";"Larva";211;1
"Unit";"Zergling";"Larva";211;1
"Unit";"Zergling";"Larva";211;1
"Unit";"Zergling";"Larva";211;1
"Unit";"Zergling";"Larva";211;1
"Unit";"Zergling";"Larva";217;1
"Unit";"Zergling";"Larva";217;1
"Unit";"Queen";"Hatchery";209;2
"Building";"CreepTumorQueen";NA;257;0
"Building";"CreepTumorQueen";NA;257;0
"Building";"CreepTumorQueen";NA;257;0
"Unit";"Zergling";"Larva";259;1
"Unit";"Zergling";"Larva";259;1
"Unit";"Zergling";"Larva";259;1
"Unit";"Zergling";"Larva";259;1
"Unit";"Zergling";"Larva";259;1
"Unit";"Zergling";"Larva";259;1
"Unit";"Zergling";"Larva";259;1
"Unit";"Zergling";"Larva";259;1
"Unit";"Zergling";"Larva";259;1
"Unit";"Zergling";"Larva";259;1
"Unit";"Zergling";"Larva";259;1
"Unit";"Zergling";"Larva";259;1
"Building";"Extractor";NA;259;0
"Building";"CreepTumor";NA;259;0
"Building";"CreepTumor";NA;259;0
"Building";"Extractor";NA;259;0
"Unit";"Hydralisk";"Larva";259;2
"Unit";"Hydralisk";"Larva";259;2
"Unit";"Hydralisk";"Larva";259;2
"Unit";"Hydralisk";"Larva";259;2
"Unit";"Hydralisk";"Larva";259;2
"Unit";"Hydralisk";"Larva";259;2
"Unit";"Hydralisk";"Larva";259;2
"Unit";"Hydralisk";"Larva";259;2
"Unit";"Hydralisk";"Larva";259;2
"Unit";"Hydralisk";"Larva";259;2
"Unit";"Queen";"Hatchery";257;2
"Unit";"Overlord";"Larva";259;0
"Unit";"Overlord";"Larva";259;0
"Building";"CreepTumor";NA;259;0
"Upgrade";"EvolveMuscularAugments";"HydraliskDen";257;0
"Building";"CreepTumor";NA;259;0
"Building";"CreepTumor";NA;271;0
"Building";"CreepTumor";NA;271;0
"Building";"CreepTumor";NA;271;0
"Unit";"Queen";"Hatchery";259;2
"Building";"CreepTumor";NA;271;0
"Building";"CreepTumor";NA;295;0
"Building";"CreepTumor";NA;297;0
"Building";"CreepTumor";NA;299;0
"Building";"CreepTumor";NA;299;0
"Unit";"Overlord";"Larva";299;0
"Unit";"Overlord";"Larva";299;0
"Unit";"Overlord";"Larva";299;0
"Unit";"Zergling";"Larva";299;1
"Unit";"Zergling";"Larva";299;1
"Unit";"Zergling";"Larva";299;1
"Unit";"Zergling";"Larva";299;1
"Unit";"Zergling";"Larva";299;1
"Unit";"Zergling";"Larva";299;1
"Unit";"Zergling";"Larva";299;1
"Unit";"Zergling";"Larva";299;1
"Unit";"Zergling";"Larva";299;1
"Unit";"Zergling";"Larva";299;1
"Unit";"Zergling";"Larva";299;1
"Unit";"Zergling";"Larva";299;1
"Unit";"Zergling";"Larva";299;1
"Unit";"Zergling";"Larva";299;1
"Unit";"Zergling";"Larva";299;1
"Unit";"Zergling";"Larva";299;1
"Unit";"Zergling";"Larva";299;1
"Unit";"Zergling";"Larva";299;1
"Unit";"Zergling";"Larva";299;1
"Unit";"Zergling";"Larva";299;1
"Unit";"Zergling";"Larva";299;1
"Unit";"Zergling";"Larva";299;1
"Unit";"Zergling";"Larva";299;1
"Unit";"Zergling";"Larva";299;1
"Unit";"Zergling";"Larva";299;1
"Unit";"Zergling";"Larva";299;1
"Unit";"Zergling";"Larva";299;1
"Unit";"Zergling";"Larva";299;1
"Unit";"Zergling";"Larva";299;1
"Unit";"Zergling";"Larva";299;1
"Unit";"Zergling";"Larva";299;1
"Unit";"Zergling";"Larva";299;1
"Unit";"Zergling";"Larva";299;1
"Unit";"Zergling";"Larva";299;1
"Building";"CreepTumor";NA;299;0
"Building";"CreepTumorQueen";NA;299;0
"Building";"CreepTumor";NA;299;0
"Building";"CreepTumorQueen";NA;299;0
"Building";"SpineCrawler";NA;299;0
"Unit";"Overlord";"Larva";299;0
"Unit";"Overlord";"Larva";299;0
"Unit";"Overlord";"Larva";299;0
"Building";"CreepTumor";NA;333;0
"Unit";"Zergling";"Larva";333;1
"Unit";"Zergling";"Larva";333;1
"Unit";"Zergling";"Larva";333;1
"Unit";"Zergling";"Larva";333;1
"Unit";"Zergling";"Larva";333;1
"Unit";"Zergling";"Larva";333;1
"Unit";"Zergling";"Larva";333;1
"Unit";"Zergling";"Larva";333;1
"Unit";"Zergling";"Larva";333;1
"Unit";"Zergling";"Larva";333;1
"Unit";"Zergling";"Larva";333;1
"Unit";"Zergling";"Larva";333;1
"Unit";"Zergling";"Larva";333;1
"Unit";"Zergling";"Larva";333;1
"Unit";"Zergling";"Larva";333;1
"Unit";"Zergling";"Larva";333;1
"Unit";"Zergling";"Larva";333;1
"Unit";"Zergling";"Larva";333;1
"Unit";"Zergling";"Larva";333;1
"Unit";"Zergling";"Larva";333;1
"Unit";"Zergling";"Larva";333;1
"Unit";"Zergling";"Larva";333;1
"Unit";"Zergling";"Larva";333;1
"Unit";"Zergling";"Larva";333;1
"Unit";"Zergling";"Larva";333;1
"Unit";"Zergling";"Larva";333;1
"Unit";"Zergling";"Larva";333;1
"Unit";"Zergling";"Larva";333;1
"Building";"SpineCrawler";NA;333;0
"Building";"Hatchery";NA;299;0
"Upgrade";"ZergGroundArmorsLevel2";"EvolutionChamber";297;0
"Upgrade";"ZergMeleeWeaponsLevel2";"EvolutionChamber";297;0
"Building";"SporeCrawler";NA;366;0
"Building";"CreepTumor";NA;366;0
"Building";"CreepTumor";NA;366;0
"Building";"CreepTumor";NA;369;0
"Building";"UltraliskCavern";NA;361;0
"Building";"SpineCrawler";NA;366;0
"Building";"CreepTumor";NA;369;0
"Building";"CreepTumor";NA;369;0
"Building";"CreepTumor";NA;369;0
"Building";"Spire";NA;361;0
"Building";"CreepTumor";NA;369;0
"Building";"CreepTumor";NA;369;0
"Building";"CreepTumor";NA;369;0
"Building";"CreepTumor";NA;369;0
"Building";"SpineCrawler";NA;369;0
"Building";"CreepTumor";NA;369;0
"Unit";"Ultralisk";"Larva";369;6
"Unit";"Ultralisk";"Larva";369;6
"Building";"CreepTumorQueen";NA;375;0
"Unit";"Ultralisk";"Larva";369;6
"Unit";"Baneling";"Zergling";375;0
"Unit";"Baneling";"Zergling";375;0
"Unit";"Baneling";"Zergling";375;0
"Unit";"Baneling";"Zergling";375;0
"Unit";"Baneling";"Zergling";375;0
"Unit";"Baneling";"Zergling";375;0
"Unit";"Baneling";"Zergling";375;0
"Unit";"Baneling";"Zergling";375;0
"Unit";"Baneling";"Zergling";375;0
"Unit";"Baneling";"Zergling";375;0
"Unit";"Baneling";"Zergling";375;0
"Unit";"Baneling";"Zergling";375;0
"Unit";"Baneling";"Zergling";375;0
"Unit";"Baneling";"Zergling";375;0
"Unit";"Baneling";"Zergling";375;0
"Unit";"Baneling";"Zergling";375;0
"Unit";"Baneling";"Zergling";375;0
"Building";"CreepTumorQueen";NA;375;0
"Building";"CreepTumor";NA;375;0
"Building";"CreepTumorQueen";NA;393;0
"Building";"CreepTumorQueen";NA;393;0
"Building";"CreepTumorQueen";NA;393;0
"Unit";"Corruptor";"Larva";393;2
"Upgrade";"ChitinousPlating";"UltraliskCavern";369;0
"Unit";"Corruptor";"Larva";393;2
"Unit";"Corruptor";"Larva";393;2
"Unit";"Corruptor";"Larva";393;2
"Building";"CreepTumor";NA;393;0
"Building";"CreepTumor";NA;401;0
"Building";"CreepTumor";NA;401;0
"Building";"CreepTumor";NA;401;0
"Building";"CreepTumor";NA;401;0
"Building";"CreepTumor";NA;401;0
"Building";"CreepTumor";NA;401;0
"Building";"CreepTumor";NA;401;0
"Building";"SporeCrawler";NA;395;0
"Building";"SporeCrawler";NA;401;0
"Unit";"Baneling";"Zergling";403;0
"Unit";"Baneling";"Zergling";403;0
"Unit";"Baneling";"Zergling";403;0
"Unit";"Baneling";"Zergling";403;0
"Unit";"Baneling";"Zergling";403;0
"Unit";"Baneling";"Zergling";403;0
"Unit";"Baneling";"Zergling";403;0
"Unit";"Baneling";"Zergling";403;0
"Unit";"Baneling";"Zergling";403;0
"Unit";"Baneling";"Zergling";403;0
"Unit";"Baneling";"Zergling";403;0
"Unit";"Baneling";"Zergling";403;0
"Unit";"Baneling";"Zergling";403;0
"Unit";"Baneling";"Zergling";403;0
"Unit";"Baneling";"Zergling";403;0
"Unit";"Baneling";"Zergling";403;0
"Unit";"Baneling";"Zergling";403;0
"Unit";"Baneling";"Zergling";403;0
"Unit";"Baneling";"Zergling";403;0
"Unit";"Baneling";"Zergling";403;0
"Unit";"Baneling";"Zergling";403;0
"Unit";"Baneling";"Zergling";403;0
"Unit";"Baneling";"Zergling";403;0
"Unit";"Baneling";"Zergling";403;0
"Unit";"Baneling";"Zergling";403;0
"Unit";"Baneling";"Zergling";403;0
"Unit";"Baneling";"Zergling";403;0
"Building";"CreepTumor";NA;403;0
"Building";"CreepTumor";NA;403;0
"Building";"CreepTumor";NA;403;0
"Building";"CreepTumor";NA;403;0
"Building";"CreepTumor";NA;403;0
"Building";"CreepTumor";NA;403;0
"Building";"CreepTumor";NA;403;0
"Building";"CreepTumor";NA;403;0
"Upgrade";"ZergGroundArmorsLevel3";"EvolutionChamber";375;0
"Upgrade";"ZergMeleeWeaponsLevel3";"EvolutionChamber";375;0
"Unit";"Zergling";"Larva";403;1
"Unit";"Zergling";"Larva";403;1
"Unit";"Zergling";"Larva";403;1
"Unit";"Zergling";"Larva";403;1
"Unit";"Zergling";"Larva";403;1
"Unit";"Zergling";"Larva";403;1
"Unit";"Zergling";"Larva";403;1
"Unit";"Zergling";"Larva";403;1
"Unit";"Zergling";"Larva";403;1
"Unit";"Zergling";"Larva";403;1
"Unit";"Zergling";"Larva";403;1
"Unit";"Zergling";"Larva";403;1
"Unit";"Zergling";"Larva";403;1
"Unit";"Zergling";"Larva";403;1
"Unit";"Zergling";"Larva";403;1
"Unit";"Zergling";"Larva";403;1
"Unit";"Zergling";"Larva";403;1
"Unit";"Zergling";"Larva";403;1
"Unit";"Zergling";"Larva";403;1
"Unit";"Zergling";"Larva";403;1
"Unit";"Zergling";"Larva";403;1
"Unit";"Zergling";"Larva";403;1
"Unit";"Zergling";"Larva";403;1
"Unit";"Zergling";"Larva";403;1
"Unit";"Zergling";"Larva";403;1
"Unit";"Zergling";"Larva";403;1
"Unit";"Corruptor";"Larva";403;2
"Unit";"Corruptor";"Larva";403;2
"Unit";"Corruptor";"Larva";403;2
"Unit";"Corruptor";"Larva";403;2
"Unit";"Corruptor";"Larva";403;2
"Unit";"Corruptor";"Larva";403;2
"Unit";"Corruptor";"Larva";403;2
"Unit";"Corruptor";"Larva";403;2
"Unit";"Corruptor";"Larva";403;2
"Unit";"Corruptor";"Larva";403;2
"Unit";"Corruptor";"Larva";403;2
"Unit";"Baneling";"Zergling";429;0
"Unit";"Baneling";"Zergling";429;0
"Unit";"Baneling";"Zergling";429;0
"Unit";"Baneling";"Zergling";429;0
"Unit";"Baneling";"Zergling";429;0
"Unit";"Baneling";"Zergling";429;0
"Unit";"Baneling";"Zergling";429;0
"Building";"CreepTumor";NA;457;0
"Building";"CreepTumor";NA;457;0
"Building";"CreepTumor";NA;457;0
"Building";"CreepTumor";NA;457;0
"Building";"CreepTumor";NA;457;0
"Building";"CreepTumor";NA;457;0
"Unit";"Viper";"Larva";457;3
"Unit";"Viper";"Larva";457;3
"Building";"CreepTumor";NA;457;0
"Building";"Spire";NA;429;0
"Building";"CreepTumor";NA;463;0
"Building";"CreepTumor";NA;463;0
"Unit";"Zergling";"Larva";463;1
"Unit";"Zergling";"Larva";463;1
"Unit";"Zergling";"Larva";463;1
"Unit";"Zergling";"Larva";463;1
"Unit";"Zergling";"Larva";463;1
"Unit";"Zergling";"Larva";463;1
"Unit";"Zergling";"Larva";463;1
"Unit";"Zergling";"Larva";463;1
"Unit";"Zergling";"Larva";463;1
"Unit";"Zergling";"Larva";463;1
"Unit";"Zergling";"Larva";463;1
"Unit";"Zergling";"Larva";463;1
"Building";"CreepTumor";NA;463;0
"Building";"SporeCrawler";NA;463;0
"Building";"CreepTumor";NA;463;0
"Building";"CreepTumor";NA;463;0
"Building";"CreepTumor";NA;463;0
"Building";"CreepTumor";NA;463;0
"Building";"SporeCrawler";NA;463;0
"Building";"CreepTumor";NA;465;0
"Building";"SporeCrawler";NA;463;0
"Building";"CreepTumor";NA;475;0
"Building";"SporeCrawler";NA;463;0
"Building";"CreepTumor";NA;475;0
"Building";"SporeCrawler";NA;463;0
"Building";"SporeCrawler";NA;463;0
"Building";"SporeCrawler";NA;463;0
"Building";"CreepTumor";NA;491;0
"Building";"CreepTumor";NA;491;0
"Building";"CreepTumor";NA;491;0
"Building";"CreepTumor";NA;491;0
"Building";"CreepTumor";NA;491;0
"Building";"CreepTumor";NA;491;0
"Building";"Extractor";NA;491;0
"Building";"Extractor";NA;491;0
"Building";"SporeCrawler";NA;491;0
"Building";"SporeCrawler";NA;491;0
"Building";"CreepTumorQueen";NA;491;0
"Building";"CreepTumorQueen";NA;491;0
"Building";"CreepTumorQueen";NA;491;0
"Building";"CreepTumorQueen";NA;491;0
"Building";"CreepTumorQueen";NA;491;0
"Building";"CreepTumorQueen";NA;491;0
"Building";"CreepTumorQueen";NA;491;0
"Building";"CreepTumorQueen";NA;491;0
"Building";"CreepTumor";NA;491;0
"Upgrade";"ZergMissileWeaponsLevel1";"EvolutionChamber";463;0
"Building";"CreepTumor";NA;491;0
"Building";"CreepTumor";NA;491;0
"Unit";"Viper";"Larva";491;3
"Building";"CreepTumor";NA;491;0
"Building";"CreepTumor";NA;491;0
"Building";"CreepTumor";NA;491;0
"Building";"CreepTumor";NA;491;0
"Building";"Extractor";NA;491;0
"Building";"CreepTumor";NA;491;0
"Building";"Extractor";NA;491;0
"Building";"CreepTumor";NA;494;0
"Building";"CreepTumor";NA;494;0
"Building";"CreepTumor";NA;494;0
"Building";"CreepTumor";NA;494;0
"Unit";"Viper";"Larva";494;3
"Unit";"Viper";"Larva";494;3
"Building";"CreepTumorQueen";NA;494;0
"Building";"CreepTumorQueen";NA;494;0
"Building";"CreepTumorQueen";NA;494;0
"Building";"CreepTumorQueen";NA;494;0
"Unit";"Viper";"Larva";494;3
"Building";"CreepTumor";NA;500;0
"Building";"CreepTumor";NA;500;0
"Building";"CreepTumor";NA;500;0
"Building";"CreepTumor";NA;500;0
"Building";"CreepTumor";NA;500;0
"Building";"Hatchery";NA;491;0
"Unit";"Viper";"Larva";500;3
"Unit";"Viper";"Larva";500;3
"Unit";"Corruptor";"Larva";500;2
"Unit";"Corruptor";"Larva";500;2
"Unit";"Corruptor";"Larva";500;2
"Building";"CreepTumor";NA;515;0
"Building";"CreepTumor";NA;515;0
"Building";"CreepTumor";NA;515;0
"Building";"CreepTumor";NA;515;0
"Building";"CreepTumor";NA;515;0
"Building";"CreepTumor";NA;515;0
"Unit";"Corruptor";"Larva";503;2
"Unit";"Corruptor";"Larva";503;2
"Unit";"Corruptor";"Larva";506;2
"Unit";"Corruptor";"Larva";509;2
"Unit";"Zergling";"Larva";515;1
"Unit";"Zergling";"Larva";515;1
"Unit";"Zergling";"Larva";515;1
"Unit";"Zergling";"Larva";515;1
"Unit";"Zergling";"Larva";515;1
"Unit";"Zergling";"Larva";515;1
"Unit";"Zergling";"Larva";515;1
"Unit";"Zergling";"Larva";515;1
"Unit";"Zergling";"Larva";515;1
"Unit";"Zergling";"Larva";515;1
"Unit";"Zergling";"Larva";515;1
"Unit";"Zergling";"Larva";515;1
"Unit";"Zergling";"Larva";515;1
"Unit";"Zergling";"Larva";515;1
"Unit";"Zergling";"Larva";515;1
"Unit";"Zergling";"Larva";515;1
"Unit";"Zergling";"Larva";515;1
"Unit";"Zergling";"Larva";515;1
"Unit";"Zergling";"Larva";515;1
"Unit";"Zergling";"Larva";515;1
"Unit";"Zergling";"Larva";515;1
"Unit";"Zergling";"Larva";515;1
"Building";"CreepTumor";NA;515;0
"Building";"CreepTumor";NA;515;0
"Building";"CreepTumor";NA;515;0
"Building";"CreepTumor";NA;515;0
"Unit";"Zergling";"Larva";545;1
"Unit";"Zergling";"Larva";545;1
"Unit";"Zergling";"Larva";545;1
"Unit";"Zergling";"Larva";545;1
"Unit";"Zergling";"Larva";545;1
"Unit";"Zergling";"Larva";545;1
"Unit";"Zergling";"Larva";545;1
"Unit";"Zergling";"Larva";545;1
"Unit";"Zergling";"Larva";545;1
"Unit";"Zergling";"Larva";545;1
"Unit";"Zergling";"Larva";545;1
"Unit";"Zergling";"Larva";545;1
"Unit";"Zergling";"Larva";545;1
"Unit";"Zergling";"Larva";545;1
"Building";"CreepTumor";NA;545;0
"Building";"CreepTumor";NA;545;0
"Building";"CreepTumor";NA;547;0
"Building";"CreepTumor";NA;559;0
"Building";"CreepTumor";NA;559;0
"Building";"CreepTumor";NA;559;0
"Building";"CreepTumor";NA;559;0
"Building";"CreepTumor";NA;559;0
"Building";"CreepTumor";NA;559;0
"Building";"CreepTumor";NA;559;0
"Building";"CreepTumorQueen";NA;559;0
"Building";"CreepTumorQueen";NA;559;0
"Building";"CreepTumorQueen";NA;559;0
"Building";"CreepTumorQueen";NA;559;0
"Building";"SporeCrawler";NA;559;0
"Building";"SporeCrawler";NA;559;0
"Building";"SporeCrawler";NA;559;0
"Unit";"Zergling";"Larva";559;1
"Unit";"Zergling";"Larva";559;1
"Unit";"Zergling";"Larva";559;1
"Unit";"Zergling";"Larva";559;1
"Unit";"Zergling";"Larva";559;1
"Unit";"Zergling";"Larva";559;1
"Unit";"Zergling";"Larva";559;1
"Unit";"Zergling";"Larva";559;1
"Unit";"Zergling";"Larva";559;1
"Unit";"Zergling";"Larva";559;1
"Unit";"Zergling";"Larva";559;1
"Unit";"Zergling";"Larva";559;1
"Unit";"Zergling";"Larva";559;1
"Unit";"Zergling";"Larva";559;1
"Unit";"Zergling";"Larva";559;1
"Unit";"Zergling";"Larva";559;1
"Unit";"Zergling";"Larva";587;1
"Unit";"Zergling";"Larva";587;1
"Unit";"Zergling";"Larva";587;1
"Unit";"Zergling";"Larva";587;1
"Unit";"Zergling";"Larva";587;1
"Unit";"Zergling";"Larva";587;1
"Unit";"Zergling";"Larva";587;1
"Unit";"Zergling";"Larva";587;1
"Unit";"Zergling";"Larva";587;1
"Unit";"Zergling";"Larva";587;1
"Building";"CreepTumor";NA;587;0
"Building";"SporeCrawler";NA;587;0
"Building";"Extractor";NA;587;0
"Building";"Extractor";NA;597;0
"Building";"SpineCrawler";NA;587;0
"Building";"SpineCrawler";NA;587;0
"Unit";"Zergling";"Larva";597;1
"Unit";"Zergling";"Larva";597;1
"Unit";"Zergling";"Larva";597;1
"Unit";"Zergling";"Larva";597;1
"Unit";"Zergling";"Larva";597;1
"Unit";"Zergling";"Larva";597;1
"Unit";"Zergling";"Larva";597;1
"Unit";"Zergling";"Larva";597;1
"Unit";"Zergling";"Larva";597;1
"Unit";"Zergling";"Larva";597;1
"Unit";"Zergling";"Larva";597;1
"Unit";"Zergling";"Larva";597;1
"Unit";"Zergling";"Larva";597;1
"Unit";"Zergling";"Larva";597;1
"Unit";"Zergling";"Larva";597;1
"Unit";"Zergling";"Larva";597;1
"Unit";"Zergling";"Larva";597;1
"Unit";"Zergling";"Larva";597;1
"Unit";"Zergling";"Larva";597;1
"Unit";"Zergling";"Larva";597;1
"Building";"Hatchery";NA;597;0
"Unit";"Baneling";"Zergling";617;0
"Unit";"Ultralisk";"Larva";597;6
"Unit";"Baneling";"Zergling";617;0
"Unit";"Baneling";"Zergling";617;0
"Unit";"Baneling";"Zergling";617;0
"Unit";"Baneling";"Zergling";617;0
"Unit";"Baneling";"Zergling";617;0
"Unit";"Ultralisk";"Larva";597;6
"Unit";"Ultralisk";"Larva";597;6
"Unit";"Baneling";"Zergling";617;0
"Unit";"Baneling";"Zergling";617;0
"Unit";"Ultralisk";"Larva";597;6
"Unit";"Hydralisk";"Larva";648;2
"Unit";"Hydralisk";"Larva";648;2
"Unit";"Hydralisk";"Larva";648;2
"Unit";"Hydralisk";"Larva";648;2
"Unit";"Hydralisk";"Larva";648;2
"Unit";"Hydralisk";"Larva";648;2
"Unit";"Hydralisk";"Larva";648;2
"Unit";"Hydralisk";"Larva";648;2
"Unit";"Hydralisk";"Larva";648;2
"Unit";"Corruptor";"Larva";648;2
"Unit";"Corruptor";"Larva";648;2
"Unit";"Corruptor";"Larva";648;2
"Unit";"Corruptor";"Larva";648;2
"Unit";"Corruptor";"Larva";648;2
"Unit";"Corruptor";"Larva";648;2
"Unit";"Corruptor";"Larva";648;2
"Unit";"Corruptor";"Larva";648;2
"Unit";"Viper";"Larva";648;3
"Unit";"Viper";"Larva";648;3
"Unit";"Viper";"Larva";648;3
"Unit";"Viper";"Larva";648;3
"Unit";"Viper";"Larva";648;3
"Unit";"Queen";"Hatchery";648;2
"Unit";"Queen";"Hatchery";648;2
"Unit";"Queen";"Hatchery";648;2
"Unit";"Queen";"Hatchery";648;2
"Building";"CreepTumor";NA;705;0
"Building";"CreepTumor";NA;705;0
"Building";"CreepTumor";NA;705;0
"Building";"CreepTumor";NA;705;0
"Building";"CreepTumor";NA;705;0
"Unit";"Zergling";"Larva";705;1
"Unit";"Zergling";"Larva";705;1
"Unit";"Zergling";"Larva";705;1
"Unit";"Zergling";"Larva";705;1
"Unit";"Zergling";"Larva";705;1
"Unit";"Zergling";"Larva";705;1
"Unit";"Zergling";"Larva";705;1
"Unit";"Zergling";"Larva";705;1
"Unit";"Zergling";"Larva";705;1
"Unit";"Zergling";"Larva";705;1
"Unit";"Zergling";"Larva";705;1
"Unit";"Zergling";"Larva";705;1
"Unit";"Zergling";"Larva";705;1
"Unit";"Zergling";"Larva";705;1
"Unit";"Zergling";"Larva";705;1
"Unit";"Zergling";"Larva";705;1
"Unit";"Zergling";"Larva";705;1
"Unit";"Zergling";"Larva";705;1
"Unit";"Zergling";"Larva";705;1
"Unit";"Zergling";"Larva";705;1
"Unit";"Zergling";"Larva";705;1
"Unit";"Zergling";"Larva";705;1
"Unit";"Zergling";"Larva";705;1
"Unit";"Zergling";"Larva";705;1
"Unit";"Zergling";"Larva";705;1
"Unit";"Zergling";"Larva";705;1
"Unit";"Zergling";"Larva";705;1
"Unit";"Zergling";"Larva";705;1
"Unit";"Zergling";"Larva";705;1
"Unit";"Zergling";"Larva";705;1
"Unit";"Zergling";"Larva";705;1
"Unit";"Zergling";"Larva";705;1
"Unit";"Zergling";"Larva";705;1
"Unit";"Zergling";"Larva";705;1
"Unit";"Zergling";"Larva";705;1
"Unit";"Zergling";"Larva";705;1
"Building";"CreepTumor";NA;705;0
"Unit";"Zergling";"Larva";705;1
"Unit";"Zergling";"Larva";705;1
"Unit";"Zergling";"Larva";705;1
"Unit";"Zergling";"Larva";705;1
"Building";"SporeCrawler";NA;741;0
"Building";"SporeCrawler";NA;741;0
"Building";"SporeCrawler";NA;741;0
"Unit";"Zergling";"Larva";745;1
"Unit";"Zergling";"Larva";745;1
"Unit";"Zergling";"Larva";745;1
"Unit";"Zergling";"Larva";745;1
"Unit";"Zergling";"Larva";745;1
"Unit";"Zergling";"Larva";745;1
"Unit";"Zergling";"Larva";745;1
"Unit";"Zergling";"Larva";745;1
"Unit";"Zergling";"Larva";745;1
"Unit";"Zergling";"Larva";745;1
"Building";"Hatchery";NA;755;0
"Building";"CreepTumorQueen";NA;762;0
"Building";"CreepTumorQueen";NA;762;0
"Upgrade";"ZergMissileWeaponsLevel2";"EvolutionChamber";745;0
"Building";"CreepTumorQueen";NA;762;0
"Building";"CreepTumorQueen";NA;762;0
"Unit";"Zergling";"Larva";762;1
"Unit";"Zergling";"Larva";762;1
"Unit";"Zergling";"Larva";762;1
"Unit";"Zergling";"Larva";762;1
"Unit";"Zergling";"Larva";762;1
"Unit";"Zergling";"Larva";762;1
"Unit";"Zergling";"Larva";762;1
"Unit";"Zergling";"Larva";762;1
"Unit";"Hydralisk";"Larva";770;2
"Unit";"Hydralisk";"Larva";770;2
"Unit";"Hydralisk";"Larva";770;2
"Unit";"Hydralisk";"Larva";770;2
"Unit";"Hydralisk";"Larva";770;2
"Unit";"Hydralisk";"Larva";770;2
"Unit";"Hydralisk";"Larva";770;2
"Unit";"Hydralisk";"Larva";770;2
"Building";"CreepTumor";NA;786;0
"Building";"CreepTumor";NA;786;0
"Building";"CreepTumor";NA;786;0
"Building";"CreepTumor";NA;786;0
"Building";"CreepTumor";NA;786;0
"Unit";"Zergling";"Larva";786;1
"Unit";"Zergling";"Larva";786;1
"Unit";"Zergling";"Larva";786;1
"Unit";"Zergling";"Larva";786;1
"Unit";"Zergling";"Larva";786;1
"Unit";"Zergling";"Larva";786;1
"Unit";"Zergling";"Larva";786;1
"Unit";"Zergling";"Larva";786;1
"Unit";"Zergling";"Larva";786;1
"Unit";"Zergling";"Larva";786;1
"Unit";"Zergling";"Larva";786;1
"Unit";"Zergling";"Larva";786;1
"Unit";"Zergling";"Larva";786;1
"Unit";"Zergling";"Larva";786;1
"Unit";"Zergling";"Larva";786;1
"Unit";"Zergling";"Larva";786;1
"Unit";"Zergling";"Larva";786;1
"Unit";"Zergling";"Larva";786;1
"Unit";"Zergling";"Larva";786;1
"Unit";"Zergling";"Larva";786;1
"Unit";"Zergling";"Larva";786;1
"Unit";"Zergling";"Larva";786;1
"Unit";"Zergling";"Larva";786;1
"Unit";"Zergling";"Larva";786;1
"Unit";"Zergling";"Larva";786;1
"Unit";"Zergling";"Larva";786;1
"Unit";"Zergling";"Larva";786;1
"Unit";"Zergling";"Larva";786;1
"Unit";"Zergling";"Larva";786;1
"Unit";"Zergling";"Larva";786;1
"Unit";"Zergling";"Larva";786;1
"Unit";"Zergling";"Larva";786;1
"Unit";"Zergling";"Larva";786;1
"Unit";"Zergling";"Larva";786;1
"Unit";"Zergling";"Larva";786;1
"Unit";"Zergling";"Larva";786;1
"Unit";"Zergling";"Larva";786;1
"Unit";"Zergling";"Larva";786;1
"Unit";"Queen";"Hatchery";800;2
"Unit";"Queen";"Hatchery";808;2
"Unit";"Queen";"Hatchery";816;2
"Unit";"Queen";"Hatchery";824;2
"Unit";"Queen";"Hatchery";824;2
"Unit";"Queen";"Hatchery";824;2
"Building";"SporeCrawler";NA;824;0
"Building";"SporeCrawler";NA;824;0
"Building";"SporeCrawler";NA;824;0
"Building";"CreepTumor";NA;836;0
"Building";"CreepTumor";NA;836;0
"Unit";"Zergling";"Larva";836;1
"Unit";"Zergling";"Larva";836;1
"Unit";"Zergling";"Larva";836;1
"Unit";"Zergling";"Larva";836;1
"Unit";"Zergling";"Larva";836;1
"Unit";"Zergling";"Larva";836;1
"Unit";"Zergling";"Larva";836;1
"Unit";"Zergling";"Larva";836;1
"Unit";"Zergling";"Larva";836;1
"Unit";"Zergling";"Larva";836;1
"Unit";"Zergling";"Larva";836;1
"Unit";"Zergling";"Larva";836;1
"Unit";"Zergling";"Larva";836;1
"Unit";"Zergling";"Larva";836;1
"Unit";"Zergling";"Larva";836;1
"Unit";"Zergling";"Larva";836;1
"Unit";"Zergling";"Larva";836;1
"Unit";"Zergling";"Larva";836;1
"Building";"CreepTumor";NA;836;0
"Unit";"Zergling";"Larva";836;1
"Unit";"Zergling";"Larva";836;1
"Unit";"Zergling";"Larva";836;1
"Unit";"Zergling";"Larva";836;1
"Unit";"Zergling";"Larva";836;1
"Unit";"Zergling";"Larva";836;1
"Unit";"Zergling";"Larva";836;1
"Unit";"Zergling";"Larva";836;1
"Unit";"Zergling";"Larva";836;1
"Unit";"Zergling";"Larva";836;1
"Unit";"Zergling";"Larva";836;1
"Unit";"Zergling";"Larva";836;1
"Unit";"Zergling";"Larva";836;1
"Unit";"Zergling";"Larva";836;1
"Unit";"Zergling";"Larva";836;1
"Unit";"Zergling";"Larva";836;1
"Unit";"Zergling";"Larva";836;1
"Unit";"Zergling";"Larva";836;1
"Building";"CreepTumor";NA;836;0
"Building";"CreepTumor";NA;836;0
"Building";"CreepTumorQueen";NA;872;0
"Building";"CreepTumorQueen";NA;872;0
"Building";"CreepTumor";NA;872;0
"Building";"CreepTumor";NA;872;0
"Building";"CreepTumor";NA;872;0
"Building";"CreepTumor";NA;872;0
"Building";"CreepTumor";NA;872;0
"Building";"CreepTumor";NA;872;0
"Upgrade";"ZergMissileWeaponsLevel3";"EvolutionChamber";836;0
"Building";"CreepTumor";NA;872;0
"Building";"CreepTumor";NA;872;0
"Building";"CreepTumor";NA;872;0
"Building";"CreepTumor";NA;872;0
"Unit";"Corruptor";"Larva";872;2
"Unit";"Corruptor";"Larva";872;2
"Unit";"Corruptor";"Larva";872;2
"Unit";"Corruptor";"Larva";872;2
"Unit";"Corruptor";"Larva";872;2
"Unit";"Corruptor";"Larva";872;2
"Unit";"Corruptor";"Larva";872;2
"Unit";"Corruptor";"Larva";872;2
"Building";"CreepTumorQueen";NA;872;0
"Building";"CreepTumorQueen";NA;872;0
"Unit";"Viper";"Larva";872;3
"Unit";"Viper";"Larva";872;3
"Unit";"Viper";"Larva";872;3
"Building";"CreepTumor";NA;888;0
"Unit";"Corruptor";"Larva";872;2
"Unit";"Corruptor";"Larva";872;2
"Unit";"Corruptor";"Larva";872;2
"Unit";"Corruptor";"Larva";872;2
"Unit";"Corruptor";"Larva";872;2
"Unit";"Zergling";"Larva";907;1
"Unit";"Zergling";"Larva";907;1
"Unit";"Zergling";"Larva";907;1
"Unit";"Zergling";"Larva";907;1
"Unit";"Zergling";"Larva";907;1
"Unit";"Zergling";"Larva";907;1
"Unit";"Zergling";"Larva";907;1
"Unit";"Zergling";"Larva";907;1
"Unit";"Zergling";"Larva";907;1
"Unit";"Zergling";"Larva";907;1
"Unit";"Zergling";"Larva";907;1
"Unit";"Zergling";"Larva";907;1
"Unit";"Zergling";"Larva";907;1
"Unit";"Zergling";"Larva";907;1
"Unit";"Zergling";"Larva";907;1
"Unit";"Zergling";"Larva";907;1
"Unit";"Zergling";"Larva";907;1
"Unit";"Zergling";"Larva";907;1
"Unit";"Zergling";"Larva";907;1
"Unit";"Zergling";"Larva";907;1
"Unit";"Zergling";"Larva";907;1
"Unit";"Zergling";"Larva";907;1
"Unit";"Zergling";"Larva";907;1
"Unit";"Zergling";"Larva";907;1
"Unit";"Zergling";"Larva";907;1
"Unit";"Zergling";"Larva";907;1
"Unit";"Zergling";"Larva";907;1
"Unit";"Zergling";"Larva";907;1
"Unit";"Zergling";"Larva";907;1
"Unit";"Zergling";"Larva";907;1
"Unit";"Zergling";"Larva";907;1
"Unit";"Zergling";"Larva";907;1
"Unit";"Zergling";"Larva";907;1
"Unit";"Zergling";"Larva";907;1
"Unit";"Zergling";"Larva";907;1
"Unit";"Zergling";"Larva";907;1
"Unit";"Zergling";"Larva";907;1
"Unit";"Zergling";"Larva";907;1
"Unit";"Zergling";"Larva";907;1
"Unit";"Zergling";"Larva";907;1
"Unit";"Zergling";"Larva";907;1
"Unit";"Zergling";"Larva";907;1
"Building";"CreepTumor";NA;907;0
"Building";"CreepTumor";NA;907;0
"Building";"CreepTumor";NA;907;0
"Unit";"Baneling";"Zergling";949;0
"Unit";"Baneling";"Zergling";949;0
"Unit";"Baneling";"Zergling";949;0
"Unit";"Baneling";"Zergling";949;0
"Unit";"Baneling";"Zergling";949;0
"Unit";"Baneling";"Zergling";949;0
"Unit";"Baneling";"Zergling";949;0
"Unit";"Baneling";"Zergling";949;0
"Unit";"Baneling";"Zergling";949;0
"Unit";"Viper";"Larva";949;3
"Unit";"Viper";"Larva";949;3
"Building";"SporeCrawler";NA;949;0
"Building";"SporeCrawler";NA;949;0
"Building";"SporeCrawler";NA;949;0
"Building";"SporeCrawler";NA;949;0
"Unit";"Zergling";"Larva";955;1
"Unit";"Zergling";"Larva";955;1
"Unit";"Zergling";"Larva";955;1
"Unit";"Zergling";"Larva";955;1
"Unit";"Zergling";"Larva";955;1
"Unit";"Zergling";"Larva";955;1
"Unit";"Zergling";"Larva";955;1
"Unit";"Zergling";"Larva";955;1
"Unit";"Zergling";"Larva";955;1
"Unit";"Zergling";"Larva";955;1
"Unit";"Zergling";"Larva";955;1
"Unit";"Zergling";"Larva";955;1
"Unit";"Zergling";"Larva";955;1
"Unit";"Zergling";"Larva";955;1
"Unit";"Zergling";"Larva";955;1
"Unit";"Zergling";"Larva";955;1
"Unit";"Zergling";"Larva";955;1
"Unit";"Zergling";"Larva";955;1
"Unit";"Zergling";"Larva";955;1
"Unit";"Zergling";"Larva";955;1
"Unit";"Zergling";"Larva";955;1
"Unit";"Zergling";"Larva";955;1
"Unit";"Zergling";"Larva";955;1
"Unit";"Zergling";"Larva";955;1
"Unit";"Zergling";"Larva";955;1
"Unit";"Zergling";"Larva";955;1
"Unit";"Zergling";"Larva";955;1
"Unit";"Zergling";"Larva";955;1
"Unit";"Zergling";"Larva";955;1
"Unit";"Zergling";"Larva";955;1
"Unit";"Zergling";"Larva";955;1
"Unit";"Zergling";"Larva";955;1
"Unit";"Zergling";"Larva";955;1
"Unit";"Zergling";"Larva";955;1
"Unit";"Zergling";"Larva";955;1
"Unit";"Zergling";"Larva";955;1
"Building";"CreepTumor";NA;955;0
"Building";"CreepTumor";NA;955;0
"Unit";"Zergling";"Larva";955;1
"Unit";"Zergling";"Larva";955;1
"Unit";"Zergling";"Larva";955;1
"Unit";"Zergling";"Larva";955;1
"Unit";"Zergling";"Larva";955;1
"Unit";"Zergling";"Larva";955;1
"Unit";"Zergling";"Larva";955;1
"Unit";"Zergling";"Larva";955;1
"Unit";"Zergling";"Larva";955;1
"Unit";"Zergling";"Larva";955;1
"Unit";"Zergling";"Larva";955;1
"Unit";"Zergling";"Larva";955;1
"Building";"SporeCrawler";NA;955;0
"Unit";"Baneling";"Zergling";1003;0
"Unit";"Baneling";"Zergling";1003;0
"Unit";"Baneling";"Zergling";1003;0
"Unit";"Baneling";"Zergling";1003;0
"Unit";"Baneling";"Zergling";1003;0
"Unit";"Baneling";"Zergling";1003;0
"Unit";"Baneling";"Zergling";1003;0
"Unit";"Baneling";"Zergling";1003;0
"Unit";"Baneling";"Zergling";1003;0
"Building";"SporeCrawler";NA;991;0
"Building";"SporeCrawler";NA;1003;0
"Building";"SporeCrawler";NA;1003;0
"Building";"SporeCrawler";NA;1003;0
"Unit";"Zergling";"Larva";1003;1
"Unit";"Zergling";"Larva";1003;1
"Unit";"Zergling";"Larva";1003;1
"Unit";"Zergling";"Larva";1003;1
"Unit";"Zergling";"Larva";1003;1
"Unit";"Zergling";"Larva";1003;1
"Unit";"Zergling";"Larva";1003;1
"Unit";"Zergling";"Larva";1003;1
"Unit";"Zergling";"Larva";1003;1
"Unit";"Zergling";"Larva";1003;1
"Unit";"Zergling";"Larva";1003;1
"Unit";"Zergling";"Larva";1003;1
"Unit";"Zergling";"Larva";1003;1
"Unit";"Zergling";"Larva";1003;1
"Unit";"Zergling";"Larva";1003;1
"Unit";"Zergling";"Larva";1003;1
"Unit";"Zergling";"Larva";1003;1
"Unit";"Zergling";"Larva";1003;1
"Unit";"Zergling";"Larva";1003;1
"Unit";"Zergling";"Larva";1003;1
"Unit";"Zergling";"Larva";1003;1
"Unit";"Zergling";"Larva";1003;1
"Unit";"Zergling";"Larva";1003;1
"Unit";"Zergling";"Larva";1003;1
"Building";"SporeCrawler";NA;1003;0
"Building";"SporeCrawler";NA;1003;0
"Building";"SporeCrawler";NA;1003;0
"Building";"SporeCrawler";NA;1003;0
"Unit";"Zergling";"Larva";1027;1
"Unit";"Zergling";"Larva";1027;1
"Unit";"Zergling";"Larva";1027;1
"Unit";"Zergling";"Larva";1027;1
"Unit";"Zergling";"Larva";1027;1
"Unit";"Zergling";"Larva";1027;1
"Unit";"Zergling";"Larva";1027;1
"Unit";"Zergling";"Larva";1027;1
"Unit";"Zergling";"Larva";1027;1
"Unit";"Zergling";"Larva";1027;1
"Unit";"Zergling";"Larva";1027;1
"Unit";"Zergling";"Larva";1027;1
"Unit";"Zergling";"Larva";1027;1
"Unit";"Zergling";"Larva";1027;1
"Unit";"Zergling";"Larva";1027;1
"Unit";"Zergling";"Larva";1027;1
"Unit";"Zergling";"Larva";1027;1
"Unit";"Zergling";"Larva";1027;1
"Unit";"Zergling";"Larva";1027;1
"Unit";"Zergling";"Larva";1027;1
"Unit";"Zergling";"Larva";1027;1
"Unit";"Zergling";"Larva";1027;1
"Unit";"Zergling";"Larva";1027;1
"Unit";"Zergling";"Larva";1027;1
"Building";"CreepTumor";NA;1051;0
"Building";"CreepTumor";NA;1051;0
"Building";"CreepTumor";NA;1051;0
"Building";"CreepTumor";NA;1051;0
"Building";"CreepTumor";NA;1051;0
"Building";"CreepTumor";NA;1051;0
"Building";"CreepTumor";NA;1051;0
"Unit";"Zergling";"Larva";1051;1
"Unit";"Zergling";"Larva";1051;1
"Unit";"Zergling";"Larva";1051;1
"Unit";"Zergling";"Larva";1051;1
"Unit";"Zergling";"Larva";1051;1
"Unit";"Zergling";"Larva";1051;1
"Unit";"Zergling";"Larva";1051;1
"Unit";"Zergling";"Larva";1051;1
"Unit";"Zergling";"Larva";1051;1
"Unit";"Zergling";"Larva";1051;1
"Unit";"Zergling";"Larva";1051;1
"Unit";"Zergling";"Larva";1051;1
"Unit";"Zergling";"Larva";1051;1
"Unit";"Zergling";"Larva";1051;1
"Unit";"Zergling";"Larva";1051;1
"Unit";"Zergling";"Larva";1051;1
"Unit";"Zergling";"Larva";1051;1
"Unit";"Zergling";"Larva";1051;1
"Unit";"Zergling";"Larva";1051;1
"Unit";"Zergling";"Larva";1051;1
"Unit";"Zergling";"Larva";1051;1
"Unit";"Zergling";"Larva";1051;1
"Unit";"Zergling";"Larva";1051;1
"Unit";"Zergling";"Larva";1051;1
"Unit";"Zergling";"Larva";1051;1
"Unit";"Zergling";"Larva";1051;1
"Unit";"Zergling";"Larva";1051;1
"Unit";"Zergling";"Larva";1051;1
"Unit";"Zergling";"Larva";1051;1
"Unit";"Zergling";"Larva";1051;1
"Unit";"Zergling";"Larva";1051;1
"Unit";"Zergling";"Larva";1051;1
"Unit";"Zergling";"Larva";1051;1
"Unit";"Zergling";"Larva";1051;1
"Unit";"Zergling";"Larva";1051;1
"Unit";"Zergling";"Larva";1051;1
"Building";"CreepTumor";NA;1051;0
"Unit";"Zergling";"Larva";1051;1
"Unit";"Zergling";"Larva";1051;1
"Unit";"Zergling";"Larva";1051;1
"Unit";"Zergling";"Larva";1051;1
"Unit";"Zergling";"Larva";1051;1
"Unit";"Zergling";"Larva";1051;1
"Unit";"Zergling";"Larva";1051;1
"Unit";"Zergling";"Larva";1051;1
"Unit";"Zergling";"Larva";1051;1
"Unit";"Zergling";"Larva";1051;1
"Unit";"Zergling";"Larva";1051;1
"Unit";"Zergling";"Larva";1051;1
"Building";"CreepTumor";NA;1099;0
"Building";"CreepTumor";NA;1099;0
"Building";"CreepTumorQueen";NA;1099;0
"Building";"CreepTumorQueen";NA;1099;0
"Building";"CreepTumorQueen";NA;1099;0
"Building";"CreepTumorQueen";NA;1099;0
"Building";"CreepTumorQueen";NA;1099;0
"Building";"CreepTumorQueen";NA;1099;0
"Building";"CreepTumorQueen";NA;1099;0
"Unit";"Overlord";"Larva";1099;0
"Building";"CreepTumor";NA;1099;0
"Building";"CreepTumor";NA;1099;0
"Building";"CreepTumor";NA;1099;0
"Building";"CreepTumor";NA;1099;0
"Building";"CreepTumor";NA;1099;0
"Unit";"Hydralisk";"Larva";1099;2
"Unit";"Hydralisk";"Larva";1099;2
"Unit";"Hydralisk";"Larva";1099;2
"Unit";"Hydralisk";"Larva";1099;2
"Unit";"Hydralisk";"Larva";1099;2
"Unit";"Hydralisk";"Larva";1099;2
"Unit";"Hydralisk";"Larva";1099;2
"Unit";"Hydralisk";"Larva";1099;2
"Unit";"Hydralisk";"Larva";1099;2
"Unit";"Hydralisk";"Larva";1099;2
"Unit";"Hydralisk";"Larva";1099;2
"Unit";"Hydralisk";"Larva";1099;2
"Unit";"Hydralisk";"Larva";1099;2
"Unit";"Hydralisk";"Larva";1099;2
"Unit";"Hydralisk";"Larva";1099;2
"Unit";"Hydralisk";"Larva";1099;2
"Unit";"Hydralisk";"Larva";1099;2
"Unit";"Hydralisk";"Larva";1099;2
