"type";"unit_name";"on_building";"total_supply";"supply"
"Unit";"Overlord";"Larva";12;0
"Building";"SpawningPool";NA;17;0
"Building";"Hatchery";NA;16;0
"Unit";"Zergling";"Larva";23;1
"Unit";"Zergling";"Larva";23;1
"Unit";"Zergling";"Larva";23;1
"Unit";"Zergling";"Larva";23;1
"Unit";"Queen";"Hatchery";22;2
"Unit";"Zergling";"Larva";23;1
"Unit";"Zergling";"Larva";23;1
"Unit";"Overlord";"Larva";23;0
"Unit";"Queen";"Hatchery";23;2
"Building";"Hatchery";NA;22;0
"Building";"CreepTumorQueen";NA;34;0
"Unit";"Overlord";"Larva";34;0
"Unit";"Queen";"Hatchery";32;2
"Unit";"Queen";"Hatchery";32;2
"Building";"CreepTumor";NA;38;0
"Unit";"Queen";"Hatchery";36;2
"Building";"CreepTumor";NA;47;0
"Building";"SpineCrawler";NA;38;0
"Building";"CreepTumorQueen";NA;49;0
"Building";"Extractor";NA;49;0
"Unit";"Overlord";"Larva";49;0
"Building";"CreepTumorQueen";NA;57;0
"Building";"CreepTumorQueen";NA;57;0
"Building";"Extractor";NA;49;0
"Unit";"Overlord";"Larva";57;0
"Building";"CreepTumor";NA;58;0
"Unit";"Overlord";"Larva";58;0
"Building";"RoachWarren";NA;57;0
"Building";"SporeCrawler";NA;58;0
"Building";"SporeCrawler";NA;60;0
"Building";"SporeCrawler";NA;60;0
"Building";"CreepTumor";NA;60;0
"Building";"CreepTumor";NA;60;0
"Building";"Extractor";NA;68;0
"Building";"CreepTumor";NA;76;0
"Building";"CreepTumor";NA;76;0
"Building";"CreepTumorQueen";NA;76;0
"Building";"CreepTumorQueen";NA;76;0
"Building";"Extractor";NA;68;0
"Building";"CreepTumor";NA;79;0
"Building";"CreepTumor";NA;79;0
"Unit";"Roach";"Larva";79;2
"Unit";"Roach";"Larva";79;2
"Unit";"Overlord";"Larva";79;0
"Unit";"Overlord";"Larva";79;0
"Building";"Extractor";NA;79;0
"Building";"Extractor";NA;79;0
"Building";"SporeCrawler";NA;85;0
"Unit";"Overlord";"Larva";89;0
"Building";"SporeCrawler";NA;91;0
"Building";"EvolutionChamber";NA;91;0
"Building";"EvolutionChamber";NA;91;0
"Unit";"Roach";"Larva";102;2
"Unit";"Roach";"Larva";102;2
"Unit";"Roach";"Larva";102;2
"Unit";"Roach";"Larva";102;2
"Unit";"Roach";"Larva";102;2
"Unit";"Roach";"Larva";102;2
"Unit";"Roach";"Larva";102;2
"Unit";"Roach";"Larva";102;2
"Unit";"Roach";"Larva";102;2
"Unit";"Overlord";"Larva";102;0
"Unit";"Overlord";"Larva";102;0
"Unit";"Overlord";"Larva";102;0
"Unit";"Overlord";"Larva";102;0
"Unit";"Overlord";"Larva";102;0
"Unit";"Overlord";"Larva";102;0
"Building";"CreepTumorQueen";NA;102;0
"Building";"CreepTumorQueen";NA;102;0
"Building";"CreepTumorQueen";NA;104;0
"Building";"CreepTumorQueen";NA;104;0
"Building";"CreepTumorQueen";NA;120;0
"Building";"SporeCrawler";NA;102;0
"Building";"CreepTumorQueen";NA;120;0
"Unit";"Roach";"Larva";120;2
"Unit";"Roach";"Larva";120;2
"Unit";"Roach";"Larva";120;2
"Unit";"Roach";"Larva";120;2
"Unit";"Roach";"Larva";120;2
"Unit";"Roach";"Larva";120;2
"Unit";"Roach";"Larva";120;2
"Unit";"Roach";"Larva";120;2
"Building";"CreepTumor";NA;124;0
"Building";"CreepTumor";NA;124;0
"Building";"CreepTumor";NA;124;0
"Building";"CreepTumor";NA;124;0
"Building";"CreepTumorQueen";NA;124;0
"Building";"CreepTumorQueen";NA;124;0
"Upgrade";"GlialReconstitution";"RoachWarren";102;0
"Building";"CreepTumor";NA;124;0
"Building";"CreepTumorQueen";NA;140;0
"Building";"CreepTumorQueen";NA;140;0
"Unit";"Roach";"Larva";140;2
"Unit";"Roach";"Larva";140;2
"Unit";"Roach";"Larva";140;2
"Unit";"Roach";"Larva";140;2
"Unit";"Roach";"Larva";140;2
"Unit";"Roach";"Larva";140;2
"Unit";"Roach";"Larva";140;2
"Unit";"Roach";"Larva";140;2
"Unit";"Roach";"Larva";140;2
"Building";"CreepTumor";NA;140;0
"Unit";"Overlord";"Larva";144;0
"Unit";"Overlord";"Larva";158;0
"Unit";"Overlord";"Larva";158;0
"Unit";"Overlord";"Larva";158;0
"Unit";"Overlord";"Larva";158;0
"Upgrade";"ZergMissileWeaponsLevel1";"EvolutionChamber";102;0
"Upgrade";"ZergGroundArmorsLevel1";"EvolutionChamber";102;0
"Building";"InfestationPit";NA;140;0
"Building";"CreepTumor";NA;158;0
"Building";"CreepTumor";NA;158;0
"Building";"CreepTumor";NA;158;0
"Building";"CreepTumor";NA;158;0
"Building";"CreepTumor";NA;158;0
"Building";"CreepTumor";NA;158;0
"Building";"CreepTumorQueen";NA;174;0
"Building";"CreepTumor";NA;164;0
"Building";"CreepTumor";NA;174;0
"Building";"CreepTumor";NA;174;0
"Building";"Hatchery";NA;140;0
"Building";"CreepTumorQueen";NA;174;0
"Building";"CreepTumorQueen";NA;174;0
"Building";"CreepTumorQueen";NA;174;0
"Building";"CreepTumor";NA;174;0
"Building";"CreepTumorQueen";NA;174;0
"Building";"Hatchery";NA;140;0
"Unit";"Roach";"Larva";174;2
"Unit";"Roach";"Larva";174;2
"Unit";"Roach";"Larva";174;2
"Unit";"Roach";"Larva";174;2
"Unit";"Roach";"Larva";174;2
"Building";"Extractor";NA;174;0
"Unit";"Roach";"Larva";174;2
"Unit";"Roach";"Larva";174;2
"Building";"Extractor";NA;174;0
"Building";"CreepTumor";NA;174;0
"Building";"CreepTumor";NA;174;0
"Building";"CreepTumor";NA;174;0
"Building";"CreepTumor";NA;174;0
"Building";"CreepTumorQueen";NA;174;0
"Unit";"Roach";"Larva";174;2
"Unit";"Roach";"Larva";174;2
"Unit";"Roach";"Larva";174;2
"Unit";"Roach";"Larva";174;2
"Unit";"Roach";"Larva";174;2
"Building";"CreepTumorQueen";NA;188;0
"Building";"CreepTumor";NA;188;0
"Building";"CreepTumor";NA;188;0
"Building";"CreepTumor";NA;188;0
"Building";"CreepTumor";NA;188;0
"Building";"CreepTumor";NA;188;0
"Building";"CreepTumor";NA;188;0
"Building";"CreepTumor";NA;188;0
"Building";"CreepTumor";NA;188;0
"Upgrade";"TunnelingClaws";"RoachWarren";174;0
"Unit";"Roach";"Larva";198;2
"Unit";"Roach";"Larva";198;2
"Unit";"Roach";"Larva";198;2
"Unit";"Roach";"Larva";198;2
"Unit";"Roach";"Larva";198;2
"Unit";"Roach";"Larva";198;2
"Unit";"Roach";"Larva";198;2
"Unit";"Roach";"Larva";198;2
"Unit";"Roach";"Larva";198;2
"Building";"SporeCrawler";NA;198;0
"Unit";"Roach";"Larva";216;2
"Unit";"Roach";"Larva";216;2
"Unit";"Roach";"Larva";216;2
"Unit";"Roach";"Larva";216;2
"Unit";"Roach";"Larva";216;2
"Unit";"Roach";"Larva";216;2
"Unit";"Roach";"Larva";216;2
"Unit";"Roach";"Larva";216;2
"Unit";"Roach";"Larva";216;2
"Unit";"Roach";"Larva";216;2
"Unit";"Roach";"Larva";216;2
"Building";"CreepTumor";NA;216;0
"Building";"CreepTumor";NA;216;0
"Building";"CreepTumor";NA;216;0
"Upgrade";"Burrow";"Hatchery";188;0
"Building";"Hatchery";NA;174;0
"Building";"CreepTumor";NA;216;0
"Building";"CreepTumor";NA;216;0
"Building";"CreepTumor";NA;216;0
"Building";"CreepTumor";NA;216;0
"Building";"CreepTumorQueen";NA;216;0
"Unit";"Roach";"Larva";216;2
"Unit";"Roach";"Larva";216;2
"Unit";"Roach";"Larva";216;2
"Unit";"Roach";"Larva";216;2
"Unit";"Roach";"Larva";216;2
"Unit";"Overlord";"Larva";238;0
"Unit";"Overlord";"Larva";238;0
"Unit";"Overlord";"Larva";238;0
"Unit";"Overlord";"Larva";238;0
"Unit";"Overlord";"Larva";238;0
"Upgrade";"ZergMissileWeaponsLevel2";"EvolutionChamber";174;0
"Upgrade";"ZergGroundArmorsLevel2";"EvolutionChamber";174;0
"Unit";"Overlord";"Larva";248;0
"Unit";"Overlord";"Larva";248;0
