"type";"unit_name";"on_building";"total_supply_lag";"supply"
"Building";"Pylon";NA;14;0
"Building";"Gateway";NA;16;0
"Building";"Assimilator";NA;17;0
"Building";"Nexus";NA;19;0
"Building";"CyberneticsCore";NA;20;0
"Building";"Assimilator";NA;21;0
"Building";"Pylon";NA;22;0
"Unit";"Adept";"Gateway";23;2
"Building";"Stargate";NA;28;0
"Unit";"Adept";"Gateway";28;2
"Unit";"Adept";"Gateway";34;2
"Unit";"Oracle";"Stargate";39;3
"Building";"Pylon";NA;45;0
"Building";"Gateway";NA;45;0
"Building";"Gateway";NA;45;0
"Building";"Pylon";NA;47;0
"Building";"TwilightCouncil";NA;47;0
"Unit";"Phoenix";"Stargate";47;2
"Building";"Assimilator";NA;51;0
"Building";"Pylon";NA;51;0
"Building";"Pylon";NA;52;0
"Building";"Pylon";NA;55;0
"Unit";"Adept";"Gateway";55;2
"Unit";"Adept";"Gateway";58;2
"Unit";"Adept";"Gateway";60;2
"Building";"Nexus";NA;62;0
"Building";"Pylon";NA;63;0
"Unit";"Adept";"Gateway";63;2
"Unit";"Adept";"Gateway";65;2
"Unit";"Adept";"Gateway";67;2
"Building";"Assimilator";NA;71;0
"Unit";"Adept";"Gateway";71;2
"Unit";"Adept";"Gateway";73;2
"Unit";"Adept";"Gateway";75;2
"Building";"RoboticsFacility";NA;79;0
"Building";"Pylon";NA;80;0
"Building";"Forge";NA;81;0
"Unit";"Adept";"Gateway";83;2
"Unit";"Adept";"Gateway";85;2
"Unit";"Adept";"Gateway";88;2
"Unit";"Immortal";"Robotics Facility";95;4
"Unit";"Sentry";"Gateway";99;2
"Unit";"Sentry";"Gateway";101;2
"Unit";"Sentry";"Gateway";103;2
"Upgrade";"ProtossGroundWeaponsLevel1";"Forge";111;0
"Building";"Assimilator";NA;111;0
"Building";"Assimilator";NA;111;0
"Unit";"Immortal";"Robotics Facility";111;4
"Building";"Gateway";NA;116;0
"Building";"Gateway";NA;116;0
"Building";"Gateway";NA;116;0
"Building";"Gateway";NA;116;0
"Building";"TemplarArchive";NA;116;0
"Unit";"Zealot";"Gateway";116;2
"Unit";"Zealot";"Gateway";118;2
"Building";"Pylon";NA;120;0
"Unit";"Sentry";"Gateway";120;2
"Building";"Gateway";NA;125;0
"Building";"Pylon";NA;125;0
"Unit";"Immortal";"Robotics Facility";125;4
"Unit";"Sentry";"Gateway";129;2
"Unit";"Zealot";"Gateway";131;2
"Unit";"Zealot";"Gateway";133;2
"Upgrade";"Charge";"TwilightCouncil";135;0
"Unit";"Sentry";"Gateway";135;2
"Unit";"Sentry";"Gateway";137;2
"Unit";"Adept";"Gateway";139;2
"Unit";"Immortal";"Robotics Facility";141;4
"Unit";"Adept";"Gateway";145;2
"Unit";"Adept";"Gateway";147;2
"Unit";"Adept";"Gateway";149;2
"Unit";"Adept";"Gateway";151;2
"Unit";"Adept";"Gateway";153;2
"Building";"Pylon";NA;155;0
"Building";"Pylon";NA;155;0
"Unit";"Sentry";"Gateway";155;2
"Unit";"Sentry";"Gateway";157;2
"Unit";"Zealot";"Gateway";159;2
"Building";"Nexus";NA;161;0
"Unit";"Sentry";"Gateway";163;2
"Building";"HighTemplar";NA;166;0
"Building";"HighTemplar";NA;166;0
"Unit";"Zealot";"Gateway";166;2
"Unit";"Zealot";"Gateway";168;2
"Unit";"Zealot";"Gateway";170;2
"Unit";"Zealot";"Gateway";172;2
"Building";"Pylon";NA;175;0
"Building";"Pylon";NA;175;0
"Unit";"Phoenix";"Stargate";179;2
"Unit";"Observer";"Robotics Facility";181;1
"Upgrade";"ProtossGroundWeaponsLevel2";"Forge";182;0
"Unit";"Stalker";"Gateway";182;2
"Building";"Pylon";NA;184;0
"Building";"HighTemplar";NA;184;0
"Unit";"Zealot";"Gateway";184;2
"Unit";"Zealot";"Gateway";186;2
"Unit";"Zealot";"Gateway";188;2
"Unit";"Zealot";"Gateway";190;2
"Unit";"Adept";"Gateway";192;2
"Unit";"Adept";"Gateway";194;2
"Unit";"Phoenix";"Stargate";196;2
"Unit";"Immortal";"Robotics Facility";198;4
"Building";"PhotonCannon";NA;202;0
"Building";"Nexus";NA;202;0
"Unit";"Adept";"Gateway";202;2
"Building";"HighTemplar";NA;204;0
"Building";"HighTemplar";NA;204;0
"Unit";"Immortal";"Robotics Facility";204;4
"Building";"HighTemplar";NA;208;0
"Building";"HighTemplar";NA;208;0
"Unit";"Zealot";"Gateway";208;2
"Unit";"Zealot";"Gateway";210;2
"Unit";"Zealot";"Gateway";212;2
"Unit";"Zealot";"Gateway";214;2
"Unit";"Archon";"High Templar";219;0
"Building";"PhotonCannon";NA;219;0
"Building";"Assimilator";NA;219;0
"Building";"HighTemplar";NA;219;0
"Building";"HighTemplar";NA;219;0
"Unit";"Zealot";"Gateway";219;2
"Building";"Assimilator";NA;221;0
"Unit";"Zealot";"Gateway";221;2
"Unit";"Zealot";"Gateway";223;2
"Unit";"Archon";"High Templar";225;0
"Unit";"Immortal";"Robotics Facility";225;4
"Building";"Pylon";NA;229;0
"Building";"Pylon";NA;229;0
"Building";"Pylon";NA;229;0
"Building";"Pylon";NA;229;0
"Unit";"Archon";"High Templar";229;0
"Unit";"Zealot";"Gateway";229;2
"Unit";"Zealot";"Gateway";231;2
"Upgrade";"ProtossGroundWeaponsLevel3";"Forge";233;0
"Unit";"Zealot";"Gateway";233;2
"Unit";"Zealot";"Gateway";235;2
"Unit";"Zealot";"Gateway";237;2
"Building";"HighTemplar";NA;239;0
"Building";"HighTemplar";NA;239;0
"Building";"HighTemplar";NA;239;0
"Unit";"Immortal";"Robotics Facility";243;4
"Unit";"Sentry";"Gateway";251;2
"Unit";"Sentry";"Gateway";253;2
"Building";"HighTemplar";NA;255;0
"Unit";"Zealot";"Gateway";255;2
"Unit";"Zealot";"Gateway";257;2
"Building";"RoboticsFacility";NA;263;0
"Building";"PhotonCannon";NA;263;0
"Unit";"Immortal";"Robotics Facility";263;4
"Unit";"Adept";"Gateway";267;2
"Unit";"Adept";"Gateway";269;2
"Building";"HighTemplar";NA;271;0
"Building";"HighTemplar";NA;271;0
"Building";"HighTemplar";NA;271;0
"Building";"HighTemplar";NA;271;0
"Unit";"Archon";"High Templar";271;0
"Unit";"Phoenix";"Stargate";271;2
"Building";"PhotonCannon";NA;273;0
"Unit";"Archon";"High Templar";273;0
"Building";"Pylon";NA;273;0
"Unit";"Immortal";"Robotics Facility";273;4
"Unit";"Immortal";"Robotics Facility";277;4
"Building";"Pylon";NA;281;0
"Building";"HighTemplar";NA;281;0
"Building";"HighTemplar";NA;281;0
"Building";"HighTemplar";NA;281;0
"Building";"HighTemplar";NA;281;0
"Unit";"Archon";"High Templar";281;0
"Unit";"Archon";"High Templar";281;0
"Unit";"Immortal";"Robotics Facility";284;4
"Building";"Nexus";NA;288;0
"Unit";"Observer";"Robotics Facility";288;1
"Unit";"Zealot";"Gateway";289;2
"Unit";"Zealot";"Gateway";291;2
"Unit";"Zealot";"Gateway";293;2
"Unit";"Zealot";"Gateway";295;2
"Unit";"Zealot";"Gateway";297;2
"Unit";"Zealot";"Gateway";299;2
"Unit";"Zealot";"Gateway";301;2
"Unit";"Zealot";"Gateway";303;2
"Building";"PhotonCannon";NA;305;0
"Building";"Pylon";NA;305;0
"Unit";"Phoenix";"Stargate";305;2
"Building";"FleetBeacon";NA;307;0
"Building";"Stargate";NA;307;0
"Building";"Stargate";NA;307;0
"Unit";"Oracle";"Stargate";307;3
"Upgrade";"ProtossShieldsLevel1";"Forge";310;0
"Building";"Assimilator";NA;310;0
"Unit";"Carrier";"Stargate";310;6
"Unit";"Carrier";"Stargate";316;6
"Unit";"Zealot";"Gateway";322;2
"Unit";"Zealot";"Gateway";324;2
"Unit";"Zealot";"Gateway";326;2
"Unit";"Zealot";"Gateway";328;2
"Unit";"Zealot";"Gateway";330;2
"Unit";"Zealot";"Gateway";332;2
"Unit";"Zealot";"Gateway";334;2
"Unit";"Zealot";"Gateway";336;2
"Building";"Assimilator";NA;338;0
"Building";"PhotonCannon";NA;338;0
"Building";"PhotonCannon";NA;338;0
"Unit";"Immortal";"Robotics Facility";338;4
"Unit";"Immortal";"Robotics Facility";342;4
"Building";"HighTemplar";NA;346;0
"Building";"HighTemplar";NA;346;0
"Building";"HighTemplar";NA;346;0
"Building";"HighTemplar";NA;346;0
"Unit";"Carrier";"Stargate";346;6
"Unit";"Zealot";"Gateway";352;2
"Unit";"Zealot";"Gateway";354;2
"Unit";"Zealot";"Gateway";356;2
"Unit";"Zealot";"Gateway";358;2
"Building";"HighTemplar";NA;360;0
"Building";"HighTemplar";NA;360;0
"Unit";"Zealot";"Gateway";360;2
"Unit";"Zealot";"Gateway";362;2
"Unit";"Archon";"High Templar";364;0
"Building";"Nexus";NA;364;0
"Unit";"Carrier";"Stargate";364;6
"Unit";"Immortal";"Robotics Facility";370;4
"Building";"HighTemplar";NA;374;0
"Building";"OracleStasisTrap";NA;374;0
"Building";"OracleStasisTrap";NA;374;0
"Building";"Assimilator";NA;374;0
"Unit";"Carrier";"Stargate";374;6
"Unit";"Carrier";"Stargate";380;6
"Building";"PhotonCannon";NA;386;0
"Building";"PhotonCannon";NA;386;0
"Building";"PhotonCannon";NA;386;0
"Upgrade";"ProtossShieldsLevel2";"Forge";386;0
"Upgrade";"ProtossAirWeaponsLevel1";"CyberneticsCore";386;0
"Building";"Nexus";NA;386;0
"Building";"Gateway";NA;386;0
"Building";"Gateway";NA;386;0
"Building";"Gateway";NA;386;0
"Building";"Gateway";NA;386;0
"Building";"Gateway";NA;386;0
"Building";"HighTemplar";NA;386;0
"Building";"HighTemplar";NA;386;0
"Unit";"Zealot";"Gateway";386;2
"Unit";"Zealot";"Gateway";388;2
"Unit";"Zealot";"Gateway";390;2
"Building";"PhotonCannon";NA;392;0
"Unit";"Zealot";"Gateway";392;2
"Building";"HighTemplar";NA;394;0
"Building";"HighTemplar";NA;394;0
"Building";"PhotonCannon";NA;394;0
"Building";"Pylon";NA;394;0
"Building";"HighTemplar";NA;394;0
"Building";"HighTemplar";NA;394;0
"Unit";"Archon";"High Templar";394;0
"Building";"HighTemplar";NA;395;0
"Unit";"Zealot";"Gateway";396;2
"Unit";"Zealot";"Gateway";398;2
"Unit";"Zealot";"Gateway";400;2
"Unit";"Zealot";"Gateway";402;2
"Building";"Assimilator";NA;404;0
"Building";"OracleStasisTrap";NA;404;0
"Building";"Assimilator";NA;404;0
"Unit";"Zealot";"Gateway";404;2
"Unit";"Zealot";"Gateway";406;2
"Unit";"Zealot";"Gateway";408;2
"Unit";"Zealot";"Gateway";410;2
"Unit";"Zealot";"Gateway";412;2
"Unit";"Zealot";"Gateway";414;2
"Unit";"Zealot";"Gateway";416;2
"Upgrade";"SprayProtoss";NA;418;0
"Upgrade";"SprayProtoss";NA;418;0
"Upgrade";"WarpGateResearch";NA;418;0
"Upgrade";"SprayProtoss";NA;418;0
"Upgrade";"AdeptPiercingAttack";NA;418;0
"Upgrade";"SprayProtoss";NA;418;0
"Upgrade";"SprayProtoss";NA;418;0
"Upgrade";"SprayProtoss";NA;418;0
"Upgrade";"PsiStormTech";NA;418;0
"Upgrade";"SprayProtoss";NA;418;0
"Upgrade";"SprayProtoss";NA;418;0
"Upgrade";"SprayProtoss";NA;418;0
"Upgrade";"SprayProtoss";NA;418;0
"Upgrade";"SprayProtoss";NA;418;0
"Upgrade";"SprayProtoss";NA;418;0
"Upgrade";"SprayProtoss";NA;418;0
"Upgrade";"SprayProtoss";NA;418;0
"Upgrade";"SprayProtoss";NA;418;0
