"type";"unit_name";"on_building";"total_supply";"supply"
"Unit";"Overlord";"Larva";14;0
"Building";"SpawningPool";NA;14;0
"Unit";"Zergling";"Larva";19;1
"Unit";"Zergling";"Larva";19;1
"Unit";"Zergling";"Larva";19;1
"Unit";"Zergling";"Larva";19;1
"Unit";"Zergling";"Larva";19;1
"Unit";"Zergling";"Larva";19;1
"Unit";"Overlord";"Larva";25;0
"Unit";"Queen";"Hatchery";19;2
"Building";"Hatchery";NA;19;0
"Building";"SpineCrawler";NA;25;0
"Unit";"Queen";"Hatchery";25;2
"Unit";"Overlord";"Larva";29;0
"Unit";"Queen";"Hatchery";29;2
"Building";"SpineCrawler";NA;34;0
"Unit";"Queen";"Hatchery";34;2
"Building";"CreepTumorQueen";NA;37;0
"Unit";"Overlord";"Larva";48;0
"Building";"CreepTumor";NA;48;0
"Unit";"Queen";"Hatchery";39;2
"Unit";"Queen";"Hatchery";39;2
"Building";"CreepTumorQueen";NA;50;0
"Building";"EvolutionChamber";NA;50;0
"Building";"EvolutionChamber";NA;50;0
"Building";"CreepTumor";NA;54;0
"Building";"RoachWarren";NA;50;0
"Unit";"Overlord";"Larva";62;0
"Unit";"Overlord";"Larva";64;0
"Building";"CreepTumor";NA;66;0
"Building";"Extractor";NA;64;0
"Building";"Extractor";NA;64;0
"Building";"CreepTumor";NA;66;0
"Building";"Extractor";NA;66;0
"Building";"Extractor";NA;66;0
"Unit";"Overlord";"Larva";73;0
"Unit";"Overlord";"Larva";73;0
"Building";"Hatchery";NA;62;0
"Building";"CreepTumorQueen";NA;81;0
"Building";"Extractor";NA;81;0
"Building";"Extractor";NA;88;0
"Building";"CreepTumor";NA;92;0
"Unit";"Overlord";"Larva";100;0
"Unit";"Overlord";"Larva";100;0
"Unit";"Roach";"Larva";100;2
"Unit";"Zergling";"Larva";100;1
"Unit";"Zergling";"Larva";100;1
"Unit";"Zergling";"Larva";100;1
"Unit";"Zergling";"Larva";100;1
"Unit";"Overlord";"Larva";100;0
"Unit";"Overlord";"Larva";100;0
"Unit";"Zergling";"Larva";100;1
"Unit";"Zergling";"Larva";100;1
"Unit";"Zergling";"Larva";100;1
"Unit";"Zergling";"Larva";100;1
"Unit";"Zergling";"Larva";100;1
"Unit";"Zergling";"Larva";100;1
"Unit";"Zergling";"Larva";100;1
"Unit";"Zergling";"Larva";100;1
"Unit";"Zergling";"Larva";100;1
"Unit";"Zergling";"Larva";100;1
"Unit";"Zergling";"Larva";100;1
"Unit";"Zergling";"Larva";100;1
"Unit";"Zergling";"Larva";100;1
"Unit";"Zergling";"Larva";100;1
"Unit";"Zergling";"Larva";100;1
"Unit";"Zergling";"Larva";100;1
"Unit";"Zergling";"Larva";100;1
"Unit";"Zergling";"Larva";100;1
"Unit";"Zergling";"Larva";100;1
"Unit";"Zergling";"Larva";100;1
"Unit";"Zergling";"Larva";100;1
"Unit";"Zergling";"Larva";100;1
"Unit";"Zergling";"Larva";100;1
"Unit";"Zergling";"Larva";100;1
"Unit";"Zergling";"Larva";104;1
"Unit";"Zergling";"Larva";104;1
"Building";"Hatchery";NA;88;0
"Unit";"Zergling";"Larva";106;1
"Unit";"Zergling";"Larva";106;1
"Unit";"Zergling";"Larva";106;1
"Unit";"Zergling";"Larva";106;1
"Upgrade";"ZergMeleeWeaponsLevel1";"EvolutionChamber";82;0
"Unit";"Zergling";"Larva";124;1
"Unit";"Zergling";"Larva";124;1
"Unit";"Zergling";"Larva";124;1
"Unit";"Zergling";"Larva";124;1
"Unit";"Zergling";"Larva";124;1
"Unit";"Zergling";"Larva";124;1
"Unit";"Zergling";"Larva";124;1
"Unit";"Zergling";"Larva";124;1
"Unit";"Zergling";"Larva";124;1
"Unit";"Zergling";"Larva";124;1
"Unit";"Zergling";"Larva";124;1
"Unit";"Zergling";"Larva";124;1
"Unit";"Zergling";"Larva";124;1
"Unit";"Zergling";"Larva";124;1
"Unit";"Zergling";"Larva";130;1
"Unit";"Zergling";"Larva";130;1
"Unit";"Zergling";"Larva";130;1
"Unit";"Zergling";"Larva";130;1
"Unit";"Zergling";"Larva";132;1
"Unit";"Zergling";"Larva";132;1
"Unit";"Zergling";"Larva";132;1
"Unit";"Zergling";"Larva";132;1
"Unit";"Zergling";"Larva";132;1
"Unit";"Zergling";"Larva";132;1
"Unit";"Zergling";"Larva";132;1
"Unit";"Zergling";"Larva";132;1
"Unit";"Zergling";"Larva";134;1
"Unit";"Zergling";"Larva";134;1
"Building";"BanelingNest";NA;100;0
"Building";"Hatchery";NA;100;0
"Unit";"Zergling";"Larva";140;1
"Unit";"Zergling";"Larva";140;1
"Unit";"Zergling";"Larva";150;1
"Unit";"Zergling";"Larva";150;1
"Unit";"Zergling";"Larva";150;1
"Unit";"Zergling";"Larva";150;1
"Unit";"Zergling";"Larva";150;1
"Unit";"Zergling";"Larva";150;1
"Upgrade";"ZergGroundArmorsLevel1";"EvolutionChamber";92;0
"Unit";"Overlord";"Larva";164;0
"Unit";"Overlord";"Larva";164;0
"Building";"HydraliskDen";NA;164;0
"Building";"EvolutionChamber";NA;172;0
"Building";"SporeCrawler";NA;172;0
"Building";"SporeCrawler";NA;172;0
"Unit";"Hydralisk";"Larva";172;2
"Unit";"Hydralisk";"Larva";172;2
"Unit";"Hydralisk";"Larva";172;2
"Unit";"Hydralisk";"Larva";172;2
"Unit";"Hydralisk";"Larva";172;2
"Unit";"Hydralisk";"Larva";172;2
"Unit";"Hydralisk";"Larva";172;2
"Unit";"Hydralisk";"Larva";172;2
"Unit";"Hydralisk";"Larva";172;2
"Unit";"Hydralisk";"Larva";172;2
"Unit";"Hydralisk";"Larva";172;2
"Unit";"Hydralisk";"Larva";172;2
"Unit";"Hydralisk";"Larva";172;2
"Building";"SporeCrawler";NA;172;0
"Building";"SporeCrawler";NA;172;0
"Building";"SporeCrawler";NA;172;0
"Unit";"Hydralisk";"Larva";198;2
"Unit";"Hydralisk";"Larva";198;2
"Unit";"Hydralisk";"Larva";198;2
"Unit";"Hydralisk";"Larva";198;2
"Unit";"Hydralisk";"Larva";198;2
"Unit";"Hydralisk";"Larva";198;2
"Unit";"Hydralisk";"Larva";198;2
"Unit";"Hydralisk";"Larva";198;2
"Unit";"Hydralisk";"Larva";198;2
"Building";"SporeCrawler";NA;204;0
"Building";"SporeCrawler";NA;204;0
"Building";"SporeCrawler";NA;222;0
"Building";"SporeCrawler";NA;222;0
"Unit";"Hydralisk";"Larva";222;2
"Upgrade";"ZergMeleeWeaponsLevel2";"EvolutionChamber";172;0
"Unit";"Hydralisk";"Larva";225;2
"Unit";"Hydralisk";"Larva";225;2
"Unit";"Hydralisk";"Larva";225;2
"Building";"SporeCrawler";NA;225;0
"Unit";"Hydralisk";"Larva";234;2
"Unit";"Hydralisk";"Larva";234;2
"Unit";"Hydralisk";"Larva";234;2
"Unit";"Hydralisk";"Larva";241;2
"Unit";"Hydralisk";"Larva";242;2
"Unit";"Hydralisk";"Larva";242;2
"Unit";"Overlord";"Larva";242;0
"Building";"CreepTumor";NA;246;0
"Upgrade";"ZergGroundArmorsLevel2";"EvolutionChamber";198;0
"Unit";"Overlord";"Larva";242;0
"Unit";"Overlord";"Larva";242;0
"Unit";"Overlord";"Larva";242;0
"Upgrade";"EvolveMuscularAugments";"HydraliskDen";225;0
"Unit";"Overlord";"Larva";248;0
"Building";"LurkerDenMP";NA;222;0
"Unit";"Roach";"Larva";256;2
"Unit";"Roach";"Larva";256;2
"Unit";"Roach";"Larva";256;2
"Unit";"Roach";"Larva";256;2
"Unit";"Roach";"Larva";256;2
"Unit";"Roach";"Larva";258;2
"Unit";"Roach";"Larva";258;2
"Unit";"Roach";"Larva";258;2
"Unit";"Roach";"Larva";258;2
"Unit";"Roach";"Larva";258;2
"Unit";"Roach";"Larva";258;2
"Unit";"Roach";"Larva";258;2
"Unit";"Roach";"Larva";258;2
"Unit";"Roach";"Larva";258;2
"Upgrade";"ZergMissileWeaponsLevel1";"EvolutionChamber";234;0
"Unit";"Hydralisk";"Larva";268;2
"Unit";"Hydralisk";"Larva";268;2
"Unit";"Hydralisk";"Larva";268;2
"Unit";"Hydralisk";"Larva";268;2
"Unit";"Hydralisk";"Larva";268;2
"Unit";"Hydralisk";"Larva";268;2
"Unit";"Hydralisk";"Larva";268;2
"Building";"SporeCrawler";NA;286;0
"Unit";"Hydralisk";"Larva";286;2
"Unit";"Hydralisk";"Larva";286;2
"Unit";"Hydralisk";"Larva";286;2
"Unit";"Hydralisk";"Larva";286;2
"Unit";"Hydralisk";"Larva";286;2
"Unit";"Hydralisk";"Larva";286;2
"Unit";"Hydralisk";"Larva";286;2
"Upgrade";"EvolveGroovedSpines";"HydraliskDen";258;0
"Building";"SporeCrawler";NA;300;0
"Unit";"Hydralisk";"Larva";300;2
"Unit";"Hydralisk";"Larva";300;2
"Unit";"Hydralisk";"Larva";300;2
"Upgrade";"GlialReconstitution";"RoachWarren";268;0
"Unit";"Hydralisk";"Larva";300;2
"Unit";"Zergling";"Larva";314;1
"Unit";"Zergling";"Larva";314;1
"Unit";"Hydralisk";"Larva";300;2
"Unit";"Hydralisk";"Larva";300;2
"Unit";"Zergling";"Larva";314;1
"Unit";"Zergling";"Larva";314;1
"Unit";"Zergling";"Larva";314;1
"Unit";"Zergling";"Larva";314;1
"Unit";"Zergling";"Larva";314;1
"Unit";"Zergling";"Larva";314;1
"Unit";"Overlord";"Larva";314;0
"Unit";"Overlord";"Larva";314;0
"Unit";"Overlord";"Larva";314;0
"Unit";"Overlord";"Larva";314;0
"Unit";"Overlord";"Larva";334;0
"Unit";"Overlord";"Larva";334;0
"Building";"InfestationPit";NA;320;0
"Unit";"Roach";"Larva";334;2
"Unit";"Hydralisk";"Larva";334;2
"Unit";"Hydralisk";"Larva";334;2
"Unit";"Hydralisk";"Larva";334;2
"Unit";"Hydralisk";"Larva";334;2
"Unit";"Hydralisk";"Larva";334;2
"Unit";"Hydralisk";"Larva";334;2
"Unit";"Hydralisk";"Larva";334;2
"Unit";"Hydralisk";"Larva";334;2
"Unit";"Hydralisk";"Larva";334;2
