"type";"unit_name";"on_building";"total_supply";"supply"
"Unit";"Overlord";"Larva";13;0
"Building";"Extractor";NA;17;0
"Building";"SpawningPool";NA;19;0
"Building";"Hatchery";NA;17;0
"Unit";"Overlord";"Larva";23;0
"Unit";"Zergling";"Larva";23;1
"Unit";"Zergling";"Larva";23;1
"Unit";"Zergling";"Larva";23;1
"Unit";"Zergling";"Larva";23;1
"Unit";"Queen";"Hatchery";23;2
"Unit";"Queen";"Hatchery";23;2
"Building";"BanelingNest";NA;29;0
"Unit";"Overlord";"Larva";37;0
"Building";"EvolutionChamber";NA;37;0
"Unit";"Overlord";"Larva";45;0
"Building";"Hatchery";NA;37;0
"Building";"Extractor";NA;46;0
"Unit";"Zergling";"Larva";48;1
"Unit";"Zergling";"Larva";48;1
"Unit";"Zergling";"Larva";48;1
"Unit";"Zergling";"Larva";48;1
"Building";"RoachWarren";NA;45;0
"Building";"Extractor";NA;50;0
"Unit";"Queen";"Hatchery";50;2
"Unit";"Overlord";"Larva";67;0
"Unit";"Overlord";"Larva";67;0
"Building";"EvolutionChamber";NA;67;0
"Unit";"Overlord";"Larva";69;0
"Unit";"Overlord";"Larva";69;0
"Building";"Extractor";NA;69;0
"Unit";"Overlord";"Larva";74;0
"Unit";"Overlord";"Larva";74;0
"Unit";"Overlord";"Larva";74;0
"Unit";"Roach";"Larva";74;2
"Unit";"Roach";"Larva";74;2
"Unit";"Roach";"Larva";75;2
"Upgrade";"GlialReconstitution";"RoachWarren";67;0
"Unit";"Roach";"Larva";75;2
"Unit";"Roach";"Larva";75;2
"Unit";"Roach";"Larva";75;2
"Unit";"Roach";"Larva";75;2
"Upgrade";"ZergMissileWeaponsLevel1";"EvolutionChamber";60;0
"Unit";"Roach";"Larva";79;2
"Unit";"Roach";"Larva";79;2
"Unit";"Roach";"Larva";79;2
"Unit";"Roach";"Larva";89;2
"Unit";"Roach";"Larva";89;2
"Unit";"Roach";"Larva";89;2
"Unit";"Roach";"Larva";89;2
"Unit";"Roach";"Larva";89;2
"Unit";"Roach";"Larva";95;2
"Unit";"Roach";"Larva";95;2
"Unit";"Roach";"Larva";95;2
"Unit";"Roach";"Larva";95;2
"Unit";"Roach";"Larva";95;2
"Unit";"Overlord";"Larva";95;0
"Unit";"Overlord";"Larva";95;0
"Unit";"Roach";"Larva";95;2
"Unit";"Roach";"Larva";95;2
"Unit";"Roach";"Larva";105;2
"Unit";"Roach";"Larva";105;2
"Unit";"Roach";"Larva";105;2
"Unit";"Roach";"Larva";105;2
"Unit";"Roach";"Larva";105;2
"Unit";"Roach";"Larva";132;2
"Unit";"Roach";"Larva";132;2
"Unit";"Roach";"Larva";132;2
"Unit";"Roach";"Larva";132;2
"Unit";"Roach";"Larva";132;2
"Unit";"Roach";"Larva";132;2
"Unit";"Roach";"Larva";132;2
"Unit";"Roach";"Larva";132;2
"Unit";"Roach";"Larva";132;2
"Unit";"Roach";"Larva";132;2
"Unit";"Roach";"Larva";132;2
"Unit";"Roach";"Larva";132;2
"Upgrade";"ZergGroundArmorsLevel1";"EvolutionChamber";95;0
"Building";"Extractor";NA;132;0
"Unit";"Roach";"Larva";150;2
"Unit";"Roach";"Larva";150;2
"Unit";"Roach";"Larva";150;2
"Unit";"Zergling";"Larva";169;1
"Unit";"Zergling";"Larva";169;1
"Unit";"Zergling";"Larva";169;1
"Unit";"Zergling";"Larva";169;1
"Unit";"Zergling";"Larva";169;1
"Unit";"Zergling";"Larva";169;1
"Unit";"Zergling";"Larva";169;1
"Unit";"Zergling";"Larva";169;1
"Unit";"Zergling";"Larva";169;1
"Unit";"Zergling";"Larva";169;1
"Unit";"Zergling";"Larva";169;1
"Unit";"Zergling";"Larva";169;1
"Unit";"Zergling";"Larva";169;1
"Unit";"Zergling";"Larva";169;1
"Unit";"Zergling";"Larva";169;1
"Unit";"Zergling";"Larva";169;1
"Unit";"Zergling";"Larva";169;1
"Unit";"Zergling";"Larva";169;1
"Unit";"Zergling";"Larva";169;1
"Unit";"Zergling";"Larva";169;1
"Unit";"Zergling";"Larva";169;1
"Unit";"Zergling";"Larva";169;1
"Unit";"Roach";"Larva";169;2
"Unit";"Roach";"Larva";169;2
"Unit";"Roach";"Larva";169;2
"Unit";"Roach";"Larva";169;2
"Unit";"Overlord";"Larva";169;0
"Unit";"Overlord";"Larva";169;0
"Unit";"Roach";"Larva";191;2
"Unit";"Roach";"Larva";191;2
"Unit";"Roach";"Larva";191;2
"Unit";"Roach";"Larva";199;2
"Unit";"Roach";"Larva";199;2
"Unit";"Roach";"Larva";199;2
"Unit";"Roach";"Larva";199;2
"Unit";"Roach";"Larva";199;2
"Unit";"Roach";"Larva";205;2
"Unit";"Roach";"Larva";205;2
"Unit";"Roach";"Larva";205;2
"Unit";"Roach";"Larva";205;2
"Unit";"Roach";"Larva";205;2
"Unit";"Roach";"Larva";205;2
"Unit";"Roach";"Larva";213;2
"Unit";"Zergling";"Larva";215;1
"Unit";"Zergling";"Larva";215;1
"Unit";"Zergling";"Larva";217;1
"Unit";"Zergling";"Larva";217;1
"Unit";"Zergling";"Larva";217;1
"Unit";"Zergling";"Larva";217;1
"Unit";"Zergling";"Larva";217;1
"Unit";"Zergling";"Larva";217;1
"Unit";"Zergling";"Larva";217;1
"Unit";"Zergling";"Larva";217;1
"Unit";"Zergling";"Larva";219;1
"Unit";"Zergling";"Larva";219;1
"Unit";"Zergling";"Larva";219;1
"Unit";"Zergling";"Larva";219;1
"Unit";"Zergling";"Larva";219;1
"Unit";"Zergling";"Larva";219;1
"Unit";"Zergling";"Larva";219;1
"Unit";"Zergling";"Larva";219;1
"Unit";"Zergling";"Larva";221;1
"Unit";"Zergling";"Larva";221;1
"Unit";"Zergling";"Larva";221;1
"Unit";"Zergling";"Larva";221;1
"Unit";"Zergling";"Larva";227;1
"Unit";"Zergling";"Larva";227;1
"Unit";"Zergling";"Larva";227;1
"Unit";"Zergling";"Larva";227;1
"Unit";"Zergling";"Larva";227;1
"Unit";"Zergling";"Larva";227;1
"Unit";"Zergling";"Larva";229;1
"Unit";"Zergling";"Larva";229;1
"Unit";"Zergling";"Larva";229;1
"Unit";"Zergling";"Larva";229;1
"Unit";"Zergling";"Larva";229;1
"Unit";"Zergling";"Larva";229;1
"Upgrade";"ZergMissileWeaponsLevel2";"EvolutionChamber";169;0
"Unit";"Zergling";"Larva";251;1
"Unit";"Zergling";"Larva";251;1
"Unit";"Zergling";"Larva";251;1
"Unit";"Zergling";"Larva";251;1
"Unit";"Zergling";"Larva";251;1
"Unit";"Zergling";"Larva";251;1
"Unit";"Zergling";"Larva";251;1
"Unit";"Zergling";"Larva";251;1
"Unit";"Zergling";"Larva";251;1
"Unit";"Zergling";"Larva";251;1
"Unit";"Zergling";"Larva";251;1
"Unit";"Zergling";"Larva";251;1
"Unit";"Zergling";"Larva";251;1
"Unit";"Zergling";"Larva";251;1
"Unit";"Zergling";"Larva";251;1
"Unit";"Zergling";"Larva";251;1
"Unit";"Zergling";"Larva";251;1
"Unit";"Zergling";"Larva";251;1
"Unit";"Zergling";"Larva";251;1
"Unit";"Zergling";"Larva";251;1
"Unit";"Zergling";"Larva";251;1
"Unit";"Zergling";"Larva";251;1
"Building";"RoachWarren";NA;251;0
"Unit";"Zergling";"Larva";285;1
"Unit";"Zergling";"Larva";285;1
"Upgrade";"ZergGroundArmorsLevel2";"EvolutionChamber";199;0
"Unit";"Zergling";"Larva";285;1
"Unit";"Zergling";"Larva";285;1
"Unit";"Zergling";"Larva";285;1
"Unit";"Zergling";"Larva";285;1
"Unit";"Zergling";"Larva";285;1
"Unit";"Zergling";"Larva";285;1
"Unit";"Zergling";"Larva";285;1
"Unit";"Zergling";"Larva";285;1
"Unit";"Zergling";"Larva";285;1
"Unit";"Zergling";"Larva";285;1
"Unit";"Zergling";"Larva";285;1
"Unit";"Zergling";"Larva";285;1
"Unit";"Zergling";"Larva";285;1
"Unit";"Zergling";"Larva";285;1
"Unit";"Zergling";"Larva";285;1
"Unit";"Zergling";"Larva";285;1
"Building";"Extractor";NA;285;0
"Unit";"Roach";"Larva";303;2
"Unit";"Queen";"Hatchery";285;2
"Unit";"Roach";"Larva";303;2
"Unit";"Roach";"Larva";303;2
"Unit";"Roach";"Larva";303;2
"Unit";"Roach";"Larva";303;2
"Unit";"Roach";"Larva";303;2
"Unit";"Roach";"Larva";303;2
"Unit";"Roach";"Larva";303;2
"Unit";"Roach";"Larva";303;2
"Unit";"Roach";"Larva";303;2
"Unit";"Roach";"Larva";303;2
"Unit";"Roach";"Larva";303;2
"Unit";"Roach";"Larva";329;2
"Unit";"Roach";"Larva";329;2
"Unit";"Roach";"Larva";329;2
"Unit";"Roach";"Larva";329;2
"Unit";"Roach";"Larva";329;2
"Unit";"Roach";"Larva";329;2
"Unit";"Roach";"Larva";329;2
"Unit";"Roach";"Larva";329;2
"Unit";"Roach";"Larva";329;2
"Unit";"Roach";"Larva";329;2
"Unit";"Roach";"Larva";329;2
"Unit";"Roach";"Larva";329;2
"Unit";"Roach";"Larva";329;2
"Building";"Spire";NA;285;0
"Upgrade";"ZergMeleeWeaponsLevel1";"EvolutionChamber";303;0
"Unit";"Mutalisk";"Larva";355;2
"Unit";"Mutalisk";"Larva";355;2
"Unit";"Mutalisk";"Larva";355;2
"Unit";"Mutalisk";"Larva";355;2
"Unit";"Mutalisk";"Larva";355;2
"Unit";"Mutalisk";"Larva";355;2
"Unit";"Mutalisk";"Larva";355;2
"Unit";"Mutalisk";"Larva";355;2
"Unit";"Mutalisk";"Larva";355;2
"Unit";"Mutalisk";"Larva";355;2
"Unit";"Mutalisk";"Larva";355;2
"Unit";"Mutalisk";"Larva";355;2
"Unit";"Mutalisk";"Larva";355;2
"Unit";"Zergling";"Larva";355;1
"Unit";"Zergling";"Larva";355;1
"Unit";"Zergling";"Larva";355;1
"Unit";"Zergling";"Larva";355;1
"Unit";"Queen";"Hatchery";355;2
"Unit";"Mutalisk";"Larva";355;2
"Unit";"Mutalisk";"Larva";355;2
"Unit";"Mutalisk";"Larva";355;2
"Unit";"Mutalisk";"Larva";355;2
"Unit";"Mutalisk";"Larva";355;2
"Unit";"Zergling";"Larva";375;1
"Unit";"Zergling";"Larva";375;1
"Unit";"Zergling";"Larva";377;1
"Unit";"Zergling";"Larva";377;1
"Unit";"Zergling";"Larva";381;1
"Unit";"Zergling";"Larva";381;1
"Unit";"Zergling";"Larva";397;1
"Unit";"Zergling";"Larva";397;1
"Unit";"Zergling";"Larva";397;1
"Unit";"Zergling";"Larva";397;1
"Unit";"Zergling";"Larva";397;1
"Unit";"Zergling";"Larva";397;1
"Unit";"Zergling";"Larva";397;1
"Unit";"Zergling";"Larva";397;1
"Unit";"Zergling";"Larva";397;1
"Unit";"Zergling";"Larva";397;1
"Building";"Hatchery";NA;355;0
"Unit";"Zergling";"Larva";413;1
"Unit";"Zergling";"Larva";413;1
"Unit";"Mutalisk";"Larva";403;2
"Unit";"Mutalisk";"Larva";403;2
"Unit";"Mutalisk";"Larva";403;2
"Unit";"Mutalisk";"Larva";403;2
"Unit";"Mutalisk";"Larva";403;2
"Unit";"Zergling";"Larva";413;1
"Unit";"Zergling";"Larva";413;1
"Unit";"Zergling";"Larva";413;1
"Unit";"Zergling";"Larva";413;1
"Unit";"Zergling";"Larva";413;1
"Unit";"Zergling";"Larva";413;1
"Unit";"Zergling";"Larva";413;1
"Unit";"Zergling";"Larva";413;1
"Unit";"Zergling";"Larva";413;1
"Unit";"Zergling";"Larva";413;1
"Building";"BanelingNest";NA;413;0
"Unit";"Mutalisk";"Larva";435;2
"Unit";"Mutalisk";"Larva";435;2
"Unit";"Mutalisk";"Larva";435;2
"Unit";"Mutalisk";"Larva";435;2
"Unit";"Mutalisk";"Larva";435;2
"Unit";"Mutalisk";"Larva";436;2
"Unit";"Zergling";"Larva";442;1
"Unit";"Zergling";"Larva";442;1
"Unit";"Zergling";"Larva";442;1
"Unit";"Zergling";"Larva";442;1
"Unit";"Zergling";"Larva";442;1
"Unit";"Zergling";"Larva";442;1
"Unit";"Zergling";"Larva";442;1
"Unit";"Zergling";"Larva";442;1
"Unit";"Zergling";"Larva";442;1
"Unit";"Zergling";"Larva";442;1
"Unit";"Zergling";"Larva";442;1
"Unit";"Zergling";"Larva";442;1
"Unit";"Zergling";"Larva";442;1
"Unit";"Zergling";"Larva";442;1
"Unit";"Zergling";"Larva";442;1
"Unit";"Zergling";"Larva";442;1
"Unit";"Baneling";"Zergling";470;0
"Unit";"Baneling";"Zergling";470;0
"Unit";"Baneling";"Zergling";470;0
"Unit";"Baneling";"Zergling";470;0
"Unit";"Baneling";"Zergling";470;0
"Unit";"Baneling";"Zergling";470;0
"Unit";"Baneling";"Zergling";470;0
"Unit";"Baneling";"Zergling";470;0
"Unit";"Baneling";"Zergling";470;0
"Unit";"Baneling";"Zergling";470;0
"Unit";"Baneling";"Zergling";470;0
"Unit";"Baneling";"Zergling";470;0
"Unit";"Baneling";"Zergling";470;0
"Unit";"Baneling";"Zergling";470;0
"Unit";"Baneling";"Zergling";470;0
"Unit";"Baneling";"Zergling";470;0
"Unit";"Baneling";"Zergling";470;0
"Unit";"Baneling";"Zergling";470;0
"Unit";"Baneling";"Zergling";470;0
"Unit";"Baneling";"Zergling";470;0
"Unit";"Zergling";"Larva";470;1
"Unit";"Zergling";"Larva";470;1
"Unit";"Zergling";"Larva";470;1
"Unit";"Zergling";"Larva";470;1
"Unit";"Zergling";"Larva";470;1
"Unit";"Zergling";"Larva";470;1
"Unit";"Zergling";"Larva";470;1
"Unit";"Zergling";"Larva";470;1
"Unit";"Zergling";"Larva";470;1
"Unit";"Zergling";"Larva";470;1
"Unit";"Zergling";"Larva";470;1
"Unit";"Zergling";"Larva";470;1
"Unit";"Zergling";"Larva";470;1
"Unit";"Zergling";"Larva";470;1
"Unit";"Zergling";"Larva";470;1
"Unit";"Zergling";"Larva";470;1
"Building";"Extractor";NA;470;0
"Building";"Extractor";NA;470;0
"Unit";"Overlord";"Larva";470;0
"Unit";"Overlord";"Larva";470;0
"Unit";"Overlord";"Larva";470;0
"Upgrade";"ZergMeleeWeaponsLevel2";"EvolutionChamber";435;0
"Unit";"Baneling";"Zergling";488;0
"Unit";"Baneling";"Zergling";488;0
"Unit";"Baneling";"Zergling";488;0
"Unit";"Baneling";"Zergling";488;0
"Unit";"Baneling";"Zergling";488;0
"Unit";"Baneling";"Zergling";488;0
"Unit";"Baneling";"Zergling";488;0
"Unit";"Baneling";"Zergling";488;0
"Unit";"Baneling";"Zergling";488;0
"Unit";"Baneling";"Zergling";488;0
"Unit";"Baneling";"Zergling";502;0
"Unit";"Baneling";"Zergling";502;0
"Unit";"Baneling";"Zergling";502;0
"Unit";"Baneling";"Zergling";502;0
"Unit";"Baneling";"Zergling";502;0
"Unit";"Baneling";"Zergling";502;0
"Unit";"Baneling";"Zergling";502;0
"Unit";"Baneling";"Zergling";502;0
"Unit";"Baneling";"Zergling";502;0
"Unit";"Baneling";"Zergling";502;0
"Unit";"Baneling";"Zergling";502;0
"Unit";"Baneling";"Zergling";502;0
"Unit";"Baneling";"Zergling";502;0
"Unit";"Baneling";"Zergling";502;0
"Unit";"Baneling";"Zergling";502;0
"Unit";"Baneling";"Zergling";502;0
"Unit";"Baneling";"Zergling";502;0
"Unit";"Baneling";"Zergling";502;0
"Unit";"Baneling";"Zergling";502;0
"Unit";"Baneling";"Zergling";502;0
"Unit";"Baneling";"Zergling";502;0
"Unit";"Baneling";"Zergling";502;0
"Unit";"Baneling";"Zergling";502;0
"Unit";"Baneling";"Zergling";502;0
"Unit";"Baneling";"Zergling";502;0
"Unit";"Baneling";"Zergling";502;0
"Unit";"Zergling";"Larva";502;1
"Unit";"Zergling";"Larva";502;1
"Unit";"Zergling";"Larva";502;1
"Unit";"Zergling";"Larva";502;1
"Unit";"Zergling";"Larva";506;1
"Unit";"Zergling";"Larva";506;1
"Unit";"Zergling";"Larva";506;1
"Unit";"Zergling";"Larva";506;1
"Unit";"Zergling";"Larva";506;1
"Unit";"Zergling";"Larva";506;1
"Unit";"Zergling";"Larva";506;1
"Unit";"Zergling";"Larva";506;1
"Unit";"Zergling";"Larva";506;1
"Unit";"Zergling";"Larva";506;1
"Unit";"Zergling";"Larva";506;1
"Unit";"Zergling";"Larva";506;1
"Unit";"Zergling";"Larva";506;1
"Unit";"Zergling";"Larva";506;1
"Unit";"Zergling";"Larva";506;1
"Unit";"Zergling";"Larva";506;1
"Unit";"Zergling";"Larva";506;1
"Unit";"Zergling";"Larva";506;1
"Unit";"Zergling";"Larva";506;1
"Unit";"Zergling";"Larva";506;1
"Unit";"Zergling";"Larva";506;1
"Unit";"Zergling";"Larva";506;1
"Unit";"Zergling";"Larva";506;1
"Unit";"Zergling";"Larva";506;1
"Unit";"Zergling";"Larva";506;1
"Unit";"Zergling";"Larva";506;1
"Unit";"Zergling";"Larva";506;1
"Unit";"Zergling";"Larva";506;1
"Unit";"Zergling";"Larva";506;1
"Unit";"Zergling";"Larva";506;1
"Unit";"Zergling";"Larva";506;1
"Unit";"Zergling";"Larva";506;1
"Unit";"Zergling";"Larva";506;1
"Unit";"Zergling";"Larva";506;1
"Unit";"Zergling";"Larva";506;1
"Unit";"Zergling";"Larva";506;1
"Unit";"Zergling";"Larva";506;1
"Unit";"Zergling";"Larva";506;1
"Unit";"Zergling";"Larva";506;1
"Unit";"Zergling";"Larva";506;1
"Unit";"Zergling";"Larva";506;1
"Unit";"Zergling";"Larva";506;1
"Unit";"Mutalisk";"Larva";506;2
"Unit";"Mutalisk";"Larva";506;2
"Unit";"Baneling";"Zergling";548;0
"Unit";"Baneling";"Zergling";548;0
"Unit";"Baneling";"Zergling";548;0
"Unit";"Baneling";"Zergling";548;0
"Unit";"Baneling";"Zergling";548;0
"Unit";"Baneling";"Zergling";548;0
"Unit";"Baneling";"Zergling";548;0
"Unit";"Baneling";"Zergling";548;0
"Unit";"Baneling";"Zergling";548;0
"Unit";"Baneling";"Zergling";548;0
"Unit";"Baneling";"Zergling";548;0
"Unit";"Baneling";"Zergling";548;0
"Unit";"Baneling";"Zergling";548;0
"Unit";"Baneling";"Zergling";548;0
"Unit";"Baneling";"Zergling";548;0
"Unit";"Baneling";"Zergling";548;0
"Unit";"Baneling";"Zergling";548;0
"Unit";"Baneling";"Zergling";548;0
"Unit";"Baneling";"Zergling";548;0
"Unit";"Baneling";"Zergling";548;0
"Unit";"Baneling";"Zergling";548;0
"Unit";"Baneling";"Zergling";548;0
"Unit";"Baneling";"Zergling";548;0
"Unit";"Baneling";"Zergling";548;0
"Unit";"Baneling";"Zergling";548;0
"Unit";"Baneling";"Zergling";548;0
"Unit";"Baneling";"Zergling";548;0
"Upgrade";"Burrow";"Hatchery";506;0
"Unit";"Baneling";"Zergling";548;0
"Unit";"Baneling";"Zergling";548;0
"Unit";"Baneling";"Zergling";548;0
"Unit";"Baneling";"Zergling";548;0
"Unit";"Baneling";"Zergling";548;0
"Unit";"Baneling";"Zergling";548;0
"Unit";"Baneling";"Zergling";548;0
"Unit";"Baneling";"Zergling";548;0
"Unit";"Baneling";"Zergling";548;0
"Unit";"Baneling";"Zergling";548;0
"Unit";"Baneling";"Zergling";548;0
"Unit";"Baneling";"Zergling";548;0
"Unit";"Baneling";"Zergling";548;0
"Unit";"Baneling";"Zergling";548;0
"Unit";"Baneling";"Zergling";548;0
"Unit";"Baneling";"Zergling";548;0
"Unit";"Baneling";"Zergling";548;0
"Unit";"Baneling";"Zergling";548;0
"Unit";"Mutalisk";"Larva";552;2
"Unit";"Mutalisk";"Larva";552;2
"Unit";"Mutalisk";"Larva";552;2
"Unit";"Mutalisk";"Larva";552;2
"Building";"InfestationPit";NA;552;0
"Unit";"Roach";"Larva";552;2
"Unit";"Roach";"Larva";552;2
"Unit";"Roach";"Larva";552;2
"Unit";"Roach";"Larva";552;2
"Unit";"Roach";"Larva";552;2
"Unit";"Roach";"Larva";552;2
"Unit";"Roach";"Larva";552;2
"Unit";"Roach";"Larva";552;2
"Unit";"Roach";"Larva";552;2
"Unit";"Roach";"Larva";552;2
"Unit";"Roach";"Larva";552;2
"Unit";"Roach";"Larva";552;2
"Unit";"Roach";"Larva";560;2
"Unit";"Roach";"Larva";560;2
"Unit";"Roach";"Larva";560;2
"Unit";"Roach";"Larva";560;2
"Unit";"Roach";"Larva";560;2
"Unit";"Roach";"Larva";560;2
"Unit";"Roach";"Larva";560;2
"Unit";"Roach";"Larva";560;2
"Unit";"Roach";"Larva";560;2
"Building";"Hatchery";NA;552;0
"Unit";"Roach";"Larva";602;2
"Unit";"Roach";"Larva";602;2
"Unit";"Roach";"Larva";602;2
"Unit";"Roach";"Larva";602;2
"Unit";"Roach";"Larva";602;2
"Unit";"Roach";"Larva";602;2
"Unit";"Roach";"Larva";602;2
"Unit";"Roach";"Larva";602;2
"Unit";"Roach";"Larva";602;2
"Unit";"Roach";"Larva";602;2
"Unit";"Roach";"Larva";602;2
"Unit";"Roach";"Larva";602;2
"Unit";"Overlord";"Larva";626;0
"Unit";"Overlord";"Larva";626;0
"Unit";"Overlord";"Larva";626;0
"Unit";"Overlord";"Larva";626;0
"Unit";"Overlord";"Larva";626;0
"Unit";"Mutalisk";"Larva";626;2
"Unit";"Mutalisk";"Larva";626;2
"Unit";"Mutalisk";"Larva";626;2
"Unit";"Mutalisk";"Larva";626;2
"Unit";"Mutalisk";"Larva";626;2
"Unit";"Mutalisk";"Larva";626;2
"Building";"Extractor";NA;652;0
"Building";"Extractor";NA;652;0
