"type";"unit_name";"on_building";"total_supply_lag";"supply"
"Unit";"Overlord";"Larva";13;0
"Building";"Hatchery";NA;17;0
"Building";"SpawningPool";NA;19;0
"Building";"Hatchery";NA;23;0
"Unit";"Queen";"Hatchery";24;2
"Unit";"Queen";"Hatchery";26;2
"Unit";"Overlord";"Larva";29;0
"Unit";"Zergling";"Larva";29;1
"Unit";"Zergling";"Larva";30;1
"Unit";"Zergling";"Larva";31;1
"Unit";"Zergling";"Larva";32;1
"Unit";"Queen";"Hatchery";37;2
"Unit";"Queen";"Hatchery";39;2
"Building";"SpineCrawler";NA;41;0
"Unit";"Overlord";"Larva";41;0
"Building";"SpineCrawler";NA;41;0
"Unit";"Zergling";"Larva";41;1
"Unit";"Zergling";"Larva";42;1
"Unit";"Zergling";"Larva";43;1
"Unit";"Zergling";"Larva";44;1
"Unit";"Zergling";"Larva";45;1
"Unit";"Zergling";"Larva";46;1
"Unit";"Zergling";"Larva";47;1
"Unit";"Zergling";"Larva";48;1
"Unit";"Zergling";"Larva";49;1
"Unit";"Zergling";"Larva";50;1
"Unit";"Zergling";"Larva";51;1
"Unit";"Zergling";"Larva";52;1
"Unit";"Zergling";"Larva";53;1
"Unit";"Zergling";"Larva";54;1
"Unit";"Queen";"Hatchery";55;2
"Unit";"Queen";"Hatchery";57;2
"Unit";"Queen";"Hatchery";59;2
"Unit";"Zergling";"Larva";61;1
"Unit";"Zergling";"Larva";62;1
"Unit";"Zergling";"Larva";63;1
"Unit";"Zergling";"Larva";64;1
"Unit";"Zergling";"Larva";65;1
"Unit";"Zergling";"Larva";66;1
"Unit";"Zergling";"Larva";67;1
"Unit";"Zergling";"Larva";68;1
"Unit";"Zergling";"Larva";69;1
"Unit";"Zergling";"Larva";70;1
"Unit";"Overlord";"Larva";71;0
"Building";"CreepTumorQueen";NA;84;0
"Unit";"Overlord";"Larva";92;0
"Building";"CreepTumor";NA;94;0
"Building";"Extractor";NA;95;0
"Unit";"Overlord";"Larva";95;0
"Building";"Extractor";NA;95;0
"Unit";"Overlord";"Larva";97;0
"Building";"EvolutionChamber";NA;106;0
"Building";"EvolutionChamber";NA;109;0
"Building";"RoachWarren";NA;109;0
"Building";"CreepTumor";NA;112;0
"Building";"CreepTumorQueen";NA;115;0
"Unit";"Overlord";"Larva";117;0
"Building";"Extractor";NA;122;0
"Building";"Extractor";NA;123;0
"Building";"Extractor";NA;124;0
"Unit";"Overlord";"Larva";124;0
"Unit";"Overlord";"Larva";134;0
"Building";"Extractor";NA;134;0
"Building";"CreepTumor";NA;134;0
"Unit";"Overlord";"Larva";134;0
"Building";"Hatchery";NA;134;0
"Unit";"Overlord";"Larva";134;0
"Unit";"Roach";"Larva";136;2
"Unit";"Roach";"Larva";138;2
"Unit";"Roach";"Larva";140;2
"Unit";"Roach";"Larva";142;2
"Building";"CreepTumor";NA;144;0
"Building";"CreepTumorQueen";NA;144;0
"Unit";"Overlord";"Larva";144;0
"Unit";"Roach";"Larva";144;2
"Unit";"Roach";"Larva";146;2
"Unit";"Roach";"Larva";148;2
"Unit";"Roach";"Larva";150;2
"Unit";"Roach";"Larva";152;2
"Building";"CreepTumor";NA;154;0
"Unit";"Overlord";"Larva";154;0
"Unit";"Roach";"Larva";154;2
"Unit";"Roach";"Larva";156;2
"Unit";"Roach";"Larva";158;2
"Unit";"Roach";"Larva";160;2
"Unit";"Overlord";"Larva";162;0
"Unit";"Roach";"Larva";162;2
"Unit";"Roach";"Larva";164;2
"Unit";"Roach";"Larva";166;2
"Unit";"Roach";"Larva";168;2
"Unit";"Roach";"Larva";170;2
"Unit";"Overlord";"Larva";172;0
"Unit";"Overlord";"Larva";172;0
"Upgrade";"GlialReconstitution";"RoachWarren";172;0
"Unit";"Roach";"Larva";172;2
"Unit";"Roach";"Larva";174;2
"Unit";"Roach";"Larva";176;2
"Unit";"Roach";"Larva";178;2
"Unit";"Overlord";"Larva";180;0
"Unit";"Roach";"Larva";180;2
"Unit";"Roach";"Larva";182;2
"Unit";"Overlord";"Larva";184;0
"Unit";"Overlord";"Larva";184;0
"Building";"CreepTumor";NA;184;0
"Building";"CreepTumor";NA;184;0
"Building";"CreepTumor";NA;184;0
"Building";"HydraliskDen";NA;187;0
"Unit";"Overlord";"Larva";195;0
"Building";"Extractor";NA;195;0
"Unit";"Hydralisk";"Larva";195;2
"Unit";"Hydralisk";"Larva";197;2
"Unit";"Hydralisk";"Larva";199;2
"Unit";"Hydralisk";"Larva";201;2
"Unit";"Hydralisk";"Larva";203;2
"Unit";"Hydralisk";"Larva";205;2
"Unit";"Hydralisk";"Larva";207;2
"Unit";"Hydralisk";"Larva";209;2
"Unit";"Hydralisk";"Larva";211;2
"Building";"LurkerDenMP";NA;213;0
"Unit";"Roach";"Larva";213;2
"Unit";"Roach";"Larva";215;2
"Unit";"Roach";"Larva";217;2
"Unit";"Roach";"Larva";219;2
"Unit";"Overlord";"Larva";221;0
"Unit";"Roach";"Larva";221;2
"Unit";"Roach";"Larva";223;2
"Unit";"Roach";"Larva";225;2
"Unit";"Roach";"Larva";227;2
"Unit";"Roach";"Larva";229;2
"Unit";"Roach";"Larva";231;2
"Unit";"Roach";"Larva";233;2
"Unit";"Roach";"Larva";235;2
"Unit";"Overlord";"Larva";237;0
"Unit";"Roach";"Larva";237;2
"Unit";"Roach";"Larva";239;2
"Unit";"Roach";"Larva";241;2
"Unit";"Roach";"Larva";243;2
"Unit";"Roach";"Larva";245;2
"Building";"Extractor";NA;247;0
"Unit";"Overlord";"Larva";247;0
"Unit";"Roach";"Larva";247;2
"Unit";"Roach";"Larva";249;2
"Unit";"Roach";"Larva";251;2
"Unit";"Roach";"Larva";253;2
"Unit";"Roach";"Larva";255;2
"Unit";"Overlord";"Larva";257;0
"Unit";"Roach";"Larva";257;2
"Unit";"Roach";"Larva";259;2
"Unit";"Roach";"Larva";261;2
"Unit";"Roach";"Larva";263;2
"Unit";"Roach";"Larva";265;2
"Unit";"Roach";"Larva";267;2
"Unit";"Roach";"Larva";269;2
"Unit";"Roach";"Larva";271;2
"Unit";"Roach";"Larva";273;2
"Upgrade";"SprayZerg";NA;275;0
"Upgrade";"SprayZerg";NA;275;0
"Upgrade";"SprayZerg";NA;275;0
"Upgrade";"SprayZerg";NA;275;0
"Upgrade";"SprayZerg";NA;275;0
"Upgrade";"SprayZerg";NA;275;0
"Upgrade";"ZergMissileWeaponsLevel1";NA;275;0
"Upgrade";"ZergGroundArmorsLevel1";NA;275;0
"Upgrade";"SprayZerg";NA;275;0
"Upgrade";"EvolveMuscularAugments";NA;275;0
"Upgrade";"overlordspeed";NA;275;0
