"type";"unit_name";"on_building";"total_supply";"supply"
"Unit";"Overlord";"Larva";12;0
"Building";"Extractor";NA;19;0
"Building";"SpawningPool";NA;19;0
"Building";"Hatchery";NA;17;0
"Unit";"Overlord";"Larva";23;0
"Unit";"Zergling";"Larva";23;1
"Unit";"Zergling";"Larva";23;1
"Unit";"Queen";"Hatchery";23;2
"Unit";"Queen";"Hatchery";23;2
"Unit";"Zergling";"Larva";25;1
"Unit";"Zergling";"Larva";25;1
"Unit";"Zergling";"Larva";36;1
"Unit";"Zergling";"Larva";36;1
"Unit";"Zergling";"Larva";36;1
"Unit";"Zergling";"Larva";36;1
"Unit";"Zergling";"Larva";36;1
"Unit";"Zergling";"Larva";36;1
"Unit";"Overlord";"Larva";36;0
"Building";"BanelingNest";NA;31;0
"Unit";"Queen";"Hatchery";36;2
"Building";"CreepTumorQueen";NA;43;0
"Unit";"Overlord";"Larva";42;0
"Unit";"Zergling";"Larva";43;1
"Unit";"Zergling";"Larva";43;1
"Unit";"Zergling";"Larva";43;1
"Unit";"Zergling";"Larva";43;1
"Unit";"Baneling";"Zergling";43;0
"Unit";"Baneling";"Zergling";43;0
"Unit";"Baneling";"Zergling";45;0
"Unit";"Baneling";"Zergling";45;0
"Unit";"Zergling";"Larva";45;1
"Unit";"Zergling";"Larva";45;1
"Unit";"Zergling";"Larva";45;1
"Unit";"Zergling";"Larva";45;1
"Building";"CreepTumor";NA;57;0
"Building";"CreepTumorQueen";NA;61;0
"Unit";"Overlord";"Larva";61;0
"Building";"Hatchery";NA;43;0
"Unit";"Overlord";"Larva";66;0
"Building";"CreepTumorQueen";NA;68;0
"Building";"EvolutionChamber";NA;68;0
"Building";"CreepTumor";NA;69;0
"Building";"CreepTumor";NA;75;0
"Building";"Extractor";NA;69;0
"Building";"Extractor";NA;76;0
"Building";"RoachWarren";NA;69;0
"Building";"Extractor";NA;79;0
"Building";"CreepTumor";NA;83;0
"Building";"CreepTumor";NA;83;0
"Building";"CreepTumor";NA;83;0
"Unit";"Overlord";"Larva";85;0
"Unit";"Overlord";"Larva";85;0
"Unit";"Overlord";"Larva";85;0
"Unit";"Roach";"Larva";89;2
"Unit";"Roach";"Larva";89;2
"Unit";"Roach";"Larva";94;2
"Unit";"Roach";"Larva";94;2
"Building";"Extractor";NA;94;0
"Unit";"Roach";"Larva";94;2
"Unit";"Roach";"Larva";94;2
"Unit";"Roach";"Larva";94;2
"Unit";"Roach";"Larva";94;2
"Unit";"Roach";"Larva";94;2
"Unit";"Roach";"Larva";94;2
"Building";"CreepTumor";NA;102;0
"Unit";"Roach";"Larva";94;2
"Unit";"Roach";"Larva";94;2
"Unit";"Overlord";"Larva";102;0
"Unit";"Overlord";"Larva";102;0
"Unit";"Overlord";"Larva";114;0
"Unit";"Overlord";"Larva";114;0
"Unit";"Overlord";"Larva";114;0
"Building";"CreepTumor";NA;118;0
"Building";"CreepTumor";NA;118;0
"Building";"CreepTumor";NA;118;0
"Upgrade";"GlialReconstitution";"RoachWarren";94;0
"Building";"HydraliskDen";NA;118;0
"Building";"SporeCrawler";NA;118;0
"Building";"SporeCrawler";NA;128;0
"Building";"Hatchery";NA;94;0
"Building";"SporeCrawler";NA;128;0
"Building";"SporeCrawler";NA;128;0
"Unit";"Queen";"Hatchery";118;2
"Unit";"Queen";"Hatchery";118;2
"Upgrade";"ZergMissileWeaponsLevel1";"EvolutionChamber";94;0
"Unit";"Hydralisk";"Larva";128;2
"Unit";"Hydralisk";"Larva";128;2
"Unit";"Hydralisk";"Larva";128;2
"Unit";"Hydralisk";"Larva";128;2
"Building";"SporeCrawler";NA;128;0
"Unit";"Queen";"Hatchery";128;2
"Unit";"Hydralisk";"Larva";128;2
"Unit";"Hydralisk";"Larva";128;2
"Unit";"Hydralisk";"Larva";128;2
"Unit";"Hydralisk";"Larva";128;2
"Unit";"Hydralisk";"Larva";128;2
"Unit";"Hydralisk";"Larva";128;2
"Unit";"Overlord";"Larva";140;0
"Unit";"Overlord";"Larva";140;0
"Unit";"Overlord";"Larva";140;0
"Unit";"Overlord";"Larva";140;0
"Unit";"Hydralisk";"Larva";140;2
"Building";"CreepTumor";NA;156;0
"Unit";"Overlord";"Larva";154;0
"Unit";"Overlord";"Larva";154;0
"Unit";"Hydralisk";"Larva";154;2
"Unit";"Hydralisk";"Larva";154;2
"Unit";"Hydralisk";"Larva";154;2
"Unit";"Hydralisk";"Larva";154;2
"Unit";"Roach";"Larva";154;2
"Unit";"Roach";"Larva";154;2
"Unit";"Roach";"Larva";154;2
"Unit";"Roach";"Larva";154;2
"Unit";"Roach";"Larva";154;2
"Building";"CreepTumor";NA;156;0
"Building";"SporeCrawler";NA;156;0
"Unit";"Roach";"Larva";156;2
"Unit";"Roach";"Larva";156;2
"Unit";"Roach";"Larva";156;2
"Unit";"Roach";"Larva";156;2
"Unit";"Roach";"Larva";156;2
"Unit";"Hydralisk";"Larva";156;2
"Unit";"Hydralisk";"Larva";156;2
"Building";"CreepTumorQueen";NA;180;0
"Unit";"Hydralisk";"Larva";156;2
"Building";"CreepTumorQueen";NA;184;0
"Upgrade";"EvolveMuscularAugments";"HydraliskDen";154;0
"Building";"CreepTumor";NA;190;0
"Building";"Extractor";NA;184;0
"Unit";"Hydralisk";"Larva";190;2
"Unit";"Hydralisk";"Larva";190;2
"Unit";"Hydralisk";"Larva";190;2
"Unit";"Hydralisk";"Larva";190;2
"Building";"CreepTumor";NA;203;0
"Building";"Extractor";NA;203;0
"Building";"CreepTumorQueen";NA;203;0
"Building";"CreepTumor";NA;203;0
"Building";"CreepTumor";NA;209;0
"Unit";"Hydralisk";"Larva";203;2
"Unit";"Hydralisk";"Larva";203;2
"Unit";"Roach";"Larva";203;2
"Unit";"Roach";"Larva";203;2
"Unit";"Roach";"Larva";203;2
"Unit";"Roach";"Larva";203;2
"Building";"CreepTumor";NA;211;0
"Unit";"Overlord";"Larva";211;0
"Unit";"Overlord";"Larva";211;0
"Unit";"Overlord";"Larva";211;0
"Unit";"Overlord";"Larva";211;0
"Unit";"Overlord";"Larva";211;0
"Unit";"Overlord";"Larva";223;0
"Unit";"Overlord";"Larva";223;0
"Unit";"Overlord";"Larva";223;0
"Unit";"Overlord";"Larva";223;0
"Unit";"Overlord";"Larva";223;0
"Building";"CreepTumor";NA;223;0
"Unit";"Roach";"Larva";223;2
"Unit";"Roach";"Larva";223;2
"Unit";"Roach";"Larva";223;2
"Unit";"Roach";"Larva";223;2
"Unit";"Roach";"Larva";223;2
"Unit";"Roach";"Larva";223;2
"Unit";"Roach";"Larva";223;2
"Unit";"Roach";"Larva";223;2
"Unit";"Roach";"Larva";223;2
"Upgrade";"EvolveGroovedSpines";"HydraliskDen";211;0
"Building";"LurkerDenMP";NA;184;0
"Unit";"Roach";"Larva";223;2
"Unit";"Roach";"Larva";223;2
"Unit";"Roach";"Larva";223;2
"Unit";"Roach";"Larva";223;2
"Unit";"Roach";"Larva";223;2
"Unit";"Roach";"Larva";223;2
"Unit";"Roach";"Larva";253;2
"Unit";"Roach";"Larva";253;2
"Unit";"Hydralisk";"Larva";253;2
"Unit";"Hydralisk";"Larva";253;2
"Unit";"Hydralisk";"Larva";253;2
"Unit";"Hydralisk";"Larva";253;2
"Unit";"Hydralisk";"Larva";253;2
"Unit";"Hydralisk";"Larva";253;2
"Unit";"Roach";"Larva";253;2
"Unit";"Hydralisk";"Larva";253;2
"Unit";"Hydralisk";"Larva";253;2
"Unit";"Hydralisk";"Larva";253;2
"Unit";"Hydralisk";"Larva";253;2
"Unit";"Hydralisk";"Larva";253;2
"Upgrade";"ZergMissileWeaponsLevel2";"EvolutionChamber";223;0
"Building";"Extractor";NA;269;0
"Unit";"Hydralisk";"Larva";269;2
"Unit";"Hydralisk";"Larva";269;2
"Unit";"Hydralisk";"Larva";269;2
"Unit";"Hydralisk";"Larva";269;2
"Unit";"Hydralisk";"Larva";269;2
"Unit";"Hydralisk";"Larva";269;2
"Unit";"Hydralisk";"Larva";269;2
"Unit";"Roach";"Larva";281;2
"Unit";"Roach";"Larva";281;2
"Unit";"Roach";"Larva";281;2
"Unit";"Hydralisk";"Larva";281;2
"Unit";"Hydralisk";"Larva";281;2
"Unit";"Hydralisk";"Larva";281;2
"Unit";"Roach";"Larva";301;2
"Unit";"Roach";"Larva";301;2
"Unit";"Roach";"Larva";301;2
"Unit";"Roach";"Larva";301;2
"Unit";"Roach";"Larva";301;2
"Unit";"Roach";"Larva";301;2
"Unit";"Roach";"Larva";301;2
"Building";"InfestationPit";NA;281;0
"Unit";"Hydralisk";"Larva";307;2
"Unit";"Hydralisk";"Larva";307;2
"Unit";"Hydralisk";"Larva";307;2
"Unit";"Hydralisk";"Larva";307;2
"Unit";"Hydralisk";"Larva";307;2
"Unit";"Hydralisk";"Larva";307;2
"Unit";"Hydralisk";"Larva";307;2
"Building";"Hatchery";NA;269;0
"Unit";"Hydralisk";"Larva";321;2
"Unit";"Hydralisk";"Larva";321;2
"Unit";"Hydralisk";"Larva";321;2
"Unit";"Hydralisk";"Larva";321;2
"Unit";"Hydralisk";"Larva";321;2
"Unit";"Hydralisk";"Larva";321;2
"Unit";"Hydralisk";"Larva";321;2
"Unit";"Hydralisk";"Larva";335;2
"Unit";"Hydralisk";"Larva";335;2
"Unit";"Hydralisk";"Larva";335;2
"Unit";"Hydralisk";"Larva";335;2
"Unit";"Hydralisk";"Larva";335;2
"Unit";"Hydralisk";"Larva";335;2
"Unit";"Hydralisk";"Larva";335;2
"Unit";"Hydralisk";"Larva";357;2
"Unit";"Hydralisk";"Larva";357;2
"Unit";"Hydralisk";"Larva";357;2
"Unit";"Hydralisk";"Larva";357;2
"Unit";"Hydralisk";"Larva";357;2
"Unit";"Hydralisk";"Larva";357;2
"Unit";"Hydralisk";"Larva";357;2
"Unit";"Hydralisk";"Larva";357;2
"Unit";"Roach";"Larva";363;2
"Unit";"Roach";"Larva";363;2
"Unit";"Roach";"Larva";363;2
"Unit";"Roach";"Larva";363;2
"Unit";"Roach";"Larva";363;2
"Building";"CreepTumor";NA;379;0
"Unit";"Hydralisk";"Larva";363;2
"Unit";"Hydralisk";"Larva";363;2
"Unit";"Hydralisk";"Larva";363;2
"Unit";"Hydralisk";"Larva";363;2
"Unit";"Hydralisk";"Larva";363;2
"Building";"SporeCrawler";NA;389;0
"Building";"CreepTumor";NA;389;0
"Building";"CreepTumor";NA;399;0
"Unit";"Hydralisk";"Larva";389;2
"Unit";"Hydralisk";"Larva";389;2
"Unit";"Hydralisk";"Larva";389;2
"Unit";"Hydralisk";"Larva";389;2
"Unit";"Hydralisk";"Larva";389;2
"Unit";"Hydralisk";"Larva";389;2
"Unit";"Hydralisk";"Larva";389;2
"Unit";"Roach";"Larva";399;2
"Unit";"Roach";"Larva";399;2
"Unit";"Roach";"Larva";399;2
"Unit";"Roach";"Larva";399;2
"Unit";"Hydralisk";"Larva";421;2
"Unit";"Hydralisk";"Larva";421;2
"Unit";"Hydralisk";"Larva";421;2
"Unit";"Hydralisk";"Larva";421;2
"Unit";"Hydralisk";"Larva";421;2
"Unit";"Hydralisk";"Larva";421;2
"Unit";"Hydralisk";"Larva";421;2
"Unit";"Hydralisk";"Larva";421;2
"Unit";"Hydralisk";"Larva";421;2
"Unit";"Hydralisk";"Larva";421;2
"Unit";"Hydralisk";"Larva";421;2
"Unit";"Hydralisk";"Larva";421;2
"Unit";"Hydralisk";"Larva";421;2
"Unit";"Hydralisk";"Larva";421;2
"Unit";"Hydralisk";"Larva";421;2
"Unit";"Hydralisk";"Larva";421;2
"Unit";"Hydralisk";"Larva";421;2
"Building";"CreepTumor";NA;421;0
"Building";"Extractor";NA;421;0
"Unit";"Viper";"Larva";457;3
"Unit";"Viper";"Larva";457;3
"Unit";"Viper";"Larva";457;3
"Unit";"Roach";"Larva";457;2
"Unit";"Roach";"Larva";457;2
"Unit";"Roach";"Larva";457;2
"Unit";"Roach";"Larva";457;2
"Unit";"Roach";"Larva";457;2
"Unit";"Roach";"Larva";457;2
"Unit";"Roach";"Larva";457;2
"Unit";"Roach";"Larva";457;2
"Unit";"Roach";"Larva";457;2
"Unit";"Roach";"Larva";457;2
"Building";"Extractor";NA;457;0
"Building";"CreepTumorQueen";NA;466;0
"Building";"CreepTumorQueen";NA;486;0
"Building";"CreepTumorQueen";NA;486;0
"Building";"CreepTumorQueen";NA;486;0
"Building";"Extractor";NA;486;0
"Building";"Hatchery";NA;486;0
"Building";"Spire";NA;486;0
"Upgrade";"ZergMissileWeaponsLevel3";"EvolutionChamber";486;0
"Building";"Extractor";NA;490;0
"Building";"Extractor";NA;490;0
"Unit";"Hydralisk";"Larva";493;2
"Unit";"Hydralisk";"Larva";493;2
"Unit";"Hydralisk";"Larva";493;2
"Unit";"Hydralisk";"Larva";493;2
"Unit";"Hydralisk";"Larva";493;2
"Unit";"Hydralisk";"Larva";493;2
"Unit";"Hydralisk";"Larva";493;2
"Unit";"Hydralisk";"Larva";493;2
"Unit";"Hydralisk";"Larva";493;2
"Unit";"Hydralisk";"Larva";493;2
"Unit";"Roach";"Larva";495;2
"Unit";"Roach";"Larva";499;2
"Unit";"Hydralisk";"Larva";493;2
"Unit";"Hydralisk";"Larva";493;2
"Unit";"Hydralisk";"Larva";493;2
"Unit";"Hydralisk";"Larva";493;2
"Unit";"Hydralisk";"Larva";493;2
"Unit";"Hydralisk";"Larva";493;2
"Unit";"Hydralisk";"Larva";493;2
"Unit";"Hydralisk";"Larva";493;2
"Building";"SporeCrawler";NA;513;0
"Building";"SporeCrawler";NA;513;0
"Building";"SporeCrawler";NA;513;0
"Building";"Spire";NA;490;0
"Unit";"Corruptor";"Larva";533;2
"Unit";"Corruptor";"Larva";533;2
"Unit";"Corruptor";"Larva";533;2
"Unit";"Corruptor";"Larva";533;2
"Unit";"Corruptor";"Larva";533;2
"Unit";"Corruptor";"Larva";533;2
"Unit";"Corruptor";"Larva";533;2
"Unit";"Roach";"Larva";533;2
"Unit";"Roach";"Larva";533;2
"Unit";"Roach";"Larva";533;2
"Unit";"Hydralisk";"Larva";533;2
"Unit";"Hydralisk";"Larva";533;2
"Unit";"Hydralisk";"Larva";533;2
"Unit";"Hydralisk";"Larva";533;2
"Unit";"Hydralisk";"Larva";533;2
"Unit";"Hydralisk";"Larva";533;2
"Unit";"Hydralisk";"Larva";533;2
"Unit";"Hydralisk";"Larva";533;2
"Unit";"Hydralisk";"Larva";533;2
"Unit";"Hydralisk";"Larva";533;2
"Unit";"Hydralisk";"Larva";533;2
"Unit";"Hydralisk";"Larva";533;2
"Unit";"Hydralisk";"Larva";533;2
"Unit";"Hydralisk";"Larva";533;2
"Unit";"Hydralisk";"Larva";533;2
"Unit";"Hydralisk";"Larva";533;2
"Upgrade";"ZergGroundArmorsLevel1";"EvolutionChamber";493;0
"Unit";"Hydralisk";"Larva";533;2
"Unit";"Hydralisk";"Larva";533;2
"Unit";"Hydralisk";"Larva";533;2
"Unit";"Hydralisk";"Larva";533;2
"Unit";"Hydralisk";"Larva";533;2
"Unit";"Hydralisk";"Larva";533;2
"Unit";"Hydralisk";"Larva";533;2
"Unit";"Hydralisk";"Larva";533;2
"Unit";"Hydralisk";"Larva";533;2
"Unit";"Hydralisk";"Larva";533;2
"Unit";"Hydralisk";"Larva";533;2
