"type";"unit_name";"on_building";"total_supply";"supply"
"Unit";"Overlord";"Larva";13;0
"Building";"Extractor";NA;17;0
"Unit";"Overlord";"Larva";21;0
"Building";"SpawningPool";NA;18;0
"Building";"Hatchery";NA;17;0
"Unit";"Zergling";"Larva";22;1
"Unit";"Zergling";"Larva";22;1
"Unit";"Zergling";"Larva";22;1
"Unit";"Zergling";"Larva";22;1
"Unit";"Queen";"Hatchery";22;2
"Unit";"Queen";"Hatchery";22;2
"Building";"BanelingNest";NA;31;0
"Unit";"Overlord";"Larva";40;0
"Unit";"Overlord";"Larva";42;0
"Unit";"Zergling";"Larva";42;1
"Unit";"Zergling";"Larva";42;1
"Unit";"Zergling";"Larva";42;1
"Unit";"Zergling";"Larva";42;1
"Unit";"Zergling";"Larva";42;1
"Unit";"Zergling";"Larva";42;1
"Unit";"Zergling";"Larva";42;1
"Unit";"Zergling";"Larva";42;1
"Unit";"Zergling";"Larva";42;1
"Unit";"Zergling";"Larva";42;1
"Building";"EvolutionChamber";NA;42;0
"Unit";"Baneling";"Zergling";44;0
"Unit";"Baneling";"Zergling";44;0
"Building";"Extractor";NA;44;0
"Building";"Hatchery";NA;38;0
"Unit";"Overlord";"Larva";49;0
"Unit";"Zergling";"Larva";55;1
"Unit";"Zergling";"Larva";55;1
"Unit";"Zergling";"Larva";55;1
"Unit";"Zergling";"Larva";55;1
"Unit";"Zergling";"Larva";55;1
"Unit";"Zergling";"Larva";55;1
"Unit";"Baneling";"Zergling";65;0
"Unit";"Baneling";"Zergling";66;0
"Unit";"Zergling";"Larva";67;1
"Unit";"Zergling";"Larva";67;1
"Unit";"Zergling";"Larva";67;1
"Unit";"Zergling";"Larva";67;1
"Building";"Extractor";NA;71;0
"Building";"EvolutionChamber";NA;79;0
"Unit";"Zergling";"Larva";95;1
"Unit";"Zergling";"Larva";95;1
"Unit";"Zergling";"Larva";95;1
"Unit";"Zergling";"Larva";95;1
"Unit";"Zergling";"Larva";95;1
"Unit";"Zergling";"Larva";95;1
"Building";"Extractor";NA;95;0
"Unit";"Overlord";"Larva";95;0
"Unit";"Overlord";"Larva";95;0
"Unit";"Overlord";"Larva";95;0
"Building";"RoachWarren";NA;95;0
"Building";"Extractor";NA;101;0
"Building";"Extractor";NA;101;0
"Upgrade";"ZergMissileWeaponsLevel1";"EvolutionChamber";83;0
"Unit";"Overlord";"Larva";112;0
"Unit";"Overlord";"Larva";113;0
"Unit";"Overlord";"Larva";113;0
"Unit";"Overlord";"Larva";113;0
"Unit";"Queen";"Hatchery";105;2
"Unit";"Overlord";"Larva";113;0
"Unit";"Overlord";"Larva";113;0
"Unit";"Roach";"Larva";115;2
"Unit";"Roach";"Larva";115;2
"Unit";"Roach";"Larva";115;2
"Unit";"Roach";"Larva";115;2
"Unit";"Roach";"Larva";115;2
"Unit";"Roach";"Larva";115;2
"Unit";"Roach";"Larva";115;2
"Unit";"Roach";"Larva";115;2
"Unit";"Roach";"Larva";115;2
"Upgrade";"ZergGroundArmorsLevel1";"EvolutionChamber";101;0
"Building";"Extractor";NA;141;0
"Building";"Extractor";NA;141;0
"Building";"Hatchery";NA;113;0
"Upgrade";"GlialReconstitution";"RoachWarren";116;0
"Unit";"Overlord";"Larva";147;0
"Unit";"Overlord";"Larva";147;0
"Unit";"Overlord";"Larva";147;0
"Unit";"Overlord";"Larva";147;0
"Unit";"Overlord";"Larva";147;0
"Unit";"Roach";"Larva";151;2
"Unit";"Roach";"Larva";151;2
"Unit";"Roach";"Larva";151;2
"Unit";"Roach";"Larva";151;2
"Unit";"Roach";"Larva";151;2
"Unit";"Roach";"Larva";151;2
"Unit";"Roach";"Larva";151;2
"Unit";"Roach";"Larva";151;2
"Unit";"Roach";"Larva";151;2
"Unit";"Roach";"Larva";151;2
"Unit";"Roach";"Larva";151;2
"Unit";"Roach";"Larva";151;2
"Unit";"Roach";"Larva";151;2
"Unit";"Roach";"Larva";151;2
"Unit";"Roach";"Larva";151;2
"Unit";"Roach";"Larva";151;2
"Upgrade";"ZergMissileWeaponsLevel2";"EvolutionChamber";134;0
"Unit";"Overlord";"Larva";183;0
"Unit";"Overlord";"Larva";183;0
"Unit";"Overlord";"Larva";183;0
"Unit";"Overlord";"Larva";183;0
"Building";"Hatchery";NA;151;0
"Unit";"Baneling";"Zergling";183;0
"Unit";"Baneling";"Zergling";183;0
"Unit";"Baneling";"Zergling";183;0
"Unit";"Baneling";"Zergling";183;0
"Unit";"Baneling";"Zergling";183;0
"Unit";"Baneling";"Zergling";183;0
"Unit";"Baneling";"Zergling";183;0
"Unit";"Baneling";"Zergling";183;0
"Unit";"Baneling";"Zergling";183;0
"Unit";"Baneling";"Zergling";183;0
"Unit";"Baneling";"Zergling";183;0
"Building";"Hatchery";NA;151;0
"Upgrade";"ZergGroundArmorsLevel2";"EvolutionChamber";151;0
"Unit";"Roach";"Larva";183;2
"Unit";"Roach";"Larva";183;2
"Unit";"Roach";"Larva";183;2
"Unit";"Roach";"Larva";183;2
"Unit";"Roach";"Larva";183;2
"Unit";"Roach";"Larva";183;2
"Unit";"Roach";"Larva";183;2
"Unit";"Roach";"Larva";183;2
"Unit";"Roach";"Larva";183;2
"Unit";"Roach";"Larva";183;2
"Unit";"Roach";"Larva";203;2
"Unit";"Roach";"Larva";203;2
"Unit";"Roach";"Larva";203;2
"Building";"InfestationPit";NA;209;0
"Building";"Extractor";NA;209;0
"Building";"Extractor";NA;209;0
"Building";"Extractor";NA;279;0
"Building";"Extractor";NA;291;0
"Building";"Extractor";NA;291;0
"Building";"Extractor";NA;291;0
"Building";"Extractor";NA;291;0
"Building";"Extractor";NA;291;0
"Building";"Extractor";NA;291;0
"Building";"Hatchery";NA;209;0
"Building";"Extractor";NA;291;0
"Building";"Extractor";NA;291;0
"Building";"Extractor";NA;291;0
"Building";"Hatchery";NA;209;0
"Building";"Extractor";NA;291;0
"Building";"Extractor";NA;291;0
"Building";"Hatchery";NA;209;0
"Building";"Extractor";NA;291;0
"Building";"Hatchery";NA;209;0
"Building";"Extractor";NA;291;0
"Building";"Extractor";NA;291;0
"Building";"Extractor";NA;291;0
"Building";"Extractor";NA;292;0
"Building";"Extractor";NA;310;0
"Building";"Hatchery";NA;291;0
"Building";"Hatchery";NA;291;0
"Building";"Hatchery";NA;316;0
"Building";"Hatchery";NA;316;0
"Building";"Hatchery";NA;316;0
"Building";"CreepTumorQueen";NA;334;0
"Building";"CreepTumorQueen";NA;334;0
"Building";"CreepTumorQueen";NA;334;0
"Building";"CreepTumorQueen";NA;334;0
"Building";"CreepTumorQueen";NA;334;0
"Building";"CreepTumorQueen";NA;334;0
"Building";"CreepTumorQueen";NA;334;0
"Building";"CreepTumor";NA;334;0
"Building";"CreepTumor";NA;334;0
"Building";"CreepTumor";NA;334;0
"Building";"CreepTumorQueen";NA;334;0
"Building";"CreepTumor";NA;334;0
"Building";"CreepTumor";NA;334;0
"Building";"CreepTumor";NA;334;0
"Building";"CreepTumor";NA;334;0
"Building";"CreepTumor";NA;334;0
"Building";"CreepTumorQueen";NA;334;0
"Building";"CreepTumorQueen";NA;334;0
"Building";"CreepTumorQueen";NA;334;0
"Building";"CreepTumorQueen";NA;334;0
"Building";"CreepTumor";NA;334;0
"Building";"CreepTumor";NA;334;0
"Building";"CreepTumor";NA;334;0
"Building";"CreepTumor";NA;334;0
"Building";"CreepTumorQueen";NA;334;0
"Building";"CreepTumor";NA;334;0
"Building";"CreepTumor";NA;334;0
"Building";"CreepTumor";NA;334;0
"Building";"CreepTumor";NA;334;0
"Building";"CreepTumor";NA;334;0
"Building";"CreepTumor";NA;334;0
"Building";"CreepTumor";NA;334;0
"Building";"CreepTumor";NA;334;0
"Building";"CreepTumor";NA;334;0
"Building";"CreepTumorQueen";NA;334;0
"Building";"CreepTumor";NA;334;0
"Building";"CreepTumor";NA;334;0
"Building";"CreepTumor";NA;334;0
"Building";"CreepTumor";NA;334;0
"Building";"CreepTumor";NA;334;0
"Building";"CreepTumorQueen";NA;334;0
"Building";"CreepTumorQueen";NA;334;0
"Building";"CreepTumor";NA;334;0
"Building";"CreepTumor";NA;343;0
"Building";"CreepTumor";NA;346;0
"Building";"CreepTumor";NA;349;0
"Building";"CreepTumor";NA;354;0
"Building";"CreepTumor";NA;354;0
"Building";"CreepTumor";NA;354;0
"Building";"CreepTumorQueen";NA;354;0
"Building";"CreepTumorQueen";NA;354;0
"Building";"CreepTumor";NA;354;0
"Building";"CreepTumor";NA;354;0
"Building";"CreepTumorQueen";NA;354;0
"Building";"CreepTumorQueen";NA;354;0
"Building";"CreepTumor";NA;354;0
"Building";"CreepTumor";NA;354;0
"Building";"CreepTumor";NA;354;0
"Building";"CreepTumor";NA;354;0
"Building";"CreepTumor";NA;354;0
"Building";"CreepTumor";NA;354;0
"Building";"CreepTumor";NA;354;0
"Building";"CreepTumor";NA;354;0
"Building";"CreepTumor";NA;354;0
"Building";"CreepTumorQueen";NA;354;0
"Building";"CreepTumorQueen";NA;354;0
"Building";"CreepTumorQueen";NA;354;0
"Building";"CreepTumor";NA;354;0
"Building";"CreepTumor";NA;354;0
"Building";"CreepTumorQueen";NA;354;0
"Building";"CreepTumor";NA;354;0
"Building";"CreepTumor";NA;354;0
"Building";"CreepTumor";NA;354;0
"Building";"CreepTumor";NA;354;0
"Building";"CreepTumor";NA;354;0
"Building";"CreepTumor";NA;354;0
"Building";"CreepTumor";NA;354;0
"Building";"CreepTumor";NA;354;0
"Building";"CreepTumor";NA;354;0
"Building";"CreepTumor";NA;354;0
"Building";"CreepTumor";NA;354;0
"Building";"CreepTumor";NA;354;0
"Building";"CreepTumor";NA;354;0
"Building";"CreepTumor";NA;354;0
"Building";"CreepTumor";NA;354;0
"Building";"CreepTumor";NA;354;0
"Building";"CreepTumor";NA;354;0
"Building";"CreepTumor";NA;354;0
"Building";"CreepTumor";NA;354;0
"Building";"CreepTumor";NA;354;0
"Building";"CreepTumor";NA;354;0
"Building";"CreepTumor";NA;354;0
"Building";"CreepTumor";NA;354;0
"Building";"CreepTumor";NA;354;0
"Building";"CreepTumor";NA;354;0
"Building";"CreepTumor";NA;354;0
"Building";"CreepTumor";NA;354;0
"Building";"CreepTumorQueen";NA;354;0
"Building";"CreepTumor";NA;354;0
"Building";"CreepTumor";NA;354;0
"Building";"CreepTumor";NA;354;0
"Building";"CreepTumorQueen";NA;354;0
"Building";"CreepTumorQueen";NA;354;0
"Building";"CreepTumorQueen";NA;354;0
"Building";"CreepTumorQueen";NA;354;0
"Building";"CreepTumor";NA;354;0
"Building";"CreepTumor";NA;354;0
"Building";"CreepTumor";NA;354;0
"Building";"CreepTumor";NA;354;0
"Building";"CreepTumor";NA;354;0
"Building";"CreepTumor";NA;354;0
"Building";"CreepTumor";NA;354;0
"Building";"CreepTumor";NA;354;0
"Building";"CreepTumor";NA;354;0
"Building";"CreepTumor";NA;354;0
"Building";"CreepTumor";NA;354;0
"Building";"CreepTumor";NA;354;0
"Building";"CreepTumor";NA;354;0
"Building";"CreepTumor";NA;354;0
"Building";"CreepTumor";NA;354;0
"Building";"CreepTumorQueen";NA;354;0
"Building";"CreepTumor";NA;354;0
"Building";"CreepTumorQueen";NA;354;0
"Building";"CreepTumor";NA;354;0
"Building";"CreepTumorQueen";NA;354;0
"Building";"CreepTumor";NA;354;0
"Building";"CreepTumorQueen";NA;354;0
"Building";"CreepTumorQueen";NA;354;0
"Building";"CreepTumor";NA;354;0
"Building";"CreepTumorQueen";NA;354;0
"Building";"CreepTumor";NA;354;0
"Building";"CreepTumorQueen";NA;354;0
"Building";"CreepTumor";NA;354;0
"Building";"CreepTumor";NA;354;0
"Building";"CreepTumor";NA;354;0
"Building";"CreepTumor";NA;354;0
"Building";"CreepTumor";NA;354;0
"Building";"CreepTumor";NA;354;0
"Building";"CreepTumor";NA;354;0
"Building";"CreepTumor";NA;354;0
"Building";"CreepTumor";NA;354;0
"Building";"CreepTumor";NA;354;0
"Building";"CreepTumor";NA;354;0
"Building";"CreepTumor";NA;354;0
"Building";"CreepTumor";NA;354;0
"Building";"CreepTumor";NA;354;0
"Building";"CreepTumor";NA;354;0
"Building";"CreepTumor";NA;354;0
"Building";"CreepTumor";NA;354;0
"Building";"CreepTumor";NA;354;0
"Building";"CreepTumor";NA;354;0
"Building";"CreepTumor";NA;354;0
"Building";"CreepTumor";NA;354;0
"Building";"CreepTumor";NA;354;0
"Building";"CreepTumor";NA;354;0
"Building";"CreepTumor";NA;354;0
"Building";"CreepTumorQueen";NA;354;0
"Building";"CreepTumorQueen";NA;354;0
"Building";"CreepTumor";NA;354;0
"Building";"CreepTumor";NA;354;0
"Building";"CreepTumor";NA;354;0
"Building";"CreepTumor";NA;354;0
"Building";"CreepTumor";NA;354;0
"Building";"CreepTumor";NA;354;0
"Building";"CreepTumor";NA;354;0
"Building";"CreepTumorQueen";NA;354;0
"Building";"CreepTumor";NA;354;0
"Building";"CreepTumorQueen";NA;354;0
"Building";"CreepTumor";NA;354;0
"Building";"CreepTumor";NA;354;0
"Building";"CreepTumor";NA;354;0
"Building";"CreepTumor";NA;354;0
"Building";"CreepTumor";NA;354;0
"Building";"CreepTumor";NA;354;0
"Building";"CreepTumorQueen";NA;354;0
"Building";"CreepTumor";NA;354;0
"Building";"CreepTumor";NA;354;0
"Building";"CreepTumor";NA;354;0
"Building";"CreepTumor";NA;354;0
"Building";"CreepTumor";NA;354;0
"Building";"CreepTumorQueen";NA;354;0
"Building";"CreepTumor";NA;354;0
"Building";"CreepTumor";NA;354;0
"Building";"CreepTumorQueen";NA;354;0
"Building";"CreepTumor";NA;354;0
"Building";"CreepTumor";NA;354;0
"Building";"CreepTumor";NA;354;0
"Building";"CreepTumor";NA;354;0
"Building";"HydraliskDen";NA;360;0
"Building";"SporeCrawler";NA;360;0
"Building";"NydusNetwork";NA;360;0
"Building";"UltraliskCavern";NA;360;0
"Building";"SpineCrawler";NA;360;0
"Building";"Spire";NA;360;0
"Building";"Spire";NA;360;0
"Upgrade";"EvolveGroovedSpines";"HydraliskDen";360;0
"Upgrade";"Burrow";"Hatchery";360;0
"Upgrade";"ChitinousPlating";"UltraliskCavern";360;0
"Upgrade";"TunnelingClaws";"RoachWarren";360;0
"Building";"LurkerDenMP";NA;360;0
"Building";"SporeCrawler";NA;360;0
"Building";"SporeCrawler";NA;360;0
"Building";"SporeCrawler";NA;360;0
"Building";"SporeCrawler";NA;360;0
"Building";"SporeCrawler";NA;360;0
"Building";"SporeCrawler";NA;360;0
"Building";"SporeCrawler";NA;360;0
"Building";"SporeCrawler";NA;360;0
"Building";"SporeCrawler";NA;360;0
"Building";"SporeCrawler";NA;360;0
"Building";"SporeCrawler";NA;360;0
"Building";"SporeCrawler";NA;360;0
"Building";"SporeCrawler";NA;360;0
"Upgrade";"EvolveMuscularAugments";"HydraliskDen";360;0
"Building";"SporeCrawler";NA;360;0
"Building";"SporeCrawler";NA;360;0
"Building";"SporeCrawler";NA;360;0
"Upgrade";"ZergMissileWeaponsLevel3";"EvolutionChamber";360;0
"Building";"SporeCrawler";NA;360;0
"Building";"SporeCrawler";NA;360;0
"Upgrade";"ZergGroundArmorsLevel3";"EvolutionChamber";360;0
"Building";"SporeCrawler";NA;360;0
"Building";"SporeCrawler";NA;360;0
"Building";"SporeCrawler";NA;360;0
"Building";"SporeCrawler";NA;360;0
"Building";"SporeCrawler";NA;360;0
"Building";"SporeCrawler";NA;360;0
"Upgrade";"NeuralParasite";"InfestationPit";360;0
"Building";"SporeCrawler";NA;360;0
"Building";"SporeCrawler";NA;360;0
"Building";"SporeCrawler";NA;360;0
"Building";"SporeCrawler";NA;360;0
"Building";"SporeCrawler";NA;360;0
"Building";"SporeCrawler";NA;360;0
"Building";"SporeCrawler";NA;360;0
"Building";"SporeCrawler";NA;360;0
"Building";"SporeCrawler";NA;360;0
"Building";"SporeCrawler";NA;360;0
"Building";"SporeCrawler";NA;360;0
"Building";"SporeCrawler";NA;360;0
"Building";"SporeCrawler";NA;360;0
"Building";"SporeCrawler";NA;360;0
"Building";"SporeCrawler";NA;360;0
"Building";"SporeCrawler";NA;360;0
"Building";"SporeCrawler";NA;360;0
"Building";"SporeCrawler";NA;360;0
"Building";"SporeCrawler";NA;360;0
"Building";"SporeCrawler";NA;360;0
"Building";"SporeCrawler";NA;360;0
"Building";"SporeCrawler";NA;360;0
"Building";"SporeCrawler";NA;360;0
"Building";"SporeCrawler";NA;360;0
"Building";"SporeCrawler";NA;360;0
"Building";"SporeCrawler";NA;360;0
"Building";"SporeCrawler";NA;360;0
"Building";"SporeCrawler";NA;360;0
"Building";"SporeCrawler";NA;360;0
"Building";"SporeCrawler";NA;360;0
"Building";"SporeCrawler";NA;360;0
"Building";"SporeCrawler";NA;360;0
"Building";"SporeCrawler";NA;360;0
"Building";"SporeCrawler";NA;360;0
"Building";"SporeCrawler";NA;360;0
"Building";"SporeCrawler";NA;360;0
"Building";"SporeCrawler";NA;360;0
"Building";"SporeCrawler";NA;360;0
"Building";"SporeCrawler";NA;360;0
"Building";"SporeCrawler";NA;360;0
"Building";"SporeCrawler";NA;360;0
"Building";"SporeCrawler";NA;360;0
"Building";"SporeCrawler";NA;360;0
"Building";"SporeCrawler";NA;360;0
"Building";"SporeCrawler";NA;360;0
"Building";"SporeCrawler";NA;360;0
"Building";"SporeCrawler";NA;360;0
"Building";"SporeCrawler";NA;360;0
"Building";"SporeCrawler";NA;360;0
"Building";"SporeCrawler";NA;360;0
"Building";"SporeCrawler";NA;360;0
"Building";"SporeCrawler";NA;360;0
"Building";"SporeCrawler";NA;360;0
"Building";"SporeCrawler";NA;360;0
"Building";"SporeCrawler";NA;360;0
"Building";"SporeCrawler";NA;360;0
"Building";"SporeCrawler";NA;360;0
"Building";"SporeCrawler";NA;360;0
"Building";"SporeCrawler";NA;360;0
"Building";"SporeCrawler";NA;360;0
"Building";"SporeCrawler";NA;360;0
"Building";"SporeCrawler";NA;360;0
"Building";"SporeCrawler";NA;360;0
"Building";"SporeCrawler";NA;360;0
"Building";"SporeCrawler";NA;360;0
"Building";"SporeCrawler";NA;360;0
"Building";"SporeCrawler";NA;360;0
"Building";"SporeCrawler";NA;360;0
"Building";"SporeCrawler";NA;360;0
"Building";"SporeCrawler";NA;360;0
"Building";"SporeCrawler";NA;360;0
"Building";"SporeCrawler";NA;360;0
"Building";"SporeCrawler";NA;360;0
"Building";"SporeCrawler";NA;360;0
"Building";"SporeCrawler";NA;360;0
"Building";"SporeCrawler";NA;360;0
"Building";"SporeCrawler";NA;360;0
"Building";"SporeCrawler";NA;360;0
"Building";"SporeCrawler";NA;360;0
"Upgrade";"ZergMeleeWeaponsLevel1";"EvolutionChamber";360;0
"Building";"SporeCrawler";NA;360;0
"Building";"SporeCrawler";NA;360;0
"Building";"SporeCrawler";NA;360;0
"Building";"SporeCrawler";NA;360;0
"Building";"SporeCrawler";NA;360;0
"Building";"SporeCrawler";NA;360;0
"Building";"SporeCrawler";NA;360;0
"Building";"SporeCrawler";NA;360;0
"Building";"SporeCrawler";NA;360;0
"Building";"SporeCrawler";NA;360;0
"Building";"SporeCrawler";NA;360;0
"Building";"SporeCrawler";NA;360;0
"Building";"SporeCrawler";NA;360;0
"Building";"SporeCrawler";NA;360;0
"Building";"SporeCrawler";NA;360;0
"Building";"SporeCrawler";NA;360;0
"Building";"SporeCrawler";NA;360;0
"Building";"SporeCrawler";NA;360;0
"Building";"SporeCrawler";NA;360;0
"Building";"SporeCrawler";NA;360;0
"Building";"SporeCrawler";NA;360;0
"Building";"SporeCrawler";NA;360;0
"Building";"SporeCrawler";NA;360;0
"Building";"SporeCrawler";NA;360;0
"Building";"SporeCrawler";NA;360;0
"Building";"SporeCrawler";NA;360;0
"Building";"SporeCrawler";NA;360;0
"Building";"SporeCrawler";NA;360;0
"Building";"SporeCrawler";NA;360;0
"Building";"SporeCrawler";NA;360;0
"Building";"SporeCrawler";NA;360;0
"Building";"SporeCrawler";NA;360;0
"Building";"SporeCrawler";NA;360;0
"Building";"SporeCrawler";NA;360;0
"Building";"SporeCrawler";NA;360;0
"Building";"SporeCrawler";NA;360;0
"Building";"SporeCrawler";NA;360;0
"Building";"SporeCrawler";NA;360;0
"Building";"SporeCrawler";NA;360;0
"Building";"SporeCrawler";NA;360;0
"Building";"SporeCrawler";NA;360;0
"Building";"SporeCrawler";NA;360;0
"Building";"SporeCrawler";NA;360;0
"Building";"SporeCrawler";NA;360;0
"Building";"SporeCrawler";NA;360;0
"Building";"SporeCrawler";NA;360;0
"Building";"SporeCrawler";NA;360;0
"Building";"SporeCrawler";NA;360;0
"Building";"SporeCrawler";NA;360;0
"Building";"SporeCrawler";NA;360;0
"Building";"SporeCrawler";NA;360;0
"Building";"SporeCrawler";NA;360;0
"Building";"SporeCrawler";NA;360;0
"Building";"SporeCrawler";NA;360;0
"Building";"SporeCrawler";NA;360;0
"Building";"SporeCrawler";NA;360;0
"Building";"SporeCrawler";NA;360;0
"Building";"SporeCrawler";NA;360;0
"Building";"SporeCrawler";NA;360;0
"Building";"SporeCrawler";NA;360;0
"Building";"SporeCrawler";NA;360;0
"Building";"SporeCrawler";NA;360;0
"Building";"SporeCrawler";NA;360;0
"Building";"SporeCrawler";NA;360;0
"Building";"SporeCrawler";NA;360;0
"Building";"SporeCrawler";NA;360;0
"Building";"SporeCrawler";NA;360;0
"Building";"SporeCrawler";NA;360;0
"Building";"SporeCrawler";NA;360;0
"Building";"SporeCrawler";NA;360;0
"Building";"SporeCrawler";NA;360;0
"Building";"SporeCrawler";NA;360;0
"Building";"SporeCrawler";NA;360;0
"Building";"SporeCrawler";NA;360;0
"Building";"SporeCrawler";NA;360;0
"Building";"SporeCrawler";NA;360;0
"Building";"SporeCrawler";NA;360;0
"Building";"SporeCrawler";NA;360;0
"Building";"SporeCrawler";NA;360;0
"Building";"SporeCrawler";NA;360;0
"Building";"SporeCrawler";NA;360;0
"Building";"SporeCrawler";NA;360;0
"Building";"SporeCrawler";NA;360;0
"Building";"SporeCrawler";NA;360;0
"Building";"SporeCrawler";NA;360;0
"Building";"SporeCrawler";NA;360;0
"Building";"SporeCrawler";NA;360;0
"Building";"SporeCrawler";NA;360;0
"Building";"SporeCrawler";NA;360;0
"Unit";"Corruptor";"Larva";360;2
"Unit";"Corruptor";"Larva";362;2
"Building";"CreepTumor";NA;362;0
"Building";"CreepTumor";NA;364;0
"Building";"CreepTumor";NA;364;0
"Building";"CreepTumor";NA;364;0
"Building";"CreepTumor";NA;364;0
"Upgrade";"ZergMeleeWeaponsLevel2";"EvolutionChamber";364;0
"Building";"CreepTumor";NA;364;0
"Building";"CreepTumor";NA;364;0
"Building";"CreepTumor";NA;364;0
"Building";"CreepTumor";NA;364;0
"Building";"CreepTumor";NA;364;0
"Building";"CreepTumor";NA;364;0
"Building";"CreepTumor";NA;364;0
"Building";"CreepTumor";NA;364;0
"Building";"CreepTumor";NA;364;0
"Upgrade";"ZergMeleeWeaponsLevel3";"EvolutionChamber";364;0
"Building";"CreepTumor";NA;364;0
"Building";"CreepTumor";NA;364;0
"Building";"CreepTumor";NA;364;0
"Building";"CreepTumor";NA;364;0
"Building";"CreepTumor";NA;364;0
"Building";"CreepTumor";NA;364;0
"Building";"CreepTumor";NA;364;0
"Building";"CreepTumor";NA;364;0
"Building";"CreepTumor";NA;364;0
"Building";"CreepTumor";NA;364;0
"Building";"CreepTumor";NA;364;0
"Building";"CreepTumor";NA;364;0
