"type";"unit_name";"on_building";"total_supply";"supply"
"Unit";"Overlord";"Larva";12;0
"Building";"Extractor";NA;17;0
"Building";"SpawningPool";NA;19;0
"Building";"Hatchery";NA;17;0
"Unit";"Zergling";"Larva";24;1
"Unit";"Zergling";"Larva";24;1
"Unit";"Zergling";"Larva";24;1
"Unit";"Zergling";"Larva";24;1
"Unit";"Queen";"Hatchery";24;2
"Unit";"Queen";"Hatchery";24;2
"Unit";"Overlord";"Larva";28;0
"Building";"BanelingNest";NA;28;0
"Building";"Hatchery";NA;28;0
"Unit";"Overlord";"Larva";39;0
"Unit";"Overlord";"Larva";39;0
"Unit";"Queen";"Hatchery";45;2
"Building";"Extractor";NA;48;0
"Building";"Extractor";NA;48;0
"Building";"Extractor";NA;64;0
"Unit";"Overlord";"Larva";64;0
"Unit";"Overlord";"Larva";64;0
"Building";"Extractor";NA;70;0
"Building";"Extractor";NA;70;0
"Unit";"Overlord";"Larva";81;0
"Building";"SpineCrawler";NA;73;0
"Unit";"Overlord";"Larva";81;0
"Unit";"Overlord";"Larva";81;0
"Building";"SpineCrawler";NA;74;0
"Building";"SpineCrawler";NA;77;0
"Building";"Spire";NA;64;0
"Unit";"Mutalisk";"Larva";81;2
"Unit";"Mutalisk";"Larva";81;2
"Unit";"Mutalisk";"Larva";81;2
"Unit";"Mutalisk";"Larva";81;2
"Unit";"Mutalisk";"Larva";81;2
"Unit";"Mutalisk";"Larva";81;2
"Unit";"Mutalisk";"Larva";81;2
"Unit";"Mutalisk";"Larva";81;2
"Unit";"Mutalisk";"Larva";81;2
"Unit";"Mutalisk";"Larva";81;2
"Unit";"Mutalisk";"Larva";81;2
"Unit";"Overlord";"Larva";110;0
"Unit";"Overlord";"Larva";110;0
"Unit";"Overlord";"Larva";110;0
"Unit";"Mutalisk";"Larva";110;2
"Unit";"Mutalisk";"Larva";110;2
"Building";"SpineCrawler";NA;110;0
"Building";"SpineCrawler";NA;110;0
"Building";"SpineCrawler";NA;110;0
"Building";"HydraliskDen";NA;114;0
"Unit";"Overlord";"Larva";114;0
"Unit";"Mutalisk";"Larva";114;2
"Unit";"Mutalisk";"Larva";114;2
"Unit";"Mutalisk";"Larva";114;2
"Unit";"Mutalisk";"Larva";114;2
"Unit";"Mutalisk";"Larva";118;2
"Unit";"Mutalisk";"Larva";118;2
"Unit";"Mutalisk";"Larva";126;2
"Unit";"Mutalisk";"Larva";126;2
"Unit";"Mutalisk";"Larva";126;2
"Building";"RoachWarren";NA;126;0
"Unit";"Mutalisk";"Larva";147;2
"Unit";"Mutalisk";"Larva";147;2
"Unit";"Mutalisk";"Larva";147;2
"Unit";"Mutalisk";"Larva";147;2
"Building";"Hatchery";NA;120;0
"Unit";"Overlord";"Larva";147;0
"Unit";"Overlord";"Larva";147;0
"Unit";"Overlord";"Larva";147;0
"Unit";"Overlord";"Larva";147;0
"Unit";"Overlord";"Larva";147;0
"Building";"SpineCrawler";NA;147;0
"Building";"SpineCrawler";NA;147;0
"Building";"SpineCrawler";NA;147;0
"Building";"SpineCrawler";NA;147;0
"Unit";"Roach";"Larva";156;2
"Unit";"Roach";"Larva";156;2
"Unit";"Roach";"Larva";156;2
"Unit";"Roach";"Larva";156;2
"Unit";"Queen";"Hatchery";155;2
"Building";"Extractor";NA;162;0
"Building";"Extractor";NA;162;0
"Building";"EvolutionChamber";NA;162;0
"Building";"EvolutionChamber";NA;162;0
"Unit";"Hydralisk";"Larva";162;2
"Unit";"Hydralisk";"Larva";162;2
"Unit";"Hydralisk";"Larva";162;2
"Unit";"Hydralisk";"Larva";162;2
"Unit";"Hydralisk";"Larva";162;2
"Unit";"Hydralisk";"Larva";162;2
"Unit";"Hydralisk";"Larva";162;2
"Unit";"Hydralisk";"Larva";162;2
"Unit";"Hydralisk";"Larva";162;2
"Unit";"Hydralisk";"Larva";162;2
"Unit";"Hydralisk";"Larva";162;2
"Unit";"Roach";"Larva";170;2
"Unit";"Roach";"Larva";170;2
"Unit";"Roach";"Larva";170;2
"Unit";"Roach";"Larva";170;2
"Unit";"Roach";"Larva";202;2
"Unit";"Roach";"Larva";202;2
"Unit";"Roach";"Larva";202;2
"Unit";"Roach";"Larva";202;2
"Unit";"Roach";"Larva";202;2
"Unit";"Roach";"Larva";202;2
"Unit";"Roach";"Larva";202;2
"Unit";"Roach";"Larva";202;2
"Unit";"Roach";"Larva";202;2
"Unit";"Overlord";"Larva";202;0
"Unit";"Overlord";"Larva";202;0
"Unit";"Overlord";"Larva";202;0
"Upgrade";"GlialReconstitution";"RoachWarren";162;0
"Unit";"Overlord";"Larva";202;0
"Unit";"Overlord";"Larva";202;0
"Unit";"Overlord";"Larva";202;0
"Unit";"Overlord";"Larva";202;0
"Unit";"Overlord";"Larva";202;0
"Unit";"Overlord";"Larva";202;0
"Unit";"Overlord";"Larva";202;0
"Unit";"Roach";"Larva";220;2
"Unit";"Roach";"Larva";220;2
"Unit";"Roach";"Larva";220;2
"Building";"LurkerDenMP";NA;162;0
"Unit";"Roach";"Larva";220;2
"Unit";"Roach";"Larva";220;2
"Unit";"Roach";"Larva";220;2
"Unit";"Roach";"Larva";220;2
"Unit";"Roach";"Larva";220;2
"Unit";"Roach";"Larva";220;2
"Unit";"Roach";"Larva";220;2
"Unit";"Roach";"Larva";220;2
"Unit";"Roach";"Larva";220;2
"Unit";"Roach";"Larva";226;2
"Unit";"Roach";"Larva";226;2
"Unit";"Roach";"Larva";226;2
"Unit";"Roach";"Larva";226;2
"Unit";"Roach";"Larva";226;2
"Unit";"Roach";"Larva";226;2
"Unit";"Roach";"Larva";226;2
"Unit";"Roach";"Larva";226;2
"Unit";"Roach";"Larva";244;2
"Unit";"Roach";"Larva";244;2
"Unit";"Roach";"Larva";248;2
"Unit";"Roach";"Larva";260;2
"Unit";"Overlord";"Larva";264;0
"Unit";"Overlord";"Larva";264;0
"Unit";"Overlord";"Larva";264;0
"Unit";"Overlord";"Larva";264;0
"Unit";"Roach";"Larva";268;2
"Unit";"Roach";"Larva";268;2
"Unit";"Roach";"Larva";268;2
"Unit";"Roach";"Larva";268;2
"Unit";"Roach";"Larva";268;2
"Unit";"Roach";"Larva";268;2
"Unit";"Roach";"Larva";268;2
"Unit";"Roach";"Larva";268;2
"Unit";"Roach";"Larva";268;2
"Upgrade";"EvolveGroovedSpines";"HydraliskDen";264;0
"Unit";"Overlord";"Larva";268;0
"Unit";"Overlord";"Larva";268;0
"Unit";"Mutalisk";"Larva";286;2
"Unit";"Mutalisk";"Larva";286;2
"Unit";"Mutalisk";"Larva";286;2
"Unit";"Mutalisk";"Larva";286;2
"Unit";"Mutalisk";"Larva";286;2
"Upgrade";"ZergMissileWeaponsLevel1";"EvolutionChamber";266;0
"Upgrade";"ZergGroundArmorsLevel1";"EvolutionChamber";266;0
