"type";"unit_name";"on_building";"total_supply";"supply"
"Unit";"Overlord";"Larva";12;0
"Building";"Extractor";NA;18;0
"Building";"SpawningPool";NA;19;0
"Unit";"Overlord";"Larva";22;0
"Building";"Hatchery";NA;17;0
"Unit";"Zergling";"Larva";22;1
"Unit";"Zergling";"Larva";22;1
"Unit";"Zergling";"Larva";22;1
"Unit";"Zergling";"Larva";22;1
"Unit";"Queen";"Hatchery";22;2
"Unit";"Queen";"Hatchery";22;2
"Building";"BanelingNest";NA;32;0
"Unit";"Overlord";"Larva";40;0
"Building";"Hatchery";NA;30;0
"Unit";"Baneling";"Zergling";43;0
"Unit";"Baneling";"Zergling";43;0
"Unit";"Overlord";"Larva";43;0
"Unit";"Overlord";"Larva";43;0
"Unit";"Overlord";"Larva";43;0
"Unit";"Zergling";"Larva";49;1
"Unit";"Zergling";"Larva";49;1
"Unit";"Zergling";"Larva";49;1
"Unit";"Zergling";"Larva";49;1
"Unit";"Zergling";"Larva";49;1
"Unit";"Zergling";"Larva";49;1
"Unit";"Zergling";"Larva";49;1
"Unit";"Zergling";"Larva";49;1
"Unit";"Queen";"Hatchery";49;2
"Building";"Extractor";NA;62;0
"Building";"Extractor";NA;62;0
"Unit";"Baneling";"Zergling";75;0
"Unit";"Baneling";"Zergling";75;0
"Unit";"Baneling";"Zergling";75;0
"Building";"EvolutionChamber";NA;75;0
"Building";"Extractor";NA;75;0
"Building";"Extractor";NA;75;0
"Building";"RoachWarren";NA;70;0
"Unit";"Overlord";"Larva";92;0
"Unit";"Overlord";"Larva";92;0
"Unit";"Overlord";"Larva";92;0
"Unit";"Overlord";"Larva";92;0
"Unit";"Overlord";"Larva";92;0
"Unit";"Roach";"Larva";92;2
"Unit";"Roach";"Larva";92;2
"Unit";"Roach";"Larva";92;2
"Unit";"Roach";"Larva";92;2
"Unit";"Roach";"Larva";92;2
"Unit";"Roach";"Larva";92;2
"Unit";"Roach";"Larva";92;2
"Unit";"Roach";"Larva";92;2
"Unit";"Roach";"Larva";92;2
"Unit";"Roach";"Larva";92;2
"Unit";"Roach";"Larva";92;2
"Unit";"Roach";"Larva";92;2
"Unit";"Roach";"Larva";92;2
"Unit";"Overlord";"Larva";92;0
"Unit";"Roach";"Larva";92;2
"Unit";"Roach";"Larva";92;2
"Unit";"Roach";"Larva";92;2
"Unit";"Roach";"Larva";110;2
"Unit";"Roach";"Larva";110;2
"Unit";"Roach";"Larva";110;2
"Unit";"Roach";"Larva";110;2
"Unit";"Roach";"Larva";110;2
"Unit";"Overlord";"Larva";110;0
"Unit";"Roach";"Larva";118;2
"Unit";"Roach";"Larva";118;2
"Unit";"Roach";"Larva";118;2
"Unit";"Roach";"Larva";118;2
"Unit";"Roach";"Larva";118;2
"Upgrade";"GlialReconstitution";"RoachWarren";92;0
"Unit";"Roach";"Larva";134;2
"Unit";"Roach";"Larva";134;2
"Unit";"Roach";"Larva";134;2
"Unit";"Roach";"Larva";134;2
"Unit";"Overlord";"Larva";134;0
"Unit";"Overlord";"Larva";134;0
"Unit";"Overlord";"Larva";134;0
"Unit";"Overlord";"Larva";134;0
"Building";"Hatchery";NA;92;0
"Upgrade";"ZergMissileWeaponsLevel1";"EvolutionChamber";92;0
"Unit";"Roach";"Larva";152;2
"Unit";"Roach";"Larva";152;2
"Unit";"Roach";"Larva";152;2
"Unit";"Roach";"Larva";152;2
"Unit";"Roach";"Larva";152;2
"Unit";"Roach";"Larva";152;2
"Unit";"Roach";"Larva";152;2
"Unit";"Roach";"Larva";152;2
"Unit";"Roach";"Larva";152;2
"Unit";"Roach";"Larva";152;2
"Unit";"Roach";"Larva";152;2
"Unit";"Roach";"Larva";152;2
"Unit";"Roach";"Larva";152;2
"Unit";"Roach";"Larva";152;2
"Unit";"Roach";"Larva";152;2
"Unit";"Roach";"Larva";166;2
"Unit";"Roach";"Larva";166;2
"Unit";"Roach";"Larva";166;2
"Unit";"Roach";"Larva";166;2
"Unit";"Roach";"Larva";190;2
"Unit";"Roach";"Larva";190;2
"Unit";"Roach";"Larva";190;2
"Unit";"Overlord";"Larva";190;0
"Unit";"Overlord";"Larva";190;0
"Unit";"Overlord";"Larva";190;0
"Upgrade";"Burrow";"Hatchery";152;0
"Upgrade";"TunnelingClaws";"RoachWarren";156;0
"Unit";"Roach";"Larva";190;2
"Unit";"Roach";"Larva";190;2
"Unit";"Roach";"Larva";190;2
"Unit";"Overlord";"Larva";196;0
"Unit";"Overlord";"Larva";196;0
"Unit";"Roach";"Larva";196;2
"Unit";"Roach";"Larva";196;2
"Unit";"Roach";"Larva";196;2
"Unit";"Roach";"Larva";196;2
"Unit";"Roach";"Larva";196;2
"Unit";"Roach";"Larva";196;2
"Unit";"Roach";"Larva";196;2
"Unit";"Roach";"Larva";196;2
"Unit";"Roach";"Larva";196;2
"Unit";"Roach";"Larva";196;2
"Unit";"Roach";"Larva";196;2
"Unit";"Roach";"Larva";196;2
"Building";"Extractor";NA;196;0
"Unit";"Roach";"Larva";196;2
"Unit";"Roach";"Larva";196;2
"Unit";"Roach";"Larva";196;2
"Unit";"Roach";"Larva";196;2
"Unit";"Roach";"Larva";212;2
"Unit";"Roach";"Larva";226;2
"Unit";"Roach";"Larva";226;2
"Unit";"Roach";"Larva";226;2
"Unit";"Roach";"Larva";226;2
"Unit";"Roach";"Larva";234;2
"Unit";"Roach";"Larva";234;2
"Unit";"Roach";"Larva";234;2
"Unit";"Roach";"Larva";234;2
"Unit";"Roach";"Larva";234;2
"Unit";"Roach";"Larva";234;2
"Unit";"Roach";"Larva";234;2
"Unit";"Roach";"Larva";234;2
"Unit";"Roach";"Larva";234;2
"Unit";"Roach";"Larva";234;2
"Unit";"Roach";"Larva";234;2
"Unit";"Roach";"Larva";234;2
"Unit";"Roach";"Larva";234;2
"Upgrade";"ZergMissileWeaponsLevel2";"EvolutionChamber";188;0
"Unit";"Roach";"Larva";262;2
"Unit";"Roach";"Larva";262;2
"Unit";"Roach";"Larva";262;2
"Unit";"Roach";"Larva";262;2
"Building";"Extractor";NA;278;0
"Unit";"Overlord";"Larva";283;0
"Unit";"Overlord";"Larva";283;0
"Unit";"Overlord";"Larva";283;0
"Unit";"Overlord";"Larva";283;0
"Unit";"Overlord";"Larva";283;0
"Unit";"Overlord";"Larva";283;0
"Unit";"Overlord";"Larva";283;0
"Unit";"Roach";"Larva";283;2
"Unit";"Roach";"Larva";283;2
"Unit";"Roach";"Larva";283;2
"Unit";"Roach";"Larva";283;2
"Unit";"Roach";"Larva";283;2
"Unit";"Roach";"Larva";283;2
"Unit";"Roach";"Larva";283;2
"Unit";"Roach";"Larva";283;2
"Unit";"Roach";"Larva";283;2
"Unit";"Roach";"Larva";283;2
"Unit";"Roach";"Larva";283;2
"Unit";"Roach";"Larva";283;2
"Unit";"Roach";"Larva";283;2
"Unit";"Roach";"Larva";283;2
"Unit";"Roach";"Larva";283;2
"Unit";"Roach";"Larva";283;2
"Unit";"Roach";"Larva";283;2
"Unit";"Roach";"Larva";283;2
"Unit";"Roach";"Larva";293;2
"Unit";"Roach";"Larva";293;2
"Unit";"Roach";"Larva";293;2
"Unit";"Roach";"Larva";293;2
"Unit";"Roach";"Larva";293;2
"Unit";"Roach";"Larva";293;2
"Unit";"Roach";"Larva";293;2
"Unit";"Roach";"Larva";293;2
"Unit";"Roach";"Larva";327;2
"Unit";"Roach";"Larva";327;2
"Unit";"Roach";"Larva";327;2
"Unit";"Roach";"Larva";327;2
"Unit";"Roach";"Larva";327;2
"Unit";"Roach";"Larva";327;2
"Unit";"Roach";"Larva";335;2
"Unit";"Roach";"Larva";335;2
"Unit";"Roach";"Larva";335;2
"Unit";"Roach";"Larva";335;2
"Unit";"Roach";"Larva";335;2
"Unit";"Roach";"Larva";335;2
"Unit";"Roach";"Larva";335;2
"Unit";"Roach";"Larva";335;2
"Unit";"Roach";"Larva";335;2
"Unit";"Roach";"Larva";335;2
"Upgrade";"ZergGroundArmorsLevel1";"EvolutionChamber";283;0
"Unit";"Roach";"Larva";347;2
"Unit";"Roach";"Larva";347;2
"Unit";"Roach";"Larva";347;2
"Unit";"Roach";"Larva";347;2
"Unit";"Roach";"Larva";375;2
"Unit";"Roach";"Larva";375;2
"Unit";"Roach";"Larva";375;2
"Unit";"Roach";"Larva";375;2
"Unit";"Roach";"Larva";375;2
"Unit";"Roach";"Larva";375;2
"Unit";"Roach";"Larva";375;2
"Unit";"Roach";"Larva";375;2
"Unit";"Roach";"Larva";375;2
"Unit";"Roach";"Larva";375;2
"Unit";"Roach";"Larva";375;2
"Unit";"Roach";"Larva";375;2
"Unit";"Roach";"Larva";375;2
"Unit";"Roach";"Larva";375;2
"Unit";"Roach";"Larva";375;2
"Unit";"Roach";"Larva";375;2
"Unit";"Roach";"Larva";375;2
"Unit";"Roach";"Larva";375;2
"Unit";"Roach";"Larva";375;2
"Unit";"Roach";"Larva";375;2
"Unit";"Roach";"Larva";375;2
"Unit";"Roach";"Larva";375;2
