"type";"unit_name";"on_building";"total_supply";"supply"
"Unit";"Overlord";"Larva";14;0
"Building";"Hatchery";NA;14;0
"Building";"SpawningPool";NA;15;0
"Unit";"Zergling";"Larva";20;1
"Unit";"Zergling";"Larva";20;1
"Unit";"Overlord";"Larva";20;0
"Unit";"Queen";"Hatchery";20;2
"Unit";"Queen";"Hatchery";20;2
"Unit";"Overlord";"Larva";32;0
"Unit";"Queen";"Hatchery";25;2
"Unit";"Overlord";"Larva";32;0
"Unit";"Queen";"Hatchery";32;2
"Building";"CreepTumorQueen";NA;39;0
"Building";"CreepTumorQueen";NA;47;0
"Building";"Extractor";NA;47;0
"Building";"Extractor";NA;47;0
"Building";"EvolutionChamber";NA;51;0
"Building";"EvolutionChamber";NA;56;0
"Unit";"Overlord";"Larva";56;0
"Unit";"Overlord";"Larva";56;0
"Building";"RoachWarren";NA;51;0
"Unit";"Queen";"Hatchery";56;2
"Building";"Hatchery";NA;39;0
"Building";"Extractor";NA;59;0
"Building";"CreepTumor";NA;64;0
"Building";"Extractor";NA;59;0
"Building";"CreepTumorQueen";NA;64;0
"Building";"SpineCrawler";NA;56;0
"Building";"SpineCrawler";NA;56;0
"Building";"SpineCrawler";NA;56;0
"Building";"Extractor";NA;75;0
"Building";"Extractor";NA;78;0
"Unit";"Overlord";"Larva";81;0
"Unit";"Overlord";"Larva";81;0
"Building";"SpineCrawler";NA;81;0
"Building";"SpineCrawler";NA;81;0
"Building";"SpineCrawler";NA;81;0
"Unit";"Overlord";"Larva";92;0
"Unit";"Overlord";"Larva";92;0
"Building";"Spire";NA;81;0
"Building";"SpineCrawler";NA;92;0
"Building";"SpineCrawler";NA;92;0
"Building";"CreepTumor";NA;101;0
"Building";"SpineCrawler";NA;97;0
"Building";"SpineCrawler";NA;100;0
"Unit";"Mutalisk";"Larva";101;2
"Unit";"Mutalisk";"Larva";101;2
"Unit";"Mutalisk";"Larva";101;2
"Unit";"Mutalisk";"Larva";101;2
"Unit";"Mutalisk";"Larva";101;2
"Unit";"Mutalisk";"Larva";101;2
"Unit";"Mutalisk";"Larva";101;2
"Unit";"Mutalisk";"Larva";101;2
"Unit";"Mutalisk";"Larva";101;2
"Unit";"Mutalisk";"Larva";101;2
"Unit";"Mutalisk";"Larva";101;2
"Building";"CreepTumor";NA;101;0
"Unit";"Roach";"Larva";124;2
"Unit";"Roach";"Larva";124;2
"Unit";"Roach";"Larva";124;2
"Unit";"Overlord";"Larva";124;0
"Unit";"Overlord";"Larva";124;0
"Unit";"Overlord";"Larva";124;0
"Unit";"Overlord";"Larva";124;0
"Unit";"Overlord";"Larva";124;0
"Unit";"Overlord";"Larva";124;0
"Unit";"Overlord";"Larva";124;0
"Upgrade";"GlialReconstitution";"RoachWarren";123;0
"Unit";"Roach";"Larva";130;2
"Unit";"Roach";"Larva";130;2
"Unit";"Roach";"Larva";130;2
"Unit";"Roach";"Larva";130;2
"Unit";"Roach";"Larva";130;2
"Unit";"Roach";"Larva";130;2
"Unit";"Roach";"Larva";130;2
"Unit";"Roach";"Larva";130;2
"Unit";"Roach";"Larva";130;2
"Unit";"Roach";"Larva";130;2
"Unit";"Roach";"Larva";130;2
"Unit";"Roach";"Larva";130;2
"Unit";"Roach";"Larva";130;2
"Unit";"Roach";"Larva";130;2
"Building";"Hatchery";NA;123;0
"Unit";"Roach";"Larva";130;2
"Unit";"Roach";"Larva";130;2
"Unit";"Roach";"Larva";130;2
"Unit";"Roach";"Larva";130;2
"Unit";"Roach";"Larva";130;2
"Unit";"Roach";"Larva";130;2
"Unit";"Roach";"Larva";158;2
"Unit";"Roach";"Larva";158;2
"Unit";"Roach";"Larva";158;2
"Unit";"Roach";"Larva";158;2
"Upgrade";"ZergMissileWeaponsLevel1";"EvolutionChamber";124;0
"Unit";"Roach";"Larva";170;2
"Unit";"Roach";"Larva";170;2
"Unit";"Roach";"Larva";170;2
"Upgrade";"ZergGroundArmorsLevel1";"EvolutionChamber";124;0
"Building";"InfestationPit";NA;158;0
"Unit";"Overlord";"Larva";170;0
"Unit";"Overlord";"Larva";170;0
"Unit";"Overlord";"Larva";170;0
"Unit";"Roach";"Larva";178;2
"Unit";"Roach";"Larva";178;2
"Unit";"Roach";"Larva";178;2
"Unit";"Roach";"Larva";178;2
"Unit";"Roach";"Larva";178;2
"Unit";"Roach";"Larva";178;2
"Unit";"Overlord";"Larva";184;0
"Unit";"Roach";"Larva";184;2
"Unit";"Roach";"Larva";184;2
"Unit";"Roach";"Larva";184;2
"Building";"Extractor";NA;196;0
"Building";"Extractor";NA;196;0
"Unit";"Roach";"Larva";211;2
"Unit";"Roach";"Larva";211;2
"Unit";"Roach";"Larva";211;2
"Unit";"Roach";"Larva";211;2
"Unit";"Roach";"Larva";211;2
"Unit";"Roach";"Larva";211;2
"Unit";"Roach";"Larva";211;2
"Unit";"Roach";"Larva";211;2
"Unit";"Roach";"Larva";211;2
"Unit";"Overlord";"Larva";211;0
"Unit";"Overlord";"Larva";211;0
"Unit";"Roach";"Larva";211;2
"Unit";"Roach";"Larva";211;2
"Unit";"Roach";"Larva";211;2
"Unit";"Roach";"Larva";211;2
"Unit";"Roach";"Larva";211;2
"Unit";"Roach";"Larva";211;2
"Unit";"Roach";"Larva";211;2
"Unit";"Roach";"Larva";211;2
"Unit";"Roach";"Larva";213;2
"Unit";"Roach";"Larva";229;2
"Unit";"Roach";"Larva";229;2
"Unit";"Roach";"Larva";229;2
"Unit";"Roach";"Larva";229;2
"Unit";"Roach";"Larva";229;2
"Unit";"Roach";"Larva";229;2
"Unit";"Roach";"Larva";229;2
"Unit";"Roach";"Larva";229;2
"Unit";"Roach";"Larva";229;2
"Unit";"Roach";"Larva";247;2
"Unit";"Roach";"Larva";247;2
"Unit";"Roach";"Larva";247;2
"Unit";"Roach";"Larva";247;2
"Unit";"Roach";"Larva";247;2
"Unit";"Roach";"Larva";247;2
"Unit";"Roach";"Larva";247;2
"Unit";"Roach";"Larva";265;2
"Unit";"Roach";"Larva";265;2
"Unit";"Roach";"Larva";265;2
"Unit";"Roach";"Larva";265;2
"Unit";"Roach";"Larva";265;2
"Unit";"Roach";"Larva";265;2
"Unit";"Roach";"Larva";265;2
"Unit";"Roach";"Larva";279;2
"Unit";"Roach";"Larva";279;2
"Unit";"Roach";"Larva";279;2
"Unit";"Roach";"Larva";279;2
"Unit";"Roach";"Larva";279;2
"Unit";"Roach";"Larva";279;2
"Unit";"Roach";"Larva";279;2
"Unit";"Roach";"Larva";279;2
"Unit";"Roach";"Larva";279;2
"Unit";"Roach";"Larva";293;2
"Unit";"Roach";"Larva";293;2
"Unit";"Roach";"Larva";293;2
"Unit";"Roach";"Larva";293;2
"Unit";"Roach";"Larva";293;2
"Unit";"Queen";"Hatchery";293;2
"Upgrade";"ZergMissileWeaponsLevel2";"EvolutionChamber";211;0
"Upgrade";"ZergGroundArmorsLevel2";"EvolutionChamber";211;0
"Unit";"Roach";"Larva";324;2
"Unit";"Roach";"Larva";329;2
"Unit";"Roach";"Larva";331;2
"Unit";"Roach";"Larva";333;2
"Unit";"Roach";"Larva";333;2
"Unit";"Roach";"Larva";333;2
"Unit";"Roach";"Larva";334;2
"Unit";"Roach";"Larva";334;2
"Building";"CreepTumorQueen";NA;350;0
"Unit";"Roach";"Larva";350;2
"Unit";"Roach";"Larva";350;2
"Unit";"Roach";"Larva";350;2
"Unit";"Roach";"Larva";350;2
"Unit";"Roach";"Larva";350;2
"Unit";"Roach";"Larva";350;2
"Unit";"Roach";"Larva";350;2
"Unit";"Roach";"Larva";350;2
"Unit";"Roach";"Larva";350;2
"Unit";"Roach";"Larva";350;2
"Unit";"Roach";"Larva";350;2
"Building";"UltraliskCavern";NA;334;0
"Unit";"Roach";"Larva";350;2
"Unit";"Roach";"Larva";350;2
"Unit";"Roach";"Larva";350;2
"Unit";"Roach";"Larva";350;2
"Unit";"Roach";"Larva";350;2
"Unit";"Roach";"Larva";350;2
"Unit";"Roach";"Larva";350;2
"Unit";"Overlord";"Larva";372;0
"Unit";"Overlord";"Larva";372;0
"Unit";"Overlord";"Larva";372;0
"Unit";"Overlord";"Larva";386;0
"Unit";"Overlord";"Larva";386;0
"Unit";"Roach";"Larva";386;2
"Unit";"Roach";"Larva";386;2
"Unit";"Roach";"Larva";386;2
"Unit";"Overlord";"Larva";386;0
"Unit";"Overlord";"Larva";386;0
"Unit";"Overlord";"Larva";386;0
"Unit";"Overlord";"Larva";386;0
"Unit";"Overlord";"Larva";386;0
"Unit";"Roach";"Larva";386;2
"Unit";"Roach";"Larva";386;2
"Building";"CreepTumor";NA;386;0
"Building";"CreepTumor";NA;396;0
"Upgrade";"ZergMissileWeaponsLevel3";"EvolutionChamber";372;0
"Upgrade";"ZergGroundArmorsLevel3";"EvolutionChamber";372;0
"Unit";"Ultralisk";"Larva";396;6
"Unit";"Ultralisk";"Larva";396;6
"Unit";"Ultralisk";"Larva";396;6
"Upgrade";"ChitinousPlating";"UltraliskCavern";396;0
"Unit";"Roach";"Larva";396;2
"Unit";"Roach";"Larva";396;2
"Unit";"Roach";"Larva";396;2
"Unit";"Roach";"Larva";396;2
"Unit";"Roach";"Larva";396;2
"Unit";"Roach";"Larva";396;2
"Unit";"Roach";"Larva";396;2
"Unit";"Roach";"Larva";396;2
"Unit";"Roach";"Larva";396;2
"Unit";"Roach";"Larva";396;2
"Unit";"Roach";"Larva";396;2
"Unit";"Roach";"Larva";396;2
"Unit";"Roach";"Larva";396;2
"Unit";"Roach";"Larva";396;2
"Unit";"Roach";"Larva";396;2
"Unit";"Roach";"Larva";396;2
"Unit";"Roach";"Larva";396;2
"Unit";"Roach";"Larva";396;2
"Unit";"Roach";"Larva";396;2
"Unit";"Roach";"Larva";396;2
"Unit";"Roach";"Larva";396;2
"Unit";"Roach";"Larva";396;2
"Unit";"Roach";"Larva";396;2
