"type";"unit_name";"on_building";"total_supply";"supply"
"Unit";"Overlord";"Larva";12;0
"Building";"Extractor";NA;18;0
"Unit";"Overlord";"Larva";21;0
"Building";"SpawningPool";NA;19;0
"Building";"Hatchery";NA;17;0
"Unit";"Zergling";"Larva";22;1
"Unit";"Zergling";"Larva";22;1
"Unit";"Zergling";"Larva";22;1
"Unit";"Zergling";"Larva";22;1
"Unit";"Queen";"Hatchery";22;2
"Unit";"Queen";"Hatchery";22;2
"Unit";"Overlord";"Larva";36;0
"Building";"BanelingNest";NA;35;0
"Unit";"Zergling";"Larva";39;1
"Unit";"Zergling";"Larva";39;1
"Unit";"Zergling";"Larva";39;1
"Unit";"Zergling";"Larva";39;1
"Unit";"Zergling";"Larva";39;1
"Unit";"Zergling";"Larva";39;1
"Unit";"Zergling";"Larva";39;1
"Unit";"Zergling";"Larva";39;1
"Unit";"Zergling";"Larva";39;1
"Unit";"Zergling";"Larva";39;1
"Unit";"Zergling";"Larva";39;1
"Unit";"Zergling";"Larva";39;1
"Unit";"Zergling";"Larva";39;1
"Unit";"Zergling";"Larva";39;1
"Unit";"Baneling";"Zergling";39;0
"Unit";"Baneling";"Zergling";39;0
"Unit";"Baneling";"Zergling";39;0
"Unit";"Baneling";"Zergling";39;0
"Unit";"Zergling";"Larva";43;1
"Unit";"Zergling";"Larva";43;1
"Unit";"Zergling";"Larva";43;1
"Unit";"Zergling";"Larva";43;1
"Unit";"Queen";"Hatchery";39;2
"Building";"Hatchery";NA;35;0
"Unit";"Overlord";"Larva";45;0
"Unit";"Baneling";"Zergling";59;0
"Unit";"Baneling";"Zergling";59;0
"Unit";"Zergling";"Larva";63;1
"Unit";"Zergling";"Larva";63;1
"Unit";"Zergling";"Larva";63;1
"Unit";"Zergling";"Larva";63;1
"Unit";"Zergling";"Larva";63;1
"Unit";"Zergling";"Larva";63;1
"Unit";"Zergling";"Larva";63;1
"Unit";"Zergling";"Larva";63;1
"Unit";"Zergling";"Larva";63;1
"Unit";"Zergling";"Larva";63;1
"Unit";"Zergling";"Larva";63;1
"Unit";"Zergling";"Larva";63;1
"Unit";"Zergling";"Larva";63;1
"Unit";"Zergling";"Larva";63;1
"Building";"EvolutionChamber";NA;63;0
"Unit";"Zergling";"Larva";64;1
"Unit";"Zergling";"Larva";64;1
"Unit";"Zergling";"Larva";64;1
"Unit";"Zergling";"Larva";64;1
"Unit";"Zergling";"Larva";64;1
"Unit";"Zergling";"Larva";64;1
"Unit";"Zergling";"Larva";64;1
"Unit";"Zergling";"Larva";64;1
"Unit";"Overlord";"Larva";78;0
"Unit";"Zergling";"Larva";86;1
"Unit";"Zergling";"Larva";86;1
"Unit";"Zergling";"Larva";86;1
"Unit";"Zergling";"Larva";86;1
"Unit";"Zergling";"Larva";86;1
"Unit";"Zergling";"Larva";86;1
"Unit";"Zergling";"Larva";86;1
"Unit";"Zergling";"Larva";86;1
"Unit";"Zergling";"Larva";86;1
"Unit";"Zergling";"Larva";86;1
"Unit";"Zergling";"Larva";86;1
"Unit";"Zergling";"Larva";86;1
"Unit";"Zergling";"Larva";86;1
"Unit";"Zergling";"Larva";86;1
"Unit";"Zergling";"Larva";107;1
"Unit";"Zergling";"Larva";107;1
"Unit";"Zergling";"Larva";107;1
"Unit";"Zergling";"Larva";107;1
"Unit";"Zergling";"Larva";107;1
"Unit";"Zergling";"Larva";107;1
"Unit";"Zergling";"Larva";107;1
"Unit";"Zergling";"Larva";107;1
"Unit";"Zergling";"Larva";107;1
"Unit";"Zergling";"Larva";107;1
"Unit";"Zergling";"Larva";107;1
"Unit";"Zergling";"Larva";107;1
"Unit";"Baneling";"Zergling";107;0
"Unit";"Overlord";"Larva";107;0
"Unit";"Baneling";"Zergling";109;0
"Unit";"Baneling";"Zergling";111;0
"Unit";"Baneling";"Zergling";122;0
"Unit";"Zergling";"Larva";123;1
"Unit";"Zergling";"Larva";123;1
"Unit";"Zergling";"Larva";123;1
"Unit";"Zergling";"Larva";123;1
"Unit";"Zergling";"Larva";123;1
"Unit";"Zergling";"Larva";123;1
"Unit";"Zergling";"Larva";123;1
"Unit";"Zergling";"Larva";123;1
"Unit";"Zergling";"Larva";123;1
"Unit";"Zergling";"Larva";123;1
"Unit";"Zergling";"Larva";123;1
"Unit";"Zergling";"Larva";123;1
"Unit";"Zergling";"Larva";123;1
"Unit";"Zergling";"Larva";123;1
"Unit";"Zergling";"Larva";123;1
"Unit";"Zergling";"Larva";123;1
"Unit";"Zergling";"Larva";126;1
"Unit";"Zergling";"Larva";126;1
"Unit";"Zergling";"Larva";126;1
"Unit";"Zergling";"Larva";126;1
"Unit";"Zergling";"Larva";126;1
"Unit";"Zergling";"Larva";126;1
"Unit";"Zergling";"Larva";142;1
"Unit";"Zergling";"Larva";142;1
"Unit";"Zergling";"Larva";142;1
"Unit";"Zergling";"Larva";142;1
"Unit";"Zergling";"Larva";142;1
"Unit";"Zergling";"Larva";142;1
"Unit";"Zergling";"Larva";142;1
"Unit";"Zergling";"Larva";142;1
"Unit";"Zergling";"Larva";142;1
"Unit";"Zergling";"Larva";142;1
"Building";"RoachWarren";NA;123;0
"Unit";"Zergling";"Larva";142;1
"Unit";"Zergling";"Larva";142;1
"Unit";"Zergling";"Larva";142;1
"Unit";"Zergling";"Larva";142;1
"Unit";"Zergling";"Larva";144;1
"Unit";"Zergling";"Larva";144;1
"Unit";"Zergling";"Larva";144;1
"Unit";"Zergling";"Larva";144;1
"Unit";"Zergling";"Larva";148;1
"Unit";"Zergling";"Larva";148;1
"Unit";"Zergling";"Larva";148;1
"Unit";"Zergling";"Larva";148;1
"Upgrade";"ZergMeleeWeaponsLevel1";"EvolutionChamber";107;0
"Unit";"Baneling";"Zergling";166;0
"Unit";"Baneling";"Zergling";166;0
"Unit";"Roach";"Larva";166;2
"Unit";"Roach";"Larva";166;2
"Unit";"Roach";"Larva";166;2
"Unit";"Roach";"Larva";166;2
"Unit";"Roach";"Larva";166;2
"Unit";"Roach";"Larva";166;2
"Unit";"Roach";"Larva";166;2
"Unit";"Baneling";"Zergling";170;0
"Unit";"Baneling";"Zergling";170;0
"Unit";"Overlord";"Larva";170;0
"Unit";"Overlord";"Larva";170;0
"Unit";"Queen";"Hatchery";164;2
"Unit";"Baneling";"Zergling";184;0
"Unit";"Overlord";"Larva";184;0
"Unit";"Overlord";"Larva";184;0
"Building";"Extractor";NA;184;0
"Building";"Extractor";NA;184;0
"Building";"Extractor";NA;184;0
"Unit";"Roach";"Larva";186;2
"Unit";"Roach";"Larva";186;2
"Unit";"Roach";"Larva";186;2
"Unit";"Roach";"Larva";186;2
"Unit";"Overlord";"Larva";186;0
"Unit";"Overlord";"Larva";186;0
"Unit";"Baneling";"Zergling";186;0
"Unit";"Baneling";"Zergling";186;0
"Unit";"Roach";"Larva";186;2
"Unit";"Roach";"Larva";186;2
"Unit";"Roach";"Larva";186;2
"Unit";"Roach";"Larva";186;2
"Unit";"Roach";"Larva";186;2
"Unit";"Roach";"Larva";186;2
"Building";"Extractor";NA;186;0
"Unit";"Baneling";"Zergling";194;0
"Unit";"Baneling";"Zergling";194;0
"Unit";"Roach";"Larva";199;2
"Unit";"Roach";"Larva";209;2
"Unit";"Roach";"Larva";209;2
"Unit";"Roach";"Larva";209;2
"Unit";"Roach";"Larva";209;2
"Unit";"Baneling";"Zergling";209;0
"Building";"Extractor";NA;209;0
"Unit";"Roach";"Larva";221;2
"Unit";"Roach";"Larva";221;2
"Unit";"Roach";"Larva";221;2
"Unit";"Roach";"Larva";221;2
"Unit";"Roach";"Larva";221;2
"Unit";"Roach";"Larva";221;2
"Unit";"Roach";"Larva";221;2
"Unit";"Roach";"Larva";221;2
"Unit";"Roach";"Larva";221;2
"Unit";"Overlord";"Larva";221;0
"Unit";"Overlord";"Larva";221;0
"Unit";"Roach";"Larva";221;2
"Unit";"Roach";"Larva";221;2
"Unit";"Roach";"Larva";239;2
"Unit";"Roach";"Larva";239;2
"Unit";"Roach";"Larva";239;2
"Unit";"Roach";"Larva";243;2
"Unit";"Roach";"Larva";243;2
"Unit";"Roach";"Larva";243;2
"Building";"Hatchery";NA;221;0
"Unit";"Roach";"Larva";245;2
