"type";"unit_name";"on_building";"total_supply";"supply"
"Unit";"Overlord";"Larva";12;0
"Building";"Extractor";NA;18;0
"Unit";"Overlord";"Larva";21;0
"Building";"SpawningPool";NA;19;0
"Building";"Hatchery";NA;17;0
"Unit";"Zergling";"Larva";22;1
"Unit";"Zergling";"Larva";22;1
"Unit";"Zergling";"Larva";22;1
"Unit";"Zergling";"Larva";22;1
"Unit";"Queen";"Hatchery";22;2
"Unit";"Queen";"Hatchery";22;2
"Building";"CreepTumorQueen";NA;35;0
"Unit";"Overlord";"Larva";38;0
"Unit";"Queen";"Hatchery";35;2
"Building";"CreepTumor";NA;39;0
"Unit";"Overlord";"Larva";39;0
"Building";"EvolutionChamber";NA;39;0
"Building";"Extractor";NA;39;0
"Building";"RoachWarren";NA;38;0
"Building";"EvolutionChamber";NA;46;0
"Unit";"Roach";"Larva";48;2
"Unit";"Roach";"Larva";48;2
"Unit";"Roach";"Larva";48;2
"Unit";"Roach";"Larva";48;2
"Unit";"Roach";"Larva";48;2
"Building";"EvolutionChamber";NA;48;0
"Unit";"Roach";"Larva";48;2
"Unit";"Roach";"Larva";48;2
"Unit";"Roach";"Larva";48;2
"Unit";"Roach";"Larva";58;2
"Unit";"Roach";"Larva";58;2
"Unit";"Roach";"Larva";58;2
"Unit";"Roach";"Larva";62;2
"Unit";"Roach";"Larva";64;2
"Unit";"Roach";"Larva";70;2
"Unit";"Roach";"Larva";74;2
"Unit";"Roach";"Larva";74;2
"Unit";"Roach";"Larva";76;2
"Upgrade";"GlialReconstitution";"RoachWarren";62;0
"Unit";"Roach";"Larva";76;2
"Unit";"Roach";"Larva";84;2
"Unit";"Overlord";"Larva";86;0
"Unit";"Roach";"Larva";89;2
"Unit";"Roach";"Larva";89;2
"Building";"Extractor";NA;108;0
"Unit";"Queen";"Hatchery";108;2
"Unit";"Overlord";"Larva";119;0
"Unit";"Overlord";"Larva";119;0
"Unit";"Overlord";"Larva";121;0
"Unit";"Overlord";"Larva";121;0
"Unit";"Roach";"Larva";121;2
"Unit";"Roach";"Larva";121;2
"Unit";"Roach";"Larva";121;2
"Unit";"Roach";"Larva";121;2
"Building";"Hatchery";NA;115;0
"Upgrade";"ZergMissileWeaponsLevel1";"EvolutionChamber";115;0
"Unit";"Overlord";"Larva";135;0
"Unit";"Roach";"Larva";135;2
"Unit";"Roach";"Larva";135;2
"Unit";"Roach";"Larva";136;2
"Unit";"Roach";"Larva";136;2
"Unit";"Roach";"Larva";136;2
"Unit";"Roach";"Larva";136;2
"Building";"Extractor";NA;136;0
"Unit";"Overlord";"Larva";136;0
"Unit";"Overlord";"Larva";136;0
"Unit";"Queen";"Hatchery";136;2
"Unit";"Roach";"Larva";153;2
"Unit";"Roach";"Larva";153;2
"Unit";"Roach";"Larva";153;2
"Unit";"Roach";"Larva";155;2
"Building";"Extractor";NA;153;0
"Unit";"Roach";"Larva";160;2
"Unit";"Roach";"Larva";160;2
"Unit";"Roach";"Larva";162;2
"Unit";"Roach";"Larva";162;2
"Unit";"Overlord";"Larva";162;0
"Unit";"Overlord";"Larva";162;0
"Unit";"Overlord";"Larva";166;0
"Unit";"Overlord";"Larva";168;0
"Upgrade";"ZergGroundArmorsLevel1";"EvolutionChamber";136;0
"Unit";"Roach";"Larva";176;2
"Unit";"Roach";"Larva";176;2
"Unit";"Roach";"Larva";176;2
"Unit";"Roach";"Larva";176;2
"Unit";"Roach";"Larva";176;2
"Unit";"Roach";"Larva";176;2
"Unit";"Roach";"Larva";176;2
"Unit";"Roach";"Larva";176;2
"Unit";"Roach";"Larva";176;2
"Unit";"Roach";"Larva";176;2
"Unit";"Roach";"Larva";176;2
"Unit";"Roach";"Larva";176;2
"Unit";"Roach";"Larva";176;2
"Unit";"Roach";"Larva";190;2
"Unit";"Roach";"Larva";190;2
"Unit";"Roach";"Larva";190;2
"Unit";"Roach";"Larva";190;2
"Unit";"Roach";"Larva";190;2
"Unit";"Roach";"Larva";190;2
"Unit";"Roach";"Larva";190;2
"Unit";"Roach";"Larva";190;2
"Unit";"Roach";"Larva";204;2
"Unit";"Roach";"Larva";206;2
"Unit";"Roach";"Larva";206;2
"Unit";"Roach";"Larva";206;2
"Unit";"Roach";"Larva";206;2
"Unit";"Roach";"Larva";208;2
"Unit";"Roach";"Larva";208;2
"Unit";"Roach";"Larva";208;2
"Unit";"Roach";"Larva";214;2
"Unit";"Roach";"Larva";218;2
"Upgrade";"Burrow";"Hatchery";190;0
"Unit";"Roach";"Larva";218;2
"Unit";"Roach";"Larva";218;2
"Upgrade";"TunnelingClaws";"RoachWarren";190;0
"Unit";"Roach";"Larva";226;2
"Upgrade";"ZergMissileWeaponsLevel2";"EvolutionChamber";168;0
"Unit";"Roach";"Larva";234;2
"Unit";"Roach";"Larva";236;2
"Unit";"Roach";"Larva";236;2
"Unit";"Roach";"Larva";244;2
"Unit";"Roach";"Larva";244;2
"Unit";"Roach";"Larva";244;2
"Unit";"Roach";"Larva";246;2
"Unit";"Roach";"Larva";246;2
"Unit";"Roach";"Larva";246;2
"Unit";"Roach";"Larva";246;2
"Unit";"Roach";"Larva";246;2
"Unit";"Overlord";"Larva";250;0
"Unit";"Roach";"Larva";250;2
"Unit";"Roach";"Larva";256;2
"Unit";"Roach";"Larva";256;2
"Unit";"Roach";"Larva";256;2
"Unit";"Overlord";"Larva";256;0
"Unit";"Overlord";"Larva";256;0
"Unit";"Overlord";"Larva";266;0
"Unit";"Overlord";"Larva";266;0
"Unit";"Overlord";"Larva";266;0
"Unit";"Roach";"Larva";266;2
"Unit";"Roach";"Larva";266;2
"Unit";"Roach";"Larva";272;2
"Unit";"Roach";"Larva";274;2
"Unit";"Roach";"Larva";274;2
"Unit";"Roach";"Larva";274;2
"Unit";"Roach";"Larva";274;2
"Unit";"Roach";"Larva";274;2
"Unit";"Roach";"Larva";274;2
"Unit";"Roach";"Larva";274;2
"Unit";"Roach";"Larva";274;2
"Unit";"Roach";"Larva";278;2
"Unit";"Roach";"Larva";278;2
"Unit";"Roach";"Larva";282;2
"Unit";"Roach";"Larva";286;2
"Unit";"Roach";"Larva";288;2
"Unit";"Roach";"Larva";288;2
"Unit";"Roach";"Larva";294;2
"Unit";"Roach";"Larva";294;2
