"type";"unit_name";"on_building";"total_supply";"supply"
"Unit";"Overlord";"Larva";12;0
"Building";"Extractor";NA;18;0
"Unit";"Overlord";"Larva";22;0
"Building";"SpawningPool";NA;19;0
"Building";"Hatchery";NA;17;0
"Unit";"Zergling";"Larva";23;1
"Unit";"Zergling";"Larva";23;1
"Unit";"Zergling";"Larva";23;1
"Unit";"Zergling";"Larva";23;1
"Unit";"Queen";"Hatchery";23;2
"Unit";"Queen";"Hatchery";23;2
"Unit";"Overlord";"Larva";36;0
"Unit";"Zergling";"Larva";38;1
"Unit";"Zergling";"Larva";38;1
"Unit";"Zergling";"Larva";38;1
"Unit";"Zergling";"Larva";38;1
"Unit";"Overlord";"Larva";38;0
"Building";"BanelingNest";NA;36;0
"Unit";"Zergling";"Larva";38;1
"Unit";"Zergling";"Larva";38;1
"Unit";"Zergling";"Larva";38;1
"Unit";"Zergling";"Larva";38;1
"Unit";"Zergling";"Larva";38;1
"Unit";"Zergling";"Larva";38;1
"Unit";"Zergling";"Larva";38;1
"Unit";"Zergling";"Larva";38;1
"Unit";"Zergling";"Larva";38;1
"Unit";"Zergling";"Larva";38;1
"Unit";"Zergling";"Larva";38;1
"Unit";"Zergling";"Larva";38;1
"Unit";"Overlord";"Larva";42;0
"Unit";"Zergling";"Larva";42;1
"Unit";"Zergling";"Larva";42;1
"Unit";"Zergling";"Larva";42;1
"Unit";"Zergling";"Larva";42;1
"Building";"Hatchery";NA;35;0
"Unit";"Baneling";"Zergling";54;0
"Unit";"Baneling";"Zergling";54;0
"Unit";"Zergling";"Larva";54;1
"Unit";"Zergling";"Larva";54;1
"Unit";"Zergling";"Larva";54;1
"Unit";"Zergling";"Larva";54;1
"Unit";"Zergling";"Larva";54;1
"Unit";"Zergling";"Larva";54;1
"Unit";"Zergling";"Larva";58;1
"Unit";"Zergling";"Larva";58;1
"Unit";"Baneling";"Zergling";58;0
"Unit";"Baneling";"Zergling";58;0
"Unit";"Baneling";"Zergling";58;0
"Unit";"Zergling";"Larva";58;1
"Unit";"Zergling";"Larva";58;1
"Unit";"Zergling";"Larva";64;1
"Unit";"Zergling";"Larva";64;1
"Unit";"Zergling";"Larva";64;1
"Unit";"Zergling";"Larva";64;1
"Unit";"Zergling";"Larva";64;1
"Unit";"Zergling";"Larva";64;1
"Unit";"Zergling";"Larva";64;1
"Unit";"Zergling";"Larva";64;1
"Unit";"Zergling";"Larva";64;1
"Unit";"Zergling";"Larva";64;1
"Unit";"Zergling";"Larva";64;1
"Unit";"Zergling";"Larva";64;1
"Unit";"Zergling";"Larva";68;1
"Unit";"Zergling";"Larva";68;1
"Unit";"Zergling";"Larva";68;1
"Unit";"Zergling";"Larva";68;1
"Unit";"Zergling";"Larva";80;1
"Unit";"Zergling";"Larva";80;1
"Unit";"Zergling";"Larva";80;1
"Unit";"Zergling";"Larva";80;1
"Unit";"Zergling";"Larva";80;1
"Unit";"Zergling";"Larva";80;1
"Unit";"Zergling";"Larva";80;1
"Unit";"Zergling";"Larva";80;1
"Unit";"Baneling";"Zergling";84;0
"Unit";"Baneling";"Zergling";86;0
"Unit";"Baneling";"Zergling";86;0
"Unit";"Baneling";"Zergling";86;0
"Unit";"Baneling";"Zergling";86;0
"Unit";"Baneling";"Zergling";86;0
"Unit";"Baneling";"Zergling";86;0
"Unit";"Baneling";"Zergling";86;0
"Unit";"Zergling";"Larva";92;1
"Unit";"Zergling";"Larva";92;1
"Unit";"Zergling";"Larva";92;1
"Unit";"Zergling";"Larva";92;1
"Unit";"Zergling";"Larva";92;1
"Unit";"Zergling";"Larva";92;1
"Unit";"Zergling";"Larva";92;1
"Unit";"Zergling";"Larva";92;1
"Unit";"Zergling";"Larva";92;1
"Unit";"Zergling";"Larva";92;1
"Unit";"Zergling";"Larva";104;1
"Unit";"Zergling";"Larva";104;1
"Unit";"Zergling";"Larva";104;1
"Unit";"Zergling";"Larva";104;1
"Unit";"Zergling";"Larva";104;1
"Unit";"Zergling";"Larva";104;1
"Unit";"Zergling";"Larva";104;1
"Unit";"Zergling";"Larva";104;1
"Unit";"Zergling";"Larva";104;1
"Unit";"Zergling";"Larva";104;1
"Unit";"Zergling";"Larva";104;1
"Unit";"Zergling";"Larva";104;1
"Unit";"Zergling";"Larva";104;1
"Unit";"Zergling";"Larva";104;1
"Unit";"Zergling";"Larva";104;1
"Unit";"Zergling";"Larva";104;1
"Unit";"Zergling";"Larva";104;1
"Unit";"Zergling";"Larva";104;1
"Unit";"Zergling";"Larva";104;1
"Unit";"Zergling";"Larva";104;1
"Unit";"Zergling";"Larva";104;1
"Unit";"Zergling";"Larva";104;1
"Unit";"Zergling";"Larva";104;1
"Unit";"Zergling";"Larva";104;1
"Unit";"Zergling";"Larva";104;1
"Unit";"Zergling";"Larva";104;1
"Unit";"Baneling";"Zergling";104;0
"Unit";"Baneling";"Zergling";104;0
"Unit";"Baneling";"Zergling";104;0
"Unit";"Baneling";"Zergling";104;0
"Unit";"Baneling";"Zergling";106;0
"Unit";"Zergling";"Larva";104;1
"Unit";"Zergling";"Larva";104;1
"Unit";"Zergling";"Larva";104;1
"Unit";"Zergling";"Larva";104;1
"Unit";"Zergling";"Larva";114;1
"Unit";"Zergling";"Larva";114;1
"Unit";"Zergling";"Larva";114;1
"Unit";"Zergling";"Larva";114;1
"Unit";"Zergling";"Larva";130;1
"Unit";"Zergling";"Larva";130;1
"Unit";"Zergling";"Larva";134;1
"Unit";"Zergling";"Larva";134;1
"Unit";"Zergling";"Larva";134;1
"Unit";"Zergling";"Larva";134;1
"Unit";"Baneling";"Zergling";138;0
"Unit";"Baneling";"Zergling";138;0
"Unit";"Baneling";"Zergling";138;0
"Unit";"Zergling";"Larva";138;1
"Unit";"Zergling";"Larva";138;1
"Unit";"Zergling";"Larva";138;1
"Unit";"Zergling";"Larva";138;1
"Unit";"Zergling";"Larva";138;1
"Unit";"Zergling";"Larva";138;1
"Unit";"Zergling";"Larva";138;1
"Unit";"Zergling";"Larva";138;1
"Unit";"Zergling";"Larva";138;1
"Unit";"Zergling";"Larva";138;1
"Unit";"Zergling";"Larva";138;1
"Unit";"Zergling";"Larva";138;1
"Unit";"Zergling";"Larva";138;1
"Unit";"Zergling";"Larva";138;1
"Unit";"Zergling";"Larva";144;1
"Unit";"Zergling";"Larva";144;1
"Unit";"Zergling";"Larva";144;1
"Unit";"Zergling";"Larva";144;1
"Unit";"Zergling";"Larva";144;1
"Unit";"Zergling";"Larva";144;1
"Unit";"Zergling";"Larva";144;1
"Unit";"Zergling";"Larva";144;1
"Unit";"Zergling";"Larva";158;1
"Unit";"Zergling";"Larva";158;1
"Unit";"Zergling";"Larva";158;1
"Unit";"Zergling";"Larva";158;1
"Unit";"Zergling";"Larva";158;1
"Unit";"Zergling";"Larva";158;1
"Unit";"Zergling";"Larva";158;1
"Unit";"Zergling";"Larva";158;1
"Unit";"Zergling";"Larva";158;1
"Unit";"Zergling";"Larva";158;1
"Unit";"Zergling";"Larva";158;1
"Unit";"Zergling";"Larva";158;1
"Unit";"Zergling";"Larva";158;1
"Unit";"Zergling";"Larva";158;1
"Unit";"Zergling";"Larva";158;1
"Unit";"Zergling";"Larva";158;1
"Unit";"Zergling";"Larva";158;1
"Unit";"Zergling";"Larva";158;1
