"type";"unit_name";"on_building";"total_supply";"supply"
"Unit";"Overlord";"Larva";13;0
"Building";"Extractor";NA;18;0
"Unit";"Overlord";"Larva";21;0
"Building";"SpawningPool";NA;19;0
"Building";"Hatchery";NA;17;0
"Unit";"Zergling";"Larva";22;1
"Unit";"Zergling";"Larva";22;1
"Unit";"Zergling";"Larva";22;1
"Unit";"Zergling";"Larva";22;1
"Unit";"Zergling";"Larva";22;1
"Unit";"Zergling";"Larva";22;1
"Unit";"Queen";"Hatchery";22;2
"Unit";"Queen";"Hatchery";22;2
"Unit";"Zergling";"Larva";29;1
"Unit";"Zergling";"Larva";29;1
"Building";"EvolutionChamber";NA;33;0
"Unit";"Overlord";"Larva";42;0
"Unit";"Overlord";"Larva";45;0
"Building";"Hatchery";NA;39;0
"Unit";"Overlord";"Larva";52;0
"Building";"Extractor";NA;56;0
"Building";"Extractor";NA;56;0
"Unit";"Zergling";"Larva";59;1
"Unit";"Zergling";"Larva";59;1
"Unit";"Zergling";"Larva";59;1
"Unit";"Zergling";"Larva";59;1
"Unit";"Zergling";"Larva";59;1
"Unit";"Zergling";"Larva";59;1
"Unit";"Zergling";"Larva";59;1
"Unit";"Zergling";"Larva";59;1
"Unit";"Zergling";"Larva";59;1
"Unit";"Zergling";"Larva";59;1
"Unit";"Zergling";"Larva";59;1
"Unit";"Zergling";"Larva";59;1
"Unit";"Zergling";"Larva";59;1
"Unit";"Zergling";"Larva";59;1
"Unit";"Zergling";"Larva";59;1
"Unit";"Zergling";"Larva";59;1
"Unit";"Zergling";"Larva";59;1
"Unit";"Zergling";"Larva";59;1
"Unit";"Zergling";"Larva";59;1
"Unit";"Zergling";"Larva";59;1
"Unit";"Zergling";"Larva";59;1
"Unit";"Zergling";"Larva";59;1
"Unit";"Zergling";"Larva";59;1
"Unit";"Zergling";"Larva";59;1
"Unit";"Zergling";"Larva";59;1
"Unit";"Zergling";"Larva";59;1
"Unit";"Zergling";"Larva";65;1
"Unit";"Zergling";"Larva";65;1
"Building";"RoachWarren";NA;59;0
"Unit";"Overlord";"Larva";69;0
"Unit";"Zergling";"Larva";71;1
"Unit";"Zergling";"Larva";71;1
"Upgrade";"ZergGroundArmorsLevel1";"EvolutionChamber";47;0
"Unit";"Zergling";"Larva";75;1
"Unit";"Zergling";"Larva";75;1
"Unit";"Overlord";"Larva";101;0
"Unit";"Overlord";"Larva";106;0
"Building";"Extractor";NA;106;0
"Building";"Extractor";NA;106;0
"Unit";"Roach";"Larva";113;2
"Unit";"Roach";"Larva";113;2
"Unit";"Roach";"Larva";113;2
"Unit";"Roach";"Larva";113;2
"Unit";"Roach";"Larva";113;2
"Unit";"Roach";"Larva";113;2
"Unit";"Queen";"Hatchery";113;2
"Unit";"Roach";"Larva";116;2
"Unit";"Roach";"Larva";116;2
"Upgrade";"GlialReconstitution";"RoachWarren";101;0
"Unit";"Roach";"Larva";116;2
"Unit";"Roach";"Larva";116;2
"Unit";"Roach";"Larva";116;2
"Unit";"Roach";"Larva";116;2
"Unit";"Overlord";"Larva";122;0
"Unit";"Overlord";"Larva";122;0
"Unit";"Overlord";"Larva";124;0
"Unit";"Overlord";"Larva";138;0
"Upgrade";"ZergMissileWeaponsLevel1";"EvolutionChamber";101;0
"Unit";"Roach";"Larva";142;2
"Unit";"Roach";"Larva";142;2
"Unit";"Roach";"Larva";142;2
"Unit";"Roach";"Larva";142;2
"Unit";"Roach";"Larva";142;2
"Unit";"Roach";"Larva";142;2
"Unit";"Roach";"Larva";142;2
"Unit";"Roach";"Larva";142;2
"Building";"EvolutionChamber";NA;142;0
"Unit";"Roach";"Larva";142;2
"Building";"Hatchery";NA;113;0
"Unit";"Roach";"Larva";142;2
"Unit";"Roach";"Larva";142;2
"Unit";"Roach";"Larva";142;2
"Unit";"Roach";"Larva";142;2
"Unit";"Roach";"Larva";142;2
"Unit";"Roach";"Larva";142;2
"Unit";"Roach";"Larva";144;2
"Unit";"Roach";"Larva";158;2
"Unit";"Overlord";"Larva";158;0
"Unit";"Overlord";"Larva";162;0
"Unit";"Overlord";"Larva";164;0
"Unit";"Overlord";"Larva";164;0
"Unit";"Overlord";"Larva";174;0
"Unit";"Roach";"Larva";176;2
"Unit";"Roach";"Larva";176;2
"Unit";"Roach";"Larva";176;2
"Unit";"Roach";"Larva";176;2
"Unit";"Roach";"Larva";176;2
"Unit";"Roach";"Larva";176;2
"Unit";"Roach";"Larva";176;2
"Unit";"Roach";"Larva";176;2
"Unit";"Roach";"Larva";176;2
"Unit";"Roach";"Larva";176;2
"Unit";"Roach";"Larva";176;2
"Unit";"Roach";"Larva";176;2
"Unit";"Roach";"Larva";184;2
"Unit";"Roach";"Larva";184;2
"Unit";"Roach";"Larva";184;2
"Unit";"Overlord";"Larva";186;0
"Unit";"Roach";"Larva";190;2
"Unit";"Roach";"Larva";190;2
"Unit";"Roach";"Larva";200;2
"Unit";"Roach";"Larva";200;2
"Unit";"Roach";"Larva";200;2
"Unit";"Roach";"Larva";206;2
"Unit";"Roach";"Larva";206;2
"Unit";"Roach";"Larva";206;2
"Unit";"Roach";"Larva";206;2
"Unit";"Roach";"Larva";216;2
"Unit";"Roach";"Larva";216;2
"Unit";"Roach";"Larva";216;2
"Unit";"Roach";"Larva";216;2
"Unit";"Roach";"Larva";216;2
"Unit";"Roach";"Larva";216;2
"Unit";"Roach";"Larva";216;2
"Unit";"Roach";"Larva";216;2
"Unit";"Roach";"Larva";216;2
"Unit";"Roach";"Larva";216;2
"Unit";"Roach";"Larva";216;2
"Unit";"Roach";"Larva";224;2
"Unit";"Roach";"Larva";224;2
"Unit";"Roach";"Larva";224;2
"Unit";"Roach";"Larva";224;2
"Unit";"Roach";"Larva";224;2
"Unit";"Roach";"Larva";224;2
"Unit";"Roach";"Larva";246;2
"Unit";"Roach";"Larva";246;2
"Unit";"Roach";"Larva";246;2
"Upgrade";"ZergMissileWeaponsLevel2";"EvolutionChamber";176;0
"Unit";"Roach";"Larva";246;2
"Unit";"Roach";"Larva";246;2
"Unit";"Roach";"Larva";246;2
"Unit";"Roach";"Larva";246;2
"Unit";"Roach";"Larva";246;2
"Upgrade";"ZergGroundArmorsLevel2";"EvolutionChamber";176;0
"Unit";"Roach";"Larva";258;2
"Unit";"Roach";"Larva";258;2
"Unit";"Roach";"Larva";258;2
"Unit";"Roach";"Larva";258;2
"Unit";"Roach";"Larva";264;2
"Unit";"Roach";"Larva";264;2
"Unit";"Roach";"Larva";264;2
"Unit";"Roach";"Larva";264;2
"Unit";"Roach";"Larva";264;2
"Unit";"Roach";"Larva";264;2
"Unit";"Roach";"Larva";274;2
"Unit";"Roach";"Larva";274;2
"Unit";"Roach";"Larva";282;2
"Unit";"Roach";"Larva";282;2
"Unit";"Roach";"Larva";282;2
"Unit";"Roach";"Larva";282;2
"Unit";"Roach";"Larva";282;2
"Unit";"Roach";"Larva";282;2
"Unit";"Roach";"Larva";282;2
"Unit";"Roach";"Larva";282;2
"Unit";"Roach";"Larva";294;2
"Unit";"Roach";"Larva";294;2
"Unit";"Roach";"Larva";298;2
"Unit";"Roach";"Larva";304;2
"Unit";"Roach";"Larva";304;2
"Unit";"Roach";"Larva";304;2
"Unit";"Roach";"Larva";304;2
"Unit";"Roach";"Larva";304;2
"Unit";"Roach";"Larva";318;2
"Unit";"Roach";"Larva";318;2
"Unit";"Roach";"Larva";318;2
"Unit";"Roach";"Larva";318;2
"Unit";"Roach";"Larva";318;2
"Unit";"Roach";"Larva";320;2
"Unit";"Roach";"Larva";320;2
"Unit";"Roach";"Larva";330;2
"Unit";"Roach";"Larva";330;2
"Unit";"Roach";"Larva";330;2
"Unit";"Roach";"Larva";332;2
"Unit";"Roach";"Larva";332;2
"Unit";"Roach";"Larva";340;2
"Unit";"Roach";"Larva";344;2
"Unit";"Roach";"Larva";344;2
"Unit";"Roach";"Larva";344;2
"Unit";"Roach";"Larva";344;2
"Unit";"Roach";"Larva";344;2
"Unit";"Roach";"Larva";348;2
"Unit";"Roach";"Larva";350;2
"Unit";"Roach";"Larva";350;2
"Unit";"Roach";"Larva";350;2
"Unit";"Overlord";"Larva";356;0
"Unit";"Overlord";"Larva";356;0
"Unit";"Overlord";"Larva";356;0
"Unit";"Overlord";"Larva";356;0
"Unit";"Overlord";"Larva";356;0
"Unit";"Roach";"Larva";374;2
"Unit";"Roach";"Larva";374;2
"Unit";"Roach";"Larva";374;2
"Unit";"Roach";"Larva";374;2
"Unit";"Roach";"Larva";374;2
"Unit";"Roach";"Larva";374;2
"Unit";"Roach";"Larva";374;2
"Unit";"Roach";"Larva";374;2
"Unit";"Roach";"Larva";374;2
"Unit";"Roach";"Larva";374;2
"Unit";"Roach";"Larva";374;2
"Unit";"Roach";"Larva";374;2
"Unit";"Roach";"Larva";374;2
"Unit";"Roach";"Larva";374;2
"Unit";"Roach";"Larva";374;2
"Unit";"Roach";"Larva";374;2
"Unit";"Roach";"Larva";374;2
"Unit";"Roach";"Larva";374;2
"Unit";"Roach";"Larva";374;2
"Unit";"Roach";"Larva";374;2
"Unit";"Roach";"Larva";374;2
"Unit";"Roach";"Larva";374;2
"Unit";"Roach";"Larva";400;2
"Unit";"Roach";"Larva";400;2
"Unit";"Roach";"Larva";400;2
"Unit";"Roach";"Larva";400;2
"Unit";"Roach";"Larva";400;2
"Unit";"Roach";"Larva";400;2
"Unit";"Roach";"Larva";418;2
"Unit";"Roach";"Larva";418;2
"Unit";"Roach";"Larva";418;2
"Unit";"Roach";"Larva";430;2
"Unit";"Roach";"Larva";430;2
"Unit";"Roach";"Larva";430;2
"Unit";"Roach";"Larva";430;2
"Unit";"Roach";"Larva";430;2
"Building";"Extractor";NA;430;0
"Unit";"Roach";"Larva";436;2
"Unit";"Roach";"Larva";438;2
"Unit";"Roach";"Larva";446;2
"Unit";"Roach";"Larva";448;2
"Unit";"Roach";"Larva";452;2
"Unit";"Roach";"Larva";452;2
"Unit";"Roach";"Larva";455;2
"Unit";"Roach";"Larva";455;2
"Unit";"Roach";"Larva";459;2
"Unit";"Roach";"Larva";459;2
"Unit";"Roach";"Larva";459;2
"Unit";"Roach";"Larva";459;2
"Building";"Hatchery";NA;402;0
"Unit";"Roach";"Larva";461;2
"Unit";"Roach";"Larva";467;2
"Unit";"Roach";"Larva";467;2
"Building";"SpineCrawler";NA;463;0
"Unit";"Roach";"Larva";485;2
"Unit";"Roach";"Larva";485;2
"Unit";"Roach";"Larva";485;2
"Unit";"Roach";"Larva";485;2
"Unit";"Roach";"Larva";485;2
"Unit";"Roach";"Larva";485;2
"Unit";"Roach";"Larva";485;2
"Unit";"Roach";"Larva";485;2
"Unit";"Roach";"Larva";485;2
"Unit";"Roach";"Larva";485;2
"Unit";"Roach";"Larva";485;2
"Unit";"Roach";"Larva";485;2
"Unit";"Roach";"Larva";485;2
"Unit";"Roach";"Larva";485;2
"Unit";"Roach";"Larva";485;2
"Unit";"Roach";"Larva";485;2
"Unit";"Roach";"Larva";485;2
"Unit";"Roach";"Larva";485;2
"Unit";"Roach";"Larva";485;2
"Unit";"Roach";"Larva";485;2
"Unit";"Roach";"Larva";485;2
"Unit";"Roach";"Larva";485;2
"Unit";"Roach";"Larva";485;2
"Unit";"Roach";"Larva";503;2
"Unit";"Roach";"Larva";503;2
"Unit";"Roach";"Larva";503;2
"Unit";"Roach";"Larva";503;2
"Unit";"Roach";"Larva";503;2
"Unit";"Roach";"Larva";529;2
"Unit";"Roach";"Larva";529;2
"Unit";"Roach";"Larva";529;2
"Unit";"Roach";"Larva";529;2
"Unit";"Roach";"Larva";529;2
"Unit";"Roach";"Larva";541;2
"Unit";"Roach";"Larva";541;2
"Unit";"Roach";"Larva";541;2
"Unit";"Roach";"Larva";541;2
"Unit";"Roach";"Larva";541;2
"Unit";"Roach";"Larva";541;2
"Unit";"Roach";"Larva";543;2
"Unit";"Roach";"Larva";547;2
"Unit";"Roach";"Larva";551;2
"Unit";"Roach";"Larva";551;2
"Unit";"Roach";"Larva";551;2
"Unit";"Roach";"Larva";551;2
"Unit";"Roach";"Larva";551;2
"Unit";"Roach";"Larva";551;2
"Unit";"Roach";"Larva";557;2
"Unit";"Roach";"Larva";559;2
"Unit";"Roach";"Larva";561;2
"Unit";"Roach";"Larva";561;2
"Unit";"Roach";"Larva";563;2
"Unit";"Roach";"Larva";565;2
"Unit";"Roach";"Larva";567;2
"Unit";"Roach";"Larva";567;2
"Unit";"Roach";"Larva";567;2
"Unit";"Roach";"Larva";567;2
"Upgrade";"Burrow";"Hatchery";551;0
"Unit";"Roach";"Larva";591;2
"Unit";"Roach";"Larva";591;2
"Unit";"Roach";"Larva";591;2
"Unit";"Roach";"Larva";591;2
"Unit";"Roach";"Larva";591;2
"Unit";"Roach";"Larva";591;2
"Unit";"Roach";"Larva";591;2
"Unit";"Roach";"Larva";591;2
"Unit";"Roach";"Larva";593;2
"Unit";"Roach";"Larva";593;2
"Upgrade";"TunnelingClaws";"RoachWarren";553;0
"Unit";"Roach";"Larva";599;2
"Unit";"Roach";"Larva";599;2
"Unit";"Roach";"Larva";599;2
"Unit";"Roach";"Larva";599;2
"Unit";"Roach";"Larva";599;2
"Unit";"Roach";"Larva";599;2
"Unit";"Roach";"Larva";599;2
"Unit";"Roach";"Larva";599;2
"Unit";"Roach";"Larva";599;2
"Unit";"Roach";"Larva";599;2
"Unit";"Roach";"Larva";633;2
"Unit";"Roach";"Larva";633;2
"Unit";"Roach";"Larva";633;2
"Unit";"Roach";"Larva";633;2
"Unit";"Roach";"Larva";633;2
"Unit";"Roach";"Larva";633;2
"Unit";"Roach";"Larva";639;2
"Unit";"Roach";"Larva";639;2
"Unit";"Roach";"Larva";639;2
"Unit";"Roach";"Larva";639;2
"Unit";"Roach";"Larva";639;2
"Unit";"Roach";"Larva";639;2
"Unit";"Roach";"Larva";639;2
"Unit";"Roach";"Larva";639;2
"Unit";"Roach";"Larva";639;2
"Unit";"Roach";"Larva";639;2
"Unit";"Roach";"Larva";651;2
"Unit";"Roach";"Larva";651;2
"Unit";"Roach";"Larva";651;2
"Unit";"Roach";"Larva";651;2
"Unit";"Roach";"Larva";651;2
"Unit";"Roach";"Larva";651;2
"Unit";"Roach";"Larva";651;2
"Unit";"Roach";"Larva";651;2
"Unit";"Roach";"Larva";661;2
"Unit";"Roach";"Larva";671;2
"Unit";"Roach";"Larva";671;2
"Unit";"Roach";"Larva";671;2
"Unit";"Roach";"Larva";675;2
"Unit";"Roach";"Larva";675;2
"Unit";"Roach";"Larva";675;2
"Unit";"Roach";"Larva";675;2
"Unit";"Roach";"Larva";675;2
"Unit";"Roach";"Larva";687;2
"Unit";"Roach";"Larva";687;2
"Unit";"Roach";"Larva";687;2
"Unit";"Roach";"Larva";687;2
"Unit";"Roach";"Larva";687;2
"Unit";"Roach";"Larva";695;2
"Unit";"Roach";"Larva";695;2
"Building";"Hatchery";NA;639;0
"Unit";"Roach";"Larva";695;2
"Unit";"Roach";"Larva";695;2
"Unit";"Roach";"Larva";695;2
"Unit";"Roach";"Larva";695;2
"Unit";"Roach";"Larva";705;2
"Unit";"Roach";"Larva";705;2
"Unit";"Roach";"Larva";705;2
"Unit";"Roach";"Larva";705;2
"Unit";"Roach";"Larva";705;2
"Unit";"Roach";"Larva";715;2
"Unit";"Roach";"Larva";719;2
"Unit";"Roach";"Larva";719;2
"Unit";"Roach";"Larva";719;2
"Unit";"Roach";"Larva";719;2
"Unit";"Roach";"Larva";719;2
"Unit";"Roach";"Larva";743;2
"Unit";"Roach";"Larva";743;2
"Unit";"Roach";"Larva";743;2
"Unit";"Roach";"Larva";743;2
"Unit";"Roach";"Larva";743;2
"Building";"Extractor";NA;739;0
"Unit";"Roach";"Larva";749;2
"Unit";"Roach";"Larva";749;2
"Unit";"Roach";"Larva";749;2
"Unit";"Roach";"Larva";749;2
"Unit";"Roach";"Larva";749;2
"Unit";"Roach";"Larva";770;2
"Unit";"Roach";"Larva";770;2
"Unit";"Roach";"Larva";770;2
"Unit";"Roach";"Larva";770;2
"Unit";"Roach";"Larva";770;2
"Unit";"Roach";"Larva";770;2
"Unit";"Roach";"Larva";770;2
"Unit";"Roach";"Larva";770;2
"Unit";"Roach";"Larva";770;2
"Unit";"Roach";"Larva";770;2
"Unit";"Roach";"Larva";770;2
"Unit";"Roach";"Larva";770;2
"Unit";"Roach";"Larva";770;2
"Unit";"Roach";"Larva";770;2
