"type";"unit_name";"on_building";"total_supply";"supply"
"Unit";"Overlord";"Larva";12;0
"Building";"Extractor";NA;18;0
"Unit";"Overlord";"Larva";21;0
"Building";"SpawningPool";NA;19;0
"Building";"Hatchery";NA;17;0
"Unit";"Zergling";"Larva";22;1
"Unit";"Zergling";"Larva";22;1
"Unit";"Zergling";"Larva";23;1
"Unit";"Zergling";"Larva";23;1
"Unit";"Queen";"Hatchery";22;2
"Unit";"Queen";"Hatchery";23;2
"Building";"BanelingNest";NA;29;0
"Unit";"Overlord";"Larva";36;0
"Unit";"Zergling";"Larva";36;1
"Unit";"Zergling";"Larva";36;1
"Unit";"Baneling";"Zergling";39;0
"Unit";"Baneling";"Zergling";39;0
"Unit";"Baneling";"Zergling";39;0
"Unit";"Zergling";"Larva";41;1
"Unit";"Zergling";"Larva";41;1
"Unit";"Zergling";"Larva";41;1
"Unit";"Zergling";"Larva";41;1
"Unit";"Zergling";"Larva";41;1
"Unit";"Zergling";"Larva";41;1
"Unit";"Zergling";"Larva";41;1
"Unit";"Zergling";"Larva";41;1
"Unit";"Baneling";"Zergling";41;0
"Unit";"Zergling";"Larva";44;1
"Unit";"Zergling";"Larva";44;1
"Unit";"Zergling";"Larva";44;1
"Unit";"Zergling";"Larva";44;1
"Unit";"Baneling";"Zergling";44;0
"Unit";"Zergling";"Larva";44;1
"Unit";"Zergling";"Larva";44;1
"Building";"Hatchery";NA;36;0
"Unit";"Zergling";"Larva";56;1
"Unit";"Zergling";"Larva";56;1
"Unit";"Zergling";"Larva";56;1
"Unit";"Zergling";"Larva";56;1
"Unit";"Zergling";"Larva";56;1
"Unit";"Zergling";"Larva";56;1
"Unit";"Queen";"Hatchery";52;2
"Unit";"Zergling";"Larva";58;1
"Unit";"Zergling";"Larva";58;1
"Unit";"Zergling";"Larva";58;1
"Unit";"Zergling";"Larva";58;1
"Unit";"Zergling";"Larva";58;1
"Unit";"Zergling";"Larva";58;1
"Unit";"Zergling";"Larva";58;1
"Unit";"Zergling";"Larva";58;1
"Unit";"Zergling";"Larva";58;1
"Unit";"Zergling";"Larva";58;1
"Unit";"Zergling";"Larva";58;1
"Unit";"Zergling";"Larva";58;1
"Unit";"Zergling";"Larva";58;1
"Unit";"Zergling";"Larva";58;1
"Unit";"Zergling";"Larva";58;1
"Unit";"Zergling";"Larva";58;1
"Unit";"Zergling";"Larva";64;1
"Unit";"Zergling";"Larva";64;1
"Unit";"Zergling";"Larva";64;1
"Unit";"Zergling";"Larva";64;1
"Unit";"Baneling";"Zergling";68;0
"Unit";"Baneling";"Zergling";68;0
"Unit";"Baneling";"Zergling";70;0
"Unit";"Baneling";"Zergling";72;0
"Unit";"Baneling";"Zergling";74;0
"Unit";"Zergling";"Larva";78;1
"Unit";"Zergling";"Larva";78;1
"Unit";"Zergling";"Larva";78;1
"Unit";"Zergling";"Larva";78;1
"Unit";"Zergling";"Larva";82;1
"Unit";"Zergling";"Larva";82;1
"Unit";"Zergling";"Larva";84;1
"Unit";"Zergling";"Larva";84;1
"Unit";"Zergling";"Larva";86;1
"Unit";"Zergling";"Larva";86;1
"Unit";"Zergling";"Larva";86;1
"Unit";"Zergling";"Larva";86;1
"Unit";"Zergling";"Larva";90;1
"Unit";"Zergling";"Larva";90;1
"Unit";"Zergling";"Larva";90;1
"Unit";"Zergling";"Larva";90;1
"Unit";"Zergling";"Larva";94;1
"Unit";"Zergling";"Larva";94;1
"Unit";"Zergling";"Larva";94;1
"Unit";"Zergling";"Larva";94;1
"Unit";"Baneling";"Zergling";109;0
"Unit";"Baneling";"Zergling";109;0
"Unit";"Baneling";"Zergling";109;0
"Unit";"Zergling";"Larva";111;1
"Unit";"Zergling";"Larva";111;1
"Unit";"Zergling";"Larva";111;1
"Unit";"Zergling";"Larva";111;1
"Unit";"Baneling";"Zergling";111;0
"Unit";"Baneling";"Zergling";111;0
"Unit";"Baneling";"Zergling";111;0
"Unit";"Baneling";"Zergling";111;0
"Unit";"Zergling";"Larva";111;1
"Unit";"Zergling";"Larva";111;1
"Unit";"Zergling";"Larva";115;1
"Unit";"Zergling";"Larva";115;1
"Unit";"Zergling";"Larva";123;1
"Unit";"Zergling";"Larva";123;1
"Unit";"Zergling";"Larva";126;1
"Unit";"Zergling";"Larva";126;1
"Unit";"Zergling";"Larva";126;1
"Unit";"Zergling";"Larva";126;1
"Unit";"Zergling";"Larva";126;1
"Unit";"Zergling";"Larva";126;1
"Unit";"Zergling";"Larva";126;1
"Unit";"Zergling";"Larva";126;1
"Unit";"Zergling";"Larva";126;1
"Unit";"Zergling";"Larva";126;1
"Unit";"Zergling";"Larva";132;1
"Unit";"Zergling";"Larva";132;1
"Unit";"Zergling";"Larva";132;1
"Unit";"Zergling";"Larva";132;1
"Unit";"Zergling";"Larva";132;1
"Unit";"Zergling";"Larva";132;1
"Unit";"Zergling";"Larva";132;1
"Unit";"Zergling";"Larva";132;1
"Unit";"Zergling";"Larva";140;1
"Unit";"Zergling";"Larva";140;1
"Unit";"Zergling";"Larva";140;1
"Unit";"Zergling";"Larva";140;1
"Unit";"Zergling";"Larva";140;1
"Unit";"Zergling";"Larva";140;1
"Unit";"Baneling";"Zergling";148;0
"Unit";"Baneling";"Zergling";148;0
"Unit";"Zergling";"Larva";148;1
"Unit";"Zergling";"Larva";148;1
"Unit";"Baneling";"Zergling";148;0
"Unit";"Zergling";"Larva";152;1
"Unit";"Zergling";"Larva";152;1
"Unit";"Zergling";"Larva";154;1
"Unit";"Zergling";"Larva";154;1
"Unit";"Zergling";"Larva";154;1
"Unit";"Zergling";"Larva";154;1
"Unit";"Zergling";"Larva";154;1
"Unit";"Zergling";"Larva";154;1
"Unit";"Zergling";"Larva";154;1
"Unit";"Zergling";"Larva";154;1
"Unit";"Queen";"Hatchery";146;2
"Unit";"Zergling";"Larva";156;1
"Unit";"Zergling";"Larva";156;1
"Unit";"Zergling";"Larva";156;1
"Unit";"Zergling";"Larva";156;1
"Unit";"Zergling";"Larva";156;1
"Unit";"Zergling";"Larva";156;1
"Unit";"Zergling";"Larva";160;1
"Unit";"Zergling";"Larva";160;1
"Unit";"Zergling";"Larva";164;1
"Unit";"Zergling";"Larva";164;1
"Unit";"Zergling";"Larva";164;1
"Unit";"Zergling";"Larva";164;1
"Unit";"Zergling";"Larva";168;1
"Unit";"Zergling";"Larva";168;1
"Unit";"Zergling";"Larva";168;1
"Unit";"Zergling";"Larva";168;1
"Unit";"Zergling";"Larva";176;1
"Unit";"Zergling";"Larva";176;1
"Unit";"Zergling";"Larva";176;1
"Unit";"Zergling";"Larva";176;1
"Unit";"Zergling";"Larva";180;1
"Unit";"Zergling";"Larva";180;1
"Unit";"Zergling";"Larva";180;1
"Unit";"Zergling";"Larva";180;1
"Unit";"Zergling";"Larva";180;1
"Unit";"Zergling";"Larva";180;1
"Unit";"Baneling";"Zergling";184;0
"Unit";"Baneling";"Zergling";184;0
"Unit";"Baneling";"Zergling";184;0
"Unit";"Baneling";"Zergling";184;0
"Unit";"Baneling";"Zergling";184;0
"Unit";"Zergling";"Larva";184;1
"Unit";"Zergling";"Larva";184;1
"Unit";"Zergling";"Larva";184;1
"Unit";"Zergling";"Larva";184;1
"Unit";"Zergling";"Larva";192;1
"Unit";"Zergling";"Larva";192;1
"Unit";"Zergling";"Larva";192;1
"Unit";"Zergling";"Larva";192;1
"Unit";"Zergling";"Larva";194;1
"Unit";"Zergling";"Larva";194;1
"Unit";"Zergling";"Larva";194;1
"Unit";"Zergling";"Larva";194;1
"Unit";"Zergling";"Larva";194;1
"Unit";"Zergling";"Larva";194;1
"Unit";"Zergling";"Larva";198;1
"Unit";"Zergling";"Larva";198;1
"Unit";"Zergling";"Larva";198;1
"Unit";"Zergling";"Larva";198;1
"Unit";"Zergling";"Larva";198;1
"Unit";"Zergling";"Larva";198;1
"Unit";"Zergling";"Larva";202;1
"Unit";"Zergling";"Larva";202;1
"Unit";"Zergling";"Larva";202;1
"Unit";"Zergling";"Larva";202;1
"Unit";"Zergling";"Larva";206;1
"Unit";"Zergling";"Larva";206;1
"Unit";"Zergling";"Larva";214;1
"Unit";"Zergling";"Larva";214;1
"Unit";"Zergling";"Larva";214;1
"Unit";"Zergling";"Larva";214;1
"Unit";"Zergling";"Larva";214;1
"Unit";"Zergling";"Larva";214;1
"Unit";"Zergling";"Larva";214;1
"Unit";"Zergling";"Larva";214;1
"Unit";"Queen";"Hatchery";206;2
"Unit";"Zergling";"Larva";220;1
"Unit";"Zergling";"Larva";220;1
"Unit";"Zergling";"Larva";220;1
"Unit";"Zergling";"Larva";220;1
"Unit";"Zergling";"Larva";220;1
"Unit";"Zergling";"Larva";220;1
"Unit";"Zergling";"Larva";220;1
"Unit";"Zergling";"Larva";220;1
"Unit";"Zergling";"Larva";220;1
"Unit";"Zergling";"Larva";220;1
"Unit";"Zergling";"Larva";222;1
"Unit";"Zergling";"Larva";222;1
"Unit";"Baneling";"Zergling";226;0
"Unit";"Baneling";"Zergling";226;0
"Unit";"Baneling";"Zergling";226;0
"Unit";"Zergling";"Larva";228;1
"Unit";"Zergling";"Larva";228;1
"Unit";"Zergling";"Larva";228;1
"Unit";"Zergling";"Larva";228;1
"Unit";"Zergling";"Larva";228;1
"Unit";"Zergling";"Larva";228;1
"Unit";"Zergling";"Larva";238;1
"Unit";"Zergling";"Larva";238;1
