"type";"unit_name";"on_building";"total_supply";"supply"
"Unit";"Overlord";"Larva";12;0
"Building";"Extractor";NA;17;0
"Unit";"Overlord";"Larva";22;0
"Building";"Hatchery";NA;17;0
"Building";"SpawningPool";NA;20;0
"Unit";"Zergling";"Larva";22;1
"Unit";"Zergling";"Larva";22;1
"Unit";"Queen";"Hatchery";22;2
"Unit";"Queen";"Hatchery";22;2
"Unit";"Zergling";"Larva";34;1
"Unit";"Zergling";"Larva";34;1
"Unit";"Overlord";"Larva";36;0
"Building";"BanelingNest";NA;28;0
"Unit";"Zergling";"Larva";39;1
"Unit";"Zergling";"Larva";39;1
"Unit";"Zergling";"Larva";39;1
"Unit";"Zergling";"Larva";39;1
"Unit";"Zergling";"Larva";39;1
"Unit";"Zergling";"Larva";39;1
"Unit";"Baneling";"Zergling";45;0
"Unit";"Baneling";"Zergling";45;0
"Building";"SpineCrawler";NA;39;0
"Building";"Hatchery";NA;36;0
"Unit";"Zergling";"Larva";53;1
"Unit";"Zergling";"Larva";53;1
"Unit";"Overlord";"Larva";55;0
"Unit";"Zergling";"Larva";55;1
"Unit";"Zergling";"Larva";55;1
"Unit";"Zergling";"Larva";57;1
"Unit";"Zergling";"Larva";57;1
"Unit";"Zergling";"Larva";57;1
"Unit";"Zergling";"Larva";57;1
"Building";"EvolutionChamber";NA;57;0
"Building";"EvolutionChamber";NA;57;0
"Unit";"Overlord";"Larva";59;0
"Building";"SpineCrawler";NA;55;0
"Unit";"Baneling";"Zergling";66;0
"Building";"RoachWarren";NA;55;0
"Building";"Extractor";NA;72;0
"Building";"Extractor";NA;72;0
"Unit";"Overlord";"Larva";83;0
"Unit";"Queen";"Hatchery";72;2
"Unit";"Overlord";"Larva";83;0
"Unit";"Overlord";"Larva";86;0
"Unit";"Overlord";"Larva";86;0
"Unit";"Overlord";"Larva";91;0
"Unit";"Roach";"Larva";91;2
"Unit";"Roach";"Larva";91;2
"Unit";"Roach";"Larva";91;2
"Unit";"Roach";"Larva";91;2
"Unit";"Roach";"Larva";91;2
"Unit";"Roach";"Larva";91;2
"Unit";"Queen";"Hatchery";91;2
"Unit";"Roach";"Larva";91;2
"Unit";"Roach";"Larva";91;2
"Unit";"Overlord";"Larva";110;0
"Building";"Extractor";NA;110;0
"Building";"CreepTumorQueen";NA;110;0
"Upgrade";"ZergMissileWeaponsLevel1";"EvolutionChamber";89;0
"Unit";"Overlord";"Larva";110;0
"Building";"Extractor";NA;114;0
"Building";"Extractor";NA;114;0
"Unit";"Overlord";"Larva";114;0
"Unit";"Roach";"Larva";121;2
"Unit";"Roach";"Larva";121;2
"Unit";"Roach";"Larva";121;2
"Unit";"Roach";"Larva";122;2
"Building";"Hatchery";NA;92;0
"Upgrade";"GlialReconstitution";"RoachWarren";110;0
"Unit";"Queen";"Hatchery";117;2
"Unit";"Roach";"Larva";127;2
"Unit";"Roach";"Larva";127;2
"Unit";"Roach";"Larva";127;2
"Unit";"Roach";"Larva";127;2
"Unit";"Roach";"Larva";127;2
"Unit";"Roach";"Larva";127;2
"Unit";"Roach";"Larva";127;2
"Building";"CreepTumorQueen";NA;135;0
"Unit";"Overlord";"Larva";127;0
"Building";"CreepTumor";NA;135;0
"Unit";"Overlord";"Larva";135;0
"Unit";"Overlord";"Larva";135;0
"Building";"CreepTumorQueen";NA;151;0
"Unit";"Overlord";"Larva";151;0
"Building";"CreepTumor";NA;151;0
"Building";"CreepTumor";NA;151;0
"Unit";"Roach";"Larva";151;2
"Unit";"Roach";"Larva";151;2
"Building";"Hatchery";NA;118;0
"Unit";"Roach";"Larva";151;2
"Unit";"Roach";"Larva";152;2
"Unit";"Roach";"Larva";153;2
"Unit";"Roach";"Larva";154;2
"Unit";"Queen";"Hatchery";151;2
"Building";"Extractor";NA;154;0
"Building";"Extractor";NA;154;0
"Unit";"Overlord";"Larva";154;0
"Unit";"Overlord";"Larva";154;0
"Unit";"Overlord";"Larva";154;0
"Unit";"Overlord";"Larva";154;0
"Unit";"Overlord";"Larva";154;0
"Unit";"Overlord";"Larva";154;0
"Building";"CreepTumorQueen";NA;168;0
"Unit";"Overlord";"Larva";168;0
"Unit";"Roach";"Larva";168;2
"Unit";"Roach";"Larva";168;2
"Unit";"Roach";"Larva";168;2
"Building";"CreepTumor";NA;169;0
"Unit";"Roach";"Larva";168;2
"Unit";"Roach";"Larva";168;2
"Unit";"Roach";"Larva";168;2
"Unit";"Roach";"Larva";168;2
"Unit";"Roach";"Larva";168;2
"Unit";"Roach";"Larva";168;2
"Unit";"Roach";"Larva";168;2
"Unit";"Roach";"Larva";168;2
"Unit";"Roach";"Larva";168;2
"Unit";"Roach";"Larva";168;2
"Unit";"Roach";"Larva";168;2
"Unit";"Roach";"Larva";168;2
"Unit";"Roach";"Larva";168;2
"Unit";"Roach";"Larva";168;2
"Unit";"Roach";"Larva";168;2
"Unit";"Roach";"Larva";168;2
"Unit";"Roach";"Larva";168;2
"Building";"CreepTumor";NA;169;0
"Unit";"Roach";"Larva";169;2
"Unit";"Roach";"Larva";169;2
"Unit";"Roach";"Larva";169;2
"Upgrade";"ZergMissileWeaponsLevel2";"EvolutionChamber";151;0
"Unit";"Roach";"Larva";215;2
"Unit";"Roach";"Larva";215;2
"Unit";"Roach";"Larva";215;2
"Unit";"Roach";"Larva";215;2
"Unit";"Roach";"Larva";215;2
"Unit";"Roach";"Larva";215;2
"Unit";"Roach";"Larva";215;2
"Unit";"Roach";"Larva";215;2
"Unit";"Roach";"Larva";215;2
"Unit";"Overlord";"Larva";215;0
"Building";"CreepTumorQueen";NA;215;0
"Building";"CreepTumorQueen";NA;215;0
"Unit";"Overlord";"Larva";234;0
"Building";"SpineCrawler";NA;215;0
"Building";"SpineCrawler";NA;215;0
"Building";"CreepTumor";NA;234;0
"Building";"CreepTumor";NA;234;0
"Building";"Spire";NA;215;0
"Unit";"Mutalisk";"Larva";234;2
"Unit";"Mutalisk";"Larva";234;2
"Unit";"Mutalisk";"Larva";234;2
"Unit";"Mutalisk";"Larva";234;2
"Unit";"Mutalisk";"Larva";234;2
"Unit";"Mutalisk";"Larva";234;2
"Unit";"Mutalisk";"Larva";234;2
"Unit";"Mutalisk";"Larva";234;2
"Unit";"Mutalisk";"Larva";234;2
"Unit";"Mutalisk";"Larva";234;2
"Unit";"Roach";"Larva";234;2
"Unit";"Roach";"Larva";234;2
"Unit";"Mutalisk";"Larva";234;2
"Unit";"Roach";"Larva";234;2
"Unit";"Roach";"Larva";234;2
"Unit";"Roach";"Larva";234;2
"Unit";"Roach";"Larva";234;2
"Upgrade";"ZergGroundArmorsLevel1";"EvolutionChamber";234;0
"Unit";"Roach";"Larva";234;2
"Unit";"Roach";"Larva";234;2
"Unit";"Roach";"Larva";234;2
"Unit";"Roach";"Larva";234;2
"Unit";"Overlord";"Larva";234;0
"Unit";"Overlord";"Larva";234;0
"Unit";"Zergling";"Larva";268;1
"Unit";"Zergling";"Larva";268;1
"Unit";"Zergling";"Larva";268;1
"Unit";"Zergling";"Larva";268;1
"Unit";"Zergling";"Larva";268;1
"Unit";"Zergling";"Larva";268;1
"Unit";"Zergling";"Larva";268;1
"Unit";"Zergling";"Larva";268;1
"Unit";"Zergling";"Larva";268;1
"Unit";"Zergling";"Larva";268;1
"Unit";"Zergling";"Larva";268;1
"Unit";"Zergling";"Larva";268;1
"Unit";"Zergling";"Larva";268;1
"Unit";"Zergling";"Larva";268;1
"Unit";"Zergling";"Larva";268;1
"Unit";"Zergling";"Larva";268;1
"Unit";"Zergling";"Larva";268;1
"Unit";"Zergling";"Larva";268;1
"Unit";"Zergling";"Larva";268;1
"Unit";"Zergling";"Larva";268;1
"Unit";"Zergling";"Larva";268;1
"Unit";"Zergling";"Larva";268;1
"Unit";"Zergling";"Larva";268;1
"Unit";"Zergling";"Larva";268;1
"Unit";"Zergling";"Larva";268;1
"Unit";"Zergling";"Larva";268;1
"Unit";"Mutalisk";"Larva";264;2
"Unit";"Mutalisk";"Larva";264;2
"Building";"CreepTumor";NA;276;0
"Unit";"Overlord";"Larva";306;0
"Unit";"Roach";"Larva";306;2
"Unit";"Roach";"Larva";306;2
"Unit";"Roach";"Larva";306;2
"Unit";"Roach";"Larva";306;2
"Unit";"Roach";"Larva";306;2
"Unit";"Overlord";"Larva";306;0
"Unit";"Overlord";"Larva";306;0
"Unit";"Roach";"Larva";306;2
"Unit";"Roach";"Larva";306;2
"Unit";"Roach";"Larva";306;2
"Unit";"Roach";"Larva";306;2
"Unit";"Roach";"Larva";306;2
"Unit";"Roach";"Larva";306;2
"Unit";"Roach";"Larva";306;2
"Unit";"Roach";"Larva";306;2
"Unit";"Roach";"Larva";306;2
"Unit";"Roach";"Larva";306;2
"Unit";"Roach";"Larva";306;2
"Unit";"Roach";"Larva";306;2
"Unit";"Roach";"Larva";306;2
"Unit";"Zergling";"Larva";316;1
"Unit";"Zergling";"Larva";316;1
"Unit";"Zergling";"Larva";316;1
"Unit";"Zergling";"Larva";316;1
"Unit";"Zergling";"Larva";316;1
"Unit";"Zergling";"Larva";316;1
"Unit";"Zergling";"Larva";316;1
"Unit";"Zergling";"Larva";316;1
"Unit";"Zergling";"Larva";316;1
"Unit";"Zergling";"Larva";316;1
"Unit";"Zergling";"Larva";316;1
"Unit";"Zergling";"Larva";316;1
"Unit";"Zergling";"Larva";316;1
"Unit";"Zergling";"Larva";316;1
"Unit";"Zergling";"Larva";316;1
"Unit";"Zergling";"Larva";316;1
"Unit";"Zergling";"Larva";316;1
"Unit";"Zergling";"Larva";316;1
"Unit";"Zergling";"Larva";316;1
"Unit";"Zergling";"Larva";316;1
"Unit";"Zergling";"Larva";316;1
"Unit";"Zergling";"Larva";316;1
"Unit";"Zergling";"Larva";316;1
"Unit";"Zergling";"Larva";316;1
"Unit";"Roach";"Larva";342;2
"Unit";"Roach";"Larva";342;2
"Unit";"Roach";"Larva";342;2
"Unit";"Roach";"Larva";342;2
"Unit";"Roach";"Larva";374;2
"Unit";"Roach";"Larva";374;2
"Unit";"Roach";"Larva";374;2
"Unit";"Roach";"Larva";374;2
"Unit";"Roach";"Larva";374;2
"Unit";"Roach";"Larva";374;2
"Unit";"Roach";"Larva";374;2
"Unit";"Roach";"Larva";374;2
"Unit";"Roach";"Larva";374;2
"Unit";"Roach";"Larva";374;2
"Unit";"Roach";"Larva";374;2
"Unit";"Roach";"Larva";374;2
"Unit";"Roach";"Larva";374;2
"Unit";"Roach";"Larva";374;2
"Unit";"Roach";"Larva";374;2
"Unit";"Roach";"Larva";374;2
"Unit";"Roach";"Larva";374;2
"Unit";"Roach";"Larva";374;2
"Unit";"Roach";"Larva";374;2
"Unit";"Roach";"Larva";374;2
"Unit";"Roach";"Larva";374;2
"Unit";"Roach";"Larva";374;2
"Unit";"Roach";"Larva";374;2
"Unit";"Roach";"Larva";374;2
"Unit";"Roach";"Larva";374;2
"Unit";"Roach";"Larva";374;2
"Unit";"Roach";"Larva";374;2
"Unit";"Roach";"Larva";392;2
"Unit";"Roach";"Larva";392;2
"Unit";"Roach";"Larva";394;2
"Unit";"Roach";"Larva";398;2
"Unit";"Roach";"Larva";398;2
"Unit";"Roach";"Larva";428;2
"Unit";"Roach";"Larva";430;2
"Unit";"Roach";"Larva";430;2
"Building";"Hatchery";NA;366;0
"Unit";"Roach";"Larva";432;2
"Unit";"Roach";"Larva";434;2
"Unit";"Roach";"Larva";438;2
"Building";"CreepTumor";NA;442;0
"Unit";"Roach";"Larva";438;2
"Unit";"Roach";"Larva";438;2
"Unit";"Roach";"Larva";438;2
"Unit";"Roach";"Larva";438;2
"Unit";"Roach";"Larva";438;2
"Unit";"Roach";"Larva";438;2
"Unit";"Roach";"Larva";438;2
"Unit";"Roach";"Larva";438;2
"Unit";"Roach";"Larva";438;2
"Unit";"Roach";"Larva";438;2
"Unit";"Overlord";"Larva";448;0
"Unit";"Roach";"Larva";470;2
"Unit";"Roach";"Larva";470;2
"Building";"CreepTumor";NA;470;0
"Unit";"Roach";"Larva";474;2
"Unit";"Roach";"Larva";474;2
"Unit";"Roach";"Larva";474;2
"Unit";"Roach";"Larva";474;2
"Unit";"Roach";"Larva";474;2
"Unit";"Roach";"Larva";474;2
"Unit";"Roach";"Larva";474;2
"Unit";"Roach";"Larva";474;2
"Unit";"Roach";"Larva";474;2
"Unit";"Roach";"Larva";474;2
"Unit";"Roach";"Larva";474;2
"Unit";"Roach";"Larva";474;2
"Unit";"Roach";"Larva";474;2
"Unit";"Roach";"Larva";474;2
"Unit";"Roach";"Larva";474;2
"Unit";"Roach";"Larva";474;2
"Unit";"Roach";"Larva";474;2
"Unit";"Roach";"Larva";474;2
"Unit";"Roach";"Larva";474;2
"Unit";"Roach";"Larva";474;2
"Unit";"Roach";"Larva";474;2
"Unit";"Roach";"Larva";474;2
"Unit";"Roach";"Larva";474;2
"Unit";"Roach";"Larva";474;2
"Unit";"Roach";"Larva";474;2
"Unit";"Roach";"Larva";474;2
"Unit";"Roach";"Larva";475;2
"Unit";"Roach";"Larva";476;2
"Unit";"Roach";"Larva";476;2
"Unit";"Roach";"Larva";476;2
"Unit";"Roach";"Larva";476;2
"Unit";"Roach";"Larva";476;2
"Unit";"Roach";"Larva";476;2
"Unit";"Roach";"Larva";476;2
"Unit";"Roach";"Larva";476;2
"Unit";"Roach";"Larva";476;2
"Unit";"Roach";"Larva";476;2
"Unit";"Roach";"Larva";478;2
"Unit";"Roach";"Larva";478;2
"Unit";"Roach";"Larva";478;2
"Unit";"Roach";"Larva";484;2
"Unit";"Roach";"Larva";538;2
"Unit";"Roach";"Larva";538;2
"Unit";"Roach";"Larva";538;2
"Unit";"Roach";"Larva";538;2
"Unit";"Roach";"Larva";550;2
