"type";"unit_name";"on_building";"total_supply";"supply"
"Unit";"Overlord";"Larva";12;0
"Building";"Extractor";NA;18;0
"Unit";"Overlord";"Larva";21;0
"Building";"SpawningPool";NA;19;0
"Building";"Hatchery";NA;17;0
"Unit";"Zergling";"Larva";23;1
"Unit";"Zergling";"Larva";23;1
"Unit";"Zergling";"Larva";23;1
"Unit";"Zergling";"Larva";23;1
"Unit";"Queen";"Hatchery";23;2
"Unit";"Queen";"Hatchery";23;2
"Unit";"Overlord";"Larva";35;0
"Building";"CreepTumorQueen";NA;36;0
"Unit";"Queen";"Hatchery";35;2
"Unit";"Overlord";"Larva";39;0
"Building";"BanelingNest";NA;35;0
"Unit";"Zergling";"Larva";44;1
"Unit";"Zergling";"Larva";44;1
"Unit";"Zergling";"Larva";45;1
"Unit";"Zergling";"Larva";45;1
"Building";"Hatchery";NA;33;0
"Building";"CreepTumor";NA;49;0
"Building";"CreepTumorQueen";NA;49;0
"Unit";"Baneling";"Zergling";49;0
"Unit";"Baneling";"Zergling";49;0
"Unit";"Baneling";"Zergling";49;0
"Building";"EvolutionChamber";NA;47;0
"Unit";"Baneling";"Zergling";53;0
"Unit";"Baneling";"Zergling";53;0
"Unit";"Baneling";"Zergling";53;0
"Unit";"Overlord";"Larva";51;0
"Unit";"Zergling";"Larva";53;1
"Unit";"Zergling";"Larva";53;1
"Unit";"Zergling";"Larva";53;1
"Unit";"Zergling";"Larva";53;1
"Unit";"Baneling";"Zergling";56;0
"Unit";"Zergling";"Larva";56;1
"Unit";"Zergling";"Larva";56;1
"Unit";"Zergling";"Larva";56;1
"Unit";"Zergling";"Larva";56;1
"Unit";"Zergling";"Larva";56;1
"Unit";"Zergling";"Larva";56;1
"Unit";"Zergling";"Larva";56;1
"Unit";"Zergling";"Larva";56;1
"Unit";"Zergling";"Larva";60;1
"Unit";"Zergling";"Larva";60;1
"Unit";"Zergling";"Larva";60;1
"Unit";"Zergling";"Larva";60;1
"Unit";"Zergling";"Larva";60;1
"Unit";"Zergling";"Larva";60;1
"Unit";"Zergling";"Larva";60;1
"Unit";"Zergling";"Larva";60;1
"Unit";"Zergling";"Larva";60;1
"Unit";"Zergling";"Larva";60;1
"Unit";"Zergling";"Larva";60;1
"Unit";"Zergling";"Larva";60;1
"Unit";"Baneling";"Zergling";68;0
"Unit";"Zergling";"Larva";60;1
"Unit";"Zergling";"Larva";60;1
"Unit";"Baneling";"Zergling";68;0
"Unit";"Zergling";"Larva";60;1
"Unit";"Zergling";"Larva";60;1
"Unit";"Baneling";"Zergling";68;0
"Unit";"Baneling";"Zergling";68;0
"Building";"RoachWarren";NA;56;0
"Building";"Extractor";NA;68;0
"Building";"Extractor";NA;68;0
"Unit";"Overlord";"Larva";95;0
"Unit";"Overlord";"Larva";102;0
"Unit";"Overlord";"Larva";103;0
"Building";"CreepTumor";NA;103;0
"Building";"CreepTumor";NA;103;0
"Building";"CreepTumorQueen";NA;103;0
"Building";"Extractor";NA;103;0
"Unit";"Roach";"Larva";103;2
"Unit";"Roach";"Larva";103;2
"Unit";"Roach";"Larva";103;2
"Unit";"Roach";"Larva";103;2
"Unit";"Roach";"Larva";103;2
"Unit";"Roach";"Larva";103;2
"Unit";"Roach";"Larva";103;2
"Unit";"Roach";"Larva";103;2
"Unit";"Roach";"Larva";103;2
"Building";"CreepTumor";NA;103;0
"Building";"CreepTumor";NA;103;0
"Unit";"Queen";"Hatchery";103;2
"Unit";"Overlord";"Larva";103;0
"Unit";"Overlord";"Larva";103;0
"Unit";"Overlord";"Larva";124;0
"Unit";"Overlord";"Larva";124;0
"Unit";"Overlord";"Larva";129;0
"Building";"CreepTumor";NA;129;0
"Building";"Extractor";NA;126;0
"Building";"CreepTumor";NA;129;0
"Building";"CreepTumorQueen";NA;129;0
"Building";"HydraliskDen";NA;129;0
"Building";"EvolutionChamber";NA;134;0
"Upgrade";"ZergMissileWeaponsLevel1";"EvolutionChamber";103;0
"Building";"Extractor";NA;138;0
"Unit";"Roach";"Larva";138;2
"Unit";"Roach";"Larva";138;2
"Unit";"Roach";"Larva";138;2
"Unit";"Roach";"Larva";138;2
"Unit";"Roach";"Larva";138;2
"Unit";"Roach";"Larva";138;2
"Unit";"Roach";"Larva";138;2
"Unit";"Roach";"Larva";138;2
"Unit";"Roach";"Larva";138;2
"Unit";"Roach";"Larva";138;2
"Unit";"Roach";"Larva";138;2
"Unit";"Roach";"Larva";138;2
"Unit";"Roach";"Larva";138;2
"Unit";"Overlord";"Larva";163;0
"Unit";"Overlord";"Larva";163;0
"Upgrade";"GlialReconstitution";"RoachWarren";138;0
"Building";"CreepTumor";NA;167;0
"Unit";"Roach";"Larva";163;2
"Unit";"Roach";"Larva";163;2
"Unit";"Roach";"Larva";163;2
"Unit";"Roach";"Larva";165;2
"Unit";"Roach";"Larva";167;2
"Building";"CreepTumor";NA;168;0
"Building";"CreepTumor";NA;168;0
"Unit";"Hydralisk";"Larva";163;2
"Unit";"Hydralisk";"Larva";163;2
"Unit";"Hydralisk";"Larva";163;2
"Unit";"Overlord";"Larva";168;0
"Unit";"Roach";"Larva";184;2
"Unit";"Roach";"Larva";184;2
"Unit";"Roach";"Larva";184;2
"Unit";"Roach";"Larva";184;2
"Unit";"Roach";"Larva";184;2
"Unit";"Overlord";"Larva";187;0
"Unit";"Overlord";"Larva";187;0
"Unit";"Overlord";"Larva";187;0
"Unit";"Roach";"Larva";187;2
"Unit";"Roach";"Larva";187;2
"Unit";"Roach";"Larva";187;2
"Unit";"Roach";"Larva";187;2
"Unit";"Overlord";"Larva";197;0
"Unit";"Overlord";"Larva";197;0
"Unit";"Roach";"Larva";197;2
"Unit";"Roach";"Larva";205;2
"Unit";"Roach";"Larva";205;2
"Unit";"Roach";"Larva";205;2
"Unit";"Roach";"Larva";205;2
"Unit";"Roach";"Larva";205;2
"Unit";"Roach";"Larva";205;2
"Unit";"Roach";"Larva";205;2
"Unit";"Roach";"Larva";205;2
"Unit";"Roach";"Larva";205;2
"Unit";"Roach";"Larva";205;2
"Unit";"Roach";"Larva";205;2
"Unit";"Roach";"Larva";205;2
"Upgrade";"ZergGroundArmorsLevel1";"EvolutionChamber";167;0
"Unit";"Roach";"Larva";205;2
"Unit";"Roach";"Larva";205;2
"Unit";"Roach";"Larva";205;2
"Upgrade";"EvolveGroovedSpines";"HydraliskDen";187;0
"Unit";"Roach";"Larva";205;2
"Unit";"Roach";"Larva";229;2
"Unit";"Roach";"Larva";231;2
"Building";"Hatchery";NA;187;0
"Unit";"Roach";"Larva";231;2
"Unit";"Roach";"Larva";237;2
"Unit";"Roach";"Larva";237;2
"Upgrade";"ZergMissileWeaponsLevel2";"EvolutionChamber";184;0
"Unit";"Queen";"Hatchery";231;2
"Unit";"Roach";"Larva";243;2
"Unit";"Roach";"Larva";243;2
"Unit";"Roach";"Larva";243;2
"Unit";"Roach";"Larva";243;2
"Unit";"Roach";"Larva";243;2
"Unit";"Roach";"Larva";243;2
"Building";"CreepTumor";NA;249;0
"Unit";"Hydralisk";"Larva";251;2
"Unit";"Hydralisk";"Larva";251;2
"Unit";"Hydralisk";"Larva";251;2
"Unit";"Hydralisk";"Larva";251;2
"Unit";"Hydralisk";"Larva";251;2
"Unit";"Hydralisk";"Larva";251;2
"Unit";"Hydralisk";"Larva";251;2
"Unit";"Roach";"Larva";267;2
"Unit";"Roach";"Larva";267;2
"Unit";"Roach";"Larva";267;2
"Unit";"Queen";"Hatchery";249;2
"Unit";"Roach";"Larva";267;2
"Unit";"Roach";"Larva";267;2
"Unit";"Roach";"Larva";267;2
"Unit";"Roach";"Larva";267;2
"Unit";"Roach";"Larva";267;2
