"type";"unit_name";"on_building";"total_supply";"supply"
"Unit";"Overlord";"Larva";12;0
"Building";"Extractor";NA;17;0
"Unit";"Overlord";"Larva";22;0
"Building";"SpawningPool";NA;19;0
"Building";"Hatchery";NA;17;0
"Unit";"Zergling";"Larva";23;1
"Unit";"Zergling";"Larva";23;1
"Unit";"Queen";"Hatchery";22;2
"Unit";"Queen";"Hatchery";22;2
"Unit";"Zergling";"Larva";28;1
"Unit";"Zergling";"Larva";28;1
"Unit";"Zergling";"Larva";30;1
"Unit";"Zergling";"Larva";30;1
"Unit";"Overlord";"Larva";34;0
"Building";"BanelingNest";NA;26;0
"Unit";"Queen";"Hatchery";28;2
"Unit";"Overlord";"Larva";51;0
"Unit";"Baneling";"Zergling";51;0
"Building";"Extractor";NA;50;0
"Building";"Extractor";NA;51;0
"Building";"Extractor";NA;51;0
"Unit";"Zergling";"Larva";51;1
"Unit";"Zergling";"Larva";51;1
"Unit";"Zergling";"Larva";51;1
"Unit";"Zergling";"Larva";51;1
"Unit";"Zergling";"Larva";51;1
"Unit";"Zergling";"Larva";51;1
"Unit";"Zergling";"Larva";51;1
"Unit";"Zergling";"Larva";51;1
"Unit";"Baneling";"Zergling";55;0
"Unit";"Overlord";"Larva";63;0
"Unit";"Overlord";"Larva";63;0
"Unit";"Overlord";"Larva";67;0
"Unit";"Overlord";"Larva";72;0
"Unit";"Overlord";"Larva";73;0
"Unit";"Overlord";"Larva";73;0
"Building";"Hatchery";NA;63;0
"Building";"Extractor";NA;73;0
"Building";"Spire";NA;67;0
"Building";"Extractor";NA;73;0
"Unit";"Mutalisk";"Larva";75;2
"Unit";"Mutalisk";"Larva";75;2
"Unit";"Mutalisk";"Larva";75;2
"Unit";"Mutalisk";"Larva";75;2
"Unit";"Mutalisk";"Larva";75;2
"Unit";"Mutalisk";"Larva";75;2
"Unit";"Mutalisk";"Larva";75;2
"Unit";"Mutalisk";"Larva";75;2
"Unit";"Zergling";"Larva";75;1
"Unit";"Zergling";"Larva";75;1
"Unit";"Zergling";"Larva";75;1
"Unit";"Zergling";"Larva";75;1
"Unit";"Zergling";"Larva";75;1
"Unit";"Zergling";"Larva";75;1
"Unit";"Zergling";"Larva";75;1
"Unit";"Zergling";"Larva";75;1
"Unit";"Zergling";"Larva";75;1
"Unit";"Zergling";"Larva";75;1
"Unit";"Zergling";"Larva";75;1
"Unit";"Zergling";"Larva";75;1
"Unit";"Mutalisk";"Larva";75;2
"Unit";"Mutalisk";"Larva";75;2
"Unit";"Overlord";"Larva";75;0
"Unit";"Overlord";"Larva";75;0
"Building";"EvolutionChamber";NA;110;0
"Building";"InfestationPit";NA;113;0
"Unit";"Mutalisk";"Larva";127;2
"Unit";"Mutalisk";"Larva";127;2
"Unit";"Mutalisk";"Larva";127;2
"Unit";"Mutalisk";"Larva";127;2
"Unit";"Mutalisk";"Larva";127;2
"Unit";"Mutalisk";"Larva";127;2
"Unit";"Mutalisk";"Larva";127;2
"Unit";"Overlord";"Larva";141;0
"Unit";"Overlord";"Larva";141;0
"Unit";"Overlord";"Larva";141;0
"Unit";"Overlord";"Larva";141;0
"Unit";"Overlord";"Larva";141;0
"Unit";"Zergling";"Larva";141;1
"Unit";"Zergling";"Larva";141;1
"Unit";"Zergling";"Larva";141;1
"Unit";"Zergling";"Larva";141;1
"Unit";"Zergling";"Larva";141;1
"Unit";"Zergling";"Larva";141;1
"Unit";"Zergling";"Larva";141;1
"Unit";"Zergling";"Larva";141;1
"Unit";"Zergling";"Larva";141;1
"Unit";"Zergling";"Larva";141;1
"Unit";"Zergling";"Larva";141;1
"Unit";"Zergling";"Larva";141;1
"Unit";"Zergling";"Larva";141;1
"Unit";"Zergling";"Larva";141;1
"Unit";"Zergling";"Larva";141;1
"Unit";"Zergling";"Larva";141;1
"Unit";"Zergling";"Larva";141;1
"Unit";"Zergling";"Larva";141;1
"Unit";"Zergling";"Larva";141;1
"Unit";"Zergling";"Larva";141;1
"Unit";"Zergling";"Larva";141;1
"Unit";"Zergling";"Larva";141;1
"Unit";"Baneling";"Zergling";141;0
"Unit";"Baneling";"Zergling";141;0
"Unit";"Baneling";"Zergling";141;0
"Building";"Hatchery";NA;127;0
"Building";"Extractor";NA;163;0
"Building";"Extractor";NA;163;0
"Unit";"Overlord";"Larva";163;0
"Unit";"Overlord";"Larva";163;0
"Unit";"Overlord";"Larva";163;0
"Unit";"Baneling";"Zergling";164;0
"Unit";"Baneling";"Zergling";164;0
"Unit";"Baneling";"Zergling";164;0
"Unit";"Baneling";"Zergling";164;0
"Unit";"Zergling";"Larva";163;1
"Unit";"Zergling";"Larva";163;1
"Unit";"Zergling";"Larva";163;1
"Unit";"Zergling";"Larva";163;1
"Unit";"Zergling";"Larva";163;1
"Unit";"Zergling";"Larva";163;1
"Unit";"Zergling";"Larva";163;1
"Unit";"Zergling";"Larva";163;1
"Unit";"Zergling";"Larva";163;1
"Unit";"Zergling";"Larva";163;1
"Upgrade";"ZergMeleeWeaponsLevel1";"EvolutionChamber";141;0
"Building";"UltraliskCavern";NA;163;0
"Building";"EvolutionChamber";NA;180;0
"Unit";"Viper";"Larva";180;3
"Unit";"Viper";"Larva";180;3
"Unit";"Viper";"Larva";180;3
"Upgrade";"Burrow";"Hatchery";180;0
"Unit";"Ultralisk";"Larva";180;6
"Unit";"Ultralisk";"Larva";180;6
"Unit";"Ultralisk";"Larva";180;6
"Unit";"Overlord";"Larva";189;0
"Unit";"Overlord";"Larva";189;0
"Unit";"Overlord";"Larva";189;0
"Unit";"Ultralisk";"Larva";180;6
"Unit";"Ultralisk";"Larva";183;6
"Unit";"Viper";"Larva";207;3
"Unit";"Ultralisk";"Larva";189;6
"Upgrade";"ChitinousPlating";"UltraliskCavern";189;0
"Building";"Hatchery";NA;180;0
"Upgrade";"ZergMeleeWeaponsLevel2";"EvolutionChamber";180;0
"Unit";"Ultralisk";"Larva";228;6
"Unit";"Ultralisk";"Larva";228;6
"Unit";"Ultralisk";"Larva";228;6
"Building";"Extractor";NA;231;0
"Building";"Extractor";NA;231;0
"Unit";"Ultralisk";"Larva";228;6
"Unit";"Ultralisk";"Larva";228;6
"Upgrade";"ZergGroundArmorsLevel1";"EvolutionChamber";207;0
"Unit";"Ultralisk";"Larva";231;6
"Unit";"Corruptor";"Larva";267;2
"Unit";"Corruptor";"Larva";267;2
"Unit";"Corruptor";"Larva";267;2
"Unit";"Corruptor";"Larva";267;2
"Unit";"Corruptor";"Larva";267;2
"Unit";"Corruptor";"Larva";267;2
"Building";"SpineCrawler";NA;279;0
