"type";"unit_name";"on_building";"total_supply";"supply"
"Unit";"Overlord";"Larva";12;0
"Building";"Extractor";NA;17;0
"Unit";"Overlord";"Larva";21;0
"Building";"SpawningPool";NA;19;0
"Building";"Hatchery";NA;17;0
"Unit";"Zergling";"Larva";22;1
"Unit";"Zergling";"Larva";22;1
"Unit";"Zergling";"Larva";23;1
"Unit";"Zergling";"Larva";23;1
"Unit";"Queen";"Hatchery";22;2
"Unit";"Queen";"Hatchery";23;2
"Unit";"Overlord";"Larva";35;0
"Unit";"Queen";"Hatchery";32;2
"Unit";"Overlord";"Larva";39;0
"Building";"CreepTumorQueen";NA;41;0
"Unit";"Overlord";"Larva";49;0
"Building";"CreepTumorQueen";NA;49;0
"Building";"CreepTumor";NA;49;0
"Unit";"Overlord";"Larva";49;0
"Unit";"Zergling";"Larva";54;1
"Unit";"Zergling";"Larva";54;1
"Unit";"Zergling";"Larva";54;1
"Unit";"Zergling";"Larva";54;1
"Unit";"Zergling";"Larva";54;1
"Unit";"Zergling";"Larva";54;1
"Unit";"Zergling";"Larva";54;1
"Unit";"Zergling";"Larva";54;1
"Unit";"Zergling";"Larva";54;1
"Unit";"Zergling";"Larva";54;1
"Unit";"Zergling";"Larva";54;1
"Unit";"Zergling";"Larva";54;1
"Unit";"Queen";"Hatchery";49;2
"Building";"EvolutionChamber";NA;54;0
"Building";"EvolutionChamber";NA;54;0
"Unit";"Queen";"Hatchery";49;2
"Unit";"Zergling";"Larva";60;1
"Unit";"Zergling";"Larva";60;1
"Unit";"Zergling";"Larva";60;1
"Unit";"Zergling";"Larva";60;1
"Unit";"Zergling";"Larva";60;1
"Unit";"Zergling";"Larva";60;1
"Unit";"Zergling";"Larva";60;1
"Unit";"Zergling";"Larva";60;1
"Unit";"Zergling";"Larva";62;1
"Unit";"Zergling";"Larva";62;1
"Unit";"Zergling";"Larva";62;1
"Unit";"Zergling";"Larva";62;1
"Building";"CreepTumor";NA;70;0
"Unit";"Overlord";"Larva";68;0
"Building";"CreepTumor";NA;70;0
"Building";"Hatchery";NA;49;0
"Building";"CreepTumorQueen";NA;70;0
"Building";"CreepTumorQueen";NA;72;0
"Building";"CreepTumorQueen";NA;84;0
"Unit";"Zergling";"Larva";84;1
"Unit";"Zergling";"Larva";84;1
"Unit";"Zergling";"Larva";84;1
"Unit";"Zergling";"Larva";84;1
"Unit";"Zergling";"Larva";84;1
"Unit";"Zergling";"Larva";84;1
"Unit";"Zergling";"Larva";84;1
"Unit";"Zergling";"Larva";84;1
"Unit";"Zergling";"Larva";84;1
"Unit";"Zergling";"Larva";84;1
"Unit";"Queen";"Hatchery";70;2
"Unit";"Overlord";"Larva";84;0
"Unit";"Overlord";"Larva";84;0
"Unit";"Queen";"Hatchery";84;2
"Building";"Extractor";NA;84;0
"Building";"Extractor";NA;84;0
"Building";"CreepTumor";NA;96;0
"Unit";"Zergling";"Larva";108;1
"Unit";"Zergling";"Larva";108;1
"Unit";"Zergling";"Larva";108;1
"Unit";"Zergling";"Larva";108;1
"Unit";"Zergling";"Larva";108;1
"Unit";"Zergling";"Larva";108;1
"Unit";"Zergling";"Larva";108;1
"Unit";"Zergling";"Larva";108;1
"Unit";"Zergling";"Larva";108;1
"Unit";"Zergling";"Larva";108;1
"Building";"CreepTumorQueen";NA;108;0
"Building";"CreepTumorQueen";NA;108;0
"Unit";"Queen";"Hatchery";98;2
"Building";"CreepTumor";NA;118;0
"Unit";"Overlord";"Larva";108;0
"Building";"CreepTumorQueen";NA;118;0
"Unit";"Overlord";"Larva";118;0
"Unit";"Overlord";"Larva";118;0
"Building";"BanelingNest";NA;108;0
"Unit";"Overlord";"Larva";118;0
"Unit";"Overlord";"Larva";122;0
"Unit";"Overlord";"Larva";122;0
"Unit";"Overlord";"Larva";124;0
"Building";"CreepTumor";NA;124;0
"Building";"CreepTumor";NA;124;0
"Upgrade";"ZergGroundArmorsLevel1";"EvolutionChamber";94;0
"Building";"CreepTumorQueen";NA;129;0
"Upgrade";"ZergMeleeWeaponsLevel1";"EvolutionChamber";96;0
"Unit";"Zergling";"Larva";129;1
"Unit";"Zergling";"Larva";129;1
"Unit";"Zergling";"Larva";129;1
"Unit";"Zergling";"Larva";129;1
"Unit";"Zergling";"Larva";129;1
"Unit";"Zergling";"Larva";129;1
"Unit";"Zergling";"Larva";129;1
"Unit";"Zergling";"Larva";129;1
"Unit";"Zergling";"Larva";129;1
"Unit";"Zergling";"Larva";129;1
"Unit";"Zergling";"Larva";129;1
"Unit";"Zergling";"Larva";129;1
"Unit";"Zergling";"Larva";129;1
"Unit";"Zergling";"Larva";129;1
"Unit";"Zergling";"Larva";129;1
"Unit";"Zergling";"Larva";129;1
"Unit";"Zergling";"Larva";129;1
"Unit";"Zergling";"Larva";129;1
"Unit";"Zergling";"Larva";129;1
"Unit";"Zergling";"Larva";129;1
"Unit";"Zergling";"Larva";129;1
"Unit";"Zergling";"Larva";129;1
"Unit";"Zergling";"Larva";129;1
"Unit";"Zergling";"Larva";129;1
"Building";"SporeCrawler";NA;129;0
"Unit";"Zergling";"Larva";147;1
"Unit";"Zergling";"Larva";147;1
"Unit";"Zergling";"Larva";147;1
"Unit";"Zergling";"Larva";147;1
"Unit";"Zergling";"Larva";147;1
"Unit";"Zergling";"Larva";147;1
"Unit";"Zergling";"Larva";147;1
"Unit";"Zergling";"Larva";147;1
"Unit";"Zergling";"Larva";147;1
"Unit";"Zergling";"Larva";147;1
"Building";"CreepTumor";NA;147;0
"Building";"Extractor";NA;147;0
"Unit";"Overlord";"Larva";153;0
"Unit";"Overlord";"Larva";153;0
"Building";"CreepTumorQueen";NA;166;0
"Unit";"Zergling";"Larva";166;1
"Unit";"Zergling";"Larva";166;1
"Unit";"Zergling";"Larva";166;1
"Unit";"Zergling";"Larva";166;1
"Unit";"Zergling";"Larva";166;1
"Unit";"Zergling";"Larva";166;1
"Unit";"Zergling";"Larva";166;1
"Unit";"Zergling";"Larva";166;1
"Unit";"Zergling";"Larva";166;1
"Unit";"Zergling";"Larva";166;1
"Unit";"Zergling";"Larva";166;1
"Unit";"Zergling";"Larva";166;1
"Unit";"Zergling";"Larva";166;1
"Unit";"Zergling";"Larva";166;1
"Unit";"Zergling";"Larva";166;1
"Unit";"Zergling";"Larva";166;1
"Unit";"Zergling";"Larva";166;1
"Unit";"Zergling";"Larva";166;1
"Unit";"Zergling";"Larva";166;1
"Unit";"Zergling";"Larva";166;1
"Unit";"Baneling";"Zergling";168;0
"Unit";"Baneling";"Zergling";168;0
"Unit";"Baneling";"Zergling";168;0
"Unit";"Baneling";"Zergling";168;0
"Unit";"Baneling";"Zergling";168;0
"Unit";"Baneling";"Zergling";168;0
"Unit";"Baneling";"Zergling";172;0
"Unit";"Baneling";"Zergling";172;0
"Unit";"Baneling";"Zergling";172;0
"Unit";"Baneling";"Zergling";174;0
"Building";"CreepTumor";NA;186;0
"Unit";"Zergling";"Larva";186;1
"Unit";"Zergling";"Larva";186;1
"Unit";"Zergling";"Larva";186;1
"Unit";"Zergling";"Larva";186;1
"Unit";"Zergling";"Larva";186;1
"Unit";"Zergling";"Larva";186;1
"Unit";"Zergling";"Larva";186;1
"Unit";"Zergling";"Larva";186;1
"Unit";"Zergling";"Larva";186;1
"Unit";"Zergling";"Larva";186;1
"Unit";"Zergling";"Larva";186;1
"Unit";"Zergling";"Larva";186;1
"Unit";"Zergling";"Larva";186;1
"Unit";"Zergling";"Larva";186;1
"Unit";"Zergling";"Larva";186;1
"Unit";"Zergling";"Larva";186;1
"Unit";"Baneling";"Zergling";186;0
"Unit";"Baneling";"Zergling";186;0
"Unit";"Baneling";"Zergling";186;0
"Unit";"Overlord";"Larva";186;0
"Building";"Extractor";NA;202;0
"Unit";"Zergling";"Larva";209;1
"Unit";"Zergling";"Larva";209;1
"Unit";"Zergling";"Larva";209;1
"Unit";"Zergling";"Larva";209;1
"Unit";"Zergling";"Larva";209;1
"Unit";"Zergling";"Larva";209;1
"Unit";"Zergling";"Larva";209;1
"Unit";"Zergling";"Larva";209;1
"Unit";"Zergling";"Larva";209;1
"Unit";"Zergling";"Larva";209;1
"Unit";"Zergling";"Larva";209;1
"Unit";"Zergling";"Larva";209;1
"Unit";"Zergling";"Larva";209;1
"Unit";"Zergling";"Larva";209;1
"Unit";"Zergling";"Larva";209;1
"Unit";"Zergling";"Larva";209;1
"Unit";"Zergling";"Larva";209;1
"Unit";"Zergling";"Larva";209;1
"Unit";"Zergling";"Larva";209;1
"Unit";"Zergling";"Larva";209;1
"Unit";"Zergling";"Larva";209;1
"Unit";"Zergling";"Larva";209;1
"Unit";"Zergling";"Larva";209;1
"Unit";"Zergling";"Larva";209;1
"Unit";"Zergling";"Larva";209;1
"Unit";"Zergling";"Larva";209;1
"Unit";"Zergling";"Larva";209;1
"Unit";"Zergling";"Larva";209;1
"Building";"Extractor";NA;209;0
"Unit";"Zergling";"Larva";230;1
"Unit";"Zergling";"Larva";230;1
"Unit";"Zergling";"Larva";238;1
"Unit";"Zergling";"Larva";238;1
"Unit";"Zergling";"Larva";238;1
"Unit";"Zergling";"Larva";238;1
"Unit";"Zergling";"Larva";238;1
"Unit";"Zergling";"Larva";238;1
"Unit";"Zergling";"Larva";238;1
"Unit";"Zergling";"Larva";238;1
"Building";"CreepTumorQueen";NA;238;0
"Building";"CreepTumorQueen";NA;238;0
"Building";"Hatchery";NA;186;0
"Unit";"Baneling";"Zergling";248;0
"Unit";"Baneling";"Zergling";248;0
"Unit";"Baneling";"Zergling";248;0
"Unit";"Baneling";"Zergling";248;0
"Unit";"Baneling";"Zergling";248;0
"Unit";"Baneling";"Zergling";248;0
"Unit";"Baneling";"Zergling";248;0
"Unit";"Baneling";"Zergling";248;0
"Unit";"Baneling";"Zergling";248;0
"Unit";"Baneling";"Zergling";248;0
"Unit";"Baneling";"Zergling";248;0
"Unit";"Baneling";"Zergling";248;0
"Unit";"Baneling";"Zergling";248;0
"Building";"CreepTumorQueen";NA;248;0
"Unit";"Zergling";"Larva";248;1
"Unit";"Zergling";"Larva";248;1
"Upgrade";"ZergGroundArmorsLevel2";"EvolutionChamber";186;0
"Unit";"Zergling";"Larva";248;1
"Unit";"Zergling";"Larva";248;1
"Unit";"Zergling";"Larva";248;1
"Unit";"Zergling";"Larva";248;1
"Unit";"Zergling";"Larva";248;1
"Unit";"Zergling";"Larva";248;1
"Unit";"Zergling";"Larva";248;1
"Unit";"Zergling";"Larva";248;1
"Upgrade";"ZergMeleeWeaponsLevel2";"EvolutionChamber";186;0
"Unit";"Zergling";"Larva";248;1
"Unit";"Zergling";"Larva";248;1
"Unit";"Zergling";"Larva";248;1
"Unit";"Zergling";"Larva";248;1
"Unit";"Zergling";"Larva";248;1
"Unit";"Zergling";"Larva";248;1
"Unit";"Zergling";"Larva";248;1
"Unit";"Zergling";"Larva";248;1
"Unit";"Zergling";"Larva";248;1
"Unit";"Zergling";"Larva";248;1
"Building";"CreepTumorQueen";NA;248;0
"Building";"CreepTumorQueen";NA;248;0
"Building";"CreepTumor";NA;248;0
"Unit";"Baneling";"Zergling";248;0
"Unit";"Baneling";"Zergling";248;0
"Unit";"Baneling";"Zergling";248;0
"Unit";"Baneling";"Zergling";248;0
"Unit";"Baneling";"Zergling";248;0
"Unit";"Baneling";"Zergling";248;0
"Unit";"Baneling";"Zergling";248;0
"Building";"SporeCrawler";NA;248;0
"Building";"SporeCrawler";NA;248;0
"Unit";"Zergling";"Larva";268;1
"Unit";"Zergling";"Larva";268;1
"Building";"SporeCrawler";NA;248;0
"Unit";"Zergling";"Larva";268;1
"Unit";"Zergling";"Larva";268;1
"Unit";"Zergling";"Larva";268;1
"Unit";"Zergling";"Larva";268;1
"Unit";"Zergling";"Larva";268;1
"Unit";"Zergling";"Larva";268;1
"Unit";"Zergling";"Larva";268;1
"Unit";"Zergling";"Larva";268;1
"Unit";"Zergling";"Larva";268;1
"Unit";"Zergling";"Larva";268;1
"Unit";"Zergling";"Larva";268;1
"Unit";"Zergling";"Larva";268;1
"Unit";"Zergling";"Larva";268;1
"Unit";"Zergling";"Larva";268;1
"Unit";"Zergling";"Larva";268;1
"Unit";"Zergling";"Larva";268;1
"Unit";"Zergling";"Larva";268;1
"Unit";"Zergling";"Larva";268;1
"Unit";"Zergling";"Larva";268;1
"Unit";"Zergling";"Larva";268;1
"Building";"Hatchery";NA;227;0
"Unit";"Queen";"Hatchery";248;2
"Building";"CreepTumor";NA;270;0
"Building";"CreepTumor";NA;278;0
"Building";"CreepTumor";NA;286;0
"Unit";"Zergling";"Larva";268;1
"Unit";"Zergling";"Larva";268;1
"Unit";"Zergling";"Larva";268;1
"Unit";"Zergling";"Larva";268;1
"Unit";"Zergling";"Larva";268;1
"Unit";"Zergling";"Larva";268;1
"Unit";"Zergling";"Larva";268;1
"Unit";"Zergling";"Larva";268;1
"Unit";"Zergling";"Larva";268;1
"Unit";"Zergling";"Larva";268;1
"Unit";"Zergling";"Larva";268;1
"Unit";"Zergling";"Larva";268;1
"Unit";"Zergling";"Larva";268;1
"Unit";"Zergling";"Larva";268;1
"Building";"CreepTumor";NA;290;0
"Building";"CreepTumor";NA;290;0
"Unit";"Queen";"Hatchery";268;2
"Unit";"Zergling";"Larva";292;1
"Unit";"Zergling";"Larva";292;1
"Unit";"Zergling";"Larva";292;1
"Unit";"Zergling";"Larva";292;1
"Unit";"Zergling";"Larva";292;1
"Unit";"Zergling";"Larva";292;1
"Unit";"Zergling";"Larva";292;1
"Unit";"Zergling";"Larva";292;1
"Unit";"Zergling";"Larva";292;1
"Unit";"Zergling";"Larva";292;1
"Unit";"Zergling";"Larva";292;1
"Unit";"Zergling";"Larva";292;1
"Unit";"Zergling";"Larva";292;1
"Unit";"Zergling";"Larva";292;1
"Unit";"Zergling";"Larva";306;1
"Unit";"Zergling";"Larva";306;1
"Unit";"Zergling";"Larva";306;1
"Unit";"Zergling";"Larva";306;1
"Unit";"Zergling";"Larva";306;1
"Unit";"Zergling";"Larva";306;1
"Unit";"Zergling";"Larva";306;1
"Unit";"Zergling";"Larva";306;1
"Unit";"Zergling";"Larva";322;1
"Unit";"Zergling";"Larva";322;1
"Unit";"Zergling";"Larva";322;1
"Unit";"Zergling";"Larva";322;1
"Unit";"Zergling";"Larva";322;1
"Unit";"Zergling";"Larva";322;1
"Unit";"Zergling";"Larva";322;1
"Unit";"Zergling";"Larva";322;1
"Unit";"Zergling";"Larva";322;1
"Unit";"Zergling";"Larva";322;1
"Unit";"Zergling";"Larva";322;1
"Unit";"Zergling";"Larva";322;1
"Unit";"Zergling";"Larva";322;1
"Unit";"Zergling";"Larva";322;1
"Unit";"Zergling";"Larva";322;1
"Unit";"Zergling";"Larva";322;1
"Unit";"Baneling";"Zergling";322;0
"Unit";"Baneling";"Zergling";322;0
"Unit";"Baneling";"Zergling";322;0
"Unit";"Baneling";"Zergling";322;0
"Unit";"Baneling";"Zergling";322;0
"Unit";"Baneling";"Zergling";322;0
"Unit";"Baneling";"Zergling";322;0
"Unit";"Baneling";"Zergling";322;0
"Unit";"Baneling";"Zergling";322;0
"Unit";"Baneling";"Zergling";322;0
"Unit";"Queen";"Hatchery";292;2
"Unit";"Queen";"Hatchery";292;2
"Building";"InfestationPit";NA;306;0
"Unit";"Overlord";"Larva";330;0
"Building";"CreepTumor";NA;330;0
"Building";"CreepTumor";NA;330;0
"Unit";"Zergling";"Larva";350;1
"Unit";"Zergling";"Larva";350;1
"Unit";"Zergling";"Larva";350;1
"Unit";"Zergling";"Larva";350;1
"Unit";"Zergling";"Larva";350;1
"Unit";"Zergling";"Larva";350;1
"Unit";"Zergling";"Larva";350;1
"Unit";"Zergling";"Larva";350;1
"Unit";"Zergling";"Larva";350;1
"Unit";"Zergling";"Larva";350;1
"Unit";"Zergling";"Larva";350;1
"Unit";"Zergling";"Larva";350;1
"Unit";"Zergling";"Larva";350;1
"Unit";"Zergling";"Larva";350;1
"Unit";"Zergling";"Larva";350;1
"Unit";"Zergling";"Larva";350;1
"Unit";"Zergling";"Larva";350;1
"Unit";"Zergling";"Larva";350;1
"Unit";"Zergling";"Larva";350;1
"Unit";"Zergling";"Larva";350;1
"Unit";"Zergling";"Larva";350;1
"Unit";"Zergling";"Larva";350;1
"Unit";"Zergling";"Larva";350;1
"Unit";"Zergling";"Larva";350;1
"Unit";"Zergling";"Larva";350;1
"Unit";"Zergling";"Larva";350;1
"Unit";"Zergling";"Larva";350;1
"Unit";"Zergling";"Larva";350;1
"Unit";"Zergling";"Larva";350;1
"Unit";"Zergling";"Larva";350;1
"Unit";"Zergling";"Larva";350;1
"Unit";"Zergling";"Larva";350;1
"Unit";"Zergling";"Larva";350;1
"Unit";"Zergling";"Larva";350;1
"Unit";"Zergling";"Larva";350;1
"Unit";"Zergling";"Larva";350;1
"Unit";"Zergling";"Larva";350;1
"Unit";"Zergling";"Larva";350;1
"Unit";"Zergling";"Larva";350;1
"Unit";"Zergling";"Larva";350;1
"Unit";"Zergling";"Larva";350;1
"Unit";"Zergling";"Larva";350;1
"Unit";"Zergling";"Larva";350;1
"Unit";"Zergling";"Larva";350;1
"Unit";"Zergling";"Larva";352;1
"Unit";"Zergling";"Larva";352;1
"Building";"CreepTumor";NA;394;0
"Building";"CreepTumor";NA;396;0
"Building";"CreepTumor";NA;396;0
"Building";"CreepTumor";NA;396;0
"Building";"HydraliskDen";NA;378;0
"Unit";"Zergling";"Larva";396;1
"Unit";"Zergling";"Larva";396;1
"Unit";"Zergling";"Larva";396;1
"Unit";"Zergling";"Larva";396;1
"Unit";"Zergling";"Larva";396;1
"Unit";"Zergling";"Larva";396;1
"Unit";"Zergling";"Larva";396;1
"Unit";"Zergling";"Larva";396;1
"Unit";"Zergling";"Larva";396;1
"Unit";"Zergling";"Larva";396;1
"Unit";"Zergling";"Larva";396;1
"Unit";"Zergling";"Larva";396;1
"Unit";"Zergling";"Larva";396;1
"Unit";"Zergling";"Larva";396;1
"Unit";"Zergling";"Larva";396;1
"Unit";"Zergling";"Larva";396;1
"Unit";"Zergling";"Larva";396;1
"Unit";"Zergling";"Larva";396;1
"Unit";"Baneling";"Zergling";396;0
"Unit";"Baneling";"Zergling";396;0
"Unit";"Baneling";"Zergling";396;0
"Unit";"Baneling";"Zergling";396;0
"Unit";"Baneling";"Zergling";396;0
"Unit";"Baneling";"Zergling";396;0
"Unit";"Baneling";"Zergling";396;0
"Building";"CreepTumor";NA;396;0
"Unit";"Baneling";"Zergling";396;0
"Unit";"Baneling";"Zergling";396;0
"Unit";"Baneling";"Zergling";396;0
"Unit";"Baneling";"Zergling";396;0
"Unit";"Baneling";"Zergling";396;0
"Unit";"Baneling";"Zergling";396;0
"Unit";"Baneling";"Zergling";396;0
"Building";"Hatchery";NA;378;0
"Unit";"Zergling";"Larva";418;1
"Unit";"Zergling";"Larva";418;1
"Unit";"Zergling";"Larva";418;1
"Unit";"Zergling";"Larva";418;1
"Unit";"Zergling";"Larva";418;1
"Unit";"Zergling";"Larva";418;1
"Unit";"Zergling";"Larva";418;1
"Unit";"Zergling";"Larva";418;1
"Unit";"Zergling";"Larva";418;1
"Unit";"Zergling";"Larva";418;1
"Unit";"Zergling";"Larva";418;1
"Unit";"Zergling";"Larva";418;1
"Unit";"Zergling";"Larva";418;1
"Unit";"Zergling";"Larva";418;1
"Unit";"Zergling";"Larva";418;1
"Unit";"Zergling";"Larva";418;1
"Unit";"Zergling";"Larva";418;1
"Unit";"Zergling";"Larva";418;1
"Unit";"Zergling";"Larva";418;1
"Unit";"Zergling";"Larva";418;1
"Unit";"Zergling";"Larva";418;1
"Unit";"Zergling";"Larva";418;1
"Unit";"Zergling";"Larva";418;1
"Unit";"Zergling";"Larva";418;1
"Unit";"Zergling";"Larva";418;1
"Unit";"Zergling";"Larva";418;1
"Unit";"Zergling";"Larva";418;1
"Unit";"Zergling";"Larva";418;1
"Unit";"Zergling";"Larva";418;1
"Unit";"Zergling";"Larva";418;1
"Unit";"Zergling";"Larva";418;1
"Unit";"Zergling";"Larva";418;1
"Unit";"Zergling";"Larva";418;1
"Unit";"Zergling";"Larva";418;1
"Unit";"Baneling";"Zergling";446;0
"Unit";"Baneling";"Zergling";446;0
"Unit";"Baneling";"Zergling";446;0
"Unit";"Baneling";"Zergling";446;0
"Unit";"Baneling";"Zergling";446;0
"Unit";"Baneling";"Zergling";446;0
"Unit";"Baneling";"Zergling";446;0
"Unit";"Baneling";"Zergling";446;0
"Unit";"Baneling";"Zergling";446;0
"Unit";"Baneling";"Zergling";446;0
"Unit";"Baneling";"Zergling";446;0
"Unit";"Baneling";"Zergling";446;0
"Unit";"Baneling";"Zergling";446;0
"Unit";"Baneling";"Zergling";446;0
"Unit";"Baneling";"Zergling";446;0
"Unit";"Baneling";"Zergling";446;0
"Unit";"Baneling";"Zergling";446;0
"Unit";"Baneling";"Zergling";446;0
"Unit";"Baneling";"Zergling";446;0
"Unit";"Baneling";"Zergling";446;0
"Building";"Hatchery";NA;414;0
"Building";"CreepTumorQueen";NA;452;0
"Building";"CreepTumor";NA;452;0
"Unit";"Baneling";"Zergling";448;0
"Unit";"Baneling";"Zergling";448;0
"Unit";"Baneling";"Zergling";448;0
"Unit";"Baneling";"Zergling";448;0
"Unit";"Baneling";"Zergling";448;0
"Unit";"Baneling";"Zergling";448;0
"Unit";"Baneling";"Zergling";448;0
"Unit";"Zergling";"Larva";448;1
"Unit";"Zergling";"Larva";448;1
"Unit";"Zergling";"Larva";448;1
"Unit";"Zergling";"Larva";448;1
"Unit";"Zergling";"Larva";448;1
"Unit";"Zergling";"Larva";448;1
"Unit";"Zergling";"Larva";448;1
"Unit";"Zergling";"Larva";448;1
"Unit";"Zergling";"Larva";448;1
"Unit";"Zergling";"Larva";448;1
"Unit";"Zergling";"Larva";462;1
"Unit";"Zergling";"Larva";462;1
"Unit";"Zergling";"Larva";462;1
"Unit";"Zergling";"Larva";462;1
"Unit";"Zergling";"Larva";462;1
"Unit";"Zergling";"Larva";462;1
"Unit";"Zergling";"Larva";462;1
"Unit";"Zergling";"Larva";462;1
"Unit";"Zergling";"Larva";462;1
"Unit";"Zergling";"Larva";462;1
"Unit";"Zergling";"Larva";462;1
"Unit";"Zergling";"Larva";462;1
"Unit";"Zergling";"Larva";462;1
"Unit";"Zergling";"Larva";462;1
"Unit";"Zergling";"Larva";462;1
"Unit";"Zergling";"Larva";462;1
"Unit";"Zergling";"Larva";462;1
"Unit";"Zergling";"Larva";462;1
"Unit";"Zergling";"Larva";462;1
"Unit";"Zergling";"Larva";462;1
"Unit";"Zergling";"Larva";462;1
"Unit";"Zergling";"Larva";462;1
"Unit";"Zergling";"Larva";462;1
"Unit";"Zergling";"Larva";462;1
"Unit";"Zergling";"Larva";462;1
"Unit";"Zergling";"Larva";462;1
"Unit";"Zergling";"Larva";462;1
"Unit";"Zergling";"Larva";462;1
"Unit";"Zergling";"Larva";462;1
"Unit";"Zergling";"Larva";462;1
"Unit";"Zergling";"Larva";462;1
"Unit";"Zergling";"Larva";462;1
"Unit";"Zergling";"Larva";462;1
"Unit";"Zergling";"Larva";462;1
"Unit";"Zergling";"Larva";462;1
"Unit";"Zergling";"Larva";462;1
"Unit";"Zergling";"Larva";462;1
"Unit";"Zergling";"Larva";462;1
"Unit";"Zergling";"Larva";462;1
"Unit";"Zergling";"Larva";462;1
"Unit";"Zergling";"Larva";462;1
"Unit";"Zergling";"Larva";462;1
"Building";"CreepTumorQueen";NA;488;0
"Building";"CreepTumorQueen";NA;488;0
"Unit";"Baneling";"Zergling";504;0
"Unit";"Zergling";"Larva";504;1
"Unit";"Zergling";"Larva";504;1
"Unit";"Zergling";"Larva";504;1
"Unit";"Zergling";"Larva";504;1
"Unit";"Zergling";"Larva";504;1
"Unit";"Zergling";"Larva";504;1
"Unit";"Zergling";"Larva";504;1
"Unit";"Zergling";"Larva";504;1
"Unit";"Zergling";"Larva";504;1
"Unit";"Zergling";"Larva";504;1
"Unit";"Zergling";"Larva";504;1
"Unit";"Zergling";"Larva";504;1
"Unit";"Zergling";"Larva";504;1
"Unit";"Zergling";"Larva";504;1
"Unit";"Zergling";"Larva";504;1
"Unit";"Zergling";"Larva";504;1
"Unit";"Zergling";"Larva";504;1
"Unit";"Zergling";"Larva";504;1
"Unit";"Zergling";"Larva";504;1
"Unit";"Zergling";"Larva";504;1
"Unit";"Zergling";"Larva";504;1
"Unit";"Zergling";"Larva";504;1
"Unit";"Zergling";"Larva";504;1
"Unit";"Zergling";"Larva";504;1
"Unit";"Zergling";"Larva";504;1
"Unit";"Zergling";"Larva";504;1
"Unit";"Baneling";"Zergling";504;0
"Unit";"Baneling";"Zergling";504;0
"Unit";"Baneling";"Zergling";504;0
"Unit";"Baneling";"Zergling";504;0
"Unit";"Baneling";"Zergling";504;0
"Unit";"Baneling";"Zergling";504;0
"Unit";"Baneling";"Zergling";504;0
"Unit";"Zergling";"Larva";504;1
"Unit";"Zergling";"Larva";504;1
"Unit";"Zergling";"Larva";504;1
"Unit";"Zergling";"Larva";504;1
"Unit";"Zergling";"Larva";504;1
"Unit";"Zergling";"Larva";504;1
"Unit";"Baneling";"Zergling";530;0
"Unit";"Baneling";"Zergling";530;0
"Unit";"Baneling";"Zergling";530;0
"Unit";"Baneling";"Zergling";530;0
"Unit";"Baneling";"Zergling";530;0
"Unit";"Baneling";"Zergling";530;0
"Building";"CreepTumor";NA;530;0
"Building";"CreepTumor";NA;536;0
"Unit";"Baneling";"Zergling";530;0
"Unit";"Baneling";"Zergling";530;0
"Unit";"Baneling";"Zergling";530;0
"Unit";"Baneling";"Zergling";530;0
"Unit";"Baneling";"Zergling";530;0
"Unit";"Baneling";"Zergling";530;0
"Unit";"Baneling";"Zergling";530;0
"Unit";"Baneling";"Zergling";530;0
"Unit";"Zergling";"Larva";530;1
"Unit";"Zergling";"Larva";530;1
"Unit";"Zergling";"Larva";530;1
"Unit";"Zergling";"Larva";530;1
"Unit";"Zergling";"Larva";530;1
"Unit";"Zergling";"Larva";530;1
"Unit";"Zergling";"Larva";530;1
"Unit";"Zergling";"Larva";530;1
"Unit";"Zergling";"Larva";530;1
"Unit";"Zergling";"Larva";530;1
"Building";"CreepTumor";NA;536;0
"Building";"CreepTumor";NA;546;0
"Building";"CreepTumor";NA;546;0
"Unit";"Zergling";"Larva";546;1
"Unit";"Zergling";"Larva";546;1
"Unit";"Zergling";"Larva";546;1
"Unit";"Zergling";"Larva";546;1
"Unit";"Zergling";"Larva";546;1
"Unit";"Zergling";"Larva";546;1
"Unit";"Zergling";"Larva";546;1
"Unit";"Zergling";"Larva";546;1
"Unit";"Zergling";"Larva";546;1
"Unit";"Zergling";"Larva";546;1
"Unit";"Zergling";"Larva";546;1
"Unit";"Zergling";"Larva";546;1
"Unit";"Zergling";"Larva";546;1
"Unit";"Zergling";"Larva";546;1
"Unit";"Zergling";"Larva";546;1
"Unit";"Zergling";"Larva";546;1
"Unit";"Zergling";"Larva";546;1
"Unit";"Zergling";"Larva";546;1
"Building";"CreepTumor";NA;546;0
"Unit";"Zergling";"Larva";546;1
"Unit";"Zergling";"Larva";546;1
"Unit";"Zergling";"Larva";546;1
"Unit";"Zergling";"Larva";546;1
"Unit";"Zergling";"Larva";546;1
"Unit";"Zergling";"Larva";546;1
"Unit";"Zergling";"Larva";546;1
"Unit";"Zergling";"Larva";546;1
"Unit";"Zergling";"Larva";546;1
"Unit";"Zergling";"Larva";546;1
"Unit";"Zergling";"Larva";546;1
"Unit";"Zergling";"Larva";546;1
"Unit";"Zergling";"Larva";546;1
"Unit";"Zergling";"Larva";546;1
"Unit";"Zergling";"Larva";546;1
"Unit";"Zergling";"Larva";546;1
"Unit";"Zergling";"Larva";546;1
"Unit";"Zergling";"Larva";546;1
"Unit";"Baneling";"Zergling";564;0
"Unit";"Baneling";"Zergling";564;0
"Unit";"Baneling";"Zergling";564;0
"Unit";"Baneling";"Zergling";564;0
"Unit";"Baneling";"Zergling";564;0
"Unit";"Baneling";"Zergling";564;0
"Unit";"Baneling";"Zergling";564;0
"Unit";"Baneling";"Zergling";564;0
"Unit";"Baneling";"Zergling";564;0
"Unit";"Baneling";"Zergling";564;0
"Unit";"Baneling";"Zergling";564;0
"Unit";"Baneling";"Zergling";564;0
"Unit";"Baneling";"Zergling";564;0
"Unit";"Baneling";"Zergling";564;0
"Unit";"Baneling";"Zergling";564;0
"Unit";"Zergling";"Larva";576;1
"Unit";"Zergling";"Larva";576;1
"Unit";"Zergling";"Larva";576;1
"Unit";"Zergling";"Larva";576;1
"Unit";"Zergling";"Larva";576;1
"Unit";"Zergling";"Larva";576;1
"Unit";"Zergling";"Larva";576;1
"Unit";"Zergling";"Larva";576;1
"Building";"Hatchery";NA;546;0
"Unit";"Zergling";"Larva";590;1
"Unit";"Zergling";"Larva";590;1
"Unit";"Zergling";"Larva";590;1
"Unit";"Zergling";"Larva";590;1
"Unit";"Zergling";"Larva";590;1
"Unit";"Zergling";"Larva";590;1
"Unit";"Zergling";"Larva";590;1
"Unit";"Zergling";"Larva";590;1
"Unit";"Zergling";"Larva";590;1
"Unit";"Zergling";"Larva";590;1
"Unit";"Zergling";"Larva";590;1
"Unit";"Zergling";"Larva";590;1
"Unit";"Zergling";"Larva";590;1
"Unit";"Zergling";"Larva";590;1
"Unit";"Zergling";"Larva";590;1
"Unit";"Zergling";"Larva";590;1
"Unit";"Zergling";"Larva";590;1
"Unit";"Zergling";"Larva";590;1
"Unit";"Zergling";"Larva";590;1
"Unit";"Zergling";"Larva";590;1
"Unit";"Zergling";"Larva";590;1
"Unit";"Zergling";"Larva";590;1
"Unit";"Zergling";"Larva";590;1
"Unit";"Zergling";"Larva";590;1
"Unit";"Zergling";"Larva";590;1
"Unit";"Zergling";"Larva";590;1
"Unit";"Zergling";"Larva";590;1
"Unit";"Zergling";"Larva";590;1
"Unit";"Zergling";"Larva";590;1
"Unit";"Zergling";"Larva";590;1
"Unit";"Zergling";"Larva";590;1
"Unit";"Zergling";"Larva";590;1
"Unit";"Zergling";"Larva";590;1
"Unit";"Zergling";"Larva";590;1
"Unit";"Zergling";"Larva";590;1
"Unit";"Zergling";"Larva";590;1
"Unit";"Zergling";"Larva";590;1
"Unit";"Zergling";"Larva";590;1
"Unit";"Zergling";"Larva";590;1
"Unit";"Zergling";"Larva";590;1
"Unit";"Zergling";"Larva";590;1
"Unit";"Zergling";"Larva";590;1
"Unit";"Zergling";"Larva";590;1
"Unit";"Zergling";"Larva";590;1
"Unit";"Zergling";"Larva";590;1
"Unit";"Zergling";"Larva";590;1
"Unit";"Zergling";"Larva";590;1
"Unit";"Zergling";"Larva";590;1
"Unit";"Baneling";"Zergling";624;0
"Unit";"Baneling";"Zergling";624;0
"Unit";"Baneling";"Zergling";624;0
"Unit";"Baneling";"Zergling";624;0
"Unit";"Baneling";"Zergling";624;0
"Unit";"Baneling";"Zergling";624;0
"Unit";"Baneling";"Zergling";624;0
"Unit";"Baneling";"Zergling";624;0
"Unit";"Baneling";"Zergling";624;0
"Unit";"Baneling";"Zergling";624;0
"Unit";"Baneling";"Zergling";624;0
"Unit";"Baneling";"Zergling";624;0
"Unit";"Baneling";"Zergling";624;0
"Unit";"Baneling";"Zergling";624;0
"Unit";"Zergling";"Larva";638;1
"Unit";"Zergling";"Larva";638;1
"Unit";"Zergling";"Larva";638;1
"Unit";"Zergling";"Larva";638;1
"Unit";"Zergling";"Larva";638;1
"Unit";"Zergling";"Larva";638;1
"Unit";"Zergling";"Larva";638;1
"Unit";"Zergling";"Larva";638;1
"Unit";"Zergling";"Larva";638;1
"Unit";"Zergling";"Larva";638;1
"Upgrade";"ZergMeleeWeaponsLevel3";"EvolutionChamber";546;0
"Upgrade";"ZergGroundArmorsLevel3";"EvolutionChamber";546;0
"Building";"CreepTumor";NA;648;0
"Building";"CreepTumor";NA;648;0
"Unit";"Hydralisk";"Larva";648;2
"Unit";"Hydralisk";"Larva";648;2
"Unit";"Hydralisk";"Larva";648;2
"Unit";"Hydralisk";"Larva";648;2
"Unit";"Hydralisk";"Larva";648;2
"Unit";"Hydralisk";"Larva";648;2
"Unit";"Hydralisk";"Larva";648;2
"Unit";"Hydralisk";"Larva";648;2
"Unit";"Hydralisk";"Larva";648;2
"Building";"CreepTumorQueen";NA;666;0
"Unit";"Zergling";"Larva";660;1
"Unit";"Zergling";"Larva";660;1
"Unit";"Zergling";"Larva";660;1
"Unit";"Zergling";"Larva";660;1
"Unit";"Zergling";"Larva";660;1
"Unit";"Zergling";"Larva";660;1
"Unit";"Zergling";"Larva";660;1
"Unit";"Zergling";"Larva";660;1
"Unit";"Zergling";"Larva";660;1
"Unit";"Zergling";"Larva";660;1
"Building";"CreepTumorQueen";NA;666;0
"Building";"CreepTumorQueen";NA;666;0
"Unit";"Hydralisk";"Larva";660;2
"Unit";"Hydralisk";"Larva";660;2
"Unit";"Hydralisk";"Larva";660;2
"Unit";"Hydralisk";"Larva";660;2
"Upgrade";"EvolveGroovedSpines";"HydraliskDen";648;0
"Unit";"Zergling";"Larva";684;1
"Unit";"Zergling";"Larva";684;1
"Unit";"Zergling";"Larva";684;1
"Unit";"Zergling";"Larva";684;1
"Unit";"Zergling";"Larva";684;1
"Unit";"Zergling";"Larva";684;1
"Unit";"Zergling";"Larva";684;1
"Unit";"Zergling";"Larva";684;1
"Unit";"Zergling";"Larva";684;1
"Unit";"Zergling";"Larva";684;1
"Unit";"Zergling";"Larva";684;1
"Unit";"Zergling";"Larva";684;1
"Unit";"Zergling";"Larva";684;1
"Unit";"Zergling";"Larva";684;1
"Unit";"Zergling";"Larva";684;1
"Unit";"Zergling";"Larva";684;1
"Unit";"Zergling";"Larva";684;1
"Unit";"Zergling";"Larva";684;1
"Unit";"Zergling";"Larva";684;1
"Unit";"Zergling";"Larva";684;1
"Unit";"Zergling";"Larva";684;1
"Unit";"Zergling";"Larva";684;1
"Unit";"Zergling";"Larva";684;1
"Unit";"Zergling";"Larva";684;1
"Unit";"Zergling";"Larva";684;1
"Unit";"Zergling";"Larva";684;1
"Unit";"Zergling";"Larva";684;1
"Unit";"Zergling";"Larva";684;1
"Building";"CreepTumor";NA;684;0
"Building";"CreepTumor";NA;684;0
"Building";"CreepTumor";NA;684;0
"Building";"CreepTumor";NA;686;0
"Unit";"Zergling";"Larva";684;1
"Unit";"Zergling";"Larva";684;1
"Unit";"Zergling";"Larva";684;1
"Unit";"Zergling";"Larva";684;1
"Unit";"Zergling";"Larva";684;1
"Unit";"Zergling";"Larva";684;1
"Unit";"Zergling";"Larva";684;1
"Unit";"Zergling";"Larva";684;1
"Unit";"Zergling";"Larva";712;1
"Unit";"Zergling";"Larva";712;1
"Unit";"Zergling";"Larva";712;1
"Unit";"Zergling";"Larva";712;1
"Unit";"Zergling";"Larva";712;1
"Unit";"Zergling";"Larva";712;1
"Unit";"Zergling";"Larva";712;1
"Unit";"Zergling";"Larva";712;1
"Upgrade";"ZergMissileWeaponsLevel1";"EvolutionChamber";660;0
"Unit";"Zergling";"Larva";712;1
"Unit";"Zergling";"Larva";712;1
"Unit";"Zergling";"Larva";712;1
"Unit";"Zergling";"Larva";712;1
"Unit";"Zergling";"Larva";712;1
"Unit";"Zergling";"Larva";712;1
"Unit";"Zergling";"Larva";712;1
"Unit";"Zergling";"Larva";712;1
"Unit";"Zergling";"Larva";736;1
"Unit";"Zergling";"Larva";736;1
"Unit";"Zergling";"Larva";736;1
"Unit";"Zergling";"Larva";736;1
"Unit";"Zergling";"Larva";736;1
"Unit";"Zergling";"Larva";736;1
"Unit";"Zergling";"Larva";736;1
"Unit";"Zergling";"Larva";736;1
"Unit";"Zergling";"Larva";736;1
"Unit";"Zergling";"Larva";736;1
"Unit";"Zergling";"Larva";736;1
"Unit";"Zergling";"Larva";736;1
"Unit";"Zergling";"Larva";736;1
"Unit";"Zergling";"Larva";736;1
"Building";"Hatchery";NA;684;0
"Building";"CreepTumor";NA;765;0
"Building";"CreepTumor";NA;765;0
"Building";"CreepTumor";NA;765;0
"Upgrade";"EvolveMuscularAugments";"HydraliskDen";712;0
"Unit";"Zergling";"Larva";765;1
"Unit";"Zergling";"Larva";765;1
"Unit";"Zergling";"Larva";765;1
"Unit";"Zergling";"Larva";765;1
"Unit";"Zergling";"Larva";765;1
"Unit";"Zergling";"Larva";765;1
"Unit";"Zergling";"Larva";765;1
"Unit";"Zergling";"Larva";765;1
"Unit";"Zergling";"Larva";765;1
"Unit";"Zergling";"Larva";765;1
"Unit";"Zergling";"Larva";765;1
"Unit";"Zergling";"Larva";765;1
"Unit";"Zergling";"Larva";765;1
"Unit";"Zergling";"Larva";765;1
"Unit";"Zergling";"Larva";765;1
"Unit";"Zergling";"Larva";765;1
"Unit";"Zergling";"Larva";765;1
"Unit";"Zergling";"Larva";765;1
"Unit";"Zergling";"Larva";765;1
"Unit";"Zergling";"Larva";765;1
"Unit";"Zergling";"Larva";765;1
"Unit";"Zergling";"Larva";765;1
"Unit";"Zergling";"Larva";765;1
"Unit";"Zergling";"Larva";765;1
"Unit";"Zergling";"Larva";765;1
"Unit";"Zergling";"Larva";765;1
"Unit";"Zergling";"Larva";765;1
"Unit";"Zergling";"Larva";765;1
"Unit";"Zergling";"Larva";765;1
"Unit";"Zergling";"Larva";765;1
"Unit";"Zergling";"Larva";765;1
"Unit";"Zergling";"Larva";765;1
"Unit";"Baneling";"Zergling";765;0
"Unit";"Baneling";"Zergling";765;0
"Unit";"Baneling";"Zergling";765;0
"Unit";"Baneling";"Zergling";765;0
"Unit";"Baneling";"Zergling";765;0
"Unit";"Baneling";"Zergling";765;0
"Unit";"Baneling";"Zergling";765;0
"Unit";"Baneling";"Zergling";765;0
"Unit";"Baneling";"Zergling";765;0
"Unit";"Baneling";"Zergling";765;0
"Unit";"Baneling";"Zergling";765;0
"Unit";"Baneling";"Zergling";765;0
"Unit";"Zergling";"Larva";797;1
"Unit";"Zergling";"Larva";797;1
"Unit";"Zergling";"Larva";797;1
"Unit";"Zergling";"Larva";797;1
"Unit";"Zergling";"Larva";797;1
"Unit";"Zergling";"Larva";797;1
"Unit";"Zergling";"Larva";797;1
"Unit";"Zergling";"Larva";797;1
"Unit";"Zergling";"Larva";797;1
"Unit";"Zergling";"Larva";797;1
"Unit";"Zergling";"Larva";797;1
"Unit";"Zergling";"Larva";797;1
"Unit";"Zergling";"Larva";797;1
"Unit";"Zergling";"Larva";797;1
"Unit";"Zergling";"Larva";797;1
"Unit";"Zergling";"Larva";797;1
"Unit";"Zergling";"Larva";797;1
"Unit";"Zergling";"Larva";797;1
"Unit";"Zergling";"Larva";797;1
"Unit";"Zergling";"Larva";797;1
"Unit";"Zergling";"Larva";797;1
"Unit";"Zergling";"Larva";797;1
"Unit";"Zergling";"Larva";797;1
"Unit";"Zergling";"Larva";797;1
"Unit";"Zergling";"Larva";797;1
"Unit";"Zergling";"Larva";797;1
"Unit";"Zergling";"Larva";797;1
"Unit";"Zergling";"Larva";797;1
"Unit";"Zergling";"Larva";797;1
"Unit";"Zergling";"Larva";797;1
"Unit";"Overlord";"Larva";797;0
"Unit";"Zergling";"Larva";827;1
"Unit";"Zergling";"Larva";827;1
"Unit";"Zergling";"Larva";827;1
"Unit";"Zergling";"Larva";827;1
"Unit";"Zergling";"Larva";827;1
"Unit";"Zergling";"Larva";827;1
"Unit";"Zergling";"Larva";827;1
"Unit";"Zergling";"Larva";827;1
"Unit";"Zergling";"Larva";827;1
"Unit";"Zergling";"Larva";827;1
"Unit";"Zergling";"Larva";827;1
"Unit";"Zergling";"Larva";827;1
"Unit";"Zergling";"Larva";827;1
"Unit";"Zergling";"Larva";827;1
"Unit";"Zergling";"Larva";827;1
"Unit";"Zergling";"Larva";827;1
"Unit";"Zergling";"Larva";827;1
"Unit";"Zergling";"Larva";827;1
"Building";"CreepTumor";NA;829;0
"Unit";"Zergling";"Larva";845;1
"Unit";"Zergling";"Larva";845;1
"Unit";"Zergling";"Larva";845;1
"Unit";"Zergling";"Larva";845;1
"Unit";"Zergling";"Larva";845;1
"Unit";"Zergling";"Larva";845;1
"Unit";"Zergling";"Larva";845;1
"Unit";"Zergling";"Larva";845;1
"Building";"CreepTumor";NA;845;0
"Building";"CreepTumor";NA;845;0
"Unit";"Hydralisk";"Larva";845;2
"Unit";"Hydralisk";"Larva";845;2
"Unit";"Baneling";"Zergling";853;0
"Unit";"Baneling";"Zergling";853;0
"Unit";"Baneling";"Zergling";853;0
"Unit";"Baneling";"Zergling";853;0
"Unit";"Baneling";"Zergling";853;0
"Unit";"Baneling";"Zergling";853;0
"Unit";"Baneling";"Zergling";853;0
"Unit";"Baneling";"Zergling";853;0
"Unit";"Baneling";"Zergling";853;0
"Unit";"Baneling";"Zergling";853;0
"Unit";"Baneling";"Zergling";853;0
"Unit";"Baneling";"Zergling";853;0
"Unit";"Baneling";"Zergling";853;0
"Unit";"Baneling";"Zergling";853;0
"Unit";"Baneling";"Zergling";853;0
"Building";"Extractor";NA;853;0
"Unit";"Queen";"Hatchery";845;2
"Unit";"Zergling";"Larva";857;1
"Unit";"Zergling";"Larva";857;1
"Unit";"Zergling";"Larva";857;1
"Unit";"Zergling";"Larva";857;1
"Unit";"Zergling";"Larva";857;1
"Unit";"Zergling";"Larva";857;1
"Unit";"Zergling";"Larva";857;1
"Unit";"Zergling";"Larva";857;1
"Unit";"Zergling";"Larva";857;1
"Unit";"Zergling";"Larva";857;1
"Unit";"Zergling";"Larva";857;1
"Unit";"Zergling";"Larva";857;1
"Unit";"Zergling";"Larva";857;1
"Unit";"Zergling";"Larva";857;1
"Unit";"Zergling";"Larva";857;1
"Unit";"Zergling";"Larva";857;1
"Unit";"Zergling";"Larva";857;1
"Unit";"Zergling";"Larva";857;1
"Building";"Hatchery";NA;827;0
"Unit";"Zergling";"Larva";859;1
"Unit";"Zergling";"Larva";859;1
"Unit";"Zergling";"Larva";859;1
"Unit";"Zergling";"Larva";859;1
"Unit";"Hydralisk";"Larva";859;2
"Unit";"Hydralisk";"Larva";859;2
"Unit";"Hydralisk";"Larva";859;2
"Unit";"Zergling";"Larva";877;1
"Unit";"Zergling";"Larva";877;1
"Unit";"Zergling";"Larva";877;1
"Unit";"Zergling";"Larva";877;1
"Unit";"Zergling";"Larva";877;1
"Unit";"Zergling";"Larva";877;1
"Unit";"Zergling";"Larva";877;1
"Unit";"Zergling";"Larva";877;1
"Unit";"Zergling";"Larva";877;1
"Unit";"Zergling";"Larva";877;1
"Unit";"Zergling";"Larva";877;1
"Unit";"Zergling";"Larva";877;1
"Building";"CreepTumor";NA;899;0
"Upgrade";"ZergMissileWeaponsLevel2";"EvolutionChamber";845;0
"Unit";"Zergling";"Larva";904;1
"Unit";"Zergling";"Larva";904;1
"Unit";"Zergling";"Larva";904;1
"Unit";"Zergling";"Larva";904;1
"Unit";"Zergling";"Larva";904;1
"Unit";"Zergling";"Larva";904;1
"Unit";"Hydralisk";"Larva";904;2
"Unit";"Hydralisk";"Larva";904;2
"Unit";"Hydralisk";"Larva";904;2
"Unit";"Zergling";"Larva";904;1
"Unit";"Zergling";"Larva";904;1
"Unit";"Zergling";"Larva";904;1
"Unit";"Zergling";"Larva";904;1
"Unit";"Zergling";"Larva";904;1
"Unit";"Zergling";"Larva";904;1
"Unit";"Hydralisk";"Larva";904;2
"Unit";"Hydralisk";"Larva";904;2
"Unit";"Baneling";"Zergling";926;0
"Unit";"Zergling";"Larva";926;1
"Unit";"Zergling";"Larva";926;1
"Unit";"Baneling";"Zergling";926;0
"Unit";"Baneling";"Zergling";926;0
"Unit";"Baneling";"Zergling";926;0
"Unit";"Baneling";"Zergling";926;0
"Unit";"Baneling";"Zergling";926;0
"Unit";"Zergling";"Larva";926;1
"Unit";"Zergling";"Larva";926;1
"Unit";"Baneling";"Zergling";926;0
"Unit";"Baneling";"Zergling";926;0
"Unit";"Baneling";"Zergling";926;0
"Unit";"Baneling";"Zergling";926;0
"Unit";"Zergling";"Larva";926;1
"Unit";"Zergling";"Larva";926;1
"Unit";"Zergling";"Larva";926;1
"Unit";"Zergling";"Larva";926;1
"Unit";"Zergling";"Larva";926;1
"Unit";"Zergling";"Larva";926;1
"Unit";"Zergling";"Larva";926;1
"Unit";"Zergling";"Larva";926;1
"Unit";"Baneling";"Zergling";926;0
"Unit";"Baneling";"Zergling";926;0
"Unit";"Baneling";"Zergling";926;0
"Unit";"Baneling";"Zergling";926;0
"Unit";"Zergling";"Larva";926;1
"Unit";"Zergling";"Larva";926;1
"Unit";"Zergling";"Larva";926;1
"Unit";"Zergling";"Larva";926;1
"Unit";"Zergling";"Larva";926;1
"Unit";"Zergling";"Larva";926;1
"Unit";"Zergling";"Larva";926;1
"Unit";"Zergling";"Larva";926;1
"Unit";"Zergling";"Larva";926;1
"Unit";"Zergling";"Larva";926;1
"Unit";"Zergling";"Larva";926;1
"Unit";"Zergling";"Larva";926;1
"Unit";"Zergling";"Larva";926;1
"Unit";"Zergling";"Larva";926;1
"Unit";"Baneling";"Zergling";926;0
"Unit";"Zergling";"Larva";926;1
"Unit";"Zergling";"Larva";926;1
"Unit";"Zergling";"Larva";926;1
"Unit";"Zergling";"Larva";926;1
"Unit";"Zergling";"Larva";926;1
"Unit";"Zergling";"Larva";926;1
"Unit";"Zergling";"Larva";926;1
"Unit";"Zergling";"Larva";926;1
"Unit";"Zergling";"Larva";926;1
"Unit";"Zergling";"Larva";926;1
"Building";"Hatchery";NA;904;0
"Unit";"Zergling";"Larva";952;1
"Unit";"Zergling";"Larva";952;1
"Unit";"Zergling";"Larva";952;1
"Unit";"Zergling";"Larva";952;1
"Unit";"Zergling";"Larva";952;1
"Unit";"Zergling";"Larva";952;1
"Unit";"Zergling";"Larva";952;1
"Unit";"Zergling";"Larva";952;1
"Unit";"Hydralisk";"Larva";975;2
"Unit";"Hydralisk";"Larva";975;2
"Unit";"Hydralisk";"Larva";975;2
"Unit";"Hydralisk";"Larva";975;2
"Unit";"Hydralisk";"Larva";975;2
"Unit";"Hydralisk";"Larva";975;2
"Unit";"Zergling";"Larva";975;1
"Unit";"Zergling";"Larva";975;1
"Unit";"Zergling";"Larva";975;1
"Unit";"Zergling";"Larva";975;1
"Unit";"Zergling";"Larva";975;1
"Unit";"Zergling";"Larva";975;1
"Unit";"Zergling";"Larva";975;1
"Unit";"Zergling";"Larva";975;1
"Unit";"Zergling";"Larva";975;1
"Unit";"Zergling";"Larva";975;1
"Building";"CreepTumor";NA;987;0
"Building";"CreepTumor";NA;997;0
"Building";"CreepTumor";NA;997;0
"Building";"CreepTumor";NA;997;0
"Building";"CreepTumor";NA;997;0
"Building";"CreepTumorQueen";NA;997;0
"Building";"CreepTumorQueen";NA;997;0
"Unit";"Zergling";"Larva";997;1
"Unit";"Zergling";"Larva";997;1
"Unit";"Zergling";"Larva";997;1
"Unit";"Zergling";"Larva";997;1
"Unit";"Zergling";"Larva";997;1
"Unit";"Zergling";"Larva";997;1
"Unit";"Zergling";"Larva";997;1
"Unit";"Zergling";"Larva";997;1
"Unit";"Zergling";"Larva";997;1
"Unit";"Zergling";"Larva";997;1
"Unit";"Zergling";"Larva";997;1
"Unit";"Zergling";"Larva";997;1
"Unit";"Zergling";"Larva";997;1
"Unit";"Zergling";"Larva";997;1
"Unit";"Zergling";"Larva";997;1
"Unit";"Zergling";"Larva";997;1
"Unit";"Zergling";"Larva";997;1
"Unit";"Zergling";"Larva";997;1
"Unit";"Zergling";"Larva";997;1
"Unit";"Zergling";"Larva";997;1
"Unit";"Zergling";"Larva";997;1
"Unit";"Zergling";"Larva";997;1
"Unit";"Zergling";"Larva";997;1
"Unit";"Zergling";"Larva";997;1
"Unit";"Zergling";"Larva";997;1
"Unit";"Zergling";"Larva";997;1
"Building";"CreepTumor";NA;1023;0
"Building";"CreepTumor";NA;1023;0
"Building";"CreepTumor";NA;1023;0
"Unit";"Infestor";"Larva";997;2
"Building";"CreepTumor";NA;1023;0
"Unit";"Infestor";"Larva";997;2
"Unit";"Infestor";"Larva";997;2
"Building";"Hatchery";NA;997;0
"Unit";"Zergling";"Larva";1023;1
"Unit";"Zergling";"Larva";1023;1
"Unit";"Zergling";"Larva";1023;1
"Unit";"Zergling";"Larva";1023;1
"Unit";"Zergling";"Larva";1023;1
"Unit";"Zergling";"Larva";1023;1
"Unit";"Zergling";"Larva";1023;1
"Unit";"Zergling";"Larva";1023;1
"Unit";"Zergling";"Larva";1023;1
"Unit";"Zergling";"Larva";1023;1
"Unit";"Zergling";"Larva";1039;1
"Unit";"Zergling";"Larva";1039;1
"Unit";"Zergling";"Larva";1039;1
"Unit";"Zergling";"Larva";1039;1
"Unit";"Zergling";"Larva";1039;1
"Unit";"Zergling";"Larva";1039;1
"Unit";"Zergling";"Larva";1039;1
"Unit";"Zergling";"Larva";1039;1
"Unit";"Zergling";"Larva";1039;1
"Unit";"Zergling";"Larva";1039;1
"Unit";"Zergling";"Larva";1039;1
"Unit";"Zergling";"Larva";1039;1
"Unit";"Zergling";"Larva";1039;1
"Unit";"Zergling";"Larva";1039;1
"Unit";"Zergling";"Larva";1039;1
"Unit";"Zergling";"Larva";1039;1
"Unit";"Zergling";"Larva";1039;1
"Unit";"Zergling";"Larva";1039;1
"Unit";"Zergling";"Larva";1039;1
"Unit";"Zergling";"Larva";1039;1
"Unit";"Zergling";"Larva";1039;1
"Unit";"Zergling";"Larva";1039;1
"Unit";"Zergling";"Larva";1039;1
"Unit";"Zergling";"Larva";1039;1
"Unit";"Zergling";"Larva";1039;1
"Unit";"Zergling";"Larva";1039;1
"Unit";"Zergling";"Larva";1039;1
"Unit";"Zergling";"Larva";1039;1
"Unit";"Zergling";"Larva";1039;1
"Unit";"Zergling";"Larva";1039;1
"Unit";"Zergling";"Larva";1039;1
"Unit";"Zergling";"Larva";1039;1
"Unit";"Zergling";"Larva";1039;1
"Unit";"Zergling";"Larva";1039;1
"Unit";"Zergling";"Larva";1039;1
"Unit";"Zergling";"Larva";1039;1
"Unit";"Zergling";"Larva";1039;1
"Unit";"Zergling";"Larva";1039;1
"Unit";"Zergling";"Larva";1039;1
"Unit";"Zergling";"Larva";1039;1
"Unit";"Zergling";"Larva";1039;1
"Unit";"Zergling";"Larva";1039;1
"Unit";"Hydralisk";"Larva";1039;2
"Unit";"Hydralisk";"Larva";1039;2
"Unit";"Hydralisk";"Larva";1039;2
"Unit";"Hydralisk";"Larva";1039;2
"Unit";"Baneling";"Zergling";1039;0
"Unit";"Baneling";"Zergling";1039;0
"Unit";"Baneling";"Zergling";1039;0
"Unit";"Baneling";"Zergling";1039;0
"Unit";"Baneling";"Zergling";1039;0
"Unit";"Overlord";"Larva";1039;0
"Unit";"Overlord";"Larva";1039;0
"Unit";"Overlord";"Larva";1039;0
"Unit";"Baneling";"Zergling";1039;0
"Unit";"Overlord";"Larva";1039;0
"Unit";"Overlord";"Larva";1039;0
"Building";"CreepTumor";NA;1089;0
"Building";"CreepTumorQueen";NA;1089;0
"Unit";"Overlord";"Larva";1089;0
"Unit";"Overlord";"Larva";1089;0
"Unit";"Overlord";"Larva";1089;0
"Unit";"Overlord";"Larva";1089;0
"Unit";"Overlord";"Larva";1089;0
"Building";"CreepTumorQueen";NA;1089;0
"Upgrade";"ZergMissileWeaponsLevel3";"EvolutionChamber";1023;0
"Unit";"Baneling";"Zergling";1089;0
"Building";"CreepTumorQueen";NA;1089;0
"Building";"CreepTumorQueen";NA;1089;0
"Unit";"Baneling";"Zergling";1089;0
"Unit";"Baneling";"Zergling";1089;0
"Unit";"Baneling";"Zergling";1089;0
"Unit";"Baneling";"Zergling";1089;0
"Unit";"Baneling";"Zergling";1089;0
"Unit";"Baneling";"Zergling";1089;0
"Unit";"Baneling";"Zergling";1089;0
"Unit";"Baneling";"Zergling";1089;0
"Unit";"Baneling";"Zergling";1089;0
"Unit";"Baneling";"Zergling";1089;0
"Unit";"Baneling";"Zergling";1089;0
"Unit";"Baneling";"Zergling";1089;0
"Unit";"Baneling";"Zergling";1089;0
"Unit";"Baneling";"Zergling";1089;0
"Unit";"Baneling";"Zergling";1089;0
"Unit";"Baneling";"Zergling";1089;0
"Unit";"Baneling";"Zergling";1089;0
"Unit";"Baneling";"Zergling";1089;0
"Unit";"Baneling";"Zergling";1089;0
"Unit";"Baneling";"Zergling";1089;0
"Unit";"Baneling";"Zergling";1089;0
"Unit";"Baneling";"Zergling";1089;0
"Unit";"Baneling";"Zergling";1089;0
"Unit";"Baneling";"Zergling";1089;0
"Building";"CreepTumor";NA;1089;0
"Building";"CreepTumor";NA;1089;0
"Building";"CreepTumor";NA;1089;0
"Building";"Extractor";NA;1089;0
"Building";"CreepTumorQueen";NA;1089;0
"Building";"CreepTumor";NA;1089;0
"Building";"CreepTumorQueen";NA;1089;0
"Upgrade";"Burrow";"Hatchery";1089;0
"Unit";"Zergling";"Larva";1089;1
"Unit";"Zergling";"Larva";1089;1
"Unit";"Zergling";"Larva";1089;1
"Unit";"Zergling";"Larva";1089;1
"Unit";"Zergling";"Larva";1089;1
"Unit";"Zergling";"Larva";1089;1
"Unit";"Zergling";"Larva";1089;1
"Unit";"Zergling";"Larva";1089;1
"Unit";"Zergling";"Larva";1089;1
"Unit";"Zergling";"Larva";1089;1
"Unit";"Zergling";"Larva";1089;1
"Unit";"Zergling";"Larva";1089;1
"Unit";"Zergling";"Larva";1089;1
"Unit";"Zergling";"Larva";1089;1
"Unit";"Zergling";"Larva";1089;1
"Unit";"Zergling";"Larva";1089;1
"Unit";"Zergling";"Larva";1089;1
"Unit";"Zergling";"Larva";1089;1
"Unit";"Zergling";"Larva";1089;1
"Unit";"Zergling";"Larva";1089;1
"Unit";"Zergling";"Larva";1089;1
"Unit";"Zergling";"Larva";1089;1
"Unit";"Zergling";"Larva";1089;1
"Unit";"Zergling";"Larva";1089;1
"Unit";"Zergling";"Larva";1089;1
"Unit";"Zergling";"Larva";1089;1
"Unit";"Zergling";"Larva";1089;1
"Unit";"Zergling";"Larva";1089;1
"Unit";"Zergling";"Larva";1089;1
"Unit";"Zergling";"Larva";1089;1
"Unit";"Zergling";"Larva";1089;1
"Unit";"Zergling";"Larva";1089;1
"Unit";"Zergling";"Larva";1089;1
"Unit";"Zergling";"Larva";1089;1
"Unit";"Zergling";"Larva";1089;1
"Unit";"Zergling";"Larva";1089;1
"Unit";"Zergling";"Larva";1089;1
"Unit";"Zergling";"Larva";1089;1
"Unit";"Zergling";"Larva";1089;1
"Unit";"Zergling";"Larva";1089;1
"Unit";"Zergling";"Larva";1089;1
"Unit";"Zergling";"Larva";1089;1
"Unit";"Zergling";"Larva";1089;1
"Unit";"Zergling";"Larva";1089;1
"Unit";"Zergling";"Larva";1089;1
"Unit";"Zergling";"Larva";1089;1
"Unit";"Zergling";"Larva";1089;1
"Unit";"Zergling";"Larva";1089;1
"Unit";"Zergling";"Larva";1089;1
"Unit";"Zergling";"Larva";1089;1
"Unit";"Zergling";"Larva";1089;1
"Unit";"Zergling";"Larva";1089;1
"Building";"CreepTumorQueen";NA;1089;0
"Building";"CreepTumorQueen";NA;1089;0
"Unit";"Infestor";"Larva";1089;2
"Unit";"Infestor";"Larva";1089;2
"Building";"CreepTumor";NA;1141;0
"Building";"CreepTumorQueen";NA;1141;0
"Building";"CreepTumorQueen";NA;1141;0
"Unit";"Hydralisk";"Larva";1141;2
"Unit";"Hydralisk";"Larva";1141;2
"Unit";"Hydralisk";"Larva";1141;2
"Unit";"Hydralisk";"Larva";1141;2
"Unit";"Hydralisk";"Larva";1141;2
"Unit";"Hydralisk";"Larva";1141;2
"Unit";"Hydralisk";"Larva";1141;2
"Unit";"Hydralisk";"Larva";1141;2
"Unit";"Hydralisk";"Larva";1141;2
"Unit";"Hydralisk";"Larva";1141;2
"Building";"Extractor";NA;1165;0
"Building";"Extractor";NA;1165;0
"Building";"Hatchery";NA;1141;0
"Unit";"Viper";"Larva";1169;3
"Building";"Spire";NA;1145;0
"Building";"CreepTumor";NA;1172;0
"Upgrade";"NeuralParasite";"InfestationPit";1165;0
"Building";"CreepTumorQueen";NA;1172;0
"Building";"CreepTumorQueen";NA;1172;0
"Building";"CreepTumorQueen";NA;1172;0
"Unit";"Viper";"Larva";1172;3
"Unit";"Viper";"Larva";1172;3
"Unit";"Viper";"Larva";1172;3
"Unit";"Zergling";"Larva";1181;1
"Unit";"Zergling";"Larva";1181;1
"Unit";"Zergling";"Larva";1181;1
"Unit";"Zergling";"Larva";1181;1
"Unit";"Zergling";"Larva";1181;1
"Unit";"Zergling";"Larva";1181;1
"Unit";"Zergling";"Larva";1181;1
"Unit";"Zergling";"Larva";1181;1
"Unit";"Zergling";"Larva";1181;1
"Unit";"Zergling";"Larva";1181;1
"Unit";"Zergling";"Larva";1181;1
"Unit";"Zergling";"Larva";1181;1
"Unit";"Zergling";"Larva";1181;1
"Unit";"Zergling";"Larva";1181;1
"Unit";"Zergling";"Larva";1181;1
"Unit";"Zergling";"Larva";1181;1
"Unit";"Zergling";"Larva";1181;1
"Unit";"Zergling";"Larva";1181;1
"Unit";"Zergling";"Larva";1181;1
"Unit";"Zergling";"Larva";1181;1
"Unit";"Zergling";"Larva";1181;1
"Unit";"Zergling";"Larva";1181;1
"Unit";"Zergling";"Larva";1181;1
"Unit";"Zergling";"Larva";1181;1
"Unit";"Zergling";"Larva";1181;1
"Unit";"Zergling";"Larva";1181;1
"Unit";"Zergling";"Larva";1181;1
"Unit";"Zergling";"Larva";1181;1
"Unit";"Zergling";"Larva";1181;1
"Unit";"Zergling";"Larva";1181;1
"Unit";"Zergling";"Larva";1181;1
"Unit";"Zergling";"Larva";1181;1
"Unit";"Zergling";"Larva";1181;1
"Unit";"Zergling";"Larva";1181;1
"Unit";"Zergling";"Larva";1181;1
"Unit";"Zergling";"Larva";1181;1
"Unit";"Zergling";"Larva";1181;1
"Unit";"Zergling";"Larva";1181;1
"Unit";"Zergling";"Larva";1181;1
"Unit";"Zergling";"Larva";1181;1
"Unit";"Zergling";"Larva";1181;1
"Unit";"Zergling";"Larva";1181;1
"Unit";"Zergling";"Larva";1181;1
"Unit";"Zergling";"Larva";1181;1
"Unit";"Zergling";"Larva";1181;1
"Unit";"Zergling";"Larva";1181;1
"Unit";"Zergling";"Larva";1181;1
"Unit";"Zergling";"Larva";1181;1
"Unit";"Zergling";"Larva";1181;1
"Unit";"Zergling";"Larva";1181;1
"Unit";"Zergling";"Larva";1181;1
"Unit";"Zergling";"Larva";1181;1
"Unit";"Zergling";"Larva";1181;1
"Unit";"Zergling";"Larva";1181;1
"Unit";"Zergling";"Larva";1181;1
"Unit";"Zergling";"Larva";1181;1
"Unit";"Zergling";"Larva";1181;1
"Unit";"Zergling";"Larva";1181;1
"Unit";"Zergling";"Larva";1181;1
"Unit";"Zergling";"Larva";1181;1
"Unit";"Zergling";"Larva";1181;1
"Unit";"Zergling";"Larva";1181;1
"Unit";"Zergling";"Larva";1181;1
"Unit";"Zergling";"Larva";1181;1
"Unit";"Zergling";"Larva";1181;1
"Unit";"Zergling";"Larva";1181;1
"Unit";"Zergling";"Larva";1181;1
"Unit";"Zergling";"Larva";1181;1
"Unit";"Zergling";"Larva";1181;1
"Unit";"Zergling";"Larva";1181;1
"Unit";"Zergling";"Larva";1181;1
"Unit";"Zergling";"Larva";1181;1
"Unit";"Zergling";"Larva";1181;1
"Unit";"Zergling";"Larva";1181;1
"Unit";"Zergling";"Larva";1181;1
"Unit";"Zergling";"Larva";1181;1
"Unit";"Zergling";"Larva";1181;1
"Unit";"Zergling";"Larva";1181;1
"Unit";"Zergling";"Larva";1181;1
"Unit";"Zergling";"Larva";1181;1
"Unit";"Zergling";"Larva";1181;1
"Unit";"Zergling";"Larva";1181;1
"Unit";"Zergling";"Larva";1181;1
"Unit";"Zergling";"Larva";1181;1
"Unit";"Zergling";"Larva";1181;1
"Unit";"Zergling";"Larva";1181;1
"Building";"CreepTumor";NA;1267;0
"Unit";"Baneling";"Zergling";1267;0
"Unit";"Baneling";"Zergling";1267;0
"Unit";"Baneling";"Zergling";1267;0
"Unit";"Baneling";"Zergling";1267;0
"Unit";"Baneling";"Zergling";1267;0
"Unit";"Baneling";"Zergling";1267;0
"Unit";"Baneling";"Zergling";1267;0
"Building";"Spire";NA;1181;0
"Building";"CreepTumor";NA;1269;0
"Building";"CreepTumor";NA;1269;0
"Building";"CreepTumorQueen";NA;1269;0
"Building";"CreepTumorQueen";NA;1269;0
"Building";"Extractor";NA;1269;0
"Building";"CreepTumorQueen";NA;1269;0
"Building";"CreepTumorQueen";NA;1269;0
"Building";"Hatchery";NA;1267;0
"Unit";"Zergling";"Larva";1269;1
"Unit";"Zergling";"Larva";1269;1
"Unit";"Zergling";"Larva";1269;1
"Unit";"Zergling";"Larva";1269;1
"Unit";"Zergling";"Larva";1269;1
"Unit";"Zergling";"Larva";1269;1
"Unit";"Zergling";"Larva";1269;1
"Unit";"Zergling";"Larva";1269;1
"Unit";"Zergling";"Larva";1269;1
"Unit";"Zergling";"Larva";1269;1
"Unit";"Zergling";"Larva";1303;1
"Unit";"Zergling";"Larva";1303;1
"Unit";"Zergling";"Larva";1303;1
"Unit";"Zergling";"Larva";1303;1
"Unit";"Zergling";"Larva";1303;1
"Unit";"Zergling";"Larva";1303;1
"Unit";"Zergling";"Larva";1303;1
"Unit";"Zergling";"Larva";1303;1
"Unit";"Hydralisk";"Larva";1303;2
"Unit";"Hydralisk";"Larva";1303;2
"Unit";"Hydralisk";"Larva";1303;2
"Unit";"Hydralisk";"Larva";1303;2
"Unit";"Zergling";"Larva";1304;1
"Unit";"Zergling";"Larva";1304;1
"Unit";"Zergling";"Larva";1304;1
"Unit";"Zergling";"Larva";1304;1
"Unit";"Zergling";"Larva";1304;1
"Unit";"Zergling";"Larva";1304;1
"Unit";"Zergling";"Larva";1304;1
"Unit";"Zergling";"Larva";1304;1
"Unit";"Zergling";"Larva";1304;1
"Unit";"Zergling";"Larva";1304;1
"Unit";"Hydralisk";"Larva";1304;2
"Unit";"Hydralisk";"Larva";1304;2
"Unit";"Hydralisk";"Larva";1304;2
"Unit";"Hydralisk";"Larva";1304;2
"Unit";"Hydralisk";"Larva";1304;2
"Unit";"Hydralisk";"Larva";1304;2
"Building";"CreepTumor";NA;1320;0
"Building";"CreepTumorQueen";NA;1342;0
"Building";"CreepTumor";NA;1338;0
"Building";"CreepTumorQueen";NA;1342;0
"Unit";"Corruptor";"Larva";1320;2
"Unit";"Corruptor";"Larva";1320;2
"Unit";"Corruptor";"Larva";1320;2
"Unit";"Corruptor";"Larva";1320;2
"Unit";"Corruptor";"Larva";1320;2
"Unit";"Corruptor";"Larva";1320;2
"Unit";"Baneling";"Zergling";1342;0
"Unit";"Baneling";"Zergling";1342;0
"Unit";"Baneling";"Zergling";1342;0
"Unit";"Baneling";"Zergling";1342;0
"Building";"CreepTumor";NA;1342;0
"Building";"CreepTumor";NA;1347;0
"Building";"CreepTumorQueen";NA;1359;0
"Unit";"Queen";"Hatchery";1330;2
"Unit";"Corruptor";"Larva";1359;2
"Unit";"Corruptor";"Larva";1359;2
"Unit";"Baneling";"Zergling";1361;0
"Unit";"Baneling";"Zergling";1361;0
"Unit";"Baneling";"Zergling";1361;0
"Unit";"Baneling";"Zergling";1361;0
"Unit";"Baneling";"Zergling";1361;0
"Unit";"Baneling";"Zergling";1361;0
"Unit";"Baneling";"Zergling";1361;0
"Unit";"Baneling";"Zergling";1361;0
"Building";"CreepTumor";NA;1361;0
"Building";"CreepTumor";NA;1361;0
"Building";"CreepTumor";NA;1361;0
"Building";"CreepTumor";NA;1361;0
"Unit";"Viper";"Larva";1359;3
"Unit";"Viper";"Larva";1359;3
"Unit";"Viper";"Larva";1359;3
"Building";"Extractor";NA;1361;0
"Building";"Extractor";NA;1361;0
"Building";"CreepTumor";NA;1370;0
"Building";"Extractor";NA;1379;0
"Unit";"Zergling";"Larva";1379;1
"Unit";"Zergling";"Larva";1379;1
"Unit";"Zergling";"Larva";1379;1
"Unit";"Zergling";"Larva";1379;1
"Unit";"Zergling";"Larva";1379;1
"Unit";"Zergling";"Larva";1379;1
"Unit";"Zergling";"Larva";1379;1
"Unit";"Zergling";"Larva";1379;1
"Unit";"Zergling";"Larva";1379;1
"Unit";"Zergling";"Larva";1379;1
"Unit";"Zergling";"Larva";1379;1
"Unit";"Zergling";"Larva";1379;1
"Unit";"Zergling";"Larva";1379;1
"Unit";"Zergling";"Larva";1379;1
"Unit";"Zergling";"Larva";1379;1
"Unit";"Zergling";"Larva";1379;1
"Unit";"Zergling";"Larva";1379;1
"Unit";"Zergling";"Larva";1379;1
"Unit";"Zergling";"Larva";1379;1
"Unit";"Zergling";"Larva";1379;1
"Unit";"Zergling";"Larva";1379;1
"Unit";"Zergling";"Larva";1379;1
"Unit";"Zergling";"Larva";1379;1
"Unit";"Zergling";"Larva";1379;1
"Unit";"Zergling";"Larva";1379;1
"Unit";"Zergling";"Larva";1379;1
"Unit";"Zergling";"Larva";1379;1
"Unit";"Zergling";"Larva";1379;1
"Unit";"Zergling";"Larva";1379;1
"Unit";"Zergling";"Larva";1379;1
"Unit";"Zergling";"Larva";1379;1
"Unit";"Zergling";"Larva";1379;1
"Unit";"Zergling";"Larva";1379;1
"Unit";"Zergling";"Larva";1379;1
"Unit";"Zergling";"Larva";1379;1
"Unit";"Zergling";"Larva";1379;1
"Unit";"Zergling";"Larva";1379;1
"Unit";"Zergling";"Larva";1379;1
"Unit";"Zergling";"Larva";1379;1
"Unit";"Zergling";"Larva";1379;1
"Unit";"Corruptor";"Larva";1379;2
"Unit";"Baneling";"Zergling";1419;0
"Unit";"Baneling";"Zergling";1419;0
"Unit";"Baneling";"Zergling";1419;0
"Unit";"Baneling";"Zergling";1419;0
"Unit";"Baneling";"Zergling";1419;0
"Unit";"Baneling";"Zergling";1419;0
"Unit";"Baneling";"Zergling";1419;0
"Unit";"Baneling";"Zergling";1419;0
"Unit";"Baneling";"Zergling";1419;0
"Unit";"Baneling";"Zergling";1419;0
"Unit";"Baneling";"Zergling";1419;0
"Unit";"Baneling";"Zergling";1419;0
"Unit";"Baneling";"Zergling";1419;0
"Building";"Extractor";NA;1419;0
"Building";"Extractor";NA;1419;0
"Unit";"Corruptor";"Larva";1421;2
"Unit";"Corruptor";"Larva";1421;2
