"type";"unit_name";"on_building";"total_supply";"supply"
"Unit";"Overlord";"Larva";13;0
"Building";"Extractor";NA;17;0
"Building";"Hatchery";NA;17;0
"Unit";"Overlord";"Larva";22;0
"Building";"SpawningPool";NA;19;0
"Unit";"Zergling";"Larva";23;1
"Unit";"Zergling";"Larva";23;1
"Unit";"Zergling";"Larva";23;1
"Unit";"Zergling";"Larva";23;1
"Unit";"Queen";"Hatchery";23;2
"Unit";"Queen";"Hatchery";23;2
"Unit";"Overlord";"Larva";29;0
"Unit";"Queen";"Hatchery";35;2
"Unit";"Queen";"Hatchery";35;2
"Unit";"Overlord";"Larva";39;0
"Building";"CreepTumorQueen";NA;45;0
"Building";"CreepTumorQueen";NA;45;0
"Unit";"Overlord";"Larva";45;0
"Unit";"Overlord";"Larva";49;0
"Building";"CreepTumorQueen";NA;49;0
"Building";"CreepTumorQueen";NA;51;0
"Building";"CreepTumor";NA;51;0
"Unit";"Zergling";"Larva";53;1
"Unit";"Zergling";"Larva";53;1
"Unit";"Zergling";"Larva";53;1
"Unit";"Zergling";"Larva";53;1
"Unit";"Zergling";"Larva";53;1
"Unit";"Zergling";"Larva";53;1
"Unit";"Zergling";"Larva";53;1
"Unit";"Zergling";"Larva";53;1
"Building";"Hatchery";NA;45;0
"Building";"CreepTumor";NA;63;0
"Building";"Extractor";NA;55;0
"Building";"CreepTumor";NA;63;0
"Building";"CreepTumor";NA;66;0
"Unit";"Overlord";"Larva";63;0
"Building";"EvolutionChamber";NA;55;0
"Building";"EvolutionChamber";NA;55;0
"Unit";"Queen";"Hatchery";55;2
"Unit";"Queen";"Hatchery";55;2
"Unit";"Overlord";"Larva";67;0
"Building";"CreepTumor";NA;77;0
"Building";"CreepTumor";NA;77;0
"Unit";"Queen";"Hatchery";67;2
"Unit";"Zergling";"Larva";73;1
"Unit";"Zergling";"Larva";73;1
"Building";"CreepTumor";NA;77;0
"Building";"CreepTumor";NA;81;0
"Unit";"Overlord";"Larva";85;0
"Unit";"Zergling";"Larva";85;1
"Unit";"Zergling";"Larva";85;1
"Unit";"Zergling";"Larva";85;1
"Unit";"Zergling";"Larva";85;1
"Unit";"Zergling";"Larva";85;1
"Unit";"Zergling";"Larva";85;1
"Unit";"Zergling";"Larva";85;1
"Unit";"Zergling";"Larva";85;1
"Building";"CreepTumor";NA;86;0
"Building";"CreepTumorQueen";NA;91;0
"Building";"CreepTumorQueen";NA;91;0
"Unit";"Overlord";"Larva";85;0
"Building";"CreepTumor";NA;91;0
"Building";"CreepTumor";NA;91;0
"Unit";"Zergling";"Larva";91;1
"Unit";"Zergling";"Larva";91;1
"Unit";"Zergling";"Larva";91;1
"Unit";"Zergling";"Larva";91;1
"Unit";"Zergling";"Larva";91;1
"Unit";"Zergling";"Larva";91;1
"Building";"CreepTumorQueen";NA;99;0
"Building";"CreepTumorQueen";NA;99;0
"Building";"CreepTumorQueen";NA;99;0
"Building";"Extractor";NA;99;0
"Building";"Extractor";NA;99;0
"Unit";"Zergling";"Larva";99;1
"Unit";"Zergling";"Larva";99;1
"Unit";"Zergling";"Larva";99;1
"Unit";"Zergling";"Larva";99;1
"Unit";"Zergling";"Larva";99;1
"Unit";"Zergling";"Larva";99;1
"Unit";"Zergling";"Larva";99;1
"Unit";"Zergling";"Larva";99;1
"Unit";"Zergling";"Larva";99;1
"Unit";"Zergling";"Larva";99;1
"Unit";"Zergling";"Larva";99;1
"Unit";"Zergling";"Larva";99;1
"Unit";"Zergling";"Larva";99;1
"Unit";"Zergling";"Larva";99;1
"Unit";"Zergling";"Larva";99;1
"Unit";"Zergling";"Larva";99;1
"Unit";"Zergling";"Larva";99;1
"Unit";"Zergling";"Larva";99;1
"Unit";"Zergling";"Larva";99;1
"Unit";"Zergling";"Larva";99;1
"Building";"BanelingNest";NA;85;0
"Unit";"Zergling";"Larva";105;1
"Unit";"Zergling";"Larva";105;1
"Unit";"Zergling";"Larva";105;1
"Unit";"Zergling";"Larva";105;1
"Unit";"Zergling";"Larva";105;1
"Unit";"Zergling";"Larva";105;1
"Unit";"Baneling";"Zergling";125;0
"Unit";"Baneling";"Zergling";125;0
"Unit";"Baneling";"Zergling";125;0
"Unit";"Baneling";"Zergling";125;0
"Unit";"Baneling";"Zergling";125;0
"Unit";"Baneling";"Zergling";125;0
"Unit";"Baneling";"Zergling";125;0
"Unit";"Baneling";"Zergling";125;0
"Unit";"Baneling";"Zergling";125;0
"Unit";"Zergling";"Larva";127;1
"Unit";"Zergling";"Larva";127;1
"Unit";"Zergling";"Larva";131;1
"Unit";"Zergling";"Larva";131;1
"Unit";"Zergling";"Larva";131;1
"Unit";"Zergling";"Larva";131;1
"Unit";"Zergling";"Larva";131;1
"Unit";"Zergling";"Larva";131;1
"Unit";"Zergling";"Larva";131;1
"Unit";"Zergling";"Larva";131;1
"Unit";"Zergling";"Larva";131;1
"Unit";"Zergling";"Larva";131;1
"Unit";"Zergling";"Larva";131;1
"Unit";"Zergling";"Larva";131;1
"Unit";"Zergling";"Larva";131;1
"Unit";"Zergling";"Larva";131;1
"Unit";"Zergling";"Larva";131;1
"Unit";"Zergling";"Larva";131;1
"Upgrade";"ZergMeleeWeaponsLevel1";"EvolutionChamber";85;0
"Upgrade";"ZergGroundArmorsLevel1";"EvolutionChamber";85;0
"Unit";"Zergling";"Larva";131;1
"Unit";"Zergling";"Larva";131;1
"Unit";"Zergling";"Larva";131;1
"Unit";"Zergling";"Larva";131;1
"Unit";"Zergling";"Larva";131;1
"Unit";"Zergling";"Larva";131;1
"Unit";"Zergling";"Larva";131;1
"Unit";"Zergling";"Larva";131;1
"Unit";"Zergling";"Larva";131;1
"Unit";"Zergling";"Larva";131;1
"Building";"Hatchery";NA;99;0
"Unit";"Zergling";"Larva";149;1
"Unit";"Zergling";"Larva";149;1
"Unit";"Zergling";"Larva";149;1
"Unit";"Zergling";"Larva";149;1
"Unit";"Zergling";"Larva";159;1
"Unit";"Zergling";"Larva";159;1
"Unit";"Zergling";"Larva";159;1
"Unit";"Zergling";"Larva";159;1
"Unit";"Zergling";"Larva";159;1
"Unit";"Zergling";"Larva";159;1
"Unit";"Overlord";"Larva";163;0
"Building";"CreepTumorQueen";NA;169;0
"Building";"CreepTumorQueen";NA;170;0
"Building";"CreepTumor";NA;175;0
"Building";"Extractor";NA;169;0
"Building";"CreepTumorQueen";NA;175;0
"Building";"CreepTumorQueen";NA;175;0
"Building";"CreepTumor";NA;175;0
"Building";"Extractor";NA;169;0
"Building";"Extractor";NA;175;0
"Building";"Extractor";NA;175;0
"Unit";"Zergling";"Larva";175;1
"Unit";"Zergling";"Larva";175;1
"Unit";"Zergling";"Larva";175;1
"Unit";"Zergling";"Larva";175;1
"Unit";"Zergling";"Larva";175;1
"Unit";"Zergling";"Larva";175;1
"Unit";"Zergling";"Larva";175;1
"Unit";"Zergling";"Larva";175;1
"Unit";"Zergling";"Larva";175;1
"Unit";"Zergling";"Larva";175;1
"Unit";"Zergling";"Larva";175;1
"Unit";"Zergling";"Larva";175;1
"Unit";"Zergling";"Larva";175;1
"Unit";"Zergling";"Larva";175;1
"Building";"Hatchery";NA;159;0
"Building";"CreepTumor";NA;191;0
"Building";"CreepTumor";NA;192;0
"Unit";"Baneling";"Zergling";189;0
"Unit";"Baneling";"Zergling";189;0
"Unit";"Baneling";"Zergling";189;0
"Unit";"Baneling";"Zergling";189;0
"Unit";"Baneling";"Zergling";189;0
"Unit";"Baneling";"Zergling";189;0
"Building";"CreepTumor";NA;192;0
"Unit";"Baneling";"Zergling";189;0
"Building";"CreepTumor";NA;192;0
"Building";"CreepTumor";NA;192;0
"Building";"CreepTumor";NA;192;0
"Building";"HydraliskDen";NA;175;0
"Building";"CreepTumor";NA;196;0
"Building";"RoachWarren";NA;189;0
"Unit";"Hydralisk";"Larva";201;2
"Unit";"Hydralisk";"Larva";201;2
"Unit";"Hydralisk";"Larva";201;2
"Unit";"Hydralisk";"Larva";201;2
"Unit";"Hydralisk";"Larva";201;2
"Unit";"Hydralisk";"Larva";201;2
"Unit";"Hydralisk";"Larva";201;2
"Building";"CreepTumor";NA;204;0
"Unit";"Overlord";"Larva";201;0
"Unit";"Overlord";"Larva";201;0
"Building";"CreepTumor";NA;206;0
"Unit";"Overlord";"Larva";201;0
"Building";"CreepTumor";NA;218;0
"Building";"CreepTumor";NA;219;0
"Unit";"Overlord";"Larva";201;0
"Building";"CreepTumor";NA;224;0
"Building";"CreepTumor";NA;224;0
"Unit";"Hydralisk";"Larva";204;2
"Unit";"Hydralisk";"Larva";204;2
"Upgrade";"ZergMeleeWeaponsLevel2";"EvolutionChamber";175;0
"Unit";"Overlord";"Larva";224;0
"Building";"InfestationPit";NA;201;0
"Unit";"Baneling";"Zergling";224;0
"Unit";"Baneling";"Zergling";224;0
"Unit";"Overlord";"Larva";224;0
"Unit";"Zergling";"Larva";224;1
"Unit";"Zergling";"Larva";224;1
"Unit";"Hydralisk";"Larva";224;2
"Unit";"Hydralisk";"Larva";224;2
"Unit";"Hydralisk";"Larva";224;2
"Unit";"Hydralisk";"Larva";224;2
"Unit";"Hydralisk";"Larva";224;2
"Unit";"Hydralisk";"Larva";224;2
"Unit";"Hydralisk";"Larva";224;2
"Unit";"Hydralisk";"Larva";224;2
"Unit";"Roach";"Larva";224;2
"Unit";"Zergling";"Larva";228;1
"Unit";"Zergling";"Larva";228;1
"Upgrade";"EvolveGroovedSpines";"HydraliskDen";201;0
"Building";"CreepTumor";NA;228;0
"Unit";"Hydralisk";"Larva";228;2
"Unit";"Hydralisk";"Larva";228;2
"Unit";"Hydralisk";"Larva";228;2
"Building";"CreepTumor";NA;246;0
"Unit";"Zergling";"Larva";228;1
"Unit";"Zergling";"Larva";228;1
"Building";"CreepTumor";NA;248;0
"Upgrade";"ZergMissileWeaponsLevel1";"EvolutionChamber";198;0
"Unit";"Queen";"Hatchery";228;2
"Building";"CreepTumorQueen";NA;258;0
"Unit";"Overlord";"Larva";258;0
"Unit";"Overlord";"Larva";260;0
"Unit";"Overlord";"Larva";260;0
"Unit";"Overlord";"Larva";260;0
"Building";"CreepTumor";NA;260;0
"Building";"CreepTumorQueen";NA;260;0
"Building";"CreepTumor";NA;260;0
"Building";"CreepTumor";NA;260;0
"Unit";"Overlord";"Larva";260;0
"Unit";"Overlord";"Larva";260;0
"Unit";"Overlord";"Larva";260;0
"Unit";"Hydralisk";"Larva";260;2
"Unit";"Hydralisk";"Larva";260;2
"Unit";"Hydralisk";"Larva";260;2
"Unit";"Hydralisk";"Larva";260;2
"Unit";"Hydralisk";"Larva";260;2
"Building";"Hatchery";NA;258;0
"Building";"CreepTumor";NA;260;0
"Building";"CreepTumor";NA;260;0
"Building";"CreepTumor";NA;270;0
"Building";"SpineCrawler";NA;260;0
"Building";"SpineCrawler";NA;260;0
"Building";"SpineCrawler";NA;260;0
"Building";"SpineCrawler";NA;260;0
"Building";"SpineCrawler";NA;260;0
"Building";"CreepTumor";NA;270;0
"Unit";"Zergling";"Larva";270;1
"Unit";"Zergling";"Larva";270;1
"Unit";"Zergling";"Larva";270;1
"Unit";"Zergling";"Larva";270;1
"Unit";"Zergling";"Larva";270;1
"Unit";"Zergling";"Larva";270;1
"Unit";"Zergling";"Larva";270;1
"Unit";"Zergling";"Larva";270;1
"Unit";"Hydralisk";"Larva";270;2
"Unit";"Hydralisk";"Larva";270;2
"Unit";"Hydralisk";"Larva";270;2
"Unit";"Hydralisk";"Larva";270;2
"Unit";"Hydralisk";"Larva";270;2
"Unit";"Hydralisk";"Larva";270;2
"Unit";"Hydralisk";"Larva";270;2
"Building";"CreepTumor";NA;284;0
"Upgrade";"ZergMissileWeaponsLevel2";"EvolutionChamber";260;0
"Building";"CreepTumor";NA;296;0
"Building";"NydusNetwork";NA;270;0
"Building";"NydusNetwork";NA;270;0
"Building";"NydusNetwork";NA;270;0
"Building";"CreepTumorQueen";NA;296;0
"Building";"Extractor";NA;282;0
"Building";"CreepTumorQueen";NA;296;0
"Building";"Extractor";NA;296;0
"Building";"CreepTumorQueen";NA;296;0
"Building";"CreepTumorQueen";NA;296;0
"Upgrade";"EvolveMuscularAugments";"HydraliskDen";270;0
"Building";"SpineCrawler";NA;296;0
"Building";"SpineCrawler";NA;296;0
"Building";"CreepTumor";NA;296;0
"Building";"CreepTumor";NA;296;0
"Unit";"Hydralisk";"Larva";296;2
"Unit";"Hydralisk";"Larva";296;2
"Unit";"Hydralisk";"Larva";296;2
"Building";"CreepTumor";NA;296;0
"Building";"CreepTumor";NA;296;0
"Building";"CreepTumor";NA;296;0
"Building";"SporeCrawler";NA;302;0
"Building";"CreepTumor";NA;302;0
"Building";"CreepTumor";NA;302;0
"Unit";"Hydralisk";"Larva";302;2
"Unit";"Hydralisk";"Larva";302;2
"Unit";"Hydralisk";"Larva";302;2
"Unit";"Hydralisk";"Larva";302;2
"Unit";"Hydralisk";"Larva";302;2
"Unit";"Hydralisk";"Larva";302;2
"Unit";"Hydralisk";"Larva";302;2
"Unit";"Hydralisk";"Larva";302;2
"Unit";"Hydralisk";"Larva";302;2
"Unit";"Hydralisk";"Larva";302;2
"Unit";"Hydralisk";"Larva";302;2
"Unit";"Hydralisk";"Larva";302;2
"Unit";"Hydralisk";"Larva";302;2
"Unit";"Hydralisk";"Larva";302;2
"Unit";"Hydralisk";"Larva";302;2
"Building";"CreepTumor";NA;302;0
"Building";"CreepTumor";NA;302;0
"Unit";"Zergling";"Larva";302;1
"Unit";"Zergling";"Larva";302;1
"Unit";"Zergling";"Larva";302;1
"Unit";"Zergling";"Larva";302;1
"Unit";"Zergling";"Larva";302;1
"Unit";"Zergling";"Larva";302;1
"Unit";"Zergling";"Larva";302;1
"Unit";"Zergling";"Larva";302;1
"Unit";"Zergling";"Larva";302;1
"Unit";"Zergling";"Larva";302;1
"Unit";"Hydralisk";"Larva";302;2
"Unit";"Hydralisk";"Larva";302;2
"Unit";"Hydralisk";"Larva";302;2
"Unit";"Hydralisk";"Larva";302;2
"Unit";"Hydralisk";"Larva";302;2
"Unit";"Hydralisk";"Larva";302;2
"Unit";"Hydralisk";"Larva";302;2
"Unit";"Zergling";"Larva";359;1
"Unit";"Zergling";"Larva";359;1
"Unit";"Zergling";"Larva";359;1
"Unit";"Zergling";"Larva";359;1
"Unit";"Zergling";"Larva";359;1
"Unit";"Zergling";"Larva";359;1
"Unit";"Zergling";"Larva";359;1
"Unit";"Zergling";"Larva";359;1
"Unit";"Zergling";"Larva";359;1
"Unit";"Zergling";"Larva";359;1
"Upgrade";"ZergGroundArmorsLevel2";"EvolutionChamber";302;0
"Unit";"Hydralisk";"Larva";359;2
"Building";"NydusCanal";NA;359;0
"Building";"NydusCanal";NA;369;0
"Building";"NydusCanal";NA;369;0
"Unit";"Hydralisk";"Larva";371;2
"Unit";"Hydralisk";"Larva";371;2
"Unit";"Hydralisk";"Larva";371;2
"Unit";"Hydralisk";"Larva";371;2
"Unit";"Hydralisk";"Larva";371;2
"Unit";"Hydralisk";"Larva";371;2
"Building";"NydusCanal";NA;371;0
"Building";"NydusCanal";NA;371;0
"Building";"CreepTumor";NA;371;0
"Unit";"Hydralisk";"Larva";371;2
"Unit";"Hydralisk";"Larva";375;2
"Unit";"Hydralisk";"Larva";375;2
"Building";"NydusCanal";NA;383;0
"Building";"NydusCanal";NA;383;0
"Unit";"Hydralisk";"Larva";389;2
"Unit";"Hydralisk";"Larva";389;2
"Unit";"Hydralisk";"Larva";389;2
"Unit";"Hydralisk";"Larva";389;2
"Unit";"Hydralisk";"Larva";389;2
"Unit";"Hydralisk";"Larva";389;2
"Unit";"Hydralisk";"Larva";389;2
"Unit";"Hydralisk";"Larva";389;2
"Unit";"Hydralisk";"Larva";389;2
"Unit";"Hydralisk";"Larva";389;2
"Unit";"Hydralisk";"Larva";389;2
"Upgrade";"ZergMissileWeaponsLevel3";"EvolutionChamber";359;0
