"type";"unit_name";"on_building";"total_supply";"supply"
"Unit";"Overlord";"Larva";12;0
"Building";"Extractor";NA;18;0
"Building";"SpawningPool";NA;19;0
"Unit";"Overlord";"Larva";21;0
"Building";"Hatchery";NA;17;0
"Unit";"Zergling";"Larva";22;1
"Unit";"Zergling";"Larva";22;1
"Unit";"Zergling";"Larva";22;1
"Unit";"Zergling";"Larva";22;1
"Unit";"Zergling";"Larva";22;1
"Unit";"Zergling";"Larva";22;1
"Unit";"Queen";"Hatchery";22;2
"Unit";"Queen";"Hatchery";22;2
"Unit";"Overlord";"Larva";36;0
"Unit";"Overlord";"Larva";37;0
"Unit";"Queen";"Hatchery";36;2
"Building";"CreepTumorQueen";NA;40;0
"Unit";"Overlord";"Larva";40;0
"Unit";"Overlord";"Larva";40;0
"Building";"Hatchery";NA;30;0
"Unit";"Zergling";"Larva";48;1
"Unit";"Zergling";"Larva";48;1
"Unit";"Zergling";"Larva";48;1
"Unit";"Zergling";"Larva";48;1
"Building";"CreepTumor";NA;50;0
"Building";"CreepTumorQueen";NA;50;0
"Building";"EvolutionChamber";NA;50;0
"Unit";"Zergling";"Larva";50;1
"Unit";"Zergling";"Larva";50;1
"Unit";"Zergling";"Larva";50;1
"Unit";"Zergling";"Larva";50;1
"Unit";"Queen";"Hatchery";50;2
"Unit";"Queen";"Hatchery";50;2
"Unit";"Queen";"Hatchery";50;2
"Building";"CreepTumor";NA;63;0
"Building";"CreepTumor";NA;64;0
"Building";"CreepTumorQueen";NA;66;0
"Building";"CreepTumorQueen";NA;72;0
"Unit";"Overlord";"Larva";70;0
"Unit";"Overlord";"Larva";70;0
"Unit";"Zergling";"Larva";72;1
"Unit";"Zergling";"Larva";72;1
"Building";"CreepTumorQueen";NA;72;0
"Unit";"Zergling";"Larva";72;1
"Unit";"Zergling";"Larva";72;1
"Building";"CreepTumor";NA;72;0
"Unit";"Zergling";"Larva";72;1
"Unit";"Zergling";"Larva";72;1
"Building";"CreepTumor";NA;72;0
"Building";"CreepTumor";NA;72;0
"Unit";"Overlord";"Larva";72;0
"Unit";"Overlord";"Larva";72;0
"Unit";"Zergling";"Larva";72;1
"Unit";"Zergling";"Larva";72;1
"Unit";"Zergling";"Larva";72;1
"Unit";"Zergling";"Larva";72;1
"Unit";"Zergling";"Larva";72;1
"Unit";"Zergling";"Larva";72;1
"Unit";"Queen";"Hatchery";72;2
"Unit";"Queen";"Hatchery";72;2
"Building";"SporeCrawler";NA;78;0
"Building";"SporeCrawler";NA;82;0
"Building";"SporeCrawler";NA;86;0
"Building";"CreepTumor";NA;95;0
"Building";"CreepTumor";NA;95;0
"Building";"CreepTumor";NA;95;0
"Building";"CreepTumor";NA;95;0
"Unit";"Overlord";"Larva";95;0
"Unit";"Overlord";"Larva";95;0
"Unit";"Overlord";"Larva";95;0
"Building";"EvolutionChamber";NA;100;0
"Building";"Extractor";NA;100;0
"Building";"Extractor";NA;100;0
"Building";"Extractor";NA;100;0
"Building";"Extractor";NA;100;0
"Building";"Extractor";NA;100;0
"Building";"CreepTumorQueen";NA;104;0
"Upgrade";"ZergGroundArmorsLevel1";"EvolutionChamber";72;0
"Building";"CreepTumorQueen";NA;114;0
"Building";"CreepTumor";NA;114;0
"Building";"CreepTumor";NA;114;0
"Building";"CreepTumor";NA;114;0
"Building";"CreepTumor";NA;114;0
"Building";"CreepTumorQueen";NA;119;0
"Unit";"Zergling";"Larva";119;1
"Unit";"Zergling";"Larva";119;1
"Unit";"Zergling";"Larva";119;1
"Unit";"Zergling";"Larva";119;1
"Unit";"Zergling";"Larva";119;1
"Unit";"Zergling";"Larva";119;1
"Unit";"Zergling";"Larva";119;1
"Unit";"Zergling";"Larva";119;1
"Unit";"Zergling";"Larva";119;1
"Unit";"Zergling";"Larva";119;1
"Building";"CreepTumor";NA;129;0
"Building";"BanelingNest";NA;119;0
"Building";"RoachWarren";NA;121;0
"Building";"CreepTumor";NA;134;0
"Building";"CreepTumorQueen";NA;134;0
"Building";"CreepTumorQueen";NA;134;0
"Building";"CreepTumorQueen";NA;134;0
"Building";"CreepTumorQueen";NA;134;0
"Building";"CreepTumor";NA;134;0
"Building";"CreepTumor";NA;134;0
"Building";"CreepTumorQueen";NA;134;0
"Unit";"Overlord";"Larva";148;0
"Unit";"Overlord";"Larva";148;0
"Unit";"Overlord";"Larva";148;0
"Unit";"Overlord";"Larva";148;0
"Building";"Hatchery";NA;119;0
"Unit";"Roach";"Larva";148;2
"Unit";"Roach";"Larva";148;2
"Unit";"Roach";"Larva";148;2
"Building";"CreepTumor";NA;148;0
"Building";"CreepTumor";NA;148;0
"Building";"Hatchery";NA;119;0
"Building";"CreepTumor";NA;148;0
"Building";"CreepTumor";NA;148;0
"Building";"CreepTumor";NA;148;0
"Building";"CreepTumorQueen";NA;148;0
"Building";"CreepTumor";NA;148;0
"Building";"CreepTumor";NA;148;0
"Unit";"Roach";"Larva";154;2
"Unit";"Roach";"Larva";154;2
"Unit";"Roach";"Larva";154;2
"Unit";"Roach";"Larva";154;2
"Unit";"Roach";"Larva";154;2
"Unit";"Roach";"Larva";154;2
"Unit";"Roach";"Larva";154;2
"Unit";"Roach";"Larva";154;2
"Unit";"Roach";"Larva";154;2
"Unit";"Overlord";"Larva";154;0
"Unit";"Overlord";"Larva";154;0
"Unit";"Roach";"Larva";154;2
"Unit";"Roach";"Larva";154;2
"Unit";"Roach";"Larva";154;2
"Unit";"Roach";"Larva";154;2
"Unit";"Roach";"Larva";154;2
"Unit";"Roach";"Larva";154;2
"Building";"CreepTumor";NA;172;0
"Upgrade";"ZergMeleeWeaponsLevel1";"EvolutionChamber";134;0
"Unit";"Roach";"Larva";172;2
"Unit";"Roach";"Larva";172;2
"Unit";"Roach";"Larva";172;2
"Unit";"Roach";"Larva";172;2
"Unit";"Roach";"Larva";172;2
"Unit";"Roach";"Larva";172;2
"Building";"CreepTumorQueen";NA;184;0
"Building";"CreepTumorQueen";NA;184;0
"Building";"CreepTumorQueen";NA;184;0
"Building";"HydraliskDen";NA;172;0
"Unit";"Overlord";"Larva";184;0
"Unit";"Overlord";"Larva";184;0
"Unit";"Overlord";"Larva";184;0
"Unit";"Roach";"Larva";188;2
"Unit";"Roach";"Larva";196;2
"Unit";"Roach";"Larva";196;2
"Unit";"Roach";"Larva";196;2
"Unit";"Roach";"Larva";196;2
"Unit";"Roach";"Larva";196;2
"Unit";"Roach";"Larva";196;2
"Unit";"Roach";"Larva";196;2
"Unit";"Roach";"Larva";196;2
"Unit";"Roach";"Larva";196;2
"Unit";"Roach";"Larva";196;2
"Building";"CreepTumor";NA;196;0
"Building";"CreepTumor";NA;196;0
"Building";"CreepTumor";NA;196;0
"Building";"CreepTumor";NA;196;0
"Upgrade";"ZergMissileWeaponsLevel1";"EvolutionChamber";148;0
"Building";"CreepTumor";NA;196;0
"Upgrade";"GlialReconstitution";"RoachWarren";184;0
"Unit";"Hydralisk";"Larva";218;2
"Unit";"Hydralisk";"Larva";218;2
"Unit";"Hydralisk";"Larva";218;2
"Unit";"Hydralisk";"Larva";218;2
"Unit";"Hydralisk";"Larva";218;2
"Unit";"Hydralisk";"Larva";218;2
"Unit";"Hydralisk";"Larva";218;2
"Unit";"Hydralisk";"Larva";218;2
"Unit";"Hydralisk";"Larva";218;2
"Unit";"Hydralisk";"Larva";218;2
"Unit";"Hydralisk";"Larva";218;2
"Unit";"Hydralisk";"Larva";218;2
"Unit";"Hydralisk";"Larva";218;2
