"type";"unit_name";"on_building";"total_supply";"supply"
"Unit";"Overlord";"Larva";13;0
"Building";"Extractor";NA;17;0
"Building";"SpawningPool";NA;19;0
"Building";"Hatchery";NA;17;0
"Unit";"Overlord";"Larva";22;0
"Unit";"Zergling";"Larva";22;1
"Unit";"Zergling";"Larva";22;1
"Unit";"Zergling";"Larva";22;1
"Unit";"Zergling";"Larva";22;1
"Unit";"Queen";"Hatchery";22;2
"Unit";"Queen";"Hatchery";22;2
"Unit";"Overlord";"Larva";35;0
"Unit";"Queen";"Hatchery";35;2
"Unit";"Overlord";"Larva";35;0
"Building";"CreepTumorQueen";NA;39;0
"Building";"Hatchery";NA;24;0
"Unit";"Overlord";"Larva";48;0
"Building";"CreepTumor";NA;50;0
"Building";"CreepTumorQueen";NA;50;0
"Unit";"Zergling";"Larva";50;1
"Unit";"Zergling";"Larva";50;1
"Unit";"Zergling";"Larva";50;1
"Unit";"Zergling";"Larva";50;1
"Unit";"Zergling";"Larva";50;1
"Unit";"Zergling";"Larva";50;1
"Unit";"Zergling";"Larva";50;1
"Unit";"Zergling";"Larva";50;1
"Unit";"Queen";"Hatchery";46;2
"Unit";"Zergling";"Larva";50;1
"Unit";"Zergling";"Larva";50;1
"Unit";"Zergling";"Larva";50;1
"Unit";"Zergling";"Larva";50;1
"Building";"CreepTumorQueen";NA;50;0
"Unit";"Queen";"Hatchery";50;2
"Unit";"Overlord";"Larva";58;0
"Building";"CreepTumor";NA;70;0
"Building";"CreepTumor";NA;73;0
"Building";"CreepTumor";NA;73;0
"Building";"CreepTumorQueen";NA;73;0
"Building";"CreepTumorQueen";NA;73;0
"Unit";"Overlord";"Larva";73;0
"Unit";"Queen";"Hatchery";68;2
"Building";"SporeCrawler";NA;75;0
"Building";"SporeCrawler";NA;76;0
"Building";"SporeCrawler";NA;76;0
"Unit";"Queen";"Hatchery";73;2
"Unit";"Zergling";"Larva";79;1
"Unit";"Zergling";"Larva";79;1
"Unit";"Zergling";"Larva";79;1
"Unit";"Zergling";"Larva";79;1
"Building";"EvolutionChamber";NA;76;0
"Building";"EvolutionChamber";NA;76;0
"Unit";"Zergling";"Larva";80;1
"Unit";"Zergling";"Larva";80;1
"Unit";"Zergling";"Larva";80;1
"Unit";"Zergling";"Larva";80;1
"Unit";"Zergling";"Larva";80;1
"Unit";"Zergling";"Larva";80;1
"Unit";"Zergling";"Larva";82;1
"Unit";"Zergling";"Larva";82;1
"Unit";"Zergling";"Larva";83;1
"Unit";"Zergling";"Larva";83;1
"Building";"SpineCrawler";NA;76;0
"Building";"CreepTumor";NA;96;0
"Building";"CreepTumor";NA;96;0
"Building";"CreepTumor";NA;106;0
"Building";"CreepTumor";NA;106;0
"Building";"CreepTumor";NA;106;0
"Building";"CreepTumorQueen";NA;112;0
"Building";"CreepTumorQueen";NA;112;0
"Building";"CreepTumor";NA;115;0
"Building";"CreepTumor";NA;115;0
"Building";"Extractor";NA;114;0
"Building";"Extractor";NA;114;0
"Building";"CreepTumor";NA;124;0
"Building";"CreepTumor";NA;124;0
"Building";"CreepTumor";NA;125;0
"Building";"CreepTumor";NA;125;0
"Building";"CreepTumor";NA;125;0
"Building";"Extractor";NA;121;0
"Unit";"Overlord";"Larva";126;0
"Unit";"Overlord";"Larva";126;0
"Unit";"Overlord";"Larva";126;0
"Building";"BanelingNest";NA;115;0
"Unit";"Overlord";"Larva";127;0
"Unit";"Overlord";"Larva";127;0
"Unit";"Overlord";"Larva";127;0
"Unit";"Overlord";"Larva";129;0
"Building";"Extractor";NA;128;0
"Building";"CreepTumor";NA;133;0
"Building";"CreepTumor";NA;133;0
"Building";"CreepTumorQueen";NA;133;0
"Building";"CreepTumorQueen";NA;133;0
"Building";"CreepTumorQueen";NA;133;0
"Unit";"Zergling";"Larva";133;1
"Unit";"Zergling";"Larva";133;1
"Unit";"Zergling";"Larva";133;1
"Unit";"Zergling";"Larva";133;1
"Unit";"Zergling";"Larva";133;1
"Unit";"Zergling";"Larva";133;1
"Unit";"Zergling";"Larva";133;1
"Unit";"Zergling";"Larva";133;1
"Building";"CreepTumor";NA;135;0
"Building";"CreepTumor";NA;136;0
"Unit";"Zergling";"Larva";133;1
"Unit";"Zergling";"Larva";133;1
"Unit";"Zergling";"Larva";133;1
"Unit";"Zergling";"Larva";133;1
"Unit";"Zergling";"Larva";133;1
"Unit";"Zergling";"Larva";133;1
"Unit";"Zergling";"Larva";133;1
"Unit";"Zergling";"Larva";133;1
"Unit";"Zergling";"Larva";133;1
"Unit";"Zergling";"Larva";133;1
"Unit";"Zergling";"Larva";133;1
"Unit";"Zergling";"Larva";133;1
"Building";"CreepTumor";NA;144;0
"Building";"CreepTumor";NA;146;0
"Building";"CreepTumor";NA;156;0
"Unit";"Overlord";"Larva";144;0
"Building";"CreepTumor";NA;158;0
"Building";"CreepTumor";NA;158;0
"Building";"CreepTumorQueen";NA;158;0
"Building";"CreepTumorQueen";NA;158;0
"Building";"HydraliskDen";NA;144;0
"Unit";"Baneling";"Zergling";158;0
"Unit";"Baneling";"Zergling";158;0
"Unit";"Baneling";"Zergling";158;0
"Unit";"Baneling";"Zergling";158;0
"Unit";"Baneling";"Zergling";158;0
"Unit";"Baneling";"Zergling";158;0
"Unit";"Baneling";"Zergling";158;0
"Unit";"Baneling";"Zergling";158;0
"Unit";"Baneling";"Zergling";158;0
"Unit";"Baneling";"Zergling";158;0
"Unit";"Zergling";"Larva";158;1
"Unit";"Zergling";"Larva";158;1
"Unit";"Baneling";"Zergling";164;0
"Unit";"Baneling";"Zergling";164;0
"Unit";"Zergling";"Larva";164;1
"Unit";"Zergling";"Larva";164;1
"Building";"CreepTumor";NA;168;0
"Building";"CreepTumor";NA;168;0
"Unit";"Zergling";"Larva";164;1
"Unit";"Zergling";"Larva";164;1
"Unit";"Zergling";"Larva";164;1
"Unit";"Zergling";"Larva";164;1
"Unit";"Zergling";"Larva";164;1
"Unit";"Zergling";"Larva";164;1
"Building";"CreepTumor";NA;168;0
"Building";"CreepTumor";NA;168;0
"Unit";"Zergling";"Larva";164;1
"Unit";"Zergling";"Larva";164;1
"Building";"CreepTumor";NA;168;0
"Building";"CreepTumor";NA;168;0
"Building";"CreepTumor";NA;168;0
"Unit";"Zergling";"Larva";168;1
"Unit";"Zergling";"Larva";168;1
"Unit";"Zergling";"Larva";168;1
"Unit";"Zergling";"Larva";168;1
"Unit";"Zergling";"Larva";168;1
"Unit";"Zergling";"Larva";168;1
"Upgrade";"ZergMeleeWeaponsLevel1";"EvolutionChamber";129;0
"Unit";"Zergling";"Larva";168;1
"Unit";"Zergling";"Larva";168;1
"Unit";"Zergling";"Larva";168;1
"Unit";"Zergling";"Larva";168;1
"Unit";"Zergling";"Larva";168;1
"Unit";"Zergling";"Larva";168;1
"Unit";"Zergling";"Larva";168;1
"Unit";"Zergling";"Larva";168;1
"Building";"Hatchery";NA;133;0
"Building";"CreepTumor";NA;186;0
"Unit";"Overlord";"Larva";176;0
"Unit";"Overlord";"Larva";176;0
"Building";"CreepTumor";NA;192;0
"Unit";"Hydralisk";"Larva";170;2
"Unit";"Overlord";"Larva";192;0
"Unit";"Overlord";"Larva";192;0
"Building";"CreepTumor";NA;193;0
"Building";"CreepTumor";NA;193;0
"Building";"CreepTumor";NA;194;0
"Building";"CreepTumor";NA;196;0
"Building";"CreepTumor";NA;196;0
"Building";"CreepTumor";NA;196;0
"Building";"CreepTumor";NA;196;0
"Building";"CreepTumor";NA;202;0
"Unit";"Overlord";"Larva";196;0
"Building";"CreepTumor";NA;202;0
"Unit";"Zergling";"Larva";196;1
"Unit";"Zergling";"Larva";196;1
"Unit";"Hydralisk";"Larva";196;2
"Unit";"Hydralisk";"Larva";202;2
"Building";"CreepTumor";NA;208;0
"Building";"CreepTumor";NA;208;0
"Unit";"Hydralisk";"Larva";206;2
"Unit";"Hydralisk";"Larva";206;2
"Unit";"Hydralisk";"Larva";206;2
"Unit";"Hydralisk";"Larva";206;2
"Unit";"Baneling";"Zergling";208;0
"Unit";"Baneling";"Zergling";208;0
"Unit";"Baneling";"Zergling";208;0
"Unit";"Baneling";"Zergling";208;0
"Upgrade";"EvolveGroovedSpines";"HydraliskDen";192;0
"Unit";"Zergling";"Larva";208;1
"Unit";"Zergling";"Larva";208;1
"Unit";"Zergling";"Larva";208;1
"Unit";"Zergling";"Larva";208;1
"Unit";"Zergling";"Larva";208;1
"Unit";"Zergling";"Larva";208;1
"Unit";"Hydralisk";"Larva";208;2
"Unit";"Hydralisk";"Larva";208;2
"Unit";"Hydralisk";"Larva";208;2
"Unit";"Baneling";"Zergling";210;0
"Unit";"Hydralisk";"Larva";208;2
"Unit";"Baneling";"Zergling";210;0
"Unit";"Baneling";"Zergling";210;0
"Unit";"Baneling";"Zergling";212;0
"Unit";"Baneling";"Zergling";212;0
"Unit";"Zergling";"Larva";212;1
"Unit";"Zergling";"Larva";212;1
"Unit";"Zergling";"Larva";212;1
"Unit";"Zergling";"Larva";212;1
"Unit";"Zergling";"Larva";212;1
"Unit";"Zergling";"Larva";212;1
"Unit";"Zergling";"Larva";212;1
"Unit";"Zergling";"Larva";212;1
"Unit";"Zergling";"Larva";212;1
"Unit";"Zergling";"Larva";212;1
"Upgrade";"ZergGroundArmorsLevel1";"EvolutionChamber";168;0
"Unit";"Zergling";"Larva";216;1
"Unit";"Zergling";"Larva";216;1
"Unit";"Zergling";"Larva";216;1
"Unit";"Zergling";"Larva";216;1
"Unit";"Zergling";"Larva";216;1
"Unit";"Zergling";"Larva";216;1
"Building";"CreepTumor";NA;220;0
"Unit";"Zergling";"Larva";220;1
"Unit";"Zergling";"Larva";220;1
"Building";"CreepTumor";NA;222;0
"Building";"CreepTumor";NA;234;0
"Building";"CreepTumor";NA;234;0
"Unit";"Zergling";"Larva";220;1
"Unit";"Zergling";"Larva";220;1
"Unit";"Zergling";"Larva";220;1
"Unit";"Zergling";"Larva";220;1
"Unit";"Zergling";"Larva";220;1
"Unit";"Zergling";"Larva";220;1
"Building";"CreepTumor";NA;234;0
"Building";"Hatchery";NA;192;0
"Unit";"Zergling";"Larva";226;1
"Unit";"Zergling";"Larva";226;1
"Unit";"Zergling";"Larva";234;1
"Unit";"Zergling";"Larva";234;1
"Unit";"Zergling";"Larva";234;1
"Unit";"Zergling";"Larva";234;1
"Unit";"Zergling";"Larva";242;1
"Unit";"Zergling";"Larva";242;1
"Unit";"Zergling";"Larva";244;1
"Unit";"Zergling";"Larva";244;1
"Unit";"Zergling";"Larva";244;1
"Unit";"Zergling";"Larva";244;1
"Unit";"Baneling";"Zergling";260;0
"Unit";"Baneling";"Zergling";260;0
"Unit";"Baneling";"Zergling";260;0
"Unit";"Baneling";"Zergling";260;0
"Unit";"Baneling";"Zergling";260;0
"Unit";"Baneling";"Zergling";260;0
"Unit";"Baneling";"Zergling";260;0
"Unit";"Baneling";"Zergling";260;0
"Unit";"Baneling";"Zergling";260;0
"Unit";"Baneling";"Zergling";260;0
"Unit";"Baneling";"Zergling";260;0
"Unit";"Baneling";"Zergling";260;0
"Unit";"Zergling";"Larva";264;1
"Unit";"Zergling";"Larva";264;1
"Unit";"Zergling";"Larva";264;1
"Unit";"Zergling";"Larva";264;1
"Unit";"Zergling";"Larva";264;1
"Unit";"Zergling";"Larva";264;1
"Unit";"Zergling";"Larva";264;1
"Unit";"Zergling";"Larva";264;1
"Unit";"Zergling";"Larva";264;1
"Unit";"Zergling";"Larva";264;1
"Unit";"Zergling";"Larva";264;1
"Unit";"Zergling";"Larva";264;1
"Unit";"Zergling";"Larva";264;1
"Unit";"Zergling";"Larva";264;1
"Unit";"Zergling";"Larva";264;1
"Unit";"Zergling";"Larva";264;1
"Unit";"Zergling";"Larva";264;1
"Unit";"Zergling";"Larva";264;1
"Unit";"Zergling";"Larva";264;1
"Unit";"Zergling";"Larva";264;1
"Unit";"Zergling";"Larva";270;1
"Unit";"Zergling";"Larva";270;1
"Unit";"Zergling";"Larva";270;1
"Unit";"Zergling";"Larva";270;1
"Unit";"Hydralisk";"Larva";264;2
"Unit";"Zergling";"Larva";288;1
"Unit";"Zergling";"Larva";288;1
"Unit";"Hydralisk";"Larva";270;2
"Unit";"Hydralisk";"Larva";270;2
"Unit";"Baneling";"Zergling";292;0
"Unit";"Zergling";"Larva";290;1
"Unit";"Zergling";"Larva";290;1
"Unit";"Zergling";"Larva";290;1
"Unit";"Zergling";"Larva";290;1
"Unit";"Zergling";"Larva";290;1
"Unit";"Zergling";"Larva";290;1
"Unit";"Zergling";"Larva";290;1
"Unit";"Zergling";"Larva";290;1
"Unit";"Baneling";"Zergling";294;0
"Unit";"Zergling";"Larva";290;1
"Unit";"Zergling";"Larva";290;1
"Unit";"Zergling";"Larva";290;1
"Unit";"Zergling";"Larva";290;1
"Unit";"Zergling";"Larva";290;1
"Unit";"Zergling";"Larva";290;1
"Unit";"Baneling";"Zergling";294;0
"Building";"CreepTumor";NA;296;0
"Building";"CreepTumor";NA;296;0
"Building";"CreepTumor";NA;296;0
"Building";"CreepTumor";NA;296;0
"Unit";"Zergling";"Larva";294;1
"Unit";"Zergling";"Larva";294;1
"Unit";"Zergling";"Larva";294;1
"Unit";"Zergling";"Larva";294;1
"Unit";"Hydralisk";"Larva";272;2
"Unit";"Hydralisk";"Larva";272;2
"Unit";"Hydralisk";"Larva";278;2
"Unit";"Baneling";"Zergling";296;0
"Unit";"Baneling";"Zergling";296;0
"Unit";"Baneling";"Zergling";296;0
"Unit";"Baneling";"Zergling";296;0
"Unit";"Baneling";"Zergling";296;0
"Unit";"Zergling";"Larva";296;1
"Unit";"Zergling";"Larva";296;1
"Upgrade";"EvolveMuscularAugments";"HydraliskDen";258;0
"Unit";"Zergling";"Larva";296;1
"Unit";"Zergling";"Larva";296;1
"Unit";"Zergling";"Larva";296;1
"Unit";"Zergling";"Larva";296;1
"Unit";"Zergling";"Larva";296;1
"Unit";"Zergling";"Larva";296;1
"Unit";"Zergling";"Larva";296;1
"Unit";"Zergling";"Larva";296;1
"Unit";"Zergling";"Larva";296;1
"Unit";"Zergling";"Larva";296;1
"Unit";"Zergling";"Larva";320;1
"Unit";"Zergling";"Larva";320;1
"Unit";"Zergling";"Larva";320;1
"Unit";"Zergling";"Larva";320;1
"Unit";"Zergling";"Larva";320;1
"Unit";"Zergling";"Larva";320;1
"Upgrade";"ZergMeleeWeaponsLevel2";"EvolutionChamber";208;0
"Unit";"Zergling";"Larva";326;1
"Unit";"Zergling";"Larva";326;1
"Unit";"Zergling";"Larva";336;1
"Unit";"Zergling";"Larva";336;1
"Unit";"Hydralisk";"Larva";326;2
"Unit";"Hydralisk";"Larva";326;2
"Unit";"Hydralisk";"Larva";328;2
"Unit";"Zergling";"Larva";338;1
"Unit";"Zergling";"Larva";338;1
"Unit";"Zergling";"Larva";338;1
"Unit";"Zergling";"Larva";338;1
"Unit";"Zergling";"Larva";338;1
"Unit";"Zergling";"Larva";338;1
"Unit";"Zergling";"Larva";338;1
"Unit";"Zergling";"Larva";338;1
"Unit";"Zergling";"Larva";338;1
"Unit";"Zergling";"Larva";338;1
"Unit";"Zergling";"Larva";338;1
"Unit";"Zergling";"Larva";338;1
"Unit";"Zergling";"Larva";338;1
"Unit";"Zergling";"Larva";338;1
"Unit";"Zergling";"Larva";340;1
"Unit";"Zergling";"Larva";340;1
"Building";"CreepTumor";NA;346;0
"Building";"CreepTumor";NA;346;0
"Building";"Extractor";NA;338;0
"Building";"CreepTumor";NA;346;0
"Building";"Extractor";NA;338;0
"Building";"CreepTumor";NA;346;0
"Building";"CreepTumor";NA;346;0
"Unit";"Hydralisk";"Larva";338;2
"Unit";"Hydralisk";"Larva";338;2
"Unit";"Queen";"Hatchery";336;2
"Unit";"Baneling";"Zergling";354;0
"Unit";"Baneling";"Zergling";354;0
"Unit";"Baneling";"Zergling";354;0
"Unit";"Baneling";"Zergling";354;0
"Unit";"Baneling";"Zergling";354;0
"Unit";"Baneling";"Zergling";354;0
"Unit";"Zergling";"Larva";348;1
"Unit";"Zergling";"Larva";348;1
"Unit";"Baneling";"Zergling";354;0
"Unit";"Baneling";"Zergling";354;0
"Unit";"Zergling";"Larva";348;1
"Unit";"Zergling";"Larva";348;1
"Unit";"Zergling";"Larva";348;1
"Unit";"Zergling";"Larva";348;1
"Unit";"Zergling";"Larva";348;1
"Unit";"Zergling";"Larva";348;1
"Unit";"Zergling";"Larva";348;1
"Unit";"Zergling";"Larva";348;1
"Unit";"Zergling";"Larva";348;1
"Unit";"Zergling";"Larva";348;1
"Unit";"Zergling";"Larva";348;1
"Unit";"Zergling";"Larva";348;1
"Unit";"Zergling";"Larva";348;1
"Unit";"Zergling";"Larva";348;1
"Unit";"Zergling";"Larva";348;1
"Unit";"Zergling";"Larva";348;1
"Unit";"Zergling";"Larva";350;1
"Unit";"Zergling";"Larva";350;1
"Unit";"Zergling";"Larva";354;1
"Unit";"Zergling";"Larva";354;1
"Unit";"Zergling";"Larva";354;1
"Unit";"Zergling";"Larva";354;1
"Building";"InfestationPit";NA;338;0
"Building";"CreepTumor";NA;400;0
"Building";"Extractor";NA;374;0
"Unit";"Overlord";"Larva";396;0
"Unit";"Overlord";"Larva";396;0
"Unit";"Zergling";"Larva";396;1
"Unit";"Zergling";"Larva";396;1
"Unit";"Zergling";"Larva";396;1
"Unit";"Zergling";"Larva";396;1
"Unit";"Zergling";"Larva";396;1
"Unit";"Zergling";"Larva";396;1
"Unit";"Zergling";"Larva";400;1
"Unit";"Zergling";"Larva";400;1
"Unit";"Zergling";"Larva";400;1
"Unit";"Zergling";"Larva";400;1
"Unit";"Zergling";"Larva";400;1
"Unit";"Zergling";"Larva";400;1
"Unit";"Baneling";"Zergling";404;0
"Unit";"Baneling";"Zergling";406;0
"Unit";"Baneling";"Zergling";406;0
"Unit";"Baneling";"Zergling";406;0
"Unit";"Baneling";"Zergling";407;0
"Building";"CreepTumor";NA;407;0
"Unit";"Zergling";"Larva";407;1
"Unit";"Zergling";"Larva";407;1
"Unit";"Zergling";"Larva";407;1
"Unit";"Zergling";"Larva";407;1
"Building";"CreepTumor";NA;407;0
"Unit";"Overlord";"Larva";407;0
"Unit";"Overlord";"Larva";407;0
"Unit";"Overlord";"Larva";407;0
"Unit";"Overlord";"Larva";407;0
"Building";"CreepTumor";NA;407;0
"Unit";"Overlord";"Larva";415;0
"Unit";"Overlord";"Larva";415;0
"Building";"Hatchery";NA;338;0
"Unit";"Zergling";"Larva";419;1
"Unit";"Zergling";"Larva";419;1
"Unit";"Zergling";"Larva";419;1
"Unit";"Zergling";"Larva";419;1
"Unit";"Zergling";"Larva";419;1
"Unit";"Zergling";"Larva";419;1
"Unit";"Zergling";"Larva";419;1
"Unit";"Zergling";"Larva";419;1
"Unit";"Zergling";"Larva";419;1
"Unit";"Zergling";"Larva";419;1
"Unit";"Zergling";"Larva";419;1
"Unit";"Zergling";"Larva";419;1
"Unit";"Zergling";"Larva";419;1
"Unit";"Zergling";"Larva";419;1
"Unit";"Zergling";"Larva";419;1
"Unit";"Zergling";"Larva";419;1
"Unit";"Zergling";"Larva";419;1
"Unit";"Zergling";"Larva";419;1
"Building";"CreepTumorQueen";NA;423;0
"Unit";"Zergling";"Larva";423;1
"Unit";"Zergling";"Larva";423;1
"Unit";"Baneling";"Zergling";423;0
"Unit";"Baneling";"Zergling";423;0
"Unit";"Baneling";"Zergling";423;0
"Unit";"Baneling";"Zergling";423;0
"Building";"SpineCrawler";NA;407;0
"Building";"SporeCrawler";NA;423;0
"Unit";"Zergling";"Larva";423;1
"Unit";"Zergling";"Larva";423;1
"Building";"CreepTumor";NA;441;0
"Building";"CreepTumor";NA;441;0
"Building";"CreepTumor";NA;441;0
"Building";"CreepTumor";NA;443;0
"Unit";"Zergling";"Larva";423;1
"Unit";"Zergling";"Larva";423;1
"Unit";"Zergling";"Larva";423;1
"Unit";"Zergling";"Larva";423;1
"Unit";"Zergling";"Larva";423;1
"Unit";"Zergling";"Larva";423;1
"Unit";"Zergling";"Larva";425;1
"Unit";"Zergling";"Larva";425;1
"Unit";"Zergling";"Larva";425;1
"Unit";"Zergling";"Larva";425;1
"Unit";"Zergling";"Larva";436;1
"Unit";"Zergling";"Larva";436;1
"Unit";"Baneling";"Zergling";443;0
"Unit";"Baneling";"Zergling";443;0
"Unit";"Baneling";"Zergling";443;0
"Unit";"Baneling";"Zergling";443;0
"Unit";"Baneling";"Zergling";443;0
"Unit";"Baneling";"Zergling";443;0
"Unit";"Baneling";"Zergling";443;0
"Unit";"Baneling";"Zergling";443;0
"Unit";"Overlord";"Larva";443;0
"Unit";"Zergling";"Larva";445;1
"Unit";"Zergling";"Larva";445;1
"Unit";"Zergling";"Larva";445;1
"Unit";"Zergling";"Larva";445;1
"Unit";"Zergling";"Larva";445;1
"Unit";"Zergling";"Larva";445;1
"Unit";"Zergling";"Larva";445;1
"Unit";"Zergling";"Larva";445;1
"Unit";"Zergling";"Larva";445;1
"Unit";"Zergling";"Larva";445;1
"Unit";"Zergling";"Larva";445;1
"Unit";"Zergling";"Larva";445;1
"Unit";"Zergling";"Larva";445;1
"Unit";"Zergling";"Larva";445;1
"Unit";"Zergling";"Larva";445;1
"Unit";"Zergling";"Larva";445;1
"Building";"SporeCrawler";NA;475;0
"Building";"SporeCrawler";NA;475;0
"Building";"SporeCrawler";NA;475;0
"Building";"SporeCrawler";NA;475;0
"Unit";"Baneling";"Zergling";475;0
"Unit";"Baneling";"Zergling";475;0
"Unit";"Baneling";"Zergling";475;0
"Unit";"Baneling";"Zergling";475;0
"Unit";"Baneling";"Zergling";475;0
"Unit";"Baneling";"Zergling";475;0
"Unit";"Baneling";"Zergling";475;0
"Unit";"Baneling";"Zergling";475;0
"Unit";"Baneling";"Zergling";475;0
"Unit";"Baneling";"Zergling";475;0
"Unit";"Baneling";"Zergling";475;0
"Unit";"Baneling";"Zergling";475;0
"Unit";"Baneling";"Zergling";475;0
"Building";"SporeCrawler";NA;475;0
"Building";"CreepTumor";NA;475;0
"Building";"CreepTumor";NA;475;0
"Building";"CreepTumor";NA;475;0
"Building";"CreepTumor";NA;475;0
"Unit";"Zergling";"Larva";475;1
"Unit";"Zergling";"Larva";475;1
"Unit";"Zergling";"Larva";475;1
"Unit";"Zergling";"Larva";475;1
"Unit";"Zergling";"Larva";475;1
"Unit";"Zergling";"Larva";475;1
"Unit";"Zergling";"Larva";475;1
"Unit";"Zergling";"Larva";475;1
"Unit";"Zergling";"Larva";475;1
"Unit";"Zergling";"Larva";475;1
"Unit";"Zergling";"Larva";475;1
"Unit";"Zergling";"Larva";475;1
"Unit";"Hydralisk";"Larva";475;2
"Unit";"Hydralisk";"Larva";475;2
"Unit";"Viper";"Larva";475;3
"Unit";"Viper";"Larva";475;3
"Unit";"Baneling";"Zergling";475;0
"Unit";"Baneling";"Zergling";475;0
"Unit";"Baneling";"Zergling";475;0
"Unit";"Baneling";"Zergling";475;0
"Unit";"Baneling";"Zergling";475;0
"Unit";"Baneling";"Zergling";475;0
"Unit";"Baneling";"Zergling";475;0
"Unit";"Baneling";"Zergling";475;0
"Unit";"Baneling";"Zergling";475;0
"Unit";"Baneling";"Zergling";475;0
"Unit";"Baneling";"Zergling";475;0
"Building";"CreepTumor";NA;487;0
"Upgrade";"ZergGroundArmorsLevel2";"EvolutionChamber";441;0
"Upgrade";"ZergMissileWeaponsLevel1";"EvolutionChamber";457;0
"Unit";"Baneling";"Zergling";497;0
"Unit";"Baneling";"Zergling";497;0
"Unit";"Baneling";"Zergling";497;0
"Unit";"Baneling";"Zergling";497;0
"Unit";"Baneling";"Zergling";497;0
"Unit";"Baneling";"Zergling";497;0
"Building";"UltraliskCavern";NA;475;0
"Unit";"Baneling";"Zergling";497;0
"Unit";"Baneling";"Zergling";497;0
"Unit";"Baneling";"Zergling";497;0
"Unit";"Baneling";"Zergling";497;0
"Unit";"Baneling";"Zergling";497;0
"Unit";"Baneling";"Zergling";497;0
"Unit";"Baneling";"Zergling";497;0
"Unit";"Baneling";"Zergling";497;0
"Building";"CreepTumor";NA;497;0
"Unit";"Zergling";"Larva";497;1
"Unit";"Zergling";"Larva";497;1
"Unit";"Zergling";"Larva";497;1
"Unit";"Zergling";"Larva";497;1
"Unit";"Zergling";"Larva";497;1
"Unit";"Zergling";"Larva";497;1
"Unit";"Zergling";"Larva";497;1
"Unit";"Zergling";"Larva";497;1
"Unit";"Zergling";"Larva";497;1
"Unit";"Zergling";"Larva";497;1
"Unit";"Zergling";"Larva";497;1
"Unit";"Zergling";"Larva";497;1
"Building";"CreepTumor";NA;497;0
"Unit";"Baneling";"Zergling";497;0
"Unit";"Baneling";"Zergling";497;0
"Unit";"Baneling";"Zergling";497;0
"Unit";"Baneling";"Zergling";497;0
"Unit";"Baneling";"Zergling";497;0
"Unit";"Baneling";"Zergling";497;0
"Unit";"Baneling";"Zergling";497;0
"Unit";"Baneling";"Zergling";497;0
"Unit";"Baneling";"Zergling";497;0
"Unit";"Baneling";"Zergling";497;0
"Unit";"Baneling";"Zergling";497;0
