"type";"unit_name";"on_building";"total_supply";"supply"
"Unit";"Overlord";"Larva";12;0
"Building";"Extractor";NA;18;0
"Unit";"Overlord";"Larva";21;0
"Building";"SpawningPool";NA;19;0
"Building";"Hatchery";NA;17;0
"Unit";"Zergling";"Larva";23;1
"Unit";"Zergling";"Larva";23;1
"Unit";"Zergling";"Larva";23;1
"Unit";"Zergling";"Larva";23;1
"Unit";"Queen";"Hatchery";22;2
"Unit";"Overlord";"Larva";23;0
"Unit";"Queen";"Hatchery";23;2
"Unit";"Overlord";"Larva";34;0
"Unit";"Overlord";"Larva";34;0
"Unit";"Queen";"Hatchery";31;2
"Unit";"Queen";"Hatchery";34;2
"Building";"CreepTumorQueen";NA;36;0
"Building";"CreepTumorQueen";NA;38;0
"Building";"CreepTumor";NA;50;0
"Building";"CreepTumor";NA;50;0
"Unit";"Overlord";"Larva";52;0
"Building";"CreepTumorQueen";NA;54;0
"Building";"CreepTumorQueen";NA;54;0
"Building";"Extractor";NA;54;0
"Building";"CreepTumor";NA;57;0
"Building";"Extractor";NA;54;0
"Building";"CreepTumor";NA;57;0
"Unit";"Queen";"Hatchery";52;2
"Building";"RoachWarren";NA;54;0
"Unit";"Zergling";"Larva";61;1
"Unit";"Zergling";"Larva";61;1
"Unit";"Zergling";"Larva";61;1
"Unit";"Zergling";"Larva";61;1
"Unit";"Zergling";"Larva";61;1
"Unit";"Zergling";"Larva";61;1
"Building";"SporeCrawler";NA;60;0
"Building";"SporeCrawler";NA;61;0
"Building";"CreepTumor";NA;63;0
"Building";"Hatchery";NA;47;0
"Building";"CreepTumor";NA;63;0
"Building";"CreepTumor";NA;69;0
"Unit";"Overlord";"Larva";69;0
"Unit";"Overlord";"Larva";69;0
"Unit";"Overlord";"Larva";69;0
"Unit";"Overlord";"Larva";69;0
"Building";"SporeCrawler";NA;69;0
"Unit";"Queen";"Hatchery";63;2
"Unit";"Roach";"Larva";69;2
"Unit";"Roach";"Larva";69;2
"Unit";"Roach";"Larva";69;2
"Unit";"Roach";"Larva";69;2
"Unit";"Roach";"Larva";69;2
"Unit";"Roach";"Larva";69;2
"Unit";"Roach";"Larva";69;2
"Unit";"Roach";"Larva";71;2
"Unit";"Roach";"Larva";71;2
"Unit";"Roach";"Larva";71;2
"Unit";"Roach";"Larva";71;2
"Unit";"Roach";"Larva";71;2
"Unit";"Roach";"Larva";93;2
"Unit";"Roach";"Larva";93;2
"Unit";"Roach";"Larva";93;2
"Unit";"Roach";"Larva";93;2
"Unit";"Roach";"Larva";93;2
"Unit";"Roach";"Larva";93;2
"Building";"CreepTumor";NA;95;0
"Unit";"Overlord";"Larva";95;0
"Unit";"Overlord";"Larva";95;0
"Building";"CreepTumor";NA;107;0
"Building";"CreepTumor";NA;107;0
"Building";"CreepTumorQueen";NA;110;0
"Building";"CreepTumorQueen";NA;110;0
"Building";"CreepTumorQueen";NA;110;0
"Building";"CreepTumorQueen";NA;110;0
"Building";"EvolutionChamber";NA;110;0
"Building";"EvolutionChamber";NA;110;0
"Building";"CreepTumor";NA;116;0
"Building";"CreepTumor";NA;116;0
"Building";"CreepTumorQueen";NA;120;0
"Upgrade";"GlialReconstitution";"RoachWarren";107;0
"Building";"Extractor";NA;120;0
"Building";"InfestationPit";NA;116;0
"Unit";"Overlord";"Larva";122;0
"Unit";"Overlord";"Larva";122;0
"Building";"CreepTumor";NA;129;0
"Building";"CreepTumor";NA;129;0
"Building";"CreepTumor";NA;129;0
"Building";"CreepTumor";NA;129;0
"Building";"Spire";NA;110;0
"Building";"CreepTumorQueen";NA;129;0
"Building";"CreepTumor";NA;129;0
"Unit";"Overlord";"Larva";138;0
"Unit";"Overlord";"Larva";138;0
"Unit";"Overlord";"Larva";138;0
"Unit";"Overlord";"Larva";138;0
"Building";"CreepTumorQueen";NA;138;0
"Building";"CreepTumor";NA;138;0
"Building";"CreepTumor";NA;138;0
"Building";"Extractor";NA;138;0
"Building";"BanelingNest";NA;134;0
"Building";"CreepTumorQueen";NA;147;0
"Building";"CreepTumorQueen";NA;147;0
"Building";"CreepTumorQueen";NA;147;0
"Building";"CreepTumor";NA;147;0
"Unit";"Zergling";"Larva";147;1
"Unit";"Zergling";"Larva";147;1
"Building";"CreepTumor";NA;147;0
"Unit";"Zergling";"Larva";147;1
"Unit";"Zergling";"Larva";147;1
"Unit";"Zergling";"Larva";147;1
"Unit";"Zergling";"Larva";147;1
"Unit";"Zergling";"Larva";147;1
"Unit";"Zergling";"Larva";147;1
"Unit";"Zergling";"Larva";147;1
"Unit";"Zergling";"Larva";147;1
"Unit";"Zergling";"Larva";147;1
"Unit";"Zergling";"Larva";147;1
"Unit";"Zergling";"Larva";147;1
"Unit";"Zergling";"Larva";147;1
"Unit";"Zergling";"Larva";147;1
"Unit";"Zergling";"Larva";147;1
"Unit";"Zergling";"Larva";147;1
"Unit";"Zergling";"Larva";147;1
"Unit";"Zergling";"Larva";147;1
"Unit";"Zergling";"Larva";147;1
"Unit";"Zergling";"Larva";147;1
"Unit";"Zergling";"Larva";147;1
"Unit";"Zergling";"Larva";147;1
"Unit";"Zergling";"Larva";147;1
"Unit";"Zergling";"Larva";147;1
"Unit";"Zergling";"Larva";147;1
"Unit";"Zergling";"Larva";147;1
"Unit";"Zergling";"Larva";147;1
"Unit";"Zergling";"Larva";147;1
"Unit";"Zergling";"Larva";147;1
"Building";"CreepTumor";NA;147;0
"Building";"CreepTumor";NA;147;0
"Building";"Extractor";NA;147;0
"Building";"CreepTumorQueen";NA;147;0
"Building";"CreepTumorQueen";NA;147;0
"Building";"CreepTumorQueen";NA;147;0
"Building";"Hatchery";NA;134;0
"Building";"CreepTumor";NA;147;0
"Unit";"Zergling";"Larva";177;1
"Unit";"Zergling";"Larva";177;1
"Unit";"Zergling";"Larva";177;1
"Unit";"Zergling";"Larva";177;1
"Unit";"Zergling";"Larva";177;1
"Unit";"Zergling";"Larva";177;1
"Unit";"Zergling";"Larva";177;1
"Unit";"Zergling";"Larva";177;1
"Unit";"Zergling";"Larva";177;1
"Unit";"Zergling";"Larva";177;1
"Unit";"Zergling";"Larva";177;1
"Unit";"Zergling";"Larva";177;1
"Unit";"Zergling";"Larva";177;1
"Unit";"Zergling";"Larva";177;1
"Unit";"Zergling";"Larva";177;1
"Unit";"Zergling";"Larva";177;1
"Unit";"Zergling";"Larva";177;1
"Unit";"Zergling";"Larva";177;1
"Unit";"Baneling";"Zergling";177;0
"Unit";"Baneling";"Zergling";177;0
"Unit";"Baneling";"Zergling";177;0
"Unit";"Baneling";"Zergling";177;0
"Building";"CreepTumor";NA;177;0
"Unit";"Baneling";"Zergling";177;0
"Building";"CreepTumorQueen";NA;177;0
"Building";"Hatchery";NA;138;0
"Building";"CreepTumorQueen";NA;191;0
"Upgrade";"ZergMeleeWeaponsLevel1";"EvolutionChamber";138;0
"Building";"CreepTumorQueen";NA;195;0
"Building";"CreepTumorQueen";NA;195;0
"Building";"CreepTumor";NA;195;0
"Upgrade";"ZergGroundArmorsLevel1";"EvolutionChamber";138;0
"Building";"CreepTumor";NA;201;0
"Building";"UltraliskCavern";NA;147;0
"Building";"CreepTumor";NA;201;0
"Building";"CreepTumor";NA;201;0
"Building";"CreepTumor";NA;201;0
"Unit";"Zergling";"Larva";201;1
"Unit";"Zergling";"Larva";201;1
"Unit";"Zergling";"Larva";201;1
"Unit";"Zergling";"Larva";201;1
"Unit";"Zergling";"Larva";201;1
"Unit";"Zergling";"Larva";201;1
"Unit";"Zergling";"Larva";201;1
"Unit";"Zergling";"Larva";201;1
"Unit";"Zergling";"Larva";201;1
"Unit";"Zergling";"Larva";201;1
"Unit";"Zergling";"Larva";201;1
"Unit";"Zergling";"Larva";201;1
"Unit";"Zergling";"Larva";201;1
"Unit";"Zergling";"Larva";201;1
"Unit";"Zergling";"Larva";201;1
"Unit";"Zergling";"Larva";201;1
"Building";"Extractor";NA;195;0
"Building";"Extractor";NA;195;0
"Unit";"Queen";"Hatchery";195;2
"Unit";"Viper";"Larva";201;3
"Unit";"Viper";"Larva";201;3
"Unit";"Zergling";"Larva";217;1
"Unit";"Zergling";"Larva";217;1
"Unit";"Zergling";"Larva";217;1
"Unit";"Zergling";"Larva";217;1
"Unit";"Zergling";"Larva";217;1
"Unit";"Zergling";"Larva";217;1
"Unit";"Zergling";"Larva";217;1
"Unit";"Zergling";"Larva";217;1
"Unit";"Zergling";"Larva";217;1
"Unit";"Zergling";"Larva";217;1
"Unit";"Zergling";"Larva";217;1
"Unit";"Zergling";"Larva";217;1
"Unit";"Zergling";"Larva";217;1
"Unit";"Zergling";"Larva";217;1
"Unit";"Zergling";"Larva";217;1
"Unit";"Zergling";"Larva";217;1
"Unit";"Zergling";"Larva";217;1
"Unit";"Zergling";"Larva";217;1
"Building";"SporeCrawler";NA;203;0
"Building";"SporeCrawler";NA;217;0
"Building";"CreepTumorQueen";NA;247;0
"Building";"CreepTumorQueen";NA;247;0
"Building";"CreepTumorQueen";NA;247;0
"Building";"CreepTumorQueen";NA;247;0
"Building";"CreepTumorQueen";NA;247;0
"Unit";"Ultralisk";"Larva";221;6
"Unit";"Zergling";"Larva";247;1
"Unit";"Zergling";"Larva";247;1
"Unit";"Zergling";"Larva";247;1
"Unit";"Zergling";"Larva";247;1
"Unit";"Zergling";"Larva";247;1
"Unit";"Zergling";"Larva";247;1
"Unit";"Zergling";"Larva";247;1
"Unit";"Zergling";"Larva";247;1
"Unit";"Zergling";"Larva";247;1
"Unit";"Zergling";"Larva";247;1
"Unit";"Zergling";"Larva";247;1
"Unit";"Zergling";"Larva";247;1
"Unit";"Zergling";"Larva";247;1
"Unit";"Zergling";"Larva";247;1
"Unit";"Zergling";"Larva";247;1
"Unit";"Zergling";"Larva";247;1
"Unit";"Zergling";"Larva";247;1
"Unit";"Zergling";"Larva";247;1
"Unit";"Zergling";"Larva";247;1
"Unit";"Zergling";"Larva";247;1
"Unit";"Zergling";"Larva";247;1
"Unit";"Zergling";"Larva";247;1
"Unit";"Zergling";"Larva";247;1
"Unit";"Zergling";"Larva";247;1
"Unit";"Zergling";"Larva";247;1
"Unit";"Zergling";"Larva";247;1
"Unit";"Zergling";"Larva";247;1
"Unit";"Zergling";"Larva";247;1
"Unit";"Zergling";"Larva";247;1
"Unit";"Zergling";"Larva";247;1
"Upgrade";"ChitinousPlating";"UltraliskCavern";247;0
"Building";"CreepTumor";NA;283;0
"Building";"CreepTumor";NA;283;0
"Building";"CreepTumor";NA;283;0
"Unit";"Overlord";"Larva";283;0
"Unit";"Overlord";"Larva";283;0
"Unit";"Overlord";"Larva";283;0
"Unit";"Overlord";"Larva";283;0
"Building";"CreepTumorQueen";NA;285;0
"Building";"CreepTumorQueen";NA;285;0
"Unit";"Ultralisk";"Larva";283;6
"Unit";"Ultralisk";"Larva";283;6
"Unit";"Ultralisk";"Larva";283;6
"Building";"CreepTumor";NA;285;0
"Building";"CreepTumor";NA;285;0
"Building";"CreepTumorQueen";NA;303;0
"Building";"CreepTumor";NA;285;0
"Building";"CreepTumor";NA;303;0
"Building";"CreepTumorQueen";NA;303;0
"Building";"CreepTumor";NA;303;0
"Unit";"Zergling";"Larva";303;1
"Unit";"Zergling";"Larva";303;1
"Unit";"Zergling";"Larva";303;1
"Unit";"Zergling";"Larva";303;1
"Unit";"Zergling";"Larva";303;1
"Unit";"Zergling";"Larva";303;1
"Unit";"Zergling";"Larva";303;1
"Unit";"Zergling";"Larva";303;1
"Unit";"Baneling";"Zergling";303;0
"Unit";"Zergling";"Larva";303;1
"Unit";"Zergling";"Larva";303;1
"Unit";"Zergling";"Larva";303;1
"Unit";"Zergling";"Larva";303;1
"Unit";"Baneling";"Zergling";303;0
"Unit";"Baneling";"Zergling";303;0
"Unit";"Baneling";"Zergling";303;0
"Unit";"Baneling";"Zergling";303;0
"Unit";"Baneling";"Zergling";303;0
"Unit";"Baneling";"Zergling";303;0
"Unit";"Ultralisk";"Larva";285;6
"Unit";"Ultralisk";"Larva";285;6
"Unit";"Corruptor";"Larva";303;2
"Unit";"Corruptor";"Larva";303;2
"Unit";"Corruptor";"Larva";303;2
"Unit";"Corruptor";"Larva";303;2
"Unit";"Zergling";"Larva";303;1
"Unit";"Zergling";"Larva";303;1
"Unit";"Zergling";"Larva";305;1
"Unit";"Zergling";"Larva";305;1
"Unit";"Zergling";"Larva";305;1
"Unit";"Zergling";"Larva";305;1
"Unit";"Baneling";"Zergling";315;0
"Unit";"Baneling";"Zergling";315;0
"Unit";"Baneling";"Zergling";315;0
"Unit";"Baneling";"Zergling";315;0
"Unit";"Baneling";"Zergling";315;0
"Unit";"Baneling";"Zergling";315;0
"Unit";"Corruptor";"Larva";303;2
"Unit";"Corruptor";"Larva";303;2
"Upgrade";"ZergGroundArmorsLevel2";"EvolutionChamber";283;0
"Upgrade";"ZergMeleeWeaponsLevel2";"EvolutionChamber";283;0
"Building";"Hatchery";NA;303;0
"Unit";"Zergling";"Larva";345;1
"Unit";"Zergling";"Larva";345;1
"Unit";"Zergling";"Larva";345;1
"Unit";"Zergling";"Larva";345;1
"Unit";"Zergling";"Larva";345;1
"Unit";"Zergling";"Larva";345;1
"Unit";"Zergling";"Larva";345;1
"Unit";"Zergling";"Larva";345;1
"Unit";"Zergling";"Larva";345;1
"Unit";"Zergling";"Larva";345;1
"Unit";"Zergling";"Larva";345;1
"Unit";"Zergling";"Larva";345;1
"Unit";"Zergling";"Larva";345;1
"Unit";"Zergling";"Larva";345;1
"Unit";"Zergling";"Larva";345;1
"Unit";"Zergling";"Larva";345;1
"Unit";"Zergling";"Larva";345;1
"Unit";"Zergling";"Larva";345;1
"Unit";"Zergling";"Larva";345;1
"Unit";"Zergling";"Larva";345;1
"Unit";"Zergling";"Larva";345;1
"Unit";"Zergling";"Larva";345;1
"Unit";"Zergling";"Larva";345;1
"Unit";"Zergling";"Larva";345;1
"Unit";"Ultralisk";"Larva";341;6
"Unit";"Ultralisk";"Larva";341;6
"Building";"CreepTumorQueen";NA;384;0
"Building";"CreepTumorQueen";NA;384;0
"Building";"CreepTumorQueen";NA;384;0
"Building";"CreepTumorQueen";NA;384;0
"Building";"CreepTumorQueen";NA;389;0
"Building";"CreepTumorQueen";NA;389;0
"Unit";"Ultralisk";"Larva";384;6
"Building";"CreepTumor";NA;389;0
"Building";"CreepTumor";NA;389;0
"Building";"CreepTumor";NA;389;0
"Building";"CreepTumor";NA;389;0
"Building";"CreepTumor";NA;389;0
"Unit";"Overlord";"Larva";389;0
"Building";"CreepTumor";NA;389;0
"Building";"CreepTumor";NA;395;0
"Unit";"Overlord";"Larva";389;0
"Building";"CreepTumor";NA;395;0
"Building";"CreepTumor";NA;395;0
"Unit";"Corruptor";"Larva";389;2
"Unit";"Corruptor";"Larva";389;2
"Unit";"Corruptor";"Larva";389;2
"Unit";"Ultralisk";"Larva";389;6
"Unit";"Ultralisk";"Larva";389;6
"Building";"CreepTumor";NA;395;0
"Building";"CreepTumorQueen";NA;395;0
"Building";"CreepTumorQueen";NA;399;0
"Building";"CreepTumorQueen";NA;413;0
"Building";"CreepTumor";NA;401;0
"Building";"CreepTumor";NA;401;0
"Unit";"Baneling";"Zergling";413;0
"Unit";"Baneling";"Zergling";413;0
"Unit";"Baneling";"Zergling";413;0
"Unit";"Baneling";"Zergling";413;0
"Unit";"Baneling";"Zergling";413;0
"Unit";"Baneling";"Zergling";413;0
"Unit";"Baneling";"Zergling";413;0
"Unit";"Baneling";"Zergling";413;0
"Unit";"Baneling";"Zergling";413;0
"Unit";"Baneling";"Zergling";413;0
"Unit";"Baneling";"Zergling";413;0
"Unit";"Baneling";"Zergling";413;0
"Building";"Extractor";NA;413;0
"Building";"Extractor";NA;413;0
"Unit";"Ultralisk";"Larva";395;6
"Unit";"Ultralisk";"Larva";395;6
"Unit";"Ultralisk";"Larva";397;6
"Unit";"Overlord";"Larva";413;0
"Unit";"Overlord";"Larva";413;0
"Building";"CreepTumorQueen";NA;431;0
"Building";"CreepTumorQueen";NA;431;0
"Building";"CreepTumor";NA;431;0
"Building";"CreepTumor";NA;431;0
"Building";"CreepTumor";NA;431;0
"Building";"CreepTumorQueen";NA;431;0
"Building";"CreepTumorQueen";NA;431;0
"Building";"SporeCrawler";NA;431;0
"Building";"CreepTumorQueen";NA;443;0
"Upgrade";"ZergGroundArmorsLevel3";"EvolutionChamber";389;0
"Upgrade";"ZergMeleeWeaponsLevel3";"EvolutionChamber";389;0
"Building";"Hatchery";NA;413;0
