"type";"unit_name";"on_building";"total_supply_lag";"supply"
"Unit";"Overlord";"Larva";13;0
"Building";"SpawningPool";NA;17;0
"Building";"Hatchery";NA;18;0
"Building";"Extractor";NA;20;0
"Unit";"Zergling";"Larva";20;1
"Unit";"Zergling";"Larva";21;1
"Unit";"Zergling";"Larva";22;1
"Unit";"Zergling";"Larva";23;1
"Unit";"Queen";"Hatchery";24;2
"Unit";"Overlord";"Larva";26;0
"Unit";"Queen";"Hatchery";28;2
"Unit";"Queen";"Hatchery";32;2
"Unit";"Overlord";"Larva";36;0
"Building";"CreepTumorQueen";NA;43;0
"Building";"Hatchery";NA;43;0
"Unit";"Overlord";"Larva";45;0
"Building";"CreepTumor";NA;47;0
"Unit";"Overlord";"Larva";49;0
"Building";"CreepTumorQueen";NA;49;0
"Building";"RoachWarren";NA;51;0
"Unit";"Zergling";"Larva";53;1
"Unit";"Zergling";"Larva";54;1
"Unit";"Zergling";"Larva";55;1
"Unit";"Zergling";"Larva";56;1
"Unit";"Zergling";"Larva";57;1
"Unit";"Zergling";"Larva";58;1
"Unit";"Zergling";"Larva";59;1
"Unit";"Zergling";"Larva";60;1
"Unit";"Zergling";"Larva";61;1
"Unit";"Zergling";"Larva";62;1
"Unit";"Overlord";"Larva";63;0
"Building";"CreepTumor";NA;63;0
"Building";"CreepTumor";NA;63;0
"Building";"Extractor";NA;65;0
"Building";"CreepTumorQueen";NA;65;0
"Unit";"Overlord";"Larva";65;0
"Unit";"Overlord";"Larva";65;0
"Unit";"Overlord";"Larva";65;0
"Unit";"Queen";"Hatchery";65;2
"Unit";"Roach";"Larva";67;2
"Unit";"Roach";"Larva";69;2
"Unit";"Roach";"Larva";71;2
"Unit";"Roach";"Larva";73;2
"Unit";"Roach";"Larva";75;2
"Unit";"Roach";"Larva";77;2
"Building";"CreepTumor";NA;79;0
"Unit";"Roach";"Larva";79;2
"Unit";"Roach";"Larva";81;2
"Unit";"Roach";"Larva";83;2
"Building";"CreepTumor";NA;85;0
"Building";"CreepTumor";NA;85;0
"Unit";"Overlord";"Larva";99;0
"Unit";"Zergling";"Larva";102;1
"Unit";"Zergling";"Larva";103;1
"Unit";"Zergling";"Larva";104;1
"Unit";"Zergling";"Larva";105;1
"Unit";"Zergling";"Larva";106;1
"Unit";"Zergling";"Larva";107;1
"Building";"CreepTumor";NA;108;0
"Building";"SporeCrawler";NA;108;0
"Building";"SporeCrawler";NA;108;0
"Unit";"Overlord";"Larva";108;0
"Unit";"Roach";"Larva";108;2
"Unit";"Roach";"Larva";110;2
"Unit";"Roach";"Larva";112;2
"Unit";"Roach";"Larva";114;2
"Building";"SporeCrawler";NA;116;0
"Unit";"Roach";"Larva";116;2
"Unit";"Roach";"Larva";118;2
"Unit";"Roach";"Larva";120;2
"Unit";"Roach";"Larva";122;2
"Unit";"Roach";"Larva";124;2
"Unit";"Roach";"Larva";126;2
"Building";"CreepTumor";NA;138;0
"Unit";"Queen";"Hatchery";142;2
"Unit";"Queen";"Hatchery";144;2
"Unit";"Roach";"Larva";146;2
"Upgrade";"GlialReconstitution";"RoachWarren";148;0
"Unit";"Overlord";"Larva";148;0
"Building";"CreepTumor";NA;153;0
"Unit";"Queen";"Hatchery";154;2
"Building";"HydraliskDen";NA;156;0
"Building";"Extractor";NA;158;0
"Unit";"Roach";"Larva";158;2
"Unit";"Roach";"Larva";160;2
"Unit";"Roach";"Larva";162;2
"Unit";"Roach";"Larva";164;2
"Unit";"Roach";"Larva";166;2
"Unit";"Queen";"Hatchery";168;2
"Unit";"Roach";"Larva";170;2
"Unit";"Roach";"Larva";172;2
"Unit";"Roach";"Larva";174;2
"Building";"Extractor";NA;178;0
"Building";"Extractor";NA;181;0
"Unit";"Overlord";"Larva";184;0
"Unit";"Overlord";"Larva";184;0
"Building";"CreepTumor";NA;186;0
"Unit";"Roach";"Larva";194;2
"Unit";"Roach";"Larva";196;2
"Unit";"Roach";"Larva";198;2
"Unit";"Roach";"Larva";200;2
"Building";"EvolutionChamber";NA;202;0
"Building";"EvolutionChamber";NA;202;0
"Building";"CreepTumor";NA;202;0
"Building";"CreepTumor";NA;202;0
"Building";"Hatchery";NA;202;0
"Unit";"Overlord";"Larva";203;0
"Unit";"Overlord";"Larva";203;0
"Building";"Extractor";NA;203;0
"Building";"CreepTumor";NA;203;0
"Unit";"Overlord";"Larva";203;0
"Building";"CreepTumorQueen";NA;203;0
"Building";"CreepTumorQueen";NA;203;0
"Building";"CreepTumorQueen";NA;203;0
"Unit";"Overlord";"Larva";203;0
"Unit";"Hydralisk";"Larva";203;2
"Unit";"Hydralisk";"Larva";205;2
"Unit";"Hydralisk";"Larva";207;2
"Building";"CreepTumorQueen";NA;209;0
"Building";"CreepTumorQueen";NA;216;0
"Building";"CreepTumorQueen";NA;217;0
"Unit";"Hydralisk";"Larva";217;2
"Unit";"Hydralisk";"Larva";219;2
"Unit";"Hydralisk";"Larva";221;2
"Unit";"Hydralisk";"Larva";224;2
"Unit";"Hydralisk";"Larva";226;2
"Unit";"Hydralisk";"Larva";228;2
"Unit";"Overlord";"Larva";230;0
"Unit";"Overlord";"Larva";230;0
"Building";"CreepTumor";NA;230;0
"Building";"CreepTumor";NA;230;0
"Building";"CreepTumor";NA;230;0
"Building";"CreepTumor";NA;230;0
"Building";"CreepTumor";NA;234;0
"Building";"CreepTumor";NA;234;0
"Building";"CreepTumor";NA;234;0
"Building";"CreepTumor";NA;234;0
"Building";"CreepTumor";NA;234;0
"Unit";"Overlord";"Larva";234;0
"Unit";"Overlord";"Larva";234;0
"Unit";"Overlord";"Larva";234;0
"Building";"Extractor";NA;234;0
"Building";"InfestationPit";NA;234;0
"Unit";"Hydralisk";"Larva";234;2
"Unit";"Hydralisk";"Larva";236;2
"Unit";"Hydralisk";"Larva";238;2
"Unit";"Hydralisk";"Larva";240;2
"Unit";"Hydralisk";"Larva";242;2
"Unit";"Hydralisk";"Larva";244;2
"Unit";"Hydralisk";"Larva";246;2
"Building";"Hatchery";NA;248;0
"Unit";"Roach";"Larva";251;2
"Unit";"Roach";"Larva";253;2
"Unit";"Roach";"Larva";255;2
"Building";"Extractor";NA;257;0
"Unit";"Overlord";"Larva";257;0
"Building";"CreepTumor";NA;260;0
"Building";"CreepTumor";NA;260;0
"Unit";"Hydralisk";"Larva";260;2
"Unit";"Hydralisk";"Larva";262;2
"Unit";"Hydralisk";"Larva";264;2
"Unit";"Hydralisk";"Larva";266;2
"Building";"CreepTumor";NA;268;0
"Building";"CreepTumor";NA;268;0
"Building";"CreepTumorQueen";NA;268;0
"Building";"CreepTumor";NA;268;0
"Unit";"Overlord";"Larva";268;0
"Building";"CreepTumorQueen";NA;268;0
"Unit";"Overlord";"Larva";268;0
"Building";"CreepTumor";NA;268;0
"Building";"CreepTumorQueen";NA;268;0
"Building";"CreepTumor";NA;268;0
"Building";"CreepTumor";NA;268;0
"Building";"CreepTumorQueen";NA;268;0
"Building";"Spire";NA;268;0
"Unit";"Roach";"Larva";268;2
"Unit";"Roach";"Larva";270;2
"Unit";"Roach";"Larva";272;2
"Unit";"Roach";"Larva";274;2
"Unit";"Roach";"Larva";276;2
"Building";"CreepTumor";NA;278;0
"Building";"CreepTumorQueen";NA;278;0
"Building";"CreepTumorQueen";NA;278;0
"Building";"CreepTumor";NA;279;0
"Unit";"Roach";"Larva";279;2
"Unit";"Roach";"Larva";281;2
"Unit";"Roach";"Larva";283;2
"Unit";"Roach";"Larva";285;2
"Unit";"Roach";"Larva";287;2
"Unit";"Roach";"Larva";289;2
"Unit";"Roach";"Larva";291;2
"Unit";"Roach";"Larva";293;2
"Building";"SpineCrawler";NA;295;0
"Building";"SpineCrawler";NA;295;0
"Unit";"Roach";"Larva";295;2
"Unit";"Roach";"Larva";297;2
"Unit";"Roach";"Larva";299;2
"Unit";"Roach";"Larva";301;2
"Unit";"Roach";"Larva";303;2
"Unit";"Roach";"Larva";305;2
"Unit";"Roach";"Larva";307;2
"Unit";"Roach";"Larva";309;2
"Unit";"Roach";"Larva";311;2
"Unit";"Roach";"Larva";313;2
"Unit";"Roach";"Larva";315;2
"Unit";"Roach";"Larva";317;2
"Unit";"Roach";"Larva";319;2
"Upgrade";"SprayZerg";NA;321;0
"Upgrade";"SprayZerg";NA;321;0
"Upgrade";"SprayZerg";NA;321;0
"Upgrade";"zerglingmovementspeed";NA;321;0
"Upgrade";"SprayZerg";NA;321;0
"Upgrade";"SprayZerg";NA;321;0
"Upgrade";"EvolveMuscularAugments";NA;321;0
"Upgrade";"SprayZerg";NA;321;0
"Upgrade";"SprayZerg";NA;321;0
"Upgrade";"EvolveGroovedSpines";NA;321;0
"Upgrade";"ZergMissileWeaponsLevel1";NA;321;0
"Upgrade";"ZergGroundArmorsLevel1";NA;321;0
"Upgrade";"SprayZerg";NA;321;0
