"type";"unit_name";"on_building";"total_supply";"supply"
"Unit";"Overlord";"Larva";12;0
"Building";"Extractor";NA;19;0
"Unit";"Overlord";"Larva";21;0
"Building";"SpawningPool";NA;19;0
"Building";"Hatchery";NA;17;0
"Unit";"Zergling";"Larva";23;1
"Unit";"Zergling";"Larva";23;1
"Unit";"Zergling";"Larva";23;1
"Unit";"Zergling";"Larva";23;1
"Unit";"Queen";"Hatchery";22;2
"Unit";"Queen";"Hatchery";23;2
"Building";"CreepTumorQueen";NA;35;0
"Unit";"Overlord";"Larva";35;0
"Building";"CreepTumor";NA;40;0
"Unit";"Overlord";"Larva";40;0
"Unit";"Queen";"Hatchery";37;2
"Unit";"Overlord";"Larva";40;0
"Building";"Hatchery";NA;35;0
"Unit";"Zergling";"Larva";48;1
"Unit";"Zergling";"Larva";48;1
"Unit";"Zergling";"Larva";48;1
"Unit";"Zergling";"Larva";48;1
"Building";"CreepTumor";NA;49;0
"Building";"EvolutionChamber";NA;49;0
"Unit";"Queen";"Hatchery";48;2
"Building";"CreepTumorQueen";NA;56;0
"Unit";"Zergling";"Larva";56;1
"Unit";"Zergling";"Larva";56;1
"Unit";"Zergling";"Larva";56;1
"Unit";"Zergling";"Larva";56;1
"Unit";"Zergling";"Larva";56;1
"Unit";"Zergling";"Larva";56;1
"Unit";"Zergling";"Larva";56;1
"Unit";"Zergling";"Larva";56;1
"Building";"Extractor";NA;56;0
"Building";"BanelingNest";NA;48;0
"Building";"CreepTumor";NA;61;0
"Building";"CreepTumorQueen";NA;69;0
"Unit";"Queen";"Hatchery";56;2
"Building";"CreepTumor";NA;77;0
"Building";"CreepTumor";NA;77;0
"Building";"SporeCrawler";NA;77;0
"Unit";"Zergling";"Larva";77;1
"Unit";"Zergling";"Larva";77;1
"Unit";"Zergling";"Larva";77;1
"Unit";"Zergling";"Larva";77;1
"Unit";"Zergling";"Larva";77;1
"Unit";"Zergling";"Larva";77;1
"Unit";"Zergling";"Larva";77;1
"Unit";"Zergling";"Larva";77;1
"Unit";"Zergling";"Larva";77;1
"Unit";"Zergling";"Larva";77;1
"Unit";"Overlord";"Larva";77;0
"Unit";"Overlord";"Larva";77;0
"Unit";"Overlord";"Larva";77;0
"Unit";"Overlord";"Larva";77;0
"Building";"CreepTumor";NA;77;0
"Unit";"Queen";"Hatchery";77;2
"Building";"Extractor";NA;77;0
"Unit";"Zergling";"Larva";88;1
"Unit";"Zergling";"Larva";88;1
"Unit";"Zergling";"Larva";88;1
"Unit";"Zergling";"Larva";88;1
"Unit";"Zergling";"Larva";88;1
"Unit";"Zergling";"Larva";88;1
"Unit";"Zergling";"Larva";88;1
"Unit";"Zergling";"Larva";88;1
"Unit";"Zergling";"Larva";88;1
"Unit";"Zergling";"Larva";88;1
"Unit";"Zergling";"Larva";88;1
"Unit";"Zergling";"Larva";88;1
"Upgrade";"ZergGroundArmorsLevel1";"EvolutionChamber";77;0
"Building";"CreepTumor";NA;117;0
"Building";"HydraliskDen";NA;102;0
"Building";"Extractor";NA;116;0
"Building";"EvolutionChamber";NA;116;0
"Building";"CreepTumorQueen";NA;119;0
"Building";"CreepTumorQueen";NA;119;0
"Building";"CreepTumorQueen";NA;122;0
"Building";"CreepTumorQueen";NA;122;0
"Building";"CreepTumorQueen";NA;122;0
"Building";"CreepTumorQueen";NA;122;0
"Unit";"Hydralisk";"Larva";119;2
"Unit";"Hydralisk";"Larva";119;2
"Unit";"Hydralisk";"Larva";119;2
"Unit";"Hydralisk";"Larva";119;2
"Unit";"Hydralisk";"Larva";119;2
"Unit";"Hydralisk";"Larva";119;2
"Building";"Hatchery";NA;102;0
"Unit";"Zergling";"Larva";135;1
"Unit";"Zergling";"Larva";135;1
"Unit";"Zergling";"Larva";135;1
"Unit";"Zergling";"Larva";135;1
"Unit";"Zergling";"Larva";135;1
"Unit";"Zergling";"Larva";135;1
"Unit";"Zergling";"Larva";135;1
"Unit";"Zergling";"Larva";135;1
"Unit";"Zergling";"Larva";135;1
"Unit";"Zergling";"Larva";135;1
"Unit";"Zergling";"Larva";135;1
"Unit";"Zergling";"Larva";135;1
"Unit";"Zergling";"Larva";135;1
"Unit";"Zergling";"Larva";135;1
"Unit";"Zergling";"Larva";135;1
"Unit";"Zergling";"Larva";135;1
"Unit";"Zergling";"Larva";135;1
"Unit";"Zergling";"Larva";135;1
"Unit";"Zergling";"Larva";135;1
"Unit";"Zergling";"Larva";135;1
"Unit";"Zergling";"Larva";135;1
"Unit";"Zergling";"Larva";135;1
"Building";"SporeCrawler";NA;135;0
"Building";"SporeCrawler";NA;135;0
"Upgrade";"EvolveMuscularAugments";"HydraliskDen";134;0
"Building";"Extractor";NA;157;0
"Building";"Extractor";NA;157;0
"Building";"CreepTumor";NA;157;0
"Unit";"Hydralisk";"Larva";157;2
"Building";"CreepTumor";NA;157;0
"Unit";"Hydralisk";"Larva";157;2
"Unit";"Hydralisk";"Larva";157;2
"Unit";"Hydralisk";"Larva";157;2
"Building";"CreepTumor";NA;157;0
"Upgrade";"ZergMeleeWeaponsLevel1";"EvolutionChamber";124;0
"Building";"CreepTumor";NA;165;0
"Unit";"Overlord";"Larva";165;0
"Unit";"Overlord";"Larva";165;0
"Unit";"Overlord";"Larva";165;0
"Building";"InfestationPit";NA;157;0
"Building";"CreepTumor";NA;165;0
"Building";"Hatchery";NA;135;0
"Unit";"Overlord";"Larva";165;0
"Building";"CreepTumor";NA;165;0
"Building";"CreepTumor";NA;165;0
"Building";"CreepTumor";NA;165;0
"Unit";"Overlord";"Larva";165;0
"Unit";"Overlord";"Larva";165;0
"Unit";"Overlord";"Larva";165;0
"Unit";"Overlord";"Larva";165;0
"Unit";"Overlord";"Larva";165;0
"Unit";"Baneling";"Zergling";165;0
"Unit";"Baneling";"Zergling";165;0
"Unit";"Baneling";"Zergling";165;0
"Unit";"Baneling";"Zergling";165;0
"Unit";"Baneling";"Zergling";165;0
"Unit";"Baneling";"Zergling";165;0
"Unit";"Baneling";"Zergling";165;0
"Unit";"Baneling";"Zergling";165;0
"Unit";"Baneling";"Zergling";165;0
"Unit";"Zergling";"Larva";165;1
"Unit";"Zergling";"Larva";165;1
"Unit";"Zergling";"Larva";165;1
"Unit";"Zergling";"Larva";165;1
"Unit";"Zergling";"Larva";165;1
"Unit";"Zergling";"Larva";165;1
"Unit";"Zergling";"Larva";165;1
"Unit";"Zergling";"Larva";165;1
"Building";"CreepTumor";NA;179;0
"Building";"CreepTumor";NA;179;0
"Building";"CreepTumor";NA;179;0
"Unit";"Queen";"Hatchery";165;2
"Building";"CreepTumor";NA;181;0
"Building";"CreepTumor";NA;179;0
"Upgrade";"EvolveGroovedSpines";"HydraliskDen";165;0
"Building";"CreepTumorQueen";NA;187;0
"Building";"CreepTumorQueen";NA;187;0
"Building";"CreepTumorQueen";NA;187;0
"Building";"CreepTumorQueen";NA;189;0
"Building";"SporeCrawler";NA;187;0
"Building";"Extractor";NA;189;0
"Building";"Extractor";NA;189;0
"Unit";"Baneling";"Zergling";189;0
"Unit";"Zergling";"Larva";189;1
"Unit";"Zergling";"Larva";189;1
"Unit";"Baneling";"Zergling";189;0
"Unit";"Baneling";"Zergling";189;0
"Unit";"Baneling";"Zergling";189;0
"Unit";"Baneling";"Zergling";189;0
"Unit";"Baneling";"Zergling";189;0
"Unit";"Baneling";"Zergling";189;0
"Unit";"Baneling";"Zergling";189;0
"Unit";"Baneling";"Zergling";189;0
"Unit";"Baneling";"Zergling";189;0
"Unit";"Baneling";"Zergling";189;0
"Unit";"Baneling";"Zergling";189;0
"Unit";"Zergling";"Larva";189;1
"Unit";"Zergling";"Larva";189;1
"Unit";"Zergling";"Larva";189;1
"Unit";"Zergling";"Larva";189;1
"Unit";"Baneling";"Zergling";189;0
"Unit";"Baneling";"Zergling";189;0
"Unit";"Baneling";"Zergling";189;0
"Unit";"Baneling";"Zergling";189;0
"Unit";"Baneling";"Zergling";189;0
"Unit";"Baneling";"Zergling";189;0
"Unit";"Baneling";"Zergling";189;0
"Unit";"Baneling";"Zergling";189;0
"Building";"SpineCrawler";NA;187;0
"Unit";"Baneling";"Zergling";189;0
"Unit";"Baneling";"Zergling";189;0
"Unit";"Baneling";"Zergling";189;0
"Unit";"Baneling";"Zergling";189;0
"Building";"SpineCrawler";NA;189;0
"Unit";"Baneling";"Zergling";189;0
"Building";"SpineCrawler";NA;189;0
"Unit";"Queen";"Hatchery";212;2
"Unit";"Hydralisk";"Larva";218;2
"Upgrade";"ZergGroundArmorsLevel2";"EvolutionChamber";165;0
"Unit";"Hydralisk";"Larva";218;2
"Unit";"Hydralisk";"Larva";218;2
"Unit";"Hydralisk";"Larva";218;2
"Building";"CreepTumor";NA;224;0
"Building";"CreepTumor";NA;224;0
"Building";"CreepTumor";NA;224;0
"Building";"CreepTumor";NA;224;0
"Unit";"Zergling";"Larva";224;1
"Unit";"Zergling";"Larva";224;1
"Unit";"Zergling";"Larva";224;1
"Unit";"Zergling";"Larva";224;1
"Unit";"Zergling";"Larva";224;1
"Unit";"Zergling";"Larva";224;1
"Unit";"Zergling";"Larva";224;1
"Unit";"Zergling";"Larva";224;1
"Unit";"Zergling";"Larva";224;1
"Unit";"Zergling";"Larva";224;1
"Unit";"Zergling";"Larva";224;1
"Unit";"Zergling";"Larva";224;1
"Unit";"Zergling";"Larva";224;1
"Unit";"Zergling";"Larva";224;1
"Unit";"Zergling";"Larva";224;1
"Unit";"Zergling";"Larva";224;1
"Unit";"Zergling";"Larva";224;1
"Unit";"Zergling";"Larva";224;1
"Unit";"Zergling";"Larva";224;1
"Unit";"Zergling";"Larva";224;1
"Unit";"Zergling";"Larva";224;1
"Unit";"Zergling";"Larva";224;1
"Unit";"Zergling";"Larva";224;1
"Unit";"Zergling";"Larva";224;1
"Unit";"Zergling";"Larva";224;1
"Unit";"Zergling";"Larva";224;1
"Unit";"Zergling";"Larva";224;1
"Unit";"Zergling";"Larva";224;1
"Unit";"Zergling";"Larva";224;1
"Unit";"Zergling";"Larva";224;1
"Building";"CreepTumor";NA;224;0
"Building";"CreepTumor";NA;224;0
"Building";"CreepTumor";NA;224;0
"Building";"CreepTumor";NA;234;0
"Unit";"Zergling";"Larva";264;1
"Unit";"Zergling";"Larva";264;1
"Unit";"Zergling";"Larva";264;1
"Unit";"Zergling";"Larva";264;1
"Unit";"Zergling";"Larva";264;1
"Unit";"Zergling";"Larva";264;1
"Unit";"Zergling";"Larva";264;1
"Unit";"Zergling";"Larva";264;1
"Unit";"Zergling";"Larva";264;1
"Unit";"Zergling";"Larva";264;1
"Unit";"Zergling";"Larva";264;1
"Unit";"Zergling";"Larva";264;1
"Unit";"Zergling";"Larva";264;1
"Unit";"Zergling";"Larva";264;1
"Unit";"Zergling";"Larva";264;1
"Unit";"Zergling";"Larva";264;1
"Unit";"Zergling";"Larva";264;1
"Unit";"Zergling";"Larva";264;1
"Unit";"Zergling";"Larva";264;1
"Unit";"Zergling";"Larva";264;1
"Unit";"Zergling";"Larva";264;1
"Unit";"Zergling";"Larva";264;1
"Unit";"Overlord";"Larva";264;0
"Unit";"Overlord";"Larva";264;0
"Unit";"Overlord";"Larva";264;0
"Unit";"Overlord";"Larva";264;0
"Building";"CreepTumor";NA;286;0
"Building";"CreepTumor";NA;286;0
"Building";"CreepTumor";NA;286;0
"Building";"CreepTumor";NA;286;0
"Building";"CreepTumor";NA;286;0
"Building";"CreepTumor";NA;286;0
"Building";"CreepTumor";NA;286;0
"Building";"Spire";NA;218;0
"Building";"UltraliskCavern";NA;234;0
"Building";"CreepTumor";NA;286;0
"Building";"CreepTumor";NA;286;0
"Building";"CreepTumor";NA;286;0
"Building";"CreepTumorQueen";NA;286;0
"Unit";"Zergling";"Larva";286;1
"Unit";"Zergling";"Larva";286;1
"Building";"CreepTumorQueen";NA;286;0
"Unit";"Zergling";"Larva";286;1
"Unit";"Zergling";"Larva";286;1
"Unit";"Zergling";"Larva";286;1
"Unit";"Zergling";"Larva";286;1
"Unit";"Zergling";"Larva";286;1
"Unit";"Zergling";"Larva";286;1
"Unit";"Zergling";"Larva";286;1
"Unit";"Zergling";"Larva";286;1
"Unit";"Zergling";"Larva";286;1
"Unit";"Zergling";"Larva";286;1
"Unit";"Zergling";"Larva";286;1
"Unit";"Zergling";"Larva";286;1
"Unit";"Zergling";"Larva";286;1
"Unit";"Zergling";"Larva";286;1
"Unit";"Zergling";"Larva";286;1
"Unit";"Zergling";"Larva";286;1
"Unit";"Zergling";"Larva";286;1
"Unit";"Zergling";"Larva";286;1
"Building";"CreepTumorQueen";NA;286;0
"Building";"CreepTumorQueen";NA;286;0
"Building";"CreepTumorQueen";NA;286;0
"Upgrade";"ZergMeleeWeaponsLevel2";"EvolutionChamber";224;0
"Unit";"Ultralisk";"Larva";286;6
"Unit";"Ultralisk";"Larva";286;6
"Unit";"Ultralisk";"Larva";286;6
"Building";"CreepTumor";NA;306;0
"Building";"CreepTumor";NA;306;0
"Building";"CreepTumor";NA;306;0
"Unit";"Hydralisk";"Larva";306;2
"Unit";"Hydralisk";"Larva";306;2
"Unit";"Hydralisk";"Larva";306;2
"Unit";"Hydralisk";"Larva";306;2
"Building";"Extractor";NA;324;0
"Building";"Extractor";NA;324;0
"Unit";"Baneling";"Zergling";332;0
"Unit";"Baneling";"Zergling";332;0
"Unit";"Baneling";"Zergling";332;0
"Unit";"Baneling";"Zergling";332;0
"Unit";"Baneling";"Zergling";332;0
"Unit";"Baneling";"Zergling";332;0
"Unit";"Baneling";"Zergling";332;0
"Unit";"Baneling";"Zergling";332;0
"Unit";"Baneling";"Zergling";332;0
"Unit";"Baneling";"Zergling";332;0
"Unit";"Baneling";"Zergling";332;0
"Unit";"Baneling";"Zergling";332;0
"Unit";"Baneling";"Zergling";332;0
"Unit";"Baneling";"Zergling";332;0
"Unit";"Baneling";"Zergling";332;0
"Unit";"Baneling";"Zergling";332;0
"Building";"CreepTumor";NA;332;0
"Building";"CreepTumor";NA;332;0
"Building";"CreepTumor";NA;332;0
"Upgrade";"ZergGroundArmorsLevel3";"EvolutionChamber";286;0
"Building";"Hatchery";NA;324;0
"Building";"Hatchery";NA;324;0
"Unit";"Corruptor";"Larva";332;2
"Unit";"Corruptor";"Larva";332;2
"Unit";"Corruptor";"Larva";332;2
"Unit";"Baneling";"Zergling";332;0
"Unit";"Baneling";"Zergling";332;0
"Unit";"Baneling";"Zergling";332;0
"Unit";"Baneling";"Zergling";332;0
"Unit";"Baneling";"Zergling";332;0
"Unit";"Baneling";"Zergling";332;0
"Unit";"Baneling";"Zergling";332;0
"Unit";"Baneling";"Zergling";332;0
"Unit";"Baneling";"Zergling";332;0
"Unit";"Baneling";"Zergling";332;0
"Unit";"Baneling";"Zergling";332;0
"Building";"CreepTumor";NA;332;0
"Unit";"Baneling";"Zergling";332;0
"Building";"CreepTumor";NA;332;0
"Building";"CreepTumor";NA;332;0
"Building";"CreepTumor";NA;332;0
"Building";"CreepTumor";NA;338;0
"Building";"CreepTumorQueen";NA;338;0
"Building";"CreepTumorQueen";NA;338;0
"Building";"CreepTumorQueen";NA;338;0
"Building";"CreepTumorQueen";NA;338;0
"Building";"CreepTumorQueen";NA;338;0
"Unit";"Zergling";"Larva";338;1
"Unit";"Zergling";"Larva";338;1
"Unit";"Zergling";"Larva";338;1
"Unit";"Zergling";"Larva";338;1
"Unit";"Zergling";"Larva";338;1
"Unit";"Zergling";"Larva";338;1
"Unit";"Zergling";"Larva";338;1
"Unit";"Zergling";"Larva";338;1
"Unit";"Zergling";"Larva";338;1
"Unit";"Zergling";"Larva";338;1
"Unit";"Zergling";"Larva";338;1
"Unit";"Zergling";"Larva";338;1
"Unit";"Zergling";"Larva";338;1
"Unit";"Zergling";"Larva";338;1
"Unit";"Zergling";"Larva";338;1
"Unit";"Zergling";"Larva";338;1
"Unit";"Zergling";"Larva";338;1
"Unit";"Zergling";"Larva";338;1
"Unit";"Zergling";"Larva";338;1
"Unit";"Zergling";"Larva";338;1
"Unit";"Zergling";"Larva";338;1
"Unit";"Zergling";"Larva";338;1
"Unit";"Zergling";"Larva";338;1
"Unit";"Zergling";"Larva";338;1
"Unit";"Zergling";"Larva";338;1
"Unit";"Zergling";"Larva";338;1
"Unit";"Zergling";"Larva";338;1
"Unit";"Zergling";"Larva";338;1
"Unit";"Zergling";"Larva";338;1
"Unit";"Zergling";"Larva";338;1
"Unit";"Zergling";"Larva";338;1
"Unit";"Zergling";"Larva";338;1
"Unit";"Zergling";"Larva";338;1
"Unit";"Zergling";"Larva";338;1
"Unit";"Zergling";"Larva";338;1
"Unit";"Zergling";"Larva";338;1
"Unit";"Zergling";"Larva";338;1
"Unit";"Zergling";"Larva";338;1
"Unit";"Zergling";"Larva";338;1
"Unit";"Zergling";"Larva";338;1
"Unit";"Zergling";"Larva";338;1
"Unit";"Zergling";"Larva";338;1
"Unit";"Corruptor";"Larva";338;2
"Unit";"Corruptor";"Larva";338;2
"Unit";"Corruptor";"Larva";338;2
"Unit";"Corruptor";"Larva";338;2
"Unit";"Corruptor";"Larva";338;2
"Unit";"Corruptor";"Larva";338;2
"Unit";"Zergling";"Larva";338;1
"Unit";"Zergling";"Larva";338;1
"Unit";"Zergling";"Larva";338;1
"Unit";"Zergling";"Larva";338;1
"Unit";"Zergling";"Larva";338;1
"Unit";"Zergling";"Larva";338;1
"Unit";"Zergling";"Larva";338;1
"Unit";"Zergling";"Larva";338;1
"Unit";"Zergling";"Larva";338;1
"Unit";"Zergling";"Larva";338;1
"Unit";"Zergling";"Larva";338;1
"Unit";"Zergling";"Larva";338;1
"Unit";"Zergling";"Larva";338;1
"Unit";"Zergling";"Larva";338;1
"Unit";"Zergling";"Larva";338;1
"Unit";"Zergling";"Larva";338;1
"Unit";"Zergling";"Larva";338;1
"Unit";"Zergling";"Larva";338;1
"Unit";"Zergling";"Larva";338;1
"Unit";"Zergling";"Larva";338;1
"Unit";"Zergling";"Larva";338;1
"Unit";"Zergling";"Larva";338;1
"Unit";"Zergling";"Larva";338;1
"Unit";"Zergling";"Larva";338;1
"Unit";"Zergling";"Larva";338;1
"Unit";"Zergling";"Larva";338;1
"Unit";"Zergling";"Larva";338;1
"Unit";"Zergling";"Larva";338;1
"Unit";"Zergling";"Larva";338;1
"Unit";"Zergling";"Larva";338;1
"Unit";"Zergling";"Larva";338;1
"Unit";"Zergling";"Larva";338;1
"Unit";"Zergling";"Larva";338;1
"Unit";"Zergling";"Larva";338;1
"Unit";"Zergling";"Larva";338;1
"Unit";"Zergling";"Larva";338;1
"Unit";"Zergling";"Larva";338;1
"Unit";"Zergling";"Larva";338;1
"Building";"CreepTumor";NA;380;0
"Building";"CreepTumor";NA;380;0
"Building";"CreepTumor";NA;380;0
"Building";"CreepTumor";NA;426;0
"Building";"CreepTumor";NA;430;0
"Building";"CreepTumor";NA;430;0
"Building";"CreepTumor";NA;430;0
"Building";"SporeCrawler";NA;430;0
"Unit";"Ultralisk";"Larva";392;6
"Unit";"Ultralisk";"Larva";392;6
"Building";"CreepTumor";NA;433;0
"Building";"CreepTumor";NA;433;0
"Building";"SpineCrawler";NA;430;0
"Building";"SpineCrawler";NA;430;0
"Building";"SpineCrawler";NA;430;0
"Building";"SpineCrawler";NA;430;0
"Building";"CreepTumor";NA;445;0
"Building";"CreepTumor";NA;445;0
"Building";"CreepTumor";NA;445;0
"Building";"CreepTumorQueen";NA;445;0
"Building";"CreepTumorQueen";NA;445;0
"Unit";"Hydralisk";"Larva";433;2
"Building";"CreepTumorQueen";NA;445;0
"Unit";"Baneling";"Zergling";445;0
"Unit";"Baneling";"Zergling";445;0
"Unit";"Baneling";"Zergling";445;0
"Unit";"Baneling";"Zergling";445;0
"Unit";"Baneling";"Zergling";445;0
"Unit";"Baneling";"Zergling";445;0
"Unit";"Baneling";"Zergling";445;0
"Unit";"Baneling";"Zergling";445;0
"Unit";"Baneling";"Zergling";445;0
"Unit";"Baneling";"Zergling";445;0
"Unit";"Baneling";"Zergling";445;0
"Unit";"Baneling";"Zergling";445;0
"Unit";"Baneling";"Zergling";445;0
"Unit";"Baneling";"Zergling";445;0
"Unit";"Baneling";"Zergling";445;0
"Unit";"Baneling";"Zergling";445;0
"Building";"CreepTumor";NA;445;0
"Unit";"Baneling";"Zergling";445;0
"Unit";"Baneling";"Zergling";445;0
"Unit";"Baneling";"Zergling";445;0
"Unit";"Baneling";"Zergling";445;0
"Unit";"Baneling";"Zergling";445;0
"Unit";"Baneling";"Zergling";445;0
"Unit";"Baneling";"Zergling";445;0
"Building";"CreepTumorQueen";NA;445;0
"Building";"CreepTumor";NA;445;0
"Building";"CreepTumor";NA;445;0
"Building";"CreepTumor";NA;445;0
"Upgrade";"ChitinousPlating";"UltraliskCavern";430;0
"Unit";"Overlord";"Larva";447;0
"Unit";"Overlord";"Larva";447;0
"Building";"CreepTumor";NA;447;0
