"type";"unit_name";"on_building";"total_supply";"supply"
"Unit";"Overlord";"Larva";12;0
"Building";"Extractor";NA;17;0
"Building";"SpawningPool";NA;16;0
"Unit";"Zergling";"Larva";20;1
"Unit";"Zergling";"Larva";20;1
"Unit";"Zergling";"Larva";20;1
"Unit";"Zergling";"Larva";20;1
"Unit";"Queen";"Hatchery";19;2
"Unit";"Overlord";"Larva";25;0
"Building";"Hatchery";NA;19;0
"Unit";"Queen";"Hatchery";27;2
"Unit";"Overlord";"Larva";39;0
"Unit";"Overlord";"Larva";40;0
"Unit";"Overlord";"Larva";44;0
"Building";"EvolutionChamber";NA;44;0
"Building";"EvolutionChamber";NA;47;0
"Building";"Hatchery";NA;39;0
"Unit";"Queen";"Hatchery";44;2
"Unit";"Overlord";"Larva";47;0
"Building";"CreepTumorQueen";NA;48;0
"Building";"Extractor";NA;47;0
"Building";"CreepTumorQueen";NA;55;0
"Unit";"Zergling";"Larva";55;1
"Unit";"Zergling";"Larva";55;1
"Unit";"Zergling";"Larva";55;1
"Unit";"Zergling";"Larva";55;1
"Unit";"Zergling";"Larva";55;1
"Unit";"Zergling";"Larva";55;1
"Unit";"Zergling";"Larva";55;1
"Unit";"Zergling";"Larva";55;1
"Unit";"Zergling";"Larva";55;1
"Unit";"Zergling";"Larva";55;1
"Unit";"Zergling";"Larva";55;1
"Unit";"Zergling";"Larva";55;1
"Unit";"Zergling";"Larva";55;1
"Unit";"Zergling";"Larva";55;1
"Unit";"Zergling";"Larva";55;1
"Unit";"Zergling";"Larva";55;1
"Unit";"Zergling";"Larva";55;1
"Unit";"Zergling";"Larva";55;1
"Unit";"Queen";"Hatchery";53;2
"Building";"CreepTumor";NA;55;0
"Building";"CreepTumor";NA;55;0
"Unit";"Zergling";"Larva";76;1
"Unit";"Zergling";"Larva";76;1
"Unit";"Zergling";"Larva";76;1
"Unit";"Zergling";"Larva";76;1
"Unit";"Zergling";"Larva";76;1
"Unit";"Zergling";"Larva";76;1
"Unit";"Zergling";"Larva";76;1
"Unit";"Zergling";"Larva";76;1
"Building";"SporeCrawler";NA;76;0
"Unit";"Zergling";"Larva";80;1
"Unit";"Zergling";"Larva";80;1
"Unit";"Zergling";"Larva";80;1
"Unit";"Zergling";"Larva";80;1
"Building";"CreepTumor";NA;88;0
"Building";"CreepTumor";NA;88;0
"Unit";"Queen";"Hatchery";76;2
"Building";"CreepTumorQueen";NA;92;0
"Building";"BanelingNest";NA;76;0
"Unit";"Overlord";"Larva";96;0
"Unit";"Overlord";"Larva";96;0
"Unit";"Overlord";"Larva";96;0
"Unit";"Overlord";"Larva";96;0
"Building";"SporeCrawler";NA;96;0
"Upgrade";"ZergMeleeWeaponsLevel1";"EvolutionChamber";74;0
"Upgrade";"ZergGroundArmorsLevel1";"EvolutionChamber";74;0
"Unit";"Baneling";"Zergling";96;0
"Unit";"Baneling";"Zergling";96;0
"Unit";"Baneling";"Zergling";96;0
"Unit";"Baneling";"Zergling";96;0
"Unit";"Baneling";"Zergling";96;0
"Unit";"Baneling";"Zergling";96;0
"Unit";"Baneling";"Zergling";96;0
"Unit";"Baneling";"Zergling";96;0
"Unit";"Baneling";"Zergling";96;0
"Unit";"Baneling";"Zergling";96;0
"Unit";"Baneling";"Zergling";96;0
"Unit";"Zergling";"Larva";96;1
"Unit";"Zergling";"Larva";96;1
"Unit";"Zergling";"Larva";96;1
"Unit";"Zergling";"Larva";96;1
"Unit";"Zergling";"Larva";96;1
"Unit";"Zergling";"Larva";96;1
"Unit";"Zergling";"Larva";96;1
"Unit";"Zergling";"Larva";96;1
"Unit";"Zergling";"Larva";96;1
"Unit";"Zergling";"Larva";96;1
"Unit";"Zergling";"Larva";96;1
"Unit";"Zergling";"Larva";96;1
"Unit";"Zergling";"Larva";96;1
"Unit";"Zergling";"Larva";96;1
"Unit";"Zergling";"Larva";96;1
"Unit";"Zergling";"Larva";96;1
"Unit";"Zergling";"Larva";96;1
"Unit";"Zergling";"Larva";96;1
"Unit";"Zergling";"Larva";96;1
"Unit";"Zergling";"Larva";96;1
"Unit";"Zergling";"Larva";96;1
"Unit";"Zergling";"Larva";96;1
"Unit";"Zergling";"Larva";96;1
"Unit";"Zergling";"Larva";96;1
"Unit";"Zergling";"Larva";96;1
"Unit";"Zergling";"Larva";96;1
"Unit";"Zergling";"Larva";96;1
"Unit";"Zergling";"Larva";96;1
"Unit";"Zergling";"Larva";96;1
"Unit";"Zergling";"Larva";96;1
"Unit";"Zergling";"Larva";96;1
"Unit";"Zergling";"Larva";96;1
"Unit";"Zergling";"Larva";96;1
"Unit";"Zergling";"Larva";96;1
"Unit";"Zergling";"Larva";96;1
"Unit";"Zergling";"Larva";96;1
"Unit";"Zergling";"Larva";96;1
"Unit";"Zergling";"Larva";96;1
"Unit";"Zergling";"Larva";96;1
"Unit";"Zergling";"Larva";96;1
"Unit";"Zergling";"Larva";96;1
"Unit";"Zergling";"Larva";96;1
"Unit";"Zergling";"Larva";138;1
"Unit";"Zergling";"Larva";138;1
"Unit";"Zergling";"Larva";138;1
"Unit";"Zergling";"Larva";138;1
"Unit";"Zergling";"Larva";138;1
"Unit";"Zergling";"Larva";138;1
"Unit";"Zergling";"Larva";138;1
"Unit";"Zergling";"Larva";138;1
"Unit";"Zergling";"Larva";138;1
"Unit";"Zergling";"Larva";138;1
"Unit";"Zergling";"Larva";138;1
"Unit";"Zergling";"Larva";138;1
"Unit";"Zergling";"Larva";138;1
"Unit";"Zergling";"Larva";138;1
"Unit";"Zergling";"Larva";138;1
"Unit";"Zergling";"Larva";138;1
"Unit";"Zergling";"Larva";138;1
"Unit";"Zergling";"Larva";138;1
"Unit";"Zergling";"Larva";138;1
"Unit";"Zergling";"Larva";138;1
"Unit";"Zergling";"Larva";138;1
"Unit";"Zergling";"Larva";138;1
"Unit";"Zergling";"Larva";138;1
"Unit";"Zergling";"Larva";138;1
"Unit";"Zergling";"Larva";138;1
"Unit";"Zergling";"Larva";138;1
"Unit";"Zergling";"Larva";162;1
"Unit";"Zergling";"Larva";162;1
"Unit";"Zergling";"Larva";162;1
"Unit";"Zergling";"Larva";162;1
"Unit";"Zergling";"Larva";162;1
"Unit";"Zergling";"Larva";162;1
"Building";"CreepTumor";NA;165;0
"Unit";"Baneling";"Zergling";165;0
"Unit";"Baneling";"Zergling";165;0
"Unit";"Baneling";"Zergling";165;0
"Unit";"Baneling";"Zergling";165;0
"Unit";"Baneling";"Zergling";165;0
"Unit";"Baneling";"Zergling";165;0
"Unit";"Baneling";"Zergling";165;0
"Unit";"Zergling";"Larva";171;1
"Unit";"Zergling";"Larva";171;1
"Unit";"Zergling";"Larva";171;1
"Unit";"Zergling";"Larva";171;1
"Unit";"Zergling";"Larva";172;1
"Unit";"Zergling";"Larva";172;1
"Unit";"Zergling";"Larva";172;1
"Unit";"Zergling";"Larva";172;1
"Unit";"Zergling";"Larva";172;1
"Unit";"Zergling";"Larva";172;1
"Unit";"Zergling";"Larva";177;1
"Unit";"Zergling";"Larva";177;1
"Unit";"Zergling";"Larva";191;1
"Unit";"Zergling";"Larva";191;1
"Unit";"Zergling";"Larva";191;1
"Unit";"Zergling";"Larva";191;1
"Unit";"Zergling";"Larva";191;1
"Unit";"Zergling";"Larva";191;1
"Unit";"Zergling";"Larva";191;1
"Unit";"Zergling";"Larva";191;1
"Unit";"Zergling";"Larva";191;1
"Unit";"Zergling";"Larva";191;1
"Unit";"Zergling";"Larva";191;1
"Unit";"Zergling";"Larva";191;1
"Upgrade";"ZergMeleeWeaponsLevel2";"EvolutionChamber";138;0
"Unit";"Zergling";"Larva";209;1
"Unit";"Zergling";"Larva";209;1
"Unit";"Overlord";"Larva";209;0
"Unit";"Zergling";"Larva";209;1
"Unit";"Zergling";"Larva";209;1
"Unit";"Zergling";"Larva";209;1
"Unit";"Zergling";"Larva";209;1
"Building";"CreepTumor";NA;209;0
"Building";"CreepTumor";NA;209;0
"Unit";"Overlord";"Larva";220;0
"Unit";"Overlord";"Larva";220;0
"Unit";"Overlord";"Larva";220;0
"Unit";"Overlord";"Larva";220;0
"Unit";"Overlord";"Larva";220;0
"Building";"CreepTumorQueen";NA;220;0
"Unit";"Baneling";"Zergling";220;0
"Unit";"Baneling";"Zergling";220;0
"Unit";"Baneling";"Zergling";220;0
"Unit";"Baneling";"Zergling";220;0
"Unit";"Baneling";"Zergling";220;0
"Unit";"Baneling";"Zergling";220;0
"Unit";"Baneling";"Zergling";220;0
"Unit";"Baneling";"Zergling";220;0
"Unit";"Baneling";"Zergling";220;0
"Unit";"Baneling";"Zergling";220;0
"Unit";"Baneling";"Zergling";220;0
"Unit";"Baneling";"Zergling";220;0
"Unit";"Baneling";"Zergling";220;0
"Unit";"Baneling";"Zergling";220;0
"Unit";"Baneling";"Zergling";220;0
"Building";"CreepTumorQueen";NA;220;0
"Unit";"Overlord";"Larva";220;0
"Unit";"Overlord";"Larva";220;0
"Building";"CreepTumor";NA;220;0
"Building";"CreepTumor";NA;220;0
"Upgrade";"ZergGroundArmorsLevel2";"EvolutionChamber";189;0
"Unit";"Zergling";"Larva";220;1
"Unit";"Zergling";"Larva";220;1
"Unit";"Zergling";"Larva";220;1
"Unit";"Zergling";"Larva";220;1
"Unit";"Zergling";"Larva";220;1
"Unit";"Zergling";"Larva";220;1
"Unit";"Zergling";"Larva";220;1
"Unit";"Zergling";"Larva";220;1
"Unit";"Zergling";"Larva";220;1
"Unit";"Zergling";"Larva";220;1
"Unit";"Zergling";"Larva";220;1
"Unit";"Zergling";"Larva";220;1
"Unit";"Zergling";"Larva";220;1
"Unit";"Zergling";"Larva";220;1
"Unit";"Zergling";"Larva";220;1
"Unit";"Zergling";"Larva";220;1
"Unit";"Zergling";"Larva";220;1
"Unit";"Zergling";"Larva";220;1
"Unit";"Zergling";"Larva";220;1
"Unit";"Zergling";"Larva";220;1
"Unit";"Zergling";"Larva";220;1
"Unit";"Zergling";"Larva";220;1
"Unit";"Zergling";"Larva";220;1
"Unit";"Zergling";"Larva";220;1
"Unit";"Zergling";"Larva";220;1
"Unit";"Zergling";"Larva";220;1
"Unit";"Zergling";"Larva";220;1
"Unit";"Zergling";"Larva";220;1
"Building";"Hatchery";NA;209;0
"Unit";"Zergling";"Larva";220;1
"Unit";"Zergling";"Larva";220;1
"Unit";"Zergling";"Larva";220;1
"Unit";"Zergling";"Larva";220;1
"Unit";"Zergling";"Larva";220;1
"Unit";"Zergling";"Larva";220;1
"Unit";"Zergling";"Larva";220;1
"Unit";"Zergling";"Larva";220;1
"Unit";"Zergling";"Larva";220;1
"Unit";"Zergling";"Larva";220;1
"Unit";"Zergling";"Larva";220;1
"Unit";"Zergling";"Larva";220;1
"Unit";"Zergling";"Larva";220;1
"Unit";"Zergling";"Larva";220;1
"Unit";"Zergling";"Larva";220;1
"Unit";"Zergling";"Larva";220;1
"Building";"CreepTumor";NA;248;0
"Unit";"Zergling";"Larva";264;1
"Unit";"Zergling";"Larva";264;1
"Unit";"Zergling";"Larva";264;1
"Unit";"Zergling";"Larva";264;1
"Unit";"Zergling";"Larva";264;1
"Unit";"Zergling";"Larva";264;1
"Unit";"Zergling";"Larva";264;1
"Unit";"Zergling";"Larva";264;1
"Unit";"Zergling";"Larva";264;1
"Unit";"Zergling";"Larva";264;1
"Unit";"Zergling";"Larva";264;1
"Unit";"Zergling";"Larva";264;1
"Unit";"Zergling";"Larva";264;1
"Unit";"Zergling";"Larva";264;1
"Unit";"Zergling";"Larva";264;1
"Unit";"Zergling";"Larva";264;1
"Unit";"Zergling";"Larva";264;1
"Unit";"Zergling";"Larva";264;1
"Unit";"Zergling";"Larva";264;1
"Unit";"Zergling";"Larva";264;1
"Unit";"Zergling";"Larva";264;1
"Unit";"Zergling";"Larva";264;1
"Unit";"Queen";"Hatchery";248;2
"Building";"Hatchery";NA;220;0
"Unit";"Zergling";"Larva";264;1
"Unit";"Zergling";"Larva";264;1
"Unit";"Zergling";"Larva";264;1
"Unit";"Zergling";"Larva";264;1
"Unit";"Zergling";"Larva";264;1
"Unit";"Zergling";"Larva";264;1
"Unit";"Zergling";"Larva";264;1
"Unit";"Zergling";"Larva";264;1
"Unit";"Zergling";"Larva";264;1
"Unit";"Zergling";"Larva";264;1
"Unit";"Zergling";"Larva";264;1
"Unit";"Zergling";"Larva";264;1
"Unit";"Zergling";"Larva";264;1
"Unit";"Zergling";"Larva";264;1
"Building";"SporeCrawler";NA;264;0
"Building";"SporeCrawler";NA;264;0
"Building";"SporeCrawler";NA;266;0
"Building";"Extractor";NA;303;0
"Building";"Extractor";NA;323;0
"Unit";"Baneling";"Zergling";323;0
"Unit";"Baneling";"Zergling";323;0
"Unit";"Baneling";"Zergling";323;0
"Unit";"Baneling";"Zergling";323;0
"Unit";"Baneling";"Zergling";323;0
"Unit";"Baneling";"Zergling";323;0
"Unit";"Baneling";"Zergling";323;0
"Unit";"Baneling";"Zergling";323;0
"Unit";"Baneling";"Zergling";323;0
"Unit";"Baneling";"Zergling";323;0
"Unit";"Baneling";"Zergling";323;0
"Unit";"Baneling";"Zergling";323;0
"Unit";"Baneling";"Zergling";323;0
"Unit";"Baneling";"Zergling";323;0
"Unit";"Baneling";"Zergling";323;0
"Unit";"Baneling";"Zergling";323;0
"Unit";"Baneling";"Zergling";323;0
"Unit";"Baneling";"Zergling";323;0
"Unit";"Baneling";"Zergling";323;0
"Unit";"Baneling";"Zergling";323;0
"Building";"Extractor";NA;323;0
"Building";"Extractor";NA;323;0
