"type";"unit_name";"on_building";"total_supply_lag";"supply"
"Unit";"Overlord";"Larva";13;0
"Building";"SpawningPool";NA;16;0
"Building";"Hatchery";NA;18;0
"Building";"Extractor";NA;20;0
"Unit";"Zergling";"Larva";21;1
"Unit";"Zergling";"Larva";22;1
"Unit";"Queen";"Hatchery";23;2
"Unit";"Overlord";"Larva";25;0
"Unit";"Queen";"Hatchery";27;2
"Unit";"Queen";"Hatchery";30;2
"Unit";"Zergling";"Larva";32;1
"Unit";"Zergling";"Larva";33;1
"Unit";"Overlord";"Larva";35;0
"Building";"CreepTumorQueen";NA;38;0
"Building";"CreepTumor";NA;44;0
"Unit";"Overlord";"Larva";45;0
"Building";"CreepTumorQueen";NA;47;0
"Unit";"Zergling";"Larva";49;1
"Unit";"Zergling";"Larva";50;1
"Unit";"Zergling";"Larva";51;1
"Unit";"Zergling";"Larva";52;1
"Unit";"Overlord";"Larva";55;0
"Building";"CreepTumor";NA;56;0
"Building";"CreepTumor";NA;56;0
"Unit";"Overlord";"Larva";57;0
"Building";"Hatchery";NA;57;0
"Building";"BanelingNest";NA;57;0
"Unit";"Zergling";"Larva";57;1
"Unit";"Zergling";"Larva";58;1
"Unit";"Zergling";"Larva";60;1
"Unit";"Zergling";"Larva";61;1
"Unit";"Queen";"Hatchery";62;2
"Building";"CreepTumor";NA;69;0
"Unit";"Zergling";"Larva";69;1
"Unit";"Zergling";"Larva";70;1
"Building";"SporeCrawler";NA;73;0
"Building";"SporeCrawler";NA;73;0
"Building";"SporeCrawler";NA;73;0
"Unit";"Zergling";"Larva";74;1
"Unit";"Zergling";"Larva";75;1
"Building";"SporeCrawler";NA;76;0
"Unit";"Zergling";"Larva";77;1
"Unit";"Zergling";"Larva";78;1
"Unit";"Queen";"Hatchery";82;2
"Unit";"Queen";"Hatchery";84;2
"Building";"CreepTumor";NA;87;0
"Building";"CreepTumor";NA;87;0
"Unit";"Overlord";"Larva";87;0
"Unit";"Overlord";"Larva";87;0
"Building";"EvolutionChamber";NA;87;0
"Unit";"Overlord";"Larva";87;0
"Building";"EvolutionChamber";NA;88;0
"Unit";"Zergling";"Larva";94;1
"Unit";"Zergling";"Larva";95;1
"Building";"Extractor";NA;96;0
"Building";"Extractor";NA;96;0
"Building";"CreepTumor";NA;99;0
"Building";"CreepTumor";NA;99;0
"Unit";"Zergling";"Larva";100;1
"Unit";"Zergling";"Larva";101;1
"Unit";"Zergling";"Larva";107;1
"Unit";"Zergling";"Larva";108;1
"Building";"CreepTumorQueen";NA;109;0
"Building";"Hatchery";NA;110;0
"Unit";"Zergling";"Larva";110;1
"Unit";"Zergling";"Larva";111;1
"Building";"Extractor";NA;112;0
"Building";"Extractor";NA;112;0
"Building";"Extractor";NA;112;0
"Building";"RoachWarren";NA;119;0
"Building";"CreepTumor";NA;123;0
"Building";"CreepTumorQueen";NA;123;0
"Building";"CreepTumorQueen";NA;123;0
"Building";"CreepTumor";NA;123;0
"Building";"CreepTumor";NA;124;0
"Unit";"Overlord";"Larva";124;0
"Building";"SporeCrawler";NA;125;0
"Unit";"Zergling";"Larva";125;1
"Unit";"Zergling";"Larva";126;1
"Unit";"Zergling";"Larva";127;1
"Unit";"Zergling";"Larva";128;1
"Unit";"Zergling";"Larva";129;1
"Unit";"Zergling";"Larva";130;1
"Unit";"Zergling";"Larva";131;1
"Unit";"Zergling";"Larva";132;1
"Unit";"Zergling";"Larva";133;1
"Unit";"Zergling";"Larva";134;1
"Unit";"Zergling";"Larva";135;1
"Unit";"Zergling";"Larva";136;1
"Unit";"Zergling";"Larva";137;1
"Unit";"Zergling";"Larva";138;1
"Unit";"Overlord";"Larva";139;0
"Unit";"Overlord";"Larva";139;0
"Building";"CreepTumorQueen";NA;139;0
"Building";"CreepTumor";NA;139;0
"Building";"CreepTumor";NA;139;0
"Building";"CreepTumor";NA;139;0
"Unit";"Baneling";"Zergling";139;0
"Unit";"Baneling";"Zergling";139;0
"Unit";"Overlord";"Larva";139;0
"Unit";"Zergling";"Larva";139;1
"Unit";"Zergling";"Larva";140;1
"Unit";"Zergling";"Larva";141;1
"Unit";"Zergling";"Larva";142;1
"Building";"CreepTumor";NA;143;0
"Building";"CreepTumor";NA;143;0
"Unit";"Zergling";"Larva";143;1
"Unit";"Zergling";"Larva";144;1
"Unit";"Zergling";"Larva";145;1
"Unit";"Zergling";"Larva";146;1
"Unit";"Zergling";"Larva";147;1
"Unit";"Zergling";"Larva";148;1
"Building";"CreepTumorQueen";NA;150;0
"Unit";"Baneling";"Zergling";151;0
"Unit";"Baneling";"Zergling";151;0
"Unit";"Baneling";"Zergling";151;0
"Unit";"Zergling";"Larva";151;1
"Unit";"Zergling";"Larva";152;1
"Unit";"Zergling";"Larva";155;1
"Unit";"Zergling";"Larva";156;1
"Unit";"Zergling";"Larva";157;1
"Unit";"Zergling";"Larva";158;1
"Unit";"Zergling";"Larva";159;1
"Unit";"Zergling";"Larva";160;1
"Unit";"Zergling";"Larva";161;1
"Unit";"Zergling";"Larva";162;1
"Building";"HydraliskDen";NA;164;0
"Building";"CreepTumor";NA;171;0
"Building";"CreepTumor";NA;171;0
"Building";"CreepTumor";NA;173;0
"Unit";"Zergling";"Larva";177;1
"Unit";"Zergling";"Larva";178;1
"Unit";"Zergling";"Larva";179;1
"Unit";"Zergling";"Larva";180;1
"Unit";"Overlord";"Larva";181;0
"Unit";"Overlord";"Larva";181;0
"Building";"SporeCrawler";NA;181;0
"Building";"CreepTumor";NA;181;0
"Unit";"Baneling";"Zergling";181;0
"Unit";"Baneling";"Zergling";181;0
"Unit";"Zergling";"Larva";181;1
"Unit";"Zergling";"Larva";182;1
"Unit";"Zergling";"Larva";183;1
"Unit";"Zergling";"Larva";184;1
"Unit";"Zergling";"Larva";185;1
"Unit";"Zergling";"Larva";186;1
"Unit";"Zergling";"Larva";187;1
"Unit";"Zergling";"Larva";188;1
"Building";"CreepTumorQueen";NA;191;0
"Building";"InfestationPit";NA;191;0
"Unit";"Hydralisk";"Larva";191;2
"Unit";"Hydralisk";"Larva";193;2
"Building";"EvolutionChamber";NA;195;0
"Unit";"Hydralisk";"Larva";195;2
"Building";"CreepTumor";NA;197;0
"Building";"CreepTumorQueen";NA;197;0
"Building";"CreepTumor";NA;197;0
"Building";"CreepTumor";NA;197;0
"Unit";"Hydralisk";"Larva";197;2
"Building";"CreepTumor";NA;199;0
"Building";"CreepTumorQueen";NA;199;0
"Building";"CreepTumor";NA;199;0
"Unit";"Overlord";"Larva";204;0
"Unit";"Hydralisk";"Larva";204;2
"Unit";"Overlord";"Larva";206;0
"Unit";"Zergling";"Larva";206;1
"Unit";"Zergling";"Larva";207;1
"Unit";"Zergling";"Larva";208;1
"Unit";"Zergling";"Larva";209;1
"Unit";"Zergling";"Larva";210;1
"Unit";"Zergling";"Larva";211;1
"Unit";"Zergling";"Larva";212;1
"Unit";"Zergling";"Larva";213;1
"Unit";"Zergling";"Larva";214;1
"Unit";"Zergling";"Larva";215;1
"Unit";"Zergling";"Larva";216;1
"Unit";"Zergling";"Larva";217;1
"Building";"CreepTumor";NA;218;0
"Unit";"Zergling";"Larva";218;1
"Unit";"Zergling";"Larva";219;1
"Building";"CreepTumor";NA;220;0
"Unit";"Zergling";"Larva";220;1
"Unit";"Zergling";"Larva";221;1
"Unit";"Zergling";"Larva";222;1
"Unit";"Zergling";"Larva";223;1
"Building";"CreepTumor";NA;224;0
"Unit";"Zergling";"Larva";224;1
"Unit";"Zergling";"Larva";225;1
"Building";"CreepTumor";NA;226;0
"Unit";"Zergling";"Larva";226;1
"Unit";"Zergling";"Larva";227;1
"Unit";"Zergling";"Larva";228;1
"Unit";"Zergling";"Larva";229;1
"Building";"CreepTumor";NA;230;0
"Building";"CreepTumor";NA;230;0
"Building";"CreepTumor";NA;230;0
"Building";"CreepTumor";NA;230;0
"Building";"Extractor";NA;230;0
"Unit";"Overlord";"Larva";230;0
"Unit";"Hydralisk";"Larva";230;2
"Unit";"Hydralisk";"Larva";232;2
"Unit";"Hydralisk";"Larva";234;2
"Unit";"Hydralisk";"Larva";236;2
"Unit";"Zergling";"Larva";238;1
"Unit";"Zergling";"Larva";239;1
"Unit";"Zergling";"Larva";240;1
"Unit";"Zergling";"Larva";241;1
"Building";"CreepTumorQueen";NA;242;0
"Building";"CreepTumorQueen";NA;242;0
"Unit";"Zergling";"Larva";242;1
"Unit";"Zergling";"Larva";243;1
"Unit";"Zergling";"Larva";244;1
"Unit";"Zergling";"Larva";245;1
"Unit";"Zergling";"Larva";246;1
"Unit";"Zergling";"Larva";247;1
"Unit";"Zergling";"Larva";248;1
"Unit";"Zergling";"Larva";249;1
"Unit";"Overlord";"Larva";250;0
"Unit";"Hydralisk";"Larva";250;2
"Building";"CreepTumor";NA;252;0
"Unit";"Zergling";"Larva";252;1
"Unit";"Zergling";"Larva";253;1
"Unit";"Zergling";"Larva";254;1
"Unit";"Zergling";"Larva";255;1
"Building";"CreepTumor";NA;256;0
"Unit";"Zergling";"Larva";256;1
"Unit";"Zergling";"Larva";257;1
"Building";"Hatchery";NA;258;0
"Unit";"Zergling";"Larva";258;1
"Unit";"Zergling";"Larva";259;1
"Unit";"Zergling";"Larva";260;1
"Unit";"Zergling";"Larva";261;1
"Unit";"Zergling";"Larva";262;1
"Unit";"Zergling";"Larva";263;1
"Unit";"Zergling";"Larva";264;1
"Unit";"Zergling";"Larva";265;1
"Unit";"Zergling";"Larva";266;1
"Unit";"Zergling";"Larva";267;1
"Unit";"Hydralisk";"Larva";268;2
"Unit";"Zergling";"Larva";270;1
"Unit";"Zergling";"Larva";271;1
"Unit";"Hydralisk";"Larva";272;2
"Unit";"Hydralisk";"Larva";274;2
"Building";"CreepTumor";NA;276;0
"Unit";"Hydralisk";"Larva";276;2
"Building";"CreepTumor";NA;278;0
"Unit";"Zergling";"Larva";278;1
"Unit";"Zergling";"Larva";279;1
"Unit";"Queen";"Hatchery";282;2
"Unit";"Zergling";"Larva";284;1
"Unit";"Zergling";"Larva";285;1
"Unit";"Zergling";"Larva";286;1
"Unit";"Zergling";"Larva";287;1
"Unit";"Zergling";"Larva";288;1
"Unit";"Zergling";"Larva";289;1
"Unit";"Hydralisk";"Larva";290;2
"Unit";"Hydralisk";"Larva";292;2
"Unit";"Zergling";"Larva";294;1
"Unit";"Zergling";"Larva";295;1
"Unit";"Zergling";"Larva";296;1
"Unit";"Zergling";"Larva";297;1
"Unit";"Zergling";"Larva";298;1
"Unit";"Zergling";"Larva";299;1
"Unit";"Zergling";"Larva";300;1
"Unit";"Zergling";"Larva";301;1
"Unit";"Zergling";"Larva";302;1
"Unit";"Zergling";"Larva";303;1
"Unit";"Zergling";"Larva";304;1
"Unit";"Zergling";"Larva";305;1
"Unit";"Zergling";"Larva";306;1
"Unit";"Zergling";"Larva";307;1
"Unit";"Zergling";"Larva";308;1
"Unit";"Zergling";"Larva";309;1
"Unit";"Overlord";"Larva";310;0
"Unit";"Overlord";"Larva";310;0
"Unit";"Overlord";"Larva";310;0
"Building";"CreepTumorQueen";NA;310;0
"Unit";"Overlord";"Larva";310;0
"Unit";"Zergling";"Larva";310;1
"Unit";"Zergling";"Larva";311;1
"Unit";"Zergling";"Larva";312;1
"Unit";"Zergling";"Larva";313;1
"Unit";"Zergling";"Larva";314;1
"Unit";"Zergling";"Larva";315;1
"Unit";"Zergling";"Larva";316;1
"Unit";"Zergling";"Larva";317;1
"Unit";"Zergling";"Larva";318;1
"Unit";"Zergling";"Larva";319;1
"Unit";"Overlord";"Larva";320;0
"Unit";"Overlord";"Larva";320;0
"Unit";"Overlord";"Larva";320;0
"Unit";"Overlord";"Larva";320;0
"Unit";"Baneling";"Zergling";321;0
"Unit";"Baneling";"Zergling";321;0
"Unit";"Baneling";"Zergling";321;0
"Unit";"Baneling";"Zergling";321;0
"Unit";"Baneling";"Zergling";321;0
"Unit";"Baneling";"Zergling";321;0
"Building";"CreepTumor";NA;321;0
"Building";"CreepTumor";NA;321;0
"Building";"UltraliskCavern";NA;321;0
"Unit";"Viper";"Larva";321;3
"Unit";"Viper";"Larva";324;3
"Unit";"Zergling";"Larva";327;1
"Unit";"Zergling";"Larva";328;1
"Unit";"Zergling";"Larva";329;1
"Unit";"Zergling";"Larva";330;1
"Unit";"Zergling";"Larva";331;1
"Unit";"Zergling";"Larva";332;1
"Unit";"Zergling";"Larva";333;1
"Unit";"Zergling";"Larva";334;1
"Unit";"Zergling";"Larva";335;1
"Unit";"Zergling";"Larva";336;1
"Unit";"Zergling";"Larva";337;1
"Unit";"Zergling";"Larva";338;1
"Unit";"Zergling";"Larva";339;1
"Unit";"Zergling";"Larva";340;1
"Unit";"Zergling";"Larva";341;1
"Unit";"Zergling";"Larva";342;1
"Unit";"Zergling";"Larva";343;1
"Unit";"Zergling";"Larva";344;1
"Unit";"Zergling";"Larva";345;1
"Unit";"Zergling";"Larva";346;1
"Unit";"Zergling";"Larva";347;1
"Unit";"Zergling";"Larva";348;1
"Building";"CreepTumor";NA;349;0
"Unit";"Zergling";"Larva";349;1
"Unit";"Zergling";"Larva";350;1
"Unit";"Zergling";"Larva";351;1
"Unit";"Zergling";"Larva";352;1
"Unit";"Zergling";"Larva";353;1
"Unit";"Zergling";"Larva";354;1
"Unit";"Zergling";"Larva";355;1
"Unit";"Zergling";"Larva";356;1
"Unit";"Zergling";"Larva";357;1
"Unit";"Zergling";"Larva";358;1
"Unit";"Overlord";"Larva";359;0
"Unit";"Zergling";"Larva";359;1
"Unit";"Zergling";"Larva";360;1
"Unit";"Zergling";"Larva";361;1
"Unit";"Zergling";"Larva";362;1
"Unit";"Overlord";"Larva";363;0
"Building";"CreepTumorQueen";NA;363;0
"Building";"CreepTumor";NA;363;0
"Building";"CreepTumor";NA;363;0
"Building";"CreepTumor";NA;363;0
"Unit";"Zergling";"Larva";368;1
"Unit";"Zergling";"Larva";369;1
"Unit";"Zergling";"Larva";370;1
"Unit";"Zergling";"Larva";371;1
"Unit";"Hydralisk";"Larva";372;2
"Unit";"Hydralisk";"Larva";374;2
"Unit";"Hydralisk";"Larva";376;2
"Unit";"Hydralisk";"Larva";378;2
"Unit";"Hydralisk";"Larva";380;2
"Unit";"Hydralisk";"Larva";382;2
"Unit";"Hydralisk";"Larva";384;2
"Unit";"Hydralisk";"Larva";386;2
"Unit";"Hydralisk";"Larva";388;2
"Unit";"Ultralisk";"Larva";390;6
"Unit";"Ultralisk";"Larva";396;6
"Unit";"Zergling";"Larva";402;1
"Unit";"Zergling";"Larva";403;1
"Unit";"Zergling";"Larva";404;1
"Unit";"Zergling";"Larva";405;1
"Unit";"Zergling";"Larva";406;1
"Unit";"Zergling";"Larva";407;1
"Unit";"Zergling";"Larva";408;1
"Unit";"Zergling";"Larva";409;1
"Upgrade";"ChitinousPlating";"UltraliskCavern";410;0
"Unit";"Ultralisk";"Larva";410;6
"Unit";"Zergling";"Larva";416;1
"Unit";"Zergling";"Larva";417;1
"Unit";"Zergling";"Larva";418;1
"Unit";"Zergling";"Larva";419;1
"Unit";"Zergling";"Larva";421;1
"Unit";"Zergling";"Larva";422;1
"Unit";"Zergling";"Larva";423;1
"Unit";"Zergling";"Larva";424;1
"Unit";"Zergling";"Larva";425;1
"Unit";"Zergling";"Larva";426;1
"Unit";"Ultralisk";"Larva";427;6
"Unit";"Overlord";"Larva";433;0
"Unit";"Overlord";"Larva";433;0
"Unit";"Ultralisk";"Larva";433;6
"Unit";"Overlord";"Larva";439;0
"Unit";"Zergling";"Larva";439;1
"Unit";"Zergling";"Larva";440;1
"Unit";"Overlord";"Larva";441;0
"Building";"CreepTumor";NA;441;0
"Unit";"Overlord";"Larva";441;0
"Building";"Hatchery";NA;441;0
"Unit";"Ultralisk";"Larva";441;6
"Unit";"Baneling";"Zergling";447;0
"Unit";"Baneling";"Zergling";447;0
"Unit";"Baneling";"Zergling";447;0
"Unit";"Baneling";"Zergling";447;0
"Unit";"Baneling";"Zergling";447;0
"Unit";"Zergling";"Larva";447;1
"Unit";"Zergling";"Larva";448;1
"Building";"CreepTumor";NA;454;0
"Building";"CreepTumor";NA;454;0
"Unit";"Zergling";"Larva";454;1
"Unit";"Zergling";"Larva";455;1
"Unit";"Zergling";"Larva";456;1
"Unit";"Zergling";"Larva";457;1
"Unit";"Zergling";"Larva";458;1
"Unit";"Zergling";"Larva";459;1
"Building";"CreepTumor";NA;460;0
"Building";"CreepTumor";NA;460;0
"Building";"CreepTumorQueen";NA;460;0
"Unit";"Ultralisk";"Larva";460;6
"Building";"CreepTumorQueen";NA;466;0
"Unit";"Zergling";"Larva";466;1
"Unit";"Zergling";"Larva";467;1
"Building";"CreepTumorQueen";NA;468;0
"Building";"CreepTumorQueen";NA;468;0
"Building";"CreepTumor";NA;469;0
"Building";"CreepTumor";NA;469;0
"Unit";"Ultralisk";"Larva";469;6
"Unit";"Zergling";"Larva";475;1
"Unit";"Zergling";"Larva";476;1
"Building";"CreepTumor";NA;477;0
"Building";"CreepTumor";NA;477;0
"Building";"Hatchery";NA;477;0
"Unit";"Zergling";"Larva";477;1
"Unit";"Zergling";"Larva";478;1
"Unit";"Ultralisk";"Larva";479;6
"Unit";"Ultralisk";"Larva";485;6
"Unit";"Ultralisk";"Larva";491;6
"Unit";"Ultralisk";"Larva";497;6
"Unit";"Zergling";"Larva";503;1
"Unit";"Zergling";"Larva";504;1
"Unit";"Zergling";"Larva";505;1
"Unit";"Zergling";"Larva";506;1
"Unit";"Zergling";"Larva";507;1
"Unit";"Zergling";"Larva";508;1
"Unit";"Zergling";"Larva";509;1
"Unit";"Zergling";"Larva";510;1
"Unit";"Zergling";"Larva";511;1
"Unit";"Zergling";"Larva";512;1
"Unit";"Hydralisk";"Larva";513;2
"Unit";"Hydralisk";"Larva";515;2
"Unit";"Zergling";"Larva";527;1
"Unit";"Zergling";"Larva";528;1
"Unit";"Zergling";"Larva";529;1
"Unit";"Zergling";"Larva";530;1
"Building";"CreepTumor";NA;531;0
"Unit";"Zergling";"Larva";531;1
"Unit";"Zergling";"Larva";532;1
"Unit";"Zergling";"Larva";533;1
"Unit";"Zergling";"Larva";534;1
"Unit";"Zergling";"Larva";535;1
"Unit";"Zergling";"Larva";536;1
"Unit";"Zergling";"Larva";537;1
"Unit";"Zergling";"Larva";538;1
"Unit";"Zergling";"Larva";539;1
"Unit";"Zergling";"Larva";540;1
"Building";"Extractor";NA;541;0
"Building";"Extractor";NA;541;0
"Unit";"Zergling";"Larva";541;1
"Unit";"Zergling";"Larva";542;1
"Unit";"Zergling";"Larva";543;1
"Unit";"Zergling";"Larva";544;1
"Building";"EvolutionChamber";NA;545;0
"Building";"EvolutionChamber";NA;545;0
"Unit";"Zergling";"Larva";545;1
"Unit";"Zergling";"Larva";546;1
"Unit";"Zergling";"Larva";547;1
"Unit";"Zergling";"Larva";548;1
"Unit";"Zergling";"Larva";549;1
"Unit";"Zergling";"Larva";550;1
"Unit";"Zergling";"Larva";551;1
"Unit";"Zergling";"Larva";552;1
"Unit";"Zergling";"Larva";553;1
"Unit";"Zergling";"Larva";554;1
"Building";"CreepTumor";NA;555;0
"Unit";"Zergling";"Larva";555;1
"Unit";"Zergling";"Larva";556;1
"Unit";"Baneling";"Zergling";557;0
"Unit";"Baneling";"Zergling";557;0
"Unit";"Baneling";"Zergling";557;0
"Unit";"Baneling";"Zergling";557;0
"Unit";"Baneling";"Zergling";557;0
"Unit";"Baneling";"Zergling";557;0
"Unit";"Baneling";"Zergling";557;0
"Unit";"Baneling";"Zergling";557;0
"Unit";"Baneling";"Zergling";557;0
"Unit";"Baneling";"Zergling";557;0
"Unit";"Baneling";"Zergling";557;0
"Unit";"Baneling";"Zergling";557;0
"Unit";"Baneling";"Zergling";557;0
"Unit";"Baneling";"Zergling";557;0
"Unit";"Baneling";"Zergling";557;0
"Unit";"Zergling";"Larva";557;1
"Unit";"Zergling";"Larva";558;1
"Unit";"Zergling";"Larva";559;1
"Unit";"Zergling";"Larva";560;1
"Unit";"Zergling";"Larva";561;1
"Unit";"Zergling";"Larva";562;1
"Building";"CreepTumor";NA;563;0
"Building";"CreepTumor";NA;563;0
"Building";"CreepTumor";NA;563;0
"Building";"CreepTumor";NA;563;0
"Building";"CreepTumor";NA;563;0
"Unit";"Baneling";"Zergling";563;0
"Unit";"Baneling";"Zergling";563;0
"Unit";"Baneling";"Zergling";563;0
"Unit";"Baneling";"Zergling";563;0
"Unit";"Baneling";"Zergling";563;0
"Building";"SpineCrawler";NA;563;0
"Building";"SporeCrawler";NA;563;0
"Building";"SporeCrawler";NA;563;0
"Building";"SpineCrawler";NA;563;0
"Building";"SpineCrawler";NA;564;0
"Building";"CreepTumor";NA;565;0
"Building";"CreepTumor";NA;566;0
"Building";"CreepTumor";NA;566;0
"Unit";"Baneling";"Zergling";566;0
"Unit";"Baneling";"Zergling";566;0
"Unit";"Baneling";"Zergling";566;0
"Unit";"Baneling";"Zergling";566;0
"Unit";"Baneling";"Zergling";566;0
"Unit";"Baneling";"Zergling";566;0
"Unit";"Baneling";"Zergling";566;0
"Unit";"Baneling";"Zergling";566;0
"Unit";"Baneling";"Zergling";566;0
"Unit";"Baneling";"Zergling";566;0
"Unit";"Baneling";"Zergling";566;0
"Building";"Spire";NA;566;0
"Unit";"Zergling";"Larva";566;1
"Unit";"Zergling";"Larva";567;1
"Unit";"Zergling";"Larva";568;1
"Unit";"Zergling";"Larva";569;1
"Unit";"Zergling";"Larva";570;1
"Unit";"Zergling";"Larva";571;1
"Unit";"Zergling";"Larva";572;1
"Unit";"Zergling";"Larva";573;1
"Unit";"Zergling";"Larva";574;1
"Unit";"Zergling";"Larva";575;1
"Unit";"Zergling";"Larva";576;1
"Unit";"Zergling";"Larva";577;1
"Unit";"Zergling";"Larva";578;1
"Unit";"Zergling";"Larva";579;1
"Unit";"Zergling";"Larva";580;1
"Unit";"Zergling";"Larva";581;1
"Unit";"Zergling";"Larva";582;1
"Unit";"Zergling";"Larva";583;1
"Unit";"Zergling";"Larva";584;1
"Unit";"Zergling";"Larva";585;1
"Unit";"Zergling";"Larva";586;1
"Unit";"Zergling";"Larva";587;1
"Unit";"Hydralisk";"Larva";588;2
"Unit";"Hydralisk";"Larva";590;2
"Unit";"Hydralisk";"Larva";592;2
"Unit";"Hydralisk";"Larva";594;2
"Unit";"Hydralisk";"Larva";596;2
"Unit";"Hydralisk";"Larva";598;2
"Unit";"Hydralisk";"Larva";600;2
"Unit";"Hydralisk";"Larva";602;2
"Unit";"Hydralisk";"Larva";604;2
"Unit";"Hydralisk";"Larva";606;2
"Unit";"Hydralisk";"Larva";608;2
"Unit";"Hydralisk";"Larva";610;2
"Unit";"Hydralisk";"Larva";612;2
"Unit";"Zergling";"Larva";614;1
"Unit";"Zergling";"Larva";615;1
"Unit";"Zergling";"Larva";616;1
"Unit";"Zergling";"Larva";617;1
"Unit";"Zergling";"Larva";618;1
"Unit";"Zergling";"Larva";619;1
"Unit";"Zergling";"Larva";620;1
"Unit";"Zergling";"Larva";621;1
"Unit";"Zergling";"Larva";622;1
"Unit";"Zergling";"Larva";623;1
"Unit";"Zergling";"Larva";624;1
"Unit";"Zergling";"Larva";625;1
"Unit";"Zergling";"Larva";626;1
"Unit";"Zergling";"Larva";627;1
"Unit";"Zergling";"Larva";628;1
"Unit";"Zergling";"Larva";629;1
"Unit";"Zergling";"Larva";630;1
"Unit";"Zergling";"Larva";631;1
"Upgrade";"SprayZerg";NA;632;0
"Upgrade";"SprayZerg";NA;632;0
"Upgrade";"zerglingmovementspeed";NA;632;0
"Upgrade";"SprayZerg";NA;632;0
"Upgrade";"SprayZerg";NA;632;0
"Upgrade";"SprayZerg";NA;632;0
"Upgrade";"SprayZerg";NA;632;0
"Upgrade";"ZergGroundArmorsLevel1";NA;632;0
"Upgrade";"ZergMeleeWeaponsLevel1";NA;632;0
"Upgrade";"CentrificalHooks";NA;632;0
"Upgrade";"overlordspeed";NA;632;0
"Upgrade";"SprayZerg";NA;632;0
"Upgrade";"EvolveMuscularAugments";NA;632;0
"Upgrade";"ZergGroundArmorsLevel2";NA;632;0
"Upgrade";"ZergMeleeWeaponsLevel2";NA;632;0
"Upgrade";"SprayZerg";NA;632;0
"Upgrade";"ZergMissileWeaponsLevel1";NA;632;0
"Upgrade";"zerglingattackspeed";NA;632;0
"Upgrade";"SprayZerg";NA;632;0
"Upgrade";"SprayZerg";NA;632;0
"Upgrade";"ZergGroundArmorsLevel3";NA;632;0
"Upgrade";"ZergMeleeWeaponsLevel3";NA;632;0
"Upgrade";"SprayZerg";NA;632;0
"Upgrade";"SprayZerg";NA;632;0
"Upgrade";"SprayZerg";NA;632;0
"Upgrade";"ZergMissileWeaponsLevel2";NA;632;0
