"type";"unit_name";"on_building";"total_supply";"supply"
"Unit";"Overlord";"Larva";13;0
"Building";"Extractor";NA;19;0
"Building";"SpawningPool";NA;19;0
"Unit";"Overlord";"Larva";21;0
"Building";"Hatchery";NA;17;0
"Unit";"Zergling";"Larva";22;1
"Unit";"Zergling";"Larva";22;1
"Unit";"Queen";"Hatchery";22;2
"Unit";"Queen";"Hatchery";23;2
"Unit";"Overlord";"Larva";31;0
"Unit";"Queen";"Hatchery";27;2
"Unit";"Queen";"Hatchery";34;2
"Building";"CreepTumorQueen";NA;44;0
"Unit";"Overlord";"Larva";44;0
"Unit";"Overlord";"Larva";49;0
"Building";"EvolutionChamber";NA;44;0
"Building";"Extractor";NA;49;0
"Building";"CreepTumorQueen";NA;51;0
"Building";"BanelingNest";NA;49;0
"Unit";"Queen";"Hatchery";49;2
"Unit";"Overlord";"Larva";51;0
"Building";"CreepTumor";NA;51;0
"Building";"SporeCrawler";NA;51;0
"Building";"SporeCrawler";NA;51;0
"Unit";"Overlord";"Larva";58;0
"Unit";"Overlord";"Larva";58;0
"Building";"Hatchery";NA;44;0
"Unit";"Zergling";"Larva";58;1
"Unit";"Zergling";"Larva";58;1
"Unit";"Zergling";"Larva";58;1
"Unit";"Zergling";"Larva";58;1
"Unit";"Zergling";"Larva";58;1
"Unit";"Zergling";"Larva";58;1
"Unit";"Zergling";"Larva";58;1
"Unit";"Zergling";"Larva";58;1
"Building";"CreepTumorQueen";NA;58;0
"Building";"CreepTumorQueen";NA;58;0
"Building";"CreepTumor";NA;58;0
"Unit";"Zergling";"Larva";58;1
"Unit";"Zergling";"Larva";58;1
"Unit";"Overlord";"Larva";58;0
"Unit";"Overlord";"Larva";68;0
"Unit";"Zergling";"Larva";70;1
"Unit";"Zergling";"Larva";70;1
"Unit";"Zergling";"Larva";70;1
"Unit";"Zergling";"Larva";70;1
"Unit";"Zergling";"Larva";70;1
"Unit";"Zergling";"Larva";70;1
"Unit";"Zergling";"Larva";70;1
"Unit";"Zergling";"Larva";70;1
"Unit";"Zergling";"Larva";70;1
"Unit";"Zergling";"Larva";70;1
"Unit";"Zergling";"Larva";70;1
"Unit";"Zergling";"Larva";70;1
"Building";"CreepTumor";NA;72;0
"Building";"CreepTumor";NA;72;0
"Unit";"Zergling";"Larva";70;1
"Unit";"Zergling";"Larva";70;1
"Unit";"Zergling";"Larva";70;1
"Unit";"Zergling";"Larva";70;1
"Building";"CreepTumor";NA;72;0
"Building";"SporeCrawler";NA;70;0
"Unit";"Zergling";"Larva";88;1
"Unit";"Zergling";"Larva";88;1
"Unit";"Zergling";"Larva";88;1
"Unit";"Zergling";"Larva";88;1
"Unit";"Zergling";"Larva";88;1
"Unit";"Zergling";"Larva";88;1
"Unit";"Zergling";"Larva";88;1
"Unit";"Zergling";"Larva";88;1
"Unit";"Zergling";"Larva";88;1
"Unit";"Zergling";"Larva";88;1
"Unit";"Zergling";"Larva";88;1
"Unit";"Zergling";"Larva";88;1
"Unit";"Zergling";"Larva";88;1
"Unit";"Zergling";"Larva";88;1
"Unit";"Overlord";"Larva";88;0
"Unit";"Zergling";"Larva";88;1
"Unit";"Zergling";"Larva";88;1
"Unit";"Zergling";"Larva";88;1
"Unit";"Zergling";"Larva";88;1
"Unit";"Zergling";"Larva";88;1
"Unit";"Zergling";"Larva";88;1
"Unit";"Zergling";"Larva";88;1
"Unit";"Zergling";"Larva";88;1
"Unit";"Zergling";"Larva";88;1
"Unit";"Zergling";"Larva";88;1
"Unit";"Zergling";"Larva";88;1
"Unit";"Zergling";"Larva";88;1
"Unit";"Zergling";"Larva";88;1
"Unit";"Zergling";"Larva";88;1
"Unit";"Zergling";"Larva";88;1
"Unit";"Zergling";"Larva";88;1
"Upgrade";"ZergMeleeWeaponsLevel1";"EvolutionChamber";58;0
"Unit";"Zergling";"Larva";118;1
"Unit";"Zergling";"Larva";118;1
"Unit";"Zergling";"Larva";118;1
"Unit";"Zergling";"Larva";118;1
"Unit";"Zergling";"Larva";118;1
"Unit";"Zergling";"Larva";118;1
"Unit";"Zergling";"Larva";118;1
"Unit";"Zergling";"Larva";118;1
"Unit";"Zergling";"Larva";118;1
"Unit";"Zergling";"Larva";118;1
"Unit";"Zergling";"Larva";118;1
"Unit";"Zergling";"Larva";118;1
"Unit";"Zergling";"Larva";118;1
"Unit";"Zergling";"Larva";118;1
"Unit";"Zergling";"Larva";118;1
"Unit";"Zergling";"Larva";118;1
"Unit";"Zergling";"Larva";118;1
"Unit";"Zergling";"Larva";118;1
"Unit";"Zergling";"Larva";118;1
"Unit";"Zergling";"Larva";118;1
"Unit";"Zergling";"Larva";118;1
"Unit";"Zergling";"Larva";118;1
"Unit";"Zergling";"Larva";118;1
"Unit";"Zergling";"Larva";118;1
"Unit";"Zergling";"Larva";118;1
"Unit";"Zergling";"Larva";118;1
"Unit";"Zergling";"Larva";118;1
"Unit";"Zergling";"Larva";118;1
"Unit";"Baneling";"Zergling";118;0
"Unit";"Baneling";"Zergling";118;0
"Unit";"Baneling";"Zergling";118;0
"Unit";"Baneling";"Zergling";118;0
"Unit";"Baneling";"Zergling";118;0
"Unit";"Baneling";"Zergling";118;0
"Unit";"Baneling";"Zergling";118;0
"Unit";"Baneling";"Zergling";118;0
"Unit";"Baneling";"Zergling";118;0
"Unit";"Baneling";"Zergling";118;0
"Unit";"Zergling";"Larva";118;1
"Unit";"Zergling";"Larva";118;1
"Unit";"Zergling";"Larva";128;1
"Unit";"Zergling";"Larva";128;1
"Unit";"Zergling";"Larva";142;1
"Unit";"Zergling";"Larva";142;1
"Unit";"Zergling";"Larva";142;1
"Unit";"Zergling";"Larva";142;1
"Unit";"Zergling";"Larva";142;1
"Unit";"Zergling";"Larva";142;1
"Unit";"Baneling";"Zergling";146;0
"Unit";"Baneling";"Zergling";146;0
"Unit";"Zergling";"Larva";148;1
"Unit";"Zergling";"Larva";148;1
"Unit";"Zergling";"Larva";148;1
"Unit";"Zergling";"Larva";148;1
"Unit";"Zergling";"Larva";156;1
"Unit";"Zergling";"Larva";156;1
"Unit";"Zergling";"Larva";156;1
"Unit";"Zergling";"Larva";156;1
"Unit";"Zergling";"Larva";156;1
"Unit";"Zergling";"Larva";156;1
"Unit";"Zergling";"Larva";156;1
"Unit";"Zergling";"Larva";156;1
"Unit";"Zergling";"Larva";156;1
"Unit";"Zergling";"Larva";156;1
"Unit";"Zergling";"Larva";156;1
"Unit";"Zergling";"Larva";156;1
"Unit";"Zergling";"Larva";156;1
"Unit";"Zergling";"Larva";156;1
"Building";"CreepTumor";NA;160;0
"Building";"CreepTumor";NA;160;0
"Building";"CreepTumor";NA;160;0
"Building";"CreepTumorQueen";NA;174;0
"Building";"CreepTumor";NA;178;0
"Building";"CreepTumor";NA;179;0
"Unit";"Overlord";"Larva";181;0
"Unit";"Overlord";"Larva";181;0
"Unit";"Overlord";"Larva";181;0
"Unit";"Overlord";"Larva";181;0
"Building";"Hatchery";NA;156;0
"Upgrade";"Burrow";"Hatchery";174;0
"Building";"SporeCrawler";NA;181;0
"Unit";"Zergling";"Larva";182;1
"Unit";"Zergling";"Larva";182;1
"Unit";"Baneling";"Zergling";182;0
"Unit";"Baneling";"Zergling";182;0
"Unit";"Baneling";"Zergling";182;0
"Unit";"Baneling";"Zergling";182;0
"Unit";"Baneling";"Zergling";182;0
"Unit";"Baneling";"Zergling";182;0
"Unit";"Baneling";"Zergling";182;0
"Unit";"Baneling";"Zergling";182;0
"Unit";"Zergling";"Larva";182;1
"Unit";"Zergling";"Larva";182;1
"Building";"Hatchery";NA;160;0
"Unit";"Zergling";"Larva";182;1
"Unit";"Zergling";"Larva";182;1
"Unit";"Zergling";"Larva";182;1
"Unit";"Zergling";"Larva";182;1
"Unit";"Zergling";"Larva";182;1
"Unit";"Zergling";"Larva";182;1
"Unit";"Zergling";"Larva";182;1
"Unit";"Zergling";"Larva";182;1
"Unit";"Zergling";"Larva";182;1
"Unit";"Zergling";"Larva";182;1
"Unit";"Zergling";"Larva";182;1
"Unit";"Zergling";"Larva";182;1
"Unit";"Zergling";"Larva";182;1
"Unit";"Zergling";"Larva";182;1
"Unit";"Zergling";"Larva";182;1
"Unit";"Zergling";"Larva";182;1
"Unit";"Zergling";"Larva";182;1
"Unit";"Zergling";"Larva";182;1
"Unit";"Zergling";"Larva";182;1
"Unit";"Zergling";"Larva";182;1
"Unit";"Zergling";"Larva";182;1
"Unit";"Zergling";"Larva";182;1
"Unit";"Zergling";"Larva";182;1
"Unit";"Zergling";"Larva";182;1
"Unit";"Zergling";"Larva";182;1
"Unit";"Zergling";"Larva";182;1
"Unit";"Zergling";"Larva";208;1
"Unit";"Zergling";"Larva";208;1
"Unit";"Zergling";"Larva";210;1
"Unit";"Zergling";"Larva";210;1
"Unit";"Zergling";"Larva";210;1
"Unit";"Zergling";"Larva";210;1
"Unit";"Zergling";"Larva";212;1
"Unit";"Zergling";"Larva";212;1
"Unit";"Zergling";"Larva";212;1
"Unit";"Zergling";"Larva";212;1
"Unit";"Zergling";"Larva";212;1
"Unit";"Zergling";"Larva";212;1
"Unit";"Zergling";"Larva";212;1
"Unit";"Zergling";"Larva";212;1
"Unit";"Zergling";"Larva";212;1
"Unit";"Zergling";"Larva";212;1
"Unit";"Zergling";"Larva";212;1
"Unit";"Zergling";"Larva";212;1
"Unit";"Zergling";"Larva";212;1
"Unit";"Zergling";"Larva";212;1
"Unit";"Zergling";"Larva";212;1
"Unit";"Zergling";"Larva";212;1
"Unit";"Zergling";"Larva";234;1
"Unit";"Zergling";"Larva";234;1
"Unit";"Zergling";"Larva";234;1
"Unit";"Zergling";"Larva";234;1
"Unit";"Zergling";"Larva";234;1
"Unit";"Zergling";"Larva";234;1
"Unit";"Zergling";"Larva";234;1
"Unit";"Zergling";"Larva";234;1
"Unit";"Zergling";"Larva";234;1
"Unit";"Zergling";"Larva";234;1
"Unit";"Zergling";"Larva";234;1
"Unit";"Zergling";"Larva";234;1
"Unit";"Zergling";"Larva";234;1
"Unit";"Zergling";"Larva";234;1
"Unit";"Zergling";"Larva";234;1
"Unit";"Zergling";"Larva";234;1
"Unit";"Zergling";"Larva";234;1
"Unit";"Zergling";"Larva";234;1
"Unit";"Zergling";"Larva";234;1
"Unit";"Zergling";"Larva";234;1
"Unit";"Zergling";"Larva";234;1
"Unit";"Zergling";"Larva";234;1
"Unit";"Zergling";"Larva";234;1
"Unit";"Zergling";"Larva";234;1
"Unit";"Baneling";"Zergling";234;0
"Unit";"Baneling";"Zergling";234;0
"Unit";"Baneling";"Zergling";234;0
"Unit";"Baneling";"Zergling";234;0
"Unit";"Baneling";"Zergling";234;0
"Unit";"Baneling";"Zergling";234;0
"Unit";"Baneling";"Zergling";234;0
"Unit";"Baneling";"Zergling";234;0
"Unit";"Baneling";"Zergling";234;0
"Upgrade";"ZergGroundArmorsLevel1";"EvolutionChamber";182;0
"Unit";"Zergling";"Larva";258;1
"Unit";"Zergling";"Larva";258;1
"Unit";"Zergling";"Larva";258;1
"Unit";"Zergling";"Larva";258;1
"Unit";"Zergling";"Larva";258;1
"Unit";"Zergling";"Larva";258;1
"Unit";"Zergling";"Larva";258;1
"Unit";"Zergling";"Larva";258;1
"Unit";"Zergling";"Larva";258;1
"Unit";"Zergling";"Larva";258;1
"Unit";"Zergling";"Larva";258;1
"Unit";"Zergling";"Larva";258;1
"Unit";"Zergling";"Larva";258;1
"Unit";"Zergling";"Larva";258;1
"Unit";"Zergling";"Larva";258;1
"Unit";"Zergling";"Larva";258;1
"Unit";"Zergling";"Larva";258;1
"Unit";"Zergling";"Larva";258;1
"Unit";"Zergling";"Larva";258;1
"Unit";"Zergling";"Larva";258;1
"Unit";"Zergling";"Larva";258;1
"Unit";"Zergling";"Larva";258;1
"Unit";"Zergling";"Larva";258;1
"Unit";"Zergling";"Larva";258;1
"Unit";"Zergling";"Larva";258;1
"Unit";"Zergling";"Larva";258;1
"Unit";"Zergling";"Larva";258;1
"Unit";"Zergling";"Larva";258;1
"Unit";"Zergling";"Larva";258;1
"Unit";"Zergling";"Larva";258;1
"Unit";"Zergling";"Larva";258;1
"Unit";"Zergling";"Larva";258;1
"Unit";"Zergling";"Larva";258;1
"Unit";"Zergling";"Larva";258;1
"Unit";"Baneling";"Zergling";276;0
"Unit";"Baneling";"Zergling";276;0
"Unit";"Baneling";"Zergling";278;0
"Unit";"Baneling";"Zergling";278;0
"Unit";"Baneling";"Zergling";278;0
"Unit";"Overlord";"Larva";276;0
"Unit";"Zergling";"Larva";295;1
"Unit";"Zergling";"Larva";295;1
"Unit";"Zergling";"Larva";295;1
"Unit";"Zergling";"Larva";295;1
"Unit";"Zergling";"Larva";295;1
"Unit";"Zergling";"Larva";295;1
"Unit";"Zergling";"Larva";295;1
"Unit";"Zergling";"Larva";295;1
"Unit";"Zergling";"Larva";295;1
"Unit";"Zergling";"Larva";295;1
"Unit";"Zergling";"Larva";295;1
"Unit";"Zergling";"Larva";295;1
"Unit";"Zergling";"Larva";295;1
"Unit";"Zergling";"Larva";295;1
"Unit";"Zergling";"Larva";295;1
"Unit";"Zergling";"Larva";295;1
"Unit";"Zergling";"Larva";295;1
"Unit";"Zergling";"Larva";295;1
"Unit";"Zergling";"Larva";295;1
"Unit";"Zergling";"Larva";295;1
"Unit";"Zergling";"Larva";295;1
"Unit";"Zergling";"Larva";295;1
"Unit";"Zergling";"Larva";295;1
"Unit";"Zergling";"Larva";295;1
"Unit";"Zergling";"Larva";295;1
"Unit";"Zergling";"Larva";295;1
"Unit";"Zergling";"Larva";295;1
"Unit";"Zergling";"Larva";295;1
"Unit";"Zergling";"Larva";295;1
"Unit";"Zergling";"Larva";295;1
"Unit";"Zergling";"Larva";295;1
"Unit";"Zergling";"Larva";295;1
"Unit";"Baneling";"Zergling";327;0
"Unit";"Baneling";"Zergling";327;0
"Unit";"Baneling";"Zergling";327;0
"Unit";"Baneling";"Zergling";327;0
"Unit";"Baneling";"Zergling";327;0
"Unit";"Baneling";"Zergling";327;0
"Unit";"Baneling";"Zergling";327;0
"Unit";"Baneling";"Zergling";327;0
"Unit";"Baneling";"Zergling";327;0
"Unit";"Baneling";"Zergling";327;0
"Unit";"Baneling";"Zergling";327;0
"Unit";"Baneling";"Zergling";327;0
"Unit";"Baneling";"Zergling";327;0
"Unit";"Baneling";"Zergling";327;0
"Unit";"Baneling";"Zergling";327;0
"Unit";"Baneling";"Zergling";327;0
"Unit";"Baneling";"Zergling";327;0
"Unit";"Baneling";"Zergling";327;0
"Building";"CreepTumor";NA;334;0
"Building";"CreepTumor";NA;334;0
"Unit";"Baneling";"Zergling";334;0
"Unit";"Baneling";"Zergling";334;0
"Unit";"Zergling";"Larva";337;1
"Unit";"Zergling";"Larva";337;1
"Unit";"Zergling";"Larva";337;1
"Unit";"Zergling";"Larva";337;1
"Unit";"Zergling";"Larva";337;1
"Unit";"Zergling";"Larva";337;1
"Unit";"Zergling";"Larva";337;1
"Unit";"Zergling";"Larva";337;1
"Unit";"Zergling";"Larva";337;1
"Unit";"Zergling";"Larva";337;1
"Unit";"Zergling";"Larva";337;1
"Unit";"Zergling";"Larva";337;1
"Unit";"Zergling";"Larva";337;1
"Unit";"Zergling";"Larva";337;1
"Unit";"Zergling";"Larva";337;1
"Unit";"Zergling";"Larva";337;1
"Unit";"Zergling";"Larva";337;1
"Unit";"Zergling";"Larva";337;1
"Unit";"Zergling";"Larva";337;1
"Unit";"Zergling";"Larva";337;1
"Unit";"Zergling";"Larva";337;1
"Unit";"Zergling";"Larva";337;1
"Unit";"Zergling";"Larva";337;1
"Unit";"Zergling";"Larva";337;1
"Unit";"Zergling";"Larva";361;1
"Unit";"Zergling";"Larva";361;1
"Unit";"Zergling";"Larva";361;1
"Unit";"Zergling";"Larva";361;1
"Unit";"Zergling";"Larva";361;1
"Unit";"Zergling";"Larva";361;1
"Unit";"Zergling";"Larva";361;1
"Unit";"Zergling";"Larva";361;1
"Unit";"Zergling";"Larva";361;1
"Unit";"Zergling";"Larva";361;1
"Unit";"Zergling";"Larva";361;1
"Unit";"Zergling";"Larva";361;1
"Unit";"Baneling";"Zergling";361;0
"Unit";"Baneling";"Zergling";361;0
"Unit";"Baneling";"Zergling";361;0
"Unit";"Baneling";"Zergling";361;0
"Unit";"Baneling";"Zergling";361;0
"Unit";"Baneling";"Zergling";361;0
"Unit";"Baneling";"Zergling";361;0
"Unit";"Baneling";"Zergling";361;0
"Unit";"Baneling";"Zergling";361;0
"Unit";"Baneling";"Zergling";361;0
"Unit";"Baneling";"Zergling";361;0
"Unit";"Baneling";"Zergling";361;0
"Unit";"Zergling";"Larva";373;1
"Unit";"Zergling";"Larva";373;1
"Unit";"Zergling";"Larva";373;1
"Unit";"Zergling";"Larva";373;1
"Unit";"Zergling";"Larva";373;1
"Unit";"Zergling";"Larva";373;1
"Unit";"Zergling";"Larva";373;1
"Unit";"Zergling";"Larva";373;1
"Unit";"Zergling";"Larva";373;1
"Unit";"Zergling";"Larva";373;1
"Unit";"Zergling";"Larva";373;1
"Unit";"Zergling";"Larva";373;1
"Unit";"Queen";"Hatchery";361;2
"Unit";"Queen";"Hatchery";361;2
"Unit";"Zergling";"Larva";373;1
"Unit";"Zergling";"Larva";373;1
"Unit";"Zergling";"Larva";373;1
"Unit";"Zergling";"Larva";373;1
"Unit";"Zergling";"Larva";373;1
"Unit";"Zergling";"Larva";373;1
"Unit";"Zergling";"Larva";373;1
"Unit";"Zergling";"Larva";373;1
"Unit";"Queen";"Hatchery";373;2
"Unit";"Baneling";"Zergling";387;0
"Unit";"Baneling";"Zergling";387;0
"Unit";"Baneling";"Zergling";387;0
"Unit";"Baneling";"Zergling";397;0
"Unit";"Zergling";"Larva";395;1
"Unit";"Zergling";"Larva";395;1
"Unit";"Zergling";"Larva";397;1
"Unit";"Zergling";"Larva";397;1
"Unit";"Zergling";"Larva";397;1
"Unit";"Zergling";"Larva";397;1
"Unit";"Zergling";"Larva";397;1
"Unit";"Zergling";"Larva";397;1
"Unit";"Zergling";"Larva";397;1
"Unit";"Zergling";"Larva";397;1
"Unit";"Zergling";"Larva";397;1
"Unit";"Zergling";"Larva";397;1
"Unit";"Zergling";"Larva";397;1
"Unit";"Zergling";"Larva";397;1
"Unit";"Zergling";"Larva";397;1
"Unit";"Zergling";"Larva";397;1
"Unit";"Zergling";"Larva";415;1
"Unit";"Zergling";"Larva";415;1
"Unit";"Zergling";"Larva";415;1
"Unit";"Zergling";"Larva";415;1
"Unit";"Zergling";"Larva";415;1
"Unit";"Zergling";"Larva";415;1
"Unit";"Zergling";"Larva";415;1
"Unit";"Zergling";"Larva";415;1
