"type";"unit_name";"on_building";"total_supply";"supply"
"Unit";"Overlord";"Larva";13;0
"Building";"Extractor";NA;17;0
"Building";"SpawningPool";NA;19;0
"Unit";"Overlord";"Larva";22;0
"Building";"Hatchery";NA;17;0
"Unit";"Zergling";"Larva";22;1
"Unit";"Zergling";"Larva";22;1
"Unit";"Zergling";"Larva";22;1
"Unit";"Zergling";"Larva";22;1
"Unit";"Zergling";"Larva";22;1
"Unit";"Zergling";"Larva";22;1
"Unit";"Queen";"Hatchery";22;2
"Unit";"Queen";"Hatchery";22;2
"Unit";"Queen";"Hatchery";36;2
"Building";"CreepTumorQueen";NA;40;0
"Unit";"Overlord";"Larva";40;0
"Unit";"Overlord";"Larva";40;0
"Unit";"Overlord";"Larva";43;0
"Unit";"Zergling";"Larva";43;1
"Unit";"Zergling";"Larva";43;1
"Unit";"Zergling";"Larva";43;1
"Unit";"Zergling";"Larva";43;1
"Unit";"Queen";"Hatchery";43;2
"Unit";"Overlord";"Larva";49;0
"Unit";"Overlord";"Larva";49;0
"Building";"CreepTumor";NA;54;0
"Building";"CreepTumorQueen";NA;55;0
"Building";"Hatchery";NA;37;0
"Unit";"Zergling";"Larva";54;1
"Unit";"Zergling";"Larva";54;1
"Unit";"Zergling";"Larva";54;1
"Unit";"Zergling";"Larva";54;1
"Unit";"Zergling";"Larva";54;1
"Unit";"Zergling";"Larva";54;1
"Building";"SporeCrawler";NA;65;0
"Building";"SporeCrawler";NA;67;0
"Building";"SporeCrawler";NA;67;0
"Building";"CreepTumor";NA;69;0
"Building";"CreepTumorQueen";NA;77;0
"Unit";"Overlord";"Larva";77;0
"Unit";"Zergling";"Larva";77;1
"Unit";"Zergling";"Larva";77;1
"Unit";"Zergling";"Larva";77;1
"Unit";"Zergling";"Larva";77;1
"Unit";"Zergling";"Larva";77;1
"Unit";"Zergling";"Larva";77;1
"Unit";"Zergling";"Larva";77;1
"Unit";"Zergling";"Larva";77;1
"Unit";"Zergling";"Larva";77;1
"Unit";"Zergling";"Larva";77;1
"Unit";"Queen";"Hatchery";77;2
"Unit";"Overlord";"Larva";77;0
"Unit";"Overlord";"Larva";97;0
"Building";"Extractor";NA;95;0
"Building";"EvolutionChamber";NA;97;0
"Building";"EvolutionChamber";NA;97;0
"Building";"CreepTumorQueen";NA;101;0
"Building";"Extractor";NA;101;0
"Building";"Extractor";NA;101;0
"Building";"BanelingNest";NA;95;0
"Unit";"Overlord";"Larva";101;0
"Unit";"Overlord";"Larva";101;0
"Building";"CreepTumor";NA;108;0
"Building";"CreepTumorQueen";NA;108;0
"Building";"HydraliskDen";NA;104;0
"Unit";"Zergling";"Larva";120;1
"Unit";"Zergling";"Larva";120;1
"Unit";"Zergling";"Larva";120;1
"Unit";"Zergling";"Larva";120;1
"Unit";"Zergling";"Larva";120;1
"Unit";"Zergling";"Larva";120;1
"Building";"Extractor";NA;118;0
"Building";"Extractor";NA;120;0
"Building";"CreepTumorQueen";NA;124;0
"Building";"CreepTumor";NA;124;0
"Unit";"Zergling";"Larva";124;1
"Unit";"Zergling";"Larva";124;1
"Unit";"Zergling";"Larva";124;1
"Unit";"Zergling";"Larva";124;1
"Unit";"Zergling";"Larva";124;1
"Unit";"Zergling";"Larva";124;1
"Unit";"Zergling";"Larva";124;1
"Unit";"Zergling";"Larva";124;1
"Building";"Hatchery";NA;104;0
"Unit";"Zergling";"Larva";130;1
"Unit";"Zergling";"Larva";130;1
"Unit";"Zergling";"Larva";130;1
"Unit";"Zergling";"Larva";130;1
"Unit";"Zergling";"Larva";130;1
"Unit";"Zergling";"Larva";130;1
"Unit";"Zergling";"Larva";130;1
"Unit";"Zergling";"Larva";130;1
"Building";"CreepTumorQueen";NA;138;0
"Unit";"Hydralisk";"Larva";130;2
"Unit";"Hydralisk";"Larva";130;2
"Unit";"Hydralisk";"Larva";130;2
"Unit";"Hydralisk";"Larva";138;2
"Unit";"Hydralisk";"Larva";138;2
"Building";"CreepTumor";NA;146;0
"Building";"Extractor";NA;146;0
"Building";"Extractor";NA;146;0
"Unit";"Hydralisk";"Larva";149;2
"Unit";"Hydralisk";"Larva";149;2
"Unit";"Hydralisk";"Larva";149;2
"Unit";"Overlord";"Larva";163;0
"Unit";"Overlord";"Larva";163;0
"Unit";"Overlord";"Larva";163;0
"Unit";"Overlord";"Larva";163;0
"Unit";"Overlord";"Larva";163;0
"Unit";"Overlord";"Larva";163;0
"Unit";"Overlord";"Larva";163;0
"Upgrade";"EvolveMuscularAugments";"HydraliskDen";130;0
"Building";"CreepTumor";NA;163;0
"Building";"CreepTumorQueen";NA;163;0
"Building";"CreepTumor";NA;169;0
"Upgrade";"ZergMeleeWeaponsLevel1";"EvolutionChamber";130;0
"Unit";"Queen";"Hatchery";163;2
"Building";"InfestationPit";NA;163;0
"Unit";"Hydralisk";"Larva";169;2
"Unit";"Hydralisk";"Larva";169;2
"Unit";"Hydralisk";"Larva";169;2
"Unit";"Hydralisk";"Larva";169;2
"Unit";"Hydralisk";"Larva";169;2
"Building";"CreepTumor";NA;170;0
"Building";"CreepTumor";NA;186;0
"Unit";"Hydralisk";"Larva";170;2
"Unit";"Hydralisk";"Larva";170;2
"Upgrade";"ZergGroundArmorsLevel1";"EvolutionChamber";146;0
"Building";"Hatchery";NA;163;0
"Unit";"Baneling";"Zergling";201;0
"Unit";"Baneling";"Zergling";201;0
"Unit";"Baneling";"Zergling";201;0
"Unit";"Baneling";"Zergling";201;0
"Building";"CreepTumorQueen";NA;201;0
"Building";"CreepTumorQueen";NA;201;0
"Upgrade";"EvolveGroovedSpines";"HydraliskDen";170;0
"Building";"CreepTumor";NA;201;0
"Building";"CreepTumor";NA;201;0
"Unit";"Zergling";"Larva";201;1
"Unit";"Zergling";"Larva";201;1
"Unit";"Zergling";"Larva";201;1
"Unit";"Zergling";"Larva";201;1
"Unit";"Zergling";"Larva";201;1
"Unit";"Zergling";"Larva";201;1
"Unit";"Zergling";"Larva";201;1
"Unit";"Zergling";"Larva";201;1
"Unit";"Zergling";"Larva";201;1
"Unit";"Zergling";"Larva";201;1
"Unit";"Zergling";"Larva";201;1
"Unit";"Zergling";"Larva";201;1
"Unit";"Zergling";"Larva";201;1
"Unit";"Zergling";"Larva";201;1
"Unit";"Zergling";"Larva";201;1
"Unit";"Zergling";"Larva";201;1
"Unit";"Zergling";"Larva";201;1
"Unit";"Zergling";"Larva";201;1
"Unit";"Zergling";"Larva";201;1
"Unit";"Zergling";"Larva";201;1
"Building";"SporeCrawler";NA;202;0
"Unit";"Queen";"Hatchery";201;2
"Building";"SporeCrawler";NA;202;0
"Building";"SporeCrawler";NA;202;0
"Building";"CreepTumorQueen";NA;222;0
"Unit";"Zergling";"Larva";222;1
"Unit";"Zergling";"Larva";222;1
"Unit";"Zergling";"Larva";222;1
"Unit";"Zergling";"Larva";222;1
"Unit";"Zergling";"Larva";222;1
"Unit";"Zergling";"Larva";222;1
"Building";"CreepTumor";NA;224;0
"Building";"CreepTumor";NA;224;0
"Building";"CreepTumorQueen";NA;230;0
"Building";"CreepTumor";NA;230;0
"Unit";"Hydralisk";"Larva";230;2
"Unit";"Hydralisk";"Larva";230;2
"Unit";"Hydralisk";"Larva";230;2
"Unit";"Hydralisk";"Larva";230;2
"Unit";"Viper";"Larva";230;3
"Unit";"Viper";"Larva";230;3
"Unit";"Viper";"Larva";230;3
"Unit";"Viper";"Larva";230;3
"Unit";"Viper";"Larva";230;3
"Building";"Hatchery";NA;201;0
"Unit";"Zergling";"Larva";230;1
"Unit";"Zergling";"Larva";230;1
"Unit";"Zergling";"Larva";230;1
"Unit";"Zergling";"Larva";230;1
"Unit";"Baneling";"Zergling";238;0
"Unit";"Baneling";"Zergling";238;0
"Unit";"Baneling";"Zergling";238;0
"Unit";"Baneling";"Zergling";238;0
"Unit";"Baneling";"Zergling";238;0
"Unit";"Baneling";"Zergling";238;0
"Unit";"Baneling";"Zergling";238;0
"Unit";"Baneling";"Zergling";238;0
"Unit";"Baneling";"Zergling";238;0
"Unit";"Baneling";"Zergling";238;0
"Building";"UltraliskCavern";NA;224;0
"Unit";"Overlord";"Larva";253;0
"Unit";"Overlord";"Larva";253;0
"Unit";"Overlord";"Larva";253;0
"Unit";"Overlord";"Larva";253;0
"Unit";"Overlord";"Larva";253;0
"Unit";"Zergling";"Larva";257;1
"Unit";"Zergling";"Larva";257;1
"Unit";"Zergling";"Larva";257;1
"Unit";"Zergling";"Larva";257;1
"Unit";"Zergling";"Larva";257;1
"Unit";"Zergling";"Larva";257;1
"Unit";"Zergling";"Larva";257;1
"Unit";"Zergling";"Larva";257;1
"Unit";"Baneling";"Zergling";257;0
"Unit";"Baneling";"Zergling";257;0
"Unit";"Baneling";"Zergling";257;0
"Unit";"Baneling";"Zergling";257;0
"Unit";"Baneling";"Zergling";257;0
"Unit";"Baneling";"Zergling";257;0
"Unit";"Baneling";"Zergling";257;0
"Unit";"Baneling";"Zergling";257;0
"Building";"EvolutionChamber";NA;257;0
"Building";"EvolutionChamber";NA;257;0
"Building";"EvolutionChamber";NA;257;0
"Unit";"Zergling";"Larva";257;1
"Unit";"Zergling";"Larva";257;1
"Unit";"Zergling";"Larva";257;1
"Unit";"Zergling";"Larva";257;1
"Unit";"Zergling";"Larva";257;1
"Unit";"Zergling";"Larva";257;1
"Unit";"Zergling";"Larva";257;1
"Unit";"Zergling";"Larva";257;1
"Unit";"Zergling";"Larva";257;1
"Unit";"Zergling";"Larva";257;1
"Unit";"Zergling";"Larva";257;1
"Unit";"Zergling";"Larva";257;1
"Unit";"Zergling";"Larva";257;1
"Unit";"Zergling";"Larva";257;1
"Unit";"Zergling";"Larva";257;1
"Unit";"Zergling";"Larva";257;1
"Unit";"Zergling";"Larva";257;1
"Unit";"Zergling";"Larva";257;1
"Unit";"Zergling";"Larva";257;1
"Unit";"Zergling";"Larva";257;1
"Unit";"Zergling";"Larva";257;1
"Unit";"Zergling";"Larva";257;1
"Unit";"Zergling";"Larva";257;1
"Unit";"Zergling";"Larva";257;1
"Unit";"Zergling";"Larva";257;1
"Unit";"Zergling";"Larva";257;1
"Unit";"Zergling";"Larva";257;1
"Unit";"Zergling";"Larva";257;1
"Unit";"Zergling";"Larva";257;1
"Unit";"Zergling";"Larva";257;1
"Unit";"Zergling";"Larva";257;1
"Unit";"Zergling";"Larva";257;1
"Unit";"Zergling";"Larva";257;1
"Unit";"Zergling";"Larva";257;1
"Unit";"Zergling";"Larva";257;1
"Unit";"Zergling";"Larva";257;1
"Unit";"Zergling";"Larva";257;1
"Unit";"Zergling";"Larva";257;1
"Unit";"Zergling";"Larva";257;1
"Unit";"Zergling";"Larva";257;1
"Unit";"Zergling";"Larva";257;1
"Unit";"Zergling";"Larva";257;1
"Building";"Spire";NA;230;0
"Upgrade";"ZergMeleeWeaponsLevel2";"EvolutionChamber";222;0
"Upgrade";"ZergGroundArmorsLevel2";"EvolutionChamber";222;0
"Unit";"Ultralisk";"Larva";257;6
"Building";"CreepTumor";NA;307;0
"Building";"CreepTumor";NA;307;0
"Building";"CreepTumor";NA;307;0
"Unit";"Baneling";"Zergling";307;0
"Unit";"Baneling";"Zergling";307;0
"Unit";"Baneling";"Zergling";307;0
"Unit";"Baneling";"Zergling";307;0
"Building";"CreepTumorQueen";NA;313;0
"Building";"CreepTumorQueen";NA;313;0
"Building";"CreepTumorQueen";NA;313;0
"Unit";"Ultralisk";"Larva";307;6
"Unit";"Ultralisk";"Larva";307;6
"Unit";"Queen";"Hatchery";307;2
"Upgrade";"ChitinousPlating";"UltraliskCavern";307;0
"Building";"CreepTumorQueen";NA;330;0
"Unit";"Ultralisk";"Larva";313;6
"Unit";"Ultralisk";"Larva";313;6
"Building";"CreepTumorQueen";NA;330;0
"Unit";"Baneling";"Zergling";330;0
"Unit";"Baneling";"Zergling";330;0
"Unit";"Baneling";"Zergling";330;0
"Unit";"Baneling";"Zergling";330;0
"Unit";"Baneling";"Zergling";330;0
"Unit";"Baneling";"Zergling";330;0
"Unit";"Baneling";"Zergling";336;0
"Unit";"Zergling";"Larva";342;1
"Unit";"Zergling";"Larva";342;1
"Unit";"Zergling";"Larva";342;1
"Unit";"Zergling";"Larva";342;1
"Unit";"Zergling";"Larva";342;1
"Unit";"Zergling";"Larva";342;1
"Unit";"Zergling";"Larva";342;1
"Unit";"Zergling";"Larva";342;1
"Building";"CreepTumorQueen";NA;342;0
"Building";"CreepTumorQueen";NA;342;0
"Building";"CreepTumor";NA;342;0
"Building";"Hatchery";NA;313;0
"Building";"CreepTumor";NA;342;0
"Unit";"Ultralisk";"Larva";330;6
"Unit";"Ultralisk";"Larva";330;6
"Building";"SporeCrawler";NA;350;0
"Building";"SporeCrawler";NA;350;0
