"type";"unit_name";"on_building";"total_supply";"supply"
"Unit";"Overlord";"Larva";12;0
"Building";"SpawningPool";NA;19;0
"Building";"Hatchery";NA;17;0
"Building";"Extractor";NA;22;0
"Unit";"Zergling";"Larva";24;1
"Unit";"Zergling";"Larva";24;1
"Unit";"Zergling";"Larva";25;1
"Unit";"Zergling";"Larva";25;1
"Unit";"Overlord";"Larva";25;0
"Unit";"Queen";"Hatchery";24;2
"Unit";"Queen";"Hatchery";25;2
"Building";"Hatchery";NA;21;0
"Unit";"Overlord";"Larva";32;0
"Unit";"Zergling";"Larva";40;1
"Unit";"Zergling";"Larva";40;1
"Unit";"Zergling";"Larva";40;1
"Unit";"Zergling";"Larva";40;1
"Unit";"Zergling";"Larva";40;1
"Unit";"Zergling";"Larva";40;1
"Unit";"Zergling";"Larva";40;1
"Unit";"Zergling";"Larva";40;1
"Unit";"Overlord";"Larva";40;0
"Unit";"Zergling";"Larva";40;1
"Unit";"Zergling";"Larva";40;1
"Unit";"Zergling";"Larva";40;1
"Unit";"Zergling";"Larva";40;1
"Unit";"Queen";"Hatchery";37;2
"Unit";"Overlord";"Larva";40;0
"Unit";"Overlord";"Larva";40;0
"Unit";"Zergling";"Larva";54;1
"Unit";"Zergling";"Larva";54;1
"Unit";"Overlord";"Larva";54;0
"Unit";"Zergling";"Larva";54;1
"Unit";"Zergling";"Larva";54;1
"Unit";"Zergling";"Larva";54;1
"Unit";"Zergling";"Larva";54;1
"Unit";"Zergling";"Larva";54;1
"Unit";"Zergling";"Larva";54;1
"Unit";"Overlord";"Larva";54;0
"Unit";"Zergling";"Larva";54;1
"Unit";"Zergling";"Larva";54;1
"Unit";"Zergling";"Larva";54;1
"Unit";"Zergling";"Larva";54;1
"Unit";"Zergling";"Larva";54;1
"Unit";"Zergling";"Larva";54;1
"Unit";"Zergling";"Larva";63;1
"Unit";"Zergling";"Larva";63;1
"Unit";"Zergling";"Larva";63;1
"Unit";"Zergling";"Larva";63;1
"Unit";"Zergling";"Larva";63;1
"Unit";"Zergling";"Larva";63;1
"Building";"BanelingNest";NA;54;0
"Unit";"Baneling";"Zergling";81;0
"Unit";"Baneling";"Zergling";81;0
"Unit";"Baneling";"Zergling";81;0
"Unit";"Baneling";"Zergling";81;0
"Unit";"Baneling";"Zergling";81;0
"Unit";"Baneling";"Zergling";81;0
"Unit";"Overlord";"Larva";84;0
"Unit";"Baneling";"Zergling";88;0
"Unit";"Baneling";"Zergling";89;0
"Unit";"Zergling";"Larva";88;1
"Unit";"Zergling";"Larva";88;1
"Unit";"Baneling";"Zergling";89;0
"Unit";"Zergling";"Larva";88;1
"Unit";"Zergling";"Larva";88;1
"Unit";"Zergling";"Larva";88;1
"Unit";"Zergling";"Larva";88;1
"Unit";"Zergling";"Larva";88;1
"Unit";"Zergling";"Larva";88;1
"Unit";"Zergling";"Larva";99;1
"Unit";"Zergling";"Larva";99;1
"Unit";"Zergling";"Larva";99;1
"Unit";"Zergling";"Larva";99;1
"Unit";"Zergling";"Larva";99;1
"Unit";"Zergling";"Larva";99;1
"Unit";"Zergling";"Larva";99;1
"Unit";"Zergling";"Larva";99;1
"Unit";"Zergling";"Larva";99;1
"Unit";"Zergling";"Larva";99;1
"Unit";"Zergling";"Larva";99;1
"Unit";"Zergling";"Larva";99;1
"Unit";"Zergling";"Larva";99;1
"Unit";"Zergling";"Larva";99;1
"Unit";"Zergling";"Larva";99;1
"Unit";"Zergling";"Larva";99;1
"Unit";"Zergling";"Larva";99;1
"Unit";"Zergling";"Larva";99;1
"Unit";"Zergling";"Larva";99;1
"Unit";"Zergling";"Larva";99;1
"Unit";"Zergling";"Larva";99;1
"Unit";"Zergling";"Larva";99;1
"Unit";"Zergling";"Larva";99;1
"Unit";"Zergling";"Larva";99;1
"Unit";"Zergling";"Larva";99;1
"Unit";"Zergling";"Larva";99;1
"Unit";"Zergling";"Larva";99;1
"Unit";"Zergling";"Larva";99;1
"Unit";"Baneling";"Zergling";99;0
"Unit";"Baneling";"Zergling";99;0
"Unit";"Baneling";"Zergling";99;0
"Unit";"Baneling";"Zergling";99;0
"Unit";"Overlord";"Larva";99;0
"Unit";"Overlord";"Larva";99;0
"Unit";"Baneling";"Zergling";128;0
"Unit";"Overlord";"Larva";128;0
"Unit";"Overlord";"Larva";128;0
"Unit";"Overlord";"Larva";128;0
"Unit";"Zergling";"Larva";129;1
"Unit";"Zergling";"Larva";129;1
"Unit";"Zergling";"Larva";129;1
"Unit";"Zergling";"Larva";129;1
"Unit";"Zergling";"Larva";129;1
"Unit";"Zergling";"Larva";129;1
"Unit";"Zergling";"Larva";129;1
"Unit";"Zergling";"Larva";129;1
"Unit";"Zergling";"Larva";129;1
"Unit";"Zergling";"Larva";129;1
"Unit";"Zergling";"Larva";129;1
"Unit";"Zergling";"Larva";129;1
"Unit";"Zergling";"Larva";129;1
"Unit";"Zergling";"Larva";129;1
"Unit";"Zergling";"Larva";129;1
"Unit";"Zergling";"Larva";129;1
"Unit";"Zergling";"Larva";129;1
"Unit";"Zergling";"Larva";129;1
"Unit";"Zergling";"Larva";129;1
"Unit";"Zergling";"Larva";129;1
"Unit";"Zergling";"Larva";129;1
"Unit";"Zergling";"Larva";129;1
"Building";"Extractor";NA;129;0
"Building";"Extractor";NA;129;0
"Unit";"Queen";"Hatchery";129;2
"Unit";"Queen";"Hatchery";129;2
"Building";"Hatchery";NA;128;0
"Building";"Extractor";NA;158;0
"Building";"EvolutionChamber";NA;158;0
"Building";"EvolutionChamber";NA;158;0
"Building";"SporeCrawler";NA;158;0
"Building";"CreepTumorQueen";NA;170;0
"Building";"CreepTumorQueen";NA;170;0
"Building";"CreepTumorQueen";NA;170;0
"Building";"CreepTumorQueen";NA;170;0
"Unit";"Zergling";"Larva";170;1
"Unit";"Zergling";"Larva";170;1
"Unit";"Zergling";"Larva";170;1
"Unit";"Zergling";"Larva";170;1
"Unit";"Zergling";"Larva";170;1
"Unit";"Zergling";"Larva";170;1
"Unit";"Overlord";"Larva";170;0
"Unit";"Zergling";"Larva";170;1
"Unit";"Zergling";"Larva";170;1
"Unit";"Zergling";"Larva";170;1
"Unit";"Zergling";"Larva";170;1
"Unit";"Zergling";"Larva";170;1
"Unit";"Zergling";"Larva";170;1
"Unit";"Zergling";"Larva";170;1
"Unit";"Zergling";"Larva";170;1
"Unit";"Zergling";"Larva";170;1
"Unit";"Zergling";"Larva";170;1
"Unit";"Zergling";"Larva";170;1
"Unit";"Zergling";"Larva";170;1
"Unit";"Zergling";"Larva";170;1
"Unit";"Zergling";"Larva";170;1
"Unit";"Queen";"Hatchery";169;2
"Unit";"Queen";"Hatchery";169;2
"Unit";"Queen";"Hatchery";170;2
"Unit";"Zergling";"Larva";170;1
"Unit";"Zergling";"Larva";170;1
"Unit";"Zergling";"Larva";170;1
"Unit";"Zergling";"Larva";170;1
"Unit";"Zergling";"Larva";170;1
"Unit";"Zergling";"Larva";170;1
"Unit";"Zergling";"Larva";170;1
"Unit";"Zergling";"Larva";170;1
"Unit";"Zergling";"Larva";170;1
"Unit";"Zergling";"Larva";170;1
"Unit";"Zergling";"Larva";170;1
"Unit";"Zergling";"Larva";170;1
"Unit";"Zergling";"Larva";190;1
"Unit";"Zergling";"Larva";190;1
"Unit";"Zergling";"Larva";190;1
"Unit";"Zergling";"Larva";190;1
"Unit";"Zergling";"Larva";190;1
"Unit";"Zergling";"Larva";190;1
"Unit";"Zergling";"Larva";190;1
"Unit";"Zergling";"Larva";190;1
"Unit";"Baneling";"Zergling";190;0
"Unit";"Zergling";"Larva";190;1
"Unit";"Zergling";"Larva";190;1
"Unit";"Zergling";"Larva";190;1
"Unit";"Zergling";"Larva";190;1
"Unit";"Baneling";"Zergling";190;0
"Unit";"Baneling";"Zergling";190;0
"Unit";"Baneling";"Zergling";190;0
"Unit";"Baneling";"Zergling";190;0
"Unit";"Baneling";"Zergling";190;0
"Building";"CreepTumor";NA;220;0
"Unit";"Zergling";"Larva";220;1
"Unit";"Zergling";"Larva";220;1
"Unit";"Zergling";"Larva";220;1
"Unit";"Zergling";"Larva";220;1
"Unit";"Zergling";"Larva";220;1
"Unit";"Zergling";"Larva";220;1
"Unit";"Zergling";"Larva";220;1
"Unit";"Zergling";"Larva";220;1
"Unit";"Zergling";"Larva";220;1
"Unit";"Zergling";"Larva";220;1
"Unit";"Zergling";"Larva";220;1
"Unit";"Zergling";"Larva";220;1
"Unit";"Zergling";"Larva";220;1
"Unit";"Zergling";"Larva";220;1
"Unit";"Zergling";"Larva";220;1
"Unit";"Zergling";"Larva";220;1
"Unit";"Zergling";"Larva";220;1
"Unit";"Zergling";"Larva";220;1
"Unit";"Zergling";"Larva";220;1
"Unit";"Zergling";"Larva";220;1
"Building";"CreepTumorQueen";NA;220;0
"Unit";"Zergling";"Larva";220;1
"Unit";"Zergling";"Larva";220;1
"Unit";"Zergling";"Larva";220;1
"Unit";"Zergling";"Larva";220;1
"Unit";"Zergling";"Larva";220;1
"Unit";"Zergling";"Larva";220;1
"Unit";"Zergling";"Larva";220;1
"Unit";"Zergling";"Larva";220;1
"Unit";"Zergling";"Larva";220;1
"Unit";"Zergling";"Larva";220;1
"Unit";"Zergling";"Larva";220;1
"Unit";"Zergling";"Larva";220;1
"Unit";"Zergling";"Larva";220;1
"Unit";"Zergling";"Larva";220;1
"Unit";"Zergling";"Larva";220;1
"Unit";"Zergling";"Larva";220;1
"Unit";"Zergling";"Larva";220;1
"Unit";"Zergling";"Larva";220;1
"Unit";"Baneling";"Zergling";240;0
"Building";"CreepTumor";NA;240;0
"Unit";"Baneling";"Zergling";240;0
"Unit";"Baneling";"Zergling";240;0
"Unit";"Baneling";"Zergling";240;0
"Unit";"Baneling";"Zergling";240;0
"Unit";"Baneling";"Zergling";240;0
"Unit";"Baneling";"Zergling";240;0
"Unit";"Baneling";"Zergling";240;0
"Unit";"Baneling";"Zergling";240;0
"Unit";"Queen";"Hatchery";220;2
"Unit";"Queen";"Hatchery";220;2
"Unit";"Queen";"Hatchery";220;2
"Building";"CreepTumor";NA;250;0
"Unit";"Zergling";"Larva";250;1
"Unit";"Zergling";"Larva";250;1
"Unit";"Zergling";"Larva";250;1
"Unit";"Zergling";"Larva";250;1
"Unit";"Zergling";"Larva";250;1
"Unit";"Zergling";"Larva";250;1
"Unit";"Zergling";"Larva";250;1
"Unit";"Zergling";"Larva";250;1
"Unit";"Zergling";"Larva";258;1
"Unit";"Zergling";"Larva";258;1
"Unit";"Zergling";"Larva";258;1
"Unit";"Zergling";"Larva";258;1
"Unit";"Zergling";"Larva";258;1
"Unit";"Zergling";"Larva";258;1
"Unit";"Queen";"Hatchery";258;2
"Unit";"Queen";"Hatchery";258;2
"Upgrade";"ZergGroundArmorsLevel1";"EvolutionChamber";220;0
"Upgrade";"ZergMeleeWeaponsLevel1";"EvolutionChamber";220;0
"Unit";"Zergling";"Larva";278;1
"Unit";"Zergling";"Larva";278;1
"Unit";"Zergling";"Larva";278;1
"Unit";"Zergling";"Larva";278;1
"Unit";"Zergling";"Larva";278;1
"Unit";"Zergling";"Larva";278;1
"Unit";"Zergling";"Larva";278;1
"Unit";"Zergling";"Larva";278;1
"Unit";"Zergling";"Larva";278;1
"Unit";"Zergling";"Larva";278;1
"Unit";"Zergling";"Larva";278;1
"Unit";"Zergling";"Larva";278;1
"Unit";"Zergling";"Larva";278;1
"Unit";"Zergling";"Larva";278;1
"Unit";"Zergling";"Larva";278;1
"Unit";"Zergling";"Larva";278;1
"Unit";"Zergling";"Larva";278;1
"Unit";"Zergling";"Larva";278;1
"Unit";"Zergling";"Larva";278;1
"Unit";"Zergling";"Larva";278;1
"Unit";"Zergling";"Larva";278;1
"Unit";"Zergling";"Larva";278;1
"Unit";"Zergling";"Larva";278;1
"Unit";"Zergling";"Larva";278;1
"Unit";"Zergling";"Larva";280;1
"Unit";"Zergling";"Larva";280;1
"Unit";"Zergling";"Larva";280;1
"Unit";"Zergling";"Larva";280;1
"Unit";"Zergling";"Larva";280;1
"Unit";"Zergling";"Larva";280;1
"Unit";"Zergling";"Larva";280;1
"Unit";"Zergling";"Larva";280;1
