"type";"unit_name";"on_building";"total_supply_lag";"supply"
"Unit";"Overlord";"Larva";13;0
"Building";"Hatchery";NA;17;0
"Building";"SpawningPool";NA;18;0
"Building";"Extractor";NA;18;0
"Unit";"Overlord";"Larva";22;0
"Unit";"Queen";"Hatchery";22;2
"Unit";"Zergling";"Larva";24;1
"Unit";"Zergling";"Larva";25;1
"Unit";"Zergling";"Larva";26;1
"Unit";"Zergling";"Larva";27;1
"Unit";"Queen";"Hatchery";28;2
"Unit";"Zergling";"Larva";30;1
"Unit";"Zergling";"Larva";31;1
"Unit";"Queen";"Hatchery";37;2
"Unit";"Overlord";"Larva";40;0
"Unit";"Queen";"Hatchery";40;2
"Building";"CreepTumorQueen";NA;42;0
"Unit";"Overlord";"Larva";50;0
"Building";"Hatchery";NA;50;0
"Building";"CreepTumor";NA;50;0
"Unit";"Queen";"Hatchery";50;2
"Unit";"Overlord";"Larva";58;0
"Building";"EvolutionChamber";NA;58;0
"Building";"RoachWarren";NA;58;0
"Building";"Extractor";NA;59;0
"Building";"Extractor";NA;59;0
"Building";"CreepTumor";NA;60;0
"Unit";"Overlord";"Larva";63;0
"Unit";"Overlord";"Larva";63;0
"Building";"Extractor";NA;63;0
"Unit";"Queen";"Hatchery";64;2
"Unit";"Roach";"Larva";71;2
"Unit";"Roach";"Larva";73;2
"Unit";"Roach";"Larva";75;2
"Unit";"Roach";"Larva";79;2
"Unit";"Roach";"Larva";81;2
"Unit";"Overlord";"Larva";83;0
"Building";"CreepTumorQueen";NA;83;0
"Building";"CreepTumorQueen";NA;83;0
"Upgrade";"GlialReconstitution";"RoachWarren";83;0
"Unit";"Roach";"Larva";83;2
"Unit";"Overlord";"Larva";85;0
"Unit";"Overlord";"Larva";85;0
"Unit";"Overlord";"Larva";85;0
"Unit";"Overlord";"Larva";85;0
"Building";"CreepTumor";NA;85;0
"Building";"CreepTumor";NA;94;0
"Building";"CreepTumor";NA;94;0
"Building";"CreepTumorQueen";NA;94;0
"Building";"CreepTumorQueen";NA;94;0
"Building";"InfestationPit";NA;95;0
"Building";"CreepTumorQueen";NA;99;0
"Unit";"Overlord";"Larva";99;0
"Unit";"Roach";"Larva";99;2
"Unit";"Roach";"Larva";101;2
"Unit";"Roach";"Larva";103;2
"Unit";"Roach";"Larva";105;2
"Unit";"Roach";"Larva";107;2
"Building";"Extractor";NA;112;0
"Unit";"Queen";"Hatchery";112;2
"Building";"SporeCrawler";NA;114;0
"Building";"SporeCrawler";NA;114;0
"Building";"CreepTumor";NA;128;0
"Building";"CreepTumor";NA;128;0
"Building";"CreepTumor";NA;128;0
"Building";"CreepTumor";NA;128;0
"Upgrade";"Burrow";"Hatchery";128;0
"Building";"Extractor";NA;136;0
"Building";"Hatchery";NA;136;0
"Building";"EvolutionChamber";NA;136;0
"Unit";"Zergling";"Larva";136;1
"Unit";"Zergling";"Larva";137;1
"Unit";"Zergling";"Larva";138;1
"Unit";"Zergling";"Larva";139;1
"Unit";"Zergling";"Larva";140;1
"Unit";"Zergling";"Larva";141;1
"Unit";"Zergling";"Larva";142;1
"Unit";"Zergling";"Larva";143;1
"Unit";"Zergling";"Larva";144;1
"Unit";"Zergling";"Larva";145;1
"Unit";"Zergling";"Larva";146;1
"Unit";"Zergling";"Larva";147;1
"Unit";"Zergling";"Larva";148;1
"Unit";"Zergling";"Larva";149;1
"Unit";"Infestor";"Larva";150;2
"Unit";"Infestor";"Larva";152;2
"Unit";"Zergling";"Larva";154;1
"Unit";"Zergling";"Larva";155;1
"Unit";"Zergling";"Larva";156;1
"Unit";"Zergling";"Larva";157;1
"Unit";"Zergling";"Larva";158;1
"Unit";"Zergling";"Larva";159;1
"Building";"CreepTumor";NA;160;0
"Building";"CreepTumor";NA;160;0
"Building";"CreepTumor";NA;160;0
"Building";"CreepTumor";NA;160;0
"Building";"CreepTumor";NA;160;0
"Unit";"Overlord";"Larva";160;0
"Unit";"Overlord";"Larva";160;0
"Unit";"Overlord";"Larva";160;0
"Unit";"Overlord";"Larva";160;0
"Unit";"Overlord";"Larva";160;0
"Unit";"Overlord";"Larva";160;0
"Unit";"Overlord";"Larva";160;0
"Unit";"Overlord";"Larva";160;0
"Building";"CreepTumor";NA;160;0
"Unit";"Overlord";"Larva";160;0
"Building";"Hatchery";NA;160;0
"Building";"BanelingNest";NA;160;0
"Unit";"Zergling";"Larva";160;1
"Unit";"Zergling";"Larva";161;1
"Unit";"Zergling";"Larva";162;1
"Unit";"Zergling";"Larva";163;1
"Building";"CreepTumor";NA;164;0
"Unit";"Zergling";"Larva";164;1
"Unit";"Zergling";"Larva";165;1
"Building";"CreepTumor";NA;166;0
"Building";"CreepTumor";NA;166;0
"Unit";"Zergling";"Larva";166;1
"Unit";"Zergling";"Larva";167;1
"Unit";"Zergling";"Larva";168;1
"Unit";"Zergling";"Larva";169;1
"Unit";"Zergling";"Larva";170;1
"Unit";"Zergling";"Larva";171;1
"Unit";"Zergling";"Larva";172;1
"Unit";"Zergling";"Larva";173;1
"Unit";"Zergling";"Larva";174;1
"Unit";"Zergling";"Larva";175;1
"Unit";"Zergling";"Larva";176;1
"Unit";"Zergling";"Larva";177;1
"Unit";"Zergling";"Larva";178;1
"Unit";"Zergling";"Larva";179;1
"Unit";"Zergling";"Larva";180;1
"Unit";"Zergling";"Larva";181;1
"Unit";"Zergling";"Larva";182;1
"Unit";"Zergling";"Larva";183;1
"Unit";"Zergling";"Larva";184;1
"Unit";"Zergling";"Larva";185;1
"Unit";"Zergling";"Larva";186;1
"Unit";"Zergling";"Larva";187;1
"Unit";"Zergling";"Larva";189;1
"Unit";"Zergling";"Larva";190;1
"Unit";"Zergling";"Larva";191;1
"Unit";"Zergling";"Larva";192;1
"Unit";"Zergling";"Larva";193;1
"Unit";"Zergling";"Larva";194;1
"Unit";"Zergling";"Larva";195;1
"Unit";"Zergling";"Larva";196;1
"Unit";"Zergling";"Larva";197;1
"Unit";"Zergling";"Larva";198;1
"Unit";"Zergling";"Larva";199;1
"Unit";"Zergling";"Larva";200;1
"Building";"CreepTumor";NA;201;0
"Unit";"Zergling";"Larva";201;1
"Unit";"Zergling";"Larva";202;1
"Unit";"Zergling";"Larva";203;1
"Unit";"Zergling";"Larva";204;1
"Unit";"Zergling";"Larva";205;1
"Unit";"Zergling";"Larva";206;1
"Unit";"Zergling";"Larva";207;1
"Unit";"Zergling";"Larva";208;1
"Unit";"Zergling";"Larva";209;1
"Unit";"Zergling";"Larva";210;1
"Unit";"Zergling";"Larva";211;1
"Unit";"Zergling";"Larva";212;1
"Unit";"Queen";"Hatchery";213;2
"Unit";"Zergling";"Larva";215;1
"Unit";"Zergling";"Larva";216;1
"Building";"SporeCrawler";NA;217;0
"Unit";"Zergling";"Larva";217;1
"Unit";"Zergling";"Larva";218;1
"Unit";"Zergling";"Larva";219;1
"Unit";"Zergling";"Larva";220;1
"Unit";"Baneling";"Zergling";221;0
"Unit";"Baneling";"Zergling";221;0
"Unit";"Baneling";"Zergling";221;0
"Unit";"Baneling";"Zergling";221;0
"Unit";"Baneling";"Zergling";221;0
"Unit";"Baneling";"Zergling";221;0
"Unit";"Baneling";"Zergling";221;0
"Unit";"Baneling";"Zergling";221;0
"Unit";"Baneling";"Zergling";221;0
"Unit";"Baneling";"Zergling";221;0
"Unit";"Baneling";"Zergling";221;0
"Unit";"Baneling";"Zergling";221;0
"Unit";"Baneling";"Zergling";221;0
"Unit";"Baneling";"Zergling";221;0
"Unit";"Zergling";"Larva";221;1
"Unit";"Zergling";"Larva";222;1
"Unit";"Zergling";"Larva";223;1
"Unit";"Zergling";"Larva";224;1
"Unit";"Zergling";"Larva";225;1
"Unit";"Zergling";"Larva";226;1
"Building";"CreepTumor";NA;227;0
"Unit";"Zergling";"Larva";227;1
"Unit";"Zergling";"Larva";228;1
"Unit";"Zergling";"Larva";229;1
"Unit";"Zergling";"Larva";230;1
"Unit";"Zergling";"Larva";231;1
"Unit";"Zergling";"Larva";232;1
"Unit";"Zergling";"Larva";233;1
"Unit";"Zergling";"Larva";234;1
"Building";"CreepTumor";NA;235;0
"Building";"CreepTumor";NA;235;0
"Unit";"Zergling";"Larva";235;1
"Unit";"Zergling";"Larva";236;1
"Unit";"Zergling";"Larva";237;1
"Unit";"Zergling";"Larva";238;1
"Building";"CreepTumor";NA;239;0
"Unit";"Zergling";"Larva";239;1
"Unit";"Zergling";"Larva";240;1
"Unit";"Zergling";"Larva";241;1
"Unit";"Zergling";"Larva";242;1
"Unit";"Zergling";"Larva";243;1
"Unit";"Zergling";"Larva";244;1
"Unit";"Zergling";"Larva";245;1
"Unit";"Zergling";"Larva";246;1
"Building";"CreepTumor";NA;247;0
"Unit";"Zergling";"Larva";247;1
"Unit";"Zergling";"Larva";248;1
"Unit";"Zergling";"Larva";249;1
"Unit";"Zergling";"Larva";250;1
"Unit";"Zergling";"Larva";251;1
"Unit";"Zergling";"Larva";252;1
"Unit";"Zergling";"Larva";253;1
"Unit";"Zergling";"Larva";254;1
"Unit";"Zergling";"Larva";255;1
"Unit";"Zergling";"Larva";256;1
"Unit";"Zergling";"Larva";257;1
"Unit";"Zergling";"Larva";258;1
"Unit";"Zergling";"Larva";259;1
"Unit";"Zergling";"Larva";260;1
"Unit";"Zergling";"Larva";261;1
"Unit";"Zergling";"Larva";262;1
"Unit";"Zergling";"Larva";263;1
"Unit";"Zergling";"Larva";264;1
"Unit";"Zergling";"Larva";265;1
"Unit";"Zergling";"Larva";266;1
"Unit";"Zergling";"Larva";267;1
"Unit";"Zergling";"Larva";268;1
"Unit";"Zergling";"Larva";269;1
"Unit";"Zergling";"Larva";270;1
"Unit";"Zergling";"Larva";271;1
"Unit";"Zergling";"Larva";272;1
"Unit";"Zergling";"Larva";273;1
"Unit";"Zergling";"Larva";274;1
"Unit";"Zergling";"Larva";275;1
"Unit";"Zergling";"Larva";276;1
"Unit";"Zergling";"Larva";277;1
"Unit";"Zergling";"Larva";278;1
"Building";"CreepTumor";NA;279;0
"Unit";"Zergling";"Larva";279;1
"Unit";"Zergling";"Larva";280;1
"Unit";"Zergling";"Larva";281;1
"Unit";"Zergling";"Larva";282;1
"Unit";"Zergling";"Larva";283;1
"Unit";"Zergling";"Larva";284;1
"Unit";"Zergling";"Larva";285;1
"Unit";"Zergling";"Larva";286;1
"Unit";"Zergling";"Larva";287;1
"Unit";"Zergling";"Larva";288;1
"Unit";"Zergling";"Larva";289;1
"Unit";"Zergling";"Larva";290;1
"Unit";"Zergling";"Larva";291;1
"Unit";"Zergling";"Larva";292;1
"Unit";"Zergling";"Larva";293;1
"Unit";"Zergling";"Larva";294;1
"Unit";"Baneling";"Zergling";295;0
"Unit";"Baneling";"Zergling";295;0
"Unit";"Baneling";"Zergling";295;0
"Unit";"Baneling";"Zergling";295;0
"Unit";"Zergling";"Larva";295;1
"Unit";"Zergling";"Larva";296;1
"Unit";"Zergling";"Larva";297;1
"Unit";"Zergling";"Larva";298;1
"Unit";"Zergling";"Larva";299;1
"Unit";"Zergling";"Larva";300;1
"Unit";"Zergling";"Larva";301;1
"Unit";"Zergling";"Larva";302;1
"Unit";"Zergling";"Larva";303;1
"Unit";"Zergling";"Larva";304;1
"Unit";"Zergling";"Larva";305;1
"Unit";"Zergling";"Larva";306;1
"Unit";"Zergling";"Larva";307;1
"Unit";"Zergling";"Larva";308;1
"Unit";"Zergling";"Larva";309;1
"Unit";"Zergling";"Larva";310;1
"Unit";"Zergling";"Larva";311;1
"Unit";"Zergling";"Larva";312;1
"Unit";"Zergling";"Larva";313;1
"Unit";"Zergling";"Larva";314;1
"Unit";"Zergling";"Larva";315;1
"Unit";"Zergling";"Larva";316;1
"Unit";"Zergling";"Larva";317;1
"Unit";"Zergling";"Larva";318;1
"Unit";"Zergling";"Larva";319;1
"Unit";"Zergling";"Larva";320;1
"Unit";"Zergling";"Larva";321;1
"Unit";"Zergling";"Larva";322;1
"Unit";"Zergling";"Larva";323;1
"Unit";"Zergling";"Larva";324;1
"Unit";"Zergling";"Larva";325;1
"Unit";"Zergling";"Larva";326;1
"Unit";"Zergling";"Larva";327;1
"Unit";"Zergling";"Larva";328;1
"Building";"CreepTumor";NA;329;0
"Building";"CreepTumor";NA;329;0
"Unit";"Overlord";"Larva";329;0
"Building";"CreepTumorQueen";NA;329;0
"Building";"CreepTumorQueen";NA;329;0
"Unit";"Overlord";"Larva";329;0
"Building";"CreepTumorQueen";NA;329;0
"Unit";"Overlord";"Larva";329;0
"Unit";"Overlord";"Larva";329;0
"Unit";"Baneling";"Zergling";329;0
"Unit";"Baneling";"Zergling";329;0
"Unit";"Baneling";"Zergling";329;0
"Unit";"Baneling";"Zergling";329;0
"Unit";"Baneling";"Zergling";329;0
"Unit";"Baneling";"Zergling";329;0
"Unit";"Baneling";"Zergling";329;0
"Unit";"Overlord";"Larva";329;0
"Unit";"Zergling";"Larva";330;1
"Unit";"Zergling";"Larva";331;1
"Building";"Hatchery";NA;332;0
"Unit";"Zergling";"Larva";332;1
"Unit";"Zergling";"Larva";333;1
"Building";"Spire";NA;334;0
"Unit";"Zergling";"Larva";334;1
"Unit";"Zergling";"Larva";335;1
"Unit";"Zergling";"Larva";336;1
"Unit";"Zergling";"Larva";337;1
"Unit";"Zergling";"Larva";338;1
"Unit";"Zergling";"Larva";339;1
"Unit";"Zergling";"Larva";340;1
"Unit";"Zergling";"Larva";341;1
"Unit";"Zergling";"Larva";342;1
"Unit";"Zergling";"Larva";343;1
"Unit";"Zergling";"Larva";344;1
"Unit";"Zergling";"Larva";345;1
"Unit";"Zergling";"Larva";346;1
"Unit";"Zergling";"Larva";347;1
"Unit";"Zergling";"Larva";348;1
"Unit";"Zergling";"Larva";349;1
"Unit";"Zergling";"Larva";350;1
"Unit";"Zergling";"Larva";351;1
"Unit";"Viper";"Larva";352;3
"Unit";"Viper";"Larva";355;3
"Building";"CreepTumor";NA;358;0
"Building";"UltraliskCavern";NA;358;0
"Unit";"Overlord";"Larva";358;0
"Unit";"Baneling";"Zergling";358;0
"Unit";"Baneling";"Zergling";358;0
"Unit";"Baneling";"Zergling";358;0
"Unit";"Baneling";"Zergling";358;0
"Unit";"Baneling";"Zergling";358;0
"Unit";"Baneling";"Zergling";358;0
"Unit";"Baneling";"Zergling";358;0
"Unit";"Baneling";"Zergling";358;0
"Unit";"Baneling";"Zergling";358;0
"Unit";"Baneling";"Zergling";358;0
"Unit";"Baneling";"Zergling";358;0
"Unit";"Baneling";"Zergling";358;0
"Unit";"Baneling";"Zergling";358;0
"Building";"CreepTumor";NA;358;0
"Building";"CreepTumor";NA;358;0
"Building";"CreepTumor";NA;358;0
"Building";"CreepTumor";NA;358;0
"Building";"CreepTumor";NA;358;0
"Building";"CreepTumorQueen";NA;358;0
"Building";"CreepTumorQueen";NA;358;0
"Unit";"Zergling";"Larva";358;1
"Unit";"Zergling";"Larva";359;1
"Unit";"Zergling";"Larva";360;1
"Unit";"Zergling";"Larva";361;1
"Unit";"Zergling";"Larva";362;1
"Unit";"Zergling";"Larva";363;1
"Unit";"Zergling";"Larva";364;1
"Unit";"Zergling";"Larva";365;1
"Unit";"Zergling";"Larva";366;1
"Unit";"Zergling";"Larva";367;1
"Unit";"Zergling";"Larva";368;1
"Unit";"Zergling";"Larva";369;1
"Unit";"Zergling";"Larva";370;1
"Unit";"Zergling";"Larva";371;1
"Unit";"Zergling";"Larva";372;1
"Unit";"Zergling";"Larva";373;1
"Unit";"Zergling";"Larva";374;1
"Unit";"Zergling";"Larva";375;1
"Unit";"Zergling";"Larva";376;1
"Unit";"Zergling";"Larva";377;1
"Unit";"Zergling";"Larva";378;1
"Unit";"Zergling";"Larva";379;1
"Unit";"Zergling";"Larva";380;1
"Unit";"Zergling";"Larva";381;1
"Unit";"Zergling";"Larva";382;1
"Unit";"Zergling";"Larva";383;1
"Unit";"Zergling";"Larva";384;1
"Unit";"Zergling";"Larva";385;1
"Unit";"Zergling";"Larva";386;1
"Unit";"Zergling";"Larva";387;1
"Unit";"Zergling";"Larva";388;1
"Unit";"Zergling";"Larva";389;1
"Unit";"Zergling";"Larva";390;1
"Unit";"Zergling";"Larva";391;1
"Unit";"Zergling";"Larva";392;1
"Unit";"Zergling";"Larva";393;1
"Unit";"Zergling";"Larva";394;1
"Unit";"Zergling";"Larva";395;1
"Unit";"Zergling";"Larva";396;1
"Unit";"Zergling";"Larva";397;1
"Unit";"Zergling";"Larva";398;1
"Unit";"Zergling";"Larva";399;1
"Unit";"Zergling";"Larva";400;1
"Unit";"Zergling";"Larva";401;1
"Unit";"Zergling";"Larva";402;1
"Unit";"Zergling";"Larva";403;1
"Unit";"Zergling";"Larva";404;1
"Unit";"Zergling";"Larva";405;1
"Unit";"Zergling";"Larva";406;1
"Unit";"Zergling";"Larva";407;1
"Unit";"Zergling";"Larva";408;1
"Unit";"Zergling";"Larva";409;1
"Unit";"Zergling";"Larva";410;1
"Unit";"Zergling";"Larva";411;1
"Unit";"Zergling";"Larva";412;1
"Unit";"Zergling";"Larva";413;1
"Unit";"Zergling";"Larva";414;1
"Unit";"Zergling";"Larva";415;1
"Unit";"Zergling";"Larva";416;1
"Unit";"Zergling";"Larva";417;1
"Unit";"Zergling";"Larva";418;1
"Unit";"Zergling";"Larva";419;1
"Unit";"Zergling";"Larva";420;1
"Unit";"Zergling";"Larva";421;1
"Unit";"Zergling";"Larva";422;1
"Unit";"Zergling";"Larva";423;1
"Unit";"Zergling";"Larva";424;1
"Unit";"Zergling";"Larva";425;1
"Unit";"Zergling";"Larva";426;1
"Unit";"Zergling";"Larva";427;1
"Unit";"Baneling";"Zergling";428;0
"Unit";"Baneling";"Zergling";428;0
"Unit";"Baneling";"Zergling";428;0
"Unit";"Baneling";"Zergling";428;0
"Unit";"Baneling";"Zergling";428;0
"Unit";"Baneling";"Zergling";428;0
"Unit";"Baneling";"Zergling";428;0
"Unit";"Baneling";"Zergling";428;0
"Unit";"Zergling";"Larva";428;1
"Unit";"Zergling";"Larva";429;1
"Unit";"Zergling";"Larva";430;1
"Unit";"Zergling";"Larva";431;1
"Unit";"Zergling";"Larva";432;1
"Unit";"Zergling";"Larva";433;1
"Unit";"Zergling";"Larva";434;1
"Unit";"Zergling";"Larva";435;1
"Unit";"Zergling";"Larva";436;1
"Unit";"Zergling";"Larva";437;1
"Unit";"Zergling";"Larva";438;1
"Unit";"Zergling";"Larva";439;1
"Unit";"Zergling";"Larva";440;1
"Unit";"Zergling";"Larva";441;1
"Upgrade";"ChitinousPlating";"UltraliskCavern";442;0
"Unit";"Corruptor";"Larva";442;2
"Unit";"Corruptor";"Larva";444;2
"Unit";"Corruptor";"Larva";446;2
"Unit";"Corruptor";"Larva";448;2
"Unit";"Viper";"Larva";450;3
"Unit";"Corruptor";"Larva";453;2
"Unit";"Corruptor";"Larva";455;2
"Unit";"Corruptor";"Larva";457;2
"Building";"CreepTumor";NA;471;0
"Building";"CreepTumor";NA;486;0
"Building";"CreepTumor";NA;486;0
"Building";"CreepTumor";NA;486;0
"Building";"CreepTumor";NA;486;0
"Unit";"Viper";"Larva";486;3
"Building";"CreepTumorQueen";NA;489;0
"Building";"CreepTumorQueen";NA;489;0
"Building";"CreepTumorQueen";NA;489;0
"Unit";"Infestor";"Larva";489;2
"Unit";"Infestor";"Larva";491;2
"Unit";"Infestor";"Larva";493;2
"Building";"CreepTumorQueen";NA;495;0
"Building";"CreepTumorQueen";NA;495;0
"Building";"CreepTumorQueen";NA;495;0
"Building";"CreepTumor";NA;495;0
"Building";"CreepTumor";NA;495;0
"Building";"CreepTumor";NA;495;0
"Building";"CreepTumor";NA;495;0
"Unit";"Zergling";"Larva";495;1
"Unit";"Zergling";"Larva";496;1
"Unit";"Zergling";"Larva";497;1
"Unit";"Zergling";"Larva";498;1
"Unit";"Corruptor";"Larva";499;2
"Unit";"Corruptor";"Larva";501;2
"Building";"CreepTumor";NA;503;0
"Building";"CreepTumor";NA;503;0
"Building";"CreepTumor";NA;503;0
"Building";"CreepTumor";NA;503;0
"Building";"CreepTumor";NA;503;0
"Building";"CreepTumor";NA;503;0
"Building";"SporeCrawler";NA;503;0
"Unit";"Corruptor";"Larva";503;2
"Unit";"Corruptor";"Larva";505;2
"Unit";"Corruptor";"Larva";507;2
"Unit";"Corruptor";"Larva";509;2
"Unit";"Corruptor";"Larva";511;2
"Unit";"Zergling";"Larva";513;1
"Unit";"Zergling";"Larva";514;1
"Unit";"Zergling";"Larva";515;1
"Unit";"Zergling";"Larva";516;1
"Unit";"Zergling";"Larva";517;1
"Unit";"Zergling";"Larva";518;1
"Unit";"Zergling";"Larva";519;1
"Unit";"Zergling";"Larva";520;1
"Unit";"Zergling";"Larva";521;1
"Unit";"Zergling";"Larva";522;1
"Unit";"Zergling";"Larva";523;1
"Unit";"Zergling";"Larva";524;1
"Unit";"Zergling";"Larva";525;1
"Unit";"Zergling";"Larva";526;1
"Unit";"Zergling";"Larva";527;1
"Unit";"Zergling";"Larva";528;1
"Unit";"Zergling";"Larva";529;1
"Unit";"Zergling";"Larva";530;1
"Unit";"Zergling";"Larva";531;1
"Unit";"Zergling";"Larva";532;1
"Unit";"Zergling";"Larva";533;1
"Unit";"Zergling";"Larva";534;1
"Unit";"Zergling";"Larva";535;1
"Unit";"Zergling";"Larva";536;1
"Unit";"Zergling";"Larva";537;1
"Unit";"Zergling";"Larva";538;1
"Unit";"Zergling";"Larva";539;1
"Unit";"Zergling";"Larva";540;1
"Unit";"Zergling";"Larva";541;1
"Unit";"Zergling";"Larva";542;1
"Unit";"Zergling";"Larva";543;1
"Unit";"Zergling";"Larva";544;1
"Unit";"Infestor";"Larva";545;2
"Unit";"Infestor";"Larva";547;2
"Building";"CreepTumor";NA;549;0
"Unit";"Zergling";"Larva";552;1
"Unit";"Zergling";"Larva";553;1
"Unit";"Zergling";"Larva";554;1
"Unit";"Zergling";"Larva";555;1
"Unit";"Zergling";"Larva";556;1
"Unit";"Zergling";"Larva";557;1
"Unit";"Zergling";"Larva";558;1
"Unit";"Zergling";"Larva";559;1
"Unit";"Zergling";"Larva";560;1
"Unit";"Zergling";"Larva";561;1
"Unit";"Zergling";"Larva";562;1
"Unit";"Zergling";"Larva";563;1
"Unit";"Zergling";"Larva";564;1
"Unit";"Zergling";"Larva";565;1
"Building";"Hatchery";NA;566;0
"Building";"CreepTumor";NA;566;0
"Building";"CreepTumor";NA;566;0
"Building";"CreepTumor";NA;566;0
"Building";"CreepTumor";NA;566;0
"Building";"CreepTumor";NA;566;0
"Building";"CreepTumor";NA;566;0
"Unit";"Baneling";"Zergling";566;0
"Unit";"Baneling";"Zergling";566;0
"Unit";"Baneling";"Zergling";566;0
"Unit";"Baneling";"Zergling";566;0
"Unit";"Baneling";"Zergling";566;0
"Unit";"Baneling";"Zergling";566;0
"Unit";"Baneling";"Zergling";566;0
"Unit";"Baneling";"Zergling";566;0
"Unit";"Baneling";"Zergling";566;0
"Unit";"Baneling";"Zergling";566;0
"Unit";"Baneling";"Zergling";566;0
"Unit";"Baneling";"Zergling";566;0
"Unit";"Baneling";"Zergling";566;0
"Unit";"Baneling";"Zergling";566;0
"Unit";"Baneling";"Zergling";566;0
"Unit";"Baneling";"Zergling";566;0
"Unit";"Baneling";"Zergling";566;0
"Unit";"Baneling";"Zergling";566;0
"Unit";"Baneling";"Zergling";566;0
"Unit";"Baneling";"Zergling";566;0
"Building";"Hatchery";NA;566;0
"Unit";"Baneling";"Zergling";566;0
"Unit";"Zergling";"Larva";566;1
"Unit";"Zergling";"Larva";567;1
"Unit";"Zergling";"Larva";568;1
"Unit";"Zergling";"Larva";569;1
"Building";"Extractor";NA;570;0
"Unit";"Zergling";"Larva";570;1
"Unit";"Zergling";"Larva";571;1
"Building";"Extractor";NA;572;0
"Unit";"Zergling";"Larva";572;1
"Unit";"Zergling";"Larva";573;1
"Unit";"Zergling";"Larva";574;1
"Unit";"Zergling";"Larva";575;1
"Unit";"Zergling";"Larva";576;1
"Unit";"Zergling";"Larva";577;1
"Unit";"Zergling";"Larva";578;1
"Unit";"Zergling";"Larva";579;1
"Unit";"Zergling";"Larva";580;1
"Unit";"Zergling";"Larva";581;1
"Unit";"Zergling";"Larva";582;1
"Unit";"Zergling";"Larva";583;1
"Unit";"Zergling";"Larva";584;1
"Unit";"Zergling";"Larva";585;1
"Unit";"Zergling";"Larva";586;1
"Unit";"Zergling";"Larva";587;1
"Unit";"Zergling";"Larva";588;1
"Unit";"Zergling";"Larva";589;1
"Unit";"Zergling";"Larva";590;1
"Unit";"Zergling";"Larva";591;1
"Unit";"Zergling";"Larva";592;1
"Unit";"Zergling";"Larva";593;1
"Unit";"Zergling";"Larva";594;1
"Unit";"Zergling";"Larva";595;1
"Unit";"Zergling";"Larva";596;1
"Unit";"Zergling";"Larva";597;1
"Unit";"Zergling";"Larva";598;1
"Unit";"Zergling";"Larva";599;1
"Unit";"Zergling";"Larva";600;1
"Unit";"Zergling";"Larva";601;1
"Unit";"Zergling";"Larva";602;1
"Unit";"Zergling";"Larva";603;1
"Unit";"Zergling";"Larva";604;1
"Unit";"Zergling";"Larva";605;1
"Unit";"Zergling";"Larva";606;1
"Unit";"Zergling";"Larva";607;1
"Unit";"Zergling";"Larva";608;1
"Unit";"Zergling";"Larva";609;1
"Unit";"Zergling";"Larva";610;1
"Unit";"Zergling";"Larva";611;1
"Unit";"Zergling";"Larva";612;1
"Unit";"Zergling";"Larva";613;1
"Unit";"Zergling";"Larva";614;1
"Unit";"Zergling";"Larva";615;1
"Unit";"Zergling";"Larva";616;1
"Unit";"Zergling";"Larva";617;1
"Unit";"Zergling";"Larva";618;1
"Unit";"Zergling";"Larva";619;1
"Unit";"Zergling";"Larva";620;1
"Unit";"Zergling";"Larva";621;1
"Unit";"Zergling";"Larva";622;1
"Unit";"Zergling";"Larva";623;1
"Unit";"Zergling";"Larva";624;1
"Unit";"Zergling";"Larva";625;1
"Unit";"Zergling";"Larva";626;1
"Unit";"Zergling";"Larva";627;1
"Unit";"Zergling";"Larva";628;1
"Unit";"Zergling";"Larva";629;1
"Unit";"Zergling";"Larva";630;1
"Unit";"Zergling";"Larva";631;1
"Unit";"Zergling";"Larva";632;1
"Unit";"Zergling";"Larva";633;1
"Unit";"Zergling";"Larva";634;1
"Unit";"Zergling";"Larva";635;1
"Unit";"Zergling";"Larva";636;1
"Unit";"Zergling";"Larva";637;1
"Unit";"Zergling";"Larva";638;1
"Unit";"Zergling";"Larva";639;1
"Unit";"Zergling";"Larva";640;1
"Unit";"Zergling";"Larva";641;1
"Unit";"Zergling";"Larva";642;1
"Unit";"Zergling";"Larva";643;1
"Unit";"Zergling";"Larva";644;1
"Unit";"Zergling";"Larva";645;1
"Unit";"Zergling";"Larva";646;1
"Unit";"Zergling";"Larva";647;1
"Unit";"Infestor";"Larva";648;2
"Unit";"Infestor";"Larva";650;2
"Unit";"Zergling";"Larva";652;1
"Unit";"Zergling";"Larva";653;1
"Unit";"Baneling";"Zergling";654;0
"Unit";"Baneling";"Zergling";654;0
"Unit";"Baneling";"Zergling";654;0
"Unit";"Baneling";"Zergling";654;0
"Unit";"Baneling";"Zergling";654;0
"Unit";"Baneling";"Zergling";654;0
"Unit";"Baneling";"Zergling";654;0
"Unit";"Baneling";"Zergling";654;0
"Unit";"Baneling";"Zergling";654;0
"Unit";"Baneling";"Zergling";654;0
"Unit";"Baneling";"Zergling";654;0
"Unit";"Baneling";"Zergling";654;0
"Unit";"Baneling";"Zergling";654;0
"Unit";"Baneling";"Zergling";654;0
"Unit";"Baneling";"Zergling";654;0
"Unit";"Baneling";"Zergling";654;0
"Unit";"Baneling";"Zergling";654;0
"Unit";"Baneling";"Zergling";654;0
"Unit";"Baneling";"Zergling";654;0
"Unit";"Baneling";"Zergling";654;0
"Unit";"Baneling";"Zergling";654;0
"Unit";"Baneling";"Zergling";654;0
"Unit";"Baneling";"Zergling";654;0
"Unit";"Baneling";"Zergling";654;0
"Unit";"Baneling";"Zergling";654;0
"Unit";"Baneling";"Zergling";654;0
"Unit";"Baneling";"Zergling";654;0
"Unit";"Baneling";"Zergling";654;0
"Unit";"Baneling";"Zergling";654;0
"Unit";"Baneling";"Zergling";654;0
"Unit";"Baneling";"Zergling";654;0
"Unit";"Baneling";"Zergling";654;0
"Unit";"Baneling";"Zergling";654;0
"Unit";"Baneling";"Zergling";654;0
"Building";"CreepTumor";NA;660;0
"Building";"CreepTumor";NA;660;0
"Building";"CreepTumor";NA;660;0
"Unit";"Infestor";"Larva";660;2
"Building";"CreepTumorQueen";NA;662;0
"Building";"CreepTumorQueen";NA;662;0
"Unit";"Zergling";"Larva";662;1
"Unit";"Zergling";"Larva";663;1
"Unit";"Zergling";"Larva";664;1
"Unit";"Zergling";"Larva";665;1
"Unit";"Zergling";"Larva";666;1
"Unit";"Zergling";"Larva";667;1
"Unit";"Zergling";"Larva";668;1
"Unit";"Zergling";"Larva";669;1
"Unit";"Zergling";"Larva";670;1
"Unit";"Zergling";"Larva";671;1
"Unit";"Zergling";"Larva";672;1
"Unit";"Zergling";"Larva";673;1
"Unit";"Zergling";"Larva";674;1
"Unit";"Zergling";"Larva";675;1
"Unit";"Zergling";"Larva";676;1
"Unit";"Zergling";"Larva";677;1
"Building";"CreepTumorQueen";NA;678;0
"Building";"CreepTumor";NA;678;0
"Building";"CreepTumor";NA;678;0
"Unit";"Zergling";"Larva";678;1
"Unit";"Zergling";"Larva";679;1
"Building";"CreepTumorQueen";NA;680;0
"Building";"CreepTumor";NA;680;0
"Building";"CreepTumor";NA;680;0
"Building";"CreepTumorQueen";NA;681;0
"Unit";"Zergling";"Larva";681;1
"Unit";"Zergling";"Larva";682;1
"Unit";"Zergling";"Larva";683;1
"Unit";"Zergling";"Larva";684;1
"Building";"CreepTumorQueen";NA;685;0
"Unit";"Zergling";"Larva";685;1
"Unit";"Zergling";"Larva";686;1
"Unit";"Zergling";"Larva";687;1
"Unit";"Zergling";"Larva";688;1
"Building";"CreepTumorQueen";NA;689;0
"Unit";"Infestor";"Larva";689;2
"Unit";"Infestor";"Larva";691;2
"Building";"CreepTumor";NA;693;0
"Unit";"Zergling";"Larva";693;1
"Unit";"Zergling";"Larva";694;1
"Unit";"Zergling";"Larva";695;1
"Unit";"Zergling";"Larva";696;1
"Unit";"Zergling";"Larva";697;1
"Unit";"Zergling";"Larva";698;1
"Unit";"Zergling";"Larva";699;1
"Unit";"Zergling";"Larva";700;1
"Unit";"Zergling";"Larva";701;1
"Unit";"Zergling";"Larva";702;1
"Unit";"Zergling";"Larva";703;1
"Unit";"Zergling";"Larva";704;1
"Unit";"Zergling";"Larva";705;1
"Unit";"Zergling";"Larva";706;1
"Unit";"Zergling";"Larva";707;1
"Unit";"Zergling";"Larva";708;1
"Unit";"Zergling";"Larva";709;1
"Unit";"Zergling";"Larva";710;1
"Unit";"Zergling";"Larva";711;1
"Unit";"Zergling";"Larva";712;1
"Unit";"Zergling";"Larva";713;1
"Unit";"Zergling";"Larva";714;1
"Unit";"Zergling";"Larva";715;1
"Unit";"Zergling";"Larva";716;1
"Unit";"Zergling";"Larva";717;1
"Unit";"Zergling";"Larva";718;1
"Building";"CreepTumor";NA;719;0
"Unit";"Zergling";"Larva";719;1
"Unit";"Zergling";"Larva";720;1
"Unit";"Zergling";"Larva";721;1
"Unit";"Zergling";"Larva";722;1
"Building";"Extractor";NA;725;0
"Building";"SporeCrawler";NA;725;0
"Unit";"Zergling";"Larva";725;1
"Unit";"Zergling";"Larva";726;1
"Unit";"Zergling";"Larva";727;1
"Unit";"Zergling";"Larva";728;1
"Unit";"Zergling";"Larva";729;1
"Unit";"Zergling";"Larva";730;1
"Building";"CreepTumor";NA;731;0
"Building";"CreepTumor";NA;731;0
"Building";"CreepTumor";NA;731;0
"Building";"CreepTumor";NA;731;0
"Building";"CreepTumor";NA;731;0
"Building";"CreepTumor";NA;731;0
"Building";"CreepTumor";NA;731;0
"Unit";"Overlord";"Larva";731;0
"Unit";"Baneling";"Zergling";731;0
"Unit";"Baneling";"Zergling";731;0
"Unit";"Baneling";"Zergling";731;0
"Unit";"Baneling";"Zergling";731;0
"Unit";"Baneling";"Zergling";731;0
"Unit";"Baneling";"Zergling";731;0
"Unit";"Baneling";"Zergling";731;0
"Unit";"Baneling";"Zergling";731;0
"Unit";"Baneling";"Zergling";731;0
"Unit";"Infestor";"Larva";731;2
"Unit";"Infestor";"Larva";733;2
"Unit";"Infestor";"Larva";735;2
"Unit";"Infestor";"Larva";737;2
"Unit";"Zergling";"Larva";739;1
"Unit";"Zergling";"Larva";740;1
"Unit";"Zergling";"Larva";741;1
"Unit";"Zergling";"Larva";742;1
"Unit";"Zergling";"Larva";743;1
"Unit";"Zergling";"Larva";744;1
"Unit";"Zergling";"Larva";745;1
"Unit";"Zergling";"Larva";746;1
"Unit";"Zergling";"Larva";747;1
"Unit";"Zergling";"Larva";748;1
"Unit";"Zergling";"Larva";749;1
"Unit";"Zergling";"Larva";750;1
"Unit";"Zergling";"Larva";751;1
"Unit";"Zergling";"Larva";752;1
"Unit";"Zergling";"Larva";753;1
"Unit";"Zergling";"Larva";754;1
"Unit";"Zergling";"Larva";755;1
"Unit";"Zergling";"Larva";756;1
"Unit";"Zergling";"Larva";757;1
"Unit";"Zergling";"Larva";758;1
"Unit";"Zergling";"Larva";759;1
"Unit";"Zergling";"Larva";760;1
"Unit";"Zergling";"Larva";761;1
"Unit";"Zergling";"Larva";762;1
"Unit";"Zergling";"Larva";763;1
"Unit";"Zergling";"Larva";764;1
"Unit";"Zergling";"Larva";765;1
"Unit";"Zergling";"Larva";766;1
"Unit";"Zergling";"Larva";767;1
"Unit";"Zergling";"Larva";768;1
"Unit";"Zergling";"Larva";769;1
"Unit";"Zergling";"Larva";770;1
"Unit";"Zergling";"Larva";771;1
"Unit";"Zergling";"Larva";772;1
"Unit";"Zergling";"Larva";773;1
"Unit";"Zergling";"Larva";774;1
"Unit";"Zergling";"Larva";775;1
"Unit";"Zergling";"Larva";776;1
"Unit";"Zergling";"Larva";777;1
"Unit";"Zergling";"Larva";778;1
"Unit";"Zergling";"Larva";779;1
"Unit";"Zergling";"Larva";780;1
"Unit";"Zergling";"Larva";781;1
"Unit";"Zergling";"Larva";782;1
"Unit";"Zergling";"Larva";783;1
"Unit";"Zergling";"Larva";784;1
"Unit";"Zergling";"Larva";785;1
"Unit";"Zergling";"Larva";786;1
"Unit";"Zergling";"Larva";787;1
"Unit";"Zergling";"Larva";788;1
"Unit";"Zergling";"Larva";789;1
"Unit";"Zergling";"Larva";790;1
"Unit";"Zergling";"Larva";791;1
"Unit";"Zergling";"Larva";792;1
"Unit";"Zergling";"Larva";793;1
"Unit";"Zergling";"Larva";794;1
"Unit";"Zergling";"Larva";795;1
"Unit";"Zergling";"Larva";796;1
"Unit";"Zergling";"Larva";797;1
"Unit";"Zergling";"Larva";798;1
"Unit";"Zergling";"Larva";799;1
"Unit";"Zergling";"Larva";800;1
"Unit";"Zergling";"Larva";801;1
"Unit";"Zergling";"Larva";802;1
"Unit";"Zergling";"Larva";803;1
"Unit";"Zergling";"Larva";804;1
"Unit";"Zergling";"Larva";805;1
"Unit";"Zergling";"Larva";806;1
"Unit";"Zergling";"Larva";807;1
"Unit";"Zergling";"Larva";808;1
"Unit";"Zergling";"Larva";809;1
"Unit";"Zergling";"Larva";810;1
"Building";"CreepTumor";NA;811;0
"Unit";"Zergling";"Larva";811;1
"Unit";"Zergling";"Larva";812;1
"Unit";"Corruptor";"Larva";813;2
"Unit";"Baneling";"Zergling";815;0
"Unit";"Baneling";"Zergling";815;0
"Unit";"Baneling";"Zergling";815;0
"Unit";"Baneling";"Zergling";815;0
"Unit";"Baneling";"Zergling";815;0
"Unit";"Baneling";"Zergling";815;0
"Unit";"Baneling";"Zergling";815;0
"Unit";"Baneling";"Zergling";815;0
"Unit";"Baneling";"Zergling";815;0
"Unit";"Baneling";"Zergling";815;0
"Unit";"Baneling";"Zergling";815;0
"Unit";"Baneling";"Zergling";815;0
"Unit";"Baneling";"Zergling";815;0
"Unit";"Baneling";"Zergling";815;0
"Unit";"Baneling";"Zergling";815;0
"Unit";"Baneling";"Zergling";815;0
"Unit";"Baneling";"Zergling";815;0
"Unit";"Baneling";"Zergling";815;0
"Unit";"Corruptor";"Larva";815;2
"Unit";"Zergling";"Larva";821;1
"Unit";"Zergling";"Larva";822;1
"Building";"Extractor";NA;823;0
"Unit";"Corruptor";"Larva";823;2
"Unit";"Corruptor";"Larva";828;2
"Building";"CreepTumor";NA;831;0
"Building";"CreepTumor";NA;831;0
"Building";"CreepTumor";NA;831;0
"Building";"SpineCrawler";NA;831;0
"Unit";"Zergling";"Larva";831;1
"Unit";"Zergling";"Larva";832;1
"Unit";"Zergling";"Larva";833;1
"Unit";"Zergling";"Larva";834;1
"Unit";"Zergling";"Larva";835;1
"Unit";"Zergling";"Larva";836;1
"Unit";"Zergling";"Larva";837;1
"Unit";"Zergling";"Larva";838;1
"Unit";"Zergling";"Larva";839;1
"Unit";"Zergling";"Larva";840;1
"Unit";"Zergling";"Larva";841;1
"Unit";"Zergling";"Larva";842;1
"Unit";"Zergling";"Larva";843;1
"Unit";"Zergling";"Larva";844;1
"Unit";"Zergling";"Larva";845;1
"Unit";"Zergling";"Larva";846;1
"Unit";"Zergling";"Larva";847;1
"Unit";"Zergling";"Larva";848;1
"Unit";"Zergling";"Larva";849;1
"Unit";"Zergling";"Larva";850;1
"Unit";"Zergling";"Larva";851;1
"Unit";"Zergling";"Larva";852;1
"Unit";"Zergling";"Larva";853;1
"Unit";"Zergling";"Larva";854;1
"Building";"CreepTumor";NA;856;0
"Building";"CreepTumor";NA;856;0
"Unit";"Corruptor";"Larva";856;2
"Unit";"Corruptor";"Larva";858;2
"Unit";"Corruptor";"Larva";860;2
"Unit";"Corruptor";"Larva";862;2
"Unit";"Corruptor";"Larva";864;2
"Unit";"Corruptor";"Larva";867;2
"Building";"CreepTumor";NA;869;0
"Unit";"Corruptor";"Larva";869;2
"Unit";"Corruptor";"Larva";871;2
"Unit";"Corruptor";"Larva";873;2
"Unit";"Overlord";"Larva";876;0
"Unit";"Overlord";"Larva";876;0
"Unit";"Overlord";"Larva";876;0
"Building";"CreepTumor";NA;876;0
"Building";"CreepTumor";NA;876;0
"Building";"CreepTumor";NA;876;0
"Upgrade";"NeuralParasite";"InfestationPit";876;0
"Building";"SporeCrawler";NA;876;0
"Building";"CreepTumorQueen";NA;876;0
"Building";"CreepTumorQueen";NA;876;0
"Building";"CreepTumorQueen";NA;876;0
"Building";"CreepTumorQueen";NA;878;0
"Building";"CreepTumorQueen";NA;879;0
"Building";"CreepTumor";NA;879;0
"Unit";"Zergling";"Larva";879;1
"Unit";"Zergling";"Larva";880;1
"Unit";"Zergling";"Larva";881;1
"Unit";"Zergling";"Larva";882;1
"Unit";"Zergling";"Larva";883;1
"Unit";"Zergling";"Larva";884;1
"Unit";"Zergling";"Larva";885;1
"Unit";"Zergling";"Larva";886;1
"Unit";"Zergling";"Larva";887;1
"Unit";"Zergling";"Larva";888;1
"Unit";"Zergling";"Larva";889;1
"Unit";"Zergling";"Larva";890;1
"Unit";"Zergling";"Larva";891;1
"Unit";"Zergling";"Larva";892;1
"Unit";"Zergling";"Larva";893;1
"Unit";"Zergling";"Larva";894;1
"Unit";"Zergling";"Larva";895;1
"Unit";"Zergling";"Larva";896;1
"Unit";"Zergling";"Larva";897;1
"Unit";"Zergling";"Larva";898;1
"Unit";"Zergling";"Larva";899;1
"Unit";"Zergling";"Larva";900;1
"Unit";"Zergling";"Larva";901;1
"Unit";"Zergling";"Larva";902;1
"Unit";"Zergling";"Larva";903;1
"Unit";"Zergling";"Larva";904;1
"Unit";"Zergling";"Larva";905;1
"Unit";"Zergling";"Larva";906;1
"Unit";"Zergling";"Larva";907;1
"Unit";"Zergling";"Larva";908;1
"Unit";"Zergling";"Larva";909;1
"Unit";"Zergling";"Larva";910;1
"Unit";"Zergling";"Larva";911;1
"Unit";"Zergling";"Larva";912;1
"Unit";"Zergling";"Larva";913;1
"Unit";"Zergling";"Larva";914;1
"Unit";"Zergling";"Larva";915;1
"Unit";"Zergling";"Larva";916;1
"Unit";"Zergling";"Larva";917;1
"Unit";"Zergling";"Larva";918;1
"Unit";"Zergling";"Larva";919;1
"Unit";"Zergling";"Larva";920;1
"Unit";"Zergling";"Larva";921;1
"Unit";"Zergling";"Larva";922;1
"Unit";"Zergling";"Larva";923;1
"Unit";"Zergling";"Larva";924;1
"Unit";"Zergling";"Larva";925;1
"Unit";"Zergling";"Larva";926;1
"Unit";"Zergling";"Larva";927;1
"Unit";"Zergling";"Larva";928;1
"Unit";"Zergling";"Larva";929;1
"Unit";"Zergling";"Larva";930;1
"Unit";"Zergling";"Larva";931;1
"Unit";"Zergling";"Larva";932;1
"Unit";"Zergling";"Larva";933;1
"Unit";"Zergling";"Larva";934;1
"Unit";"Zergling";"Larva";935;1
"Unit";"Zergling";"Larva";936;1
"Unit";"Zergling";"Larva";937;1
"Unit";"Zergling";"Larva";938;1
"Unit";"Zergling";"Larva";939;1
"Unit";"Zergling";"Larva";940;1
"Unit";"Zergling";"Larva";941;1
"Unit";"Zergling";"Larva";942;1
"Unit";"Zergling";"Larva";943;1
"Unit";"Zergling";"Larva";944;1
"Unit";"Zergling";"Larva";945;1
"Unit";"Zergling";"Larva";946;1
"Unit";"Zergling";"Larva";947;1
"Unit";"Zergling";"Larva";948;1
"Unit";"Zergling";"Larva";949;1
"Unit";"Zergling";"Larva";950;1
"Unit";"Zergling";"Larva";951;1
"Unit";"Zergling";"Larva";952;1
"Unit";"Zergling";"Larva";953;1
"Unit";"Zergling";"Larva";954;1
"Unit";"Zergling";"Larva";955;1
"Unit";"Zergling";"Larva";956;1
"Unit";"Zergling";"Larva";957;1
"Unit";"Zergling";"Larva";958;1
"Unit";"Zergling";"Larva";959;1
"Unit";"Zergling";"Larva";960;1
"Unit";"Zergling";"Larva";961;1
"Unit";"Zergling";"Larva";962;1
"Unit";"Zergling";"Larva";963;1
"Unit";"Zergling";"Larva";964;1
"Building";"CreepTumor";NA;974;0
"Unit";"Zergling";"Larva";978;1
"Unit";"Zergling";"Larva";979;1
"Unit";"Zergling";"Larva";980;1
"Unit";"Zergling";"Larva";981;1
"Unit";"Zergling";"Larva";982;1
"Unit";"Zergling";"Larva";983;1
"Unit";"Infestor";"Larva";984;2
"Unit";"Infestor";"Larva";986;2
"Building";"Hatchery";NA;988;0
"Unit";"Baneling";"Zergling";988;0
"Unit";"Baneling";"Zergling";988;0
"Unit";"Baneling";"Zergling";988;0
"Unit";"Baneling";"Zergling";988;0
"Unit";"Baneling";"Zergling";988;0
"Unit";"Baneling";"Zergling";988;0
"Unit";"Baneling";"Zergling";988;0
"Unit";"Baneling";"Zergling";988;0
"Unit";"Baneling";"Zergling";988;0
"Unit";"Baneling";"Zergling";988;0
"Unit";"Baneling";"Zergling";988;0
"Unit";"Baneling";"Zergling";988;0
"Unit";"Baneling";"Zergling";988;0
"Unit";"Baneling";"Zergling";988;0
"Unit";"Baneling";"Zergling";988;0
"Unit";"Baneling";"Zergling";988;0
"Unit";"Baneling";"Zergling";988;0
"Unit";"Zergling";"Larva";1000;1
"Unit";"Zergling";"Larva";1001;1
"Unit";"Zergling";"Larva";1002;1
"Unit";"Zergling";"Larva";1003;1
"Unit";"Zergling";"Larva";1004;1
"Unit";"Zergling";"Larva";1005;1
"Unit";"Zergling";"Larva";1006;1
"Unit";"Zergling";"Larva";1007;1
"Unit";"Zergling";"Larva";1008;1
"Unit";"Zergling";"Larva";1009;1
"Unit";"Zergling";"Larva";1010;1
"Unit";"Zergling";"Larva";1011;1
"Unit";"Zergling";"Larva";1012;1
"Unit";"Zergling";"Larva";1013;1
"Unit";"Zergling";"Larva";1014;1
"Unit";"Zergling";"Larva";1015;1
"Unit";"Zergling";"Larva";1016;1
"Unit";"Zergling";"Larva";1017;1
"Unit";"Zergling";"Larva";1018;1
"Unit";"Zergling";"Larva";1019;1
"Unit";"Corruptor";"Larva";1020;2
"Unit";"Corruptor";"Larva";1022;2
"Unit";"Corruptor";"Larva";1024;2
"Unit";"Corruptor";"Larva";1026;2
"Unit";"Corruptor";"Larva";1028;2
"Unit";"Zergling";"Larva";1033;1
"Unit";"Zergling";"Larva";1034;1
"Unit";"Zergling";"Larva";1035;1
"Unit";"Zergling";"Larva";1036;1
"Unit";"Zergling";"Larva";1037;1
"Unit";"Zergling";"Larva";1038;1
"Unit";"Zergling";"Larva";1039;1
"Unit";"Zergling";"Larva";1040;1
"Unit";"Zergling";"Larva";1041;1
"Unit";"Zergling";"Larva";1042;1
"Unit";"Zergling";"Larva";1043;1
"Unit";"Zergling";"Larva";1044;1
"Unit";"Zergling";"Larva";1045;1
"Unit";"Zergling";"Larva";1046;1
"Unit";"Zergling";"Larva";1047;1
"Unit";"Zergling";"Larva";1048;1
"Unit";"Zergling";"Larva";1049;1
"Unit";"Zergling";"Larva";1050;1
"Unit";"Corruptor";"Larva";1051;2
"Unit";"Corruptor";"Larva";1053;2
"Unit";"Corruptor";"Larva";1055;2
"Unit";"Corruptor";"Larva";1057;2
"Unit";"Corruptor";"Larva";1059;2
"Unit";"Zergling";"Larva";1061;1
"Unit";"Zergling";"Larva";1062;1
"Unit";"Zergling";"Larva";1063;1
"Unit";"Zergling";"Larva";1064;1
"Unit";"Zergling";"Larva";1065;1
"Unit";"Zergling";"Larva";1066;1
"Unit";"Zergling";"Larva";1067;1
"Unit";"Zergling";"Larva";1068;1
"Unit";"Zergling";"Larva";1069;1
"Unit";"Zergling";"Larva";1070;1
"Unit";"Zergling";"Larva";1071;1
"Unit";"Zergling";"Larva";1072;1
"Building";"Hatchery";NA;1073;0
"Unit";"Zergling";"Larva";1073;1
"Unit";"Zergling";"Larva";1074;1
"Unit";"Zergling";"Larva";1075;1
"Unit";"Zergling";"Larva";1076;1
"Unit";"Zergling";"Larva";1077;1
"Unit";"Zergling";"Larva";1078;1
"Unit";"Zergling";"Larva";1079;1
"Unit";"Zergling";"Larva";1080;1
"Unit";"Zergling";"Larva";1081;1
"Unit";"Zergling";"Larva";1082;1
"Unit";"Zergling";"Larva";1083;1
"Unit";"Zergling";"Larva";1084;1
"Unit";"Corruptor";"Larva";1086;2
"Unit";"Corruptor";"Larva";1088;2
"Unit";"Corruptor";"Larva";1090;2
"Building";"Extractor";NA;1092;0
"Unit";"Zergling";"Larva";1092;1
"Unit";"Zergling";"Larva";1093;1
"Unit";"Zergling";"Larva";1094;1
"Unit";"Zergling";"Larva";1095;1
"Unit";"Zergling";"Larva";1096;1
"Unit";"Zergling";"Larva";1097;1
"Unit";"Zergling";"Larva";1098;1
"Unit";"Zergling";"Larva";1099;1
"Unit";"Zergling";"Larva";1100;1
"Unit";"Zergling";"Larva";1101;1
"Unit";"Zergling";"Larva";1102;1
"Unit";"Zergling";"Larva";1103;1
"Unit";"Zergling";"Larva";1104;1
"Unit";"Zergling";"Larva";1105;1
"Unit";"Zergling";"Larva";1106;1
"Unit";"Zergling";"Larva";1107;1
"Unit";"Zergling";"Larva";1108;1
"Unit";"Zergling";"Larva";1109;1
"Unit";"Zergling";"Larva";1110;1
"Unit";"Zergling";"Larva";1111;1
"Unit";"Zergling";"Larva";1112;1
"Unit";"Zergling";"Larva";1113;1
"Unit";"Zergling";"Larva";1114;1
"Unit";"Zergling";"Larva";1115;1
"Unit";"Zergling";"Larva";1116;1
"Unit";"Zergling";"Larva";1117;1
"Unit";"Zergling";"Larva";1118;1
"Unit";"Zergling";"Larva";1119;1
"Unit";"Zergling";"Larva";1120;1
"Unit";"Zergling";"Larva";1121;1
"Building";"SporeCrawler";NA;1122;0
"Building";"SporeCrawler";NA;1122;0
"Unit";"Zergling";"Larva";1122;1
"Unit";"Zergling";"Larva";1123;1
"Unit";"Zergling";"Larva";1124;1
"Unit";"Zergling";"Larva";1125;1
"Unit";"Zergling";"Larva";1126;1
"Unit";"Zergling";"Larva";1127;1
"Unit";"Zergling";"Larva";1128;1
"Unit";"Zergling";"Larva";1129;1
"Unit";"Zergling";"Larva";1130;1
"Unit";"Zergling";"Larva";1131;1
"Unit";"Zergling";"Larva";1132;1
"Unit";"Zergling";"Larva";1133;1
"Unit";"Zergling";"Larva";1134;1
"Unit";"Zergling";"Larva";1135;1
"Unit";"Zergling";"Larva";1136;1
"Unit";"Zergling";"Larva";1137;1
"Unit";"Zergling";"Larva";1138;1
"Unit";"Zergling";"Larva";1139;1
"Unit";"Zergling";"Larva";1140;1
"Unit";"Zergling";"Larva";1141;1
"Unit";"Infestor";"Larva";1142;2
"Unit";"Infestor";"Larva";1144;2
"Unit";"Infestor";"Larva";1146;2
"Unit";"Infestor";"Larva";1148;2
"Unit";"Zergling";"Larva";1150;1
"Unit";"Zergling";"Larva";1151;1
"Unit";"Zergling";"Larva";1152;1
"Unit";"Zergling";"Larva";1153;1
"Unit";"Zergling";"Larva";1154;1
"Unit";"Zergling";"Larva";1155;1
"Unit";"Zergling";"Larva";1156;1
"Unit";"Zergling";"Larva";1157;1
"Unit";"Zergling";"Larva";1158;1
"Unit";"Zergling";"Larva";1159;1
"Unit";"Baneling";"Zergling";1161;0
"Unit";"Baneling";"Zergling";1161;0
"Unit";"Baneling";"Zergling";1161;0
"Unit";"Baneling";"Zergling";1161;0
"Unit";"Baneling";"Zergling";1161;0
"Unit";"Baneling";"Zergling";1161;0
"Unit";"Baneling";"Zergling";1161;0
"Unit";"Baneling";"Zergling";1161;0
"Unit";"Baneling";"Zergling";1161;0
"Unit";"Baneling";"Zergling";1161;0
"Unit";"Baneling";"Zergling";1161;0
"Unit";"Baneling";"Zergling";1161;0
"Unit";"Baneling";"Zergling";1161;0
"Unit";"Baneling";"Zergling";1161;0
"Unit";"Baneling";"Zergling";1161;0
"Unit";"Baneling";"Zergling";1161;0
"Unit";"Baneling";"Zergling";1161;0
"Unit";"Baneling";"Zergling";1161;0
"Unit";"Baneling";"Zergling";1161;0
"Unit";"Baneling";"Zergling";1161;0
"Unit";"Baneling";"Zergling";1161;0
"Building";"CreepTumor";NA;1161;0
"Unit";"Overlord";"Larva";1161;0
"Unit";"Zergling";"Larva";1161;1
"Unit";"Zergling";"Larva";1162;1
"Unit";"Zergling";"Larva";1163;1
"Unit";"Zergling";"Larva";1164;1
"Unit";"Zergling";"Larva";1165;1
"Unit";"Zergling";"Larva";1166;1
"Unit";"Zergling";"Larva";1167;1
"Unit";"Zergling";"Larva";1168;1
"Unit";"Infestor";"Larva";1169;2
"Unit";"Infestor";"Larva";1171;2
"Unit";"Zergling";"Larva";1173;1
"Unit";"Zergling";"Larva";1174;1
"Unit";"Zergling";"Larva";1175;1
"Unit";"Zergling";"Larva";1176;1
"Unit";"Zergling";"Larva";1180;1
"Unit";"Zergling";"Larva";1181;1
"Building";"Extractor";NA;1182;0
"Unit";"Zergling";"Larva";1182;1
"Unit";"Zergling";"Larva";1183;1
"Unit";"Zergling";"Larva";1184;1
"Unit";"Zergling";"Larva";1185;1
"Unit";"Zergling";"Larva";1186;1
"Unit";"Zergling";"Larva";1187;1
"Upgrade";"SprayZerg";NA;1188;0
"Upgrade";"SprayZerg";NA;1188;0
"Upgrade";"zerglingmovementspeed";NA;1188;0
"Upgrade";"SprayZerg";NA;1188;0
"Upgrade";"SprayZerg";NA;1188;0
"Upgrade";"SprayZerg";NA;1188;0
"Upgrade";"ZergMissileWeaponsLevel1";NA;1188;0
"Upgrade";"SprayZerg";NA;1188;0
"Upgrade";"SprayZerg";NA;1188;0
"Upgrade";"SprayZerg";NA;1188;0
"Upgrade";"ZergGroundArmorsLevel1";NA;1188;0
"Upgrade";"ZergMeleeWeaponsLevel1";NA;1188;0
"Upgrade";"CentrificalHooks";NA;1188;0
"Upgrade";"SprayZerg";NA;1188;0
"Upgrade";"SprayZerg";NA;1188;0
"Upgrade";"ZergGroundArmorsLevel2";NA;1188;0
"Upgrade";"ZergMeleeWeaponsLevel2";NA;1188;0
"Upgrade";"zerglingattackspeed";NA;1188;0
"Upgrade";"ZergFlyerWeaponsLevel1";NA;1188;0
"Upgrade";"ZergGroundArmorsLevel3";NA;1188;0
"Upgrade";"InfestorEnergyUpgrade";NA;1188;0
"Upgrade";"ZergMeleeWeaponsLevel3";NA;1188;0
"Upgrade";"SprayZerg";NA;1188;0
"Upgrade";"SprayZerg";NA;1188;0
"Upgrade";"SprayZerg";NA;1188;0
"Upgrade";"SprayZerg";NA;1188;0
"Upgrade";"ZergFlyerWeaponsLevel2";NA;1188;0
"Upgrade";"SprayZerg";NA;1188;0
"Upgrade";"overlordspeed";NA;1188;0
"Upgrade";"SprayZerg";NA;1188;0
"Upgrade";"SprayZerg";NA;1188;0
"Upgrade";"SprayZerg";NA;1188;0
