"type";"unit_name";"on_building";"total_supply";"supply"
"Unit";"Overlord";"Larva";13;0
"Building";"Extractor";NA;18;0
"Building";"SpawningPool";NA;19;0
"Building";"Hatchery";NA;17;0
"Unit";"Overlord";"Larva";23;0
"Unit";"Zergling";"Larva";23;1
"Unit";"Zergling";"Larva";23;1
"Unit";"Zergling";"Larva";23;1
"Unit";"Zergling";"Larva";23;1
"Unit";"Queen";"Hatchery";23;2
"Unit";"Queen";"Hatchery";23;2
"Unit";"Overlord";"Larva";33;0
"Unit";"Overlord";"Larva";36;0
"Unit";"Zergling";"Larva";36;1
"Unit";"Zergling";"Larva";36;1
"Unit";"Zergling";"Larva";36;1
"Unit";"Zergling";"Larva";36;1
"Unit";"Queen";"Hatchery";34;2
"Building";"CreepTumorQueen";NA;49;0
"Unit";"Overlord";"Larva";39;0
"Building";"Hatchery";NA;29;0
"Unit";"Zergling";"Larva";51;1
"Unit";"Zergling";"Larva";51;1
"Unit";"Zergling";"Larva";51;1
"Unit";"Zergling";"Larva";51;1
"Unit";"Zergling";"Larva";51;1
"Unit";"Zergling";"Larva";51;1
"Unit";"Overlord";"Larva";64;0
"Unit";"Zergling";"Larva";64;1
"Unit";"Zergling";"Larva";64;1
"Unit";"Zergling";"Larva";64;1
"Unit";"Zergling";"Larva";64;1
"Unit";"Zergling";"Larva";66;1
"Unit";"Zergling";"Larva";66;1
"Unit";"Queen";"Hatchery";51;2
"Building";"CreepTumorQueen";NA;66;0
"Building";"SpineCrawler";NA;57;0
"Unit";"Overlord";"Larva";66;0
"Unit";"Zergling";"Larva";70;1
"Unit";"Zergling";"Larva";70;1
"Unit";"Zergling";"Larva";70;1
"Unit";"Zergling";"Larva";70;1
"Unit";"Zergling";"Larva";70;1
"Unit";"Zergling";"Larva";70;1
"Unit";"Zergling";"Larva";70;1
"Unit";"Zergling";"Larva";70;1
"Unit";"Zergling";"Larva";70;1
"Unit";"Zergling";"Larva";70;1
"Building";"SpineCrawler";NA;66;0
"Unit";"Queen";"Hatchery";66;2
"Building";"CreepTumorQueen";NA;86;0
"Unit";"Zergling";"Larva";86;1
"Unit";"Zergling";"Larva";86;1
"Unit";"Zergling";"Larva";86;1
"Unit";"Zergling";"Larva";86;1
"Unit";"Zergling";"Larva";86;1
"Unit";"Zergling";"Larva";86;1
"Unit";"Zergling";"Larva";86;1
"Unit";"Zergling";"Larva";86;1
"Unit";"Zergling";"Larva";86;1
"Unit";"Zergling";"Larva";86;1
"Unit";"Zergling";"Larva";86;1
"Unit";"Zergling";"Larva";86;1
"Building";"CreepTumorQueen";NA;86;0
"Building";"Extractor";NA;84;0
"Unit";"Overlord";"Larva";86;0
"Unit";"Overlord";"Larva";86;0
"Unit";"Queen";"Hatchery";84;2
"Unit";"Queen";"Hatchery";84;2
"Unit";"Queen";"Hatchery";84;2
"Building";"BanelingNest";NA;84;0
"Unit";"Overlord";"Larva";98;0
"Unit";"Overlord";"Larva";98;0
"Building";"SporeCrawler";NA;106;0
"Building";"SporeCrawler";NA;106;0
"Building";"SporeCrawler";NA;108;0
"Building";"CreepTumor";NA;108;0
"Building";"CreepTumor";NA;108;0
"Unit";"Overlord";"Larva";108;0
"Building";"EvolutionChamber";NA;108;0
"Building";"EvolutionChamber";NA;108;0
"Unit";"Overlord";"Larva";116;0
"Building";"CreepTumor";NA;119;0
"Building";"CreepTumor";NA;123;0
"Unit";"Zergling";"Larva";123;1
"Unit";"Zergling";"Larva";123;1
"Unit";"Zergling";"Larva";123;1
"Unit";"Zergling";"Larva";123;1
"Unit";"Zergling";"Larva";123;1
"Unit";"Zergling";"Larva";123;1
"Unit";"Zergling";"Larva";123;1
"Unit";"Zergling";"Larva";123;1
"Unit";"Zergling";"Larva";123;1
"Unit";"Zergling";"Larva";123;1
"Unit";"Zergling";"Larva";123;1
"Unit";"Zergling";"Larva";123;1
"Unit";"Zergling";"Larva";123;1
"Unit";"Zergling";"Larva";123;1
"Unit";"Zergling";"Larva";123;1
"Unit";"Zergling";"Larva";123;1
"Unit";"Zergling";"Larva";123;1
"Unit";"Zergling";"Larva";123;1
"Building";"Extractor";NA;123;0
"Building";"Extractor";NA;123;0
"Building";"CreepTumorQueen";NA;150;0
"Building";"CreepTumorQueen";NA;152;0
"Building";"CreepTumorQueen";NA;152;0
"Building";"CreepTumorQueen";NA;152;0
"Building";"CreepTumorQueen";NA;152;0
"Building";"CreepTumorQueen";NA;152;0
"Building";"Extractor";NA;152;0
"Building";"CreepTumorQueen";NA;158;0
"Building";"Extractor";NA;152;0
"Building";"CreepTumor";NA;158;0
"Unit";"Overlord";"Larva";161;0
"Unit";"Overlord";"Larva";161;0
"Unit";"Overlord";"Larva";161;0
"Unit";"Overlord";"Larva";161;0
"Building";"CreepTumorQueen";NA;164;0
"Building";"CreepTumorQueen";NA;164;0
"Building";"CreepTumor";NA;164;0
"Building";"CreepTumor";NA;164;0
"Building";"CreepTumorQueen";NA;164;0
"Building";"CreepTumorQueen";NA;164;0
"Building";"CreepTumorQueen";NA;164;0
"Upgrade";"ZergMeleeWeaponsLevel1";"EvolutionChamber";123;0
"Upgrade";"ZergGroundArmorsLevel1";"EvolutionChamber";123;0
"Building";"CreepTumor";NA;164;0
"Unit";"Zergling";"Larva";164;1
"Unit";"Zergling";"Larva";164;1
"Unit";"Overlord";"Larva";164;0
"Unit";"Overlord";"Larva";164;0
"Unit";"Baneling";"Zergling";164;0
"Unit";"Baneling";"Zergling";164;0
"Unit";"Baneling";"Zergling";164;0
"Unit";"Baneling";"Zergling";164;0
"Unit";"Baneling";"Zergling";164;0
"Unit";"Baneling";"Zergling";164;0
"Unit";"Baneling";"Zergling";164;0
"Unit";"Baneling";"Zergling";164;0
"Unit";"Baneling";"Zergling";164;0
"Unit";"Baneling";"Zergling";164;0
"Unit";"Baneling";"Zergling";164;0
"Unit";"Baneling";"Zergling";164;0
"Unit";"Baneling";"Zergling";164;0
"Unit";"Baneling";"Zergling";164;0
"Unit";"Baneling";"Zergling";164;0
"Unit";"Baneling";"Zergling";164;0
"Unit";"Zergling";"Larva";164;1
"Unit";"Zergling";"Larva";164;1
"Unit";"Zergling";"Larva";164;1
"Unit";"Zergling";"Larva";164;1
"Unit";"Zergling";"Larva";164;1
"Unit";"Zergling";"Larva";164;1
"Building";"CreepTumor";NA;174;0
"Building";"HydraliskDen";NA;164;0
"Building";"CreepTumor";NA;174;0
"Unit";"Zergling";"Larva";172;1
"Unit";"Zergling";"Larva";172;1
"Unit";"Zergling";"Larva";172;1
"Unit";"Zergling";"Larva";172;1
"Unit";"Zergling";"Larva";172;1
"Unit";"Zergling";"Larva";172;1
"Building";"CreepTumorQueen";NA;180;0
"Building";"CreepTumorQueen";NA;180;0
"Building";"CreepTumor";NA;180;0
"Building";"CreepTumorQueen";NA;180;0
"Building";"Hatchery";NA;152;0
"Unit";"Zergling";"Larva";180;1
"Unit";"Zergling";"Larva";180;1
"Unit";"Zergling";"Larva";180;1
"Unit";"Zergling";"Larva";180;1
"Unit";"Zergling";"Larva";180;1
"Unit";"Zergling";"Larva";180;1
"Unit";"Zergling";"Larva";180;1
"Unit";"Zergling";"Larva";180;1
"Unit";"Zergling";"Larva";180;1
"Unit";"Zergling";"Larva";180;1
"Unit";"Zergling";"Larva";180;1
"Unit";"Zergling";"Larva";180;1
"Unit";"Zergling";"Larva";180;1
"Unit";"Zergling";"Larva";180;1
"Unit";"Hydralisk";"Larva";186;2
"Unit";"Hydralisk";"Larva";186;2
"Unit";"Hydralisk";"Larva";186;2
"Unit";"Hydralisk";"Larva";186;2
"Unit";"Hydralisk";"Larva";186;2
"Unit";"Hydralisk";"Larva";186;2
"Unit";"Hydralisk";"Larva";186;2
"Building";"CreepTumor";NA;200;0
"Building";"SporeCrawler";NA;200;0
"Building";"CreepTumor";NA;214;0
"Building";"SporeCrawler";NA;200;0
"Building";"CreepTumor";NA;214;0
"Building";"CreepTumorQueen";NA;214;0
"Unit";"Overlord";"Larva";200;0
"Unit";"Overlord";"Larva";200;0
"Building";"SporeCrawler";NA;200;0
"Unit";"Overlord";"Larva";200;0
"Unit";"Hydralisk";"Larva";200;2
"Unit";"Hydralisk";"Larva";200;2
"Unit";"Hydralisk";"Larva";200;2
"Unit";"Hydralisk";"Larva";200;2
"Unit";"Hydralisk";"Larva";200;2
"Unit";"Hydralisk";"Larva";200;2
"Building";"CreepTumor";NA;214;0
"Building";"CreepTumorQueen";NA;214;0
"Unit";"Overlord";"Larva";214;0
"Building";"CreepTumorQueen";NA;227;0
"Building";"CreepTumorQueen";NA;227;0
"Upgrade";"EvolveMuscularAugments";"HydraliskDen";200;0
"Building";"CreepTumor";NA;227;0
"Unit";"Zergling";"Larva";227;1
"Unit";"Zergling";"Larva";227;1
"Unit";"Zergling";"Larva";227;1
"Unit";"Zergling";"Larva";227;1
"Unit";"Zergling";"Larva";227;1
"Unit";"Zergling";"Larva";227;1
"Building";"CreepTumorQueen";NA;227;0
"Unit";"Zergling";"Larva";227;1
"Unit";"Zergling";"Larva";227;1
"Unit";"Zergling";"Larva";227;1
"Unit";"Zergling";"Larva";227;1
"Unit";"Zergling";"Larva";227;1
"Unit";"Zergling";"Larva";227;1
"Unit";"Zergling";"Larva";227;1
"Unit";"Zergling";"Larva";227;1
"Unit";"Zergling";"Larva";227;1
"Unit";"Zergling";"Larva";227;1
"Unit";"Zergling";"Larva";227;1
"Unit";"Zergling";"Larva";227;1
"Unit";"Zergling";"Larva";227;1
"Unit";"Zergling";"Larva";227;1
"Unit";"Zergling";"Larva";227;1
"Unit";"Zergling";"Larva";227;1
"Unit";"Zergling";"Larva";227;1
"Unit";"Zergling";"Larva";227;1
"Unit";"Zergling";"Larva";227;1
"Unit";"Zergling";"Larva";227;1
"Unit";"Zergling";"Larva";227;1
"Unit";"Zergling";"Larva";227;1
"Unit";"Zergling";"Larva";227;1
"Unit";"Zergling";"Larva";227;1
"Unit";"Zergling";"Larva";227;1
"Unit";"Zergling";"Larva";227;1
"Unit";"Zergling";"Larva";227;1
"Unit";"Zergling";"Larva";227;1
"Unit";"Zergling";"Larva";227;1
"Unit";"Zergling";"Larva";227;1
"Unit";"Zergling";"Larva";227;1
"Unit";"Zergling";"Larva";227;1
"Building";"CreepTumor";NA;265;0
"Building";"CreepTumor";NA;265;0
"Building";"CreepTumor";NA;265;0
"Building";"Extractor";NA;265;0
"Building";"Extractor";NA;265;0
"Upgrade";"ZergMeleeWeaponsLevel2";"EvolutionChamber";214;0
"Unit";"Zergling";"Larva";271;1
"Unit";"Zergling";"Larva";271;1
"Upgrade";"ZergGroundArmorsLevel2";"EvolutionChamber";214;0
"Unit";"Zergling";"Larva";271;1
"Unit";"Zergling";"Larva";271;1
"Unit";"Zergling";"Larva";271;1
"Unit";"Zergling";"Larva";271;1
"Unit";"Zergling";"Larva";271;1
"Unit";"Zergling";"Larva";271;1
"Unit";"Zergling";"Larva";271;1
"Unit";"Zergling";"Larva";271;1
"Unit";"Zergling";"Larva";271;1
"Unit";"Zergling";"Larva";271;1
"Unit";"Zergling";"Larva";271;1
"Unit";"Zergling";"Larva";271;1
"Unit";"Zergling";"Larva";271;1
"Unit";"Zergling";"Larva";271;1
"Unit";"Zergling";"Larva";271;1
"Unit";"Zergling";"Larva";271;1
"Unit";"Zergling";"Larva";271;1
"Unit";"Zergling";"Larva";271;1
"Unit";"Zergling";"Larva";271;1
"Unit";"Zergling";"Larva";271;1
"Unit";"Zergling";"Larva";271;1
"Unit";"Zergling";"Larva";271;1
"Unit";"Zergling";"Larva";271;1
"Unit";"Zergling";"Larva";271;1
"Unit";"Zergling";"Larva";271;1
"Unit";"Zergling";"Larva";271;1
"Unit";"Zergling";"Larva";271;1
"Unit";"Zergling";"Larva";271;1
"Unit";"Zergling";"Larva";271;1
"Unit";"Zergling";"Larva";271;1
"Unit";"Zergling";"Larva";271;1
"Unit";"Zergling";"Larva";271;1
"Unit";"Zergling";"Larva";271;1
"Unit";"Zergling";"Larva";271;1
"Building";"InfestationPit";NA;265;0
"Unit";"Baneling";"Zergling";307;0
"Unit";"Baneling";"Zergling";307;0
"Unit";"Baneling";"Zergling";307;0
"Unit";"Baneling";"Zergling";307;0
"Unit";"Baneling";"Zergling";307;0
"Unit";"Baneling";"Zergling";307;0
"Unit";"Baneling";"Zergling";307;0
"Unit";"Baneling";"Zergling";307;0
"Unit";"Baneling";"Zergling";307;0
"Unit";"Baneling";"Zergling";307;0
"Unit";"Baneling";"Zergling";307;0
"Unit";"Baneling";"Zergling";307;0
"Unit";"Baneling";"Zergling";307;0
"Unit";"Baneling";"Zergling";307;0
"Unit";"Baneling";"Zergling";307;0
"Unit";"Baneling";"Zergling";307;0
"Unit";"Baneling";"Zergling";307;0
"Unit";"Baneling";"Zergling";307;0
"Unit";"Baneling";"Zergling";307;0
"Unit";"Baneling";"Zergling";307;0
"Unit";"Baneling";"Zergling";307;0
"Unit";"Baneling";"Zergling";307;0
"Unit";"Baneling";"Zergling";307;0
"Unit";"Baneling";"Zergling";307;0
"Unit";"Baneling";"Zergling";307;0
"Unit";"Baneling";"Zergling";307;0
"Unit";"Baneling";"Zergling";307;0
"Unit";"Baneling";"Zergling";307;0
"Unit";"Baneling";"Zergling";307;0
"Unit";"Baneling";"Zergling";307;0
"Unit";"Baneling";"Zergling";307;0
"Unit";"Baneling";"Zergling";307;0
"Unit";"Baneling";"Zergling";307;0
"Unit";"Baneling";"Zergling";307;0
"Unit";"Baneling";"Zergling";307;0
"Upgrade";"EvolveGroovedSpines";"HydraliskDen";271;0
"Unit";"Overlord";"Larva";307;0
"Unit";"Overlord";"Larva";307;0
"Unit";"Overlord";"Larva";307;0
"Building";"Hatchery";NA;265;0
"Building";"Hatchery";NA;268;0
"Building";"Hatchery";NA;271;0
"Unit";"Zergling";"Larva";313;1
"Unit";"Zergling";"Larva";313;1
"Unit";"Zergling";"Larva";313;1
"Unit";"Zergling";"Larva";313;1
"Unit";"Zergling";"Larva";313;1
"Unit";"Zergling";"Larva";313;1
"Unit";"Zergling";"Larva";313;1
"Unit";"Zergling";"Larva";313;1
"Unit";"Zergling";"Larva";313;1
"Unit";"Zergling";"Larva";313;1
"Unit";"Zergling";"Larva";313;1
"Unit";"Zergling";"Larva";313;1
"Unit";"Zergling";"Larva";313;1
"Unit";"Zergling";"Larva";313;1
"Unit";"Zergling";"Larva";313;1
"Unit";"Zergling";"Larva";313;1
"Unit";"Zergling";"Larva";313;1
"Unit";"Zergling";"Larva";313;1
"Unit";"Zergling";"Larva";313;1
"Unit";"Zergling";"Larva";313;1
"Unit";"Zergling";"Larva";313;1
"Unit";"Zergling";"Larva";313;1
"Unit";"Zergling";"Larva";313;1
"Unit";"Zergling";"Larva";313;1
"Unit";"Zergling";"Larva";313;1
"Unit";"Zergling";"Larva";313;1
"Unit";"Zergling";"Larva";313;1
"Unit";"Zergling";"Larva";313;1
"Unit";"Zergling";"Larva";313;1
"Unit";"Zergling";"Larva";313;1
"Unit";"Zergling";"Larva";313;1
"Unit";"Zergling";"Larva";313;1
"Unit";"Zergling";"Larva";313;1
"Unit";"Zergling";"Larva";313;1
"Unit";"Zergling";"Larva";313;1
"Unit";"Zergling";"Larva";313;1
"Unit";"Zergling";"Larva";313;1
"Unit";"Zergling";"Larva";313;1
"Unit";"Zergling";"Larva";313;1
"Unit";"Zergling";"Larva";313;1
"Unit";"Zergling";"Larva";313;1
"Unit";"Zergling";"Larva";313;1
"Unit";"Zergling";"Larva";337;1
"Unit";"Zergling";"Larva";337;1
"Unit";"Baneling";"Zergling";337;0
"Unit";"Zergling";"Larva";337;1
"Unit";"Zergling";"Larva";337;1
"Unit";"Zergling";"Larva";337;1
"Unit";"Zergling";"Larva";337;1
"Unit";"Baneling";"Zergling";337;0
"Unit";"Baneling";"Zergling";337;0
"Unit";"Baneling";"Zergling";337;0
"Unit";"Zergling";"Larva";337;1
"Unit";"Zergling";"Larva";337;1
"Unit";"Zergling";"Larva";337;1
"Unit";"Zergling";"Larva";337;1
"Unit";"Zergling";"Larva";337;1
"Unit";"Zergling";"Larva";337;1
"Building";"EvolutionChamber";NA;313;0
"Unit";"Baneling";"Zergling";337;0
"Unit";"Baneling";"Zergling";337;0
"Unit";"Baneling";"Zergling";337;0
"Unit";"Baneling";"Zergling";337;0
"Unit";"Baneling";"Zergling";337;0
"Unit";"Baneling";"Zergling";337;0
"Unit";"Baneling";"Zergling";337;0
"Unit";"Baneling";"Zergling";337;0
"Unit";"Baneling";"Zergling";337;0
"Unit";"Baneling";"Zergling";337;0
"Unit";"Baneling";"Zergling";367;0
"Unit";"Baneling";"Zergling";367;0
"Unit";"Baneling";"Zergling";367;0
"Unit";"Baneling";"Zergling";367;0
"Unit";"Baneling";"Zergling";367;0
"Unit";"Baneling";"Zergling";367;0
"Unit";"Baneling";"Zergling";367;0
"Unit";"Baneling";"Zergling";367;0
"Unit";"Baneling";"Zergling";367;0
"Unit";"Baneling";"Zergling";367;0
"Unit";"Baneling";"Zergling";367;0
"Unit";"Baneling";"Zergling";367;0
"Unit";"Baneling";"Zergling";367;0
"Unit";"Baneling";"Zergling";367;0
"Unit";"Hydralisk";"Larva";339;2
"Unit";"Baneling";"Zergling";367;0
"Unit";"Baneling";"Zergling";367;0
"Unit";"Baneling";"Zergling";367;0
"Unit";"Baneling";"Zergling";367;0
"Unit";"Baneling";"Zergling";367;0
"Unit";"Baneling";"Zergling";367;0
"Unit";"Hydralisk";"Larva";345;2
"Unit";"Hydralisk";"Larva";345;2
"Unit";"Hydralisk";"Larva";349;2
"Unit";"Hydralisk";"Larva";353;2
"Unit";"Hydralisk";"Larva";353;2
"Unit";"Hydralisk";"Larva";355;2
"Unit";"Zergling";"Larva";355;1
"Unit";"Zergling";"Larva";355;1
"Building";"CreepTumor";NA;367;0
"Unit";"Zergling";"Larva";355;1
"Unit";"Zergling";"Larva";355;1
"Unit";"Zergling";"Larva";355;1
"Unit";"Zergling";"Larva";355;1
"Building";"CreepTumorQueen";NA;367;0
"Building";"CreepTumorQueen";NA;367;0
"Unit";"Zergling";"Larva";367;1
"Unit";"Zergling";"Larva";367;1
"Unit";"Zergling";"Larva";367;1
"Unit";"Zergling";"Larva";367;1
"Unit";"Zergling";"Larva";367;1
"Unit";"Zergling";"Larva";367;1
"Unit";"Zergling";"Larva";367;1
"Unit";"Zergling";"Larva";367;1
"Unit";"Zergling";"Larva";367;1
"Unit";"Zergling";"Larva";367;1
"Unit";"Zergling";"Larva";367;1
"Unit";"Zergling";"Larva";367;1
"Unit";"Zergling";"Larva";367;1
"Unit";"Zergling";"Larva";367;1
"Unit";"Zergling";"Larva";367;1
"Unit";"Zergling";"Larva";367;1
"Unit";"Zergling";"Larva";367;1
"Unit";"Zergling";"Larva";367;1
"Unit";"Zergling";"Larva";367;1
"Unit";"Zergling";"Larva";367;1
"Unit";"Zergling";"Larva";367;1
"Unit";"Zergling";"Larva";367;1
"Unit";"Zergling";"Larva";367;1
"Unit";"Zergling";"Larva";367;1
"Unit";"Zergling";"Larva";367;1
"Unit";"Zergling";"Larva";367;1
"Unit";"Zergling";"Larva";367;1
"Unit";"Zergling";"Larva";367;1
"Building";"CreepTumor";NA;418;0
"Building";"CreepTumor";NA;418;0
"Building";"CreepTumor";NA;418;0
"Building";"CreepTumorQueen";NA;418;0
"Building";"CreepTumorQueen";NA;426;0
"Unit";"Zergling";"Larva";426;1
"Unit";"Zergling";"Larva";426;1
"Unit";"Zergling";"Larva";426;1
"Unit";"Zergling";"Larva";426;1
"Unit";"Zergling";"Larva";426;1
"Unit";"Zergling";"Larva";426;1
"Unit";"Zergling";"Larva";426;1
"Unit";"Zergling";"Larva";426;1
"Unit";"Zergling";"Larva";426;1
"Unit";"Zergling";"Larva";426;1
"Unit";"Zergling";"Larva";426;1
"Unit";"Zergling";"Larva";426;1
"Unit";"Zergling";"Larva";426;1
"Unit";"Zergling";"Larva";426;1
"Unit";"Zergling";"Larva";426;1
"Unit";"Zergling";"Larva";426;1
"Unit";"Zergling";"Larva";426;1
"Unit";"Zergling";"Larva";426;1
"Unit";"Zergling";"Larva";426;1
"Unit";"Zergling";"Larva";426;1
"Unit";"Zergling";"Larva";426;1
"Unit";"Zergling";"Larva";426;1
"Unit";"Zergling";"Larva";426;1
"Unit";"Zergling";"Larva";426;1
"Unit";"Zergling";"Larva";426;1
"Unit";"Zergling";"Larva";426;1
"Unit";"Zergling";"Larva";426;1
"Unit";"Zergling";"Larva";426;1
"Unit";"Zergling";"Larva";426;1
"Unit";"Zergling";"Larva";426;1
"Unit";"Zergling";"Larva";426;1
"Unit";"Zergling";"Larva";426;1
"Unit";"Zergling";"Larva";426;1
"Unit";"Zergling";"Larva";426;1
"Unit";"Zergling";"Larva";426;1
"Unit";"Zergling";"Larva";426;1
"Unit";"Zergling";"Larva";426;1
"Unit";"Zergling";"Larva";426;1
"Unit";"Zergling";"Larva";426;1
"Unit";"Zergling";"Larva";426;1
"Unit";"Zergling";"Larva";426;1
"Unit";"Zergling";"Larva";426;1
"Unit";"Zergling";"Larva";426;1
"Unit";"Zergling";"Larva";426;1
"Unit";"Zergling";"Larva";426;1
"Unit";"Zergling";"Larva";426;1
"Unit";"Zergling";"Larva";426;1
"Unit";"Zergling";"Larva";426;1
"Unit";"Zergling";"Larva";426;1
"Unit";"Zergling";"Larva";426;1
"Unit";"Zergling";"Larva";426;1
"Unit";"Zergling";"Larva";426;1
"Unit";"Zergling";"Larva";426;1
"Unit";"Zergling";"Larva";426;1
"Upgrade";"ZergMissileWeaponsLevel1";"EvolutionChamber";367;0
"Building";"UltraliskCavern";NA;418;0
"Unit";"Zergling";"Larva";480;1
"Unit";"Zergling";"Larva";480;1
"Unit";"Zergling";"Larva";480;1
"Unit";"Zergling";"Larva";480;1
"Unit";"Zergling";"Larva";480;1
"Unit";"Zergling";"Larva";480;1
"Unit";"Zergling";"Larva";480;1
"Unit";"Zergling";"Larva";480;1
"Unit";"Zergling";"Larva";480;1
"Unit";"Zergling";"Larva";480;1
"Unit";"Zergling";"Larva";480;1
"Unit";"Zergling";"Larva";480;1
"Unit";"Zergling";"Larva";480;1
"Unit";"Zergling";"Larva";480;1
"Unit";"Zergling";"Larva";480;1
"Unit";"Zergling";"Larva";480;1
"Unit";"Zergling";"Larva";480;1
"Unit";"Zergling";"Larva";480;1
"Unit";"Zergling";"Larva";480;1
"Unit";"Zergling";"Larva";480;1
"Unit";"Zergling";"Larva";480;1
"Unit";"Zergling";"Larva";480;1
