"type";"unit_name";"on_building";"total_supply";"supply"
"Unit";"Overlord";"Larva";13;0
"Building";"Extractor";NA;17;0
"Unit";"Overlord";"Larva";21;0
"Building";"SpawningPool";NA;19;0
"Building";"Hatchery";NA;17;0
"Unit";"Zergling";"Larva";23;1
"Unit";"Zergling";"Larva";23;1
"Unit";"Zergling";"Larva";23;1
"Unit";"Zergling";"Larva";23;1
"Unit";"Queen";"Hatchery";22;2
"Unit";"Queen";"Hatchery";23;2
"Unit";"Overlord";"Larva";34;0
"Unit";"Queen";"Hatchery";34;2
"Building";"CreepTumorQueen";NA;37;0
"Unit";"Queen";"Hatchery";36;2
"Unit";"Overlord";"Larva";41;0
"Building";"CreepTumorQueen";NA;51;0
"Building";"BanelingNest";NA;39;0
"Building";"Hatchery";NA;34;0
"Building";"CreepTumorQueen";NA;54;0
"Building";"Extractor";NA;51;0
"Building";"CreepTumor";NA;53;0
"Building";"Extractor";NA;51;0
"Unit";"Overlord";"Larva";57;0
"Building";"CreepTumorQueen";NA;58;0
"Unit";"Overlord";"Larva";58;0
"Unit";"Overlord";"Larva";58;0
"Building";"CreepTumor";NA;58;0
"Building";"CreepTumor";NA;61;0
"Building";"CreepTumorQueen";NA;62;0
"Unit";"Zergling";"Larva";62;1
"Unit";"Zergling";"Larva";62;1
"Unit";"Zergling";"Larva";68;1
"Unit";"Zergling";"Larva";68;1
"Unit";"Queen";"Hatchery";58;2
"Unit";"Zergling";"Larva";68;1
"Unit";"Zergling";"Larva";68;1
"Unit";"Zergling";"Larva";68;1
"Unit";"Zergling";"Larva";68;1
"Unit";"Zergling";"Larva";68;1
"Unit";"Zergling";"Larva";68;1
"Unit";"Zergling";"Larva";68;1
"Unit";"Zergling";"Larva";68;1
"Building";"EvolutionChamber";NA;62;0
"Building";"CreepTumorQueen";NA;82;0
"Building";"CreepTumor";NA;82;0
"Unit";"Queen";"Hatchery";68;2
"Unit";"Overlord";"Larva";84;0
"Building";"CreepTumorQueen";NA;89;0
"Building";"CreepTumor";NA;89;0
"Building";"CreepTumor";NA;89;0
"Building";"CreepTumorQueen";NA;89;0
"Unit";"Overlord";"Larva";89;0
"Unit";"Overlord";"Larva";89;0
"Unit";"Overlord";"Larva";89;0
"Unit";"Overlord";"Larva";89;0
"Unit";"Zergling";"Larva";93;1
"Unit";"Zergling";"Larva";93;1
"Unit";"Zergling";"Larva";93;1
"Unit";"Zergling";"Larva";93;1
"Unit";"Zergling";"Larva";93;1
"Unit";"Zergling";"Larva";93;1
"Unit";"Zergling";"Larva";93;1
"Unit";"Zergling";"Larva";93;1
"Unit";"Zergling";"Larva";93;1
"Unit";"Zergling";"Larva";93;1
"Building";"EvolutionChamber";NA;89;0
"Building";"Extractor";NA;93;0
"Building";"CreepTumor";NA;94;0
"Unit";"Overlord";"Larva";94;0
"Unit";"Overlord";"Larva";111;0
"Building";"Hatchery";NA;89;0
"Building";"Extractor";NA;116;0
"Building";"CreepTumorQueen";NA;116;0
"Building";"Extractor";NA;116;0
"Unit";"Baneling";"Zergling";116;0
"Unit";"Baneling";"Zergling";116;0
"Unit";"Baneling";"Zergling";116;0
"Unit";"Baneling";"Zergling";116;0
"Unit";"Baneling";"Zergling";116;0
"Unit";"Baneling";"Zergling";116;0
"Unit";"Baneling";"Zergling";116;0
"Unit";"Baneling";"Zergling";116;0
"Building";"CreepTumor";NA;116;0
"Building";"CreepTumor";NA;117;0
"Unit";"Zergling";"Larva";116;1
"Unit";"Zergling";"Larva";116;1
"Unit";"Zergling";"Larva";116;1
"Unit";"Zergling";"Larva";116;1
"Unit";"Zergling";"Larva";116;1
"Unit";"Zergling";"Larva";116;1
"Building";"CreepTumorQueen";NA;125;0
"Building";"CreepTumor";NA;125;0
"Building";"CreepTumor";NA;125;0
"Building";"CreepTumorQueen";NA;125;0
"Building";"CreepTumorQueen";NA;125;0
"Building";"CreepTumor";NA;125;0
"Building";"Spire";NA;93;0
"Building";"CreepTumorQueen";NA;125;0
"Unit";"Zergling";"Larva";131;1
"Unit";"Zergling";"Larva";131;1
"Unit";"Zergling";"Larva";131;1
"Unit";"Zergling";"Larva";131;1
"Unit";"Zergling";"Larva";131;1
"Unit";"Zergling";"Larva";131;1
"Unit";"Zergling";"Larva";131;1
"Unit";"Zergling";"Larva";131;1
"Unit";"Zergling";"Larva";131;1
"Unit";"Zergling";"Larva";131;1
"Building";"SporeCrawler";NA;131;0
"Building";"SporeCrawler";NA;131;0
"Upgrade";"ZergGroundArmorsLevel1";"EvolutionChamber";94;0
"Unit";"Queen";"Hatchery";125;2
"Unit";"Queen";"Hatchery";125;2
"Building";"CreepTumor";NA;141;0
"Building";"CreepTumor";NA;141;0
"Building";"CreepTumor";NA;141;0
"Building";"CreepTumor";NA;141;0
"Unit";"Mutalisk";"Larva";131;2
"Unit";"Mutalisk";"Larva";131;2
"Unit";"Mutalisk";"Larva";131;2
"Unit";"Mutalisk";"Larva";131;2
"Building";"CreepTumor";NA;141;0
"Building";"CreepTumor";NA;141;0
"Building";"CreepTumor";NA;141;0
"Unit";"Mutalisk";"Larva";141;2
"Unit";"Queen";"Hatchery";131;2
"Building";"CreepTumor";NA;149;0
"Building";"CreepTumorQueen";NA;149;0
"Building";"CreepTumor";NA;149;0
"Unit";"Overlord";"Larva";149;0
"Unit";"Mutalisk";"Larva";143;2
"Unit";"Overlord";"Larva";149;0
"Unit";"Mutalisk";"Larva";145;2
"Unit";"Mutalisk";"Larva";145;2
"Unit";"Mutalisk";"Larva";145;2
"Unit";"Overlord";"Larva";149;0
"Building";"CreepTumor";NA;161;0
"Unit";"Overlord";"Larva";161;0
"Unit";"Overlord";"Larva";161;0
"Unit";"Overlord";"Larva";161;0
"Unit";"Mutalisk";"Larva";169;2
"Unit";"Mutalisk";"Larva";169;2
"Unit";"Mutalisk";"Larva";169;2
"Unit";"Mutalisk";"Larva";169;2
"Upgrade";"ZergMeleeWeaponsLevel1";"EvolutionChamber";131;0
"Unit";"Zergling";"Larva";169;1
"Unit";"Zergling";"Larva";169;1
"Unit";"Zergling";"Larva";169;1
"Unit";"Zergling";"Larva";169;1
"Unit";"Zergling";"Larva";169;1
"Unit";"Zergling";"Larva";169;1
"Unit";"Zergling";"Larva";169;1
"Unit";"Zergling";"Larva";169;1
"Unit";"Zergling";"Larva";169;1
"Unit";"Zergling";"Larva";169;1
"Unit";"Baneling";"Zergling";192;0
"Unit";"Baneling";"Zergling";193;0
"Unit";"Baneling";"Zergling";193;0
"Unit";"Baneling";"Zergling";193;0
"Unit";"Baneling";"Zergling";193;0
"Unit";"Baneling";"Zergling";193;0
"Unit";"Baneling";"Zergling";193;0
"Unit";"Baneling";"Zergling";193;0
"Unit";"Baneling";"Zergling";193;0
"Unit";"Baneling";"Zergling";193;0
"Unit";"Zergling";"Larva";193;1
"Unit";"Zergling";"Larva";193;1
"Unit";"Zergling";"Larva";193;1
"Unit";"Zergling";"Larva";193;1
"Unit";"Zergling";"Larva";193;1
"Unit";"Zergling";"Larva";193;1
"Unit";"Zergling";"Larva";193;1
"Unit";"Zergling";"Larva";193;1
"Unit";"Zergling";"Larva";193;1
"Unit";"Zergling";"Larva";193;1
"Unit";"Zergling";"Larva";193;1
"Unit";"Zergling";"Larva";193;1
"Unit";"Zergling";"Larva";193;1
"Unit";"Zergling";"Larva";193;1
"Unit";"Zergling";"Larva";193;1
"Unit";"Zergling";"Larva";193;1
"Unit";"Zergling";"Larva";193;1
"Unit";"Zergling";"Larva";193;1
"Unit";"Zergling";"Larva";193;1
"Unit";"Zergling";"Larva";193;1
"Unit";"Zergling";"Larva";193;1
"Unit";"Zergling";"Larva";193;1
"Unit";"Zergling";"Larva";193;1
"Unit";"Zergling";"Larva";193;1
"Unit";"Zergling";"Larva";193;1
"Unit";"Zergling";"Larva";193;1
"Unit";"Zergling";"Larva";193;1
"Unit";"Zergling";"Larva";193;1
"Unit";"Zergling";"Larva";193;1
"Unit";"Zergling";"Larva";193;1
"Unit";"Zergling";"Larva";193;1
"Unit";"Zergling";"Larva";193;1
"Unit";"Zergling";"Larva";193;1
"Unit";"Zergling";"Larva";193;1
"Unit";"Zergling";"Larva";193;1
"Unit";"Zergling";"Larva";193;1
"Unit";"Zergling";"Larva";193;1
"Unit";"Zergling";"Larva";193;1
"Unit";"Zergling";"Larva";193;1
"Unit";"Zergling";"Larva";193;1
"Unit";"Zergling";"Larva";193;1
"Unit";"Zergling";"Larva";193;1
"Unit";"Zergling";"Larva";193;1
"Unit";"Zergling";"Larva";193;1
"Unit";"Zergling";"Larva";193;1
"Unit";"Zergling";"Larva";193;1
"Unit";"Zergling";"Larva";193;1
"Unit";"Zergling";"Larva";193;1
"Unit";"Baneling";"Zergling";213;0
"Unit";"Baneling";"Zergling";213;0
"Unit";"Baneling";"Zergling";213;0
"Unit";"Baneling";"Zergling";213;0
"Building";"CreepTumor";NA;213;0
"Building";"CreepTumor";NA;213;0
"Building";"CreepTumor";NA;213;0
"Building";"Hatchery";NA;169;0
"Unit";"Mutalisk";"Larva";215;2
"Unit";"Mutalisk";"Larva";221;2
"Unit";"Mutalisk";"Larva";223;2
"Unit";"Mutalisk";"Larva";223;2
"Unit";"Overlord";"Larva";241;0
"Unit";"Overlord";"Larva";241;0
"Unit";"Overlord";"Larva";241;0
"Building";"CreepTumorQueen";NA;241;0
"Building";"CreepTumor";NA;241;0
"Building";"CreepTumorQueen";NA;249;0
"Unit";"Baneling";"Zergling";241;0
"Unit";"Baneling";"Zergling";241;0
"Unit";"Baneling";"Zergling";241;0
"Unit";"Baneling";"Zergling";241;0
"Unit";"Baneling";"Zergling";241;0
"Building";"CreepTumor";NA;249;0
"Building";"CreepTumor";NA;249;0
"Building";"CreepTumorQueen";NA;249;0
"Building";"CreepTumor";NA;249;0
"Building";"CreepTumorQueen";NA;249;0
"Building";"CreepTumor";NA;249;0
"Building";"CreepTumor";NA;249;0
"Building";"CreepTumor";NA;249;0
"Building";"CreepTumor";NA;249;0
"Building";"CreepTumor";NA;258;0
"Building";"CreepTumorQueen";NA;259;0
"Building";"CreepTumorQueen";NA;259;0
"Building";"CreepTumorQueen";NA;259;0
"Building";"InfestationPit";NA;241;0
"Building";"CreepTumorQueen";NA;259;0
"Building";"Extractor";NA;259;0
"Building";"Extractor";NA;259;0
"Building";"SporeCrawler";NA;259;0
"Building";"Hatchery";NA;227;0
"Unit";"Baneling";"Zergling";270;0
"Unit";"Baneling";"Zergling";270;0
"Unit";"Baneling";"Zergling";270;0
"Unit";"Baneling";"Zergling";270;0
"Unit";"Baneling";"Zergling";270;0
"Unit";"Baneling";"Zergling";270;0
"Unit";"Queen";"Hatchery";259;2
"Building";"SpineCrawler";NA;270;0
"Upgrade";"ZergGroundArmorsLevel2";"EvolutionChamber";213;0
"Unit";"Zergling";"Larva";270;1
"Unit";"Zergling";"Larva";270;1
"Unit";"Zergling";"Larva";270;1
"Unit";"Zergling";"Larva";270;1
"Unit";"Zergling";"Larva";270;1
"Unit";"Zergling";"Larva";270;1
"Unit";"Zergling";"Larva";270;1
"Unit";"Zergling";"Larva";270;1
"Unit";"Zergling";"Larva";270;1
"Unit";"Zergling";"Larva";270;1
"Unit";"Zergling";"Larva";270;1
"Unit";"Zergling";"Larva";270;1
"Unit";"Zergling";"Larva";270;1
"Unit";"Zergling";"Larva";270;1
"Unit";"Zergling";"Larva";270;1
"Unit";"Zergling";"Larva";270;1
"Unit";"Zergling";"Larva";270;1
"Unit";"Zergling";"Larva";270;1
"Unit";"Zergling";"Larva";270;1
"Unit";"Zergling";"Larva";270;1
"Unit";"Zergling";"Larva";270;1
"Unit";"Zergling";"Larva";270;1
"Unit";"Zergling";"Larva";270;1
"Unit";"Zergling";"Larva";270;1
"Unit";"Zergling";"Larva";270;1
"Unit";"Zergling";"Larva";270;1
"Unit";"Zergling";"Larva";270;1
"Unit";"Zergling";"Larva";270;1
"Unit";"Zergling";"Larva";270;1
"Unit";"Zergling";"Larva";270;1
"Unit";"Zergling";"Larva";270;1
"Unit";"Zergling";"Larva";270;1
"Unit";"Zergling";"Larva";270;1
"Unit";"Zergling";"Larva";270;1
"Unit";"Zergling";"Larva";270;1
"Unit";"Zergling";"Larva";270;1
"Unit";"Zergling";"Larva";270;1
"Unit";"Zergling";"Larva";270;1
"Unit";"Zergling";"Larva";270;1
"Unit";"Zergling";"Larva";270;1
"Unit";"Zergling";"Larva";270;1
"Unit";"Zergling";"Larva";270;1
"Unit";"Zergling";"Larva";270;1
"Unit";"Zergling";"Larva";270;1
"Unit";"Zergling";"Larva";272;1
"Unit";"Zergling";"Larva";272;1
"Unit";"Zergling";"Larva";272;1
"Unit";"Zergling";"Larva";272;1
"Unit";"Zergling";"Larva";292;1
"Unit";"Zergling";"Larva";292;1
"Unit";"Zergling";"Larva";298;1
"Unit";"Zergling";"Larva";298;1
"Unit";"Zergling";"Larva";298;1
"Unit";"Zergling";"Larva";298;1
"Unit";"Zergling";"Larva";298;1
"Unit";"Zergling";"Larva";298;1
"Unit";"Zergling";"Larva";298;1
"Unit";"Zergling";"Larva";298;1
"Unit";"Zergling";"Larva";298;1
"Unit";"Zergling";"Larva";298;1
"Unit";"Zergling";"Larva";298;1
"Unit";"Zergling";"Larva";298;1
"Unit";"Zergling";"Larva";298;1
"Unit";"Zergling";"Larva";298;1
"Unit";"Baneling";"Zergling";320;0
"Unit";"Baneling";"Zergling";320;0
"Unit";"Baneling";"Zergling";320;0
"Unit";"Baneling";"Zergling";320;0
"Unit";"Baneling";"Zergling";320;0
"Unit";"Baneling";"Zergling";320;0
"Unit";"Baneling";"Zergling";320;0
"Unit";"Zergling";"Larva";326;1
"Unit";"Zergling";"Larva";326;1
"Building";"CreepTumorQueen";NA;326;0
"Building";"CreepTumorQueen";NA;326;0
"Unit";"Mutalisk";"Larva";326;2
"Unit";"Mutalisk";"Larva";326;2
"Unit";"Mutalisk";"Larva";326;2
"Unit";"Mutalisk";"Larva";326;2
"Unit";"Mutalisk";"Larva";326;2
"Unit";"Mutalisk";"Larva";326;2
"Unit";"Zergling";"Larva";326;1
"Unit";"Zergling";"Larva";326;1
"Unit";"Zergling";"Larva";326;1
"Unit";"Zergling";"Larva";326;1
"Unit";"Zergling";"Larva";326;1
"Unit";"Zergling";"Larva";326;1
"Unit";"Zergling";"Larva";326;1
"Unit";"Zergling";"Larva";326;1
"Unit";"Zergling";"Larva";326;1
"Unit";"Zergling";"Larva";326;1
"Unit";"Zergling";"Larva";326;1
"Unit";"Zergling";"Larva";326;1
"Unit";"Zergling";"Larva";326;1
"Unit";"Zergling";"Larva";326;1
"Unit";"Baneling";"Zergling";338;0
"Unit";"Baneling";"Zergling";338;0
"Unit";"Baneling";"Zergling";338;0
"Unit";"Baneling";"Zergling";338;0
"Unit";"Baneling";"Zergling";338;0
"Unit";"Baneling";"Zergling";338;0
"Unit";"Baneling";"Zergling";338;0
"Unit";"Baneling";"Zergling";338;0
"Unit";"Zergling";"Larva";338;1
"Unit";"Zergling";"Larva";338;1
"Unit";"Zergling";"Larva";338;1
"Unit";"Zergling";"Larva";338;1
"Unit";"Zergling";"Larva";338;1
"Unit";"Zergling";"Larva";338;1
"Unit";"Zergling";"Larva";338;1
"Unit";"Zergling";"Larva";338;1
"Unit";"Zergling";"Larva";338;1
"Unit";"Zergling";"Larva";338;1
"Unit";"Zergling";"Larva";338;1
"Unit";"Zergling";"Larva";338;1
"Unit";"Zergling";"Larva";338;1
"Unit";"Zergling";"Larva";338;1
"Unit";"Zergling";"Larva";338;1
"Unit";"Zergling";"Larva";338;1
"Unit";"Zergling";"Larva";338;1
"Unit";"Zergling";"Larva";338;1
"Unit";"Zergling";"Larva";338;1
"Unit";"Zergling";"Larva";338;1
"Unit";"Zergling";"Larva";338;1
"Unit";"Zergling";"Larva";338;1
"Unit";"Zergling";"Larva";338;1
"Unit";"Zergling";"Larva";338;1
"Unit";"Zergling";"Larva";338;1
"Unit";"Zergling";"Larva";338;1
"Unit";"Zergling";"Larva";364;1
"Unit";"Zergling";"Larva";364;1
"Unit";"Zergling";"Larva";364;1
"Unit";"Zergling";"Larva";364;1
"Unit";"Zergling";"Larva";364;1
"Unit";"Zergling";"Larva";364;1
"Unit";"Zergling";"Larva";364;1
"Unit";"Zergling";"Larva";364;1
"Unit";"Zergling";"Larva";364;1
"Unit";"Zergling";"Larva";364;1
"Unit";"Zergling";"Larva";364;1
"Unit";"Zergling";"Larva";364;1
"Unit";"Zergling";"Larva";364;1
"Unit";"Zergling";"Larva";364;1
"Unit";"Zergling";"Larva";364;1
"Unit";"Zergling";"Larva";364;1
"Unit";"Zergling";"Larva";364;1
"Unit";"Zergling";"Larva";364;1
"Unit";"Zergling";"Larva";364;1
"Unit";"Zergling";"Larva";364;1
"Unit";"Zergling";"Larva";364;1
"Unit";"Zergling";"Larva";364;1
"Unit";"Zergling";"Larva";364;1
"Unit";"Zergling";"Larva";364;1
"Unit";"Zergling";"Larva";364;1
"Unit";"Zergling";"Larva";364;1
"Unit";"Zergling";"Larva";366;1
"Unit";"Zergling";"Larva";366;1
"Unit";"Zergling";"Larva";388;1
"Unit";"Zergling";"Larva";388;1
"Unit";"Zergling";"Larva";392;1
"Unit";"Zergling";"Larva";392;1
"Unit";"Zergling";"Larva";398;1
"Unit";"Zergling";"Larva";398;1
"Unit";"Zergling";"Larva";398;1
"Unit";"Zergling";"Larva";398;1
"Upgrade";"ZergMeleeWeaponsLevel2";"EvolutionChamber";270;0
"Unit";"Mutalisk";"Larva";406;2
"Building";"CreepTumor";NA;426;0
"Unit";"Baneling";"Zergling";426;0
"Unit";"Baneling";"Zergling";426;0
"Unit";"Baneling";"Zergling";426;0
"Unit";"Baneling";"Zergling";426;0
"Unit";"Baneling";"Zergling";426;0
"Unit";"Baneling";"Zergling";426;0
"Building";"CreepTumor";NA;426;0
"Building";"CreepTumor";NA;426;0
"Building";"CreepTumor";NA;426;0
"Unit";"Mutalisk";"Larva";420;2
"Unit";"Mutalisk";"Larva";420;2
"Unit";"Mutalisk";"Larva";420;2
"Unit";"Mutalisk";"Larva";420;2
"Unit";"Mutalisk";"Larva";420;2
"Unit";"Mutalisk";"Larva";420;2
"Unit";"Mutalisk";"Larva";420;2
"Building";"CreepTumor";NA;426;0
"Building";"Hatchery";NA;338;0
"Unit";"Mutalisk";"Larva";426;2
"Unit";"Mutalisk";"Larva";426;2
"Building";"CreepTumor";NA;442;0
"Building";"CreepTumor";NA;442;0
"Building";"CreepTumor";NA;442;0
"Unit";"Zergling";"Larva";442;1
"Unit";"Zergling";"Larva";442;1
"Unit";"Zergling";"Larva";442;1
"Unit";"Zergling";"Larva";442;1
"Unit";"Zergling";"Larva";442;1
"Unit";"Zergling";"Larva";442;1
"Unit";"Zergling";"Larva";442;1
"Unit";"Zergling";"Larva";442;1
"Unit";"Zergling";"Larva";442;1
"Unit";"Zergling";"Larva";442;1
"Unit";"Zergling";"Larva";442;1
"Unit";"Zergling";"Larva";442;1
"Unit";"Zergling";"Larva";446;1
"Unit";"Zergling";"Larva";446;1
"Unit";"Zergling";"Larva";446;1
"Unit";"Zergling";"Larva";446;1
"Unit";"Zergling";"Larva";446;1
"Unit";"Zergling";"Larva";446;1
"Unit";"Zergling";"Larva";446;1
"Unit";"Zergling";"Larva";446;1
"Unit";"Zergling";"Larva";446;1
"Unit";"Zergling";"Larva";446;1
"Unit";"Zergling";"Larva";446;1
"Unit";"Zergling";"Larva";446;1
"Unit";"Zergling";"Larva";446;1
"Unit";"Zergling";"Larva";446;1
"Unit";"Zergling";"Larva";446;1
"Unit";"Zergling";"Larva";446;1
"Unit";"Zergling";"Larva";446;1
"Unit";"Zergling";"Larva";446;1
"Unit";"Zergling";"Larva";446;1
"Unit";"Zergling";"Larva";446;1
"Unit";"Zergling";"Larva";446;1
"Unit";"Zergling";"Larva";446;1
"Unit";"Zergling";"Larva";446;1
"Unit";"Zergling";"Larva";446;1
"Unit";"Zergling";"Larva";446;1
"Unit";"Zergling";"Larva";446;1
"Building";"CreepTumor";NA;484;0
"Building";"CreepTumor";NA;484;0
"Unit";"Mutalisk";"Larva";458;2
"Unit";"Mutalisk";"Larva";458;2
"Unit";"Mutalisk";"Larva";458;2
"Unit";"Mutalisk";"Larva";458;2
"Unit";"Mutalisk";"Larva";458;2
"Unit";"Mutalisk";"Larva";458;2
"Unit";"Mutalisk";"Larva";458;2
"Unit";"Baneling";"Zergling";484;0
"Unit";"Baneling";"Zergling";484;0
"Unit";"Baneling";"Zergling";484;0
"Unit";"Baneling";"Zergling";484;0
"Unit";"Baneling";"Zergling";484;0
"Unit";"Baneling";"Zergling";484;0
"Unit";"Baneling";"Zergling";484;0
"Unit";"Baneling";"Zergling";484;0
"Unit";"Baneling";"Zergling";484;0
"Unit";"Baneling";"Zergling";484;0
"Unit";"Baneling";"Zergling";484;0
"Unit";"Baneling";"Zergling";484;0
"Unit";"Baneling";"Zergling";484;0
"Unit";"Baneling";"Zergling";484;0
"Unit";"Baneling";"Zergling";484;0
"Unit";"Baneling";"Zergling";484;0
"Building";"CreepTumor";NA;501;0
"Building";"Extractor";NA;484;0
"Building";"Extractor";NA;484;0
"Building";"CreepTumor";NA;508;0
"Building";"Hatchery";NA;442;0
"Unit";"Zergling";"Larva";488;1
"Unit";"Zergling";"Larva";488;1
"Unit";"Zergling";"Larva";498;1
"Unit";"Zergling";"Larva";498;1
"Unit";"Zergling";"Larva";511;1
"Unit";"Zergling";"Larva";511;1
"Unit";"Zergling";"Larva";511;1
"Unit";"Zergling";"Larva";511;1
"Unit";"Zergling";"Larva";511;1
"Unit";"Zergling";"Larva";511;1
"Unit";"Overlord";"Larva";511;0
"Unit";"Overlord";"Larva";511;0
"Unit";"Overlord";"Larva";511;0
"Unit";"Zergling";"Larva";521;1
"Unit";"Zergling";"Larva";521;1
"Unit";"Zergling";"Larva";521;1
"Unit";"Zergling";"Larva";521;1
"Unit";"Zergling";"Larva";521;1
"Unit";"Zergling";"Larva";521;1
"Unit";"Zergling";"Larva";521;1
"Unit";"Zergling";"Larva";521;1
"Unit";"Zergling";"Larva";521;1
"Unit";"Zergling";"Larva";521;1
"Unit";"Zergling";"Larva";521;1
"Unit";"Zergling";"Larva";521;1
"Unit";"Zergling";"Larva";521;1
"Unit";"Zergling";"Larva";521;1
"Unit";"Zergling";"Larva";521;1
"Unit";"Zergling";"Larva";521;1
"Unit";"Zergling";"Larva";521;1
"Unit";"Zergling";"Larva";521;1
"Unit";"Zergling";"Larva";521;1
"Unit";"Zergling";"Larva";521;1
"Unit";"Zergling";"Larva";521;1
"Unit";"Zergling";"Larva";521;1
"Unit";"Zergling";"Larva";521;1
"Unit";"Zergling";"Larva";521;1
"Unit";"Zergling";"Larva";521;1
"Unit";"Zergling";"Larva";521;1
"Unit";"Zergling";"Larva";521;1
"Unit";"Zergling";"Larva";521;1
"Unit";"Zergling";"Larva";521;1
"Unit";"Zergling";"Larva";521;1
"Unit";"Zergling";"Larva";521;1
"Unit";"Zergling";"Larva";521;1
"Unit";"Zergling";"Larva";521;1
"Unit";"Zergling";"Larva";521;1
"Unit";"Zergling";"Larva";521;1
"Unit";"Zergling";"Larva";521;1
"Unit";"Zergling";"Larva";521;1
"Unit";"Zergling";"Larva";521;1
"Unit";"Zergling";"Larva";521;1
"Unit";"Zergling";"Larva";521;1
"Unit";"Zergling";"Larva";521;1
"Unit";"Zergling";"Larva";521;1
"Unit";"Baneling";"Zergling";551;0
"Building";"CreepTumor";NA;563;0
"Building";"CreepTumor";NA;565;0
"Unit";"Zergling";"Larva";563;1
"Unit";"Zergling";"Larva";563;1
"Building";"UltraliskCavern";NA;521;0
"Unit";"Zergling";"Larva";563;1
"Unit";"Zergling";"Larva";563;1
"Unit";"Zergling";"Larva";563;1
"Unit";"Zergling";"Larva";563;1
"Unit";"Zergling";"Larva";563;1
"Unit";"Zergling";"Larva";563;1
"Unit";"Zergling";"Larva";563;1
"Unit";"Zergling";"Larva";563;1
"Unit";"Zergling";"Larva";563;1
"Unit";"Zergling";"Larva";563;1
"Unit";"Zergling";"Larva";563;1
"Unit";"Zergling";"Larva";563;1
"Unit";"Zergling";"Larva";563;1
"Unit";"Zergling";"Larva";563;1
"Unit";"Zergling";"Larva";563;1
"Unit";"Zergling";"Larva";563;1
"Unit";"Zergling";"Larva";563;1
"Unit";"Zergling";"Larva";563;1
"Unit";"Baneling";"Zergling";573;0
"Unit";"Baneling";"Zergling";573;0
"Unit";"Baneling";"Zergling";573;0
"Unit";"Baneling";"Zergling";573;0
"Unit";"Baneling";"Zergling";573;0
"Unit";"Baneling";"Zergling";573;0
"Unit";"Baneling";"Zergling";573;0
"Unit";"Baneling";"Zergling";593;0
"Unit";"Baneling";"Zergling";593;0
"Unit";"Baneling";"Zergling";593;0
"Unit";"Baneling";"Zergling";593;0
"Unit";"Baneling";"Zergling";593;0
"Unit";"Baneling";"Zergling";593;0
"Unit";"Baneling";"Zergling";593;0
"Unit";"Baneling";"Zergling";593;0
"Unit";"Baneling";"Zergling";593;0
"Unit";"Baneling";"Zergling";593;0
"Unit";"Baneling";"Zergling";593;0
"Unit";"Baneling";"Zergling";593;0
"Unit";"Baneling";"Zergling";593;0
"Unit";"Baneling";"Zergling";593;0
"Unit";"Baneling";"Zergling";593;0
"Unit";"Baneling";"Zergling";593;0
"Unit";"Zergling";"Larva";593;1
"Unit";"Zergling";"Larva";593;1
"Unit";"Zergling";"Larva";593;1
"Unit";"Zergling";"Larva";593;1
"Unit";"Zergling";"Larva";593;1
"Unit";"Zergling";"Larva";593;1
"Unit";"Zergling";"Larva";593;1
"Unit";"Zergling";"Larva";593;1
"Unit";"Zergling";"Larva";593;1
"Unit";"Zergling";"Larva";593;1
"Unit";"Zergling";"Larva";593;1
"Unit";"Zergling";"Larva";593;1
"Unit";"Zergling";"Larva";593;1
"Unit";"Zergling";"Larva";593;1
"Unit";"Zergling";"Larva";593;1
"Unit";"Zergling";"Larva";593;1
"Unit";"Zergling";"Larva";593;1
"Unit";"Zergling";"Larva";593;1
"Building";"SpineCrawler";NA;573;0
"Building";"SpineCrawler";NA;573;0
"Unit";"Zergling";"Larva";593;1
"Unit";"Zergling";"Larva";593;1
"Unit";"Zergling";"Larva";593;1
"Unit";"Zergling";"Larva";593;1
"Unit";"Zergling";"Larva";593;1
"Unit";"Zergling";"Larva";593;1
"Unit";"Zergling";"Larva";593;1
"Unit";"Zergling";"Larva";593;1
"Unit";"Zergling";"Larva";593;1
"Unit";"Zergling";"Larva";593;1
"Unit";"Zergling";"Larva";593;1
"Unit";"Zergling";"Larva";593;1
"Unit";"Zergling";"Larva";593;1
"Unit";"Zergling";"Larva";593;1
"Unit";"Zergling";"Larva";593;1
"Unit";"Zergling";"Larva";593;1
"Unit";"Zergling";"Larva";593;1
"Unit";"Zergling";"Larva";593;1
"Unit";"Zergling";"Larva";593;1
"Unit";"Zergling";"Larva";593;1
"Unit";"Zergling";"Larva";593;1
"Unit";"Zergling";"Larva";593;1
"Building";"Hatchery";NA;551;0
"Unit";"Zergling";"Larva";615;1
"Unit";"Zergling";"Larva";615;1
"Unit";"Zergling";"Larva";629;1
"Unit";"Zergling";"Larva";629;1
"Unit";"Zergling";"Larva";629;1
"Unit";"Zergling";"Larva";629;1
"Unit";"Zergling";"Larva";633;1
"Unit";"Zergling";"Larva";633;1
"Unit";"Zergling";"Larva";633;1
"Unit";"Zergling";"Larva";633;1
"Unit";"Zergling";"Larva";633;1
"Unit";"Zergling";"Larva";633;1
"Unit";"Zergling";"Larva";633;1
"Unit";"Zergling";"Larva";633;1
"Unit";"Zergling";"Larva";633;1
"Unit";"Zergling";"Larva";633;1
"Unit";"Zergling";"Larva";633;1
"Unit";"Zergling";"Larva";633;1
"Unit";"Zergling";"Larva";633;1
"Unit";"Zergling";"Larva";633;1
"Unit";"Zergling";"Larva";633;1
"Unit";"Zergling";"Larva";633;1
"Unit";"Zergling";"Larva";633;1
"Unit";"Zergling";"Larva";633;1
"Building";"Extractor";NA;633;0
"Unit";"Baneling";"Zergling";633;0
"Unit";"Baneling";"Zergling";633;0
"Unit";"Baneling";"Zergling";633;0
"Unit";"Baneling";"Zergling";635;0
"Unit";"Baneling";"Zergling";635;0
"Unit";"Baneling";"Zergling";635;0
"Unit";"Baneling";"Zergling";635;0
"Unit";"Baneling";"Zergling";635;0
"Unit";"Baneling";"Zergling";635;0
"Unit";"Baneling";"Zergling";635;0
"Unit";"Baneling";"Zergling";635;0
"Unit";"Baneling";"Zergling";639;0
"Unit";"Baneling";"Zergling";639;0
"Unit";"Baneling";"Zergling";643;0
"Unit";"Baneling";"Zergling";647;0
"Unit";"Baneling";"Zergling";647;0
"Unit";"Baneling";"Zergling";651;0
"Building";"CreepTumor";NA;657;0
"Building";"CreepTumor";NA;660;0
"Unit";"Zergling";"Larva";657;1
"Unit";"Zergling";"Larva";657;1
"Unit";"Zergling";"Larva";657;1
"Unit";"Zergling";"Larva";657;1
"Unit";"Zergling";"Larva";657;1
"Unit";"Zergling";"Larva";657;1
"Building";"CreepTumor";NA;660;0
"Unit";"Zergling";"Larva";657;1
"Unit";"Zergling";"Larva";657;1
"Building";"CreepTumor";NA;660;0
"Building";"CreepTumor";NA;660;0
"Building";"CreepTumor";NA;660;0
"Building";"CreepTumor";NA;660;0
"Building";"CreepTumorQueen";NA;668;0
"Building";"CreepTumorQueen";NA;668;0
"Building";"CreepTumorQueen";NA;668;0
"Building";"CreepTumorQueen";NA;668;0
"Unit";"Baneling";"Zergling";668;0
"Unit";"Baneling";"Zergling";668;0
"Building";"CreepTumorQueen";NA;668;0
"Unit";"Baneling";"Zergling";668;0
"Unit";"Baneling";"Zergling";668;0
"Unit";"Baneling";"Zergling";668;0
"Unit";"Baneling";"Zergling";668;0
"Unit";"Baneling";"Zergling";668;0
"Unit";"Baneling";"Zergling";668;0
"Unit";"Baneling";"Zergling";668;0
"Unit";"Baneling";"Zergling";668;0
"Unit";"Baneling";"Zergling";668;0
"Unit";"Baneling";"Zergling";668;0
"Unit";"Baneling";"Zergling";668;0
"Unit";"Baneling";"Zergling";668;0
"Unit";"Baneling";"Zergling";668;0
"Unit";"Baneling";"Zergling";668;0
"Unit";"Baneling";"Zergling";668;0
"Unit";"Baneling";"Zergling";668;0
"Unit";"Baneling";"Zergling";668;0
"Unit";"Baneling";"Zergling";668;0
"Unit";"Baneling";"Zergling";668;0
"Unit";"Baneling";"Zergling";668;0
"Building";"CreepTumorQueen";NA;668;0
"Unit";"Queen";"Hatchery";660;2
