"type";"unit_name";"on_building";"total_supply";"supply"
"Unit";"Overlord";"Larva";13;0
"Building";"Extractor";NA;18;0
"Building";"SpawningPool";NA;19;0
"Building";"Hatchery";NA;17;0
"Unit";"Overlord";"Larva";22;0
"Unit";"Zergling";"Larva";22;1
"Unit";"Zergling";"Larva";22;1
"Unit";"Zergling";"Larva";22;1
"Unit";"Zergling";"Larva";22;1
"Unit";"Zergling";"Larva";22;1
"Unit";"Zergling";"Larva";22;1
"Unit";"Queen";"Hatchery";22;2
"Unit";"Queen";"Hatchery";22;2
"Unit";"Overlord";"Larva";37;0
"Unit";"Queen";"Hatchery";30;2
"Building";"CreepTumorQueen";NA;39;0
"Unit";"Overlord";"Larva";42;0
"Building";"CreepTumor";NA;50;0
"Building";"CreepTumorQueen";NA;50;0
"Unit";"Overlord";"Larva";50;0
"Unit";"Queen";"Hatchery";50;2
"Building";"CreepTumorQueen";NA;57;0
"Building";"CreepTumor";NA;57;0
"Building";"CreepTumor";NA;57;0
"Unit";"Queen";"Hatchery";50;2
"Unit";"Zergling";"Larva";57;1
"Unit";"Zergling";"Larva";57;1
"Unit";"Zergling";"Larva";57;1
"Unit";"Zergling";"Larva";57;1
"Unit";"Zergling";"Larva";57;1
"Unit";"Zergling";"Larva";57;1
"Building";"Hatchery";NA;50;0
"Building";"Extractor";NA;57;0
"Unit";"Overlord";"Larva";57;0
"Building";"BanelingNest";NA;50;0
"Building";"SporeCrawler";NA;57;0
"Unit";"Queen";"Hatchery";57;2
"Building";"CreepTumor";NA;68;0
"Building";"CreepTumor";NA;68;0
"Unit";"Baneling";"Zergling";68;0
"Unit";"Baneling";"Zergling";68;0
"Unit";"Queen";"Hatchery";57;2
"Building";"EvolutionChamber";NA;66;0
"Building";"EvolutionChamber";NA;66;0
"Building";"CreepTumorQueen";NA;71;0
"Building";"CreepTumorQueen";NA;73;0
"Building";"CreepTumor";NA;73;0
"Building";"CreepTumorQueen";NA;73;0
"Building";"CreepTumorQueen";NA;80;0
"Building";"CreepTumorQueen";NA;80;0
"Unit";"Overlord";"Larva";80;0
"Unit";"Overlord";"Larva";80;0
"Building";"CreepTumor";NA;91;0
"Building";"CreepTumor";NA;91;0
"Building";"CreepTumor";NA;91;0
"Building";"Extractor";NA;91;0
"Building";"Extractor";NA;91;0
"Unit";"Overlord";"Larva";91;0
"Unit";"Queen";"Hatchery";91;2
"Unit";"Zergling";"Larva";91;1
"Unit";"Zergling";"Larva";91;1
"Unit";"Zergling";"Larva";91;1
"Unit";"Zergling";"Larva";91;1
"Unit";"Zergling";"Larva";91;1
"Unit";"Zergling";"Larva";91;1
"Unit";"Zergling";"Larva";91;1
"Unit";"Zergling";"Larva";91;1
"Unit";"Zergling";"Larva";91;1
"Unit";"Zergling";"Larva";91;1
"Building";"CreepTumorQueen";NA;91;0
"Building";"CreepTumorQueen";NA;91;0
"Building";"CreepTumorQueen";NA;93;0
"Building";"CreepTumorQueen";NA;93;0
"Building";"CreepTumor";NA;93;0
"Building";"CreepTumor";NA;93;0
"Building";"CreepTumor";NA;93;0
"Building";"CreepTumor";NA;93;0
"Building";"CreepTumor";NA;93;0
"Building";"CreepTumor";NA;93;0
"Building";"CreepTumorQueen";NA;114;0
"Unit";"Zergling";"Larva";114;1
"Unit";"Zergling";"Larva";114;1
"Unit";"Zergling";"Larva";114;1
"Unit";"Zergling";"Larva";114;1
"Unit";"Zergling";"Larva";114;1
"Unit";"Zergling";"Larva";114;1
"Unit";"Zergling";"Larva";114;1
"Unit";"Zergling";"Larva";114;1
"Unit";"Zergling";"Larva";114;1
"Unit";"Zergling";"Larva";114;1
"Unit";"Overlord";"Larva";114;0
"Unit";"Overlord";"Larva";114;0
"Unit";"Overlord";"Larva";114;0
"Unit";"Overlord";"Larva";114;0
"Building";"InfestationPit";NA;93;0
"Unit";"Zergling";"Larva";114;1
"Unit";"Zergling";"Larva";114;1
"Unit";"Zergling";"Larva";114;1
"Unit";"Zergling";"Larva";114;1
"Building";"SporeCrawler";NA;114;0
"Unit";"Baneling";"Zergling";124;0
"Unit";"Baneling";"Zergling";124;0
"Unit";"Baneling";"Zergling";124;0
"Unit";"Baneling";"Zergling";124;0
"Building";"CreepTumor";NA;124;0
"Building";"CreepTumor";NA;124;0
"Building";"CreepTumor";NA;124;0
"Building";"CreepTumor";NA;124;0
"Building";"CreepTumor";NA;124;0
"Building";"CreepTumor";NA;124;0
"Building";"CreepTumorQueen";NA;128;0
"Building";"CreepTumorQueen";NA;128;0
"Building";"CreepTumor";NA;126;0
"Building";"CreepTumor";NA;126;0
"Building";"CreepTumor";NA;128;0
"Building";"CreepTumor";NA;128;0
"Building";"CreepTumor";NA;128;0
"Upgrade";"ZergMeleeWeaponsLevel1";"EvolutionChamber";91;0
"Upgrade";"ZergGroundArmorsLevel1";"EvolutionChamber";91;0
"Building";"CreepTumorQueen";NA;128;0
"Unit";"Zergling";"Larva";128;1
"Unit";"Zergling";"Larva";128;1
"Unit";"Zergling";"Larva";128;1
"Unit";"Zergling";"Larva";128;1
"Unit";"Zergling";"Larva";128;1
"Unit";"Zergling";"Larva";128;1
"Unit";"Zergling";"Larva";128;1
"Unit";"Zergling";"Larva";128;1
"Unit";"Zergling";"Larva";128;1
"Unit";"Zergling";"Larva";128;1
"Unit";"Zergling";"Larva";128;1
"Unit";"Zergling";"Larva";128;1
"Unit";"Zergling";"Larva";128;1
"Unit";"Zergling";"Larva";128;1
"Unit";"Zergling";"Larva";128;1
"Unit";"Zergling";"Larva";128;1
"Unit";"Zergling";"Larva";128;1
"Unit";"Zergling";"Larva";128;1
"Unit";"Zergling";"Larva";128;1
"Unit";"Zergling";"Larva";128;1
"Unit";"Zergling";"Larva";128;1
"Unit";"Zergling";"Larva";128;1
"Building";"SporeCrawler";NA;128;0
"Building";"SporeCrawler";NA;128;0
"Building";"CreepTumorQueen";NA;131;0
"Building";"CreepTumorQueen";NA;131;0
"Building";"Hatchery";NA;114;0
"Building";"CreepTumor";NA;153;0
"Building";"CreepTumor";NA;153;0
"Building";"CreepTumor";NA;153;0
"Building";"CreepTumor";NA;153;0
"Building";"Hatchery";NA;114;0
"Unit";"Zergling";"Larva";163;1
"Unit";"Zergling";"Larva";163;1
"Unit";"Zergling";"Larva";163;1
"Unit";"Zergling";"Larva";163;1
"Unit";"Zergling";"Larva";163;1
"Unit";"Zergling";"Larva";163;1
"Unit";"Zergling";"Larva";163;1
"Unit";"Zergling";"Larva";163;1
"Unit";"Zergling";"Larva";163;1
"Unit";"Zergling";"Larva";163;1
"Unit";"Zergling";"Larva";163;1
"Unit";"Zergling";"Larva";163;1
"Unit";"Zergling";"Larva";163;1
"Unit";"Zergling";"Larva";163;1
"Unit";"Zergling";"Larva";163;1
"Unit";"Zergling";"Larva";163;1
"Unit";"Zergling";"Larva";163;1
"Unit";"Zergling";"Larva";163;1
"Unit";"Zergling";"Larva";163;1
"Unit";"Zergling";"Larva";163;1
"Unit";"Zergling";"Larva";163;1
"Unit";"Zergling";"Larva";163;1
"Unit";"Zergling";"Larva";163;1
"Unit";"Zergling";"Larva";163;1
"Unit";"Zergling";"Larva";163;1
"Unit";"Zergling";"Larva";163;1
"Unit";"Zergling";"Larva";163;1
"Unit";"Zergling";"Larva";163;1
"Unit";"Baneling";"Zergling";163;0
"Unit";"Baneling";"Zergling";163;0
"Unit";"Baneling";"Zergling";163;0
"Unit";"Baneling";"Zergling";163;0
"Unit";"Baneling";"Zergling";163;0
"Unit";"Baneling";"Zergling";163;0
"Unit";"Baneling";"Zergling";163;0
"Unit";"Baneling";"Zergling";163;0
"Unit";"Baneling";"Zergling";163;0
"Unit";"Baneling";"Zergling";163;0
"Unit";"Baneling";"Zergling";163;0
"Unit";"Baneling";"Zergling";163;0
"Unit";"Baneling";"Zergling";163;0
"Unit";"Baneling";"Zergling";163;0
"Unit";"Baneling";"Zergling";163;0
"Unit";"Zergling";"Larva";163;1
"Unit";"Zergling";"Larva";163;1
"Unit";"Zergling";"Larva";163;1
"Unit";"Zergling";"Larva";163;1
"Building";"CreepTumor";NA;163;0
"Building";"CreepTumor";NA;163;0
"Unit";"Zergling";"Larva";163;1
"Unit";"Zergling";"Larva";163;1
"Unit";"Zergling";"Larva";191;1
"Unit";"Zergling";"Larva";191;1
"Unit";"Zergling";"Larva";191;1
"Unit";"Zergling";"Larva";191;1
"Unit";"Zergling";"Larva";191;1
"Unit";"Zergling";"Larva";191;1
"Unit";"Zergling";"Larva";191;1
"Unit";"Zergling";"Larva";191;1
"Unit";"Zergling";"Larva";191;1
"Unit";"Zergling";"Larva";191;1
"Unit";"Zergling";"Larva";191;1
"Unit";"Zergling";"Larva";191;1
"Unit";"Zergling";"Larva";191;1
"Unit";"Zergling";"Larva";191;1
"Unit";"Zergling";"Larva";191;1
"Unit";"Zergling";"Larva";191;1
"Building";"CreepTumorQueen";NA;197;0
"Building";"CreepTumorQueen";NA;197;0
"Unit";"Zergling";"Larva";197;1
"Unit";"Zergling";"Larva";197;1
"Unit";"Zergling";"Larva";197;1
"Unit";"Zergling";"Larva";197;1
"Unit";"Zergling";"Larva";197;1
"Unit";"Zergling";"Larva";197;1
"Unit";"Zergling";"Larva";213;1
"Unit";"Zergling";"Larva";213;1
"Unit";"Baneling";"Zergling";213;0
"Unit";"Baneling";"Zergling";213;0
"Unit";"Zergling";"Larva";213;1
"Unit";"Zergling";"Larva";213;1
"Unit";"Baneling";"Zergling";213;0
"Unit";"Baneling";"Zergling";213;0
"Unit";"Baneling";"Zergling";213;0
"Unit";"Baneling";"Zergling";213;0
"Unit";"Zergling";"Larva";213;1
"Unit";"Zergling";"Larva";213;1
"Unit";"Zergling";"Larva";213;1
"Unit";"Zergling";"Larva";213;1
"Unit";"Zergling";"Larva";213;1
"Unit";"Zergling";"Larva";213;1
"Unit";"Zergling";"Larva";213;1
"Unit";"Zergling";"Larva";213;1
"Unit";"Baneling";"Zergling";213;0
"Unit";"Zergling";"Larva";219;1
"Unit";"Zergling";"Larva";219;1
"Unit";"Zergling";"Larva";219;1
"Unit";"Zergling";"Larva";219;1
"Unit";"Zergling";"Larva";219;1
"Unit";"Zergling";"Larva";219;1
"Unit";"Zergling";"Larva";219;1
"Unit";"Zergling";"Larva";219;1
"Unit";"Zergling";"Larva";219;1
"Unit";"Zergling";"Larva";219;1
"Unit";"Zergling";"Larva";219;1
"Unit";"Zergling";"Larva";219;1
"Unit";"Zergling";"Larva";219;1
"Unit";"Zergling";"Larva";219;1
"Unit";"Zergling";"Larva";219;1
"Unit";"Zergling";"Larva";219;1
"Unit";"Queen";"Hatchery";197;2
"Unit";"Queen";"Hatchery";213;2
"Building";"Extractor";NA;231;0
"Building";"Extractor";NA;231;0
"Building";"Extractor";NA;231;0
"Building";"CreepTumor";NA;253;0
"Building";"CreepTumor";NA;253;0
"Building";"SporeCrawler";NA;231;0
"Building";"CreepTumorQueen";NA;253;0
"Building";"CreepTumorQueen";NA;253;0
"Unit";"Zergling";"Larva";253;1
"Unit";"Zergling";"Larva";253;1
"Unit";"Zergling";"Larva";253;1
"Unit";"Zergling";"Larva";253;1
"Unit";"Zergling";"Larva";253;1
"Unit";"Zergling";"Larva";253;1
"Unit";"Zergling";"Larva";253;1
"Unit";"Zergling";"Larva";253;1
"Unit";"Zergling";"Larva";253;1
"Unit";"Zergling";"Larva";253;1
"Unit";"Zergling";"Larva";253;1
"Unit";"Zergling";"Larva";253;1
"Unit";"Zergling";"Larva";253;1
"Unit";"Zergling";"Larva";253;1
"Unit";"Zergling";"Larva";253;1
"Unit";"Zergling";"Larva";253;1
"Unit";"Zergling";"Larva";253;1
"Unit";"Zergling";"Larva";253;1
"Unit";"Zergling";"Larva";253;1
"Unit";"Zergling";"Larva";253;1
"Unit";"Zergling";"Larva";253;1
"Unit";"Zergling";"Larva";253;1
"Unit";"Zergling";"Larva";253;1
"Unit";"Zergling";"Larva";253;1
"Unit";"Zergling";"Larva";253;1
"Unit";"Zergling";"Larva";253;1
"Unit";"Zergling";"Larva";253;1
"Unit";"Zergling";"Larva";253;1
"Unit";"Zergling";"Larva";253;1
"Unit";"Zergling";"Larva";253;1
"Building";"CreepTumor";NA;255;0
"Upgrade";"ZergMeleeWeaponsLevel2";"EvolutionChamber";163;0
"Building";"CreepTumor";NA;257;0
"Upgrade";"ZergGroundArmorsLevel2";"EvolutionChamber";163;0
"Building";"CreepTumorQueen";NA;285;0
"Building";"UltraliskCavern";NA;231;0
"Building";"CreepTumor";NA;285;0
"Unit";"Baneling";"Zergling";291;0
"Unit";"Baneling";"Zergling";291;0
"Unit";"Zergling";"Larva";291;1
"Unit";"Zergling";"Larva";291;1
"Unit";"Baneling";"Zergling";291;0
"Unit";"Baneling";"Zergling";291;0
"Unit";"Baneling";"Zergling";291;0
"Unit";"Baneling";"Zergling";291;0
"Unit";"Baneling";"Zergling";291;0
"Unit";"Baneling";"Zergling";291;0
"Unit";"Baneling";"Zergling";291;0
"Unit";"Zergling";"Larva";291;1
"Unit";"Zergling";"Larva";291;1
"Unit";"Zergling";"Larva";291;1
"Unit";"Zergling";"Larva";291;1
"Unit";"Zergling";"Larva";291;1
"Unit";"Zergling";"Larva";291;1
"Unit";"Zergling";"Larva";291;1
"Unit";"Zergling";"Larva";291;1
"Unit";"Zergling";"Larva";291;1
"Unit";"Zergling";"Larva";291;1
"Unit";"Zergling";"Larva";291;1
"Unit";"Zergling";"Larva";291;1
"Unit";"Zergling";"Larva";291;1
"Unit";"Zergling";"Larva";291;1
"Unit";"Zergling";"Larva";291;1
"Unit";"Zergling";"Larva";291;1
"Building";"CreepTumor";NA;291;0
"Building";"CreepTumor";NA;291;0
"Building";"CreepTumor";NA;291;0
"Unit";"Zergling";"Larva";291;1
"Unit";"Zergling";"Larva";291;1
"Unit";"Zergling";"Larva";291;1
"Unit";"Zergling";"Larva";291;1
"Unit";"Zergling";"Larva";291;1
"Unit";"Zergling";"Larva";291;1
"Unit";"Zergling";"Larva";291;1
"Unit";"Zergling";"Larva";291;1
"Unit";"Zergling";"Larva";291;1
"Unit";"Zergling";"Larva";291;1
"Unit";"Zergling";"Larva";291;1
"Unit";"Zergling";"Larva";291;1
"Unit";"Zergling";"Larva";291;1
"Unit";"Zergling";"Larva";291;1
"Unit";"Zergling";"Larva";291;1
"Unit";"Zergling";"Larva";291;1
"Unit";"Zergling";"Larva";291;1
"Unit";"Zergling";"Larva";291;1
"Unit";"Zergling";"Larva";291;1
"Unit";"Zergling";"Larva";291;1
"Unit";"Zergling";"Larva";291;1
"Unit";"Zergling";"Larva";291;1
"Unit";"Zergling";"Larva";291;1
"Unit";"Zergling";"Larva";291;1
"Unit";"Zergling";"Larva";291;1
"Unit";"Zergling";"Larva";291;1
"Unit";"Zergling";"Larva";309;1
"Unit";"Zergling";"Larva";309;1
"Unit";"Zergling";"Larva";309;1
"Unit";"Zergling";"Larva";309;1
"Unit";"Zergling";"Larva";309;1
"Unit";"Zergling";"Larva";309;1
"Unit";"Zergling";"Larva";309;1
"Unit";"Zergling";"Larva";309;1
"Unit";"Zergling";"Larva";309;1
"Unit";"Zergling";"Larva";309;1
"Unit";"Zergling";"Larva";309;1
"Unit";"Zergling";"Larva";309;1
"Unit";"Zergling";"Larva";309;1
"Unit";"Zergling";"Larva";309;1
"Unit";"Zergling";"Larva";309;1
"Unit";"Zergling";"Larva";309;1
"Unit";"Overlord";"Larva";331;0
"Unit";"Overlord";"Larva";331;0
"Unit";"Overlord";"Larva";331;0
"Unit";"Overlord";"Larva";331;0
"Building";"Hatchery";NA;255;0
"Unit";"Zergling";"Larva";335;1
"Unit";"Zergling";"Larva";335;1
"Unit";"Zergling";"Larva";335;1
"Unit";"Zergling";"Larva";335;1
"Unit";"Zergling";"Larva";335;1
"Unit";"Zergling";"Larva";335;1
"Unit";"Zergling";"Larva";335;1
"Unit";"Zergling";"Larva";335;1
"Unit";"Zergling";"Larva";335;1
"Unit";"Zergling";"Larva";335;1
"Unit";"Zergling";"Larva";335;1
"Unit";"Zergling";"Larva";335;1
"Unit";"Zergling";"Larva";335;1
"Unit";"Zergling";"Larva";335;1
"Unit";"Zergling";"Larva";335;1
"Unit";"Zergling";"Larva";335;1
"Unit";"Zergling";"Larva";335;1
"Unit";"Zergling";"Larva";335;1
"Unit";"Zergling";"Larva";335;1
"Unit";"Zergling";"Larva";335;1
"Unit";"Zergling";"Larva";335;1
"Unit";"Zergling";"Larva";335;1
"Unit";"Zergling";"Larva";335;1
"Unit";"Zergling";"Larva";335;1
"Unit";"Zergling";"Larva";335;1
"Unit";"Zergling";"Larva";335;1
"Unit";"Zergling";"Larva";335;1
"Unit";"Zergling";"Larva";335;1
"Unit";"Zergling";"Larva";351;1
"Unit";"Zergling";"Larva";351;1
"Building";"CreepTumor";NA;371;0
"Building";"CreepTumor";NA;371;0
"Building";"CreepTumor";NA;371;0
"Building";"CreepTumor";NA;371;0
"Unit";"Baneling";"Zergling";379;0
"Unit";"Baneling";"Zergling";379;0
"Unit";"Baneling";"Zergling";379;0
"Unit";"Baneling";"Zergling";379;0
"Unit";"Baneling";"Zergling";379;0
"Unit";"Baneling";"Zergling";379;0
"Unit";"Baneling";"Zergling";379;0
"Unit";"Baneling";"Zergling";379;0
"Unit";"Baneling";"Zergling";379;0
"Unit";"Baneling";"Zergling";379;0
"Unit";"Baneling";"Zergling";379;0
"Building";"CreepTumor";NA;381;0
"Building";"CreepTumor";NA;381;0
"Building";"CreepTumor";NA;381;0
"Building";"CreepTumor";NA;381;0
"Building";"CreepTumor";NA;381;0
"Building";"CreepTumor";NA;381;0
"Building";"CreepTumor";NA;381;0
"Building";"CreepTumor";NA;381;0
"Building";"CreepTumor";NA;381;0
"Building";"CreepTumor";NA;381;0
"Building";"CreepTumor";NA;381;0
"Building";"CreepTumor";NA;381;0
"Unit";"Ultralisk";"Larva";351;6
"Unit";"Ultralisk";"Larva";351;6
"Unit";"Ultralisk";"Larva";351;6
"Unit";"Zergling";"Larva";381;1
"Unit";"Zergling";"Larva";381;1
"Unit";"Zergling";"Larva";381;1
"Unit";"Zergling";"Larva";381;1
"Building";"CreepTumor";NA;381;0
"Unit";"Zergling";"Larva";381;1
"Unit";"Zergling";"Larva";381;1
"Building";"CreepTumor";NA;381;0
"Building";"CreepTumor";NA;381;0
"Unit";"Zergling";"Larva";381;1
"Unit";"Zergling";"Larva";381;1
"Unit";"Zergling";"Larva";381;1
"Unit";"Zergling";"Larva";381;1
"Unit";"Zergling";"Larva";381;1
"Unit";"Zergling";"Larva";381;1
"Unit";"Zergling";"Larva";381;1
"Unit";"Zergling";"Larva";381;1
"Unit";"Zergling";"Larva";381;1
"Unit";"Zergling";"Larva";381;1
"Unit";"Zergling";"Larva";381;1
"Unit";"Zergling";"Larva";381;1
"Unit";"Zergling";"Larva";381;1
"Unit";"Zergling";"Larva";381;1
"Unit";"Zergling";"Larva";381;1
"Unit";"Zergling";"Larva";381;1
"Building";"CreepTumor";NA;381;0
"Unit";"Zergling";"Larva";381;1
"Unit";"Zergling";"Larva";381;1
"Unit";"Zergling";"Larva";381;1
"Unit";"Zergling";"Larva";381;1
"Unit";"Zergling";"Larva";381;1
"Unit";"Zergling";"Larva";381;1
"Building";"CreepTumorQueen";NA;381;0
"Building";"CreepTumorQueen";NA;387;0
"Building";"SporeCrawler";NA;381;0
"Unit";"Ultralisk";"Larva";381;6
"Unit";"Ultralisk";"Larva";381;6
"Unit";"Zergling";"Larva";427;1
"Unit";"Zergling";"Larva";427;1
"Unit";"Zergling";"Larva";427;1
"Unit";"Zergling";"Larva";427;1
"Unit";"Zergling";"Larva";427;1
"Unit";"Zergling";"Larva";427;1
"Unit";"Zergling";"Larva";427;1
"Unit";"Zergling";"Larva";427;1
"Unit";"Zergling";"Larva";427;1
"Unit";"Zergling";"Larva";427;1
"Unit";"Zergling";"Larva";427;1
"Unit";"Zergling";"Larva";427;1
"Unit";"Zergling";"Larva";427;1
"Unit";"Zergling";"Larva";427;1
"Unit";"Zergling";"Larva";427;1
"Unit";"Zergling";"Larva";427;1
"Unit";"Zergling";"Larva";427;1
"Unit";"Zergling";"Larva";427;1
"Unit";"Zergling";"Larva";427;1
"Unit";"Zergling";"Larva";427;1
"Unit";"Zergling";"Larva";427;1
"Unit";"Zergling";"Larva";427;1
"Unit";"Zergling";"Larva";427;1
"Unit";"Zergling";"Larva";427;1
"Unit";"Zergling";"Larva";427;1
"Unit";"Zergling";"Larva";427;1
"Building";"SporeCrawler";NA;427;0
"Building";"CreepTumor";NA;465;0
"Building";"CreepTumor";NA;465;0
"Building";"CreepTumor";NA;465;0
"Building";"CreepTumorQueen";NA;465;0
"Building";"CreepTumorQueen";NA;465;0
"Unit";"Overlord";"Larva";465;0
"Unit";"Overlord";"Larva";465;0
"Unit";"Overlord";"Larva";465;0
"Unit";"Overlord";"Larva";465;0
"Upgrade";"ZergMeleeWeaponsLevel3";"EvolutionChamber";351;0
"Upgrade";"ZergGroundArmorsLevel3";"EvolutionChamber";351;0
"Unit";"Overlord";"Larva";465;0
"Unit";"Overlord";"Larva";465;0
"Unit";"Overlord";"Larva";465;0
"Unit";"Viper";"Larva";465;3
"Unit";"Viper";"Larva";465;3
"Unit";"Zergling";"Larva";465;1
"Unit";"Zergling";"Larva";465;1
"Unit";"Zergling";"Larva";465;1
"Unit";"Zergling";"Larva";465;1
"Unit";"Zergling";"Larva";465;1
"Unit";"Zergling";"Larva";465;1
"Unit";"Zergling";"Larva";465;1
"Unit";"Zergling";"Larva";465;1
"Unit";"Zergling";"Larva";465;1
"Unit";"Zergling";"Larva";465;1
"Unit";"Zergling";"Larva";465;1
"Unit";"Zergling";"Larva";465;1
"Unit";"Zergling";"Larva";465;1
"Unit";"Zergling";"Larva";465;1
"Unit";"Zergling";"Larva";465;1
"Unit";"Zergling";"Larva";465;1
"Unit";"Zergling";"Larva";465;1
"Unit";"Zergling";"Larva";465;1
"Unit";"Zergling";"Larva";465;1
"Unit";"Zergling";"Larva";465;1
"Unit";"Zergling";"Larva";465;1
"Unit";"Zergling";"Larva";465;1
"Unit";"Zergling";"Larva";465;1
"Unit";"Zergling";"Larva";465;1
"Unit";"Zergling";"Larva";465;1
"Unit";"Zergling";"Larva";465;1
"Unit";"Zergling";"Larva";465;1
"Unit";"Zergling";"Larva";465;1
"Unit";"Zergling";"Larva";465;1
"Unit";"Zergling";"Larva";465;1
"Unit";"Zergling";"Larva";465;1
"Unit";"Zergling";"Larva";465;1
"Unit";"Zergling";"Larva";465;1
"Unit";"Zergling";"Larva";465;1
"Unit";"Zergling";"Larva";465;1
"Unit";"Zergling";"Larva";465;1
"Unit";"Zergling";"Larva";465;1
"Unit";"Zergling";"Larva";465;1
"Unit";"Zergling";"Larva";465;1
"Unit";"Zergling";"Larva";465;1
"Unit";"Zergling";"Larva";465;1
"Unit";"Zergling";"Larva";465;1
"Unit";"Viper";"Larva";465;3
"Unit";"Viper";"Larva";465;3
"Building";"Extractor";NA;471;0
"Unit";"Baneling";"Zergling";519;0
"Unit";"Baneling";"Zergling";520;0
"Unit";"Baneling";"Zergling";520;0
"Unit";"Baneling";"Zergling";522;0
"Unit";"Baneling";"Zergling";522;0
"Unit";"Baneling";"Zergling";523;0
"Unit";"Baneling";"Zergling";523;0
"Unit";"Baneling";"Zergling";525;0
"Unit";"Baneling";"Zergling";525;0
"Unit";"Baneling";"Zergling";525;0
"Unit";"Baneling";"Zergling";525;0
"Unit";"Baneling";"Zergling";525;0
"Unit";"Baneling";"Zergling";525;0
"Unit";"Baneling";"Zergling";525;0
"Unit";"Baneling";"Zergling";525;0
"Unit";"Baneling";"Zergling";525;0
"Unit";"Baneling";"Zergling";525;0
"Unit";"Baneling";"Zergling";525;0
"Unit";"Baneling";"Zergling";525;0
"Unit";"Baneling";"Zergling";525;0
"Unit";"Zergling";"Larva";525;1
"Unit";"Zergling";"Larva";525;1
"Unit";"Queen";"Hatchery";513;2
"Unit";"Queen";"Hatchery";513;2
"Building";"CreepTumor";NA;525;0
"Building";"CreepTumor";NA;525;0
"Building";"CreepTumorQueen";NA;531;0
"Building";"CreepTumorQueen";NA;531;0
"Building";"CreepTumorQueen";NA;531;0
"Building";"Spire";NA;525;0
"Unit";"Ultralisk";"Larva";531;6
"Unit";"Ultralisk";"Larva";531;6
"Unit";"Zergling";"Larva";531;1
"Unit";"Zergling";"Larva";531;1
"Unit";"Zergling";"Larva";531;1
"Unit";"Zergling";"Larva";531;1
"Unit";"Zergling";"Larva";531;1
"Unit";"Zergling";"Larva";531;1
"Unit";"Zergling";"Larva";531;1
"Unit";"Zergling";"Larva";531;1
"Unit";"Zergling";"Larva";531;1
"Unit";"Zergling";"Larva";531;1
"Unit";"Zergling";"Larva";531;1
"Unit";"Zergling";"Larva";531;1
"Unit";"Zergling";"Larva";531;1
"Unit";"Zergling";"Larva";531;1
"Unit";"Zergling";"Larva";531;1
"Unit";"Zergling";"Larva";531;1
"Unit";"Zergling";"Larva";531;1
"Unit";"Zergling";"Larva";531;1
"Unit";"Zergling";"Larva";531;1
"Unit";"Zergling";"Larva";531;1
"Unit";"Zergling";"Larva";531;1
"Unit";"Zergling";"Larva";531;1
"Unit";"Zergling";"Larva";531;1
"Unit";"Zergling";"Larva";531;1
"Unit";"Zergling";"Larva";531;1
"Unit";"Zergling";"Larva";531;1
"Unit";"Zergling";"Larva";531;1
"Unit";"Zergling";"Larva";531;1
"Unit";"Zergling";"Larva";531;1
"Unit";"Zergling";"Larva";531;1
"Unit";"Zergling";"Larva";531;1
"Unit";"Zergling";"Larva";531;1
"Unit";"Zergling";"Larva";531;1
"Unit";"Zergling";"Larva";531;1
"Unit";"Zergling";"Larva";531;1
"Unit";"Zergling";"Larva";531;1
"Unit";"Zergling";"Larva";531;1
"Unit";"Zergling";"Larva";531;1
"Unit";"Zergling";"Larva";531;1
"Unit";"Zergling";"Larva";531;1
"Building";"CreepTumor";NA;531;0
"Building";"CreepTumor";NA;531;0
"Unit";"Ultralisk";"Larva";531;6
"Unit";"Ultralisk";"Larva";531;6
"Unit";"Ultralisk";"Larva";531;6
"Unit";"Ultralisk";"Larva";531;6
"Unit";"Ultralisk";"Larva";531;6
"Unit";"Ultralisk";"Larva";531;6
"Unit";"Ultralisk";"Larva";531;6
"Unit";"Ultralisk";"Larva";531;6
"Unit";"Zergling";"Larva";583;1
"Unit";"Zergling";"Larva";583;1
"Unit";"Zergling";"Larva";583;1
"Unit";"Zergling";"Larva";583;1
"Unit";"Zergling";"Larva";583;1
"Unit";"Zergling";"Larva";583;1
"Unit";"Zergling";"Larva";583;1
"Unit";"Zergling";"Larva";583;1
"Unit";"Zergling";"Larva";583;1
"Unit";"Zergling";"Larva";583;1
"Unit";"Zergling";"Larva";583;1
"Unit";"Zergling";"Larva";583;1
"Unit";"Zergling";"Larva";583;1
"Unit";"Zergling";"Larva";583;1
"Building";"CreepTumor";NA;583;0
"Building";"CreepTumor";NA;583;0
"Building";"CreepTumor";NA;631;0
"Unit";"Queen";"Hatchery";543;2
"Unit";"Corruptor";"Larva";631;2
"Unit";"Corruptor";"Larva";631;2
"Unit";"Corruptor";"Larva";631;2
"Unit";"Corruptor";"Larva";631;2
"Unit";"Corruptor";"Larva";631;2
"Unit";"Zergling";"Larva";657;1
"Unit";"Zergling";"Larva";657;1
"Unit";"Zergling";"Larva";657;1
"Unit";"Zergling";"Larva";657;1
"Unit";"Zergling";"Larva";657;1
"Unit";"Zergling";"Larva";657;1
"Unit";"Zergling";"Larva";657;1
"Unit";"Zergling";"Larva";657;1
"Building";"SporeCrawler";NA;657;0
"Unit";"Corruptor";"Larva";657;2
"Unit";"Corruptor";"Larva";657;2
"Unit";"Corruptor";"Larva";657;2
"Building";"Hatchery";NA;583;0
"Building";"CreepTumor";NA;676;0
"Building";"CreepTumor";NA;676;0
"Building";"CreepTumor";NA;676;0
"Building";"CreepTumorQueen";NA;676;0
"Building";"CreepTumorQueen";NA;676;0
"Building";"CreepTumorQueen";NA;676;0
"Building";"Hatchery";NA;657;0
"Building";"Hatchery";NA;657;0
"Unit";"Corruptor";"Larva";682;2
"Unit";"Corruptor";"Larva";682;2
"Unit";"Corruptor";"Larva";682;2
"Unit";"Corruptor";"Larva";682;2
"Unit";"Corruptor";"Larva";682;2
"Unit";"Zergling";"Larva";684;1
"Unit";"Zergling";"Larva";684;1
"Unit";"Zergling";"Larva";684;1
"Unit";"Zergling";"Larva";684;1
"Unit";"Zergling";"Larva";684;1
"Unit";"Zergling";"Larva";684;1
"Unit";"Zergling";"Larva";684;1
"Unit";"Zergling";"Larva";684;1
"Unit";"Zergling";"Larva";684;1
"Unit";"Zergling";"Larva";684;1
"Unit";"Zergling";"Larva";684;1
"Unit";"Zergling";"Larva";684;1
"Unit";"Zergling";"Larva";684;1
"Unit";"Zergling";"Larva";684;1
"Unit";"Zergling";"Larva";684;1
"Unit";"Zergling";"Larva";684;1
"Unit";"Zergling";"Larva";684;1
"Unit";"Zergling";"Larva";684;1
"Unit";"Zergling";"Larva";684;1
"Unit";"Zergling";"Larva";684;1
"Unit";"Zergling";"Larva";684;1
"Unit";"Zergling";"Larva";684;1
"Unit";"Zergling";"Larva";684;1
"Unit";"Zergling";"Larva";684;1
"Unit";"Zergling";"Larva";684;1
"Unit";"Zergling";"Larva";684;1
"Upgrade";"ChitinousPlating";"UltraliskCavern";676;0
"Building";"CreepTumor";NA;720;0
"Building";"CreepTumor";NA;720;0
"Building";"CreepTumor";NA;720;0
"Building";"CreepTumor";NA;720;0
"Unit";"Corruptor";"Larva";694;2
"Unit";"Corruptor";"Larva";694;2
"Unit";"Corruptor";"Larva";694;2
"Unit";"Baneling";"Zergling";720;0
"Unit";"Baneling";"Zergling";720;0
"Unit";"Baneling";"Zergling";720;0
"Unit";"Baneling";"Zergling";720;0
"Unit";"Baneling";"Zergling";720;0
"Unit";"Baneling";"Zergling";720;0
"Unit";"Baneling";"Zergling";720;0
"Unit";"Baneling";"Zergling";720;0
"Unit";"Baneling";"Zergling";720;0
"Unit";"Baneling";"Zergling";720;0
"Unit";"Baneling";"Zergling";720;0
"Unit";"Baneling";"Zergling";720;0
"Unit";"Baneling";"Zergling";720;0
"Unit";"Baneling";"Zergling";720;0
"Unit";"Baneling";"Zergling";720;0
"Unit";"Baneling";"Zergling";720;0
"Unit";"Baneling";"Zergling";720;0
"Unit";"Baneling";"Zergling";720;0
"Unit";"Baneling";"Zergling";720;0
"Unit";"Baneling";"Zergling";720;0
"Unit";"Zergling";"Larva";720;1
"Unit";"Zergling";"Larva";720;1
"Unit";"Zergling";"Larva";720;1
"Unit";"Zergling";"Larva";720;1
"Unit";"Zergling";"Larva";720;1
"Unit";"Zergling";"Larva";720;1
"Unit";"Zergling";"Larva";720;1
"Unit";"Zergling";"Larva";720;1
"Unit";"Zergling";"Larva";720;1
"Unit";"Zergling";"Larva";720;1
"Unit";"Zergling";"Larva";720;1
"Unit";"Zergling";"Larva";720;1
"Unit";"Zergling";"Larva";720;1
"Unit";"Zergling";"Larva";720;1
"Unit";"Zergling";"Larva";720;1
"Unit";"Zergling";"Larva";720;1
"Unit";"Zergling";"Larva";720;1
"Unit";"Zergling";"Larva";720;1
"Unit";"Zergling";"Larva";720;1
"Unit";"Zergling";"Larva";720;1
"Unit";"Baneling";"Zergling";726;0
"Unit";"Baneling";"Zergling";726;0
"Unit";"Baneling";"Zergling";726;0
"Unit";"Baneling";"Zergling";726;0
"Unit";"Baneling";"Zergling";726;0
"Unit";"Baneling";"Zergling";726;0
"Building";"Extractor";NA;726;0
"Building";"Extractor";NA;726;0
"Building";"Hatchery";NA;684;0
