"type";"unit_name";"on_building";"total_supply_lag";"supply"
"Unit";"Overlord";"Larva";13;0
"Building";"SpawningPool";NA;17;0
"Building";"Extractor";NA;19;0
"Building";"Hatchery";NA;20;0
"Unit";"Queen";"Hatchery";22;2
"Unit";"Zergling";"Larva";24;1
"Unit";"Zergling";"Larva";25;1
"Unit";"Overlord";"Larva";26;0
"Unit";"Queen";"Hatchery";27;2
"Unit";"Queen";"Hatchery";31;2
"Building";"Hatchery";NA;35;0
"Unit";"Overlord";"Larva";39;0
"Unit";"Overlord";"Larva";41;0
"Building";"CreepTumorQueen";NA;41;0
"Unit";"Zergling";"Larva";41;1
"Unit";"Zergling";"Larva";42;1
"Unit";"Zergling";"Larva";43;1
"Unit";"Zergling";"Larva";44;1
"Unit";"Zergling";"Larva";45;1
"Unit";"Zergling";"Larva";46;1
"Unit";"Zergling";"Larva";47;1
"Unit";"Zergling";"Larva";48;1
"Unit";"Zergling";"Larva";49;1
"Unit";"Zergling";"Larva";50;1
"Unit";"Zergling";"Larva";51;1
"Unit";"Zergling";"Larva";52;1
"Unit";"Zergling";"Larva";53;1
"Unit";"Zergling";"Larva";54;1
"Unit";"Zergling";"Larva";55;1
"Unit";"Zergling";"Larva";56;1
"Unit";"Overlord";"Larva";59;0
"Unit";"Overlord";"Larva";65;0
"Unit";"Queen";"Hatchery";65;2
"Building";"CreepTumor";NA;70;0
"Unit";"Queen";"Hatchery";70;2
"Building";"CreepTumorQueen";NA;72;0
"Unit";"Zergling";"Larva";74;1
"Unit";"Zergling";"Larva";75;1
"Unit";"Zergling";"Larva";76;1
"Unit";"Zergling";"Larva";77;1
"Unit";"Zergling";"Larva";78;1
"Unit";"Zergling";"Larva";79;1
"Unit";"Zergling";"Larva";80;1
"Unit";"Zergling";"Larva";81;1
"Unit";"Zergling";"Larva";82;1
"Unit";"Zergling";"Larva";83;1
"Unit";"Zergling";"Larva";84;1
"Unit";"Zergling";"Larva";85;1
"Unit";"Overlord";"Larva";86;0
"Building";"Extractor";NA;92;0
"Building";"RoachWarren";NA;92;0
"Building";"Extractor";NA;92;0
"Building";"SporeCrawler";NA;95;0
"Building";"SporeCrawler";NA;95;0
"Building";"SporeCrawler";NA;95;0
"Unit";"Overlord";"Larva";98;0
"Building";"CreepTumor";NA;100;0
"Building";"CreepTumor";NA;100;0
"Unit";"Overlord";"Larva";102;0
"Unit";"Overlord";"Larva";102;0
"Unit";"Roach";"Larva";102;2
"Unit";"Roach";"Larva";104;2
"Unit";"Roach";"Larva";106;2
"Unit";"Overlord";"Larva";108;0
"Unit";"Roach";"Larva";108;2
"Building";"Extractor";NA;110;0
"Building";"EvolutionChamber";NA;115;0
"Building";"EvolutionChamber";NA;116;0
"Upgrade";"GlialReconstitution";"RoachWarren";120;0
"Building";"CreepTumor";NA;125;0
"Unit";"Overlord";"Larva";125;0
"Building";"Extractor";NA;125;0
"Building";"Extractor";NA;126;0
"Building";"Hatchery";NA;131;0
"Unit";"Roach";"Larva";132;2
"Unit";"Roach";"Larva";134;2
"Unit";"Roach";"Larva";136;2
"Unit";"Roach";"Larva";138;2
"Unit";"Roach";"Larva";140;2
"Unit";"Overlord";"Larva";142;0
"Building";"CreepTumor";NA;144;0
"Unit";"Overlord";"Larva";144;0
"Unit";"Overlord";"Larva";144;0
"Unit";"Overlord";"Larva";144;0
"Unit";"Overlord";"Larva";144;0
"Building";"CreepTumor";NA;144;0
"Building";"CreepTumorQueen";NA;144;0
"Building";"CreepTumorQueen";NA;144;0
"Unit";"Roach";"Larva";144;2
"Unit";"Roach";"Larva";146;2
"Unit";"Roach";"Larva";148;2
"Unit";"Roach";"Larva";150;2
"Unit";"Roach";"Larva";152;2
"Unit";"Overlord";"Larva";154;0
"Building";"CreepTumorQueen";NA;154;0
"Building";"CreepTumorQueen";NA;154;0
"Unit";"Roach";"Larva";154;2
"Unit";"Roach";"Larva";156;2
"Unit";"Roach";"Larva";158;2
"Unit";"Roach";"Larva";160;2
"Unit";"Roach";"Larva";162;2
"Unit";"Roach";"Larva";164;2
"Building";"CreepTumorQueen";NA;166;0
"Building";"CreepTumorQueen";NA;166;0
"Unit";"Roach";"Larva";166;2
"Unit";"Roach";"Larva";168;2
"Unit";"Roach";"Larva";170;2
"Unit";"Roach";"Larva";172;2
"Unit";"Roach";"Larva";174;2
"Unit";"Roach";"Larva";176;2
"Unit";"Roach";"Larva";178;2
"Unit";"Roach";"Larva";180;2
"Unit";"Roach";"Larva";182;2
"Unit";"Roach";"Larva";184;2
"Unit";"Roach";"Larva";186;2
"Unit";"Overlord";"Larva";188;0
"Building";"CreepTumor";NA;188;0
"Building";"InfestationPit";NA;188;0
"Building";"HydraliskDen";NA;194;0
"Building";"Extractor";NA;202;0
"Building";"Extractor";NA;202;0
"Building";"Hatchery";NA;202;0
"Unit";"Overlord";"Larva";202;0
"Unit";"Overlord";"Larva";206;0
"Unit";"Roach";"Larva";206;2
"Unit";"Roach";"Larva";208;2
"Unit";"Roach";"Larva";210;2
"Unit";"Roach";"Larva";212;2
"Unit";"Roach";"Larva";214;2
"Unit";"Roach";"Larva";216;2
"Unit";"Roach";"Larva";218;2
"Unit";"Roach";"Larva";220;2
"Unit";"Roach";"Larva";222;2
"Unit";"Hydralisk";"Larva";224;2
"Unit";"Hydralisk";"Larva";226;2
"Unit";"Hydralisk";"Larva";228;2
"Unit";"Hydralisk";"Larva";230;2
"Unit";"Hydralisk";"Larva";232;2
"Unit";"Hydralisk";"Larva";234;2
"Unit";"Hydralisk";"Larva";236;2
"Unit";"Hydralisk";"Larva";238;2
"Unit";"Hydralisk";"Larva";240;2
"Unit";"Hydralisk";"Larva";242;2
"Unit";"Hydralisk";"Larva";244;2
"Unit";"Hydralisk";"Larva";246;2
"Unit";"Hydralisk";"Larva";248;2
"Building";"SporeCrawler";NA;250;0
"Unit";"Hydralisk";"Larva";250;2
"Unit";"Hydralisk";"Larva";252;2
"Building";"CreepTumorQueen";NA;262;0
"Unit";"Overlord";"Larva";262;0
"Unit";"Overlord";"Larva";262;0
"Building";"CreepTumor";NA;262;0
"Unit";"Roach";"Larva";262;2
"Unit";"Roach";"Larva";264;2
"Unit";"Roach";"Larva";266;2
"Unit";"Overlord";"Larva";268;0
"Building";"CreepTumor";NA;268;0
"Building";"CreepTumorQueen";NA;268;0
"Unit";"Roach";"Larva";268;2
"Unit";"Roach";"Larva";270;2
"Unit";"Roach";"Larva";272;2
"Unit";"Roach";"Larva";274;2
"Unit";"Roach";"Larva";276;2
"Unit";"Roach";"Larva";278;2
"Unit";"Roach";"Larva";280;2
"Unit";"Roach";"Larva";282;2
"Building";"CreepTumorQueen";NA;284;0
"Building";"SpineCrawler";NA;284;0
"Building";"SporeCrawler";NA;284;0
"Unit";"Hydralisk";"Larva";284;2
"Unit";"Hydralisk";"Larva";286;2
"Unit";"Hydralisk";"Larva";288;2
"Unit";"Hydralisk";"Larva";290;2
"Unit";"Hydralisk";"Larva";292;2
"Unit";"Hydralisk";"Larva";294;2
"Unit";"Hydralisk";"Larva";296;2
"Unit";"Hydralisk";"Larva";298;2
"Unit";"Hydralisk";"Larva";300;2
"Building";"SpineCrawler";NA;302;0
"Building";"EvolutionChamber";NA;302;0
"Building";"CreepTumor";NA;302;0
"Building";"CreepTumor";NA;302;0
"Building";"CreepTumor";NA;302;0
"Unit";"Viper";"Larva";302;3
"Unit";"Viper";"Larva";305;3
"Unit";"Viper";"Larva";308;3
"Unit";"Viper";"Larva";311;3
"Unit";"Viper";"Larva";314;3
"Building";"CreepTumorQueen";NA;317;0
"Building";"CreepTumorQueen";NA;317;0
"Building";"CreepTumorQueen";NA;317;0
"Building";"Extractor";NA;317;0
"Building";"Extractor";NA;317;0
"Building";"CreepTumor";NA;317;0
"Building";"CreepTumor";NA;317;0
"Building";"CreepTumor";NA;317;0
"Building";"CreepTumor";NA;317;0
"Building";"CreepTumor";NA;317;0
"Building";"Hatchery";NA;317;0
"Unit";"Zergling";"Larva";317;1
"Unit";"Zergling";"Larva";318;1
"Unit";"Zergling";"Larva";319;1
"Unit";"Zergling";"Larva";320;1
"Unit";"Zergling";"Larva";321;1
"Unit";"Zergling";"Larva";322;1
"Unit";"Zergling";"Larva";323;1
"Unit";"Zergling";"Larva";324;1
"Unit";"Zergling";"Larva";325;1
"Unit";"Zergling";"Larva";326;1
"Unit";"Zergling";"Larva";327;1
"Unit";"Zergling";"Larva";328;1
"Unit";"Zergling";"Larva";329;1
"Unit";"Zergling";"Larva";330;1
"Unit";"Zergling";"Larva";331;1
"Unit";"Zergling";"Larva";332;1
"Unit";"Zergling";"Larva";333;1
"Unit";"Zergling";"Larva";334;1
"Unit";"Zergling";"Larva";335;1
"Unit";"Zergling";"Larva";336;1
"Unit";"Zergling";"Larva";337;1
"Unit";"Zergling";"Larva";338;1
"Unit";"Zergling";"Larva";339;1
"Unit";"Zergling";"Larva";340;1
"Unit";"Zergling";"Larva";341;1
"Unit";"Zergling";"Larva";342;1
"Unit";"Zergling";"Larva";343;1
"Unit";"Zergling";"Larva";344;1
"Unit";"Zergling";"Larva";345;1
"Unit";"Zergling";"Larva";346;1
"Unit";"Zergling";"Larva";347;1
"Unit";"Zergling";"Larva";348;1
"Building";"CreepTumorQueen";NA;349;0
"Building";"CreepTumorQueen";NA;349;0
"Building";"Hatchery";NA;349;0
"Unit";"Zergling";"Larva";349;1
"Unit";"Zergling";"Larva";350;1
"Building";"Hatchery";NA;351;0
"Building";"CreepTumorQueen";NA;351;0
"Building";"CreepTumorQueen";NA;351;0
"Building";"CreepTumorQueen";NA;351;0
"Building";"CreepTumor";NA;351;0
"Building";"CreepTumor";NA;351;0
"Building";"CreepTumor";NA;351;0
"Building";"CreepTumor";NA;351;0
"Building";"CreepTumorQueen";NA;351;0
"Building";"CreepTumor";NA;351;0
"Building";"CreepTumor";NA;351;0
"Building";"CreepTumor";NA;351;0
"Building";"CreepTumor";NA;351;0
"Building";"CreepTumor";NA;351;0
"Building";"CreepTumor";NA;351;0
"Building";"Spire";NA;351;0
"Building";"Spire";NA;351;0
"Unit";"Roach";"Larva";351;2
"Unit";"Hydralisk";"Larva";353;2
"Unit";"Hydralisk";"Larva";355;2
"Unit";"Hydralisk";"Larva";357;2
"Unit";"Hydralisk";"Larva";359;2
"Unit";"Hydralisk";"Larva";361;2
"Unit";"Hydralisk";"Larva";363;2
"Unit";"Hydralisk";"Larva";365;2
"Unit";"Hydralisk";"Larva";367;2
"Unit";"Hydralisk";"Larva";369;2
"Unit";"Hydralisk";"Larva";371;2
"Unit";"Hydralisk";"Larva";373;2
"Unit";"Hydralisk";"Larva";375;2
"Unit";"Hydralisk";"Larva";377;2
"Unit";"Hydralisk";"Larva";379;2
"Unit";"Roach";"Larva";381;2
"Unit";"Hydralisk";"Larva";383;2
"Unit";"Hydralisk";"Larva";385;2
"Unit";"Hydralisk";"Larva";387;2
"Unit";"Hydralisk";"Larva";389;2
"Unit";"Hydralisk";"Larva";391;2
"Unit";"Hydralisk";"Larva";393;2
"Unit";"Hydralisk";"Larva";395;2
"Unit";"Hydralisk";"Larva";397;2
"Unit";"Hydralisk";"Larva";399;2
"Unit";"Hydralisk";"Larva";401;2
"Unit";"Hydralisk";"Larva";403;2
"Unit";"Hydralisk";"Larva";405;2
"Unit";"Hydralisk";"Larva";407;2
"Unit";"Hydralisk";"Larva";409;2
"Unit";"Hydralisk";"Larva";411;2
"Unit";"Hydralisk";"Larva";413;2
"Unit";"Hydralisk";"Larva";415;2
"Unit";"Zergling";"Larva";417;1
"Unit";"Zergling";"Larva";418;1
"Unit";"Zergling";"Larva";419;1
"Unit";"Zergling";"Larva";420;1
"Unit";"Zergling";"Larva";421;1
"Unit";"Zergling";"Larva";422;1
"Unit";"Zergling";"Larva";423;1
"Unit";"Zergling";"Larva";424;1
"Unit";"Zergling";"Larva";425;1
"Unit";"Zergling";"Larva";426;1
"Unit";"Zergling";"Larva";427;1
"Unit";"Zergling";"Larva";428;1
"Unit";"Zergling";"Larva";429;1
"Unit";"Zergling";"Larva";430;1
"Unit";"Zergling";"Larva";431;1
"Unit";"Zergling";"Larva";432;1
"Unit";"Zergling";"Larva";433;1
"Unit";"Zergling";"Larva";434;1
"Unit";"Zergling";"Larva";435;1
"Unit";"Zergling";"Larva";436;1
"Unit";"Zergling";"Larva";437;1
"Unit";"Zergling";"Larva";438;1
"Unit";"Zergling";"Larva";439;1
"Unit";"Zergling";"Larva";440;1
"Unit";"Zergling";"Larva";441;1
"Unit";"Zergling";"Larva";442;1
"Unit";"Zergling";"Larva";443;1
"Unit";"Zergling";"Larva";444;1
"Unit";"Zergling";"Larva";445;1
"Unit";"Zergling";"Larva";446;1
"Upgrade";"SprayZerg";NA;447;0
"Upgrade";"SprayZerg";NA;447;0
"Upgrade";"SprayZerg";NA;447;0
"Upgrade";"zerglingmovementspeed";NA;447;0
"Upgrade";"SprayZerg";NA;447;0
"Upgrade";"SprayZerg";NA;447;0
"Upgrade";"SprayZerg";NA;447;0
"Upgrade";"SprayZerg";NA;447;0
"Upgrade";"ZergMissileWeaponsLevel1";NA;447;0
"Upgrade";"ZergGroundArmorsLevel1";NA;447;0
"Upgrade";"SprayZerg";NA;447;0
"Upgrade";"EvolveMuscularAugments";NA;447;0
"Upgrade";"overlordspeed";NA;447;0
"Upgrade";"SprayZerg";NA;447;0
"Upgrade";"SprayZerg";NA;447;0
"Upgrade";"ZergMissileWeaponsLevel2";NA;447;0
"Upgrade";"SprayZerg";NA;447;0
"Upgrade";"ZergGroundArmorsLevel2";NA;447;0
"Upgrade";"SprayZerg";NA;447;0
"Upgrade";"SprayZerg";NA;447;0
"Upgrade";"SprayZerg";NA;447;0
"Upgrade";"ZergMeleeWeaponsLevel1";NA;447;0
