"type";"unit_name";"on_building";"total_supply";"supply"
"Unit";"Overlord";"Larva";13;0
"Building";"Extractor";NA;18;0
"Unit";"Overlord";"Larva";22;0
"Building";"SpawningPool";NA;19;0
"Building";"Hatchery";NA;17;0
"Unit";"Zergling";"Larva";22;1
"Unit";"Zergling";"Larva";22;1
"Unit";"Zergling";"Larva";22;1
"Unit";"Zergling";"Larva";22;1
"Unit";"Queen";"Hatchery";22;2
"Unit";"Queen";"Hatchery";22;2
"Unit";"Overlord";"Larva";37;0
"Unit";"Overlord";"Larva";37;0
"Unit";"Queen";"Hatchery";37;2
"Building";"CreepTumorQueen";NA;38;0
"Unit";"Overlord";"Larva";40;0
"Unit";"Overlord";"Larva";46;0
"Building";"Hatchery";NA;35;0
"Building";"CreepTumor";NA;49;0
"Building";"CreepTumorQueen";NA;49;0
"Unit";"Queen";"Hatchery";46;2
"Unit";"Overlord";"Larva";55;0
"Building";"CreepTumorQueen";NA;58;0
"Building";"CreepTumor";NA;58;0
"Building";"CreepTumor";NA;62;0
"Unit";"Queen";"Hatchery";49;2
"Unit";"Zergling";"Larva";62;1
"Unit";"Zergling";"Larva";62;1
"Unit";"Zergling";"Larva";62;1
"Unit";"Zergling";"Larva";62;1
"Unit";"Zergling";"Larva";62;1
"Unit";"Zergling";"Larva";62;1
"Unit";"Zergling";"Larva";62;1
"Unit";"Zergling";"Larva";62;1
"Building";"SporeCrawler";NA;62;0
"Unit";"Queen";"Hatchery";58;2
"Building";"SporeCrawler";NA;62;0
"Building";"SporeCrawler";NA;62;0
"Unit";"Overlord";"Larva";78;0
"Unit";"Overlord";"Larva";78;0
"Building";"CreepTumor";NA;82;0
"Building";"Extractor";NA;82;0
"Unit";"Overlord";"Larva";92;0
"Building";"CreepTumor";NA;102;0
"Building";"Extractor";NA;92;0
"Building";"CreepTumor";NA;102;0
"Building";"CreepTumorQueen";NA;102;0
"Building";"EvolutionChamber";NA;99;0
"Building";"EvolutionChamber";NA;99;0
"Unit";"Overlord";"Larva";102;0
"Building";"Extractor";NA;102;0
"Building";"Extractor";NA;102;0
"Building";"Hatchery";NA;86;0
"Unit";"Overlord";"Larva";105;0
"Building";"CreepTumorQueen";NA;107;0
"Building";"CreepTumorQueen";NA;110;0
"Building";"CreepTumorQueen";NA;110;0
"Building";"CreepTumor";NA;110;0
"Unit";"Queen";"Hatchery";105;2
"Unit";"Overlord";"Larva";109;0
"Building";"BanelingNest";NA;102;0
"Building";"CreepTumorQueen";NA;110;0
"Building";"Extractor";NA;110;0
"Unit";"Overlord";"Larva";117;0
"Building";"SporeCrawler";NA;113;0
"Building";"CreepTumorQueen";NA;126;0
"Building";"CreepTumor";NA;126;0
"Building";"CreepTumor";NA;126;0
"Building";"CreepTumor";NA;126;0
"Building";"CreepTumor";NA;126;0
"Building";"CreepTumor";NA;126;0
"Unit";"Zergling";"Larva";126;1
"Unit";"Zergling";"Larva";126;1
"Unit";"Zergling";"Larva";126;1
"Unit";"Zergling";"Larva";126;1
"Unit";"Zergling";"Larva";126;1
"Unit";"Zergling";"Larva";126;1
"Unit";"Zergling";"Larva";126;1
"Unit";"Zergling";"Larva";126;1
"Unit";"Queen";"Hatchery";121;2
"Building";"HydraliskDen";NA;126;0
"Building";"CreepTumor";NA;126;0
"Building";"Hatchery";NA;105;0
"Unit";"Zergling";"Larva";126;1
"Unit";"Zergling";"Larva";126;1
"Unit";"Zergling";"Larva";126;1
"Unit";"Zergling";"Larva";126;1
"Unit";"Zergling";"Larva";126;1
"Unit";"Zergling";"Larva";126;1
"Unit";"Zergling";"Larva";126;1
"Unit";"Zergling";"Larva";126;1
"Unit";"Zergling";"Larva";126;1
"Unit";"Zergling";"Larva";126;1
"Unit";"Zergling";"Larva";126;1
"Unit";"Zergling";"Larva";126;1
"Unit";"Zergling";"Larva";126;1
"Unit";"Zergling";"Larva";126;1
"Unit";"Zergling";"Larva";126;1
"Unit";"Zergling";"Larva";126;1
"Unit";"Zergling";"Larva";126;1
"Unit";"Zergling";"Larva";126;1
"Building";"CreepTumor";NA;136;0
"Building";"CreepTumor";NA;136;0
"Building";"CreepTumor";NA;136;0
"Building";"CreepTumor";NA;136;0
"Building";"CreepTumor";NA;136;0
"Unit";"Baneling";"Zergling";154;0
"Unit";"Baneling";"Zergling";154;0
"Unit";"Baneling";"Zergling";154;0
"Unit";"Baneling";"Zergling";154;0
"Unit";"Baneling";"Zergling";154;0
"Unit";"Baneling";"Zergling";154;0
"Unit";"Baneling";"Zergling";154;0
"Unit";"Baneling";"Zergling";154;0
"Unit";"Baneling";"Zergling";154;0
"Unit";"Baneling";"Zergling";154;0
"Unit";"Baneling";"Zergling";154;0
"Unit";"Baneling";"Zergling";154;0
"Unit";"Baneling";"Zergling";154;0
"Unit";"Overlord";"Larva";154;0
"Unit";"Overlord";"Larva";154;0
"Unit";"Queen";"Hatchery";128;2
"Building";"CreepTumorQueen";NA;154;0
"Building";"CreepTumorQueen";NA;154;0
"Unit";"Zergling";"Larva";154;1
"Unit";"Zergling";"Larva";154;1
"Unit";"Zergling";"Larva";154;1
"Unit";"Zergling";"Larva";154;1
"Unit";"Zergling";"Larva";154;1
"Unit";"Zergling";"Larva";154;1
"Unit";"Zergling";"Larva";154;1
"Unit";"Zergling";"Larva";154;1
"Unit";"Zergling";"Larva";154;1
"Unit";"Zergling";"Larva";154;1
"Unit";"Zergling";"Larva";156;1
"Unit";"Zergling";"Larva";156;1
"Unit";"Zergling";"Larva";156;1
"Unit";"Zergling";"Larva";156;1
"Unit";"Zergling";"Larva";156;1
"Unit";"Zergling";"Larva";156;1
"Unit";"Zergling";"Larva";156;1
"Unit";"Zergling";"Larva";156;1
"Unit";"Zergling";"Larva";156;1
"Unit";"Zergling";"Larva";156;1
"Unit";"Baneling";"Zergling";156;0
"Unit";"Baneling";"Zergling";156;0
"Unit";"Baneling";"Zergling";156;0
"Unit";"Baneling";"Zergling";156;0
"Building";"CreepTumor";NA;156;0
"Building";"CreepTumor";NA;156;0
"Building";"CreepTumor";NA;156;0
"Unit";"Hydralisk";"Larva";154;2
"Building";"CreepTumor";NA;156;0
"Unit";"Hydralisk";"Larva";154;2
"Unit";"Hydralisk";"Larva";154;2
"Unit";"Hydralisk";"Larva";154;2
"Unit";"Hydralisk";"Larva";154;2
"Building";"CreepTumor";NA;156;0
"Upgrade";"ZergMeleeWeaponsLevel1";"EvolutionChamber";121;0
"Unit";"Zergling";"Larva";156;1
"Unit";"Zergling";"Larva";156;1
"Unit";"Zergling";"Larva";158;1
"Unit";"Zergling";"Larva";158;1
"Building";"InfestationPit";NA;154;0
"Unit";"Zergling";"Larva";158;1
"Unit";"Zergling";"Larva";158;1
"Unit";"Zergling";"Larva";158;1
"Unit";"Zergling";"Larva";158;1
"Unit";"Zergling";"Larva";158;1
"Unit";"Zergling";"Larva";158;1
"Unit";"Zergling";"Larva";158;1
"Unit";"Zergling";"Larva";158;1
"Unit";"Zergling";"Larva";158;1
"Unit";"Zergling";"Larva";158;1
"Unit";"Zergling";"Larva";158;1
"Unit";"Zergling";"Larva";158;1
"Unit";"Zergling";"Larva";158;1
"Unit";"Zergling";"Larva";158;1
"Unit";"Zergling";"Larva";158;1
"Unit";"Zergling";"Larva";158;1
"Unit";"Zergling";"Larva";158;1
"Unit";"Zergling";"Larva";158;1
"Unit";"Zergling";"Larva";158;1
"Unit";"Zergling";"Larva";158;1
"Building";"Hatchery";NA;154;0
"Unit";"Queen";"Hatchery";186;2
"Building";"CreepTumor";NA;210;0
"Unit";"Hydralisk";"Larva";210;2
"Unit";"Hydralisk";"Larva";210;2
"Unit";"Hydralisk";"Larva";210;2
"Unit";"Hydralisk";"Larva";210;2
"Unit";"Hydralisk";"Larva";210;2
"Unit";"Hydralisk";"Larva";210;2
"Unit";"Hydralisk";"Larva";210;2
"Unit";"Hydralisk";"Larva";210;2
"Upgrade";"EvolveGroovedSpines";"HydraliskDen";174;0
"Unit";"Overlord";"Larva";210;0
"Unit";"Overlord";"Larva";210;0
"Unit";"Overlord";"Larva";210;0
"Unit";"Overlord";"Larva";210;0
"Unit";"Overlord";"Larva";210;0
"Building";"CreepTumor";NA;212;0
"Unit";"Baneling";"Zergling";212;0
"Building";"CreepTumor";NA;228;0
"Building";"CreepTumor";NA;228;0
"Building";"Extractor";NA;212;0
"Building";"CreepTumor";NA;228;0
"Unit";"Zergling";"Larva";228;1
"Unit";"Zergling";"Larva";228;1
"Unit";"Zergling";"Larva";228;1
"Unit";"Zergling";"Larva";228;1
"Unit";"Zergling";"Larva";228;1
"Unit";"Zergling";"Larva";228;1
"Unit";"Zergling";"Larva";228;1
"Unit";"Zergling";"Larva";228;1
"Unit";"Zergling";"Larva";228;1
"Unit";"Zergling";"Larva";228;1
"Unit";"Zergling";"Larva";228;1
"Unit";"Zergling";"Larva";228;1
"Unit";"Zergling";"Larva";228;1
"Unit";"Zergling";"Larva";228;1
"Unit";"Zergling";"Larva";228;1
"Unit";"Zergling";"Larva";228;1
"Building";"CreepTumor";NA;228;0
"Unit";"Zergling";"Larva";228;1
"Unit";"Zergling";"Larva";228;1
"Unit";"Zergling";"Larva";228;1
"Unit";"Zergling";"Larva";228;1
"Unit";"Zergling";"Larva";228;1
"Unit";"Zergling";"Larva";228;1
"Unit";"Zergling";"Larva";228;1
"Unit";"Zergling";"Larva";228;1
"Unit";"Zergling";"Larva";228;1
"Unit";"Zergling";"Larva";228;1
"Unit";"Zergling";"Larva";228;1
"Unit";"Zergling";"Larva";228;1
"Unit";"Zergling";"Larva";228;1
"Unit";"Zergling";"Larva";228;1
"Unit";"Zergling";"Larva";228;1
"Unit";"Zergling";"Larva";228;1
"Unit";"Zergling";"Larva";228;1
"Unit";"Zergling";"Larva";228;1
"Building";"CreepTumor";NA;228;0
"Upgrade";"ZergGroundArmorsLevel1";"EvolutionChamber";156;0
"Unit";"Baneling";"Zergling";228;0
"Unit";"Baneling";"Zergling";228;0
"Unit";"Baneling";"Zergling";228;0
"Unit";"Baneling";"Zergling";228;0
"Unit";"Baneling";"Zergling";228;0
"Unit";"Overlord";"Larva";228;0
"Unit";"Overlord";"Larva";228;0
"Unit";"Overlord";"Larva";228;0
"Unit";"Baneling";"Zergling";262;0
"Unit";"Baneling";"Zergling";262;0
"Unit";"Baneling";"Zergling";262;0
"Unit";"Baneling";"Zergling";262;0
"Unit";"Baneling";"Zergling";262;0
"Unit";"Baneling";"Zergling";262;0
"Unit";"Baneling";"Zergling";262;0
"Unit";"Baneling";"Zergling";262;0
"Unit";"Baneling";"Zergling";262;0
"Unit";"Baneling";"Zergling";262;0
"Unit";"Baneling";"Zergling";262;0
"Unit";"Baneling";"Zergling";262;0
"Unit";"Baneling";"Zergling";262;0
"Unit";"Baneling";"Zergling";262;0
"Unit";"Baneling";"Zergling";262;0
"Unit";"Baneling";"Zergling";262;0
"Unit";"Baneling";"Zergling";262;0
"Unit";"Baneling";"Zergling";262;0
"Unit";"Baneling";"Zergling";262;0
"Unit";"Baneling";"Zergling";262;0
"Unit";"Baneling";"Zergling";262;0
"Unit";"Baneling";"Zergling";262;0
"Unit";"Baneling";"Zergling";262;0
"Unit";"Baneling";"Zergling";262;0
"Unit";"Zergling";"Larva";262;1
"Unit";"Zergling";"Larva";262;1
"Unit";"Zergling";"Larva";262;1
"Unit";"Zergling";"Larva";262;1
"Unit";"Zergling";"Larva";262;1
"Unit";"Zergling";"Larva";262;1
"Unit";"Zergling";"Larva";262;1
"Unit";"Zergling";"Larva";262;1
"Unit";"Zergling";"Larva";262;1
"Unit";"Zergling";"Larva";262;1
"Unit";"Zergling";"Larva";262;1
"Unit";"Zergling";"Larva";262;1
"Unit";"Zergling";"Larva";262;1
"Unit";"Zergling";"Larva";262;1
"Unit";"Zergling";"Larva";262;1
"Unit";"Zergling";"Larva";262;1
"Unit";"Zergling";"Larva";262;1
"Unit";"Zergling";"Larva";262;1
"Unit";"Zergling";"Larva";262;1
"Unit";"Zergling";"Larva";262;1
"Unit";"Zergling";"Larva";262;1
"Unit";"Zergling";"Larva";262;1
"Unit";"Zergling";"Larva";262;1
"Unit";"Zergling";"Larva";262;1
"Unit";"Hydralisk";"Larva";262;2
"Unit";"Hydralisk";"Larva";262;2
"Unit";"Hydralisk";"Larva";262;2
"Unit";"Baneling";"Zergling";262;0
"Unit";"Baneling";"Zergling";262;0
"Unit";"Baneling";"Zergling";262;0
"Unit";"Baneling";"Zergling";262;0
"Unit";"Baneling";"Zergling";262;0
"Unit";"Baneling";"Zergling";262;0
"Unit";"Baneling";"Zergling";262;0
"Unit";"Baneling";"Zergling";262;0
"Unit";"Baneling";"Zergling";262;0
"Unit";"Zergling";"Larva";262;1
"Unit";"Zergling";"Larva";262;1
"Unit";"Zergling";"Larva";262;1
"Unit";"Zergling";"Larva";262;1
"Unit";"Zergling";"Larva";262;1
"Unit";"Zergling";"Larva";262;1
"Unit";"Zergling";"Larva";262;1
"Unit";"Zergling";"Larva";262;1
"Unit";"Zergling";"Larva";262;1
"Unit";"Zergling";"Larva";262;1
"Unit";"Zergling";"Larva";262;1
"Unit";"Zergling";"Larva";262;1
"Unit";"Zergling";"Larva";262;1
"Unit";"Zergling";"Larva";262;1
"Unit";"Zergling";"Larva";262;1
"Unit";"Zergling";"Larva";262;1
"Unit";"Zergling";"Larva";262;1
"Unit";"Zergling";"Larva";262;1
"Unit";"Zergling";"Larva";262;1
"Unit";"Zergling";"Larva";262;1
"Upgrade";"EvolveMuscularAugments";"HydraliskDen";228;0
