"type";"unit_name";"on_building";"total_supply";"supply"
"Unit";"Overlord";"Larva";12;0
"Building";"SpawningPool";NA;14;0
"Building";"Extractor";NA;17;0
"Unit";"Zergling";"Larva";20;1
"Unit";"Zergling";"Larva";20;1
"Unit";"Overlord";"Larva";20;0
"Unit";"Queen";"Hatchery";19;2
"Building";"Hatchery";NA;17;0
"Unit";"Queen";"Hatchery";23;2
"Building";"RoachWarren";NA;26;0
"Unit";"Overlord";"Larva";31;0
"Unit";"Roach";"Larva";36;2
"Unit";"Roach";"Larva";36;2
"Unit";"Roach";"Larva";36;2
"Unit";"Roach";"Larva";36;2
"Unit";"Overlord";"Larva";36;0
"Unit";"Roach";"Larva";36;2
"Unit";"Roach";"Larva";36;2
"Unit";"Zergling";"Larva";48;1
"Unit";"Zergling";"Larva";48;1
"Unit";"Zergling";"Larva";48;1
"Unit";"Zergling";"Larva";48;1
"Unit";"Zergling";"Larva";48;1
"Unit";"Zergling";"Larva";48;1
"Unit";"Zergling";"Larva";48;1
"Unit";"Zergling";"Larva";48;1
"Unit";"Zergling";"Larva";48;1
"Unit";"Zergling";"Larva";48;1
"Unit";"Zergling";"Larva";48;1
"Unit";"Zergling";"Larva";48;1
"Unit";"Overlord";"Larva";48;0
"Unit";"Zergling";"Larva";48;1
"Unit";"Zergling";"Larva";48;1
"Unit";"Zergling";"Larva";48;1
"Unit";"Zergling";"Larva";48;1
"Unit";"Zergling";"Larva";48;1
"Unit";"Zergling";"Larva";48;1
"Unit";"Zergling";"Larva";60;1
"Unit";"Zergling";"Larva";60;1
"Building";"BanelingNest";NA;44;0
"Unit";"Overlord";"Larva";60;0
"Unit";"Zergling";"Larva";66;1
"Unit";"Zergling";"Larva";66;1
"Unit";"Zergling";"Larva";66;1
"Unit";"Zergling";"Larva";66;1
"Unit";"Overlord";"Larva";66;0
"Unit";"Zergling";"Larva";66;1
"Unit";"Zergling";"Larva";66;1
"Unit";"Zergling";"Larva";66;1
"Unit";"Zergling";"Larva";66;1
"Unit";"Baneling";"Zergling";68;0
"Unit";"Baneling";"Zergling";68;0
"Unit";"Baneling";"Zergling";68;0
"Unit";"Baneling";"Zergling";68;0
"Unit";"Baneling";"Zergling";68;0
"Unit";"Baneling";"Zergling";76;0
"Unit";"Baneling";"Zergling";76;0
"Building";"CreepTumorQueen";NA;89;0
"Building";"CreepTumorQueen";NA;89;0
"Unit";"Baneling";"Zergling";89;0
"Building";"CreepTumorQueen";NA;91;0
"Unit";"Overlord";"Larva";89;0
"Building";"CreepTumorQueen";NA;91;0
"Building";"Extractor";NA;89;0
"Building";"Extractor";NA;90;0
"Building";"Extractor";NA;91;0
"Building";"EvolutionChamber";NA;92;0
"Building";"CreepTumor";NA;92;0
"Building";"CreepTumor";NA;92;0
"Building";"CreepTumor";NA;98;0
"Building";"CreepTumor";NA;98;0
"Building";"EvolutionChamber";NA;98;0
"Building";"Hatchery";NA;89;0
"Unit";"Queen";"Hatchery";98;2
"Building";"CreepTumor";NA;105;0
"Unit";"Zergling";"Larva";105;1
"Unit";"Zergling";"Larva";105;1
"Unit";"Zergling";"Larva";105;1
"Unit";"Zergling";"Larva";105;1
"Building";"CreepTumor";NA;105;0
"Unit";"Zergling";"Larva";105;1
"Unit";"Zergling";"Larva";105;1
"Unit";"Zergling";"Larva";105;1
"Unit";"Zergling";"Larva";105;1
"Unit";"Zergling";"Larva";105;1
"Unit";"Zergling";"Larva";105;1
"Unit";"Zergling";"Larva";105;1
"Unit";"Zergling";"Larva";105;1
"Unit";"Zergling";"Larva";105;1
"Unit";"Zergling";"Larva";105;1
"Building";"CreepTumorQueen";NA;115;0
"Unit";"Zergling";"Larva";107;1
"Unit";"Zergling";"Larva";107;1
"Unit";"Zergling";"Larva";112;1
"Unit";"Zergling";"Larva";112;1
"Unit";"Zergling";"Larva";115;1
"Unit";"Zergling";"Larva";115;1
"Unit";"Baneling";"Zergling";123;0
"Unit";"Baneling";"Zergling";123;0
"Unit";"Queen";"Hatchery";107;2
"Building";"CreepTumor";NA;131;0
"Building";"Hatchery";NA;98;0
"Unit";"Baneling";"Zergling";131;0
"Unit";"Baneling";"Zergling";131;0
"Unit";"Baneling";"Zergling";131;0
"Unit";"Baneling";"Zergling";131;0
"Unit";"Baneling";"Zergling";131;0
"Unit";"Zergling";"Larva";131;1
"Unit";"Zergling";"Larva";131;1
"Unit";"Zergling";"Larva";131;1
"Unit";"Zergling";"Larva";131;1
"Unit";"Zergling";"Larva";132;1
"Unit";"Zergling";"Larva";132;1
"Unit";"Zergling";"Larva";133;1
"Unit";"Zergling";"Larva";133;1
"Unit";"Zergling";"Larva";133;1
"Unit";"Zergling";"Larva";133;1
"Unit";"Zergling";"Larva";133;1
"Unit";"Zergling";"Larva";133;1
"Unit";"Zergling";"Larva";133;1
"Unit";"Zergling";"Larva";133;1
"Unit";"Zergling";"Larva";133;1
"Unit";"Zergling";"Larva";133;1
"Unit";"Zergling";"Larva";133;1
"Unit";"Zergling";"Larva";133;1
"Building";"CreepTumor";NA;148;0
"Building";"CreepTumor";NA;148;0
"Unit";"Overlord";"Larva";148;0
"Unit";"Queen";"Hatchery";136;2
"Unit";"Queen";"Hatchery";148;2
"Building";"SporeCrawler";NA;158;0
"Building";"CreepTumor";NA;171;0
"Building";"CreepTumor";NA;171;0
"Unit";"Overlord";"Larva";171;0
"Upgrade";"ZergMeleeWeaponsLevel1";"EvolutionChamber";131;0
"Upgrade";"Burrow";"Hatchery";158;0
"Building";"SporeCrawler";NA;171;0
"Unit";"Overlord";"Larva";171;0
"Building";"SporeCrawler";NA;171;0
"Building";"CreepTumor";NA;179;0
"Building";"SporeCrawler";NA;171;0
"Unit";"Overlord";"Larva";179;0
"Unit";"Baneling";"Zergling";179;0
"Unit";"Baneling";"Zergling";179;0
"Unit";"Baneling";"Zergling";179;0
"Unit";"Overlord";"Larva";179;0
"Unit";"Overlord";"Larva";179;0
"Unit";"Zergling";"Larva";180;1
"Unit";"Zergling";"Larva";180;1
"Unit";"Zergling";"Larva";180;1
"Unit";"Zergling";"Larva";180;1
"Unit";"Zergling";"Larva";180;1
"Unit";"Zergling";"Larva";180;1
"Unit";"Zergling";"Larva";180;1
"Unit";"Zergling";"Larva";180;1
"Unit";"Zergling";"Larva";180;1
"Unit";"Zergling";"Larva";180;1
"Unit";"Zergling";"Larva";180;1
"Unit";"Zergling";"Larva";180;1
"Unit";"Zergling";"Larva";180;1
"Unit";"Zergling";"Larva";180;1
"Building";"CreepTumor";NA;180;0
"Building";"CreepTumor";NA;180;0
"Building";"EvolutionChamber";NA;180;0
"Unit";"Zergling";"Larva";195;1
"Unit";"Zergling";"Larva";195;1
"Unit";"Zergling";"Larva";195;1
"Unit";"Zergling";"Larva";195;1
"Unit";"Overlord";"Larva";195;0
"Unit";"Zergling";"Larva";195;1
"Unit";"Zergling";"Larva";195;1
"Unit";"Zergling";"Larva";195;1
"Unit";"Zergling";"Larva";195;1
"Unit";"Zergling";"Larva";195;1
"Unit";"Zergling";"Larva";195;1
"Unit";"Zergling";"Larva";195;1
"Unit";"Zergling";"Larva";195;1
"Unit";"Zergling";"Larva";195;1
"Unit";"Zergling";"Larva";195;1
"Unit";"Zergling";"Larva";195;1
"Unit";"Zergling";"Larva";195;1
"Unit";"Zergling";"Larva";195;1
"Unit";"Zergling";"Larva";195;1
"Building";"CreepTumor";NA;195;0
"Building";"CreepTumor";NA;195;0
"Building";"CreepTumor";NA;195;0
"Unit";"Overlord";"Larva";195;0
"Upgrade";"ZergGroundArmorsLevel1";"EvolutionChamber";167;0
"Unit";"Roach";"Larva";195;2
"Unit";"Roach";"Larva";195;2
"Unit";"Roach";"Larva";195;2
"Unit";"Overlord";"Larva";204;0
"Unit";"Roach";"Larva";204;2
"Unit";"Roach";"Larva";204;2
"Unit";"Roach";"Larva";204;2
"Upgrade";"GlialReconstitution";"RoachWarren";180;0
"Unit";"Roach";"Larva";214;2
"Unit";"Zergling";"Larva";214;1
"Unit";"Zergling";"Larva";214;1
"Unit";"Roach";"Larva";214;2
"Unit";"Zergling";"Larva";214;1
"Unit";"Zergling";"Larva";214;1
"Unit";"Roach";"Larva";214;2
"Unit";"Roach";"Larva";214;2
"Unit";"Baneling";"Zergling";218;0
"Unit";"Baneling";"Zergling";218;0
"Unit";"Baneling";"Zergling";220;0
"Unit";"Baneling";"Zergling";220;0
"Unit";"Roach";"Larva";218;2
"Unit";"Zergling";"Larva";220;1
"Unit";"Zergling";"Larva";220;1
"Unit";"Overlord";"Larva";220;0
"Unit";"Baneling";"Zergling";226;0
"Unit";"Baneling";"Zergling";226;0
"Unit";"Baneling";"Zergling";226;0
"Unit";"Baneling";"Zergling";226;0
"Unit";"Baneling";"Zergling";226;0
"Unit";"Baneling";"Zergling";226;0
"Unit";"Baneling";"Zergling";226;0
"Unit";"Baneling";"Zergling";228;0
"Building";"Hatchery";NA;180;0
"Unit";"Roach";"Larva";242;2
"Unit";"Roach";"Larva";242;2
"Unit";"Roach";"Larva";242;2
"Unit";"Roach";"Larva";242;2
"Unit";"Roach";"Larva";242;2
"Unit";"Roach";"Larva";242;2
"Unit";"Zergling";"Larva";242;1
"Unit";"Zergling";"Larva";242;1
"Unit";"Zergling";"Larva";242;1
"Unit";"Zergling";"Larva";242;1
"Unit";"Zergling";"Larva";242;1
"Unit";"Zergling";"Larva";242;1
"Unit";"Zergling";"Larva";242;1
"Unit";"Zergling";"Larva";242;1
"Unit";"Zergling";"Larva";242;1
"Unit";"Zergling";"Larva";242;1
"Unit";"Zergling";"Larva";242;1
"Unit";"Zergling";"Larva";242;1
"Unit";"Zergling";"Larva";242;1
"Unit";"Zergling";"Larva";242;1
"Unit";"Zergling";"Larva";242;1
"Unit";"Zergling";"Larva";242;1
"Unit";"Zergling";"Larva";242;1
"Unit";"Zergling";"Larva";242;1
"Unit";"Zergling";"Larva";242;1
"Unit";"Zergling";"Larva";242;1
"Unit";"Zergling";"Larva";242;1
"Unit";"Zergling";"Larva";242;1
"Unit";"Zergling";"Larva";242;1
"Unit";"Zergling";"Larva";242;1
"Unit";"Zergling";"Larva";242;1
"Unit";"Zergling";"Larva";242;1
"Unit";"Zergling";"Larva";242;1
"Unit";"Zergling";"Larva";242;1
"Unit";"Zergling";"Larva";242;1
"Unit";"Zergling";"Larva";242;1
"Unit";"Roach";"Larva";242;2
"Unit";"Overlord";"Larva";242;0
"Upgrade";"ZergMeleeWeaponsLevel2";"EvolutionChamber";214;0
"Building";"Extractor";NA;286;0
"Upgrade";"ZergMissileWeaponsLevel1";"EvolutionChamber";242;0
"Building";"Extractor";NA;286;0
"Unit";"Overlord";"Larva";286;0
"Unit";"Overlord";"Larva";286;0
"Unit";"Overlord";"Larva";286;0
"Unit";"Overlord";"Larva";286;0
"Unit";"Overlord";"Larva";286;0
"Building";"Extractor";NA;286;0
"Building";"Extractor";NA;286;0
"Unit";"Baneling";"Zergling";287;0
"Unit";"Baneling";"Zergling";287;0
"Unit";"Baneling";"Zergling";287;0
"Unit";"Queen";"Hatchery";286;2
"Unit";"Baneling";"Zergling";287;0
"Unit";"Baneling";"Zergling";287;0
"Unit";"Queen";"Hatchery";286;2
"Unit";"Zergling";"Larva";289;1
"Unit";"Zergling";"Larva";289;1
"Unit";"Zergling";"Larva";291;1
"Unit";"Zergling";"Larva";291;1
"Unit";"Zergling";"Larva";291;1
"Unit";"Zergling";"Larva";291;1
"Unit";"Zergling";"Larva";291;1
"Unit";"Zergling";"Larva";291;1
"Unit";"Zergling";"Larva";291;1
"Unit";"Zergling";"Larva";291;1
"Unit";"Zergling";"Larva";291;1
"Unit";"Zergling";"Larva";291;1
"Unit";"Zergling";"Larva";291;1
"Unit";"Zergling";"Larva";291;1
"Unit";"Zergling";"Larva";291;1
"Unit";"Zergling";"Larva";291;1
"Unit";"Zergling";"Larva";291;1
"Unit";"Zergling";"Larva";291;1
"Unit";"Zergling";"Larva";291;1
"Unit";"Zergling";"Larva";291;1
"Unit";"Roach";"Larva";289;2
"Unit";"Roach";"Larva";289;2
"Unit";"Roach";"Larva";289;2
"Unit";"Zergling";"Larva";291;1
"Unit";"Zergling";"Larva";291;1
"Unit";"Zergling";"Larva";291;1
"Unit";"Zergling";"Larva";291;1
"Unit";"Zergling";"Larva";291;1
"Unit";"Zergling";"Larva";291;1
"Unit";"Zergling";"Larva";291;1
"Unit";"Zergling";"Larva";291;1
"Unit";"Zergling";"Larva";291;1
"Unit";"Zergling";"Larva";291;1
"Unit";"Zergling";"Larva";291;1
"Unit";"Zergling";"Larva";291;1
"Unit";"Zergling";"Larva";291;1
"Unit";"Zergling";"Larva";291;1
"Unit";"Zergling";"Larva";291;1
"Unit";"Zergling";"Larva";291;1
"Unit";"Zergling";"Larva";291;1
"Unit";"Zergling";"Larva";291;1
"Unit";"Zergling";"Larva";291;1
"Unit";"Zergling";"Larva";291;1
"Unit";"Roach";"Larva";291;2
"Unit";"Overlord";"Larva";291;0
"Unit";"Roach";"Larva";291;2
"Unit";"Roach";"Larva";291;2
"Unit";"Baneling";"Zergling";323;0
"Unit";"Baneling";"Zergling";323;0
"Unit";"Baneling";"Zergling";325;0
"Unit";"Baneling";"Zergling";335;0
"Building";"CreepTumor";NA;339;0
"Building";"CreepTumor";NA;339;0
"Unit";"Overlord";"Larva";339;0
"Unit";"Overlord";"Larva";339;0
"Unit";"Overlord";"Larva";339;0
"Unit";"Overlord";"Larva";339;0
"Unit";"Overlord";"Larva";339;0
"Unit";"Overlord";"Larva";339;0
"Building";"CreepTumorQueen";NA;343;0
"Building";"CreepTumorQueen";NA;343;0
"Building";"CreepTumorQueen";NA;343;0
"Unit";"Baneling";"Zergling";343;0
"Building";"CreepTumor";NA;343;0
"Unit";"Baneling";"Zergling";343;0
"Unit";"Baneling";"Zergling";343;0
"Unit";"Baneling";"Zergling";343;0
"Building";"InfestationPit";NA;344;0
"Building";"CreepTumor";NA;360;0
"Building";"SpineCrawler";NA;344;0
"Building";"CreepTumor";NA;360;0
"Upgrade";"ZergGroundArmorsLevel2";"EvolutionChamber";291;0
"Building";"CreepTumor";NA;360;0
"Building";"SpineCrawler";NA;344;0
"Building";"CreepTumor";NA;360;0
"Building";"SpineCrawler";NA;346;0
"Building";"CreepTumor";NA;360;0
"Building";"CreepTumor";NA;360;0
"Unit";"Baneling";"Zergling";360;0
"Unit";"Baneling";"Zergling";360;0
"Unit";"Baneling";"Zergling";360;0
"Unit";"Baneling";"Zergling";360;0
"Unit";"Zergling";"Larva";360;1
"Unit";"Zergling";"Larva";360;1
"Unit";"Zergling";"Larva";360;1
"Unit";"Zergling";"Larva";360;1
"Unit";"Zergling";"Larva";360;1
"Unit";"Zergling";"Larva";360;1
"Unit";"Zergling";"Larva";360;1
"Unit";"Zergling";"Larva";360;1
"Unit";"Zergling";"Larva";360;1
"Unit";"Zergling";"Larva";360;1
"Unit";"Zergling";"Larva";360;1
"Unit";"Zergling";"Larva";360;1
"Unit";"Zergling";"Larva";360;1
"Unit";"Zergling";"Larva";360;1
"Unit";"Zergling";"Larva";360;1
"Unit";"Zergling";"Larva";360;1
"Unit";"Roach";"Larva";360;2
"Unit";"Roach";"Larva";360;2
"Unit";"Roach";"Larva";360;2
"Unit";"Roach";"Larva";360;2
"Building";"Hatchery";NA;355;0
"Building";"CreepTumor";NA;376;0
"Unit";"Baneling";"Zergling";376;0
"Unit";"Baneling";"Zergling";376;0
"Unit";"Baneling";"Zergling";376;0
"Unit";"Baneling";"Zergling";376;0
"Unit";"Baneling";"Zergling";376;0
"Unit";"Baneling";"Zergling";376;0
"Unit";"Baneling";"Zergling";376;0
"Unit";"Baneling";"Zergling";376;0
"Unit";"Baneling";"Zergling";376;0
"Unit";"Baneling";"Zergling";376;0
"Unit";"Baneling";"Zergling";376;0
"Unit";"Baneling";"Zergling";376;0
"Unit";"Baneling";"Zergling";376;0
"Unit";"Baneling";"Zergling";376;0
"Unit";"Baneling";"Zergling";376;0
"Unit";"Baneling";"Zergling";376;0
"Unit";"Baneling";"Zergling";376;0
"Unit";"Baneling";"Zergling";376;0
"Unit";"Baneling";"Zergling";376;0
"Unit";"Baneling";"Zergling";376;0
"Unit";"Baneling";"Zergling";376;0
"Unit";"Baneling";"Zergling";376;0
"Unit";"Baneling";"Zergling";376;0
"Unit";"Baneling";"Zergling";376;0
"Unit";"Baneling";"Zergling";376;0
"Unit";"Baneling";"Zergling";376;0
"Unit";"Baneling";"Zergling";376;0
"Unit";"Baneling";"Zergling";376;0
"Unit";"Baneling";"Zergling";376;0
"Unit";"Baneling";"Zergling";376;0
"Unit";"Baneling";"Zergling";376;0
"Unit";"Baneling";"Zergling";384;0
"Unit";"Baneling";"Zergling";384;0
"Unit";"Baneling";"Zergling";384;0
"Unit";"Baneling";"Zergling";384;0
"Unit";"Baneling";"Zergling";384;0
"Unit";"Zergling";"Larva";384;1
"Unit";"Zergling";"Larva";384;1
"Unit";"Zergling";"Larva";384;1
"Unit";"Zergling";"Larva";384;1
"Unit";"Zergling";"Larva";384;1
"Unit";"Zergling";"Larva";384;1
"Unit";"Zergling";"Larva";384;1
"Unit";"Zergling";"Larva";384;1
"Unit";"Zergling";"Larva";384;1
"Unit";"Zergling";"Larva";384;1
"Unit";"Zergling";"Larva";384;1
"Unit";"Zergling";"Larva";384;1
"Unit";"Zergling";"Larva";384;1
"Unit";"Zergling";"Larva";384;1
"Unit";"Zergling";"Larva";384;1
"Unit";"Zergling";"Larva";384;1
"Unit";"Zergling";"Larva";384;1
"Unit";"Zergling";"Larva";384;1
"Unit";"Baneling";"Zergling";384;0
"Unit";"Baneling";"Zergling";384;0
"Unit";"Baneling";"Zergling";384;0
"Unit";"Roach";"Larva";384;2
"Unit";"Roach";"Larva";384;2
"Unit";"Roach";"Larva";384;2
"Unit";"Roach";"Larva";384;2
"Unit";"Roach";"Larva";384;2
"Unit";"Roach";"Larva";384;2
"Unit";"Roach";"Larva";384;2
"Unit";"Roach";"Larva";402;2
"Unit";"Roach";"Larva";402;2
"Unit";"Roach";"Larva";402;2
"Unit";"Roach";"Larva";402;2
"Unit";"Roach";"Larva";402;2
"Unit";"Roach";"Larva";402;2
"Unit";"Roach";"Larva";402;2
"Building";"CreepTumor";NA;438;0
"Building";"CreepTumor";NA;438;0
"Building";"Hatchery";NA;438;0
"Building";"Extractor";NA;438;0
"Building";"Extractor";NA;438;0
"Building";"Extractor";NA;438;0
"Building";"Hatchery";NA;438;0
"Building";"Hatchery";NA;438;0
"Building";"Hatchery";NA;438;0
"Building";"CreepTumor";NA;438;0
"Unit";"Viper";"Larva";438;3
"Building";"Hatchery";NA;438;0
"Building";"CreepTumor";NA;438;0
"Unit";"Viper";"Larva";438;3
"Building";"CreepTumor";NA;438;0
"Building";"CreepTumor";NA;438;0
"Building";"CreepTumorQueen";NA;438;0
"Building";"Hatchery";NA;438;0
"Building";"Hatchery";NA;438;0
"Building";"Hatchery";NA;438;0
"Building";"Extractor";NA;438;0
"Building";"Extractor";NA;438;0
"Upgrade";"ZergMissileWeaponsLevel2";"EvolutionChamber";438;0
"Building";"CreepTumorQueen";NA;444;0
"Unit";"Viper";"Larva";438;3
"Building";"CreepTumorQueen";NA;444;0
"Building";"CreepTumorQueen";NA;444;0
"Building";"CreepTumorQueen";NA;444;0
"Building";"CreepTumorQueen";NA;447;0
"Building";"CreepTumor";NA;447;0
"Building";"CreepTumorQueen";NA;447;0
"Building";"CreepTumor";NA;447;0
"Building";"CreepTumorQueen";NA;447;0
"Building";"CreepTumor";NA;447;0
"Building";"CreepTumorQueen";NA;447;0
"Unit";"Viper";"Larva";444;3
"Building";"CreepTumorQueen";NA;447;0
"Building";"CreepTumorQueen";NA;447;0
"Building";"CreepTumorQueen";NA;447;0
"Building";"CreepTumorQueen";NA;447;0
"Building";"CreepTumorQueen";NA;450;0
"Unit";"Viper";"Larva";447;3
"Building";"CreepTumorQueen";NA;450;0
"Building";"CreepTumorQueen";NA;450;0
"Building";"Hatchery";NA;438;0
"Building";"Extractor";NA;450;0
"Building";"CreepTumorQueen";NA;453;0
"Building";"CreepTumorQueen";NA;453;0
"Building";"CreepTumor";NA;453;0
"Building";"CreepTumorQueen";NA;453;0
"Building";"CreepTumor";NA;453;0
"Building";"CreepTumorQueen";NA;453;0
"Building";"CreepTumor";NA;453;0
"Building";"CreepTumor";NA;453;0
"Building";"CreepTumor";NA;453;0
"Building";"CreepTumorQueen";NA;453;0
"Building";"CreepTumorQueen";NA;453;0
"Unit";"Viper";"Larva";453;3
"Unit";"Viper";"Larva";453;3
"Unit";"Viper";"Larva";453;3
"Unit";"Viper";"Larva";453;3
"Unit";"Zergling";"Larva";453;1
"Unit";"Zergling";"Larva";453;1
"Unit";"Zergling";"Larva";453;1
"Unit";"Zergling";"Larva";453;1
"Unit";"Zergling";"Larva";453;1
"Unit";"Zergling";"Larva";453;1
"Unit";"Zergling";"Larva";453;1
"Unit";"Zergling";"Larva";453;1
"Unit";"Zergling";"Larva";453;1
"Unit";"Zergling";"Larva";453;1
"Unit";"Zergling";"Larva";453;1
"Unit";"Zergling";"Larva";453;1
"Unit";"Zergling";"Larva";453;1
"Unit";"Zergling";"Larva";453;1
"Unit";"Zergling";"Larva";453;1
"Unit";"Zergling";"Larva";453;1
"Unit";"Zergling";"Larva";453;1
"Unit";"Zergling";"Larva";453;1
"Unit";"Zergling";"Larva";453;1
"Unit";"Zergling";"Larva";453;1
"Unit";"Zergling";"Larva";453;1
"Unit";"Zergling";"Larva";453;1
"Unit";"Zergling";"Larva";453;1
"Unit";"Zergling";"Larva";453;1
"Unit";"Zergling";"Larva";453;1
"Unit";"Zergling";"Larva";453;1
"Unit";"Zergling";"Larva";453;1
"Unit";"Zergling";"Larva";453;1
"Unit";"Zergling";"Larva";453;1
"Unit";"Zergling";"Larva";453;1
"Unit";"Zergling";"Larva";453;1
"Unit";"Zergling";"Larva";453;1
"Unit";"Baneling";"Zergling";453;0
"Unit";"Baneling";"Zergling";453;0
"Unit";"Baneling";"Zergling";453;0
"Unit";"Baneling";"Zergling";453;0
"Unit";"Baneling";"Zergling";453;0
"Unit";"Baneling";"Zergling";453;0
"Unit";"Baneling";"Zergling";453;0
"Unit";"Baneling";"Zergling";453;0
"Unit";"Zergling";"Larva";453;1
"Unit";"Zergling";"Larva";453;1
"Unit";"Baneling";"Zergling";453;0
"Unit";"Baneling";"Zergling";453;0
"Unit";"Baneling";"Zergling";453;0
"Unit";"Baneling";"Zergling";453;0
"Unit";"Baneling";"Zergling";453;0
"Unit";"Baneling";"Zergling";453;0
"Unit";"Zergling";"Larva";453;1
"Unit";"Zergling";"Larva";453;1
"Unit";"Baneling";"Zergling";453;0
"Unit";"Zergling";"Larva";453;1
"Unit";"Zergling";"Larva";453;1
"Building";"CreepTumor";NA;453;0
"Unit";"Baneling";"Zergling";489;0
"Unit";"Baneling";"Zergling";489;0
"Unit";"Baneling";"Zergling";489;0
"Unit";"Baneling";"Zergling";491;0
"Unit";"Baneling";"Zergling";491;0
"Unit";"Baneling";"Zergling";491;0
"Unit";"Baneling";"Zergling";491;0
"Building";"Hatchery";NA;453;0
"Unit";"Baneling";"Zergling";503;0
"Unit";"Baneling";"Zergling";503;0
"Unit";"Baneling";"Zergling";503;0
"Unit";"Zergling";"Larva";503;1
"Unit";"Zergling";"Larva";503;1
"Unit";"Zergling";"Larva";503;1
"Unit";"Zergling";"Larva";503;1
"Unit";"Zergling";"Larva";503;1
"Unit";"Zergling";"Larva";503;1
"Unit";"Zergling";"Larva";503;1
"Unit";"Zergling";"Larva";503;1
"Unit";"Zergling";"Larva";503;1
"Unit";"Zergling";"Larva";503;1
"Unit";"Zergling";"Larva";503;1
"Unit";"Zergling";"Larva";503;1
"Unit";"Zergling";"Larva";503;1
"Unit";"Zergling";"Larva";503;1
"Unit";"Zergling";"Larva";503;1
"Unit";"Zergling";"Larva";503;1
"Unit";"Zergling";"Larva";503;1
"Unit";"Zergling";"Larva";503;1
"Unit";"Zergling";"Larva";503;1
"Unit";"Zergling";"Larva";503;1
"Unit";"Zergling";"Larva";503;1
"Unit";"Zergling";"Larva";503;1
"Unit";"Zergling";"Larva";503;1
"Unit";"Zergling";"Larva";503;1
"Unit";"Zergling";"Larva";503;1
"Unit";"Zergling";"Larva";503;1
"Unit";"Zergling";"Larva";503;1
"Unit";"Zergling";"Larva";503;1
"Building";"UltraliskCavern";NA;503;0
"Unit";"Zergling";"Larva";531;1
"Unit";"Zergling";"Larva";531;1
"Unit";"Zergling";"Larva";531;1
"Unit";"Zergling";"Larva";531;1
"Unit";"Zergling";"Larva";531;1
"Unit";"Zergling";"Larva";531;1
"Unit";"Zergling";"Larva";531;1
"Unit";"Zergling";"Larva";531;1
"Unit";"Roach";"Larva";531;2
"Unit";"Roach";"Larva";531;2
"Unit";"Roach";"Larva";531;2
"Unit";"Roach";"Larva";531;2
"Unit";"Roach";"Larva";531;2
"Unit";"Roach";"Larva";531;2
"Unit";"Roach";"Larva";531;2
"Unit";"Roach";"Larva";531;2
"Unit";"Roach";"Larva";531;2
"Unit";"Roach";"Larva";531;2
"Unit";"Roach";"Larva";531;2
"Unit";"Roach";"Larva";531;2
"Unit";"Roach";"Larva";531;2
"Unit";"Roach";"Larva";531;2
"Unit";"Roach";"Larva";531;2
"Unit";"Roach";"Larva";531;2
"Unit";"Roach";"Larva";531;2
"Unit";"Roach";"Larva";531;2
"Unit";"Roach";"Larva";531;2
"Unit";"Roach";"Larva";531;2
"Unit";"Roach";"Larva";531;2
"Unit";"Roach";"Larva";531;2
"Unit";"Zergling";"Larva";537;1
"Unit";"Zergling";"Larva";537;1
"Unit";"Zergling";"Larva";537;1
"Unit";"Zergling";"Larva";537;1
"Unit";"Zergling";"Larva";537;1
"Unit";"Zergling";"Larva";537;1
"Unit";"Zergling";"Larva";537;1
"Unit";"Zergling";"Larva";537;1
"Unit";"Zergling";"Larva";537;1
"Unit";"Zergling";"Larva";537;1
"Unit";"Zergling";"Larva";537;1
"Unit";"Zergling";"Larva";537;1
"Unit";"Zergling";"Larva";537;1
"Unit";"Zergling";"Larva";537;1
"Unit";"Zergling";"Larva";537;1
"Unit";"Zergling";"Larva";537;1
"Unit";"Zergling";"Larva";537;1
"Unit";"Zergling";"Larva";537;1
"Unit";"Zergling";"Larva";537;1
"Unit";"Zergling";"Larva";537;1
"Unit";"Zergling";"Larva";537;1
"Unit";"Zergling";"Larva";537;1
"Unit";"Zergling";"Larva";537;1
"Unit";"Zergling";"Larva";537;1
"Unit";"Zergling";"Larva";537;1
"Unit";"Zergling";"Larva";537;1
"Unit";"Zergling";"Larva";537;1
"Unit";"Zergling";"Larva";537;1
"Unit";"Zergling";"Larva";537;1
"Unit";"Zergling";"Larva";537;1
"Unit";"Zergling";"Larva";613;1
"Unit";"Zergling";"Larva";613;1
"Unit";"Zergling";"Larva";613;1
"Unit";"Zergling";"Larva";613;1
"Unit";"Zergling";"Larva";613;1
"Unit";"Zergling";"Larva";613;1
"Unit";"Zergling";"Larva";613;1
"Unit";"Zergling";"Larva";613;1
"Unit";"Zergling";"Larva";613;1
"Unit";"Zergling";"Larva";613;1
"Unit";"Zergling";"Larva";613;1
"Unit";"Zergling";"Larva";613;1
"Unit";"Zergling";"Larva";613;1
"Unit";"Zergling";"Larva";613;1
"Unit";"Zergling";"Larva";613;1
"Unit";"Zergling";"Larva";613;1
"Unit";"Zergling";"Larva";613;1
"Unit";"Zergling";"Larva";613;1
"Unit";"Zergling";"Larva";613;1
"Unit";"Zergling";"Larva";613;1
"Unit";"Zergling";"Larva";613;1
"Unit";"Zergling";"Larva";613;1
"Unit";"Zergling";"Larva";613;1
"Unit";"Zergling";"Larva";613;1
"Unit";"Zergling";"Larva";613;1
"Unit";"Zergling";"Larva";613;1
"Unit";"Zergling";"Larva";613;1
"Unit";"Zergling";"Larva";613;1
"Unit";"Zergling";"Larva";613;1
"Unit";"Zergling";"Larva";613;1
"Unit";"Zergling";"Larva";613;1
"Unit";"Zergling";"Larva";613;1
"Unit";"Ultralisk";"Larva";531;6
"Unit";"Ultralisk";"Larva";531;6
"Unit";"Baneling";"Zergling";613;0
"Unit";"Baneling";"Zergling";613;0
"Unit";"Baneling";"Zergling";613;0
"Unit";"Baneling";"Zergling";613;0
"Unit";"Baneling";"Zergling";613;0
"Unit";"Baneling";"Zergling";613;0
"Unit";"Baneling";"Zergling";613;0
"Unit";"Baneling";"Zergling";613;0
"Unit";"Baneling";"Zergling";613;0
"Unit";"Baneling";"Zergling";613;0
"Unit";"Baneling";"Zergling";613;0
"Unit";"Baneling";"Zergling";613;0
"Unit";"Baneling";"Zergling";613;0
"Unit";"Baneling";"Zergling";613;0
"Unit";"Baneling";"Zergling";613;0
"Unit";"Baneling";"Zergling";613;0
"Unit";"Baneling";"Zergling";613;0
"Unit";"Baneling";"Zergling";613;0
"Unit";"Baneling";"Zergling";613;0
"Unit";"Baneling";"Zergling";613;0
"Unit";"Baneling";"Zergling";613;0
"Unit";"Baneling";"Zergling";613;0
"Unit";"Baneling";"Zergling";613;0
"Unit";"Baneling";"Zergling";613;0
"Unit";"Baneling";"Zergling";613;0
"Upgrade";"ZergMeleeWeaponsLevel3";"EvolutionChamber";503;0
"Upgrade";"ZergGroundArmorsLevel3";"EvolutionChamber";503;0
"Upgrade";"ZergMissileWeaponsLevel3";"EvolutionChamber";503;0
"Unit";"Zergling";"Larva";657;1
"Unit";"Zergling";"Larva";657;1
"Unit";"Zergling";"Larva";657;1
"Unit";"Zergling";"Larva";657;1
"Unit";"Zergling";"Larva";657;1
"Unit";"Zergling";"Larva";657;1
"Unit";"Zergling";"Larva";657;1
"Unit";"Zergling";"Larva";657;1
"Unit";"Zergling";"Larva";657;1
"Unit";"Zergling";"Larva";657;1
"Unit";"Ultralisk";"Larva";657;6
"Unit";"Ultralisk";"Larva";657;6
"Building";"SpineCrawler";NA;657;0
"Building";"SpineCrawler";NA;657;0
"Unit";"Zergling";"Larva";679;1
"Unit";"Zergling";"Larva";679;1
"Unit";"Zergling";"Larva";679;1
"Unit";"Zergling";"Larva";679;1
"Unit";"Zergling";"Larva";679;1
"Unit";"Zergling";"Larva";679;1
"Unit";"Zergling";"Larva";679;1
"Unit";"Zergling";"Larva";679;1
"Unit";"Zergling";"Larva";679;1
"Unit";"Zergling";"Larva";679;1
"Unit";"Zergling";"Larva";679;1
"Unit";"Zergling";"Larva";679;1
"Unit";"Zergling";"Larva";679;1
"Unit";"Zergling";"Larva";679;1
"Unit";"Zergling";"Larva";679;1
"Unit";"Zergling";"Larva";679;1
"Unit";"Zergling";"Larva";679;1
"Unit";"Zergling";"Larva";679;1
"Unit";"Zergling";"Larva";679;1
"Unit";"Zergling";"Larva";679;1
"Unit";"Zergling";"Larva";679;1
"Unit";"Zergling";"Larva";679;1
"Unit";"Zergling";"Larva";679;1
"Unit";"Zergling";"Larva";679;1
"Unit";"Zergling";"Larva";679;1
"Unit";"Zergling";"Larva";679;1
"Unit";"Zergling";"Larva";679;1
"Unit";"Zergling";"Larva";679;1
"Unit";"Zergling";"Larva";679;1
"Unit";"Zergling";"Larva";679;1
"Unit";"Zergling";"Larva";679;1
"Unit";"Zergling";"Larva";679;1
"Unit";"Zergling";"Larva";679;1
"Unit";"Zergling";"Larva";679;1
"Unit";"Zergling";"Larva";679;1
"Unit";"Zergling";"Larva";679;1
"Unit";"Zergling";"Larva";679;1
"Unit";"Zergling";"Larva";679;1
"Unit";"Ultralisk";"Larva";679;6
"Unit";"Zergling";"Larva";717;1
"Unit";"Zergling";"Larva";717;1
"Unit";"Zergling";"Larva";717;1
"Unit";"Zergling";"Larva";717;1
"Unit";"Zergling";"Larva";717;1
"Unit";"Zergling";"Larva";717;1
"Unit";"Zergling";"Larva";717;1
"Unit";"Zergling";"Larva";717;1
"Unit";"Zergling";"Larva";717;1
"Unit";"Zergling";"Larva";717;1
"Unit";"Zergling";"Larva";717;1
"Unit";"Zergling";"Larva";717;1
"Unit";"Zergling";"Larva";717;1
"Unit";"Zergling";"Larva";717;1
"Unit";"Zergling";"Larva";717;1
"Unit";"Zergling";"Larva";717;1
"Unit";"Zergling";"Larva";717;1
"Unit";"Zergling";"Larva";717;1
"Unit";"Zergling";"Larva";717;1
"Unit";"Zergling";"Larva";717;1
"Unit";"Zergling";"Larva";717;1
"Unit";"Zergling";"Larva";717;1
"Unit";"Zergling";"Larva";717;1
"Unit";"Zergling";"Larva";717;1
"Unit";"Zergling";"Larva";717;1
"Unit";"Zergling";"Larva";717;1
"Unit";"Zergling";"Larva";717;1
"Unit";"Zergling";"Larva";717;1
"Unit";"Zergling";"Larva";717;1
"Unit";"Zergling";"Larva";717;1
"Unit";"Zergling";"Larva";717;1
"Unit";"Zergling";"Larva";717;1
"Unit";"Zergling";"Larva";717;1
"Unit";"Zergling";"Larva";717;1
"Unit";"Zergling";"Larva";717;1
"Unit";"Zergling";"Larva";717;1
"Unit";"Zergling";"Larva";717;1
"Unit";"Zergling";"Larva";717;1
"Unit";"Zergling";"Larva";717;1
"Unit";"Zergling";"Larva";717;1
"Unit";"Zergling";"Larva";717;1
"Unit";"Zergling";"Larva";717;1
"Unit";"Zergling";"Larva";717;1
"Unit";"Zergling";"Larva";717;1
"Unit";"Zergling";"Larva";717;1
"Unit";"Zergling";"Larva";717;1
"Unit";"Zergling";"Larva";717;1
"Unit";"Zergling";"Larva";717;1
"Unit";"Zergling";"Larva";717;1
"Unit";"Zergling";"Larva";717;1
"Unit";"Zergling";"Larva";717;1
"Unit";"Zergling";"Larva";717;1
"Unit";"Zergling";"Larva";717;1
"Unit";"Zergling";"Larva";717;1
"Unit";"Zergling";"Larva";717;1
"Unit";"Zergling";"Larva";717;1
"Unit";"Zergling";"Larva";717;1
"Unit";"Zergling";"Larva";717;1
"Unit";"Zergling";"Larva";717;1
"Unit";"Zergling";"Larva";717;1
"Unit";"Zergling";"Larva";723;1
"Unit";"Zergling";"Larva";723;1
"Unit";"Zergling";"Larva";723;1
"Unit";"Zergling";"Larva";723;1
"Unit";"Zergling";"Larva";723;1
"Unit";"Zergling";"Larva";723;1
"Unit";"Zergling";"Larva";723;1
"Unit";"Zergling";"Larva";723;1
"Unit";"Zergling";"Larva";723;1
"Unit";"Zergling";"Larva";723;1
"Unit";"Zergling";"Larva";723;1
"Unit";"Zergling";"Larva";723;1
"Unit";"Zergling";"Larva";723;1
"Unit";"Zergling";"Larva";723;1
"Unit";"Zergling";"Larva";723;1
"Unit";"Zergling";"Larva";723;1
"Unit";"Zergling";"Larva";723;1
"Unit";"Zergling";"Larva";723;1
"Unit";"Zergling";"Larva";723;1
"Unit";"Zergling";"Larva";723;1
"Unit";"Zergling";"Larva";723;1
"Unit";"Zergling";"Larva";723;1
