"type";"unit_name";"on_building";"total_supply";"supply"
"Unit";"Overlord";"Larva";13;0
"Building";"SpawningPool";NA;18;0
"Building";"Hatchery";NA;16;0
"Unit";"Zergling";"Larva";24;1
"Unit";"Zergling";"Larva";24;1
"Unit";"Zergling";"Larva";24;1
"Unit";"Zergling";"Larva";24;1
"Unit";"Overlord";"Larva";24;0
"Unit";"Queen";"Hatchery";24;2
"Unit";"Queen";"Hatchery";24;2
"Unit";"Overlord";"Larva";29;0
"Building";"Hatchery";NA;22;0
"Unit";"Overlord";"Larva";36;0
"Unit";"Queen";"Hatchery";32;2
"Unit";"Queen";"Hatchery";34;2
"Building";"CreepTumorQueen";NA;37;0
"Building";"CreepTumorQueen";NA;44;0
"Unit";"Queen";"Hatchery";37;2
"Building";"CreepTumor";NA;54;0
"Building";"CreepTumorQueen";NA;57;0
"Building";"CreepTumor";NA;60;0
"Building";"CreepTumorQueen";NA;60;0
"Unit";"Overlord";"Larva";60;0
"Unit";"Overlord";"Larva";60;0
"Unit";"Overlord";"Larva";62;0
"Unit";"Overlord";"Larva";62;0
"Unit";"Overlord";"Larva";63;0
"Building";"SpineCrawler";NA;63;0
"Building";"SpineCrawler";NA;63;0
"Building";"Extractor";NA;67;0
"Building";"Extractor";NA;67;0
"Building";"CreepTumor";NA;80;0
"Unit";"Overlord";"Larva";80;0
"Unit";"Queen";"Hatchery";67;2
"Unit";"Queen";"Hatchery";67;2
"Building";"Extractor";NA;80;0
"Building";"Extractor";NA;80;0
"Building";"Extractor";NA;80;0
"Building";"Extractor";NA;80;0
"Building";"Hatchery";NA;63;0
"Building";"CreepTumorQueen";NA;89;0
"Unit";"Queen";"Hatchery";80;2
"Unit";"Queen";"Hatchery";85;2
"Building";"CreepTumor";NA;95;0
"Building";"CreepTumorQueen";NA;108;0
"Building";"CreepTumorQueen";NA;110;0
"Building";"EvolutionChamber";NA;95;0
"Building";"CreepTumorQueen";NA;116;0
"Building";"EvolutionChamber";NA;95;0
"Unit";"Overlord";"Larva";116;0
"Building";"CreepTumorQueen";NA;120;0
"Unit";"Overlord";"Larva";116;0
"Unit";"Overlord";"Larva";116;0
"Unit";"Overlord";"Larva";116;0
"Unit";"Overlord";"Larva";116;0
"Unit";"Queen";"Hatchery";95;2
"Unit";"Overlord";"Larva";120;0
"Building";"CreepTumorQueen";NA;120;0
"Building";"CreepTumor";NA;120;0
"Building";"CreepTumor";NA;120;0
"Building";"CreepTumorQueen";NA;120;0
"Unit";"Overlord";"Larva";120;0
"Building";"CreepTumor";NA;120;0
"Building";"CreepTumorQueen";NA;122;0
"Building";"SpineCrawler";NA;120;0
"Building";"CreepTumorQueen";NA;122;0
"Building";"CreepTumorQueen";NA;122;0
"Unit";"Overlord";"Larva";122;0
"Unit";"Overlord";"Larva";122;0
"Building";"CreepTumorQueen";NA;122;0
"Building";"CreepTumorQueen";NA;122;0
"Building";"CreepTumor";NA;122;0
"Building";"CreepTumor";NA;122;0
"Building";"CreepTumor";NA;122;0
"Building";"CreepTumor";NA;122;0
"Building";"CreepTumorQueen";NA;122;0
"Unit";"Overlord";"Larva";122;0
"Unit";"Overlord";"Larva";122;0
"Building";"CreepTumor";NA;122;0
"Building";"CreepTumor";NA;122;0
"Unit";"Zergling";"Larva";122;1
"Unit";"Zergling";"Larva";122;1
"Unit";"Overlord";"Larva";122;0
"Building";"BanelingNest";NA;122;0
"Unit";"Overlord";"Larva";122;0
"Unit";"Zergling";"Larva";122;1
"Unit";"Zergling";"Larva";122;1
"Unit";"Zergling";"Larva";122;1
"Unit";"Zergling";"Larva";122;1
"Unit";"Zergling";"Larva";122;1
"Unit";"Zergling";"Larva";122;1
"Unit";"Zergling";"Larva";122;1
"Unit";"Zergling";"Larva";122;1
"Unit";"Zergling";"Larva";122;1
"Unit";"Zergling";"Larva";122;1
"Unit";"Zergling";"Larva";122;1
"Unit";"Zergling";"Larva";122;1
"Unit";"Zergling";"Larva";122;1
"Unit";"Zergling";"Larva";122;1
"Unit";"Zergling";"Larva";122;1
"Unit";"Zergling";"Larva";122;1
"Unit";"Zergling";"Larva";122;1
"Unit";"Zergling";"Larva";122;1
"Unit";"Zergling";"Larva";122;1
"Unit";"Zergling";"Larva";122;1
"Unit";"Zergling";"Larva";122;1
"Unit";"Zergling";"Larva";122;1
"Unit";"Zergling";"Larva";122;1
"Unit";"Zergling";"Larva";122;1
"Unit";"Zergling";"Larva";122;1
"Unit";"Zergling";"Larva";122;1
"Unit";"Zergling";"Larva";122;1
"Unit";"Zergling";"Larva";122;1
"Building";"CreepTumorQueen";NA;122;0
"Unit";"Zergling";"Larva";122;1
"Unit";"Zergling";"Larva";122;1
"Unit";"Zergling";"Larva";122;1
"Unit";"Zergling";"Larva";122;1
"Building";"CreepTumorQueen";NA;156;0
"Unit";"Zergling";"Larva";152;1
"Unit";"Zergling";"Larva";152;1
"Unit";"Zergling";"Larva";152;1
"Unit";"Zergling";"Larva";152;1
"Unit";"Zergling";"Larva";152;1
"Unit";"Zergling";"Larva";152;1
"Unit";"Zergling";"Larva";152;1
"Unit";"Zergling";"Larva";152;1
"Unit";"Zergling";"Larva";152;1
"Unit";"Zergling";"Larva";152;1
"Unit";"Zergling";"Larva";152;1
"Unit";"Zergling";"Larva";152;1
"Unit";"Zergling";"Larva";152;1
"Unit";"Zergling";"Larva";152;1
"Unit";"Zergling";"Larva";152;1
"Unit";"Zergling";"Larva";152;1
"Unit";"Zergling";"Larva";152;1
"Unit";"Zergling";"Larva";152;1
"Building";"CreepTumor";NA;156;0
"Unit";"Overlord";"Larva";156;0
"Building";"HydraliskDen";NA;156;0
"Building";"CreepTumorQueen";NA;180;0
"Building";"CreepTumor";NA;180;0
"Building";"CreepTumor";NA;180;0
"Building";"CreepTumor";NA;180;0
"Building";"CreepTumor";NA;180;0
"Building";"CreepTumor";NA;180;0
"Building";"CreepTumorQueen";NA;190;0
"Building";"InfestationPit";NA;156;0
"Upgrade";"ZergMeleeWeaponsLevel1";"EvolutionChamber";122;0
"Building";"CreepTumorQueen";NA;190;0
"Upgrade";"ZergGroundArmorsLevel1";"EvolutionChamber";122;0
"Building";"CreepTumor";NA;190;0
"Building";"CreepTumor";NA;190;0
"Building";"CreepTumor";NA;190;0
"Building";"CreepTumor";NA;190;0
"Building";"CreepTumor";NA;190;0
"Building";"CreepTumor";NA;190;0
"Unit";"Overlord";"Larva";190;0
"Unit";"Hydralisk";"Larva";190;2
"Unit";"Hydralisk";"Larva";190;2
"Unit";"Hydralisk";"Larva";190;2
"Unit";"Hydralisk";"Larva";190;2
"Unit";"Hydralisk";"Larva";190;2
"Unit";"Hydralisk";"Larva";190;2
"Unit";"Hydralisk";"Larva";190;2
"Unit";"Hydralisk";"Larva";190;2
"Unit";"Hydralisk";"Larva";190;2
"Unit";"Hydralisk";"Larva";190;2
"Unit";"Hydralisk";"Larva";190;2
"Unit";"Hydralisk";"Larva";190;2
"Unit";"Hydralisk";"Larva";190;2
"Unit";"Baneling";"Zergling";190;0
"Unit";"Baneling";"Zergling";190;0
"Unit";"Baneling";"Zergling";190;0
"Unit";"Baneling";"Zergling";190;0
"Unit";"Baneling";"Zergling";190;0
"Unit";"Baneling";"Zergling";190;0
"Unit";"Baneling";"Zergling";190;0
"Unit";"Baneling";"Zergling";190;0
"Unit";"Baneling";"Zergling";190;0
"Unit";"Baneling";"Zergling";190;0
"Unit";"Baneling";"Zergling";190;0
"Unit";"Baneling";"Zergling";190;0
"Unit";"Baneling";"Zergling";190;0
"Unit";"Baneling";"Zergling";190;0
"Building";"CreepTumor";NA;190;0
"Building";"CreepTumor";NA;190;0
"Unit";"Zergling";"Larva";190;1
"Unit";"Zergling";"Larva";190;1
"Unit";"Zergling";"Larva";190;1
"Unit";"Zergling";"Larva";190;1
"Unit";"Zergling";"Larva";190;1
"Unit";"Zergling";"Larva";190;1
"Unit";"Zergling";"Larva";190;1
"Unit";"Zergling";"Larva";190;1
"Unit";"Zergling";"Larva";190;1
"Unit";"Zergling";"Larva";190;1
"Unit";"Zergling";"Larva";190;1
"Unit";"Zergling";"Larva";190;1
"Unit";"Zergling";"Larva";190;1
"Unit";"Zergling";"Larva";190;1
"Unit";"Zergling";"Larva";190;1
"Unit";"Zergling";"Larva";190;1
"Building";"CreepTumorQueen";NA;216;0
"Building";"CreepTumorQueen";NA;216;0
"Building";"CreepTumorQueen";NA;218;0
"Building";"CreepTumorQueen";NA;232;0
"Building";"Hatchery";NA;180;0
"Building";"Hatchery";NA;185;0
"Building";"CreepTumor";NA;232;0
"Building";"CreepTumor";NA;232;0
"Unit";"Zergling";"Larva";232;1
"Unit";"Zergling";"Larva";232;1
"Unit";"Zergling";"Larva";232;1
"Unit";"Zergling";"Larva";232;1
"Unit";"Zergling";"Larva";232;1
"Unit";"Zergling";"Larva";232;1
"Unit";"Zergling";"Larva";232;1
"Unit";"Zergling";"Larva";232;1
"Unit";"Zergling";"Larva";232;1
"Unit";"Zergling";"Larva";232;1
"Unit";"Zergling";"Larva";232;1
"Unit";"Zergling";"Larva";232;1
"Unit";"Zergling";"Larva";232;1
"Unit";"Zergling";"Larva";232;1
"Unit";"Zergling";"Larva";232;1
"Unit";"Zergling";"Larva";232;1
"Unit";"Zergling";"Larva";232;1
"Unit";"Zergling";"Larva";232;1
"Unit";"Zergling";"Larva";232;1
"Unit";"Zergling";"Larva";232;1
"Unit";"Zergling";"Larva";232;1
"Unit";"Zergling";"Larva";232;1
"Unit";"Zergling";"Larva";232;1
"Unit";"Zergling";"Larva";232;1
"Unit";"Zergling";"Larva";232;1
"Unit";"Zergling";"Larva";232;1
"Unit";"Zergling";"Larva";232;1
"Unit";"Zergling";"Larva";232;1
"Unit";"Zergling";"Larva";232;1
"Unit";"Zergling";"Larva";232;1
"Unit";"Zergling";"Larva";232;1
"Unit";"Zergling";"Larva";232;1
"Unit";"Zergling";"Larva";232;1
"Unit";"Zergling";"Larva";232;1
"Unit";"Zergling";"Larva";232;1
"Unit";"Zergling";"Larva";232;1
"Upgrade";"EvolveMuscularAugments";"HydraliskDen";190;0
"Building";"CreepTumor";NA;232;0
"Building";"CreepTumor";NA;232;0
"Building";"Extractor";NA;232;0
"Building";"Extractor";NA;232;0
"Unit";"Baneling";"Zergling";278;0
"Unit";"Baneling";"Zergling";278;0
"Unit";"Baneling";"Zergling";278;0
"Unit";"Baneling";"Zergling";278;0
"Unit";"Baneling";"Zergling";278;0
"Unit";"Zergling";"Larva";269;1
"Unit";"Zergling";"Larva";269;1
"Unit";"Baneling";"Zergling";278;0
"Unit";"Baneling";"Zergling";278;0
"Unit";"Baneling";"Zergling";278;0
"Unit";"Baneling";"Zergling";278;0
"Unit";"Baneling";"Zergling";278;0
"Unit";"Baneling";"Zergling";278;0
"Unit";"Baneling";"Zergling";278;0
"Unit";"Baneling";"Zergling";278;0
"Unit";"Zergling";"Larva";269;1
"Unit";"Zergling";"Larva";269;1
"Unit";"Zergling";"Larva";269;1
"Unit";"Zergling";"Larva";269;1
"Unit";"Baneling";"Zergling";278;0
"Unit";"Zergling";"Larva";269;1
"Unit";"Zergling";"Larva";269;1
"Unit";"Zergling";"Larva";269;1
"Unit";"Zergling";"Larva";269;1
"Unit";"Zergling";"Larva";269;1
"Unit";"Zergling";"Larva";269;1
"Unit";"Zergling";"Larva";269;1
"Unit";"Zergling";"Larva";269;1
"Unit";"Zergling";"Larva";270;1
"Unit";"Zergling";"Larva";270;1
"Unit";"Zergling";"Larva";270;1
"Unit";"Zergling";"Larva";270;1
"Unit";"Zergling";"Larva";270;1
"Unit";"Zergling";"Larva";270;1
"Unit";"Zergling";"Larva";270;1
"Unit";"Zergling";"Larva";270;1
"Building";"CreepTumorQueen";NA;278;0
"Building";"CreepTumorQueen";NA;278;0
"Building";"CreepTumorQueen";NA;280;0
"Building";"CreepTumorQueen";NA;300;0
"Building";"CreepTumor";NA;300;0
"Building";"CreepTumor";NA;300;0
"Building";"SporeCrawler";NA;300;0
"Building";"CreepTumor";NA;300;0
"Building";"CreepTumor";NA;300;0
"Building";"SporeCrawler";NA;300;0
"Building";"CreepTumor";NA;300;0
"Unit";"Overlord";"Larva";300;0
"Building";"CreepTumor";NA;300;0
"Unit";"Overlord";"Larva";300;0
"Building";"SporeCrawler";NA;300;0
"Building";"SporeCrawler";NA;300;0
"Building";"SporeCrawler";NA;300;0
"Building";"CreepTumor";NA;300;0
"Building";"CreepTumor";NA;300;0
"Building";"CreepTumor";NA;300;0
"Building";"SporeCrawler";NA;300;0
"Building";"CreepTumorQueen";NA;300;0
"Unit";"Zergling";"Larva";300;1
"Unit";"Zergling";"Larva";300;1
"Building";"CreepTumor";NA;300;0
"Unit";"Zergling";"Larva";300;1
"Unit";"Zergling";"Larva";300;1
"Unit";"Zergling";"Larva";300;1
"Unit";"Zergling";"Larva";300;1
"Unit";"Zergling";"Larva";300;1
"Unit";"Zergling";"Larva";300;1
"Unit";"Zergling";"Larva";300;1
"Unit";"Zergling";"Larva";300;1
"Unit";"Zergling";"Larva";300;1
"Unit";"Zergling";"Larva";300;1
"Unit";"Zergling";"Larva";300;1
"Unit";"Zergling";"Larva";300;1
"Unit";"Zergling";"Larva";300;1
"Unit";"Zergling";"Larva";300;1
"Unit";"Zergling";"Larva";300;1
"Unit";"Zergling";"Larva";300;1
"Unit";"Zergling";"Larva";300;1
"Unit";"Zergling";"Larva";300;1
"Unit";"Zergling";"Larva";300;1
"Unit";"Zergling";"Larva";300;1
"Unit";"Zergling";"Larva";300;1
"Unit";"Zergling";"Larva";300;1
"Unit";"Zergling";"Larva";300;1
"Unit";"Zergling";"Larva";300;1
"Unit";"Zergling";"Larva";300;1
"Unit";"Zergling";"Larva";300;1
"Unit";"Zergling";"Larva";300;1
"Unit";"Zergling";"Larva";300;1
"Unit";"Zergling";"Larva";300;1
"Unit";"Zergling";"Larva";300;1
"Unit";"Zergling";"Larva";300;1
"Unit";"Zergling";"Larva";300;1
"Unit";"Zergling";"Larva";300;1
"Unit";"Zergling";"Larva";300;1
"Unit";"Zergling";"Larva";300;1
"Unit";"Zergling";"Larva";300;1
"Unit";"Zergling";"Larva";300;1
"Unit";"Zergling";"Larva";300;1
"Unit";"Zergling";"Larva";300;1
"Unit";"Zergling";"Larva";300;1
"Unit";"Zergling";"Larva";300;1
"Unit";"Zergling";"Larva";300;1
"Unit";"Zergling";"Larva";300;1
"Unit";"Zergling";"Larva";300;1
"Unit";"Zergling";"Larva";300;1
"Unit";"Zergling";"Larva";300;1
"Unit";"Zergling";"Larva";300;1
"Unit";"Zergling";"Larva";300;1
"Upgrade";"ZergMeleeWeaponsLevel2";"EvolutionChamber";232;0
"Upgrade";"ZergGroundArmorsLevel2";"EvolutionChamber";232;0
"Building";"Hatchery";NA;278;0
"Building";"UltraliskCavern";NA;300;0
"Building";"Extractor";NA;350;0
"Building";"Extractor";NA;350;0
"Building";"CreepTumor";NA;350;0
"Unit";"Viper";"Larva";350;3
"Unit";"Viper";"Larva";350;3
"Unit";"Viper";"Larva";350;3
"Unit";"Viper";"Larva";350;3
"Building";"SpineCrawler";NA;350;0
"Building";"SpineCrawler";NA;350;0
"Unit";"Zergling";"Larva";350;1
"Unit";"Zergling";"Larva";350;1
"Unit";"Zergling";"Larva";350;1
"Unit";"Zergling";"Larva";350;1
"Unit";"Zergling";"Larva";350;1
"Unit";"Zergling";"Larva";350;1
"Unit";"Zergling";"Larva";350;1
"Unit";"Zergling";"Larva";350;1
"Unit";"Zergling";"Larva";350;1
"Unit";"Zergling";"Larva";350;1
"Unit";"Zergling";"Larva";350;1
"Unit";"Zergling";"Larva";350;1
"Unit";"Zergling";"Larva";350;1
"Unit";"Zergling";"Larva";350;1
"Unit";"Zergling";"Larva";350;1
"Unit";"Zergling";"Larva";350;1
"Unit";"Zergling";"Larva";350;1
"Unit";"Zergling";"Larva";350;1
"Unit";"Zergling";"Larva";350;1
"Unit";"Zergling";"Larva";350;1
"Unit";"Zergling";"Larva";350;1
"Unit";"Zergling";"Larva";350;1
"Unit";"Zergling";"Larva";350;1
"Unit";"Zergling";"Larva";350;1
"Unit";"Zergling";"Larva";350;1
"Unit";"Zergling";"Larva";350;1
"Unit";"Zergling";"Larva";350;1
"Unit";"Zergling";"Larva";350;1
"Unit";"Zergling";"Larva";350;1
"Unit";"Zergling";"Larva";350;1
"Unit";"Zergling";"Larva";350;1
"Unit";"Zergling";"Larva";350;1
"Unit";"Zergling";"Larva";350;1
"Unit";"Zergling";"Larva";350;1
"Unit";"Zergling";"Larva";350;1
"Unit";"Zergling";"Larva";350;1
"Unit";"Zergling";"Larva";350;1
"Unit";"Zergling";"Larva";350;1
"Unit";"Zergling";"Larva";350;1
"Unit";"Zergling";"Larva";350;1
"Unit";"Zergling";"Larva";350;1
"Unit";"Zergling";"Larva";350;1
"Unit";"Zergling";"Larva";350;1
"Unit";"Zergling";"Larva";350;1
"Unit";"Zergling";"Larva";350;1
"Unit";"Zergling";"Larva";350;1
"Unit";"Zergling";"Larva";350;1
"Unit";"Zergling";"Larva";350;1
"Unit";"Zergling";"Larva";350;1
"Unit";"Zergling";"Larva";350;1
"Unit";"Zergling";"Larva";350;1
"Unit";"Zergling";"Larva";350;1
"Unit";"Zergling";"Larva";350;1
"Unit";"Zergling";"Larva";350;1
"Unit";"Zergling";"Larva";350;1
"Unit";"Zergling";"Larva";350;1
"Unit";"Baneling";"Zergling";362;0
"Unit";"Baneling";"Zergling";362;0
"Unit";"Baneling";"Zergling";362;0
"Unit";"Baneling";"Zergling";362;0
"Unit";"Baneling";"Zergling";362;0
"Unit";"Baneling";"Zergling";362;0
"Unit";"Baneling";"Zergling";362;0
"Unit";"Baneling";"Zergling";362;0
"Unit";"Baneling";"Zergling";362;0
"Unit";"Baneling";"Zergling";362;0
"Unit";"Baneling";"Zergling";362;0
"Unit";"Baneling";"Zergling";362;0
"Unit";"Baneling";"Zergling";362;0
"Unit";"Baneling";"Zergling";362;0
"Unit";"Baneling";"Zergling";362;0
"Unit";"Baneling";"Zergling";362;0
"Unit";"Baneling";"Zergling";362;0
"Unit";"Baneling";"Zergling";362;0
"Unit";"Baneling";"Zergling";362;0
"Unit";"Baneling";"Zergling";362;0
"Unit";"Baneling";"Zergling";362;0
"Unit";"Baneling";"Zergling";362;0
"Unit";"Baneling";"Zergling";362;0
"Unit";"Baneling";"Zergling";362;0
"Unit";"Baneling";"Zergling";362;0
"Unit";"Baneling";"Zergling";362;0
"Unit";"Baneling";"Zergling";362;0
"Unit";"Baneling";"Zergling";362;0
"Unit";"Baneling";"Zergling";362;0
"Unit";"Baneling";"Zergling";362;0
"Unit";"Baneling";"Zergling";362;0
"Unit";"Baneling";"Zergling";362;0
"Unit";"Baneling";"Zergling";362;0
"Unit";"Baneling";"Zergling";362;0
"Unit";"Baneling";"Zergling";362;0
"Unit";"Baneling";"Zergling";362;0
"Unit";"Baneling";"Zergling";362;0
"Unit";"Baneling";"Zergling";362;0
"Unit";"Baneling";"Zergling";362;0
"Unit";"Baneling";"Zergling";362;0
"Unit";"Baneling";"Zergling";362;0
"Unit";"Baneling";"Zergling";362;0
"Unit";"Baneling";"Zergling";362;0
"Unit";"Baneling";"Zergling";362;0
"Unit";"Baneling";"Zergling";362;0
"Unit";"Zergling";"Larva";362;1
"Unit";"Zergling";"Larva";362;1
"Unit";"Zergling";"Larva";362;1
"Unit";"Zergling";"Larva";362;1
"Unit";"Zergling";"Larva";362;1
"Unit";"Zergling";"Larva";362;1
"Unit";"Zergling";"Larva";362;1
"Unit";"Zergling";"Larva";362;1
"Unit";"Zergling";"Larva";362;1
"Unit";"Zergling";"Larva";362;1
"Unit";"Zergling";"Larva";362;1
"Unit";"Zergling";"Larva";362;1
"Unit";"Zergling";"Larva";362;1
"Unit";"Zergling";"Larva";362;1
"Unit";"Zergling";"Larva";362;1
"Unit";"Zergling";"Larva";362;1
"Unit";"Zergling";"Larva";362;1
"Unit";"Zergling";"Larva";362;1
"Unit";"Zergling";"Larva";362;1
"Unit";"Zergling";"Larva";362;1
"Unit";"Zergling";"Larva";418;1
"Unit";"Zergling";"Larva";418;1
"Unit";"Zergling";"Larva";418;1
"Unit";"Zergling";"Larva";418;1
"Unit";"Zergling";"Larva";418;1
"Unit";"Zergling";"Larva";418;1
"Unit";"Zergling";"Larva";418;1
"Unit";"Zergling";"Larva";418;1
"Unit";"Zergling";"Larva";418;1
"Unit";"Zergling";"Larva";418;1
"Unit";"Zergling";"Larva";418;1
"Unit";"Zergling";"Larva";418;1
"Unit";"Zergling";"Larva";418;1
"Unit";"Zergling";"Larva";418;1
"Unit";"Zergling";"Larva";418;1
"Unit";"Zergling";"Larva";418;1
"Unit";"Zergling";"Larva";418;1
"Unit";"Zergling";"Larva";418;1
"Unit";"Zergling";"Larva";438;1
"Unit";"Zergling";"Larva";438;1
"Unit";"Zergling";"Larva";438;1
"Unit";"Zergling";"Larva";438;1
"Unit";"Zergling";"Larva";438;1
"Unit";"Zergling";"Larva";438;1
"Unit";"Zergling";"Larva";438;1
"Unit";"Zergling";"Larva";438;1
"Unit";"Zergling";"Larva";438;1
"Unit";"Zergling";"Larva";438;1
"Unit";"Zergling";"Larva";438;1
"Unit";"Zergling";"Larva";438;1
"Unit";"Zergling";"Larva";438;1
"Unit";"Zergling";"Larva";438;1
"Unit";"Zergling";"Larva";438;1
"Unit";"Zergling";"Larva";438;1
"Unit";"Zergling";"Larva";438;1
"Unit";"Zergling";"Larva";438;1
"Unit";"Zergling";"Larva";438;1
"Unit";"Zergling";"Larva";438;1
"Unit";"Zergling";"Larva";438;1
"Unit";"Zergling";"Larva";438;1
"Unit";"Zergling";"Larva";438;1
"Unit";"Zergling";"Larva";438;1
"Building";"CreepTumorQueen";NA;458;0
"Building";"CreepTumorQueen";NA;480;0
"Building";"CreepTumorQueen";NA;480;0
"Building";"CreepTumorQueen";NA;480;0
"Building";"CreepTumor";NA;480;0
"Building";"CreepTumor";NA;480;0
"Building";"CreepTumor";NA;481;0
"Building";"CreepTumorQueen";NA;491;0
"Building";"CreepTumorQueen";NA;491;0
"Building";"CreepTumor";NA;491;0
"Building";"CreepTumor";NA;491;0
"Building";"CreepTumor";NA;491;0
"Building";"CreepTumorQueen";NA;491;0
"Building";"CreepTumorQueen";NA;491;0
"Building";"CreepTumorQueen";NA;491;0
"Building";"CreepTumor";NA;491;0
"Unit";"Ultralisk";"Larva";486;6
"Unit";"Overlord";"Larva";491;0
"Building";"Extractor";NA;491;0
"Building";"Extractor";NA;491;0
"Building";"CreepTumor";NA;491;0
"Building";"CreepTumorQueen";NA;497;0
"Unit";"Ultralisk";"Larva";491;6
"Unit";"Ultralisk";"Larva";491;6
"Building";"CreepTumorQueen";NA;497;0
"Building";"CreepTumor";NA;497;0
"Building";"CreepTumor";NA;497;0
"Unit";"Viper";"Larva";491;3
"Unit";"Viper";"Larva";491;3
"Building";"CreepTumorQueen";NA;497;0
"Unit";"Viper";"Larva";491;3
"Building";"CreepTumorQueen";NA;497;0
"Unit";"Baneling";"Zergling";497;0
"Unit";"Baneling";"Zergling";497;0
"Unit";"Baneling";"Zergling";497;0
"Unit";"Baneling";"Zergling";497;0
"Unit";"Baneling";"Zergling";497;0
"Unit";"Zergling";"Larva";497;1
"Unit";"Zergling";"Larva";497;1
"Unit";"Zergling";"Larva";497;1
"Unit";"Zergling";"Larva";497;1
"Unit";"Zergling";"Larva";497;1
"Unit";"Zergling";"Larva";497;1
"Unit";"Zergling";"Larva";497;1
"Unit";"Zergling";"Larva";497;1
"Unit";"Baneling";"Zergling";497;0
"Unit";"Zergling";"Larva";497;1
"Unit";"Zergling";"Larva";497;1
"Unit";"Zergling";"Larva";497;1
"Unit";"Zergling";"Larva";497;1
"Unit";"Zergling";"Larva";497;1
"Unit";"Zergling";"Larva";497;1
"Unit";"Zergling";"Larva";497;1
"Unit";"Zergling";"Larva";497;1
"Unit";"Zergling";"Larva";497;1
"Unit";"Zergling";"Larva";497;1
"Unit";"Zergling";"Larva";497;1
"Unit";"Zergling";"Larva";497;1
"Unit";"Zergling";"Larva";497;1
"Unit";"Zergling";"Larva";497;1
"Unit";"Zergling";"Larva";497;1
"Unit";"Zergling";"Larva";497;1
"Unit";"Zergling";"Larva";497;1
"Unit";"Zergling";"Larva";497;1
"Unit";"Zergling";"Larva";497;1
"Unit";"Zergling";"Larva";497;1
"Unit";"Baneling";"Zergling";497;0
"Unit";"Zergling";"Larva";497;1
"Unit";"Zergling";"Larva";497;1
"Unit";"Zergling";"Larva";497;1
"Unit";"Zergling";"Larva";497;1
"Unit";"Zergling";"Larva";497;1
"Unit";"Zergling";"Larva";497;1
"Unit";"Baneling";"Zergling";497;0
"Unit";"Baneling";"Zergling";497;0
"Unit";"Baneling";"Zergling";497;0
"Unit";"Ultralisk";"Larva";491;6
"Unit";"Ultralisk";"Larva";491;6
"Upgrade";"ChitinousPlating";"UltraliskCavern";491;0
"Unit";"Baneling";"Zergling";518;0
"Unit";"Baneling";"Zergling";518;0
"Unit";"Baneling";"Zergling";518;0
"Unit";"Baneling";"Zergling";518;0
"Unit";"Baneling";"Zergling";520;0
"Unit";"Baneling";"Zergling";520;0
"Unit";"Baneling";"Zergling";520;0
"Unit";"Baneling";"Zergling";520;0
"Unit";"Baneling";"Zergling";520;0
"Unit";"Baneling";"Zergling";520;0
"Unit";"Baneling";"Zergling";520;0
"Unit";"Baneling";"Zergling";520;0
"Unit";"Baneling";"Zergling";524;0
"Unit";"Baneling";"Zergling";526;0
"Unit";"Baneling";"Zergling";526;0
"Unit";"Baneling";"Zergling";532;0
"Unit";"Baneling";"Zergling";532;0
"Unit";"Baneling";"Zergling";532;0
"Unit";"Baneling";"Zergling";536;0
"Unit";"Baneling";"Zergling";538;0
"Unit";"Baneling";"Zergling";538;0
"Unit";"Baneling";"Zergling";538;0
"Unit";"Baneling";"Zergling";542;0
"Unit";"Baneling";"Zergling";546;0
"Unit";"Baneling";"Zergling";546;0
"Unit";"Baneling";"Zergling";550;0
"Unit";"Baneling";"Zergling";550;0
"Unit";"Baneling";"Zergling";552;0
"Unit";"Baneling";"Zergling";552;0
"Unit";"Baneling";"Zergling";552;0
"Unit";"Baneling";"Zergling";552;0
"Building";"CreepTumor";NA;564;0
"Building";"CreepTumorQueen";NA;564;0
"Unit";"Zergling";"Larva";564;1
"Unit";"Zergling";"Larva";564;1
"Unit";"Zergling";"Larva";564;1
"Unit";"Zergling";"Larva";564;1
"Unit";"Zergling";"Larva";564;1
"Unit";"Zergling";"Larva";564;1
"Unit";"Zergling";"Larva";564;1
"Unit";"Zergling";"Larva";564;1
"Unit";"Zergling";"Larva";564;1
"Unit";"Zergling";"Larva";564;1
"Unit";"Zergling";"Larva";564;1
"Unit";"Zergling";"Larva";564;1
"Unit";"Zergling";"Larva";564;1
"Unit";"Zergling";"Larva";564;1
"Unit";"Zergling";"Larva";564;1
"Unit";"Zergling";"Larva";564;1
"Unit";"Zergling";"Larva";564;1
"Unit";"Zergling";"Larva";564;1
"Unit";"Zergling";"Larva";564;1
"Unit";"Zergling";"Larva";564;1
"Unit";"Zergling";"Larva";564;1
"Unit";"Zergling";"Larva";564;1
"Unit";"Zergling";"Larva";564;1
"Unit";"Zergling";"Larva";564;1
"Unit";"Zergling";"Larva";564;1
"Unit";"Zergling";"Larva";564;1
"Unit";"Zergling";"Larva";564;1
"Unit";"Zergling";"Larva";564;1
"Unit";"Zergling";"Larva";564;1
"Unit";"Zergling";"Larva";564;1
"Unit";"Zergling";"Larva";564;1
"Unit";"Zergling";"Larva";564;1
"Unit";"Zergling";"Larva";564;1
"Unit";"Zergling";"Larva";564;1
"Unit";"Zergling";"Larva";564;1
"Unit";"Zergling";"Larva";564;1
"Unit";"Zergling";"Larva";564;1
"Unit";"Zergling";"Larva";564;1
"Unit";"Zergling";"Larva";564;1
"Unit";"Zergling";"Larva";564;1
"Unit";"Zergling";"Larva";564;1
"Unit";"Zergling";"Larva";564;1
"Unit";"Zergling";"Larva";564;1
"Unit";"Zergling";"Larva";564;1
"Unit";"Zergling";"Larva";564;1
"Unit";"Zergling";"Larva";564;1
"Unit";"Zergling";"Larva";564;1
"Unit";"Zergling";"Larva";564;1
"Unit";"Zergling";"Larva";564;1
"Unit";"Zergling";"Larva";564;1
"Upgrade";"ZergMeleeWeaponsLevel3";"EvolutionChamber";491;0
"Upgrade";"ZergGroundArmorsLevel3";"EvolutionChamber";491;0
"Building";"CreepTumor";NA;614;0
"Building";"CreepTumorQueen";NA;614;0
"Building";"Hatchery";NA;564;0
"Building";"CreepTumor";NA;614;0
"Building";"CreepTumor";NA;614;0
"Unit";"Baneling";"Zergling";614;0
"Unit";"Baneling";"Zergling";614;0
"Unit";"Baneling";"Zergling";614;0
"Unit";"Baneling";"Zergling";614;0
"Unit";"Baneling";"Zergling";614;0
"Unit";"Baneling";"Zergling";614;0
"Unit";"Baneling";"Zergling";614;0
"Unit";"Baneling";"Zergling";614;0
"Unit";"Baneling";"Zergling";614;0
"Unit";"Baneling";"Zergling";614;0
"Unit";"Baneling";"Zergling";614;0
"Unit";"Baneling";"Zergling";614;0
"Unit";"Baneling";"Zergling";614;0
"Unit";"Baneling";"Zergling";614;0
"Unit";"Baneling";"Zergling";614;0
"Unit";"Baneling";"Zergling";614;0
"Unit";"Baneling";"Zergling";614;0
"Unit";"Baneling";"Zergling";614;0
"Unit";"Baneling";"Zergling";614;0
"Unit";"Baneling";"Zergling";614;0
"Unit";"Baneling";"Zergling";614;0
"Unit";"Baneling";"Zergling";614;0
"Unit";"Baneling";"Zergling";614;0
"Unit";"Baneling";"Zergling";614;0
"Unit";"Baneling";"Zergling";614;0
"Unit";"Baneling";"Zergling";614;0
"Unit";"Baneling";"Zergling";614;0
"Unit";"Baneling";"Zergling";614;0
"Unit";"Baneling";"Zergling";614;0
"Unit";"Baneling";"Zergling";614;0
"Unit";"Baneling";"Zergling";614;0
"Unit";"Baneling";"Zergling";614;0
"Unit";"Baneling";"Zergling";614;0
"Unit";"Baneling";"Zergling";614;0
"Unit";"Baneling";"Zergling";614;0
"Building";"CreepTumor";NA;614;0
"Building";"CreepTumor";NA;614;0
"Building";"CreepTumor";NA;614;0
"Building";"CreepTumor";NA;614;0
"Building";"CreepTumor";NA;614;0
"Building";"CreepTumor";NA;614;0
"Unit";"Ultralisk";"Larva";614;6
"Unit";"Ultralisk";"Larva";614;6
"Unit";"Ultralisk";"Larva";614;6
"Building";"CreepTumor";NA;614;0
"Building";"CreepTumor";NA;614;0
"Unit";"Zergling";"Larva";632;1
"Unit";"Zergling";"Larva";632;1
"Unit";"Zergling";"Larva";632;1
"Unit";"Zergling";"Larva";632;1
"Unit";"Zergling";"Larva";632;1
"Unit";"Zergling";"Larva";632;1
"Unit";"Zergling";"Larva";632;1
"Unit";"Zergling";"Larva";632;1
"Unit";"Zergling";"Larva";632;1
"Unit";"Zergling";"Larva";632;1
"Unit";"Zergling";"Larva";632;1
"Unit";"Zergling";"Larva";632;1
"Unit";"Zergling";"Larva";632;1
"Unit";"Zergling";"Larva";632;1
"Unit";"Zergling";"Larva";632;1
"Unit";"Zergling";"Larva";632;1
"Unit";"Zergling";"Larva";632;1
"Unit";"Zergling";"Larva";632;1
"Unit";"Zergling";"Larva";632;1
"Unit";"Zergling";"Larva";632;1
"Unit";"Zergling";"Larva";632;1
"Unit";"Zergling";"Larva";632;1
"Unit";"Zergling";"Larva";632;1
"Unit";"Zergling";"Larva";632;1
"Unit";"Zergling";"Larva";632;1
"Unit";"Zergling";"Larva";632;1
"Unit";"Zergling";"Larva";632;1
"Unit";"Zergling";"Larva";632;1
"Unit";"Zergling";"Larva";632;1
"Unit";"Zergling";"Larva";632;1
"Unit";"Zergling";"Larva";632;1
"Unit";"Zergling";"Larva";632;1
"Unit";"Zergling";"Larva";632;1
"Unit";"Zergling";"Larva";632;1
"Unit";"Zergling";"Larva";632;1
"Unit";"Zergling";"Larva";632;1
"Unit";"Zergling";"Larva";632;1
"Unit";"Zergling";"Larva";632;1
"Unit";"Zergling";"Larva";632;1
"Unit";"Zergling";"Larva";632;1
"Unit";"Zergling";"Larva";632;1
"Unit";"Zergling";"Larva";632;1
"Unit";"Zergling";"Larva";632;1
"Unit";"Zergling";"Larva";632;1
"Unit";"Zergling";"Larva";632;1
"Unit";"Zergling";"Larva";632;1
"Unit";"Zergling";"Larva";632;1
"Unit";"Zergling";"Larva";632;1
"Unit";"Zergling";"Larva";632;1
"Unit";"Zergling";"Larva";632;1
"Unit";"Zergling";"Larva";632;1
"Unit";"Zergling";"Larva";632;1
"Unit";"Zergling";"Larva";632;1
"Unit";"Zergling";"Larva";632;1
"Unit";"Zergling";"Larva";632;1
"Unit";"Zergling";"Larva";632;1
"Unit";"Zergling";"Larva";632;1
"Unit";"Zergling";"Larva";632;1
"Unit";"Zergling";"Larva";632;1
"Unit";"Zergling";"Larva";632;1
"Unit";"Zergling";"Larva";632;1
"Unit";"Zergling";"Larva";632;1
"Unit";"Zergling";"Larva";632;1
"Unit";"Zergling";"Larva";632;1
"Unit";"Zergling";"Larva";632;1
"Unit";"Zergling";"Larva";632;1
"Unit";"Zergling";"Larva";632;1
"Unit";"Zergling";"Larva";632;1
"Unit";"Zergling";"Larva";632;1
"Unit";"Zergling";"Larva";632;1
"Unit";"Zergling";"Larva";632;1
"Unit";"Zergling";"Larva";632;1
"Unit";"Zergling";"Larva";632;1
"Unit";"Zergling";"Larva";632;1
"Unit";"Zergling";"Larva";632;1
"Unit";"Zergling";"Larva";632;1
"Unit";"Zergling";"Larva";632;1
"Unit";"Zergling";"Larva";632;1
"Unit";"Zergling";"Larva";632;1
"Unit";"Zergling";"Larva";632;1
"Unit";"Zergling";"Larva";632;1
"Unit";"Zergling";"Larva";632;1
"Unit";"Zergling";"Larva";632;1
"Unit";"Zergling";"Larva";632;1
"Building";"Spire";NA;614;0
"Unit";"Overlord";"Larva";716;0
"Unit";"Overlord";"Larva";716;0
"Unit";"Overlord";"Larva";716;0
"Unit";"Overlord";"Larva";716;0
"Unit";"Overlord";"Larva";716;0
"Unit";"Overlord";"Larva";716;0
"Unit";"Overlord";"Larva";716;0
"Unit";"Overlord";"Larva";716;0
"Building";"CreepTumor";NA;716;0
"Unit";"Ultralisk";"Larva";716;6
"Unit";"Ultralisk";"Larva";716;6
"Building";"CreepTumor";NA;716;0
"Unit";"Baneling";"Zergling";716;0
"Unit";"Baneling";"Zergling";716;0
"Unit";"Baneling";"Zergling";716;0
"Building";"CreepTumor";NA;716;0
"Unit";"Baneling";"Zergling";716;0
"Unit";"Baneling";"Zergling";716;0
"Unit";"Baneling";"Zergling";716;0
"Unit";"Baneling";"Zergling";716;0
"Unit";"Baneling";"Zergling";716;0
"Unit";"Baneling";"Zergling";716;0
"Unit";"Baneling";"Zergling";716;0
"Unit";"Baneling";"Zergling";716;0
"Unit";"Baneling";"Zergling";716;0
"Unit";"Baneling";"Zergling";716;0
"Unit";"Baneling";"Zergling";716;0
"Unit";"Baneling";"Zergling";716;0
"Unit";"Baneling";"Zergling";716;0
"Unit";"Baneling";"Zergling";716;0
"Unit";"Baneling";"Zergling";716;0
"Unit";"Baneling";"Zergling";716;0
"Unit";"Baneling";"Zergling";716;0
"Unit";"Baneling";"Zergling";716;0
"Unit";"Baneling";"Zergling";716;0
"Unit";"Baneling";"Zergling";716;0
"Unit";"Baneling";"Zergling";716;0
"Unit";"Baneling";"Zergling";716;0
"Unit";"Baneling";"Zergling";716;0
"Unit";"Baneling";"Zergling";716;0
"Unit";"Baneling";"Zergling";716;0
"Unit";"Baneling";"Zergling";716;0
"Unit";"Baneling";"Zergling";716;0
"Unit";"Baneling";"Zergling";716;0
"Unit";"Baneling";"Zergling";716;0
"Unit";"Baneling";"Zergling";716;0
"Unit";"Baneling";"Zergling";716;0
"Unit";"Baneling";"Zergling";716;0
"Unit";"Baneling";"Zergling";716;0
"Unit";"Baneling";"Zergling";716;0
"Unit";"Baneling";"Zergling";716;0
"Unit";"Baneling";"Zergling";716;0
"Unit";"Baneling";"Zergling";716;0
"Unit";"Baneling";"Zergling";716;0
"Unit";"Baneling";"Zergling";730;0
"Unit";"Baneling";"Zergling";730;0
"Unit";"Baneling";"Zergling";730;0
"Unit";"Baneling";"Zergling";730;0
"Building";"CreepTumor";NA;730;0
"Unit";"Baneling";"Zergling";730;0
"Unit";"Baneling";"Zergling";730;0
"Unit";"Baneling";"Zergling";730;0
"Unit";"Baneling";"Zergling";730;0
"Unit";"Baneling";"Zergling";730;0
"Unit";"Baneling";"Zergling";730;0
"Unit";"Ultralisk";"Larva";716;6
"Unit";"Ultralisk";"Larva";716;6
"Unit";"Ultralisk";"Larva";716;6
"Unit";"Ultralisk";"Larva";716;6
"Unit";"Ultralisk";"Larva";716;6
"Unit";"Ultralisk";"Larva";716;6
"Unit";"Ultralisk";"Larva";716;6
"Building";"CreepTumor";NA;730;0
"Building";"CreepTumor";NA;730;0
"Building";"CreepTumorQueen";NA;772;0
"Unit";"Zergling";"Larva";772;1
"Unit";"Zergling";"Larva";772;1
"Unit";"Zergling";"Larva";772;1
"Unit";"Zergling";"Larva";772;1
"Unit";"Zergling";"Larva";772;1
"Unit";"Zergling";"Larva";772;1
"Unit";"Zergling";"Larva";772;1
"Unit";"Zergling";"Larva";772;1
"Unit";"Zergling";"Larva";772;1
"Unit";"Zergling";"Larva";772;1
"Unit";"Zergling";"Larva";772;1
"Unit";"Zergling";"Larva";772;1
"Unit";"Zergling";"Larva";772;1
"Unit";"Zergling";"Larva";772;1
"Unit";"Zergling";"Larva";772;1
"Unit";"Zergling";"Larva";772;1
"Unit";"Zergling";"Larva";772;1
"Unit";"Zergling";"Larva";772;1
"Unit";"Zergling";"Larva";772;1
"Unit";"Zergling";"Larva";772;1
"Unit";"Zergling";"Larva";772;1
"Unit";"Zergling";"Larva";772;1
"Unit";"Zergling";"Larva";772;1
"Unit";"Zergling";"Larva";772;1
"Unit";"Zergling";"Larva";772;1
"Unit";"Zergling";"Larva";772;1
"Unit";"Zergling";"Larva";772;1
"Unit";"Zergling";"Larva";772;1
"Unit";"Zergling";"Larva";772;1
"Unit";"Zergling";"Larva";772;1
"Unit";"Zergling";"Larva";772;1
"Unit";"Zergling";"Larva";772;1
"Unit";"Zergling";"Larva";772;1
"Unit";"Zergling";"Larva";772;1
"Unit";"Zergling";"Larva";772;1
"Unit";"Zergling";"Larva";772;1
"Unit";"Zergling";"Larva";772;1
"Unit";"Zergling";"Larva";772;1
"Unit";"Zergling";"Larva";772;1
"Unit";"Zergling";"Larva";772;1
"Unit";"Zergling";"Larva";772;1
"Unit";"Zergling";"Larva";772;1
"Unit";"Zergling";"Larva";772;1
"Unit";"Zergling";"Larva";772;1
"Unit";"Zergling";"Larva";772;1
"Unit";"Zergling";"Larva";772;1
"Building";"CreepTumorQueen";NA;772;0
"Unit";"Zergling";"Larva";772;1
"Unit";"Zergling";"Larva";772;1
"Unit";"Zergling";"Larva";772;1
"Unit";"Zergling";"Larva";772;1
"Unit";"Zergling";"Larva";772;1
"Unit";"Zergling";"Larva";772;1
"Unit";"Zergling";"Larva";772;1
"Unit";"Zergling";"Larva";772;1
"Unit";"Zergling";"Larva";772;1
"Unit";"Zergling";"Larva";772;1
"Unit";"Zergling";"Larva";772;1
"Unit";"Zergling";"Larva";772;1
"Unit";"Zergling";"Larva";772;1
"Unit";"Zergling";"Larva";772;1
"Unit";"Zergling";"Larva";772;1
"Unit";"Zergling";"Larva";772;1
