"type";"unit_name";"on_building";"total_supply";"supply"
"Unit";"Overlord";"Larva";12;0
"Building";"SpawningPool";NA;19;0
"Building";"Hatchery";NA;17;0
"Building";"Extractor";NA;22;0
"Unit";"Zergling";"Larva";24;1
"Unit";"Zergling";"Larva";24;1
"Unit";"Zergling";"Larva";24;1
"Unit";"Zergling";"Larva";24;1
"Unit";"Overlord";"Larva";24;0
"Unit";"Overlord";"Larva";24;0
"Unit";"Queen";"Hatchery";24;2
"Unit";"Queen";"Hatchery";24;2
"Building";"Hatchery";NA;21;0
"Building";"CreepTumorQueen";NA;34;0
"Building";"CreepTumor";NA;41;0
"Unit";"Overlord";"Larva";43;0
"Unit";"Overlord";"Larva";44;0
"Unit";"Queen";"Hatchery";41;2
"Building";"CreepTumor";NA;46;0
"Unit";"Queen";"Hatchery";44;2
"Building";"CreepTumorQueen";NA;48;0
"Unit";"Overlord";"Larva";48;0
"Building";"CreepTumorQueen";NA;54;0
"Unit";"Overlord";"Larva";50;0
"Building";"CreepTumorQueen";NA;58;0
"Unit";"Zergling";"Larva";58;1
"Unit";"Zergling";"Larva";58;1
"Building";"CreepTumor";NA;58;0
"Unit";"Zergling";"Larva";58;1
"Unit";"Zergling";"Larva";58;1
"Building";"CreepTumor";NA;61;0
"Unit";"Queen";"Hatchery";48;2
"Building";"EvolutionChamber";NA;58;0
"Unit";"Zergling";"Larva";61;1
"Unit";"Zergling";"Larva";61;1
"Building";"CreepTumorQueen";NA;61;0
"Unit";"Zergling";"Larva";61;1
"Unit";"Zergling";"Larva";61;1
"Unit";"Zergling";"Larva";61;1
"Unit";"Zergling";"Larva";61;1
"Unit";"Zergling";"Larva";61;1
"Unit";"Zergling";"Larva";61;1
"Building";"CreepTumor";NA;61;0
"Building";"CreepTumorQueen";NA;65;0
"Building";"CreepTumor";NA;75;0
"Unit";"Zergling";"Larva";75;1
"Unit";"Zergling";"Larva";75;1
"Unit";"Zergling";"Larva";75;1
"Unit";"Zergling";"Larva";75;1
"Unit";"Zergling";"Larva";75;1
"Unit";"Zergling";"Larva";75;1
"Unit";"Zergling";"Larva";75;1
"Unit";"Zergling";"Larva";75;1
"Unit";"Zergling";"Larva";75;1
"Unit";"Zergling";"Larva";75;1
"Unit";"Zergling";"Larva";75;1
"Unit";"Zergling";"Larva";75;1
"Unit";"Zergling";"Larva";75;1
"Unit";"Zergling";"Larva";75;1
"Unit";"Zergling";"Larva";75;1
"Unit";"Zergling";"Larva";75;1
"Unit";"Zergling";"Larva";75;1
"Unit";"Zergling";"Larva";75;1
"Building";"CreepTumorQueen";NA;75;0
"Unit";"Queen";"Hatchery";61;2
"Building";"CreepTumor";NA;75;0
"Unit";"Zergling";"Larva";75;1
"Unit";"Zergling";"Larva";75;1
"Building";"CreepTumor";NA;93;0
"Building";"CreepTumor";NA;93;0
"Building";"CreepTumor";NA;93;0
"Building";"CreepTumor";NA;95;0
"Unit";"Zergling";"Larva";95;1
"Unit";"Zergling";"Larva";95;1
"Unit";"Zergling";"Larva";95;1
"Unit";"Zergling";"Larva";95;1
"Unit";"Zergling";"Larva";95;1
"Unit";"Zergling";"Larva";95;1
"Unit";"Zergling";"Larva";95;1
"Unit";"Zergling";"Larva";95;1
"Unit";"Zergling";"Larva";95;1
"Unit";"Zergling";"Larva";95;1
"Unit";"Zergling";"Larva";95;1
"Unit";"Zergling";"Larva";95;1
"Unit";"Zergling";"Larva";95;1
"Unit";"Zergling";"Larva";95;1
"Building";"CreepTumor";NA;97;0
"Building";"CreepTumorQueen";NA;97;0
"Unit";"Zergling";"Larva";97;1
"Unit";"Zergling";"Larva";97;1
"Unit";"Zergling";"Larva";97;1
"Unit";"Zergling";"Larva";97;1
"Unit";"Zergling";"Larva";97;1
"Unit";"Zergling";"Larva";97;1
"Building";"CreepTumorQueen";NA;97;0
"Building";"CreepTumor";NA;97;0
"Unit";"Overlord";"Larva";97;0
"Building";"CreepTumor";NA;111;0
"Building";"CreepTumor";NA;111;0
"Building";"CreepTumor";NA;111;0
"Building";"CreepTumor";NA;117;0
"Building";"CreepTumorQueen";NA;117;0
"Building";"CreepTumorQueen";NA;117;0
"Unit";"Overlord";"Larva";117;0
"Unit";"Overlord";"Larva";117;0
"Unit";"Overlord";"Larva";117;0
"Building";"CreepTumorQueen";NA;117;0
"Building";"CreepTumor";NA;117;0
"Building";"CreepTumor";NA;117;0
"Building";"CreepTumor";NA;117;0
"Building";"Hatchery";NA;75;0
"Building";"SporeCrawler";NA;117;0
"Building";"CreepTumorQueen";NA;124;0
"Building";"SporeCrawler";NA;117;0
"Building";"CreepTumorQueen";NA;124;0
"Building";"Extractor";NA;124;0
"Building";"Extractor";NA;124;0
"Building";"Extractor";NA;124;0
"Building";"BanelingNest";NA;117;0
"Building";"CreepTumor";NA;131;0
"Building";"CreepTumor";NA;131;0
"Building";"CreepTumor";NA;133;0
"Building";"CreepTumor";NA;133;0
"Building";"CreepTumor";NA;133;0
"Building";"CreepTumor";NA;133;0
"Building";"CreepTumor";NA;133;0
"Building";"CreepTumor";NA;137;0
"Upgrade";"ZergGroundArmorsLevel1";"EvolutionChamber";97;0
"Building";"CreepTumor";NA;139;0
"Building";"CreepTumor";NA;139;0
"Unit";"Queen";"Hatchery";128;2
"Unit";"Queen";"Hatchery";128;2
"Building";"CreepTumor";NA;143;0
"Building";"CreepTumor";NA;143;0
"Building";"EvolutionChamber";NA;139;0
"Building";"CreepTumor";NA;143;0
"Building";"CreepTumor";NA;143;0
"Building";"SporeCrawler";NA;139;0
"Building";"CreepTumor";NA;143;0
"Building";"CreepTumor";NA;143;0
"Unit";"Overlord";"Larva";143;0
"Unit";"Overlord";"Larva";143;0
"Building";"SporeCrawler";NA;141;0
"Building";"CreepTumor";NA;143;0
"Unit";"Overlord";"Larva";143;0
"Building";"CreepTumor";NA;143;0
"Building";"Extractor";NA;141;0
"Building";"CreepTumor";NA;143;0
"Building";"Extractor";NA;141;0
"Building";"CreepTumor";NA;151;0
"Building";"CreepTumor";NA;151;0
"Building";"CreepTumor";NA;151;0
"Unit";"Zergling";"Larva";151;1
"Unit";"Zergling";"Larva";151;1
"Unit";"Zergling";"Larva";151;1
"Unit";"Zergling";"Larva";151;1
"Unit";"Zergling";"Larva";151;1
"Unit";"Zergling";"Larva";151;1
"Unit";"Zergling";"Larva";151;1
"Unit";"Zergling";"Larva";151;1
"Unit";"Zergling";"Larva";151;1
"Unit";"Zergling";"Larva";151;1
"Unit";"Zergling";"Larva";151;1
"Unit";"Zergling";"Larva";151;1
"Unit";"Zergling";"Larva";151;1
"Unit";"Zergling";"Larva";151;1
"Unit";"Zergling";"Larva";151;1
"Unit";"Zergling";"Larva";151;1
"Unit";"Zergling";"Larva";151;1
"Unit";"Zergling";"Larva";151;1
"Building";"CreepTumor";NA;169;0
"Building";"CreepTumor";NA;169;0
"Building";"CreepTumor";NA;169;0
"Building";"CreepTumor";NA;169;0
"Building";"CreepTumor";NA;169;0
"Building";"CreepTumor";NA;169;0
"Building";"CreepTumor";NA;169;0
"Building";"CreepTumor";NA;169;0
"Building";"CreepTumor";NA;169;0
"Building";"CreepTumor";NA;169;0
"Building";"Hatchery";NA;139;0
"Unit";"Zergling";"Larva";169;1
"Unit";"Zergling";"Larva";169;1
"Unit";"Overlord";"Larva";169;0
"Unit";"Zergling";"Larva";169;1
"Unit";"Zergling";"Larva";169;1
"Unit";"Zergling";"Larva";169;1
"Unit";"Zergling";"Larva";169;1
"Unit";"Overlord";"Larva";169;0
"Unit";"Zergling";"Larva";169;1
"Unit";"Zergling";"Larva";169;1
"Unit";"Zergling";"Larva";169;1
"Unit";"Zergling";"Larva";169;1
"Unit";"Zergling";"Larva";169;1
"Unit";"Zergling";"Larva";169;1
"Unit";"Zergling";"Larva";169;1
"Unit";"Zergling";"Larva";169;1
"Unit";"Zergling";"Larva";169;1
"Unit";"Zergling";"Larva";169;1
"Unit";"Zergling";"Larva";169;1
"Unit";"Zergling";"Larva";169;1
"Unit";"Zergling";"Larva";169;1
"Unit";"Zergling";"Larva";169;1
"Unit";"Zergling";"Larva";169;1
"Unit";"Zergling";"Larva";169;1
"Unit";"Zergling";"Larva";169;1
"Unit";"Zergling";"Larva";169;1
"Unit";"Zergling";"Larva";169;1
"Unit";"Zergling";"Larva";169;1
"Unit";"Zergling";"Larva";169;1
"Unit";"Zergling";"Larva";169;1
"Unit";"Zergling";"Larva";169;1
"Unit";"Zergling";"Larva";169;1
"Unit";"Zergling";"Larva";169;1
"Unit";"Zergling";"Larva";169;1
"Building";"CreepTumorQueen";NA;169;0
"Building";"CreepTumorQueen";NA;169;0
"Building";"CreepTumor";NA;183;0
"Building";"CreepTumor";NA;201;0
"Building";"CreepTumor";NA;201;0
"Building";"CreepTumor";NA;201;0
"Unit";"Baneling";"Zergling";206;0
"Unit";"Baneling";"Zergling";206;0
"Unit";"Baneling";"Zergling";206;0
"Unit";"Baneling";"Zergling";206;0
"Unit";"Baneling";"Zergling";206;0
"Unit";"Baneling";"Zergling";206;0
"Unit";"Baneling";"Zergling";206;0
"Unit";"Baneling";"Zergling";206;0
"Unit";"Baneling";"Zergling";206;0
"Unit";"Baneling";"Zergling";206;0
"Unit";"Baneling";"Zergling";206;0
"Unit";"Baneling";"Zergling";206;0
"Unit";"Baneling";"Zergling";206;0
"Building";"CreepTumor";NA;206;0
"Building";"CreepTumor";NA;206;0
"Building";"CreepTumor";NA;206;0
"Building";"HydraliskDen";NA;175;0
"Unit";"Zergling";"Larva";206;1
"Unit";"Zergling";"Larva";206;1
"Building";"CreepTumorQueen";NA;206;0
"Unit";"Zergling";"Larva";206;1
"Unit";"Zergling";"Larva";206;1
"Unit";"Zergling";"Larva";206;1
"Unit";"Zergling";"Larva";206;1
"Unit";"Zergling";"Larva";206;1
"Unit";"Zergling";"Larva";206;1
"Unit";"Zergling";"Larva";206;1
"Unit";"Zergling";"Larva";206;1
"Unit";"Zergling";"Larva";206;1
"Unit";"Zergling";"Larva";206;1
"Unit";"Zergling";"Larva";206;1
"Unit";"Zergling";"Larva";206;1
"Unit";"Zergling";"Larva";206;1
"Unit";"Zergling";"Larva";206;1
"Unit";"Zergling";"Larva";206;1
"Unit";"Zergling";"Larva";206;1
"Unit";"Zergling";"Larva";206;1
"Unit";"Zergling";"Larva";206;1
"Unit";"Zergling";"Larva";206;1
"Unit";"Zergling";"Larva";206;1
"Unit";"Zergling";"Larva";206;1
"Unit";"Zergling";"Larva";206;1
"Building";"CreepTumor";NA;206;0
"Building";"CreepTumor";NA;206;0
"Building";"CreepTumorQueen";NA;206;0
"Building";"CreepTumorQueen";NA;206;0
"Upgrade";"ZergMeleeWeaponsLevel1";"EvolutionChamber";151;0
"Building";"CreepTumor";NA;230;0
"Building";"CreepTumor";NA;230;0
"Building";"CreepTumorQueen";NA;230;0
"Building";"CreepTumor";NA;230;0
"Building";"CreepTumor";NA;243;0
"Building";"CreepTumor";NA;231;0
"Building";"CreepTumor";NA;235;0
"Building";"CreepTumor";NA;243;0
"Building";"CreepTumor";NA;243;0
"Building";"CreepTumor";NA;243;0
"Building";"CreepTumor";NA;243;0
"Building";"CreepTumor";NA;243;0
"Building";"CreepTumor";NA;243;0
"Building";"CreepTumor";NA;243;0
"Unit";"Hydralisk";"Larva";230;2
"Building";"CreepTumor";NA;243;0
"Building";"CreepTumor";NA;243;0
"Unit";"Queen";"Hatchery";230;2
"Building";"CreepTumor";NA;245;0
"Unit";"Zergling";"Larva";243;1
"Unit";"Zergling";"Larva";243;1
"Unit";"Zergling";"Larva";243;1
"Unit";"Zergling";"Larva";243;1
"Unit";"Zergling";"Larva";243;1
"Unit";"Zergling";"Larva";243;1
"Building";"CreepTumor";NA;245;0
"Unit";"Overlord";"Larva";245;0
"Unit";"Overlord";"Larva";245;0
"Unit";"Overlord";"Larva";245;0
"Unit";"Overlord";"Larva";245;0
"Unit";"Overlord";"Larva";245;0
"Unit";"Overlord";"Larva";245;0
"Unit";"Overlord";"Larva";245;0
"Unit";"Overlord";"Larva";245;0
"Unit";"Overlord";"Larva";245;0
"Building";"SporeCrawler";NA;243;0
"Unit";"Zergling";"Larva";247;1
"Unit";"Zergling";"Larva";247;1
"Building";"CreepTumor";NA;253;0
"Building";"CreepTumor";NA;253;0
"Building";"CreepTumor";NA;253;0
"Building";"CreepTumor";NA;253;0
"Upgrade";"EvolveGroovedSpines";"HydraliskDen";243;0
"Building";"CreepTumor";NA;255;0
"Building";"CreepTumorQueen";NA;255;0
"Building";"CreepTumor";NA;255;0
"Building";"CreepTumorQueen";NA;255;0
"Unit";"Hydralisk";"Larva";253;2
"Unit";"Hydralisk";"Larva";253;2
"Unit";"Hydralisk";"Larva";253;2
"Unit";"Hydralisk";"Larva";253;2
"Unit";"Hydralisk";"Larva";255;2
"Unit";"Hydralisk";"Larva";255;2
"Unit";"Hydralisk";"Larva";255;2
"Unit";"Hydralisk";"Larva";255;2
"Unit";"Hydralisk";"Larva";255;2
"Unit";"Hydralisk";"Larva";255;2
"Unit";"Hydralisk";"Larva";255;2
"Unit";"Hydralisk";"Larva";255;2
"Unit";"Hydralisk";"Larva";255;2
"Unit";"Hydralisk";"Larva";255;2
"Unit";"Hydralisk";"Larva";255;2
"Unit";"Hydralisk";"Larva";255;2
"Unit";"Hydralisk";"Larva";255;2
"Unit";"Hydralisk";"Larva";255;2
"Upgrade";"ZergGroundArmorsLevel2";"EvolutionChamber";228;0
"Unit";"Zergling";"Larva";255;1
"Unit";"Zergling";"Larva";255;1
"Unit";"Zergling";"Larva";255;1
"Unit";"Zergling";"Larva";255;1
"Unit";"Zergling";"Larva";255;1
"Unit";"Zergling";"Larva";255;1
"Unit";"Zergling";"Larva";255;1
"Unit";"Zergling";"Larva";255;1
"Unit";"Zergling";"Larva";255;1
"Unit";"Zergling";"Larva";255;1
"Unit";"Zergling";"Larva";255;1
"Unit";"Zergling";"Larva";255;1
"Unit";"Zergling";"Larva";255;1
"Unit";"Zergling";"Larva";255;1
"Unit";"Zergling";"Larva";255;1
"Unit";"Zergling";"Larva";255;1
"Unit";"Zergling";"Larva";255;1
"Unit";"Zergling";"Larva";255;1
"Unit";"Zergling";"Larva";255;1
"Unit";"Zergling";"Larva";255;1
"Unit";"Zergling";"Larva";311;1
"Unit";"Zergling";"Larva";311;1
"Unit";"Zergling";"Larva";311;1
"Unit";"Zergling";"Larva";311;1
"Building";"CreepTumor";NA;330;0
"Upgrade";"EvolveMuscularAugments";"HydraliskDen";301;0
"Building";"Extractor";NA;330;0
"Building";"Extractor";NA;330;0
"Building";"InfestationPit";NA;330;0
"Building";"CreepTumor";NA;330;0
"Building";"SporeCrawler";NA;330;0
"Building";"SporeCrawler";NA;330;0
"Unit";"Zergling";"Larva";330;1
"Unit";"Zergling";"Larva";330;1
"Unit";"Zergling";"Larva";330;1
"Unit";"Zergling";"Larva";330;1
"Unit";"Zergling";"Larva";330;1
"Unit";"Zergling";"Larva";330;1
"Unit";"Zergling";"Larva";330;1
"Unit";"Zergling";"Larva";330;1
"Unit";"Zergling";"Larva";330;1
"Unit";"Zergling";"Larva";330;1
"Unit";"Zergling";"Larva";330;1
"Unit";"Zergling";"Larva";330;1
"Unit";"Hydralisk";"Larva";330;2
"Unit";"Hydralisk";"Larva";330;2
"Unit";"Hydralisk";"Larva";330;2
"Unit";"Hydralisk";"Larva";330;2
"Unit";"Hydralisk";"Larva";330;2
"Unit";"Hydralisk";"Larva";330;2
"Unit";"Hydralisk";"Larva";330;2
"Unit";"Hydralisk";"Larva";330;2
"Unit";"Hydralisk";"Larva";330;2
"Unit";"Queen";"Hatchery";330;2
"Unit";"Queen";"Hatchery";330;2
"Unit";"Zergling";"Larva";330;1
"Unit";"Zergling";"Larva";330;1
"Building";"CreepTumor";NA;330;0
"Unit";"Zergling";"Larva";330;1
"Unit";"Zergling";"Larva";330;1
"Unit";"Zergling";"Larva";330;1
"Unit";"Zergling";"Larva";330;1
"Unit";"Zergling";"Larva";330;1
"Unit";"Zergling";"Larva";330;1
"Unit";"Zergling";"Larva";330;1
"Unit";"Zergling";"Larva";330;1
"Unit";"Zergling";"Larva";330;1
"Unit";"Zergling";"Larva";330;1
"Unit";"Zergling";"Larva";330;1
"Unit";"Zergling";"Larva";330;1
"Building";"CreepTumor";NA;330;0
"Building";"CreepTumorQueen";NA;360;0
"Unit";"Zergling";"Larva";342;1
"Unit";"Zergling";"Larva";342;1
"Unit";"Zergling";"Larva";342;1
"Unit";"Zergling";"Larva";342;1
"Unit";"Zergling";"Larva";342;1
"Unit";"Zergling";"Larva";342;1
"Unit";"Zergling";"Larva";342;1
"Unit";"Zergling";"Larva";342;1
"Unit";"Baneling";"Zergling";360;0
"Unit";"Baneling";"Zergling";360;0
"Unit";"Baneling";"Zergling";360;0
"Building";"CreepTumor";NA;378;0
"Unit";"Zergling";"Larva";378;1
"Unit";"Zergling";"Larva";378;1
"Unit";"Zergling";"Larva";378;1
"Unit";"Zergling";"Larva";378;1
"Unit";"Zergling";"Larva";378;1
"Unit";"Zergling";"Larva";378;1
"Unit";"Zergling";"Larva";378;1
"Unit";"Zergling";"Larva";378;1
"Unit";"Zergling";"Larva";378;1
"Unit";"Zergling";"Larva";378;1
"Building";"Hatchery";NA;330;0
"Unit";"Hydralisk";"Larva";386;2
"Unit";"Hydralisk";"Larva";386;2
"Unit";"Hydralisk";"Larva";386;2
"Unit";"Hydralisk";"Larva";386;2
"Unit";"Hydralisk";"Larva";386;2
"Building";"CreepTumor";NA;396;0
"Building";"CreepTumor";NA;396;0
"Building";"CreepTumorQueen";NA;396;0
"Building";"CreepTumorQueen";NA;396;0
"Building";"CreepTumor";NA;396;0
"Building";"CreepTumorQueen";NA;396;0
"Building";"CreepTumor";NA;396;0
"Building";"CreepTumorQueen";NA;396;0
"Building";"CreepTumorQueen";NA;396;0
"Upgrade";"ZergMeleeWeaponsLevel2";"EvolutionChamber";330;0
"Upgrade";"ZergMissileWeaponsLevel1";"EvolutionChamber";330;0
"Unit";"Zergling";"Larva";406;1
"Unit";"Zergling";"Larva";406;1
"Unit";"Zergling";"Larva";406;1
"Unit";"Zergling";"Larva";406;1
"Unit";"Zergling";"Larva";406;1
"Unit";"Zergling";"Larva";406;1
"Unit";"Zergling";"Larva";406;1
"Unit";"Zergling";"Larva";406;1
"Unit";"Zergling";"Larva";406;1
"Unit";"Zergling";"Larva";406;1
"Unit";"Zergling";"Larva";406;1
"Unit";"Zergling";"Larva";406;1
"Unit";"Zergling";"Larva";406;1
"Unit";"Zergling";"Larva";406;1
"Unit";"Zergling";"Larva";406;1
"Unit";"Zergling";"Larva";406;1
"Unit";"Zergling";"Larva";406;1
"Unit";"Zergling";"Larva";406;1
"Unit";"Zergling";"Larva";406;1
"Unit";"Zergling";"Larva";406;1
"Unit";"Zergling";"Larva";406;1
"Unit";"Zergling";"Larva";406;1
"Unit";"Zergling";"Larva";406;1
"Unit";"Zergling";"Larva";406;1
"Unit";"Zergling";"Larva";406;1
"Unit";"Zergling";"Larva";406;1
"Unit";"Zergling";"Larva";406;1
"Unit";"Zergling";"Larva";406;1
"Unit";"Zergling";"Larva";406;1
"Unit";"Zergling";"Larva";406;1
"Unit";"Zergling";"Larva";406;1
"Unit";"Zergling";"Larva";406;1
"Unit";"Zergling";"Larva";406;1
"Unit";"Zergling";"Larva";406;1
"Unit";"Zergling";"Larva";406;1
"Unit";"Zergling";"Larva";406;1
"Unit";"Zergling";"Larva";406;1
"Unit";"Zergling";"Larva";406;1
"Unit";"Zergling";"Larva";406;1
"Unit";"Zergling";"Larva";406;1
"Unit";"Zergling";"Larva";406;1
"Unit";"Zergling";"Larva";406;1
"Unit";"Zergling";"Larva";406;1
"Unit";"Zergling";"Larva";406;1
"Unit";"Zergling";"Larva";406;1
"Unit";"Zergling";"Larva";406;1
"Unit";"Zergling";"Larva";406;1
"Unit";"Zergling";"Larva";406;1
"Unit";"Zergling";"Larva";406;1
"Unit";"Zergling";"Larva";406;1
"Building";"CreepTumor";NA;406;0
"Building";"CreepTumor";NA;406;0
"Building";"CreepTumor";NA;406;0
"Building";"CreepTumor";NA;456;0
"Building";"CreepTumor";NA;456;0
"Building";"CreepTumor";NA;456;0
"Building";"CreepTumor";NA;456;0
"Building";"CreepTumor";NA;456;0
"Building";"CreepTumor";NA;456;0
"Unit";"Viper";"Larva";456;3
"Unit";"Viper";"Larva";456;3
"Unit";"Viper";"Larva";456;3
"Unit";"Viper";"Larva";456;3
"Unit";"Viper";"Larva";456;3
"Building";"Spire";NA;406;0
"Building";"CreepTumor";NA;471;0
"Building";"CreepTumor";NA;471;0
"Building";"CreepTumor";NA;471;0
"Building";"CreepTumor";NA;471;0
"Building";"CreepTumor";NA;471;0
"Building";"CreepTumor";NA;471;0
"Unit";"Baneling";"Zergling";471;0
"Unit";"Baneling";"Zergling";471;0
"Unit";"Baneling";"Zergling";471;0
"Unit";"Baneling";"Zergling";471;0
"Unit";"Baneling";"Zergling";471;0
"Unit";"Baneling";"Zergling";471;0
"Unit";"Baneling";"Zergling";471;0
"Unit";"Baneling";"Zergling";471;0
"Unit";"Baneling";"Zergling";471;0
"Unit";"Baneling";"Zergling";471;0
"Unit";"Baneling";"Zergling";471;0
"Unit";"Baneling";"Zergling";471;0
"Unit";"Baneling";"Zergling";471;0
"Unit";"Baneling";"Zergling";471;0
"Unit";"Baneling";"Zergling";471;0
"Unit";"Baneling";"Zergling";471;0
"Unit";"Baneling";"Zergling";471;0
"Unit";"Baneling";"Zergling";471;0
"Unit";"Zergling";"Larva";471;1
"Unit";"Zergling";"Larva";471;1
"Unit";"Baneling";"Zergling";471;0
"Unit";"Zergling";"Larva";471;1
"Unit";"Zergling";"Larva";471;1
"Unit";"Zergling";"Larva";471;1
"Unit";"Zergling";"Larva";471;1
"Unit";"Zergling";"Larva";471;1
"Unit";"Zergling";"Larva";471;1
"Unit";"Zergling";"Larva";471;1
"Unit";"Zergling";"Larva";471;1
"Unit";"Zergling";"Larva";471;1
"Unit";"Zergling";"Larva";471;1
"Unit";"Zergling";"Larva";471;1
"Unit";"Zergling";"Larva";471;1
"Building";"CreepTumor";NA;471;0
"Building";"CreepTumor";NA;471;0
"Building";"CreepTumor";NA;471;0
"Unit";"Zergling";"Larva";485;1
"Unit";"Zergling";"Larva";485;1
"Unit";"Zergling";"Larva";485;1
"Unit";"Zergling";"Larva";485;1
"Unit";"Zergling";"Larva";485;1
"Unit";"Zergling";"Larva";485;1
"Unit";"Zergling";"Larva";485;1
"Unit";"Zergling";"Larva";485;1
"Unit";"Zergling";"Larva";485;1
"Unit";"Zergling";"Larva";485;1
"Unit";"Zergling";"Larva";485;1
"Unit";"Zergling";"Larva";485;1
"Unit";"Zergling";"Larva";485;1
"Unit";"Zergling";"Larva";485;1
"Unit";"Zergling";"Larva";485;1
"Unit";"Zergling";"Larva";485;1
"Unit";"Zergling";"Larva";485;1
"Unit";"Zergling";"Larva";485;1
"Unit";"Zergling";"Larva";485;1
"Unit";"Zergling";"Larva";485;1
"Unit";"Zergling";"Larva";485;1
"Unit";"Zergling";"Larva";485;1
"Unit";"Zergling";"Larva";485;1
"Unit";"Zergling";"Larva";485;1
"Unit";"Zergling";"Larva";485;1
"Unit";"Zergling";"Larva";485;1
"Unit";"Zergling";"Larva";511;1
"Unit";"Zergling";"Larva";511;1
"Unit";"Zergling";"Larva";511;1
"Unit";"Zergling";"Larva";511;1
"Unit";"Zergling";"Larva";511;1
"Unit";"Zergling";"Larva";511;1
"Unit";"Zergling";"Larva";511;1
"Unit";"Zergling";"Larva";511;1
"Unit";"Zergling";"Larva";511;1
"Unit";"Zergling";"Larva";511;1
"Unit";"Zergling";"Larva";511;1
"Unit";"Zergling";"Larva";511;1
"Unit";"Zergling";"Larva";511;1
"Unit";"Zergling";"Larva";511;1
"Unit";"Zergling";"Larva";511;1
"Unit";"Zergling";"Larva";511;1
"Unit";"Zergling";"Larva";511;1
"Unit";"Zergling";"Larva";511;1
"Unit";"Zergling";"Larva";511;1
"Unit";"Zergling";"Larva";511;1
"Unit";"Zergling";"Larva";511;1
"Unit";"Zergling";"Larva";511;1
"Unit";"Zergling";"Larva";511;1
"Unit";"Zergling";"Larva";511;1
"Unit";"Zergling";"Larva";511;1
"Unit";"Zergling";"Larva";511;1
"Unit";"Zergling";"Larva";511;1
"Unit";"Zergling";"Larva";511;1
"Unit";"Zergling";"Larva";511;1
"Unit";"Zergling";"Larva";511;1
"Unit";"Zergling";"Larva";511;1
"Unit";"Zergling";"Larva";511;1
"Building";"CreepTumorQueen";NA;511;0
"Building";"CreepTumorQueen";NA;511;0
"Building";"CreepTumor";NA;511;0
"Building";"CreepTumorQueen";NA;511;0
"Building";"CreepTumorQueen";NA;543;0
"Building";"CreepTumorQueen";NA;543;0
"Unit";"Baneling";"Zergling";543;0
"Building";"CreepTumor";NA;543;0
"Unit";"Baneling";"Zergling";543;0
"Unit";"Baneling";"Zergling";543;0
"Unit";"Baneling";"Zergling";543;0
"Unit";"Baneling";"Zergling";543;0
"Unit";"Baneling";"Zergling";543;0
"Unit";"Baneling";"Zergling";543;0
"Unit";"Baneling";"Zergling";543;0
"Unit";"Baneling";"Zergling";543;0
"Unit";"Baneling";"Zergling";543;0
"Unit";"Baneling";"Zergling";543;0
"Unit";"Baneling";"Zergling";543;0
"Unit";"Baneling";"Zergling";543;0
"Unit";"Baneling";"Zergling";543;0
"Building";"CreepTumor";NA;543;0
"Unit";"Queen";"Hatchery";521;2
"Building";"CreepTumor";NA;543;0
"Unit";"Corruptor";"Larva";543;2
"Unit";"Corruptor";"Larva";543;2
"Building";"CreepTumor";NA;543;0
"Unit";"Corruptor";"Larva";543;2
"Unit";"Corruptor";"Larva";543;2
"Unit";"Corruptor";"Larva";543;2
"Unit";"Corruptor";"Larva";543;2
"Unit";"Corruptor";"Larva";543;2
"Upgrade";"ZergGroundArmorsLevel3";"EvolutionChamber";471;0
"Upgrade";"ZergMeleeWeaponsLevel3";"EvolutionChamber";471;0
"Building";"CreepTumor";NA;559;0
"Building";"CreepTumor";NA;559;0
"Unit";"Zergling";"Larva";559;1
"Unit";"Zergling";"Larva";559;1
"Unit";"Zergling";"Larva";559;1
"Unit";"Zergling";"Larva";559;1
"Unit";"Zergling";"Larva";559;1
"Unit";"Zergling";"Larva";559;1
"Unit";"Zergling";"Larva";559;1
"Unit";"Zergling";"Larva";559;1
"Unit";"Zergling";"Larva";559;1
"Unit";"Zergling";"Larva";559;1
"Unit";"Zergling";"Larva";559;1
"Unit";"Zergling";"Larva";559;1
"Unit";"Zergling";"Larva";559;1
"Unit";"Zergling";"Larva";559;1
"Unit";"Zergling";"Larva";561;1
"Unit";"Zergling";"Larva";561;1
"Unit";"Zergling";"Larva";569;1
"Unit";"Zergling";"Larva";569;1
"Unit";"Zergling";"Larva";569;1
"Unit";"Zergling";"Larva";569;1
"Unit";"Zergling";"Larva";569;1
"Unit";"Zergling";"Larva";569;1
"Unit";"Zergling";"Larva";573;1
"Unit";"Zergling";"Larva";573;1
"Unit";"Zergling";"Larva";573;1
"Unit";"Zergling";"Larva";573;1
"Unit";"Zergling";"Larva";573;1
"Unit";"Zergling";"Larva";573;1
"Unit";"Zergling";"Larva";573;1
"Unit";"Zergling";"Larva";573;1
"Unit";"Zergling";"Larva";573;1
"Unit";"Zergling";"Larva";573;1
"Unit";"Zergling";"Larva";573;1
"Unit";"Zergling";"Larva";573;1
"Unit";"Zergling";"Larva";573;1
"Unit";"Zergling";"Larva";573;1
"Building";"Extractor";NA;573;0
"Building";"Extractor";NA;573;0
"Building";"CreepTumor";NA;595;0
"Building";"SporeCrawler";NA;595;0
"Building";"SpineCrawler";NA;595;0
"Building";"SpineCrawler";NA;595;0
"Building";"SpineCrawler";NA;595;0
"Building";"SpineCrawler";NA;595;0
"Building";"SpineCrawler";NA;595;0
"Building";"CreepTumorQueen";NA;595;0
"Building";"CreepTumorQueen";NA;595;0
"Building";"CreepTumor";NA;595;0
"Building";"CreepTumor";NA;595;0
"Building";"CreepTumor";NA;595;0
"Building";"CreepTumor";NA;595;0
"Building";"CreepTumor";NA;595;0
"Building";"CreepTumor";NA;595;0
"Building";"CreepTumor";NA;595;0
"Building";"CreepTumor";NA;595;0
"Building";"SpineCrawler";NA;595;0
"Building";"SpineCrawler";NA;595;0
"Building";"SpineCrawler";NA;595;0
"Building";"SpineCrawler";NA;595;0
"Unit";"Baneling";"Zergling";595;0
"Unit";"Baneling";"Zergling";595;0
"Unit";"Baneling";"Zergling";595;0
"Unit";"Baneling";"Zergling";595;0
"Unit";"Baneling";"Zergling";595;0
"Unit";"Baneling";"Zergling";595;0
"Unit";"Baneling";"Zergling";595;0
"Unit";"Baneling";"Zergling";595;0
"Unit";"Baneling";"Zergling";595;0
"Unit";"Baneling";"Zergling";595;0
"Unit";"Baneling";"Zergling";595;0
"Unit";"Baneling";"Zergling";595;0
"Upgrade";"ZergMissileWeaponsLevel2";"EvolutionChamber";573;0
"Unit";"Corruptor";"Larva";595;2
"Unit";"Corruptor";"Larva";595;2
"Unit";"Corruptor";"Larva";595;2
"Unit";"Corruptor";"Larva";595;2
"Unit";"Corruptor";"Larva";595;2
"Unit";"Corruptor";"Larva";595;2
"Unit";"Corruptor";"Larva";595;2
"Unit";"Zergling";"Larva";595;1
"Unit";"Zergling";"Larva";595;1
"Unit";"Zergling";"Larva";595;1
"Unit";"Zergling";"Larva";595;1
"Unit";"Zergling";"Larva";595;1
"Unit";"Zergling";"Larva";595;1
"Unit";"Zergling";"Larva";595;1
"Unit";"Zergling";"Larva";595;1
"Unit";"Zergling";"Larva";595;1
"Unit";"Zergling";"Larva";595;1
"Unit";"Zergling";"Larva";595;1
"Unit";"Zergling";"Larva";595;1
"Unit";"Zergling";"Larva";595;1
"Unit";"Zergling";"Larva";595;1
"Unit";"Zergling";"Larva";595;1
"Unit";"Zergling";"Larva";595;1
"Unit";"Zergling";"Larva";595;1
"Unit";"Zergling";"Larva";595;1
"Unit";"Zergling";"Larva";595;1
"Unit";"Zergling";"Larva";595;1
"Unit";"Zergling";"Larva";595;1
"Unit";"Zergling";"Larva";595;1
"Unit";"Zergling";"Larva";595;1
"Unit";"Zergling";"Larva";595;1
"Unit";"Zergling";"Larva";595;1
"Unit";"Zergling";"Larva";595;1
"Unit";"Zergling";"Larva";595;1
"Unit";"Zergling";"Larva";595;1
"Building";"Spire";NA;595;0
"Unit";"Zergling";"Larva";637;1
"Unit";"Zergling";"Larva";637;1
"Unit";"Zergling";"Larva";637;1
"Unit";"Zergling";"Larva";637;1
"Unit";"Zergling";"Larva";637;1
"Unit";"Zergling";"Larva";637;1
"Unit";"Zergling";"Larva";637;1
"Unit";"Zergling";"Larva";637;1
"Unit";"Zergling";"Larva";637;1
"Unit";"Zergling";"Larva";637;1
"Unit";"Zergling";"Larva";637;1
"Unit";"Zergling";"Larva";637;1
"Unit";"Zergling";"Larva";637;1
"Unit";"Zergling";"Larva";637;1
"Unit";"Zergling";"Larva";637;1
"Unit";"Zergling";"Larva";637;1
"Unit";"Zergling";"Larva";637;1
"Unit";"Zergling";"Larva";637;1
"Unit";"Zergling";"Larva";637;1
"Unit";"Zergling";"Larva";637;1
"Unit";"Zergling";"Larva";637;1
"Unit";"Zergling";"Larva";637;1
"Unit";"Zergling";"Larva";637;1
"Unit";"Zergling";"Larva";637;1
"Unit";"Zergling";"Larva";637;1
"Unit";"Zergling";"Larva";637;1
"Building";"SpineCrawler";NA;637;0
"Building";"SpineCrawler";NA;637;0
"Building";"SpineCrawler";NA;637;0
"Unit";"Zergling";"Larva";663;1
"Unit";"Zergling";"Larva";663;1
"Unit";"Zergling";"Larva";663;1
"Unit";"Zergling";"Larva";663;1
"Unit";"Zergling";"Larva";663;1
"Unit";"Zergling";"Larva";663;1
"Unit";"Zergling";"Larva";663;1
"Unit";"Zergling";"Larva";663;1
"Unit";"Zergling";"Larva";663;1
"Unit";"Zergling";"Larva";663;1
"Unit";"Zergling";"Larva";663;1
"Unit";"Zergling";"Larva";663;1
"Unit";"Zergling";"Larva";663;1
"Unit";"Zergling";"Larva";663;1
"Unit";"Zergling";"Larva";663;1
"Unit";"Zergling";"Larva";663;1
"Unit";"Zergling";"Larva";663;1
"Unit";"Zergling";"Larva";663;1
"Unit";"Zergling";"Larva";663;1
"Unit";"Zergling";"Larva";663;1
"Unit";"Zergling";"Larva";663;1
"Unit";"Zergling";"Larva";663;1
"Unit";"Zergling";"Larva";663;1
"Unit";"Zergling";"Larva";663;1
"Unit";"Zergling";"Larva";663;1
"Unit";"Zergling";"Larva";663;1
"Unit";"Zergling";"Larva";663;1
"Unit";"Zergling";"Larva";663;1
"Unit";"Zergling";"Larva";663;1
"Unit";"Zergling";"Larva";663;1
"Unit";"Zergling";"Larva";663;1
"Unit";"Zergling";"Larva";663;1
"Unit";"Zergling";"Larva";663;1
"Unit";"Zergling";"Larva";663;1
"Unit";"Zergling";"Larva";663;1
"Unit";"Zergling";"Larva";663;1
"Unit";"Zergling";"Larva";663;1
"Unit";"Zergling";"Larva";663;1
"Unit";"Zergling";"Larva";663;1
"Unit";"Zergling";"Larva";663;1
"Unit";"Zergling";"Larva";663;1
"Unit";"Zergling";"Larva";663;1
"Unit";"Zergling";"Larva";663;1
"Unit";"Zergling";"Larva";663;1
"Unit";"Zergling";"Larva";663;1
"Unit";"Zergling";"Larva";663;1
"Unit";"Zergling";"Larva";663;1
"Unit";"Zergling";"Larva";663;1
"Unit";"Zergling";"Larva";663;1
"Unit";"Zergling";"Larva";663;1
"Unit";"Zergling";"Larva";663;1
"Unit";"Zergling";"Larva";663;1
"Unit";"Zergling";"Larva";663;1
"Unit";"Zergling";"Larva";663;1
"Unit";"Zergling";"Larva";663;1
"Unit";"Zergling";"Larva";663;1
"Unit";"Zergling";"Larva";663;1
"Unit";"Zergling";"Larva";663;1
"Unit";"Zergling";"Larva";663;1
"Unit";"Zergling";"Larva";663;1
"Building";"CreepTumorQueen";NA;697;0
"Unit";"Zergling";"Larva";723;1
"Unit";"Zergling";"Larva";723;1
"Unit";"Zergling";"Larva";723;1
"Unit";"Zergling";"Larva";723;1
"Unit";"Zergling";"Larva";723;1
"Unit";"Zergling";"Larva";723;1
"Unit";"Zergling";"Larva";723;1
"Unit";"Zergling";"Larva";723;1
"Unit";"Zergling";"Larva";723;1
"Unit";"Zergling";"Larva";723;1
"Unit";"Zergling";"Larva";723;1
"Unit";"Zergling";"Larva";723;1
"Unit";"Zergling";"Larva";723;1
"Unit";"Zergling";"Larva";723;1
"Unit";"Zergling";"Larva";723;1
"Unit";"Zergling";"Larva";723;1
"Unit";"Zergling";"Larva";723;1
"Unit";"Zergling";"Larva";723;1
"Unit";"Zergling";"Larva";723;1
"Unit";"Zergling";"Larva";723;1
"Unit";"Zergling";"Larva";723;1
"Unit";"Zergling";"Larva";723;1
"Unit";"Zergling";"Larva";723;1
"Unit";"Zergling";"Larva";723;1
"Unit";"Zergling";"Larva";723;1
"Unit";"Zergling";"Larva";723;1
"Unit";"Zergling";"Larva";723;1
"Unit";"Zergling";"Larva";723;1
"Unit";"Zergling";"Larva";723;1
"Unit";"Zergling";"Larva";723;1
"Unit";"Zergling";"Larva";723;1
"Unit";"Zergling";"Larva";723;1
"Unit";"Zergling";"Larva";723;1
"Unit";"Zergling";"Larva";723;1
"Unit";"Zergling";"Larva";723;1
"Unit";"Zergling";"Larva";723;1
"Unit";"Zergling";"Larva";723;1
"Unit";"Zergling";"Larva";723;1
"Unit";"Zergling";"Larva";723;1
"Unit";"Zergling";"Larva";723;1
"Unit";"Zergling";"Larva";723;1
"Unit";"Zergling";"Larva";723;1
"Unit";"Zergling";"Larva";723;1
"Unit";"Zergling";"Larva";723;1
"Unit";"Hydralisk";"Larva";723;2
"Unit";"Hydralisk";"Larva";723;2
"Unit";"Hydralisk";"Larva";723;2
"Unit";"Hydralisk";"Larva";723;2
"Unit";"Hydralisk";"Larva";723;2
"Unit";"Hydralisk";"Larva";723;2
"Unit";"Hydralisk";"Larva";723;2
"Unit";"Hydralisk";"Larva";723;2
"Building";"CreepTumor";NA;767;0
"Unit";"Baneling";"Zergling";767;0
"Unit";"Baneling";"Zergling";767;0
"Unit";"Baneling";"Zergling";767;0
"Unit";"Baneling";"Zergling";767;0
"Unit";"Baneling";"Zergling";767;0
"Unit";"Baneling";"Zergling";767;0
"Unit";"Baneling";"Zergling";767;0
"Unit";"Baneling";"Zergling";767;0
"Unit";"Baneling";"Zergling";767;0
"Unit";"Baneling";"Zergling";767;0
"Unit";"Baneling";"Zergling";767;0
"Unit";"Baneling";"Zergling";767;0
"Unit";"Baneling";"Zergling";767;0
"Unit";"Baneling";"Zergling";767;0
"Unit";"Baneling";"Zergling";767;0
"Unit";"Baneling";"Zergling";767;0
"Unit";"Baneling";"Zergling";767;0
"Unit";"Baneling";"Zergling";767;0
"Unit";"Baneling";"Zergling";767;0
"Building";"Extractor";NA;767;0
"Unit";"Zergling";"Larva";767;1
"Unit";"Zergling";"Larva";767;1
"Unit";"Zergling";"Larva";767;1
"Unit";"Zergling";"Larva";767;1
"Unit";"Zergling";"Larva";767;1
"Unit";"Zergling";"Larva";767;1
"Unit";"Zergling";"Larva";767;1
"Unit";"Zergling";"Larva";767;1
"Unit";"Zergling";"Larva";767;1
"Unit";"Zergling";"Larva";767;1
"Unit";"Zergling";"Larva";767;1
"Unit";"Zergling";"Larva";767;1
"Unit";"Zergling";"Larva";769;1
"Unit";"Zergling";"Larva";769;1
"Unit";"Zergling";"Larva";769;1
"Unit";"Zergling";"Larva";769;1
"Unit";"Zergling";"Larva";769;1
"Unit";"Zergling";"Larva";769;1
"Unit";"Zergling";"Larva";769;1
"Unit";"Zergling";"Larva";769;1
"Unit";"Zergling";"Larva";788;1
"Unit";"Zergling";"Larva";788;1
"Unit";"Zergling";"Larva";788;1
"Unit";"Zergling";"Larva";788;1
"Unit";"Zergling";"Larva";788;1
"Unit";"Zergling";"Larva";788;1
"Unit";"Zergling";"Larva";788;1
"Unit";"Zergling";"Larva";788;1
"Unit";"Zergling";"Larva";788;1
"Unit";"Zergling";"Larva";788;1
"Unit";"Zergling";"Larva";788;1
"Unit";"Zergling";"Larva";788;1
"Unit";"Zergling";"Larva";788;1
"Unit";"Zergling";"Larva";788;1
"Unit";"Zergling";"Larva";788;1
"Unit";"Zergling";"Larva";788;1
"Building";"CreepTumor";NA;808;0
"Unit";"Zergling";"Larva";808;1
"Unit";"Zergling";"Larva";808;1
"Unit";"Zergling";"Larva";808;1
"Unit";"Zergling";"Larva";808;1
"Unit";"Zergling";"Larva";808;1
"Unit";"Zergling";"Larva";808;1
"Unit";"Zergling";"Larva";808;1
"Unit";"Zergling";"Larva";808;1
"Unit";"Zergling";"Larva";810;1
"Unit";"Zergling";"Larva";810;1
"Unit";"Zergling";"Larva";810;1
"Unit";"Zergling";"Larva";810;1
"Unit";"Zergling";"Larva";810;1
"Unit";"Zergling";"Larva";810;1
"Unit";"Zergling";"Larva";810;1
"Unit";"Zergling";"Larva";810;1
"Unit";"Zergling";"Larva";810;1
"Unit";"Zergling";"Larva";810;1
"Unit";"Zergling";"Larva";810;1
"Unit";"Zergling";"Larva";810;1
"Unit";"Zergling";"Larva";810;1
"Unit";"Zergling";"Larva";810;1
"Unit";"Zergling";"Larva";810;1
"Unit";"Zergling";"Larva";810;1
"Building";"CreepTumor";NA;824;0
"Building";"CreepTumor";NA;848;0
"Unit";"Corruptor";"Larva";824;2
"Unit";"Corruptor";"Larva";824;2
"Unit";"Corruptor";"Larva";824;2
"Unit";"Corruptor";"Larva";824;2
"Unit";"Baneling";"Zergling";848;0
"Unit";"Baneling";"Zergling";848;0
"Unit";"Baneling";"Zergling";848;0
"Unit";"Baneling";"Zergling";848;0
"Unit";"Baneling";"Zergling";848;0
"Unit";"Baneling";"Zergling";848;0
"Unit";"Baneling";"Zergling";848;0
"Unit";"Baneling";"Zergling";848;0
"Unit";"Baneling";"Zergling";848;0
"Unit";"Baneling";"Zergling";848;0
"Unit";"Baneling";"Zergling";848;0
"Unit";"Baneling";"Zergling";848;0
"Unit";"Baneling";"Zergling";848;0
"Unit";"Baneling";"Zergling";848;0
"Unit";"Baneling";"Zergling";848;0
"Unit";"Baneling";"Zergling";848;0
"Building";"CreepTumor";NA;856;0
"Unit";"Baneling";"Zergling";856;0
"Unit";"Baneling";"Zergling";856;0
"Unit";"Baneling";"Zergling";856;0
"Unit";"Baneling";"Zergling";856;0
"Unit";"Baneling";"Zergling";856;0
"Unit";"Baneling";"Zergling";856;0
"Unit";"Baneling";"Zergling";856;0
"Unit";"Baneling";"Zergling";856;0
"Building";"CreepTumorQueen";NA;856;0
"Unit";"Zergling";"Larva";856;1
"Unit";"Zergling";"Larva";856;1
"Unit";"Zergling";"Larva";856;1
"Unit";"Zergling";"Larva";856;1
"Unit";"Zergling";"Larva";856;1
"Unit";"Zergling";"Larva";856;1
"Unit";"Zergling";"Larva";856;1
"Unit";"Zergling";"Larva";856;1
"Unit";"Zergling";"Larva";856;1
"Unit";"Zergling";"Larva";856;1
"Unit";"Zergling";"Larva";856;1
"Unit";"Zergling";"Larva";856;1
"Unit";"Zergling";"Larva";856;1
"Unit";"Zergling";"Larva";856;1
"Unit";"Zergling";"Larva";856;1
"Unit";"Zergling";"Larva";856;1
"Unit";"Zergling";"Larva";856;1
"Unit";"Zergling";"Larva";856;1
"Unit";"Zergling";"Larva";856;1
"Unit";"Zergling";"Larva";856;1
"Unit";"Zergling";"Larva";856;1
"Unit";"Zergling";"Larva";856;1
"Unit";"Zergling";"Larva";856;1
"Unit";"Zergling";"Larva";856;1
"Unit";"Zergling";"Larva";856;1
"Unit";"Zergling";"Larva";856;1
"Unit";"Zergling";"Larva";856;1
"Unit";"Zergling";"Larva";856;1
"Unit";"Zergling";"Larva";856;1
"Unit";"Zergling";"Larva";856;1
"Unit";"Zergling";"Larva";856;1
"Unit";"Zergling";"Larva";856;1
"Unit";"Zergling";"Larva";856;1
"Unit";"Zergling";"Larva";856;1
"Unit";"Zergling";"Larva";856;1
"Unit";"Zergling";"Larva";856;1
"Building";"CreepTumor";NA;856;0
"Building";"CreepTumor";NA;856;0
"Building";"CreepTumor";NA;856;0
"Building";"Extractor";NA;856;0
"Building";"Extractor";NA;856;0
"Unit";"Zergling";"Larva";856;1
"Unit";"Zergling";"Larva";856;1
"Unit";"Zergling";"Larva";856;1
"Unit";"Zergling";"Larva";856;1
"Unit";"Zergling";"Larva";856;1
"Unit";"Zergling";"Larva";856;1
"Unit";"Zergling";"Larva";856;1
"Unit";"Zergling";"Larva";856;1
"Unit";"Zergling";"Larva";856;1
"Unit";"Zergling";"Larva";856;1
"Unit";"Baneling";"Zergling";892;0
"Building";"CreepTumorQueen";NA;902;0
"Building";"CreepTumor";NA;902;0
"Building";"CreepTumor";NA;902;0
"Building";"Hatchery";NA;856;0
"Building";"CreepTumor";NA;902;0
"Unit";"Overlord";"Larva";902;0
"Unit";"Overlord";"Larva";902;0
"Unit";"Overlord";"Larva";902;0
"Building";"CreepTumor";NA;902;0
"Building";"CreepTumor";NA;902;0
"Building";"CreepTumor";NA;902;0
"Unit";"Zergling";"Larva";902;1
"Unit";"Zergling";"Larva";902;1
"Unit";"Zergling";"Larva";902;1
"Unit";"Zergling";"Larva";902;1
"Unit";"Zergling";"Larva";902;1
"Unit";"Zergling";"Larva";902;1
"Unit";"Zergling";"Larva";902;1
"Unit";"Zergling";"Larva";902;1
"Unit";"Zergling";"Larva";902;1
"Unit";"Zergling";"Larva";902;1
"Unit";"Zergling";"Larva";902;1
"Unit";"Zergling";"Larva";902;1
"Unit";"Zergling";"Larva";902;1
"Unit";"Zergling";"Larva";902;1
"Unit";"Zergling";"Larva";902;1
"Unit";"Zergling";"Larva";902;1
"Unit";"Zergling";"Larva";902;1
"Unit";"Zergling";"Larva";902;1
"Unit";"Zergling";"Larva";902;1
"Unit";"Zergling";"Larva";902;1
"Unit";"Zergling";"Larva";902;1
"Unit";"Zergling";"Larva";902;1
"Unit";"Zergling";"Larva";902;1
"Unit";"Zergling";"Larva";902;1
"Unit";"Zergling";"Larva";902;1
"Unit";"Zergling";"Larva";902;1
"Unit";"Zergling";"Larva";902;1
"Unit";"Zergling";"Larva";902;1
"Unit";"Zergling";"Larva";902;1
"Unit";"Zergling";"Larva";902;1
"Unit";"Zergling";"Larva";902;1
"Unit";"Zergling";"Larva";902;1
"Building";"CreepTumor";NA;902;0
"Unit";"Baneling";"Zergling";902;0
"Unit";"Baneling";"Zergling";902;0
"Unit";"Baneling";"Zergling";902;0
"Unit";"Baneling";"Zergling";902;0
"Unit";"Baneling";"Zergling";902;0
"Unit";"Baneling";"Zergling";902;0
"Building";"CreepTumorQueen";NA;938;0
"Building";"CreepTumorQueen";NA;938;0
"Building";"CreepTumorQueen";NA;938;0
"Building";"CreepTumorQueen";NA;938;0
"Unit";"Queen";"Hatchery";902;2
"Building";"CreepTumor";NA;938;0
"Building";"CreepTumor";NA;938;0
"Building";"CreepTumor";NA;938;0
"Building";"CreepTumor";NA;938;0
"Building";"CreepTumor";NA;938;0
"Building";"CreepTumor";NA;938;0
"Building";"Hatchery";NA;902;0
"Unit";"Zergling";"Larva";940;1
"Unit";"Zergling";"Larva";940;1
"Unit";"Zergling";"Larva";940;1
"Unit";"Zergling";"Larva";940;1
"Unit";"Zergling";"Larva";940;1
"Unit";"Zergling";"Larva";940;1
"Unit";"Zergling";"Larva";940;1
"Unit";"Zergling";"Larva";940;1
"Unit";"Zergling";"Larva";940;1
"Unit";"Zergling";"Larva";940;1
"Unit";"Zergling";"Larva";940;1
"Unit";"Zergling";"Larva";940;1
"Unit";"Zergling";"Larva";940;1
"Unit";"Zergling";"Larva";940;1
"Unit";"Zergling";"Larva";940;1
"Unit";"Zergling";"Larva";940;1
"Unit";"Zergling";"Larva";940;1
"Unit";"Zergling";"Larva";940;1
"Unit";"Zergling";"Larva";940;1
"Unit";"Zergling";"Larva";940;1
"Unit";"Zergling";"Larva";940;1
"Unit";"Zergling";"Larva";940;1
"Unit";"Zergling";"Larva";940;1
"Unit";"Zergling";"Larva";940;1
"Unit";"Zergling";"Larva";940;1
"Unit";"Zergling";"Larva";940;1
"Unit";"Zergling";"Larva";940;1
"Unit";"Zergling";"Larva";940;1
"Unit";"Zergling";"Larva";940;1
"Unit";"Zergling";"Larva";940;1
"Unit";"Zergling";"Larva";940;1
"Unit";"Zergling";"Larva";940;1
"Unit";"Zergling";"Larva";940;1
"Unit";"Zergling";"Larva";940;1
"Unit";"Zergling";"Larva";940;1
"Unit";"Zergling";"Larva";940;1
"Unit";"Baneling";"Zergling";940;0
"Unit";"Baneling";"Zergling";940;0
"Unit";"Baneling";"Zergling";940;0
"Unit";"Baneling";"Zergling";940;0
"Unit";"Baneling";"Zergling";940;0
"Unit";"Baneling";"Zergling";940;0
"Unit";"Baneling";"Zergling";940;0
"Unit";"Baneling";"Zergling";940;0
"Unit";"Baneling";"Zergling";940;0
"Unit";"Baneling";"Zergling";940;0
"Unit";"Baneling";"Zergling";940;0
"Building";"CreepTumor";NA;976;0
"Building";"CreepTumor";NA;976;0
"Building";"CreepTumorQueen";NA;976;0
"Building";"CreepTumor";NA;976;0
"Building";"Extractor";NA;976;0
"Building";"CreepTumor";NA;976;0
"Building";"CreepTumorQueen";NA;976;0
"Building";"CreepTumor";NA;976;0
"Building";"SporeCrawler";NA;976;0
"Building";"SpineCrawler";NA;976;0
"Building";"CreepTumor";NA;983;0
"Building";"CreepTumor";NA;983;0
"Building";"CreepTumor";NA;983;0
"Building";"CreepTumor";NA;983;0
"Building";"CreepTumor";NA;989;0
"Building";"CreepTumor";NA;989;0
"Unit";"Corruptor";"Larva";989;2
"Unit";"Corruptor";"Larva";989;2
"Unit";"Corruptor";"Larva";989;2
"Unit";"Corruptor";"Larva";989;2
"Unit";"Corruptor";"Larva";989;2
"Unit";"Corruptor";"Larva";989;2
"Unit";"Corruptor";"Larva";989;2
"Unit";"Viper";"Larva";989;3
"Unit";"Viper";"Larva";989;3
"Unit";"Viper";"Larva";989;3
"Unit";"Baneling";"Zergling";989;0
"Unit";"Baneling";"Zergling";989;0
"Unit";"Baneling";"Zergling";989;0
"Unit";"Baneling";"Zergling";989;0
"Unit";"Baneling";"Zergling";989;0
"Unit";"Baneling";"Zergling";989;0
"Unit";"Baneling";"Zergling";989;0
"Unit";"Baneling";"Zergling";989;0
"Building";"CreepTumorQueen";NA;989;0
"Building";"Extractor";NA;989;0
"Building";"Extractor";NA;1003;0
"Building";"SporeCrawler";NA;1012;0
"Building";"CreepTumor";NA;1012;0
"Building";"SporeCrawler";NA;1012;0
"Building";"CreepTumor";NA;1012;0
"Building";"CreepTumor";NA;1012;0
"Building";"CreepTumor";NA;1012;0
"Building";"SpineCrawler";NA;1012;0
"Building";"SpineCrawler";NA;1012;0
"Unit";"Zergling";"Larva";1012;1
"Unit";"Zergling";"Larva";1012;1
"Unit";"Zergling";"Larva";1012;1
"Unit";"Zergling";"Larva";1012;1
"Unit";"Zergling";"Larva";1012;1
"Unit";"Zergling";"Larva";1012;1
"Unit";"Zergling";"Larva";1012;1
"Unit";"Zergling";"Larva";1012;1
"Unit";"Zergling";"Larva";1012;1
"Unit";"Zergling";"Larva";1012;1
"Unit";"Zergling";"Larva";1012;1
"Unit";"Zergling";"Larva";1012;1
"Unit";"Zergling";"Larva";1012;1
"Unit";"Zergling";"Larva";1012;1
"Unit";"Zergling";"Larva";1012;1
"Unit";"Zergling";"Larva";1012;1
"Unit";"Zergling";"Larva";1012;1
"Unit";"Zergling";"Larva";1012;1
"Unit";"Zergling";"Larva";1012;1
"Unit";"Zergling";"Larva";1012;1
"Unit";"Zergling";"Larva";1012;1
"Unit";"Zergling";"Larva";1012;1
"Unit";"Zergling";"Larva";1012;1
"Unit";"Zergling";"Larva";1012;1
"Unit";"Zergling";"Larva";1012;1
"Unit";"Zergling";"Larva";1012;1
"Unit";"Zergling";"Larva";1012;1
"Unit";"Zergling";"Larva";1012;1
"Unit";"Zergling";"Larva";1012;1
"Unit";"Zergling";"Larva";1012;1
"Unit";"Zergling";"Larva";1012;1
"Unit";"Zergling";"Larva";1012;1
"Unit";"Zergling";"Larva";1012;1
"Unit";"Zergling";"Larva";1012;1
"Unit";"Zergling";"Larva";1012;1
"Unit";"Zergling";"Larva";1012;1
"Unit";"Zergling";"Larva";1012;1
"Unit";"Zergling";"Larva";1012;1
"Unit";"Zergling";"Larva";1012;1
"Unit";"Zergling";"Larva";1012;1
"Unit";"Zergling";"Larva";1012;1
"Unit";"Zergling";"Larva";1012;1
"Unit";"Zergling";"Larva";1012;1
"Unit";"Zergling";"Larva";1012;1
"Unit";"Zergling";"Larva";1012;1
"Unit";"Zergling";"Larva";1012;1
"Unit";"Zergling";"Larva";1012;1
"Unit";"Zergling";"Larva";1012;1
"Unit";"Overlord";"Larva";1040;0
"Unit";"Overlord";"Larva";1040;0
"Unit";"Overlord";"Larva";1040;0
"Unit";"Overlord";"Larva";1040;0
"Unit";"Overlord";"Larva";1040;0
"Unit";"Overlord";"Larva";1040;0
"Unit";"Overlord";"Larva";1040;0
"Unit";"Overlord";"Larva";1040;0
"Building";"Hatchery";NA;1012;0
"Unit";"Zergling";"Larva";1060;1
"Unit";"Zergling";"Larva";1060;1
"Unit";"Zergling";"Larva";1060;1
"Unit";"Zergling";"Larva";1060;1
"Unit";"Zergling";"Larva";1060;1
"Unit";"Zergling";"Larva";1060;1
"Unit";"Zergling";"Larva";1060;1
"Unit";"Zergling";"Larva";1060;1
"Unit";"Zergling";"Larva";1060;1
"Unit";"Zergling";"Larva";1060;1
"Unit";"Zergling";"Larva";1060;1
"Unit";"Zergling";"Larva";1060;1
"Unit";"Zergling";"Larva";1060;1
"Unit";"Zergling";"Larva";1060;1
"Unit";"Zergling";"Larva";1060;1
"Unit";"Zergling";"Larva";1060;1
"Unit";"Zergling";"Larva";1060;1
"Unit";"Zergling";"Larva";1060;1
"Unit";"Zergling";"Larva";1060;1
"Unit";"Zergling";"Larva";1060;1
"Unit";"Zergling";"Larva";1060;1
"Unit";"Zergling";"Larva";1060;1
"Unit";"Zergling";"Larva";1060;1
"Unit";"Zergling";"Larva";1060;1
"Unit";"Zergling";"Larva";1060;1
"Unit";"Zergling";"Larva";1060;1
"Unit";"Zergling";"Larva";1060;1
"Unit";"Zergling";"Larva";1060;1
"Unit";"Zergling";"Larva";1060;1
"Unit";"Zergling";"Larva";1060;1
"Unit";"Zergling";"Larva";1060;1
"Unit";"Zergling";"Larva";1060;1
"Building";"CreepTumor";NA;1078;0
"Building";"CreepTumor";NA;1078;0
"Unit";"Hydralisk";"Larva";1078;2
"Unit";"Hydralisk";"Larva";1078;2
"Unit";"Hydralisk";"Larva";1078;2
"Unit";"Hydralisk";"Larva";1078;2
"Unit";"Hydralisk";"Larva";1078;2
"Unit";"Hydralisk";"Larva";1078;2
"Unit";"Hydralisk";"Larva";1078;2
"Unit";"Hydralisk";"Larva";1078;2
"Unit";"Baneling";"Zergling";1092;0
"Unit";"Baneling";"Zergling";1092;0
"Unit";"Baneling";"Zergling";1092;0
"Unit";"Baneling";"Zergling";1092;0
"Unit";"Baneling";"Zergling";1092;0
"Unit";"Baneling";"Zergling";1092;0
"Unit";"Baneling";"Zergling";1092;0
"Unit";"Baneling";"Zergling";1092;0
"Unit";"Baneling";"Zergling";1092;0
"Unit";"Baneling";"Zergling";1092;0
"Unit";"Baneling";"Zergling";1092;0
"Unit";"Baneling";"Zergling";1092;0
"Unit";"Baneling";"Zergling";1092;0
"Unit";"Baneling";"Zergling";1092;0
"Unit";"Baneling";"Zergling";1092;0
"Unit";"Baneling";"Zergling";1092;0
"Unit";"Baneling";"Zergling";1092;0
"Unit";"Baneling";"Zergling";1092;0
"Unit";"Baneling";"Zergling";1092;0
"Unit";"Baneling";"Zergling";1092;0
"Unit";"Baneling";"Zergling";1092;0
"Unit";"Baneling";"Zergling";1092;0
"Unit";"Baneling";"Zergling";1092;0
"Unit";"Baneling";"Zergling";1092;0
"Unit";"Baneling";"Zergling";1092;0
"Building";"CreepTumor";NA;1115;0
"Building";"CreepTumor";NA;1115;0
"Building";"CreepTumor";NA;1115;0
"Unit";"Hydralisk";"Larva";1109;2
"Unit";"Hydralisk";"Larva";1115;2
"Unit";"Hydralisk";"Larva";1115;2
"Unit";"Hydralisk";"Larva";1115;2
"Unit";"Hydralisk";"Larva";1115;2
"Unit";"Hydralisk";"Larva";1115;2
"Unit";"Hydralisk";"Larva";1115;2
"Unit";"Hydralisk";"Larva";1115;2
"Unit";"Hydralisk";"Larva";1115;2
"Building";"SporeCrawler";NA;1115;0
"Unit";"Overlord";"Larva";1133;0
"Unit";"Overlord";"Larva";1135;0
"Unit";"Overlord";"Larva";1135;0
"Unit";"Overlord";"Larva";1138;0
"Unit";"Overlord";"Larva";1138;0
"Unit";"Zergling";"Larva";1143;1
"Unit";"Zergling";"Larva";1143;1
"Unit";"Zergling";"Larva";1143;1
"Unit";"Zergling";"Larva";1143;1
"Unit";"Zergling";"Larva";1143;1
"Unit";"Zergling";"Larva";1143;1
"Unit";"Zergling";"Larva";1143;1
"Unit";"Zergling";"Larva";1143;1
"Unit";"Zergling";"Larva";1143;1
"Unit";"Zergling";"Larva";1143;1
"Unit";"Zergling";"Larva";1143;1
"Unit";"Zergling";"Larva";1143;1
"Unit";"Zergling";"Larva";1143;1
"Unit";"Zergling";"Larva";1143;1
"Unit";"Zergling";"Larva";1143;1
"Unit";"Zergling";"Larva";1143;1
"Unit";"Zergling";"Larva";1143;1
"Unit";"Zergling";"Larva";1143;1
"Unit";"Zergling";"Larva";1143;1
"Unit";"Zergling";"Larva";1143;1
"Building";"CreepTumorQueen";NA;1163;0
"Unit";"Zergling";"Larva";1163;1
"Unit";"Zergling";"Larva";1163;1
"Unit";"Zergling";"Larva";1163;1
"Unit";"Zergling";"Larva";1163;1
"Unit";"Zergling";"Larva";1163;1
"Unit";"Zergling";"Larva";1163;1
"Unit";"Zergling";"Larva";1163;1
"Unit";"Zergling";"Larva";1163;1
"Unit";"Zergling";"Larva";1163;1
"Unit";"Zergling";"Larva";1163;1
"Unit";"Zergling";"Larva";1163;1
"Unit";"Zergling";"Larva";1163;1
"Unit";"Zergling";"Larva";1163;1
"Unit";"Zergling";"Larva";1163;1
"Unit";"Zergling";"Larva";1163;1
"Unit";"Zergling";"Larva";1163;1
"Unit";"Zergling";"Larva";1163;1
"Unit";"Zergling";"Larva";1163;1
"Unit";"Zergling";"Larva";1163;1
"Unit";"Zergling";"Larva";1163;1
"Unit";"Zergling";"Larva";1163;1
"Unit";"Zergling";"Larva";1163;1
"Unit";"Zergling";"Larva";1163;1
"Unit";"Zergling";"Larva";1163;1
"Unit";"Zergling";"Larva";1163;1
"Unit";"Zergling";"Larva";1163;1
"Unit";"Zergling";"Larva";1163;1
"Unit";"Zergling";"Larva";1163;1
"Unit";"Zergling";"Larva";1163;1
"Unit";"Zergling";"Larva";1163;1
"Unit";"Baneling";"Zergling";1163;0
"Unit";"Baneling";"Zergling";1163;0
"Unit";"Baneling";"Zergling";1163;0
"Unit";"Baneling";"Zergling";1163;0
"Unit";"Baneling";"Zergling";1163;0
"Unit";"Baneling";"Zergling";1163;0
"Unit";"Zergling";"Larva";1163;1
"Unit";"Zergling";"Larva";1163;1
"Unit";"Zergling";"Larva";1163;1
"Unit";"Zergling";"Larva";1163;1
"Unit";"Zergling";"Larva";1163;1
"Unit";"Zergling";"Larva";1163;1
"Unit";"Zergling";"Larva";1163;1
"Unit";"Zergling";"Larva";1163;1
"Unit";"Zergling";"Larva";1163;1
"Unit";"Zergling";"Larva";1163;1
"Unit";"Zergling";"Larva";1163;1
"Unit";"Zergling";"Larva";1163;1
"Unit";"Zergling";"Larva";1163;1
"Unit";"Zergling";"Larva";1163;1
"Unit";"Zergling";"Larva";1163;1
"Unit";"Zergling";"Larva";1163;1
"Unit";"Zergling";"Larva";1163;1
"Unit";"Zergling";"Larva";1163;1
"Unit";"Zergling";"Larva";1163;1
"Unit";"Zergling";"Larva";1163;1
"Unit";"Zergling";"Larva";1163;1
"Unit";"Zergling";"Larva";1163;1
"Unit";"Zergling";"Larva";1163;1
"Unit";"Zergling";"Larva";1163;1
"Unit";"Zergling";"Larva";1163;1
"Unit";"Zergling";"Larva";1163;1
"Building";"CreepTumorQueen";NA;1203;0
"Building";"CreepTumorQueen";NA;1203;0
"Building";"SporeCrawler";NA;1219;0
"Building";"SporeCrawler";NA;1219;0
"Unit";"Zergling";"Larva";1219;1
"Unit";"Zergling";"Larva";1219;1
"Unit";"Zergling";"Larva";1219;1
"Unit";"Zergling";"Larva";1219;1
"Unit";"Zergling";"Larva";1219;1
"Unit";"Zergling";"Larva";1219;1
"Unit";"Zergling";"Larva";1219;1
"Unit";"Zergling";"Larva";1219;1
"Unit";"Zergling";"Larva";1219;1
"Unit";"Zergling";"Larva";1219;1
"Unit";"Zergling";"Larva";1219;1
"Unit";"Zergling";"Larva";1219;1
"Unit";"Zergling";"Larva";1219;1
"Unit";"Zergling";"Larva";1219;1
"Unit";"Zergling";"Larva";1219;1
"Unit";"Zergling";"Larva";1219;1
"Building";"SporeCrawler";NA;1219;0
"Unit";"Zergling";"Larva";1219;1
"Unit";"Zergling";"Larva";1219;1
"Unit";"Zergling";"Larva";1219;1
"Unit";"Zergling";"Larva";1219;1
"Unit";"Zergling";"Larva";1219;1
"Unit";"Zergling";"Larva";1219;1
"Unit";"Zergling";"Larva";1219;1
"Unit";"Zergling";"Larva";1219;1
"Unit";"Zergling";"Larva";1219;1
"Unit";"Zergling";"Larva";1219;1
"Unit";"Zergling";"Larva";1219;1
"Unit";"Zergling";"Larva";1219;1
"Unit";"Zergling";"Larva";1219;1
"Unit";"Zergling";"Larva";1219;1
"Unit";"Zergling";"Larva";1219;1
"Unit";"Zergling";"Larva";1219;1
"Building";"CreepTumor";NA;1219;0
"Building";"CreepTumor";NA;1219;0
"Building";"Extractor";NA;1219;0
"Unit";"Zergling";"Larva";1219;1
"Unit";"Zergling";"Larva";1219;1
"Unit";"Zergling";"Larva";1219;1
"Unit";"Zergling";"Larva";1219;1
"Unit";"Zergling";"Larva";1219;1
"Unit";"Zergling";"Larva";1219;1
"Unit";"Zergling";"Larva";1219;1
"Unit";"Zergling";"Larva";1219;1
"Unit";"Zergling";"Larva";1219;1
"Unit";"Zergling";"Larva";1219;1
"Unit";"Zergling";"Larva";1219;1
"Unit";"Zergling";"Larva";1219;1
"Unit";"Zergling";"Larva";1219;1
"Unit";"Zergling";"Larva";1219;1
"Unit";"Zergling";"Larva";1219;1
"Unit";"Zergling";"Larva";1219;1
"Unit";"Zergling";"Larva";1219;1
"Unit";"Zergling";"Larva";1219;1
"Unit";"Zergling";"Larva";1219;1
"Unit";"Zergling";"Larva";1219;1
"Unit";"Zergling";"Larva";1219;1
"Unit";"Zergling";"Larva";1219;1
"Unit";"Zergling";"Larva";1219;1
"Unit";"Zergling";"Larva";1219;1
"Unit";"Zergling";"Larva";1219;1
"Unit";"Zergling";"Larva";1219;1
"Unit";"Zergling";"Larva";1219;1
"Unit";"Zergling";"Larva";1219;1
"Unit";"Zergling";"Larva";1219;1
"Unit";"Zergling";"Larva";1219;1
"Building";"Extractor";NA;1219;0
"Building";"SpineCrawler";NA;1219;0
"Building";"SpineCrawler";NA;1219;0
"Building";"SpineCrawler";NA;1219;0
"Building";"SpineCrawler";NA;1219;0
"Unit";"Hydralisk";"Larva";1235;2
"Unit";"Hydralisk";"Larva";1235;2
"Unit";"Hydralisk";"Larva";1235;2
"Unit";"Hydralisk";"Larva";1235;2
"Unit";"Hydralisk";"Larva";1235;2
"Unit";"Hydralisk";"Larva";1235;2
"Unit";"Hydralisk";"Larva";1235;2
"Unit";"Zergling";"Larva";1281;1
"Unit";"Zergling";"Larva";1281;1
"Unit";"Zergling";"Larva";1283;1
"Unit";"Zergling";"Larva";1283;1
"Unit";"Zergling";"Larva";1283;1
"Unit";"Zergling";"Larva";1283;1
"Unit";"Zergling";"Larva";1283;1
"Unit";"Zergling";"Larva";1283;1
"Unit";"Zergling";"Larva";1283;1
"Unit";"Zergling";"Larva";1283;1
"Unit";"Zergling";"Larva";1283;1
"Unit";"Zergling";"Larva";1283;1
"Unit";"Zergling";"Larva";1283;1
"Unit";"Zergling";"Larva";1283;1
"Unit";"Zergling";"Larva";1285;1
"Unit";"Zergling";"Larva";1285;1
"Unit";"Zergling";"Larva";1285;1
"Unit";"Zergling";"Larva";1285;1
"Unit";"Zergling";"Larva";1287;1
"Unit";"Zergling";"Larva";1287;1
"Unit";"Zergling";"Larva";1287;1
"Unit";"Zergling";"Larva";1287;1
"Unit";"Zergling";"Larva";1291;1
"Unit";"Zergling";"Larva";1291;1
"Unit";"Zergling";"Larva";1295;1
"Unit";"Zergling";"Larva";1295;1
"Unit";"Zergling";"Larva";1295;1
"Unit";"Zergling";"Larva";1295;1
"Unit";"Zergling";"Larva";1295;1
"Unit";"Zergling";"Larva";1295;1
"Unit";"Zergling";"Larva";1295;1
"Unit";"Zergling";"Larva";1295;1
"Building";"CreepTumor";NA;1295;0
"Building";"CreepTumorQueen";NA;1295;0
"Building";"SporeCrawler";NA;1295;0
"Building";"CreepTumor";NA;1327;0
"Unit";"Baneling";"Zergling";1327;0
"Unit";"Baneling";"Zergling";1327;0
"Unit";"Baneling";"Zergling";1327;0
"Unit";"Baneling";"Zergling";1327;0
"Unit";"Baneling";"Zergling";1327;0
"Unit";"Baneling";"Zergling";1327;0
"Unit";"Baneling";"Zergling";1327;0
"Unit";"Baneling";"Zergling";1327;0
"Unit";"Baneling";"Zergling";1327;0
"Unit";"Baneling";"Zergling";1327;0
"Unit";"Baneling";"Zergling";1327;0
"Unit";"Baneling";"Zergling";1327;0
"Unit";"Baneling";"Zergling";1327;0
"Unit";"Baneling";"Zergling";1327;0
"Unit";"Baneling";"Zergling";1327;0
"Unit";"Baneling";"Zergling";1327;0
"Unit";"Baneling";"Zergling";1327;0
"Unit";"Baneling";"Zergling";1327;0
"Unit";"Baneling";"Zergling";1327;0
"Unit";"Baneling";"Zergling";1327;0
"Unit";"Baneling";"Zergling";1327;0
"Unit";"Baneling";"Zergling";1327;0
"Unit";"Baneling";"Zergling";1327;0
"Unit";"Baneling";"Zergling";1327;0
"Building";"SporeCrawler";NA;1327;0
