"type";"unit_name";"on_building";"total_supply";"supply"
"Unit";"Overlord";"Larva";12;0
"Building";"Extractor";NA;17;0
"Unit";"Overlord";"Larva";21;0
"Building";"SpawningPool";NA;19;0
"Building";"Hatchery";NA;17;0
"Unit";"Zergling";"Larva";23;1
"Unit";"Zergling";"Larva";23;1
"Unit";"Zergling";"Larva";24;1
"Unit";"Zergling";"Larva";24;1
"Unit";"Queen";"Hatchery";23;2
"Unit";"Queen";"Hatchery";23;2
"Unit";"Overlord";"Larva";37;0
"Building";"CreepTumorQueen";NA;38;0
"Unit";"Queen";"Hatchery";36;2
"Unit";"Overlord";"Larva";40;0
"Unit";"Zergling";"Larva";40;1
"Unit";"Zergling";"Larva";40;1
"Unit";"Zergling";"Larva";40;1
"Unit";"Zergling";"Larva";40;1
"Building";"CreepTumor";NA;52;0
"Building";"CreepTumorQueen";NA;52;0
"Unit";"Overlord";"Larva";47;0
"Building";"Hatchery";NA;35;0
"Unit";"Overlord";"Larva";52;0
"Unit";"Queen";"Hatchery";47;2
"Unit";"Zergling";"Larva";55;1
"Unit";"Zergling";"Larva";55;1
"Unit";"Zergling";"Larva";55;1
"Unit";"Zergling";"Larva";55;1
"Unit";"Zergling";"Larva";55;1
"Unit";"Zergling";"Larva";55;1
"Unit";"Zergling";"Larva";55;1
"Unit";"Zergling";"Larva";55;1
"Unit";"Zergling";"Larva";55;1
"Unit";"Zergling";"Larva";55;1
"Unit";"Overlord";"Larva";56;0
"Unit";"Zergling";"Larva";56;1
"Unit";"Zergling";"Larva";56;1
"Building";"CreepTumor";NA;58;0
"Building";"CreepTumor";NA;62;0
"Building";"RoachWarren";NA;52;0
"Building";"Extractor";NA;70;0
"Building";"Extractor";NA;73;0
"Building";"SporeCrawler";NA;73;0
"Building";"SporeCrawler";NA;73;0
"Unit";"Roach";"Larva";75;2
"Building";"CreepTumor";NA;80;0
"Unit";"Roach";"Larva";80;2
"Unit";"Roach";"Larva";80;2
"Unit";"Roach";"Larva";81;2
"Unit";"Roach";"Larva";82;2
"Building";"SporeCrawler";NA;87;0
"Building";"Extractor";NA;87;0
"Unit";"Overlord";"Larva";95;0
"Unit";"Overlord";"Larva";95;0
"Unit";"Overlord";"Larva";95;0
"Unit";"Roach";"Larva";96;2
"Unit";"Roach";"Larva";96;2
"Unit";"Roach";"Larva";99;2
"Unit";"Roach";"Larva";99;2
"Building";"CreepTumor";NA;103;0
"Unit";"Roach";"Larva";99;2
"Unit";"Roach";"Larva";99;2
"Unit";"Roach";"Larva";103;2
"Unit";"Roach";"Larva";103;2
"Unit";"Roach";"Larva";103;2
"Building";"NydusNetwork";NA;99;0
"Unit";"Queen";"Hatchery";99;2
"Unit";"Roach";"Larva";107;2
"Unit";"Roach";"Larva";107;2
"Unit";"Roach";"Larva";107;2
"Unit";"Overlord";"Larva";111;0
"Unit";"Overlord";"Larva";111;0
"Building";"NydusCanal";NA;117;0
"Unit";"Roach";"Larva";125;2
"Unit";"Roach";"Larva";125;2
"Unit";"Roach";"Larva";125;2
"Unit";"Overlord";"Larva";125;0
"Building";"CreepTumorQueen";NA;125;0
"Unit";"Roach";"Larva";125;2
"Unit";"Roach";"Larva";125;2
"Unit";"Roach";"Larva";125;2
"Unit";"Roach";"Larva";131;2
"Unit";"Roach";"Larva";131;2
"Unit";"Roach";"Larva";131;2
"Unit";"Roach";"Larva";131;2
"Unit";"Queen";"Hatchery";125;2
"Upgrade";"GlialReconstitution";"RoachWarren";117;0
"Unit";"Roach";"Larva";147;2
"Unit";"Roach";"Larva";147;2
"Unit";"Roach";"Larva";147;2
"Unit";"Roach";"Larva";147;2
"Unit";"Roach";"Larva";147;2
"Unit";"Roach";"Larva";147;2
"Unit";"Roach";"Larva";147;2
"Unit";"Roach";"Larva";147;2
"Unit";"Roach";"Larva";147;2
"Unit";"Queen";"Hatchery";131;2
"Building";"NydusCanal";NA;147;0
"Unit";"Roach";"Larva";147;2
"Unit";"Roach";"Larva";147;2
"Building";"EvolutionChamber";NA;167;0
"Building";"EvolutionChamber";NA;167;0
"Unit";"Roach";"Larva";170;2
"Unit";"Roach";"Larva";170;2
"Unit";"Overlord";"Larva";176;0
"Unit";"Overlord";"Larva";176;0
"Unit";"Overlord";"Larva";180;0
"Unit";"Overlord";"Larva";183;0
"Unit";"Roach";"Larva";183;2
"Unit";"Roach";"Larva";183;2
"Unit";"Roach";"Larva";183;2
"Unit";"Roach";"Larva";183;2
"Unit";"Roach";"Larva";183;2
"Unit";"Roach";"Larva";183;2
"Unit";"Roach";"Larva";183;2
"Unit";"Roach";"Larva";183;2
"Unit";"Roach";"Larva";183;2
"Unit";"Roach";"Larva";183;2
"Unit";"Overlord";"Larva";203;0
"Unit";"Overlord";"Larva";203;0
"Building";"HydraliskDen";NA;203;0
"Unit";"Roach";"Larva";207;2
"Unit";"Roach";"Larva";207;2
"Unit";"Roach";"Larva";207;2
"Unit";"Roach";"Larva";207;2
"Unit";"Roach";"Larva";207;2
"Unit";"Roach";"Larva";207;2
"Unit";"Roach";"Larva";207;2
"Unit";"Roach";"Larva";207;2
"Unit";"Roach";"Larva";207;2
"Unit";"Roach";"Larva";207;2
"Unit";"Roach";"Larva";207;2
"Unit";"Roach";"Larva";207;2
"Unit";"Roach";"Larva";207;2
"Unit";"Roach";"Larva";207;2
"Unit";"Roach";"Larva";207;2
"Unit";"Roach";"Larva";207;2
"Unit";"Roach";"Larva";207;2
"Unit";"Roach";"Larva";207;2
"Unit";"Roach";"Larva";207;2
"Unit";"Roach";"Larva";207;2
"Unit";"Overlord";"Larva";243;0
"Unit";"Overlord";"Larva";243;0
"Unit";"Overlord";"Larva";243;0
"Unit";"Overlord";"Larva";247;0
"Unit";"Overlord";"Larva";247;0
"Unit";"Overlord";"Larva";247;0
"Unit";"Overlord";"Larva";247;0
"Building";"CreepTumor";NA;247;0
"Building";"Extractor";NA;247;0
"Building";"Extractor";NA;247;0
"Building";"Hatchery";NA;207;0
"Building";"InfestationPit";NA;247;0
"Upgrade";"ZergMissileWeaponsLevel1";"EvolutionChamber";207;0
"Upgrade";"ZergGroundArmorsLevel1";"EvolutionChamber";207;0
"Unit";"Hydralisk";"Larva";253;2
"Building";"NydusCanal";NA;264;0
"Unit";"Hydralisk";"Larva";264;2
"Unit";"Hydralisk";"Larva";264;2
"Unit";"Hydralisk";"Larva";264;2
"Unit";"Hydralisk";"Larva";264;2
"Unit";"Hydralisk";"Larva";264;2
"Building";"CreepTumorQueen";NA;264;0
"Building";"CreepTumorQueen";NA;264;0
"Unit";"Hydralisk";"Larva";264;2
"Unit";"Hydralisk";"Larva";264;2
"Unit";"Hydralisk";"Larva";264;2
"Building";"SporeCrawler";NA;264;0
"Upgrade";"EvolveGroovedSpines";"HydraliskDen";264;0
"Building";"CreepTumor";NA;285;0
"Building";"CreepTumor";NA;285;0
"Building";"CreepTumorQueen";NA;285;0
"Building";"CreepTumorQueen";NA;285;0
"Unit";"Overlord";"Larva";285;0
"Unit";"Overlord";"Larva";285;0
"Unit";"Overlord";"Larva";285;0
"Building";"CreepTumorQueen";NA;286;0
"Building";"CreepTumor";NA;286;0
"Building";"CreepTumorQueen";NA;286;0
"Building";"CreepTumor";NA;286;0
"Building";"CreepTumor";NA;286;0
"Building";"CreepTumor";NA;286;0
"Building";"CreepTumor";NA;286;0
"Unit";"Overlord";"Larva";286;0
"Building";"Extractor";NA;288;0
"Building";"Extractor";NA;289;0
"Unit";"Hydralisk";"Larva";289;2
"Unit";"Hydralisk";"Larva";289;2
"Unit";"Hydralisk";"Larva";289;2
"Unit";"Hydralisk";"Larva";289;2
"Unit";"Hydralisk";"Larva";289;2
"Building";"CreepTumorQueen";NA;289;0
"Unit";"Overlord";"Larva";289;0
"Unit";"Overlord";"Larva";289;0
"Building";"Hatchery";NA;286;0
"Building";"CreepTumorQueen";NA;299;0
"Unit";"Overlord";"Larva";299;0
"Unit";"Overlord";"Larva";299;0
"Unit";"Hydralisk";"Larva";299;2
"Unit";"Hydralisk";"Larva";299;2
"Unit";"Hydralisk";"Larva";299;2
"Unit";"Hydralisk";"Larva";299;2
"Unit";"Hydralisk";"Larva";299;2
"Unit";"Hydralisk";"Larva";299;2
"Unit";"Hydralisk";"Larva";299;2
"Unit";"Hydralisk";"Larva";299;2
"Unit";"Hydralisk";"Larva";299;2
"Unit";"Hydralisk";"Larva";299;2
"Unit";"Hydralisk";"Larva";299;2
"Upgrade";"EvolveMuscularAugments";"HydraliskDen";289;0
"Building";"CreepTumor";NA;299;0
"Building";"CreepTumorQueen";NA;300;0
"Upgrade";"ZergMissileWeaponsLevel2";"EvolutionChamber";286;0
"Upgrade";"ZergGroundArmorsLevel2";"EvolutionChamber";286;0
"Unit";"Hydralisk";"Larva";322;2
"Unit";"Hydralisk";"Larva";322;2
"Building";"Extractor";NA;322;0
"Building";"Extractor";NA;322;0
"Building";"SpineCrawler";NA;322;0
"Building";"SpineCrawler";NA;322;0
"Building";"SpineCrawler";NA;322;0
"Building";"SpineCrawler";NA;322;0
"Unit";"Hydralisk";"Larva";329;2
"Unit";"Roach";"Larva";329;2
"Unit";"Roach";"Larva";329;2
"Unit";"Roach";"Larva";329;2
"Unit";"Roach";"Larva";329;2
"Unit";"Roach";"Larva";329;2
"Unit";"Roach";"Larva";329;2
"Unit";"Roach";"Larva";329;2
"Unit";"Roach";"Larva";329;2
"Unit";"Roach";"Larva";329;2
"Building";"NydusCanal";NA;329;0
"Building";"Spire";NA;322;0
"Unit";"Roach";"Larva";329;2
"Unit";"Roach";"Larva";329;2
"Unit";"Roach";"Larva";329;2
"Building";"CreepTumor";NA;355;0
"Building";"CreepTumor";NA;357;0
"Building";"CreepTumor";NA;357;0
"Unit";"Roach";"Larva";355;2
"Unit";"Roach";"Larva";355;2
"Unit";"Roach";"Larva";355;2
"Unit";"Roach";"Larva";355;2
"Unit";"Hydralisk";"Larva";357;2
"Unit";"Hydralisk";"Larva";357;2
"Unit";"Hydralisk";"Larva";357;2
"Unit";"Hydralisk";"Larva";357;2
"Unit";"Hydralisk";"Larva";357;2
"Unit";"Hydralisk";"Larva";357;2
"Unit";"Hydralisk";"Larva";357;2
"Unit";"Hydralisk";"Larva";357;2
"Unit";"Hydralisk";"Larva";357;2
"Unit";"Hydralisk";"Larva";357;2
"Unit";"Hydralisk";"Larva";357;2
"Unit";"Hydralisk";"Larva";357;2
"Building";"Extractor";NA;365;0
"Building";"Extractor";NA;365;0
"Unit";"Overlord";"Larva";392;0
"Unit";"Overlord";"Larva";393;0
"Unit";"Overlord";"Larva";394;0
"Building";"CreepTumor";NA;394;0
"Building";"SpineCrawler";NA;397;0
"Building";"SpineCrawler";NA;397;0
"Building";"Hatchery";NA;365;0
"Building";"SpineCrawler";NA;397;0
