"type";"unit_name";"on_building";"total_supply";"supply"
"Unit";"Overlord";"Larva";12;0
"Building";"Extractor";NA;21;0
"Building";"SpawningPool";NA;19;0
"Building";"Hatchery";NA;17;0
"Unit";"Zergling";"Larva";23;1
"Unit";"Zergling";"Larva";23;1
"Unit";"Zergling";"Larva";23;1
"Unit";"Zergling";"Larva";23;1
"Unit";"Overlord";"Larva";23;0
"Unit";"Queen";"Hatchery";23;2
"Unit";"Queen";"Hatchery";23;2
"Building";"Hatchery";NA;22;0
"Unit";"Overlord";"Larva";39;0
"Building";"CreepTumorQueen";NA;39;0
"Unit";"Queen";"Hatchery";37;2
"Building";"CreepTumorQueen";NA;39;0
"Unit";"Queen";"Hatchery";39;2
"Unit";"Overlord";"Larva";39;0
"Building";"CreepTumor";NA;44;0
"Building";"CreepTumorQueen";NA;46;0
"Building";"CreepTumorQueen";NA;46;0
"Building";"CreepTumorQueen";NA;48;0
"Unit";"Overlord";"Larva";48;0
"Unit";"Overlord";"Larva";48;0
"Building";"CreepTumorQueen";NA;48;0
"Building";"CreepTumor";NA;49;0
"Unit";"Queen";"Hatchery";48;2
"Building";"CreepTumor";NA;49;0
"Building";"CreepTumor";NA;49;0
"Unit";"Queen";"Hatchery";48;2
"Building";"CreepTumor";NA;52;0
"Unit";"Zergling";"Larva";50;1
"Unit";"Zergling";"Larva";50;1
"Unit";"Zergling";"Larva";51;1
"Unit";"Zergling";"Larva";51;1
"Unit";"Zergling";"Larva";52;1
"Unit";"Zergling";"Larva";52;1
"Unit";"Zergling";"Larva";52;1
"Unit";"Zergling";"Larva";52;1
"Unit";"Zergling";"Larva";52;1
"Unit";"Zergling";"Larva";52;1
"Building";"BanelingNest";NA;48;0
"Unit";"Queen";"Hatchery";49;2
"Building";"CreepTumorQueen";NA;62;0
"Unit";"Overlord";"Larva";56;0
"Building";"CreepTumor";NA;66;0
"Building";"CreepTumor";NA;69;0
"Building";"CreepTumorQueen";NA;73;0
"Unit";"Baneling";"Zergling";75;0
"Unit";"Baneling";"Zergling";75;0
"Unit";"Baneling";"Zergling";75;0
"Unit";"Baneling";"Zergling";75;0
"Unit";"Zergling";"Larva";73;1
"Unit";"Zergling";"Larva";73;1
"Unit";"Zergling";"Larva";73;1
"Unit";"Zergling";"Larva";73;1
"Unit";"Baneling";"Zergling";75;0
"Unit";"Zergling";"Larva";73;1
"Unit";"Zergling";"Larva";73;1
"Building";"CreepTumorQueen";NA;75;0
"Building";"CreepTumor";NA;82;0
"Building";"CreepTumor";NA;82;0
"Building";"CreepTumor";NA;82;0
"Building";"CreepTumor";NA;82;0
"Building";"CreepTumor";NA;82;0
"Building";"CreepTumorQueen";NA;85;0
"Unit";"Overlord";"Larva";85;0
"Unit";"Overlord";"Larva";85;0
"Building";"CreepTumorQueen";NA;85;0
"Building";"CreepTumorQueen";NA;85;0
"Building";"CreepTumor";NA;85;0
"Unit";"Overlord";"Larva";85;0
"Unit";"Overlord";"Larva";85;0
"Unit";"Overlord";"Larva";85;0
"Building";"CreepTumorQueen";NA;90;0
"Building";"CreepTumorQueen";NA;90;0
"Building";"CreepTumorQueen";NA;90;0
"Building";"CreepTumor";NA;90;0
"Building";"CreepTumor";NA;90;0
"Building";"CreepTumorQueen";NA;90;0
"Building";"Extractor";NA;85;0
"Building";"Extractor";NA;85;0
"Building";"EvolutionChamber";NA;85;0
"Building";"CreepTumor";NA;91;0
"Building";"EvolutionChamber";NA;90;0
"Building";"CreepTumor";NA;95;0
"Building";"CreepTumor";NA;102;0
"Building";"CreepTumor";NA;102;0
"Building";"Extractor";NA;95;0
"Building";"Extractor";NA;95;0
"Building";"CreepTumorQueen";NA;106;0
"Building";"Hatchery";NA;85;0
"Building";"CreepTumorQueen";NA;106;0
"Unit";"Queen";"Hatchery";95;2
"Building";"CreepTumorQueen";NA;106;0
"Building";"CreepTumor";NA;106;0
"Building";"CreepTumor";NA;106;0
"Building";"CreepTumor";NA;106;0
"Building";"CreepTumor";NA;106;0
"Building";"Hatchery";NA;85;0
"Building";"SporeCrawler";NA;106;0
"Unit";"Zergling";"Larva";106;1
"Unit";"Zergling";"Larva";106;1
"Unit";"Zergling";"Larva";106;1
"Unit";"Zergling";"Larva";106;1
"Unit";"Zergling";"Larva";106;1
"Unit";"Zergling";"Larva";106;1
"Unit";"Zergling";"Larva";106;1
"Unit";"Zergling";"Larva";106;1
"Unit";"Zergling";"Larva";106;1
"Unit";"Zergling";"Larva";106;1
"Building";"CreepTumorQueen";NA;115;0
"Building";"CreepTumor";NA;125;0
"Building";"HydraliskDen";NA;115;0
"Building";"CreepTumor";NA;129;0
"Building";"CreepTumor";NA;129;0
"Building";"CreepTumor";NA;129;0
"Building";"CreepTumor";NA;129;0
"Unit";"Zergling";"Larva";129;1
"Unit";"Zergling";"Larva";129;1
"Unit";"Zergling";"Larva";129;1
"Unit";"Zergling";"Larva";129;1
"Unit";"Zergling";"Larva";129;1
"Unit";"Zergling";"Larva";129;1
"Unit";"Zergling";"Larva";129;1
"Unit";"Zergling";"Larva";129;1
"Unit";"Zergling";"Larva";129;1
"Unit";"Zergling";"Larva";129;1
"Unit";"Zergling";"Larva";129;1
"Unit";"Zergling";"Larva";129;1
"Unit";"Zergling";"Larva";129;1
"Unit";"Zergling";"Larva";129;1
"Unit";"Zergling";"Larva";129;1
"Unit";"Zergling";"Larva";129;1
"Unit";"Zergling";"Larva";129;1
"Unit";"Zergling";"Larva";129;1
"Unit";"Zergling";"Larva";129;1
"Unit";"Zergling";"Larva";129;1
"Unit";"Zergling";"Larva";129;1
"Unit";"Zergling";"Larva";129;1
"Unit";"Zergling";"Larva";129;1
"Unit";"Zergling";"Larva";129;1
"Building";"CreepTumor";NA;129;0
"Building";"CreepTumor";NA;129;0
"Building";"CreepTumor";NA;129;0
"Unit";"Queen";"Hatchery";129;2
"Unit";"Queen";"Hatchery";129;2
"Building";"CreepTumor";NA;153;0
"Building";"CreepTumor";NA;153;0
"Building";"CreepTumor";NA;153;0
"Building";"CreepTumor";NA;153;0
"Building";"CreepTumor";NA;153;0
"Building";"CreepTumor";NA;153;0
"Building";"SporeCrawler";NA;153;0
"Building";"SporeCrawler";NA;153;0
"Unit";"Hydralisk";"Larva";153;2
"Unit";"Hydralisk";"Larva";153;2
"Building";"CreepTumor";NA;162;0
"Building";"CreepTumor";NA;162;0
"Building";"CreepTumor";NA;162;0
"Building";"SporeCrawler";NA;162;0
"Unit";"Overlord";"Larva";162;0
"Unit";"Overlord";"Larva";162;0
"Unit";"Queen";"Hatchery";155;2
"Building";"CreepTumor";NA;169;0
"Building";"CreepTumor";NA;169;0
"Building";"CreepTumor";NA;169;0
"Building";"InfestationPit";NA;162;0
"Unit";"Overlord";"Larva";169;0
"Unit";"Overlord";"Larva";169;0
"Unit";"Overlord";"Larva";169;0
"Building";"CreepTumorQueen";NA;171;0
"Building";"CreepTumorQueen";NA;171;0
"Building";"CreepTumorQueen";NA;171;0
"Building";"CreepTumor";NA;171;0
"Building";"CreepTumorQueen";NA;171;0
"Upgrade";"ZergGroundArmorsLevel1";"EvolutionChamber";129;0
"Upgrade";"ZergMeleeWeaponsLevel1";"EvolutionChamber";129;0
"Upgrade";"EvolveGroovedSpines";"HydraliskDen";162;0
"Unit";"Queen";"Hatchery";169;2
"Unit";"Overlord";"Larva";171;0
"Unit";"Overlord";"Larva";171;0
"Building";"Extractor";NA;171;0
"Building";"SporeCrawler";NA;171;0
"Unit";"Hydralisk";"Larva";171;2
"Unit";"Hydralisk";"Larva";171;2
"Building";"CreepTumor";NA;178;0
"Unit";"Hydralisk";"Larva";171;2
"Unit";"Hydralisk";"Larva";171;2
"Unit";"Hydralisk";"Larva";171;2
"Unit";"Hydralisk";"Larva";171;2
"Unit";"Hydralisk";"Larva";171;2
"Building";"CreepTumor";NA;178;0
"Building";"CreepTumorQueen";NA;180;0
"Building";"CreepTumorQueen";NA;182;0
"Building";"CreepTumorQueen";NA;194;0
"Unit";"Zergling";"Larva";180;1
"Unit";"Zergling";"Larva";180;1
"Unit";"Zergling";"Larva";180;1
"Unit";"Zergling";"Larva";180;1
"Unit";"Zergling";"Larva";180;1
"Unit";"Zergling";"Larva";180;1
"Unit";"Zergling";"Larva";180;1
"Unit";"Zergling";"Larva";180;1
"Unit";"Zergling";"Larva";180;1
"Unit";"Zergling";"Larva";180;1
"Unit";"Zergling";"Larva";180;1
"Unit";"Zergling";"Larva";180;1
"Unit";"Zergling";"Larva";180;1
"Unit";"Zergling";"Larva";180;1
"Unit";"Overlord";"Larva";194;0
"Unit";"Overlord";"Larva";194;0
"Unit";"Zergling";"Larva";194;1
"Unit";"Zergling";"Larva";194;1
"Unit";"Zergling";"Larva";194;1
"Unit";"Zergling";"Larva";194;1
"Unit";"Zergling";"Larva";194;1
"Unit";"Zergling";"Larva";194;1
"Unit";"Zergling";"Larva";194;1
"Unit";"Zergling";"Larva";194;1
"Unit";"Zergling";"Larva";194;1
"Unit";"Zergling";"Larva";194;1
"Unit";"Zergling";"Larva";194;1
"Unit";"Zergling";"Larva";194;1
"Unit";"Zergling";"Larva";194;1
"Unit";"Zergling";"Larva";194;1
"Unit";"Zergling";"Larva";208;1
"Unit";"Zergling";"Larva";208;1
"Unit";"Zergling";"Larva";208;1
"Unit";"Zergling";"Larva";208;1
"Unit";"Zergling";"Larva";208;1
"Unit";"Zergling";"Larva";208;1
"Unit";"Zergling";"Larva";208;1
"Unit";"Zergling";"Larva";208;1
"Unit";"Zergling";"Larva";208;1
"Unit";"Zergling";"Larva";208;1
"Unit";"Zergling";"Larva";208;1
"Unit";"Zergling";"Larva";208;1
"Unit";"Zergling";"Larva";208;1
"Unit";"Zergling";"Larva";208;1
"Unit";"Zergling";"Larva";208;1
"Unit";"Zergling";"Larva";208;1
"Unit";"Zergling";"Larva";208;1
"Unit";"Zergling";"Larva";208;1
"Unit";"Zergling";"Larva";208;1
"Unit";"Zergling";"Larva";208;1
"Building";"CreepTumorQueen";NA;222;0
"Unit";"Zergling";"Larva";222;1
"Unit";"Zergling";"Larva";222;1
"Unit";"Zergling";"Larva";222;1
"Unit";"Zergling";"Larva";222;1
"Unit";"Zergling";"Larva";222;1
"Unit";"Zergling";"Larva";222;1
"Unit";"Zergling";"Larva";222;1
"Unit";"Zergling";"Larva";222;1
"Unit";"Zergling";"Larva";222;1
"Unit";"Zergling";"Larva";222;1
"Unit";"Zergling";"Larva";222;1
"Unit";"Zergling";"Larva";222;1
"Unit";"Zergling";"Larva";222;1
"Unit";"Zergling";"Larva";222;1
"Unit";"Zergling";"Larva";222;1
"Unit";"Zergling";"Larva";222;1
"Unit";"Zergling";"Larva";222;1
"Unit";"Zergling";"Larva";222;1
"Unit";"Zergling";"Larva";222;1
"Unit";"Zergling";"Larva";222;1
"Unit";"Zergling";"Larva";222;1
"Unit";"Zergling";"Larva";222;1
"Unit";"Zergling";"Larva";222;1
"Unit";"Zergling";"Larva";222;1
"Unit";"Zergling";"Larva";222;1
"Unit";"Zergling";"Larva";222;1
"Unit";"Zergling";"Larva";222;1
"Unit";"Zergling";"Larva";222;1
"Unit";"Zergling";"Larva";222;1
"Unit";"Zergling";"Larva";222;1
"Unit";"Zergling";"Larva";222;1
"Unit";"Zergling";"Larva";222;1
"Building";"CreepTumorQueen";NA;242;0
"Building";"CreepTumor";NA;242;0
"Building";"CreepTumor";NA;242;0
"Building";"CreepTumorQueen";NA;242;0
"Upgrade";"EvolveMuscularAugments";"HydraliskDen";194;0
"Building";"Spire";NA;180;0
"Building";"CreepTumorQueen";NA;274;0
"Building";"SporeCrawler";NA;274;0
"Building";"SporeCrawler";NA;274;0
"Building";"Extractor";NA;274;0
"Building";"CreepTumorQueen";NA;282;0
"Building";"CreepTumorQueen";NA;282;0
"Building";"CreepTumorQueen";NA;282;0
"Unit";"Overlord";"Larva";274;0
"Unit";"Overlord";"Larva";274;0
"Unit";"Overlord";"Larva";274;0
"Unit";"Overlord";"Larva";274;0
"Unit";"Overlord";"Larva";274;0
"Building";"CreepTumor";NA;282;0
"Building";"CreepTumor";NA;282;0
"Building";"CreepTumor";NA;282;0
"Unit";"Baneling";"Zergling";282;0
"Unit";"Baneling";"Zergling";282;0
"Unit";"Baneling";"Zergling";282;0
"Unit";"Baneling";"Zergling";282;0
"Unit";"Baneling";"Zergling";282;0
"Unit";"Baneling";"Zergling";282;0
"Unit";"Baneling";"Zergling";282;0
"Unit";"Baneling";"Zergling";282;0
"Unit";"Baneling";"Zergling";282;0
"Unit";"Baneling";"Zergling";282;0
"Unit";"Baneling";"Zergling";282;0
"Building";"CreepTumor";NA;282;0
"Unit";"Corruptor";"Larva";274;2
"Unit";"Corruptor";"Larva";274;2
"Unit";"Overlord";"Larva";282;0
"Upgrade";"ZergGroundArmorsLevel2";"EvolutionChamber";208;0
"Upgrade";"ZergMeleeWeaponsLevel2";"EvolutionChamber";208;0
"Building";"CreepTumor";NA;286;0
"Building";"CreepTumor";NA;286;0
"Building";"CreepTumor";NA;286;0
"Building";"CreepTumor";NA;286;0
"Building";"CreepTumor";NA;286;0
"Building";"CreepTumor";NA;286;0
"Building";"Extractor";NA;286;0
"Building";"CreepTumor";NA;286;0
"Unit";"Corruptor";"Larva";282;2
"Unit";"Corruptor";"Larva";282;2
"Unit";"Corruptor";"Larva";282;2
"Unit";"Corruptor";"Larva";282;2
"Unit";"Corruptor";"Larva";282;2
"Building";"CreepTumor";NA;286;0
"Building";"CreepTumor";NA;286;0
"Building";"Hatchery";NA;274;0
"Building";"CreepTumor";NA;296;0
"Building";"CreepTumor";NA;296;0
"Building";"CreepTumor";NA;296;0
"Building";"CreepTumor";NA;296;0
"Building";"CreepTumorQueen";NA;296;0
"Building";"CreepTumor";NA;296;0
"Building";"CreepTumorQueen";NA;296;0
"Building";"CreepTumorQueen";NA;296;0
"Unit";"Corruptor";"Larva";296;2
"Unit";"Corruptor";"Larva";296;2
"Unit";"Corruptor";"Larva";296;2
"Building";"CreepTumorQueen";NA;296;0
"Building";"CreepTumorQueen";NA;302;0
"Building";"CreepTumorQueen";NA;302;0
"Building";"CreepTumorQueen";NA;302;0
"Building";"CreepTumor";NA;302;0
"Building";"CreepTumor";NA;302;0
"Building";"CreepTumor";NA;302;0
"Building";"CreepTumor";NA;302;0
"Building";"CreepTumor";NA;302;0
"Building";"CreepTumor";NA;302;0
"Unit";"Baneling";"Zergling";302;0
"Unit";"Baneling";"Zergling";302;0
"Unit";"Baneling";"Zergling";302;0
"Unit";"Baneling";"Zergling";302;0
"Unit";"Baneling";"Zergling";302;0
"Unit";"Baneling";"Zergling";302;0
"Unit";"Viper";"Larva";302;3
"Unit";"Corruptor";"Larva";302;2
"Building";"CreepTumor";NA;302;0
"Building";"CreepTumor";NA;302;0
"Building";"CreepTumor";NA;302;0
"Unit";"Baneling";"Zergling";302;0
"Unit";"Baneling";"Zergling";302;0
"Unit";"Baneling";"Zergling";302;0
"Unit";"Baneling";"Zergling";305;0
"Unit";"Baneling";"Zergling";305;0
"Unit";"Baneling";"Zergling";305;0
"Unit";"Baneling";"Zergling";305;0
"Unit";"Baneling";"Zergling";305;0
"Unit";"Baneling";"Zergling";305;0
"Unit";"Baneling";"Zergling";305;0
"Unit";"Baneling";"Zergling";305;0
"Unit";"Baneling";"Zergling";305;0
"Unit";"Baneling";"Zergling";305;0
"Unit";"Baneling";"Zergling";305;0
"Unit";"Baneling";"Zergling";305;0
"Unit";"Baneling";"Zergling";305;0
"Unit";"Zergling";"Larva";307;1
"Unit";"Zergling";"Larva";307;1
"Unit";"Zergling";"Larva";307;1
"Unit";"Zergling";"Larva";307;1
"Unit";"Zergling";"Larva";307;1
"Unit";"Zergling";"Larva";307;1
"Unit";"Zergling";"Larva";307;1
"Unit";"Zergling";"Larva";307;1
"Unit";"Zergling";"Larva";307;1
"Unit";"Zergling";"Larva";307;1
"Unit";"Zergling";"Larva";307;1
"Unit";"Zergling";"Larva";307;1
"Unit";"Zergling";"Larva";307;1
"Unit";"Zergling";"Larva";307;1
"Unit";"Zergling";"Larva";307;1
"Unit";"Zergling";"Larva";307;1
"Unit";"Zergling";"Larva";307;1
"Unit";"Zergling";"Larva";307;1
"Unit";"Zergling";"Larva";307;1
"Unit";"Zergling";"Larva";307;1
"Unit";"Zergling";"Larva";307;1
"Unit";"Zergling";"Larva";307;1
"Unit";"Zergling";"Larva";307;1
"Unit";"Zergling";"Larva";307;1
"Unit";"Zergling";"Larva";307;1
"Unit";"Zergling";"Larva";307;1
"Unit";"Zergling";"Larva";307;1
"Unit";"Zergling";"Larva";307;1
"Unit";"Zergling";"Larva";307;1
"Unit";"Zergling";"Larva";307;1
"Unit";"Viper";"Larva";307;3
"Unit";"Overlord";"Larva";307;0
"Unit";"Overlord";"Larva";307;0
"Unit";"Overlord";"Larva";307;0
"Unit";"Overlord";"Larva";307;0
"Unit";"Overlord";"Larva";307;0
"Unit";"Overlord";"Larva";307;0
"Unit";"Overlord";"Larva";307;0
"Upgrade";"ZergGroundArmorsLevel3";"EvolutionChamber";302;0
"Upgrade";"ZergMeleeWeaponsLevel3";"EvolutionChamber";302;0
"Unit";"Corruptor";"Larva";340;2
"Unit";"Corruptor";"Larva";340;2
"Unit";"Corruptor";"Larva";340;2
"Unit";"Corruptor";"Larva";340;2
"Building";"UltraliskCavern";NA;307;0
"Unit";"Zergling";"Larva";340;1
"Unit";"Zergling";"Larva";340;1
"Unit";"Zergling";"Larva";340;1
"Unit";"Zergling";"Larva";340;1
"Unit";"Zergling";"Larva";340;1
"Unit";"Zergling";"Larva";340;1
"Unit";"Zergling";"Larva";340;1
"Unit";"Zergling";"Larva";340;1
"Unit";"Zergling";"Larva";340;1
"Unit";"Zergling";"Larva";340;1
"Unit";"Zergling";"Larva";340;1
"Unit";"Zergling";"Larva";340;1
"Unit";"Zergling";"Larva";340;1
"Unit";"Zergling";"Larva";340;1
"Unit";"Zergling";"Larva";340;1
"Unit";"Zergling";"Larva";340;1
"Unit";"Zergling";"Larva";340;1
"Unit";"Zergling";"Larva";340;1
"Unit";"Zergling";"Larva";340;1
"Unit";"Zergling";"Larva";340;1
"Unit";"Zergling";"Larva";340;1
"Unit";"Zergling";"Larva";340;1
"Unit";"Zergling";"Larva";340;1
"Unit";"Zergling";"Larva";340;1
"Unit";"Zergling";"Larva";340;1
"Unit";"Zergling";"Larva";340;1
"Unit";"Zergling";"Larva";340;1
"Unit";"Zergling";"Larva";340;1
"Unit";"Zergling";"Larva";340;1
"Unit";"Zergling";"Larva";340;1
"Unit";"Zergling";"Larva";340;1
"Unit";"Zergling";"Larva";340;1
"Unit";"Zergling";"Larva";340;1
"Unit";"Zergling";"Larva";340;1
"Unit";"Zergling";"Larva";340;1
"Unit";"Zergling";"Larva";340;1
"Unit";"Zergling";"Larva";340;1
"Unit";"Zergling";"Larva";340;1
"Unit";"Zergling";"Larva";340;1
"Unit";"Zergling";"Larva";340;1
"Unit";"Zergling";"Larva";340;1
"Unit";"Zergling";"Larva";340;1
"Unit";"Zergling";"Larva";340;1
"Unit";"Zergling";"Larva";340;1
"Unit";"Zergling";"Larva";340;1
"Unit";"Zergling";"Larva";340;1
"Unit";"Zergling";"Larva";340;1
"Unit";"Zergling";"Larva";340;1
"Unit";"Zergling";"Larva";340;1
"Unit";"Zergling";"Larva";340;1
"Unit";"Zergling";"Larva";340;1
"Unit";"Zergling";"Larva";340;1
"Unit";"Zergling";"Larva";340;1
"Unit";"Zergling";"Larva";340;1
"Building";"CreepTumorQueen";NA;402;0
"Building";"CreepTumor";NA;402;0
"Building";"CreepTumorQueen";NA;402;0
"Building";"CreepTumorQueen";NA;402;0
"Building";"CreepTumorQueen";NA;402;0
"Building";"CreepTumorQueen";NA;402;0
"Unit";"Baneling";"Zergling";402;0
"Unit";"Baneling";"Zergling";402;0
"Unit";"Baneling";"Zergling";402;0
"Unit";"Baneling";"Zergling";402;0
"Unit";"Baneling";"Zergling";402;0
"Unit";"Baneling";"Zergling";402;0
"Unit";"Baneling";"Zergling";402;0
"Unit";"Baneling";"Zergling";402;0
"Unit";"Baneling";"Zergling";402;0
"Unit";"Baneling";"Zergling";402;0
"Unit";"Baneling";"Zergling";402;0
"Unit";"Baneling";"Zergling";402;0
"Unit";"Baneling";"Zergling";402;0
"Unit";"Baneling";"Zergling";402;0
"Unit";"Baneling";"Zergling";402;0
"Unit";"Zergling";"Larva";402;1
"Unit";"Zergling";"Larva";402;1
"Unit";"Zergling";"Larva";402;1
"Unit";"Zergling";"Larva";402;1
"Unit";"Zergling";"Larva";402;1
"Unit";"Zergling";"Larva";402;1
"Unit";"Zergling";"Larva";402;1
"Unit";"Zergling";"Larva";402;1
"Unit";"Zergling";"Larva";402;1
"Unit";"Zergling";"Larva";402;1
"Unit";"Zergling";"Larva";402;1
"Unit";"Zergling";"Larva";402;1
"Building";"CreepTumor";NA;402;0
"Building";"CreepTumor";NA;402;0
"Building";"Hatchery";NA;340;0
"Building";"CreepTumor";NA;414;0
"Building";"CreepTumor";NA;414;0
"Building";"CreepTumor";NA;414;0
"Building";"CreepTumor";NA;414;0
"Unit";"Ultralisk";"Larva";402;6
"Building";"CreepTumorQueen";NA;414;0
"Building";"CreepTumor";NA;414;0
"Unit";"Overlord";"Larva";404;0
"Unit";"Overlord";"Larva";408;0
"Unit";"Overlord";"Larva";408;0
"Unit";"Overlord";"Larva";410;0
"Unit";"Overlord";"Larva";410;0
"Unit";"Overlord";"Larva";414;0
"Building";"Hatchery";NA;340;0
"Unit";"Overlord";"Larva";414;0
"Unit";"Overlord";"Larva";414;0
"Building";"CreepTumor";NA;420;0
"Building";"Extractor";NA;414;0
"Building";"Extractor";NA;414;0
"Building";"SporeCrawler";NA;420;0
"Building";"CreepTumor";NA;420;0
"Building";"CreepTumor";NA;420;0
"Building";"SporeCrawler";NA;420;0
"Building";"SporeCrawler";NA;420;0
"Building";"SporeCrawler";NA;420;0
"Building";"SporeCrawler";NA;420;0
"Building";"CreepTumorQueen";NA;437;0
"Building";"CreepTumorQueen";NA;437;0
"Building";"SporeCrawler";NA;437;0
"Building";"SporeCrawler";NA;437;0
"Building";"SporeCrawler";NA;437;0
"Building";"SporeCrawler";NA;437;0
"Building";"CreepTumor";NA;437;0
"Building";"CreepTumor";NA;437;0
"Building";"CreepTumor";NA;437;0
"Building";"CreepTumor";NA;437;0
"Building";"CreepTumor";NA;437;0
"Upgrade";"ChitinousPlating";"UltraliskCavern";426;0
"Unit";"Zergling";"Larva";437;1
"Unit";"Zergling";"Larva";437;1
"Unit";"Zergling";"Larva";437;1
"Unit";"Zergling";"Larva";437;1
"Unit";"Zergling";"Larva";437;1
"Unit";"Zergling";"Larva";437;1
"Unit";"Zergling";"Larva";437;1
"Unit";"Zergling";"Larva";437;1
"Unit";"Zergling";"Larva";437;1
"Unit";"Zergling";"Larva";437;1
"Unit";"Zergling";"Larva";437;1
"Unit";"Zergling";"Larva";437;1
"Unit";"Zergling";"Larva";437;1
"Unit";"Zergling";"Larva";437;1
"Unit";"Zergling";"Larva";437;1
"Unit";"Zergling";"Larva";437;1
"Unit";"Zergling";"Larva";437;1
"Unit";"Zergling";"Larva";437;1
"Unit";"Zergling";"Larva";437;1
"Unit";"Zergling";"Larva";437;1
"Unit";"Zergling";"Larva";437;1
"Unit";"Zergling";"Larva";437;1
"Unit";"Zergling";"Larva";437;1
"Unit";"Zergling";"Larva";437;1
"Unit";"Zergling";"Larva";437;1
"Unit";"Zergling";"Larva";437;1
"Unit";"Zergling";"Larva";437;1
"Unit";"Zergling";"Larva";437;1
"Upgrade";"ZergMissileWeaponsLevel1";"EvolutionChamber";420;0
"Building";"SporeCrawler";NA;437;0
"Building";"SporeCrawler";NA;437;0
"Building";"SporeCrawler";NA;437;0
"Unit";"Viper";"Larva";437;3
"Unit";"Viper";"Larva";437;3
"Building";"CreepTumor";NA;471;0
"Building";"CreepTumor";NA;477;0
"Building";"CreepTumor";NA;477;0
"Building";"CreepTumor";NA;477;0
"Building";"CreepTumor";NA;477;0
"Building";"SporeCrawler";NA;477;0
"Unit";"Zergling";"Larva";484;1
"Unit";"Zergling";"Larva";484;1
"Unit";"Zergling";"Larva";484;1
"Unit";"Zergling";"Larva";484;1
"Unit";"Zergling";"Larva";484;1
"Unit";"Zergling";"Larva";484;1
"Unit";"Zergling";"Larva";484;1
"Unit";"Zergling";"Larva";484;1
"Unit";"Zergling";"Larva";484;1
"Unit";"Zergling";"Larva";484;1
"Unit";"Zergling";"Larva";484;1
"Unit";"Zergling";"Larva";484;1
"Unit";"Zergling";"Larva";484;1
"Unit";"Zergling";"Larva";484;1
"Unit";"Zergling";"Larva";484;1
"Unit";"Zergling";"Larva";484;1
"Unit";"Zergling";"Larva";484;1
"Unit";"Zergling";"Larva";484;1
"Unit";"Zergling";"Larva";484;1
"Unit";"Zergling";"Larva";484;1
"Unit";"Zergling";"Larva";484;1
"Unit";"Zergling";"Larva";484;1
"Unit";"Zergling";"Larva";484;1
"Unit";"Zergling";"Larva";484;1
"Building";"SporeCrawler";NA;484;0
"Building";"SporeCrawler";NA;484;0
"Unit";"Baneling";"Zergling";508;0
"Unit";"Baneling";"Zergling";508;0
"Unit";"Baneling";"Zergling";508;0
"Unit";"Baneling";"Zergling";508;0
"Unit";"Baneling";"Zergling";508;0
"Unit";"Baneling";"Zergling";508;0
"Unit";"Baneling";"Zergling";508;0
"Unit";"Baneling";"Zergling";508;0
"Unit";"Baneling";"Zergling";508;0
"Unit";"Baneling";"Zergling";508;0
"Unit";"Corruptor";"Larva";484;2
"Unit";"Corruptor";"Larva";484;2
"Unit";"Corruptor";"Larva";484;2
"Unit";"Corruptor";"Larva";484;2
"Unit";"Corruptor";"Larva";484;2
"Building";"CreepTumor";NA;508;0
"Building";"CreepTumor";NA;508;0
"Building";"CreepTumor";NA;508;0
"Building";"Extractor";NA;508;0
"Building";"CreepTumor";NA;529;0
"Building";"CreepTumor";NA;529;0
"Building";"CreepTumor";NA;529;0
"Building";"CreepTumor";NA;530;0
"Building";"Hatchery";NA;508;0
"Building";"Spire";NA;508;0
"Upgrade";"ZergMissileWeaponsLevel2";"EvolutionChamber";486;0
"Building";"Hatchery";NA;518;0
"Unit";"Zergling";"Larva";539;1
"Unit";"Zergling";"Larva";539;1
"Unit";"Zergling";"Larva";539;1
"Unit";"Zergling";"Larva";539;1
"Unit";"Zergling";"Larva";539;1
"Unit";"Zergling";"Larva";539;1
"Unit";"Zergling";"Larva";539;1
"Unit";"Zergling";"Larva";539;1
"Unit";"Zergling";"Larva";539;1
"Unit";"Zergling";"Larva";539;1
"Unit";"Zergling";"Larva";539;1
"Unit";"Zergling";"Larva";539;1
"Unit";"Zergling";"Larva";539;1
"Unit";"Zergling";"Larva";539;1
"Unit";"Zergling";"Larva";544;1
"Unit";"Zergling";"Larva";544;1
"Unit";"Zergling";"Larva";544;1
"Unit";"Zergling";"Larva";544;1
"Unit";"Zergling";"Larva";544;1
"Unit";"Zergling";"Larva";544;1
"Building";"CreepTumorQueen";NA;558;0
"Building";"CreepTumorQueen";NA;558;0
"Building";"CreepTumorQueen";NA;558;0
"Building";"CreepTumor";NA;558;0
"Building";"CreepTumor";NA;558;0
"Building";"SporeCrawler";NA;558;0
"Building";"SporeCrawler";NA;558;0
"Building";"CreepTumor";NA;564;0
"Unit";"Baneling";"Zergling";564;0
"Unit";"Baneling";"Zergling";564;0
"Unit";"Baneling";"Zergling";564;0
"Unit";"Baneling";"Zergling";564;0
"Unit";"Baneling";"Zergling";564;0
"Unit";"Baneling";"Zergling";564;0
"Unit";"Baneling";"Zergling";564;0
"Unit";"Baneling";"Zergling";564;0
"Unit";"Baneling";"Zergling";564;0
"Unit";"Baneling";"Zergling";564;0
"Building";"CreepTumor";NA;569;0
"Unit";"Ultralisk";"Larva";558;6
"Building";"CreepTumor";NA;569;0
"Building";"CreepTumor";NA;569;0
"Unit";"Zergling";"Larva";575;1
"Unit";"Zergling";"Larva";575;1
"Unit";"Zergling";"Larva";575;1
"Unit";"Zergling";"Larva";575;1
"Building";"Hatchery";NA;544;0
"Unit";"Zergling";"Larva";575;1
"Unit";"Zergling";"Larva";575;1
"Unit";"Zergling";"Larva";575;1
"Unit";"Zergling";"Larva";575;1
"Unit";"Zergling";"Larva";575;1
"Unit";"Zergling";"Larva";575;1
"Unit";"Zergling";"Larva";575;1
"Unit";"Zergling";"Larva";575;1
"Unit";"Zergling";"Larva";575;1
"Unit";"Zergling";"Larva";575;1
"Unit";"Zergling";"Larva";575;1
"Unit";"Zergling";"Larva";575;1
"Unit";"Zergling";"Larva";575;1
"Unit";"Zergling";"Larva";575;1
"Unit";"Zergling";"Larva";575;1
"Unit";"Zergling";"Larva";575;1
"Unit";"Baneling";"Zergling";595;0
"Unit";"Baneling";"Zergling";595;0
"Unit";"Baneling";"Zergling";595;0
"Unit";"Baneling";"Zergling";595;0
"Unit";"Baneling";"Zergling";595;0
"Unit";"Baneling";"Zergling";595;0
"Unit";"Baneling";"Zergling";595;0
"Unit";"Baneling";"Zergling";595;0
"Unit";"Baneling";"Zergling";595;0
"Unit";"Ultralisk";"Larva";575;6
"Unit";"Baneling";"Zergling";595;0
"Unit";"Baneling";"Zergling";595;0
"Unit";"Baneling";"Zergling";595;0
"Unit";"Baneling";"Zergling";595;0
"Unit";"Baneling";"Zergling";595;0
"Unit";"Zergling";"Larva";595;1
"Unit";"Zergling";"Larva";595;1
"Unit";"Zergling";"Larva";595;1
"Unit";"Zergling";"Larva";595;1
"Unit";"Zergling";"Larva";595;1
"Unit";"Zergling";"Larva";595;1
"Unit";"Zergling";"Larva";595;1
"Unit";"Zergling";"Larva";595;1
"Unit";"Zergling";"Larva";595;1
"Unit";"Zergling";"Larva";595;1
"Unit";"Zergling";"Larva";595;1
"Unit";"Zergling";"Larva";595;1
"Unit";"Zergling";"Larva";595;1
"Unit";"Zergling";"Larva";595;1
"Unit";"Zergling";"Larva";595;1
"Unit";"Zergling";"Larva";595;1
"Unit";"Zergling";"Larva";595;1
"Unit";"Zergling";"Larva";595;1
"Unit";"Zergling";"Larva";595;1
"Unit";"Zergling";"Larva";595;1
"Unit";"Zergling";"Larva";595;1
"Unit";"Zergling";"Larva";595;1
"Building";"CreepTumorQueen";NA;629;0
"Building";"CreepTumorQueen";NA;629;0
"Building";"CreepTumor";NA;629;0
"Building";"CreepTumorQueen";NA;629;0
"Building";"CreepTumorQueen";NA;629;0
"Building";"CreepTumorQueen";NA;629;0
"Building";"CreepTumorQueen";NA;629;0
"Building";"CreepTumorQueen";NA;629;0
"Unit";"Baneling";"Zergling";629;0
"Unit";"Baneling";"Zergling";629;0
"Unit";"Baneling";"Zergling";629;0
"Unit";"Baneling";"Zergling";629;0
"Unit";"Baneling";"Zergling";629;0
"Unit";"Zergling";"Larva";629;1
"Unit";"Zergling";"Larva";629;1
"Unit";"Zergling";"Larva";629;1
"Unit";"Zergling";"Larva";629;1
"Unit";"Zergling";"Larva";629;1
"Unit";"Zergling";"Larva";629;1
"Unit";"Zergling";"Larva";629;1
"Unit";"Zergling";"Larva";629;1
"Unit";"Zergling";"Larva";629;1
"Unit";"Zergling";"Larva";629;1
"Unit";"Zergling";"Larva";629;1
"Unit";"Zergling";"Larva";629;1
"Unit";"Zergling";"Larva";629;1
"Unit";"Zergling";"Larva";629;1
"Unit";"Zergling";"Larva";629;1
"Unit";"Zergling";"Larva";629;1
"Unit";"Zergling";"Larva";629;1
"Unit";"Zergling";"Larva";629;1
"Unit";"Zergling";"Larva";629;1
"Unit";"Zergling";"Larva";629;1
"Unit";"Zergling";"Larva";629;1
"Unit";"Zergling";"Larva";629;1
"Unit";"Hydralisk";"Larva";629;2
"Unit";"Hydralisk";"Larva";629;2
"Unit";"Hydralisk";"Larva";629;2
"Unit";"Hydralisk";"Larva";629;2
"Unit";"Hydralisk";"Larva";629;2
"Unit";"Hydralisk";"Larva";629;2
"Unit";"Hydralisk";"Larva";629;2
"Unit";"Hydralisk";"Larva";629;2
"Building";"CreepTumorQueen";NA;667;0
"Building";"CreepTumor";NA;667;0
"Building";"CreepTumor";NA;667;0
"Building";"CreepTumor";NA;667;0
"Building";"CreepTumor";NA;667;0
"Building";"CreepTumor";NA;667;0
"Unit";"Zergling";"Larva";667;1
"Unit";"Zergling";"Larva";667;1
"Unit";"Zergling";"Larva";667;1
"Unit";"Zergling";"Larva";667;1
"Unit";"Zergling";"Larva";667;1
"Unit";"Zergling";"Larva";667;1
"Unit";"Zergling";"Larva";667;1
"Unit";"Zergling";"Larva";667;1
"Unit";"Zergling";"Larva";667;1
"Unit";"Zergling";"Larva";667;1
"Unit";"Zergling";"Larva";667;1
"Unit";"Zergling";"Larva";667;1
"Unit";"Zergling";"Larva";667;1
"Unit";"Zergling";"Larva";667;1
"Unit";"Zergling";"Larva";667;1
"Unit";"Zergling";"Larva";667;1
"Building";"CreepTumor";NA;667;0
"Building";"CreepTumor";NA;667;0
"Building";"CreepTumor";NA;669;0
"Building";"CreepTumor";NA;675;0
"Building";"CreepTumor";NA;669;0
"Building";"CreepTumor";NA;679;0
"Building";"Extractor";NA;683;0
"Unit";"Zergling";"Larva";683;1
"Unit";"Zergling";"Larva";683;1
"Unit";"Zergling";"Larva";683;1
"Unit";"Zergling";"Larva";683;1
"Unit";"Zergling";"Larva";683;1
"Unit";"Zergling";"Larva";683;1
"Unit";"Zergling";"Larva";683;1
"Unit";"Zergling";"Larva";683;1
"Unit";"Zergling";"Larva";683;1
"Unit";"Zergling";"Larva";683;1
"Unit";"Zergling";"Larva";683;1
"Unit";"Zergling";"Larva";683;1
"Unit";"Zergling";"Larva";683;1
"Unit";"Zergling";"Larva";683;1
"Unit";"Zergling";"Larva";683;1
"Unit";"Zergling";"Larva";683;1
"Unit";"Zergling";"Larva";683;1
"Unit";"Zergling";"Larva";683;1
"Unit";"Zergling";"Larva";683;1
"Unit";"Zergling";"Larva";683;1
"Unit";"Zergling";"Larva";683;1
"Unit";"Zergling";"Larva";683;1
"Unit";"Zergling";"Larva";683;1
"Unit";"Zergling";"Larva";683;1
"Unit";"Zergling";"Larva";683;1
"Unit";"Zergling";"Larva";683;1
"Unit";"Zergling";"Larva";683;1
"Unit";"Zergling";"Larva";683;1
"Unit";"Zergling";"Larva";683;1
"Unit";"Zergling";"Larva";683;1
"Unit";"Zergling";"Larva";683;1
"Unit";"Zergling";"Larva";683;1
"Unit";"Zergling";"Larva";683;1
"Unit";"Zergling";"Larva";683;1
"Unit";"Zergling";"Larva";683;1
"Unit";"Zergling";"Larva";683;1
"Unit";"Zergling";"Larva";683;1
"Unit";"Zergling";"Larva";683;1
"Unit";"Zergling";"Larva";683;1
"Unit";"Zergling";"Larva";683;1
"Unit";"Zergling";"Larva";683;1
"Unit";"Zergling";"Larva";683;1
"Building";"CreepTumor";NA;725;0
"Building";"CreepTumor";NA;725;0
"Unit";"Hydralisk";"Larva";683;2
"Unit";"Hydralisk";"Larva";683;2
"Unit";"Hydralisk";"Larva";683;2
"Unit";"Hydralisk";"Larva";683;2
"Unit";"Hydralisk";"Larva";683;2
"Unit";"Hydralisk";"Larva";683;2
"Unit";"Hydralisk";"Larva";683;2
"Unit";"Zergling";"Larva";725;1
"Unit";"Zergling";"Larva";725;1
"Unit";"Zergling";"Larva";725;1
"Unit";"Zergling";"Larva";725;1
"Unit";"Zergling";"Larva";725;1
"Unit";"Zergling";"Larva";725;1
"Unit";"Zergling";"Larva";725;1
"Unit";"Zergling";"Larva";725;1
"Unit";"Zergling";"Larva";725;1
"Unit";"Zergling";"Larva";725;1
"Unit";"Zergling";"Larva";725;1
"Unit";"Zergling";"Larva";725;1
"Unit";"Zergling";"Larva";725;1
"Unit";"Zergling";"Larva";725;1
"Building";"Hatchery";NA;683;0
"Building";"CreepTumor";NA;753;0
"Building";"CreepTumor";NA;753;0
"Unit";"Corruptor";"Larva";739;2
"Building";"CreepTumorQueen";NA;753;0
"Unit";"Corruptor";"Larva";739;2
"Unit";"Corruptor";"Larva";739;2
"Unit";"Corruptor";"Larva";739;2
"Unit";"Corruptor";"Larva";739;2
"Unit";"Corruptor";"Larva";739;2
"Building";"CreepTumorQueen";NA;753;0
"Unit";"Corruptor";"Larva";739;2
"Building";"CreepTumor";NA;753;0
"Unit";"Baneling";"Zergling";767;0
"Unit";"Baneling";"Zergling";767;0
"Unit";"Baneling";"Zergling";767;0
"Unit";"Baneling";"Zergling";767;0
"Unit";"Baneling";"Zergling";767;0
"Unit";"Zergling";"Larva";767;1
"Unit";"Zergling";"Larva";767;1
"Unit";"Zergling";"Larva";767;1
"Unit";"Zergling";"Larva";767;1
"Unit";"Zergling";"Larva";767;1
"Unit";"Zergling";"Larva";767;1
"Unit";"Zergling";"Larva";767;1
"Unit";"Zergling";"Larva";767;1
"Unit";"Zergling";"Larva";767;1
"Unit";"Zergling";"Larva";767;1
"Unit";"Zergling";"Larva";767;1
"Unit";"Zergling";"Larva";767;1
"Unit";"Zergling";"Larva";767;1
"Unit";"Zergling";"Larva";767;1
"Unit";"Zergling";"Larva";767;1
"Unit";"Zergling";"Larva";767;1
"Unit";"Zergling";"Larva";767;1
"Unit";"Zergling";"Larva";767;1
"Unit";"Zergling";"Larva";767;1
"Unit";"Zergling";"Larva";767;1
"Unit";"Zergling";"Larva";767;1
"Unit";"Zergling";"Larva";767;1
"Unit";"Zergling";"Larva";767;1
"Unit";"Zergling";"Larva";767;1
"Unit";"Zergling";"Larva";767;1
"Unit";"Zergling";"Larva";767;1
"Unit";"Zergling";"Larva";767;1
"Unit";"Zergling";"Larva";767;1
"Unit";"Zergling";"Larva";767;1
"Unit";"Zergling";"Larva";767;1
"Unit";"Zergling";"Larva";767;1
"Unit";"Zergling";"Larva";767;1
"Unit";"Zergling";"Larva";767;1
"Unit";"Zergling";"Larva";767;1
"Unit";"Zergling";"Larva";767;1
"Unit";"Zergling";"Larva";767;1
"Unit";"Zergling";"Larva";767;1
"Unit";"Zergling";"Larva";767;1
"Unit";"Zergling";"Larva";767;1
"Unit";"Zergling";"Larva";767;1
"Unit";"Zergling";"Larva";767;1
"Unit";"Zergling";"Larva";767;1
"Building";"CreepTumor";NA;767;0
"Building";"Extractor";NA;812;0
"Unit";"Corruptor";"Larva";809;2
"Unit";"Corruptor";"Larva";809;2
"Unit";"Corruptor";"Larva";809;2
"Unit";"Corruptor";"Larva";809;2
"Unit";"Corruptor";"Larva";809;2
"Unit";"Corruptor";"Larva";809;2
"Unit";"Corruptor";"Larva";809;2
"Building";"Extractor";NA;812;0
"Unit";"Overlord";"Larva";812;0
"Unit";"Overlord";"Larva";812;0
"Unit";"Overlord";"Larva";812;0
"Building";"CreepTumor";NA;826;0
"Building";"CreepTumor";NA;826;0
"Unit";"Ultralisk";"Larva";812;6
"Unit";"Ultralisk";"Larva";812;6
"Unit";"Zergling";"Larva";826;1
"Unit";"Zergling";"Larva";826;1
"Unit";"Zergling";"Larva";826;1
"Unit";"Zergling";"Larva";826;1
"Unit";"Zergling";"Larva";826;1
"Unit";"Zergling";"Larva";826;1
"Unit";"Zergling";"Larva";826;1
"Unit";"Zergling";"Larva";826;1
"Unit";"Zergling";"Larva";826;1
"Unit";"Zergling";"Larva";826;1
"Unit";"Zergling";"Larva";826;1
"Unit";"Zergling";"Larva";826;1
"Unit";"Zergling";"Larva";826;1
"Unit";"Zergling";"Larva";826;1
"Unit";"Zergling";"Larva";826;1
"Unit";"Zergling";"Larva";826;1
"Unit";"Zergling";"Larva";826;1
"Unit";"Zergling";"Larva";826;1
"Unit";"Zergling";"Larva";826;1
"Unit";"Zergling";"Larva";826;1
"Unit";"Zergling";"Larva";826;1
"Unit";"Zergling";"Larva";826;1
"Unit";"Baneling";"Zergling";826;0
"Unit";"Baneling";"Zergling";826;0
"Unit";"Baneling";"Zergling";826;0
"Unit";"Baneling";"Zergling";826;0
"Unit";"Baneling";"Zergling";826;0
"Unit";"Baneling";"Zergling";826;0
"Unit";"Baneling";"Zergling";826;0
"Unit";"Baneling";"Zergling";826;0
"Unit";"Baneling";"Zergling";826;0
"Unit";"Baneling";"Zergling";826;0
"Unit";"Baneling";"Zergling";826;0
"Unit";"Baneling";"Zergling";826;0
"Unit";"Baneling";"Zergling";826;0
"Unit";"Baneling";"Zergling";826;0
"Unit";"Baneling";"Zergling";826;0
"Unit";"Baneling";"Zergling";826;0
"Unit";"Baneling";"Zergling";826;0
"Unit";"Baneling";"Zergling";826;0
"Unit";"Baneling";"Zergling";826;0
"Unit";"Baneling";"Zergling";826;0
"Unit";"Baneling";"Zergling";826;0
"Unit";"Baneling";"Zergling";826;0
"Unit";"Baneling";"Zergling";826;0
"Unit";"Baneling";"Zergling";826;0
"Unit";"Baneling";"Zergling";826;0
"Unit";"Baneling";"Zergling";826;0
"Unit";"Overlord";"Larva";838;0
"Unit";"Overlord";"Larva";838;0
"Building";"Extractor";NA;860;0
"Unit";"Zergling";"Larva";860;1
"Unit";"Zergling";"Larva";860;1
"Unit";"Zergling";"Larva";860;1
"Unit";"Zergling";"Larva";860;1
"Unit";"Zergling";"Larva";860;1
"Unit";"Zergling";"Larva";860;1
"Building";"CreepTumor";NA;862;0
"Building";"CreepTumor";NA;866;0
"Unit";"Zergling";"Larva";866;1
"Unit";"Zergling";"Larva";866;1
"Unit";"Zergling";"Larva";866;1
"Unit";"Zergling";"Larva";866;1
"Unit";"Zergling";"Larva";866;1
"Unit";"Zergling";"Larva";866;1
"Unit";"Zergling";"Larva";866;1
"Unit";"Zergling";"Larva";866;1
"Unit";"Zergling";"Larva";866;1
"Unit";"Zergling";"Larva";866;1
"Unit";"Zergling";"Larva";866;1
"Unit";"Zergling";"Larva";866;1
"Unit";"Zergling";"Larva";866;1
"Unit";"Zergling";"Larva";866;1
"Unit";"Zergling";"Larva";866;1
"Unit";"Zergling";"Larva";866;1
"Unit";"Zergling";"Larva";866;1
"Unit";"Zergling";"Larva";866;1
"Unit";"Zergling";"Larva";866;1
"Unit";"Zergling";"Larva";866;1
"Unit";"Zergling";"Larva";866;1
"Unit";"Zergling";"Larva";866;1
"Unit";"Zergling";"Larva";866;1
"Unit";"Zergling";"Larva";866;1
"Unit";"Zergling";"Larva";866;1
"Unit";"Zergling";"Larva";866;1
"Unit";"Zergling";"Larva";866;1
"Unit";"Zergling";"Larva";866;1
"Unit";"Zergling";"Larva";866;1
"Unit";"Zergling";"Larva";866;1
"Unit";"Zergling";"Larva";866;1
"Unit";"Zergling";"Larva";866;1
"Unit";"Zergling";"Larva";866;1
"Unit";"Zergling";"Larva";866;1
"Unit";"Zergling";"Larva";866;1
"Unit";"Zergling";"Larva";866;1
"Unit";"Zergling";"Larva";866;1
"Unit";"Zergling";"Larva";866;1
"Unit";"Baneling";"Zergling";866;0
"Unit";"Baneling";"Zergling";866;0
"Unit";"Baneling";"Zergling";866;0
"Unit";"Baneling";"Zergling";866;0
"Unit";"Baneling";"Zergling";866;0
"Unit";"Baneling";"Zergling";866;0
"Unit";"Baneling";"Zergling";866;0
"Building";"CreepTumorQueen";NA;904;0
"Building";"SporeCrawler";NA;866;0
"Building";"SporeCrawler";NA;866;0
"Building";"CreepTumorQueen";NA;904;0
"Building";"SporeCrawler";NA;866;0
"Building";"CreepTumorQueen";NA;904;0
"Building";"CreepTumorQueen";NA;904;0
"Building";"Extractor";NA;904;0
"Building";"CreepTumor";NA;904;0
"Upgrade";"Burrow";"Hatchery";866;0
"Building";"SporeCrawler";NA;904;0
"Unit";"Zergling";"Larva";904;1
"Unit";"Zergling";"Larva";904;1
"Unit";"Zergling";"Larva";904;1
"Unit";"Zergling";"Larva";904;1
"Unit";"Zergling";"Larva";904;1
"Unit";"Zergling";"Larva";904;1
"Unit";"Zergling";"Larva";904;1
"Unit";"Zergling";"Larva";904;1
"Unit";"Zergling";"Larva";904;1
"Unit";"Zergling";"Larva";904;1
"Unit";"Zergling";"Larva";904;1
"Unit";"Zergling";"Larva";904;1
"Unit";"Zergling";"Larva";904;1
"Unit";"Zergling";"Larva";904;1
"Unit";"Zergling";"Larva";904;1
"Unit";"Zergling";"Larva";904;1
"Unit";"Zergling";"Larva";904;1
"Unit";"Zergling";"Larva";904;1
"Unit";"Zergling";"Larva";904;1
"Unit";"Zergling";"Larva";904;1
"Unit";"Zergling";"Larva";904;1
"Unit";"Zergling";"Larva";904;1
"Unit";"Zergling";"Larva";904;1
"Unit";"Zergling";"Larva";904;1
"Unit";"Zergling";"Larva";904;1
"Unit";"Zergling";"Larva";904;1
"Unit";"Zergling";"Larva";904;1
"Unit";"Zergling";"Larva";904;1
"Unit";"Zergling";"Larva";904;1
"Unit";"Zergling";"Larva";904;1
"Unit";"Zergling";"Larva";904;1
"Unit";"Zergling";"Larva";904;1
"Building";"CreepTumor";NA;904;0
"Unit";"Baneling";"Zergling";918;0
"Unit";"Baneling";"Zergling";932;0
"Unit";"Baneling";"Zergling";932;0
"Unit";"Baneling";"Zergling";936;0
"Unit";"Baneling";"Zergling";936;0
"Unit";"Baneling";"Zergling";936;0
"Unit";"Baneling";"Zergling";936;0
"Unit";"Baneling";"Zergling";936;0
"Unit";"Baneling";"Zergling";936;0
"Unit";"Baneling";"Zergling";936;0
"Unit";"Baneling";"Zergling";936;0
"Unit";"Baneling";"Zergling";936;0
"Unit";"Baneling";"Zergling";936;0
"Unit";"Baneling";"Zergling";936;0
"Building";"CreepTumor";NA;936;0
"Building";"CreepTumor";NA;936;0
"Unit";"Zergling";"Larva";936;1
"Unit";"Zergling";"Larva";936;1
"Unit";"Zergling";"Larva";936;1
"Unit";"Zergling";"Larva";936;1
"Unit";"Zergling";"Larva";936;1
"Unit";"Zergling";"Larva";936;1
"Unit";"Zergling";"Larva";936;1
"Unit";"Zergling";"Larva";936;1
"Unit";"Zergling";"Larva";936;1
"Unit";"Zergling";"Larva";936;1
"Unit";"Zergling";"Larva";936;1
"Unit";"Zergling";"Larva";936;1
"Unit";"Zergling";"Larva";936;1
"Unit";"Zergling";"Larva";936;1
"Unit";"Zergling";"Larva";936;1
"Unit";"Zergling";"Larva";936;1
"Building";"Hatchery";NA;904;0
"Building";"CreepTumor";NA;952;0
"Building";"CreepTumor";NA;952;0
"Unit";"Zergling";"Larva";952;1
"Unit";"Zergling";"Larva";952;1
"Unit";"Zergling";"Larva";952;1
"Unit";"Zergling";"Larva";952;1
"Unit";"Zergling";"Larva";952;1
"Unit";"Zergling";"Larva";952;1
"Unit";"Zergling";"Larva";952;1
"Unit";"Zergling";"Larva";952;1
"Unit";"Zergling";"Larva";952;1
"Unit";"Zergling";"Larva";952;1
"Unit";"Zergling";"Larva";952;1
"Unit";"Zergling";"Larva";952;1
"Unit";"Zergling";"Larva";952;1
"Unit";"Zergling";"Larva";952;1
"Unit";"Zergling";"Larva";952;1
"Unit";"Zergling";"Larva";952;1
"Unit";"Zergling";"Larva";952;1
"Unit";"Zergling";"Larva";952;1
"Unit";"Zergling";"Larva";952;1
"Unit";"Zergling";"Larva";952;1
"Unit";"Zergling";"Larva";952;1
"Unit";"Zergling";"Larva";952;1
"Unit";"Zergling";"Larva";952;1
"Unit";"Zergling";"Larva";952;1
"Unit";"Zergling";"Larva";952;1
"Unit";"Zergling";"Larva";952;1
"Unit";"Zergling";"Larva";952;1
"Unit";"Zergling";"Larva";952;1
"Unit";"Zergling";"Larva";952;1
"Unit";"Zergling";"Larva";952;1
"Unit";"Zergling";"Larva";952;1
"Unit";"Zergling";"Larva";952;1
"Unit";"Zergling";"Larva";952;1
"Unit";"Zergling";"Larva";952;1
"Unit";"Zergling";"Larva";952;1
"Unit";"Zergling";"Larva";952;1
"Building";"CreepTumor";NA;952;0
"Building";"CreepTumor";NA;988;0
"Building";"CreepTumor";NA;988;0
"Building";"Extractor";NA;952;0
"Building";"CreepTumor";NA;988;0
"Building";"CreepTumor";NA;992;0
"Building";"CreepTumor";NA;993;0
"Unit";"Baneling";"Zergling";993;0
"Unit";"Baneling";"Zergling";993;0
"Unit";"Baneling";"Zergling";993;0
"Unit";"Baneling";"Zergling";993;0
"Unit";"Corruptor";"Larva";993;2
"Building";"Extractor";NA;999;0
"Building";"Extractor";NA;999;0
"Building";"CreepTumorQueen";NA;1008;0
"Building";"CreepTumorQueen";NA;1008;0
"Building";"CreepTumor";NA;1008;0
"Building";"CreepTumor";NA;1011;0
"Building";"CreepTumor";NA;1011;0
"Building";"CreepTumor";NA;1011;0
"Building";"CreepTumor";NA;1011;0
"Building";"CreepTumor";NA;1011;0
