"type";"unit_name";"on_building";"total_supply";"supply"
"Unit";"Overlord";"Larva";12;0
"Building";"Extractor";NA;19;0
"Building";"SpawningPool";NA;19;0
"Building";"Hatchery";NA;17;0
"Unit";"Zergling";"Larva";23;1
"Unit";"Zergling";"Larva";23;1
"Unit";"Zergling";"Larva";23;1
"Unit";"Zergling";"Larva";23;1
"Unit";"Queen";"Hatchery";23;2
"Unit";"Overlord";"Larva";23;0
"Unit";"Queen";"Hatchery";23;2
"Building";"CreepTumorQueen";NA;34;0
"Building";"Hatchery";NA;22;0
"Unit";"Overlord";"Larva";37;0
"Building";"CreepTumorQueen";NA;38;0
"Unit";"Queen";"Hatchery";37;2
"Building";"CreepTumor";NA;40;0
"Unit";"Queen";"Hatchery";37;2
"Unit";"Overlord";"Larva";42;0
"Building";"CreepTumorQueen";NA;49;0
"Building";"CreepTumor";NA;49;0
"Unit";"Queen";"Hatchery";40;2
"Unit";"Overlord";"Larva";49;0
"Building";"CreepTumorQueen";NA;54;0
"Unit";"Zergling";"Larva";56;1
"Unit";"Zergling";"Larva";56;1
"Unit";"Zergling";"Larva";56;1
"Unit";"Zergling";"Larva";56;1
"Unit";"Zergling";"Larva";56;1
"Unit";"Zergling";"Larva";56;1
"Unit";"Zergling";"Larva";56;1
"Unit";"Zergling";"Larva";56;1
"Unit";"Zergling";"Larva";56;1
"Unit";"Zergling";"Larva";56;1
"Unit";"Zergling";"Larva";56;1
"Unit";"Zergling";"Larva";56;1
"Unit";"Queen";"Hatchery";54;2
"Unit";"Overlord";"Larva";61;0
"Building";"Extractor";NA;61;0
"Building";"Extractor";NA;61;0
"Building";"CreepTumor";NA;78;0
"Building";"CreepTumor";NA;78;0
"Building";"SporeCrawler";NA;81;0
"Unit";"Overlord";"Larva";96;0
"Building";"Extractor";NA;98;0
"Building";"Extractor";NA;98;0
"Unit";"Queen";"Hatchery";96;2
"Building";"Extractor";NA;104;0
"Building";"CreepTumor";NA;116;0
"Building";"CreepTumor";NA;117;0
"Building";"EvolutionChamber";NA;124;0
"Building";"EvolutionChamber";NA;124;0
"Building";"CreepTumor";NA;129;0
"Building";"BanelingNest";NA;112;0
"Building";"Spire";NA;98;0
"Building";"CreepTumor";NA;130;0
"Building";"CreepTumorQueen";NA;131;0
"Building";"CreepTumorQueen";NA;132;0
"Building";"CreepTumorQueen";NA;132;0
"Unit";"Overlord";"Larva";132;0
"Unit";"Overlord";"Larva";132;0
"Unit";"Overlord";"Larva";132;0
"Building";"CreepTumorQueen";NA;133;0
"Building";"CreepTumor";NA;132;0
"Building";"CreepTumor";NA;135;0
"Unit";"Overlord";"Larva";135;0
"Unit";"Overlord";"Larva";135;0
"Unit";"Overlord";"Larva";135;0
"Unit";"Zergling";"Larva";135;1
"Unit";"Zergling";"Larva";135;1
"Unit";"Zergling";"Larva";135;1
"Unit";"Zergling";"Larva";135;1
"Unit";"Zergling";"Larva";135;1
"Unit";"Zergling";"Larva";135;1
"Unit";"Zergling";"Larva";135;1
"Unit";"Zergling";"Larva";135;1
"Unit";"Zergling";"Larva";135;1
"Unit";"Zergling";"Larva";135;1
"Unit";"Zergling";"Larva";135;1
"Unit";"Zergling";"Larva";135;1
"Unit";"Zergling";"Larva";135;1
"Unit";"Zergling";"Larva";135;1
"Unit";"Zergling";"Larva";135;1
"Unit";"Zergling";"Larva";135;1
"Unit";"Zergling";"Larva";135;1
"Unit";"Zergling";"Larva";135;1
"Unit";"Zergling";"Larva";135;1
"Unit";"Zergling";"Larva";135;1
"Unit";"Zergling";"Larva";135;1
"Unit";"Zergling";"Larva";135;1
"Unit";"Zergling";"Larva";135;1
"Unit";"Zergling";"Larva";135;1
"Unit";"Zergling";"Larva";135;1
"Unit";"Zergling";"Larva";135;1
"Unit";"Zergling";"Larva";135;1
"Unit";"Zergling";"Larva";135;1
"Unit";"Zergling";"Larva";135;1
"Unit";"Zergling";"Larva";135;1
"Unit";"Baneling";"Zergling";153;0
"Unit";"Baneling";"Zergling";153;0
"Unit";"Zergling";"Larva";135;1
"Unit";"Zergling";"Larva";135;1
"Unit";"Zergling";"Larva";135;1
"Unit";"Zergling";"Larva";135;1
"Unit";"Baneling";"Zergling";155;0
"Unit";"Baneling";"Zergling";155;0
"Unit";"Baneling";"Zergling";155;0
"Unit";"Baneling";"Zergling";157;0
"Unit";"Baneling";"Zergling";157;0
"Unit";"Baneling";"Zergling";157;0
"Unit";"Baneling";"Zergling";157;0
"Unit";"Baneling";"Zergling";157;0
"Unit";"Zergling";"Larva";157;1
"Unit";"Zergling";"Larva";157;1
"Unit";"Zergling";"Larva";157;1
"Unit";"Zergling";"Larva";157;1
"Building";"CreepTumor";NA;163;0
"Building";"CreepTumor";NA;163;0
"Building";"CreepTumor";NA;163;0
"Building";"CreepTumor";NA;163;0
"Building";"Hatchery";NA;131;0
"Unit";"Zergling";"Larva";163;1
"Unit";"Zergling";"Larva";163;1
"Unit";"Zergling";"Larva";163;1
"Unit";"Zergling";"Larva";163;1
"Unit";"Zergling";"Larva";163;1
"Unit";"Zergling";"Larva";163;1
"Unit";"Zergling";"Larva";163;1
"Unit";"Zergling";"Larva";163;1
"Unit";"Zergling";"Larva";163;1
"Unit";"Zergling";"Larva";163;1
"Unit";"Zergling";"Larva";163;1
"Unit";"Zergling";"Larva";163;1
"Unit";"Zergling";"Larva";163;1
"Unit";"Zergling";"Larva";163;1
"Building";"CreepTumor";NA;169;0
"Unit";"Zergling";"Larva";169;1
"Unit";"Zergling";"Larva";169;1
"Unit";"Zergling";"Larva";169;1
"Unit";"Zergling";"Larva";169;1
"Unit";"Zergling";"Larva";169;1
"Unit";"Zergling";"Larva";169;1
"Unit";"Zergling";"Larva";169;1
"Unit";"Zergling";"Larva";169;1
"Unit";"Zergling";"Larva";169;1
"Unit";"Zergling";"Larva";169;1
"Building";"CreepTumorQueen";NA;197;0
"Building";"CreepTumorQueen";NA;197;0
"Building";"CreepTumor";NA;197;0
"Building";"CreepTumor";NA;197;0
"Building";"CreepTumor";NA;197;0
"Building";"CreepTumor";NA;197;0
"Building";"CreepTumor";NA;197;0
"Unit";"Mutalisk";"Larva";187;2
"Unit";"Mutalisk";"Larva";187;2
"Unit";"Mutalisk";"Larva";187;2
"Unit";"Mutalisk";"Larva";187;2
"Unit";"Mutalisk";"Larva";187;2
"Unit";"Mutalisk";"Larva";197;2
"Building";"Hatchery";NA;135;0
"Unit";"Mutalisk";"Larva";197;2
"Unit";"Mutalisk";"Larva";197;2
"Unit";"Mutalisk";"Larva";197;2
"Building";"InfestationPit";NA;173;0
"Unit";"Mutalisk";"Larva";197;2
"Upgrade";"ZergMeleeWeaponsLevel1";"EvolutionChamber";135;0
"Upgrade";"ZergGroundArmorsLevel1";"EvolutionChamber";135;0
"Unit";"Zergling";"Larva";197;1
"Unit";"Zergling";"Larva";197;1
"Unit";"Zergling";"Larva";197;1
"Unit";"Zergling";"Larva";197;1
"Unit";"Zergling";"Larva";197;1
"Unit";"Zergling";"Larva";197;1
"Unit";"Zergling";"Larva";197;1
"Unit";"Zergling";"Larva";197;1
"Unit";"Overlord";"Larva";207;0
"Unit";"Overlord";"Larva";207;0
"Unit";"Overlord";"Larva";207;0
"Unit";"Overlord";"Larva";207;0
"Unit";"Mutalisk";"Larva";197;2
"Unit";"Mutalisk";"Larva";197;2
"Unit";"Baneling";"Zergling";217;0
"Unit";"Baneling";"Zergling";217;0
"Unit";"Baneling";"Zergling";217;0
"Unit";"Baneling";"Zergling";217;0
"Unit";"Zergling";"Larva";217;1
"Unit";"Zergling";"Larva";217;1
"Unit";"Overlord";"Larva";217;0
"Unit";"Zergling";"Larva";217;1
"Unit";"Zergling";"Larva";217;1
"Unit";"Zergling";"Larva";217;1
"Unit";"Zergling";"Larva";217;1
"Unit";"Zergling";"Larva";217;1
"Unit";"Zergling";"Larva";217;1
"Unit";"Zergling";"Larva";217;1
"Unit";"Zergling";"Larva";217;1
"Unit";"Overlord";"Larva";217;0
"Building";"CreepTumorQueen";NA;230;0
"Building";"CreepTumorQueen";NA;240;0
"Building";"CreepTumor";NA;240;0
"Building";"CreepTumorQueen";NA;240;0
"Building";"CreepTumorQueen";NA;240;0
"Unit";"Zergling";"Larva";240;1
"Unit";"Zergling";"Larva";240;1
"Unit";"Zergling";"Larva";240;1
"Unit";"Zergling";"Larva";240;1
"Unit";"Zergling";"Larva";240;1
"Unit";"Zergling";"Larva";240;1
"Unit";"Zergling";"Larva";240;1
"Unit";"Zergling";"Larva";240;1
"Unit";"Zergling";"Larva";240;1
"Unit";"Zergling";"Larva";240;1
"Building";"CreepTumor";NA;240;0
"Unit";"Zergling";"Larva";240;1
"Unit";"Zergling";"Larva";240;1
"Unit";"Zergling";"Larva";240;1
"Unit";"Zergling";"Larva";240;1
"Building";"CreepTumor";NA;240;0
"Building";"CreepTumorQueen";NA;240;0
"Unit";"Mutalisk";"Larva";240;2
"Unit";"Mutalisk";"Larva";240;2
"Building";"CreepTumorQueen";NA;240;0
"Unit";"Queen";"Hatchery";225;2
"Unit";"Mutalisk";"Larva";240;2
"Unit";"Baneling";"Zergling";240;0
"Unit";"Baneling";"Zergling";240;0
"Unit";"Baneling";"Zergling";240;0
"Unit";"Baneling";"Zergling";240;0
"Unit";"Baneling";"Zergling";240;0
"Unit";"Baneling";"Zergling";240;0
"Unit";"Baneling";"Zergling";240;0
"Unit";"Baneling";"Zergling";240;0
"Building";"Extractor";NA;240;0
"Unit";"Zergling";"Larva";240;1
"Unit";"Zergling";"Larva";240;1
"Unit";"Zergling";"Larva";240;1
"Unit";"Zergling";"Larva";240;1
"Unit";"Zergling";"Larva";240;1
"Unit";"Zergling";"Larva";240;1
"Unit";"Zergling";"Larva";242;1
"Unit";"Zergling";"Larva";242;1
"Unit";"Zergling";"Larva";242;1
"Unit";"Zergling";"Larva";242;1
"Unit";"Zergling";"Larva";242;1
"Unit";"Zergling";"Larva";242;1
"Unit";"Zergling";"Larva";242;1
"Unit";"Zergling";"Larva";242;1
"Unit";"Zergling";"Larva";242;1
"Unit";"Zergling";"Larva";242;1
"Unit";"Zergling";"Larva";242;1
"Unit";"Zergling";"Larva";242;1
"Unit";"Zergling";"Larva";242;1
"Unit";"Zergling";"Larva";242;1
"Unit";"Zergling";"Larva";242;1
"Unit";"Zergling";"Larva";242;1
"Unit";"Zergling";"Larva";242;1
"Unit";"Zergling";"Larva";242;1
"Unit";"Zergling";"Larva";258;1
"Unit";"Zergling";"Larva";258;1
"Unit";"Zergling";"Larva";258;1
"Unit";"Zergling";"Larva";258;1
"Building";"CreepTumor";NA;290;0
"Building";"CreepTumor";NA;290;0
"Unit";"Mutalisk";"Larva";262;2
"Unit";"Mutalisk";"Larva";262;2
"Unit";"Mutalisk";"Larva";262;2
"Unit";"Zergling";"Larva";290;1
"Unit";"Zergling";"Larva";290;1
"Unit";"Baneling";"Zergling";290;0
"Unit";"Zergling";"Larva";290;1
"Unit";"Zergling";"Larva";290;1
"Unit";"Zergling";"Larva";290;1
"Unit";"Zergling";"Larva";290;1
"Unit";"Zergling";"Larva";290;1
"Unit";"Zergling";"Larva";290;1
"Unit";"Zergling";"Larva";290;1
"Unit";"Zergling";"Larva";290;1
"Unit";"Zergling";"Larva";290;1
"Unit";"Zergling";"Larva";290;1
"Unit";"Zergling";"Larva";290;1
"Unit";"Zergling";"Larva";290;1
"Unit";"Zergling";"Larva";290;1
"Unit";"Zergling";"Larva";290;1
"Unit";"Zergling";"Larva";290;1
"Unit";"Zergling";"Larva";290;1
"Unit";"Zergling";"Larva";290;1
"Unit";"Zergling";"Larva";290;1
"Unit";"Baneling";"Zergling";290;0
"Unit";"Baneling";"Zergling";290;0
"Unit";"Baneling";"Zergling";290;0
"Unit";"Baneling";"Zergling";290;0
"Unit";"Baneling";"Zergling";290;0
"Unit";"Baneling";"Zergling";290;0
"Unit";"Mutalisk";"Larva";290;2
"Unit";"Mutalisk";"Larva";290;2
"Unit";"Zergling";"Larva";320;1
"Unit";"Zergling";"Larva";320;1
"Unit";"Zergling";"Larva";320;1
"Unit";"Zergling";"Larva";320;1
"Unit";"Zergling";"Larva";320;1
"Unit";"Zergling";"Larva";320;1
"Unit";"Zergling";"Larva";320;1
"Unit";"Zergling";"Larva";320;1
"Unit";"Zergling";"Larva";320;1
"Unit";"Zergling";"Larva";320;1
"Unit";"Zergling";"Larva";320;1
"Unit";"Zergling";"Larva";320;1
"Unit";"Zergling";"Larva";320;1
"Unit";"Zergling";"Larva";320;1
"Unit";"Zergling";"Larva";320;1
"Unit";"Zergling";"Larva";320;1
"Unit";"Zergling";"Larva";320;1
"Unit";"Zergling";"Larva";320;1
"Unit";"Zergling";"Larva";320;1
"Unit";"Zergling";"Larva";320;1
"Unit";"Zergling";"Larva";320;1
"Unit";"Zergling";"Larva";320;1
"Unit";"Zergling";"Larva";320;1
"Unit";"Zergling";"Larva";320;1
"Building";"CreepTumor";NA;344;0
"Building";"CreepTumor";NA;344;0
"Building";"CreepTumor";NA;344;0
"Building";"CreepTumor";NA;347;0
"Building";"CreepTumor";NA;347;0
"Building";"CreepTumor";NA;347;0
"Unit";"Zergling";"Larva";344;1
"Unit";"Zergling";"Larva";344;1
"Unit";"Zergling";"Larva";344;1
"Unit";"Zergling";"Larva";344;1
"Unit";"Zergling";"Larva";344;1
"Unit";"Zergling";"Larva";344;1
"Unit";"Zergling";"Larva";344;1
"Unit";"Zergling";"Larva";344;1
"Building";"CreepTumor";NA;348;0
"Unit";"Zergling";"Larva";348;1
"Unit";"Zergling";"Larva";348;1
"Unit";"Zergling";"Larva";348;1
"Unit";"Zergling";"Larva";348;1
"Unit";"Zergling";"Larva";348;1
"Unit";"Zergling";"Larva";348;1
"Unit";"Zergling";"Larva";348;1
"Unit";"Zergling";"Larva";348;1
"Unit";"Zergling";"Larva";348;1
"Unit";"Zergling";"Larva";348;1
"Unit";"Baneling";"Zergling";348;0
"Unit";"Baneling";"Zergling";348;0
"Unit";"Baneling";"Zergling";348;0
"Unit";"Baneling";"Zergling";348;0
"Unit";"Baneling";"Zergling";348;0
"Unit";"Baneling";"Zergling";348;0
"Unit";"Baneling";"Zergling";348;0
"Unit";"Baneling";"Zergling";348;0
"Unit";"Baneling";"Zergling";348;0
"Unit";"Baneling";"Zergling";348;0
"Unit";"Baneling";"Zergling";348;0
"Unit";"Baneling";"Zergling";348;0
"Unit";"Baneling";"Zergling";348;0
"Building";"UltraliskCavern";NA;320;0
"Unit";"Zergling";"Larva";356;1
"Unit";"Zergling";"Larva";356;1
"Unit";"Zergling";"Larva";356;1
"Unit";"Zergling";"Larva";356;1
"Unit";"Zergling";"Larva";356;1
"Unit";"Zergling";"Larva";356;1
"Unit";"Baneling";"Zergling";356;0
"Unit";"Zergling";"Larva";356;1
"Unit";"Zergling";"Larva";356;1
"Unit";"Zergling";"Larva";356;1
"Unit";"Zergling";"Larva";356;1
"Unit";"Zergling";"Larva";356;1
"Unit";"Zergling";"Larva";356;1
"Unit";"Zergling";"Larva";356;1
"Unit";"Zergling";"Larva";356;1
"Unit";"Zergling";"Larva";356;1
"Unit";"Zergling";"Larva";356;1
"Unit";"Zergling";"Larva";356;1
"Unit";"Zergling";"Larva";356;1
"Unit";"Zergling";"Larva";356;1
"Unit";"Zergling";"Larva";356;1
"Unit";"Zergling";"Larva";356;1
"Unit";"Zergling";"Larva";356;1
"Unit";"Zergling";"Larva";356;1
"Unit";"Zergling";"Larva";356;1
"Unit";"Zergling";"Larva";356;1
"Unit";"Zergling";"Larva";356;1
"Unit";"Zergling";"Larva";356;1
"Unit";"Zergling";"Larva";356;1
"Unit";"Zergling";"Larva";356;1
"Unit";"Zergling";"Larva";356;1
"Unit";"Baneling";"Zergling";356;0
"Unit";"Baneling";"Zergling";356;0
"Unit";"Baneling";"Zergling";356;0
"Unit";"Baneling";"Zergling";356;0
"Unit";"Baneling";"Zergling";356;0
"Unit";"Baneling";"Zergling";356;0
"Unit";"Baneling";"Zergling";358;0
"Unit";"Zergling";"Larva";366;1
"Unit";"Zergling";"Larva";366;1
"Building";"CreepTumor";NA;396;0
"Building";"CreepTumor";NA;396;0
"Unit";"Zergling";"Larva";396;1
"Unit";"Zergling";"Larva";396;1
"Unit";"Zergling";"Larva";396;1
"Unit";"Zergling";"Larva";396;1
"Unit";"Zergling";"Larva";396;1
"Unit";"Zergling";"Larva";396;1
"Unit";"Zergling";"Larva";396;1
"Unit";"Zergling";"Larva";396;1
"Unit";"Zergling";"Larva";396;1
"Unit";"Zergling";"Larva";396;1
"Unit";"Zergling";"Larva";396;1
"Unit";"Zergling";"Larva";396;1
"Unit";"Zergling";"Larva";396;1
"Unit";"Zergling";"Larva";396;1
"Building";"Hatchery";NA;320;0
"Unit";"Ultralisk";"Larva";366;6
"Building";"CreepTumor";NA;412;0
"Building";"CreepTumor";NA;412;0
"Building";"Extractor";NA;398;0
"Unit";"Baneling";"Zergling";412;0
"Unit";"Baneling";"Zergling";412;0
"Unit";"Baneling";"Zergling";412;0
"Unit";"Baneling";"Zergling";412;0
"Unit";"Baneling";"Zergling";412;0
"Unit";"Baneling";"Zergling";412;0
"Unit";"Overlord";"Larva";412;0
"Unit";"Overlord";"Larva";412;0
"Unit";"Overlord";"Larva";412;0
"Building";"CreepTumor";NA;418;0
"Building";"CreepTumor";NA;418;0
"Unit";"Ultralisk";"Larva";398;6
"Building";"CreepTumor";NA;418;0
"Building";"CreepTumorQueen";NA;418;0
"Building";"CreepTumorQueen";NA;418;0
"Building";"CreepTumorQueen";NA;424;0
"Unit";"Ultralisk";"Larva";412;6
"Unit";"Baneling";"Zergling";418;0
"Unit";"Baneling";"Zergling";418;0
"Building";"CreepTumorQueen";NA;424;0
"Building";"CreepTumorQueen";NA;430;0
"Upgrade";"ChitinousPlating";"UltraliskCavern";412;0
"Upgrade";"ZergMeleeWeaponsLevel2";"EvolutionChamber";358;0
"Unit";"Baneling";"Zergling";430;0
"Unit";"Ultralisk";"Larva";418;6
"Unit";"Ultralisk";"Larva";418;6
"Unit";"Baneling";"Zergling";430;0
"Unit";"Baneling";"Zergling";430;0
"Unit";"Baneling";"Zergling";430;0
"Unit";"Baneling";"Zergling";430;0
"Unit";"Baneling";"Zergling";430;0
"Unit";"Baneling";"Zergling";430;0
"Upgrade";"ZergGroundArmorsLevel2";"EvolutionChamber";366;0
"Unit";"Baneling";"Zergling";430;0
"Unit";"Baneling";"Zergling";430;0
"Unit";"Baneling";"Zergling";430;0
"Unit";"Baneling";"Zergling";430;0
"Unit";"Baneling";"Zergling";430;0
"Unit";"Baneling";"Zergling";430;0
"Unit";"Baneling";"Zergling";430;0
"Unit";"Baneling";"Zergling";430;0
"Unit";"Baneling";"Zergling";430;0
"Unit";"Baneling";"Zergling";430;0
"Unit";"Baneling";"Zergling";430;0
"Unit";"Baneling";"Zergling";430;0
"Unit";"Baneling";"Zergling";430;0
"Unit";"Baneling";"Zergling";430;0
"Unit";"Baneling";"Zergling";430;0
"Unit";"Zergling";"Larva";442;1
"Unit";"Zergling";"Larva";442;1
"Unit";"Zergling";"Larva";442;1
"Unit";"Zergling";"Larva";442;1
"Unit";"Zergling";"Larva";442;1
"Unit";"Zergling";"Larva";442;1
"Unit";"Zergling";"Larva";442;1
"Unit";"Zergling";"Larva";442;1
"Unit";"Zergling";"Larva";442;1
"Unit";"Zergling";"Larva";442;1
"Unit";"Zergling";"Larva";442;1
"Unit";"Zergling";"Larva";442;1
"Unit";"Zergling";"Larva";442;1
"Unit";"Zergling";"Larva";442;1
"Unit";"Zergling";"Larva";442;1
"Unit";"Zergling";"Larva";442;1
"Unit";"Zergling";"Larva";442;1
"Unit";"Zergling";"Larva";442;1
"Unit";"Zergling";"Larva";442;1
"Unit";"Zergling";"Larva";442;1
"Unit";"Zergling";"Larva";442;1
"Unit";"Zergling";"Larva";442;1
"Unit";"Zergling";"Larva";442;1
"Unit";"Zergling";"Larva";442;1
"Unit";"Zergling";"Larva";442;1
"Unit";"Zergling";"Larva";442;1
"Unit";"Zergling";"Larva";442;1
"Unit";"Zergling";"Larva";442;1
"Unit";"Zergling";"Larva";442;1
"Unit";"Zergling";"Larva";442;1
"Unit";"Zergling";"Larva";442;1
"Unit";"Zergling";"Larva";442;1
"Unit";"Zergling";"Larva";442;1
"Unit";"Zergling";"Larva";442;1
"Unit";"Zergling";"Larva";442;1
"Unit";"Zergling";"Larva";442;1
"Unit";"Zergling";"Larva";442;1
"Unit";"Zergling";"Larva";442;1
"Unit";"Zergling";"Larva";442;1
"Unit";"Zergling";"Larva";442;1
"Unit";"Zergling";"Larva";442;1
"Unit";"Zergling";"Larva";442;1
"Unit";"Zergling";"Larva";442;1
"Unit";"Zergling";"Larva";442;1
"Unit";"Zergling";"Larva";442;1
"Unit";"Zergling";"Larva";442;1
"Unit";"Zergling";"Larva";442;1
"Unit";"Zergling";"Larva";442;1
"Unit";"Zergling";"Larva";442;1
"Unit";"Zergling";"Larva";442;1
"Unit";"Zergling";"Larva";442;1
"Unit";"Zergling";"Larva";442;1
"Unit";"Zergling";"Larva";442;1
"Unit";"Zergling";"Larva";442;1
"Unit";"Zergling";"Larva";442;1
"Unit";"Zergling";"Larva";442;1
"Unit";"Zergling";"Larva";442;1
"Unit";"Zergling";"Larva";442;1
"Unit";"Zergling";"Larva";442;1
"Unit";"Zergling";"Larva";442;1
"Unit";"Zergling";"Larva";442;1
"Unit";"Zergling";"Larva";442;1
"Unit";"Zergling";"Larva";442;1
"Unit";"Zergling";"Larva";442;1
"Unit";"Zergling";"Larva";442;1
"Unit";"Zergling";"Larva";442;1
"Unit";"Zergling";"Larva";442;1
"Unit";"Zergling";"Larva";442;1
"Unit";"Ultralisk";"Larva";442;6
