"type";"unit_name";"on_building";"total_supply";"supply"
"Unit";"Overlord";"Larva";13;0
"Building";"Extractor";NA;18;0
"Unit";"Overlord";"Larva";21;0
"Building";"SpawningPool";NA;19;0
"Building";"Hatchery";NA;17;0
"Unit";"Zergling";"Larva";22;1
"Unit";"Zergling";"Larva";22;1
"Unit";"Zergling";"Larva";22;1
"Unit";"Zergling";"Larva";22;1
"Unit";"Queen";"Hatchery";22;2
"Unit";"Queen";"Hatchery";22;2
"Unit";"Overlord";"Larva";36;0
"Unit";"Queen";"Hatchery";36;2
"Building";"CreepTumorQueen";NA;39;0
"Unit";"Overlord";"Larva";47;0
"Building";"Extractor";NA;49;0
"Unit";"Overlord";"Larva";49;0
"Building";"CreepTumor";NA;51;0
"Building";"CreepTumorQueen";NA;51;0
"Unit";"Zergling";"Larva";51;1
"Unit";"Zergling";"Larva";51;1
"Unit";"Zergling";"Larva";51;1
"Unit";"Zergling";"Larva";51;1
"Unit";"Zergling";"Larva";51;1
"Unit";"Zergling";"Larva";51;1
"Unit";"Zergling";"Larva";51;1
"Unit";"Zergling";"Larva";51;1
"Unit";"Zergling";"Larva";51;1
"Unit";"Zergling";"Larva";51;1
"Unit";"Zergling";"Larva";51;1
"Unit";"Zergling";"Larva";51;1
"Unit";"Zergling";"Larva";51;1
"Unit";"Zergling";"Larva";51;1
"Unit";"Zergling";"Larva";51;1
"Unit";"Zergling";"Larva";51;1
"Unit";"Zergling";"Larva";51;1
"Unit";"Zergling";"Larva";51;1
"Unit";"Overlord";"Larva";51;0
"Building";"CreepTumorQueen";NA;70;0
"Building";"CreepTumor";NA;70;0
"Building";"EvolutionChamber";NA;51;0
"Building";"CreepTumor";NA;70;0
"Building";"EvolutionChamber";NA;51;0
"Building";"Hatchery";NA;49;0
"Building";"BanelingNest";NA;51;0
"Unit";"Overlord";"Larva";70;0
"Unit";"Overlord";"Larva";70;0
"Unit";"Zergling";"Larva";70;1
"Unit";"Zergling";"Larva";70;1
"Unit";"Zergling";"Larva";70;1
"Unit";"Zergling";"Larva";70;1
"Unit";"Baneling";"Zergling";75;0
"Unit";"Baneling";"Zergling";75;0
"Unit";"Baneling";"Zergling";75;0
"Unit";"Baneling";"Zergling";75;0
"Unit";"Baneling";"Zergling";75;0
"Unit";"Baneling";"Zergling";75;0
"Unit";"Baneling";"Zergling";75;0
"Unit";"Baneling";"Zergling";75;0
"Building";"CreepTumor";NA;75;0
"Building";"CreepTumorQueen";NA;79;0
"Building";"CreepTumor";NA;79;0
"Unit";"Zergling";"Larva";75;1
"Unit";"Zergling";"Larva";75;1
"Unit";"Zergling";"Larva";75;1
"Unit";"Zergling";"Larva";75;1
"Unit";"Zergling";"Larva";75;1
"Unit";"Zergling";"Larva";75;1
"Building";"CreepTumor";NA;79;0
"Unit";"Overlord";"Larva";79;0
"Unit";"Overlord";"Larva";79;0
"Building";"Extractor";NA;85;0
"Unit";"Queen";"Hatchery";79;2
"Unit";"Overlord";"Larva";85;0
"Unit";"Overlord";"Larva";85;0
"Building";"CreepTumor";NA;94;0
"Building";"CreepTumor";NA;94;0
"Building";"CreepTumor";NA;94;0
"Building";"CreepTumor";NA;94;0
"Unit";"Zergling";"Larva";94;1
"Unit";"Zergling";"Larva";94;1
"Unit";"Zergling";"Larva";94;1
"Unit";"Zergling";"Larva";94;1
"Unit";"Zergling";"Larva";94;1
"Unit";"Zergling";"Larva";94;1
"Unit";"Zergling";"Larva";94;1
"Unit";"Zergling";"Larva";94;1
"Unit";"Zergling";"Larva";94;1
"Unit";"Zergling";"Larva";94;1
"Unit";"Zergling";"Larva";94;1
"Unit";"Zergling";"Larva";94;1
"Building";"SporeCrawler";NA;94;0
"Building";"CreepTumorQueen";NA;97;0
"Building";"CreepTumor";NA;97;0
"Building";"CreepTumor";NA;97;0
"Building";"CreepTumorQueen";NA;97;0
"Building";"CreepTumor";NA;97;0
"Building";"Extractor";NA;97;0
"Building";"Hatchery";NA;85;0
"Unit";"Zergling";"Larva";112;1
"Unit";"Zergling";"Larva";112;1
"Unit";"Zergling";"Larva";112;1
"Unit";"Zergling";"Larva";112;1
"Unit";"Zergling";"Larva";112;1
"Unit";"Zergling";"Larva";112;1
"Unit";"Zergling";"Larva";112;1
"Unit";"Zergling";"Larva";112;1
"Unit";"Zergling";"Larva";112;1
"Unit";"Zergling";"Larva";112;1
"Unit";"Zergling";"Larva";112;1
"Unit";"Zergling";"Larva";112;1
"Unit";"Zergling";"Larva";112;1
"Unit";"Zergling";"Larva";112;1
"Unit";"Zergling";"Larva";112;1
"Unit";"Zergling";"Larva";112;1
"Building";"CreepTumor";NA;112;0
"Building";"CreepTumor";NA;112;0
"Building";"CreepTumor";NA;112;0
"Unit";"Baneling";"Zergling";112;0
"Unit";"Baneling";"Zergling";112;0
"Unit";"Baneling";"Zergling";112;0
"Unit";"Baneling";"Zergling";112;0
"Unit";"Baneling";"Zergling";112;0
"Upgrade";"ZergGroundArmorsLevel1";"EvolutionChamber";94;0
"Building";"CreepTumorQueen";NA;137;0
"Building";"CreepTumorQueen";NA;137;0
"Unit";"Zergling";"Larva";137;1
"Unit";"Zergling";"Larva";137;1
"Unit";"Zergling";"Larva";137;1
"Unit";"Zergling";"Larva";137;1
"Unit";"Zergling";"Larva";137;1
"Unit";"Zergling";"Larva";137;1
"Unit";"Zergling";"Larva";137;1
"Unit";"Zergling";"Larva";137;1
"Unit";"Zergling";"Larva";137;1
"Unit";"Zergling";"Larva";137;1
"Unit";"Zergling";"Larva";140;1
"Unit";"Zergling";"Larva";140;1
"Unit";"Zergling";"Larva";140;1
"Unit";"Zergling";"Larva";140;1
"Unit";"Zergling";"Larva";140;1
"Unit";"Zergling";"Larva";140;1
"Building";"InfestationPit";NA;128;0
"Unit";"Zergling";"Larva";140;1
"Unit";"Zergling";"Larva";140;1
"Unit";"Zergling";"Larva";140;1
"Unit";"Zergling";"Larva";140;1
"Unit";"Zergling";"Larva";140;1
"Unit";"Zergling";"Larva";140;1
"Unit";"Zergling";"Larva";140;1
"Unit";"Zergling";"Larva";140;1
"Building";"CreepTumor";NA;156;0
"Upgrade";"ZergMeleeWeaponsLevel1";"EvolutionChamber";112;0
"Building";"CreepTumor";NA;170;0
"Building";"CreepTumor";NA;170;0
"Building";"CreepTumor";NA;170;0
"Building";"CreepTumor";NA;170;0
"Unit";"Zergling";"Larva";170;1
"Unit";"Zergling";"Larva";170;1
"Unit";"Zergling";"Larva";170;1
"Unit";"Zergling";"Larva";170;1
"Unit";"Zergling";"Larva";170;1
"Unit";"Zergling";"Larva";170;1
"Unit";"Zergling";"Larva";170;1
"Unit";"Zergling";"Larva";170;1
"Unit";"Zergling";"Larva";170;1
"Unit";"Zergling";"Larva";170;1
"Unit";"Zergling";"Larva";170;1
"Unit";"Zergling";"Larva";170;1
"Unit";"Zergling";"Larva";170;1
"Unit";"Zergling";"Larva";170;1
"Unit";"Zergling";"Larva";170;1
"Unit";"Zergling";"Larva";170;1
"Unit";"Zergling";"Larva";170;1
"Unit";"Zergling";"Larva";170;1
"Building";"CreepTumor";NA;190;0
"Building";"CreepTumor";NA;190;0
"Building";"CreepTumor";NA;190;0
"Unit";"Zergling";"Larva";190;1
"Unit";"Zergling";"Larva";190;1
"Unit";"Zergling";"Larva";190;1
"Unit";"Zergling";"Larva";190;1
"Unit";"Zergling";"Larva";190;1
"Unit";"Zergling";"Larva";190;1
"Unit";"Zergling";"Larva";190;1
"Unit";"Zergling";"Larva";190;1
"Unit";"Zergling";"Larva";190;1
"Unit";"Zergling";"Larva";190;1
"Unit";"Zergling";"Larva";190;1
"Unit";"Zergling";"Larva";190;1
"Unit";"Zergling";"Larva";190;1
"Unit";"Zergling";"Larva";190;1
"Unit";"Zergling";"Larva";190;1
"Unit";"Zergling";"Larva";190;1
"Unit";"Zergling";"Larva";190;1
"Unit";"Zergling";"Larva";190;1
"Unit";"Zergling";"Larva";190;1
"Unit";"Zergling";"Larva";190;1
"Unit";"Zergling";"Larva";190;1
"Unit";"Zergling";"Larva";190;1
"Building";"CreepTumor";NA;190;0
"Building";"CreepTumor";NA;190;0
"Unit";"Overlord";"Larva";190;0
"Unit";"Baneling";"Zergling";190;0
"Unit";"Baneling";"Zergling";190;0
"Unit";"Baneling";"Zergling";190;0
"Unit";"Baneling";"Zergling";190;0
"Unit";"Baneling";"Zergling";190;0
"Unit";"Baneling";"Zergling";190;0
"Unit";"Baneling";"Zergling";190;0
"Building";"Hatchery";NA;170;0
"Building";"CreepTumor";NA;212;0
"Building";"CreepTumor";NA;213;0
"Unit";"Overlord";"Larva";212;0
"Unit";"Overlord";"Larva";212;0
"Building";"CreepTumor";NA;215;0
"Building";"CreepTumor";NA;215;0
"Unit";"Overlord";"Larva";215;0
"Unit";"Overlord";"Larva";215;0
"Unit";"Overlord";"Larva";215;0
"Unit";"Overlord";"Larva";215;0
"Unit";"Overlord";"Larva";215;0
"Building";"SpineCrawler";NA;190;0
"Unit";"Queen";"Hatchery";212;2
"Unit";"Baneling";"Zergling";216;0
"Unit";"Baneling";"Zergling";220;0
"Unit";"Baneling";"Zergling";220;0
"Unit";"Baneling";"Zergling";220;0
"Unit";"Baneling";"Zergling";220;0
"Unit";"Baneling";"Zergling";220;0
"Unit";"Baneling";"Zergling";220;0
"Unit";"Baneling";"Zergling";220;0
"Unit";"Baneling";"Zergling";220;0
"Unit";"Baneling";"Zergling";220;0
"Unit";"Baneling";"Zergling";220;0
"Unit";"Baneling";"Zergling";220;0
"Unit";"Baneling";"Zergling";220;0
"Unit";"Baneling";"Zergling";220;0
"Unit";"Baneling";"Zergling";220;0
"Unit";"Baneling";"Zergling";220;0
"Unit";"Overlord";"Larva";220;0
"Unit";"Zergling";"Larva";222;1
"Unit";"Zergling";"Larva";222;1
"Unit";"Zergling";"Larva";222;1
"Unit";"Zergling";"Larva";222;1
"Unit";"Zergling";"Larva";222;1
"Unit";"Zergling";"Larva";222;1
"Unit";"Zergling";"Larva";222;1
"Unit";"Zergling";"Larva";222;1
"Unit";"Zergling";"Larva";222;1
"Unit";"Zergling";"Larva";222;1
"Unit";"Zergling";"Larva";222;1
"Unit";"Zergling";"Larva";222;1
"Unit";"Zergling";"Larva";222;1
"Unit";"Zergling";"Larva";222;1
"Unit";"Zergling";"Larva";222;1
"Unit";"Zergling";"Larva";222;1
"Unit";"Zergling";"Larva";222;1
"Unit";"Zergling";"Larva";222;1
"Unit";"Zergling";"Larva";222;1
"Unit";"Zergling";"Larva";222;1
"Unit";"Zergling";"Larva";222;1
"Unit";"Zergling";"Larva";222;1
"Unit";"Zergling";"Larva";222;1
"Unit";"Zergling";"Larva";222;1
"Unit";"Zergling";"Larva";222;1
"Unit";"Zergling";"Larva";222;1
"Unit";"Zergling";"Larva";222;1
"Unit";"Zergling";"Larva";222;1
"Unit";"Zergling";"Larva";222;1
"Unit";"Zergling";"Larva";222;1
"Unit";"Zergling";"Larva";222;1
"Unit";"Zergling";"Larva";222;1
"Unit";"Zergling";"Larva";222;1
"Unit";"Zergling";"Larva";222;1
"Unit";"Zergling";"Larva";222;1
"Unit";"Zergling";"Larva";222;1
"Unit";"Zergling";"Larva";222;1
"Unit";"Zergling";"Larva";222;1
"Building";"UltraliskCavern";NA;220;0
"Upgrade";"ZergGroundArmorsLevel2";"EvolutionChamber";190;0
"Building";"CreepTumorQueen";NA;246;0
"Unit";"Baneling";"Zergling";246;0
"Unit";"Baneling";"Zergling";246;0
"Unit";"Baneling";"Zergling";246;0
"Upgrade";"ZergMeleeWeaponsLevel2";"EvolutionChamber";190;0
"Unit";"Zergling";"Larva";246;1
"Unit";"Zergling";"Larva";246;1
"Unit";"Zergling";"Larva";246;1
"Unit";"Zergling";"Larva";246;1
"Unit";"Zergling";"Larva";246;1
"Unit";"Zergling";"Larva";246;1
"Unit";"Zergling";"Larva";246;1
"Unit";"Zergling";"Larva";246;1
"Unit";"Zergling";"Larva";246;1
"Unit";"Zergling";"Larva";246;1
"Unit";"Zergling";"Larva";246;1
"Unit";"Zergling";"Larva";246;1
"Building";"CreepTumorQueen";NA;272;0
"Building";"CreepTumorQueen";NA;272;0
"Building";"CreepTumor";NA;272;0
"Building";"CreepTumor";NA;272;0
"Unit";"Baneling";"Zergling";272;0
"Unit";"Zergling";"Larva";272;1
"Unit";"Zergling";"Larva";272;1
"Unit";"Zergling";"Larva";272;1
"Unit";"Zergling";"Larva";272;1
"Unit";"Zergling";"Larva";272;1
"Unit";"Zergling";"Larva";272;1
"Unit";"Zergling";"Larva";272;1
"Unit";"Zergling";"Larva";272;1
"Unit";"Zergling";"Larva";272;1
"Unit";"Zergling";"Larva";272;1
"Unit";"Zergling";"Larva";272;1
"Unit";"Zergling";"Larva";272;1
"Unit";"Zergling";"Larva";272;1
"Unit";"Zergling";"Larva";272;1
"Unit";"Zergling";"Larva";272;1
"Unit";"Zergling";"Larva";272;1
"Unit";"Zergling";"Larva";272;1
"Unit";"Zergling";"Larva";272;1
"Unit";"Zergling";"Larva";272;1
"Unit";"Zergling";"Larva";272;1
"Unit";"Zergling";"Larva";272;1
"Unit";"Zergling";"Larva";272;1
"Unit";"Zergling";"Larva";272;1
"Unit";"Zergling";"Larva";272;1
"Unit";"Zergling";"Larva";272;1
"Unit";"Zergling";"Larva";272;1
"Unit";"Zergling";"Larva";272;1
"Unit";"Zergling";"Larva";272;1
"Unit";"Zergling";"Larva";272;1
"Unit";"Zergling";"Larva";272;1
"Unit";"Zergling";"Larva";272;1
"Unit";"Zergling";"Larva";272;1
"Unit";"Baneling";"Zergling";304;0
"Unit";"Baneling";"Zergling";304;0
"Unit";"Baneling";"Zergling";304;0
"Unit";"Baneling";"Zergling";304;0
"Unit";"Baneling";"Zergling";304;0
"Unit";"Baneling";"Zergling";304;0
"Building";"CreepTumorQueen";NA;304;0
"Building";"Hatchery";NA;272;0
"Building";"CreepTumor";NA;304;0
"Unit";"Ultralisk";"Larva";304;6
"Unit";"Ultralisk";"Larva";304;6
"Unit";"Baneling";"Zergling";304;0
"Unit";"Baneling";"Zergling";304;0
"Unit";"Baneling";"Zergling";304;0
"Unit";"Baneling";"Zergling";304;0
"Unit";"Baneling";"Zergling";304;0
"Unit";"Baneling";"Zergling";304;0
"Unit";"Baneling";"Zergling";304;0
"Unit";"Zergling";"Larva";304;1
"Unit";"Zergling";"Larva";304;1
"Unit";"Zergling";"Larva";304;1
"Unit";"Zergling";"Larva";304;1
"Unit";"Zergling";"Larva";304;1
"Unit";"Zergling";"Larva";304;1
"Unit";"Zergling";"Larva";304;1
"Unit";"Zergling";"Larva";304;1
"Unit";"Zergling";"Larva";304;1
"Unit";"Zergling";"Larva";304;1
"Unit";"Zergling";"Larva";304;1
"Unit";"Zergling";"Larva";304;1
"Unit";"Zergling";"Larva";304;1
"Unit";"Zergling";"Larva";304;1
"Unit";"Zergling";"Larva";304;1
"Unit";"Zergling";"Larva";304;1
"Unit";"Zergling";"Larva";304;1
"Unit";"Zergling";"Larva";304;1
"Unit";"Zergling";"Larva";304;1
"Unit";"Zergling";"Larva";304;1
"Unit";"Zergling";"Larva";304;1
"Unit";"Zergling";"Larva";304;1
"Unit";"Zergling";"Larva";304;1
"Unit";"Zergling";"Larva";304;1
"Unit";"Zergling";"Larva";304;1
"Unit";"Zergling";"Larva";304;1
"Unit";"Zergling";"Larva";304;1
"Unit";"Zergling";"Larva";304;1
"Unit";"Zergling";"Larva";304;1
"Unit";"Zergling";"Larva";304;1
"Unit";"Zergling";"Larva";304;1
"Unit";"Zergling";"Larva";304;1
"Unit";"Zergling";"Larva";304;1
"Unit";"Zergling";"Larva";304;1
"Unit";"Zergling";"Larva";304;1
"Unit";"Zergling";"Larva";304;1
"Unit";"Zergling";"Larva";304;1
"Unit";"Zergling";"Larva";304;1
"Unit";"Baneling";"Zergling";304;0
"Unit";"Baneling";"Zergling";304;0
"Unit";"Baneling";"Zergling";304;0
"Unit";"Baneling";"Zergling";304;0
"Unit";"Baneling";"Zergling";304;0
"Unit";"Baneling";"Zergling";304;0
"Building";"CreepTumor";NA;304;0
"Building";"CreepTumor";NA;304;0
"Unit";"Baneling";"Zergling";354;0
"Unit";"Baneling";"Zergling";354;0
"Unit";"Baneling";"Zergling";354;0
"Unit";"Zergling";"Larva";328;1
"Unit";"Zergling";"Larva";328;1
"Unit";"Zergling";"Larva";346;1
"Unit";"Zergling";"Larva";346;1
"Unit";"Zergling";"Larva";346;1
"Unit";"Zergling";"Larva";346;1
"Unit";"Zergling";"Larva";346;1
"Unit";"Zergling";"Larva";346;1
"Unit";"Zergling";"Larva";350;1
"Unit";"Zergling";"Larva";350;1
"Unit";"Zergling";"Larva";354;1
"Unit";"Zergling";"Larva";354;1
"Unit";"Zergling";"Larva";354;1
"Unit";"Zergling";"Larva";354;1
"Unit";"Zergling";"Larva";354;1
"Unit";"Zergling";"Larva";354;1
"Unit";"Zergling";"Larva";354;1
"Unit";"Zergling";"Larva";354;1
"Unit";"Zergling";"Larva";354;1
"Unit";"Zergling";"Larva";354;1
"Unit";"Zergling";"Larva";354;1
"Unit";"Zergling";"Larva";354;1
"Unit";"Zergling";"Larva";354;1
"Unit";"Zergling";"Larva";354;1
"Unit";"Zergling";"Larva";354;1
"Unit";"Zergling";"Larva";354;1
"Unit";"Zergling";"Larva";354;1
"Unit";"Zergling";"Larva";354;1
"Unit";"Zergling";"Larva";354;1
"Unit";"Zergling";"Larva";354;1
"Building";"CreepTumorQueen";NA;354;0
"Building";"CreepTumor";NA;384;0
"Upgrade";"ChitinousPlating";"UltraliskCavern";304;0
"Building";"CreepTumor";NA;384;0
"Building";"CreepTumor";NA;384;0
"Building";"Extractor";NA;384;0
"Building";"Hatchery";NA;304;0
"Building";"Extractor";NA;384;0
"Unit";"Zergling";"Larva";384;1
"Unit";"Zergling";"Larva";384;1
"Unit";"Zergling";"Larva";384;1
"Unit";"Zergling";"Larva";384;1
"Unit";"Zergling";"Larva";384;1
"Unit";"Zergling";"Larva";384;1
"Unit";"Zergling";"Larva";384;1
"Unit";"Zergling";"Larva";384;1
"Unit";"Zergling";"Larva";384;1
"Unit";"Zergling";"Larva";384;1
"Unit";"Zergling";"Larva";384;1
"Unit";"Zergling";"Larva";384;1
"Unit";"Zergling";"Larva";384;1
"Unit";"Zergling";"Larva";384;1
"Unit";"Zergling";"Larva";384;1
"Unit";"Zergling";"Larva";384;1
"Unit";"Zergling";"Larva";384;1
"Unit";"Zergling";"Larva";384;1
"Unit";"Zergling";"Larva";384;1
"Unit";"Zergling";"Larva";384;1
"Unit";"Zergling";"Larva";384;1
"Unit";"Zergling";"Larva";384;1
"Unit";"Zergling";"Larva";384;1
"Unit";"Zergling";"Larva";384;1
"Unit";"Zergling";"Larva";384;1
"Unit";"Zergling";"Larva";384;1
"Unit";"Zergling";"Larva";384;1
"Unit";"Zergling";"Larva";384;1
"Unit";"Zergling";"Larva";384;1
"Unit";"Zergling";"Larva";384;1
"Upgrade";"ZergGroundArmorsLevel3";"EvolutionChamber";304;0
"Unit";"Ultralisk";"Larva";384;6
"Unit";"Baneling";"Zergling";414;0
"Unit";"Baneling";"Zergling";414;0
"Unit";"Baneling";"Zergling";414;0
"Unit";"Baneling";"Zergling";420;0
"Unit";"Baneling";"Zergling";420;0
"Unit";"Baneling";"Zergling";420;0
"Unit";"Baneling";"Zergling";420;0
"Unit";"Baneling";"Zergling";420;0
"Unit";"Baneling";"Zergling";420;0
"Unit";"Ultralisk";"Larva";384;6
"Unit";"Ultralisk";"Larva";384;6
"Unit";"Zergling";"Larva";432;1
"Unit";"Zergling";"Larva";432;1
"Unit";"Zergling";"Larva";432;1
"Unit";"Zergling";"Larva";432;1
"Unit";"Zergling";"Larva";432;1
"Unit";"Zergling";"Larva";432;1
"Unit";"Zergling";"Larva";432;1
"Unit";"Zergling";"Larva";432;1
"Unit";"Zergling";"Larva";432;1
"Unit";"Zergling";"Larva";432;1
"Unit";"Zergling";"Larva";432;1
"Unit";"Zergling";"Larva";432;1
"Unit";"Zergling";"Larva";432;1
"Unit";"Zergling";"Larva";432;1
"Unit";"Zergling";"Larva";432;1
"Unit";"Zergling";"Larva";432;1
"Unit";"Zergling";"Larva";432;1
"Unit";"Zergling";"Larva";432;1
"Unit";"Zergling";"Larva";432;1
"Unit";"Zergling";"Larva";432;1
"Unit";"Zergling";"Larva";432;1
"Unit";"Zergling";"Larva";432;1
"Unit";"Zergling";"Larva";432;1
"Unit";"Zergling";"Larva";432;1
"Unit";"Zergling";"Larva";432;1
"Unit";"Zergling";"Larva";432;1
"Unit";"Zergling";"Larva";432;1
"Unit";"Zergling";"Larva";432;1
"Upgrade";"ZergMeleeWeaponsLevel3";"EvolutionChamber";328;0
"Unit";"Ultralisk";"Larva";420;6
"Unit";"Zergling";"Larva";460;1
"Unit";"Zergling";"Larva";460;1
"Unit";"Zergling";"Larva";460;1
"Unit";"Zergling";"Larva";460;1
"Unit";"Zergling";"Larva";460;1
"Unit";"Zergling";"Larva";460;1
"Unit";"Zergling";"Larva";460;1
"Unit";"Zergling";"Larva";460;1
"Unit";"Zergling";"Larva";460;1
"Unit";"Zergling";"Larva";460;1
"Unit";"Zergling";"Larva";460;1
"Unit";"Zergling";"Larva";460;1
"Unit";"Zergling";"Larva";460;1
"Unit";"Zergling";"Larva";460;1
"Unit";"Zergling";"Larva";460;1
"Unit";"Zergling";"Larva";460;1
"Unit";"Zergling";"Larva";460;1
"Unit";"Zergling";"Larva";460;1
"Unit";"Zergling";"Larva";460;1
"Unit";"Zergling";"Larva";460;1
"Unit";"Zergling";"Larva";460;1
"Unit";"Zergling";"Larva";460;1
"Unit";"Zergling";"Larva";460;1
"Unit";"Zergling";"Larva";460;1
"Unit";"Zergling";"Larva";460;1
"Unit";"Zergling";"Larva";460;1
"Unit";"Zergling";"Larva";460;1
"Unit";"Zergling";"Larva";460;1
"Unit";"Zergling";"Larva";460;1
"Unit";"Zergling";"Larva";460;1
"Unit";"Zergling";"Larva";460;1
"Unit";"Zergling";"Larva";460;1
"Unit";"Zergling";"Larva";460;1
"Unit";"Zergling";"Larva";460;1
"Unit";"Zergling";"Larva";460;1
"Unit";"Zergling";"Larva";460;1
"Unit";"Zergling";"Larva";460;1
"Unit";"Zergling";"Larva";460;1
"Unit";"Zergling";"Larva";460;1
"Unit";"Zergling";"Larva";460;1
"Building";"CreepTumor";NA;492;0
"Unit";"Baneling";"Zergling";492;0
"Unit";"Baneling";"Zergling";492;0
"Unit";"Baneling";"Zergling";492;0
"Unit";"Baneling";"Zergling";492;0
"Unit";"Baneling";"Zergling";492;0
"Unit";"Baneling";"Zergling";492;0
"Unit";"Baneling";"Zergling";492;0
"Unit";"Queen";"Hatchery";492;2
"Unit";"Infestor";"Larva";492;2
"Unit";"Infestor";"Larva";492;2
"Unit";"Infestor";"Larva";492;2
"Unit";"Infestor";"Larva";492;2
"Unit";"Baneling";"Zergling";506;0
"Unit";"Baneling";"Zergling";506;0
"Unit";"Baneling";"Zergling";506;0
"Unit";"Baneling";"Zergling";506;0
"Unit";"Baneling";"Zergling";506;0
"Unit";"Baneling";"Zergling";506;0
"Unit";"Baneling";"Zergling";506;0
"Unit";"Baneling";"Zergling";506;0
"Unit";"Baneling";"Zergling";506;0
"Unit";"Zergling";"Larva";508;1
"Unit";"Zergling";"Larva";508;1
"Unit";"Zergling";"Larva";508;1
"Unit";"Zergling";"Larva";508;1
"Unit";"Zergling";"Larva";508;1
"Unit";"Zergling";"Larva";508;1
"Unit";"Zergling";"Larva";508;1
"Unit";"Zergling";"Larva";508;1
"Unit";"Zergling";"Larva";508;1
"Unit";"Zergling";"Larva";508;1
"Unit";"Zergling";"Larva";508;1
"Unit";"Zergling";"Larva";508;1
"Unit";"Zergling";"Larva";508;1
"Unit";"Zergling";"Larva";508;1
"Unit";"Zergling";"Larva";508;1
"Unit";"Zergling";"Larva";508;1
"Unit";"Zergling";"Larva";508;1
"Unit";"Zergling";"Larva";508;1
"Unit";"Zergling";"Larva";508;1
"Unit";"Zergling";"Larva";508;1
