"type";"unit_name";"on_building";"total_supply";"supply"
"Unit";"Overlord";"Larva";13;0
"Building";"Extractor";NA;17;0
"Unit";"Overlord";"Larva";22;0
"Building";"SpawningPool";NA;19;0
"Building";"Hatchery";NA;17;0
"Unit";"Zergling";"Larva";23;1
"Unit";"Zergling";"Larva";23;1
"Unit";"Zergling";"Larva";23;1
"Unit";"Zergling";"Larva";23;1
"Unit";"Queen";"Hatchery";23;2
"Unit";"Queen";"Hatchery";23;2
"Building";"CreepTumorQueen";NA;35;0
"Unit";"Overlord";"Larva";35;0
"Building";"CreepTumor";NA;39;0
"Unit";"Queen";"Hatchery";35;2
"Building";"CreepTumorQueen";NA;40;0
"Unit";"Overlord";"Larva";42;0
"Building";"CreepTumor";NA;47;0
"Building";"Hatchery";NA;30;0
"Building";"CreepTumor";NA;47;0
"Building";"CreepTumorQueen";NA;47;0
"Unit";"Zergling";"Larva";47;1
"Unit";"Zergling";"Larva";47;1
"Unit";"Zergling";"Larva";47;1
"Unit";"Zergling";"Larva";47;1
"Unit";"Zergling";"Larva";47;1
"Unit";"Zergling";"Larva";47;1
"Unit";"Zergling";"Larva";47;1
"Unit";"Zergling";"Larva";47;1
"Unit";"Zergling";"Larva";47;1
"Unit";"Zergling";"Larva";47;1
"Unit";"Zergling";"Larva";47;1
"Unit";"Zergling";"Larva";47;1
"Unit";"Zergling";"Larva";47;1
"Unit";"Zergling";"Larva";47;1
"Unit";"Queen";"Hatchery";42;2
"Building";"CreepTumor";NA;69;0
"Unit";"Queen";"Hatchery";47;2
"Building";"CreepTumor";NA;69;0
"Building";"SporeCrawler";NA;67;0
"Building";"SporeCrawler";NA;68;0
"Building";"SporeCrawler";NA;69;0
"Unit";"Overlord";"Larva";69;0
"Unit";"Overlord";"Larva";69;0
"Unit";"Overlord";"Larva";71;0
"Unit";"Overlord";"Larva";76;0
"Unit";"Zergling";"Larva";76;1
"Unit";"Zergling";"Larva";76;1
"Building";"Extractor";NA;76;0
"Building";"Extractor";NA;76;0
"Unit";"Zergling";"Larva";76;1
"Unit";"Zergling";"Larva";76;1
"Unit";"Zergling";"Larva";76;1
"Unit";"Zergling";"Larva";76;1
"Unit";"Zergling";"Larva";76;1
"Unit";"Zergling";"Larva";76;1
"Unit";"Zergling";"Larva";76;1
"Unit";"Zergling";"Larva";76;1
"Building";"Extractor";NA;76;0
"Unit";"Overlord";"Larva";76;0
"Building";"CreepTumor";NA;102;0
"Unit";"Overlord";"Larva";93;0
"Building";"CreepTumor";NA;102;0
"Building";"CreepTumorQueen";NA;102;0
"Building";"CreepTumorQueen";NA;102;0
"Unit";"Zergling";"Larva";102;1
"Unit";"Zergling";"Larva";102;1
"Unit";"Zergling";"Larva";102;1
"Unit";"Zergling";"Larva";102;1
"Unit";"Zergling";"Larva";102;1
"Unit";"Zergling";"Larva";102;1
"Unit";"Zergling";"Larva";102;1
"Unit";"Zergling";"Larva";102;1
"Unit";"Zergling";"Larva";102;1
"Unit";"Zergling";"Larva";102;1
"Unit";"Zergling";"Larva";102;1
"Unit";"Zergling";"Larva";102;1
"Unit";"Zergling";"Larva";102;1
"Unit";"Zergling";"Larva";102;1
"Unit";"Zergling";"Larva";102;1
"Unit";"Zergling";"Larva";102;1
"Unit";"Zergling";"Larva";102;1
"Unit";"Zergling";"Larva";102;1
"Unit";"Zergling";"Larva";102;1
"Unit";"Zergling";"Larva";102;1
"Unit";"Zergling";"Larva";102;1
"Unit";"Zergling";"Larva";102;1
"Building";"HydraliskDen";NA;102;0
"Building";"CreepTumorQueen";NA;102;0
"Unit";"Overlord";"Larva";102;0
"Building";"CreepTumor";NA;126;0
"Building";"CreepTumor";NA;128;0
"Building";"EvolutionChamber";NA;102;0
"Building";"CreepTumor";NA;127;0
"Building";"EvolutionChamber";NA;102;0
"Unit";"Overlord";"Larva";138;0
"Building";"Extractor";NA;138;0
"Building";"Extractor";NA;138;0
"Building";"CreepTumor";NA;151;0
"Building";"CreepTumor";NA;151;0
"Building";"CreepTumor";NA;151;0
"Unit";"Overlord";"Larva";151;0
"Unit";"Overlord";"Larva";151;0
"Unit";"Overlord";"Larva";151;0
"Unit";"Overlord";"Larva";151;0
"Unit";"Overlord";"Larva";151;0
"Unit";"Hydralisk";"Larva";151;2
"Unit";"Overlord";"Larva";151;0
"Unit";"Hydralisk";"Larva";151;2
"Unit";"Hydralisk";"Larva";151;2
"Unit";"Hydralisk";"Larva";151;2
"Unit";"Hydralisk";"Larva";151;2
"Unit";"Hydralisk";"Larva";151;2
"Unit";"Hydralisk";"Larva";151;2
"Unit";"Hydralisk";"Larva";151;2
"Unit";"Hydralisk";"Larva";151;2
"Unit";"Overlord";"Larva";151;0
"Building";"BanelingNest";NA;151;0
"Unit";"Overlord";"Larva";151;0
"Building";"CreepTumorQueen";NA;151;0
"Unit";"Overlord";"Larva";151;0
"Unit";"Overlord";"Larva";169;0
"Building";"CreepTumor";NA;172;0
"Building";"CreepTumorQueen";NA;172;0
"Building";"CreepTumorQueen";NA;172;0
"Building";"InfestationPit";NA;169;0
"Building";"CreepTumorQueen";NA;172;0
"Building";"Hatchery";NA;151;0
"Unit";"Hydralisk";"Larva";172;2
"Unit";"Hydralisk";"Larva";172;2
"Unit";"Hydralisk";"Larva";172;2
"Unit";"Hydralisk";"Larva";172;2
"Unit";"Hydralisk";"Larva";172;2
"Unit";"Hydralisk";"Larva";172;2
"Unit";"Hydralisk";"Larva";172;2
"Unit";"Hydralisk";"Larva";172;2
"Unit";"Hydralisk";"Larva";172;2
"Unit";"Hydralisk";"Larva";172;2
"Unit";"Hydralisk";"Larva";172;2
"Unit";"Hydralisk";"Larva";172;2
"Building";"CreepTumor";NA;172;0
"Building";"CreepTumor";NA;172;0
"Building";"CreepTumor";NA;172;0
"Building";"CreepTumorQueen";NA;172;0
"Building";"CreepTumorQueen";NA;172;0
"Building";"CreepTumorQueen";NA;196;0
"Upgrade";"ZergMeleeWeaponsLevel1";"EvolutionChamber";151;0
"Upgrade";"ZergGroundArmorsLevel1";"EvolutionChamber";151;0
"Unit";"Hydralisk";"Larva";172;2
"Unit";"Hydralisk";"Larva";172;2
"Unit";"Zergling";"Larva";201;1
"Unit";"Zergling";"Larva";201;1
"Unit";"Zergling";"Larva";201;1
"Unit";"Zergling";"Larva";201;1
"Unit";"Zergling";"Larva";201;1
"Unit";"Zergling";"Larva";201;1
"Unit";"Zergling";"Larva";201;1
"Unit";"Zergling";"Larva";201;1
"Unit";"Zergling";"Larva";201;1
"Unit";"Zergling";"Larva";201;1
"Unit";"Zergling";"Larva";201;1
"Unit";"Zergling";"Larva";201;1
"Unit";"Zergling";"Larva";201;1
"Unit";"Zergling";"Larva";201;1
"Unit";"Zergling";"Larva";201;1
"Unit";"Zergling";"Larva";201;1
"Upgrade";"EvolveMuscularAugments";"HydraliskDen";172;0
"Building";"CreepTumor";NA;201;0
"Building";"CreepTumor";NA;201;0
"Building";"CreepTumor";NA;201;0
"Building";"CreepTumor";NA;201;0
"Building";"Extractor";NA;209;0
"Building";"Extractor";NA;221;0
"Unit";"Hydralisk";"Larva";221;2
"Building";"CreepTumorQueen";NA;228;0
"Building";"CreepTumorQueen";NA;228;0
"Building";"CreepTumor";NA;228;0
"Unit";"Hydralisk";"Larva";228;2
"Unit";"Hydralisk";"Larva";228;2
"Unit";"Zergling";"Larva";228;1
"Unit";"Zergling";"Larva";228;1
"Unit";"Zergling";"Larva";228;1
"Unit";"Zergling";"Larva";228;1
"Unit";"Zergling";"Larva";228;1
"Unit";"Zergling";"Larva";228;1
"Unit";"Zergling";"Larva";228;1
"Unit";"Zergling";"Larva";228;1
"Unit";"Zergling";"Larva";228;1
"Unit";"Zergling";"Larva";228;1
"Unit";"Zergling";"Larva";228;1
"Unit";"Zergling";"Larva";228;1
"Unit";"Hydralisk";"Larva";228;2
"Unit";"Hydralisk";"Larva";228;2
"Unit";"Hydralisk";"Larva";228;2
"Unit";"Overlord";"Larva";246;0
"Unit";"Overlord";"Larva";246;0
"Unit";"Overlord";"Larva";246;0
"Building";"CreepTumorQueen";NA;257;0
"Building";"CreepTumorQueen";NA;257;0
"Building";"CreepTumor";NA;257;0
"Building";"CreepTumor";NA;257;0
"Building";"CreepTumor";NA;257;0
"Building";"CreepTumor";NA;257;0
"Building";"CreepTumor";NA;257;0
"Building";"CreepTumorQueen";NA;257;0
"Building";"CreepTumor";NA;257;0
"Unit";"Overlord";"Larva";246;0
"Unit";"Overlord";"Larva";246;0
"Unit";"Overlord";"Larva";257;0
"Unit";"Overlord";"Larva";257;0
"Unit";"Overlord";"Larva";257;0
"Unit";"Overlord";"Larva";257;0
"Unit";"Overlord";"Larva";257;0
"Unit";"Overlord";"Larva";257;0
"Unit";"Baneling";"Zergling";257;0
"Unit";"Baneling";"Zergling";257;0
"Unit";"Baneling";"Zergling";257;0
"Unit";"Baneling";"Zergling";257;0
"Unit";"Baneling";"Zergling";257;0
"Unit";"Baneling";"Zergling";257;0
"Unit";"Baneling";"Zergling";257;0
"Unit";"Baneling";"Zergling";257;0
"Unit";"Baneling";"Zergling";257;0
"Unit";"Zergling";"Larva";257;1
"Unit";"Zergling";"Larva";257;1
"Unit";"Zergling";"Larva";257;1
"Unit";"Zergling";"Larva";257;1
"Unit";"Zergling";"Larva";257;1
"Unit";"Zergling";"Larva";257;1
"Unit";"Zergling";"Larva";257;1
"Unit";"Zergling";"Larva";257;1
"Unit";"Zergling";"Larva";257;1
"Unit";"Zergling";"Larva";257;1
"Unit";"Zergling";"Larva";257;1
"Unit";"Zergling";"Larva";257;1
"Unit";"Zergling";"Larva";257;1
"Unit";"Zergling";"Larva";257;1
"Unit";"Zergling";"Larva";257;1
"Unit";"Zergling";"Larva";257;1
"Unit";"Zergling";"Larva";257;1
"Unit";"Zergling";"Larva";257;1
"Unit";"Zergling";"Larva";257;1
"Unit";"Zergling";"Larva";257;1
"Unit";"Zergling";"Larva";257;1
"Unit";"Zergling";"Larva";257;1
"Unit";"Zergling";"Larva";257;1
"Unit";"Zergling";"Larva";257;1
"Unit";"Zergling";"Larva";257;1
"Unit";"Zergling";"Larva";257;1
"Unit";"Zergling";"Larva";257;1
"Unit";"Zergling";"Larva";257;1
"Unit";"Zergling";"Larva";257;1
"Unit";"Zergling";"Larva";257;1
"Upgrade";"EvolveGroovedSpines";"HydraliskDen";246;0
"Unit";"Zergling";"Larva";275;1
"Unit";"Zergling";"Larva";275;1
"Building";"UltraliskCavern";NA;257;0
"Unit";"Zergling";"Larva";275;1
"Unit";"Zergling";"Larva";275;1
"Unit";"Hydralisk";"Larva";275;2
"Unit";"Hydralisk";"Larva";275;2
"Unit";"Zergling";"Larva";287;1
"Unit";"Zergling";"Larva";287;1
"Unit";"Hydralisk";"Larva";275;2
"Building";"CreepTumor";NA;287;0
"Building";"CreepTumor";NA;287;0
"Building";"CreepTumor";NA;287;0
"Building";"CreepTumor";NA;287;0
"Building";"CreepTumor";NA;291;0
"Building";"CreepTumor";NA;291;0
"Building";"CreepTumor";NA;291;0
"Building";"CreepTumor";NA;291;0
"Building";"CreepTumor";NA;291;0
"Building";"CreepTumor";NA;291;0
"Building";"CreepTumor";NA;299;0
"Unit";"Overlord";"Larva";291;0
"Building";"CreepTumorQueen";NA;299;0
"Building";"CreepTumorQueen";NA;299;0
"Building";"CreepTumorQueen";NA;299;0
"Building";"CreepTumor";NA;299;0
"Building";"CreepTumor";NA;299;0
"Unit";"Ultralisk";"Larva";299;6
"Unit";"Ultralisk";"Larva";299;6
"Unit";"Ultralisk";"Larva";299;6
"Unit";"Ultralisk";"Larva";299;6
"Unit";"Hydralisk";"Larva";299;2
"Upgrade";"ZergMeleeWeaponsLevel2";"EvolutionChamber";257;0
"Upgrade";"ZergGroundArmorsLevel2";"EvolutionChamber";257;0
"Building";"CreepTumor";NA;308;0
"Building";"CreepTumor";NA;308;0
"Building";"CreepTumor";NA;308;0
"Building";"CreepTumor";NA;308;0
"Building";"CreepTumor";NA;308;0
"Unit";"Overlord";"Larva";335;0
"Unit";"Overlord";"Larva";335;0
"Building";"SporeCrawler";NA;335;0
"Upgrade";"ChitinousPlating";"UltraliskCavern";299;0
"Unit";"Hydralisk";"Larva";335;2
"Unit";"Hydralisk";"Larva";335;2
"Building";"Hatchery";NA;299;0
"Building";"SpineCrawler";NA;335;0
"Building";"SpineCrawler";NA;335;0
"Building";"CreepTumor";NA;337;0
"Building";"CreepTumor";NA;337;0
"Building";"CreepTumor";NA;337;0
"Unit";"Baneling";"Zergling";337;0
"Unit";"Baneling";"Zergling";337;0
"Unit";"Baneling";"Zergling";337;0
"Unit";"Baneling";"Zergling";337;0
"Unit";"Baneling";"Zergling";337;0
"Unit";"Baneling";"Zergling";337;0
"Unit";"Baneling";"Zergling";337;0
"Unit";"Baneling";"Zergling";337;0
"Unit";"Baneling";"Zergling";337;0
"Unit";"Baneling";"Zergling";337;0
"Building";"CreepTumor";NA;337;0
"Building";"CreepTumor";NA;337;0
"Building";"CreepTumor";NA;337;0
"Building";"CreepTumor";NA;339;0
"Building";"CreepTumor";NA;339;0
"Building";"CreepTumor";NA;339;0
"Building";"CreepTumor";NA;339;0
"Building";"CreepTumorQueen";NA;339;0
"Building";"CreepTumorQueen";NA;339;0
"Unit";"Zergling";"Larva";339;1
"Unit";"Zergling";"Larva";339;1
"Unit";"Zergling";"Larva";339;1
"Unit";"Zergling";"Larva";339;1
"Unit";"Zergling";"Larva";339;1
"Unit";"Zergling";"Larva";339;1
"Unit";"Zergling";"Larva";339;1
"Unit";"Zergling";"Larva";339;1
"Unit";"Zergling";"Larva";339;1
"Unit";"Zergling";"Larva";339;1
"Unit";"Zergling";"Larva";339;1
"Unit";"Zergling";"Larva";339;1
"Unit";"Zergling";"Larva";339;1
"Unit";"Zergling";"Larva";339;1
"Unit";"Zergling";"Larva";339;1
"Unit";"Zergling";"Larva";339;1
"Unit";"Zergling";"Larva";339;1
"Unit";"Zergling";"Larva";339;1
"Unit";"Zergling";"Larva";339;1
"Unit";"Zergling";"Larva";339;1
"Unit";"Zergling";"Larva";339;1
"Unit";"Zergling";"Larva";339;1
"Unit";"Zergling";"Larva";339;1
"Unit";"Zergling";"Larva";339;1
"Unit";"Zergling";"Larva";339;1
"Unit";"Zergling";"Larva";339;1
"Unit";"Zergling";"Larva";339;1
"Unit";"Zergling";"Larva";339;1
"Unit";"Zergling";"Larva";339;1
"Unit";"Zergling";"Larva";339;1
"Unit";"Zergling";"Larva";339;1
"Unit";"Zergling";"Larva";339;1
"Unit";"Zergling";"Larva";339;1
"Unit";"Zergling";"Larva";339;1
"Unit";"Zergling";"Larva";339;1
"Unit";"Zergling";"Larva";339;1
"Unit";"Zergling";"Larva";339;1
"Unit";"Zergling";"Larva";339;1
"Unit";"Zergling";"Larva";339;1
"Unit";"Zergling";"Larva";339;1
"Unit";"Ultralisk";"Larva";339;6
"Unit";"Ultralisk";"Larva";339;6
"Unit";"Zergling";"Larva";355;1
"Unit";"Zergling";"Larva";355;1
"Unit";"Zergling";"Larva";355;1
"Unit";"Zergling";"Larva";355;1
"Unit";"Zergling";"Larva";355;1
"Unit";"Zergling";"Larva";355;1
"Unit";"Zergling";"Larva";379;1
"Unit";"Zergling";"Larva";379;1
"Unit";"Zergling";"Larva";379;1
"Unit";"Zergling";"Larva";379;1
"Unit";"Zergling";"Larva";379;1
"Unit";"Zergling";"Larva";379;1
"Unit";"Zergling";"Larva";379;1
"Unit";"Zergling";"Larva";379;1
"Unit";"Zergling";"Larva";379;1
"Unit";"Zergling";"Larva";379;1
"Unit";"Zergling";"Larva";379;1
"Unit";"Zergling";"Larva";379;1
"Unit";"Zergling";"Larva";379;1
"Unit";"Zergling";"Larva";379;1
"Unit";"Zergling";"Larva";397;1
"Unit";"Zergling";"Larva";397;1
"Unit";"Zergling";"Larva";397;1
"Unit";"Zergling";"Larva";397;1
"Unit";"Zergling";"Larva";397;1
"Unit";"Zergling";"Larva";397;1
"Unit";"Zergling";"Larva";397;1
"Unit";"Zergling";"Larva";397;1
"Unit";"Ultralisk";"Larva";345;6
"Unit";"Ultralisk";"Larva";345;6
"Unit";"Ultralisk";"Larva";345;6
"Unit";"Ultralisk";"Larva";345;6
"Unit";"Ultralisk";"Larva";345;6
"Unit";"Ultralisk";"Larva";345;6
"Unit";"Zergling";"Larva";411;1
"Unit";"Zergling";"Larva";411;1
"Unit";"Zergling";"Larva";411;1
"Unit";"Zergling";"Larva";411;1
"Unit";"Zergling";"Larva";411;1
"Unit";"Zergling";"Larva";411;1
"Unit";"Zergling";"Larva";411;1
"Unit";"Zergling";"Larva";411;1
"Unit";"Queen";"Hatchery";397;2
"Unit";"Zergling";"Larva";457;1
"Unit";"Zergling";"Larva";457;1
"Unit";"Zergling";"Larva";457;1
"Unit";"Zergling";"Larva";457;1
"Unit";"Zergling";"Larva";457;1
"Unit";"Zergling";"Larva";457;1
"Unit";"Zergling";"Larva";457;1
"Unit";"Zergling";"Larva";457;1
"Unit";"Zergling";"Larva";457;1
"Unit";"Zergling";"Larva";457;1
"Unit";"Zergling";"Larva";457;1
"Unit";"Zergling";"Larva";457;1
"Unit";"Zergling";"Larva";457;1
"Unit";"Zergling";"Larva";457;1
"Unit";"Zergling";"Larva";457;1
"Unit";"Zergling";"Larva";457;1
"Unit";"Zergling";"Larva";457;1
"Unit";"Zergling";"Larva";457;1
"Unit";"Zergling";"Larva";457;1
"Unit";"Zergling";"Larva";457;1
"Unit";"Zergling";"Larva";457;1
"Unit";"Zergling";"Larva";457;1
"Unit";"Zergling";"Larva";457;1
"Unit";"Zergling";"Larva";457;1
"Unit";"Zergling";"Larva";461;1
"Unit";"Zergling";"Larva";461;1
"Unit";"Zergling";"Larva";461;1
"Unit";"Zergling";"Larva";461;1
"Unit";"Zergling";"Larva";465;1
"Unit";"Zergling";"Larva";465;1
"Unit";"Zergling";"Larva";465;1
"Unit";"Zergling";"Larva";465;1
"Unit";"Zergling";"Larva";465;1
"Unit";"Zergling";"Larva";465;1
"Unit";"Ultralisk";"Larva";411;6
"Unit";"Zergling";"Larva";467;1
"Unit";"Zergling";"Larva";467;1
"Unit";"Zergling";"Larva";469;1
"Unit";"Zergling";"Larva";469;1
"Unit";"Zergling";"Larva";469;1
"Unit";"Zergling";"Larva";469;1
"Unit";"Zergling";"Larva";471;1
"Unit";"Zergling";"Larva";471;1
