"type";"unit_name";"on_building";"total_supply";"supply"
"Unit";"Overlord";"Larva";13;0
"Building";"Extractor";NA;18;0
"Unit";"Overlord";"Larva";21;0
"Building";"SpawningPool";NA;19;0
"Building";"Hatchery";NA;17;0
"Unit";"Zergling";"Larva";22;1
"Unit";"Zergling";"Larva";22;1
"Unit";"Zergling";"Larva";23;1
"Unit";"Zergling";"Larva";23;1
"Unit";"Queen";"Hatchery";22;2
"Unit";"Queen";"Hatchery";23;2
"Unit";"Overlord";"Larva";33;0
"Unit";"Zergling";"Larva";35;1
"Unit";"Zergling";"Larva";35;1
"Unit";"Zergling";"Larva";35;1
"Unit";"Zergling";"Larva";35;1
"Unit";"Queen";"Hatchery";33;2
"Unit";"Overlord";"Larva";41;0
"Building";"CreepTumorQueen";NA;51;0
"Building";"CreepTumorQueen";NA;51;0
"Unit";"Queen";"Hatchery";50;2
"Unit";"Queen";"Hatchery";51;2
"Unit";"Overlord";"Larva";51;0
"Unit";"Overlord";"Larva";52;0
"Building";"Hatchery";NA;43;0
"Building";"CreepTumorQueen";NA;62;0
"Building";"CreepTumor";NA;62;0
"Building";"CreepTumorQueen";NA;62;0
"Building";"CreepTumorQueen";NA;62;0
"Unit";"Zergling";"Larva";62;1
"Unit";"Zergling";"Larva";62;1
"Unit";"Zergling";"Larva";62;1
"Unit";"Zergling";"Larva";62;1
"Unit";"Zergling";"Larva";62;1
"Unit";"Zergling";"Larva";62;1
"Unit";"Zergling";"Larva";62;1
"Unit";"Zergling";"Larva";62;1
"Unit";"Zergling";"Larva";62;1
"Unit";"Zergling";"Larva";62;1
"Unit";"Zergling";"Larva";62;1
"Unit";"Zergling";"Larva";62;1
"Unit";"Zergling";"Larva";62;1
"Unit";"Zergling";"Larva";62;1
"Unit";"Zergling";"Larva";62;1
"Unit";"Zergling";"Larva";62;1
"Unit";"Zergling";"Larva";62;1
"Unit";"Zergling";"Larva";62;1
"Unit";"Queen";"Hatchery";62;2
"Unit";"Queen";"Hatchery";62;2
"Building";"CreepTumorQueen";NA;62;0
"Building";"CreepTumor";NA;62;0
"Building";"CreepTumorQueen";NA;62;0
"Unit";"Overlord";"Larva";62;0
"Unit";"Zergling";"Larva";62;1
"Unit";"Zergling";"Larva";62;1
"Building";"CreepTumorQueen";NA;80;0
"Unit";"Zergling";"Larva";62;1
"Unit";"Zergling";"Larva";62;1
"Unit";"Zergling";"Larva";62;1
"Unit";"Zergling";"Larva";62;1
"Unit";"Zergling";"Larva";62;1
"Unit";"Zergling";"Larva";62;1
"Unit";"Zergling";"Larva";62;1
"Unit";"Zergling";"Larva";62;1
"Unit";"Zergling";"Larva";62;1
"Unit";"Zergling";"Larva";62;1
"Unit";"Zergling";"Larva";62;1
"Unit";"Zergling";"Larva";62;1
"Building";"CreepTumor";NA;80;0
"Building";"CreepTumorQueen";NA;80;0
"Unit";"Overlord";"Larva";62;0
"Building";"CreepTumor";NA;84;0
"Building";"CreepTumor";NA;84;0
"Building";"CreepTumor";NA;84;0
"Unit";"Overlord";"Larva";80;0
"Unit";"Queen";"Hatchery";62;2
"Building";"CreepTumor";NA;104;0
"Building";"CreepTumor";NA;106;0
"Building";"CreepTumor";NA;106;0
"Building";"EvolutionChamber";NA;103;0
"Building";"EvolutionChamber";NA;103;0
"Building";"CreepTumorQueen";NA;106;0
"Building";"CreepTumor";NA;106;0
"Building";"CreepTumorQueen";NA;106;0
"Building";"CreepTumorQueen";NA;106;0
"Building";"CreepTumor";NA;106;0
"Building";"CreepTumor";NA;106;0
"Building";"Extractor";NA;106;0
"Building";"Extractor";NA;106;0
"Building";"BanelingNest";NA;103;0
"Unit";"Overlord";"Larva";106;0
"Building";"Extractor";NA;117;0
"Building";"CreepTumor";NA;127;0
"Unit";"Zergling";"Larva";127;1
"Unit";"Zergling";"Larva";127;1
"Unit";"Zergling";"Larva";127;1
"Unit";"Zergling";"Larva";127;1
"Unit";"Zergling";"Larva";127;1
"Unit";"Zergling";"Larva";127;1
"Unit";"Zergling";"Larva";127;1
"Unit";"Zergling";"Larva";127;1
"Unit";"Zergling";"Larva";127;1
"Unit";"Zergling";"Larva";127;1
"Building";"SporeCrawler";NA;127;0
"Unit";"Baneling";"Zergling";142;0
"Unit";"Baneling";"Zergling";142;0
"Unit";"Baneling";"Zergling";142;0
"Unit";"Baneling";"Zergling";142;0
"Unit";"Baneling";"Zergling";142;0
"Unit";"Baneling";"Zergling";142;0
"Unit";"Baneling";"Zergling";142;0
"Building";"Hatchery";NA;118;0
"Building";"Hatchery";NA;118;0
"Building";"Extractor";NA;134;0
"Building";"Extractor";NA;142;0
"Unit";"Zergling";"Larva";144;1
"Unit";"Zergling";"Larva";144;1
"Unit";"Zergling";"Larva";144;1
"Unit";"Zergling";"Larva";144;1
"Unit";"Zergling";"Larva";144;1
"Unit";"Zergling";"Larva";144;1
"Unit";"Overlord";"Larva";145;0
"Unit";"Overlord";"Larva";145;0
"Building";"CreepTumorQueen";NA;147;0
"Building";"CreepTumor";NA;147;0
"Unit";"Zergling";"Larva";145;1
"Unit";"Zergling";"Larva";145;1
"Unit";"Overlord";"Larva";145;0
"Unit";"Zergling";"Larva";145;1
"Unit";"Zergling";"Larva";145;1
"Building";"CreepTumor";NA;149;0
"Building";"CreepTumor";NA;153;0
"Building";"CreepTumor";NA;153;0
"Building";"CreepTumor";NA;153;0
"Building";"CreepTumor";NA;153;0
"Building";"CreepTumor";NA;153;0
"Unit";"Zergling";"Larva";153;1
"Unit";"Zergling";"Larva";153;1
"Unit";"Zergling";"Larva";153;1
"Unit";"Zergling";"Larva";153;1
"Unit";"Zergling";"Larva";153;1
"Unit";"Zergling";"Larva";153;1
"Unit";"Zergling";"Larva";153;1
"Unit";"Zergling";"Larva";153;1
"Unit";"Zergling";"Larva";153;1
"Unit";"Zergling";"Larva";153;1
"Unit";"Zergling";"Larva";153;1
"Unit";"Zergling";"Larva";153;1
"Unit";"Zergling";"Larva";153;1
"Unit";"Zergling";"Larva";153;1
"Unit";"Zergling";"Larva";153;1
"Unit";"Zergling";"Larva";153;1
"Unit";"Baneling";"Zergling";157;0
"Unit";"Baneling";"Zergling";157;0
"Unit";"Baneling";"Zergling";157;0
"Unit";"Baneling";"Zergling";157;0
"Upgrade";"ZergGroundArmorsLevel1";"EvolutionChamber";122;0
"Upgrade";"ZergMeleeWeaponsLevel1";"EvolutionChamber";122;0
"Unit";"Zergling";"Larva";160;1
"Unit";"Zergling";"Larva";160;1
"Unit";"Zergling";"Larva";160;1
"Unit";"Zergling";"Larva";160;1
"Unit";"Zergling";"Larva";160;1
"Unit";"Zergling";"Larva";160;1
"Unit";"Zergling";"Larva";160;1
"Unit";"Zergling";"Larva";160;1
"Unit";"Zergling";"Larva";160;1
"Unit";"Zergling";"Larva";160;1
"Unit";"Zergling";"Larva";160;1
"Unit";"Zergling";"Larva";160;1
"Building";"CreepTumor";NA;176;0
"Building";"CreepTumor";NA;176;0
"Building";"CreepTumor";NA;176;0
"Building";"CreepTumor";NA;177;0
"Unit";"Zergling";"Larva";177;1
"Unit";"Zergling";"Larva";177;1
"Building";"HydraliskDen";NA;160;0
"Unit";"Zergling";"Larva";177;1
"Unit";"Zergling";"Larva";177;1
"Unit";"Zergling";"Larva";177;1
"Unit";"Zergling";"Larva";177;1
"Unit";"Zergling";"Larva";177;1
"Unit";"Zergling";"Larva";177;1
"Unit";"Zergling";"Larva";177;1
"Unit";"Zergling";"Larva";177;1
"Unit";"Zergling";"Larva";177;1
"Unit";"Zergling";"Larva";177;1
"Unit";"Zergling";"Larva";177;1
"Unit";"Zergling";"Larva";177;1
"Unit";"Zergling";"Larva";177;1
"Unit";"Zergling";"Larva";177;1
"Unit";"Zergling";"Larva";177;1
"Unit";"Zergling";"Larva";177;1
"Unit";"Overlord";"Larva";177;0
"Unit";"Overlord";"Larva";190;0
"Building";"CreepTumor";NA;190;0
"Building";"CreepTumor";NA;190;0
"Building";"CreepTumor";NA;190;0
"Building";"Extractor";NA;190;0
"Building";"Extractor";NA;190;0
"Unit";"Baneling";"Zergling";208;0
"Unit";"Baneling";"Zergling";208;0
"Unit";"Baneling";"Zergling";208;0
"Unit";"Baneling";"Zergling";208;0
"Unit";"Baneling";"Zergling";208;0
"Unit";"Baneling";"Zergling";208;0
"Unit";"Baneling";"Zergling";208;0
"Unit";"Overlord";"Larva";208;0
"Unit";"Overlord";"Larva";208;0
"Unit";"Hydralisk";"Larva";212;2
"Unit";"Hydralisk";"Larva";212;2
"Unit";"Hydralisk";"Larva";212;2
"Unit";"Hydralisk";"Larva";212;2
"Unit";"Hydralisk";"Larva";212;2
"Unit";"Zergling";"Larva";212;1
"Unit";"Zergling";"Larva";212;1
"Unit";"Zergling";"Larva";212;1
"Unit";"Zergling";"Larva";212;1
"Unit";"Zergling";"Larva";212;1
"Unit";"Zergling";"Larva";212;1
"Unit";"Zergling";"Larva";212;1
"Unit";"Zergling";"Larva";212;1
"Unit";"Zergling";"Larva";212;1
"Unit";"Zergling";"Larva";212;1
"Unit";"Zergling";"Larva";212;1
"Unit";"Zergling";"Larva";212;1
"Unit";"Zergling";"Larva";212;1
"Unit";"Zergling";"Larva";212;1
"Unit";"Zergling";"Larva";212;1
"Unit";"Zergling";"Larva";212;1
"Unit";"Zergling";"Larva";212;1
"Unit";"Zergling";"Larva";212;1
"Unit";"Zergling";"Larva";212;1
"Unit";"Zergling";"Larva";212;1
"Unit";"Zergling";"Larva";212;1
"Unit";"Zergling";"Larva";212;1
"Unit";"Zergling";"Larva";212;1
"Unit";"Zergling";"Larva";212;1
"Unit";"Zergling";"Larva";212;1
"Unit";"Zergling";"Larva";212;1
"Unit";"Zergling";"Larva";212;1
"Unit";"Zergling";"Larva";212;1
"Unit";"Zergling";"Larva";212;1
"Unit";"Zergling";"Larva";212;1
"Building";"CreepTumor";NA;222;0
"Building";"CreepTumor";NA;222;0
"Building";"CreepTumorQueen";NA;222;0
"Building";"CreepTumorQueen";NA;222;0
"Building";"CreepTumor";NA;222;0
"Building";"CreepTumorQueen";NA;222;0
"Building";"CreepTumor";NA;222;0
"Building";"CreepTumor";NA;222;0
"Building";"CreepTumor";NA;222;0
"Building";"CreepTumor";NA;222;0
"Building";"CreepTumor";NA;224;0
"Unit";"Overlord";"Larva";222;0
"Unit";"Overlord";"Larva";222;0
"Unit";"Hydralisk";"Larva";222;2
"Unit";"Hydralisk";"Larva";222;2
"Unit";"Hydralisk";"Larva";222;2
"Unit";"Hydralisk";"Larva";222;2
"Unit";"Hydralisk";"Larva";222;2
"Unit";"Hydralisk";"Larva";222;2
"Building";"InfestationPit";NA;212;0
"Unit";"Overlord";"Larva";252;0
"Unit";"Overlord";"Larva";252;0
"Unit";"Overlord";"Larva";252;0
"Unit";"Overlord";"Larva";252;0
"Unit";"Overlord";"Larva";252;0
"Unit";"Hydralisk";"Larva";252;2
"Unit";"Hydralisk";"Larva";252;2
"Upgrade";"EvolveGroovedSpines";"HydraliskDen";212;0
"Unit";"Baneling";"Zergling";268;0
"Unit";"Zergling";"Larva";268;1
"Unit";"Zergling";"Larva";268;1
"Unit";"Baneling";"Zergling";268;0
"Unit";"Baneling";"Zergling";268;0
"Unit";"Baneling";"Zergling";268;0
"Unit";"Baneling";"Zergling";268;0
"Unit";"Zergling";"Larva";268;1
"Unit";"Zergling";"Larva";268;1
"Unit";"Zergling";"Larva";268;1
"Unit";"Zergling";"Larva";268;1
"Unit";"Zergling";"Larva";268;1
"Unit";"Zergling";"Larva";268;1
"Unit";"Zergling";"Larva";268;1
"Unit";"Zergling";"Larva";268;1
"Unit";"Baneling";"Zergling";268;0
"Unit";"Baneling";"Zergling";268;0
"Unit";"Baneling";"Zergling";268;0
"Unit";"Zergling";"Larva";268;1
"Unit";"Zergling";"Larva";268;1
"Unit";"Zergling";"Larva";268;1
"Unit";"Zergling";"Larva";268;1
"Unit";"Zergling";"Larva";268;1
"Unit";"Zergling";"Larva";268;1
"Unit";"Zergling";"Larva";268;1
"Unit";"Zergling";"Larva";268;1
"Unit";"Baneling";"Zergling";268;0
"Unit";"Baneling";"Zergling";268;0
"Unit";"Baneling";"Zergling";268;0
"Unit";"Baneling";"Zergling";268;0
"Unit";"Zergling";"Larva";268;1
"Unit";"Zergling";"Larva";268;1
"Unit";"Zergling";"Larva";268;1
"Unit";"Zergling";"Larva";268;1
"Unit";"Baneling";"Zergling";268;0
"Unit";"Baneling";"Zergling";268;0
"Unit";"Baneling";"Zergling";268;0
"Unit";"Baneling";"Zergling";268;0
"Unit";"Baneling";"Zergling";268;0
"Unit";"Hydralisk";"Larva";268;2
"Unit";"Hydralisk";"Larva";268;2
"Unit";"Zergling";"Larva";268;1
"Unit";"Zergling";"Larva";268;1
"Unit";"Zergling";"Larva";268;1
"Unit";"Zergling";"Larva";268;1
"Unit";"Zergling";"Larva";268;1
"Unit";"Zergling";"Larva";268;1
"Unit";"Zergling";"Larva";268;1
"Unit";"Zergling";"Larva";268;1
"Unit";"Zergling";"Larva";268;1
"Unit";"Zergling";"Larva";268;1
"Unit";"Zergling";"Larva";268;1
"Unit";"Zergling";"Larva";268;1
"Unit";"Zergling";"Larva";268;1
"Unit";"Zergling";"Larva";268;1
"Unit";"Zergling";"Larva";268;1
"Unit";"Zergling";"Larva";268;1
"Unit";"Zergling";"Larva";268;1
"Unit";"Zergling";"Larva";268;1
"Unit";"Zergling";"Larva";268;1
"Unit";"Zergling";"Larva";268;1
"Building";"Hatchery";NA;252;0
"Unit";"Zergling";"Larva";294;1
"Unit";"Zergling";"Larva";294;1
"Unit";"Zergling";"Larva";294;1
"Unit";"Zergling";"Larva";294;1
"Building";"CreepTumorQueen";NA;314;0
"Unit";"Hydralisk";"Larva";294;2
"Unit";"Hydralisk";"Larva";294;2
"Building";"CreepTumorQueen";NA;314;0
"Unit";"Zergling";"Larva";314;1
"Unit";"Zergling";"Larva";314;1
"Unit";"Zergling";"Larva";314;1
"Unit";"Zergling";"Larva";314;1
"Unit";"Zergling";"Larva";314;1
"Unit";"Zergling";"Larva";314;1
"Unit";"Zergling";"Larva";314;1
"Unit";"Zergling";"Larva";314;1
"Unit";"Zergling";"Larva";314;1
"Unit";"Zergling";"Larva";314;1
"Unit";"Zergling";"Larva";314;1
"Unit";"Zergling";"Larva";314;1
"Unit";"Zergling";"Larva";314;1
"Unit";"Zergling";"Larva";314;1
"Unit";"Zergling";"Larva";314;1
"Unit";"Zergling";"Larva";314;1
"Unit";"Zergling";"Larva";314;1
"Unit";"Zergling";"Larva";314;1
"Unit";"Baneling";"Zergling";318;0
"Unit";"Baneling";"Zergling";318;0
"Unit";"Baneling";"Zergling";318;0
"Unit";"Baneling";"Zergling";318;0
"Unit";"Baneling";"Zergling";318;0
"Unit";"Baneling";"Zergling";318;0
"Unit";"Baneling";"Zergling";318;0
"Unit";"Baneling";"Zergling";318;0
"Unit";"Baneling";"Zergling";318;0
"Unit";"Baneling";"Zergling";318;0
"Upgrade";"ZergGroundArmorsLevel2";"EvolutionChamber";252;0
"Upgrade";"ZergMeleeWeaponsLevel2";"EvolutionChamber";252;0
"Unit";"Zergling";"Larva";324;1
"Unit";"Zergling";"Larva";324;1
"Unit";"Zergling";"Larva";340;1
"Unit";"Zergling";"Larva";340;1
"Unit";"Zergling";"Larva";340;1
"Unit";"Zergling";"Larva";340;1
"Unit";"Zergling";"Larva";340;1
"Unit";"Zergling";"Larva";340;1
"Unit";"Zergling";"Larva";340;1
"Unit";"Zergling";"Larva";340;1
"Unit";"Zergling";"Larva";340;1
"Unit";"Zergling";"Larva";340;1
"Unit";"Zergling";"Larva";340;1
"Unit";"Zergling";"Larva";340;1
"Unit";"Zergling";"Larva";340;1
"Unit";"Zergling";"Larva";340;1
"Unit";"Zergling";"Larva";340;1
"Unit";"Zergling";"Larva";340;1
"Unit";"Zergling";"Larva";340;1
"Unit";"Zergling";"Larva";340;1
"Unit";"Zergling";"Larva";340;1
"Unit";"Zergling";"Larva";340;1
"Unit";"Zergling";"Larva";340;1
"Unit";"Zergling";"Larva";340;1
"Unit";"Zergling";"Larva";340;1
"Unit";"Zergling";"Larva";340;1
"Unit";"Zergling";"Larva";340;1
"Unit";"Zergling";"Larva";340;1
"Unit";"Hydralisk";"Larva";340;2
"Unit";"Hydralisk";"Larva";340;2
"Unit";"Hydralisk";"Larva";340;2
"Unit";"Hydralisk";"Larva";340;2
"Upgrade";"EvolveMuscularAugments";"HydraliskDen";340;0
"Building";"CreepTumor";NA;395;0
"Building";"CreepTumor";NA;395;0
"Building";"CreepTumor";NA;395;0
"Unit";"Baneling";"Zergling";395;0
"Unit";"Baneling";"Zergling";395;0
"Unit";"Baneling";"Zergling";395;0
"Unit";"Baneling";"Zergling";395;0
"Unit";"Baneling";"Zergling";395;0
"Unit";"Zergling";"Larva";395;1
"Unit";"Zergling";"Larva";395;1
"Unit";"Baneling";"Zergling";395;0
"Unit";"Baneling";"Zergling";395;0
"Unit";"Zergling";"Larva";395;1
"Unit";"Zergling";"Larva";395;1
"Unit";"Zergling";"Larva";395;1
"Unit";"Zergling";"Larva";395;1
"Unit";"Zergling";"Larva";395;1
"Unit";"Zergling";"Larva";395;1
"Unit";"Zergling";"Larva";395;1
"Unit";"Zergling";"Larva";395;1
"Unit";"Zergling";"Larva";395;1
"Unit";"Zergling";"Larva";395;1
"Unit";"Zergling";"Larva";395;1
"Unit";"Zergling";"Larva";395;1
"Unit";"Zergling";"Larva";395;1
"Unit";"Zergling";"Larva";395;1
"Unit";"Zergling";"Larva";395;1
"Unit";"Zergling";"Larva";395;1
"Unit";"Zergling";"Larva";395;1
"Unit";"Zergling";"Larva";395;1
"Unit";"Zergling";"Larva";395;1
"Unit";"Zergling";"Larva";395;1
"Building";"CreepTumor";NA;395;0
"Building";"CreepTumor";NA;395;0
"Building";"CreepTumor";NA;417;0
"Building";"CreepTumor";NA;417;0
"Building";"CreepTumor";NA;417;0
"Building";"CreepTumorQueen";NA;417;0
"Building";"CreepTumorQueen";NA;417;0
"Building";"CreepTumorQueen";NA;417;0
"Building";"CreepTumor";NA;420;0
"Building";"UltraliskCavern";NA;395;0
"Building";"CreepTumor";NA;420;0
"Building";"CreepTumor";NA;420;0
"Building";"CreepTumor";NA;420;0
"Building";"CreepTumor";NA;420;0
"Building";"SporeCrawler";NA;417;0
"Unit";"Queen";"Hatchery";417;2
"Building";"SpineCrawler";NA;417;0
"Building";"SpineCrawler";NA;417;0
"Building";"SporeCrawler";NA;422;0
"Unit";"Overlord";"Larva";422;0
"Unit";"Overlord";"Larva";422;0
"Building";"SporeCrawler";NA;422;0
"Unit";"Overlord";"Larva";422;0
"Unit";"Overlord";"Larva";422;0
"Building";"SpineCrawler";NA;422;0
"Building";"SpineCrawler";NA;422;0
"Unit";"Zergling";"Larva";422;1
"Unit";"Zergling";"Larva";422;1
"Unit";"Zergling";"Larva";422;1
"Unit";"Zergling";"Larva";422;1
"Building";"SpineCrawler";NA;422;0
"Unit";"Ultralisk";"Larva";422;6
"Unit";"Ultralisk";"Larva";422;6
"Unit";"Ultralisk";"Larva";422;6
"Unit";"Overlord";"Larva";422;0
"Building";"SporeCrawler";NA;422;0
"Building";"Hatchery";NA;422;0
"Unit";"Zergling";"Larva";444;1
"Unit";"Zergling";"Larva";444;1
"Unit";"Zergling";"Larva";444;1
"Unit";"Zergling";"Larva";444;1
"Unit";"Zergling";"Larva";444;1
"Unit";"Zergling";"Larva";444;1
"Unit";"Zergling";"Larva";444;1
"Unit";"Zergling";"Larva";444;1
"Unit";"Zergling";"Larva";444;1
"Unit";"Zergling";"Larva";444;1
"Building";"SpineCrawler";NA;422;0
"Unit";"Ultralisk";"Larva";422;6
"Unit";"Ultralisk";"Larva";422;6
"Unit";"Ultralisk";"Larva";444;6
"Unit";"Ultralisk";"Larva";444;6
"Unit";"Ultralisk";"Larva";444;6
"Unit";"Zergling";"Larva";454;1
"Unit";"Zergling";"Larva";454;1
"Unit";"Zergling";"Larva";466;1
"Unit";"Zergling";"Larva";466;1
"Unit";"Zergling";"Larva";466;1
"Unit";"Zergling";"Larva";466;1
"Unit";"Zergling";"Larva";466;1
"Unit";"Zergling";"Larva";466;1
"Unit";"Zergling";"Larva";466;1
"Unit";"Zergling";"Larva";466;1
"Unit";"Zergling";"Larva";466;1
"Unit";"Zergling";"Larva";466;1
"Unit";"Zergling";"Larva";466;1
"Unit";"Zergling";"Larva";466;1
"Unit";"Zergling";"Larva";466;1
"Unit";"Zergling";"Larva";466;1
"Unit";"Zergling";"Larva";466;1
"Unit";"Zergling";"Larva";466;1
"Unit";"Zergling";"Larva";466;1
"Unit";"Zergling";"Larva";466;1
"Unit";"Zergling";"Larva";466;1
"Unit";"Zergling";"Larva";466;1
"Unit";"Zergling";"Larva";466;1
"Unit";"Zergling";"Larva";466;1
"Unit";"Zergling";"Larva";466;1
"Unit";"Zergling";"Larva";466;1
"Unit";"Zergling";"Larva";466;1
"Unit";"Zergling";"Larva";466;1
"Unit";"Zergling";"Larva";466;1
"Unit";"Zergling";"Larva";466;1
"Unit";"Zergling";"Larva";466;1
"Unit";"Zergling";"Larva";466;1
"Unit";"Zergling";"Larva";466;1
"Unit";"Zergling";"Larva";466;1
