"type";"unit_name";"on_building";"total_supply";"supply"
"Unit";"Overlord";"Larva";12;0
"Building";"Extractor";NA;17;0
"Building";"Hatchery";NA;17;0
"Building";"SpawningPool";NA;19;0
"Unit";"Zergling";"Larva";24;1
"Unit";"Zergling";"Larva";24;1
"Unit";"Zergling";"Larva";24;1
"Unit";"Zergling";"Larva";24;1
"Unit";"Overlord";"Larva";24;0
"Unit";"Queen";"Hatchery";24;2
"Unit";"Queen";"Hatchery";24;2
"Unit";"Overlord";"Larva";36;0
"Unit";"Queen";"Hatchery";29;2
"Unit";"Queen";"Hatchery";31;2
"Unit";"Overlord";"Larva";37;0
"Building";"CreepTumorQueen";NA;49;0
"Unit";"Overlord";"Larva";54;0
"Building";"CreepTumorQueen";NA;54;0
"Building";"CreepTumorQueen";NA;54;0
"Building";"CreepTumor";NA;54;0
"Building";"CreepTumorQueen";NA;54;0
"Unit";"Queen";"Hatchery";49;2
"Unit";"Queen";"Hatchery";50;2
"Unit";"Zergling";"Larva";54;1
"Unit";"Zergling";"Larva";54;1
"Unit";"Zergling";"Larva";54;1
"Unit";"Zergling";"Larva";54;1
"Unit";"Zergling";"Larva";54;1
"Unit";"Zergling";"Larva";54;1
"Unit";"Zergling";"Larva";54;1
"Unit";"Zergling";"Larva";54;1
"Unit";"Zergling";"Larva";54;1
"Unit";"Zergling";"Larva";54;1
"Unit";"Zergling";"Larva";54;1
"Unit";"Zergling";"Larva";54;1
"Unit";"Zergling";"Larva";54;1
"Unit";"Zergling";"Larva";54;1
"Unit";"Zergling";"Larva";54;1
"Unit";"Zergling";"Larva";54;1
"Building";"CreepTumor";NA;58;0
"Building";"Hatchery";NA;46;0
"Building";"CreepTumor";NA;58;0
"Building";"CreepTumor";NA;58;0
"Building";"Extractor";NA;54;0
"Building";"Extractor";NA;56;0
"Building";"CreepTumorQueen";NA;74;0
"Building";"CreepTumorQueen";NA;74;0
"Building";"CreepTumorQueen";NA;74;0
"Building";"CreepTumorQueen";NA;74;0
"Unit";"Overlord";"Larva";74;0
"Unit";"Overlord";"Larva";74;0
"Building";"CreepTumor";NA;74;0
"Unit";"Queen";"Hatchery";56;2
"Unit";"Overlord";"Larva";74;0
"Building";"CreepTumor";NA;80;0
"Building";"CreepTumor";NA;80;0
"Building";"CreepTumor";NA;80;0
"Building";"CreepTumor";NA;80;0
"Building";"CreepTumor";NA;80;0
"Building";"CreepTumor";NA;80;0
"Building";"CreepTumor";NA;80;0
"Unit";"Queen";"Hatchery";74;2
"Building";"EvolutionChamber";NA;79;0
"Building";"EvolutionChamber";NA;80;0
"Building";"BanelingNest";NA;74;0
"Unit";"Queen";"Hatchery";74;2
"Building";"CreepTumorQueen";NA;92;0
"Building";"CreepTumorQueen";NA;92;0
"Unit";"Overlord";"Larva";89;0
"Building";"CreepTumor";NA;97;0
"Unit";"Baneling";"Zergling";95;0
"Unit";"Baneling";"Zergling";95;0
"Building";"CreepTumor";NA;97;0
"Unit";"Baneling";"Zergling";95;0
"Unit";"Baneling";"Zergling";95;0
"Building";"CreepTumor";NA;97;0
"Building";"CreepTumor";NA;97;0
"Building";"CreepTumor";NA;97;0
"Building";"CreepTumor";NA;97;0
"Building";"CreepTumorQueen";NA;97;0
"Building";"CreepTumorQueen";NA;97;0
"Building";"CreepTumorQueen";NA;97;0
"Unit";"Zergling";"Larva";97;1
"Unit";"Zergling";"Larva";97;1
"Unit";"Zergling";"Larva";97;1
"Unit";"Zergling";"Larva";97;1
"Unit";"Zergling";"Larva";97;1
"Unit";"Zergling";"Larva";97;1
"Unit";"Zergling";"Larva";97;1
"Unit";"Zergling";"Larva";97;1
"Unit";"Zergling";"Larva";97;1
"Unit";"Zergling";"Larva";97;1
"Unit";"Zergling";"Larva";97;1
"Unit";"Zergling";"Larva";97;1
"Unit";"Zergling";"Larva";97;1
"Unit";"Zergling";"Larva";97;1
"Unit";"Zergling";"Larva";97;1
"Unit";"Zergling";"Larva";97;1
"Unit";"Zergling";"Larva";97;1
"Unit";"Zergling";"Larva";97;1
"Unit";"Zergling";"Larva";97;1
"Unit";"Zergling";"Larva";97;1
"Unit";"Zergling";"Larva";97;1
"Unit";"Zergling";"Larva";97;1
"Building";"CreepTumorQueen";NA;103;0
"Unit";"Zergling";"Larva";103;1
"Unit";"Zergling";"Larva";103;1
"Unit";"Zergling";"Larva";103;1
"Unit";"Zergling";"Larva";103;1
"Unit";"Zergling";"Larva";103;1
"Unit";"Zergling";"Larva";103;1
"Unit";"Zergling";"Larva";103;1
"Unit";"Zergling";"Larva";103;1
"Unit";"Zergling";"Larva";103;1
"Unit";"Zergling";"Larva";103;1
"Unit";"Zergling";"Larva";103;1
"Unit";"Zergling";"Larva";103;1
"Unit";"Overlord";"Larva";123;0
"Unit";"Overlord";"Larva";123;0
"Building";"CreepTumor";NA;123;0
"Building";"CreepTumor";NA;123;0
"Building";"CreepTumor";NA;123;0
"Building";"CreepTumor";NA;125;0
"Building";"CreepTumor";NA;127;0
"Building";"CreepTumor";NA;135;0
"Unit";"Queen";"Hatchery";103;2
"Unit";"Baneling";"Zergling";135;0
"Unit";"Baneling";"Zergling";135;0
"Unit";"Baneling";"Zergling";135;0
"Unit";"Baneling";"Zergling";135;0
"Unit";"Baneling";"Zergling";135;0
"Unit";"Baneling";"Zergling";135;0
"Unit";"Baneling";"Zergling";135;0
"Unit";"Baneling";"Zergling";135;0
"Unit";"Baneling";"Zergling";135;0
"Building";"CreepTumor";NA;135;0
"Building";"CreepTumor";NA;145;0
"Building";"CreepTumor";NA;145;0
"Building";"CreepTumor";NA;145;0
"Building";"CreepTumor";NA;145;0
"Unit";"Overlord";"Larva";139;0
"Building";"CreepTumor";NA;145;0
"Building";"CreepTumor";NA;145;0
"Building";"CreepTumor";NA;145;0
"Building";"CreepTumor";NA;145;0
"Upgrade";"ZergMeleeWeaponsLevel1";"EvolutionChamber";97;0
"Upgrade";"ZergGroundArmorsLevel1";"EvolutionChamber";97;0
"Unit";"Overlord";"Larva";145;0
"Unit";"Overlord";"Larva";145;0
"Unit";"Queen";"Hatchery";137;2
"Unit";"Queen";"Hatchery";137;2
"Building";"Extractor";NA;152;0
"Building";"Extractor";NA;152;0
"Unit";"Zergling";"Larva";152;1
"Unit";"Zergling";"Larva";152;1
"Unit";"Zergling";"Larva";152;1
"Unit";"Zergling";"Larva";152;1
"Unit";"Zergling";"Larva";152;1
"Unit";"Zergling";"Larva";152;1
"Unit";"Zergling";"Larva";152;1
"Unit";"Zergling";"Larva";152;1
"Unit";"Zergling";"Larva";152;1
"Unit";"Zergling";"Larva";152;1
"Building";"Extractor";NA;152;0
"Unit";"Overlord";"Larva";152;0
"Unit";"Zergling";"Larva";152;1
"Unit";"Zergling";"Larva";152;1
"Unit";"Zergling";"Larva";152;1
"Unit";"Zergling";"Larva";152;1
"Unit";"Zergling";"Larva";152;1
"Unit";"Zergling";"Larva";152;1
"Unit";"Zergling";"Larva";152;1
"Unit";"Zergling";"Larva";152;1
"Unit";"Zergling";"Larva";152;1
"Unit";"Zergling";"Larva";152;1
"Unit";"Zergling";"Larva";152;1
"Unit";"Zergling";"Larva";152;1
"Building";"Hatchery";NA;135;0
"Unit";"Overlord";"Larva";154;0
"Unit";"Overlord";"Larva";156;0
"Unit";"Zergling";"Larva";178;1
"Unit";"Zergling";"Larva";178;1
"Unit";"Zergling";"Larva";178;1
"Unit";"Zergling";"Larva";178;1
"Unit";"Zergling";"Larva";178;1
"Unit";"Zergling";"Larva";178;1
"Unit";"Zergling";"Larva";178;1
"Unit";"Zergling";"Larva";178;1
"Unit";"Zergling";"Larva";178;1
"Unit";"Zergling";"Larva";178;1
"Unit";"Zergling";"Larva";178;1
"Unit";"Zergling";"Larva";178;1
"Unit";"Zergling";"Larva";178;1
"Unit";"Zergling";"Larva";178;1
"Building";"CreepTumorQueen";NA;178;0
"Building";"CreepTumorQueen";NA;178;0
"Building";"CreepTumorQueen";NA;182;0
"Building";"CreepTumorQueen";NA;192;0
"Building";"CreepTumorQueen";NA;192;0
"Unit";"Zergling";"Larva";178;1
"Unit";"Zergling";"Larva";178;1
"Unit";"Zergling";"Larva";178;1
"Unit";"Zergling";"Larva";178;1
"Unit";"Zergling";"Larva";178;1
"Unit";"Zergling";"Larva";178;1
"Unit";"Zergling";"Larva";178;1
"Unit";"Zergling";"Larva";178;1
"Unit";"Zergling";"Larva";178;1
"Unit";"Zergling";"Larva";178;1
"Unit";"Zergling";"Larva";178;1
"Unit";"Zergling";"Larva";178;1
"Unit";"Zergling";"Larva";178;1
"Unit";"Zergling";"Larva";178;1
"Unit";"Baneling";"Zergling";192;0
"Unit";"Zergling";"Larva";178;1
"Unit";"Zergling";"Larva";178;1
"Unit";"Baneling";"Zergling";192;0
"Unit";"Zergling";"Larva";178;1
"Unit";"Zergling";"Larva";178;1
"Unit";"Baneling";"Zergling";192;0
"Unit";"Zergling";"Larva";178;1
"Unit";"Zergling";"Larva";178;1
"Unit";"Baneling";"Zergling";192;0
"Unit";"Queen";"Hatchery";178;2
"Unit";"Overlord";"Larva";192;0
"Unit";"Baneling";"Zergling";198;0
"Unit";"Baneling";"Zergling";200;0
"Unit";"Baneling";"Zergling";202;0
"Unit";"Zergling";"Larva";212;1
"Unit";"Zergling";"Larva";212;1
"Unit";"Zergling";"Larva";212;1
"Unit";"Zergling";"Larva";212;1
"Unit";"Zergling";"Larva";212;1
"Unit";"Zergling";"Larva";212;1
"Unit";"Zergling";"Larva";212;1
"Unit";"Zergling";"Larva";212;1
"Unit";"Zergling";"Larva";212;1
"Unit";"Zergling";"Larva";212;1
"Unit";"Zergling";"Larva";213;1
"Unit";"Zergling";"Larva";213;1
"Unit";"Zergling";"Larva";214;1
"Unit";"Zergling";"Larva";214;1
"Building";"CreepTumor";NA;218;0
"Unit";"Queen";"Hatchery";192;2
"Unit";"Zergling";"Larva";218;1
"Unit";"Zergling";"Larva";218;1
"Unit";"Zergling";"Larva";218;1
"Unit";"Zergling";"Larva";218;1
"Unit";"Zergling";"Larva";218;1
"Unit";"Zergling";"Larva";218;1
"Unit";"Zergling";"Larva";218;1
"Unit";"Zergling";"Larva";218;1
"Unit";"Overlord";"Larva";234;0
"Unit";"Zergling";"Larva";236;1
"Unit";"Zergling";"Larva";236;1
"Unit";"Overlord";"Larva";234;0
"Unit";"Zergling";"Larva";242;1
"Unit";"Zergling";"Larva";242;1
"Unit";"Zergling";"Larva";242;1
"Unit";"Zergling";"Larva";242;1
"Unit";"Zergling";"Larva";242;1
"Unit";"Zergling";"Larva";242;1
"Unit";"Zergling";"Larva";242;1
"Unit";"Zergling";"Larva";242;1
"Unit";"Zergling";"Larva";242;1
"Unit";"Zergling";"Larva";242;1
"Unit";"Zergling";"Larva";242;1
"Unit";"Zergling";"Larva";242;1
"Unit";"Zergling";"Larva";242;1
"Unit";"Zergling";"Larva";242;1
"Unit";"Zergling";"Larva";242;1
"Unit";"Zergling";"Larva";242;1
"Unit";"Zergling";"Larva";242;1
"Unit";"Zergling";"Larva";242;1
"Unit";"Zergling";"Larva";242;1
"Unit";"Zergling";"Larva";242;1
"Unit";"Zergling";"Larva";242;1
"Unit";"Zergling";"Larva";242;1
"Unit";"Overlord";"Larva";242;0
"Building";"InfestationPit";NA;232;0
"Unit";"Overlord";"Larva";242;0
"Building";"CreepTumorQueen";NA;268;0
"Unit";"Overlord";"Larva";242;0
"Building";"CreepTumorQueen";NA;268;0
"Building";"Hatchery";NA;192;0
"Unit";"Baneling";"Zergling";268;0
"Unit";"Baneling";"Zergling";268;0
"Upgrade";"ZergMeleeWeaponsLevel2";"EvolutionChamber";192;0
"Upgrade";"ZergGroundArmorsLevel2";"EvolutionChamber";192;0
"Unit";"Overlord";"Larva";277;0
"Unit";"Overlord";"Larva";277;0
"Unit";"Overlord";"Larva";277;0
"Building";"CreepTumorQueen";NA;277;0
"Building";"CreepTumorQueen";NA;277;0
"Building";"CreepTumorQueen";NA;277;0
"Building";"CreepTumor";NA;277;0
"Building";"CreepTumor";NA;277;0
"Building";"Extractor";NA;277;0
"Building";"CreepTumor";NA;277;0
"Building";"Extractor";NA;277;0
"Building";"CreepTumor";NA;277;0
"Building";"CreepTumorQueen";NA;277;0
"Building";"CreepTumorQueen";NA;277;0
"Building";"CreepTumor";NA;277;0
"Building";"CreepTumor";NA;277;0
"Unit";"Zergling";"Larva";277;1
"Unit";"Zergling";"Larva";277;1
"Unit";"Overlord";"Larva";277;0
"Unit";"Overlord";"Larva";277;0
"Building";"CreepTumor";NA;277;0
"Unit";"Zergling";"Larva";277;1
"Unit";"Zergling";"Larva";277;1
"Unit";"Zergling";"Larva";277;1
"Unit";"Zergling";"Larva";277;1
"Unit";"Zergling";"Larva";277;1
"Unit";"Zergling";"Larva";277;1
"Unit";"Zergling";"Larva";277;1
"Unit";"Zergling";"Larva";277;1
"Unit";"Zergling";"Larva";277;1
"Unit";"Zergling";"Larva";277;1
"Unit";"Zergling";"Larva";277;1
"Unit";"Zergling";"Larva";277;1
"Unit";"Zergling";"Larva";277;1
"Unit";"Zergling";"Larva";277;1
"Building";"CreepTumor";NA;277;0
"Unit";"Zergling";"Larva";277;1
"Unit";"Zergling";"Larva";277;1
"Unit";"Zergling";"Larva";277;1
"Unit";"Zergling";"Larva";277;1
"Unit";"Zergling";"Larva";277;1
"Unit";"Zergling";"Larva";277;1
"Unit";"Zergling";"Larva";277;1
"Unit";"Zergling";"Larva";277;1
"Unit";"Zergling";"Larva";277;1
"Unit";"Zergling";"Larva";277;1
"Unit";"Zergling";"Larva";277;1
"Unit";"Zergling";"Larva";277;1
"Unit";"Zergling";"Larva";277;1
"Unit";"Zergling";"Larva";277;1
"Unit";"Zergling";"Larva";277;1
"Unit";"Zergling";"Larva";277;1
"Unit";"Zergling";"Larva";277;1
"Unit";"Zergling";"Larva";277;1
"Unit";"Zergling";"Larva";277;1
"Unit";"Zergling";"Larva";277;1
"Unit";"Zergling";"Larva";277;1
"Unit";"Zergling";"Larva";277;1
"Unit";"Zergling";"Larva";277;1
"Unit";"Zergling";"Larva";277;1
"Unit";"Zergling";"Larva";277;1
"Unit";"Zergling";"Larva";277;1
"Building";"CreepTumorQueen";NA;277;0
"Unit";"Baneling";"Zergling";277;0
"Unit";"Baneling";"Zergling";277;0
"Unit";"Zergling";"Larva";319;1
"Unit";"Zergling";"Larva";319;1
"Unit";"Overlord";"Larva";289;0
"Unit";"Zergling";"Larva";319;1
"Unit";"Zergling";"Larva";319;1
"Unit";"Zergling";"Larva";319;1
"Unit";"Zergling";"Larva";319;1
"Unit";"Zergling";"Larva";319;1
"Unit";"Zergling";"Larva";319;1
"Unit";"Zergling";"Larva";319;1
"Unit";"Zergling";"Larva";319;1
"Unit";"Zergling";"Larva";319;1
"Unit";"Zergling";"Larva";319;1
"Unit";"Zergling";"Larva";319;1
"Unit";"Zergling";"Larva";319;1
"Unit";"Zergling";"Larva";319;1
"Unit";"Zergling";"Larva";319;1
"Unit";"Zergling";"Larva";319;1
"Unit";"Zergling";"Larva";319;1
"Unit";"Zergling";"Larva";319;1
"Unit";"Zergling";"Larva";319;1
"Unit";"Zergling";"Larva";319;1
"Unit";"Zergling";"Larva";319;1
"Unit";"Zergling";"Larva";319;1
"Unit";"Zergling";"Larva";319;1
"Unit";"Zergling";"Larva";319;1
"Unit";"Zergling";"Larva";319;1
"Unit";"Zergling";"Larva";319;1
"Unit";"Zergling";"Larva";319;1
"Unit";"Zergling";"Larva";319;1
"Unit";"Zergling";"Larva";319;1
"Unit";"Zergling";"Larva";319;1
"Unit";"Zergling";"Larva";319;1
"Building";"CreepTumor";NA;319;0
"Building";"CreepTumor";NA;354;0
"Building";"CreepTumor";NA;354;0
"Building";"CreepTumor";NA;354;0
"Building";"CreepTumor";NA;354;0
"Building";"CreepTumor";NA;354;0
"Building";"CreepTumor";NA;354;0
"Building";"CreepTumor";NA;354;0
"Building";"CreepTumor";NA;354;0
"Building";"CreepTumor";NA;354;0
"Building";"CreepTumor";NA;354;0
"Unit";"Overlord";"Larva";354;0
"Unit";"Overlord";"Larva";354;0
"Unit";"Baneling";"Zergling";354;0
"Unit";"Baneling";"Zergling";354;0
"Unit";"Baneling";"Zergling";354;0
"Unit";"Baneling";"Zergling";354;0
"Unit";"Baneling";"Zergling";354;0
"Unit";"Baneling";"Zergling";354;0
"Unit";"Baneling";"Zergling";354;0
"Unit";"Baneling";"Zergling";354;0
"Unit";"Baneling";"Zergling";354;0
"Unit";"Baneling";"Zergling";354;0
"Unit";"Baneling";"Zergling";354;0
"Unit";"Baneling";"Zergling";354;0
"Unit";"Baneling";"Zergling";354;0
"Unit";"Baneling";"Zergling";354;0
"Unit";"Baneling";"Zergling";354;0
"Unit";"Baneling";"Zergling";354;0
"Unit";"Baneling";"Zergling";354;0
"Unit";"Baneling";"Zergling";354;0
"Unit";"Baneling";"Zergling";354;0
"Unit";"Baneling";"Zergling";354;0
"Unit";"Baneling";"Zergling";354;0
"Unit";"Baneling";"Zergling";354;0
"Building";"CreepTumor";NA;354;0
"Unit";"Zergling";"Larva";354;1
"Unit";"Zergling";"Larva";354;1
"Building";"CreepTumor";NA;354;0
"Unit";"Zergling";"Larva";354;1
"Unit";"Zergling";"Larva";354;1
"Building";"CreepTumor";NA;354;0
"Unit";"Zergling";"Larva";354;1
"Unit";"Zergling";"Larva";354;1
"Unit";"Zergling";"Larva";354;1
"Unit";"Zergling";"Larva";354;1
"Unit";"Zergling";"Larva";354;1
"Unit";"Zergling";"Larva";354;1
"Unit";"Zergling";"Larva";354;1
"Unit";"Zergling";"Larva";354;1
"Unit";"Zergling";"Larva";354;1
"Unit";"Zergling";"Larva";354;1
"Unit";"Zergling";"Larva";354;1
"Unit";"Zergling";"Larva";354;1
"Unit";"Zergling";"Larva";354;1
"Unit";"Zergling";"Larva";354;1
"Unit";"Zergling";"Larva";354;1
"Unit";"Zergling";"Larva";354;1
"Unit";"Zergling";"Larva";354;1
"Unit";"Zergling";"Larva";354;1
"Unit";"Zergling";"Larva";354;1
"Unit";"Zergling";"Larva";354;1
"Unit";"Zergling";"Larva";354;1
"Unit";"Zergling";"Larva";354;1
"Unit";"Zergling";"Larva";354;1
"Unit";"Zergling";"Larva";354;1
"Unit";"Zergling";"Larva";354;1
"Unit";"Zergling";"Larva";354;1
"Unit";"Zergling";"Larva";354;1
"Unit";"Zergling";"Larva";354;1
"Unit";"Zergling";"Larva";354;1
"Unit";"Zergling";"Larva";354;1
"Building";"CreepTumor";NA;354;0
"Building";"CreepTumor";NA;354;0
"Building";"CreepTumor";NA;354;0
"Building";"CreepTumor";NA;359;0
"Building";"CreepTumor";NA;361;0
"Building";"CreepTumor";NA;369;0
"Building";"UltraliskCavern";NA;354;0
"Building";"Hatchery";NA;354;0
"Unit";"Zergling";"Larva";403;1
"Unit";"Zergling";"Larva";403;1
"Unit";"Zergling";"Larva";403;1
"Unit";"Zergling";"Larva";403;1
"Unit";"Zergling";"Larva";403;1
"Unit";"Zergling";"Larva";403;1
"Unit";"Zergling";"Larva";403;1
"Unit";"Zergling";"Larva";403;1
"Unit";"Zergling";"Larva";403;1
"Unit";"Zergling";"Larva";403;1
"Unit";"Zergling";"Larva";403;1
"Unit";"Zergling";"Larva";403;1
"Unit";"Zergling";"Larva";403;1
"Unit";"Zergling";"Larva";403;1
"Unit";"Zergling";"Larva";403;1
"Unit";"Zergling";"Larva";403;1
"Unit";"Zergling";"Larva";403;1
"Unit";"Zergling";"Larva";403;1
"Unit";"Zergling";"Larva";403;1
"Unit";"Zergling";"Larva";403;1
"Unit";"Zergling";"Larva";403;1
"Unit";"Zergling";"Larva";403;1
"Unit";"Zergling";"Larva";403;1
"Unit";"Zergling";"Larva";403;1
"Unit";"Zergling";"Larva";403;1
"Unit";"Zergling";"Larva";403;1
"Unit";"Zergling";"Larva";403;1
"Unit";"Zergling";"Larva";403;1
"Unit";"Zergling";"Larva";403;1
"Unit";"Zergling";"Larva";403;1
"Unit";"Ultralisk";"Larva";403;6
"Unit";"Ultralisk";"Larva";403;6
"Unit";"Ultralisk";"Larva";403;6
"Unit";"Ultralisk";"Larva";403;6
"Building";"Spire";NA;403;0
"Building";"Spire";NA;403;0
"Unit";"Ultralisk";"Larva";433;6
"Building";"Extractor";NA;433;0
"Unit";"Ultralisk";"Larva";433;6
"Building";"Extractor";NA;433;0
"Unit";"Infestor";"Larva";433;2
"Unit";"Infestor";"Larva";433;2
"Unit";"Infestor";"Larva";433;2
"Unit";"Infestor";"Larva";433;2
"Unit";"Infestor";"Larva";433;2
"Unit";"Infestor";"Larva";433;2
"Unit";"Zergling";"Larva";457;1
"Unit";"Zergling";"Larva";457;1
"Unit";"Zergling";"Larva";457;1
"Unit";"Zergling";"Larva";457;1
"Unit";"Zergling";"Larva";457;1
"Unit";"Zergling";"Larva";457;1
"Unit";"Zergling";"Larva";457;1
"Unit";"Zergling";"Larva";457;1
"Unit";"Zergling";"Larva";457;1
"Unit";"Zergling";"Larva";457;1
"Unit";"Zergling";"Larva";457;1
"Unit";"Zergling";"Larva";457;1
"Unit";"Zergling";"Larva";457;1
"Unit";"Zergling";"Larva";457;1
"Unit";"Zergling";"Larva";457;1
"Unit";"Zergling";"Larva";457;1
"Unit";"Zergling";"Larva";457;1
"Unit";"Zergling";"Larva";457;1
"Unit";"Zergling";"Larva";457;1
"Unit";"Zergling";"Larva";457;1
"Unit";"Zergling";"Larva";457;1
"Unit";"Zergling";"Larva";457;1
"Unit";"Zergling";"Larva";457;1
"Unit";"Zergling";"Larva";457;1
"Building";"CreepTumor";NA;457;0
"Building";"CreepTumor";NA;457;0
"Building";"CreepTumor";NA;463;0
"Building";"CreepTumor";NA;469;0
"Unit";"Baneling";"Zergling";481;0
"Upgrade";"ChitinousPlating";"UltraliskCavern";433;0
"Unit";"Baneling";"Zergling";483;0
"Unit";"Baneling";"Zergling";483;0
"Unit";"Baneling";"Zergling";483;0
"Unit";"Baneling";"Zergling";485;0
"Unit";"Baneling";"Zergling";485;0
"Unit";"Baneling";"Zergling";485;0
"Unit";"Baneling";"Zergling";485;0
"Unit";"Baneling";"Zergling";485;0
"Unit";"Baneling";"Zergling";485;0
"Unit";"Baneling";"Zergling";485;0
"Unit";"Baneling";"Zergling";485;0
"Unit";"Baneling";"Zergling";485;0
"Unit";"Baneling";"Zergling";485;0
"Unit";"Baneling";"Zergling";485;0
"Unit";"Baneling";"Zergling";485;0
"Unit";"Baneling";"Zergling";485;0
"Unit";"Baneling";"Zergling";485;0
"Unit";"Ultralisk";"Larva";457;6
"Unit";"Ultralisk";"Larva";457;6
"Unit";"Ultralisk";"Larva";457;6
"Unit";"Zergling";"Larva";505;1
"Unit";"Zergling";"Larva";505;1
"Upgrade";"ZergMeleeWeaponsLevel3";"EvolutionChamber";403;0
"Upgrade";"ZergGroundArmorsLevel3";"EvolutionChamber";403;0
"Unit";"Zergling";"Larva";523;1
"Unit";"Zergling";"Larva";523;1
"Unit";"Zergling";"Larva";523;1
"Unit";"Zergling";"Larva";523;1
"Unit";"Zergling";"Larva";523;1
"Unit";"Zergling";"Larva";523;1
"Unit";"Zergling";"Larva";523;1
"Unit";"Zergling";"Larva";523;1
"Unit";"Zergling";"Larva";523;1
"Unit";"Zergling";"Larva";523;1
"Unit";"Zergling";"Larva";523;1
"Unit";"Zergling";"Larva";523;1
"Unit";"Zergling";"Larva";523;1
"Unit";"Zergling";"Larva";523;1
"Unit";"Zergling";"Larva";523;1
"Unit";"Zergling";"Larva";523;1
"Unit";"Zergling";"Larva";525;1
"Unit";"Zergling";"Larva";525;1
"Unit";"Zergling";"Larva";525;1
"Unit";"Zergling";"Larva";525;1
"Unit";"Zergling";"Larva";525;1
"Unit";"Zergling";"Larva";525;1
"Unit";"Zergling";"Larva";525;1
"Unit";"Zergling";"Larva";525;1
"Unit";"Zergling";"Larva";525;1
"Unit";"Zergling";"Larva";525;1
"Unit";"Zergling";"Larva";525;1
"Unit";"Zergling";"Larva";525;1
