"type";"unit_name";"on_building";"total_supply";"supply"
"Unit";"Overlord";"Larva";13;0
"Building";"Extractor";NA;18;0
"Unit";"Overlord";"Larva";21;0
"Building";"SpawningPool";NA;19;0
"Building";"Hatchery";NA;16;0
"Unit";"Zergling";"Larva";23;1
"Unit";"Zergling";"Larva";23;1
"Unit";"Zergling";"Larva";23;1
"Unit";"Zergling";"Larva";23;1
"Unit";"Queen";"Hatchery";23;2
"Unit";"Queen";"Hatchery";23;2
"Unit";"Overlord";"Larva";35;0
"Unit";"Queen";"Hatchery";33;2
"Building";"CreepTumorQueen";NA;42;0
"Unit";"Overlord";"Larva";40;0
"Unit";"Overlord";"Larva";44;0
"Unit";"Zergling";"Larva";44;1
"Unit";"Zergling";"Larva";44;1
"Unit";"Zergling";"Larva";44;1
"Unit";"Zergling";"Larva";44;1
"Unit";"Zergling";"Larva";44;1
"Unit";"Zergling";"Larva";44;1
"Unit";"Queen";"Hatchery";42;2
"Unit";"Queen";"Hatchery";42;2
"Building";"CreepTumorQueen";NA;46;0
"Unit";"Zergling";"Larva";46;1
"Unit";"Zergling";"Larva";46;1
"Building";"Hatchery";NA;35;0
"Unit";"Zergling";"Larva";46;1
"Unit";"Zergling";"Larva";46;1
"Building";"CreepTumor";NA;46;0
"Unit";"Overlord";"Larva";46;0
"Unit";"Overlord";"Larva";46;0
"Building";"CreepTumorQueen";NA;64;0
"Building";"CreepTumorQueen";NA;64;0
"Building";"CreepTumor";NA;66;0
"Building";"EvolutionChamber";NA;64;0
"Building";"CreepTumorQueen";NA;66;0
"Building";"EvolutionChamber";NA;66;0
"Building";"CreepTumor";NA;67;0
"Building";"CreepTumor";NA;67;0
"Building";"CreepTumorQueen";NA;71;0
"Unit";"Queen";"Hatchery";64;2
"Unit";"Overlord";"Larva";71;0
"Unit";"Zergling";"Larva";71;1
"Unit";"Zergling";"Larva";71;1
"Unit";"Zergling";"Larva";71;1
"Unit";"Zergling";"Larva";71;1
"Building";"CreepTumor";NA;77;0
"Unit";"Zergling";"Larva";77;1
"Unit";"Zergling";"Larva";77;1
"Unit";"Zergling";"Larva";77;1
"Unit";"Zergling";"Larva";77;1
"Unit";"Overlord";"Larva";79;0
"Unit";"Zergling";"Larva";79;1
"Unit";"Zergling";"Larva";79;1
"Unit";"Zergling";"Larva";79;1
"Unit";"Zergling";"Larva";79;1
"Unit";"Zergling";"Larva";79;1
"Unit";"Zergling";"Larva";79;1
"Unit";"Zergling";"Larva";79;1
"Unit";"Zergling";"Larva";79;1
"Building";"CreepTumor";NA;83;0
"Building";"CreepTumor";NA;83;0
"Building";"CreepTumor";NA;83;0
"Unit";"Overlord";"Larva";83;0
"Building";"CreepTumor";NA;87;0
"Building";"CreepTumor";NA;95;0
"Unit";"Zergling";"Larva";87;1
"Unit";"Zergling";"Larva";87;1
"Unit";"Zergling";"Larva";87;1
"Unit";"Zergling";"Larva";87;1
"Unit";"Zergling";"Larva";87;1
"Unit";"Zergling";"Larva";87;1
"Building";"CreepTumor";NA;95;0
"Upgrade";"Burrow";"Hatchery";71;0
"Unit";"Queen";"Hatchery";83;2
"Unit";"Overlord";"Larva";95;0
"Unit";"Zergling";"Larva";95;1
"Unit";"Zergling";"Larva";95;1
"Unit";"Zergling";"Larva";95;1
"Unit";"Zergling";"Larva";95;1
"Unit";"Zergling";"Larva";95;1
"Unit";"Zergling";"Larva";95;1
"Unit";"Zergling";"Larva";95;1
"Unit";"Zergling";"Larva";95;1
"Unit";"Queen";"Hatchery";83;2
"Building";"CreepTumorQueen";NA;101;0
"Building";"CreepTumorQueen";NA;101;0
"Building";"CreepTumorQueen";NA;111;0
"Unit";"Zergling";"Larva";101;1
"Unit";"Zergling";"Larva";101;1
"Building";"CreepTumor";NA;103;0
"Unit";"Zergling";"Larva";101;1
"Unit";"Zergling";"Larva";101;1
"Unit";"Zergling";"Larva";101;1
"Unit";"Zergling";"Larva";101;1
"Unit";"Zergling";"Larva";101;1
"Unit";"Zergling";"Larva";101;1
"Unit";"Zergling";"Larva";101;1
"Unit";"Zergling";"Larva";101;1
"Unit";"Zergling";"Larva";101;1
"Unit";"Zergling";"Larva";101;1
"Unit";"Zergling";"Larva";101;1
"Unit";"Zergling";"Larva";101;1
"Unit";"Zergling";"Larva";101;1
"Unit";"Zergling";"Larva";101;1
"Building";"CreepTumorQueen";NA;113;0
"Building";"CreepTumor";NA;115;0
"Building";"CreepTumor";NA;115;0
"Building";"CreepTumor";NA;115;0
"Building";"Extractor";NA;113;0
"Unit";"Overlord";"Larva";129;0
"Unit";"Overlord";"Larva";129;0
"Building";"CreepTumor";NA;135;0
"Building";"CreepTumor";NA;135;0
"Building";"CreepTumor";NA;135;0
"Building";"CreepTumor";NA;135;0
"Building";"CreepTumor";NA;135;0
"Unit";"Zergling";"Larva";135;1
"Unit";"Zergling";"Larva";135;1
"Unit";"Zergling";"Larva";135;1
"Unit";"Zergling";"Larva";135;1
"Unit";"Zergling";"Larva";135;1
"Unit";"Zergling";"Larva";135;1
"Unit";"Zergling";"Larva";135;1
"Unit";"Zergling";"Larva";135;1
"Unit";"Zergling";"Larva";135;1
"Unit";"Zergling";"Larva";135;1
"Unit";"Zergling";"Larva";135;1
"Unit";"Zergling";"Larva";135;1
"Unit";"Zergling";"Larva";135;1
"Unit";"Zergling";"Larva";135;1
"Building";"Extractor";NA;135;0
"Building";"CreepTumorQueen";NA;152;0
"Building";"CreepTumorQueen";NA;152;0
"Building";"CreepTumorQueen";NA;152;0
"Building";"CreepTumor";NA;152;0
"Building";"CreepTumor";NA;152;0
"Building";"EvolutionChamber";NA;135;0
"Building";"BanelingNest";NA;135;0
"Building";"CreepTumor";NA;157;0
"Unit";"Overlord";"Larva";157;0
"Building";"CreepTumor";NA;157;0
"Building";"CreepTumor";NA;157;0
"Building";"CreepTumor";NA;157;0
"Building";"Hatchery";NA;133;0
"Building";"Extractor";NA;157;0
"Building";"Extractor";NA;157;0
"Upgrade";"ZergGroundArmorsLevel1";"EvolutionChamber";135;0
"Building";"CreepTumor";NA;166;0
"Building";"CreepTumor";NA;166;0
"Building";"Extractor";NA;166;0
"Building";"CreepTumor";NA;171;0
"Building";"CreepTumor";NA;171;0
"Building";"CreepTumor";NA;171;0
"Building";"CreepTumorQueen";NA;174;0
"Building";"CreepTumor";NA;172;0
"Building";"CreepTumor";NA;173;0
"Building";"CreepTumor";NA;174;0
"Unit";"Overlord";"Larva";171;0
"Unit";"Overlord";"Larva";171;0
"Unit";"Zergling";"Larva";171;1
"Unit";"Zergling";"Larva";171;1
"Unit";"Zergling";"Larva";171;1
"Unit";"Zergling";"Larva";171;1
"Unit";"Zergling";"Larva";171;1
"Unit";"Zergling";"Larva";171;1
"Unit";"Zergling";"Larva";171;1
"Unit";"Zergling";"Larva";171;1
"Unit";"Zergling";"Larva";171;1
"Unit";"Zergling";"Larva";171;1
"Unit";"Zergling";"Larva";171;1
"Unit";"Zergling";"Larva";171;1
"Unit";"Zergling";"Larva";171;1
"Unit";"Zergling";"Larva";171;1
"Unit";"Zergling";"Larva";171;1
"Unit";"Zergling";"Larva";171;1
"Unit";"Zergling";"Larva";171;1
"Unit";"Zergling";"Larva";171;1
"Unit";"Zergling";"Larva";171;1
"Unit";"Zergling";"Larva";171;1
"Unit";"Zergling";"Larva";171;1
"Unit";"Zergling";"Larva";171;1
"Building";"CreepTumorQueen";NA;175;0
"Building";"CreepTumorQueen";NA;175;0
"Unit";"Baneling";"Zergling";197;0
"Unit";"Baneling";"Zergling";197;0
"Unit";"Baneling";"Zergling";197;0
"Unit";"Baneling";"Zergling";197;0
"Unit";"Baneling";"Zergling";197;0
"Unit";"Baneling";"Zergling";197;0
"Unit";"Baneling";"Zergling";197;0
"Unit";"Baneling";"Zergling";197;0
"Unit";"Baneling";"Zergling";197;0
"Unit";"Baneling";"Zergling";197;0
"Unit";"Baneling";"Zergling";197;0
"Unit";"Baneling";"Zergling";197;0
"Building";"Hatchery";NA;166;0
"Building";"CreepTumor";NA;197;0
"Building";"CreepTumor";NA;197;0
"Building";"CreepTumor";NA;198;0
"Unit";"Zergling";"Larva";198;1
"Unit";"Zergling";"Larva";198;1
"Unit";"Zergling";"Larva";198;1
"Unit";"Zergling";"Larva";198;1
"Unit";"Baneling";"Zergling";198;0
"Unit";"Zergling";"Larva";198;1
"Unit";"Zergling";"Larva";198;1
"Unit";"Baneling";"Zergling";198;0
"Unit";"Baneling";"Zergling";198;0
"Unit";"Baneling";"Zergling";198;0
"Unit";"Baneling";"Zergling";198;0
"Building";"CreepTumor";NA;211;0
"Building";"CreepTumor";NA;211;0
"Building";"CreepTumor";NA;211;0
"Building";"CreepTumor";NA;211;0
"Building";"CreepTumor";NA;211;0
"Upgrade";"ZergMeleeWeaponsLevel1";"EvolutionChamber";166;0
"Building";"CreepTumor";NA;211;0
"Building";"CreepTumor";NA;211;0
"Unit";"Overlord";"Larva";211;0
"Unit";"Overlord";"Larva";211;0
"Unit";"Zergling";"Larva";217;1
"Unit";"Zergling";"Larva";217;1
"Unit";"Zergling";"Larva";217;1
"Unit";"Zergling";"Larva";217;1
"Unit";"Zergling";"Larva";217;1
"Unit";"Zergling";"Larva";217;1
"Unit";"Zergling";"Larva";217;1
"Unit";"Zergling";"Larva";217;1
"Unit";"Zergling";"Larva";217;1
"Unit";"Zergling";"Larva";217;1
"Unit";"Zergling";"Larva";217;1
"Unit";"Zergling";"Larva";217;1
"Unit";"Zergling";"Larva";217;1
"Unit";"Zergling";"Larva";217;1
"Unit";"Zergling";"Larva";217;1
"Unit";"Zergling";"Larva";217;1
"Unit";"Zergling";"Larva";217;1
"Unit";"Zergling";"Larva";217;1
"Unit";"Zergling";"Larva";217;1
"Unit";"Zergling";"Larva";217;1
"Unit";"Zergling";"Larva";217;1
"Unit";"Zergling";"Larva";217;1
"Unit";"Zergling";"Larva";217;1
"Unit";"Zergling";"Larva";217;1
"Unit";"Zergling";"Larva";217;1
"Unit";"Zergling";"Larva";217;1
"Building";"Extractor";NA;217;0
"Unit";"Overlord";"Larva";217;0
"Unit";"Overlord";"Larva";217;0
"Unit";"Overlord";"Larva";217;0
"Building";"CreepTumor";NA;243;0
"Building";"CreepTumor";NA;243;0
"Building";"Extractor";NA;217;0
"Building";"Spire";NA;197;0
"Unit";"Mutalisk";"Larva";246;2
"Unit";"Mutalisk";"Larva";246;2
"Unit";"Mutalisk";"Larva";246;2
"Unit";"Mutalisk";"Larva";246;2
"Unit";"Mutalisk";"Larva";246;2
"Unit";"Mutalisk";"Larva";246;2
"Unit";"Mutalisk";"Larva";246;2
"Unit";"Queen";"Hatchery";246;2
"Unit";"Zergling";"Larva";246;1
"Unit";"Zergling";"Larva";246;1
"Unit";"Zergling";"Larva";246;1
"Unit";"Zergling";"Larva";246;1
"Unit";"Zergling";"Larva";246;1
"Unit";"Zergling";"Larva";246;1
"Unit";"Zergling";"Larva";246;1
"Unit";"Zergling";"Larva";246;1
"Unit";"Zergling";"Larva";246;1
"Unit";"Zergling";"Larva";246;1
"Unit";"Zergling";"Larva";246;1
"Unit";"Zergling";"Larva";246;1
"Unit";"Zergling";"Larva";246;1
"Unit";"Zergling";"Larva";246;1
"Unit";"Zergling";"Larva";246;1
"Unit";"Zergling";"Larva";246;1
"Unit";"Zergling";"Larva";246;1
"Unit";"Zergling";"Larva";246;1
"Unit";"Zergling";"Larva";246;1
"Unit";"Zergling";"Larva";246;1
"Unit";"Zergling";"Larva";246;1
"Unit";"Zergling";"Larva";246;1
"Unit";"Zergling";"Larva";246;1
"Unit";"Zergling";"Larva";246;1
"Unit";"Zergling";"Larva";246;1
"Unit";"Zergling";"Larva";246;1
"Unit";"Zergling";"Larva";246;1
"Unit";"Zergling";"Larva";246;1
"Unit";"Zergling";"Larva";246;1
"Unit";"Zergling";"Larva";246;1
"Unit";"Zergling";"Larva";246;1
"Unit";"Zergling";"Larva";246;1
"Unit";"Mutalisk";"Larva";246;2
"Unit";"Mutalisk";"Larva";246;2
"Unit";"Mutalisk";"Larva";262;2
"Unit";"Mutalisk";"Larva";262;2
"Unit";"Mutalisk";"Larva";262;2
"Unit";"Mutalisk";"Larva";262;2
"Building";"Hatchery";NA;246;0
"Building";"CreepTumor";NA;316;0
"Building";"CreepTumorQueen";NA;316;0
"Building";"CreepTumorQueen";NA;316;0
"Building";"CreepTumorQueen";NA;316;0
"Building";"CreepTumorQueen";NA;316;0
"Building";"CreepTumorQueen";NA;316;0
"Building";"Hatchery";NA;246;0
"Upgrade";"ZergGroundArmorsLevel2";"EvolutionChamber";243;0
"Unit";"Overlord";"Larva";316;0
"Unit";"Overlord";"Larva";316;0
"Unit";"Mutalisk";"Larva";316;2
"Unit";"Mutalisk";"Larva";316;2
"Unit";"Mutalisk";"Larva";316;2
"Unit";"Mutalisk";"Larva";316;2
"Unit";"Baneling";"Zergling";316;0
"Unit";"Zergling";"Larva";316;1
"Unit";"Zergling";"Larva";316;1
"Unit";"Baneling";"Zergling";316;0
"Unit";"Baneling";"Zergling";316;0
"Unit";"Baneling";"Zergling";316;0
"Unit";"Baneling";"Zergling";316;0
"Unit";"Baneling";"Zergling";316;0
"Unit";"Baneling";"Zergling";316;0
"Unit";"Baneling";"Zergling";316;0
"Unit";"Baneling";"Zergling";316;0
"Unit";"Zergling";"Larva";316;1
"Unit";"Zergling";"Larva";316;1
"Unit";"Zergling";"Larva";316;1
"Unit";"Zergling";"Larva";316;1
"Unit";"Zergling";"Larva";316;1
"Unit";"Zergling";"Larva";316;1
"Unit";"Zergling";"Larva";316;1
"Unit";"Zergling";"Larva";316;1
"Unit";"Zergling";"Larva";316;1
"Unit";"Zergling";"Larva";316;1
"Unit";"Zergling";"Larva";316;1
"Unit";"Zergling";"Larva";316;1
"Unit";"Zergling";"Larva";316;1
"Unit";"Zergling";"Larva";316;1
"Unit";"Zergling";"Larva";316;1
"Unit";"Zergling";"Larva";316;1
"Unit";"Zergling";"Larva";316;1
"Unit";"Zergling";"Larva";316;1
"Unit";"Zergling";"Larva";316;1
"Unit";"Zergling";"Larva";316;1
"Unit";"Zergling";"Larva";316;1
"Unit";"Zergling";"Larva";316;1
"Unit";"Zergling";"Larva";316;1
"Unit";"Zergling";"Larva";316;1
"Building";"InfestationPit";NA;313;0
"Building";"CreepTumor";NA;316;0
"Building";"CreepTumor";NA;316;0
"Building";"CreepTumor";NA;316;0
"Unit";"Baneling";"Zergling";316;0
"Unit";"Baneling";"Zergling";316;0
"Unit";"Baneling";"Zergling";316;0
"Unit";"Baneling";"Zergling";316;0
"Unit";"Baneling";"Zergling";316;0
"Unit";"Baneling";"Zergling";316;0
"Unit";"Baneling";"Zergling";316;0
"Unit";"Baneling";"Zergling";316;0
"Building";"CreepTumor";NA;324;0
"Building";"CreepTumor";NA;324;0
"Building";"CreepTumor";NA;324;0
"Building";"CreepTumor";NA;324;0
"Unit";"Zergling";"Larva";350;1
"Unit";"Zergling";"Larva";350;1
"Unit";"Zergling";"Larva";350;1
"Unit";"Zergling";"Larva";350;1
"Unit";"Zergling";"Larva";350;1
"Unit";"Zergling";"Larva";350;1
"Unit";"Zergling";"Larva";350;1
"Unit";"Zergling";"Larva";350;1
"Unit";"Zergling";"Larva";350;1
"Unit";"Zergling";"Larva";350;1
"Unit";"Zergling";"Larva";350;1
"Unit";"Zergling";"Larva";350;1
"Unit";"Zergling";"Larva";350;1
"Unit";"Zergling";"Larva";350;1
"Unit";"Zergling";"Larva";350;1
"Unit";"Zergling";"Larva";350;1
"Unit";"Zergling";"Larva";350;1
"Unit";"Zergling";"Larva";350;1
"Unit";"Zergling";"Larva";350;1
"Unit";"Zergling";"Larva";350;1
"Unit";"Zergling";"Larva";350;1
"Unit";"Zergling";"Larva";350;1
"Building";"CreepTumorQueen";NA;354;0
"Building";"CreepTumorQueen";NA;354;0
"Building";"CreepTumorQueen";NA;354;0
"Building";"CreepTumorQueen";NA;354;0
"Building";"CreepTumorQueen";NA;354;0
"Building";"CreepTumorQueen";NA;354;0
"Building";"CreepTumorQueen";NA;354;0
"Building";"CreepTumorQueen";NA;354;0
"Building";"CreepTumorQueen";NA;376;0
"Upgrade";"ZergMeleeWeaponsLevel2";"EvolutionChamber";282;0
"Unit";"Mutalisk";"Larva";354;2
"Unit";"Mutalisk";"Larva";354;2
"Unit";"Zergling";"Larva";376;1
"Unit";"Zergling";"Larva";376;1
"Unit";"Zergling";"Larva";376;1
"Unit";"Zergling";"Larva";376;1
"Building";"CreepTumor";NA;380;0
"Building";"CreepTumor";NA;380;0
"Building";"CreepTumor";NA;380;0
"Building";"CreepTumor";NA;380;0
"Building";"CreepTumor";NA;380;0
"Building";"CreepTumor";NA;380;0
"Building";"CreepTumor";NA;380;0
"Building";"CreepTumor";NA;380;0
"Building";"CreepTumor";NA;380;0
"Building";"CreepTumor";NA;384;0
"Building";"CreepTumor";NA;384;0
"Building";"CreepTumor";NA;384;0
"Building";"CreepTumorQueen";NA;384;0
"Unit";"Mutalisk";"Larva";380;2
"Building";"CreepTumorQueen";NA;384;0
"Unit";"Mutalisk";"Larva";380;2
"Unit";"Mutalisk";"Larva";380;2
"Unit";"Mutalisk";"Larva";380;2
"Unit";"Mutalisk";"Larva";380;2
"Unit";"Mutalisk";"Larva";380;2
"Building";"CreepTumorQueen";NA;384;0
"Building";"CreepTumorQueen";NA;384;0
"Building";"CreepTumorQueen";NA;384;0
"Building";"CreepTumor";NA;384;0
"Building";"CreepTumor";NA;384;0
"Unit";"Zergling";"Larva";396;1
"Unit";"Zergling";"Larva";396;1
"Unit";"Zergling";"Larva";396;1
"Unit";"Zergling";"Larva";396;1
"Unit";"Zergling";"Larva";396;1
"Unit";"Zergling";"Larva";396;1
"Unit";"Zergling";"Larva";396;1
"Unit";"Zergling";"Larva";396;1
"Unit";"Zergling";"Larva";396;1
"Unit";"Zergling";"Larva";396;1
"Unit";"Zergling";"Larva";396;1
"Unit";"Zergling";"Larva";396;1
"Unit";"Zergling";"Larva";396;1
"Unit";"Zergling";"Larva";396;1
"Unit";"Zergling";"Larva";396;1
"Unit";"Zergling";"Larva";396;1
"Unit";"Zergling";"Larva";396;1
"Unit";"Zergling";"Larva";396;1
"Unit";"Zergling";"Larva";396;1
"Unit";"Zergling";"Larva";396;1
"Unit";"Zergling";"Larva";396;1
"Unit";"Zergling";"Larva";396;1
"Unit";"Zergling";"Larva";396;1
"Unit";"Zergling";"Larva";396;1
"Unit";"Zergling";"Larva";396;1
"Unit";"Zergling";"Larva";396;1
"Unit";"Zergling";"Larva";396;1
"Unit";"Zergling";"Larva";396;1
"Unit";"Zergling";"Larva";396;1
"Unit";"Zergling";"Larva";396;1
"Unit";"Zergling";"Larva";396;1
"Unit";"Zergling";"Larva";396;1
"Unit";"Zergling";"Larva";396;1
"Unit";"Zergling";"Larva";396;1
"Unit";"Zergling";"Larva";396;1
"Unit";"Zergling";"Larva";396;1
"Unit";"Zergling";"Larva";396;1
"Unit";"Zergling";"Larva";396;1
"Unit";"Zergling";"Larva";396;1
"Unit";"Zergling";"Larva";396;1
"Unit";"Zergling";"Larva";396;1
"Unit";"Zergling";"Larva";396;1
"Unit";"Zergling";"Larva";396;1
"Unit";"Zergling";"Larva";396;1
"Unit";"Zergling";"Larva";396;1
"Unit";"Zergling";"Larva";396;1
"Unit";"Zergling";"Larva";396;1
"Unit";"Zergling";"Larva";396;1
"Unit";"Zergling";"Larva";396;1
"Unit";"Zergling";"Larva";396;1
"Unit";"Zergling";"Larva";396;1
"Unit";"Zergling";"Larva";396;1
"Unit";"Zergling";"Larva";396;1
"Unit";"Zergling";"Larva";396;1
"Unit";"Zergling";"Larva";396;1
"Unit";"Zergling";"Larva";396;1
"Unit";"Zergling";"Larva";396;1
"Unit";"Zergling";"Larva";396;1
"Unit";"Zergling";"Larva";396;1
"Unit";"Zergling";"Larva";396;1
"Unit";"Zergling";"Larva";396;1
"Unit";"Zergling";"Larva";396;1
"Building";"CreepTumor";NA;458;0
"Building";"CreepTumor";NA;458;0
"Unit";"Zergling";"Larva";458;1
"Unit";"Zergling";"Larva";458;1
"Unit";"Zergling";"Larva";458;1
"Unit";"Zergling";"Larva";458;1
"Unit";"Zergling";"Larva";458;1
"Unit";"Zergling";"Larva";458;1
"Unit";"Zergling";"Larva";458;1
"Unit";"Zergling";"Larva";458;1
"Unit";"Zergling";"Larva";458;1
"Unit";"Zergling";"Larva";458;1
"Unit";"Zergling";"Larva";458;1
"Unit";"Zergling";"Larva";458;1
"Unit";"Zergling";"Larva";458;1
"Unit";"Zergling";"Larva";458;1
"Unit";"Zergling";"Larva";458;1
"Unit";"Zergling";"Larva";458;1
"Unit";"Zergling";"Larva";458;1
"Unit";"Zergling";"Larva";458;1
"Unit";"Zergling";"Larva";458;1
"Unit";"Zergling";"Larva";458;1
"Unit";"Zergling";"Larva";458;1
"Unit";"Zergling";"Larva";458;1
"Unit";"Zergling";"Larva";458;1
"Unit";"Zergling";"Larva";458;1
"Unit";"Mutalisk";"Larva";440;2
"Unit";"Mutalisk";"Larva";448;2
"Unit";"Mutalisk";"Larva";458;2
"Unit";"Mutalisk";"Larva";458;2
"Building";"Extractor";NA;458;0
"Building";"Extractor";NA;458;0
"Unit";"Baneling";"Zergling";458;0
"Unit";"Baneling";"Zergling";458;0
"Unit";"Baneling";"Zergling";458;0
"Unit";"Baneling";"Zergling";458;0
"Unit";"Baneling";"Zergling";458;0
"Unit";"Baneling";"Zergling";458;0
"Unit";"Baneling";"Zergling";458;0
"Unit";"Baneling";"Zergling";458;0
"Unit";"Baneling";"Zergling";458;0
"Unit";"Baneling";"Zergling";458;0
"Unit";"Baneling";"Zergling";458;0
"Unit";"Baneling";"Zergling";458;0
"Unit";"Baneling";"Zergling";458;0
"Unit";"Baneling";"Zergling";458;0
"Unit";"Baneling";"Zergling";458;0
"Unit";"Baneling";"Zergling";458;0
"Unit";"Baneling";"Zergling";458;0
"Unit";"Baneling";"Zergling";458;0
"Unit";"Baneling";"Zergling";458;0
"Unit";"Baneling";"Zergling";458;0
"Unit";"Baneling";"Zergling";458;0
"Building";"CreepTumor";NA;458;0
"Building";"CreepTumor";NA;458;0
"Building";"CreepTumor";NA;468;0
"Building";"CreepTumor";NA;460;0
"Building";"CreepTumor";NA;482;0
"Building";"CreepTumor";NA;482;0
"Building";"CreepTumor";NA;482;0
"Building";"CreepTumor";NA;490;0
"Building";"CreepTumor";NA;490;0
"Building";"CreepTumor";NA;490;0
"Building";"CreepTumor";NA;490;0
"Building";"CreepTumor";NA;490;0
"Unit";"Zergling";"Larva";482;1
"Unit";"Zergling";"Larva";482;1
"Unit";"Zergling";"Larva";482;1
"Unit";"Zergling";"Larva";482;1
"Unit";"Zergling";"Larva";482;1
"Unit";"Zergling";"Larva";482;1
"Unit";"Zergling";"Larva";482;1
"Unit";"Zergling";"Larva";482;1
"Unit";"Zergling";"Larva";482;1
"Unit";"Zergling";"Larva";482;1
"Unit";"Zergling";"Larva";482;1
"Unit";"Zergling";"Larva";482;1
"Unit";"Zergling";"Larva";482;1
"Unit";"Zergling";"Larva";482;1
"Unit";"Zergling";"Larva";482;1
"Unit";"Zergling";"Larva";482;1
"Unit";"Zergling";"Larva";482;1
"Unit";"Zergling";"Larva";482;1
"Unit";"Zergling";"Larva";482;1
"Unit";"Zergling";"Larva";482;1
"Unit";"Zergling";"Larva";482;1
"Unit";"Zergling";"Larva";482;1
"Unit";"Zergling";"Larva";482;1
"Unit";"Zergling";"Larva";482;1
"Unit";"Zergling";"Larva";482;1
"Unit";"Zergling";"Larva";482;1
"Unit";"Zergling";"Larva";482;1
"Unit";"Zergling";"Larva";482;1
"Unit";"Zergling";"Larva";482;1
"Unit";"Zergling";"Larva";482;1
"Unit";"Zergling";"Larva";482;1
"Unit";"Zergling";"Larva";482;1
"Building";"UltraliskCavern";NA;424;0
"Building";"CreepTumor";NA;490;0
"Building";"CreepTumor";NA;490;0
"Unit";"Zergling";"Larva";522;1
"Unit";"Zergling";"Larva";522;1
"Unit";"Zergling";"Larva";522;1
"Unit";"Zergling";"Larva";522;1
"Unit";"Zergling";"Larva";522;1
"Unit";"Zergling";"Larva";522;1
"Building";"CreepTumor";NA;528;0
"Building";"CreepTumor";NA;528;0
"Building";"CreepTumor";NA;528;0
"Building";"CreepTumor";NA;528;0
"Building";"CreepTumor";NA;528;0
"Building";"CreepTumor";NA;528;0
"Building";"CreepTumor";NA;528;0
"Building";"Hatchery";NA;458;0
"Unit";"Ultralisk";"Larva";522;6
"Building";"CreepTumorQueen";NA;528;0
"Unit";"Ultralisk";"Larva";522;6
"Building";"CreepTumorQueen";NA;528;0
"Building";"CreepTumorQueen";NA;528;0
"Building";"CreepTumorQueen";NA;528;0
"Building";"CreepTumorQueen";NA;528;0
"Upgrade";"ChitinousPlating";"UltraliskCavern";528;0
"Building";"CreepTumor";NA;540;0
"Building";"CreepTumor";NA;540;0
"Unit";"Zergling";"Larva";540;1
"Unit";"Zergling";"Larva";540;1
"Building";"CreepTumor";NA;540;0
"Unit";"Zergling";"Larva";540;1
"Unit";"Zergling";"Larva";540;1
"Unit";"Zergling";"Larva";540;1
"Unit";"Zergling";"Larva";540;1
"Unit";"Zergling";"Larva";540;1
"Unit";"Zergling";"Larva";540;1
"Unit";"Zergling";"Larva";540;1
"Unit";"Zergling";"Larva";540;1
"Unit";"Zergling";"Larva";540;1
"Unit";"Zergling";"Larva";540;1
"Unit";"Zergling";"Larva";540;1
"Unit";"Zergling";"Larva";540;1
"Unit";"Zergling";"Larva";540;1
"Unit";"Zergling";"Larva";540;1
"Unit";"Zergling";"Larva";540;1
"Unit";"Zergling";"Larva";540;1
"Unit";"Zergling";"Larva";540;1
"Unit";"Zergling";"Larva";540;1
"Unit";"Zergling";"Larva";540;1
"Unit";"Zergling";"Larva";540;1
"Unit";"Zergling";"Larva";540;1
"Unit";"Zergling";"Larva";540;1
"Unit";"Zergling";"Larva";540;1
"Unit";"Zergling";"Larva";540;1
"Unit";"Zergling";"Larva";540;1
"Unit";"Zergling";"Larva";540;1
"Unit";"Zergling";"Larva";540;1
"Unit";"Zergling";"Larva";540;1
"Unit";"Zergling";"Larva";540;1
"Unit";"Zergling";"Larva";540;1
"Unit";"Zergling";"Larva";540;1
"Unit";"Zergling";"Larva";540;1
"Unit";"Zergling";"Larva";540;1
"Unit";"Zergling";"Larva";540;1
"Unit";"Zergling";"Larva";540;1
"Unit";"Zergling";"Larva";540;1
"Unit";"Zergling";"Larva";540;1
"Unit";"Zergling";"Larva";540;1
"Unit";"Zergling";"Larva";540;1
"Unit";"Zergling";"Larva";540;1
"Unit";"Zergling";"Larva";540;1
"Unit";"Zergling";"Larva";540;1
"Building";"CreepTumor";NA;540;0
"Building";"CreepTumor";NA;540;0
"Building";"CreepTumor";NA;540;0
"Building";"CreepTumor";NA;540;0
"Building";"CreepTumor";NA;540;0
"Building";"CreepTumor";NA;540;0
"Building";"CreepTumorQueen";NA;540;0
"Building";"CreepTumor";NA;540;0
"Building";"CreepTumor";NA;540;0
"Building";"CreepTumorQueen";NA;540;0
"Building";"CreepTumorQueen";NA;584;0
"Unit";"Ultralisk";"Larva";540;6
"Unit";"Ultralisk";"Larva";540;6
"Unit";"Ultralisk";"Larva";540;6
"Unit";"Ultralisk";"Larva";540;6
"Unit";"Ultralisk";"Larva";540;6
"Building";"Spire";NA;528;0
"Upgrade";"ZergMeleeWeaponsLevel3";"EvolutionChamber";522;0
"Upgrade";"ZergGroundArmorsLevel3";"EvolutionChamber";522;0
"Unit";"Baneling";"Zergling";584;0
"Unit";"Baneling";"Zergling";584;0
"Unit";"Baneling";"Zergling";584;0
"Unit";"Baneling";"Zergling";584;0
"Unit";"Baneling";"Zergling";584;0
"Unit";"Baneling";"Zergling";584;0
"Unit";"Baneling";"Zergling";584;0
"Unit";"Baneling";"Zergling";584;0
"Unit";"Baneling";"Zergling";584;0
"Unit";"Baneling";"Zergling";584;0
"Unit";"Baneling";"Zergling";584;0
"Unit";"Baneling";"Zergling";584;0
"Unit";"Baneling";"Zergling";584;0
"Unit";"Baneling";"Zergling";584;0
"Unit";"Baneling";"Zergling";584;0
"Upgrade";"ZergMissileWeaponsLevel1";"EvolutionChamber";540;0
"Unit";"Corruptor";"Larva";614;2
"Unit";"Corruptor";"Larva";614;2
"Unit";"Corruptor";"Larva";614;2
"Unit";"Corruptor";"Larva";614;2
"Unit";"Corruptor";"Larva";614;2
"Unit";"Corruptor";"Larva";614;2
"Unit";"Corruptor";"Larva";614;2
"Unit";"Corruptor";"Larva";614;2
"Unit";"Corruptor";"Larva";614;2
"Unit";"Corruptor";"Larva";614;2
"Unit";"Corruptor";"Larva";614;2
"Unit";"Corruptor";"Larva";614;2
"Unit";"Zergling";"Larva";614;1
"Unit";"Zergling";"Larva";614;1
"Unit";"Zergling";"Larva";614;1
"Unit";"Zergling";"Larva";614;1
"Unit";"Zergling";"Larva";614;1
"Unit";"Zergling";"Larva";614;1
"Unit";"Zergling";"Larva";614;1
"Unit";"Zergling";"Larva";614;1
"Unit";"Zergling";"Larva";614;1
"Unit";"Zergling";"Larva";614;1
"Unit";"Zergling";"Larva";614;1
"Unit";"Zergling";"Larva";614;1
"Unit";"Zergling";"Larva";614;1
"Unit";"Zergling";"Larva";614;1
"Unit";"Zergling";"Larva";614;1
"Unit";"Zergling";"Larva";614;1
"Unit";"Zergling";"Larva";614;1
"Unit";"Zergling";"Larva";614;1
"Unit";"Corruptor";"Larva";614;2
"Unit";"Corruptor";"Larva";614;2
"Unit";"Corruptor";"Larva";614;2
"Unit";"Corruptor";"Larva";614;2
"Building";"CreepTumor";NA;642;0
"Unit";"Zergling";"Larva";664;1
"Unit";"Zergling";"Larva";664;1
"Unit";"Zergling";"Larva";664;1
"Unit";"Zergling";"Larva";664;1
"Unit";"Zergling";"Larva";664;1
"Unit";"Zergling";"Larva";664;1
"Unit";"Zergling";"Larva";664;1
"Unit";"Zergling";"Larva";664;1
"Unit";"Zergling";"Larva";664;1
"Unit";"Zergling";"Larva";664;1
"Unit";"Zergling";"Larva";664;1
"Unit";"Zergling";"Larva";664;1
"Unit";"Zergling";"Larva";664;1
"Unit";"Zergling";"Larva";664;1
"Building";"CreepTumor";NA;664;0
"Building";"Extractor";NA;664;0
"Building";"Extractor";NA;664;0
"Building";"CreepTumor";NA;678;0
"Unit";"Zergling";"Larva";682;1
"Unit";"Zergling";"Larva";682;1
"Unit";"Zergling";"Larva";682;1
"Unit";"Zergling";"Larva";682;1
"Unit";"Zergling";"Larva";682;1
"Unit";"Zergling";"Larva";682;1
"Unit";"Zergling";"Larva";682;1
"Unit";"Zergling";"Larva";682;1
"Unit";"Zergling";"Larva";682;1
"Unit";"Zergling";"Larva";682;1
"Unit";"Zergling";"Larva";682;1
"Unit";"Zergling";"Larva";682;1
"Unit";"Zergling";"Larva";682;1
"Unit";"Zergling";"Larva";682;1
"Unit";"Zergling";"Larva";682;1
"Unit";"Zergling";"Larva";682;1
"Unit";"Zergling";"Larva";682;1
"Unit";"Zergling";"Larva";682;1
"Unit";"Zergling";"Larva";682;1
"Unit";"Zergling";"Larva";682;1
"Unit";"Zergling";"Larva";682;1
"Unit";"Zergling";"Larva";682;1
"Unit";"Zergling";"Larva";682;1
"Unit";"Zergling";"Larva";682;1
"Unit";"Zergling";"Larva";682;1
"Unit";"Zergling";"Larva";682;1
"Unit";"Zergling";"Larva";682;1
"Unit";"Zergling";"Larva";682;1
"Unit";"Zergling";"Larva";682;1
"Unit";"Zergling";"Larva";682;1
"Unit";"Zergling";"Larva";682;1
"Unit";"Zergling";"Larva";682;1
"Unit";"Zergling";"Larva";682;1
"Unit";"Zergling";"Larva";682;1
"Unit";"Zergling";"Larva";682;1
"Unit";"Zergling";"Larva";682;1
"Unit";"Zergling";"Larva";682;1
"Unit";"Zergling";"Larva";682;1
"Unit";"Zergling";"Larva";682;1
"Unit";"Zergling";"Larva";682;1
"Unit";"Zergling";"Larva";682;1
"Unit";"Zergling";"Larva";682;1
"Unit";"Ultralisk";"Larva";682;6
"Unit";"Ultralisk";"Larva";682;6
"Unit";"Ultralisk";"Larva";682;6
"Unit";"Corruptor";"Larva";682;2
"Unit";"Corruptor";"Larva";682;2
"Unit";"Corruptor";"Larva";682;2
"Unit";"Corruptor";"Larva";682;2
"Building";"CreepTumor";NA;751;0
"Building";"CreepTumor";NA;751;0
"Unit";"Baneling";"Zergling";751;0
"Unit";"Baneling";"Zergling";751;0
"Unit";"Baneling";"Zergling";751;0
"Unit";"Baneling";"Zergling";751;0
"Unit";"Baneling";"Zergling";751;0
"Unit";"Baneling";"Zergling";751;0
"Unit";"Baneling";"Zergling";751;0
"Unit";"Baneling";"Zergling";751;0
"Unit";"Baneling";"Zergling";751;0
"Unit";"Baneling";"Zergling";751;0
"Unit";"Zergling";"Larva";751;1
"Unit";"Zergling";"Larva";751;1
