"type";"unit_name";"on_building";"total_supply";"supply"
"Unit";"Overlord";"Larva";13;0
"Building";"Extractor";NA;18;0
"Unit";"Overlord";"Larva";21;0
"Building";"SpawningPool";NA;19;0
"Building";"Hatchery";NA;17;0
"Unit";"Zergling";"Larva";22;1
"Unit";"Zergling";"Larva";22;1
"Unit";"Zergling";"Larva";23;1
"Unit";"Zergling";"Larva";23;1
"Unit";"Queen";"Hatchery";22;2
"Unit";"Queen";"Hatchery";23;2
"Building";"CreepTumorQueen";NA;32;0
"Unit";"Overlord";"Larva";32;0
"Unit";"Queen";"Hatchery";32;2
"Building";"CreepTumor";NA;37;0
"Building";"CreepTumorQueen";NA;39;0
"Building";"CreepTumorQueen";NA;39;0
"Unit";"Queen";"Hatchery";32;2
"Building";"Hatchery";NA;28;0
"Unit";"Overlord";"Larva";39;0
"Building";"CreepTumorQueen";NA;46;0
"Unit";"Queen";"Hatchery";39;2
"Building";"CreepTumor";NA;48;0
"Building";"CreepTumor";NA;48;0
"Unit";"Overlord";"Larva";48;0
"Building";"CreepTumorQueen";NA;48;0
"Unit";"Zergling";"Larva";48;1
"Unit";"Zergling";"Larva";48;1
"Unit";"Zergling";"Larva";48;1
"Unit";"Zergling";"Larva";48;1
"Unit";"Zergling";"Larva";48;1
"Unit";"Zergling";"Larva";48;1
"Unit";"Zergling";"Larva";48;1
"Unit";"Zergling";"Larva";48;1
"Building";"CreepTumorQueen";NA;48;0
"Unit";"Zergling";"Larva";48;1
"Unit";"Zergling";"Larva";48;1
"Unit";"Queen";"Hatchery";46;2
"Unit";"Overlord";"Larva";50;0
"Building";"CreepTumorQueen";NA;63;0
"Building";"CreepTumorQueen";NA;63;0
"Unit";"Overlord";"Larva";53;0
"Building";"CreepTumor";NA;63;0
"Unit";"Overlord";"Larva";65;0
"Building";"CreepTumor";NA;68;0
"Building";"CreepTumor";NA;68;0
"Building";"EvolutionChamber";NA;65;0
"Building";"EvolutionChamber";NA;68;0
"Building";"RoachWarren";NA;68;0
"Unit";"Overlord";"Larva";75;0
"Building";"CreepTumor";NA;75;0
"Building";"CreepTumor";NA;75;0
"Building";"CreepTumorQueen";NA;75;0
"Building";"CreepTumor";NA;75;0
"Building";"CreepTumorQueen";NA;75;0
"Unit";"Overlord";"Larva";75;0
"Building";"SporeCrawler";NA;75;0
"Building";"SporeCrawler";NA;75;0
"Building";"CreepTumorQueen";NA;77;0
"Building";"SporeCrawler";NA;75;0
"Building";"CreepTumor";NA;77;0
"Building";"CreepTumor";NA;77;0
"Building";"CreepTumor";NA;77;0
"Unit";"Overlord";"Larva";77;0
"Building";"CreepTumor";NA;79;0
"Building";"CreepTumor";NA;79;0
"Unit";"Queen";"Hatchery";75;2
"Unit";"Overlord";"Larva";79;0
"Unit";"Overlord";"Larva";79;0
"Building";"Extractor";NA;79;0
"Building";"Extractor";NA;79;0
"Unit";"Roach";"Larva";84;2
"Unit";"Roach";"Larva";84;2
"Unit";"Roach";"Larva";84;2
"Building";"CreepTumorQueen";NA;95;0
"Building";"CreepTumorQueen";NA;95;0
"Unit";"Overlord";"Larva";95;0
"Building";"CreepTumor";NA;95;0
"Building";"CreepTumor";NA;95;0
"Unit";"Overlord";"Larva";95;0
"Building";"CreepTumor";NA;95;0
"Building";"CreepTumor";NA;95;0
"Building";"CreepTumor";NA;100;0
"Building";"Extractor";NA;95;0
"Unit";"Overlord";"Larva";100;0
"Unit";"Overlord";"Larva";104;0
"Building";"CreepTumor";NA;104;0
"Unit";"Overlord";"Larva";104;0
"Building";"CreepTumor";NA;104;0
"Building";"CreepTumor";NA;104;0
"Building";"CreepTumor";NA;104;0
"Building";"CreepTumor";NA;104;0
"Building";"Extractor";NA;104;0
"Building";"Extractor";NA;104;0
"Unit";"Overlord";"Larva";104;0
"Unit";"Roach";"Larva";104;2
"Building";"CreepTumor";NA;107;0
"Unit";"Overlord";"Larva";107;0
"Building";"CreepTumor";NA;107;0
"Unit";"Roach";"Larva";107;2
"Unit";"Roach";"Larva";107;2
"Unit";"Roach";"Larva";107;2
"Unit";"Roach";"Larva";107;2
"Unit";"Roach";"Larva";107;2
"Upgrade";"ZergMissileWeaponsLevel1";"EvolutionChamber";93;0
"Building";"CreepTumor";NA;109;0
"Building";"CreepTumor";NA;109;0
"Building";"CreepTumor";NA;109;0
"Unit";"Roach";"Larva";107;2
"Unit";"Roach";"Larva";107;2
"Unit";"Roach";"Larva";107;2
"Unit";"Roach";"Larva";109;2
"Building";"HydraliskDen";NA;107;0
"Building";"Hatchery";NA;100;0
"Unit";"Roach";"Larva";119;2
"Unit";"Roach";"Larva";124;2
"Building";"CreepTumor";NA;136;0
"Building";"CreepTumor";NA;136;0
"Building";"CreepTumor";NA;136;0
"Building";"CreepTumor";NA;138;0
"Building";"CreepTumor";NA;140;0
"Unit";"Overlord";"Larva";136;0
"Building";"CreepTumor";NA;140;0
"Upgrade";"GlialReconstitution";"RoachWarren";107;0
"Building";"CreepTumor";NA;140;0
"Unit";"Hydralisk";"Larva";140;2
"Unit";"Hydralisk";"Larva";140;2
"Unit";"Hydralisk";"Larva";140;2
"Unit";"Hydralisk";"Larva";140;2
"Unit";"Hydralisk";"Larva";140;2
"Building";"CreepTumor";NA;147;0
"Building";"CreepTumor";NA;147;0
"Upgrade";"ZergGroundArmorsLevel1";"EvolutionChamber";107;0
"Unit";"Roach";"Larva";140;2
"Unit";"Roach";"Larva";141;2
"Unit";"Roach";"Larva";147;2
"Unit";"Roach";"Larva";147;2
"Building";"SporeCrawler";NA;147;0
"Building";"InfestationPit";NA;147;0
"Building";"SpineCrawler";NA;147;0
"Unit";"Queen";"Hatchery";149;2
"Building";"CreepTumor";NA;165;0
"Unit";"Hydralisk";"Larva";165;2
"Unit";"Hydralisk";"Larva";165;2
"Unit";"Hydralisk";"Larva";165;2
"Upgrade";"EvolveMuscularAugments";"HydraliskDen";140;0
"Unit";"Hydralisk";"Larva";165;2
"Unit";"Hydralisk";"Larva";165;2
"Unit";"Hydralisk";"Larva";165;2
"Unit";"Hydralisk";"Larva";165;2
"Unit";"Hydralisk";"Larva";165;2
"Building";"CreepTumor";NA;165;0
"Building";"CreepTumor";NA;165;0
"Unit";"Overlord";"Larva";165;0
"Building";"Extractor";NA;165;0
"Building";"Extractor";NA;165;0
"Unit";"Overlord";"Larva";167;0
"Building";"CreepTumor";NA;186;0
"Unit";"Hydralisk";"Larva";186;2
"Unit";"Hydralisk";"Larva";186;2
"Unit";"Hydralisk";"Larva";186;2
"Unit";"Hydralisk";"Larva";186;2
"Unit";"Hydralisk";"Larva";186;2
"Unit";"Hydralisk";"Larva";186;2
"Building";"CreepTumor";NA;186;0
"Building";"CreepTumor";NA;186;0
"Building";"CreepTumor";NA;186;0
"Building";"CreepTumor";NA;186;0
"Unit";"Hydralisk";"Larva";186;2
"Unit";"Hydralisk";"Larva";186;2
"Unit";"Hydralisk";"Larva";186;2
"Building";"CreepTumor";NA;198;0
"Unit";"Hydralisk";"Larva";186;2
"Unit";"Roach";"Larva";198;2
"Unit";"Roach";"Larva";198;2
"Unit";"Roach";"Larva";198;2
"Unit";"Roach";"Larva";198;2
"Unit";"Roach";"Larva";198;2
"Unit";"Roach";"Larva";198;2
"Unit";"Roach";"Larva";198;2
"Unit";"Roach";"Larva";198;2
"Unit";"Roach";"Larva";198;2
"Unit";"Roach";"Larva";198;2
"Unit";"Roach";"Larva";198;2
"Upgrade";"ZergMissileWeaponsLevel2";"EvolutionChamber";147;0
"Unit";"Overlord";"Larva";222;0
"Upgrade";"EvolveGroovedSpines";"HydraliskDen";186;0
"Unit";"Overlord";"Larva";228;0
"Unit";"Overlord";"Larva";228;0
"Unit";"Overlord";"Larva";228;0
"Unit";"Overlord";"Larva";228;0
"Unit";"Overlord";"Larva";228;0
"Unit";"Overlord";"Larva";228;0
"Building";"CreepTumor";NA;228;0
"Building";"CreepTumor";NA;228;0
"Unit";"Overlord";"Larva";228;0
"Unit";"Roach";"Larva";228;2
"Unit";"Roach";"Larva";228;2
"Unit";"Roach";"Larva";228;2
"Unit";"Roach";"Larva";228;2
"Unit";"Roach";"Larva";228;2
"Unit";"Roach";"Larva";228;2
"Unit";"Roach";"Larva";228;2
"Unit";"Roach";"Larva";228;2
"Unit";"Roach";"Larva";228;2
"Unit";"Roach";"Larva";228;2
"Unit";"Overlord";"Larva";228;0
"Building";"CreepTumorQueen";NA;228;0
"Unit";"Overlord";"Larva";228;0
"Unit";"Hydralisk";"Larva";228;2
"Building";"CreepTumorQueen";NA;228;0
"Unit";"Hydralisk";"Larva";228;2
"Building";"CreepTumorQueen";NA;248;0
"Building";"CreepTumorQueen";NA;248;0
"Building";"CreepTumor";NA;248;0
"Building";"CreepTumorQueen";NA;252;0
"Building";"CreepTumorQueen";NA;252;0
"Building";"CreepTumorQueen";NA;252;0
"Unit";"Viper";"Larva";248;3
"Unit";"Viper";"Larva";248;3
"Unit";"Viper";"Larva";248;3
"Unit";"Overlord";"Larva";252;0
"Building";"CreepTumor";NA;261;0
"Unit";"Roach";"Larva";252;2
"Unit";"Roach";"Larva";252;2
"Unit";"Roach";"Larva";252;2
"Unit";"Roach";"Larva";252;2
"Building";"CreepTumor";NA;261;0
"Building";"CreepTumor";NA;269;0
"Building";"CreepTumorQueen";NA;269;0
"Building";"CreepTumorQueen";NA;269;0
"Building";"CreepTumor";NA;269;0
"Building";"CreepTumor";NA;269;0
"Building";"CreepTumorQueen";NA;269;0
"Building";"CreepTumor";NA;269;0
"Building";"CreepTumor";NA;269;0
"Building";"CreepTumor";NA;269;0
"Building";"CreepTumor";NA;269;0
"Building";"CreepTumorQueen";NA;269;0
"Building";"CreepTumor";NA;269;0
"Upgrade";"ZergGroundArmorsLevel2";"EvolutionChamber";248;0
"Building";"Hatchery";NA;252;0
"Upgrade";"ZergMissileWeaponsLevel3";"EvolutionChamber";252;0
