"type";"unit_name";"on_building";"total_supply";"supply"
"Building";"Extractor";NA;13;0
"Unit";"Overlord";"Larva";15;0
"Building";"SpawningPool";NA;15;0
"Unit";"Zergling";"Larva";18;1
"Unit";"Zergling";"Larva";18;1
"Unit";"Zergling";"Larva";18;1
"Unit";"Zergling";"Larva";18;1
"Unit";"Zergling";"Larva";18;1
"Unit";"Zergling";"Larva";18;1
"Unit";"Zergling";"Larva";18;1
"Unit";"Zergling";"Larva";18;1
"Unit";"Overlord";"Larva";26;0
"Unit";"Queen";"Hatchery";26;2
"Building";"Hatchery";NA;24;0
"Unit";"Queen";"Hatchery";29;2
"Building";"CreepTumorQueen";NA;34;0
"Unit";"Queen";"Hatchery";33;2
"Unit";"Overlord";"Larva";38;0
"Unit";"Overlord";"Larva";38;0
"Building";"CreepTumor";NA;41;0
"Building";"CreepTumorQueen";NA;43;0
"Unit";"Overlord";"Larva";43;0
"Building";"CreepTumorQueen";NA;46;0
"Building";"CreepTumor";NA;46;0
"Unit";"Queen";"Hatchery";43;2
"Building";"CreepTumor";NA;49;0
"Building";"CreepTumorQueen";NA;51;0
"Unit";"Overlord";"Larva";49;0
"Unit";"Queen";"Hatchery";48;2
"Building";"CreepTumor";NA;56;0
"Building";"Extractor";NA;54;0
"Building";"CreepTumor";NA;58;0
"Building";"CreepTumor";NA;58;0
"Building";"Hatchery";NA;41;0
"Building";"CreepTumorQueen";NA;62;0
"Building";"EvolutionChamber";NA;57;0
"Building";"Extractor";NA;60;0
"Building";"CreepTumor";NA;65;0
"Building";"CreepTumor";NA;65;0
"Building";"CreepTumor";NA;70;0
"Building";"CreepTumorQueen";NA;73;0
"Building";"BanelingNest";NA;63;0
"Unit";"Overlord";"Larva";73;0
"Unit";"Overlord";"Larva";77;0
"Building";"CreepTumor";NA;77;0
"Unit";"Zergling";"Larva";77;1
"Unit";"Zergling";"Larva";77;1
"Unit";"Zergling";"Larva";77;1
"Unit";"Zergling";"Larva";77;1
"Unit";"Zergling";"Larva";77;1
"Unit";"Zergling";"Larva";77;1
"Building";"CreepTumor";NA;78;0
"Unit";"Zergling";"Larva";77;1
"Unit";"Zergling";"Larva";77;1
"Unit";"Zergling";"Larva";77;1
"Unit";"Zergling";"Larva";77;1
"Building";"CreepTumor";NA;78;0
"Building";"CreepTumor";NA;78;0
"Unit";"Overlord";"Larva";78;0
"Unit";"Queen";"Hatchery";73;2
"Unit";"Overlord";"Larva";78;0
"Unit";"Overlord";"Larva";78;0
"Unit";"Overlord";"Larva";90;0
"Building";"CreepTumor";NA;90;0
"Unit";"Zergling";"Larva";90;1
"Unit";"Zergling";"Larva";90;1
"Building";"CreepTumor";NA;91;0
"Building";"CreepTumor";NA;94;0
"Building";"CreepTumor";NA;97;0
"Building";"CreepTumorQueen";NA;97;0
"Unit";"Zergling";"Larva";90;1
"Unit";"Zergling";"Larva";90;1
"Building";"CreepTumor";NA;97;0
"Unit";"Zergling";"Larva";90;1
"Unit";"Zergling";"Larva";90;1
"Unit";"Zergling";"Larva";90;1
"Unit";"Zergling";"Larva";90;1
"Unit";"Zergling";"Larva";90;1
"Unit";"Zergling";"Larva";90;1
"Unit";"Zergling";"Larva";90;1
"Unit";"Zergling";"Larva";90;1
"Unit";"Zergling";"Larva";97;1
"Unit";"Zergling";"Larva";97;1
"Unit";"Baneling";"Zergling";99;0
"Unit";"Baneling";"Zergling";99;0
"Unit";"Baneling";"Zergling";99;0
"Unit";"Baneling";"Zergling";99;0
"Unit";"Baneling";"Zergling";99;0
"Unit";"Baneling";"Zergling";99;0
"Unit";"Zergling";"Larva";99;1
"Unit";"Zergling";"Larva";99;1
"Unit";"Zergling";"Larva";99;1
"Unit";"Zergling";"Larva";99;1
"Unit";"Zergling";"Larva";99;1
"Unit";"Zergling";"Larva";99;1
"Unit";"Zergling";"Larva";99;1
"Unit";"Zergling";"Larva";99;1
"Unit";"Baneling";"Zergling";99;0
"Building";"CreepTumor";NA;111;0
"Building";"CreepTumor";NA;119;0
"Unit";"Zergling";"Larva";111;1
"Unit";"Zergling";"Larva";111;1
"Unit";"Zergling";"Larva";111;1
"Unit";"Zergling";"Larva";111;1
"Unit";"Zergling";"Larva";111;1
"Unit";"Zergling";"Larva";111;1
"Unit";"Zergling";"Larva";111;1
"Unit";"Zergling";"Larva";111;1
"Unit";"Zergling";"Larva";111;1
"Unit";"Zergling";"Larva";111;1
"Unit";"Zergling";"Larva";111;1
"Unit";"Zergling";"Larva";111;1
"Unit";"Zergling";"Larva";119;1
"Unit";"Zergling";"Larva";119;1
"Unit";"Zergling";"Larva";119;1
"Unit";"Zergling";"Larva";119;1
"Unit";"Baneling";"Zergling";119;0
"Unit";"Zergling";"Larva";119;1
"Unit";"Zergling";"Larva";119;1
"Unit";"Zergling";"Larva";119;1
"Unit";"Zergling";"Larva";119;1
"Unit";"Zergling";"Larva";119;1
"Unit";"Zergling";"Larva";119;1
"Unit";"Zergling";"Larva";119;1
"Unit";"Zergling";"Larva";119;1
"Unit";"Baneling";"Zergling";119;0
"Unit";"Zergling";"Larva";119;1
"Unit";"Zergling";"Larva";119;1
"Unit";"Zergling";"Larva";119;1
"Unit";"Zergling";"Larva";119;1
"Unit";"Baneling";"Zergling";119;0
"Unit";"Baneling";"Zergling";119;0
"Unit";"Baneling";"Zergling";119;0
"Unit";"Baneling";"Zergling";119;0
"Unit";"Baneling";"Zergling";119;0
"Building";"EvolutionChamber";NA;119;0
"Unit";"Zergling";"Larva";121;1
"Unit";"Zergling";"Larva";121;1
"Unit";"Zergling";"Larva";132;1
"Unit";"Zergling";"Larva";132;1
"Upgrade";"ZergGroundArmorsLevel1";"EvolutionChamber";84;0
"Building";"Hatchery";NA;97;0
"Building";"CreepTumor";NA;152;0
"Building";"Extractor";NA;152;0
"Building";"CreepTumor";NA;152;0
"Building";"CreepTumor";NA;162;0
"Building";"CreepTumor";NA;162;0
"Building";"Extractor";NA;152;0
"Building";"Extractor";NA;152;0
"Building";"CreepTumor";NA;162;0
"Building";"SpawningPool";NA;144;0
"Building";"CreepTumor";NA;167;0
"Unit";"Zergling";"Larva";163;1
"Unit";"Zergling";"Larva";163;1
"Unit";"Zergling";"Larva";167;1
"Unit";"Zergling";"Larva";167;1
"Unit";"Zergling";"Larva";167;1
"Unit";"Zergling";"Larva";167;1
"Unit";"Zergling";"Larva";167;1
"Unit";"Zergling";"Larva";167;1
"Unit";"Overlord";"Larva";167;0
"Unit";"Baneling";"Zergling";186;0
"Unit";"Baneling";"Zergling";186;0
"Unit";"Baneling";"Zergling";186;0
"Unit";"Baneling";"Zergling";186;0
"Unit";"Baneling";"Zergling";186;0
"Unit";"Baneling";"Zergling";186;0
"Building";"Spire";NA;152;0
"Unit";"Mutalisk";"Larva";186;2
"Unit";"Mutalisk";"Larva";186;2
"Unit";"Mutalisk";"Larva";186;2
"Building";"Extractor";NA;190;0
"Building";"Hatchery";NA;178;0
"Building";"HydraliskDen";NA;195;0
"Building";"SporeCrawler";NA;205;0
"Upgrade";"ZergMeleeWeaponsLevel1";"EvolutionChamber";167;0
"Building";"Extractor";NA;205;0
"Building";"Extractor";NA;205;0
"Unit";"Mutalisk";"Larva";205;2
"Building";"InfestationPit";NA;199;0
"Unit";"Mutalisk";"Larva";214;2
"Unit";"Mutalisk";"Larva";214;2
"Unit";"Overlord";"Larva";216;0
"Unit";"Overlord";"Larva";216;0
"Unit";"Overlord";"Larva";216;0
"Unit";"Overlord";"Larva";216;0
"Unit";"Overlord";"Larva";216;0
"Unit";"Overlord";"Larva";216;0
"Building";"CreepTumor";NA;229;0
"Unit";"Overlord";"Larva";229;0
"Unit";"Overlord";"Larva";229;0
"Unit";"Overlord";"Larva";229;0
"Unit";"Overlord";"Larva";229;0
"Upgrade";"ZergGroundArmorsLevel2";"EvolutionChamber";186;0
"Building";"Extractor";NA;229;0
"Building";"CreepTumorQueen";NA;229;0
"Building";"Extractor";NA;229;0
"Building";"CreepTumorQueen";NA;229;0
"Building";"CreepTumorQueen";NA;229;0
"Building";"CreepTumorQueen";NA;229;0
"Building";"Hatchery";NA;214;0
"Building";"CreepTumorQueen";NA;229;0
"Building";"CreepTumorQueen";NA;237;0
"Unit";"Hydralisk";"Larva";229;2
"Unit";"Hydralisk";"Larva";229;2
"Unit";"Hydralisk";"Larva";229;2
"Building";"RoachWarren";NA;229;0
"Unit";"Hydralisk";"Larva";237;2
"Unit";"Hydralisk";"Larva";237;2
"Unit";"Hydralisk";"Larva";237;2
"Unit";"Hydralisk";"Larva";237;2
"Unit";"Hydralisk";"Larva";237;2
"Upgrade";"EvolveMuscularAugments";"HydraliskDen";229;0
"Building";"CreepTumorQueen";NA;243;0
"Building";"CreepTumor";NA;243;0
"Building";"CreepTumorQueen";NA;253;0
"Building";"CreepTumorQueen";NA;253;0
"Unit";"Hydralisk";"Larva";243;2
"Unit";"Hydralisk";"Larva";243;2
"Unit";"Hydralisk";"Larva";243;2
"Unit";"Hydralisk";"Larva";243;2
"Unit";"Hydralisk";"Larva";243;2
"Unit";"Hydralisk";"Larva";243;2
"Unit";"Hydralisk";"Larva";243;2
"Unit";"Hydralisk";"Larva";243;2
"Building";"CreepTumorQueen";NA;253;0
"Building";"CreepTumorQueen";NA;253;0
"Building";"CreepTumor";NA;253;0
"Building";"CreepTumor";NA;253;0
"Building";"CreepTumor";NA;253;0
"Building";"CreepTumor";NA;253;0
"Building";"CreepTumor";NA;253;0
"Building";"CreepTumor";NA;253;0
"Building";"SporeCrawler";NA;253;0
"Building";"Extractor";NA;253;0
"Building";"Hatchery";NA;229;0
"Building";"Extractor";NA;253;0
"Building";"SpineCrawler";NA;245;0
"Unit";"Viper";"Larva";253;3
"Unit";"Viper";"Larva";253;3
"Unit";"Viper";"Larva";253;3
"Building";"SpineCrawler";NA;253;0
"Building";"SpineCrawler";NA;253;0
"Unit";"Zergling";"Larva";271;1
"Unit";"Zergling";"Larva";271;1
"Unit";"Zergling";"Larva";271;1
"Unit";"Zergling";"Larva";271;1
"Unit";"Zergling";"Larva";271;1
"Unit";"Zergling";"Larva";271;1
"Unit";"Zergling";"Larva";271;1
"Unit";"Zergling";"Larva";271;1
"Unit";"Zergling";"Larva";271;1
"Unit";"Zergling";"Larva";271;1
"Unit";"Zergling";"Larva";271;1
"Unit";"Zergling";"Larva";271;1
"Unit";"Zergling";"Larva";271;1
"Unit";"Zergling";"Larva";271;1
"Unit";"Zergling";"Larva";271;1
"Unit";"Zergling";"Larva";271;1
"Unit";"Roach";"Larva";271;2
"Unit";"Roach";"Larva";271;2
"Unit";"Roach";"Larva";271;2
"Unit";"Roach";"Larva";271;2
"Unit";"Roach";"Larva";271;2
"Unit";"Roach";"Larva";271;2
"Unit";"Viper";"Larva";271;3
"Upgrade";"ZergMissileWeaponsLevel1";"EvolutionChamber";237;0
"Unit";"Roach";"Larva";280;2
"Unit";"Roach";"Larva";280;2
"Unit";"Roach";"Larva";280;2
"Unit";"Roach";"Larva";280;2
"Unit";"Roach";"Larva";280;2
"Upgrade";"GlialReconstitution";"RoachWarren";271;0
"Building";"Extractor";NA;311;0
"Building";"Extractor";NA;311;0
"Building";"SporeCrawler";NA;311;0
"Building";"CreepTumor";NA;333;0
"Building";"SpineCrawler";NA;298;0
"Upgrade";"EvolveGroovedSpines";"HydraliskDen";271;0
"Building";"CreepTumor";NA;333;0
"Building";"CreepTumor";NA;333;0
"Building";"CreepTumor";NA;333;0
"Building";"CreepTumor";NA;333;0
"Building";"CreepTumor";NA;333;0
"Building";"CreepTumor";NA;333;0
"Building";"SporeCrawler";NA;333;0
"Building";"SpineCrawler";NA;333;0
"Building";"SpineCrawler";NA;333;0
"Unit";"Corruptor";"Larva";333;2
"Unit";"Corruptor";"Larva";333;2
"Unit";"Corruptor";"Larva";333;2
"Unit";"Corruptor";"Larva";333;2
"Unit";"Corruptor";"Larva";333;2
"Upgrade";"ZergMeleeWeaponsLevel2";"EvolutionChamber";271;0
"Building";"SpineCrawler";NA;333;0
"Unit";"Viper";"Larva";333;3
"Unit";"Viper";"Larva";333;3
"Building";"CreepTumorQueen";NA;343;0
"Building";"CreepTumor";NA;343;0
"Building";"CreepTumorQueen";NA;349;0
"Building";"CreepTumor";NA;349;0
"Building";"CreepTumor";NA;349;0
"Building";"CreepTumor";NA;349;0
"Building";"CreepTumor";NA;349;0
"Building";"CreepTumor";NA;349;0
"Building";"CreepTumor";NA;349;0
"Building";"CreepTumor";NA;349;0
"Building";"CreepTumor";NA;349;0
"Building";"CreepTumor";NA;349;0
"Building";"CreepTumorQueen";NA;349;0
"Unit";"Corruptor";"Larva";343;2
"Unit";"Corruptor";"Larva";343;2
"Unit";"Corruptor";"Larva";343;2
"Building";"CreepTumorQueen";NA;355;0
"Building";"CreepTumorQueen";NA;355;0
"Building";"CreepTumorQueen";NA;355;0
"Unit";"Corruptor";"Larva";351;2
"Unit";"Corruptor";"Larva";355;2
"Unit";"Corruptor";"Larva";355;2
"Unit";"Corruptor";"Larva";355;2
"Unit";"Corruptor";"Larva";355;2
"Unit";"Corruptor";"Larva";355;2
"Unit";"Corruptor";"Larva";355;2
"Building";"CreepTumor";NA;355;0
"Building";"CreepTumor";NA;355;0
"Building";"EvolutionChamber";NA;355;0
"Building";"EvolutionChamber";NA;355;0
"Building";"CreepTumor";NA;369;0
"Building";"CreepTumor";NA;369;0
"Building";"CreepTumor";NA;369;0
"Building";"EvolutionChamber";NA;355;0
"Upgrade";"ZergMissileWeaponsLevel2";"EvolutionChamber";333;0
"Building";"EvolutionChamber";NA;355;0
