"type";"unit_name";"on_building";"total_supply_lag";"supply"
"Unit";"Overlord";"Larva";13;0
"Building";"Hatchery";NA;17;0
"Building";"Extractor";NA;19;0
"Building";"SpawningPool";NA;19;0
"Unit";"Overlord";"Larva";22;0
"Unit";"Zergling";"Larva";22;1
"Unit";"Zergling";"Larva";23;1
"Unit";"Zergling";"Larva";24;1
"Unit";"Zergling";"Larva";25;1
"Unit";"Queen";"Hatchery";26;2
"Unit";"Queen";"Hatchery";28;2
"Unit";"Zergling";"Larva";30;1
"Unit";"Zergling";"Larva";31;1
"Unit";"Overlord";"Larva";35;0
"Unit";"Queen";"Hatchery";35;2
"Building";"CreepTumorQueen";NA;48;0
"Building";"Hatchery";NA;48;0
"Unit";"Overlord";"Larva";51;0
"Building";"CreepTumor";NA;51;0
"Building";"CreepTumorQueen";NA;51;0
"Unit";"Overlord";"Larva";51;0
"Building";"Extractor";NA;51;0
"Unit";"Queen";"Hatchery";51;2
"Unit";"Zergling";"Larva";57;1
"Unit";"Zergling";"Larva";58;1
"Unit";"Zergling";"Larva";59;1
"Unit";"Zergling";"Larva";60;1
"Unit";"Zergling";"Larva";61;1
"Unit";"Zergling";"Larva";62;1
"Unit";"Zergling";"Larva";63;1
"Unit";"Zergling";"Larva";64;1
"Unit";"Zergling";"Larva";65;1
"Unit";"Zergling";"Larva";66;1
"Unit";"Zergling";"Larva";67;1
"Unit";"Zergling";"Larva";68;1
"Building";"SporeCrawler";NA;75;0
"Building";"SporeCrawler";NA;77;0
"Unit";"Queen";"Hatchery";77;2
"Unit";"Zergling";"Larva";83;1
"Unit";"Zergling";"Larva";84;1
"Unit";"Zergling";"Larva";85;1
"Unit";"Zergling";"Larva";86;1
"Building";"CreepTumor";NA;87;0
"Building";"CreepTumor";NA;87;0
"Unit";"Zergling";"Larva";88;1
"Unit";"Zergling";"Larva";89;1
"Unit";"Zergling";"Larva";90;1
"Unit";"Zergling";"Larva";91;1
"Building";"SporeCrawler";NA;92;0
"Unit";"Overlord";"Larva";96;0
"Unit";"Overlord";"Larva";96;0
"Building";"EvolutionChamber";NA;96;0
"Building";"EvolutionChamber";NA;96;0
"Building";"CreepTumor";NA;98;0
"Building";"CreepTumor";NA;98;0
"Unit";"Overlord";"Larva";98;0
"Building";"BanelingNest";NA;98;0
"Building";"CreepTumorQueen";NA;106;0
"Building";"CreepTumorQueen";NA;106;0
"Building";"Extractor";NA;112;0
"Building";"Extractor";NA;112;0
"Building";"Extractor";NA;117;0
"Building";"HydraliskDen";NA;117;0
"Building";"CreepTumor";NA;117;0
"Building";"CreepTumor";NA;117;0
"Building";"CreepTumor";NA;117;0
"Building";"CreepTumor";NA;117;0
"Building";"CreepTumorQueen";NA;118;0
"Unit";"Zergling";"Larva";119;1
"Unit";"Zergling";"Larva";120;1
"Unit";"Zergling";"Larva";121;1
"Unit";"Zergling";"Larva";122;1
"Unit";"Zergling";"Larva";123;1
"Unit";"Zergling";"Larva";124;1
"Unit";"Zergling";"Larva";125;1
"Unit";"Zergling";"Larva";126;1
"Unit";"Zergling";"Larva";127;1
"Unit";"Zergling";"Larva";128;1
"Building";"CreepTumorQueen";NA;129;0
"Building";"Hatchery";NA;129;0
"Unit";"Baneling";"Zergling";129;0
"Unit";"Baneling";"Zergling";129;0
"Unit";"Baneling";"Zergling";129;0
"Unit";"Baneling";"Zergling";129;0
"Unit";"Baneling";"Zergling";129;0
"Unit";"Zergling";"Larva";129;1
"Unit";"Zergling";"Larva";130;1
"Unit";"Zergling";"Larva";131;1
"Unit";"Zergling";"Larva";132;1
"Unit";"Zergling";"Larva";133;1
"Unit";"Zergling";"Larva";134;1
"Unit";"Zergling";"Larva";135;1
"Unit";"Zergling";"Larva";136;1
"Unit";"Overlord";"Larva";137;0
"Unit";"Overlord";"Larva";137;0
"Unit";"Overlord";"Larva";137;0
"Unit";"Zergling";"Larva";137;1
"Unit";"Zergling";"Larva";138;1
"Unit";"Zergling";"Larva";139;1
"Unit";"Zergling";"Larva";140;1
"Unit";"Zergling";"Larva";141;1
"Unit";"Zergling";"Larva";142;1
"Unit";"Zergling";"Larva";143;1
"Unit";"Zergling";"Larva";144;1
"Unit";"Zergling";"Larva";145;1
"Unit";"Zergling";"Larva";146;1
"Unit";"Zergling";"Larva";147;1
"Unit";"Zergling";"Larva";148;1
"Unit";"Zergling";"Larva";149;1
"Unit";"Zergling";"Larva";150;1
"Unit";"Zergling";"Larva";151;1
"Unit";"Zergling";"Larva";152;1
"Unit";"Zergling";"Larva";153;1
"Unit";"Zergling";"Larva";154;1
"Unit";"Zergling";"Larva";155;1
"Unit";"Zergling";"Larva";156;1
"Unit";"Zergling";"Larva";157;1
"Unit";"Zergling";"Larva";158;1
"Unit";"Zergling";"Larva";159;1
"Unit";"Zergling";"Larva";160;1
"Unit";"Zergling";"Larva";161;1
"Unit";"Zergling";"Larva";162;1
"Unit";"Queen";"Hatchery";163;2
"Unit";"Queen";"Hatchery";165;2
"Unit";"Queen";"Hatchery";167;2
"Unit";"Baneling";"Zergling";177;0
"Unit";"Baneling";"Zergling";177;0
"Unit";"Baneling";"Zergling";177;0
"Unit";"Baneling";"Zergling";177;0
"Unit";"Baneling";"Zergling";177;0
"Unit";"Baneling";"Zergling";177;0
"Unit";"Baneling";"Zergling";177;0
"Unit";"Baneling";"Zergling";177;0
"Unit";"Baneling";"Zergling";177;0
"Unit";"Zergling";"Larva";177;1
"Unit";"Zergling";"Larva";178;1
"Unit";"Zergling";"Larva";179;1
"Unit";"Zergling";"Larva";180;1
"Unit";"Zergling";"Larva";181;1
"Unit";"Zergling";"Larva";182;1
"Unit";"Zergling";"Larva";183;1
"Unit";"Zergling";"Larva";184;1
"Unit";"Zergling";"Larva";185;1
"Unit";"Zergling";"Larva";186;1
"Building";"Extractor";NA;187;0
"Building";"Hatchery";NA;187;0
"Unit";"Zergling";"Larva";187;1
"Unit";"Zergling";"Larva";188;1
"Unit";"Zergling";"Larva";189;1
"Unit";"Zergling";"Larva";190;1
"Unit";"Zergling";"Larva";191;1
"Unit";"Zergling";"Larva";192;1
"Unit";"Zergling";"Larva";193;1
"Unit";"Zergling";"Larva";194;1
"Unit";"Zergling";"Larva";195;1
"Unit";"Zergling";"Larva";196;1
"Unit";"Zergling";"Larva";197;1
"Unit";"Zergling";"Larva";198;1
"Building";"CreepTumor";NA;199;0
"Building";"CreepTumorQueen";NA;199;0
"Unit";"Hydralisk";"Larva";199;2
"Unit";"Hydralisk";"Larva";201;2
"Unit";"Hydralisk";"Larva";203;2
"Unit";"Hydralisk";"Larva";205;2
"Unit";"Hydralisk";"Larva";207;2
"Unit";"Hydralisk";"Larva";209;2
"Unit";"Hydralisk";"Larva";211;2
"Building";"CreepTumor";NA;213;0
"Building";"CreepTumor";NA;213;0
"Unit";"Baneling";"Zergling";213;0
"Unit";"Baneling";"Zergling";213;0
"Unit";"Baneling";"Zergling";213;0
"Unit";"Baneling";"Zergling";213;0
"Unit";"Baneling";"Zergling";213;0
"Unit";"Baneling";"Zergling";213;0
"Unit";"Baneling";"Zergling";213;0
"Unit";"Baneling";"Zergling";213;0
"Unit";"Zergling";"Larva";213;1
"Unit";"Zergling";"Larva";214;1
"Unit";"Zergling";"Larva";215;1
"Unit";"Zergling";"Larva";216;1
"Unit";"Zergling";"Larva";217;1
"Unit";"Zergling";"Larva";218;1
"Unit";"Zergling";"Larva";219;1
"Unit";"Zergling";"Larva";220;1
"Unit";"Zergling";"Larva";221;1
"Unit";"Zergling";"Larva";222;1
"Unit";"Zergling";"Larva";223;1
"Unit";"Zergling";"Larva";224;1
"Unit";"Zergling";"Larva";225;1
"Unit";"Zergling";"Larva";226;1
"Unit";"Zergling";"Larva";227;1
"Unit";"Zergling";"Larva";228;1
"Unit";"Zergling";"Larva";229;1
"Unit";"Zergling";"Larva";230;1
"Unit";"Zergling";"Larva";231;1
"Unit";"Zergling";"Larva";232;1
"Unit";"Zergling";"Larva";233;1
"Unit";"Zergling";"Larva";234;1
"Unit";"Zergling";"Larva";235;1
"Unit";"Zergling";"Larva";236;1
"Unit";"Zergling";"Larva";237;1
"Unit";"Zergling";"Larva";238;1
"Unit";"Zergling";"Larva";239;1
"Unit";"Zergling";"Larva";240;1
"Unit";"Zergling";"Larva";241;1
"Unit";"Zergling";"Larva";242;1
"Unit";"Queen";"Hatchery";243;2
"Building";"CreepTumorQueen";NA;245;0
"Unit";"Hydralisk";"Larva";245;2
"Unit";"Overlord";"Larva";247;0
"Unit";"Overlord";"Larva";247;0
"Unit";"Overlord";"Larva";247;0
"Building";"InfestationPit";NA;247;0
"Building";"CreepTumor";NA;247;0
"Building";"CreepTumor";NA;247;0
"Building";"CreepTumor";NA;247;0
"Building";"CreepTumor";NA;247;0
"Unit";"Overlord";"Larva";247;0
"Unit";"Overlord";"Larva";247;0
"Unit";"Baneling";"Zergling";247;0
"Unit";"Baneling";"Zergling";247;0
"Unit";"Baneling";"Zergling";247;0
"Unit";"Baneling";"Zergling";247;0
"Unit";"Baneling";"Zergling";247;0
"Unit";"Baneling";"Zergling";247;0
"Unit";"Baneling";"Zergling";247;0
"Unit";"Baneling";"Zergling";247;0
"Building";"CreepTumor";NA;247;0
"Building";"CreepTumorQueen";NA;247;0
"Building";"CreepTumorQueen";NA;247;0
"Unit";"Hydralisk";"Larva";253;2
"Unit";"Hydralisk";"Larva";255;2
"Unit";"Hydralisk";"Larva";257;2
"Unit";"Hydralisk";"Larva";259;2
"Unit";"Hydralisk";"Larva";261;2
"Unit";"Hydralisk";"Larva";263;2
"Unit";"Hydralisk";"Larva";265;2
"Unit";"Hydralisk";"Larva";267;2
"Unit";"Queen";"Hatchery";269;2
"Unit";"Zergling";"Larva";271;1
"Unit";"Zergling";"Larva";272;1
"Unit";"Zergling";"Larva";273;1
"Unit";"Zergling";"Larva";274;1
"Unit";"Zergling";"Larva";275;1
"Unit";"Zergling";"Larva";276;1
"Unit";"Zergling";"Larva";277;1
"Unit";"Zergling";"Larva";278;1
"Unit";"Zergling";"Larva";279;1
"Unit";"Zergling";"Larva";280;1
"Building";"CreepTumor";NA;281;0
"Building";"CreepTumor";NA;281;0
"Building";"CreepTumor";NA;281;0
"Building";"CreepTumor";NA;281;0
"Unit";"Zergling";"Larva";281;1
"Unit";"Zergling";"Larva";282;1
"Unit";"Zergling";"Larva";283;1
"Unit";"Zergling";"Larva";284;1
"Unit";"Zergling";"Larva";285;1
"Unit";"Zergling";"Larva";286;1
"Unit";"Zergling";"Larva";287;1
"Unit";"Zergling";"Larva";288;1
"Unit";"Zergling";"Larva";289;1
"Unit";"Zergling";"Larva";290;1
"Unit";"Zergling";"Larva";291;1
"Unit";"Zergling";"Larva";292;1
"Unit";"Zergling";"Larva";293;1
"Unit";"Zergling";"Larva";294;1
"Unit";"Zergling";"Larva";295;1
"Unit";"Zergling";"Larva";296;1
"Unit";"Zergling";"Larva";297;1
"Unit";"Zergling";"Larva";298;1
"Unit";"Baneling";"Zergling";299;0
"Unit";"Baneling";"Zergling";299;0
"Unit";"Baneling";"Zergling";299;0
"Building";"CreepTumorQueen";NA;299;0
"Building";"CreepTumor";NA;299;0
"Building";"CreepTumor";NA;299;0
"Building";"CreepTumorQueen";NA;299;0
"Unit";"Overlord";"Larva";299;0
"Unit";"Overlord";"Larva";299;0
"Unit";"Overlord";"Larva";299;0
"Unit";"Overlord";"Larva";299;0
"Unit";"Overlord";"Larva";299;0
"Unit";"Overlord";"Larva";299;0
"Unit";"Zergling";"Larva";299;1
"Unit";"Zergling";"Larva";300;1
"Unit";"Zergling";"Larva";301;1
"Unit";"Zergling";"Larva";302;1
"Unit";"Zergling";"Larva";303;1
"Unit";"Zergling";"Larva";304;1
"Unit";"Zergling";"Larva";305;1
"Unit";"Zergling";"Larva";306;1
"Unit";"Zergling";"Larva";307;1
"Unit";"Zergling";"Larva";308;1
"Unit";"Zergling";"Larva";309;1
"Unit";"Zergling";"Larva";310;1
"Unit";"Zergling";"Larva";311;1
"Unit";"Zergling";"Larva";312;1
"Unit";"Zergling";"Larva";313;1
"Unit";"Zergling";"Larva";314;1
"Unit";"Zergling";"Larva";315;1
"Unit";"Zergling";"Larva";316;1
"Unit";"Baneling";"Zergling";317;0
"Unit";"Baneling";"Zergling";317;0
"Unit";"Baneling";"Zergling";317;0
"Unit";"Baneling";"Zergling";317;0
"Unit";"Baneling";"Zergling";317;0
"Building";"SporeCrawler";NA;317;0
"Unit";"Overlord";"Larva";317;0
"Unit";"Zergling";"Larva";317;1
"Unit";"Zergling";"Larva";318;1
"Unit";"Zergling";"Larva";319;1
"Unit";"Zergling";"Larva";320;1
"Unit";"Zergling";"Larva";321;1
"Unit";"Zergling";"Larva";322;1
"Unit";"Zergling";"Larva";323;1
"Unit";"Zergling";"Larva";324;1
"Unit";"Zergling";"Larva";325;1
"Unit";"Zergling";"Larva";326;1
"Unit";"Zergling";"Larva";327;1
"Unit";"Zergling";"Larva";328;1
"Unit";"Zergling";"Larva";329;1
"Unit";"Zergling";"Larva";330;1
"Unit";"Zergling";"Larva";331;1
"Unit";"Zergling";"Larva";332;1
"Unit";"Zergling";"Larva";333;1
"Unit";"Zergling";"Larva";334;1
"Unit";"Zergling";"Larva";335;1
"Unit";"Zergling";"Larva";336;1
"Unit";"Zergling";"Larva";337;1
"Unit";"Zergling";"Larva";338;1
"Unit";"Zergling";"Larva";339;1
"Unit";"Zergling";"Larva";340;1
"Building";"CreepTumor";NA;341;0
"Building";"CreepTumor";NA;341;0
"Building";"CreepTumor";NA;341;0
"Unit";"Zergling";"Larva";341;1
"Unit";"Zergling";"Larva";342;1
"Unit";"Zergling";"Larva";343;1
"Unit";"Zergling";"Larva";344;1
"Unit";"Zergling";"Larva";345;1
"Unit";"Zergling";"Larva";346;1
"Unit";"Zergling";"Larva";347;1
"Unit";"Zergling";"Larva";348;1
"Unit";"Zergling";"Larva";349;1
"Unit";"Zergling";"Larva";350;1
"Unit";"Zergling";"Larva";351;1
"Unit";"Zergling";"Larva";352;1
"Unit";"Zergling";"Larva";353;1
"Unit";"Zergling";"Larva";354;1
"Unit";"Zergling";"Larva";355;1
"Unit";"Zergling";"Larva";356;1
"Building";"UltraliskCavern";NA;357;0
"Unit";"Viper";"Larva";357;3
"Unit";"Viper";"Larva";360;3
"Unit";"Viper";"Larva";363;3
"Unit";"Zergling";"Larva";366;1
"Unit";"Zergling";"Larva";367;1
"Unit";"Zergling";"Larva";368;1
"Unit";"Zergling";"Larva";369;1
"Unit";"Zergling";"Larva";370;1
"Unit";"Zergling";"Larva";371;1
"Unit";"Zergling";"Larva";372;1
"Unit";"Zergling";"Larva";373;1
"Unit";"Zergling";"Larva";374;1
"Unit";"Zergling";"Larva";375;1
"Unit";"Zergling";"Larva";376;1
"Unit";"Zergling";"Larva";377;1
"Unit";"Zergling";"Larva";378;1
"Unit";"Zergling";"Larva";379;1
"Unit";"Zergling";"Larva";380;1
"Unit";"Zergling";"Larva";381;1
"Unit";"Zergling";"Larva";382;1
"Unit";"Zergling";"Larva";383;1
"Building";"CreepTumor";NA;384;0
"Building";"CreepTumorQueen";NA;384;0
"Building";"CreepTumorQueen";NA;384;0
"Building";"CreepTumor";NA;384;0
"Building";"CreepTumor";NA;384;0
"Building";"CreepTumorQueen";NA;384;0
"Building";"CreepTumor";NA;384;0
"Building";"Extractor";NA;389;0
"Unit";"Baneling";"Zergling";389;0
"Unit";"Baneling";"Zergling";389;0
"Unit";"Baneling";"Zergling";389;0
"Unit";"Baneling";"Zergling";389;0
"Unit";"Baneling";"Zergling";389;0
"Unit";"Baneling";"Zergling";389;0
"Unit";"Baneling";"Zergling";389;0
"Unit";"Baneling";"Zergling";389;0
"Unit";"Baneling";"Zergling";389;0
"Unit";"Baneling";"Zergling";389;0
"Unit";"Baneling";"Zergling";389;0
"Unit";"Baneling";"Zergling";389;0
"Unit";"Baneling";"Zergling";389;0
"Unit";"Baneling";"Zergling";389;0
"Unit";"Baneling";"Zergling";389;0
"Unit";"Zergling";"Larva";389;1
"Unit";"Zergling";"Larva";390;1
"Unit";"Zergling";"Larva";391;1
"Unit";"Zergling";"Larva";392;1
"Unit";"Zergling";"Larva";393;1
"Unit";"Zergling";"Larva";394;1
"Unit";"Zergling";"Larva";395;1
"Unit";"Zergling";"Larva";396;1
"Unit";"Zergling";"Larva";397;1
"Unit";"Zergling";"Larva";398;1
"Unit";"Zergling";"Larva";399;1
"Unit";"Zergling";"Larva";400;1
"Unit";"Zergling";"Larva";401;1
"Unit";"Zergling";"Larva";402;1
"Unit";"Zergling";"Larva";403;1
"Unit";"Zergling";"Larva";404;1
"Unit";"Zergling";"Larva";405;1
"Unit";"Zergling";"Larva";406;1
"Unit";"Zergling";"Larva";407;1
"Unit";"Zergling";"Larva";408;1
"Unit";"Zergling";"Larva";409;1
"Unit";"Zergling";"Larva";410;1
"Unit";"Zergling";"Larva";411;1
"Unit";"Zergling";"Larva";412;1
"Unit";"Zergling";"Larva";413;1
"Unit";"Zergling";"Larva";414;1
"Unit";"Zergling";"Larva";415;1
"Unit";"Zergling";"Larva";416;1
"Unit";"Zergling";"Larva";417;1
"Unit";"Zergling";"Larva";418;1
"Unit";"Zergling";"Larva";419;1
"Unit";"Zergling";"Larva";420;1
"Unit";"Zergling";"Larva";421;1
"Unit";"Zergling";"Larva";422;1
"Unit";"Zergling";"Larva";423;1
"Unit";"Zergling";"Larva";424;1
"Unit";"Zergling";"Larva";425;1
"Unit";"Zergling";"Larva";426;1
"Unit";"Zergling";"Larva";427;1
"Unit";"Zergling";"Larva";428;1
"Unit";"Ultralisk";"Larva";433;6
"Building";"Hatchery";NA;439;0
"Upgrade";"ChitinousPlating";"UltraliskCavern";439;0
"Unit";"Ultralisk";"Larva";442;6
"Building";"CreepTumor";NA;448;0
"Building";"CreepTumor";NA;448;0
"Building";"CreepTumor";NA;448;0
"Building";"CreepTumor";NA;448;0
"Building";"CreepTumor";NA;448;0
"Building";"CreepTumor";NA;448;0
"Unit";"Baneling";"Zergling";448;0
"Unit";"Baneling";"Zergling";448;0
"Unit";"Baneling";"Zergling";448;0
"Unit";"Baneling";"Zergling";448;0
"Unit";"Baneling";"Zergling";448;0
"Unit";"Zergling";"Larva";448;1
"Unit";"Zergling";"Larva";449;1
"Unit";"Zergling";"Larva";450;1
"Unit";"Zergling";"Larva";451;1
"Unit";"Zergling";"Larva";452;1
"Unit";"Zergling";"Larva";453;1
"Unit";"Ultralisk";"Larva";454;6
"Unit";"Zergling";"Larva";460;1
"Unit";"Zergling";"Larva";461;1
"Unit";"Zergling";"Larva";462;1
"Unit";"Zergling";"Larva";463;1
"Unit";"Zergling";"Larva";464;1
"Unit";"Zergling";"Larva";465;1
"Unit";"Zergling";"Larva";466;1
"Unit";"Zergling";"Larva";467;1
"Unit";"Zergling";"Larva";468;1
"Unit";"Zergling";"Larva";469;1
"Unit";"Zergling";"Larva";470;1
"Unit";"Zergling";"Larva";471;1
"Unit";"Zergling";"Larva";472;1
"Unit";"Zergling";"Larva";473;1
"Unit";"Zergling";"Larva";474;1
"Unit";"Zergling";"Larva";475;1
"Unit";"Zergling";"Larva";476;1
"Unit";"Zergling";"Larva";477;1
"Building";"Spire";NA;478;0
"Building";"CreepTumorQueen";NA;478;0
"Unit";"Zergling";"Larva";478;1
"Unit";"Zergling";"Larva";479;1
"Unit";"Zergling";"Larva";480;1
"Unit";"Zergling";"Larva";481;1
"Unit";"Zergling";"Larva";482;1
"Unit";"Zergling";"Larva";483;1
"Unit";"Zergling";"Larva";484;1
"Unit";"Zergling";"Larva";485;1
"Unit";"Zergling";"Larva";486;1
"Unit";"Zergling";"Larva";487;1
"Unit";"Zergling";"Larva";488;1
"Unit";"Zergling";"Larva";489;1
"Unit";"Zergling";"Larva";490;1
"Unit";"Zergling";"Larva";491;1
"Unit";"Zergling";"Larva";492;1
"Unit";"Zergling";"Larva";493;1
"Unit";"Zergling";"Larva";494;1
"Unit";"Zergling";"Larva";495;1
"Unit";"Zergling";"Larva";496;1
"Unit";"Zergling";"Larva";497;1
"Unit";"Zergling";"Larva";498;1
"Unit";"Zergling";"Larva";499;1
"Unit";"Zergling";"Larva";500;1
"Unit";"Zergling";"Larva";501;1
"Unit";"Zergling";"Larva";502;1
"Unit";"Zergling";"Larva";503;1
"Unit";"Zergling";"Larva";504;1
"Unit";"Zergling";"Larva";505;1
"Unit";"Zergling";"Larva";506;1
"Unit";"Zergling";"Larva";507;1
"Unit";"Zergling";"Larva";508;1
"Unit";"Zergling";"Larva";509;1
"Unit";"Zergling";"Larva";510;1
"Unit";"Zergling";"Larva";511;1
"Unit";"Zergling";"Larva";512;1
"Unit";"Zergling";"Larva";513;1
"Unit";"Zergling";"Larva";514;1
"Unit";"Zergling";"Larva";515;1
"Unit";"Zergling";"Larva";516;1
"Unit";"Zergling";"Larva";517;1
"Unit";"Zergling";"Larva";518;1
"Unit";"Zergling";"Larva";519;1
"Unit";"Zergling";"Larva";520;1
"Unit";"Zergling";"Larva";521;1
"Unit";"Zergling";"Larva";522;1
"Unit";"Zergling";"Larva";523;1
"Unit";"Ultralisk";"Larva";524;6
"Unit";"Zergling";"Larva";530;1
"Unit";"Zergling";"Larva";531;1
"Unit";"Zergling";"Larva";532;1
"Unit";"Zergling";"Larva";533;1
"Unit";"Zergling";"Larva";534;1
"Unit";"Zergling";"Larva";535;1
"Unit";"Queen";"Hatchery";536;2
"Unit";"Viper";"Larva";538;3
"Unit";"Viper";"Larva";541;3
"Unit";"Viper";"Larva";544;3
"Unit";"Zergling";"Larva";547;1
"Unit";"Zergling";"Larva";548;1
"Unit";"Zergling";"Larva";549;1
"Unit";"Zergling";"Larva";550;1
"Unit";"Zergling";"Larva";551;1
"Unit";"Zergling";"Larva";552;1
"Unit";"Zergling";"Larva";553;1
"Unit";"Zergling";"Larva";554;1
"Unit";"Zergling";"Larva";555;1
"Unit";"Zergling";"Larva";556;1
"Building";"CreepTumor";NA;557;0
"Building";"CreepTumor";NA;557;0
"Building";"CreepTumor";NA;557;0
"Building";"CreepTumor";NA;557;0
"Building";"CreepTumor";NA;557;0
"Building";"CreepTumor";NA;557;0
"Building";"CreepTumor";NA;557;0
"Unit";"Corruptor";"Larva";557;2
"Unit";"Corruptor";"Larva";559;2
"Unit";"Corruptor";"Larva";561;2
"Unit";"Baneling";"Zergling";563;0
"Unit";"Baneling";"Zergling";563;0
"Unit";"Baneling";"Zergling";563;0
"Unit";"Baneling";"Zergling";563;0
"Unit";"Baneling";"Zergling";563;0
"Unit";"Baneling";"Zergling";563;0
"Unit";"Baneling";"Zergling";563;0
"Unit";"Baneling";"Zergling";563;0
"Unit";"Baneling";"Zergling";563;0
"Unit";"Baneling";"Zergling";563;0
"Unit";"Baneling";"Zergling";563;0
"Unit";"Baneling";"Zergling";563;0
"Unit";"Baneling";"Zergling";563;0
"Unit";"Baneling";"Zergling";563;0
"Unit";"Baneling";"Zergling";563;0
"Unit";"Baneling";"Zergling";563;0
"Unit";"Baneling";"Zergling";563;0
"Unit";"Baneling";"Zergling";563;0
"Unit";"Baneling";"Zergling";563;0
"Unit";"Baneling";"Zergling";563;0
"Building";"SpineCrawler";NA;563;0
"Building";"SporeCrawler";NA;563;0
"Building";"SpineCrawler";NA;563;0
"Building";"Extractor";NA;563;0
"Building";"CreepTumor";NA;566;0
"Building";"CreepTumor";NA;566;0
"Unit";"Corruptor";"Larva";566;2
"Building";"CreepTumorQueen";NA;568;0
"Building";"CreepTumor";NA;568;0
"Building";"CreepTumor";NA;568;0
"Building";"CreepTumor";NA;568;0
"Building";"CreepTumorQueen";NA;568;0
"Building";"CreepTumor";NA;568;0
"Unit";"Baneling";"Zergling";569;0
"Unit";"Baneling";"Zergling";569;0
"Unit";"Baneling";"Zergling";569;0
"Unit";"Baneling";"Zergling";569;0
"Unit";"Baneling";"Zergling";569;0
"Unit";"Baneling";"Zergling";569;0
"Unit";"Baneling";"Zergling";569;0
"Unit";"Baneling";"Zergling";569;0
"Unit";"Baneling";"Zergling";569;0
"Unit";"Baneling";"Zergling";569;0
"Unit";"Baneling";"Zergling";569;0
"Unit";"Baneling";"Zergling";569;0
"Unit";"Baneling";"Zergling";569;0
"Unit";"Baneling";"Zergling";569;0
"Unit";"Baneling";"Zergling";569;0
"Unit";"Baneling";"Zergling";569;0
"Unit";"Baneling";"Zergling";569;0
"Unit";"Baneling";"Zergling";569;0
"Unit";"Baneling";"Zergling";569;0
"Unit";"Baneling";"Zergling";569;0
"Unit";"Corruptor";"Larva";569;2
"Unit";"Corruptor";"Larva";571;2
"Unit";"Corruptor";"Larva";573;2
"Unit";"Corruptor";"Larva";575;2
"Unit";"Corruptor";"Larva";577;2
"Unit";"Corruptor";"Larva";579;2
"Unit";"Zergling";"Larva";581;1
"Unit";"Zergling";"Larva";582;1
"Unit";"Zergling";"Larva";583;1
"Unit";"Zergling";"Larva";584;1
"Unit";"Zergling";"Larva";585;1
"Unit";"Zergling";"Larva";586;1
"Unit";"Zergling";"Larva";587;1
"Unit";"Zergling";"Larva";588;1
"Unit";"Zergling";"Larva";589;1
"Unit";"Zergling";"Larva";590;1
"Unit";"Zergling";"Larva";591;1
"Unit";"Zergling";"Larva";592;1
"Unit";"Zergling";"Larva";593;1
"Unit";"Zergling";"Larva";594;1
"Unit";"Zergling";"Larva";595;1
"Unit";"Zergling";"Larva";596;1
"Unit";"Zergling";"Larva";597;1
"Unit";"Zergling";"Larva";598;1
"Unit";"Zergling";"Larva";599;1
"Unit";"Zergling";"Larva";600;1
"Unit";"Zergling";"Larva";601;1
"Unit";"Zergling";"Larva";602;1
"Unit";"Zergling";"Larva";603;1
"Unit";"Zergling";"Larva";604;1
"Unit";"Zergling";"Larva";605;1
"Unit";"Zergling";"Larva";606;1
"Unit";"Zergling";"Larva";607;1
"Unit";"Zergling";"Larva";608;1
"Unit";"Zergling";"Larva";609;1
"Unit";"Zergling";"Larva";610;1
"Unit";"Zergling";"Larva";611;1
"Unit";"Zergling";"Larva";612;1
"Unit";"Zergling";"Larva";613;1
"Unit";"Zergling";"Larva";614;1
"Unit";"Zergling";"Larva";615;1
"Unit";"Zergling";"Larva";616;1
"Unit";"Zergling";"Larva";617;1
"Unit";"Zergling";"Larva";618;1
"Unit";"Zergling";"Larva";619;1
"Unit";"Zergling";"Larva";620;1
"Unit";"Zergling";"Larva";621;1
"Unit";"Zergling";"Larva";622;1
"Unit";"Zergling";"Larva";623;1
"Unit";"Zergling";"Larva";624;1
"Unit";"Overlord";"Larva";625;0
"Unit";"Overlord";"Larva";625;0
"Unit";"Overlord";"Larva";625;0
"Building";"Extractor";NA;625;0
"Building";"CreepTumor";NA;626;0
"Building";"CreepTumor";NA;626;0
"Building";"CreepTumor";NA;626;0
"Building";"CreepTumor";NA;626;0
"Building";"CreepTumor";NA;626;0
"Building";"CreepTumor";NA;626;0
"Building";"Hatchery";NA;626;0
"Unit";"Corruptor";"Larva";626;2
"Unit";"Corruptor";"Larva";628;2
"Unit";"Zergling";"Larva";630;1
"Unit";"Zergling";"Larva";631;1
"Unit";"Zergling";"Larva";632;1
"Unit";"Zergling";"Larva";633;1
"Unit";"Zergling";"Larva";634;1
"Unit";"Zergling";"Larva";635;1
"Unit";"Zergling";"Larva";636;1
"Unit";"Zergling";"Larva";637;1
"Unit";"Zergling";"Larva";638;1
"Unit";"Zergling";"Larva";639;1
"Unit";"Zergling";"Larva";640;1
"Unit";"Zergling";"Larva";641;1
"Unit";"Zergling";"Larva";642;1
"Unit";"Zergling";"Larva";643;1
"Unit";"Zergling";"Larva";644;1
"Unit";"Zergling";"Larva";645;1
"Unit";"Zergling";"Larva";646;1
"Unit";"Zergling";"Larva";647;1
"Unit";"Baneling";"Zergling";648;0
"Unit";"Baneling";"Zergling";648;0
"Unit";"Baneling";"Zergling";648;0
"Unit";"Baneling";"Zergling";648;0
"Unit";"Baneling";"Zergling";648;0
"Unit";"Baneling";"Zergling";648;0
"Unit";"Baneling";"Zergling";648;0
"Unit";"Baneling";"Zergling";648;0
"Unit";"Baneling";"Zergling";648;0
"Unit";"Baneling";"Zergling";648;0
"Unit";"Baneling";"Zergling";648;0
"Unit";"Baneling";"Zergling";648;0
"Unit";"Baneling";"Zergling";648;0
"Unit";"Baneling";"Zergling";648;0
"Unit";"Baneling";"Zergling";648;0
"Building";"Extractor";NA;648;0
"Building";"CreepTumor";NA;649;0
"Unit";"Baneling";"Zergling";649;0
"Unit";"Baneling";"Zergling";649;0
"Unit";"Baneling";"Zergling";649;0
"Unit";"Baneling";"Zergling";649;0
"Unit";"Baneling";"Zergling";649;0
"Unit";"Baneling";"Zergling";649;0
"Unit";"Baneling";"Zergling";649;0
"Unit";"Baneling";"Zergling";649;0
"Unit";"Baneling";"Zergling";649;0
"Unit";"Baneling";"Zergling";649;0
"Unit";"Baneling";"Zergling";649;0
"Unit";"Zergling";"Larva";649;1
"Unit";"Zergling";"Larva";650;1
"Unit";"Zergling";"Larva";651;1
"Unit";"Zergling";"Larva";652;1
"Unit";"Zergling";"Larva";653;1
"Unit";"Zergling";"Larva";654;1
"Unit";"Zergling";"Larva";655;1
"Unit";"Zergling";"Larva";656;1
"Unit";"Zergling";"Larva";657;1
"Unit";"Zergling";"Larva";658;1
"Unit";"Zergling";"Larva";659;1
"Unit";"Zergling";"Larva";660;1
"Unit";"Zergling";"Larva";661;1
"Unit";"Zergling";"Larva";662;1
"Unit";"Zergling";"Larva";663;1
"Unit";"Zergling";"Larva";664;1
"Unit";"Zergling";"Larva";665;1
"Unit";"Zergling";"Larva";666;1
"Unit";"Zergling";"Larva";667;1
"Unit";"Zergling";"Larva";668;1
"Unit";"Zergling";"Larva";669;1
"Unit";"Zergling";"Larva";670;1
"Unit";"Zergling";"Larva";671;1
"Unit";"Zergling";"Larva";672;1
"Unit";"Zergling";"Larva";673;1
"Unit";"Zergling";"Larva";674;1
"Unit";"Zergling";"Larva";675;1
"Unit";"Zergling";"Larva";676;1
"Unit";"Zergling";"Larva";677;1
"Unit";"Zergling";"Larva";678;1
"Unit";"Zergling";"Larva";679;1
"Unit";"Zergling";"Larva";680;1
"Unit";"Zergling";"Larva";681;1
"Unit";"Zergling";"Larva";682;1
"Unit";"Zergling";"Larva";683;1
"Unit";"Zergling";"Larva";684;1
"Unit";"Zergling";"Larva";685;1
"Unit";"Zergling";"Larva";686;1
"Unit";"Zergling";"Larva";687;1
"Unit";"Zergling";"Larva";688;1
"Unit";"Zergling";"Larva";689;1
"Unit";"Zergling";"Larva";690;1
"Unit";"Zergling";"Larva";691;1
"Unit";"Zergling";"Larva";692;1
"Unit";"Zergling";"Larva";693;1
"Unit";"Zergling";"Larva";694;1
"Unit";"Zergling";"Larva";695;1
"Unit";"Zergling";"Larva";696;1
"Unit";"Zergling";"Larva";697;1
"Unit";"Zergling";"Larva";698;1
"Unit";"Zergling";"Larva";699;1
"Unit";"Zergling";"Larva";700;1
"Unit";"Zergling";"Larva";701;1
"Unit";"Zergling";"Larva";702;1
"Unit";"Zergling";"Larva";703;1
"Unit";"Zergling";"Larva";704;1
"Unit";"Zergling";"Larva";705;1
"Unit";"Zergling";"Larva";706;1
"Unit";"Zergling";"Larva";707;1
"Unit";"Zergling";"Larva";708;1
"Unit";"Zergling";"Larva";709;1
"Unit";"Zergling";"Larva";710;1
"Unit";"Zergling";"Larva";711;1
"Unit";"Zergling";"Larva";712;1
"Unit";"Zergling";"Larva";713;1
"Unit";"Zergling";"Larva";714;1
"Unit";"Zergling";"Larva";715;1
"Unit";"Zergling";"Larva";716;1
"Unit";"Zergling";"Larva";717;1
"Unit";"Zergling";"Larva";718;1
"Unit";"Zergling";"Larva";719;1
"Unit";"Zergling";"Larva";720;1
"Unit";"Zergling";"Larva";721;1
"Unit";"Zergling";"Larva";722;1
"Unit";"Zergling";"Larva";723;1
"Unit";"Zergling";"Larva";724;1
"Unit";"Zergling";"Larva";725;1
"Unit";"Zergling";"Larva";726;1
"Unit";"Zergling";"Larva";727;1
"Unit";"Zergling";"Larva";728;1
"Unit";"Zergling";"Larva";729;1
"Unit";"Zergling";"Larva";730;1
"Unit";"Zergling";"Larva";731;1
"Unit";"Zergling";"Larva";732;1
"Unit";"Zergling";"Larva";733;1
"Unit";"Zergling";"Larva";734;1
"Unit";"Zergling";"Larva";735;1
"Unit";"Zergling";"Larva";736;1
"Unit";"Zergling";"Larva";737;1
"Unit";"Zergling";"Larva";738;1
"Unit";"Ultralisk";"Larva";739;6
"Unit";"Zergling";"Larva";745;1
"Unit";"Zergling";"Larva";746;1
"Unit";"Zergling";"Larva";747;1
"Unit";"Zergling";"Larva";748;1
"Unit";"Zergling";"Larva";749;1
"Unit";"Zergling";"Larva";750;1
"Unit";"Zergling";"Larva";751;1
"Unit";"Zergling";"Larva";752;1
"Unit";"Zergling";"Larva";753;1
"Unit";"Zergling";"Larva";754;1
"Unit";"Baneling";"Zergling";755;0
"Unit";"Baneling";"Zergling";755;0
"Unit";"Baneling";"Zergling";755;0
"Unit";"Corruptor";"Larva";755;2
"Unit";"Corruptor";"Larva";757;2
"Unit";"Zergling";"Larva";759;1
"Unit";"Zergling";"Larva";760;1
"Unit";"Zergling";"Larva";761;1
"Unit";"Zergling";"Larva";762;1
"Unit";"Zergling";"Larva";763;1
"Unit";"Zergling";"Larva";764;1
"Unit";"Zergling";"Larva";765;1
"Unit";"Zergling";"Larva";766;1
"Unit";"Zergling";"Larva";767;1
"Unit";"Zergling";"Larva";768;1
"Unit";"Zergling";"Larva";769;1
"Unit";"Zergling";"Larva";770;1
"Unit";"Zergling";"Larva";771;1
"Unit";"Zergling";"Larva";772;1
"Unit";"Baneling";"Zergling";773;0
"Unit";"Baneling";"Zergling";773;0
"Unit";"Baneling";"Zergling";773;0
"Unit";"Baneling";"Zergling";773;0
"Unit";"Baneling";"Zergling";773;0
"Unit";"Baneling";"Zergling";773;0
"Unit";"Baneling";"Zergling";773;0
"Unit";"Baneling";"Zergling";773;0
"Unit";"Baneling";"Zergling";773;0
"Unit";"Baneling";"Zergling";773;0
"Unit";"Baneling";"Zergling";773;0
"Unit";"Baneling";"Zergling";773;0
"Unit";"Baneling";"Zergling";773;0
"Unit";"Baneling";"Zergling";773;0
"Unit";"Baneling";"Zergling";773;0
"Unit";"Baneling";"Zergling";773;0
"Unit";"Baneling";"Zergling";773;0
"Unit";"Baneling";"Zergling";773;0
"Unit";"Baneling";"Zergling";773;0
"Unit";"Baneling";"Zergling";773;0
"Unit";"Baneling";"Zergling";773;0
"Unit";"Baneling";"Zergling";773;0
"Building";"CreepTumor";NA;773;0
"Unit";"Baneling";"Zergling";773;0
"Unit";"Baneling";"Zergling";773;0
"Unit";"Baneling";"Zergling";773;0
"Unit";"Baneling";"Zergling";773;0
"Unit";"Baneling";"Zergling";773;0
"Unit";"Baneling";"Zergling";773;0
"Unit";"Baneling";"Zergling";773;0
"Unit";"Baneling";"Zergling";773;0
"Unit";"Baneling";"Zergling";773;0
"Unit";"Zergling";"Larva";773;1
"Unit";"Zergling";"Larva";774;1
"Unit";"Zergling";"Larva";775;1
"Unit";"Zergling";"Larva";776;1
"Unit";"Baneling";"Zergling";777;0
"Unit";"Baneling";"Zergling";777;0
"Unit";"Baneling";"Zergling";777;0
"Unit";"Baneling";"Zergling";777;0
"Unit";"Baneling";"Zergling";777;0
"Unit";"Baneling";"Zergling";777;0
"Unit";"Zergling";"Larva";777;1
"Unit";"Zergling";"Larva";778;1
"Unit";"Zergling";"Larva";779;1
"Unit";"Zergling";"Larva";780;1
"Unit";"Zergling";"Larva";781;1
"Unit";"Zergling";"Larva";782;1
"Unit";"Zergling";"Larva";783;1
"Unit";"Zergling";"Larva";784;1
"Unit";"Zergling";"Larva";785;1
"Unit";"Zergling";"Larva";786;1
"Unit";"Zergling";"Larva";787;1
"Unit";"Zergling";"Larva";788;1
"Unit";"Zergling";"Larva";789;1
"Unit";"Zergling";"Larva";790;1
"Unit";"Zergling";"Larva";791;1
"Unit";"Zergling";"Larva";792;1
"Unit";"Zergling";"Larva";793;1
"Unit";"Zergling";"Larva";794;1
"Unit";"Zergling";"Larva";795;1
"Unit";"Zergling";"Larva";796;1
"Unit";"Zergling";"Larva";797;1
"Unit";"Zergling";"Larva";798;1
"Unit";"Zergling";"Larva";799;1
"Unit";"Zergling";"Larva";800;1
"Unit";"Zergling";"Larva";801;1
"Unit";"Zergling";"Larva";802;1
"Unit";"Zergling";"Larva";803;1
"Unit";"Zergling";"Larva";804;1
"Unit";"Zergling";"Larva";805;1
"Unit";"Zergling";"Larva";806;1
"Unit";"Zergling";"Larva";807;1
"Unit";"Zergling";"Larva";808;1
"Unit";"Zergling";"Larva";809;1
"Unit";"Zergling";"Larva";810;1
"Unit";"Zergling";"Larva";811;1
"Unit";"Zergling";"Larva";812;1
"Unit";"Corruptor";"Larva";813;2
"Unit";"Corruptor";"Larva";815;2
"Unit";"Corruptor";"Larva";817;2
"Unit";"Zergling";"Larva";819;1
"Unit";"Zergling";"Larva";820;1
"Unit";"Zergling";"Larva";821;1
"Unit";"Zergling";"Larva";822;1
"Unit";"Zergling";"Larva";823;1
"Unit";"Zergling";"Larva";824;1
"Unit";"Zergling";"Larva";825;1
"Unit";"Zergling";"Larva";826;1
"Unit";"Zergling";"Larva";827;1
"Unit";"Zergling";"Larva";828;1
"Unit";"Baneling";"Zergling";829;0
"Unit";"Baneling";"Zergling";829;0
"Unit";"Baneling";"Zergling";829;0
"Unit";"Baneling";"Zergling";829;0
"Unit";"Baneling";"Zergling";829;0
"Unit";"Baneling";"Zergling";829;0
"Unit";"Baneling";"Zergling";829;0
"Unit";"Baneling";"Zergling";829;0
"Unit";"Baneling";"Zergling";829;0
"Unit";"Baneling";"Zergling";829;0
"Building";"CreepTumor";NA;829;0
"Building";"CreepTumor";NA;829;0
"Unit";"Baneling";"Zergling";832;0
"Unit";"Baneling";"Zergling";832;0
"Unit";"Baneling";"Zergling";832;0
"Unit";"Baneling";"Zergling";832;0
"Unit";"Baneling";"Zergling";832;0
"Unit";"Baneling";"Zergling";832;0
"Unit";"Baneling";"Zergling";832;0
"Unit";"Baneling";"Zergling";832;0
"Unit";"Baneling";"Zergling";832;0
"Unit";"Baneling";"Zergling";832;0
"Unit";"Baneling";"Zergling";832;0
"Unit";"Baneling";"Zergling";832;0
"Unit";"Corruptor";"Larva";832;2
"Unit";"Corruptor";"Larva";834;2
"Unit";"Corruptor";"Larva";836;2
"Unit";"Corruptor";"Larva";838;2
"Unit";"Zergling";"Larva";840;1
"Unit";"Zergling";"Larva";841;1
"Unit";"Zergling";"Larva";842;1
"Unit";"Zergling";"Larva";843;1
"Unit";"Zergling";"Larva";844;1
"Unit";"Zergling";"Larva";845;1
"Unit";"Zergling";"Larva";846;1
"Unit";"Zergling";"Larva";847;1
"Unit";"Zergling";"Larva";848;1
"Unit";"Zergling";"Larva";849;1
"Unit";"Zergling";"Larva";850;1
"Unit";"Zergling";"Larva";851;1
"Unit";"Zergling";"Larva";852;1
"Unit";"Zergling";"Larva";853;1
"Unit";"Zergling";"Larva";854;1
"Unit";"Zergling";"Larva";855;1
"Unit";"Zergling";"Larva";856;1
"Unit";"Zergling";"Larva";857;1
"Unit";"Zergling";"Larva";858;1
"Unit";"Zergling";"Larva";859;1
"Unit";"Zergling";"Larva";860;1
"Unit";"Zergling";"Larva";861;1
"Unit";"Zergling";"Larva";862;1
"Unit";"Zergling";"Larva";863;1
"Unit";"Corruptor";"Larva";865;2
"Unit";"Corruptor";"Larva";867;2
"Unit";"Corruptor";"Larva";869;2
"Unit";"Corruptor";"Larva";871;2
"Unit";"Corruptor";"Larva";876;2
"Unit";"Baneling";"Zergling";878;0
"Unit";"Baneling";"Zergling";878;0
"Unit";"Baneling";"Zergling";878;0
"Unit";"Baneling";"Zergling";878;0
"Unit";"Baneling";"Zergling";878;0
"Building";"CreepTumor";NA;878;0
"Building";"CreepTumor";NA;878;0
"Building";"Hatchery";NA;878;0
"Unit";"Zergling";"Larva";878;1
"Unit";"Zergling";"Larva";879;1
"Unit";"Zergling";"Larva";880;1
"Unit";"Zergling";"Larva";881;1
"Unit";"Zergling";"Larva";882;1
"Unit";"Zergling";"Larva";883;1
"Unit";"Zergling";"Larva";884;1
"Unit";"Zergling";"Larva";885;1
"Unit";"Zergling";"Larva";886;1
"Unit";"Zergling";"Larva";887;1
"Unit";"Zergling";"Larva";888;1
"Unit";"Zergling";"Larva";889;1
"Unit";"Zergling";"Larva";890;1
"Unit";"Zergling";"Larva";891;1
"Unit";"Zergling";"Larva";892;1
"Unit";"Zergling";"Larva";893;1
"Unit";"Zergling";"Larva";894;1
"Unit";"Zergling";"Larva";895;1
"Unit";"Zergling";"Larva";896;1
"Unit";"Zergling";"Larva";897;1
"Unit";"Zergling";"Larva";898;1
"Unit";"Zergling";"Larva";899;1
"Unit";"Zergling";"Larva";900;1
"Unit";"Zergling";"Larva";901;1
"Unit";"Zergling";"Larva";902;1
"Unit";"Zergling";"Larva";903;1
"Unit";"Zergling";"Larva";904;1
"Unit";"Zergling";"Larva";905;1
"Unit";"Zergling";"Larva";906;1
"Unit";"Zergling";"Larva";907;1
"Upgrade";"Burrow";"Hatchery";908;0
"Building";"Extractor";NA;908;0
"Unit";"Baneling";"Zergling";909;0
"Unit";"Baneling";"Zergling";909;0
"Unit";"Baneling";"Zergling";909;0
"Unit";"Baneling";"Zergling";909;0
"Unit";"Baneling";"Zergling";909;0
"Unit";"Baneling";"Zergling";909;0
"Unit";"Baneling";"Zergling";909;0
"Unit";"Baneling";"Zergling";909;0
"Unit";"Baneling";"Zergling";909;0
"Unit";"Baneling";"Zergling";909;0
"Unit";"Overlord";"Larva";909;0
"Unit";"Overlord";"Larva";909;0
"Unit";"Overlord";"Larva";909;0
"Unit";"Baneling";"Zergling";909;0
"Unit";"Baneling";"Zergling";912;0
"Unit";"Baneling";"Zergling";912;0
"Unit";"Zergling";"Larva";912;1
"Unit";"Zergling";"Larva";913;1
"Unit";"Zergling";"Larva";914;1
"Unit";"Zergling";"Larva";915;1
"Unit";"Zergling";"Larva";916;1
"Unit";"Zergling";"Larva";917;1
"Unit";"Zergling";"Larva";918;1
"Unit";"Zergling";"Larva";919;1
"Unit";"Zergling";"Larva";920;1
"Unit";"Zergling";"Larva";921;1
"Unit";"Zergling";"Larva";922;1
"Unit";"Zergling";"Larva";923;1
"Unit";"Zergling";"Larva";924;1
"Unit";"Zergling";"Larva";925;1
"Unit";"Zergling";"Larva";926;1
"Unit";"Zergling";"Larva";927;1
"Unit";"Zergling";"Larva";928;1
"Unit";"Zergling";"Larva";929;1
"Unit";"Zergling";"Larva";930;1
"Unit";"Zergling";"Larva";931;1
"Unit";"Corruptor";"Larva";932;2
"Unit";"Corruptor";"Larva";934;2
"Unit";"Baneling";"Zergling";936;0
"Unit";"Baneling";"Zergling";936;0
"Unit";"Baneling";"Zergling";936;0
"Building";"Extractor";NA;936;0
"Unit";"Viper";"Larva";936;3
"Unit";"Viper";"Larva";939;3
"Unit";"Viper";"Larva";942;3
"Unit";"Viper";"Larva";945;3
"Unit";"Viper";"Larva";948;3
"Unit";"Zergling";"Larva";951;1
"Unit";"Zergling";"Larva";952;1
"Unit";"Zergling";"Larva";953;1
"Unit";"Zergling";"Larva";954;1
"Unit";"Zergling";"Larva";955;1
"Unit";"Zergling";"Larva";956;1
"Unit";"Zergling";"Larva";957;1
"Unit";"Zergling";"Larva";958;1
"Unit";"Zergling";"Larva";959;1
"Unit";"Zergling";"Larva";960;1
"Unit";"Zergling";"Larva";961;1
"Unit";"Zergling";"Larva";962;1
"Unit";"Zergling";"Larva";963;1
"Unit";"Zergling";"Larva";964;1
"Unit";"Zergling";"Larva";965;1
"Unit";"Zergling";"Larva";966;1
"Unit";"Zergling";"Larva";967;1
"Unit";"Zergling";"Larva";968;1
"Building";"Hatchery";NA;969;0
"Unit";"Zergling";"Larva";969;1
"Unit";"Zergling";"Larva";970;1
"Unit";"Zergling";"Larva";971;1
"Unit";"Zergling";"Larva";972;1
"Unit";"Zergling";"Larva";973;1
"Unit";"Zergling";"Larva";974;1
"Unit";"Zergling";"Larva";975;1
"Unit";"Zergling";"Larva";976;1
"Unit";"Zergling";"Larva";977;1
"Unit";"Zergling";"Larva";978;1
"Unit";"Zergling";"Larva";979;1
"Unit";"Zergling";"Larva";980;1
"Unit";"Zergling";"Larva";981;1
"Unit";"Zergling";"Larva";982;1
"Unit";"Zergling";"Larva";983;1
"Unit";"Zergling";"Larva";984;1
"Unit";"Zergling";"Larva";985;1
"Unit";"Zergling";"Larva";986;1
"Unit";"Zergling";"Larva";987;1
"Unit";"Zergling";"Larva";988;1
"Unit";"Zergling";"Larva";989;1
"Unit";"Zergling";"Larva";990;1
"Unit";"Zergling";"Larva";991;1
"Unit";"Zergling";"Larva";992;1
"Unit";"Zergling";"Larva";993;1
"Unit";"Zergling";"Larva";994;1
"Unit";"Zergling";"Larva";995;1
"Unit";"Zergling";"Larva";996;1
"Unit";"Zergling";"Larva";997;1
"Unit";"Zergling";"Larva";998;1
"Unit";"Zergling";"Larva";999;1
"Unit";"Zergling";"Larva";1000;1
"Unit";"Zergling";"Larva";1001;1
"Unit";"Zergling";"Larva";1002;1
"Unit";"Zergling";"Larva";1003;1
"Unit";"Zergling";"Larva";1004;1
"Unit";"Zergling";"Larva";1005;1
"Unit";"Zergling";"Larva";1006;1
"Unit";"Corruptor";"Larva";1007;2
"Unit";"Corruptor";"Larva";1009;2
"Unit";"Corruptor";"Larva";1011;2
"Unit";"Corruptor";"Larva";1013;2
"Unit";"Corruptor";"Larva";1015;2
"Unit";"Corruptor";"Larva";1017;2
"Unit";"Corruptor";"Larva";1019;2
"Unit";"Queen";"Hatchery";1021;2
"Building";"Extractor";NA;1023;0
"Unit";"Zergling";"Larva";1023;1
"Unit";"Zergling";"Larva";1024;1
"Unit";"Zergling";"Larva";1025;1
"Unit";"Zergling";"Larva";1026;1
"Unit";"Zergling";"Larva";1027;1
"Unit";"Zergling";"Larva";1028;1
"Unit";"Zergling";"Larva";1029;1
"Unit";"Zergling";"Larva";1030;1
"Unit";"Zergling";"Larva";1031;1
"Unit";"Zergling";"Larva";1032;1
"Unit";"Zergling";"Larva";1033;1
"Unit";"Zergling";"Larva";1034;1
"Unit";"Zergling";"Larva";1035;1
"Unit";"Zergling";"Larva";1036;1
"Unit";"Zergling";"Larva";1037;1
"Unit";"Zergling";"Larva";1038;1
"Unit";"Zergling";"Larva";1039;1
"Unit";"Zergling";"Larva";1040;1
"Unit";"Zergling";"Larva";1041;1
"Unit";"Zergling";"Larva";1042;1
"Unit";"Zergling";"Larva";1043;1
"Unit";"Zergling";"Larva";1044;1
"Unit";"Zergling";"Larva";1045;1
"Unit";"Zergling";"Larva";1046;1
"Unit";"Zergling";"Larva";1047;1
"Unit";"Zergling";"Larva";1048;1
"Unit";"Zergling";"Larva";1049;1
"Unit";"Zergling";"Larva";1050;1
"Unit";"Zergling";"Larva";1051;1
"Unit";"Zergling";"Larva";1052;1
"Unit";"Zergling";"Larva";1053;1
"Unit";"Zergling";"Larva";1054;1
"Unit";"Zergling";"Larva";1055;1
"Unit";"Zergling";"Larva";1056;1
"Unit";"Zergling";"Larva";1057;1
"Unit";"Zergling";"Larva";1058;1
"Unit";"Zergling";"Larva";1059;1
"Unit";"Zergling";"Larva";1060;1
"Unit";"Zergling";"Larva";1061;1
"Unit";"Zergling";"Larva";1062;1
"Unit";"Zergling";"Larva";1063;1
"Unit";"Zergling";"Larva";1064;1
"Unit";"Zergling";"Larva";1065;1
"Unit";"Zergling";"Larva";1066;1
"Unit";"Zergling";"Larva";1067;1
"Unit";"Zergling";"Larva";1068;1
"Unit";"Zergling";"Larva";1069;1
"Unit";"Zergling";"Larva";1070;1
"Unit";"Zergling";"Larva";1071;1
"Unit";"Zergling";"Larva";1072;1
"Unit";"Zergling";"Larva";1073;1
"Unit";"Zergling";"Larva";1074;1
"Unit";"Zergling";"Larva";1075;1
"Unit";"Zergling";"Larva";1076;1
"Unit";"Zergling";"Larva";1077;1
"Unit";"Zergling";"Larva";1078;1
"Unit";"Zergling";"Larva";1079;1
"Unit";"Zergling";"Larva";1080;1
"Unit";"Zergling";"Larva";1081;1
"Unit";"Zergling";"Larva";1082;1
"Unit";"Overlord";"Larva";1083;0
"Unit";"Overlord";"Larva";1083;0
"Unit";"Overlord";"Larva";1083;0
"Unit";"Overlord";"Larva";1083;0
"Unit";"Baneling";"Zergling";1083;0
"Unit";"Baneling";"Zergling";1083;0
"Unit";"Baneling";"Zergling";1083;0
"Unit";"Baneling";"Zergling";1083;0
"Unit";"Baneling";"Zergling";1083;0
"Unit";"Baneling";"Zergling";1083;0
"Unit";"Baneling";"Zergling";1083;0
"Unit";"Baneling";"Zergling";1083;0
"Unit";"Baneling";"Zergling";1083;0
"Unit";"Baneling";"Zergling";1083;0
"Unit";"Baneling";"Zergling";1083;0
"Unit";"Baneling";"Zergling";1083;0
"Unit";"Baneling";"Zergling";1083;0
"Unit";"Baneling";"Zergling";1083;0
"Unit";"Baneling";"Zergling";1083;0
"Unit";"Baneling";"Zergling";1083;0
"Unit";"Baneling";"Zergling";1083;0
"Unit";"Baneling";"Zergling";1083;0
"Unit";"Baneling";"Zergling";1083;0
"Unit";"Baneling";"Zergling";1083;0
"Unit";"Baneling";"Zergling";1083;0
"Unit";"Baneling";"Zergling";1083;0
"Unit";"Baneling";"Zergling";1083;0
"Unit";"Baneling";"Zergling";1083;0
"Unit";"Baneling";"Zergling";1083;0
"Building";"CreepTumorQueen";NA;1083;0
"Building";"CreepTumorQueen";NA;1083;0
"Building";"CreepTumorQueen";NA;1083;0
"Building";"Extractor";NA;1083;0
"Unit";"Zergling";"Larva";1088;1
"Unit";"Zergling";"Larva";1089;1
"Unit";"Zergling";"Larva";1090;1
"Unit";"Zergling";"Larva";1091;1
"Unit";"Zergling";"Larva";1092;1
"Unit";"Zergling";"Larva";1093;1
"Unit";"Zergling";"Larva";1094;1
"Unit";"Zergling";"Larva";1095;1
"Unit";"Zergling";"Larva";1096;1
"Unit";"Zergling";"Larva";1097;1
"Unit";"Zergling";"Larva";1098;1
"Unit";"Zergling";"Larva";1099;1
"Unit";"Zergling";"Larva";1100;1
"Unit";"Zergling";"Larva";1101;1
"Unit";"Zergling";"Larva";1102;1
"Unit";"Zergling";"Larva";1103;1
"Unit";"Zergling";"Larva";1104;1
"Unit";"Zergling";"Larva";1105;1
"Unit";"Zergling";"Larva";1106;1
"Unit";"Zergling";"Larva";1107;1
"Unit";"Zergling";"Larva";1108;1
"Unit";"Zergling";"Larva";1109;1
"Unit";"Zergling";"Larva";1110;1
"Unit";"Zergling";"Larva";1111;1
"Unit";"Zergling";"Larva";1112;1
"Unit";"Zergling";"Larva";1113;1
"Unit";"Zergling";"Larva";1114;1
"Unit";"Zergling";"Larva";1115;1
"Unit";"Zergling";"Larva";1116;1
"Unit";"Zergling";"Larva";1117;1
"Unit";"Zergling";"Larva";1118;1
"Unit";"Zergling";"Larva";1119;1
"Unit";"Zergling";"Larva";1120;1
"Unit";"Zergling";"Larva";1121;1
"Unit";"Zergling";"Larva";1122;1
"Unit";"Zergling";"Larva";1123;1
"Unit";"Zergling";"Larva";1124;1
"Unit";"Zergling";"Larva";1125;1
"Building";"Extractor";NA;1126;0
"Building";"Hatchery";NA;1126;0
"Building";"Extractor";NA;1126;0
"Unit";"Corruptor";"Larva";1126;2
"Building";"CreepTumor";NA;1128;0
"Building";"CreepTumor";NA;1128;0
"Building";"CreepTumor";NA;1128;0
"Unit";"Baneling";"Zergling";1128;0
"Unit";"Baneling";"Zergling";1128;0
"Unit";"Baneling";"Zergling";1128;0
"Unit";"Baneling";"Zergling";1128;0
"Unit";"Baneling";"Zergling";1128;0
"Unit";"Corruptor";"Larva";1128;2
"Unit";"Corruptor";"Larva";1130;2
"Unit";"Corruptor";"Larva";1132;2
"Unit";"Corruptor";"Larva";1134;2
"Unit";"Corruptor";"Larva";1136;2
"Unit";"Corruptor";"Larva";1138;2
"Unit";"Corruptor";"Larva";1140;2
"Unit";"Corruptor";"Larva";1142;2
"Unit";"Corruptor";"Larva";1144;2
"Unit";"Corruptor";"Larva";1146;2
"Unit";"Corruptor";"Larva";1148;2
"Unit";"Corruptor";"Larva";1150;2
"Unit";"Corruptor";"Larva";1152;2
"Unit";"Corruptor";"Larva";1154;2
"Unit";"Corruptor";"Larva";1156;2
"Unit";"Corruptor";"Larva";1158;2
"Unit";"Corruptor";"Larva";1160;2
"Unit";"Corruptor";"Larva";1162;2
"Unit";"Corruptor";"Larva";1164;2
"Unit";"Corruptor";"Larva";1166;2
"Unit";"Corruptor";"Larva";1168;2
"Unit";"Corruptor";"Larva";1170;2
"Unit";"Corruptor";"Larva";1172;2
"Unit";"Corruptor";"Larva";1174;2
"Unit";"Corruptor";"Larva";1176;2
"Unit";"Viper";"Larva";1178;3
"Unit";"Viper";"Larva";1181;3
"Unit";"Viper";"Larva";1184;3
"Unit";"Overlord";"Larva";1187;0
"Unit";"Overlord";"Larva";1187;0
"Unit";"Overlord";"Larva";1187;0
"Unit";"Zergling";"Larva";1187;1
"Unit";"Zergling";"Larva";1188;1
"Unit";"Zergling";"Larva";1189;1
"Unit";"Zergling";"Larva";1190;1
"Unit";"Zergling";"Larva";1191;1
"Unit";"Zergling";"Larva";1192;1
"Unit";"Zergling";"Larva";1193;1
"Unit";"Zergling";"Larva";1194;1
"Unit";"Zergling";"Larva";1195;1
"Unit";"Zergling";"Larva";1196;1
"Unit";"Zergling";"Larva";1197;1
"Unit";"Zergling";"Larva";1198;1
"Unit";"Zergling";"Larva";1199;1
"Unit";"Zergling";"Larva";1200;1
"Unit";"Zergling";"Larva";1201;1
"Unit";"Zergling";"Larva";1202;1
"Unit";"Zergling";"Larva";1203;1
"Unit";"Zergling";"Larva";1204;1
"Unit";"Baneling";"Zergling";1205;0
"Unit";"Baneling";"Zergling";1205;0
"Unit";"Baneling";"Zergling";1205;0
"Unit";"Baneling";"Zergling";1205;0
"Unit";"Baneling";"Zergling";1205;0
"Unit";"Baneling";"Zergling";1205;0
"Unit";"Baneling";"Zergling";1205;0
"Unit";"Baneling";"Zergling";1205;0
"Unit";"Baneling";"Zergling";1205;0
"Unit";"Baneling";"Zergling";1205;0
"Unit";"Baneling";"Zergling";1205;0
"Unit";"Baneling";"Zergling";1205;0
"Unit";"Baneling";"Zergling";1205;0
"Unit";"Baneling";"Zergling";1205;0
"Unit";"Baneling";"Zergling";1205;0
"Unit";"Baneling";"Zergling";1205;0
"Unit";"Baneling";"Zergling";1205;0
"Unit";"Baneling";"Zergling";1205;0
"Unit";"Baneling";"Zergling";1205;0
"Unit";"Baneling";"Zergling";1205;0
"Unit";"Baneling";"Zergling";1205;0
"Unit";"Baneling";"Zergling";1205;0
"Unit";"Baneling";"Zergling";1205;0
"Unit";"Baneling";"Zergling";1205;0
"Unit";"Zergling";"Larva";1205;1
"Unit";"Zergling";"Larva";1206;1
"Unit";"Zergling";"Larva";1207;1
"Unit";"Zergling";"Larva";1208;1
"Unit";"Zergling";"Larva";1209;1
"Unit";"Zergling";"Larva";1210;1
"Unit";"Zergling";"Larva";1211;1
"Unit";"Zergling";"Larva";1212;1
"Unit";"Zergling";"Larva";1213;1
"Unit";"Zergling";"Larva";1214;1
"Unit";"Zergling";"Larva";1215;1
"Unit";"Zergling";"Larva";1216;1
"Unit";"Zergling";"Larva";1217;1
"Unit";"Zergling";"Larva";1218;1
"Unit";"Zergling";"Larva";1219;1
"Unit";"Zergling";"Larva";1220;1
"Unit";"Zergling";"Larva";1221;1
"Unit";"Zergling";"Larva";1222;1
"Unit";"Zergling";"Larva";1223;1
"Unit";"Zergling";"Larva";1224;1
"Unit";"Zergling";"Larva";1225;1
"Unit";"Zergling";"Larva";1226;1
"Unit";"Zergling";"Larva";1227;1
"Unit";"Zergling";"Larva";1228;1
"Unit";"Zergling";"Larva";1229;1
"Unit";"Zergling";"Larva";1230;1
"Unit";"Zergling";"Larva";1231;1
"Unit";"Zergling";"Larva";1232;1
"Unit";"Zergling";"Larva";1233;1
"Unit";"Zergling";"Larva";1234;1
"Unit";"Zergling";"Larva";1235;1
"Unit";"Zergling";"Larva";1236;1
"Unit";"Zergling";"Larva";1237;1
"Unit";"Zergling";"Larva";1238;1
"Unit";"Zergling";"Larva";1239;1
"Unit";"Zergling";"Larva";1240;1
"Unit";"Zergling";"Larva";1241;1
"Unit";"Zergling";"Larva";1242;1
"Unit";"Zergling";"Larva";1243;1
"Unit";"Zergling";"Larva";1244;1
"Unit";"Zergling";"Larva";1245;1
"Unit";"Zergling";"Larva";1246;1
"Unit";"Zergling";"Larva";1247;1
"Unit";"Zergling";"Larva";1248;1
"Unit";"Zergling";"Larva";1249;1
"Unit";"Zergling";"Larva";1250;1
"Unit";"Zergling";"Larva";1251;1
"Unit";"Zergling";"Larva";1252;1
"Unit";"Zergling";"Larva";1253;1
"Unit";"Zergling";"Larva";1254;1
"Unit";"Zergling";"Larva";1255;1
"Unit";"Zergling";"Larva";1256;1
"Unit";"Zergling";"Larva";1257;1
"Unit";"Zergling";"Larva";1258;1
"Unit";"Zergling";"Larva";1259;1
"Unit";"Zergling";"Larva";1260;1
"Unit";"Zergling";"Larva";1261;1
"Unit";"Zergling";"Larva";1262;1
"Unit";"Zergling";"Larva";1263;1
"Unit";"Zergling";"Larva";1264;1
"Unit";"Zergling";"Larva";1265;1
"Unit";"Zergling";"Larva";1266;1
"Unit";"Zergling";"Larva";1267;1
"Unit";"Zergling";"Larva";1268;1
"Unit";"Zergling";"Larva";1269;1
"Unit";"Zergling";"Larva";1270;1
"Unit";"Zergling";"Larva";1271;1
"Unit";"Zergling";"Larva";1272;1
"Unit";"Zergling";"Larva";1273;1
"Unit";"Zergling";"Larva";1274;1
"Unit";"Zergling";"Larva";1275;1
"Unit";"Zergling";"Larva";1276;1
"Unit";"Baneling";"Zergling";1277;0
"Unit";"Baneling";"Zergling";1277;0
"Unit";"Baneling";"Zergling";1277;0
"Unit";"Baneling";"Zergling";1277;0
"Unit";"Baneling";"Zergling";1277;0
"Unit";"Baneling";"Zergling";1277;0
"Unit";"Ultralisk";"Larva";1277;6
"Unit";"Ultralisk";"Larva";1283;6
"Unit";"Zergling";"Larva";1289;1
"Unit";"Zergling";"Larva";1290;1
"Unit";"Zergling";"Larva";1291;1
"Unit";"Zergling";"Larva";1292;1
"Unit";"Zergling";"Larva";1293;1
"Unit";"Zergling";"Larva";1294;1
"Unit";"Zergling";"Larva";1295;1
"Unit";"Zergling";"Larva";1296;1
"Unit";"Zergling";"Larva";1297;1
"Unit";"Zergling";"Larva";1298;1
"Unit";"Zergling";"Larva";1299;1
"Unit";"Zergling";"Larva";1300;1
"Unit";"Zergling";"Larva";1301;1
"Unit";"Zergling";"Larva";1302;1
"Unit";"Zergling";"Larva";1303;1
"Unit";"Zergling";"Larva";1304;1
"Unit";"Zergling";"Larva";1305;1
"Unit";"Zergling";"Larva";1306;1
"Unit";"Zergling";"Larva";1307;1
"Unit";"Zergling";"Larva";1308;1
"Unit";"Zergling";"Larva";1309;1
"Unit";"Zergling";"Larva";1310;1
"Unit";"Zergling";"Larva";1311;1
"Unit";"Zergling";"Larva";1312;1
"Unit";"Zergling";"Larva";1313;1
"Unit";"Zergling";"Larva";1314;1
"Unit";"Zergling";"Larva";1315;1
"Unit";"Zergling";"Larva";1316;1
"Unit";"Zergling";"Larva";1317;1
"Unit";"Zergling";"Larva";1318;1
"Unit";"Zergling";"Larva";1319;1
"Unit";"Zergling";"Larva";1320;1
"Unit";"Zergling";"Larva";1321;1
"Unit";"Zergling";"Larva";1322;1
"Unit";"Zergling";"Larva";1323;1
"Unit";"Zergling";"Larva";1324;1
"Unit";"Zergling";"Larva";1325;1
"Unit";"Zergling";"Larva";1326;1
"Unit";"Zergling";"Larva";1327;1
"Unit";"Zergling";"Larva";1328;1
"Unit";"Zergling";"Larva";1329;1
"Unit";"Zergling";"Larva";1330;1
"Unit";"Zergling";"Larva";1331;1
"Unit";"Zergling";"Larva";1332;1
"Unit";"Zergling";"Larva";1333;1
"Unit";"Zergling";"Larva";1334;1
"Unit";"Zergling";"Larva";1335;1
"Unit";"Zergling";"Larva";1336;1
"Unit";"Zergling";"Larva";1337;1
"Unit";"Zergling";"Larva";1338;1
"Unit";"Zergling";"Larva";1339;1
"Unit";"Zergling";"Larva";1340;1
"Unit";"Zergling";"Larva";1341;1
"Unit";"Zergling";"Larva";1342;1
"Unit";"Zergling";"Larva";1343;1
"Unit";"Zergling";"Larva";1344;1
"Unit";"Zergling";"Larva";1345;1
"Unit";"Zergling";"Larva";1346;1
"Unit";"Zergling";"Larva";1347;1
"Unit";"Zergling";"Larva";1348;1
"Building";"Extractor";NA;1349;0
"Unit";"Overlord";"Larva";1349;0
"Unit";"Overlord";"Larva";1349;0
"Upgrade";"SprayZerg";NA;1349;0
"Upgrade";"SprayZerg";NA;1349;0
"Upgrade";"SprayZerg";NA;1349;0
"Upgrade";"zerglingmovementspeed";NA;1349;0
"Upgrade";"overlordspeed";NA;1349;0
"Upgrade";"SprayZerg";NA;1349;0
"Upgrade";"SprayZerg";NA;1349;0
"Upgrade";"SprayZerg";NA;1349;0
"Upgrade";"SprayZerg";NA;1349;0
"Upgrade";"ZergMeleeWeaponsLevel1";NA;1349;0
"Upgrade";"ZergGroundArmorsLevel1";NA;1349;0
"Upgrade";"CentrificalHooks";NA;1349;0
"Upgrade";"EvolveMuscularAugments";NA;1349;0
"Upgrade";"SprayZerg";NA;1349;0
"Upgrade";"ZergMeleeWeaponsLevel2";NA;1349;0
"Upgrade";"ZergGroundArmorsLevel2";NA;1349;0
"Upgrade";"SprayZerg";NA;1349;0
"Upgrade";"SprayZerg";NA;1349;0
"Upgrade";"zerglingattackspeed";NA;1349;0
"Upgrade";"ZergMeleeWeaponsLevel3";NA;1349;0
"Upgrade";"ZergGroundArmorsLevel3";NA;1349;0
"Upgrade";"SprayZerg";NA;1349;0
"Upgrade";"SprayZerg";NA;1349;0
"Upgrade";"ZergFlyerWeaponsLevel1";NA;1349;0
"Upgrade";"SprayZerg";NA;1349;0
"Upgrade";"SprayZerg";NA;1349;0
"Upgrade";"InfestorEnergyUpgrade";NA;1349;0
"Upgrade";"SprayZerg";NA;1349;0
"Upgrade";"ZergFlyerWeaponsLevel2";NA;1349;0
"Upgrade";"SprayZerg";NA;1349;0
"Upgrade";"SprayZerg";NA;1349;0
"Upgrade";"SprayZerg";NA;1349;0
"Upgrade";"SprayZerg";NA;1349;0
