"type";"unit_name";"on_building";"total_supply";"supply"
"Unit";"Overlord";"Larva";13;0
"Building";"Extractor";NA;18;0
"Unit";"Overlord";"Larva";21;0
"Building";"SpawningPool";NA;19;0
"Building";"Hatchery";NA;17;0
"Unit";"Zergling";"Larva";22;1
"Unit";"Zergling";"Larva";22;1
"Unit";"Zergling";"Larva";22;1
"Unit";"Zergling";"Larva";22;1
"Unit";"Queen";"Hatchery";22;2
"Unit";"Queen";"Hatchery";22;2
"Building";"CreepTumorQueen";NA;33;0
"Unit";"Overlord";"Larva";36;0
"Building";"CreepTumor";NA;37;0
"Unit";"Queen";"Hatchery";34;2
"Unit";"Overlord";"Larva";40;0
"Building";"CreepTumorQueen";NA;46;0
"Unit";"Zergling";"Larva";44;1
"Unit";"Zergling";"Larva";44;1
"Building";"Hatchery";NA;29;0
"Unit";"Overlord";"Larva";46;0
"Building";"CreepTumor";NA;47;0
"Unit";"Zergling";"Larva";47;1
"Unit";"Zergling";"Larva";47;1
"Unit";"Zergling";"Larva";49;1
"Unit";"Zergling";"Larva";49;1
"Unit";"Zergling";"Larva";49;1
"Unit";"Zergling";"Larva";49;1
"Unit";"Zergling";"Larva";49;1
"Unit";"Zergling";"Larva";49;1
"Building";"CreepTumor";NA;51;0
"Unit";"Queen";"Hatchery";47;2
"Unit";"Queen";"Hatchery";47;2
"Building";"CreepTumorQueen";NA;56;0
"Building";"CreepTumor";NA;54;0
"Unit";"Overlord";"Larva";63;0
"Building";"CreepTumor";NA;71;0
"Building";"CreepTumor";NA;72;0
"Unit";"Overlord";"Larva";71;0
"Building";"EvolutionChamber";NA;71;0
"Building";"EvolutionChamber";NA;71;0
"Unit";"Queen";"Hatchery";70;2
"Building";"CreepTumorQueen";NA;82;0
"Building";"Extractor";NA;76;0
"Building";"Extractor";NA;76;0
"Building";"CreepTumor";NA;85;0
"Building";"CreepTumor";NA;85;0
"Building";"Extractor";NA;85;0
"Building";"Extractor";NA;85;0
"Building";"Extractor";NA;92;0
"Unit";"Zergling";"Larva";97;1
"Unit";"Zergling";"Larva";97;1
"Unit";"Zergling";"Larva";97;1
"Unit";"Zergling";"Larva";97;1
"Unit";"Zergling";"Larva";97;1
"Unit";"Zergling";"Larva";97;1
"Unit";"Zergling";"Larva";97;1
"Unit";"Zergling";"Larva";97;1
"Unit";"Zergling";"Larva";97;1
"Unit";"Zergling";"Larva";97;1
"Building";"SporeCrawler";NA;94;0
"Building";"SporeCrawler";NA;96;0
"Building";"SporeCrawler";NA;96;0
"Unit";"Zergling";"Larva";97;1
"Unit";"Zergling";"Larva";97;1
"Unit";"Zergling";"Larva";97;1
"Unit";"Zergling";"Larva";97;1
"Unit";"Zergling";"Larva";97;1
"Unit";"Zergling";"Larva";97;1
"Unit";"Zergling";"Larva";97;1
"Unit";"Zergling";"Larva";97;1
"Unit";"Zergling";"Larva";97;1
"Unit";"Zergling";"Larva";97;1
"Unit";"Zergling";"Larva";97;1
"Unit";"Zergling";"Larva";97;1
"Unit";"Zergling";"Larva";97;1
"Unit";"Zergling";"Larva";97;1
"Unit";"Zergling";"Larva";97;1
"Unit";"Zergling";"Larva";97;1
"Unit";"Zergling";"Larva";97;1
"Unit";"Zergling";"Larva";97;1
"Building";"Hatchery";NA;85;0
"Unit";"Zergling";"Larva";125;1
"Unit";"Zergling";"Larva";125;1
"Unit";"Zergling";"Larva";125;1
"Unit";"Zergling";"Larva";125;1
"Unit";"Zergling";"Larva";125;1
"Unit";"Zergling";"Larva";125;1
"Unit";"Zergling";"Larva";125;1
"Unit";"Zergling";"Larva";125;1
"Unit";"Zergling";"Larva";125;1
"Unit";"Zergling";"Larva";125;1
"Unit";"Queen";"Hatchery";107;2
"Unit";"Zergling";"Larva";125;1
"Unit";"Zergling";"Larva";125;1
"Unit";"Zergling";"Larva";125;1
"Unit";"Zergling";"Larva";125;1
"Unit";"Zergling";"Larva";125;1
"Unit";"Zergling";"Larva";125;1
"Unit";"Zergling";"Larva";125;1
"Unit";"Zergling";"Larva";125;1
"Building";"CreepTumor";NA;130;0
"Unit";"Overlord";"Larva";130;0
"Building";"CreepTumor";NA;150;0
"Building";"BanelingNest";NA;125;0
"Upgrade";"ZergMeleeWeaponsLevel1";"EvolutionChamber";96;0
"Upgrade";"ZergGroundArmorsLevel1";"EvolutionChamber";96;0
"Unit";"Queen";"Hatchery";154;2
"Building";"Spire";NA;130;0
"Unit";"Zergling";"Larva";160;1
"Unit";"Zergling";"Larva";160;1
"Unit";"Zergling";"Larva";160;1
"Unit";"Zergling";"Larva";160;1
"Unit";"Zergling";"Larva";160;1
"Unit";"Zergling";"Larva";160;1
"Building";"RoachWarren";NA;160;0
"Unit";"Queen";"Hatchery";160;2
"Unit";"Queen";"Hatchery";160;2
"Building";"CreepTumor";NA;168;0
"Unit";"Queen";"Hatchery";160;2
"Building";"CreepTumor";NA;168;0
"Building";"CreepTumorQueen";NA;172;0
"Building";"CreepTumorQueen";NA;174;0
"Building";"CreepTumorQueen";NA;174;0
"Unit";"Overlord";"Larva";174;0
"Unit";"Overlord";"Larva";174;0
"Unit";"Overlord";"Larva";174;0
"Unit";"Mutalisk";"Larva";174;2
"Unit";"Mutalisk";"Larva";174;2
"Unit";"Queen";"Hatchery";168;2
"Building";"CreepTumorQueen";NA;174;0
"Unit";"Overlord";"Larva";174;0
"Building";"CreepTumorQueen";NA;174;0
"Unit";"Overlord";"Larva";174;0
"Unit";"Overlord";"Larva";174;0
"Building";"HydraliskDen";NA;174;0
"Building";"CreepTumor";NA;181;0
"Unit";"Mutalisk";"Larva";181;2
"Unit";"Mutalisk";"Larva";181;2
"Unit";"Mutalisk";"Larva";181;2
"Unit";"Mutalisk";"Larva";181;2
"Unit";"Mutalisk";"Larva";181;2
"Unit";"Mutalisk";"Larva";181;2
"Unit";"Mutalisk";"Larva";181;2
"Unit";"Mutalisk";"Larva";181;2
"Unit";"Mutalisk";"Larva";181;2
"Unit";"Mutalisk";"Larva";181;2
"Unit";"Mutalisk";"Larva";181;2
"Unit";"Mutalisk";"Larva";181;2
"Building";"CreepTumor";NA;181;0
"Building";"CreepTumor";NA;181;0
"Building";"CreepTumorQueen";NA;181;0
"Building";"Hatchery";NA;162;0
"Building";"CreepTumorQueen";NA;181;0
"Building";"CreepTumor";NA;181;0
"Building";"CreepTumor";NA;181;0
"Building";"CreepTumor";NA;189;0
"Unit";"Overlord";"Larva";181;0
"Building";"CreepTumor";NA;199;0
"Upgrade";"ZergMissileWeaponsLevel1";"EvolutionChamber";162;0
"Building";"CreepTumor";NA;213;0
"Unit";"Hydralisk";"Larva";209;2
"Unit";"Hydralisk";"Larva";213;2
"Unit";"Hydralisk";"Larva";213;2
"Unit";"Hydralisk";"Larva";213;2
"Unit";"Hydralisk";"Larva";213;2
"Unit";"Hydralisk";"Larva";213;2
"Unit";"Hydralisk";"Larva";213;2
"Building";"CreepTumor";NA;213;0
"Building";"CreepTumor";NA;213;0
"Unit";"Hydralisk";"Larva";213;2
"Upgrade";"ZergGroundArmorsLevel2";"EvolutionChamber";168;0
"Building";"CreepTumor";NA;221;0
"Unit";"Hydralisk";"Larva";213;2
"Building";"CreepTumor";NA;221;0
"Building";"CreepTumor";NA;221;0
"Building";"CreepTumor";NA;221;0
"Upgrade";"GlialReconstitution";"RoachWarren";181;0
"Building";"Extractor";NA;213;0
"Building";"Extractor";NA;213;0
"Building";"CreepTumorQueen";NA;225;0
"Building";"CreepTumorQueen";NA;227;0
"Building";"CreepTumorQueen";NA;227;0
"Unit";"Hydralisk";"Larva";213;2
"Unit";"Hydralisk";"Larva";213;2
"Building";"CreepTumorQueen";NA;227;0
"Building";"CreepTumorQueen";NA;231;0
"Building";"InfestationPit";NA;213;0
"Unit";"Hydralisk";"Larva";223;2
"Unit";"Hydralisk";"Larva";223;2
"Unit";"Hydralisk";"Larva";223;2
"Unit";"Hydralisk";"Larva";223;2
"Building";"CreepTumorQueen";NA;235;0
"Unit";"Hydralisk";"Larva";227;2
"Unit";"Hydralisk";"Larva";227;2
"Unit";"Overlord";"Larva";235;0
"Unit";"Overlord";"Larva";235;0
"Unit";"Overlord";"Larva";235;0
"Upgrade";"EvolveMuscularAugments";"HydraliskDen";213;0
"Unit";"Hydralisk";"Larva";235;2
"Unit";"Hydralisk";"Larva";235;2
"Unit";"Hydralisk";"Larva";235;2
"Unit";"Hydralisk";"Larva";235;2
"Unit";"Hydralisk";"Larva";235;2
"Building";"CreepTumor";NA;247;0
"Building";"CreepTumor";NA;247;0
"Building";"CreepTumor";NA;247;0
"Building";"CreepTumor";NA;247;0
"Building";"CreepTumor";NA;247;0
"Building";"CreepTumor";NA;247;0
"Building";"CreepTumor";NA;247;0
"Building";"CreepTumor";NA;247;0
"Building";"CreepTumor";NA;247;0
"Building";"CreepTumor";NA;247;0
"Building";"CreepTumor";NA;247;0
"Building";"CreepTumor";NA;247;0
"Building";"CreepTumor";NA;247;0
"Building";"CreepTumor";NA;247;0
"Building";"CreepTumorQueen";NA;257;0
"Building";"CreepTumorQueen";NA;257;0
"Unit";"Overlord";"Larva";257;0
"Unit";"Overlord";"Larva";257;0
"Unit";"Hydralisk";"Larva";257;2
"Unit";"Hydralisk";"Larva";257;2
"Unit";"Hydralisk";"Larva";257;2
"Unit";"Hydralisk";"Larva";257;2
"Unit";"Hydralisk";"Larva";257;2
"Building";"CreepTumor";NA;257;0
"Building";"CreepTumor";NA;257;0
"Building";"CreepTumor";NA;257;0
"Building";"CreepTumor";NA;257;0
"Building";"CreepTumor";NA;257;0
"Building";"CreepTumor";NA;257;0
"Building";"CreepTumor";NA;257;0
"Building";"CreepTumor";NA;257;0
"Building";"CreepTumor";NA;257;0
"Building";"CreepTumor";NA;257;0
"Building";"CreepTumor";NA;260;0
"Building";"CreepTumor";NA;270;0
"Building";"CreepTumor";NA;270;0
"Building";"CreepTumor";NA;270;0
"Unit";"Roach";"Larva";270;2
"Unit";"Roach";"Larva";270;2
"Unit";"Roach";"Larva";270;2
"Unit";"Roach";"Larva";270;2
"Unit";"Roach";"Larva";270;2
"Unit";"Roach";"Larva";270;2
"Unit";"Roach";"Larva";270;2
"Unit";"Roach";"Larva";270;2
"Unit";"Roach";"Larva";270;2
"Building";"CreepTumor";NA;270;0
"Building";"CreepTumor";NA;270;0
"Unit";"Roach";"Larva";270;2
"Building";"CreepTumor";NA;270;0
"Unit";"Roach";"Larva";270;2
"Unit";"Roach";"Larva";270;2
"Building";"CreepTumor";NA;270;0
"Building";"CreepTumor";NA;270;0
"Building";"CreepTumor";NA;288;0
"Building";"CreepTumor";NA;288;0
"Unit";"Overlord";"Larva";274;0
"Unit";"Overlord";"Larva";280;0
"Building";"CreepTumor";NA;294;0
"Building";"CreepTumor";NA;294;0
"Unit";"Overlord";"Larva";288;0
"Building";"Hatchery";NA;257;0
"Upgrade";"EvolveGroovedSpines";"HydraliskDen";257;0
"Building";"CreepTumor";NA;294;0
"Building";"CreepTumor";NA;294;0
"Building";"CreepTumor";NA;294;0
"Building";"CreepTumor";NA;294;0
"Unit";"Viper";"Larva";294;3
"Unit";"Viper";"Larva";294;3
"Unit";"Viper";"Larva";294;3
"Building";"CreepTumor";NA;322;0
"Building";"CreepTumor";NA;322;0
"Building";"CreepTumor";NA;322;0
"Building";"CreepTumor";NA;322;0
"Building";"CreepTumor";NA;322;0
"Building";"CreepTumor";NA;322;0
"Building";"CreepTumor";NA;322;0
"Building";"CreepTumor";NA;322;0
"Building";"CreepTumor";NA;322;0
"Building";"CreepTumor";NA;322;0
"Building";"CreepTumor";NA;322;0
"Upgrade";"ZergMissileWeaponsLevel2";"EvolutionChamber";288;0
"Building";"CreepTumorQueen";NA;322;0
"Unit";"Zergling";"Larva";322;1
"Unit";"Zergling";"Larva";322;1
"Building";"SpineCrawler";NA;322;0
"Unit";"Corruptor";"Larva";322;2
"Building";"SpineCrawler";NA;322;0
"Unit";"Corruptor";"Larva";322;2
"Unit";"Corruptor";"Larva";322;2
"Unit";"Corruptor";"Larva";322;2
"Unit";"Corruptor";"Larva";322;2
"Unit";"Corruptor";"Larva";322;2
"Unit";"Corruptor";"Larva";322;2
"Unit";"Corruptor";"Larva";322;2
"Building";"SpineCrawler";NA;322;0
"Building";"SpineCrawler";NA;322;0
"Building";"CreepTumor";NA;340;0
"Building";"CreepTumor";NA;340;0
"Building";"CreepTumor";NA;340;0
"Building";"Extractor";NA;340;0
"Building";"CreepTumor";NA;340;0
"Building";"Extractor";NA;340;0
"Building";"CreepTumor";NA;340;0
"Unit";"Corruptor";"Larva";340;2
"Unit";"Corruptor";"Larva";340;2
"Building";"CreepTumor";NA;342;0
"Building";"CreepTumor";NA;342;0
"Upgrade";"ZergGroundArmorsLevel3";"EvolutionChamber";322;0
"Unit";"Zergling";"Larva";344;1
"Unit";"Zergling";"Larva";344;1
"Unit";"Corruptor";"Larva";340;2
"Unit";"Corruptor";"Larva";340;2
"Unit";"Corruptor";"Larva";340;2
"Unit";"Corruptor";"Larva";340;2
"Building";"CreepTumor";NA;344;0
"Building";"CreepTumorQueen";NA;344;0
"Building";"CreepTumorQueen";NA;344;0
"Building";"CreepTumorQueen";NA;344;0
"Building";"CreepTumorQueen";NA;344;0
"Building";"CreepTumorQueen";NA;344;0
"Building";"Hatchery";NA;340;0
