"type";"unit_name";"on_building";"total_supply";"supply"
"Unit";"Overlord";"Larva";13;0
"Unit";"Overlord";"Larva";14;0
"Building";"SpawningPool";NA;18;0
"Building";"Hatchery";NA;16;0
"Unit";"Zergling";"Larva";24;1
"Unit";"Zergling";"Larva";24;1
"Unit";"Zergling";"Larva";24;1
"Unit";"Zergling";"Larva";24;1
"Unit";"Queen";"Hatchery";23;2
"Unit";"Queen";"Hatchery";23;2
"Building";"Hatchery";NA;20;0
"Unit";"Overlord";"Larva";39;0
"Unit";"Queen";"Hatchery";37;2
"Building";"Extractor";NA;41;0
"Building";"Extractor";NA;41;0
"Unit";"Overlord";"Larva";48;0
"Building";"RoachWarren";NA;43;0
"Unit";"Overlord";"Larva";56;0
"Unit";"Overlord";"Larva";58;0
"Unit";"Roach";"Larva";59;2
"Unit";"Roach";"Larva";59;2
"Unit";"Roach";"Larva";59;2
"Unit";"Roach";"Larva";59;2
"Unit";"Roach";"Larva";59;2
"Unit";"Overlord";"Larva";59;0
"Unit";"Overlord";"Larva";59;0
"Unit";"Overlord";"Larva";75;0
"Unit";"Overlord";"Larva";75;0
"Unit";"Overlord";"Larva";76;0
"Unit";"Overlord";"Larva";83;0
"Building";"EvolutionChamber";NA;75;0
"Unit";"Roach";"Larva";83;2
"Unit";"Roach";"Larva";83;2
"Building";"Extractor";NA;83;0
"Unit";"Queen";"Hatchery";75;2
"Unit";"Roach";"Larva";86;2
"Unit";"Roach";"Larva";86;2
"Unit";"Roach";"Larva";86;2
"Unit";"Roach";"Larva";86;2
"Building";"Extractor";NA;86;0
"Unit";"Overlord";"Larva";90;0
"Unit";"Roach";"Larva";91;2
"Unit";"Roach";"Larva";103;2
"Unit";"Zergling";"Larva";107;1
"Unit";"Zergling";"Larva";107;1
"Unit";"Roach";"Larva";107;2
"Unit";"Zergling";"Larva";107;1
"Unit";"Zergling";"Larva";107;1
"Unit";"Zergling";"Larva";107;1
"Unit";"Zergling";"Larva";107;1
"Unit";"Zergling";"Larva";107;1
"Unit";"Zergling";"Larva";107;1
"Unit";"Zergling";"Larva";107;1
"Unit";"Zergling";"Larva";107;1
"Unit";"Roach";"Larva";107;2
"Unit";"Roach";"Larva";107;2
"Building";"CreepTumorQueen";NA;111;0
"Building";"CreepTumorQueen";NA;117;0
"Unit";"Queen";"Hatchery";107;2
"Unit";"Queen";"Hatchery";107;2
"Unit";"Zergling";"Larva";127;1
"Unit";"Zergling";"Larva";127;1
"Unit";"Zergling";"Larva";127;1
"Unit";"Zergling";"Larva";127;1
"Unit";"Zergling";"Larva";127;1
"Unit";"Zergling";"Larva";127;1
"Unit";"Zergling";"Larva";127;1
"Unit";"Zergling";"Larva";127;1
"Unit";"Zergling";"Larva";127;1
"Unit";"Zergling";"Larva";127;1
"Unit";"Zergling";"Larva";127;1
"Unit";"Zergling";"Larva";127;1
"Unit";"Zergling";"Larva";127;1
"Unit";"Zergling";"Larva";127;1
"Unit";"Zergling";"Larva";127;1
"Unit";"Zergling";"Larva";127;1
"Unit";"Roach";"Larva";127;2
"Unit";"Overlord";"Larva";131;0
"Unit";"Overlord";"Larva";131;0
"Unit";"Overlord";"Larva";131;0
"Unit";"Overlord";"Larva";147;0
"Building";"BanelingNest";NA;127;0
"Building";"Extractor";NA;149;0
"Building";"Extractor";NA;149;0
"Unit";"Roach";"Larva";149;2
"Unit";"Roach";"Larva";149;2
"Unit";"Roach";"Larva";149;2
"Unit";"Roach";"Larva";149;2
"Unit";"Roach";"Larva";149;2
"Unit";"Roach";"Larva";149;2
"Unit";"Roach";"Larva";149;2
"Unit";"Roach";"Larva";149;2
"Unit";"Roach";"Larva";155;2
"Unit";"Roach";"Larva";155;2
"Unit";"Roach";"Larva";155;2
"Unit";"Roach";"Larva";155;2
"Building";"Hatchery";NA;127;0
"Unit";"Roach";"Larva";161;2
"Unit";"Overlord";"Larva";174;0
"Unit";"Overlord";"Larva";174;0
"Unit";"Overlord";"Larva";174;0
"Unit";"Overlord";"Larva";174;0
"Unit";"Overlord";"Larva";174;0
"Unit";"Overlord";"Larva";174;0
"Unit";"Overlord";"Larva";182;0
"Unit";"Overlord";"Larva";182;0
"Upgrade";"GlialReconstitution";"RoachWarren";155;0
"Unit";"Zergling";"Larva";185;1
"Unit";"Zergling";"Larva";185;1
"Unit";"Zergling";"Larva";185;1
"Unit";"Zergling";"Larva";185;1
"Unit";"Zergling";"Larva";185;1
"Unit";"Zergling";"Larva";185;1
"Unit";"Zergling";"Larva";185;1
"Unit";"Zergling";"Larva";185;1
"Unit";"Zergling";"Larva";185;1
"Unit";"Zergling";"Larva";185;1
"Unit";"Zergling";"Larva";185;1
"Unit";"Zergling";"Larva";185;1
"Unit";"Zergling";"Larva";185;1
"Unit";"Zergling";"Larva";185;1
"Unit";"Zergling";"Larva";185;1
"Unit";"Zergling";"Larva";185;1
"Upgrade";"ZergMeleeWeaponsLevel1";"EvolutionChamber";147;0
"Unit";"Zergling";"Larva";185;1
"Unit";"Zergling";"Larva";185;1
"Unit";"Zergling";"Larva";185;1
"Unit";"Zergling";"Larva";185;1
"Unit";"Zergling";"Larva";185;1
"Unit";"Zergling";"Larva";185;1
"Unit";"Zergling";"Larva";185;1
"Unit";"Zergling";"Larva";185;1
"Unit";"Zergling";"Larva";185;1
"Unit";"Zergling";"Larva";185;1
"Unit";"Zergling";"Larva";185;1
"Unit";"Zergling";"Larva";185;1
"Unit";"Zergling";"Larva";185;1
"Unit";"Zergling";"Larva";185;1
"Unit";"Zergling";"Larva";185;1
"Unit";"Zergling";"Larva";185;1
"Unit";"Zergling";"Larva";185;1
"Unit";"Zergling";"Larva";185;1
"Unit";"Zergling";"Larva";207;1
"Unit";"Zergling";"Larva";207;1
"Unit";"Zergling";"Larva";207;1
"Unit";"Zergling";"Larva";207;1
"Unit";"Zergling";"Larva";207;1
"Unit";"Zergling";"Larva";207;1
"Unit";"Zergling";"Larva";209;1
"Unit";"Zergling";"Larva";209;1
"Unit";"Zergling";"Larva";209;1
"Unit";"Zergling";"Larva";209;1
"Unit";"Zergling";"Larva";217;1
"Unit";"Zergling";"Larva";217;1
"Unit";"Zergling";"Larva";217;1
"Unit";"Zergling";"Larva";217;1
"Unit";"Zergling";"Larva";219;1
"Unit";"Zergling";"Larva";219;1
"Unit";"Zergling";"Larva";219;1
"Unit";"Zergling";"Larva";219;1
"Unit";"Zergling";"Larva";219;1
"Unit";"Zergling";"Larva";219;1
"Unit";"Zergling";"Larva";219;1
"Unit";"Zergling";"Larva";219;1
"Unit";"Zergling";"Larva";219;1
"Unit";"Zergling";"Larva";219;1
"Unit";"Zergling";"Larva";219;1
"Unit";"Zergling";"Larva";219;1
"Unit";"Zergling";"Larva";219;1
"Unit";"Zergling";"Larva";219;1
"Unit";"Baneling";"Zergling";219;0
"Unit";"Baneling";"Zergling";219;0
"Unit";"Baneling";"Zergling";219;0
"Unit";"Baneling";"Zergling";219;0
"Unit";"Baneling";"Zergling";219;0
"Unit";"Baneling";"Zergling";219;0
"Unit";"Baneling";"Zergling";219;0
"Unit";"Baneling";"Zergling";219;0
"Unit";"Baneling";"Zergling";219;0
"Unit";"Baneling";"Zergling";219;0
"Unit";"Baneling";"Zergling";219;0
"Unit";"Baneling";"Zergling";219;0
"Unit";"Baneling";"Zergling";219;0
"Unit";"Baneling";"Zergling";219;0
"Unit";"Baneling";"Zergling";219;0
"Unit";"Baneling";"Zergling";219;0
"Unit";"Baneling";"Zergling";219;0
"Unit";"Baneling";"Zergling";219;0
"Unit";"Baneling";"Zergling";219;0
"Unit";"Baneling";"Zergling";219;0
"Unit";"Baneling";"Zergling";219;0
"Unit";"Baneling";"Zergling";219;0
"Unit";"Zergling";"Larva";219;1
"Unit";"Zergling";"Larva";219;1
"Unit";"Zergling";"Larva";219;1
"Unit";"Zergling";"Larva";219;1
"Unit";"Zergling";"Larva";219;1
"Unit";"Zergling";"Larva";219;1
"Unit";"Zergling";"Larva";221;1
"Unit";"Zergling";"Larva";221;1
"Unit";"Zergling";"Larva";223;1
"Unit";"Zergling";"Larva";223;1
"Unit";"Roach";"Larva";247;2
"Unit";"Roach";"Larva";247;2
"Unit";"Roach";"Larva";247;2
"Unit";"Roach";"Larva";247;2
"Unit";"Zergling";"Larva";247;1
"Unit";"Zergling";"Larva";247;1
"Unit";"Zergling";"Larva";257;1
"Unit";"Zergling";"Larva";257;1
"Unit";"Zergling";"Larva";257;1
"Unit";"Zergling";"Larva";257;1
"Unit";"Zergling";"Larva";267;1
"Unit";"Zergling";"Larva";267;1
"Unit";"Zergling";"Larva";267;1
"Unit";"Zergling";"Larva";267;1
"Unit";"Zergling";"Larva";267;1
"Unit";"Zergling";"Larva";267;1
"Unit";"Zergling";"Larva";267;1
"Unit";"Zergling";"Larva";267;1
"Unit";"Zergling";"Larva";269;1
"Unit";"Zergling";"Larva";269;1
"Unit";"Zergling";"Larva";269;1
"Unit";"Zergling";"Larva";269;1
"Unit";"Zergling";"Larva";269;1
"Unit";"Zergling";"Larva";269;1
"Unit";"Zergling";"Larva";269;1
"Unit";"Zergling";"Larva";269;1
"Unit";"Zergling";"Larva";269;1
"Unit";"Zergling";"Larva";269;1
"Unit";"Zergling";"Larva";269;1
"Unit";"Zergling";"Larva";269;1
