"type";"unit_name";"on_building";"total_supply";"supply"
"Unit";"Overlord";"Larva";13;0
"Building";"Extractor";NA;15;0
"Building";"SpawningPool";NA;17;0
"Unit";"Zergling";"Larva";21;1
"Unit";"Zergling";"Larva";21;1
"Unit";"Overlord";"Larva";21;0
"Unit";"Queen";"Hatchery";21;2
"Building";"Hatchery";NA;20;0
"Unit";"Zergling";"Larva";28;1
"Unit";"Zergling";"Larva";28;1
"Unit";"Zergling";"Larva";28;1
"Unit";"Zergling";"Larva";28;1
"Unit";"Queen";"Hatchery";26;2
"Unit";"Zergling";"Larva";28;1
"Unit";"Zergling";"Larva";28;1
"Unit";"Zergling";"Larva";30;1
"Unit";"Zergling";"Larva";30;1
"Unit";"Zergling";"Larva";30;1
"Unit";"Zergling";"Larva";30;1
"Unit";"Zergling";"Larva";30;1
"Unit";"Zergling";"Larva";30;1
"Unit";"Overlord";"Larva";53;0
"Unit";"Overlord";"Larva";63;0
"Unit";"Queen";"Hatchery";58;2
"Building";"SporeCrawler";NA;63;0
"Building";"SporeCrawler";NA;63;0
"Unit";"Overlord";"Larva";69;0
"Unit";"Overlord";"Larva";69;0
"Unit";"Overlord";"Larva";69;0
"Unit";"Zergling";"Larva";69;1
"Unit";"Zergling";"Larva";69;1
"Unit";"Zergling";"Larva";69;1
"Unit";"Zergling";"Larva";69;1
"Unit";"Zergling";"Larva";69;1
"Unit";"Zergling";"Larva";69;1
"Unit";"Zergling";"Larva";69;1
"Unit";"Zergling";"Larva";69;1
"Unit";"Zergling";"Larva";69;1
"Unit";"Zergling";"Larva";69;1
"Unit";"Zergling";"Larva";69;1
"Unit";"Zergling";"Larva";69;1
"Unit";"Zergling";"Larva";69;1
"Unit";"Zergling";"Larva";69;1
"Unit";"Queen";"Hatchery";69;2
"Building";"RoachWarren";NA;69;0
"Building";"Hatchery";NA;69;0
"Building";"Extractor";NA;88;0
"Building";"CreepTumorQueen";NA;94;0
"Building";"Extractor";NA;89;0
"Unit";"Overlord";"Larva";91;0
"Unit";"Overlord";"Larva";95;0
"Unit";"Overlord";"Larva";95;0
"Unit";"Queen";"Hatchery";91;2
"Building";"CreepTumor";NA;98;0
"Unit";"Roach";"Larva";98;2
"Unit";"Roach";"Larva";98;2
"Unit";"Roach";"Larva";98;2
"Unit";"Roach";"Larva";98;2
"Unit";"Roach";"Larva";98;2
"Unit";"Roach";"Larva";98;2
"Unit";"Roach";"Larva";98;2
"Building";"CreepTumorQueen";NA;114;0
"Building";"CreepTumor";NA;114;0
"Unit";"Overlord";"Larva";122;0
"Building";"CreepTumorQueen";NA;125;0
"Building";"CreepTumor";NA;125;0
"Building";"CreepTumor";NA;125;0
"Unit";"Queen";"Hatchery";119;2
"Building";"EvolutionChamber";NA;125;0
"Building";"EvolutionChamber";NA;125;0
"Unit";"Overlord";"Larva";130;0
"Unit";"Overlord";"Larva";130;0
"Upgrade";"GlialReconstitution";"RoachWarren";120;0
"Building";"Extractor";NA;139;0
"Building";"Extractor";NA;139;0
"Building";"CreepTumor";NA;141;0
"Building";"CreepTumorQueen";NA;142;0
"Building";"CreepTumor";NA;142;0
"Building";"CreepTumor";NA;142;0
"Building";"CreepTumorQueen";NA;142;0
"Unit";"Zergling";"Larva";142;1
"Unit";"Zergling";"Larva";142;1
"Unit";"Zergling";"Larva";142;1
"Unit";"Zergling";"Larva";142;1
"Unit";"Zergling";"Larva";142;1
"Unit";"Zergling";"Larva";142;1
"Unit";"Zergling";"Larva";142;1
"Unit";"Zergling";"Larva";142;1
"Unit";"Zergling";"Larva";142;1
"Unit";"Zergling";"Larva";142;1
"Unit";"Zergling";"Larva";142;1
"Unit";"Zergling";"Larva";142;1
"Unit";"Zergling";"Larva";142;1
"Unit";"Zergling";"Larva";142;1
"Unit";"Zergling";"Larva";142;1
"Unit";"Zergling";"Larva";142;1
"Building";"HydraliskDen";NA;141;0
"Building";"BanelingNest";NA;141;0
"Unit";"Overlord";"Larva";160;0
"Unit";"Queen";"Hatchery";142;2
"Unit";"Queen";"Hatchery";144;2
"Unit";"Hydralisk";"Larva";160;2
"Unit";"Hydralisk";"Larva";160;2
"Unit";"Hydralisk";"Larva";160;2
"Unit";"Hydralisk";"Larva";160;2
"Unit";"Hydralisk";"Larva";160;2
"Unit";"Queen";"Hatchery";154;2
"Unit";"Hydralisk";"Larva";160;2
"Unit";"Hydralisk";"Larva";160;2
"Building";"Hatchery";NA;141;0
"Unit";"Hydralisk";"Larva";160;2
"Unit";"Hydralisk";"Larva";160;2
"Unit";"Hydralisk";"Larva";160;2
"Unit";"Hydralisk";"Larva";160;2
"Unit";"Hydralisk";"Larva";162;2
"Unit";"Hydralisk";"Larva";162;2
"Unit";"Hydralisk";"Larva";180;2
"Unit";"Hydralisk";"Larva";180;2
"Unit";"Hydralisk";"Larva";180;2
"Unit";"Hydralisk";"Larva";180;2
"Building";"CreepTumor";NA;192;0
"Upgrade";"ZergMeleeWeaponsLevel1";"EvolutionChamber";144;0
"Upgrade";"ZergGroundArmorsLevel1";"EvolutionChamber";144;0
"Unit";"Hydralisk";"Larva";192;2
"Unit";"Hydralisk";"Larva";192;2
"Unit";"Hydralisk";"Larva";192;2
"Building";"SporeCrawler";NA;192;0
"Building";"CreepTumor";NA;207;0
"Building";"CreepTumor";NA;207;0
"Building";"CreepTumor";NA;207;0
"Unit";"Queen";"Hatchery";192;2
"Building";"Extractor";NA;217;0
"Building";"Extractor";NA;217;0
"Upgrade";"EvolveMuscularAugments";"HydraliskDen";201;0
"Unit";"Hydralisk";"Larva";217;2
"Unit";"Hydralisk";"Larva";217;2
"Building";"CreepTumor";NA;223;0
"Unit";"Hydralisk";"Larva";223;2
"Unit";"Hydralisk";"Larva";223;2
"Unit";"Overlord";"Larva";223;0
"Unit";"Overlord";"Larva";223;0
"Unit";"Overlord";"Larva";223;0
"Building";"CreepTumor";NA;228;0
"Building";"CreepTumor";NA;232;0
"Unit";"Overlord";"Larva";232;0
"Building";"Hatchery";NA;217;0
"Building";"Extractor";NA;243;0
"Unit";"Queen";"Hatchery";232;2
"Upgrade";"EvolveGroovedSpines";"HydraliskDen";232;0
"Upgrade";"ZergMissileWeaponsLevel1";"EvolutionChamber";222;0
"Building";"CreepTumor";NA;243;0
"Unit";"Zergling";"Larva";243;1
"Unit";"Zergling";"Larva";243;1
"Unit";"Zergling";"Larva";243;1
"Unit";"Zergling";"Larva";243;1
"Unit";"Zergling";"Larva";243;1
"Unit";"Zergling";"Larva";243;1
"Unit";"Zergling";"Larva";243;1
"Unit";"Zergling";"Larva";243;1
"Unit";"Zergling";"Larva";243;1
"Unit";"Zergling";"Larva";243;1
"Unit";"Zergling";"Larva";243;1
"Unit";"Zergling";"Larva";243;1
"Unit";"Zergling";"Larva";243;1
"Unit";"Zergling";"Larva";243;1
"Building";"CreepTumor";NA;243;0
"Building";"InfestationPit";NA;243;0
"Unit";"Zergling";"Larva";243;1
"Unit";"Zergling";"Larva";243;1
"Unit";"Zergling";"Larva";249;1
"Unit";"Zergling";"Larva";249;1
"Building";"CreepTumorQueen";NA;254;0
"Unit";"Baneling";"Zergling";272;0
"Unit";"Baneling";"Zergling";272;0
"Unit";"Baneling";"Zergling";272;0
"Unit";"Baneling";"Zergling";272;0
"Unit";"Baneling";"Zergling";272;0
"Unit";"Baneling";"Zergling";272;0
"Unit";"Baneling";"Zergling";272;0
"Unit";"Baneling";"Zergling";272;0
"Unit";"Queen";"Hatchery";249;2
"Unit";"Zergling";"Larva";272;1
"Unit";"Zergling";"Larva";272;1
"Unit";"Zergling";"Larva";272;1
"Unit";"Zergling";"Larva";272;1
"Unit";"Zergling";"Larva";272;1
"Unit";"Zergling";"Larva";272;1
"Unit";"Zergling";"Larva";272;1
"Unit";"Zergling";"Larva";272;1
"Unit";"Zergling";"Larva";272;1
"Unit";"Zergling";"Larva";272;1
"Unit";"Zergling";"Larva";272;1
"Unit";"Zergling";"Larva";272;1
"Unit";"Zergling";"Larva";272;1
"Unit";"Zergling";"Larva";272;1
"Unit";"Zergling";"Larva";272;1
"Unit";"Zergling";"Larva";272;1
"Unit";"Zergling";"Larva";272;1
"Unit";"Zergling";"Larva";272;1
"Unit";"Zergling";"Larva";272;1
"Unit";"Zergling";"Larva";272;1
"Building";"Extractor";NA;272;0
"Building";"Extractor";NA;294;0
"Building";"CreepTumor";NA;294;0
"Building";"CreepTumor";NA;294;0
"Building";"CreepTumor";NA;294;0
"Building";"Extractor";NA;294;0
"Unit";"Hydralisk";"Larva";294;2
"Unit";"Hydralisk";"Larva";294;2
"Unit";"Hydralisk";"Larva";294;2
"Unit";"Hydralisk";"Larva";294;2
"Unit";"Hydralisk";"Larva";294;2
"Building";"CreepTumorQueen";NA;297;0
"Building";"CreepTumorQueen";NA;297;0
"Unit";"Zergling";"Larva";297;1
"Unit";"Zergling";"Larva";297;1
"Unit";"Zergling";"Larva";297;1
"Unit";"Zergling";"Larva";297;1
"Unit";"Zergling";"Larva";297;1
"Unit";"Zergling";"Larva";297;1
"Unit";"Zergling";"Larva";297;1
"Unit";"Zergling";"Larva";297;1
"Unit";"Zergling";"Larva";297;1
"Unit";"Zergling";"Larva";297;1
"Unit";"Zergling";"Larva";297;1
"Unit";"Zergling";"Larva";297;1
"Unit";"Zergling";"Larva";297;1
"Unit";"Zergling";"Larva";297;1
"Unit";"Zergling";"Larva";297;1
"Unit";"Zergling";"Larva";297;1
"Unit";"Zergling";"Larva";297;1
"Unit";"Zergling";"Larva";297;1
"Building";"CreepTumorQueen";NA;307;0
"Building";"CreepTumorQueen";NA;307;0
"Unit";"Overlord";"Larva";307;0
"Unit";"Overlord";"Larva";307;0
"Unit";"Overlord";"Larva";307;0
"Unit";"Overlord";"Larva";307;0
"Unit";"Overlord";"Larva";307;0
"Building";"Hatchery";NA;274;0
"Building";"CreepTumor";NA;325;0
"Building";"Extractor";NA;325;0
"Upgrade";"ZergGroundArmorsLevel2";"EvolutionChamber";272;0
"Building";"CreepTumor";NA;325;0
"Building";"CreepTumor";NA;325;0
"Building";"CreepTumor";NA;325;0
"Unit";"Viper";"Larva";325;3
"Building";"CreepTumor";NA;325;0
"Unit";"Viper";"Larva";325;3
"Unit";"Viper";"Larva";325;3
"Building";"CreepTumor";NA;325;0
"Building";"CreepTumor";NA;325;0
"Unit";"Zergling";"Larva";325;1
"Unit";"Zergling";"Larva";325;1
"Building";"CreepTumor";NA;328;0
"Unit";"Zergling";"Larva";325;1
"Unit";"Zergling";"Larva";325;1
"Unit";"Zergling";"Larva";325;1
"Unit";"Zergling";"Larva";325;1
"Unit";"Zergling";"Larva";325;1
"Unit";"Zergling";"Larva";325;1
"Unit";"Zergling";"Larva";325;1
"Unit";"Zergling";"Larva";325;1
"Unit";"Zergling";"Larva";325;1
"Unit";"Zergling";"Larva";325;1
"Unit";"Zergling";"Larva";325;1
"Unit";"Zergling";"Larva";325;1
"Unit";"Zergling";"Larva";325;1
"Unit";"Zergling";"Larva";325;1
"Unit";"Zergling";"Larva";325;1
"Unit";"Zergling";"Larva";325;1
"Unit";"Zergling";"Larva";325;1
"Unit";"Zergling";"Larva";325;1
"Unit";"Zergling";"Larva";325;1
"Unit";"Zergling";"Larva";325;1
"Unit";"Zergling";"Larva";325;1
"Unit";"Zergling";"Larva";325;1
"Unit";"Zergling";"Larva";325;1
"Unit";"Zergling";"Larva";325;1
"Unit";"Zergling";"Larva";325;1
"Unit";"Zergling";"Larva";325;1
"Unit";"Zergling";"Larva";325;1
"Unit";"Zergling";"Larva";325;1
"Unit";"Zergling";"Larva";325;1
"Unit";"Zergling";"Larva";325;1
"Unit";"Zergling";"Larva";325;1
"Unit";"Zergling";"Larva";325;1
"Unit";"Zergling";"Larva";325;1
"Unit";"Zergling";"Larva";325;1
"Unit";"Zergling";"Larva";325;1
"Unit";"Zergling";"Larva";325;1
"Building";"CreepTumorQueen";NA;328;0
"Building";"CreepTumorQueen";NA;328;0
"Upgrade";"ZergMeleeWeaponsLevel2";"EvolutionChamber";294;0
"Unit";"Overlord";"Larva";328;0
"Building";"UltraliskCavern";NA;325;0
"Building";"CreepTumor";NA;375;0
"Building";"CreepTumor";NA;375;0
"Building";"CreepTumor";NA;375;0
"Building";"CreepTumor";NA;375;0
"Building";"CreepTumor";NA;375;0
"Unit";"Overlord";"Larva";375;0
"Building";"CreepTumor";NA;375;0
"Building";"CreepTumor";NA;375;0
"Building";"CreepTumor";NA;375;0
"Building";"CreepTumor";NA;375;0
"Building";"CreepTumorQueen";NA;375;0
"Unit";"Zergling";"Larva";375;1
"Unit";"Zergling";"Larva";375;1
"Building";"CreepTumorQueen";NA;375;0
"Unit";"Zergling";"Larva";375;1
"Unit";"Zergling";"Larva";375;1
"Unit";"Zergling";"Larva";375;1
"Unit";"Zergling";"Larva";375;1
"Unit";"Baneling";"Zergling";375;0
"Unit";"Baneling";"Zergling";375;0
"Unit";"Baneling";"Zergling";375;0
"Unit";"Baneling";"Zergling";375;0
"Unit";"Baneling";"Zergling";375;0
"Unit";"Baneling";"Zergling";375;0
"Unit";"Baneling";"Zergling";375;0
"Unit";"Baneling";"Zergling";375;0
"Unit";"Baneling";"Zergling";375;0
"Unit";"Baneling";"Zergling";375;0
"Unit";"Baneling";"Zergling";375;0
"Unit";"Baneling";"Zergling";375;0
"Unit";"Baneling";"Zergling";375;0
"Building";"CreepTumor";NA;375;0
"Unit";"Ultralisk";"Larva";375;6
"Unit";"Ultralisk";"Larva";375;6
"Unit";"Ultralisk";"Larva";375;6
"Building";"Hatchery";NA;328;0
"Building";"CreepTumor";NA;381;0
"Building";"SporeCrawler";NA;381;0
"Building";"SporeCrawler";NA;381;0
"Building";"Hatchery";NA;375;0
"Building";"CreepTumor";NA;399;0
"Building";"Spire";NA;375;0
"Building";"SporeCrawler";NA;399;0
"Upgrade";"ChitinousPlating";"UltraliskCavern";375;0
"Building";"CreepTumor";NA;399;0
"Building";"CreepTumor";NA;399;0
"Building";"CreepTumor";NA;399;0
"Building";"CreepTumor";NA;399;0
"Building";"CreepTumor";NA;399;0
"Building";"CreepTumor";NA;399;0
"Building";"Extractor";NA;399;0
"Building";"Extractor";NA;399;0
"Upgrade";"Burrow";"Hatchery";399;0
"Building";"CreepTumorQueen";NA;399;0
"Building";"CreepTumor";NA;399;0
"Building";"CreepTumorQueen";NA;399;0
"Upgrade";"ZergGroundArmorsLevel3";"EvolutionChamber";375;0
"Building";"CreepTumor";NA;399;0
"Building";"CreepTumor";NA;399;0
"Building";"CreepTumorQueen";NA;399;0
"Unit";"Ultralisk";"Larva";399;6
"Unit";"Ultralisk";"Larva";399;6
"Unit";"Ultralisk";"Larva";399;6
"Unit";"Ultralisk";"Larva";399;6
"Unit";"Ultralisk";"Larva";399;6
"Unit";"Corruptor";"Larva";399;2
"Unit";"Corruptor";"Larva";399;2
"Unit";"Corruptor";"Larva";399;2
"Unit";"Corruptor";"Larva";399;2
"Unit";"Corruptor";"Larva";399;2
"Unit";"Corruptor";"Larva";399;2
"Unit";"Corruptor";"Larva";399;2
"Unit";"Corruptor";"Larva";399;2
"Unit";"Zergling";"Larva";399;1
"Unit";"Zergling";"Larva";399;1
"Unit";"Corruptor";"Larva";399;2
"Unit";"Zergling";"Larva";399;1
"Unit";"Zergling";"Larva";399;1
"Unit";"Zergling";"Larva";399;1
"Unit";"Zergling";"Larva";399;1
"Unit";"Zergling";"Larva";399;1
"Unit";"Zergling";"Larva";399;1
"Unit";"Zergling";"Larva";399;1
"Unit";"Zergling";"Larva";399;1
"Unit";"Zergling";"Larva";399;1
"Unit";"Zergling";"Larva";399;1
"Unit";"Zergling";"Larva";399;1
"Unit";"Zergling";"Larva";399;1
"Unit";"Corruptor";"Larva";399;2
"Upgrade";"ZergMeleeWeaponsLevel3";"EvolutionChamber";399;0
"Building";"CreepTumor";NA;465;0
"Building";"CreepTumor";NA;465;0
"Building";"CreepTumor";NA;465;0
"Building";"CreepTumor";NA;465;0
"Building";"CreepTumor";NA;465;0
"Building";"CreepTumor";NA;465;0
"Building";"CreepTumor";NA;465;0
"Building";"CreepTumor";NA;465;0
"Building";"CreepTumor";NA;465;0
"Unit";"Zergling";"Larva";465;1
"Unit";"Zergling";"Larva";465;1
"Unit";"Baneling";"Zergling";465;0
"Unit";"Baneling";"Zergling";465;0
"Unit";"Baneling";"Zergling";465;0
"Unit";"Baneling";"Zergling";465;0
"Unit";"Baneling";"Zergling";465;0
"Unit";"Baneling";"Zergling";465;0
"Unit";"Baneling";"Zergling";465;0
"Unit";"Baneling";"Zergling";465;0
"Unit";"Baneling";"Zergling";465;0
"Building";"CreepTumor";NA;468;0
"Building";"CreepTumorQueen";NA;468;0
"Building";"CreepTumor";NA;468;0
"Building";"CreepTumor";NA;468;0
"Building";"CreepTumor";NA;468;0
"Building";"Extractor";NA;468;0
"Building";"Extractor";NA;468;0
"Unit";"Zergling";"Larva";477;1
"Unit";"Zergling";"Larva";477;1
"Unit";"Zergling";"Larva";477;1
"Unit";"Zergling";"Larva";477;1
"Unit";"Zergling";"Larva";477;1
"Unit";"Zergling";"Larva";477;1
"Unit";"Zergling";"Larva";477;1
"Unit";"Zergling";"Larva";477;1
"Unit";"Zergling";"Larva";477;1
"Unit";"Zergling";"Larva";477;1
"Unit";"Zergling";"Larva";477;1
"Unit";"Zergling";"Larva";477;1
"Unit";"Zergling";"Larva";477;1
"Unit";"Zergling";"Larva";477;1
"Unit";"Zergling";"Larva";477;1
"Unit";"Zergling";"Larva";477;1
"Unit";"Zergling";"Larva";477;1
"Unit";"Zergling";"Larva";477;1
"Unit";"Zergling";"Larva";477;1
"Unit";"Zergling";"Larva";477;1
"Unit";"Zergling";"Larva";477;1
"Unit";"Zergling";"Larva";477;1
"Building";"CreepTumor";NA;482;0
"Building";"CreepTumor";NA;482;0
"Building";"CreepTumor";NA;482;0
"Upgrade";"ZergMissileWeaponsLevel2";"EvolutionChamber";465;0
