"type";"unit_name";"on_building";"total_supply";"supply"
"Unit";"Overlord";"Larva";12;0
"Building";"SpawningPool";NA;16;0
"Building";"Extractor";NA;18;0
"Unit";"Zergling";"Larva";20;1
"Unit";"Zergling";"Larva";20;1
"Unit";"Zergling";"Larva";20;1
"Unit";"Zergling";"Larva";20;1
"Unit";"Overlord";"Larva";20;0
"Unit";"Queen";"Hatchery";20;2
"Building";"Hatchery";NA;18;0
"Unit";"Queen";"Hatchery";25;2
"Unit";"Overlord";"Larva";38;0
"Building";"CreepTumorQueen";NA;40;0
"Unit";"Overlord";"Larva";41;0
"Unit";"Queen";"Hatchery";40;2
"Building";"CreepTumor";NA;48;0
"Unit";"Zergling";"Larva";47;1
"Unit";"Zergling";"Larva";47;1
"Unit";"Zergling";"Larva";47;1
"Unit";"Zergling";"Larva";47;1
"Building";"CreepTumorQueen";NA;48;0
"Building";"Hatchery";NA;35;0
"Unit";"Overlord";"Larva";48;0
"Unit";"Zergling";"Larva";48;1
"Unit";"Zergling";"Larva";48;1
"Unit";"Zergling";"Larva";48;1
"Unit";"Zergling";"Larva";48;1
"Unit";"Zergling";"Larva";48;1
"Unit";"Zergling";"Larva";48;1
"Unit";"Zergling";"Larva";48;1
"Unit";"Zergling";"Larva";48;1
"Unit";"Overlord";"Larva";54;0
"Unit";"Overlord";"Larva";54;0
"Unit";"Queen";"Hatchery";48;2
"Building";"CreepTumor";NA;62;0
"Building";"CreepTumor";NA;62;0
"Unit";"Overlord";"Larva";62;0
"Unit";"Queen";"Hatchery";54;2
"Unit";"Overlord";"Larva";68;0
"Unit";"Queen";"Hatchery";62;2
"Building";"SporeCrawler";NA;72;0
"Building";"SporeCrawler";NA;72;0
"Building";"CreepTumor";NA;78;0
"Building";"CreepTumor";NA;78;0
"Building";"CreepTumorQueen";NA;80;0
"Building";"SporeCrawler";NA;78;0
"Building";"CreepTumorQueen";NA;80;0
"Building";"CreepTumorQueen";NA;80;0
"Building";"EvolutionChamber";NA;78;0
"Building";"EvolutionChamber";NA;78;0
"Unit";"Queen";"Hatchery";74;2
"Unit";"Overlord";"Larva";80;0
"Unit";"Zergling";"Larva";93;1
"Unit";"Zergling";"Larva";93;1
"Unit";"Zergling";"Larva";94;1
"Unit";"Zergling";"Larva";94;1
"Unit";"Zergling";"Larva";94;1
"Unit";"Zergling";"Larva";94;1
"Unit";"Zergling";"Larva";94;1
"Unit";"Zergling";"Larva";94;1
"Unit";"Zergling";"Larva";94;1
"Unit";"Zergling";"Larva";94;1
"Unit";"Overlord";"Larva";94;0
"Building";"CreepTumor";NA;94;0
"Building";"CreepTumorQueen";NA;96;0
"Building";"CreepTumor";NA;94;0
"Building";"CreepTumorQueen";NA;104;0
"Building";"BanelingNest";NA;89;0
"Unit";"Queen";"Hatchery";94;2
"Unit";"Zergling";"Larva";109;1
"Unit";"Zergling";"Larva";109;1
"Unit";"Zergling";"Larva";109;1
"Unit";"Zergling";"Larva";109;1
"Building";"Extractor";NA;109;0
"Building";"Extractor";NA;110;0
"Building";"Extractor";NA;110;0
"Building";"SporeCrawler";NA;110;0
"Building";"Extractor";NA;110;0
"Unit";"Zergling";"Larva";111;1
"Unit";"Zergling";"Larva";111;1
"Unit";"Zergling";"Larva";111;1
"Unit";"Zergling";"Larva";111;1
"Unit";"Zergling";"Larva";111;1
"Unit";"Zergling";"Larva";111;1
"Unit";"Zergling";"Larva";111;1
"Unit";"Zergling";"Larva";111;1
"Unit";"Zergling";"Larva";111;1
"Unit";"Zergling";"Larva";111;1
"Building";"CreepTumor";NA;132;0
"Building";"CreepTumor";NA;132;0
"Building";"CreepTumor";NA;133;0
"Building";"CreepTumor";NA;133;0
"Unit";"Overlord";"Larva";133;0
"Building";"CreepTumorQueen";NA;141;0
"Building";"CreepTumor";NA;141;0
"Building";"Extractor";NA;141;0
"Upgrade";"ZergGroundArmorsLevel1";"EvolutionChamber";109;0
"Unit";"Zergling";"Larva";143;1
"Unit";"Zergling";"Larva";143;1
"Unit";"Zergling";"Larva";143;1
"Unit";"Zergling";"Larva";143;1
"Unit";"Zergling";"Larva";143;1
"Unit";"Zergling";"Larva";143;1
"Building";"CreepTumor";NA;143;0
"Building";"CreepTumor";NA;146;0
"Building";"CreepTumor";NA;146;0
"Upgrade";"ZergMeleeWeaponsLevel1";"EvolutionChamber";117;0
"Building";"CreepTumorQueen";NA;152;0
"Building";"CreepTumorQueen";NA;152;0
"Building";"CreepTumorQueen";NA;152;0
"Building";"CreepTumor";NA;152;0
"Building";"CreepTumor";NA;152;0
"Unit";"Overlord";"Larva";152;0
"Building";"CreepTumor";NA;152;0
"Building";"Hatchery";NA;137;0
"Building";"CreepTumorQueen";NA;161;0
"Building";"RoachWarren";NA;152;0
"Building";"HydraliskDen";NA;162;0
"Building";"CreepTumor";NA;162;0
"Unit";"Roach";"Larva";162;2
"Unit";"Overlord";"Larva";162;0
"Unit";"Roach";"Larva";162;2
"Unit";"Overlord";"Larva";162;0
"Unit";"Roach";"Larva";162;2
"Unit";"Roach";"Larva";162;2
"Unit";"Roach";"Larva";162;2
"Unit";"Roach";"Larva";162;2
"Unit";"Overlord";"Larva";162;0
"Unit";"Roach";"Larva";162;2
"Unit";"Roach";"Larva";162;2
"Unit";"Roach";"Larva";162;2
"Unit";"Roach";"Larva";162;2
"Unit";"Overlord";"Larva";162;0
"Unit";"Overlord";"Larva";162;0
"Unit";"Overlord";"Larva";162;0
"Unit";"Overlord";"Larva";162;0
"Building";"InfestationPit";NA;162;0
"Building";"CreepTumor";NA;162;0
"Building";"Extractor";NA;162;0
"Building";"Extractor";NA;162;0
"Building";"CreepTumor";NA;162;0
"Building";"CreepTumor";NA;162;0
"Building";"CreepTumor";NA;162;0
"Building";"CreepTumorQueen";NA;166;0
"Building";"CreepTumor";NA;186;0
"Unit";"Overlord";"Larva";178;0
"Unit";"Overlord";"Larva";186;0
"Building";"SpineCrawler";NA;162;0
"Building";"SpineCrawler";NA;162;0
"Building";"CreepTumorQueen";NA;191;0
"Building";"CreepTumor";NA;191;0
"Building";"CreepTumor";NA;191;0
"Building";"CreepTumor";NA;191;0
"Building";"CreepTumor";NA;191;0
"Building";"CreepTumor";NA;191;0
"Building";"CreepTumorQueen";NA;191;0
"Unit";"Roach";"Larva";191;2
"Unit";"Roach";"Larva";191;2
"Unit";"Roach";"Larva";191;2
"Unit";"Roach";"Larva";191;2
"Unit";"Roach";"Larva";191;2
"Unit";"Roach";"Larva";191;2
"Unit";"Roach";"Larva";191;2
"Upgrade";"ZergMissileWeaponsLevel1";"EvolutionChamber";162;0
"Unit";"Hydralisk";"Larva";191;2
"Unit";"Hydralisk";"Larva";191;2
"Unit";"Hydralisk";"Larva";191;2
"Unit";"Hydralisk";"Larva";191;2
"Unit";"Hydralisk";"Larva";191;2
"Upgrade";"GlialReconstitution";"RoachWarren";186;0
"Unit";"Roach";"Larva";205;2
"Unit";"Roach";"Larva";205;2
"Unit";"Overlord";"Larva";205;0
"Unit";"Roach";"Larva";205;2
"Unit";"Roach";"Larva";205;2
"Unit";"Roach";"Larva";205;2
"Unit";"Roach";"Larva";205;2
"Unit";"Hydralisk";"Larva";205;2
"Unit";"Hydralisk";"Larva";205;2
"Unit";"Hydralisk";"Larva";205;2
"Unit";"Hydralisk";"Larva";205;2
"Unit";"Hydralisk";"Larva";205;2
"Unit";"Overlord";"Larva";205;0
"Unit";"Overlord";"Larva";205;0
"Unit";"Overlord";"Larva";205;0
"Unit";"Overlord";"Larva";205;0
"Building";"CreepTumor";NA;215;0
"Building";"CreepTumor";NA;215;0
"Building";"CreepTumor";NA;215;0
"Building";"CreepTumor";NA;215;0
"Building";"CreepTumor";NA;215;0
"Building";"CreepTumor";NA;215;0
"Building";"CreepTumor";NA;215;0
"Building";"CreepTumor";NA;223;0
"Building";"Hatchery";NA;186;0
"Building";"CreepTumor";NA;227;0
"Building";"CreepTumor";NA;237;0
"Building";"CreepTumorQueen";NA;237;0
"Building";"CreepTumorQueen";NA;237;0
"Building";"CreepTumor";NA;237;0
"Building";"CreepTumor";NA;237;0
"Building";"CreepTumorQueen";NA;237;0
"Upgrade";"EvolveGroovedSpines";"HydraliskDen";205;0
"Building";"CreepTumorQueen";NA;237;0
"Building";"CreepTumor";NA;237;0
"Building";"CreepTumor";NA;237;0
"Building";"CreepTumor";NA;237;0
"Building";"CreepTumor";NA;237;0
"Building";"CreepTumor";NA;237;0
"Building";"CreepTumor";NA;237;0
"Building";"CreepTumor";NA;239;0
"Building";"CreepTumor";NA;239;0
"Building";"CreepTumor";NA;239;0
"Unit";"Viper";"Larva";237;3
"Building";"CreepTumor";NA;239;0
"Building";"CreepTumor";NA;239;0
"Building";"CreepTumor";NA;239;0
"Building";"CreepTumor";NA;242;0
"Building";"CreepTumor";NA;242;0
"Unit";"Hydralisk";"Larva";242;2
"Unit";"Hydralisk";"Larva";242;2
"Unit";"Hydralisk";"Larva";242;2
"Unit";"Hydralisk";"Larva";242;2
"Unit";"Hydralisk";"Larva";242;2
"Unit";"Hydralisk";"Larva";242;2
"Upgrade";"EvolveMuscularAugments";"HydraliskDen";239;0
"Unit";"Roach";"Larva";248;2
"Unit";"Roach";"Larva";248;2
"Unit";"Roach";"Larva";248;2
"Unit";"Roach";"Larva";248;2
"Unit";"Roach";"Larva";248;2
"Unit";"Roach";"Larva";248;2
"Unit";"Roach";"Larva";248;2
"Unit";"Roach";"Larva";248;2
"Unit";"Roach";"Larva";248;2
"Unit";"Roach";"Larva";248;2
"Unit";"Roach";"Larva";248;2
"Unit";"Roach";"Larva";248;2
"Building";"CreepTumor";NA;254;0
"Upgrade";"ZergMissileWeaponsLevel2";"EvolutionChamber";237;0
"Building";"CreepTumor";NA;254;0
"Building";"CreepTumor";NA;254;0
"Unit";"Roach";"Larva";254;2
"Unit";"Overlord";"Larva";254;0
"Building";"Extractor";NA;254;0
"Building";"Extractor";NA;254;0
"Building";"CreepTumorQueen";NA;278;0
"Unit";"Hydralisk";"Larva";278;2
"Unit";"Hydralisk";"Larva";278;2
"Building";"SpineCrawler";NA;278;0
"Building";"SpineCrawler";NA;278;0
"Building";"CreepTumorQueen";NA;284;0
"Unit";"Hydralisk";"Larva";280;2
"Unit";"Hydralisk";"Larva";280;2
"Building";"CreepTumor";NA;284;0
"Building";"CreepTumor";NA;284;0
"Building";"CreepTumorQueen";NA;284;0
"Building";"CreepTumor";NA;284;0
"Building";"CreepTumor";NA;284;0
"Building";"CreepTumor";NA;284;0
"Building";"CreepTumor";NA;284;0
"Building";"CreepTumor";NA;288;0
"Unit";"Queen";"Hatchery";280;2
"Building";"CreepTumor";NA;290;0
"Building";"CreepTumor";NA;290;0
"Unit";"Hydralisk";"Larva";290;2
"Unit";"Hydralisk";"Larva";290;2
"Unit";"Hydralisk";"Larva";290;2
"Unit";"Hydralisk";"Larva";290;2
"Building";"Spire";NA;288;0
"Building";"Hatchery";NA;288;0
"Unit";"Roach";"Larva";321;2
"Unit";"Roach";"Larva";321;2
"Unit";"Roach";"Larva";321;2
"Unit";"Roach";"Larva";321;2
"Building";"SpineCrawler";NA;305;0
"Building";"SpineCrawler";NA;309;0
"Building";"SpineCrawler";NA;319;0
"Building";"Hatchery";NA;290;0
"Building";"CreepTumor";NA;335;0
"Building";"CreepTumor";NA;335;0
"Building";"CreepTumor";NA;335;0
"Building";"CreepTumor";NA;335;0
"Building";"CreepTumor";NA;335;0
"Building";"CreepTumor";NA;335;0
"Building";"CreepTumor";NA;335;0
"Building";"CreepTumor";NA;335;0
"Upgrade";"ZergGroundArmorsLevel2";"EvolutionChamber";290;0
"Building";"CreepTumorQueen";NA;335;0
"Upgrade";"Burrow";"Hatchery";327;0
"Upgrade";"ZergMissileWeaponsLevel3";"EvolutionChamber";290;0
"Building";"CreepTumor";NA;335;0
"Building";"CreepTumor";NA;335;0
"Building";"CreepTumor";NA;335;0
"Building";"CreepTumor";NA;335;0
"Unit";"Viper";"Larva";335;3
"Building";"CreepTumorQueen";NA;335;0
"Unit";"Hydralisk";"Larva";335;2
"Unit";"Hydralisk";"Larva";335;2
"Unit";"Hydralisk";"Larva";335;2
"Unit";"Hydralisk";"Larva";344;2
"Unit";"Hydralisk";"Larva";344;2
"Unit";"Hydralisk";"Larva";344;2
"Unit";"Overlord";"Larva";344;0
"Unit";"Overlord";"Larva";344;0
"Unit";"Overlord";"Larva";344;0
"Unit";"Hydralisk";"Larva";350;2
"Unit";"Hydralisk";"Larva";350;2
"Unit";"Hydralisk";"Larva";350;2
"Unit";"Hydralisk";"Larva";350;2
"Unit";"Viper";"Larva";344;3
"Unit";"Viper";"Larva";344;3
"Unit";"Queen";"Hatchery";344;2
"Unit";"Queen";"Hatchery";344;2
"Building";"CreepTumorQueen";NA;350;0
"Unit";"Hydralisk";"Larva";350;2
"Unit";"Hydralisk";"Larva";350;2
"Unit";"Hydralisk";"Larva";350;2
"Unit";"Hydralisk";"Larva";350;2
"Unit";"Hydralisk";"Larva";350;2
"Building";"CreepTumorQueen";NA;364;0
"Building";"SporeCrawler";NA;378;0
"Unit";"Hydralisk";"Larva";378;2
"Unit";"Hydralisk";"Larva";378;2
"Unit";"Hydralisk";"Larva";378;2
"Unit";"Hydralisk";"Larva";378;2
"Unit";"Hydralisk";"Larva";378;2
"Unit";"Hydralisk";"Larva";378;2
"Unit";"Corruptor";"Larva";378;2
"Unit";"Corruptor";"Larva";378;2
"Unit";"Corruptor";"Larva";378;2
"Unit";"Corruptor";"Larva";378;2
"Unit";"Corruptor";"Larva";378;2
"Unit";"Corruptor";"Larva";378;2
"Unit";"Corruptor";"Larva";378;2
"Unit";"Corruptor";"Larva";378;2
"Unit";"Corruptor";"Larva";378;2
"Unit";"Corruptor";"Larva";378;2
"Unit";"Corruptor";"Larva";378;2
"Unit";"Corruptor";"Larva";378;2
"Unit";"Overlord";"Larva";390;0
"Building";"CreepTumor";NA;414;0
"Building";"CreepTumor";NA;414;0
"Building";"CreepTumor";NA;414;0
"Building";"CreepTumor";NA;414;0
"Upgrade";"ZergMeleeWeaponsLevel2";"EvolutionChamber";350;0
"Building";"CreepTumor";NA;418;0
"Building";"Hatchery";NA;378;0
"Upgrade";"ZergGroundArmorsLevel3";"EvolutionChamber";350;0
"Building";"CreepTumor";NA;418;0
"Building";"Extractor";NA;418;0
"Building";"Extractor";NA;418;0
"Building";"CreepTumor";NA;418;0
"Building";"CreepTumor";NA;423;0
"Building";"SporeCrawler";NA;423;0
"Building";"SporeCrawler";NA;425;0
"Building";"SporeCrawler";NA;425;0
"Building";"SporeCrawler";NA;425;0
"Building";"SporeCrawler";NA;425;0
"Building";"CreepTumorQueen";NA;429;0
"Building";"CreepTumorQueen";NA;429;0
"Building";"CreepTumorQueen";NA;429;0
"Building";"CreepTumorQueen";NA;429;0
"Building";"CreepTumorQueen";NA;429;0
