"type";"unit_name";"on_building";"total_supply_lag";"supply"
"Unit";"Overlord";"Larva";13;0
"Building";"SpawningPool";NA;17;0
"Building";"Hatchery";NA;18;0
"Building";"Extractor";NA;20;0
"Unit";"Queen";"Hatchery";21;2
"Unit";"Zergling";"Larva";23;1
"Unit";"Zergling";"Larva";24;1
"Unit";"Overlord";"Larva";25;0
"Unit";"Queen";"Hatchery";27;2
"Unit";"Overlord";"Larva";29;0
"Unit";"Queen";"Hatchery";32;2
"Unit";"Overlord";"Larva";40;0
"Building";"Hatchery";NA;40;0
"Unit";"Overlord";"Larva";40;0
"Building";"CreepTumorQueen";NA;42;0
"Unit";"Overlord";"Larva";47;0
"Unit";"Queen";"Hatchery";47;2
"Unit";"Zergling";"Larva";49;1
"Unit";"Zergling";"Larva";50;1
"Building";"CreepTumor";NA;51;0
"Unit";"Zergling";"Larva";51;1
"Unit";"Zergling";"Larva";52;1
"Unit";"Zergling";"Larva";53;1
"Unit";"Zergling";"Larva";54;1
"Unit";"Zergling";"Larva";55;1
"Unit";"Zergling";"Larva";56;1
"Unit";"Zergling";"Larva";57;1
"Unit";"Zergling";"Larva";58;1
"Unit";"Zergling";"Larva";59;1
"Unit";"Zergling";"Larva";60;1
"Unit";"Zergling";"Larva";61;1
"Unit";"Zergling";"Larva";62;1
"Unit";"Zergling";"Larva";63;1
"Unit";"Zergling";"Larva";64;1
"Unit";"Zergling";"Larva";65;1
"Unit";"Zergling";"Larva";66;1
"Unit";"Zergling";"Larva";67;1
"Unit";"Zergling";"Larva";68;1
"Unit";"Zergling";"Larva";69;1
"Unit";"Zergling";"Larva";70;1
"Unit";"Zergling";"Larva";71;1
"Unit";"Zergling";"Larva";72;1
"Unit";"Overlord";"Larva";73;0
"Unit";"Zergling";"Larva";73;1
"Unit";"Zergling";"Larva";74;1
"Unit";"Zergling";"Larva";75;1
"Unit";"Zergling";"Larva";76;1
"Building";"CreepTumor";NA;77;0
"Unit";"Queen";"Hatchery";77;2
"Unit";"Overlord";"Larva";79;0
"Unit";"Queen";"Hatchery";81;2
"Unit";"Queen";"Hatchery";85;2
"Building";"CreepTumor";NA;90;0
"Unit";"Queen";"Hatchery";90;2
"Building";"CreepTumorQueen";NA;98;0
"Unit";"Queen";"Hatchery";100;2
"Building";"EvolutionChamber";NA;102;0
"Building";"EvolutionChamber";NA;103;0
"Building";"SporeCrawler";NA;103;0
"Building";"SporeCrawler";NA;103;0
"Building";"CreepTumorQueen";NA;103;0
"Building";"SporeCrawler";NA;103;0
"Building";"CreepTumor";NA;104;0
"Building";"CreepTumorQueen";NA;113;0
"Unit";"Zergling";"Larva";118;1
"Unit";"Zergling";"Larva";119;1
"Unit";"Overlord";"Larva";120;0
"Building";"Extractor";NA;120;0
"Building";"Extractor";NA;120;0
"Building";"RoachWarren";NA;120;0
"Unit";"Zergling";"Larva";120;1
"Unit";"Zergling";"Larva";121;1
"Unit";"Zergling";"Larva";122;1
"Unit";"Zergling";"Larva";123;1
"Unit";"Zergling";"Larva";124;1
"Unit";"Zergling";"Larva";125;1
"Unit";"Zergling";"Larva";126;1
"Unit";"Zergling";"Larva";127;1
"Unit";"Overlord";"Larva";128;0
"Unit";"Overlord";"Larva";128;0
"Building";"Extractor";NA;129;0
"Unit";"Overlord";"Larva";129;0
"Building";"CreepTumorQueen";NA;129;0
"Unit";"Overlord";"Larva";129;0
"Building";"CreepTumorQueen";NA;129;0
"Building";"Extractor";NA;132;0
"Building";"Extractor";NA;132;0
"Building";"CreepTumorQueen";NA;132;0
"Building";"CreepTumorQueen";NA;133;0
"Unit";"Overlord";"Larva";138;0
"Building";"CreepTumorQueen";NA;141;0
"Building";"CreepTumor";NA;141;0
"Building";"CreepTumor";NA;141;0
"Unit";"Overlord";"Larva";141;0
"Building";"CreepTumorQueen";NA;141;0
"Unit";"Roach";"Larva";141;2
"Unit";"Roach";"Larva";143;2
"Unit";"Roach";"Larva";145;2
"Unit";"Roach";"Larva";147;2
"Unit";"Roach";"Larva";149;2
"Building";"CreepTumor";NA;151;0
"Unit";"Roach";"Larva";151;2
"Building";"CreepTumor";NA;153;0
"Building";"CreepTumor";NA;153;0
"Building";"CreepTumor";NA;153;0
"Unit";"Roach";"Larva";153;2
"Building";"CreepTumorQueen";NA;156;0
"Unit";"Roach";"Larva";158;2
"Building";"CreepTumorQueen";NA;160;0
"Unit";"Roach";"Larva";160;2
"Building";"InfestationPit";NA;162;0
"Building";"CreepTumorQueen";NA;162;0
"Unit";"Roach";"Larva";162;2
"Unit";"Roach";"Larva";164;2
"Building";"CreepTumor";NA;166;0
"Building";"CreepTumor";NA;166;0
"Building";"CreepTumor";NA;166;0
"Unit";"Roach";"Larva";166;2
"Unit";"Roach";"Larva";168;2
"Unit";"Roach";"Larva";170;2
"Unit";"Roach";"Larva";172;2
"Unit";"Roach";"Larva";174;2
"Building";"CreepTumorQueen";NA;176;0
"Unit";"Roach";"Larva";176;2
"Unit";"Roach";"Larva";178;2
"Unit";"Roach";"Larva";180;2
"Unit";"Roach";"Larva";182;2
"Unit";"Roach";"Larva";184;2
"Upgrade";"GlialReconstitution";"RoachWarren";186;0
"Building";"Hatchery";NA;186;0
"Building";"Spire";NA;186;0
"Unit";"Roach";"Larva";186;2
"Unit";"Roach";"Larva";188;2
"Unit";"Roach";"Larva";190;2
"Building";"CreepTumor";NA;192;0
"Building";"CreepTumor";NA;192;0
"Building";"CreepTumor";NA;192;0
"Building";"CreepTumor";NA;192;0
"Building";"CreepTumorQueen";NA;192;0
"Building";"CreepTumor";NA;192;0
"Building";"CreepTumor";NA;192;0
"Building";"CreepTumor";NA;192;0
"Unit";"Overlord";"Larva";192;0
"Unit";"Overlord";"Larva";192;0
"Unit";"Overlord";"Larva";192;0
"Unit";"Overlord";"Larva";192;0
"Building";"CreepTumor";NA;192;0
"Unit";"Overlord";"Larva";192;0
"Building";"CreepTumorQueen";NA;192;0
"Building";"CreepTumorQueen";NA;192;0
"Building";"Hatchery";NA;192;0
"Unit";"Overlord";"Larva";192;0
"Building";"CreepTumor";NA;200;0
"Building";"CreepTumor";NA;200;0
"Building";"CreepTumor";NA;200;0
"Building";"CreepTumor";NA;200;0
"Building";"CreepTumor";NA;200;0
"Building";"CreepTumor";NA;200;0
"Building";"Extractor";NA;200;0
"Building";"CreepTumorQueen";NA;200;0
"Building";"CreepTumor";NA;200;0
"Building";"CreepTumor";NA;200;0
"Unit";"Queen";"Hatchery";200;2
"Unit";"Queen";"Hatchery";202;2
"Building";"Extractor";NA;204;0
"Building";"SporeCrawler";NA;212;0
"Unit";"Viper";"Larva";216;3
"Unit";"Viper";"Larva";219;3
"Building";"CreepTumor";NA;222;0
"Building";"CreepTumor";NA;222;0
"Building";"CreepTumor";NA;222;0
"Building";"CreepTumor";NA;222;0
"Building";"CreepTumor";NA;222;0
"Unit";"Overlord";"Larva";222;0
"Unit";"Overlord";"Larva";222;0
"Unit";"Overlord";"Larva";222;0
"Building";"HydraliskDen";NA;222;0
"Unit";"Queen";"Hatchery";222;2
"Unit";"Queen";"Hatchery";224;2
"Building";"SpineCrawler";NA;226;0
"Building";"SpineCrawler";NA;226;0
"Building";"SpineCrawler";NA;226;0
"Building";"CreepTumorQueen";NA;226;0
"Building";"CreepTumorQueen";NA;226;0
"Building";"CreepTumorQueen";NA;226;0
"Building";"CreepTumorQueen";NA;226;0
"Unit";"Corruptor";"Larva";226;2
"Unit";"Corruptor";"Larva";228;2
"Unit";"Corruptor";"Larva";230;2
"Unit";"Corruptor";"Larva";232;2
"Unit";"Corruptor";"Larva";234;2
"Unit";"Corruptor";"Larva";236;2
"Unit";"Queen";"Hatchery";238;2
"Building";"CreepTumor";NA;240;0
"Building";"CreepTumorQueen";NA;240;0
"Building";"CreepTumorQueen";NA;240;0
"Building";"CreepTumorQueen";NA;240;0
"Building";"CreepTumorQueen";NA;240;0
"Unit";"Corruptor";"Larva";240;2
"Unit";"Corruptor";"Larva";242;2
"Building";"CreepTumorQueen";NA;244;0
"Building";"CreepTumorQueen";NA;244;0
"Unit";"Queen";"Hatchery";244;2
"Unit";"Queen";"Hatchery";246;2
"Building";"CreepTumor";NA;248;0
"Building";"CreepTumorQueen";NA;248;0
"Building";"CreepTumorQueen";NA;248;0
"Building";"CreepTumorQueen";NA;248;0
"Building";"CreepTumorQueen";NA;248;0
"Building";"CreepTumor";NA;248;0
"Building";"CreepTumor";NA;248;0
"Building";"CreepTumor";NA;248;0
"Building";"CreepTumor";NA;248;0
"Building";"CreepTumor";NA;248;0
"Building";"CreepTumor";NA;248;0
"Building";"CreepTumorQueen";NA;248;0
"Building";"CreepTumorQueen";NA;248;0
"Building";"CreepTumorQueen";NA;248;0
"Unit";"Corruptor";"Larva";248;2
"Unit";"Corruptor";"Larva";250;2
"Building";"CreepTumorQueen";NA;252;0
"Building";"CreepTumor";NA;252;0
"Building";"CreepTumor";NA;252;0
"Building";"CreepTumor";NA;252;0
"Building";"CreepTumor";NA;252;0
"Unit";"Overlord";"Larva";252;0
"Unit";"Corruptor";"Larva";252;2
"Unit";"Roach";"Larva";254;2
"Unit";"Roach";"Larva";256;2
"Unit";"Roach";"Larva";258;2
"Unit";"Roach";"Larva";260;2
"Unit";"Roach";"Larva";262;2
"Unit";"Roach";"Larva";264;2
"Unit";"Roach";"Larva";266;2
"Unit";"Roach";"Larva";268;2
"Unit";"Roach";"Larva";270;2
"Unit";"Hydralisk";"Larva";272;2
"Unit";"Hydralisk";"Larva";274;2
"Unit";"Hydralisk";"Larva";276;2
"Unit";"Hydralisk";"Larva";278;2
"Unit";"Hydralisk";"Larva";280;2
"Unit";"Hydralisk";"Larva";282;2
"Unit";"Hydralisk";"Larva";284;2
"Unit";"Hydralisk";"Larva";286;2
"Unit";"Hydralisk";"Larva";288;2
"Unit";"Hydralisk";"Larva";290;2
"Unit";"Hydralisk";"Larva";292;2
"Unit";"Hydralisk";"Larva";294;2
"Unit";"Hydralisk";"Larva";296;2
"Unit";"Hydralisk";"Larva";298;2
"Building";"CreepTumorQueen";NA;300;0
"Building";"CreepTumorQueen";NA;300;0
"Unit";"Hydralisk";"Larva";300;2
"Unit";"Hydralisk";"Larva";302;2
"Unit";"Hydralisk";"Larva";304;2
"Unit";"Hydralisk";"Larva";306;2
"Unit";"Hydralisk";"Larva";308;2
"Building";"CreepTumor";NA;310;0
"Building";"CreepTumor";NA;310;0
"Building";"CreepTumor";NA;310;0
"Building";"CreepTumor";NA;310;0
"Building";"CreepTumor";NA;310;0
"Building";"CreepTumor";NA;310;0
"Building";"CreepTumor";NA;310;0
"Building";"CreepTumor";NA;310;0
"Building";"CreepTumor";NA;310;0
"Building";"CreepTumor";NA;310;0
"Building";"CreepTumor";NA;310;0
"Building";"CreepTumor";NA;310;0
"Building";"CreepTumor";NA;310;0
"Building";"CreepTumor";NA;310;0
"Building";"CreepTumor";NA;310;0
"Building";"CreepTumor";NA;310;0
"Building";"CreepTumorQueen";NA;310;0
"Building";"CreepTumorQueen";NA;310;0
"Unit";"Hydralisk";"Larva";310;2
"Unit";"Hydralisk";"Larva";312;2
"Building";"CreepTumorQueen";NA;314;0
"Building";"CreepTumorQueen";NA;314;0
"Building";"CreepTumorQueen";NA;314;0
"Building";"CreepTumorQueen";NA;314;0
"Building";"CreepTumorQueen";NA;314;0
"Upgrade";"SprayZerg";NA;314;0
"Upgrade";"SprayZerg";NA;314;0
"Upgrade";"SprayZerg";NA;314;0
"Upgrade";"zerglingmovementspeed";NA;314;0
"Upgrade";"SprayZerg";NA;314;0
"Upgrade";"SprayZerg";NA;314;0
"Upgrade";"ZergMissileWeaponsLevel1";NA;314;0
"Upgrade";"SprayZerg";NA;314;0
"Upgrade";"ZergGroundArmorsLevel1";NA;314;0
"Upgrade";"SprayZerg";NA;314;0
"Upgrade";"SprayZerg";NA;314;0
"Upgrade";"SprayZerg";NA;314;0
"Upgrade";"ZergMissileWeaponsLevel2";NA;314;0
"Upgrade";"EvolveMuscularAugments";NA;314;0
"Upgrade";"ZergFlyerArmorsLevel1";NA;314;0
