"type";"unit_name";"on_building";"total_supply";"supply"
"Unit";"Overlord";"Larva";13;0
"Building";"Extractor";NA;19;0
"Building";"SpawningPool";NA;19;0
"Building";"Hatchery";NA;17;0
"Unit";"Overlord";"Larva";22;0
"Unit";"Zergling";"Larva";23;1
"Unit";"Zergling";"Larva";23;1
"Unit";"Zergling";"Larva";23;1
"Unit";"Zergling";"Larva";23;1
"Unit";"Queen";"Hatchery";23;2
"Unit";"Queen";"Hatchery";23;2
"Unit";"Overlord";"Larva";37;0
"Unit";"Queen";"Hatchery";34;2
"Building";"CreepTumorQueen";NA;39;0
"Building";"Hatchery";NA;29;0
"Unit";"Overlord";"Larva";42;0
"Unit";"Overlord";"Larva";50;0
"Unit";"Queen";"Hatchery";50;2
"Unit";"Queen";"Hatchery";50;2
"Unit";"Queen";"Hatchery";50;2
"Building";"CreepTumorQueen";NA;64;0
"Building";"CreepTumor";NA;64;0
"Building";"RoachWarren";NA;50;0
"Unit";"Zergling";"Larva";68;1
"Unit";"Zergling";"Larva";68;1
"Unit";"Zergling";"Larva";68;1
"Unit";"Zergling";"Larva";68;1
"Unit";"Zergling";"Larva";68;1
"Unit";"Zergling";"Larva";68;1
"Unit";"Roach";"Larva";68;2
"Unit";"Roach";"Larva";68;2
"Unit";"Roach";"Larva";68;2
"Unit";"Roach";"Larva";68;2
"Unit";"Overlord";"Larva";68;0
"Unit";"Overlord";"Larva";68;0
"Unit";"Roach";"Larva";74;2
"Building";"CreepTumor";NA;82;0
"Building";"CreepTumor";NA;82;0
"Unit";"Roach";"Larva";82;2
"Unit";"Roach";"Larva";82;2
"Unit";"Roach";"Larva";82;2
"Unit";"Roach";"Larva";82;2
"Unit";"Roach";"Larva";82;2
"Building";"Extractor";NA;84;0
"Building";"Extractor";NA;84;0
"Unit";"Zergling";"Larva";92;1
"Unit";"Zergling";"Larva";92;1
"Unit";"Zergling";"Larva";92;1
"Unit";"Zergling";"Larva";92;1
"Unit";"Zergling";"Larva";92;1
"Unit";"Zergling";"Larva";92;1
"Unit";"Zergling";"Larva";92;1
"Unit";"Zergling";"Larva";92;1
"Unit";"Zergling";"Larva";92;1
"Unit";"Zergling";"Larva";92;1
"Building";"CreepTumor";NA;94;0
"Unit";"Roach";"Larva";92;2
"Unit";"Overlord";"Larva";94;0
"Unit";"Queen";"Hatchery";84;2
"Unit";"Queen";"Hatchery";84;2
"Building";"CreepTumor";NA;123;0
"Building";"Hatchery";NA;82;0
"Building";"Extractor";NA;123;0
"Building";"EvolutionChamber";NA;123;0
"Building";"EvolutionChamber";NA;123;0
"Unit";"Overlord";"Larva";123;0
"Unit";"Overlord";"Larva";123;0
"Unit";"Overlord";"Larva";123;0
"Unit";"Overlord";"Larva";123;0
"Unit";"Roach";"Larva";130;2
"Unit";"Queen";"Hatchery";123;2
"Building";"SpineCrawler";NA;123;0
"Building";"SpineCrawler";NA;123;0
"Unit";"Roach";"Larva";133;2
"Unit";"Roach";"Larva";133;2
"Unit";"Roach";"Larva";133;2
"Unit";"Roach";"Larva";133;2
"Unit";"Roach";"Larva";133;2
"Unit";"Overlord";"Larva";133;0
"Unit";"Overlord";"Larva";133;0
"Building";"CreepTumorQueen";NA;135;0
"Building";"CreepTumor";NA;135;0
"Building";"Extractor";NA;135;0
"Building";"Extractor";NA;135;0
"Building";"CreepTumor";NA;148;0
"Building";"CreepTumorQueen";NA;151;0
"Unit";"Overlord";"Larva";151;0
"Building";"CreepTumor";NA;159;0
"Building";"CreepTumor";NA;161;0
"Building";"CreepTumor";NA;161;0
"Building";"CreepTumor";NA;161;0
"Building";"CreepTumorQueen";NA;161;0
"Unit";"Overlord";"Larva";161;0
"Building";"HydraliskDen";NA;159;0
"Building";"InfestationPit";NA;159;0
"Building";"Hatchery";NA;135;0
"Upgrade";"GlialReconstitution";"RoachWarren";148;0
"Building";"CreepTumorQueen";NA;161;0
"Building";"CreepTumor";NA;171;0
"Building";"CreepTumor";NA;171;0
"Building";"CreepTumor";NA;171;0
"Building";"CreepTumor";NA;171;0
"Upgrade";"ZergMissileWeaponsLevel1";"EvolutionChamber";138;0
"Upgrade";"ZergGroundArmorsLevel1";"EvolutionChamber";138;0
"Building";"Extractor";NA;171;0
"Building";"Extractor";NA;171;0
"Building";"BanelingNest";NA;161;0
"Unit";"Overlord";"Larva";185;0
"Unit";"Overlord";"Larva";185;0
"Unit";"Overlord";"Larva";185;0
"Unit";"Overlord";"Larva";185;0
"Unit";"Overlord";"Larva";185;0
"Building";"SporeCrawler";NA;185;0
"Building";"CreepTumor";NA;190;0
"Building";"CreepTumor";NA;190;0
"Building";"CreepTumor";NA;190;0
"Building";"SporeCrawler";NA;185;0
"Building";"CreepTumor";NA;190;0
"Building";"CreepTumor";NA;192;0
"Building";"CreepTumor";NA;192;0
"Upgrade";"EvolveMuscularAugments";"HydraliskDen";185;0
"Building";"Spire";NA;171;0
"Building";"SpineCrawler";NA;185;0
"Building";"SpineCrawler";NA;185;0
"Building";"SpineCrawler";NA;185;0
"Building";"SpineCrawler";NA;185;0
"Building";"SpineCrawler";NA;185;0
"Building";"CreepTumorQueen";NA;192;0
"Building";"CreepTumorQueen";NA;192;0
"Building";"CreepTumorQueen";NA;192;0
"Unit";"Hydralisk";"Larva";192;2
"Unit";"Hydralisk";"Larva";192;2
"Unit";"Hydralisk";"Larva";192;2
"Unit";"Hydralisk";"Larva";192;2
"Unit";"Hydralisk";"Larva";192;2
"Unit";"Hydralisk";"Larva";192;2
"Unit";"Baneling";"Zergling";192;0
"Unit";"Baneling";"Zergling";192;0
"Unit";"Baneling";"Zergling";192;0
"Unit";"Baneling";"Zergling";192;0
"Unit";"Baneling";"Zergling";192;0
"Unit";"Baneling";"Zergling";192;0
"Building";"Extractor";NA;194;0
"Building";"Extractor";NA;204;0
"Unit";"Hydralisk";"Larva";194;2
"Building";"CreepTumor";NA;206;0
"Building";"CreepTumor";NA;206;0
"Building";"CreepTumor";NA;206;0
"Upgrade";"ZergMissileWeaponsLevel2";"EvolutionChamber";190;0
"Upgrade";"ZergGroundArmorsLevel2";"EvolutionChamber";190;0
"Building";"CreepTumor";NA;206;0
"Building";"CreepTumor";NA;206;0
"Building";"CreepTumor";NA;206;0
"Building";"CreepTumor";NA;206;0
"Unit";"Overlord";"Larva";206;0
"Unit";"Overlord";"Larva";206;0
"Unit";"Overlord";"Larva";206;0
"Upgrade";"EvolveGroovedSpines";"HydraliskDen";206;0
"Unit";"Hydralisk";"Larva";206;2
"Unit";"Hydralisk";"Larva";206;2
"Unit";"Hydralisk";"Larva";206;2
"Unit";"Hydralisk";"Larva";206;2
"Unit";"Hydralisk";"Larva";206;2
"Unit";"Hydralisk";"Larva";206;2
"Unit";"Hydralisk";"Larva";206;2
"Unit";"Hydralisk";"Larva";206;2
"Unit";"Hydralisk";"Larva";206;2
"Unit";"Hydralisk";"Larva";206;2
"Unit";"Hydralisk";"Larva";206;2
"Unit";"Hydralisk";"Larva";206;2
"Unit";"Hydralisk";"Larva";206;2
"Unit";"Hydralisk";"Larva";222;2
"Unit";"Hydralisk";"Larva";232;2
"Unit";"Hydralisk";"Larva";232;2
"Unit";"Hydralisk";"Larva";232;2
"Unit";"Hydralisk";"Larva";232;2
"Unit";"Hydralisk";"Larva";232;2
"Building";"Hatchery";NA;206;0
"Unit";"Hydralisk";"Larva";244;2
"Unit";"Hydralisk";"Larva";244;2
"Unit";"Hydralisk";"Larva";244;2
"Unit";"Hydralisk";"Larva";244;2
"Unit";"Hydralisk";"Larva";244;2
"Unit";"Hydralisk";"Larva";244;2
"Unit";"Hydralisk";"Larva";244;2
"Unit";"Hydralisk";"Larva";244;2
"Unit";"Hydralisk";"Larva";244;2
"Unit";"Hydralisk";"Larva";244;2
"Unit";"Hydralisk";"Larva";244;2
"Unit";"Hydralisk";"Larva";244;2
"Unit";"Hydralisk";"Larva";244;2
"Unit";"Hydralisk";"Larva";244;2
"Unit";"Hydralisk";"Larva";244;2
"Unit";"Hydralisk";"Larva";244;2
"Unit";"Hydralisk";"Larva";244;2
"Unit";"Hydralisk";"Larva";244;2
"Unit";"Hydralisk";"Larva";244;2
"Unit";"Hydralisk";"Larva";244;2
"Unit";"Hydralisk";"Larva";244;2
"Unit";"Hydralisk";"Larva";244;2
"Unit";"Hydralisk";"Larva";244;2
"Unit";"Hydralisk";"Larva";244;2
"Unit";"Hydralisk";"Larva";244;2
"Unit";"Hydralisk";"Larva";244;2
"Unit";"Overlord";"Larva";244;0
"Unit";"Overlord";"Larva";244;0
"Unit";"Overlord";"Larva";244;0
