"type";"unit_name";"on_building";"total_supply";"supply"
"Unit";"Overlord";"Larva";13;0
"Building";"Extractor";NA;17;0
"Unit";"Overlord";"Larva";21;0
"Building";"SpawningPool";NA;19;0
"Building";"Hatchery";NA;17;0
"Unit";"Zergling";"Larva";23;1
"Unit";"Zergling";"Larva";23;1
"Unit";"Zergling";"Larva";23;1
"Unit";"Zergling";"Larva";23;1
"Unit";"Zergling";"Larva";23;1
"Unit";"Zergling";"Larva";23;1
"Unit";"Queen";"Hatchery";22;2
"Unit";"Queen";"Hatchery";22;2
"Unit";"Queen";"Hatchery";36;2
"Building";"CreepTumorQueen";NA;40;0
"Unit";"Overlord";"Larva";40;0
"Building";"CreepTumorQueen";NA;42;0
"Unit";"Overlord";"Larva";42;0
"Building";"CreepTumor";NA;50;0
"Building";"CreepTumorQueen";NA;50;0
"Unit";"Overlord";"Larva";48;0
"Unit";"Overlord";"Larva";50;0
"Building";"Hatchery";NA;36;0
"Building";"Extractor";NA;53;0
"Building";"CreepTumor";NA;53;0
"Building";"CreepTumor";NA;53;0
"Unit";"Zergling";"Larva";53;1
"Unit";"Zergling";"Larva";53;1
"Unit";"Zergling";"Larva";53;1
"Unit";"Zergling";"Larva";53;1
"Unit";"Zergling";"Larva";53;1
"Unit";"Zergling";"Larva";53;1
"Building";"RoachWarren";NA;53;0
"Unit";"Queen";"Hatchery";53;2
"Unit";"Roach";"Larva";63;2
"Unit";"Roach";"Larva";63;2
"Unit";"Roach";"Larva";63;2
"Unit";"Roach";"Larva";63;2
"Unit";"Roach";"Larva";63;2
"Unit";"Zergling";"Larva";63;1
"Unit";"Zergling";"Larva";63;1
"Unit";"Zergling";"Larva";63;1
"Unit";"Zergling";"Larva";63;1
"Unit";"Zergling";"Larva";63;1
"Unit";"Zergling";"Larva";63;1
"Unit";"Zergling";"Larva";63;1
"Unit";"Zergling";"Larva";63;1
"Unit";"Zergling";"Larva";65;1
"Unit";"Zergling";"Larva";65;1
"Unit";"Zergling";"Larva";65;1
"Unit";"Zergling";"Larva";65;1
"Unit";"Overlord";"Larva";65;0
"Unit";"Roach";"Larva";75;2
"Unit";"Roach";"Larva";75;2
"Unit";"Zergling";"Larva";83;1
"Unit";"Zergling";"Larva";83;1
"Unit";"Zergling";"Larva";83;1
"Unit";"Zergling";"Larva";83;1
"Unit";"Zergling";"Larva";83;1
"Unit";"Zergling";"Larva";83;1
"Unit";"Zergling";"Larva";83;1
"Unit";"Zergling";"Larva";83;1
"Unit";"Zergling";"Larva";83;1
"Unit";"Zergling";"Larva";83;1
"Unit";"Zergling";"Larva";83;1
"Unit";"Zergling";"Larva";83;1
"Unit";"Zergling";"Larva";83;1
"Unit";"Zergling";"Larva";83;1
"Unit";"Zergling";"Larva";87;1
"Unit";"Zergling";"Larva";87;1
"Unit";"Zergling";"Larva";87;1
"Unit";"Zergling";"Larva";87;1
"Unit";"Zergling";"Larva";91;1
"Unit";"Zergling";"Larva";91;1
"Unit";"Zergling";"Larva";105;1
"Unit";"Zergling";"Larva";105;1
"Unit";"Zergling";"Larva";105;1
"Unit";"Zergling";"Larva";105;1
"Unit";"Zergling";"Larva";105;1
"Unit";"Zergling";"Larva";105;1
"Unit";"Zergling";"Larva";105;1
"Unit";"Zergling";"Larva";105;1
"Building";"CreepTumor";NA;124;0
"Building";"Extractor";NA;121;0
"Unit";"Queen";"Hatchery";111;2
"Unit";"Queen";"Hatchery";111;2
"Building";"EvolutionChamber";NA;121;0
"Building";"EvolutionChamber";NA;121;0
"Unit";"Overlord";"Larva";124;0
"Building";"CreepTumor";NA;133;0
"Building";"CreepTumor";NA;133;0
"Building";"CreepTumorQueen";NA;136;0
"Building";"CreepTumorQueen";NA;136;0
"Building";"BanelingNest";NA;127;0
"Unit";"Queen";"Hatchery";133;2
"Building";"Extractor";NA;141;0
"Building";"Extractor";NA;141;0
"Unit";"Zergling";"Larva";141;1
"Unit";"Zergling";"Larva";141;1
"Unit";"Zergling";"Larva";141;1
"Unit";"Zergling";"Larva";141;1
"Unit";"Zergling";"Larva";141;1
"Unit";"Zergling";"Larva";141;1
"Unit";"Zergling";"Larva";141;1
"Unit";"Zergling";"Larva";141;1
"Unit";"Zergling";"Larva";141;1
"Unit";"Zergling";"Larva";141;1
"Building";"Extractor";NA;141;0
"Building";"CreepTumor";NA;146;0
"Building";"HydraliskDen";NA;141;0
"Building";"CreepTumor";NA;146;0
"Building";"CreepTumorQueen";NA;156;0
"Building";"CreepTumorQueen";NA;156;0
"Building";"CreepTumorQueen";NA;156;0
"Building";"CreepTumor";NA;170;0
"Building";"CreepTumor";NA;170;0
"Unit";"Overlord";"Larva";170;0
"Unit";"Overlord";"Larva";170;0
"Unit";"Overlord";"Larva";170;0
"Building";"CreepTumor";NA;170;0
"Unit";"Overlord";"Larva";170;0
"Building";"CreepTumor";NA;171;0
"Building";"CreepTumor";NA;171;0
"Building";"Hatchery";NA;141;0
"Unit";"Overlord";"Larva";171;0
"Building";"CreepTumor";NA;171;0
"Building";"CreepTumorQueen";NA;171;0
"Building";"CreepTumorQueen";NA;171;0
"Building";"CreepTumorQueen";NA;171;0
"Building";"CreepTumor";NA;171;0
"Building";"CreepTumor";NA;171;0
"Building";"Spire";NA;146;0
"Building";"CreepTumor";NA;171;0
"Unit";"Overlord";"Larva";171;0
"Unit";"Overlord";"Larva";171;0
"Unit";"Overlord";"Larva";171;0
"Building";"CreepTumor";NA;171;0
"Building";"CreepTumor";NA;171;0
"Building";"CreepTumorQueen";NA;183;0
"Upgrade";"ZergMeleeWeaponsLevel1";"EvolutionChamber";144;0
"Building";"CreepTumorQueen";NA;183;0
"Building";"Extractor";NA;171;0
"Building";"Extractor";NA;179;0
"Upgrade";"EvolveGroovedSpines";"HydraliskDen";171;0
"Unit";"Overlord";"Larva";183;0
"Unit";"Overlord";"Larva";183;0
"Building";"CreepTumorQueen";NA;183;0
"Building";"CreepTumor";NA;183;0
"Building";"CreepTumor";NA;183;0
"Unit";"Mutalisk";"Larva";183;2
"Unit";"Mutalisk";"Larva";183;2
"Unit";"Mutalisk";"Larva";183;2
"Unit";"Mutalisk";"Larva";183;2
"Unit";"Mutalisk";"Larva";183;2
"Unit";"Mutalisk";"Larva";183;2
"Unit";"Mutalisk";"Larva";183;2
"Building";"CreepTumor";NA;183;0
"Unit";"Mutalisk";"Larva";183;2
"Unit";"Mutalisk";"Larva";183;2
"Unit";"Mutalisk";"Larva";183;2
"Unit";"Hydralisk";"Larva";209;2
"Unit";"Hydralisk";"Larva";209;2
"Unit";"Hydralisk";"Larva";209;2
"Building";"CreepTumor";NA;215;0
"Building";"CreepTumor";NA;215;0
"Building";"CreepTumor";NA;215;0
"Building";"CreepTumorQueen";NA;215;0
"Building";"CreepTumor";NA;215;0
"Upgrade";"ZergGroundArmorsLevel1";"EvolutionChamber";171;0
"Unit";"Zergling";"Larva";215;1
"Unit";"Zergling";"Larva";215;1
"Building";"CreepTumor";NA;215;0
"Unit";"Zergling";"Larva";215;1
"Unit";"Zergling";"Larva";215;1
"Unit";"Zergling";"Larva";215;1
"Unit";"Zergling";"Larva";215;1
"Unit";"Zergling";"Larva";215;1
"Unit";"Zergling";"Larva";215;1
"Unit";"Zergling";"Larva";215;1
"Unit";"Zergling";"Larva";215;1
"Unit";"Zergling";"Larva";215;1
"Unit";"Zergling";"Larva";215;1
"Unit";"Zergling";"Larva";215;1
"Unit";"Zergling";"Larva";215;1
"Unit";"Zergling";"Larva";215;1
"Unit";"Zergling";"Larva";215;1
"Unit";"Zergling";"Larva";215;1
"Unit";"Zergling";"Larva";215;1
"Building";"CreepTumor";NA;215;0
"Unit";"Zergling";"Larva";215;1
"Unit";"Zergling";"Larva";215;1
"Unit";"Zergling";"Larva";215;1
"Unit";"Zergling";"Larva";215;1
"Unit";"Zergling";"Larva";215;1
"Unit";"Zergling";"Larva";215;1
"Unit";"Zergling";"Larva";215;1
"Unit";"Zergling";"Larva";215;1
"Unit";"Zergling";"Larva";215;1
"Unit";"Zergling";"Larva";215;1
"Building";"CreepTumor";NA;221;0
"Building";"CreepTumor";NA;221;0
"Building";"CreepTumor";NA;221;0
"Building";"CreepTumorQueen";NA;221;0
"Building";"CreepTumorQueen";NA;221;0
"Building";"InfestationPit";NA;211;0
"Building";"CreepTumorQueen";NA;249;0
"Upgrade";"EvolveMuscularAugments";"HydraliskDen";207;0
"Unit";"Hydralisk";"Larva";221;2
"Unit";"Hydralisk";"Larva";221;2
"Unit";"Hydralisk";"Larva";221;2
"Unit";"Hydralisk";"Larva";221;2
"Unit";"Hydralisk";"Larva";221;2
"Unit";"Baneling";"Zergling";249;0
"Unit";"Baneling";"Zergling";249;0
"Unit";"Baneling";"Zergling";249;0
"Unit";"Baneling";"Zergling";249;0
"Unit";"Baneling";"Zergling";249;0
"Unit";"Baneling";"Zergling";249;0
"Unit";"Baneling";"Zergling";249;0
"Unit";"Baneling";"Zergling";249;0
"Unit";"Baneling";"Zergling";249;0
"Unit";"Mutalisk";"Larva";249;2
"Unit";"Mutalisk";"Larva";249;2
"Unit";"Baneling";"Zergling";249;0
"Unit";"Hydralisk";"Larva";249;2
"Unit";"Hydralisk";"Larva";249;2
"Unit";"Hydralisk";"Larva";249;2
"Unit";"Hydralisk";"Larva";249;2
"Unit";"Hydralisk";"Larva";249;2
"Unit";"Hydralisk";"Larva";249;2
"Building";"Hatchery";NA;209;0
"Building";"CreepTumor";NA;275;0
"Unit";"Mutalisk";"Larva";275;2
"Building";"CreepTumorQueen";NA;279;0
"Unit";"Zergling";"Larva";283;1
"Unit";"Zergling";"Larva";283;1
"Unit";"Zergling";"Larva";283;1
"Unit";"Zergling";"Larva";283;1
"Unit";"Zergling";"Larva";283;1
"Unit";"Zergling";"Larva";283;1
"Unit";"Zergling";"Larva";283;1
"Unit";"Zergling";"Larva";283;1
"Unit";"Zergling";"Larva";283;1
"Unit";"Zergling";"Larva";283;1
"Unit";"Zergling";"Larva";283;1
"Unit";"Zergling";"Larva";283;1
"Building";"CreepTumor";NA;297;0
"Building";"CreepTumorQueen";NA;297;0
"Unit";"Overlord";"Larva";285;0
"Unit";"Overlord";"Larva";285;0
"Unit";"Zergling";"Larva";295;1
"Unit";"Zergling";"Larva";295;1
"Building";"CreepTumorQueen";NA;297;0
"Unit";"Overlord";"Larva";285;0
"Unit";"Zergling";"Larva";297;1
"Unit";"Zergling";"Larva";297;1
"Unit";"Zergling";"Larva";297;1
"Unit";"Zergling";"Larva";297;1
"Building";"CreepTumorQueen";NA;297;0
"Upgrade";"ZergMeleeWeaponsLevel2";"EvolutionChamber";221;0
"Unit";"Overlord";"Larva";297;0
"Unit";"Overlord";"Larva";297;0
"Building";"CreepTumor";NA;303;0
"Building";"CreepTumor";NA;303;0
"Building";"CreepTumor";NA;303;0
"Building";"CreepTumor";NA;303;0
"Building";"EvolutionChamber";NA;303;0
"Building";"Extractor";NA;303;0
"Building";"Extractor";NA;303;0
"Building";"CreepTumorQueen";NA;303;0
"Unit";"Baneling";"Zergling";303;0
"Building";"CreepTumorQueen";NA;303;0
"Unit";"Baneling";"Zergling";303;0
"Unit";"Baneling";"Zergling";303;0
"Unit";"Baneling";"Zergling";303;0
"Unit";"Baneling";"Zergling";303;0
"Unit";"Baneling";"Zergling";303;0
"Unit";"Baneling";"Zergling";303;0
"Unit";"Baneling";"Zergling";303;0
"Unit";"Baneling";"Zergling";303;0
"Unit";"Baneling";"Zergling";303;0
"Unit";"Baneling";"Zergling";303;0
"Unit";"Baneling";"Zergling";303;0
"Unit";"Baneling";"Zergling";303;0
"Unit";"Baneling";"Zergling";303;0
"Building";"CreepTumor";NA;303;0
"Building";"CreepTumor";NA;303;0
"Building";"CreepTumor";NA;303;0
"Building";"Spire";NA;303;0
"Building";"CreepTumor";NA;303;0
"Building";"CreepTumorQueen";NA;303;0
"Building";"CreepTumor";NA;308;0
"Building";"CreepTumorQueen";NA;308;0
"Building";"CreepTumor";NA;308;0
"Building";"CreepTumor";NA;308;0
"Building";"CreepTumor";NA;308;0
"Building";"CreepTumor";NA;310;0
"Building";"CreepTumorQueen";NA;311;0
"Building";"CreepTumorQueen";NA;311;0
"Building";"Extractor";NA;311;0
"Building";"Hatchery";NA;303;0
"Building";"CreepTumorQueen";NA;311;0
"Building";"CreepTumorQueen";NA;311;0
"Building";"CreepTumorQueen";NA;311;0
"Building";"CreepTumor";NA;311;0
"Building";"CreepTumor";NA;311;0
"Building";"CreepTumorQueen";NA;311;0
"Building";"CreepTumorQueen";NA;311;0
"Building";"CreepTumor";NA;311;0
"Building";"CreepTumor";NA;311;0
"Building";"CreepTumor";NA;311;0
"Building";"CreepTumor";NA;311;0
"Building";"CreepTumor";NA;311;0
"Upgrade";"ZergGroundArmorsLevel2";"EvolutionChamber";303;0
"Building";"CreepTumor";NA;311;0
"Building";"CreepTumor";NA;311;0
"Building";"CreepTumor";NA;311;0
"Building";"CreepTumorQueen";NA;311;0
"Unit";"Corruptor";"Larva";311;2
"Unit";"Corruptor";"Larva";311;2
"Unit";"Corruptor";"Larva";311;2
"Building";"CreepTumor";NA;317;0
"Building";"CreepTumor";NA;317;0
"Building";"CreepTumor";NA;317;0
"Building";"CreepTumor";NA;317;0
"Building";"CreepTumor";NA;317;0
"Building";"CreepTumor";NA;317;0
"Unit";"Corruptor";"Larva";317;2
"Unit";"Corruptor";"Larva";317;2
"Unit";"Corruptor";"Larva";317;2
"Unit";"Corruptor";"Larva";317;2
"Building";"CreepTumor";NA;317;0
"Building";"CreepTumor";NA;317;0
"Building";"CreepTumorQueen";NA;317;0
"Building";"CreepTumorQueen";NA;326;0
"Building";"SporeCrawler";NA;317;0
"Building";"SporeCrawler";NA;317;0
"Building";"SporeCrawler";NA;317;0
"Building";"SporeCrawler";NA;317;0
"Building";"SporeCrawler";NA;317;0
"Building";"SporeCrawler";NA;327;0
"Building";"SporeCrawler";NA;327;0
"Building";"SpineCrawler";NA;317;0
"Building";"SpineCrawler";NA;317;0
"Building";"SpineCrawler";NA;317;0
"Building";"SpineCrawler";NA;317;0
"Building";"SpineCrawler";NA;327;0
"Building";"SpineCrawler";NA;327;0
"Building";"CreepTumorQueen";NA;327;0
"Unit";"Corruptor";"Larva";327;2
"Unit";"Corruptor";"Larva";327;2
"Unit";"Corruptor";"Larva";327;2
"Unit";"Corruptor";"Larva";327;2
"Unit";"Corruptor";"Larva";327;2
"Unit";"Corruptor";"Larva";327;2
"Unit";"Corruptor";"Larva";327;2
"Unit";"Corruptor";"Larva";327;2
"Unit";"Corruptor";"Larva";327;2
"Unit";"Corruptor";"Larva";327;2
"Unit";"Corruptor";"Larva";327;2
"Unit";"Corruptor";"Larva";327;2
"Unit";"Corruptor";"Larva";327;2
"Unit";"Corruptor";"Larva";327;2
"Unit";"Corruptor";"Larva";327;2
"Building";"SporeCrawler";NA;327;0
"Building";"SporeCrawler";NA;327;0
"Building";"SporeCrawler";NA;327;0
"Building";"SpineCrawler";NA;327;0
"Building";"SpineCrawler";NA;327;0
"Unit";"Infestor";"Larva";342;2
"Building";"SporeCrawler";NA;379;0
"Building";"SpineCrawler";NA;379;0
"Building";"SpineCrawler";NA;379;0
"Building";"SpineCrawler";NA;379;0
"Building";"SpineCrawler";NA;379;0
"Building";"SpineCrawler";NA;379;0
"Building";"SpineCrawler";NA;379;0
"Building";"SpineCrawler";NA;379;0
"Building";"Extractor";NA;381;0
"Building";"Hatchery";NA;379;0
"Building";"CreepTumorQueen";NA;381;0
"Building";"SporeCrawler";NA;381;0
"Building";"CreepTumorQueen";NA;381;0
"Building";"SporeCrawler";NA;381;0
"Building";"CreepTumorQueen";NA;381;0
"Building";"SporeCrawler";NA;381;0
"Building";"SporeCrawler";NA;381;0
"Building";"SporeCrawler";NA;381;0
"Building";"SporeCrawler";NA;381;0
"Building";"CreepTumorQueen";NA;381;0
"Unit";"Infestor";"Larva";381;2
"Unit";"Infestor";"Larva";381;2
"Unit";"Infestor";"Larva";381;2
"Unit";"Infestor";"Larva";381;2
"Building";"SpineCrawler";NA;381;0
"Building";"SpineCrawler";NA;381;0
"Building";"SpineCrawler";NA;381;0
"Building";"SpineCrawler";NA;381;0
"Building";"SpineCrawler";NA;381;0
"Building";"SpineCrawler";NA;381;0
"Upgrade";"NeuralParasite";"InfestationPit";381;0
"Building";"Hatchery";NA;381;0
"Building";"UltraliskCavern";NA;381;0
"Upgrade";"Burrow";"Hatchery";389;0
"Upgrade";"ChitinousPlating";"UltraliskCavern";389;0
"Upgrade";"ZergMeleeWeaponsLevel3";"EvolutionChamber";389;0
"Upgrade";"ZergGroundArmorsLevel3";"EvolutionChamber";389;0
"Unit";"Ultralisk";"Larva";389;6
"Unit";"Ultralisk";"Larva";389;6
"Unit";"Ultralisk";"Larva";389;6
"Unit";"Ultralisk";"Larva";389;6
"Unit";"Ultralisk";"Larva";389;6
"Unit";"Ultralisk";"Larva";389;6
"Building";"CreepTumor";NA;389;0
"Unit";"Ultralisk";"Larva";389;6
"Building";"CreepTumor";NA;395;0
"Building";"SpineCrawler";NA;389;0
"Building";"SpineCrawler";NA;389;0
"Building";"SpineCrawler";NA;389;0
"Building";"Extractor";NA;425;0
"Building";"SpineCrawler";NA;389;0
"Building";"SpineCrawler";NA;389;0
"Building";"Extractor";NA;425;0
"Building";"SpineCrawler";NA;389;0
"Unit";"Queen";"Hatchery";389;2
"Unit";"Queen";"Hatchery";389;2
"Unit";"Queen";"Hatchery";389;2
"Unit";"Corruptor";"Larva";431;2
"Unit";"Corruptor";"Larva";431;2
"Unit";"Corruptor";"Larva";431;2
"Unit";"Zergling";"Larva";443;1
"Unit";"Zergling";"Larva";443;1
"Unit";"Zergling";"Larva";443;1
"Unit";"Zergling";"Larva";443;1
"Unit";"Zergling";"Larva";443;1
"Unit";"Zergling";"Larva";443;1
"Unit";"Zergling";"Larva";443;1
"Unit";"Zergling";"Larva";443;1
"Unit";"Corruptor";"Larva";443;2
"Unit";"Corruptor";"Larva";443;2
"Unit";"Corruptor";"Larva";443;2
"Unit";"Corruptor";"Larva";443;2
"Unit";"Corruptor";"Larva";443;2
"Unit";"Corruptor";"Larva";443;2
"Unit";"Corruptor";"Larva";443;2
"Unit";"Corruptor";"Larva";443;2
"Building";"CreepTumor";NA;451;0
"Building";"SpineCrawler";NA;451;0
"Unit";"Corruptor";"Larva";467;2
"Unit";"Corruptor";"Larva";467;2
"Unit";"Corruptor";"Larva";467;2
"Unit";"Corruptor";"Larva";467;2
"Unit";"Corruptor";"Larva";467;2
"Unit";"Corruptor";"Larva";467;2
"Unit";"Corruptor";"Larva";467;2
"Unit";"Corruptor";"Larva";467;2
"Unit";"Corruptor";"Larva";467;2
"Unit";"Corruptor";"Larva";467;2
"Unit";"Corruptor";"Larva";467;2
"Unit";"Corruptor";"Larva";467;2
"Unit";"Zergling";"Larva";491;1
"Unit";"Zergling";"Larva";491;1
"Unit";"Zergling";"Larva";491;1
"Unit";"Zergling";"Larva";491;1
"Unit";"Zergling";"Larva";491;1
"Unit";"Zergling";"Larva";491;1
"Unit";"Zergling";"Larva";491;1
"Unit";"Zergling";"Larva";491;1
"Unit";"Zergling";"Larva";491;1
"Unit";"Zergling";"Larva";491;1
"Unit";"Zergling";"Larva";491;1
"Unit";"Zergling";"Larva";491;1
"Unit";"Zergling";"Larva";491;1
"Unit";"Zergling";"Larva";491;1
"Building";"SporeCrawler";NA;505;0
"Building";"SporeCrawler";NA;505;0
"Building";"SporeCrawler";NA;505;0
"Building";"SporeCrawler";NA;505;0
"Building";"SporeCrawler";NA;505;0
"Building";"SpineCrawler";NA;505;0
"Building";"SpineCrawler";NA;505;0
"Building";"SpineCrawler";NA;505;0
"Building";"SpineCrawler";NA;505;0
