"type";"unit_name";"on_building";"total_supply";"supply"
"Unit";"Overlord";"Larva";13;0
"Building";"Extractor";NA;18;0
"Unit";"Overlord";"Larva";22;0
"Building";"SpawningPool";NA;19;0
"Building";"Hatchery";NA;17;0
"Unit";"Zergling";"Larva";22;1
"Unit";"Zergling";"Larva";22;1
"Unit";"Zergling";"Larva";22;1
"Unit";"Zergling";"Larva";22;1
"Unit";"Queen";"Hatchery";22;2
"Building";"Hatchery";NA;22;0
"Unit";"Overlord";"Larva";34;0
"Unit";"Queen";"Hatchery";34;2
"Unit";"Overlord";"Larva";36;0
"Building";"CreepTumorQueen";NA;36;0
"Unit";"Zergling";"Larva";36;1
"Unit";"Zergling";"Larva";36;1
"Unit";"Zergling";"Larva";36;1
"Unit";"Zergling";"Larva";36;1
"Unit";"Zergling";"Larva";36;1
"Unit";"Zergling";"Larva";36;1
"Unit";"Queen";"Hatchery";36;2
"Unit";"Zergling";"Larva";44;1
"Unit";"Zergling";"Larva";44;1
"Unit";"Zergling";"Larva";44;1
"Unit";"Zergling";"Larva";44;1
"Unit";"Queen";"Hatchery";36;2
"Building";"CreepTumor";NA;50;0
"Building";"CreepTumorQueen";NA;54;0
"Building";"BanelingNest";NA;44;0
"Unit";"Overlord";"Larva";56;0
"Unit";"Overlord";"Larva";56;0
"Building";"CreepTumorQueen";NA;72;0
"Building";"CreepTumor";NA;72;0
"Building";"CreepTumor";NA;72;0
"Building";"Extractor";NA;62;0
"Building";"Extractor";NA;62;0
"Unit";"Baneling";"Zergling";72;0
"Unit";"Queen";"Hatchery";62;2
"Unit";"Queen";"Hatchery";62;2
"Unit";"Baneling";"Zergling";72;0
"Unit";"Baneling";"Zergling";72;0
"Unit";"Baneling";"Zergling";72;0
"Unit";"Baneling";"Zergling";72;0
"Building";"CreepTumorQueen";NA;75;0
"Building";"Extractor";NA;72;0
"Building";"CreepTumorQueen";NA;80;0
"Unit";"Overlord";"Larva";80;0
"Unit";"Overlord";"Larva";80;0
"Unit";"Overlord";"Larva";80;0
"Unit";"Overlord";"Larva";81;0
"Unit";"Overlord";"Larva";81;0
"Building";"CreepTumor";NA;81;0
"Building";"CreepTumor";NA;81;0
"Building";"EvolutionChamber";NA;80;0
"Building";"CreepTumor";NA;81;0
"Building";"EvolutionChamber";NA;80;0
"Building";"CreepTumor";NA;88;0
"Building";"CreepTumor";NA;90;0
"Building";"CreepTumor";NA;93;0
"Unit";"Baneling";"Zergling";100;0
"Unit";"Baneling";"Zergling";100;0
"Unit";"Baneling";"Zergling";100;0
"Unit";"Baneling";"Zergling";100;0
"Unit";"Baneling";"Zergling";100;0
"Unit";"Queen";"Hatchery";96;2
"Unit";"Zergling";"Larva";100;1
"Unit";"Zergling";"Larva";100;1
"Unit";"Zergling";"Larva";100;1
"Unit";"Zergling";"Larva";100;1
"Unit";"Zergling";"Larva";100;1
"Unit";"Zergling";"Larva";100;1
"Unit";"Zergling";"Larva";100;1
"Unit";"Zergling";"Larva";100;1
"Unit";"Zergling";"Larva";100;1
"Unit";"Zergling";"Larva";100;1
"Unit";"Zergling";"Larva";100;1
"Unit";"Zergling";"Larva";100;1
"Unit";"Zergling";"Larva";100;1
"Unit";"Zergling";"Larva";100;1
"Unit";"Zergling";"Larva";100;1
"Unit";"Zergling";"Larva";100;1
"Unit";"Zergling";"Larva";104;1
"Unit";"Zergling";"Larva";104;1
"Unit";"Zergling";"Larva";104;1
"Unit";"Zergling";"Larva";104;1
"Unit";"Zergling";"Larva";104;1
"Unit";"Zergling";"Larva";104;1
"Unit";"Zergling";"Larva";104;1
"Unit";"Zergling";"Larva";104;1
"Unit";"Zergling";"Larva";112;1
"Unit";"Zergling";"Larva";112;1
"Unit";"Zergling";"Larva";118;1
"Unit";"Zergling";"Larva";118;1
"Unit";"Zergling";"Larva";118;1
"Unit";"Zergling";"Larva";118;1
"Unit";"Zergling";"Larva";118;1
"Unit";"Zergling";"Larva";118;1
"Unit";"Zergling";"Larva";118;1
"Unit";"Zergling";"Larva";118;1
"Unit";"Zergling";"Larva";118;1
"Unit";"Zergling";"Larva";118;1
"Unit";"Zergling";"Larva";118;1
"Unit";"Zergling";"Larva";118;1
"Unit";"Zergling";"Larva";118;1
"Unit";"Zergling";"Larva";118;1
"Building";"SporeCrawler";NA;118;0
"Building";"SporeCrawler";NA;144;0
"Unit";"Queen";"Hatchery";118;2
"Building";"HydraliskDen";NA;144;0
"Unit";"Queen";"Hatchery";144;2
"Upgrade";"ZergMeleeWeaponsLevel1";"EvolutionChamber";100;0
"Upgrade";"ZergGroundArmorsLevel1";"EvolutionChamber";100;0
"Building";"Extractor";NA;154;0
"Building";"Extractor";NA;154;0
"Building";"SporeCrawler";NA;161;0
"Building";"SporeCrawler";NA;161;0
"Building";"CreepTumor";NA;173;0
"Unit";"Hydralisk";"Larva";173;2
"Unit";"Hydralisk";"Larva";173;2
"Unit";"Hydralisk";"Larva";173;2
"Unit";"Hydralisk";"Larva";173;2
"Unit";"Hydralisk";"Larva";173;2
"Unit";"Queen";"Hatchery";168;2
"Unit";"Queen";"Hatchery";168;2
"Unit";"Queen";"Hatchery";168;2
"Unit";"Overlord";"Larva";189;0
"Unit";"Overlord";"Larva";189;0
"Unit";"Overlord";"Larva";189;0
"Unit";"Queen";"Hatchery";183;2
"Upgrade";"EvolveGroovedSpines";"HydraliskDen";173;0
"Building";"CreepTumor";NA;189;0
"Building";"Hatchery";NA;168;0
"Building";"CreepTumor";NA;195;0
"Building";"CreepTumor";NA;195;0
"Building";"InfestationPit";NA;189;0
"Building";"CreepTumor";NA;195;0
"Unit";"Hydralisk";"Larva";190;2
"Unit";"Hydralisk";"Larva";190;2
"Unit";"Hydralisk";"Larva";190;2
"Unit";"Hydralisk";"Larva";191;2
"Unit";"Hydralisk";"Larva";191;2
"Unit";"Hydralisk";"Larva";192;2
"Unit";"Hydralisk";"Larva";193;2
"Unit";"Hydralisk";"Larva";193;2
"Unit";"Hydralisk";"Larva";193;2
"Unit";"Hydralisk";"Larva";193;2
"Building";"CreepTumorQueen";NA;222;0
"Building";"Hatchery";NA;189;0
"Unit";"Hydralisk";"Larva";225;2
"Unit";"Hydralisk";"Larva";225;2
"Upgrade";"ZergMissileWeaponsLevel1";"EvolutionChamber";189;0
"Unit";"Overlord";"Larva";225;0
"Unit";"Overlord";"Larva";225;0
"Unit";"Overlord";"Larva";225;0
"Building";"Extractor";NA;225;0
"Unit";"Overlord";"Larva";225;0
"Unit";"Overlord";"Larva";225;0
"Unit";"Overlord";"Larva";225;0
"Building";"Extractor";NA;225;0
"Building";"CreepTumor";NA;237;0
"Upgrade";"ZergGroundArmorsLevel2";"EvolutionChamber";189;0
"Building";"Extractor";NA;237;0
"Building";"Extractor";NA;237;0
"Building";"SporeCrawler";NA;237;0
"Building";"SporeCrawler";NA;243;0
"Building";"SporeCrawler";NA;243;0
"Building";"SporeCrawler";NA;243;0
"Upgrade";"EvolveMuscularAugments";"HydraliskDen";237;0
"Unit";"Zergling";"Larva";261;1
"Unit";"Zergling";"Larva";261;1
"Unit";"Zergling";"Larva";263;1
"Unit";"Zergling";"Larva";263;1
"Unit";"Zergling";"Larva";263;1
"Unit";"Zergling";"Larva";263;1
"Unit";"Zergling";"Larva";263;1
"Unit";"Zergling";"Larva";263;1
"Unit";"Zergling";"Larva";263;1
"Unit";"Zergling";"Larva";263;1
"Unit";"Zergling";"Larva";263;1
"Unit";"Zergling";"Larva";263;1
"Unit";"Zergling";"Larva";263;1
"Unit";"Zergling";"Larva";263;1
"Unit";"Zergling";"Larva";263;1
"Unit";"Zergling";"Larva";263;1
"Unit";"Zergling";"Larva";263;1
"Unit";"Zergling";"Larva";263;1
"Unit";"Zergling";"Larva";263;1
"Unit";"Zergling";"Larva";263;1
"Unit";"Hydralisk";"Larva";263;2
"Unit";"Hydralisk";"Larva";263;2
"Unit";"Hydralisk";"Larva";263;2
"Unit";"Hydralisk";"Larva";263;2
"Unit";"Zergling";"Larva";283;1
"Unit";"Zergling";"Larva";283;1
"Unit";"Zergling";"Larva";283;1
"Unit";"Zergling";"Larva";283;1
"Unit";"Zergling";"Larva";283;1
"Unit";"Zergling";"Larva";283;1
"Unit";"Zergling";"Larva";283;1
"Unit";"Zergling";"Larva";283;1
"Unit";"Zergling";"Larva";283;1
"Unit";"Zergling";"Larva";283;1
"Unit";"Zergling";"Larva";283;1
"Unit";"Zergling";"Larva";283;1
"Unit";"Zergling";"Larva";283;1
"Unit";"Zergling";"Larva";283;1
"Unit";"Zergling";"Larva";283;1
"Unit";"Zergling";"Larva";283;1
"Unit";"Zergling";"Larva";283;1
"Unit";"Zergling";"Larva";283;1
"Unit";"Zergling";"Larva";283;1
"Unit";"Zergling";"Larva";283;1
"Building";"CreepTumorQueen";NA;299;0
"Building";"CreepTumorQueen";NA;301;0
"Building";"CreepTumorQueen";NA;311;0
"Unit";"Zergling";"Larva";299;1
"Unit";"Zergling";"Larva";299;1
"Unit";"Zergling";"Larva";301;1
"Unit";"Zergling";"Larva";301;1
"Unit";"Zergling";"Larva";301;1
"Unit";"Zergling";"Larva";301;1
"Unit";"Zergling";"Larva";301;1
"Unit";"Zergling";"Larva";301;1
"Unit";"Zergling";"Larva";301;1
"Unit";"Zergling";"Larva";301;1
"Unit";"Baneling";"Zergling";314;0
"Unit";"Baneling";"Zergling";314;0
"Unit";"Baneling";"Zergling";314;0
"Unit";"Baneling";"Zergling";314;0
"Unit";"Baneling";"Zergling";314;0
"Unit";"Baneling";"Zergling";314;0
"Unit";"Baneling";"Zergling";314;0
"Unit";"Baneling";"Zergling";314;0
"Unit";"Baneling";"Zergling";314;0
"Unit";"Baneling";"Zergling";314;0
"Unit";"Baneling";"Zergling";314;0
"Unit";"Baneling";"Zergling";314;0
"Unit";"Baneling";"Zergling";314;0
"Unit";"Baneling";"Zergling";314;0
"Unit";"Baneling";"Zergling";314;0
"Unit";"Baneling";"Zergling";314;0
"Unit";"Baneling";"Zergling";314;0
"Unit";"Baneling";"Zergling";314;0
"Unit";"Baneling";"Zergling";314;0
"Unit";"Baneling";"Zergling";314;0
"Unit";"Baneling";"Zergling";314;0
"Unit";"Baneling";"Zergling";314;0
"Unit";"Baneling";"Zergling";314;0
"Unit";"Baneling";"Zergling";314;0
"Unit";"Baneling";"Zergling";314;0
"Unit";"Baneling";"Zergling";314;0
"Unit";"Baneling";"Zergling";314;0
"Unit";"Baneling";"Zergling";314;0
"Unit";"Baneling";"Zergling";314;0
"Building";"CreepTumor";NA;314;0
"Building";"CreepTumor";NA;314;0
"Building";"CreepTumor";NA;314;0
"Building";"CreepTumorQueen";NA;324;0
"Building";"CreepTumorQueen";NA;324;0
"Building";"UltraliskCavern";NA;289;0
"Unit";"Zergling";"Larva";324;1
"Unit";"Zergling";"Larva";324;1
"Unit";"Zergling";"Larva";324;1
"Unit";"Zergling";"Larva";324;1
"Unit";"Zergling";"Larva";324;1
"Unit";"Zergling";"Larva";324;1
"Unit";"Zergling";"Larva";324;1
"Unit";"Zergling";"Larva";324;1
"Unit";"Zergling";"Larva";324;1
"Unit";"Zergling";"Larva";324;1
"Unit";"Zergling";"Larva";324;1
"Unit";"Zergling";"Larva";324;1
"Unit";"Zergling";"Larva";324;1
"Unit";"Zergling";"Larva";324;1
"Unit";"Zergling";"Larva";324;1
"Unit";"Zergling";"Larva";324;1
"Unit";"Zergling";"Larva";324;1
"Unit";"Zergling";"Larva";324;1
"Unit";"Zergling";"Larva";324;1
"Unit";"Zergling";"Larva";324;1
"Unit";"Zergling";"Larva";324;1
"Unit";"Zergling";"Larva";324;1
"Unit";"Zergling";"Larva";324;1
"Unit";"Zergling";"Larva";324;1
"Unit";"Zergling";"Larva";324;1
"Unit";"Zergling";"Larva";324;1
"Unit";"Zergling";"Larva";324;1
"Unit";"Zergling";"Larva";324;1
"Unit";"Zergling";"Larva";324;1
"Unit";"Zergling";"Larva";324;1
"Unit";"Zergling";"Larva";324;1
"Unit";"Zergling";"Larva";324;1
"Unit";"Zergling";"Larva";324;1
"Unit";"Zergling";"Larva";324;1
"Unit";"Zergling";"Larva";324;1
"Unit";"Zergling";"Larva";324;1
"Building";"SpineCrawler";NA;324;0
"Upgrade";"ZergMeleeWeaponsLevel2";"EvolutionChamber";263;0
"Unit";"Overlord";"Larva";324;0
"Unit";"Overlord";"Larva";324;0
"Unit";"Overlord";"Larva";324;0
"Unit";"Overlord";"Larva";324;0
"Unit";"Baneling";"Zergling";360;0
"Building";"CreepTumor";NA;360;0
"Unit";"Baneling";"Zergling";360;0
"Unit";"Baneling";"Zergling";360;0
"Unit";"Baneling";"Zergling";360;0
"Unit";"Baneling";"Zergling";360;0
"Unit";"Baneling";"Zergling";360;0
"Unit";"Baneling";"Zergling";360;0
"Unit";"Ultralisk";"Larva";324;6
"Unit";"Zergling";"Larva";360;1
"Unit";"Zergling";"Larva";360;1
"Unit";"Zergling";"Larva";360;1
"Unit";"Zergling";"Larva";360;1
"Unit";"Zergling";"Larva";360;1
"Unit";"Zergling";"Larva";360;1
"Unit";"Zergling";"Larva";360;1
"Unit";"Zergling";"Larva";360;1
"Unit";"Zergling";"Larva";360;1
"Unit";"Zergling";"Larva";360;1
"Unit";"Zergling";"Larva";360;1
"Unit";"Zergling";"Larva";360;1
"Unit";"Zergling";"Larva";360;1
"Unit";"Zergling";"Larva";360;1
"Unit";"Zergling";"Larva";360;1
"Unit";"Zergling";"Larva";360;1
"Unit";"Zergling";"Larva";360;1
"Unit";"Zergling";"Larva";360;1
"Unit";"Zergling";"Larva";360;1
"Unit";"Zergling";"Larva";360;1
"Unit";"Zergling";"Larva";360;1
"Unit";"Zergling";"Larva";360;1
"Unit";"Zergling";"Larva";360;1
"Unit";"Zergling";"Larva";360;1
"Building";"Hatchery";NA;324;0
"Building";"CreepTumor";NA;390;0
"Building";"CreepTumor";NA;390;0
"Building";"CreepTumor";NA;390;0
"Building";"CreepTumorQueen";NA;390;0
"Building";"CreepTumorQueen";NA;390;0
"Unit";"Ultralisk";"Larva";360;6
"Unit";"Ultralisk";"Larva";360;6
"Unit";"Ultralisk";"Larva";360;6
"Upgrade";"ChitinousPlating";"UltraliskCavern";360;0
"Unit";"Ultralisk";"Larva";366;6
"Unit";"Ultralisk";"Larva";366;6
"Building";"Extractor";NA;390;0
"Unit";"Overlord";"Larva";390;0
"Unit";"Overlord";"Larva";390;0
"Unit";"Overlord";"Larva";390;0
"Building";"Extractor";NA;390;0
"Building";"CreepTumorQueen";NA;402;0
"Unit";"Overlord";"Larva";390;0
"Unit";"Overlord";"Larva";390;0
"Building";"CreepTumorQueen";NA;402;0
"Unit";"Overlord";"Larva";390;0
"Upgrade";"ZergGroundArmorsLevel3";"EvolutionChamber";324;0
"Unit";"Ultralisk";"Larva";390;6
"Building";"CreepTumor";NA;420;0
"Unit";"Zergling";"Larva";420;1
"Unit";"Zergling";"Larva";420;1
"Building";"CreepTumor";NA;420;0
"Unit";"Zergling";"Larva";420;1
"Unit";"Zergling";"Larva";420;1
"Unit";"Zergling";"Larva";420;1
"Unit";"Zergling";"Larva";420;1
"Unit";"Zergling";"Larva";420;1
"Unit";"Zergling";"Larva";420;1
"Unit";"Zergling";"Larva";420;1
"Unit";"Zergling";"Larva";420;1
"Unit";"Zergling";"Larva";420;1
"Unit";"Zergling";"Larva";420;1
"Unit";"Zergling";"Larva";420;1
"Unit";"Zergling";"Larva";420;1
"Unit";"Zergling";"Larva";420;1
"Unit";"Zergling";"Larva";420;1
"Building";"CreepTumor";NA;420;0
"Building";"CreepTumor";NA;420;0
"Building";"Spire";NA;390;0
"Unit";"Zergling";"Larva";442;1
"Unit";"Zergling";"Larva";442;1
"Unit";"Zergling";"Larva";442;1
"Unit";"Zergling";"Larva";442;1
"Unit";"Ultralisk";"Larva";442;6
"Unit";"Ultralisk";"Larva";442;6
"Unit";"Ultralisk";"Larva";442;6
"Upgrade";"ZergMeleeWeaponsLevel3";"EvolutionChamber";420;0
"Unit";"Corruptor";"Larva";464;2
"Unit";"Corruptor";"Larva";464;2
"Unit";"Corruptor";"Larva";464;2
"Unit";"Corruptor";"Larva";464;2
"Unit";"Corruptor";"Larva";464;2
"Unit";"Corruptor";"Larva";464;2
"Unit";"Corruptor";"Larva";464;2
"Unit";"Corruptor";"Larva";464;2
"Unit";"Corruptor";"Larva";464;2
"Unit";"Corruptor";"Larva";464;2
"Unit";"Corruptor";"Larva";464;2
"Unit";"Corruptor";"Larva";464;2
"Unit";"Corruptor";"Larva";464;2
"Building";"Hatchery";NA;446;0
"Building";"Hatchery";NA;464;0
"Building";"Hatchery";NA;490;0
"Unit";"Zergling";"Larva";490;1
"Unit";"Zergling";"Larva";490;1
"Unit";"Zergling";"Larva";490;1
"Unit";"Zergling";"Larva";490;1
"Unit";"Zergling";"Larva";490;1
"Unit";"Zergling";"Larva";490;1
"Unit";"Zergling";"Larva";490;1
"Unit";"Zergling";"Larva";490;1
"Unit";"Zergling";"Larva";490;1
"Unit";"Zergling";"Larva";490;1
"Unit";"Zergling";"Larva";490;1
"Unit";"Zergling";"Larva";490;1
"Unit";"Zergling";"Larva";490;1
"Unit";"Zergling";"Larva";490;1
"Unit";"Zergling";"Larva";490;1
"Unit";"Zergling";"Larva";490;1
"Unit";"Zergling";"Larva";490;1
"Unit";"Zergling";"Larva";490;1
"Unit";"Zergling";"Larva";490;1
"Unit";"Zergling";"Larva";490;1
"Unit";"Zergling";"Larva";490;1
"Unit";"Zergling";"Larva";490;1
"Unit";"Zergling";"Larva";490;1
"Unit";"Zergling";"Larva";490;1
"Unit";"Zergling";"Larva";490;1
"Unit";"Zergling";"Larva";490;1
"Unit";"Zergling";"Larva";490;1
"Unit";"Zergling";"Larva";490;1
"Unit";"Zergling";"Larva";490;1
"Unit";"Zergling";"Larva";490;1
"Unit";"Zergling";"Larva";490;1
"Unit";"Zergling";"Larva";490;1
"Building";"Hatchery";NA;490;0
"Building";"Hatchery";NA;490;0
"Building";"SporeCrawler";NA;522;0
"Building";"Extractor";NA;522;0
"Building";"SporeCrawler";NA;522;0
"Building";"SporeCrawler";NA;522;0
"Building";"SporeCrawler";NA;522;0
"Building";"SporeCrawler";NA;522;0
"Building";"Extractor";NA;522;0
"Building";"SporeCrawler";NA;522;0
"Building";"SporeCrawler";NA;522;0
"Building";"SporeCrawler";NA;522;0
"Building";"SporeCrawler";NA;522;0
