"type";"unit_name";"on_building";"total_supply";"supply"
"Unit";"Overlord";"Larva";12;0
"Building";"Extractor";NA;18;0
"Unit";"Overlord";"Larva";21;0
"Building";"SpawningPool";NA;18;0
"Building";"Hatchery";NA;17;0
"Unit";"Zergling";"Larva";23;1
"Unit";"Zergling";"Larva";23;1
"Unit";"Zergling";"Larva";24;1
"Unit";"Zergling";"Larva";24;1
"Unit";"Queen";"Hatchery";22;2
"Unit";"Queen";"Hatchery";22;2
"Unit";"Overlord";"Larva";35;0
"Unit";"Overlord";"Larva";35;0
"Unit";"Overlord";"Larva";37;0
"Building";"CreepTumorQueen";NA;39;0
"Unit";"Queen";"Hatchery";35;2
"Building";"CreepTumor";NA;48;0
"Unit";"Overlord";"Larva";48;0
"Unit";"Overlord";"Larva";48;0
"Building";"CreepTumorQueen";NA;53;0
"Building";"Extractor";NA;54;0
"Unit";"Queen";"Hatchery";48;2
"Unit";"Zergling";"Larva";54;1
"Unit";"Zergling";"Larva";54;1
"Unit";"Zergling";"Larva";54;1
"Unit";"Zergling";"Larva";54;1
"Unit";"Zergling";"Larva";54;1
"Unit";"Zergling";"Larva";54;1
"Unit";"Zergling";"Larva";54;1
"Unit";"Zergling";"Larva";54;1
"Unit";"Zergling";"Larva";54;1
"Unit";"Zergling";"Larva";54;1
"Unit";"Zergling";"Larva";56;1
"Unit";"Zergling";"Larva";56;1
"Unit";"Zergling";"Larva";56;1
"Unit";"Zergling";"Larva";56;1
"Unit";"Overlord";"Larva";56;0
"Building";"CreepTumor";NA;58;0
"Building";"BanelingNest";NA;54;0
"Building";"Hatchery";NA;48;0
"Unit";"Queen";"Hatchery";54;2
"Building";"EvolutionChamber";NA;72;0
"Building";"CreepTumorQueen";NA;78;0
"Building";"EvolutionChamber";NA;72;0
"Building";"SporeCrawler";NA;78;0
"Unit";"Overlord";"Larva";86;0
"Building";"SporeCrawler";NA;78;0
"Building";"SporeCrawler";NA;78;0
"Unit";"Queen";"Hatchery";76;2
"Unit";"Zergling";"Larva";88;1
"Unit";"Zergling";"Larva";88;1
"Unit";"Zergling";"Larva";88;1
"Unit";"Zergling";"Larva";88;1
"Unit";"Zergling";"Larva";88;1
"Unit";"Zergling";"Larva";88;1
"Unit";"Zergling";"Larva";88;1
"Unit";"Zergling";"Larva";88;1
"Unit";"Zergling";"Larva";88;1
"Unit";"Zergling";"Larva";88;1
"Unit";"Zergling";"Larva";88;1
"Unit";"Zergling";"Larva";88;1
"Building";"CreepTumor";NA;88;0
"Building";"CreepTumor";NA;90;0
"Building";"CreepTumorQueen";NA;90;0
"Building";"CreepTumorQueen";NA;93;0
"Unit";"Zergling";"Larva";90;1
"Unit";"Zergling";"Larva";90;1
"Unit";"Zergling";"Larva";90;1
"Unit";"Zergling";"Larva";90;1
"Unit";"Zergling";"Larva";90;1
"Unit";"Zergling";"Larva";90;1
"Unit";"Zergling";"Larva";90;1
"Unit";"Zergling";"Larva";90;1
"Unit";"Zergling";"Larva";90;1
"Unit";"Zergling";"Larva";90;1
"Unit";"Overlord";"Larva";118;0
"Unit";"Overlord";"Larva";118;0
"Unit";"Overlord";"Larva";118;0
"Unit";"Overlord";"Larva";120;0
"Unit";"Overlord";"Larva";120;0
"Unit";"Overlord";"Larva";120;0
"Building";"CreepTumor";NA;121;0
"Building";"CreepTumorQueen";NA;121;0
"Building";"CreepTumor";NA;121;0
"Building";"CreepTumor";NA;121;0
"Unit";"Zergling";"Larva";122;1
"Unit";"Zergling";"Larva";122;1
"Unit";"Zergling";"Larva";122;1
"Unit";"Zergling";"Larva";122;1
"Unit";"Zergling";"Larva";122;1
"Unit";"Zergling";"Larva";122;1
"Unit";"Zergling";"Larva";122;1
"Unit";"Zergling";"Larva";122;1
"Unit";"Zergling";"Larva";122;1
"Unit";"Zergling";"Larva";122;1
"Unit";"Zergling";"Larva";122;1
"Unit";"Zergling";"Larva";122;1
"Unit";"Zergling";"Larva";122;1
"Unit";"Zergling";"Larva";122;1
"Unit";"Zergling";"Larva";122;1
"Unit";"Zergling";"Larva";122;1
"Unit";"Zergling";"Larva";122;1
"Unit";"Zergling";"Larva";122;1
"Unit";"Zergling";"Larva";122;1
"Unit";"Zergling";"Larva";122;1
"Unit";"Zergling";"Larva";122;1
"Unit";"Zergling";"Larva";122;1
"Unit";"Zergling";"Larva";122;1
"Unit";"Zergling";"Larva";122;1
"Unit";"Zergling";"Larva";122;1
"Unit";"Zergling";"Larva";122;1
"Building";"Hatchery";NA;103;0
"Building";"Extractor";NA;122;0
"Building";"Extractor";NA;122;0
"Building";"HydraliskDen";NA;122;0
"Upgrade";"ZergMeleeWeaponsLevel1";"EvolutionChamber";113;0
"Building";"CreepTumor";NA;149;0
"Upgrade";"ZergGroundArmorsLevel1";"EvolutionChamber";113;0
"Building";"CreepTumor";NA;149;0
"Building";"Extractor";NA;149;0
"Building";"Extractor";NA;149;0
"Building";"CreepTumor";NA;159;0
"Building";"CreepTumor";NA;159;0
"Building";"CreepTumor";NA;159;0
"Unit";"Overlord";"Larva";159;0
"Unit";"Overlord";"Larva";159;0
"Building";"CreepTumorQueen";NA;159;0
"Building";"CreepTumor";NA;159;0
"Building";"CreepTumor";NA;159;0
"Unit";"Overlord";"Larva";159;0
"Unit";"Overlord";"Larva";159;0
"Unit";"Overlord";"Larva";159;0
"Building";"Hatchery";NA;122;0
"Building";"CreepTumor";NA;172;0
"Building";"CreepTumor";NA;172;0
"Unit";"Queen";"Hatchery";159;2
"Unit";"Overlord";"Larva";172;0
"Unit";"Overlord";"Larva";172;0
"Unit";"Overlord";"Larva";172;0
"Upgrade";"EvolveGroovedSpines";"HydraliskDen";159;0
"Unit";"Hydralisk";"Larva";177;2
"Unit";"Hydralisk";"Larva";177;2
"Unit";"Hydralisk";"Larva";177;2
"Unit";"Hydralisk";"Larva";177;2
"Unit";"Hydralisk";"Larva";177;2
"Unit";"Hydralisk";"Larva";177;2
"Unit";"Hydralisk";"Larva";177;2
"Unit";"Hydralisk";"Larva";177;2
"Unit";"Hydralisk";"Larva";177;2
"Unit";"Hydralisk";"Larva";177;2
"Unit";"Hydralisk";"Larva";177;2
"Unit";"Hydralisk";"Larva";177;2
"Unit";"Hydralisk";"Larva";177;2
"Unit";"Hydralisk";"Larva";177;2
"Unit";"Hydralisk";"Larva";177;2
"Unit";"Overlord";"Larva";177;0
"Building";"Extractor";NA;177;0
"Building";"CreepTumor";NA;207;0
"Building";"Extractor";NA;177;0
"Building";"CreepTumor";NA;207;0
"Building";"CreepTumor";NA;211;0
"Unit";"Zergling";"Larva";177;1
"Unit";"Zergling";"Larva";177;1
"Unit";"Zergling";"Larva";191;1
"Unit";"Zergling";"Larva";191;1
"Unit";"Zergling";"Larva";195;1
"Unit";"Zergling";"Larva";195;1
"Unit";"Zergling";"Larva";199;1
"Unit";"Zergling";"Larva";199;1
"Unit";"Zergling";"Larva";199;1
"Unit";"Zergling";"Larva";199;1
"Unit";"Zergling";"Larva";203;1
"Unit";"Zergling";"Larva";203;1
"Unit";"Zergling";"Larva";203;1
"Unit";"Zergling";"Larva";203;1
"Building";"InfestationPit";NA;177;0
"Unit";"Queen";"Hatchery";177;2
"Building";"CreepTumor";NA;225;0
"Unit";"Zergling";"Larva";225;1
"Unit";"Zergling";"Larva";225;1
"Unit";"Zergling";"Larva";225;1
"Unit";"Zergling";"Larva";225;1
"Unit";"Zergling";"Larva";225;1
"Unit";"Zergling";"Larva";225;1
"Unit";"Zergling";"Larva";225;1
"Unit";"Zergling";"Larva";225;1
"Unit";"Zergling";"Larva";225;1
"Unit";"Zergling";"Larva";225;1
"Unit";"Zergling";"Larva";225;1
"Unit";"Zergling";"Larva";225;1
"Unit";"Zergling";"Larva";225;1
"Unit";"Zergling";"Larva";225;1
"Unit";"Zergling";"Larva";225;1
"Unit";"Zergling";"Larva";225;1
"Unit";"Zergling";"Larva";225;1
"Unit";"Zergling";"Larva";225;1
"Unit";"Zergling";"Larva";225;1
"Unit";"Zergling";"Larva";225;1
"Unit";"Zergling";"Larva";225;1
"Unit";"Zergling";"Larva";225;1
"Unit";"Zergling";"Larva";225;1
"Unit";"Zergling";"Larva";225;1
"Unit";"Zergling";"Larva";225;1
"Unit";"Zergling";"Larva";225;1
"Building";"CreepTumor";NA;225;0
"Building";"CreepTumor";NA;225;0
"Building";"CreepTumor";NA;227;0
"Building";"CreepTumor";NA;227;0
"Unit";"Baneling";"Zergling";227;0
"Unit";"Baneling";"Zergling";227;0
"Unit";"Baneling";"Zergling";227;0
"Unit";"Baneling";"Zergling";227;0
"Unit";"Baneling";"Zergling";227;0
"Unit";"Baneling";"Zergling";227;0
"Unit";"Baneling";"Zergling";227;0
"Unit";"Baneling";"Zergling";227;0
"Unit";"Baneling";"Zergling";227;0
"Unit";"Baneling";"Zergling";227;0
"Unit";"Baneling";"Zergling";227;0
"Unit";"Baneling";"Zergling";227;0
"Unit";"Baneling";"Zergling";227;0
"Unit";"Zergling";"Larva";227;1
"Unit";"Zergling";"Larva";227;1
"Unit";"Zergling";"Larva";227;1
"Unit";"Zergling";"Larva";227;1
"Unit";"Zergling";"Larva";227;1
"Unit";"Zergling";"Larva";227;1
"Unit";"Zergling";"Larva";227;1
"Unit";"Zergling";"Larva";227;1
"Unit";"Zergling";"Larva";227;1
"Unit";"Zergling";"Larva";227;1
"Unit";"Zergling";"Larva";227;1
"Unit";"Zergling";"Larva";227;1
"Unit";"Zergling";"Larva";227;1
"Unit";"Zergling";"Larva";227;1
"Upgrade";"EvolveMuscularAugments";"HydraliskDen";211;0
"Upgrade";"ZergMeleeWeaponsLevel2";"EvolutionChamber";177;0
"Upgrade";"ZergGroundArmorsLevel2";"EvolutionChamber";177;0
"Building";"CreepTumor";NA;267;0
"Unit";"Queen";"Hatchery";227;2
"Unit";"Zergling";"Larva";275;1
"Unit";"Zergling";"Larva";275;1
"Unit";"Zergling";"Larva";275;1
"Unit";"Zergling";"Larva";275;1
"Unit";"Zergling";"Larva";275;1
"Unit";"Zergling";"Larva";275;1
"Unit";"Zergling";"Larva";275;1
"Unit";"Zergling";"Larva";275;1
"Unit";"Zergling";"Larva";275;1
"Unit";"Zergling";"Larva";275;1
"Unit";"Zergling";"Larva";275;1
"Unit";"Zergling";"Larva";275;1
"Unit";"Zergling";"Larva";275;1
"Unit";"Zergling";"Larva";275;1
"Unit";"Zergling";"Larva";275;1
"Unit";"Zergling";"Larva";275;1
"Unit";"Zergling";"Larva";275;1
"Unit";"Zergling";"Larva";275;1
"Building";"Spire";NA;227;0
"Building";"CreepTumorQueen";NA;301;0
"Building";"CreepTumorQueen";NA;301;0
"Building";"CreepTumorQueen";NA;301;0
"Building";"Hatchery";NA;253;0
"Building";"CreepTumor";NA;301;0
"Building";"CreepTumor";NA;301;0
"Building";"CreepTumor";NA;301;0
"Unit";"Zergling";"Larva";301;1
"Unit";"Zergling";"Larva";301;1
"Unit";"Zergling";"Larva";301;1
"Unit";"Zergling";"Larva";301;1
"Unit";"Zergling";"Larva";301;1
"Unit";"Zergling";"Larva";301;1
"Unit";"Zergling";"Larva";301;1
"Unit";"Zergling";"Larva";301;1
"Unit";"Zergling";"Larva";301;1
"Unit";"Zergling";"Larva";301;1
"Unit";"Zergling";"Larva";301;1
"Unit";"Zergling";"Larva";301;1
"Unit";"Zergling";"Larva";301;1
"Unit";"Zergling";"Larva";301;1
"Unit";"Zergling";"Larva";301;1
"Unit";"Zergling";"Larva";301;1
"Unit";"Zergling";"Larva";301;1
"Unit";"Zergling";"Larva";301;1
"Unit";"Zergling";"Larva";301;1
"Unit";"Zergling";"Larva";301;1
"Unit";"Zergling";"Larva";301;1
"Unit";"Zergling";"Larva";301;1
"Unit";"Zergling";"Larva";301;1
"Unit";"Zergling";"Larva";301;1
"Unit";"Zergling";"Larva";301;1
"Unit";"Zergling";"Larva";301;1
"Unit";"Zergling";"Larva";301;1
"Unit";"Zergling";"Larva";301;1
"Unit";"Zergling";"Larva";301;1
"Unit";"Zergling";"Larva";301;1
"Unit";"Zergling";"Larva";301;1
"Unit";"Zergling";"Larva";301;1
"Unit";"Zergling";"Larva";301;1
"Unit";"Zergling";"Larva";301;1
"Unit";"Zergling";"Larva";301;1
"Unit";"Zergling";"Larva";301;1
"Unit";"Zergling";"Larva";301;1
"Unit";"Zergling";"Larva";301;1
"Unit";"Zergling";"Larva";301;1
"Unit";"Zergling";"Larva";301;1
"Unit";"Zergling";"Larva";301;1
"Unit";"Zergling";"Larva";301;1
"Unit";"Zergling";"Larva";301;1
"Unit";"Zergling";"Larva";301;1
"Unit";"Zergling";"Larva";301;1
"Unit";"Zergling";"Larva";301;1
"Unit";"Zergling";"Larva";301;1
"Unit";"Zergling";"Larva";301;1
"Unit";"Baneling";"Zergling";301;0
"Unit";"Baneling";"Zergling";301;0
"Unit";"Baneling";"Zergling";301;0
"Unit";"Baneling";"Zergling";301;0
"Unit";"Baneling";"Zergling";301;0
"Unit";"Baneling";"Zergling";301;0
"Unit";"Baneling";"Zergling";301;0
"Unit";"Baneling";"Zergling";301;0
"Unit";"Baneling";"Zergling";301;0
"Unit";"Baneling";"Zergling";301;0
"Unit";"Baneling";"Zergling";301;0
"Unit";"Baneling";"Zergling";301;0
"Unit";"Baneling";"Zergling";301;0
"Unit";"Baneling";"Zergling";301;0
"Unit";"Baneling";"Zergling";301;0
"Unit";"Baneling";"Zergling";301;0
"Unit";"Baneling";"Zergling";301;0
"Unit";"Baneling";"Zergling";301;0
"Building";"CreepTumor";NA;349;0
"Building";"CreepTumor";NA;349;0
"Unit";"Zergling";"Larva";301;1
"Unit";"Zergling";"Larva";301;1
"Unit";"Zergling";"Larva";301;1
"Unit";"Zergling";"Larva";301;1
"Unit";"Zergling";"Larva";301;1
"Unit";"Zergling";"Larva";301;1
"Unit";"Zergling";"Larva";301;1
"Unit";"Zergling";"Larva";301;1
"Unit";"Zergling";"Larva";301;1
"Unit";"Zergling";"Larva";301;1
"Unit";"Zergling";"Larva";301;1
"Unit";"Zergling";"Larva";301;1
"Unit";"Zergling";"Larva";301;1
"Unit";"Zergling";"Larva";301;1
"Unit";"Zergling";"Larva";301;1
"Unit";"Zergling";"Larva";301;1
"Unit";"Zergling";"Larva";301;1
"Unit";"Zergling";"Larva";301;1
"Unit";"Zergling";"Larva";301;1
"Unit";"Zergling";"Larva";301;1
"Building";"CreepTumor";NA;349;0
"Building";"CreepTumor";NA;349;0
"Building";"CreepTumor";NA;349;0
"Building";"CreepTumor";NA;349;0
"Building";"SporeCrawler";NA;369;0
"Building";"CreepTumor";NA;369;0
"Upgrade";"ZergMissileWeaponsLevel1";"EvolutionChamber";301;0
"Building";"CreepTumor";NA;369;0
"Building";"CreepTumor";NA;369;0
"Building";"CreepTumor";NA;369;0
"Building";"CreepTumor";NA;369;0
"Building";"SpineCrawler";NA;369;0
"Building";"SpineCrawler";NA;369;0
"Building";"Extractor";NA;369;0
"Building";"Extractor";NA;369;0
"Unit";"Viper";"Larva";369;3
"Unit";"Viper";"Larva";369;3
"Building";"CreepTumor";NA;369;0
"Building";"CreepTumor";NA;369;0
"Building";"CreepTumor";NA;369;0
