"type";"unit_name";"on_building";"total_supply";"supply"
"Building";"Extractor";NA;13;0
"Unit";"Overlord";"Larva";16;0
"Building";"SpawningPool";NA;15;0
"Unit";"Zergling";"Larva";17;1
"Unit";"Zergling";"Larva";17;1
"Unit";"Zergling";"Larva";17;1
"Unit";"Zergling";"Larva";17;1
"Unit";"Zergling";"Larva";18;1
"Unit";"Zergling";"Larva";18;1
"Unit";"Queen";"Hatchery";17;2
"Unit";"Overlord";"Larva";27;0
"Building";"Hatchery";NA;25;0
"Unit";"Queen";"Hatchery";28;2
"Unit";"Queen";"Hatchery";34;2
"Unit";"Overlord";"Larva";38;0
"Unit";"Overlord";"Larva";38;0
"Building";"CreepTumorQueen";NA;44;0
"Unit";"Overlord";"Larva";41;0
"Building";"Extractor";NA;43;0
"Unit";"Zergling";"Larva";44;1
"Unit";"Zergling";"Larva";44;1
"Unit";"Zergling";"Larva";44;1
"Unit";"Zergling";"Larva";44;1
"Building";"BanelingNest";NA;38;0
"Unit";"Queen";"Hatchery";44;2
"Building";"CreepTumor";NA;50;0
"Unit";"Zergling";"Larva";50;1
"Unit";"Zergling";"Larva";50;1
"Building";"EvolutionChamber";NA;45;0
"Unit";"Zergling";"Larva";53;1
"Unit";"Zergling";"Larva";53;1
"Unit";"Zergling";"Larva";53;1
"Unit";"Zergling";"Larva";53;1
"Unit";"Zergling";"Larva";53;1
"Unit";"Zergling";"Larva";53;1
"Building";"Hatchery";NA;36;0
"Unit";"Overlord";"Larva";53;0
"Building";"EvolutionChamber";NA;55;0
"Unit";"Baneling";"Zergling";63;0
"Unit";"Baneling";"Zergling";63;0
"Unit";"Baneling";"Zergling";63;0
"Unit";"Baneling";"Zergling";66;0
"Building";"SporeCrawler";NA;63;0
"Unit";"Zergling";"Larva";67;1
"Unit";"Zergling";"Larva";67;1
"Unit";"Zergling";"Larva";67;1
"Unit";"Zergling";"Larva";67;1
"Unit";"Zergling";"Larva";67;1
"Unit";"Zergling";"Larva";67;1
"Unit";"Queen";"Hatchery";63;2
"Building";"CreepTumor";NA;77;0
"Building";"CreepTumorQueen";NA;77;0
"Building";"Extractor";NA;75;0
"Building";"Extractor";NA;75;0
"Unit";"Overlord";"Larva";77;0
"Unit";"Queen";"Hatchery";75;2
"Unit";"Overlord";"Larva";89;0
"Unit";"Overlord";"Larva";90;0
"Unit";"Overlord";"Larva";93;0
"Building";"CreepTumorQueen";NA;95;0
"Building";"CreepTumor";NA;95;0
"Building";"CreepTumor";NA;95;0
"Unit";"Overlord";"Larva";95;0
"Upgrade";"ZergGroundArmorsLevel1";"EvolutionChamber";75;0
"Building";"CreepTumor";NA;104;0
"Building";"CreepTumor";NA;104;0
"Unit";"Overlord";"Larva";104;0
"Unit";"Baneling";"Zergling";104;0
"Unit";"Baneling";"Zergling";104;0
"Unit";"Zergling";"Larva";104;1
"Unit";"Zergling";"Larva";104;1
"Unit";"Zergling";"Larva";104;1
"Unit";"Zergling";"Larva";104;1
"Building";"Extractor";NA;104;0
"Building";"Extractor";NA;104;0
"Unit";"Zergling";"Larva";104;1
"Unit";"Zergling";"Larva";104;1
"Building";"InfestationPit";NA;104;0
"Unit";"Zergling";"Larva";104;1
"Unit";"Zergling";"Larva";104;1
"Unit";"Zergling";"Larva";108;1
"Unit";"Zergling";"Larva";108;1
"Unit";"Zergling";"Larva";108;1
"Unit";"Zergling";"Larva";108;1
"Unit";"Overlord";"Larva";108;0
"Building";"SporeCrawler";NA;108;0
"Upgrade";"ZergMeleeWeaponsLevel1";"EvolutionChamber";93;0
"Unit";"Zergling";"Larva";112;1
"Unit";"Zergling";"Larva";112;1
"Unit";"Zergling";"Larva";112;1
"Unit";"Zergling";"Larva";112;1
"Building";"CreepTumor";NA;116;0
"Building";"CreepTumor";NA;116;0
"Building";"CreepTumor";NA;120;0
"Building";"Hatchery";NA;104;0
"Unit";"Overlord";"Larva";127;0
"Unit";"Overlord";"Larva";129;0
"Unit";"Overlord";"Larva";129;0
"Unit";"Zergling";"Larva";129;1
"Unit";"Zergling";"Larva";129;1
"Unit";"Zergling";"Larva";129;1
"Unit";"Zergling";"Larva";129;1
"Unit";"Zergling";"Larva";129;1
"Unit";"Zergling";"Larva";129;1
"Building";"CreepTumor";NA;129;0
"Building";"CreepTumor";NA;135;0
"Building";"CreepTumor";NA;138;0
"Unit";"Overlord";"Larva";139;0
"Building";"Extractor";NA;140;0
"Building";"Extractor";NA;140;0
"Building";"HydraliskDen";NA;140;0
"Unit";"Zergling";"Larva";146;1
"Unit";"Zergling";"Larva";146;1
"Unit";"Zergling";"Larva";146;1
"Unit";"Zergling";"Larva";146;1
"Unit";"Zergling";"Larva";146;1
"Unit";"Zergling";"Larva";146;1
"Unit";"Baneling";"Zergling";151;0
"Unit";"Baneling";"Zergling";151;0
"Unit";"Hydralisk";"Larva";148;2
"Unit";"Hydralisk";"Larva";148;2
"Unit";"Baneling";"Zergling";151;0
"Unit";"Hydralisk";"Larva";151;2
"Unit";"Hydralisk";"Larva";151;2
"Unit";"Hydralisk";"Larva";151;2
"Upgrade";"ZergGroundArmorsLevel2";"EvolutionChamber";125;0
"Unit";"Hydralisk";"Larva";157;2
"Unit";"Hydralisk";"Larva";157;2
"Building";"Spire";NA;140;0
"Unit";"Zergling";"Larva";167;1
"Unit";"Zergling";"Larva";167;1
"Building";"SporeCrawler";NA;167;0
"Unit";"Hydralisk";"Larva";165;2
"Unit";"Hydralisk";"Larva";167;2
"Unit";"Hydralisk";"Larva";167;2
"Unit";"Hydralisk";"Larva";167;2
"Unit";"Hydralisk";"Larva";167;2
"Unit";"Hydralisk";"Larva";167;2
"Unit";"Zergling";"Larva";171;1
"Unit";"Zergling";"Larva";171;1
"Unit";"Zergling";"Larva";171;1
"Unit";"Zergling";"Larva";171;1
"Unit";"Zergling";"Larva";171;1
"Unit";"Zergling";"Larva";171;1
"Unit";"Zergling";"Larva";171;1
"Unit";"Zergling";"Larva";171;1
"Unit";"Zergling";"Larva";171;1
"Unit";"Zergling";"Larva";171;1
"Unit";"Zergling";"Larva";171;1
"Unit";"Zergling";"Larva";171;1
"Unit";"Zergling";"Larva";171;1
"Unit";"Zergling";"Larva";171;1
"Upgrade";"EvolveMuscularAugments";"HydraliskDen";157;0
"Unit";"Zergling";"Larva";185;1
"Unit";"Zergling";"Larva";185;1
"Unit";"Zergling";"Larva";185;1
"Unit";"Zergling";"Larva";185;1
"Upgrade";"ZergMeleeWeaponsLevel2";"EvolutionChamber";142;0
"Building";"UltraliskCavern";NA;171;0
"Unit";"Overlord";"Larva";205;0
"Unit";"Overlord";"Larva";205;0
"Unit";"Overlord";"Larva";205;0
"Unit";"Overlord";"Larva";205;0
"Unit";"Overlord";"Larva";205;0
"Unit";"Overlord";"Larva";205;0
"Building";"SporeCrawler";NA;209;0
"Unit";"Corruptor";"Larva";209;2
"Unit";"Corruptor";"Larva";209;2
"Building";"CreepTumor";NA;209;0
"Building";"CreepTumor";NA;209;0
"Unit";"Corruptor";"Larva";209;2
"Building";"SpineCrawler";NA;209;0
"Building";"SpineCrawler";NA;209;0
"Building";"SpineCrawler";NA;209;0
"Unit";"Corruptor";"Larva";209;2
"Unit";"Zergling";"Larva";209;1
"Unit";"Zergling";"Larva";209;1
"Unit";"Zergling";"Larva";209;1
"Unit";"Zergling";"Larva";209;1
"Unit";"Zergling";"Larva";209;1
"Unit";"Zergling";"Larva";209;1
"Unit";"Zergling";"Larva";209;1
"Unit";"Zergling";"Larva";209;1
"Unit";"Baneling";"Zergling";213;0
"Unit";"Baneling";"Zergling";213;0
"Unit";"Baneling";"Zergling";213;0
"Unit";"Baneling";"Zergling";213;0
"Unit";"Baneling";"Zergling";213;0
"Unit";"Baneling";"Zergling";213;0
"Unit";"Baneling";"Zergling";213;0
"Unit";"Baneling";"Zergling";213;0
"Unit";"Baneling";"Zergling";213;0
"Unit";"Infestor";"Larva";209;2
"Unit";"Infestor";"Larva";209;2
"Building";"Hatchery";NA;185;0
"Unit";"Infestor";"Larva";209;2
"Upgrade";"EvolveGroovedSpines";"HydraliskDen";209;0
"Unit";"Queen";"Hatchery";225;2
"Unit";"Corruptor";"Larva";231;2
"Building";"Extractor";NA;238;0
"Building";"SporeCrawler";NA;238;0
"Building";"Extractor";NA;240;0
"Building";"SpineCrawler";NA;238;0
"Building";"SpineCrawler";NA;238;0
"Upgrade";"ZergGroundArmorsLevel3";"EvolutionChamber";209;0
"Unit";"Ultralisk";"Larva";242;6
"Upgrade";"ChitinousPlating";"UltraliskCavern";238;0
"Unit";"Zergling";"Larva";249;1
"Unit";"Zergling";"Larva";249;1
"Unit";"Zergling";"Larva";249;1
"Unit";"Zergling";"Larva";249;1
"Unit";"Zergling";"Larva";249;1
"Unit";"Zergling";"Larva";249;1
"Unit";"Zergling";"Larva";249;1
"Unit";"Zergling";"Larva";249;1
"Unit";"Zergling";"Larva";249;1
"Unit";"Zergling";"Larva";249;1
"Unit";"Zergling";"Larva";249;1
"Unit";"Zergling";"Larva";249;1
"Unit";"Zergling";"Larva";249;1
"Unit";"Zergling";"Larva";249;1
"Unit";"Ultralisk";"Larva";244;6
"Unit";"Ultralisk";"Larva";249;6
"Unit";"Ultralisk";"Larva";249;6
"Unit";"Ultralisk";"Larva";269;6
"Unit";"Ultralisk";"Larva";269;6
"Unit";"Ultralisk";"Larva";269;6
"Unit";"Hydralisk";"Larva";287;2
"Unit";"Hydralisk";"Larva";287;2
"Unit";"Hydralisk";"Larva";287;2
"Unit";"Hydralisk";"Larva";287;2
"Upgrade";"ZergMeleeWeaponsLevel3";"EvolutionChamber";238;0
"Unit";"Zergling";"Larva";305;1
"Unit";"Zergling";"Larva";305;1
"Unit";"Zergling";"Larva";305;1
"Unit";"Zergling";"Larva";305;1
"Unit";"Zergling";"Larva";305;1
"Unit";"Zergling";"Larva";305;1
"Unit";"Zergling";"Larva";305;1
"Unit";"Zergling";"Larva";305;1
"Unit";"Corruptor";"Larva";305;2
"Unit";"Corruptor";"Larva";305;2
"Unit";"Corruptor";"Larva";305;2
"Unit";"Corruptor";"Larva";305;2
"Unit";"Zergling";"Larva";313;1
"Unit";"Zergling";"Larva";313;1
"Unit";"Zergling";"Larva";313;1
"Unit";"Zergling";"Larva";313;1
"Unit";"Zergling";"Larva";313;1
"Unit";"Zergling";"Larva";313;1
"Unit";"Zergling";"Larva";313;1
"Unit";"Zergling";"Larva";313;1
"Unit";"Zergling";"Larva";313;1
"Unit";"Zergling";"Larva";313;1
"Unit";"Zergling";"Larva";313;1
"Unit";"Zergling";"Larva";313;1
"Unit";"Zergling";"Larva";313;1
"Unit";"Zergling";"Larva";313;1
"Unit";"Zergling";"Larva";313;1
"Unit";"Zergling";"Larva";313;1
"Unit";"Ultralisk";"Larva";305;6
"Unit";"Ultralisk";"Larva";305;6
"Unit";"Zergling";"Larva";327;1
"Unit";"Zergling";"Larva";327;1
"Unit";"Zergling";"Larva";327;1
"Unit";"Zergling";"Larva";327;1
"Building";"CreepTumor";NA;357;0
"Building";"CreepTumor";NA;357;0
"Unit";"Queen";"Hatchery";321;2
"Unit";"Baneling";"Zergling";357;0
"Unit";"Baneling";"Zergling";357;0
"Unit";"Baneling";"Zergling";357;0
"Unit";"Baneling";"Zergling";357;0
"Unit";"Baneling";"Zergling";357;0
"Unit";"Baneling";"Zergling";357;0
"Unit";"Baneling";"Zergling";357;0
"Unit";"Baneling";"Zergling";357;0
"Unit";"Queen";"Hatchery";321;2
"Building";"Hatchery";NA;307;0
"Unit";"Infestor";"Larva";361;2
"Unit";"Infestor";"Larva";361;2
"Unit";"Infestor";"Larva";361;2
"Unit";"Infestor";"Larva";361;2
"Building";"CreepTumorQueen";NA;365;0
"Building";"CreepTumor";NA;365;0
"Building";"CreepTumor";NA;365;0
"Building";"Extractor";NA;365;0
"Building";"CreepTumorQueen";NA;365;0
"Building";"Extractor";NA;365;0
"Building";"CreepTumorQueen";NA;365;0
"Building";"Hatchery";NA;361;0
"Unit";"Corruptor";"Larva";373;2
"Unit";"Corruptor";"Larva";373;2
"Unit";"Corruptor";"Larva";373;2
"Building";"CreepTumor";NA;373;0
"Building";"LurkerDenMP";NA;361;0
"Building";"CreepTumor";NA;377;0
"Building";"CreepTumor";NA;379;0
"Building";"CreepTumor";NA;379;0
"Building";"CreepTumor";NA;379;0
"Upgrade";"ZergMissileWeaponsLevel1";"EvolutionChamber";365;0
"Building";"SporeCrawler";NA;373;0
"Unit";"Zergling";"Larva";379;1
"Unit";"Zergling";"Larva";379;1
"Unit";"Zergling";"Larva";379;1
"Unit";"Zergling";"Larva";379;1
"Unit";"Zergling";"Larva";379;1
"Unit";"Zergling";"Larva";379;1
"Unit";"Zergling";"Larva";379;1
"Unit";"Zergling";"Larva";379;1
"Unit";"Zergling";"Larva";379;1
"Unit";"Zergling";"Larva";379;1
"Unit";"Ultralisk";"Larva";379;6
"Unit";"Baneling";"Zergling";389;0
"Unit";"Zergling";"Larva";389;1
"Unit";"Zergling";"Larva";389;1
"Unit";"Zergling";"Larva";389;1
"Unit";"Zergling";"Larva";389;1
"Unit";"Zergling";"Larva";389;1
"Unit";"Zergling";"Larva";389;1
"Unit";"Zergling";"Larva";389;1
"Unit";"Zergling";"Larva";389;1
"Unit";"Zergling";"Larva";389;1
"Unit";"Zergling";"Larva";389;1
"Unit";"Zergling";"Larva";389;1
"Unit";"Zergling";"Larva";389;1
"Unit";"Zergling";"Larva";389;1
"Unit";"Zergling";"Larva";389;1
"Unit";"Zergling";"Larva";389;1
"Unit";"Zergling";"Larva";389;1
"Unit";"Zergling";"Larva";389;1
"Unit";"Zergling";"Larva";389;1
"Unit";"Zergling";"Larva";389;1
"Unit";"Zergling";"Larva";389;1
"Unit";"Corruptor";"Larva";379;2
"Unit";"Corruptor";"Larva";379;2
"Unit";"Corruptor";"Larva";379;2
"Unit";"Corruptor";"Larva";379;2
"Building";"CreepTumor";NA;423;0
"Building";"CreepTumor";NA;423;0
