"type";"unit_name";"on_building";"total_supply";"supply"
"Unit";"Overlord";"Larva";12;0
"Building";"SpawningPool";NA;19;0
"Building";"Hatchery";NA;17;0
"Building";"Extractor";NA;23;0
"Unit";"Zergling";"Larva";24;1
"Unit";"Zergling";"Larva";24;1
"Unit";"Zergling";"Larva";24;1
"Unit";"Zergling";"Larva";24;1
"Unit";"Queen";"Hatchery";23;2
"Unit";"Queen";"Hatchery";24;2
"Unit";"Overlord";"Larva";30;0
"Unit";"Overlord";"Larva";30;0
"Building";"Hatchery";NA;22;0
"Unit";"Overlord";"Larva";34;0
"Unit";"Queen";"Hatchery";34;2
"Unit";"Overlord";"Larva";39;0
"Unit";"Overlord";"Larva";39;0
"Unit";"Queen";"Hatchery";39;2
"Unit";"Queen";"Hatchery";39;2
"Building";"CreepTumorQueen";NA;41;0
"Building";"CreepTumorQueen";NA;41;0
"Building";"CreepTumorQueen";NA;41;0
"Unit";"Overlord";"Larva";41;0
"Building";"CreepTumorQueen";NA;45;0
"Unit";"Zergling";"Larva";45;1
"Unit";"Zergling";"Larva";45;1
"Unit";"Zergling";"Larva";45;1
"Unit";"Zergling";"Larva";45;1
"Unit";"Zergling";"Larva";45;1
"Unit";"Zergling";"Larva";45;1
"Unit";"Zergling";"Larva";45;1
"Unit";"Zergling";"Larva";45;1
"Unit";"Zergling";"Larva";45;1
"Unit";"Zergling";"Larva";45;1
"Unit";"Zergling";"Larva";45;1
"Unit";"Zergling";"Larva";45;1
"Unit";"Zergling";"Larva";45;1
"Unit";"Zergling";"Larva";45;1
"Building";"CreepTumor";NA;45;0
"Building";"CreepTumor";NA;45;0
"Building";"CreepTumor";NA;45;0
"Unit";"Queen";"Hatchery";41;2
"Building";"CreepTumorQueen";NA;45;0
"Building";"CreepTumorQueen";NA;45;0
"Building";"CreepTumorQueen";NA;59;0
"Unit";"Queen";"Hatchery";45;2
"Unit";"Queen";"Hatchery";45;2
"Unit";"Zergling";"Larva";59;1
"Unit";"Zergling";"Larva";59;1
"Unit";"Zergling";"Larva";59;1
"Unit";"Zergling";"Larva";59;1
"Unit";"Zergling";"Larva";59;1
"Unit";"Zergling";"Larva";59;1
"Unit";"Zergling";"Larva";59;1
"Unit";"Zergling";"Larva";59;1
"Unit";"Zergling";"Larva";59;1
"Unit";"Zergling";"Larva";59;1
"Unit";"Zergling";"Larva";59;1
"Unit";"Zergling";"Larva";59;1
"Unit";"Zergling";"Larva";59;1
"Unit";"Zergling";"Larva";59;1
"Unit";"Zergling";"Larva";59;1
"Unit";"Zergling";"Larva";59;1
"Building";"CreepTumorQueen";NA;61;0
"Building";"CreepTumorQueen";NA;61;0
"Building";"CreepTumor";NA;61;0
"Building";"SporeCrawler";NA;61;0
"Building";"SporeCrawler";NA;63;0
"Building";"CreepTumor";NA;81;0
"Building";"CreepTumor";NA;81;0
"Building";"CreepTumor";NA;81;0
"Building";"CreepTumor";NA;81;0
"Building";"CreepTumor";NA;81;0
"Building";"CreepTumor";NA;81;0
"Building";"CreepTumorQueen";NA;81;0
"Building";"CreepTumor";NA;87;0
"Unit";"Queen";"Hatchery";65;2
"Unit";"Overlord";"Larva";87;0
"Unit";"Overlord";"Larva";87;0
"Building";"CreepTumor";NA;87;0
"Building";"CreepTumorQueen";NA;87;0
"Building";"CreepTumor";NA;87;0
"Building";"CreepTumor";NA;87;0
"Building";"CreepTumor";NA;89;0
"Building";"CreepTumor";NA;89;0
"Building";"CreepTumor";NA;89;0
"Building";"CreepTumorQueen";NA;89;0
"Building";"CreepTumor";NA;89;0
"Unit";"Zergling";"Larva";89;1
"Unit";"Zergling";"Larva";89;1
"Unit";"Zergling";"Larva";89;1
"Unit";"Zergling";"Larva";89;1
"Unit";"Zergling";"Larva";89;1
"Unit";"Zergling";"Larva";89;1
"Unit";"Zergling";"Larva";89;1
"Unit";"Zergling";"Larva";89;1
"Unit";"Zergling";"Larva";89;1
"Unit";"Zergling";"Larva";89;1
"Unit";"Zergling";"Larva";89;1
"Unit";"Zergling";"Larva";89;1
"Unit";"Zergling";"Larva";89;1
"Unit";"Zergling";"Larva";89;1
"Unit";"Zergling";"Larva";89;1
"Unit";"Zergling";"Larva";89;1
"Unit";"Zergling";"Larva";89;1
"Unit";"Zergling";"Larva";89;1
"Unit";"Zergling";"Larva";89;1
"Unit";"Zergling";"Larva";89;1
"Unit";"Zergling";"Larva";89;1
"Unit";"Zergling";"Larva";89;1
"Unit";"Zergling";"Larva";89;1
"Unit";"Zergling";"Larva";89;1
"Unit";"Zergling";"Larva";89;1
"Unit";"Zergling";"Larva";89;1
"Unit";"Zergling";"Larva";89;1
"Unit";"Zergling";"Larva";89;1
"Unit";"Zergling";"Larva";89;1
"Unit";"Zergling";"Larva";89;1
"Unit";"Queen";"Hatchery";87;2
"Unit";"Zergling";"Larva";89;1
"Unit";"Zergling";"Larva";89;1
"Unit";"Zergling";"Larva";89;1
"Unit";"Zergling";"Larva";89;1
"Unit";"Zergling";"Larva";89;1
"Unit";"Zergling";"Larva";89;1
"Unit";"Zergling";"Larva";89;1
"Unit";"Zergling";"Larva";89;1
"Unit";"Zergling";"Larva";89;1
"Unit";"Zergling";"Larva";89;1
"Unit";"Zergling";"Larva";89;1
"Unit";"Zergling";"Larva";89;1
"Unit";"Zergling";"Larva";89;1
"Unit";"Zergling";"Larva";89;1
"Unit";"Zergling";"Larva";89;1
"Unit";"Zergling";"Larva";89;1
"Building";"CreepTumorQueen";NA;121;0
"Building";"CreepTumor";NA;121;0
"Building";"CreepTumor";NA;137;0
"Building";"CreepTumor";NA;123;0
"Building";"CreepTumor";NA;137;0
"Unit";"Overlord";"Larva";121;0
"Building";"CreepTumorQueen";NA;137;0
"Building";"CreepTumorQueen";NA;137;0
"Unit";"Overlord";"Larva";137;0
"Building";"CreepTumor";NA;137;0
"Unit";"Overlord";"Larva";137;0
"Unit";"Overlord";"Larva";137;0
"Unit";"Overlord";"Larva";137;0
"Building";"BanelingNest";NA;91;0
"Building";"CreepTumor";NA;137;0
"Unit";"Overlord";"Larva";137;0
"Unit";"Baneling";"Zergling";137;0
"Unit";"Baneling";"Zergling";137;0
"Unit";"Baneling";"Zergling";137;0
"Unit";"Baneling";"Zergling";137;0
"Unit";"Baneling";"Zergling";137;0
"Unit";"Baneling";"Zergling";137;0
"Unit";"Baneling";"Zergling";137;0
"Building";"CreepTumor";NA;143;0
"Building";"Extractor";NA;137;0
"Building";"CreepTumorQueen";NA;143;0
"Unit";"Baneling";"Zergling";147;0
"Unit";"Baneling";"Zergling";147;0
"Building";"CreepTumorQueen";NA;147;0
"Building";"CreepTumorQueen";NA;147;0
"Building";"CreepTumorQueen";NA;147;0
"Building";"CreepTumorQueen";NA;147;0
"Unit";"Zergling";"Larva";147;1
"Unit";"Zergling";"Larva";147;1
"Unit";"Zergling";"Larva";147;1
"Unit";"Zergling";"Larva";147;1
"Unit";"Zergling";"Larva";147;1
"Unit";"Zergling";"Larva";147;1
"Unit";"Zergling";"Larva";147;1
"Unit";"Zergling";"Larva";147;1
"Unit";"Zergling";"Larva";147;1
"Unit";"Zergling";"Larva";147;1
"Unit";"Zergling";"Larva";147;1
"Unit";"Zergling";"Larva";147;1
"Unit";"Zergling";"Larva";147;1
"Unit";"Zergling";"Larva";147;1
"Unit";"Zergling";"Larva";147;1
"Unit";"Zergling";"Larva";147;1
"Unit";"Zergling";"Larva";147;1
"Unit";"Zergling";"Larva";147;1
"Unit";"Zergling";"Larva";147;1
"Unit";"Zergling";"Larva";147;1
"Unit";"Zergling";"Larva";147;1
"Unit";"Zergling";"Larva";147;1
"Building";"CreepTumorQueen";NA;147;0
"Building";"CreepTumorQueen";NA;147;0
"Building";"CreepTumor";NA;147;0
"Building";"CreepTumor";NA;147;0
"Building";"CreepTumor";NA;147;0
"Unit";"Zergling";"Larva";153;1
"Unit";"Zergling";"Larva";153;1
"Unit";"Zergling";"Larva";167;1
"Unit";"Zergling";"Larva";167;1
"Unit";"Zergling";"Larva";167;1
"Unit";"Zergling";"Larva";167;1
"Unit";"Zergling";"Larva";169;1
"Unit";"Zergling";"Larva";169;1
"Unit";"Zergling";"Larva";169;1
"Unit";"Zergling";"Larva";169;1
"Unit";"Zergling";"Larva";169;1
"Unit";"Zergling";"Larva";169;1
"Unit";"Zergling";"Larva";169;1
"Unit";"Zergling";"Larva";169;1
"Building";"EvolutionChamber";NA;147;0
"Building";"EvolutionChamber";NA;147;0
"Unit";"Zergling";"Larva";169;1
"Unit";"Zergling";"Larva";169;1
"Unit";"Zergling";"Larva";169;1
"Unit";"Zergling";"Larva";169;1
"Unit";"Zergling";"Larva";169;1
"Unit";"Zergling";"Larva";169;1
"Unit";"Zergling";"Larva";169;1
"Unit";"Zergling";"Larva";169;1
"Unit";"Zergling";"Larva";169;1
"Unit";"Zergling";"Larva";169;1
"Unit";"Zergling";"Larva";169;1
"Unit";"Zergling";"Larva";169;1
"Unit";"Zergling";"Larva";169;1
"Unit";"Zergling";"Larva";169;1
"Unit";"Zergling";"Larva";169;1
"Unit";"Zergling";"Larva";169;1
"Unit";"Zergling";"Larva";169;1
"Unit";"Zergling";"Larva";169;1
"Building";"CreepTumor";NA;183;0
"Building";"CreepTumor";NA;183;0
"Unit";"Baneling";"Zergling";183;0
"Unit";"Baneling";"Zergling";183;0
"Unit";"Baneling";"Zergling";183;0
"Building";"CreepTumor";NA;183;0
"Unit";"Baneling";"Zergling";183;0
"Unit";"Baneling";"Zergling";183;0
"Unit";"Baneling";"Zergling";183;0
"Building";"CreepTumor";NA;183;0
"Unit";"Zergling";"Larva";201;1
"Unit";"Zergling";"Larva";201;1
"Unit";"Zergling";"Larva";201;1
"Unit";"Zergling";"Larva";201;1
"Unit";"Zergling";"Larva";201;1
"Unit";"Zergling";"Larva";201;1
"Unit";"Zergling";"Larva";201;1
"Unit";"Zergling";"Larva";201;1
"Unit";"Zergling";"Larva";209;1
"Unit";"Zergling";"Larva";209;1
"Unit";"Zergling";"Larva";209;1
"Unit";"Zergling";"Larva";209;1
"Unit";"Zergling";"Larva";209;1
"Unit";"Zergling";"Larva";209;1
"Unit";"Zergling";"Larva";209;1
"Unit";"Zergling";"Larva";209;1
"Unit";"Zergling";"Larva";209;1
"Unit";"Zergling";"Larva";209;1
"Unit";"Zergling";"Larva";209;1
"Unit";"Zergling";"Larva";209;1
"Building";"CreepTumor";NA;209;0
"Unit";"Zergling";"Larva";217;1
"Unit";"Zergling";"Larva";217;1
"Unit";"Zergling";"Larva";217;1
"Unit";"Zergling";"Larva";217;1
"Unit";"Zergling";"Larva";217;1
"Unit";"Zergling";"Larva";217;1
"Unit";"Zergling";"Larva";217;1
"Unit";"Zergling";"Larva";217;1
"Unit";"Zergling";"Larva";217;1
"Unit";"Zergling";"Larva";217;1
"Unit";"Zergling";"Larva";217;1
"Unit";"Zergling";"Larva";217;1
"Unit";"Zergling";"Larva";231;1
"Unit";"Zergling";"Larva";231;1
"Unit";"Zergling";"Larva";233;1
"Unit";"Zergling";"Larva";233;1
"Unit";"Zergling";"Larva";233;1
"Unit";"Zergling";"Larva";233;1
"Building";"CreepTumor";NA;233;0
"Unit";"Zergling";"Larva";233;1
"Unit";"Zergling";"Larva";233;1
"Unit";"Zergling";"Larva";233;1
"Unit";"Zergling";"Larva";233;1
"Unit";"Zergling";"Larva";233;1
"Unit";"Zergling";"Larva";233;1
"Unit";"Zergling";"Larva";233;1
"Unit";"Zergling";"Larva";233;1
"Unit";"Zergling";"Larva";233;1
"Unit";"Zergling";"Larva";233;1
"Unit";"Zergling";"Larva";233;1
"Unit";"Zergling";"Larva";233;1
"Unit";"Zergling";"Larva";233;1
"Unit";"Zergling";"Larva";233;1
"Unit";"Zergling";"Larva";233;1
"Unit";"Zergling";"Larva";233;1
"Building";"Hatchery";NA;209;0
"Building";"CreepTumor";NA;255;0
"Building";"CreepTumor";NA;255;0
"Building";"CreepTumor";NA;255;0
"Unit";"Zergling";"Larva";255;1
"Unit";"Zergling";"Larva";255;1
"Unit";"Zergling";"Larva";255;1
"Unit";"Zergling";"Larva";255;1
"Unit";"Zergling";"Larva";255;1
"Unit";"Zergling";"Larva";255;1
"Unit";"Zergling";"Larva";255;1
"Unit";"Zergling";"Larva";255;1
"Unit";"Zergling";"Larva";255;1
"Unit";"Zergling";"Larva";255;1
"Unit";"Zergling";"Larva";255;1
"Unit";"Zergling";"Larva";255;1
"Unit";"Zergling";"Larva";255;1
"Unit";"Zergling";"Larva";255;1
"Unit";"Zergling";"Larva";255;1
"Unit";"Zergling";"Larva";255;1
"Unit";"Zergling";"Larva";255;1
"Unit";"Zergling";"Larva";255;1
"Unit";"Zergling";"Larva";255;1
"Unit";"Zergling";"Larva";255;1
"Unit";"Zergling";"Larva";255;1
"Unit";"Zergling";"Larva";255;1
"Unit";"Zergling";"Larva";255;1
"Unit";"Zergling";"Larva";255;1
"Unit";"Zergling";"Larva";255;1
"Unit";"Zergling";"Larva";255;1
"Upgrade";"ZergGroundArmorsLevel1";"EvolutionChamber";221;0
"Upgrade";"ZergMeleeWeaponsLevel1";"EvolutionChamber";221;0
"Building";"CreepTumor";NA;281;0
"Building";"CreepTumorQueen";NA;281;0
"Unit";"Zergling";"Larva";281;1
"Unit";"Zergling";"Larva";281;1
"Unit";"Zergling";"Larva";281;1
"Unit";"Zergling";"Larva";281;1
"Unit";"Zergling";"Larva";281;1
"Unit";"Zergling";"Larva";281;1
"Unit";"Zergling";"Larva";281;1
"Unit";"Zergling";"Larva";281;1
"Unit";"Zergling";"Larva";281;1
"Unit";"Zergling";"Larva";281;1
"Unit";"Zergling";"Larva";281;1
"Unit";"Zergling";"Larva";281;1
"Unit";"Zergling";"Larva";281;1
"Unit";"Zergling";"Larva";281;1
"Unit";"Zergling";"Larva";281;1
"Unit";"Zergling";"Larva";281;1
"Unit";"Zergling";"Larva";281;1
"Unit";"Zergling";"Larva";281;1
"Unit";"Zergling";"Larva";281;1
"Unit";"Zergling";"Larva";281;1
"Unit";"Zergling";"Larva";281;1
"Unit";"Zergling";"Larva";281;1
"Unit";"Zergling";"Larva";281;1
"Unit";"Zergling";"Larva";281;1
"Unit";"Zergling";"Larva";281;1
"Unit";"Zergling";"Larva";281;1
"Building";"CreepTumor";NA;289;0
"Building";"CreepTumorQueen";NA;307;0
"Unit";"Zergling";"Larva";307;1
"Unit";"Zergling";"Larva";307;1
"Unit";"Zergling";"Larva";307;1
"Unit";"Zergling";"Larva";307;1
"Unit";"Zergling";"Larva";307;1
"Unit";"Zergling";"Larva";307;1
"Unit";"Zergling";"Larva";307;1
"Unit";"Zergling";"Larva";307;1
"Unit";"Zergling";"Larva";307;1
"Unit";"Zergling";"Larva";307;1
"Unit";"Zergling";"Larva";307;1
"Unit";"Zergling";"Larva";307;1
"Unit";"Zergling";"Larva";307;1
"Unit";"Zergling";"Larva";307;1
"Unit";"Zergling";"Larva";307;1
"Unit";"Zergling";"Larva";307;1
"Unit";"Zergling";"Larva";307;1
"Unit";"Zergling";"Larva";307;1
"Unit";"Zergling";"Larva";307;1
"Unit";"Zergling";"Larva";307;1
"Building";"CreepTumor";NA;327;0
"Building";"CreepTumor";NA;327;0
"Unit";"Queen";"Hatchery";307;2
"Unit";"Zergling";"Larva";327;1
"Unit";"Zergling";"Larva";327;1
"Unit";"Zergling";"Larva";327;1
"Unit";"Zergling";"Larva";327;1
"Unit";"Zergling";"Larva";327;1
"Unit";"Zergling";"Larva";327;1
"Unit";"Zergling";"Larva";327;1
"Unit";"Zergling";"Larva";327;1
"Unit";"Zergling";"Larva";327;1
"Unit";"Zergling";"Larva";327;1
"Unit";"Zergling";"Larva";327;1
"Unit";"Zergling";"Larva";327;1
"Unit";"Zergling";"Larva";327;1
"Unit";"Zergling";"Larva";327;1
"Unit";"Zergling";"Larva";327;1
"Unit";"Zergling";"Larva";327;1
"Unit";"Zergling";"Larva";327;1
"Unit";"Zergling";"Larva";327;1
"Unit";"Zergling";"Larva";327;1
"Unit";"Zergling";"Larva";327;1
"Unit";"Queen";"Hatchery";327;2
"Unit";"Zergling";"Larva";327;1
"Unit";"Zergling";"Larva";327;1
"Unit";"Zergling";"Larva";327;1
"Unit";"Zergling";"Larva";327;1
"Unit";"Zergling";"Larva";327;1
"Unit";"Zergling";"Larva";327;1
"Unit";"Zergling";"Larva";327;1
"Unit";"Zergling";"Larva";327;1
"Unit";"Zergling";"Larva";327;1
"Unit";"Zergling";"Larva";327;1
"Unit";"Baneling";"Zergling";361;0
"Unit";"Baneling";"Zergling";361;0
"Unit";"Baneling";"Zergling";361;0
"Unit";"Zergling";"Larva";361;1
"Unit";"Zergling";"Larva";361;1
"Unit";"Zergling";"Larva";361;1
"Unit";"Zergling";"Larva";361;1
"Unit";"Zergling";"Larva";361;1
"Unit";"Zergling";"Larva";361;1
"Unit";"Zergling";"Larva";361;1
"Unit";"Zergling";"Larva";361;1
"Unit";"Zergling";"Larva";361;1
"Unit";"Zergling";"Larva";361;1
"Unit";"Zergling";"Larva";361;1
"Unit";"Zergling";"Larva";361;1
"Unit";"Zergling";"Larva";361;1
"Unit";"Zergling";"Larva";361;1
"Unit";"Zergling";"Larva";361;1
"Unit";"Zergling";"Larva";361;1
"Unit";"Zergling";"Larva";361;1
"Unit";"Zergling";"Larva";361;1
"Unit";"Zergling";"Larva";361;1
"Unit";"Zergling";"Larva";361;1
"Unit";"Zergling";"Larva";361;1
"Unit";"Zergling";"Larva";361;1
"Unit";"Zergling";"Larva";361;1
"Unit";"Zergling";"Larva";361;1
"Unit";"Zergling";"Larva";383;1
"Unit";"Zergling";"Larva";383;1
"Unit";"Zergling";"Larva";383;1
"Unit";"Zergling";"Larva";383;1
"Unit";"Zergling";"Larva";383;1
"Unit";"Zergling";"Larva";383;1
"Unit";"Zergling";"Larva";383;1
"Unit";"Zergling";"Larva";383;1
"Unit";"Zergling";"Larva";383;1
"Unit";"Zergling";"Larva";383;1
"Unit";"Zergling";"Larva";383;1
"Unit";"Zergling";"Larva";383;1
"Building";"CreepTumor";NA;385;0
"Building";"CreepTumor";NA;385;0
"Upgrade";"ZergGroundArmorsLevel2";"EvolutionChamber";307;0
"Upgrade";"ZergMeleeWeaponsLevel2";"EvolutionChamber";307;0
"Unit";"Zergling";"Larva";385;1
"Unit";"Zergling";"Larva";385;1
"Unit";"Zergling";"Larva";385;1
"Unit";"Zergling";"Larva";385;1
"Unit";"Zergling";"Larva";385;1
"Unit";"Zergling";"Larva";385;1
"Unit";"Baneling";"Zergling";385;0
"Unit";"Baneling";"Zergling";385;0
"Unit";"Baneling";"Zergling";385;0
"Unit";"Baneling";"Zergling";385;0
"Unit";"Baneling";"Zergling";385;0
"Unit";"Baneling";"Zergling";385;0
"Unit";"Baneling";"Zergling";385;0
"Unit";"Queen";"Hatchery";373;2
"Unit";"Queen";"Hatchery";381;2
"Unit";"Zergling";"Larva";397;1
"Unit";"Zergling";"Larva";397;1
"Unit";"Zergling";"Larva";397;1
"Unit";"Zergling";"Larva";397;1
"Unit";"Zergling";"Larva";397;1
"Unit";"Zergling";"Larva";397;1
"Unit";"Zergling";"Larva";397;1
"Unit";"Zergling";"Larva";397;1
"Unit";"Zergling";"Larva";397;1
"Unit";"Zergling";"Larva";397;1
"Unit";"Zergling";"Larva";397;1
"Unit";"Zergling";"Larva";397;1
"Unit";"Zergling";"Larva";397;1
"Unit";"Zergling";"Larva";397;1
"Unit";"Zergling";"Larva";411;1
"Unit";"Zergling";"Larva";411;1
"Unit";"Zergling";"Larva";411;1
"Unit";"Zergling";"Larva";411;1
"Unit";"Zergling";"Larva";411;1
"Unit";"Zergling";"Larva";411;1
"Unit";"Zergling";"Larva";411;1
"Unit";"Zergling";"Larva";411;1
