"type";"unit_name";"on_building";"total_supply";"supply"
"Unit";"Overlord";"Larva";13;0
"Building";"Extractor";NA;18;0
"Unit";"Overlord";"Larva";21;0
"Building";"SpawningPool";NA;19;0
"Building";"Hatchery";NA;17;0
"Unit";"Zergling";"Larva";23;1
"Unit";"Zergling";"Larva";23;1
"Unit";"Zergling";"Larva";23;1
"Unit";"Zergling";"Larva";23;1
"Unit";"Queen";"Hatchery";23;2
"Unit";"Queen";"Hatchery";23;2
"Building";"CreepTumorQueen";NA;34;0
"Unit";"Overlord";"Larva";36;0
"Unit";"Queen";"Hatchery";34;2
"Building";"CreepTumorQueen";NA;36;0
"Building";"CreepTumor";NA;40;0
"Building";"CreepTumorQueen";NA;42;0
"Building";"Hatchery";NA;27;0
"Unit";"Queen";"Hatchery";36;2
"Unit";"Overlord";"Larva";45;0
"Building";"CreepTumorQueen";NA;45;0
"Building";"CreepTumor";NA;45;0
"Building";"CreepTumor";NA;45;0
"Building";"CreepTumorQueen";NA;50;0
"Unit";"Queen";"Hatchery";44;2
"Unit";"Overlord";"Larva";50;0
"Unit";"Zergling";"Larva";50;1
"Unit";"Zergling";"Larva";50;1
"Unit";"Zergling";"Larva";50;1
"Unit";"Zergling";"Larva";50;1
"Unit";"Zergling";"Larva";50;1
"Unit";"Zergling";"Larva";50;1
"Unit";"Zergling";"Larva";50;1
"Unit";"Zergling";"Larva";50;1
"Unit";"Zergling";"Larva";50;1
"Unit";"Zergling";"Larva";50;1
"Unit";"Zergling";"Larva";50;1
"Unit";"Zergling";"Larva";50;1
"Unit";"Queen";"Hatchery";45;2
"Building";"CreepTumor";NA;66;0
"Building";"CreepTumor";NA;66;0
"Building";"CreepTumorQueen";NA;70;0
"Unit";"Queen";"Hatchery";50;2
"Building";"CreepTumor";NA;70;0
"Unit";"Zergling";"Larva";70;1
"Unit";"Zergling";"Larva";70;1
"Unit";"Overlord";"Larva";70;0
"Building";"BanelingNest";NA;50;0
"Unit";"Overlord";"Larva";70;0
"Building";"CreepTumor";NA;72;0
"Unit";"Overlord";"Larva";72;0
"Unit";"Baneling";"Zergling";74;0
"Unit";"Baneling";"Zergling";74;0
"Building";"EvolutionChamber";NA;74;0
"Building";"EvolutionChamber";NA;74;0
"Unit";"Queen";"Hatchery";74;2
"Building";"CreepTumor";NA;82;0
"Building";"CreepTumor";NA;82;0
"Building";"CreepTumor";NA;82;0
"Building";"CreepTumor";NA;82;0
"Building";"CreepTumorQueen";NA;90;0
"Unit";"Zergling";"Larva";82;1
"Unit";"Zergling";"Larva";82;1
"Building";"SporeCrawler";NA;82;0
"Building";"Extractor";NA;82;0
"Building";"Extractor";NA;82;0
"Unit";"Zergling";"Larva";92;1
"Unit";"Zergling";"Larva";92;1
"Building";"Extractor";NA;82;0
"Unit";"Overlord";"Larva";92;0
"Unit";"Overlord";"Larva";92;0
"Unit";"Overlord";"Larva";92;0
"Building";"CreepTumor";NA;96;0
"Building";"CreepTumor";NA;96;0
"Building";"CreepTumor";NA;96;0
"Building";"CreepTumor";NA;96;0
"Unit";"Baneling";"Zergling";96;0
"Unit";"Baneling";"Zergling";96;0
"Building";"SporeCrawler";NA;104;0
"Building";"CreepTumor";NA;110;0
"Building";"CreepTumor";NA;110;0
"Building";"CreepTumor";NA;114;0
"Unit";"Baneling";"Zergling";114;0
"Unit";"Baneling";"Zergling";114;0
"Unit";"Zergling";"Larva";114;1
"Unit";"Zergling";"Larva";114;1
"Unit";"Zergling";"Larva";114;1
"Unit";"Zergling";"Larva";114;1
"Unit";"Zergling";"Larva";114;1
"Unit";"Zergling";"Larva";114;1
"Unit";"Zergling";"Larva";114;1
"Unit";"Zergling";"Larva";114;1
"Unit";"Zergling";"Larva";114;1
"Unit";"Zergling";"Larva";114;1
"Unit";"Zergling";"Larva";114;1
"Unit";"Zergling";"Larva";114;1
"Unit";"Zergling";"Larva";114;1
"Unit";"Zergling";"Larva";114;1
"Building";"HydraliskDen";NA;114;0
"Unit";"Zergling";"Larva";128;1
"Unit";"Zergling";"Larva";128;1
"Upgrade";"ZergMeleeWeaponsLevel1";"EvolutionChamber";96;0
"Building";"CreepTumor";NA;133;0
"Unit";"Overlord";"Larva";133;0
"Building";"CreepTumor";NA;133;0
"Building";"Extractor";NA;133;0
"Building";"Extractor";NA;133;0
"Unit";"Overlord";"Larva";133;0
"Unit";"Overlord";"Larva";133;0
"Unit";"Overlord";"Larva";133;0
"Unit";"Overlord";"Larva";133;0
"Unit";"Overlord";"Larva";133;0
"Unit";"Overlord";"Larva";133;0
"Unit";"Overlord";"Larva";133;0
"Unit";"Overlord";"Larva";133;0
"Building";"Hatchery";NA;114;0
"Building";"InfestationPit";NA;131;0
"Building";"CreepTumor";NA;136;0
"Building";"SpineCrawler";NA;133;0
"Building";"CreepTumorQueen";NA;136;0
"Upgrade";"ZergGroundArmorsLevel1";"EvolutionChamber";114;0
"Building";"CreepTumorQueen";NA;137;0
"Building";"CreepTumorQueen";NA;137;0
"Building";"CreepTumorQueen";NA;137;0
"Building";"Extractor";NA;136;0
"Building";"SporeCrawler";NA;137;0
"Building";"Extractor";NA;137;0
"Unit";"Overlord";"Larva";143;0
"Building";"CreepTumor";NA;146;0
"Upgrade";"EvolveMuscularAugments";"HydraliskDen";133;0
"Building";"SpineCrawler";NA;137;0
"Unit";"Hydralisk";"Larva";146;2
"Unit";"Hydralisk";"Larva";146;2
"Unit";"Hydralisk";"Larva";146;2
"Building";"Hatchery";NA;131;0
"Building";"CreepTumor";NA;148;0
"Building";"CreepTumorQueen";NA;152;0
"Building";"CreepTumorQueen";NA;152;0
"Building";"CreepTumorQueen";NA;152;0
"Building";"CreepTumorQueen";NA;152;0
"Building";"CreepTumor";NA;152;0
"Unit";"Overlord";"Larva";148;0
"Building";"SporeCrawler";NA;148;0
"Building";"CreepTumor";NA;158;0
"Unit";"Hydralisk";"Larva";151;2
"Unit";"Hydralisk";"Larva";152;2
"Unit";"Hydralisk";"Larva";158;2
"Unit";"Hydralisk";"Larva";158;2
"Building";"CreepTumorQueen";NA;160;0
"Unit";"Hydralisk";"Larva";158;2
"Unit";"Hydralisk";"Larva";158;2
"Unit";"Hydralisk";"Larva";158;2
"Unit";"Hydralisk";"Larva";158;2
"Building";"CreepTumorQueen";NA;162;0
"Unit";"Zergling";"Larva";158;1
"Unit";"Zergling";"Larva";158;1
"Unit";"Zergling";"Larva";158;1
"Unit";"Zergling";"Larva";158;1
"Building";"CreepTumorQueen";NA;162;0
"Unit";"Hydralisk";"Larva";158;2
"Unit";"Hydralisk";"Larva";158;2
"Unit";"Hydralisk";"Larva";158;2
"Building";"CreepTumorQueen";NA;172;0
"Unit";"Hydralisk";"Larva";162;2
"Building";"CreepTumorQueen";NA;172;0
"Building";"CreepTumorQueen";NA;178;0
"Unit";"Zergling";"Larva";174;1
"Unit";"Zergling";"Larva";174;1
"Unit";"Hydralisk";"Larva";172;2
"Unit";"Hydralisk";"Larva";172;2
"Unit";"Hydralisk";"Larva";172;2
"Unit";"Zergling";"Larva";184;1
"Unit";"Zergling";"Larva";184;1
"Unit";"Zergling";"Larva";184;1
"Unit";"Zergling";"Larva";184;1
"Unit";"Zergling";"Larva";186;1
"Unit";"Zergling";"Larva";186;1
"Unit";"Zergling";"Larva";186;1
"Unit";"Zergling";"Larva";186;1
"Unit";"Queen";"Hatchery";162;2
"Unit";"Zergling";"Larva";188;1
"Unit";"Zergling";"Larva";188;1
"Unit";"Zergling";"Larva";188;1
"Unit";"Zergling";"Larva";188;1
"Unit";"Zergling";"Larva";188;1
"Unit";"Zergling";"Larva";188;1
"Unit";"Overlord";"Larva";194;0
"Building";"CreepTumor";NA;204;0
"Building";"CreepTumor";NA;204;0
"Unit";"Hydralisk";"Larva";188;2
"Building";"CreepTumor";NA;204;0
"Building";"CreepTumor";NA;204;0
"Building";"CreepTumor";NA;204;0
"Building";"CreepTumor";NA;205;0
"Building";"CreepTumor";NA;209;0
"Building";"CreepTumor";NA;209;0
"Unit";"Overlord";"Larva";204;0
"Building";"CreepTumor";NA;209;0
"Unit";"Viper";"Larva";194;3
"Unit";"Viper";"Larva";194;3
"Unit";"Viper";"Larva";194;3
"Unit";"Overlord";"Larva";209;0
"Unit";"Baneling";"Zergling";226;0
"Unit";"Baneling";"Zergling";226;0
"Unit";"Baneling";"Zergling";226;0
"Unit";"Baneling";"Zergling";226;0
"Upgrade";"ZergMeleeWeaponsLevel2";"EvolutionChamber";158;0
"Unit";"Baneling";"Zergling";226;0
"Building";"CreepTumor";NA;226;0
"Unit";"Baneling";"Zergling";226;0
"Unit";"Baneling";"Zergling";226;0
"Unit";"Baneling";"Zergling";226;0
"Unit";"Baneling";"Zergling";226;0
"Unit";"Baneling";"Zergling";226;0
"Building";"CreepTumor";NA;226;0
"Unit";"Baneling";"Zergling";226;0
"Unit";"Baneling";"Zergling";226;0
"Unit";"Baneling";"Zergling";226;0
"Unit";"Baneling";"Zergling";226;0
"Unit";"Baneling";"Zergling";226;0
"Building";"CreepTumor";NA;226;0
"Unit";"Baneling";"Zergling";226;0
"Building";"CreepTumor";NA;226;0
"Building";"CreepTumor";NA;226;0
"Unit";"Queen";"Hatchery";215;2
"Building";"CreepTumor";NA;226;0
"Unit";"Queen";"Hatchery";215;2
"Building";"CreepTumor";NA;226;0
"Unit";"Zergling";"Larva";226;1
"Unit";"Zergling";"Larva";226;1
"Unit";"Zergling";"Larva";226;1
"Unit";"Zergling";"Larva";226;1
"Unit";"Zergling";"Larva";226;1
"Unit";"Zergling";"Larva";226;1
"Unit";"Zergling";"Larva";226;1
"Unit";"Zergling";"Larva";226;1
"Unit";"Zergling";"Larva";226;1
"Unit";"Zergling";"Larva";226;1
"Unit";"Zergling";"Larva";226;1
"Unit";"Zergling";"Larva";226;1
"Unit";"Zergling";"Larva";226;1
"Unit";"Zergling";"Larva";226;1
"Unit";"Zergling";"Larva";226;1
"Unit";"Zergling";"Larva";226;1
"Unit";"Zergling";"Larva";226;1
"Unit";"Zergling";"Larva";226;1
"Unit";"Zergling";"Larva";226;1
"Unit";"Zergling";"Larva";226;1
"Building";"CreepTumor";NA;226;0
"Building";"CreepTumor";NA;228;0
"Building";"CreepTumor";NA;230;0
"Upgrade";"ZergGroundArmorsLevel2";"EvolutionChamber";162;0
"Unit";"Zergling";"Larva";226;1
"Unit";"Zergling";"Larva";226;1
"Unit";"Zergling";"Larva";226;1
"Unit";"Zergling";"Larva";226;1
"Unit";"Zergling";"Larva";226;1
"Unit";"Zergling";"Larva";226;1
"Unit";"Zergling";"Larva";226;1
"Unit";"Zergling";"Larva";226;1
"Unit";"Zergling";"Larva";226;1
"Unit";"Zergling";"Larva";226;1
"Unit";"Zergling";"Larva";226;1
"Unit";"Zergling";"Larva";226;1
"Unit";"Zergling";"Larva";226;1
"Unit";"Zergling";"Larva";226;1
"Building";"CreepTumor";NA;251;0
"Building";"CreepTumor";NA;251;0
"Building";"CreepTumor";NA;251;0
"Unit";"Zergling";"Larva";251;1
"Unit";"Zergling";"Larva";251;1
"Unit";"Hydralisk";"Larva";251;2
"Unit";"Hydralisk";"Larva";251;2
"Unit";"Hydralisk";"Larva";251;2
"Unit";"Hydralisk";"Larva";251;2
"Building";"CreepTumor";NA;265;0
"Building";"CreepTumor";NA;265;0
"Building";"CreepTumor";NA;265;0
"Building";"CreepTumor";NA;265;0
"Unit";"Zergling";"Larva";265;1
"Unit";"Zergling";"Larva";265;1
"Unit";"Zergling";"Larva";265;1
"Unit";"Zergling";"Larva";265;1
"Unit";"Zergling";"Larva";265;1
"Unit";"Zergling";"Larva";265;1
"Unit";"Hydralisk";"Larva";265;2
"Unit";"Hydralisk";"Larva";265;2
"Unit";"Hydralisk";"Larva";265;2
"Unit";"Hydralisk";"Larva";265;2
"Building";"CreepTumor";NA;273;0
"Unit";"Viper";"Larva";265;3
"Building";"Hatchery";NA;226;0
"Unit";"Hydralisk";"Larva";267;2
"Unit";"Hydralisk";"Larva";267;2
"Unit";"Hydralisk";"Larva";267;2
"Building";"CreepTumor";NA;281;0
"Unit";"Overlord";"Larva";292;0
"Upgrade";"EvolveGroovedSpines";"HydraliskDen";265;0
"Unit";"Baneling";"Zergling";298;0
"Unit";"Baneling";"Zergling";298;0
"Unit";"Baneling";"Zergling";298;0
"Unit";"Baneling";"Zergling";298;0
"Unit";"Baneling";"Zergling";298;0
"Building";"CreepTumor";NA;298;0
"Building";"Spire";NA;251;0
"Unit";"Overlord";"Larva";298;0
"Building";"CreepTumor";NA;298;0
"Building";"CreepTumorQueen";NA;298;0
"Building";"CreepTumorQueen";NA;298;0
"Building";"CreepTumorQueen";NA;298;0
"Building";"CreepTumorQueen";NA;298;0
"Building";"CreepTumorQueen";NA;298;0
"Building";"CreepTumorQueen";NA;298;0
"Building";"CreepTumorQueen";NA;298;0
"Building";"CreepTumorQueen";NA;298;0
"Building";"CreepTumorQueen";NA;298;0
"Building";"CreepTumorQueen";NA;305;0
"Building";"CreepTumor";NA;298;0
"Building";"CreepTumorQueen";NA;305;0
"Building";"CreepTumorQueen";NA;305;0
"Building";"CreepTumorQueen";NA;305;0
"Building";"CreepTumor";NA;305;0
"Building";"CreepTumorQueen";NA;305;0
"Building";"CreepTumorQueen";NA;305;0
"Building";"CreepTumor";NA;305;0
"Building";"CreepTumor";NA;305;0
"Building";"CreepTumor";NA;305;0
"Unit";"Overlord";"Larva";305;0
"Building";"CreepTumorQueen";NA;305;0
"Building";"CreepTumorQueen";NA;305;0
"Building";"UltraliskCavern";NA;305;0
"Building";"SpineCrawler";NA;305;0
"Building";"SpineCrawler";NA;305;0
"Building";"SpineCrawler";NA;305;0
"Unit";"Hydralisk";"Larva";311;2
"Unit";"Hydralisk";"Larva";311;2
"Building";"Extractor";NA;311;0
"Building";"SporeCrawler";NA;311;0
"Building";"CreepTumor";NA;323;0
"Building";"CreepTumor";NA;323;0
"Unit";"Corruptor";"Larva";311;2
"Building";"CreepTumor";NA;323;0
"Unit";"Corruptor";"Larva";311;2
"Unit";"Corruptor";"Larva";311;2
"Unit";"Corruptor";"Larva";311;2
"Unit";"Corruptor";"Larva";311;2
"Unit";"Corruptor";"Larva";311;2
"Unit";"Corruptor";"Larva";311;2
"Unit";"Corruptor";"Larva";311;2
"Unit";"Corruptor";"Larva";311;2
"Unit";"Corruptor";"Larva";311;2
"Unit";"Corruptor";"Larva";311;2
"Unit";"Overlord";"Larva";322;0
"Unit";"Zergling";"Larva";327;1
"Unit";"Zergling";"Larva";327;1
"Unit";"Zergling";"Larva";327;1
"Unit";"Zergling";"Larva";327;1
"Unit";"Zergling";"Larva";327;1
"Unit";"Zergling";"Larva";327;1
"Unit";"Zergling";"Larva";327;1
"Unit";"Zergling";"Larva";327;1
"Unit";"Zergling";"Larva";327;1
"Unit";"Zergling";"Larva";327;1
"Unit";"Zergling";"Larva";327;1
"Unit";"Zergling";"Larva";327;1
"Unit";"Zergling";"Larva";327;1
"Unit";"Zergling";"Larva";327;1
"Unit";"Zergling";"Larva";327;1
"Unit";"Zergling";"Larva";327;1
"Unit";"Zergling";"Larva";327;1
"Unit";"Zergling";"Larva";327;1
"Unit";"Zergling";"Larva";327;1
"Unit";"Zergling";"Larva";327;1
"Unit";"Zergling";"Larva";327;1
"Unit";"Zergling";"Larva";327;1
"Unit";"Zergling";"Larva";327;1
"Unit";"Zergling";"Larva";327;1
"Unit";"Zergling";"Larva";327;1
"Unit";"Zergling";"Larva";327;1
"Unit";"Zergling";"Larva";327;1
"Unit";"Zergling";"Larva";327;1
"Unit";"Zergling";"Larva";327;1
"Unit";"Zergling";"Larva";327;1
"Unit";"Zergling";"Larva";327;1
"Unit";"Zergling";"Larva";327;1
"Unit";"Zergling";"Larva";327;1
"Unit";"Zergling";"Larva";327;1
"Building";"SpineCrawler";NA;311;0
"Building";"SpineCrawler";NA;311;0
"Building";"Extractor";NA;327;0
"Building";"CreepTumor";NA;349;0
"Building";"CreepTumor";NA;349;0
"Building";"CreepTumor";NA;349;0
"Building";"CreepTumor";NA;349;0
"Building";"CreepTumor";NA;349;0
"Building";"CreepTumor";NA;349;0
"Building";"Hatchery";NA;306;0
"Building";"CreepTumor";NA;383;0
"Building";"CreepTumor";NA;383;0
"Upgrade";"ZergMeleeWeaponsLevel3";"EvolutionChamber";305;0
"Building";"CreepTumor";NA;383;0
"Upgrade";"ZergGroundArmorsLevel3";"EvolutionChamber";305;0
"Building";"CreepTumor";NA;383;0
"Building";"CreepTumor";NA;383;0
"Building";"CreepTumor";NA;383;0
"Building";"CreepTumor";NA;383;0
"Building";"CreepTumor";NA;383;0
"Building";"CreepTumor";NA;383;0
"Building";"Extractor";NA;383;0
"Building";"Extractor";NA;383;0
"Building";"CreepTumor";NA;385;0
"Upgrade";"ChitinousPlating";"UltraliskCavern";349;0
"Unit";"Zergling";"Larva";385;1
"Unit";"Zergling";"Larva";385;1
"Unit";"Zergling";"Larva";385;1
"Unit";"Zergling";"Larva";385;1
"Unit";"Zergling";"Larva";385;1
"Unit";"Zergling";"Larva";385;1
"Unit";"Zergling";"Larva";385;1
"Unit";"Zergling";"Larva";385;1
"Unit";"Zergling";"Larva";385;1
"Unit";"Zergling";"Larva";385;1
"Unit";"Zergling";"Larva";385;1
"Unit";"Zergling";"Larva";385;1
"Unit";"Zergling";"Larva";385;1
"Unit";"Zergling";"Larva";385;1
"Building";"CreepTumor";NA;385;0
"Building";"CreepTumor";NA;385;0
"Unit";"Overlord";"Larva";387;0
"Unit";"Overlord";"Larva";399;0
"Unit";"Overlord";"Larva";399;0
"Unit";"Corruptor";"Larva";399;2
"Unit";"Zergling";"Larva";400;1
"Unit";"Zergling";"Larva";400;1
"Unit";"Zergling";"Larva";400;1
"Unit";"Zergling";"Larva";400;1
"Unit";"Zergling";"Larva";400;1
"Unit";"Zergling";"Larva";400;1
"Unit";"Zergling";"Larva";400;1
"Unit";"Zergling";"Larva";400;1
"Unit";"Zergling";"Larva";400;1
"Unit";"Zergling";"Larva";400;1
"Building";"SpineCrawler";NA;399;0
"Building";"CreepTumor";NA;412;0
"Unit";"Zergling";"Larva";412;1
"Unit";"Zergling";"Larva";412;1
"Building";"CreepTumor";NA;412;0
"Building";"CreepTumorQueen";NA;412;0
"Building";"CreepTumorQueen";NA;412;0
"Building";"CreepTumorQueen";NA;412;0
"Unit";"Hydralisk";"Larva";402;2
"Unit";"Hydralisk";"Larva";402;2
"Unit";"Hydralisk";"Larva";402;2
"Unit";"Hydralisk";"Larva";402;2
"Unit";"Hydralisk";"Larva";402;2
"Unit";"Hydralisk";"Larva";402;2
"Unit";"Hydralisk";"Larva";402;2
"Building";"CreepTumorQueen";NA;412;0
"Building";"CreepTumorQueen";NA;412;0
"Unit";"Zergling";"Larva";414;1
"Unit";"Zergling";"Larva";414;1
"Unit";"Zergling";"Larva";414;1
"Unit";"Zergling";"Larva";414;1
"Unit";"Zergling";"Larva";414;1
"Unit";"Zergling";"Larva";414;1
"Unit";"Zergling";"Larva";414;1
"Unit";"Zergling";"Larva";414;1
"Unit";"Zergling";"Larva";414;1
"Unit";"Zergling";"Larva";414;1
"Unit";"Zergling";"Larva";414;1
"Unit";"Zergling";"Larva";414;1
"Unit";"Zergling";"Larva";414;1
"Unit";"Zergling";"Larva";414;1
"Unit";"Zergling";"Larva";414;1
"Unit";"Zergling";"Larva";414;1
"Unit";"Zergling";"Larva";414;1
"Unit";"Zergling";"Larva";414;1
"Unit";"Zergling";"Larva";414;1
"Unit";"Zergling";"Larva";414;1
"Unit";"Zergling";"Larva";416;1
"Unit";"Zergling";"Larva";416;1
"Unit";"Zergling";"Larva";416;1
"Unit";"Zergling";"Larva";416;1
"Unit";"Zergling";"Larva";416;1
"Unit";"Zergling";"Larva";416;1
"Unit";"Zergling";"Larva";416;1
"Unit";"Zergling";"Larva";416;1
"Building";"CreepTumor";NA;428;0
"Building";"CreepTumor";NA;428;0
"Building";"CreepTumor";NA;428;0
"Unit";"Baneling";"Zergling";428;0
"Unit";"Baneling";"Zergling";428;0
"Unit";"Baneling";"Zergling";428;0
"Unit";"Baneling";"Zergling";428;0
"Unit";"Baneling";"Zergling";428;0
"Unit";"Baneling";"Zergling";428;0
"Building";"Hatchery";NA;399;0
"Unit";"Hydralisk";"Larva";428;2
"Unit";"Overlord";"Larva";428;0
"Building";"CreepTumor";NA;456;0
"Building";"CreepTumor";NA;456;0
"Upgrade";"ZergMissileWeaponsLevel1";"EvolutionChamber";399;0
"Building";"CreepTumor";NA;456;0
"Unit";"Corruptor";"Larva";456;2
"Unit";"Corruptor";"Larva";456;2
"Unit";"Baneling";"Zergling";458;0
"Unit";"Baneling";"Zergling";458;0
"Unit";"Baneling";"Zergling";458;0
"Unit";"Baneling";"Zergling";458;0
"Unit";"Baneling";"Zergling";458;0
"Unit";"Baneling";"Zergling";458;0
"Unit";"Baneling";"Zergling";458;0
"Unit";"Baneling";"Zergling";458;0
"Unit";"Baneling";"Zergling";458;0
"Unit";"Overlord";"Larva";458;0
"Unit";"Zergling";"Larva";462;1
"Unit";"Zergling";"Larva";462;1
"Unit";"Zergling";"Larva";462;1
"Unit";"Zergling";"Larva";462;1
"Unit";"Zergling";"Larva";462;1
"Unit";"Zergling";"Larva";462;1
"Unit";"Zergling";"Larva";462;1
"Unit";"Zergling";"Larva";462;1
"Unit";"Zergling";"Larva";462;1
"Unit";"Zergling";"Larva";462;1
"Unit";"Zergling";"Larva";462;1
"Unit";"Zergling";"Larva";462;1
"Unit";"Zergling";"Larva";462;1
"Unit";"Zergling";"Larva";462;1
"Unit";"Zergling";"Larva";462;1
"Unit";"Zergling";"Larva";462;1
"Unit";"Zergling";"Larva";462;1
"Unit";"Zergling";"Larva";462;1
"Unit";"Zergling";"Larva";462;1
"Unit";"Zergling";"Larva";462;1
"Unit";"Zergling";"Larva";462;1
"Unit";"Zergling";"Larva";462;1
"Unit";"Zergling";"Larva";462;1
"Unit";"Zergling";"Larva";462;1
"Unit";"Zergling";"Larva";462;1
"Unit";"Zergling";"Larva";462;1
"Unit";"Zergling";"Larva";462;1
"Unit";"Zergling";"Larva";462;1
"Unit";"Zergling";"Larva";462;1
"Unit";"Zergling";"Larva";462;1
"Unit";"Zergling";"Larva";462;1
"Unit";"Zergling";"Larva";462;1
