"type";"unit_name";"on_building";"total_supply";"supply"
"Unit";"Overlord";"Larva";13;0
"Building";"Extractor";NA;18;0
"Unit";"Overlord";"Larva";20;0
"Building";"SpawningPool";NA;19;0
"Building";"Hatchery";NA;17;0
"Unit";"Zergling";"Larva";23;1
"Unit";"Zergling";"Larva";23;1
"Unit";"Zergling";"Larva";23;1
"Unit";"Zergling";"Larva";23;1
"Unit";"Queen";"Hatchery";22;2
"Unit";"Queen";"Hatchery";23;2
"Unit";"Overlord";"Larva";37;0
"Unit";"Queen";"Hatchery";31;2
"Unit";"Overlord";"Larva";39;0
"Building";"CreepTumorQueen";NA;49;0
"Building";"CreepTumorQueen";NA;53;0
"Building";"Extractor";NA;52;0
"Building";"Hatchery";NA;37;0
"Building";"EvolutionChamber";NA;53;0
"Building";"Extractor";NA;54;0
"Building";"RoachWarren";NA;53;0
"Building";"CreepTumor";NA;62;0
"Building";"CreepTumor";NA;64;0
"Building";"EvolutionChamber";NA;62;0
"Unit";"Overlord";"Larva";62;0
"Unit";"Overlord";"Larva";62;0
"Unit";"Overlord";"Larva";62;0
"Unit";"Overlord";"Larva";62;0
"Unit";"Overlord";"Larva";64;0
"Unit";"Overlord";"Larva";68;0
"Unit";"Queen";"Hatchery";62;2
"Unit";"Zergling";"Larva";69;1
"Unit";"Zergling";"Larva";69;1
"Unit";"Zergling";"Larva";69;1
"Unit";"Zergling";"Larva";69;1
"Building";"CreepTumor";NA;71;0
"Unit";"Zergling";"Larva";71;1
"Unit";"Zergling";"Larva";71;1
"Building";"CreepTumor";NA;74;0
"Unit";"Zergling";"Larva";71;1
"Unit";"Zergling";"Larva";71;1
"Building";"Extractor";NA;69;0
"Building";"CreepTumorQueen";NA;74;0
"Unit";"Zergling";"Larva";74;1
"Unit";"Zergling";"Larva";74;1
"Unit";"Zergling";"Larva";74;1
"Unit";"Zergling";"Larva";74;1
"Building";"BanelingNest";NA;69;0
"Unit";"Zergling";"Larva";74;1
"Unit";"Zergling";"Larva";74;1
"Unit";"Zergling";"Larva";74;1
"Unit";"Zergling";"Larva";74;1
"Unit";"Zergling";"Larva";78;1
"Unit";"Zergling";"Larva";78;1
"Unit";"Zergling";"Larva";80;1
"Unit";"Zergling";"Larva";80;1
"Unit";"Zergling";"Larva";82;1
"Unit";"Zergling";"Larva";82;1
"Unit";"Zergling";"Larva";85;1
"Unit";"Zergling";"Larva";85;1
"Unit";"Zergling";"Larva";85;1
"Unit";"Zergling";"Larva";85;1
"Building";"CreepTumorQueen";NA;93;0
"Unit";"Zergling";"Larva";93;1
"Unit";"Zergling";"Larva";93;1
"Unit";"Zergling";"Larva";93;1
"Unit";"Zergling";"Larva";93;1
"Unit";"Zergling";"Larva";93;1
"Unit";"Zergling";"Larva";93;1
"Unit";"Zergling";"Larva";93;1
"Unit";"Zergling";"Larva";93;1
"Unit";"Zergling";"Larva";93;1
"Unit";"Zergling";"Larva";93;1
"Unit";"Zergling";"Larva";93;1
"Unit";"Zergling";"Larva";93;1
"Unit";"Zergling";"Larva";93;1
"Unit";"Zergling";"Larva";93;1
"Unit";"Zergling";"Larva";93;1
"Unit";"Zergling";"Larva";93;1
"Building";"CreepTumorQueen";NA;119;0
"Unit";"Zergling";"Larva";119;1
"Unit";"Zergling";"Larva";119;1
"Unit";"Zergling";"Larva";119;1
"Unit";"Zergling";"Larva";119;1
"Unit";"Zergling";"Larva";119;1
"Unit";"Zergling";"Larva";119;1
"Unit";"Zergling";"Larva";119;1
"Unit";"Zergling";"Larva";119;1
"Unit";"Zergling";"Larva";119;1
"Unit";"Zergling";"Larva";119;1
"Unit";"Zergling";"Larva";131;1
"Unit";"Zergling";"Larva";131;1
"Unit";"Zergling";"Larva";131;1
"Unit";"Zergling";"Larva";131;1
"Unit";"Zergling";"Larva";131;1
"Unit";"Zergling";"Larva";131;1
"Unit";"Zergling";"Larva";131;1
"Unit";"Zergling";"Larva";131;1
"Unit";"Zergling";"Larva";131;1
"Unit";"Zergling";"Larva";131;1
"Unit";"Zergling";"Larva";131;1
"Unit";"Zergling";"Larva";131;1
"Upgrade";"ZergGroundArmorsLevel1";"EvolutionChamber";82;0
"Building";"CreepTumor";NA;144;0
"Building";"CreepTumor";NA;149;0
"Building";"CreepTumor";NA;149;0
"Unit";"Overlord";"Larva";143;0
"Upgrade";"ZergMeleeWeaponsLevel1";"EvolutionChamber";111;0
"Unit";"Overlord";"Larva";155;0
"Unit";"Overlord";"Larva";155;0
"Unit";"Overlord";"Larva";155;0
"Building";"SporeCrawler";NA;155;0
"Building";"SporeCrawler";NA;155;0
"Building";"SporeCrawler";NA;155;0
"Building";"SporeCrawler";NA;155;0
"Unit";"Overlord";"Larva";157;0
"Unit";"Overlord";"Larva";157;0
"Unit";"Overlord";"Larva";157;0
"Building";"CreepTumor";NA;158;0
"Building";"CreepTumor";NA;158;0
"Building";"CreepTumor";NA;160;0
"Building";"CreepTumorQueen";NA;162;0
"Building";"CreepTumor";NA;162;0
"Building";"CreepTumorQueen";NA;163;0
"Building";"Spire";NA;143;0
"Unit";"Baneling";"Zergling";162;0
"Unit";"Baneling";"Zergling";162;0
"Unit";"Baneling";"Zergling";163;0
"Unit";"Baneling";"Zergling";163;0
"Unit";"Baneling";"Zergling";163;0
"Unit";"Queen";"Hatchery";158;2
"Building";"CreepTumorQueen";NA;166;0
"Building";"CreepTumorQueen";NA;168;0
"Building";"CreepTumor";NA;176;0
"Building";"CreepTumorQueen";NA;183;0
"Unit";"Zergling";"Larva";183;1
"Unit";"Zergling";"Larva";183;1
"Unit";"Zergling";"Larva";183;1
"Unit";"Zergling";"Larva";183;1
"Unit";"Zergling";"Larva";183;1
"Unit";"Zergling";"Larva";183;1
"Building";"Extractor";NA;183;0
"Building";"Extractor";NA;183;0
"Building";"CreepTumor";NA;184;0
"Building";"CreepTumor";NA;184;0
"Building";"CreepTumor";NA;184;0
"Building";"CreepTumor";NA;184;0
"Building";"CreepTumor";NA;190;0
"Building";"CreepTumor";NA;190;0
"Building";"InfestationPit";NA;176;0
"Unit";"Baneling";"Zergling";190;0
"Unit";"Baneling";"Zergling";190;0
"Unit";"Baneling";"Zergling";190;0
"Unit";"Baneling";"Zergling";190;0
"Unit";"Baneling";"Zergling";190;0
"Unit";"Baneling";"Zergling";190;0
"Unit";"Baneling";"Zergling";190;0
"Unit";"Baneling";"Zergling";190;0
"Unit";"Baneling";"Zergling";190;0
"Unit";"Baneling";"Zergling";190;0
"Unit";"Baneling";"Zergling";190;0
"Unit";"Baneling";"Zergling";190;0
"Unit";"Baneling";"Zergling";190;0
"Unit";"Baneling";"Zergling";190;0
"Unit";"Baneling";"Zergling";190;0
"Unit";"Baneling";"Zergling";190;0
"Unit";"Baneling";"Zergling";190;0
"Unit";"Baneling";"Zergling";190;0
"Unit";"Baneling";"Zergling";190;0
"Unit";"Baneling";"Zergling";190;0
"Unit";"Baneling";"Zergling";190;0
"Unit";"Zergling";"Larva";190;1
"Unit";"Zergling";"Larva";190;1
"Unit";"Zergling";"Larva";190;1
"Unit";"Zergling";"Larva";190;1
"Unit";"Zergling";"Larva";190;1
"Unit";"Zergling";"Larva";190;1
"Unit";"Zergling";"Larva";190;1
"Unit";"Zergling";"Larva";190;1
"Unit";"Zergling";"Larva";190;1
"Unit";"Zergling";"Larva";190;1
"Unit";"Zergling";"Larva";190;1
"Unit";"Zergling";"Larva";190;1
"Unit";"Zergling";"Larva";190;1
"Unit";"Zergling";"Larva";190;1
"Unit";"Zergling";"Larva";190;1
"Unit";"Zergling";"Larva";190;1
"Unit";"Zergling";"Larva";190;1
"Unit";"Zergling";"Larva";190;1
"Unit";"Zergling";"Larva";190;1
"Unit";"Zergling";"Larva";190;1
"Unit";"Baneling";"Zergling";190;0
"Building";"CreepTumorQueen";NA;190;0
"Unit";"Baneling";"Zergling";190;0
"Unit";"Baneling";"Zergling";190;0
"Unit";"Baneling";"Zergling";190;0
"Unit";"Baneling";"Zergling";190;0
"Unit";"Baneling";"Zergling";190;0
"Unit";"Baneling";"Zergling";190;0
"Unit";"Baneling";"Zergling";190;0
"Unit";"Baneling";"Zergling";190;0
"Unit";"Baneling";"Zergling";190;0
"Unit";"Baneling";"Zergling";190;0
"Unit";"Baneling";"Zergling";190;0
"Unit";"Baneling";"Zergling";190;0
"Unit";"Baneling";"Zergling";190;0
"Unit";"Zergling";"Larva";190;1
"Unit";"Zergling";"Larva";190;1
"Unit";"Zergling";"Larva";190;1
"Unit";"Zergling";"Larva";190;1
"Unit";"Zergling";"Larva";190;1
"Unit";"Zergling";"Larva";190;1
"Unit";"Zergling";"Larva";190;1
"Unit";"Zergling";"Larva";190;1
"Unit";"Zergling";"Larva";190;1
"Unit";"Zergling";"Larva";190;1
"Unit";"Zergling";"Larva";202;1
"Unit";"Zergling";"Larva";202;1
"Unit";"Zergling";"Larva";202;1
"Unit";"Zergling";"Larva";202;1
"Building";"CreepTumor";NA;212;0
"Building";"CreepTumorQueen";NA;220;0
"Building";"CreepTumor";NA;220;0
"Building";"CreepTumor";NA;220;0
"Unit";"Zergling";"Larva";210;1
"Unit";"Zergling";"Larva";210;1
"Building";"CreepTumor";NA;220;0
"Building";"CreepTumorQueen";NA;220;0
"Unit";"Zergling";"Larva";220;1
"Unit";"Zergling";"Larva";220;1
"Unit";"Zergling";"Larva";220;1
"Unit";"Zergling";"Larva";220;1
"Unit";"Zergling";"Larva";220;1
"Unit";"Zergling";"Larva";220;1
"Building";"CreepTumor";NA;220;0
"Building";"CreepTumor";NA;220;0
"Building";"CreepTumorQueen";NA;224;0
"Unit";"Zergling";"Larva";220;1
"Unit";"Zergling";"Larva";220;1
"Building";"Hatchery";NA;183;0
"Unit";"Queen";"Hatchery";210;2
"Upgrade";"ZergMeleeWeaponsLevel2";"EvolutionChamber";176;0
"Upgrade";"ZergGroundArmorsLevel2";"EvolutionChamber";176;0
"Building";"Hatchery";NA;184;0
"Unit";"Overlord";"Larva";232;0
"Unit";"Overlord";"Larva";232;0
"Unit";"Overlord";"Larva";234;0
"Unit";"Overlord";"Larva";234;0
"Unit";"Overlord";"Larva";234;0
"Building";"SporeCrawler";NA;234;0
"Unit";"Zergling";"Larva";234;1
"Unit";"Zergling";"Larva";234;1
"Unit";"Zergling";"Larva";234;1
"Unit";"Zergling";"Larva";234;1
"Unit";"Zergling";"Larva";234;1
"Unit";"Zergling";"Larva";234;1
"Unit";"Zergling";"Larva";234;1
"Unit";"Zergling";"Larva";234;1
"Building";"SporeCrawler";NA;234;0
"Building";"CreepTumor";NA;236;0
"Building";"Extractor";NA;236;0
"Building";"Extractor";NA;236;0
"Building";"SporeCrawler";NA;236;0
"Building";"CreepTumor";NA;244;0
"Building";"CreepTumorQueen";NA;244;0
"Building";"CreepTumor";NA;244;0
"Unit";"Mutalisk";"Larva";236;2
"Unit";"Mutalisk";"Larva";236;2
"Building";"CreepTumorQueen";NA;244;0
"Unit";"Mutalisk";"Larva";236;2
"Building";"SpineCrawler";NA;234;0
"Building";"CreepTumor";NA;244;0
"Unit";"Mutalisk";"Larva";236;2
"Unit";"Mutalisk";"Larva";236;2
"Unit";"Mutalisk";"Larva";236;2
"Unit";"Mutalisk";"Larva";236;2
"Unit";"Mutalisk";"Larva";236;2
"Building";"SpineCrawler";NA;236;0
"Building";"Hatchery";NA;210;0
"Building";"SpineCrawler";NA;236;0
"Unit";"Queen";"Hatchery";236;2
"Unit";"Mutalisk";"Larva";244;2
"Unit";"Mutalisk";"Larva";244;2
"Unit";"Mutalisk";"Larva";244;2
"Unit";"Mutalisk";"Larva";244;2
"Unit";"Mutalisk";"Larva";244;2
"Unit";"Mutalisk";"Larva";244;2
"Unit";"Zergling";"Larva";263;1
"Unit";"Zergling";"Larva";263;1
"Unit";"Zergling";"Larva";263;1
"Unit";"Zergling";"Larva";263;1
"Unit";"Zergling";"Larva";263;1
"Unit";"Zergling";"Larva";263;1
"Unit";"Zergling";"Larva";263;1
"Unit";"Zergling";"Larva";263;1
"Unit";"Zergling";"Larva";263;1
"Unit";"Zergling";"Larva";263;1
"Unit";"Zergling";"Larva";263;1
"Unit";"Zergling";"Larva";263;1
"Unit";"Zergling";"Larva";263;1
"Unit";"Zergling";"Larva";263;1
"Unit";"Mutalisk";"Larva";279;2
"Unit";"Mutalisk";"Larva";279;2
"Unit";"Mutalisk";"Larva";279;2
"Unit";"Mutalisk";"Larva";279;2
"Unit";"Mutalisk";"Larva";279;2
"Unit";"Mutalisk";"Larva";279;2
"Building";"CreepTumor";NA;313;0
"Building";"CreepTumor";NA;313;0
"Unit";"Zergling";"Larva";309;1
"Unit";"Zergling";"Larva";309;1
"Unit";"Zergling";"Larva";313;1
"Unit";"Zergling";"Larva";313;1
"Unit";"Zergling";"Larva";313;1
"Unit";"Zergling";"Larva";313;1
"Unit";"Zergling";"Larva";313;1
"Unit";"Zergling";"Larva";313;1
"Unit";"Zergling";"Larva";313;1
"Unit";"Zergling";"Larva";313;1
"Unit";"Mutalisk";"Larva";301;2
"Unit";"Mutalisk";"Larva";301;2
"Unit";"Mutalisk";"Larva";301;2
"Unit";"Mutalisk";"Larva";301;2
"Unit";"Mutalisk";"Larva";301;2
"Unit";"Zergling";"Larva";333;1
"Unit";"Zergling";"Larva";333;1
"Building";"CreepTumor";NA;333;0
"Unit";"Zergling";"Larva";333;1
"Unit";"Zergling";"Larva";333;1
"Unit";"Zergling";"Larva";333;1
"Unit";"Zergling";"Larva";333;1
"Unit";"Zergling";"Larva";333;1
"Unit";"Zergling";"Larva";333;1
"Unit";"Zergling";"Larva";333;1
"Unit";"Zergling";"Larva";333;1
"Unit";"Zergling";"Larva";333;1
"Unit";"Zergling";"Larva";333;1
"Unit";"Zergling";"Larva";333;1
"Unit";"Zergling";"Larva";333;1
"Unit";"Zergling";"Larva";333;1
"Unit";"Zergling";"Larva";333;1
"Unit";"Zergling";"Larva";333;1
"Unit";"Zergling";"Larva";333;1
"Unit";"Zergling";"Larva";333;1
"Unit";"Zergling";"Larva";333;1
"Unit";"Zergling";"Larva";333;1
"Unit";"Zergling";"Larva";333;1
"Unit";"Zergling";"Larva";333;1
"Unit";"Zergling";"Larva";333;1
"Unit";"Zergling";"Larva";333;1
"Unit";"Zergling";"Larva";333;1
"Building";"CreepTumor";NA;333;0
"Building";"CreepTumor";NA;333;0
"Unit";"Zergling";"Larva";333;1
"Unit";"Zergling";"Larva";333;1
"Unit";"Zergling";"Larva";333;1
"Unit";"Zergling";"Larva";333;1
"Unit";"Zergling";"Larva";333;1
"Unit";"Zergling";"Larva";333;1
"Unit";"Zergling";"Larva";333;1
"Unit";"Zergling";"Larva";333;1
"Unit";"Zergling";"Larva";333;1
"Unit";"Zergling";"Larva";333;1
"Unit";"Zergling";"Larva";333;1
"Unit";"Zergling";"Larva";333;1
"Building";"SporeCrawler";NA;333;0
"Building";"CreepTumor";NA;333;0
"Building";"CreepTumor";NA;333;0
"Building";"CreepTumor";NA;333;0
"Building";"SporeCrawler";NA;333;0
"Unit";"Baneling";"Zergling";333;0
"Unit";"Baneling";"Zergling";333;0
"Unit";"Baneling";"Zergling";333;0
"Unit";"Baneling";"Zergling";333;0
"Unit";"Baneling";"Zergling";333;0
"Unit";"Baneling";"Zergling";333;0
"Unit";"Baneling";"Zergling";333;0
"Unit";"Baneling";"Zergling";333;0
"Unit";"Baneling";"Zergling";333;0
"Unit";"Baneling";"Zergling";333;0
"Unit";"Baneling";"Zergling";333;0
"Unit";"Baneling";"Zergling";333;0
"Unit";"Baneling";"Zergling";333;0
"Unit";"Baneling";"Zergling";333;0
"Unit";"Baneling";"Zergling";333;0
"Unit";"Overlord";"Larva";359;0
"Unit";"Overlord";"Larva";359;0
"Unit";"Overlord";"Larva";359;0
"Unit";"Overlord";"Larva";359;0
"Building";"Hatchery";NA;313;0
"Unit";"Overlord";"Larva";371;0
"Building";"CreepTumor";NA;371;0
"Building";"CreepTumor";NA;371;0
"Building";"CreepTumor";NA;371;0
"Building";"CreepTumorQueen";NA;371;0
"Building";"CreepTumor";NA;371;0
"Building";"CreepTumorQueen";NA;371;0
"Building";"CreepTumor";NA;371;0
"Building";"CreepTumorQueen";NA;371;0
"Building";"CreepTumorQueen";NA;371;0
"Building";"CreepTumor";NA;371;0
"Building";"CreepTumor";NA;371;0
"Building";"UltraliskCavern";NA;371;0
"Building";"CreepTumor";NA;371;0
"Building";"CreepTumorQueen";NA;371;0
"Building";"CreepTumor";NA;371;0
"Building";"CreepTumor";NA;371;0
"Building";"Extractor";NA;371;0
"Building";"Extractor";NA;371;0
"Unit";"Queen";"Hatchery";371;2
"Unit";"Mutalisk";"Larva";371;2
"Unit";"Mutalisk";"Larva";371;2
"Unit";"Mutalisk";"Larva";371;2
"Unit";"Mutalisk";"Larva";371;2
"Unit";"Mutalisk";"Larva";371;2
"Unit";"Mutalisk";"Larva";371;2
"Unit";"Mutalisk";"Larva";371;2
"Unit";"Mutalisk";"Larva";371;2
"Unit";"Mutalisk";"Larva";371;2
"Unit";"Mutalisk";"Larva";371;2
"Unit";"Mutalisk";"Larva";371;2
"Unit";"Mutalisk";"Larva";371;2
"Unit";"Zergling";"Larva";371;1
"Unit";"Zergling";"Larva";371;1
"Unit";"Zergling";"Larva";371;1
"Unit";"Zergling";"Larva";371;1
"Unit";"Zergling";"Larva";371;1
"Unit";"Zergling";"Larva";371;1
"Unit";"Zergling";"Larva";371;1
"Unit";"Zergling";"Larva";371;1
"Unit";"Zergling";"Larva";371;1
"Unit";"Zergling";"Larva";371;1
"Unit";"Zergling";"Larva";371;1
"Unit";"Zergling";"Larva";371;1
"Unit";"Zergling";"Larva";371;1
"Unit";"Zergling";"Larva";371;1
"Unit";"Zergling";"Larva";371;1
"Unit";"Zergling";"Larva";371;1
"Unit";"Zergling";"Larva";371;1
"Unit";"Zergling";"Larva";371;1
"Unit";"Zergling";"Larva";371;1
"Unit";"Zergling";"Larva";371;1
"Unit";"Zergling";"Larva";371;1
"Unit";"Zergling";"Larva";371;1
"Unit";"Zergling";"Larva";371;1
"Unit";"Zergling";"Larva";371;1
"Unit";"Zergling";"Larva";371;1
"Unit";"Zergling";"Larva";371;1
"Unit";"Zergling";"Larva";371;1
"Unit";"Zergling";"Larva";371;1
"Unit";"Zergling";"Larva";371;1
"Unit";"Zergling";"Larva";371;1
"Unit";"Zergling";"Larva";371;1
"Unit";"Zergling";"Larva";371;1
"Unit";"Zergling";"Larva";371;1
"Unit";"Zergling";"Larva";371;1
"Unit";"Zergling";"Larva";371;1
"Unit";"Zergling";"Larva";371;1
"Unit";"Zergling";"Larva";371;1
"Unit";"Zergling";"Larva";371;1
"Unit";"Zergling";"Larva";371;1
"Unit";"Zergling";"Larva";371;1
"Unit";"Zergling";"Larva";371;1
"Unit";"Zergling";"Larva";371;1
"Unit";"Zergling";"Larva";371;1
"Unit";"Zergling";"Larva";371;1
"Unit";"Zergling";"Larva";371;1
"Unit";"Zergling";"Larva";371;1
"Unit";"Zergling";"Larva";371;1
"Unit";"Zergling";"Larva";371;1
"Unit";"Zergling";"Larva";371;1
"Unit";"Zergling";"Larva";371;1
"Unit";"Zergling";"Larva";371;1
"Unit";"Zergling";"Larva";371;1
"Building";"Hatchery";NA;371;0
"Unit";"Zergling";"Larva";443;1
"Unit";"Zergling";"Larva";443;1
"Unit";"Zergling";"Larva";449;1
"Unit";"Zergling";"Larva";449;1
"Unit";"Zergling";"Larva";449;1
"Unit";"Zergling";"Larva";449;1
"Unit";"Zergling";"Larva";449;1
"Unit";"Zergling";"Larva";449;1
"Unit";"Zergling";"Larva";449;1
"Unit";"Zergling";"Larva";449;1
"Unit";"Zergling";"Larva";449;1
"Unit";"Zergling";"Larva";449;1
"Unit";"Zergling";"Larva";449;1
"Unit";"Zergling";"Larva";449;1
"Unit";"Zergling";"Larva";449;1
"Unit";"Zergling";"Larva";449;1
"Building";"CreepTumor";NA;449;0
"Unit";"Baneling";"Zergling";449;0
"Unit";"Baneling";"Zergling";449;0
"Unit";"Baneling";"Zergling";449;0
"Unit";"Baneling";"Zergling";449;0
"Unit";"Baneling";"Zergling";449;0
"Unit";"Baneling";"Zergling";449;0
"Unit";"Baneling";"Zergling";449;0
"Unit";"Baneling";"Zergling";449;0
"Unit";"Baneling";"Zergling";449;0
"Unit";"Baneling";"Zergling";449;0
"Unit";"Baneling";"Zergling";449;0
"Unit";"Baneling";"Zergling";449;0
"Unit";"Baneling";"Zergling";449;0
"Building";"CreepTumorQueen";NA;465;0
"Unit";"Zergling";"Larva";465;1
"Unit";"Zergling";"Larva";465;1
"Unit";"Zergling";"Larva";465;1
"Unit";"Zergling";"Larva";465;1
"Unit";"Zergling";"Larva";465;1
"Unit";"Zergling";"Larva";465;1
"Unit";"Zergling";"Larva";465;1
"Unit";"Zergling";"Larva";465;1
"Building";"CreepTumorQueen";NA;465;0
"Unit";"Zergling";"Larva";465;1
"Unit";"Zergling";"Larva";465;1
"Unit";"Zergling";"Larva";465;1
"Unit";"Zergling";"Larva";465;1
"Unit";"Zergling";"Larva";465;1
"Unit";"Zergling";"Larva";465;1
"Unit";"Zergling";"Larva";465;1
"Unit";"Zergling";"Larva";465;1
"Unit";"Zergling";"Larva";465;1
"Unit";"Zergling";"Larva";465;1
"Building";"CreepTumor";NA;465;0
"Building";"SpineCrawler";NA;451;0
"Upgrade";"ZergMeleeWeaponsLevel3";"EvolutionChamber";371;0
"Unit";"Mutalisk";"Larva";483;2
"Unit";"Mutalisk";"Larva";483;2
"Unit";"Mutalisk";"Larva";483;2
"Unit";"Mutalisk";"Larva";483;2
"Unit";"Mutalisk";"Larva";483;2
"Unit";"Mutalisk";"Larva";483;2
"Unit";"Mutalisk";"Larva";483;2
"Unit";"Zergling";"Larva";483;1
"Unit";"Zergling";"Larva";483;1
"Unit";"Zergling";"Larva";485;1
"Unit";"Zergling";"Larva";485;1
"Unit";"Zergling";"Larva";485;1
"Unit";"Zergling";"Larva";485;1
"Unit";"Zergling";"Larva";485;1
"Unit";"Zergling";"Larva";485;1
"Unit";"Zergling";"Larva";485;1
"Unit";"Zergling";"Larva";485;1
"Unit";"Zergling";"Larva";485;1
"Unit";"Zergling";"Larva";485;1
"Unit";"Zergling";"Larva";485;1
"Unit";"Zergling";"Larva";485;1
"Unit";"Zergling";"Larva";485;1
"Unit";"Zergling";"Larva";485;1
"Unit";"Zergling";"Larva";485;1
"Unit";"Zergling";"Larva";485;1
"Unit";"Zergling";"Larva";485;1
"Unit";"Zergling";"Larva";485;1
"Unit";"Zergling";"Larva";485;1
"Unit";"Zergling";"Larva";485;1
"Unit";"Zergling";"Larva";487;1
"Unit";"Zergling";"Larva";487;1
"Unit";"Zergling";"Larva";487;1
"Unit";"Zergling";"Larva";487;1
"Unit";"Zergling";"Larva";491;1
"Unit";"Zergling";"Larva";491;1
"Unit";"Zergling";"Larva";491;1
"Unit";"Zergling";"Larva";491;1
"Unit";"Zergling";"Larva";497;1
"Unit";"Zergling";"Larva";497;1
"Unit";"Zergling";"Larva";497;1
"Unit";"Zergling";"Larva";497;1
"Unit";"Zergling";"Larva";497;1
"Unit";"Zergling";"Larva";497;1
"Unit";"Zergling";"Larva";497;1
"Unit";"Zergling";"Larva";497;1
"Building";"Hatchery";NA;465;0
"Unit";"Zergling";"Larva";497;1
"Unit";"Zergling";"Larva";497;1
"Unit";"Zergling";"Larva";497;1
"Unit";"Zergling";"Larva";497;1
"Unit";"Zergling";"Larva";497;1
"Unit";"Zergling";"Larva";497;1
"Unit";"Zergling";"Larva";497;1
"Unit";"Zergling";"Larva";497;1
"Unit";"Zergling";"Larva";497;1
"Unit";"Zergling";"Larva";497;1
"Unit";"Zergling";"Larva";527;1
"Unit";"Zergling";"Larva";527;1
"Unit";"Zergling";"Larva";527;1
"Unit";"Zergling";"Larva";527;1
"Unit";"Zergling";"Larva";527;1
"Unit";"Zergling";"Larva";527;1
"Unit";"Zergling";"Larva";527;1
"Unit";"Zergling";"Larva";527;1
"Unit";"Zergling";"Larva";527;1
"Unit";"Zergling";"Larva";527;1
"Unit";"Zergling";"Larva";527;1
"Unit";"Zergling";"Larva";527;1
"Unit";"Zergling";"Larva";545;1
"Unit";"Zergling";"Larva";545;1
"Unit";"Zergling";"Larva";545;1
"Unit";"Zergling";"Larva";545;1
"Unit";"Zergling";"Larva";545;1
"Unit";"Zergling";"Larva";545;1
"Unit";"Zergling";"Larva";545;1
"Unit";"Zergling";"Larva";545;1
"Unit";"Zergling";"Larva";545;1
"Unit";"Zergling";"Larva";545;1
"Unit";"Zergling";"Larva";545;1
"Unit";"Zergling";"Larva";545;1
"Unit";"Zergling";"Larva";545;1
"Unit";"Zergling";"Larva";545;1
"Unit";"Ultralisk";"Larva";527;6
"Unit";"Zergling";"Larva";557;1
"Unit";"Zergling";"Larva";557;1
"Unit";"Zergling";"Larva";557;1
"Unit";"Zergling";"Larva";557;1
"Unit";"Zergling";"Larva";557;1
"Unit";"Zergling";"Larva";557;1
"Unit";"Zergling";"Larva";557;1
"Unit";"Zergling";"Larva";557;1
"Unit";"Zergling";"Larva";557;1
"Unit";"Zergling";"Larva";557;1
"Unit";"Zergling";"Larva";557;1
"Unit";"Zergling";"Larva";557;1
"Unit";"Zergling";"Larva";557;1
"Unit";"Zergling";"Larva";557;1
"Unit";"Zergling";"Larva";557;1
"Unit";"Zergling";"Larva";557;1
"Unit";"Baneling";"Zergling";571;0
"Unit";"Baneling";"Zergling";571;0
"Unit";"Baneling";"Zergling";571;0
"Unit";"Baneling";"Zergling";571;0
"Unit";"Baneling";"Zergling";571;0
"Unit";"Baneling";"Zergling";571;0
"Unit";"Baneling";"Zergling";571;0
"Unit";"Baneling";"Zergling";571;0
"Unit";"Baneling";"Zergling";571;0
"Unit";"Baneling";"Zergling";571;0
"Unit";"Baneling";"Zergling";571;0
"Unit";"Baneling";"Zergling";571;0
"Unit";"Baneling";"Zergling";571;0
"Unit";"Baneling";"Zergling";571;0
"Unit";"Baneling";"Zergling";571;0
"Building";"CreepTumor";NA;577;0
"Building";"CreepTumor";NA;577;0
"Building";"CreepTumor";NA;577;0
"Building";"CreepTumor";NA;577;0
"Building";"CreepTumor";NA;577;0
"Building";"CreepTumor";NA;577;0
"Building";"CreepTumor";NA;577;0
"Building";"CreepTumorQueen";NA;593;0
"Building";"CreepTumor";NA;589;0
"Building";"CreepTumor";NA;593;0
"Building";"CreepTumorQueen";NA;593;0
"Building";"CreepTumorQueen";NA;593;0
"Unit";"Zergling";"Larva";593;1
"Unit";"Zergling";"Larva";593;1
"Unit";"Zergling";"Larva";593;1
"Unit";"Zergling";"Larva";593;1
"Unit";"Zergling";"Larva";593;1
"Unit";"Zergling";"Larva";593;1
"Unit";"Zergling";"Larva";593;1
"Unit";"Zergling";"Larva";593;1
"Unit";"Zergling";"Larva";593;1
"Unit";"Zergling";"Larva";593;1
"Unit";"Zergling";"Larva";593;1
"Unit";"Zergling";"Larva";593;1
"Unit";"Zergling";"Larva";593;1
"Unit";"Zergling";"Larva";593;1
"Unit";"Zergling";"Larva";593;1
"Unit";"Zergling";"Larva";593;1
"Unit";"Zergling";"Larva";593;1
"Unit";"Zergling";"Larva";593;1
"Unit";"Zergling";"Larva";593;1
"Unit";"Zergling";"Larva";593;1
"Unit";"Zergling";"Larva";593;1
"Unit";"Zergling";"Larva";593;1
"Building";"CreepTumor";NA;621;0
"Building";"CreepTumor";NA;621;0
"Building";"CreepTumor";NA;621;0
"Building";"CreepTumor";NA;621;0
"Building";"CreepTumor";NA;621;0
"Unit";"Zergling";"Larva";627;1
"Unit";"Zergling";"Larva";627;1
"Unit";"Zergling";"Larva";627;1
"Unit";"Zergling";"Larva";627;1
"Unit";"Zergling";"Larva";627;1
"Unit";"Zergling";"Larva";627;1
"Unit";"Zergling";"Larva";627;1
"Unit";"Zergling";"Larva";627;1
"Unit";"Zergling";"Larva";627;1
"Unit";"Zergling";"Larva";627;1
"Unit";"Zergling";"Larva";627;1
"Unit";"Zergling";"Larva";627;1
"Unit";"Zergling";"Larva";627;1
"Unit";"Zergling";"Larva";627;1
"Unit";"Zergling";"Larva";627;1
"Unit";"Zergling";"Larva";627;1
"Unit";"Zergling";"Larva";627;1
"Unit";"Zergling";"Larva";627;1
"Unit";"Zergling";"Larva";627;1
"Unit";"Zergling";"Larva";627;1
"Unit";"Zergling";"Larva";627;1
"Unit";"Zergling";"Larva";627;1
"Unit";"Zergling";"Larva";627;1
"Unit";"Zergling";"Larva";627;1
"Unit";"Zergling";"Larva";627;1
"Unit";"Zergling";"Larva";627;1
"Unit";"Zergling";"Larva";627;1
"Unit";"Zergling";"Larva";627;1
"Unit";"Zergling";"Larva";627;1
"Unit";"Zergling";"Larva";627;1
"Unit";"Zergling";"Larva";627;1
"Unit";"Zergling";"Larva";627;1
"Unit";"Zergling";"Larva";627;1
"Unit";"Zergling";"Larva";627;1
"Unit";"Zergling";"Larva";627;1
"Unit";"Zergling";"Larva";627;1
"Unit";"Zergling";"Larva";627;1
"Unit";"Zergling";"Larva";627;1
"Unit";"Zergling";"Larva";627;1
"Unit";"Zergling";"Larva";627;1
"Unit";"Zergling";"Larva";627;1
"Unit";"Zergling";"Larva";627;1
"Unit";"Zergling";"Larva";627;1
"Unit";"Zergling";"Larva";627;1
"Unit";"Zergling";"Larva";627;1
"Unit";"Zergling";"Larva";627;1
"Upgrade";"ZergGroundArmorsLevel3";"EvolutionChamber";545;0
"Unit";"Baneling";"Zergling";627;0
"Unit";"Baneling";"Zergling";627;0
"Unit";"Baneling";"Zergling";627;0
"Unit";"Baneling";"Zergling";627;0
"Unit";"Baneling";"Zergling";627;0
"Unit";"Baneling";"Zergling";627;0
"Unit";"Baneling";"Zergling";645;0
"Unit";"Baneling";"Zergling";645;0
"Unit";"Baneling";"Zergling";645;0
"Unit";"Baneling";"Zergling";645;0
"Unit";"Baneling";"Zergling";645;0
"Unit";"Baneling";"Zergling";645;0
"Unit";"Baneling";"Zergling";645;0
"Upgrade";"ChitinousPlating";"UltraliskCavern";621;0
"Unit";"Zergling";"Larva";673;1
"Unit";"Zergling";"Larva";673;1
"Unit";"Zergling";"Larva";673;1
"Unit";"Zergling";"Larva";673;1
"Unit";"Zergling";"Larva";673;1
"Unit";"Zergling";"Larva";673;1
"Unit";"Zergling";"Larva";673;1
"Unit";"Zergling";"Larva";673;1
"Unit";"Zergling";"Larva";673;1
"Unit";"Zergling";"Larva";673;1
"Unit";"Zergling";"Larva";673;1
"Unit";"Zergling";"Larva";673;1
"Unit";"Zergling";"Larva";673;1
"Unit";"Zergling";"Larva";673;1
"Unit";"Zergling";"Larva";673;1
"Unit";"Zergling";"Larva";673;1
"Unit";"Zergling";"Larva";673;1
"Unit";"Zergling";"Larva";673;1
"Unit";"Zergling";"Larva";673;1
"Unit";"Zergling";"Larva";673;1
"Unit";"Zergling";"Larva";673;1
"Unit";"Zergling";"Larva";673;1
"Unit";"Zergling";"Larva";673;1
"Unit";"Zergling";"Larva";673;1
"Unit";"Zergling";"Larva";673;1
"Unit";"Zergling";"Larva";673;1
"Unit";"Zergling";"Larva";673;1
"Unit";"Zergling";"Larva";673;1
"Unit";"Zergling";"Larva";673;1
"Unit";"Zergling";"Larva";673;1
"Unit";"Zergling";"Larva";673;1
"Unit";"Zergling";"Larva";673;1
"Unit";"Zergling";"Larva";673;1
"Unit";"Zergling";"Larva";673;1
"Unit";"Zergling";"Larva";673;1
"Unit";"Zergling";"Larva";673;1
"Unit";"Zergling";"Larva";673;1
"Unit";"Zergling";"Larva";673;1
"Unit";"Zergling";"Larva";673;1
"Unit";"Zergling";"Larva";673;1
"Unit";"Zergling";"Larva";673;1
"Unit";"Zergling";"Larva";673;1
"Unit";"Zergling";"Larva";673;1
"Unit";"Zergling";"Larva";673;1
"Unit";"Zergling";"Larva";673;1
"Unit";"Zergling";"Larva";673;1
"Unit";"Zergling";"Larva";699;1
"Unit";"Zergling";"Larva";699;1
"Unit";"Zergling";"Larva";701;1
"Unit";"Zergling";"Larva";701;1
"Unit";"Zergling";"Larva";701;1
"Unit";"Zergling";"Larva";701;1
"Unit";"Zergling";"Larva";703;1
"Unit";"Zergling";"Larva";703;1
"Unit";"Zergling";"Larva";703;1
"Unit";"Zergling";"Larva";703;1
"Unit";"Zergling";"Larva";707;1
"Unit";"Zergling";"Larva";707;1
"Unit";"Baneling";"Zergling";731;0
"Unit";"Baneling";"Zergling";731;0
"Unit";"Baneling";"Zergling";731;0
"Unit";"Baneling";"Zergling";731;0
"Unit";"Baneling";"Zergling";731;0
"Unit";"Baneling";"Zergling";731;0
"Unit";"Baneling";"Zergling";731;0
"Unit";"Baneling";"Zergling";731;0
"Unit";"Baneling";"Zergling";731;0
"Unit";"Baneling";"Zergling";731;0
"Building";"CreepTumor";NA;731;0
"Unit";"Zergling";"Larva";731;1
"Unit";"Zergling";"Larva";731;1
"Unit";"Zergling";"Larva";731;1
"Unit";"Zergling";"Larva";731;1
"Unit";"Zergling";"Larva";731;1
"Unit";"Zergling";"Larva";731;1
"Unit";"Zergling";"Larva";731;1
"Unit";"Zergling";"Larva";731;1
"Building";"CreepTumorQueen";NA;731;0
"Building";"CreepTumorQueen";NA;731;0
"Unit";"Ultralisk";"Larva";721;6
"Unit";"Ultralisk";"Larva";721;6
"Building";"CreepTumorQueen";NA;739;0
"Building";"CreepTumor";NA;739;0
"Building";"CreepTumorQueen";NA;739;0
"Building";"CreepTumorQueen";NA;751;0
"Unit";"Baneling";"Zergling";751;0
"Unit";"Baneling";"Zergling";751;0
"Unit";"Baneling";"Zergling";751;0
"Unit";"Baneling";"Zergling";751;0
"Unit";"Baneling";"Zergling";751;0
"Unit";"Baneling";"Zergling";751;0
"Unit";"Baneling";"Zergling";751;0
"Unit";"Baneling";"Zergling";751;0
"Unit";"Baneling";"Zergling";751;0
"Unit";"Baneling";"Zergling";751;0
"Unit";"Baneling";"Zergling";751;0
"Unit";"Baneling";"Zergling";751;0
"Unit";"Baneling";"Zergling";751;0
"Unit";"Baneling";"Zergling";751;0
"Unit";"Baneling";"Zergling";751;0
"Unit";"Baneling";"Zergling";751;0
"Unit";"Baneling";"Zergling";751;0
"Unit";"Baneling";"Zergling";751;0
"Unit";"Baneling";"Zergling";751;0
"Unit";"Baneling";"Zergling";751;0
"Unit";"Baneling";"Zergling";751;0
"Unit";"Baneling";"Zergling";751;0
"Building";"CreepTumor";NA;751;0
"Building";"CreepTumor";NA;751;0
"Building";"CreepTumor";NA;751;0
"Building";"CreepTumor";NA;751;0
"Building";"CreepTumor";NA;751;0
"Building";"CreepTumor";NA;751;0
"Building";"CreepTumor";NA;751;0
"Building";"CreepTumor";NA;751;0
"Building";"CreepTumor";NA;751;0
"Building";"CreepTumor";NA;751;0
"Building";"CreepTumor";NA;751;0
"Building";"CreepTumor";NA;751;0
"Building";"CreepTumorQueen";NA;751;0
"Building";"CreepTumor";NA;751;0
"Building";"CreepTumor";NA;751;0
"Building";"CreepTumor";NA;751;0
"Building";"CreepTumor";NA;751;0
"Unit";"Ultralisk";"Larva";751;6
"Unit";"Ultralisk";"Larva";751;6
"Unit";"Ultralisk";"Larva";751;6
"Unit";"Ultralisk";"Larva";751;6
"Unit";"Ultralisk";"Larva";751;6
"Building";"CreepTumorQueen";NA;751;0
"Building";"CreepTumorQueen";NA;751;0
"Building";"CreepTumorQueen";NA;751;0
"Unit";"Ultralisk";"Larva";751;6
"Unit";"Ultralisk";"Larva";751;6
"Unit";"Mutalisk";"Larva";781;2
"Unit";"Mutalisk";"Larva";781;2
"Building";"CreepTumor";NA;793;0
"Building";"CreepTumor";NA;793;0
"Building";"CreepTumor";NA;793;0
"Unit";"Ultralisk";"Larva";763;6
"Unit";"Ultralisk";"Larva";769;6
"Building";"CreepTumor";NA;793;0
"Building";"CreepTumor";NA;793;0
"Unit";"Mutalisk";"Larva";781;2
"Building";"CreepTumor";NA;793;0
"Unit";"Mutalisk";"Larva";781;2
"Unit";"Mutalisk";"Larva";781;2
"Building";"Hatchery";NA;793;0
"Building";"CreepTumor";NA;815;0
"Building";"CreepTumor";NA;815;0
"Building";"CreepTumor";NA;815;0
"Building";"CreepTumor";NA;815;0
"Building";"CreepTumor";NA;815;0
"Building";"BanelingNest";NA;815;0
