"type";"unit_name";"on_building";"total_supply";"supply"
"Unit";"Overlord";"Larva";13;0
"Building";"Extractor";NA;19;0
"Unit";"Overlord";"Larva";21;0
"Building";"SpawningPool";NA;19;0
"Building";"Hatchery";NA;17;0
"Unit";"Zergling";"Larva";22;1
"Unit";"Zergling";"Larva";22;1
"Unit";"Zergling";"Larva";22;1
"Unit";"Zergling";"Larva";22;1
"Unit";"Queen";"Hatchery";22;2
"Unit";"Queen";"Hatchery";22;2
"Unit";"Overlord";"Larva";36;0
"Unit";"Queen";"Hatchery";36;2
"Building";"CreepTumorQueen";NA;41;0
"Building";"EvolutionChamber";NA;39;0
"Unit";"Overlord";"Larva";44;0
"Building";"Hatchery";NA;36;0
"Building";"CreepTumorQueen";NA;49;0
"Building";"CreepTumor";NA;49;0
"Unit";"Queen";"Hatchery";46;2
"Unit";"Overlord";"Larva";49;0
"Building";"CreepTumorQueen";NA;56;0
"Unit";"Zergling";"Larva";61;1
"Unit";"Zergling";"Larva";61;1
"Unit";"Zergling";"Larva";61;1
"Unit";"Zergling";"Larva";61;1
"Unit";"Zergling";"Larva";61;1
"Unit";"Zergling";"Larva";61;1
"Unit";"Zergling";"Larva";61;1
"Unit";"Zergling";"Larva";61;1
"Unit";"Zergling";"Larva";61;1
"Unit";"Zergling";"Larva";61;1
"Unit";"Zergling";"Larva";61;1
"Unit";"Zergling";"Larva";61;1
"Unit";"Zergling";"Larva";61;1
"Unit";"Zergling";"Larva";61;1
"Unit";"Queen";"Hatchery";59;2
"Building";"Extractor";NA;61;0
"Building";"BanelingNest";NA;54;0
"Building";"Extractor";NA;61;0
"Building";"SporeCrawler";NA;61;0
"Building";"CreepTumor";NA;77;0
"Building";"CreepTumor";NA;77;0
"Building";"CreepTumor";NA;77;0
"Building";"SporeCrawler";NA;61;0
"Building";"CreepTumorQueen";NA;80;0
"Building";"CreepTumorQueen";NA;80;0
"Building";"CreepTumorQueen";NA;80;0
"Unit";"Baneling";"Zergling";80;0
"Unit";"Baneling";"Zergling";80;0
"Unit";"Baneling";"Zergling";80;0
"Building";"SporeCrawler";NA;80;0
"Unit";"Overlord";"Larva";80;0
"Unit";"Overlord";"Larva";80;0
"Unit";"Overlord";"Larva";80;0
"Upgrade";"ZergGroundArmorsLevel1";"EvolutionChamber";61;0
"Building";"CreepTumor";NA;80;0
"Building";"CreepTumor";NA;80;0
"Building";"CreepTumor";NA;80;0
"Building";"Extractor";NA;80;0
"Building";"CreepTumor";NA;84;0
"Building";"CreepTumor";NA;84;0
"Building";"CreepTumor";NA;84;0
"Building";"CreepTumorQueen";NA;95;0
"Building";"CreepTumorQueen";NA;95;0
"Unit";"Zergling";"Larva";95;1
"Unit";"Zergling";"Larva";95;1
"Unit";"Zergling";"Larva";95;1
"Unit";"Zergling";"Larva";95;1
"Unit";"Zergling";"Larva";95;1
"Unit";"Zergling";"Larva";95;1
"Unit";"Zergling";"Larva";95;1
"Unit";"Zergling";"Larva";95;1
"Unit";"Zergling";"Larva";95;1
"Unit";"Zergling";"Larva";95;1
"Unit";"Zergling";"Larva";95;1
"Unit";"Zergling";"Larva";95;1
"Building";"CreepTumorQueen";NA;97;0
"Building";"EvolutionChamber";NA;95;0
"Building";"CreepTumor";NA;97;0
"Building";"CreepTumor";NA;97;0
"Unit";"Overlord";"Larva";97;0
"Unit";"Overlord";"Larva";97;0
"Unit";"Overlord";"Larva";97;0
"Unit";"Overlord";"Larva";97;0
"Building";"Extractor";NA;111;0
"Building";"Extractor";NA;111;0
"Building";"CreepTumorQueen";NA;111;0
"Building";"HydraliskDen";NA;111;0
"Building";"CreepTumor";NA;116;0
"Building";"CreepTumor";NA;116;0
"Unit";"Overlord";"Larva";116;0
"Building";"CreepTumor";NA;129;0
"Building";"CreepTumor";NA;129;0
"Building";"CreepTumor";NA;129;0
"Building";"CreepTumor";NA;129;0
"Building";"CreepTumor";NA;129;0
"Building";"CreepTumor";NA;129;0
"Building";"CreepTumor";NA;132;0
"Building";"CreepTumor";NA;135;0
"Unit";"Overlord";"Larva";132;0
"Unit";"Zergling";"Larva";135;1
"Unit";"Zergling";"Larva";135;1
"Building";"CreepTumor";NA;135;0
"Upgrade";"ZergMeleeWeaponsLevel1";"EvolutionChamber";111;0
"Building";"CreepTumor";NA;135;0
"Unit";"Zergling";"Larva";135;1
"Unit";"Zergling";"Larva";135;1
"Unit";"Zergling";"Larva";135;1
"Unit";"Zergling";"Larva";135;1
"Unit";"Zergling";"Larva";135;1
"Unit";"Zergling";"Larva";135;1
"Unit";"Zergling";"Larva";135;1
"Unit";"Zergling";"Larva";135;1
"Unit";"Zergling";"Larva";135;1
"Unit";"Zergling";"Larva";135;1
"Unit";"Zergling";"Larva";135;1
"Unit";"Zergling";"Larva";135;1
"Unit";"Zergling";"Larva";135;1
"Unit";"Zergling";"Larva";135;1
"Unit";"Zergling";"Larva";135;1
"Unit";"Zergling";"Larva";135;1
"Building";"CreepTumor";NA;135;0
"Building";"CreepTumor";NA;135;0
"Building";"Hatchery";NA;111;0
"Building";"CreepTumor";NA;135;0
"Building";"CreepTumorQueen";NA;135;0
"Building";"CreepTumorQueen";NA;149;0
"Unit";"Overlord";"Larva";135;0
"Unit";"Overlord";"Larva";135;0
"Building";"CreepTumorQueen";NA;153;0
"Unit";"Hydralisk";"Larva";135;2
"Unit";"Hydralisk";"Larva";135;2
"Unit";"Baneling";"Zergling";153;0
"Unit";"Baneling";"Zergling";153;0
"Unit";"Baneling";"Zergling";153;0
"Unit";"Baneling";"Zergling";153;0
"Unit";"Baneling";"Zergling";153;0
"Unit";"Baneling";"Zergling";153;0
"Unit";"Hydralisk";"Larva";153;2
"Unit";"Hydralisk";"Larva";153;2
"Unit";"Hydralisk";"Larva";153;2
"Unit";"Zergling";"Larva";153;1
"Unit";"Zergling";"Larva";153;1
"Unit";"Zergling";"Larva";153;1
"Unit";"Zergling";"Larva";153;1
"Unit";"Zergling";"Larva";153;1
"Unit";"Zergling";"Larva";153;1
"Unit";"Baneling";"Zergling";153;0
"Unit";"Baneling";"Zergling";153;0
"Unit";"Baneling";"Zergling";153;0
"Unit";"Baneling";"Zergling";153;0
"Unit";"Baneling";"Zergling";153;0
"Unit";"Baneling";"Zergling";153;0
"Unit";"Hydralisk";"Larva";153;2
"Unit";"Hydralisk";"Larva";153;2
"Unit";"Hydralisk";"Larva";153;2
"Unit";"Zergling";"Larva";157;1
"Unit";"Zergling";"Larva";157;1
"Unit";"Zergling";"Larva";157;1
"Unit";"Zergling";"Larva";157;1
"Unit";"Zergling";"Larva";157;1
"Unit";"Zergling";"Larva";157;1
"Unit";"Zergling";"Larva";157;1
"Unit";"Zergling";"Larva";157;1
"Upgrade";"EvolveGroovedSpines";"HydraliskDen";135;0
"Unit";"Zergling";"Larva";183;1
"Unit";"Zergling";"Larva";183;1
"Unit";"Zergling";"Larva";183;1
"Unit";"Zergling";"Larva";183;1
"Unit";"Zergling";"Larva";183;1
"Unit";"Zergling";"Larva";183;1
"Unit";"Zergling";"Larva";183;1
"Unit";"Zergling";"Larva";183;1
"Unit";"Zergling";"Larva";183;1
"Unit";"Zergling";"Larva";183;1
"Unit";"Zergling";"Larva";183;1
"Unit";"Zergling";"Larva";183;1
"Unit";"Zergling";"Larva";183;1
"Unit";"Zergling";"Larva";183;1
"Unit";"Zergling";"Larva";183;1
"Unit";"Zergling";"Larva";183;1
"Unit";"Zergling";"Larva";183;1
"Unit";"Zergling";"Larva";183;1
"Unit";"Zergling";"Larva";183;1
"Unit";"Zergling";"Larva";183;1
"Unit";"Zergling";"Larva";183;1
"Unit";"Zergling";"Larva";183;1
"Unit";"Zergling";"Larva";183;1
"Unit";"Zergling";"Larva";183;1
"Unit";"Zergling";"Larva";183;1
"Unit";"Zergling";"Larva";183;1
"Upgrade";"ZergMissileWeaponsLevel1";"EvolutionChamber";135;0
"Unit";"Zergling";"Larva";209;1
"Unit";"Zergling";"Larva";209;1
"Unit";"Hydralisk";"Larva";183;2
"Unit";"Hydralisk";"Larva";183;2
"Unit";"Hydralisk";"Larva";183;2
"Unit";"Hydralisk";"Larva";183;2
"Unit";"Hydralisk";"Larva";183;2
"Building";"InfestationPit";NA;183;0
"Unit";"Hydralisk";"Larva";209;2
"Unit";"Hydralisk";"Larva";209;2
"Unit";"Hydralisk";"Larva";209;2
"Unit";"Hydralisk";"Larva";209;2
"Unit";"Hydralisk";"Larva";209;2
"Unit";"Hydralisk";"Larva";209;2
"Unit";"Hydralisk";"Larva";209;2
"Unit";"Hydralisk";"Larva";209;2
"Unit";"Hydralisk";"Larva";209;2
"Unit";"Hydralisk";"Larva";209;2
"Unit";"Hydralisk";"Larva";209;2
"Unit";"Hydralisk";"Larva";209;2
"Unit";"Hydralisk";"Larva";209;2
"Unit";"Overlord";"Larva";237;0
"Unit";"Overlord";"Larva";237;0
"Upgrade";"EvolveMuscularAugments";"HydraliskDen";209;0
"Unit";"Overlord";"Larva";247;0
"Unit";"Overlord";"Larva";247;0
"Unit";"Zergling";"Larva";247;1
"Unit";"Zergling";"Larva";247;1
"Unit";"Zergling";"Larva";247;1
"Unit";"Zergling";"Larva";247;1
"Unit";"Zergling";"Larva";247;1
"Unit";"Zergling";"Larva";247;1
"Unit";"Zergling";"Larva";247;1
"Unit";"Zergling";"Larva";247;1
"Unit";"Zergling";"Larva";247;1
"Unit";"Zergling";"Larva";247;1
"Unit";"Zergling";"Larva";247;1
"Unit";"Zergling";"Larva";247;1
"Unit";"Zergling";"Larva";247;1
"Unit";"Zergling";"Larva";247;1
"Unit";"Zergling";"Larva";247;1
"Unit";"Zergling";"Larva";247;1
"Unit";"Zergling";"Larva";247;1
"Unit";"Zergling";"Larva";247;1
"Unit";"Zergling";"Larva";247;1
"Unit";"Zergling";"Larva";247;1
"Unit";"Zergling";"Larva";247;1
"Unit";"Zergling";"Larva";247;1
"Unit";"Zergling";"Larva";247;1
"Unit";"Zergling";"Larva";247;1
"Building";"CreepTumor";NA;247;0
"Unit";"Zergling";"Larva";247;1
"Unit";"Zergling";"Larva";247;1
"Building";"CreepTumor";NA;247;0
"Building";"CreepTumor";NA;247;0
"Building";"CreepTumor";NA;247;0
"Building";"CreepTumor";NA;247;0
"Unit";"Overlord";"Larva";247;0
"Building";"CreepTumor";NA;247;0
"Building";"CreepTumor";NA;247;0
"Unit";"Overlord";"Larva";247;0
"Upgrade";"ZergMeleeWeaponsLevel2";"EvolutionChamber";183;0
"Unit";"Zergling";"Larva";271;1
"Unit";"Zergling";"Larva";271;1
"Unit";"Zergling";"Larva";271;1
"Unit";"Zergling";"Larva";271;1
"Unit";"Zergling";"Larva";271;1
"Unit";"Zergling";"Larva";271;1
"Unit";"Zergling";"Larva";271;1
"Unit";"Zergling";"Larva";271;1
"Unit";"Baneling";"Zergling";273;0
"Unit";"Baneling";"Zergling";273;0
"Unit";"Baneling";"Zergling";273;0
"Unit";"Baneling";"Zergling";273;0
"Unit";"Baneling";"Zergling";273;0
"Unit";"Baneling";"Zergling";273;0
"Unit";"Baneling";"Zergling";273;0
"Unit";"Baneling";"Zergling";273;0
"Unit";"Baneling";"Zergling";273;0
"Unit";"Baneling";"Zergling";273;0
"Unit";"Zergling";"Larva";273;1
"Unit";"Zergling";"Larva";273;1
"Unit";"Zergling";"Larva";273;1
"Unit";"Zergling";"Larva";273;1
"Unit";"Zergling";"Larva";273;1
"Unit";"Zergling";"Larva";273;1
"Unit";"Zergling";"Larva";273;1
"Unit";"Zergling";"Larva";273;1
"Unit";"Zergling";"Larva";273;1
"Unit";"Zergling";"Larva";273;1
"Unit";"Zergling";"Larva";273;1
"Unit";"Zergling";"Larva";273;1
"Unit";"Zergling";"Larva";273;1
"Unit";"Zergling";"Larva";273;1
"Unit";"Zergling";"Larva";275;1
"Unit";"Zergling";"Larva";275;1
"Unit";"Zergling";"Larva";275;1
"Unit";"Zergling";"Larva";275;1
"Unit";"Zergling";"Larva";275;1
"Unit";"Zergling";"Larva";275;1
"Unit";"Zergling";"Larva";275;1
"Unit";"Zergling";"Larva";275;1
"Unit";"Zergling";"Larva";275;1
"Unit";"Zergling";"Larva";275;1
"Unit";"Zergling";"Larva";275;1
"Unit";"Zergling";"Larva";275;1
"Building";"Hatchery";NA;247;0
"Unit";"Zergling";"Larva";293;1
"Unit";"Zergling";"Larva";293;1
"Unit";"Zergling";"Larva";293;1
"Unit";"Zergling";"Larva";293;1
"Unit";"Zergling";"Larva";293;1
"Unit";"Zergling";"Larva";293;1
"Unit";"Baneling";"Zergling";307;0
"Unit";"Baneling";"Zergling";307;0
"Unit";"Baneling";"Zergling";307;0
"Unit";"Baneling";"Zergling";307;0
"Unit";"Baneling";"Zergling";307;0
"Unit";"Baneling";"Zergling";307;0
"Unit";"Baneling";"Zergling";307;0
"Unit";"Baneling";"Zergling";307;0
"Unit";"Baneling";"Zergling";307;0
"Unit";"Baneling";"Zergling";307;0
"Unit";"Baneling";"Zergling";307;0
"Unit";"Baneling";"Zergling";307;0
"Unit";"Baneling";"Zergling";307;0
"Unit";"Hydralisk";"Larva";307;2
"Unit";"Zergling";"Larva";307;1
"Unit";"Zergling";"Larva";307;1
"Unit";"Hydralisk";"Larva";307;2
"Unit";"Hydralisk";"Larva";307;2
"Unit";"Hydralisk";"Larva";307;2
"Unit";"Hydralisk";"Larva";307;2
"Unit";"Zergling";"Larva";307;1
"Unit";"Zergling";"Larva";307;1
"Unit";"Zergling";"Larva";307;1
"Unit";"Zergling";"Larva";307;1
"Unit";"Zergling";"Larva";307;1
"Unit";"Zergling";"Larva";307;1
"Unit";"Zergling";"Larva";307;1
"Unit";"Zergling";"Larva";307;1
"Unit";"Zergling";"Larva";307;1
"Unit";"Zergling";"Larva";307;1
"Unit";"Zergling";"Larva";309;1
"Unit";"Zergling";"Larva";309;1
"Unit";"Zergling";"Larva";313;1
"Unit";"Zergling";"Larva";313;1
"Unit";"Zergling";"Larva";313;1
"Unit";"Zergling";"Larva";313;1
"Upgrade";"ZergGroundArmorsLevel2";"EvolutionChamber";247;0
"Unit";"Zergling";"Larva";341;1
"Unit";"Zergling";"Larva";341;1
"Unit";"Zergling";"Larva";341;1
"Unit";"Zergling";"Larva";341;1
"Unit";"Zergling";"Larva";341;1
"Unit";"Zergling";"Larva";341;1
"Unit";"Zergling";"Larva";341;1
"Unit";"Zergling";"Larva";341;1
"Unit";"Zergling";"Larva";341;1
"Unit";"Zergling";"Larva";341;1
"Unit";"Zergling";"Larva";341;1
"Unit";"Zergling";"Larva";341;1
"Unit";"Zergling";"Larva";341;1
"Unit";"Zergling";"Larva";341;1
"Unit";"Zergling";"Larva";341;1
"Unit";"Zergling";"Larva";341;1
"Unit";"Zergling";"Larva";341;1
"Unit";"Zergling";"Larva";341;1
"Unit";"Zergling";"Larva";341;1
"Unit";"Zergling";"Larva";341;1
"Unit";"Zergling";"Larva";341;1
"Unit";"Zergling";"Larva";341;1
"Unit";"Zergling";"Larva";341;1
"Unit";"Zergling";"Larva";341;1
"Unit";"Zergling";"Larva";341;1
"Unit";"Zergling";"Larva";341;1
"Unit";"Zergling";"Larva";341;1
"Unit";"Zergling";"Larva";341;1
"Unit";"Zergling";"Larva";341;1
"Unit";"Zergling";"Larva";341;1
"Unit";"Zergling";"Larva";341;1
"Unit";"Zergling";"Larva";341;1
"Unit";"Zergling";"Larva";341;1
"Unit";"Zergling";"Larva";341;1
"Building";"CreepTumor";NA;341;0
"Unit";"Zergling";"Larva";341;1
"Unit";"Zergling";"Larva";341;1
"Unit";"Zergling";"Larva";341;1
"Unit";"Zergling";"Larva";341;1
"Building";"CreepTumor";NA;341;0
"Building";"CreepTumor";NA;343;0
"Building";"CreepTumor";NA;347;0
"Building";"CreepTumor";NA;357;0
"Building";"CreepTumor";NA;375;0
"Unit";"Baneling";"Zergling";375;0
"Unit";"Baneling";"Zergling";375;0
"Unit";"Baneling";"Zergling";375;0
"Unit";"Baneling";"Zergling";375;0
"Unit";"Baneling";"Zergling";375;0
"Unit";"Baneling";"Zergling";375;0
"Unit";"Baneling";"Zergling";375;0
"Unit";"Baneling";"Zergling";375;0
"Unit";"Hydralisk";"Larva";341;2
"Unit";"Baneling";"Zergling";375;0
"Unit";"Hydralisk";"Larva";341;2
"Unit";"Hydralisk";"Larva";341;2
"Unit";"Baneling";"Zergling";375;0
"Unit";"Baneling";"Zergling";375;0
"Unit";"Baneling";"Zergling";379;0
"Building";"UltraliskCavern";NA;341;0
"Unit";"Zergling";"Larva";379;1
"Unit";"Zergling";"Larva";379;1
"Unit";"Zergling";"Larva";379;1
"Unit";"Zergling";"Larva";379;1
"Unit";"Zergling";"Larva";379;1
"Unit";"Zergling";"Larva";379;1
"Unit";"Zergling";"Larva";379;1
"Unit";"Zergling";"Larva";379;1
"Unit";"Zergling";"Larva";379;1
"Unit";"Zergling";"Larva";379;1
"Unit";"Zergling";"Larva";379;1
"Unit";"Zergling";"Larva";379;1
"Unit";"Zergling";"Larva";385;1
"Unit";"Zergling";"Larva";385;1
"Unit";"Zergling";"Larva";385;1
"Unit";"Zergling";"Larva";385;1
"Unit";"Zergling";"Larva";385;1
"Unit";"Zergling";"Larva";385;1
"Unit";"Zergling";"Larva";385;1
"Unit";"Zergling";"Larva";385;1
"Unit";"Zergling";"Larva";385;1
"Unit";"Zergling";"Larva";385;1
"Unit";"Zergling";"Larva";385;1
"Unit";"Zergling";"Larva";385;1
"Unit";"Zergling";"Larva";385;1
"Unit";"Zergling";"Larva";385;1
"Unit";"Zergling";"Larva";385;1
"Unit";"Zergling";"Larva";385;1
"Unit";"Zergling";"Larva";413;1
"Unit";"Zergling";"Larva";413;1
"Unit";"Zergling";"Larva";413;1
"Unit";"Zergling";"Larva";413;1
"Unit";"Zergling";"Larva";413;1
"Unit";"Zergling";"Larva";413;1
"Unit";"Zergling";"Larva";413;1
"Unit";"Zergling";"Larva";413;1
"Unit";"Zergling";"Larva";413;1
"Unit";"Zergling";"Larva";413;1
"Unit";"Zergling";"Larva";413;1
"Unit";"Zergling";"Larva";413;1
"Unit";"Zergling";"Larva";413;1
"Unit";"Zergling";"Larva";413;1
"Unit";"Zergling";"Larva";413;1
"Unit";"Zergling";"Larva";413;1
"Unit";"Zergling";"Larva";413;1
"Unit";"Zergling";"Larva";413;1
"Unit";"Zergling";"Larva";413;1
"Unit";"Zergling";"Larva";413;1
"Unit";"Zergling";"Larva";413;1
"Unit";"Zergling";"Larva";413;1
"Unit";"Ultralisk";"Larva";413;6
"Unit";"Ultralisk";"Larva";413;6
"Unit";"Baneling";"Zergling";435;0
"Unit";"Baneling";"Zergling";435;0
"Unit";"Baneling";"Zergling";435;0
"Unit";"Baneling";"Zergling";435;0
"Unit";"Baneling";"Zergling";435;0
"Unit";"Zergling";"Larva";435;1
"Unit";"Zergling";"Larva";435;1
"Unit";"Baneling";"Zergling";435;0
"Unit";"Zergling";"Larva";435;1
"Unit";"Zergling";"Larva";435;1
"Unit";"Zergling";"Larva";435;1
"Unit";"Zergling";"Larva";435;1
"Unit";"Baneling";"Zergling";435;0
"Unit";"Baneling";"Zergling";435;0
"Building";"CreepTumor";NA;435;0
"Unit";"Baneling";"Zergling";435;0
"Unit";"Baneling";"Zergling";435;0
"Building";"CreepTumor";NA;435;0
"Unit";"Baneling";"Zergling";435;0
"Unit";"Ultralisk";"Larva";427;6
"Building";"CreepTumor";NA;453;0
"Unit";"Ultralisk";"Larva";427;6
"Unit";"Ultralisk";"Larva";427;6
"Unit";"Zergling";"Larva";453;1
"Unit";"Zergling";"Larva";453;1
"Unit";"Zergling";"Larva";453;1
"Unit";"Zergling";"Larva";453;1
"Unit";"Zergling";"Larva";453;1
"Unit";"Zergling";"Larva";453;1
"Unit";"Zergling";"Larva";453;1
"Unit";"Zergling";"Larva";453;1
"Unit";"Zergling";"Larva";453;1
"Unit";"Zergling";"Larva";453;1
"Unit";"Zergling";"Larva";453;1
"Unit";"Zergling";"Larva";453;1
"Unit";"Zergling";"Larva";453;1
"Unit";"Zergling";"Larva";453;1
"Unit";"Zergling";"Larva";453;1
"Unit";"Zergling";"Larva";453;1
"Building";"CreepTumor";NA;459;0
"Building";"CreepTumor";NA;471;0
"Upgrade";"ChitinousPlating";"UltraliskCavern";427;0
"Unit";"Overlord";"Larva";453;0
"Unit";"Zergling";"Larva";471;1
"Unit";"Zergling";"Larva";471;1
"Unit";"Zergling";"Larva";471;1
"Unit";"Zergling";"Larva";471;1
"Unit";"Zergling";"Larva";471;1
"Unit";"Zergling";"Larva";471;1
"Unit";"Zergling";"Larva";471;1
"Unit";"Zergling";"Larva";471;1
"Upgrade";"ZergGroundArmorsLevel3";"EvolutionChamber";413;0
"Unit";"Zergling";"Larva";495;1
"Unit";"Zergling";"Larva";495;1
"Unit";"Zergling";"Larva";495;1
"Unit";"Zergling";"Larva";495;1
"Unit";"Zergling";"Larva";495;1
"Unit";"Zergling";"Larva";495;1
"Unit";"Zergling";"Larva";495;1
"Unit";"Zergling";"Larva";495;1
"Unit";"Zergling";"Larva";495;1
"Unit";"Zergling";"Larva";495;1
"Unit";"Zergling";"Larva";495;1
"Unit";"Zergling";"Larva";495;1
"Unit";"Zergling";"Larva";495;1
"Unit";"Zergling";"Larva";495;1
"Unit";"Zergling";"Larva";495;1
"Unit";"Zergling";"Larva";495;1
"Unit";"Zergling";"Larva";495;1
"Unit";"Zergling";"Larva";495;1
"Unit";"Zergling";"Larva";495;1
"Unit";"Zergling";"Larva";495;1
"Unit";"Zergling";"Larva";495;1
"Unit";"Zergling";"Larva";495;1
"Unit";"Zergling";"Larva";495;1
"Unit";"Zergling";"Larva";495;1
"Unit";"Zergling";"Larva";495;1
"Unit";"Zergling";"Larva";495;1
"Unit";"Zergling";"Larva";495;1
"Unit";"Zergling";"Larva";495;1
"Building";"Hatchery";NA;453;0
"Unit";"Overlord";"Larva";523;0
"Unit";"Overlord";"Larva";523;0
"Unit";"Overlord";"Larva";523;0
"Unit";"Overlord";"Larva";528;0
"Unit";"Overlord";"Larva";528;0
"Unit";"Overlord";"Larva";528;0
"Building";"Hatchery";NA;495;0
"Unit";"Zergling";"Larva";534;1
"Unit";"Zergling";"Larva";534;1
"Unit";"Baneling";"Zergling";534;0
"Unit";"Baneling";"Zergling";534;0
"Unit";"Baneling";"Zergling";534;0
"Unit";"Zergling";"Larva";534;1
"Unit";"Zergling";"Larva";534;1
"Unit";"Baneling";"Zergling";534;0
"Unit";"Zergling";"Larva";534;1
"Unit";"Zergling";"Larva";534;1
"Unit";"Hydralisk";"Larva";534;2
"Unit";"Hydralisk";"Larva";534;2
"Unit";"Hydralisk";"Larva";534;2
"Unit";"Hydralisk";"Larva";534;2
"Unit";"Hydralisk";"Larva";534;2
"Unit";"Hydralisk";"Larva";534;2
"Unit";"Hydralisk";"Larva";534;2
"Unit";"Hydralisk";"Larva";534;2
"Unit";"Hydralisk";"Larva";534;2
"Unit";"Hydralisk";"Larva";534;2
"Unit";"Hydralisk";"Larva";534;2
"Unit";"Hydralisk";"Larva";534;2
"Upgrade";"ZergMeleeWeaponsLevel3";"EvolutionChamber";495;0
"Building";"Spire";NA;534;0
"Building";"Spire";NA;534;0
"Building";"CreepTumorQueen";NA;564;0
"Building";"CreepTumorQueen";NA;564;0
"Building";"CreepTumorQueen";NA;564;0
"Building";"CreepTumorQueen";NA;564;0
"Building";"CreepTumorQueen";NA;564;0
"Building";"CreepTumorQueen";NA;564;0
"Building";"CreepTumorQueen";NA;564;0
"Unit";"Zergling";"Larva";564;1
"Unit";"Zergling";"Larva";564;1
"Unit";"Zergling";"Larva";564;1
"Unit";"Zergling";"Larva";564;1
"Unit";"Zergling";"Larva";564;1
"Unit";"Zergling";"Larva";564;1
"Unit";"Zergling";"Larva";564;1
"Unit";"Zergling";"Larva";564;1
"Unit";"Zergling";"Larva";564;1
"Unit";"Zergling";"Larva";564;1
"Unit";"Zergling";"Larva";564;1
"Unit";"Zergling";"Larva";564;1
"Unit";"Zergling";"Larva";564;1
"Unit";"Zergling";"Larva";564;1
"Unit";"Zergling";"Larva";564;1
"Unit";"Zergling";"Larva";564;1
"Unit";"Zergling";"Larva";564;1
"Unit";"Zergling";"Larva";564;1
"Unit";"Zergling";"Larva";564;1
"Unit";"Zergling";"Larva";564;1
"Unit";"Zergling";"Larva";564;1
"Unit";"Zergling";"Larva";564;1
"Unit";"Zergling";"Larva";564;1
"Unit";"Zergling";"Larva";564;1
"Unit";"Zergling";"Larva";564;1
"Unit";"Zergling";"Larva";564;1
"Unit";"Zergling";"Larva";564;1
"Unit";"Zergling";"Larva";564;1
"Unit";"Zergling";"Larva";564;1
"Unit";"Zergling";"Larva";564;1
"Unit";"Zergling";"Larva";564;1
"Unit";"Zergling";"Larva";564;1
"Unit";"Zergling";"Larva";564;1
"Unit";"Zergling";"Larva";564;1
"Unit";"Zergling";"Larva";564;1
"Unit";"Zergling";"Larva";564;1
"Unit";"Zergling";"Larva";564;1
"Unit";"Zergling";"Larva";564;1
"Unit";"Zergling";"Larva";564;1
"Unit";"Zergling";"Larva";564;1
"Unit";"Hydralisk";"Larva";564;2
"Unit";"Hydralisk";"Larva";564;2
"Unit";"Hydralisk";"Larva";564;2
"Unit";"Hydralisk";"Larva";564;2
"Unit";"Hydralisk";"Larva";564;2
"Building";"Extractor";NA;564;0
"Building";"Extractor";NA;564;0
"Unit";"Baneling";"Zergling";564;0
"Unit";"Baneling";"Zergling";564;0
"Unit";"Baneling";"Zergling";564;0
"Unit";"Baneling";"Zergling";564;0
"Unit";"Baneling";"Zergling";564;0
"Unit";"Baneling";"Zergling";564;0
"Unit";"Baneling";"Zergling";564;0
"Unit";"Baneling";"Zergling";564;0
"Unit";"Baneling";"Zergling";564;0
"Building";"CreepTumor";NA;604;0
"Building";"CreepTumor";NA;604;0
"Unit";"Zergling";"Larva";614;1
"Unit";"Zergling";"Larva";614;1
"Unit";"Zergling";"Larva";614;1
"Unit";"Zergling";"Larva";614;1
"Unit";"Zergling";"Larva";614;1
"Unit";"Zergling";"Larva";614;1
"Unit";"Zergling";"Larva";614;1
"Unit";"Zergling";"Larva";614;1
"Unit";"Zergling";"Larva";614;1
"Unit";"Zergling";"Larva";614;1
"Unit";"Zergling";"Larva";614;1
"Unit";"Zergling";"Larva";614;1
"Unit";"Zergling";"Larva";614;1
"Unit";"Zergling";"Larva";614;1
"Unit";"Zergling";"Larva";614;1
"Unit";"Zergling";"Larva";614;1
"Unit";"Zergling";"Larva";614;1
"Unit";"Zergling";"Larva";614;1
"Unit";"Zergling";"Larva";614;1
"Unit";"Zergling";"Larva";614;1
"Unit";"Zergling";"Larva";614;1
"Unit";"Zergling";"Larva";614;1
"Unit";"Baneling";"Zergling";614;0
"Unit";"Baneling";"Zergling";614;0
"Unit";"Baneling";"Zergling";614;0
"Unit";"Baneling";"Zergling";614;0
"Unit";"Baneling";"Zergling";614;0
"Unit";"Baneling";"Zergling";614;0
"Unit";"Baneling";"Zergling";614;0
"Unit";"Ultralisk";"Larva";564;6
"Unit";"Ultralisk";"Larva";564;6
"Unit";"Ultralisk";"Larva";564;6
"Building";"CreepTumorQueen";NA;636;0
"Building";"CreepTumorQueen";NA;636;0
"Unit";"Corruptor";"Larva";636;2
"Unit";"Corruptor";"Larva";636;2
"Unit";"Corruptor";"Larva";636;2
"Unit";"Corruptor";"Larva";636;2
"Unit";"Corruptor";"Larva";636;2
"Unit";"Corruptor";"Larva";636;2
"Unit";"Corruptor";"Larva";636;2
"Building";"Hatchery";NA;636;0
"Unit";"Zergling";"Larva";675;1
"Unit";"Zergling";"Larva";675;1
"Unit";"Zergling";"Larva";675;1
"Unit";"Zergling";"Larva";675;1
"Unit";"Zergling";"Larva";675;1
"Unit";"Zergling";"Larva";675;1
"Unit";"Zergling";"Larva";675;1
"Unit";"Zergling";"Larva";675;1
"Unit";"Zergling";"Larva";675;1
"Unit";"Zergling";"Larva";675;1
"Unit";"Zergling";"Larva";675;1
"Unit";"Zergling";"Larva";675;1
"Unit";"Zergling";"Larva";675;1
"Unit";"Zergling";"Larva";675;1
"Unit";"Zergling";"Larva";675;1
"Unit";"Zergling";"Larva";675;1
"Unit";"Zergling";"Larva";675;1
"Unit";"Zergling";"Larva";675;1
"Unit";"Zergling";"Larva";675;1
"Unit";"Zergling";"Larva";675;1
"Unit";"Zergling";"Larva";675;1
"Unit";"Zergling";"Larva";675;1
"Unit";"Zergling";"Larva";675;1
"Unit";"Zergling";"Larva";675;1
"Unit";"Zergling";"Larva";675;1
"Unit";"Zergling";"Larva";675;1
"Unit";"Zergling";"Larva";675;1
"Unit";"Zergling";"Larva";675;1
"Unit";"Zergling";"Larva";675;1
"Unit";"Zergling";"Larva";675;1
"Unit";"Zergling";"Larva";675;1
"Unit";"Zergling";"Larva";675;1
"Unit";"Zergling";"Larva";675;1
"Unit";"Zergling";"Larva";675;1
"Unit";"Zergling";"Larva";675;1
"Unit";"Zergling";"Larva";675;1
"Unit";"Zergling";"Larva";675;1
"Unit";"Zergling";"Larva";675;1
"Building";"Hatchery";NA;668;0
"Building";"CreepTumor";NA;675;0
"Building";"CreepTumor";NA;675;0
"Unit";"Zergling";"Larva";675;1
"Unit";"Zergling";"Larva";675;1
"Building";"CreepTumorQueen";NA;695;0
"Building";"CreepTumor";NA;677;0
"Building";"CreepTumor";NA;677;0
"Building";"CreepTumorQueen";NA;713;0
"Unit";"Zergling";"Larva";715;1
"Unit";"Zergling";"Larva";715;1
"Unit";"Zergling";"Larva";715;1
"Unit";"Zergling";"Larva";715;1
"Unit";"Zergling";"Larva";715;1
"Unit";"Zergling";"Larva";715;1
"Unit";"Hydralisk";"Larva";715;2
"Unit";"Hydralisk";"Larva";715;2
"Unit";"Hydralisk";"Larva";715;2
"Unit";"Hydralisk";"Larva";715;2
"Unit";"Hydralisk";"Larva";715;2
"Unit";"Hydralisk";"Larva";715;2
"Unit";"Hydralisk";"Larva";715;2
"Unit";"Hydralisk";"Larva";715;2
"Unit";"Hydralisk";"Larva";715;2
"Unit";"Hydralisk";"Larva";715;2
"Unit";"Hydralisk";"Larva";715;2
"Unit";"Hydralisk";"Larva";715;2
"Unit";"Hydralisk";"Larva";715;2
"Unit";"Hydralisk";"Larva";715;2
"Building";"Extractor";NA;715;0
"Building";"Extractor";NA;715;0
"Upgrade";"ZergMissileWeaponsLevel2";"EvolutionChamber";675;0
"Unit";"Zergling";"Larva";749;1
"Unit";"Zergling";"Larva";749;1
"Unit";"Zergling";"Larva";749;1
"Unit";"Zergling";"Larva";749;1
"Unit";"Zergling";"Larva";749;1
"Unit";"Zergling";"Larva";749;1
"Unit";"Zergling";"Larva";749;1
"Unit";"Zergling";"Larva";749;1
"Unit";"Zergling";"Larva";749;1
"Unit";"Zergling";"Larva";749;1
"Unit";"Zergling";"Larva";749;1
"Unit";"Zergling";"Larva";749;1
"Unit";"Zergling";"Larva";749;1
"Unit";"Zergling";"Larva";749;1
"Unit";"Zergling";"Larva";749;1
"Unit";"Zergling";"Larva";749;1
"Unit";"Zergling";"Larva";749;1
"Unit";"Zergling";"Larva";749;1
"Unit";"Zergling";"Larva";749;1
"Unit";"Zergling";"Larva";749;1
"Unit";"Zergling";"Larva";749;1
"Unit";"Zergling";"Larva";749;1
"Unit";"Zergling";"Larva";749;1
"Unit";"Zergling";"Larva";749;1
"Unit";"Zergling";"Larva";749;1
"Unit";"Zergling";"Larva";749;1
"Unit";"Zergling";"Larva";749;1
"Unit";"Zergling";"Larva";749;1
"Unit";"Zergling";"Larva";749;1
"Unit";"Zergling";"Larva";749;1
"Building";"CreepTumor";NA;779;0
"Building";"CreepTumor";NA;779;0
"Building";"CreepTumor";NA;779;0
"Building";"CreepTumor";NA;779;0
"Building";"CreepTumor";NA;779;0
"Building";"CreepTumor";NA;779;0
"Unit";"Corruptor";"Larva";749;2
"Unit";"Corruptor";"Larva";749;2
"Unit";"Corruptor";"Larva";749;2
"Unit";"Corruptor";"Larva";749;2
"Unit";"Corruptor";"Larva";749;2
"Unit";"Zergling";"Larva";779;1
"Unit";"Zergling";"Larva";779;1
"Unit";"Zergling";"Larva";779;1
"Unit";"Zergling";"Larva";779;1
"Unit";"Zergling";"Larva";779;1
"Unit";"Zergling";"Larva";779;1
"Unit";"Zergling";"Larva";779;1
"Unit";"Zergling";"Larva";779;1
"Unit";"Zergling";"Larva";779;1
"Unit";"Zergling";"Larva";779;1
"Unit";"Zergling";"Larva";779;1
"Unit";"Zergling";"Larva";779;1
"Unit";"Zergling";"Larva";779;1
"Unit";"Zergling";"Larva";779;1
"Unit";"Zergling";"Larva";779;1
"Unit";"Zergling";"Larva";779;1
"Unit";"Zergling";"Larva";779;1
"Unit";"Zergling";"Larva";779;1
"Unit";"Zergling";"Larva";779;1
"Unit";"Zergling";"Larva";779;1
"Building";"Extractor";NA;779;0
"Building";"Extractor";NA;779;0
"Unit";"Corruptor";"Larva";789;2
"Unit";"Corruptor";"Larva";791;2
"Unit";"Corruptor";"Larva";791;2
"Unit";"Corruptor";"Larva";791;2
"Unit";"Corruptor";"Larva";791;2
"Unit";"Baneling";"Zergling";809;0
"Unit";"Zergling";"Larva";809;1
"Unit";"Zergling";"Larva";809;1
"Unit";"Baneling";"Zergling";809;0
"Unit";"Baneling";"Zergling";809;0
"Unit";"Baneling";"Zergling";809;0
"Unit";"Baneling";"Zergling";809;0
"Unit";"Baneling";"Zergling";809;0
"Unit";"Zergling";"Larva";809;1
"Unit";"Zergling";"Larva";809;1
"Unit";"Zergling";"Larva";809;1
"Unit";"Zergling";"Larva";809;1
"Unit";"Zergling";"Larva";809;1
"Unit";"Zergling";"Larva";809;1
"Unit";"Zergling";"Larva";809;1
"Unit";"Zergling";"Larva";809;1
"Unit";"Baneling";"Zergling";809;0
"Unit";"Baneling";"Zergling";809;0
"Unit";"Baneling";"Zergling";809;0
"Unit";"Baneling";"Zergling";809;0
"Unit";"Zergling";"Larva";809;1
"Unit";"Zergling";"Larva";809;1
"Unit";"Zergling";"Larva";809;1
"Unit";"Zergling";"Larva";809;1
"Unit";"Baneling";"Zergling";809;0
"Unit";"Baneling";"Zergling";809;0
"Unit";"Zergling";"Larva";809;1
"Unit";"Zergling";"Larva";809;1
"Unit";"Zergling";"Larva";809;1
"Unit";"Zergling";"Larva";809;1
"Unit";"Baneling";"Zergling";809;0
"Unit";"Baneling";"Zergling";809;0
"Unit";"Zergling";"Larva";809;1
"Unit";"Zergling";"Larva";809;1
"Unit";"Zergling";"Larva";809;1
"Unit";"Zergling";"Larva";809;1
"Unit";"Baneling";"Zergling";809;0
"Unit";"Baneling";"Zergling";809;0
"Unit";"Zergling";"Larva";809;1
"Unit";"Zergling";"Larva";809;1
"Unit";"Zergling";"Larva";809;1
"Unit";"Zergling";"Larva";809;1
"Unit";"Zergling";"Larva";809;1
"Unit";"Zergling";"Larva";809;1
"Unit";"Zergling";"Larva";809;1
"Unit";"Zergling";"Larva";809;1
"Unit";"Zergling";"Larva";809;1
"Unit";"Zergling";"Larva";809;1
"Unit";"Hydralisk";"Larva";851;2
"Unit";"Hydralisk";"Larva";851;2
"Unit";"Hydralisk";"Larva";851;2
"Unit";"Hydralisk";"Larva";851;2
"Unit";"Hydralisk";"Larva";851;2
"Unit";"Hydralisk";"Larva";851;2
"Unit";"Zergling";"Larva";851;1
"Unit";"Zergling";"Larva";851;1
"Unit";"Zergling";"Larva";851;1
"Unit";"Zergling";"Larva";851;1
"Unit";"Zergling";"Larva";851;1
"Unit";"Zergling";"Larva";851;1
"Unit";"Zergling";"Larva";851;1
"Unit";"Zergling";"Larva";851;1
"Unit";"Zergling";"Larva";851;1
"Unit";"Zergling";"Larva";851;1
"Unit";"Zergling";"Larva";851;1
"Unit";"Zergling";"Larva";851;1
"Unit";"Zergling";"Larva";851;1
"Unit";"Zergling";"Larva";851;1
"Unit";"Zergling";"Larva";851;1
"Unit";"Zergling";"Larva";851;1
"Unit";"Zergling";"Larva";851;1
"Unit";"Zergling";"Larva";851;1
"Unit";"Zergling";"Larva";851;1
"Unit";"Zergling";"Larva";851;1
"Building";"Hatchery";NA;843;0
"Unit";"Zergling";"Larva";883;1
"Unit";"Zergling";"Larva";883;1
"Unit";"Zergling";"Larva";883;1
"Unit";"Zergling";"Larva";883;1
"Unit";"Zergling";"Larva";883;1
"Unit";"Zergling";"Larva";883;1
"Unit";"Corruptor";"Larva";898;2
"Unit";"Corruptor";"Larva";898;2
"Unit";"Corruptor";"Larva";898;2
"Unit";"Corruptor";"Larva";898;2
"Unit";"Corruptor";"Larva";898;2
"Unit";"Corruptor";"Larva";898;2
"Unit";"Zergling";"Larva";898;1
"Unit";"Zergling";"Larva";898;1
"Unit";"Zergling";"Larva";898;1
"Unit";"Zergling";"Larva";898;1
"Unit";"Zergling";"Larva";898;1
"Unit";"Zergling";"Larva";898;1
"Unit";"Zergling";"Larva";898;1
"Unit";"Zergling";"Larva";898;1
"Unit";"Zergling";"Larva";898;1
"Unit";"Zergling";"Larva";898;1
"Unit";"Zergling";"Larva";898;1
"Unit";"Zergling";"Larva";898;1
"Unit";"Zergling";"Larva";898;1
"Unit";"Zergling";"Larva";898;1
"Unit";"Zergling";"Larva";898;1
"Unit";"Zergling";"Larva";898;1
"Unit";"Zergling";"Larva";898;1
"Unit";"Zergling";"Larva";898;1
"Unit";"Zergling";"Larva";898;1
"Unit";"Zergling";"Larva";898;1
"Unit";"Zergling";"Larva";898;1
"Unit";"Zergling";"Larva";898;1
"Unit";"Zergling";"Larva";898;1
"Unit";"Zergling";"Larva";898;1
"Unit";"Zergling";"Larva";898;1
"Unit";"Zergling";"Larva";898;1
"Unit";"Zergling";"Larva";898;1
"Unit";"Zergling";"Larva";898;1
"Unit";"Zergling";"Larva";910;1
"Unit";"Zergling";"Larva";910;1
"Unit";"Zergling";"Larva";910;1
"Unit";"Zergling";"Larva";910;1
"Building";"CreepTumor";NA;941;0
"Building";"CreepTumor";NA;941;0
"Building";"CreepTumor";NA;941;0
"Unit";"Ultralisk";"Larva";898;6
"Unit";"Ultralisk";"Larva";898;6
"Building";"CreepTumor";NA;941;0
"Unit";"Zergling";"Larva";938;1
"Unit";"Zergling";"Larva";938;1
"Unit";"Zergling";"Larva";938;1
"Unit";"Zergling";"Larva";938;1
"Unit";"Queen";"Hatchery";898;2
"Building";"CreepTumor";NA;963;0
"Unit";"Hydralisk";"Larva";945;2
"Building";"CreepTumor";NA;963;0
"Unit";"Hydralisk";"Larva";945;2
"Unit";"Hydralisk";"Larva";945;2
"Unit";"Hydralisk";"Larva";945;2
"Building";"Hatchery";NA;898;0
"Unit";"Zergling";"Larva";963;1
"Unit";"Zergling";"Larva";963;1
"Unit";"Zergling";"Larva";963;1
"Unit";"Zergling";"Larva";963;1
"Unit";"Zergling";"Larva";963;1
"Unit";"Zergling";"Larva";963;1
"Unit";"Zergling";"Larva";963;1
"Unit";"Zergling";"Larva";963;1
"Unit";"Zergling";"Larva";963;1
"Unit";"Zergling";"Larva";963;1
"Unit";"Zergling";"Larva";963;1
"Unit";"Zergling";"Larva";963;1
"Unit";"Zergling";"Larva";963;1
"Unit";"Zergling";"Larva";963;1
"Building";"CreepTumorQueen";NA;963;0
"Unit";"Baneling";"Zergling";963;0
"Unit";"Baneling";"Zergling";963;0
"Unit";"Baneling";"Zergling";963;0
"Unit";"Baneling";"Zergling";963;0
"Unit";"Baneling";"Zergling";963;0
"Unit";"Baneling";"Zergling";963;0
"Unit";"Baneling";"Zergling";963;0
"Unit";"Baneling";"Zergling";963;0
"Unit";"Baneling";"Zergling";963;0
"Unit";"Baneling";"Zergling";963;0
"Unit";"Zergling";"Larva";971;1
"Unit";"Zergling";"Larva";971;1
"Unit";"Zergling";"Larva";971;1
"Unit";"Zergling";"Larva";971;1
"Unit";"Zergling";"Larva";971;1
"Unit";"Zergling";"Larva";971;1
"Unit";"Zergling";"Larva";971;1
"Unit";"Zergling";"Larva";971;1
"Unit";"Zergling";"Larva";971;1
"Unit";"Zergling";"Larva";971;1
"Unit";"Zergling";"Larva";971;1
"Unit";"Zergling";"Larva";971;1
"Unit";"Zergling";"Larva";971;1
"Unit";"Zergling";"Larva";971;1
"Unit";"Zergling";"Larva";971;1
"Unit";"Zergling";"Larva";971;1
"Building";"UltraliskCavern";NA;945;0
"Building";"CreepTumor";NA;985;0
"Building";"CreepTumor";NA;985;0
"Building";"CreepTumor";NA;985;0
"Building";"CreepTumor";NA;985;0
"Building";"CreepTumor";NA;985;0
"Building";"CreepTumor";NA;985;0
"Unit";"Zergling";"Larva";1008;1
"Unit";"Zergling";"Larva";1008;1
"Unit";"Zergling";"Larva";1008;1
"Unit";"Zergling";"Larva";1008;1
"Unit";"Zergling";"Larva";1008;1
"Unit";"Zergling";"Larva";1008;1
"Unit";"Zergling";"Larva";1008;1
"Unit";"Zergling";"Larva";1008;1
"Unit";"Zergling";"Larva";1008;1
"Unit";"Zergling";"Larva";1008;1
"Unit";"Zergling";"Larva";1008;1
"Unit";"Zergling";"Larva";1008;1
"Unit";"Zergling";"Larva";1008;1
"Unit";"Zergling";"Larva";1008;1
"Unit";"Zergling";"Larva";1008;1
"Unit";"Zergling";"Larva";1008;1
"Unit";"Baneling";"Zergling";1008;0
"Unit";"Baneling";"Zergling";1008;0
"Unit";"Baneling";"Zergling";1008;0
"Unit";"Baneling";"Zergling";1008;0
"Unit";"Zergling";"Larva";1024;1
"Unit";"Zergling";"Larva";1024;1
"Unit";"Zergling";"Larva";1024;1
"Unit";"Zergling";"Larva";1024;1
"Unit";"Zergling";"Larva";1024;1
"Unit";"Zergling";"Larva";1024;1
"Unit";"Zergling";"Larva";1024;1
"Unit";"Zergling";"Larva";1024;1
"Unit";"Zergling";"Larva";1024;1
"Unit";"Zergling";"Larva";1024;1
"Unit";"Zergling";"Larva";1024;1
"Unit";"Zergling";"Larva";1024;1
"Unit";"Zergling";"Larva";1024;1
"Unit";"Zergling";"Larva";1024;1
"Unit";"Zergling";"Larva";1024;1
"Unit";"Zergling";"Larva";1024;1
"Unit";"Zergling";"Larva";1024;1
"Unit";"Zergling";"Larva";1024;1
"Unit";"Zergling";"Larva";1024;1
"Unit";"Zergling";"Larva";1024;1
"Unit";"Zergling";"Larva";1024;1
"Unit";"Zergling";"Larva";1024;1
"Unit";"Zergling";"Larva";1024;1
"Unit";"Zergling";"Larva";1024;1
"Unit";"Zergling";"Larva";1024;1
"Unit";"Zergling";"Larva";1024;1
"Building";"CreepTumor";NA;1024;0
"Building";"CreepTumor";NA;1030;0
"Building";"CreepTumor";NA;1050;0
"Building";"CreepTumor";NA;1050;0
"Unit";"Hydralisk";"Larva";1024;2
"Unit";"Hydralisk";"Larva";1024;2
"Unit";"Hydralisk";"Larva";1024;2
"Unit";"Hydralisk";"Larva";1024;2
"Unit";"Hydralisk";"Larva";1024;2
"Unit";"Hydralisk";"Larva";1024;2
"Building";"Hatchery";NA;1008;0
"Unit";"Corruptor";"Larva";1050;2
"Unit";"Corruptor";"Larva";1050;2
"Unit";"Corruptor";"Larva";1050;2
"Unit";"Corruptor";"Larva";1050;2
"Unit";"Zergling";"Larva";1062;1
"Unit";"Zergling";"Larva";1062;1
"Unit";"Zergling";"Larva";1062;1
"Unit";"Zergling";"Larva";1062;1
"Unit";"Zergling";"Larva";1062;1
"Unit";"Zergling";"Larva";1062;1
"Unit";"Zergling";"Larva";1062;1
"Unit";"Zergling";"Larva";1062;1
"Unit";"Zergling";"Larva";1062;1
"Unit";"Zergling";"Larva";1062;1
"Unit";"Zergling";"Larva";1062;1
"Unit";"Zergling";"Larva";1062;1
"Unit";"Zergling";"Larva";1062;1
"Unit";"Zergling";"Larva";1062;1
"Unit";"Zergling";"Larva";1062;1
"Unit";"Zergling";"Larva";1062;1
"Unit";"Zergling";"Larva";1062;1
"Unit";"Zergling";"Larva";1062;1
"Unit";"Zergling";"Larva";1062;1
"Unit";"Zergling";"Larva";1062;1
"Unit";"Zergling";"Larva";1062;1
"Unit";"Zergling";"Larva";1062;1
"Unit";"Zergling";"Larva";1062;1
"Unit";"Zergling";"Larva";1062;1
"Unit";"Zergling";"Larva";1062;1
"Unit";"Zergling";"Larva";1062;1
"Unit";"Zergling";"Larva";1062;1
"Unit";"Zergling";"Larva";1062;1
