"type";"unit_name";"on_building";"total_supply";"supply"
"Unit";"Overlord";"Larva";13;0
"Building";"Extractor";NA;17;0
"Unit";"Overlord";"Larva";22;0
"Building";"SpawningPool";NA;19;0
"Building";"Hatchery";NA;17;0
"Unit";"Zergling";"Larva";22;1
"Unit";"Zergling";"Larva";22;1
"Unit";"Zergling";"Larva";22;1
"Unit";"Zergling";"Larva";22;1
"Unit";"Queen";"Hatchery";22;2
"Unit";"Queen";"Hatchery";22;2
"Unit";"Overlord";"Larva";36;0
"Unit";"Overlord";"Larva";36;0
"Unit";"Queen";"Hatchery";33;2
"Unit";"Queen";"Hatchery";35;2
"Building";"CreepTumorQueen";NA;37;0
"Building";"CreepTumorQueen";NA;37;0
"Building";"CreepTumorQueen";NA;53;0
"Unit";"Overlord";"Larva";53;0
"Building";"CreepTumor";NA;53;0
"Building";"CreepTumorQueen";NA;53;0
"Unit";"Overlord";"Larva";53;0
"Building";"CreepTumor";NA;53;0
"Unit";"Zergling";"Larva";53;1
"Unit";"Zergling";"Larva";53;1
"Unit";"Zergling";"Larva";53;1
"Unit";"Zergling";"Larva";53;1
"Unit";"Zergling";"Larva";53;1
"Unit";"Zergling";"Larva";53;1
"Unit";"Overlord";"Larva";53;0
"Unit";"Overlord";"Larva";53;0
"Building";"CreepTumor";NA;53;0
"Building";"CreepTumor";NA;53;0
"Building";"CreepTumor";NA;53;0
"Building";"CreepTumorQueen";NA;59;0
"Building";"CreepTumorQueen";NA;59;0
"Building";"RoachWarren";NA;53;0
"Building";"Extractor";NA;53;0
"Unit";"Overlord";"Larva";59;0
"Unit";"Roach";"Larva";62;2
"Unit";"Roach";"Larva";62;2
"Unit";"Roach";"Larva";62;2
"Unit";"Roach";"Larva";62;2
"Unit";"Roach";"Larva";62;2
"Building";"Hatchery";NA;53;0
"Unit";"Roach";"Larva";62;2
"Unit";"Roach";"Larva";62;2
"Unit";"Queen";"Hatchery";77;2
"Building";"CreepTumor";NA;91;0
"Building";"CreepTumor";NA;92;0
"Building";"SporeCrawler";NA;84;0
"Building";"SporeCrawler";NA;84;0
"Building";"SporeCrawler";NA;91;0
"Building";"CreepTumor";NA;93;0
"Building";"CreepTumor";NA;93;0
"Unit";"Overlord";"Larva";93;0
"Building";"Extractor";NA;101;0
"Unit";"Overlord";"Larva";101;0
"Building";"Extractor";NA;101;0
"Building";"Extractor";NA;101;0
"Building";"Extractor";NA;101;0
"Building";"CreepTumor";NA;107;0
"Building";"CreepTumor";NA;107;0
"Building";"CreepTumor";NA;107;0
"Building";"CreepTumorQueen";NA;110;0
"Building";"CreepTumorQueen";NA;110;0
"Unit";"Roach";"Larva";107;2
"Unit";"Roach";"Larva";107;2
"Unit";"Roach";"Larva";107;2
"Unit";"Roach";"Larva";107;2
"Building";"CreepTumorQueen";NA;110;0
"Building";"CreepTumorQueen";NA;110;0
"Building";"EvolutionChamber";NA;107;0
"Building";"EvolutionChamber";NA;110;0
"Unit";"Overlord";"Larva";110;0
"Unit";"Overlord";"Larva";110;0
"Building";"CreepTumor";NA;122;0
"Building";"CreepTumorQueen";NA;122;0
"Building";"CreepTumor";NA;124;0
"Building";"CreepTumor";NA;127;0
"Building";"CreepTumor";NA;127;0
"Building";"CreepTumor";NA;127;0
"Building";"HydraliskDen";NA;127;0
"Building";"Hatchery";NA;105;0
"Building";"CreepTumor";NA;135;0
"Building";"CreepTumor";NA;135;0
"Building";"CreepTumorQueen";NA;135;0
"Building";"CreepTumor";NA;135;0
"Building";"CreepTumor";NA;135;0
"Building";"CreepTumor";NA;135;0
"Unit";"Roach";"Larva";135;2
"Unit";"Roach";"Larva";135;2
"Unit";"Roach";"Larva";135;2
"Unit";"Roach";"Larva";135;2
"Unit";"Roach";"Larva";135;2
"Unit";"Overlord";"Larva";135;0
"Unit";"Overlord";"Larva";135;0
"Building";"CreepTumor";NA;135;0
"Building";"CreepTumor";NA;135;0
"Building";"CreepTumor";NA;135;0
"Unit";"Overlord";"Larva";135;0
"Unit";"Overlord";"Larva";135;0
"Building";"CreepTumor";NA;145;0
"Building";"CreepTumor";NA;145;0
"Building";"CreepTumor";NA;145;0
"Unit";"Hydralisk";"Larva";135;2
"Building";"CreepTumor";NA;145;0
"Unit";"Hydralisk";"Larva";135;2
"Building";"CreepTumor";NA;145;0
"Unit";"Hydralisk";"Larva";135;2
"Unit";"Hydralisk";"Larva";145;2
"Unit";"Hydralisk";"Larva";145;2
"Unit";"Hydralisk";"Larva";145;2
"Unit";"Hydralisk";"Larva";145;2
"Unit";"Hydralisk";"Larva";145;2
"Unit";"Hydralisk";"Larva";145;2
"Unit";"Hydralisk";"Larva";145;2
"Upgrade";"GlialReconstitution";"RoachWarren";135;0
"Unit";"Roach";"Larva";151;2
"Building";"CreepTumor";NA;155;0
"Unit";"Hydralisk";"Larva";147;2
"Unit";"Hydralisk";"Larva";149;2
"Unit";"Hydralisk";"Larva";149;2
"Unit";"Hydralisk";"Larva";151;2
"Unit";"Hydralisk";"Larva";155;2
"Unit";"Hydralisk";"Larva";155;2
"Unit";"Hydralisk";"Larva";155;2
"Building";"Extractor";NA;155;0
"Building";"Extractor";NA;163;0
"Unit";"Overlord";"Larva";167;0
"Unit";"Overlord";"Larva";167;0
"Upgrade";"EvolveMuscularAugments";"HydraliskDen";145;0
"Unit";"Queen";"Hatchery";155;2
"Upgrade";"ZergMissileWeaponsLevel1";"EvolutionChamber";135;0
"Upgrade";"ZergGroundArmorsLevel1";"EvolutionChamber";135;0
"Unit";"Hydralisk";"Larva";180;2
"Unit";"Overlord";"Larva";184;0
"Building";"Hatchery";NA;145;0
"Building";"CreepTumor";NA;186;0
"Building";"CreepTumor";NA;186;0
"Unit";"Hydralisk";"Larva";184;2
"Unit";"Hydralisk";"Larva";184;2
"Unit";"Hydralisk";"Larva";184;2
"Unit";"Hydralisk";"Larva";184;2
"Unit";"Hydralisk";"Larva";184;2
"Unit";"Hydralisk";"Larva";184;2
"Unit";"Zergling";"Larva";196;1
"Unit";"Zergling";"Larva";196;1
"Building";"CreepTumorQueen";NA;196;0
"Building";"CreepTumor";NA;196;0
"Unit";"Hydralisk";"Larva";193;2
"Building";"CreepTumor";NA;196;0
"Unit";"Hydralisk";"Larva";194;2
"Unit";"Hydralisk";"Larva";195;2
"Unit";"Hydralisk";"Larva";195;2
"Building";"InfestationPit";NA;186;0
"Unit";"Overlord";"Larva";210;0
"Building";"CreepTumor";NA;222;0
"Building";"CreepTumor";NA;222;0
"Building";"CreepTumorQueen";NA;222;0
"Building";"CreepTumor";NA;222;0
"Unit";"Hydralisk";"Larva";210;2
"Unit";"Hydralisk";"Larva";210;2
"Unit";"Hydralisk";"Larva";210;2
"Unit";"Hydralisk";"Larva";210;2
"Unit";"Hydralisk";"Larva";210;2
"Unit";"Overlord";"Larva";218;0
"Building";"CreepTumor";NA;222;0
"Unit";"Hydralisk";"Larva";218;2
"Unit";"Hydralisk";"Larva";218;2
"Unit";"Hydralisk";"Larva";218;2
"Unit";"Zergling";"Larva";222;1
"Unit";"Zergling";"Larva";222;1
"Unit";"Zergling";"Larva";222;1
"Unit";"Zergling";"Larva";222;1
"Unit";"Zergling";"Larva";222;1
"Unit";"Zergling";"Larva";222;1
"Upgrade";"EvolveGroovedSpines";"HydraliskDen";196;0
"Unit";"Hydralisk";"Larva";222;2
"Building";"CreepTumor";NA;238;0
"Building";"CreepTumor";NA;238;0
"Building";"CreepTumor";NA;238;0
"Building";"CreepTumor";NA;238;0
"Building";"CreepTumor";NA;238;0
"Unit";"Overlord";"Larva";246;0
"Unit";"Overlord";"Larva";246;0
"Building";"SpineCrawler";NA;232;0
"Building";"CreepTumor";NA;246;0
"Building";"SpineCrawler";NA;232;0
"Unit";"Hydralisk";"Larva";244;2
"Unit";"Hydralisk";"Larva";244;2
"Unit";"Hydralisk";"Larva";246;2
"Unit";"Hydralisk";"Larva";246;2
"Unit";"Hydralisk";"Larva";246;2
"Building";"CreepTumorQueen";NA;246;0
"Unit";"Overlord";"Larva";256;0
"Building";"CreepTumor";NA;256;0
"Unit";"Roach";"Larva";256;2
"Unit";"Roach";"Larva";256;2
"Unit";"Roach";"Larva";256;2
"Unit";"Roach";"Larva";256;2
"Unit";"Roach";"Larva";256;2
"Unit";"Roach";"Larva";256;2
"Unit";"Roach";"Larva";256;2
"Unit";"Hydralisk";"Larva";256;2
"Unit";"Hydralisk";"Larva";256;2
"Unit";"Hydralisk";"Larva";256;2
"Upgrade";"ZergMissileWeaponsLevel2";"EvolutionChamber";232;0
"Building";"Spire";NA;246;0
"Unit";"Hydralisk";"Larva";256;2
"Unit";"Hydralisk";"Larva";256;2
"Unit";"Viper";"Larva";256;3
"Unit";"Viper";"Larva";256;3
"Unit";"Viper";"Larva";266;3
"Unit";"Viper";"Larva";268;3
"Unit";"Viper";"Larva";268;3
"Upgrade";"ZergGroundArmorsLevel2";"EvolutionChamber";246;0
"Unit";"Viper";"Larva";280;3
"Unit";"Hydralisk";"Larva";298;2
"Unit";"Overlord";"Larva";298;0
"Unit";"Overlord";"Larva";298;0
"Unit";"Overlord";"Larva";298;0
"Unit";"Overlord";"Larva";298;0
"Unit";"Overlord";"Larva";298;0
"Unit";"Hydralisk";"Larva";298;2
"Unit";"Hydralisk";"Larva";298;2
"Unit";"Hydralisk";"Larva";298;2
"Unit";"Hydralisk";"Larva";298;2
"Unit";"Hydralisk";"Larva";298;2
"Unit";"Hydralisk";"Larva";298;2
"Unit";"Hydralisk";"Larva";298;2
"Unit";"Hydralisk";"Larva";298;2
"Unit";"Hydralisk";"Larva";298;2
"Building";"Extractor";NA;300;0
"Building";"Extractor";NA;300;0
"Unit";"Overlord";"Larva";300;0
"Building";"CreepTumor";NA;310;0
"Unit";"Overlord";"Larva";300;0
"Unit";"Overlord";"Larva";300;0
"Unit";"Overlord";"Larva";300;0
"Unit";"Overlord";"Larva";300;0
"Building";"CreepTumor";NA;318;0
"Building";"CreepTumor";NA;318;0
"Building";"CreepTumor";NA;319;0
"Building";"Extractor";NA;300;0
"Building";"Extractor";NA;304;0
"Building";"CreepTumor";NA;326;0
"Unit";"Hydralisk";"Larva";326;2
"Unit";"Hydralisk";"Larva";326;2
"Unit";"Hydralisk";"Larva";326;2
"Unit";"Hydralisk";"Larva";326;2
"Unit";"Hydralisk";"Larva";326;2
"Unit";"Overlord";"Larva";326;0
"Building";"CreepTumor";NA;331;0
"Unit";"Hydralisk";"Larva";331;2
"Unit";"Hydralisk";"Larva";331;2
"Unit";"Hydralisk";"Larva";331;2
"Unit";"Hydralisk";"Larva";331;2
"Unit";"Hydralisk";"Larva";331;2
"Unit";"Hydralisk";"Larva";331;2
"Unit";"Hydralisk";"Larva";331;2
"Unit";"Roach";"Larva";331;2
"Unit";"Roach";"Larva";331;2
"Unit";"Roach";"Larva";331;2
"Unit";"Roach";"Larva";341;2
"Unit";"Roach";"Larva";341;2
"Unit";"Roach";"Larva";341;2
"Unit";"Roach";"Larva";341;2
"Unit";"Roach";"Larva";341;2
"Unit";"Roach";"Larva";341;2
"Building";"CreepTumor";NA;341;0
"Unit";"Hydralisk";"Larva";341;2
"Unit";"Hydralisk";"Larva";341;2
"Unit";"Hydralisk";"Larva";341;2
"Unit";"Hydralisk";"Larva";341;2
"Unit";"Hydralisk";"Larva";341;2
"Unit";"Hydralisk";"Larva";341;2
"Unit";"Hydralisk";"Larva";343;2
"Unit";"Hydralisk";"Larva";345;2
"Building";"Hatchery";NA;304;0
"Unit";"Hydralisk";"Larva";373;2
"Unit";"Hydralisk";"Larva";373;2
"Unit";"Hydralisk";"Larva";373;2
"Unit";"Hydralisk";"Larva";373;2
"Unit";"Roach";"Larva";389;2
"Unit";"Hydralisk";"Larva";381;2
"Unit";"Hydralisk";"Larva";381;2
"Unit";"Hydralisk";"Larva";381;2
"Unit";"Hydralisk";"Larva";381;2
"Unit";"Hydralisk";"Larva";381;2
"Unit";"Hydralisk";"Larva";381;2
"Building";"CreepTumor";NA;389;0
"Unit";"Hydralisk";"Larva";389;2
"Building";"CreepTumor";NA;389;0
"Building";"CreepTumor";NA;397;0
"Building";"CreepTumor";NA;397;0
"Building";"CreepTumorQueen";NA;411;0
"Building";"CreepTumorQueen";NA;413;0
"Building";"CreepTumorQueen";NA;413;0
"Building";"SpineCrawler";NA;411;0
"Building";"SpineCrawler";NA;411;0
"Building";"SpineCrawler";NA;413;0
"Building";"SpineCrawler";NA;413;0
"Unit";"Corruptor";"Larva";414;2
"Unit";"Corruptor";"Larva";414;2
"Upgrade";"ZergMissileWeaponsLevel3";"EvolutionChamber";331;0
"Upgrade";"ZergGroundArmorsLevel3";"EvolutionChamber";331;0
