"type";"unit_name";"on_building";"total_supply";"supply"
"Unit";"Overlord";"Larva";12;0
"Building";"Extractor";NA;18;0
"Unit";"Overlord";"Larva";22;0
"Building";"SpawningPool";NA;19;0
"Building";"Hatchery";NA;17;0
"Unit";"Zergling";"Larva";22;1
"Unit";"Zergling";"Larva";22;1
"Unit";"Zergling";"Larva";22;1
"Unit";"Zergling";"Larva";22;1
"Unit";"Queen";"Hatchery";22;2
"Unit";"Queen";"Hatchery";22;2
"Unit";"Overlord";"Larva";35;0
"Unit";"Queen";"Hatchery";32;2
"Unit";"Zergling";"Larva";42;1
"Unit";"Zergling";"Larva";42;1
"Unit";"Zergling";"Larva";42;1
"Unit";"Zergling";"Larva";42;1
"Unit";"Zergling";"Larva";42;1
"Unit";"Zergling";"Larva";42;1
"Unit";"Zergling";"Larva";42;1
"Unit";"Zergling";"Larva";42;1
"Unit";"Overlord";"Larva";47;0
"Building";"Extractor";NA;47;0
"Building";"CreepTumorQueen";NA;55;0
"Unit";"Overlord";"Larva";55;0
"Building";"CreepTumorQueen";NA;56;0
"Building";"RoachWarren";NA;47;0
"Unit";"Overlord";"Larva";56;0
"Building";"Extractor";NA;60;0
"Building";"CreepTumor";NA;60;0
"Building";"CreepTumor";NA;64;0
"Building";"CreepTumorQueen";NA;64;0
"Unit";"Roach";"Larva";64;2
"Unit";"Roach";"Larva";64;2
"Unit";"Roach";"Larva";64;2
"Unit";"Roach";"Larva";64;2
"Unit";"Overlord";"Larva";71;0
"Building";"Hatchery";NA;55;0
"Unit";"Queen";"Hatchery";64;2
"Unit";"Roach";"Larva";71;2
"Building";"CreepTumorQueen";NA;79;0
"Building";"CreepTumor";NA;79;0
"Building";"CreepTumorQueen";NA;79;0
"Building";"CreepTumor";NA;79;0
"Unit";"Overlord";"Larva";79;0
"Unit";"Overlord";"Larva";79;0
"Building";"EvolutionChamber";NA;79;0
"Building";"EvolutionChamber";NA;79;0
"Unit";"Roach";"Larva";79;2
"Unit";"Roach";"Larva";79;2
"Unit";"Roach";"Larva";79;2
"Unit";"Roach";"Larva";83;2
"Unit";"Roach";"Larva";83;2
"Building";"CreepTumor";NA;83;0
"Unit";"Roach";"Larva";83;2
"Building";"CreepTumor";NA;83;0
"Building";"CreepTumor";NA;83;0
"Building";"CreepTumor";NA;83;0
"Unit";"Roach";"Larva";83;2
"Unit";"Roach";"Larva";83;2
"Unit";"Roach";"Larva";89;2
"Unit";"Queen";"Hatchery";83;2
"Unit";"Zergling";"Larva";102;1
"Unit";"Zergling";"Larva";102;1
"Unit";"Zergling";"Larva";102;1
"Unit";"Zergling";"Larva";102;1
"Unit";"Zergling";"Larva";102;1
"Unit";"Zergling";"Larva";102;1
"Unit";"Zergling";"Larva";102;1
"Unit";"Zergling";"Larva";102;1
"Unit";"Zergling";"Larva";102;1
"Unit";"Zergling";"Larva";102;1
"Unit";"Zergling";"Larva";102;1
"Unit";"Zergling";"Larva";102;1
"Unit";"Overlord";"Larva";107;0
"Unit";"Overlord";"Larva";107;0
"Building";"CreepTumor";NA;119;0
"Building";"CreepTumor";NA;119;0
"Building";"CreepTumor";NA;119;0
"Unit";"Overlord";"Larva";119;0
"Unit";"Overlord";"Larva";119;0
"Unit";"Overlord";"Larva";119;0
"Building";"CreepTumorQueen";NA;121;0
"Building";"CreepTumorQueen";NA;121;0
"Unit";"Overlord";"Larva";120;0
"Unit";"Overlord";"Larva";121;0
"Unit";"Roach";"Larva";128;2
"Unit";"Roach";"Larva";128;2
"Unit";"Roach";"Larva";128;2
"Unit";"Roach";"Larva";128;2
"Unit";"Roach";"Larva";128;2
"Unit";"Roach";"Larva";128;2
"Unit";"Roach";"Larva";128;2
"Unit";"Roach";"Larva";128;2
"Unit";"Overlord";"Larva";128;0
"Building";"Extractor";NA;128;0
"Building";"Extractor";NA;128;0
"Building";"CreepTumorQueen";NA;144;0
"Building";"Extractor";NA;128;0
"Building";"CreepTumorQueen";NA;144;0
"Building";"CreepTumorQueen";NA;144;0
"Building";"CreepTumorQueen";NA;144;0
"Building";"CreepTumorQueen";NA;144;0
"Building";"InfestationPit";NA;128;0
"Building";"CreepTumor";NA;152;0
"Building";"CreepTumor";NA;152;0
"Upgrade";"ZergMissileWeaponsLevel1";"EvolutionChamber";107;0
"Upgrade";"ZergGroundArmorsLevel1";"EvolutionChamber";107;0
"Building";"CreepTumorQueen";NA;154;0
"Unit";"Overlord";"Larva";152;0
"Unit";"Roach";"Larva";154;2
"Unit";"Roach";"Larva";154;2
"Unit";"Roach";"Larva";154;2
"Building";"CreepTumor";NA;157;0
"Building";"CreepTumor";NA;157;0
"Building";"CreepTumor";NA;157;0
"Unit";"Roach";"Larva";157;2
"Unit";"Roach";"Larva";157;2
"Unit";"Roach";"Larva";157;2
"Unit";"Roach";"Larva";163;2
"Unit";"Roach";"Larva";163;2
"Unit";"Roach";"Larva";163;2
"Unit";"Roach";"Larva";163;2
"Building";"Extractor";NA;163;0
"Unit";"Roach";"Larva";163;2
"Unit";"Roach";"Larva";163;2
"Unit";"Roach";"Larva";163;2
"Unit";"Roach";"Larva";163;2
"Unit";"Zergling";"Larva";169;1
"Unit";"Zergling";"Larva";169;1
"Unit";"Zergling";"Larva";169;1
"Unit";"Zergling";"Larva";169;1
"Unit";"Zergling";"Larva";169;1
"Unit";"Zergling";"Larva";169;1
"Unit";"Infestor";"Larva";157;2
"Unit";"Infestor";"Larva";157;2
"Unit";"Infestor";"Larva";157;2
"Unit";"Infestor";"Larva";157;2
"Unit";"Overlord";"Larva";177;0
"Building";"CreepTumor";NA;191;0
"Building";"CreepTumor";NA;199;0
"Unit";"Overlord";"Larva";191;0
"Unit";"Overlord";"Larva";193;0
"Unit";"Overlord";"Larva";199;0
"Unit";"Overlord";"Larva";199;0
"Unit";"Overlord";"Larva";199;0
"Unit";"Queen";"Hatchery";169;2
"Building";"CreepTumorQueen";NA;199;0
"Unit";"Overlord";"Larva";199;0
"Unit";"Overlord";"Larva";199;0
"Unit";"Overlord";"Larva";199;0
"Building";"CreepTumorQueen";NA;201;0
"Unit";"Queen";"Hatchery";199;2
"Unit";"Queen";"Hatchery";199;2
"Unit";"Roach";"Larva";201;2
"Unit";"Roach";"Larva";201;2
"Unit";"Roach";"Larva";201;2
"Building";"CreepTumorQueen";NA;201;0
"Unit";"Roach";"Larva";201;2
"Unit";"Roach";"Larva";201;2
"Unit";"Roach";"Larva";201;2
"Unit";"Roach";"Larva";201;2
"Building";"CreepTumorQueen";NA;201;0
"Building";"CreepTumorQueen";NA;201;0
"Building";"CreepTumorQueen";NA;201;0
"Unit";"Queen";"Hatchery";199;2
"Unit";"Roach";"Larva";205;2
"Unit";"Roach";"Larva";205;2
"Unit";"Roach";"Larva";205;2
"Unit";"Roach";"Larva";205;2
"Unit";"Roach";"Larva";205;2
"Upgrade";"GlialReconstitution";"RoachWarren";199;0
"Building";"SporeCrawler";NA;219;0
"Unit";"Roach";"Larva";231;2
"Building";"SporeCrawler";NA;231;0
"Unit";"Roach";"Larva";231;2
"Unit";"Roach";"Larva";231;2
"Unit";"Roach";"Larva";231;2
"Unit";"Roach";"Larva";231;2
"Unit";"Roach";"Larva";231;2
"Unit";"Roach";"Larva";231;2
"Building";"SporeCrawler";NA;231;0
"Unit";"Overlord";"Larva";231;0
"Unit";"Queen";"Hatchery";231;2
"Unit";"Queen";"Hatchery";231;2
"Unit";"Roach";"Larva";247;2
"Unit";"Roach";"Larva";247;2
"Unit";"Roach";"Larva";247;2
"Unit";"Roach";"Larva";247;2
"Unit";"Roach";"Larva";247;2
"Unit";"Roach";"Larva";247;2
"Unit";"Roach";"Larva";247;2
"Unit";"Roach";"Larva";247;2
"Unit";"Roach";"Larva";247;2
"Unit";"Roach";"Larva";247;2
"Unit";"Roach";"Larva";247;2
"Unit";"Roach";"Larva";247;2
"Unit";"Roach";"Larva";273;2
"Unit";"Roach";"Larva";273;2
"Unit";"Roach";"Larva";273;2
"Unit";"Roach";"Larva";273;2
"Unit";"Roach";"Larva";273;2
"Unit";"Roach";"Larva";273;2
"Building";"Hatchery";NA;247;0
"Unit";"Queen";"Hatchery";273;2
"Unit";"Queen";"Hatchery";273;2
"Unit";"Queen";"Hatchery";273;2
"Unit";"Roach";"Larva";285;2
"Unit";"Roach";"Larva";285;2
"Unit";"Roach";"Larva";285;2
"Unit";"Roach";"Larva";285;2
"Unit";"Roach";"Larva";285;2
"Unit";"Roach";"Larva";285;2
"Building";"CreepTumorQueen";NA;285;0
"Building";"Extractor";NA;285;0
"Building";"CreepTumor";NA;303;0
"Building";"CreepTumorQueen";NA;303;0
"Building";"CreepTumorQueen";NA;303;0
"Building";"CreepTumor";NA;303;0
"Building";"CreepTumor";NA;303;0
"Building";"CreepTumor";NA;303;0
"Building";"CreepTumor";NA;303;0
"Building";"CreepTumorQueen";NA;309;0
"Building";"HydraliskDen";NA;285;0
"Unit";"Queen";"Hatchery";285;2
"Building";"CreepTumorQueen";NA;309;0
"Unit";"Roach";"Larva";309;2
"Unit";"Roach";"Larva";309;2
"Unit";"Roach";"Larva";309;2
"Unit";"Roach";"Larva";309;2
"Unit";"Roach";"Larva";309;2
"Unit";"Roach";"Larva";309;2
"Unit";"Queen";"Hatchery";285;2
"Unit";"Queen";"Hatchery";287;2
"Unit";"Roach";"Larva";309;2
"Unit";"Roach";"Larva";309;2
"Building";"CreepTumor";NA;327;0
"Unit";"Overlord";"Larva";327;0
"Building";"CreepTumor";NA;331;0
"Building";"CreepTumor";NA;331;0
"Building";"CreepTumor";NA;331;0
"Building";"CreepTumor";NA;331;0
"Building";"CreepTumor";NA;331;0
"Unit";"Hydralisk";"Larva";331;2
"Unit";"Hydralisk";"Larva";331;2
"Unit";"Hydralisk";"Larva";331;2
"Unit";"Hydralisk";"Larva";331;2
"Unit";"Hydralisk";"Larva";331;2
"Unit";"Hydralisk";"Larva";331;2
"Building";"Extractor";NA;331;0
"Building";"Extractor";NA;331;0
"Building";"CreepTumorQueen";NA;357;0
"Unit";"Hydralisk";"Larva";357;2
"Unit";"Hydralisk";"Larva";357;2
"Unit";"Hydralisk";"Larva";357;2
"Unit";"Hydralisk";"Larva";357;2
"Upgrade";"ZergMissileWeaponsLevel2";"EvolutionChamber";309;0
"Upgrade";"ZergGroundArmorsLevel2";"EvolutionChamber";309;0
"Upgrade";"EvolveGroovedSpines";"HydraliskDen";331;0
"Building";"CreepTumorQueen";NA;357;0
"Building";"CreepTumorQueen";NA;357;0
"Building";"CreepTumor";NA;357;0
"Building";"CreepTumorQueen";NA;357;0
"Building";"CreepTumor";NA;370;0
"Building";"CreepTumor";NA;370;0
"Unit";"Roach";"Larva";365;2
"Unit";"Roach";"Larva";365;2
"Unit";"Overlord";"Larva";369;0
"Unit";"Roach";"Larva";365;2
"Unit";"Roach";"Larva";365;2
"Unit";"Roach";"Larva";365;2
"Unit";"Overlord";"Larva";370;0
"Building";"CreepTumorQueen";NA;370;0
"Building";"CreepTumorQueen";NA;370;0
"Unit";"Overlord";"Larva";370;0
"Unit";"Infestor";"Larva";370;2
"Building";"Hatchery";NA;370;0
"Unit";"Hydralisk";"Larva";382;2
"Unit";"Hydralisk";"Larva";382;2
"Unit";"Hydralisk";"Larva";382;2
"Unit";"Hydralisk";"Larva";382;2
"Unit";"Hydralisk";"Larva";382;2
"Unit";"Hydralisk";"Larva";382;2
"Unit";"Hydralisk";"Larva";382;2
"Unit";"Hydralisk";"Larva";382;2
"Unit";"Hydralisk";"Larva";382;2
"Unit";"Hydralisk";"Larva";382;2
"Unit";"Hydralisk";"Larva";382;2
"Unit";"Hydralisk";"Larva";382;2
"Unit";"Hydralisk";"Larva";382;2
"Unit";"Hydralisk";"Larva";382;2
"Unit";"Hydralisk";"Larva";382;2
"Unit";"Hydralisk";"Larva";382;2
"Unit";"Hydralisk";"Larva";382;2
"Unit";"Hydralisk";"Larva";382;2
"Unit";"Hydralisk";"Larva";382;2
"Unit";"Hydralisk";"Larva";382;2
"Unit";"Hydralisk";"Larva";382;2
"Unit";"Hydralisk";"Larva";382;2
"Unit";"Hydralisk";"Larva";382;2
"Unit";"Zergling";"Larva";382;1
"Unit";"Zergling";"Larva";382;1
"Unit";"Zergling";"Larva";382;1
"Unit";"Zergling";"Larva";382;1
"Unit";"Zergling";"Larva";382;1
"Unit";"Zergling";"Larva";382;1
"Unit";"Zergling";"Larva";382;1
"Unit";"Zergling";"Larva";382;1
"Unit";"Zergling";"Larva";382;1
"Unit";"Zergling";"Larva";382;1
"Unit";"Zergling";"Larva";382;1
"Unit";"Zergling";"Larva";382;1
"Unit";"Zergling";"Larva";382;1
"Unit";"Zergling";"Larva";382;1
"Unit";"Queen";"Hatchery";382;2
"Upgrade";"ZergMeleeWeaponsLevel1";"EvolutionChamber";382;0
"Building";"CreepTumor";NA;444;0
"Unit";"Zergling";"Larva";448;1
"Unit";"Zergling";"Larva";448;1
"Unit";"Zergling";"Larva";448;1
"Unit";"Zergling";"Larva";448;1
"Unit";"Zergling";"Larva";448;1
"Unit";"Zergling";"Larva";448;1
"Unit";"Zergling";"Larva";448;1
"Unit";"Zergling";"Larva";448;1
"Unit";"Zergling";"Larva";448;1
"Unit";"Zergling";"Larva";448;1
"Unit";"Zergling";"Larva";448;1
"Unit";"Zergling";"Larva";448;1
"Unit";"Zergling";"Larva";448;1
"Unit";"Zergling";"Larva";448;1
"Unit";"Zergling";"Larva";448;1
"Unit";"Zergling";"Larva";448;1
"Unit";"Zergling";"Larva";448;1
"Unit";"Zergling";"Larva";448;1
"Unit";"Zergling";"Larva";448;1
"Unit";"Zergling";"Larva";448;1
"Building";"CreepTumor";NA;448;0
"Upgrade";"EvolveMuscularAugments";"HydraliskDen";444;0
"Building";"CreepTumor";NA;448;0
"Building";"RoachWarren";NA;448;0
"Building";"Hatchery";NA;448;0
"Unit";"Hydralisk";"Larva";468;2
"Unit";"Hydralisk";"Larva";468;2
"Unit";"Hydralisk";"Larva";468;2
"Unit";"Hydralisk";"Larva";468;2
"Unit";"Hydralisk";"Larva";468;2
"Unit";"Hydralisk";"Larva";468;2
"Unit";"Hydralisk";"Larva";468;2
"Unit";"Hydralisk";"Larva";468;2
"Unit";"Hydralisk";"Larva";468;2
"Unit";"Hydralisk";"Larva";468;2
"Unit";"Hydralisk";"Larva";468;2
"Unit";"Hydralisk";"Larva";468;2
"Building";"CreepTumor";NA;486;0
"Unit";"Roach";"Larva";486;2
"Unit";"Roach";"Larva";486;2
"Unit";"Roach";"Larva";486;2
"Unit";"Roach";"Larva";486;2
"Unit";"Infestor";"Larva";468;2
"Unit";"Roach";"Larva";492;2
"Unit";"Roach";"Larva";492;2
"Unit";"Roach";"Larva";492;2
"Unit";"Hydralisk";"Larva";500;2
"Unit";"Hydralisk";"Larva";500;2
"Unit";"Hydralisk";"Larva";500;2
"Unit";"Roach";"Larva";502;2
"Unit";"Infestor";"Larva";508;2
"Unit";"Roach";"Larva";516;2
"Unit";"Roach";"Larva";516;2
"Unit";"Roach";"Larva";516;2
"Unit";"Roach";"Larva";516;2
"Unit";"Roach";"Larva";516;2
"Unit";"Roach";"Larva";518;2
"Unit";"Roach";"Larva";518;2
