"type";"unit_name";"on_building";"total_supply";"supply"
"Unit";"Overlord";"Larva";12;0
"Building";"Extractor";NA;18;0
"Unit";"Overlord";"Larva";21;0
"Building";"SpawningPool";NA;19;0
"Building";"Hatchery";NA;17;0
"Unit";"Zergling";"Larva";22;1
"Unit";"Zergling";"Larva";22;1
"Unit";"Zergling";"Larva";22;1
"Unit";"Zergling";"Larva";22;1
"Unit";"Zergling";"Larva";22;1
"Unit";"Zergling";"Larva";22;1
"Unit";"Queen";"Hatchery";22;2
"Unit";"Queen";"Hatchery";22;2
"Building";"CreepTumorQueen";NA;36;0
"Unit";"Overlord";"Larva";37;0
"Unit";"Queen";"Hatchery";37;2
"Unit";"Queen";"Hatchery";37;2
"Building";"CreepTumorQueen";NA;42;0
"Building";"CreepTumor";NA;42;0
"Building";"CreepTumorQueen";NA;47;0
"Unit";"Overlord";"Larva";47;0
"Unit";"Overlord";"Larva";47;0
"Unit";"Overlord";"Larva";47;0
"Building";"CreepTumorQueen";NA;47;0
"Building";"CreepTumor";NA;47;0
"Unit";"Queen";"Hatchery";47;2
"Unit";"Queen";"Hatchery";47;2
"Unit";"Overlord";"Larva";47;0
"Building";"Hatchery";NA;38;0
"Unit";"Zergling";"Larva";47;1
"Unit";"Zergling";"Larva";47;1
"Unit";"Zergling";"Larva";47;1
"Unit";"Zergling";"Larva";47;1
"Unit";"Zergling";"Larva";47;1
"Unit";"Zergling";"Larva";47;1
"Unit";"Overlord";"Larva";57;0
"Building";"Extractor";NA;57;0
"Unit";"Zergling";"Larva";63;1
"Unit";"Zergling";"Larva";63;1
"Unit";"Zergling";"Larva";63;1
"Unit";"Zergling";"Larva";63;1
"Unit";"Zergling";"Larva";63;1
"Unit";"Zergling";"Larva";63;1
"Unit";"Zergling";"Larva";63;1
"Unit";"Zergling";"Larva";63;1
"Unit";"Zergling";"Larva";63;1
"Unit";"Zergling";"Larva";63;1
"Building";"Extractor";NA;63;0
"Unit";"Zergling";"Larva";63;1
"Unit";"Zergling";"Larva";63;1
"Unit";"Zergling";"Larva";63;1
"Unit";"Zergling";"Larva";63;1
"Unit";"Zergling";"Larva";63;1
"Unit";"Zergling";"Larva";63;1
"Building";"SporeCrawler";NA;64;0
"Building";"SporeCrawler";NA;64;0
"Unit";"Zergling";"Larva";80;1
"Unit";"Zergling";"Larva";80;1
"Unit";"Zergling";"Larva";80;1
"Unit";"Zergling";"Larva";80;1
"Building";"SporeCrawler";NA;80;0
"Building";"CreepTumorQueen";NA;84;0
"Building";"CreepTumorQueen";NA;87;0
"Building";"CreepTumorQueen";NA;87;0
"Unit";"Queen";"Hatchery";64;2
"Unit";"Overlord";"Larva";84;0
"Building";"CreepTumorQueen";NA;93;0
"Building";"CreepTumorQueen";NA;93;0
"Building";"CreepTumorQueen";NA;93;0
"Unit";"Zergling";"Larva";93;1
"Unit";"Zergling";"Larva";93;1
"Unit";"Zergling";"Larva";93;1
"Unit";"Zergling";"Larva";93;1
"Unit";"Zergling";"Larva";93;1
"Unit";"Zergling";"Larva";93;1
"Unit";"Zergling";"Larva";93;1
"Unit";"Zergling";"Larva";93;1
"Unit";"Zergling";"Larva";93;1
"Unit";"Zergling";"Larva";93;1
"Unit";"Zergling";"Larva";93;1
"Unit";"Zergling";"Larva";93;1
"Unit";"Zergling";"Larva";93;1
"Unit";"Zergling";"Larva";93;1
"Unit";"Zergling";"Larva";95;1
"Unit";"Zergling";"Larva";95;1
"Building";"CreepTumor";NA;110;0
"Building";"CreepTumor";NA;110;0
"Building";"CreepTumor";NA;110;0
"Building";"CreepTumor";NA;110;0
"Building";"CreepTumor";NA;110;0
"Building";"CreepTumorQueen";NA;111;0
"Unit";"Zergling";"Larva";106;1
"Unit";"Zergling";"Larva";106;1
"Building";"CreepTumor";NA;110;0
"Unit";"Zergling";"Larva";106;1
"Unit";"Zergling";"Larva";106;1
"Building";"CreepTumorQueen";NA;111;0
"Unit";"Zergling";"Larva";114;1
"Unit";"Zergling";"Larva";114;1
"Building";"RoachWarren";NA;110;0
"Building";"CreepTumor";NA;126;0
"Building";"CreepTumor";NA;126;0
"Building";"CreepTumor";NA;126;0
"Building";"CreepTumor";NA;126;0
"Building";"CreepTumor";NA;126;0
"Unit";"Overlord";"Larva";126;0
"Unit";"Overlord";"Larva";128;0
"Unit";"Roach";"Larva";129;2
"Unit";"Roach";"Larva";129;2
"Unit";"Roach";"Larva";129;2
"Unit";"Zergling";"Larva";135;1
"Unit";"Zergling";"Larva";135;1
"Unit";"Zergling";"Larva";135;1
"Unit";"Zergling";"Larva";135;1
"Unit";"Zergling";"Larva";135;1
"Unit";"Zergling";"Larva";135;1
"Building";"CreepTumor";NA;135;0
"Unit";"Zergling";"Larva";135;1
"Unit";"Zergling";"Larva";135;1
"Unit";"Roach";"Larva";135;2
"Unit";"Roach";"Larva";135;2
"Unit";"Roach";"Larva";135;2
"Unit";"Roach";"Larva";135;2
"Unit";"Roach";"Larva";135;2
"Building";"Extractor";NA;135;0
"Building";"Extractor";NA;135;0
"Building";"CreepTumor";NA;162;0
"Building";"EvolutionChamber";NA;135;0
"Building";"CreepTumorQueen";NA;164;0
"Building";"CreepTumorQueen";NA;164;0
"Building";"EvolutionChamber";NA;140;0
"Unit";"Zergling";"Larva";164;1
"Unit";"Zergling";"Larva";164;1
"Unit";"Zergling";"Larva";164;1
"Unit";"Zergling";"Larva";164;1
"Unit";"Overlord";"Larva";165;0
"Unit";"Overlord";"Larva";165;0
"Unit";"Overlord";"Larva";165;0
"Unit";"Overlord";"Larva";166;0
"Unit";"Overlord";"Larva";166;0
"Building";"CreepTumor";NA;172;0
"Building";"CreepTumor";NA;172;0
"Building";"CreepTumor";NA;172;0
"Building";"CreepTumorQueen";NA;172;0
"Building";"CreepTumorQueen";NA;172;0
"Unit";"Overlord";"Larva";172;0
"Unit";"Overlord";"Larva";172;0
"Building";"BanelingNest";NA;165;0
"Building";"Spire";NA;135;0
"Unit";"Zergling";"Larva";172;1
"Unit";"Zergling";"Larva";172;1
"Unit";"Zergling";"Larva";175;1
"Unit";"Zergling";"Larva";175;1
"Unit";"Zergling";"Larva";175;1
"Unit";"Zergling";"Larva";175;1
"Unit";"Zergling";"Larva";175;1
"Unit";"Zergling";"Larva";175;1
"Unit";"Zergling";"Larva";175;1
"Unit";"Zergling";"Larva";175;1
"Unit";"Zergling";"Larva";176;1
"Unit";"Zergling";"Larva";176;1
"Unit";"Zergling";"Larva";178;1
"Unit";"Zergling";"Larva";178;1
"Unit";"Zergling";"Larva";178;1
"Unit";"Zergling";"Larva";178;1
"Unit";"Zergling";"Larva";178;1
"Unit";"Zergling";"Larva";178;1
"Unit";"Zergling";"Larva";178;1
"Unit";"Zergling";"Larva";178;1
"Unit";"Zergling";"Larva";178;1
"Unit";"Zergling";"Larva";178;1
"Unit";"Zergling";"Larva";180;1
"Unit";"Zergling";"Larva";180;1
"Unit";"Zergling";"Larva";180;1
"Unit";"Zergling";"Larva";180;1
"Unit";"Zergling";"Larva";190;1
"Unit";"Zergling";"Larva";190;1
"Building";"Hatchery";NA;166;0
"Unit";"Zergling";"Larva";200;1
"Unit";"Zergling";"Larva";200;1
"Unit";"Zergling";"Larva";200;1
"Unit";"Zergling";"Larva";200;1
"Unit";"Zergling";"Larva";200;1
"Unit";"Zergling";"Larva";200;1
"Unit";"Zergling";"Larva";200;1
"Unit";"Zergling";"Larva";200;1
"Unit";"Zergling";"Larva";200;1
"Unit";"Zergling";"Larva";200;1
"Unit";"Zergling";"Larva";223;1
"Unit";"Zergling";"Larva";223;1
"Unit";"Mutalisk";"Larva";223;2
"Unit";"Mutalisk";"Larva";223;2
"Unit";"Mutalisk";"Larva";223;2
"Unit";"Mutalisk";"Larva";223;2
"Unit";"Mutalisk";"Larva";223;2
"Upgrade";"ZergMeleeWeaponsLevel1";"EvolutionChamber";178;0
"Unit";"Mutalisk";"Larva";223;2
"Building";"CreepTumor";NA;223;0
"Unit";"Mutalisk";"Larva";223;2
"Unit";"Mutalisk";"Larva";223;2
"Building";"CreepTumor";NA;223;0
"Upgrade";"ZergGroundArmorsLevel1";"EvolutionChamber";178;0
"Unit";"Zergling";"Larva";223;1
"Unit";"Zergling";"Larva";223;1
"Unit";"Zergling";"Larva";223;1
"Unit";"Zergling";"Larva";223;1
"Building";"Extractor";NA;223;0
"Unit";"Zergling";"Larva";223;1
"Unit";"Zergling";"Larva";223;1
"Unit";"Zergling";"Larva";223;1
"Unit";"Zergling";"Larva";223;1
"Building";"Extractor";NA;223;0
"Building";"CreepTumorQueen";NA;237;0
"Unit";"Baneling";"Zergling";237;0
"Unit";"Baneling";"Zergling";237;0
"Unit";"Baneling";"Zergling";237;0
"Unit";"Baneling";"Zergling";237;0
"Unit";"Queen";"Hatchery";223;2
"Unit";"Mutalisk";"Larva";237;2
"Unit";"Mutalisk";"Larva";237;2
"Building";"CreepTumor";NA;251;0
"Unit";"Mutalisk";"Larva";237;2
"Unit";"Overlord";"Larva";237;0
"Unit";"Overlord";"Larva";237;0
"Unit";"Overlord";"Larva";237;0
"Unit";"Overlord";"Larva";237;0
"Building";"CreepTumorQueen";NA;251;0
"Unit";"Overlord";"Larva";239;0
"Building";"CreepTumor";NA;251;0
"Unit";"Overlord";"Larva";241;0
"Building";"CreepTumor";NA;251;0
"Building";"CreepTumorQueen";NA;251;0
"Unit";"Overlord";"Larva";251;0
"Building";"CreepTumorQueen";NA;251;0
"Building";"CreepTumorQueen";NA;251;0
"Unit";"Overlord";"Larva";251;0
"Unit";"Overlord";"Larva";251;0
"Building";"CreepTumorQueen";NA;259;0
"Unit";"Overlord";"Larva";251;0
"Unit";"Overlord";"Larva";251;0
"Building";"CreepTumorQueen";NA;259;0
"Building";"CreepTumorQueen";NA;259;0
"Building";"CreepTumorQueen";NA;259;0
"Unit";"Baneling";"Zergling";259;0
"Unit";"Baneling";"Zergling";259;0
"Unit";"Baneling";"Zergling";259;0
"Unit";"Baneling";"Zergling";259;0
"Unit";"Baneling";"Zergling";259;0
"Unit";"Baneling";"Zergling";259;0
"Unit";"Baneling";"Zergling";259;0
"Unit";"Baneling";"Zergling";259;0
"Building";"CreepTumorQueen";NA;261;0
"Unit";"Zergling";"Larva";261;1
"Unit";"Zergling";"Larva";261;1
"Unit";"Zergling";"Larva";261;1
"Unit";"Zergling";"Larva";261;1
"Unit";"Zergling";"Larva";261;1
"Unit";"Zergling";"Larva";261;1
"Unit";"Zergling";"Larva";261;1
"Unit";"Zergling";"Larva";261;1
"Unit";"Zergling";"Larva";261;1
"Unit";"Zergling";"Larva";261;1
"Unit";"Zergling";"Larva";261;1
"Unit";"Zergling";"Larva";261;1
"Unit";"Zergling";"Larva";261;1
"Unit";"Zergling";"Larva";261;1
"Unit";"Zergling";"Larva";261;1
"Unit";"Zergling";"Larva";261;1
"Unit";"Zergling";"Larva";261;1
"Unit";"Zergling";"Larva";261;1
"Unit";"Zergling";"Larva";261;1
"Unit";"Zergling";"Larva";261;1
"Building";"CreepTumorQueen";NA;261;0
"Building";"CreepTumorQueen";NA;261;0
"Unit";"Zergling";"Larva";261;1
"Unit";"Zergling";"Larva";261;1
"Unit";"Zergling";"Larva";261;1
"Unit";"Zergling";"Larva";261;1
"Unit";"Zergling";"Larva";261;1
"Unit";"Zergling";"Larva";261;1
"Unit";"Zergling";"Larva";261;1
"Unit";"Zergling";"Larva";261;1
"Unit";"Zergling";"Larva";261;1
"Unit";"Zergling";"Larva";261;1
"Unit";"Zergling";"Larva";261;1
"Unit";"Zergling";"Larva";261;1
"Unit";"Zergling";"Larva";261;1
"Unit";"Zergling";"Larva";261;1
"Unit";"Baneling";"Zergling";281;0
"Unit";"Baneling";"Zergling";281;0
"Unit";"Zergling";"Larva";261;1
"Unit";"Zergling";"Larva";261;1
"Unit";"Baneling";"Zergling";281;0
"Unit";"Baneling";"Zergling";281;0
"Unit";"Baneling";"Zergling";281;0
"Unit";"Baneling";"Zergling";281;0
"Unit";"Zergling";"Larva";261;1
"Unit";"Zergling";"Larva";261;1
"Unit";"Baneling";"Zergling";281;0
"Unit";"Baneling";"Zergling";281;0
"Unit";"Zergling";"Larva";261;1
"Unit";"Zergling";"Larva";261;1
"Unit";"Zergling";"Larva";261;1
"Unit";"Zergling";"Larva";261;1
"Unit";"Zergling";"Larva";261;1
"Unit";"Zergling";"Larva";261;1
"Building";"Hatchery";NA;251;0
"Building";"CreepTumor";NA;295;0
"Unit";"Mutalisk";"Larva";289;2
"Unit";"Mutalisk";"Larva";291;2
"Unit";"Mutalisk";"Larva";293;2
"Unit";"Zergling";"Larva";305;1
"Unit";"Zergling";"Larva";305;1
"Unit";"Zergling";"Larva";305;1
"Unit";"Zergling";"Larva";305;1
"Unit";"Zergling";"Larva";305;1
"Unit";"Zergling";"Larva";305;1
"Unit";"Zergling";"Larva";305;1
"Unit";"Zergling";"Larva";305;1
"Unit";"Zergling";"Larva";305;1
"Unit";"Zergling";"Larva";305;1
"Unit";"Zergling";"Larva";305;1
"Unit";"Zergling";"Larva";305;1
"Unit";"Zergling";"Larva";305;1
"Unit";"Zergling";"Larva";305;1
"Unit";"Zergling";"Larva";305;1
"Unit";"Zergling";"Larva";305;1
"Unit";"Zergling";"Larva";305;1
"Unit";"Zergling";"Larva";305;1
"Unit";"Zergling";"Larva";305;1
"Unit";"Zergling";"Larva";305;1
"Unit";"Zergling";"Larva";305;1
"Unit";"Zergling";"Larva";305;1
"Unit";"Zergling";"Larva";305;1
"Unit";"Zergling";"Larva";305;1
"Unit";"Zergling";"Larva";305;1
"Unit";"Zergling";"Larva";305;1
"Unit";"Zergling";"Larva";305;1
"Unit";"Zergling";"Larva";305;1
"Building";"InfestationPit";NA;281;0
"Unit";"Zergling";"Larva";305;1
"Unit";"Zergling";"Larva";305;1
"Unit";"Zergling";"Larva";305;1
"Unit";"Zergling";"Larva";305;1
"Unit";"Zergling";"Larva";305;1
"Unit";"Zergling";"Larva";305;1
"Unit";"Zergling";"Larva";305;1
"Unit";"Zergling";"Larva";305;1
"Unit";"Zergling";"Larva";305;1
"Unit";"Zergling";"Larva";305;1
"Unit";"Zergling";"Larva";307;1
"Unit";"Zergling";"Larva";307;1
"Unit";"Zergling";"Larva";309;1
"Unit";"Zergling";"Larva";309;1
"Unit";"Zergling";"Larva";311;1
"Unit";"Zergling";"Larva";311;1
"Unit";"Zergling";"Larva";311;1
"Unit";"Zergling";"Larva";311;1
"Building";"CreepTumorQueen";NA;339;0
"Building";"CreepTumor";NA;339;0
"Building";"CreepTumor";NA;339;0
"Building";"CreepTumor";NA;339;0
"Building";"CreepTumor";NA;339;0
"Building";"CreepTumor";NA;339;0
"Building";"CreepTumor";NA;339;0
"Building";"CreepTumor";NA;339;0
"Building";"CreepTumor";NA;339;0
"Building";"CreepTumor";NA;339;0
"Building";"CreepTumorQueen";NA;339;0
"Unit";"Queen";"Hatchery";305;2
"Unit";"Mutalisk";"Larva";313;2
"Unit";"Zergling";"Larva";339;1
"Unit";"Zergling";"Larva";339;1
"Unit";"Zergling";"Larva";339;1
"Unit";"Zergling";"Larva";339;1
"Unit";"Zergling";"Larva";339;1
"Unit";"Zergling";"Larva";339;1
"Unit";"Zergling";"Larva";339;1
"Unit";"Zergling";"Larva";339;1
"Unit";"Zergling";"Larva";339;1
"Unit";"Zergling";"Larva";339;1
"Unit";"Zergling";"Larva";339;1
"Unit";"Zergling";"Larva";339;1
"Building";"CreepTumorQueen";NA;357;0
"Building";"CreepTumorQueen";NA;357;0
"Building";"CreepTumor";NA;357;0
"Unit";"Mutalisk";"Larva";357;2
"Unit";"Mutalisk";"Larva";357;2
"Unit";"Mutalisk";"Larva";357;2
"Unit";"Mutalisk";"Larva";357;2
"Unit";"Mutalisk";"Larva";357;2
"Unit";"Zergling";"Larva";373;1
"Unit";"Zergling";"Larva";373;1
"Unit";"Zergling";"Larva";373;1
"Unit";"Zergling";"Larva";373;1
"Unit";"Zergling";"Larva";373;1
"Unit";"Zergling";"Larva";373;1
"Unit";"Zergling";"Larva";373;1
"Unit";"Zergling";"Larva";373;1
"Unit";"Zergling";"Larva";373;1
"Unit";"Zergling";"Larva";373;1
"Unit";"Zergling";"Larva";373;1
"Unit";"Zergling";"Larva";373;1
"Building";"CreepTumorQueen";NA;373;0
"Unit";"Baneling";"Zergling";373;0
"Unit";"Overlord";"Larva";373;0
"Unit";"Baneling";"Zergling";373;0
"Unit";"Baneling";"Zergling";373;0
"Unit";"Overlord";"Larva";373;0
"Unit";"Baneling";"Zergling";373;0
"Unit";"Baneling";"Zergling";373;0
"Unit";"Baneling";"Zergling";373;0
"Unit";"Baneling";"Zergling";373;0
"Unit";"Overlord";"Larva";373;0
"Unit";"Baneling";"Zergling";373;0
"Unit";"Baneling";"Zergling";373;0
"Unit";"Baneling";"Zergling";373;0
"Unit";"Baneling";"Zergling";373;0
"Unit";"Baneling";"Zergling";373;0
"Unit";"Baneling";"Zergling";373;0
"Unit";"Baneling";"Zergling";373;0
"Unit";"Baneling";"Zergling";373;0
"Unit";"Baneling";"Zergling";373;0
"Unit";"Baneling";"Zergling";373;0
"Unit";"Baneling";"Zergling";373;0
"Unit";"Baneling";"Zergling";373;0
"Upgrade";"ZergGroundArmorsLevel2";"EvolutionChamber";295;0
"Building";"CreepTumor";NA;395;0
"Unit";"Mutalisk";"Larva";395;2
"Unit";"Mutalisk";"Larva";395;2
"Building";"CreepTumor";NA;395;0
"Building";"CreepTumor";NA;395;0
"Building";"CreepTumor";NA;395;0
"Unit";"Zergling";"Larva";399;1
"Unit";"Zergling";"Larva";399;1
"Unit";"Zergling";"Larva";399;1
"Unit";"Zergling";"Larva";399;1
"Unit";"Zergling";"Larva";399;1
"Unit";"Zergling";"Larva";399;1
"Unit";"Zergling";"Larva";399;1
"Unit";"Zergling";"Larva";399;1
"Unit";"Zergling";"Larva";399;1
"Unit";"Zergling";"Larva";399;1
"Unit";"Zergling";"Larva";399;1
"Unit";"Zergling";"Larva";399;1
"Unit";"Zergling";"Larva";399;1
"Unit";"Zergling";"Larva";399;1
"Unit";"Zergling";"Larva";399;1
"Unit";"Zergling";"Larva";399;1
"Building";"Extractor";NA;399;0
"Unit";"Baneling";"Zergling";399;0
"Unit";"Baneling";"Zergling";399;0
"Unit";"Baneling";"Zergling";399;0
"Unit";"Baneling";"Zergling";399;0
"Unit";"Baneling";"Zergling";399;0
"Unit";"Baneling";"Zergling";399;0
"Unit";"Baneling";"Zergling";399;0
"Unit";"Baneling";"Zergling";399;0
"Upgrade";"ZergMeleeWeaponsLevel2";"EvolutionChamber";373;0
"Unit";"Zergling";"Larva";415;1
"Unit";"Zergling";"Larva";415;1
"Unit";"Zergling";"Larva";415;1
"Unit";"Zergling";"Larva";415;1
"Unit";"Zergling";"Larva";415;1
"Unit";"Zergling";"Larva";415;1
"Unit";"Zergling";"Larva";415;1
"Unit";"Zergling";"Larva";415;1
"Unit";"Zergling";"Larva";415;1
"Unit";"Zergling";"Larva";415;1
"Unit";"Zergling";"Larva";415;1
"Unit";"Zergling";"Larva";415;1
"Unit";"Zergling";"Larva";415;1
"Unit";"Zergling";"Larva";415;1
"Unit";"Zergling";"Larva";415;1
"Unit";"Zergling";"Larva";415;1
"Unit";"Zergling";"Larva";415;1
"Unit";"Zergling";"Larva";415;1
"Unit";"Zergling";"Larva";415;1
"Unit";"Zergling";"Larva";415;1
"Unit";"Zergling";"Larva";415;1
"Unit";"Zergling";"Larva";415;1
"Unit";"Zergling";"Larva";415;1
"Unit";"Zergling";"Larva";415;1
"Unit";"Zergling";"Larva";415;1
"Unit";"Zergling";"Larva";415;1
"Unit";"Zergling";"Larva";415;1
"Unit";"Zergling";"Larva";415;1
"Unit";"Zergling";"Larva";415;1
"Unit";"Zergling";"Larva";415;1
"Unit";"Zergling";"Larva";415;1
"Unit";"Zergling";"Larva";415;1
"Unit";"Zergling";"Larva";415;1
"Unit";"Zergling";"Larva";415;1
"Unit";"Zergling";"Larva";415;1
"Unit";"Zergling";"Larva";415;1
"Unit";"Zergling";"Larva";415;1
"Unit";"Zergling";"Larva";415;1
"Unit";"Zergling";"Larva";415;1
"Unit";"Zergling";"Larva";415;1
"Unit";"Baneling";"Zergling";427;0
"Unit";"Baneling";"Zergling";427;0
"Unit";"Baneling";"Zergling";427;0
"Unit";"Baneling";"Zergling";427;0
"Unit";"Baneling";"Zergling";427;0
"Unit";"Baneling";"Zergling";427;0
"Unit";"Baneling";"Zergling";427;0
"Unit";"Baneling";"Zergling";427;0
"Unit";"Zergling";"Larva";427;1
"Unit";"Zergling";"Larva";427;1
"Unit";"Zergling";"Larva";427;1
"Unit";"Zergling";"Larva";427;1
"Unit";"Zergling";"Larva";427;1
"Unit";"Zergling";"Larva";427;1
"Unit";"Zergling";"Larva";427;1
"Unit";"Zergling";"Larva";427;1
"Unit";"Zergling";"Larva";427;1
"Unit";"Zergling";"Larva";427;1
"Unit";"Zergling";"Larva";427;1
"Unit";"Zergling";"Larva";427;1
"Unit";"Zergling";"Larva";427;1
"Unit";"Zergling";"Larva";427;1
"Unit";"Zergling";"Larva";427;1
"Unit";"Zergling";"Larva";427;1
"Building";"CreepTumorQueen";NA;455;0
"Building";"CreepTumorQueen";NA;455;0
"Unit";"Baneling";"Zergling";455;0
"Unit";"Baneling";"Zergling";455;0
"Unit";"Baneling";"Zergling";455;0
"Unit";"Baneling";"Zergling";455;0
"Unit";"Baneling";"Zergling";455;0
"Unit";"Baneling";"Zergling";455;0
"Unit";"Baneling";"Zergling";455;0
"Unit";"Baneling";"Zergling";455;0
"Unit";"Baneling";"Zergling";455;0
"Unit";"Baneling";"Zergling";455;0
"Unit";"Baneling";"Zergling";455;0
"Unit";"Baneling";"Zergling";455;0
"Unit";"Baneling";"Zergling";455;0
"Unit";"Baneling";"Zergling";455;0
"Unit";"Baneling";"Zergling";455;0
"Unit";"Baneling";"Zergling";455;0
"Unit";"Baneling";"Zergling";455;0
"Unit";"Baneling";"Zergling";455;0
"Unit";"Baneling";"Zergling";455;0
"Unit";"Baneling";"Zergling";455;0
"Unit";"Baneling";"Zergling";455;0
"Unit";"Baneling";"Zergling";455;0
"Unit";"Baneling";"Zergling";455;0
"Unit";"Baneling";"Zergling";455;0
"Unit";"Baneling";"Zergling";455;0
"Unit";"Baneling";"Zergling";455;0
"Unit";"Baneling";"Zergling";455;0
"Unit";"Baneling";"Zergling";455;0
"Unit";"Baneling";"Zergling";455;0
"Unit";"Baneling";"Zergling";455;0
"Unit";"Baneling";"Zergling";455;0
"Unit";"Baneling";"Zergling";455;0
"Unit";"Baneling";"Zergling";455;0
"Unit";"Baneling";"Zergling";455;0
"Unit";"Baneling";"Zergling";455;0
"Unit";"Baneling";"Zergling";455;0
"Unit";"Baneling";"Zergling";455;0
"Unit";"Baneling";"Zergling";455;0
"Unit";"Baneling";"Zergling";455;0
"Unit";"Baneling";"Zergling";455;0
"Unit";"Baneling";"Zergling";455;0
"Unit";"Baneling";"Zergling";455;0
"Unit";"Baneling";"Zergling";455;0
"Building";"CreepTumorQueen";NA;471;0
"Unit";"Zergling";"Larva";471;1
"Unit";"Zergling";"Larva";471;1
"Unit";"Zergling";"Larva";471;1
"Unit";"Zergling";"Larva";471;1
"Unit";"Zergling";"Larva";471;1
"Unit";"Zergling";"Larva";471;1
"Unit";"Zergling";"Larva";471;1
"Unit";"Zergling";"Larva";471;1
"Unit";"Zergling";"Larva";471;1
"Unit";"Zergling";"Larva";471;1
"Unit";"Zergling";"Larva";471;1
"Unit";"Zergling";"Larva";471;1
"Unit";"Zergling";"Larva";471;1
"Unit";"Zergling";"Larva";471;1
"Unit";"Zergling";"Larva";471;1
"Unit";"Zergling";"Larva";471;1
"Unit";"Zergling";"Larva";471;1
"Unit";"Zergling";"Larva";471;1
"Unit";"Zergling";"Larva";471;1
"Unit";"Zergling";"Larva";471;1
"Unit";"Zergling";"Larva";471;1
"Unit";"Zergling";"Larva";471;1
"Unit";"Zergling";"Larva";471;1
"Unit";"Zergling";"Larva";471;1
"Unit";"Zergling";"Larva";471;1
"Unit";"Zergling";"Larva";471;1
"Unit";"Zergling";"Larva";471;1
"Unit";"Zergling";"Larva";471;1
"Unit";"Zergling";"Larva";473;1
"Unit";"Zergling";"Larva";473;1
"Unit";"Zergling";"Larva";473;1
"Unit";"Zergling";"Larva";473;1
"Unit";"Zergling";"Larva";473;1
"Unit";"Zergling";"Larva";473;1
"Unit";"Zergling";"Larva";473;1
"Unit";"Zergling";"Larva";473;1
"Unit";"Zergling";"Larva";475;1
"Unit";"Zergling";"Larva";475;1
"Unit";"Zergling";"Larva";475;1
"Unit";"Zergling";"Larva";475;1
"Unit";"Zergling";"Larva";479;1
"Unit";"Zergling";"Larva";479;1
"Unit";"Zergling";"Larva";479;1
"Unit";"Zergling";"Larva";479;1
"Unit";"Zergling";"Larva";483;1
"Unit";"Zergling";"Larva";483;1
"Unit";"Zergling";"Larva";483;1
"Unit";"Zergling";"Larva";483;1
"Unit";"Zergling";"Larva";497;1
"Unit";"Zergling";"Larva";497;1
"Unit";"Zergling";"Larva";497;1
"Unit";"Zergling";"Larva";497;1
"Unit";"Zergling";"Larva";497;1
"Unit";"Zergling";"Larva";497;1
"Unit";"Zergling";"Larva";497;1
"Unit";"Zergling";"Larva";497;1
"Unit";"Zergling";"Larva";497;1
"Unit";"Zergling";"Larva";497;1
"Building";"CreepTumor";NA;519;0
"Building";"CreepTumor";NA;519;0
"Building";"CreepTumor";NA;519;0
"Building";"CreepTumor";NA;519;0
"Unit";"Baneling";"Zergling";519;0
"Unit";"Baneling";"Zergling";519;0
"Unit";"Baneling";"Zergling";519;0
"Unit";"Baneling";"Zergling";519;0
"Unit";"Baneling";"Zergling";519;0
"Unit";"Baneling";"Zergling";519;0
"Unit";"Baneling";"Zergling";519;0
"Unit";"Baneling";"Zergling";519;0
"Unit";"Baneling";"Zergling";519;0
"Unit";"Baneling";"Zergling";519;0
"Unit";"Baneling";"Zergling";519;0
"Unit";"Baneling";"Zergling";519;0
"Unit";"Baneling";"Zergling";519;0
"Unit";"Baneling";"Zergling";519;0
"Unit";"Baneling";"Zergling";519;0
"Unit";"Baneling";"Zergling";519;0
"Unit";"Baneling";"Zergling";519;0
"Unit";"Baneling";"Zergling";519;0
"Unit";"Baneling";"Zergling";519;0
"Unit";"Baneling";"Zergling";519;0
"Unit";"Baneling";"Zergling";519;0
"Unit";"Baneling";"Zergling";519;0
"Unit";"Baneling";"Zergling";519;0
"Unit";"Baneling";"Zergling";519;0
"Unit";"Baneling";"Zergling";519;0
"Unit";"Baneling";"Zergling";519;0
"Building";"CreepTumor";NA;529;0
"Unit";"Zergling";"Larva";529;1
"Unit";"Zergling";"Larva";529;1
"Unit";"Zergling";"Larva";529;1
"Unit";"Zergling";"Larva";529;1
"Unit";"Zergling";"Larva";529;1
"Unit";"Zergling";"Larva";529;1
"Unit";"Zergling";"Larva";529;1
"Unit";"Zergling";"Larva";529;1
"Unit";"Zergling";"Larva";529;1
"Unit";"Zergling";"Larva";529;1
"Unit";"Zergling";"Larva";529;1
"Unit";"Zergling";"Larva";529;1
"Unit";"Zergling";"Larva";529;1
"Unit";"Zergling";"Larva";529;1
"Unit";"Zergling";"Larva";529;1
"Unit";"Zergling";"Larva";529;1
"Unit";"Zergling";"Larva";529;1
"Unit";"Zergling";"Larva";529;1
"Unit";"Zergling";"Larva";529;1
"Unit";"Zergling";"Larva";529;1
"Unit";"Zergling";"Larva";529;1
"Unit";"Zergling";"Larva";529;1
"Building";"Extractor";NA;529;0
"Building";"CreepTumorQueen";NA;529;0
"Building";"Extractor";NA;529;0
"Building";"CreepTumorQueen";NA;529;0
"Building";"CreepTumorQueen";NA;529;0
"Unit";"Zergling";"Larva";529;1
"Unit";"Zergling";"Larva";529;1
"Unit";"Zergling";"Larva";529;1
"Unit";"Zergling";"Larva";529;1
"Building";"CreepTumorQueen";NA;529;0
"Building";"UltraliskCavern";NA;519;0
"Building";"CreepTumorQueen";NA;551;0
"Building";"CreepTumorQueen";NA;555;0
"Building";"CreepTumorQueen";NA;555;0
"Unit";"Baneling";"Zergling";551;0
"Unit";"Baneling";"Zergling";555;0
"Unit";"Baneling";"Zergling";555;0
"Unit";"Baneling";"Zergling";555;0
"Unit";"Baneling";"Zergling";555;0
"Unit";"Baneling";"Zergling";555;0
"Unit";"Baneling";"Zergling";555;0
"Unit";"Baneling";"Zergling";555;0
"Unit";"Baneling";"Zergling";555;0
"Unit";"Baneling";"Zergling";555;0
"Unit";"Zergling";"Larva";555;1
"Unit";"Zergling";"Larva";555;1
"Unit";"Zergling";"Larva";555;1
"Unit";"Zergling";"Larva";555;1
"Unit";"Zergling";"Larva";555;1
"Unit";"Zergling";"Larva";555;1
"Unit";"Zergling";"Larva";555;1
"Unit";"Zergling";"Larva";555;1
"Unit";"Zergling";"Larva";555;1
"Unit";"Zergling";"Larva";555;1
"Unit";"Zergling";"Larva";555;1
"Unit";"Zergling";"Larva";555;1
"Unit";"Zergling";"Larva";555;1
"Unit";"Zergling";"Larva";555;1
"Unit";"Zergling";"Larva";555;1
"Unit";"Zergling";"Larva";555;1
"Unit";"Zergling";"Larva";555;1
"Unit";"Zergling";"Larva";555;1
"Unit";"Zergling";"Larva";555;1
"Unit";"Zergling";"Larva";555;1
"Unit";"Zergling";"Larva";555;1
"Unit";"Zergling";"Larva";555;1
"Unit";"Zergling";"Larva";555;1
"Unit";"Zergling";"Larva";555;1
"Unit";"Zergling";"Larva";555;1
"Unit";"Zergling";"Larva";555;1
"Unit";"Zergling";"Larva";555;1
"Unit";"Zergling";"Larva";555;1
"Unit";"Baneling";"Zergling";555;0
"Unit";"Queen";"Hatchery";529;2
"Unit";"Zergling";"Larva";555;1
"Unit";"Zergling";"Larva";555;1
"Unit";"Zergling";"Larva";555;1
"Unit";"Zergling";"Larva";555;1
"Unit";"Zergling";"Larva";555;1
"Unit";"Zergling";"Larva";555;1
"Unit";"Zergling";"Larva";555;1
"Unit";"Zergling";"Larva";555;1
"Unit";"Zergling";"Larva";555;1
"Unit";"Zergling";"Larva";555;1
"Unit";"Zergling";"Larva";555;1
"Unit";"Zergling";"Larva";555;1
"Unit";"Zergling";"Larva";555;1
"Unit";"Zergling";"Larva";555;1
"Unit";"Zergling";"Larva";555;1
"Unit";"Zergling";"Larva";555;1
"Unit";"Zergling";"Larva";555;1
"Unit";"Zergling";"Larva";555;1
"Unit";"Zergling";"Larva";555;1
"Unit";"Zergling";"Larva";555;1
"Unit";"Mutalisk";"Larva";583;2
"Unit";"Mutalisk";"Larva";583;2
"Unit";"Mutalisk";"Larva";583;2
"Unit";"Mutalisk";"Larva";583;2
"Unit";"Mutalisk";"Larva";583;2
"Building";"CreepTumorQueen";NA;605;0
"Building";"CreepTumorQueen";NA;605;0
"Unit";"Baneling";"Zergling";605;0
"Unit";"Baneling";"Zergling";605;0
"Unit";"Baneling";"Zergling";605;0
"Unit";"Baneling";"Zergling";605;0
"Unit";"Baneling";"Zergling";605;0
"Unit";"Baneling";"Zergling";605;0
"Unit";"Baneling";"Zergling";605;0
"Unit";"Baneling";"Zergling";605;0
"Unit";"Baneling";"Zergling";605;0
"Unit";"Baneling";"Zergling";605;0
"Unit";"Baneling";"Zergling";605;0
"Unit";"Baneling";"Zergling";605;0
"Unit";"Baneling";"Zergling";605;0
"Unit";"Baneling";"Zergling";605;0
"Unit";"Baneling";"Zergling";605;0
"Unit";"Baneling";"Zergling";605;0
"Unit";"Baneling";"Zergling";605;0
"Unit";"Baneling";"Zergling";605;0
"Building";"CreepTumorQueen";NA;609;0
"Building";"CreepTumorQueen";NA;615;0
"Building";"CreepTumorQueen";NA;615;0
"Building";"CreepTumorQueen";NA;615;0
"Building";"CreepTumorQueen";NA;615;0
"Unit";"Baneling";"Zergling";615;0
"Unit";"Baneling";"Zergling";615;0
"Unit";"Baneling";"Zergling";615;0
"Unit";"Baneling";"Zergling";615;0
"Unit";"Baneling";"Zergling";615;0
"Unit";"Baneling";"Zergling";615;0
"Unit";"Baneling";"Zergling";615;0
"Unit";"Baneling";"Zergling";615;0
"Unit";"Baneling";"Zergling";615;0
"Unit";"Baneling";"Zergling";615;0
"Unit";"Baneling";"Zergling";615;0
"Unit";"Baneling";"Zergling";615;0
"Unit";"Baneling";"Zergling";615;0
"Unit";"Baneling";"Zergling";615;0
"Unit";"Baneling";"Zergling";615;0
"Unit";"Baneling";"Zergling";615;0
"Unit";"Baneling";"Zergling";615;0
"Building";"CreepTumor";NA;615;0
"Building";"CreepTumor";NA;615;0
"Building";"CreepTumor";NA;615;0
"Upgrade";"ChitinousPlating";"UltraliskCavern";605;0
"Building";"CreepTumorQueen";NA;615;0
"Building";"CreepTumorQueen";NA;615;0
"Unit";"Ultralisk";"Larva";615;6
"Upgrade";"ZergMeleeWeaponsLevel3";"EvolutionChamber";555;0
"Upgrade";"ZergGroundArmorsLevel3";"EvolutionChamber";555;0
"Unit";"Ultralisk";"Larva";615;6
"Unit";"Ultralisk";"Larva";615;6
"Building";"CreepTumorQueen";NA;633;0
"Unit";"Ultralisk";"Larva";621;6
"Unit";"Ultralisk";"Larva";621;6
"Building";"Hatchery";NA;615;0
"Unit";"Baneling";"Zergling";645;0
"Unit";"Baneling";"Zergling";645;0
"Unit";"Baneling";"Zergling";645;0
"Unit";"Baneling";"Zergling";645;0
"Unit";"Baneling";"Zergling";645;0
"Unit";"Baneling";"Zergling";645;0
"Unit";"Baneling";"Zergling";645;0
"Unit";"Baneling";"Zergling";645;0
"Unit";"Baneling";"Zergling";645;0
"Unit";"Baneling";"Zergling";645;0
"Unit";"Baneling";"Zergling";645;0
"Unit";"Baneling";"Zergling";645;0
"Unit";"Baneling";"Zergling";645;0
"Unit";"Baneling";"Zergling";645;0
"Unit";"Baneling";"Zergling";645;0
"Unit";"Baneling";"Zergling";645;0
"Unit";"Baneling";"Zergling";645;0
"Unit";"Baneling";"Zergling";645;0
"Unit";"Baneling";"Zergling";645;0
"Unit";"Ultralisk";"Larva";633;6
"Unit";"Ultralisk";"Larva";633;6
"Unit";"Zergling";"Larva";645;1
"Unit";"Zergling";"Larva";645;1
"Unit";"Zergling";"Larva";645;1
"Unit";"Zergling";"Larva";645;1
"Unit";"Zergling";"Larva";645;1
"Unit";"Zergling";"Larva";645;1
"Unit";"Zergling";"Larva";645;1
"Unit";"Zergling";"Larva";645;1
"Unit";"Zergling";"Larva";645;1
"Unit";"Zergling";"Larva";645;1
"Unit";"Zergling";"Larva";645;1
"Unit";"Zergling";"Larva";645;1
"Unit";"Zergling";"Larva";645;1
"Unit";"Zergling";"Larva";645;1
"Unit";"Zergling";"Larva";645;1
"Unit";"Zergling";"Larva";645;1
"Unit";"Zergling";"Larva";645;1
"Unit";"Zergling";"Larva";645;1
"Unit";"Zergling";"Larva";645;1
"Unit";"Zergling";"Larva";645;1
"Unit";"Zergling";"Larva";645;1
"Unit";"Zergling";"Larva";645;1
"Unit";"Zergling";"Larva";645;1
"Unit";"Zergling";"Larva";645;1
"Unit";"Zergling";"Larva";645;1
"Unit";"Zergling";"Larva";645;1
"Unit";"Zergling";"Larva";645;1
"Unit";"Zergling";"Larva";645;1
"Unit";"Zergling";"Larva";645;1
"Unit";"Zergling";"Larva";645;1
"Unit";"Zergling";"Larva";645;1
"Unit";"Zergling";"Larva";645;1
"Unit";"Zergling";"Larva";645;1
"Unit";"Zergling";"Larva";645;1
"Unit";"Zergling";"Larva";645;1
"Unit";"Zergling";"Larva";645;1
"Unit";"Zergling";"Larva";645;1
"Unit";"Zergling";"Larva";645;1
"Unit";"Zergling";"Larva";645;1
"Unit";"Zergling";"Larva";645;1
"Building";"CreepTumor";NA;645;0
"Building";"CreepTumor";NA;645;0
"Building";"CreepTumor";NA;645;0
"Building";"CreepTumor";NA;645;0
"Unit";"Zergling";"Larva";697;1
"Unit";"Zergling";"Larva";697;1
"Unit";"Zergling";"Larva";697;1
"Unit";"Zergling";"Larva";697;1
"Unit";"Zergling";"Larva";697;1
"Unit";"Zergling";"Larva";697;1
"Unit";"Zergling";"Larva";697;1
"Unit";"Zergling";"Larva";697;1
"Unit";"Zergling";"Larva";697;1
"Unit";"Zergling";"Larva";697;1
"Unit";"Zergling";"Larva";697;1
"Unit";"Zergling";"Larva";697;1
"Unit";"Zergling";"Larva";709;1
"Unit";"Zergling";"Larva";709;1
"Unit";"Zergling";"Larva";709;1
"Unit";"Zergling";"Larva";709;1
"Unit";"Zergling";"Larva";709;1
"Unit";"Zergling";"Larva";709;1
"Unit";"Zergling";"Larva";709;1
"Unit";"Zergling";"Larva";709;1
"Unit";"Zergling";"Larva";709;1
"Unit";"Zergling";"Larva";709;1
"Unit";"Zergling";"Larva";709;1
"Unit";"Zergling";"Larva";709;1
"Unit";"Zergling";"Larva";709;1
"Unit";"Zergling";"Larva";709;1
"Unit";"Zergling";"Larva";709;1
"Unit";"Zergling";"Larva";709;1
"Unit";"Zergling";"Larva";709;1
"Unit";"Zergling";"Larva";709;1
"Unit";"Zergling";"Larva";709;1
"Unit";"Zergling";"Larva";709;1
"Unit";"Zergling";"Larva";709;1
"Unit";"Zergling";"Larva";709;1
"Unit";"Zergling";"Larva";709;1
"Unit";"Zergling";"Larva";709;1
"Unit";"Zergling";"Larva";709;1
"Unit";"Zergling";"Larva";709;1
"Unit";"Zergling";"Larva";709;1
"Unit";"Zergling";"Larva";709;1
"Unit";"Zergling";"Larva";709;1
"Unit";"Zergling";"Larva";709;1
"Unit";"Zergling";"Larva";709;1
"Unit";"Zergling";"Larva";709;1
"Unit";"Zergling";"Larva";709;1
"Unit";"Zergling";"Larva";709;1
"Unit";"Zergling";"Larva";709;1
"Unit";"Zergling";"Larva";709;1
"Unit";"Overlord";"Larva";747;0
"Building";"CreepTumor";NA;749;0
"Building";"CreepTumor";NA;749;0
"Building";"CreepTumor";NA;749;0
"Building";"CreepTumor";NA;749;0
"Building";"CreepTumor";NA;749;0
"Building";"CreepTumor";NA;749;0
"Building";"CreepTumor";NA;749;0
"Unit";"Zergling";"Larva";749;1
"Unit";"Zergling";"Larva";749;1
"Unit";"Zergling";"Larva";749;1
"Unit";"Zergling";"Larva";749;1
"Unit";"Zergling";"Larva";749;1
"Unit";"Zergling";"Larva";749;1
"Unit";"Zergling";"Larva";749;1
"Unit";"Zergling";"Larva";749;1
"Unit";"Zergling";"Larva";749;1
"Unit";"Zergling";"Larva";749;1
"Unit";"Zergling";"Larva";749;1
"Unit";"Zergling";"Larva";749;1
"Unit";"Zergling";"Larva";749;1
"Unit";"Zergling";"Larva";749;1
"Unit";"Zergling";"Larva";757;1
"Unit";"Zergling";"Larva";757;1
"Unit";"Zergling";"Larva";757;1
"Unit";"Zergling";"Larva";757;1
"Unit";"Zergling";"Larva";757;1
"Unit";"Zergling";"Larva";757;1
"Unit";"Zergling";"Larva";757;1
"Unit";"Zergling";"Larva";757;1
"Unit";"Mutalisk";"Larva";771;2
"Building";"CreepTumorQueen";NA;771;0
"Building";"CreepTumorQueen";NA;771;0
"Building";"CreepTumorQueen";NA;771;0
"Building";"CreepTumorQueen";NA;771;0
"Building";"CreepTumorQueen";NA;771;0
"Unit";"Corruptor";"Larva";771;2
"Unit";"Ultralisk";"Larva";763;6
"Unit";"Ultralisk";"Larva";763;6
"Building";"CreepTumor";NA;788;0
"Building";"CreepTumor";NA;788;0
"Building";"CreepTumor";NA;788;0
"Building";"Hatchery";NA;771;0
"Unit";"Infestor";"Larva";787;2
"Unit";"Infestor";"Larva";787;2
"Unit";"Infestor";"Larva";787;2
"Unit";"Infestor";"Larva";787;2
"Unit";"Infestor";"Larva";787;2
"Unit";"Zergling";"Larva";788;1
"Unit";"Zergling";"Larva";788;1
"Unit";"Zergling";"Larva";788;1
"Unit";"Zergling";"Larva";788;1
"Unit";"Ultralisk";"Larva";788;6
"Unit";"Zergling";"Larva";788;1
"Unit";"Zergling";"Larva";788;1
"Unit";"Zergling";"Larva";788;1
"Unit";"Zergling";"Larva";788;1
"Unit";"Zergling";"Larva";807;1
"Unit";"Zergling";"Larva";807;1
"Unit";"Zergling";"Larva";807;1
"Unit";"Zergling";"Larva";807;1
"Unit";"Zergling";"Larva";807;1
"Unit";"Zergling";"Larva";807;1
"Unit";"Zergling";"Larva";807;1
"Unit";"Zergling";"Larva";807;1
"Unit";"Zergling";"Larva";807;1
"Unit";"Zergling";"Larva";807;1
"Unit";"Zergling";"Larva";807;1
"Unit";"Zergling";"Larva";807;1
"Unit";"Zergling";"Larva";821;1
"Unit";"Zergling";"Larva";821;1
"Unit";"Zergling";"Larva";821;1
"Unit";"Zergling";"Larva";821;1
"Unit";"Zergling";"Larva";821;1
"Unit";"Zergling";"Larva";821;1
"Upgrade";"Burrow";"Hatchery";788;0
