"type";"unit_name";"on_building";"total_supply";"supply"
"Unit";"Overlord";"Larva";13;0
"Building";"Extractor";NA;19;0
"Building";"SpawningPool";NA;19;0
"Unit";"Overlord";"Larva";22;0
"Building";"Hatchery";NA;17;0
"Unit";"Zergling";"Larva";22;1
"Unit";"Zergling";"Larva";22;1
"Unit";"Zergling";"Larva";23;1
"Unit";"Zergling";"Larva";23;1
"Unit";"Zergling";"Larva";23;1
"Unit";"Zergling";"Larva";23;1
"Unit";"Queen";"Hatchery";22;2
"Unit";"Queen";"Hatchery";23;2
"Unit";"Overlord";"Larva";37;0
"Unit";"Overlord";"Larva";39;0
"Building";"CreepTumorQueen";NA;40;0
"Unit";"Queen";"Hatchery";37;2
"Unit";"Overlord";"Larva";40;0
"Building";"Hatchery";NA;32;0
"Unit";"Zergling";"Larva";49;1
"Unit";"Zergling";"Larva";49;1
"Unit";"Zergling";"Larva";49;1
"Unit";"Zergling";"Larva";49;1
"Unit";"Zergling";"Larva";50;1
"Unit";"Zergling";"Larva";50;1
"Unit";"Zergling";"Larva";50;1
"Unit";"Zergling";"Larva";50;1
"Unit";"Zergling";"Larva";50;1
"Unit";"Zergling";"Larva";50;1
"Building";"CreepTumorQueen";NA;54;0
"Unit";"Overlord";"Larva";50;0
"Unit";"Queen";"Hatchery";50;2
"Unit";"Queen";"Hatchery";50;2
"Unit";"Queen";"Hatchery";55;2
"Building";"CreepTumorQueen";NA;70;0
"Unit";"Overlord";"Larva";74;0
"Building";"SporeCrawler";NA;74;0
"Unit";"Overlord";"Larva";74;0
"Unit";"Overlord";"Larva";74;0
"Unit";"Queen";"Hatchery";63;2
"Unit";"Queen";"Hatchery";65;2
"Building";"CreepTumor";NA;76;0
"Building";"CreepTumorQueen";NA;76;0
"Unit";"Queen";"Hatchery";74;2
"Building";"SporeCrawler";NA;76;0
"Building";"SporeCrawler";NA;76;0
"Unit";"Zergling";"Larva";80;1
"Unit";"Zergling";"Larva";80;1
"Unit";"Zergling";"Larva";80;1
"Unit";"Zergling";"Larva";80;1
"Unit";"Zergling";"Larva";80;1
"Unit";"Zergling";"Larva";80;1
"Unit";"Zergling";"Larva";80;1
"Unit";"Zergling";"Larva";80;1
"Unit";"Zergling";"Larva";80;1
"Unit";"Zergling";"Larva";80;1
"Unit";"Zergling";"Larva";80;1
"Unit";"Zergling";"Larva";80;1
"Unit";"Zergling";"Larva";80;1
"Unit";"Zergling";"Larva";80;1
"Unit";"Zergling";"Larva";80;1
"Unit";"Zergling";"Larva";80;1
"Unit";"Zergling";"Larva";80;1
"Unit";"Zergling";"Larva";80;1
"Unit";"Zergling";"Larva";80;1
"Unit";"Zergling";"Larva";80;1
"Unit";"Zergling";"Larva";80;1
"Unit";"Zergling";"Larva";80;1
"Unit";"Zergling";"Larva";80;1
"Unit";"Zergling";"Larva";80;1
"Unit";"Zergling";"Larva";80;1
"Unit";"Zergling";"Larva";80;1
"Unit";"Overlord";"Larva";121;0
"Building";"Extractor";NA;121;0
"Building";"Extractor";NA;121;0
"Building";"Extractor";NA;121;0
"Building";"CreepTumor";NA;130;0
"Building";"CreepTumor";NA;132;0
"Building";"CreepTumorQueen";NA;132;0
"Building";"CreepTumorQueen";NA;134;0
"Building";"Extractor";NA;130;0
"Building";"CreepTumorQueen";NA;134;0
"Building";"Extractor";NA;130;0
"Building";"CreepTumorQueen";NA;134;0
"Building";"BanelingNest";NA;124;0
"Building";"Hatchery";NA;121;0
"Building";"EvolutionChamber";NA;134;0
"Building";"EvolutionChamber";NA;134;0
"Unit";"Overlord";"Larva";134;0
"Unit";"Overlord";"Larva";134;0
"Unit";"Overlord";"Larva";134;0
"Building";"CreepTumor";NA;142;0
"Building";"CreepTumorQueen";NA;145;0
"Building";"CreepTumorQueen";NA;145;0
"Unit";"Overlord";"Larva";145;0
"Building";"CreepTumor";NA;145;0
"Unit";"Overlord";"Larva";145;0
"Unit";"Overlord";"Larva";145;0
"Building";"CreepTumor";NA;145;0
"Building";"CreepTumor";NA;145;0
"Building";"HydraliskDen";NA;139;0
"Building";"CreepTumorQueen";NA;145;0
"Building";"CreepTumor";NA;145;0
"Building";"CreepTumor";NA;145;0
"Building";"CreepTumorQueen";NA;152;0
"Building";"CreepTumor";NA;150;0
"Building";"Extractor";NA;150;0
"Building";"Extractor";NA;152;0
"Building";"CreepTumor";NA;152;0
"Building";"CreepTumor";NA;152;0
"Building";"CreepTumor";NA;152;0
"Building";"CreepTumor";NA;152;0
"Building";"CreepTumor";NA;152;0
"Building";"CreepTumor";NA;160;0
"Building";"CreepTumorQueen";NA;160;0
"Building";"CreepTumor";NA;160;0
"Building";"InfestationPit";NA;152;0
"Unit";"Baneling";"Zergling";160;0
"Unit";"Baneling";"Zergling";160;0
"Unit";"Baneling";"Zergling";160;0
"Unit";"Baneling";"Zergling";160;0
"Unit";"Baneling";"Zergling";160;0
"Building";"CreepTumor";NA;164;0
"Unit";"Hydralisk";"Larva";159;2
"Unit";"Hydralisk";"Larva";159;2
"Unit";"Hydralisk";"Larva";160;2
"Unit";"Hydralisk";"Larva";160;2
"Unit";"Baneling";"Zergling";160;0
"Unit";"Hydralisk";"Larva";160;2
"Building";"CreepTumor";NA;164;0
"Building";"CreepTumor";NA;164;0
"Unit";"Hydralisk";"Larva";160;2
"Unit";"Hydralisk";"Larva";160;2
"Unit";"Hydralisk";"Larva";160;2
"Unit";"Overlord";"Larva";164;0
"Unit";"Overlord";"Larva";164;0
"Unit";"Overlord";"Larva";164;0
"Unit";"Zergling";"Larva";174;1
"Unit";"Zergling";"Larva";174;1
"Unit";"Hydralisk";"Larva";174;2
"Unit";"Hydralisk";"Larva";174;2
"Unit";"Hydralisk";"Larva";174;2
"Unit";"Hydralisk";"Larva";174;2
"Upgrade";"EvolveGroovedSpines";"HydraliskDen";160;0
"Unit";"Hydralisk";"Larva";182;2
"Unit";"Hydralisk";"Larva";182;2
"Unit";"Hydralisk";"Larva";182;2
"Unit";"Hydralisk";"Larva";182;2
"Unit";"Hydralisk";"Larva";182;2
"Unit";"Hydralisk";"Larva";182;2
"Unit";"Hydralisk";"Larva";182;2
"Unit";"Hydralisk";"Larva";182;2
"Unit";"Hydralisk";"Larva";182;2
"Unit";"Zergling";"Larva";190;1
"Unit";"Zergling";"Larva";190;1
"Unit";"Zergling";"Larva";190;1
"Unit";"Zergling";"Larva";190;1
"Unit";"Zergling";"Larva";190;1
"Unit";"Zergling";"Larva";190;1
"Unit";"Zergling";"Larva";190;1
"Unit";"Zergling";"Larva";190;1
"Unit";"Zergling";"Larva";190;1
"Unit";"Zergling";"Larva";190;1
"Unit";"Zergling";"Larva";190;1
"Unit";"Zergling";"Larva";190;1
"Unit";"Hydralisk";"Larva";190;2
"Unit";"Hydralisk";"Larva";190;2
"Unit";"Hydralisk";"Larva";190;2
"Building";"CreepTumor";NA;190;0
"Building";"CreepTumor";NA;190;0
"Building";"CreepTumor";NA;190;0
"Building";"CreepTumor";NA;190;0
"Building";"CreepTumor";NA;190;0
"Building";"CreepTumor";NA;196;0
"Building";"CreepTumor";NA;208;0
"Building";"CreepTumor";NA;208;0
"Building";"CreepTumor";NA;208;0
"Upgrade";"ZergMissileWeaponsLevel1";"EvolutionChamber";160;0
"Upgrade";"ZergGroundArmorsLevel1";"EvolutionChamber";160;0
"Unit";"Overlord";"Larva";226;0
"Unit";"Overlord";"Larva";226;0
"Unit";"Queen";"Hatchery";190;2
"Unit";"Baneling";"Zergling";235;0
"Unit";"Baneling";"Zergling";235;0
"Unit";"Baneling";"Zergling";235;0
"Unit";"Baneling";"Zergling";235;0
"Unit";"Baneling";"Zergling";235;0
"Unit";"Baneling";"Zergling";235;0
"Unit";"Baneling";"Zergling";235;0
"Building";"CreepTumor";NA;237;0
"Building";"CreepTumor";NA;237;0
"Building";"CreepTumor";NA;237;0
"Building";"CreepTumor";NA;237;0
"Building";"CreepTumor";NA;237;0
"Building";"CreepTumor";NA;237;0
"Building";"CreepTumor";NA;237;0
"Building";"CreepTumor";NA;237;0
"Building";"CreepTumor";NA;237;0
"Building";"CreepTumor";NA;237;0
"Building";"CreepTumor";NA;237;0
"Building";"CreepTumor";NA;237;0
"Building";"CreepTumor";NA;237;0
"Building";"CreepTumor";NA;237;0
"Building";"CreepTumor";NA;237;0
"Building";"SporeCrawler";NA;237;0
"Building";"Hatchery";NA;226;0
"Building";"CreepTumor";NA;237;0
"Unit";"Overlord";"Larva";237;0
"Unit";"Overlord";"Larva";237;0
"Unit";"Overlord";"Larva";237;0
"Building";"CreepTumor";NA;237;0
"Unit";"Overlord";"Larva";237;0
"Unit";"Overlord";"Larva";237;0
"Building";"CreepTumor";NA;237;0
"Building";"CreepTumor";NA;237;0
"Upgrade";"EvolveMuscularAugments";"HydraliskDen";237;0
"Building";"CreepTumor";NA;237;0
"Building";"CreepTumor";NA;237;0
"Building";"CreepTumor";NA;237;0
"Building";"CreepTumor";NA;237;0
"Building";"Extractor";NA;237;0
"Building";"Extractor";NA;237;0
"Building";"CreepTumor";NA;240;0
"Building";"CreepTumor";NA;240;0
"Building";"CreepTumor";NA;240;0
"Building";"CreepTumor";NA;240;0
"Building";"CreepTumor";NA;240;0
"Building";"CreepTumor";NA;240;0
"Building";"CreepTumor";NA;240;0
"Building";"CreepTumor";NA;240;0
"Building";"SporeCrawler";NA;240;0
"Unit";"Zergling";"Larva";240;1
"Unit";"Zergling";"Larva";240;1
"Unit";"Zergling";"Larva";240;1
"Unit";"Zergling";"Larva";240;1
"Unit";"Zergling";"Larva";240;1
"Unit";"Zergling";"Larva";240;1
"Building";"SpineCrawler";NA;240;0
"Unit";"Zergling";"Larva";240;1
"Unit";"Zergling";"Larva";240;1
"Unit";"Zergling";"Larva";240;1
"Unit";"Zergling";"Larva";240;1
"Unit";"Zergling";"Larva";240;1
"Unit";"Zergling";"Larva";240;1
"Unit";"Zergling";"Larva";240;1
"Unit";"Zergling";"Larva";240;1
"Unit";"Zergling";"Larva";240;1
"Unit";"Zergling";"Larva";240;1
"Unit";"Zergling";"Larva";240;1
"Unit";"Zergling";"Larva";240;1
"Building";"SpineCrawler";NA;240;0
"Unit";"Baneling";"Zergling";240;0
"Unit";"Baneling";"Zergling";240;0
"Upgrade";"ZergMissileWeaponsLevel2";"EvolutionChamber";237;0
"Upgrade";"ZergGroundArmorsLevel2";"EvolutionChamber";237;0
"Unit";"Zergling";"Larva";258;1
"Unit";"Zergling";"Larva";258;1
"Building";"Hatchery";NA;237;0
"Unit";"Zergling";"Larva";258;1
"Unit";"Zergling";"Larva";258;1
"Unit";"Zergling";"Larva";258;1
"Unit";"Zergling";"Larva";258;1
"Unit";"Zergling";"Larva";258;1
"Unit";"Zergling";"Larva";258;1
"Unit";"Zergling";"Larva";258;1
"Unit";"Zergling";"Larva";258;1
"Unit";"Zergling";"Larva";258;1
"Unit";"Zergling";"Larva";258;1
"Unit";"Zergling";"Larva";258;1
"Unit";"Zergling";"Larva";258;1
"Unit";"Zergling";"Larva";258;1
"Unit";"Zergling";"Larva";258;1
"Unit";"Zergling";"Larva";258;1
"Unit";"Zergling";"Larva";258;1
"Unit";"Zergling";"Larva";258;1
"Unit";"Zergling";"Larva";258;1
"Unit";"Zergling";"Larva";258;1
"Unit";"Zergling";"Larva";258;1
"Unit";"Zergling";"Larva";258;1
"Unit";"Zergling";"Larva";258;1
"Unit";"Zergling";"Larva";258;1
"Unit";"Zergling";"Larva";258;1
"Unit";"Zergling";"Larva";258;1
"Unit";"Zergling";"Larva";258;1
"Unit";"Hydralisk";"Larva";258;2
"Unit";"Hydralisk";"Larva";258;2
"Unit";"Hydralisk";"Larva";258;2
"Unit";"Hydralisk";"Larva";258;2
"Unit";"Zergling";"Larva";258;1
"Unit";"Zergling";"Larva";258;1
"Unit";"Zergling";"Larva";258;1
"Unit";"Zergling";"Larva";258;1
"Unit";"Zergling";"Larva";258;1
"Unit";"Zergling";"Larva";258;1
"Unit";"Zergling";"Larva";258;1
"Unit";"Zergling";"Larva";258;1
"Unit";"Zergling";"Larva";258;1
"Unit";"Zergling";"Larva";258;1
"Unit";"Zergling";"Larva";258;1
"Unit";"Zergling";"Larva";258;1
"Unit";"Zergling";"Larva";258;1
"Unit";"Zergling";"Larva";258;1
"Unit";"Zergling";"Larva";258;1
"Unit";"Zergling";"Larva";258;1
"Building";"SpineCrawler";NA;258;0
"Unit";"Baneling";"Zergling";286;0
"Unit";"Baneling";"Zergling";286;0
"Unit";"Baneling";"Zergling";286;0
"Unit";"Baneling";"Zergling";286;0
"Unit";"Baneling";"Zergling";286;0
"Building";"SpineCrawler";NA;258;0
"Unit";"Baneling";"Zergling";286;0
"Unit";"Baneling";"Zergling";286;0
"Unit";"Baneling";"Zergling";288;0
"Unit";"Baneling";"Zergling";288;0
"Unit";"Baneling";"Zergling";290;0
"Unit";"Baneling";"Zergling";294;0
"Unit";"Baneling";"Zergling";294;0
"Unit";"Baneling";"Zergling";294;0
"Unit";"Baneling";"Zergling";294;0
"Unit";"Baneling";"Zergling";294;0
"Unit";"Baneling";"Zergling";294;0
"Unit";"Baneling";"Zergling";294;0
"Unit";"Baneling";"Zergling";294;0
"Unit";"Baneling";"Zergling";294;0
"Unit";"Baneling";"Zergling";294;0
"Unit";"Baneling";"Zergling";294;0
"Unit";"Baneling";"Zergling";294;0
"Unit";"Baneling";"Zergling";294;0
"Unit";"Baneling";"Zergling";294;0
"Unit";"Baneling";"Zergling";294;0
"Unit";"Baneling";"Zergling";294;0
"Unit";"Baneling";"Zergling";294;0
"Unit";"Baneling";"Zergling";294;0
"Building";"SpineCrawler";NA;258;0
"Unit";"Baneling";"Zergling";304;0
"Unit";"Baneling";"Zergling";304;0
"Unit";"Baneling";"Zergling";304;0
"Unit";"Baneling";"Zergling";304;0
"Unit";"Baneling";"Zergling";304;0
"Unit";"Baneling";"Zergling";304;0
"Unit";"Baneling";"Zergling";310;0
"Unit";"Baneling";"Zergling";310;0
"Unit";"Hydralisk";"Larva";310;2
"Unit";"Hydralisk";"Larva";310;2
"Unit";"Hydralisk";"Larva";310;2
"Unit";"Hydralisk";"Larva";310;2
"Unit";"Hydralisk";"Larva";310;2
"Unit";"Hydralisk";"Larva";310;2
"Unit";"Hydralisk";"Larva";310;2
"Unit";"Hydralisk";"Larva";310;2
"Unit";"Hydralisk";"Larva";310;2
"Unit";"Hydralisk";"Larva";310;2
"Unit";"Hydralisk";"Larva";310;2
"Unit";"Hydralisk";"Larva";310;2
"Unit";"Hydralisk";"Larva";310;2
"Unit";"Hydralisk";"Larva";310;2
"Unit";"Hydralisk";"Larva";310;2
"Unit";"Hydralisk";"Larva";310;2
"Unit";"Hydralisk";"Larva";310;2
"Unit";"Hydralisk";"Larva";340;2
"Unit";"Hydralisk";"Larva";340;2
"Unit";"Hydralisk";"Larva";340;2
"Unit";"Hydralisk";"Larva";340;2
"Unit";"Hydralisk";"Larva";340;2
"Unit";"Hydralisk";"Larva";340;2
"Unit";"Hydralisk";"Larva";340;2
"Unit";"Hydralisk";"Larva";340;2
"Unit";"Zergling";"Larva";344;1
"Unit";"Zergling";"Larva";344;1
"Unit";"Zergling";"Larva";344;1
"Unit";"Zergling";"Larva";344;1
"Unit";"Zergling";"Larva";344;1
"Unit";"Zergling";"Larva";344;1
"Unit";"Zergling";"Larva";344;1
"Unit";"Zergling";"Larva";344;1
"Unit";"Zergling";"Larva";344;1
"Unit";"Zergling";"Larva";344;1
"Unit";"Zergling";"Larva";344;1
"Unit";"Zergling";"Larva";344;1
"Building";"CreepTumor";NA;372;0
"Building";"CreepTumor";NA;372;0
"Building";"CreepTumor";NA;372;0
"Building";"CreepTumor";NA;374;0
"Building";"CreepTumor";NA;376;0
"Building";"CreepTumorQueen";NA;376;0
"Building";"CreepTumorQueen";NA;376;0
"Unit";"Queen";"Hatchery";360;2
"Unit";"Baneling";"Zergling";376;0
"Unit";"Baneling";"Zergling";376;0
"Unit";"Baneling";"Zergling";376;0
"Unit";"Baneling";"Zergling";376;0
"Unit";"Baneling";"Zergling";376;0
"Unit";"Baneling";"Zergling";376;0
"Unit";"Baneling";"Zergling";376;0
"Unit";"Baneling";"Zergling";376;0
"Unit";"Baneling";"Zergling";376;0
"Unit";"Baneling";"Zergling";376;0
"Unit";"Baneling";"Zergling";376;0
"Unit";"Baneling";"Zergling";376;0
"Building";"CreepTumor";NA;377;0
"Building";"CreepTumor";NA;379;0
"Building";"SpineCrawler";NA;376;0
"Building";"CreepTumor";NA;379;0
"Building";"SpineCrawler";NA;377;0
"Building";"Hatchery";NA;360;0
"Unit";"Hydralisk";"Larva";379;2
"Unit";"Hydralisk";"Larva";379;2
"Unit";"Hydralisk";"Larva";379;2
"Unit";"Hydralisk";"Larva";379;2
"Unit";"Hydralisk";"Larva";379;2
"Unit";"Hydralisk";"Larva";379;2
"Unit";"Hydralisk";"Larva";379;2
"Unit";"Hydralisk";"Larva";379;2
"Unit";"Hydralisk";"Larva";379;2
"Unit";"Hydralisk";"Larva";379;2
"Unit";"Hydralisk";"Larva";379;2
"Unit";"Hydralisk";"Larva";379;2
"Building";"CreepTumor";NA;379;0
"Building";"CreepTumor";NA;379;0
"Building";"CreepTumor";NA;379;0
"Building";"CreepTumor";NA;379;0
"Unit";"Viper";"Larva";379;3
"Unit";"Viper";"Larva";379;3
"Unit";"Viper";"Larva";379;3
"Unit";"Viper";"Larva";379;3
"Unit";"Zergling";"Larva";379;1
"Unit";"Zergling";"Larva";379;1
"Unit";"Zergling";"Larva";379;1
"Unit";"Zergling";"Larva";379;1
"Unit";"Zergling";"Larva";379;1
"Unit";"Zergling";"Larva";379;1
"Unit";"Zergling";"Larva";379;1
"Unit";"Zergling";"Larva";379;1
"Unit";"Zergling";"Larva";379;1
"Unit";"Zergling";"Larva";379;1
"Unit";"Zergling";"Larva";379;1
"Unit";"Zergling";"Larva";379;1
"Unit";"Zergling";"Larva";379;1
"Unit";"Zergling";"Larva";379;1
"Unit";"Zergling";"Larva";379;1
"Unit";"Zergling";"Larva";379;1
"Unit";"Zergling";"Larva";379;1
"Unit";"Zergling";"Larva";379;1
"Unit";"Hydralisk";"Larva";379;2
"Building";"CreepTumorQueen";NA;403;0
"Unit";"Queen";"Hatchery";379;2
"Unit";"Queen";"Hatchery";379;2
"Building";"CreepTumorQueen";NA;433;0
"Unit";"Baneling";"Zergling";433;0
"Unit";"Baneling";"Zergling";433;0
"Unit";"Baneling";"Zergling";433;0
"Unit";"Baneling";"Zergling";433;0
"Unit";"Baneling";"Zergling";433;0
"Unit";"Baneling";"Zergling";433;0
"Unit";"Baneling";"Zergling";433;0
"Unit";"Baneling";"Zergling";433;0
"Unit";"Baneling";"Zergling";433;0
"Unit";"Baneling";"Zergling";433;0
"Unit";"Baneling";"Zergling";433;0
"Unit";"Baneling";"Zergling";433;0
"Unit";"Baneling";"Zergling";433;0
"Unit";"Baneling";"Zergling";433;0
"Unit";"Baneling";"Zergling";433;0
"Unit";"Baneling";"Zergling";433;0
"Unit";"Baneling";"Zergling";433;0
"Building";"CreepTumorQueen";NA;439;0
"Building";"CreepTumor";NA;439;0
"Building";"CreepTumor";NA;439;0
"Building";"Extractor";NA;439;0
"Building";"Extractor";NA;439;0
"Building";"CreepTumor";NA;439;0
"Building";"CreepTumor";NA;439;0
"Unit";"Queen";"Hatchery";439;2
"Unit";"Zergling";"Larva";439;1
"Unit";"Zergling";"Larva";439;1
"Unit";"Zergling";"Larva";439;1
"Unit";"Zergling";"Larva";439;1
"Unit";"Zergling";"Larva";439;1
"Unit";"Zergling";"Larva";439;1
"Unit";"Zergling";"Larva";439;1
"Unit";"Zergling";"Larva";439;1
"Unit";"Zergling";"Larva";439;1
"Unit";"Zergling";"Larva";439;1
"Unit";"Zergling";"Larva";439;1
"Unit";"Zergling";"Larva";439;1
"Unit";"Zergling";"Larva";439;1
"Unit";"Zergling";"Larva";439;1
"Unit";"Zergling";"Larva";439;1
"Unit";"Zergling";"Larva";439;1
"Unit";"Zergling";"Larva";439;1
"Unit";"Zergling";"Larva";439;1
"Unit";"Zergling";"Larva";439;1
"Unit";"Zergling";"Larva";439;1
"Building";"UltraliskCavern";NA;439;0
"Building";"CreepTumor";NA;441;0
"Building";"CreepTumor";NA;441;0
"Building";"CreepTumor";NA;441;0
"Building";"CreepTumor";NA;441;0
"Building";"CreepTumor";NA;442;0
"Building";"CreepTumor";NA;462;0
"Building";"CreepTumor";NA;462;0
