"type";"unit_name";"on_building";"total_supply";"supply"
"Unit";"Overlord";"Larva";13;0
"Building";"Extractor";NA;17;0
"Unit";"Overlord";"Larva";21;0
"Building";"Hatchery";NA;17;0
"Building";"SpawningPool";NA;19;0
"Unit";"Zergling";"Larva";23;1
"Unit";"Zergling";"Larva";23;1
"Unit";"Zergling";"Larva";23;1
"Unit";"Zergling";"Larva";23;1
"Unit";"Queen";"Hatchery";23;2
"Unit";"Queen";"Hatchery";23;2
"Unit";"Overlord";"Larva";36;0
"Unit";"Overlord";"Larva";37;0
"Unit";"Queen";"Hatchery";31;2
"Unit";"Queen";"Hatchery";36;2
"Building";"CreepTumorQueen";NA;44;0
"Building";"CreepTumorQueen";NA;44;0
"Unit";"Zergling";"Larva";51;1
"Unit";"Zergling";"Larva";51;1
"Unit";"Zergling";"Larva";51;1
"Unit";"Zergling";"Larva";51;1
"Building";"CreepTumor";NA;53;0
"Unit";"Zergling";"Larva";53;1
"Unit";"Zergling";"Larva";53;1
"Building";"CreepTumorQueen";NA;53;0
"Building";"CreepTumor";NA;53;0
"Building";"CreepTumorQueen";NA;53;0
"Unit";"Overlord";"Larva";53;0
"Unit";"Overlord";"Larva";57;0
"Unit";"Zergling";"Larva";57;1
"Unit";"Zergling";"Larva";57;1
"Building";"Extractor";NA;57;0
"Unit";"Overlord";"Larva";59;0
"Building";"RoachWarren";NA;53;0
"Building";"CreepTumor";NA;65;0
"Unit";"Zergling";"Larva";63;1
"Unit";"Zergling";"Larva";63;1
"Unit";"Zergling";"Larva";63;1
"Unit";"Zergling";"Larva";63;1
"Building";"CreepTumor";NA;65;0
"Building";"Hatchery";NA;51;0
"Unit";"Roach";"Larva";70;2
"Unit";"Roach";"Larva";70;2
"Unit";"Roach";"Larva";70;2
"Unit";"Roach";"Larva";70;2
"Unit";"Roach";"Larva";70;2
"Unit";"Roach";"Larva";70;2
"Unit";"Zergling";"Larva";70;1
"Unit";"Zergling";"Larva";70;1
"Unit";"Zergling";"Larva";70;1
"Unit";"Zergling";"Larva";70;1
"Unit";"Zergling";"Larva";70;1
"Unit";"Zergling";"Larva";70;1
"Unit";"Zergling";"Larva";70;1
"Unit";"Zergling";"Larva";70;1
"Unit";"Roach";"Larva";70;2
"Unit";"Roach";"Larva";70;2
"Unit";"Zergling";"Larva";82;1
"Unit";"Zergling";"Larva";82;1
"Unit";"Queen";"Hatchery";70;2
"Unit";"Roach";"Larva";82;2
"Unit";"Roach";"Larva";82;2
"Unit";"Queen";"Hatchery";70;2
"Building";"CreepTumor";NA;96;0
"Building";"Extractor";NA;94;0
"Unit";"Roach";"Larva";94;2
"Unit";"Roach";"Larva";94;2
"Unit";"Overlord";"Larva";108;0
"Unit";"Overlord";"Larva";108;0
"Unit";"Overlord";"Larva";108;0
"Unit";"Overlord";"Larva";108;0
"Building";"Extractor";NA;108;0
"Building";"CreepTumor";NA;115;0
"Unit";"Overlord";"Larva";115;0
"Unit";"Overlord";"Larva";115;0
"Building";"EvolutionChamber";NA;115;0
"Building";"EvolutionChamber";NA;115;0
"Unit";"Overlord";"Larva";115;0
"Unit";"Overlord";"Larva";115;0
"Unit";"Roach";"Larva";115;2
"Unit";"Roach";"Larva";115;2
"Building";"CreepTumor";NA;126;0
"Unit";"Roach";"Larva";126;2
"Unit";"Roach";"Larva";126;2
"Unit";"Roach";"Larva";130;2
"Unit";"Roach";"Larva";130;2
"Unit";"Roach";"Larva";130;2
"Unit";"Roach";"Larva";130;2
"Unit";"Roach";"Larva";130;2
"Unit";"Overlord";"Larva";130;0
"Building";"CreepTumor";NA;134;0
"Unit";"Roach";"Larva";134;2
"Unit";"Roach";"Larva";134;2
"Unit";"Roach";"Larva";134;2
"Building";"CreepTumor";NA;147;0
"Building";"Extractor";NA;147;0
"Unit";"Roach";"Larva";147;2
"Building";"BanelingNest";NA;130;0
"Unit";"Overlord";"Larva";157;0
"Unit";"Roach";"Larva";157;2
"Unit";"Roach";"Larva";157;2
"Unit";"Roach";"Larva";158;2
"Unit";"Roach";"Larva";160;2
"Unit";"Roach";"Larva";160;2
"Unit";"Roach";"Larva";160;2
"Unit";"Roach";"Larva";160;2
"Upgrade";"GlialReconstitution";"RoachWarren";134;0
"Unit";"Overlord";"Larva";162;0
"Unit";"Roach";"Larva";162;2
"Unit";"Overlord";"Larva";162;0
"Unit";"Overlord";"Larva";166;0
"Unit";"Overlord";"Larva";176;0
"Unit";"Overlord";"Larva";176;0
"Unit";"Zergling";"Larva";178;1
"Unit";"Zergling";"Larva";178;1
"Unit";"Zergling";"Larva";178;1
"Unit";"Zergling";"Larva";178;1
"Unit";"Zergling";"Larva";178;1
"Unit";"Zergling";"Larva";178;1
"Unit";"Zergling";"Larva";178;1
"Unit";"Zergling";"Larva";178;1
"Unit";"Zergling";"Larva";178;1
"Unit";"Zergling";"Larva";178;1
"Unit";"Zergling";"Larva";178;1
"Unit";"Zergling";"Larva";178;1
"Unit";"Zergling";"Larva";178;1
"Unit";"Zergling";"Larva";178;1
"Upgrade";"ZergMissileWeaponsLevel1";"EvolutionChamber";134;0
"Upgrade";"ZergGroundArmorsLevel1";"EvolutionChamber";134;0
"Unit";"Overlord";"Larva";178;0
"Unit";"Overlord";"Larva";178;0
"Unit";"Queen";"Hatchery";178;2
"Unit";"Roach";"Larva";192;2
"Unit";"Roach";"Larva";192;2
"Unit";"Roach";"Larva";192;2
"Unit";"Roach";"Larva";192;2
"Unit";"Roach";"Larva";192;2
"Unit";"Roach";"Larva";192;2
"Unit";"Roach";"Larva";192;2
"Unit";"Roach";"Larva";192;2
"Unit";"Roach";"Larva";192;2
"Unit";"Roach";"Larva";192;2
"Unit";"Queen";"Hatchery";192;2
"Building";"HydraliskDen";NA;194;0
"Unit";"Overlord";"Larva";214;0
"Unit";"Overlord";"Larva";214;0
"Unit";"Overlord";"Larva";214;0
"Building";"Extractor";NA;220;0
"Building";"CreepTumor";NA;220;0
"Building";"Hatchery";NA;214;0
"Unit";"Hydralisk";"Larva";220;2
"Unit";"Hydralisk";"Larva";220;2
"Unit";"Hydralisk";"Larva";220;2
"Unit";"Hydralisk";"Larva";220;2
"Unit";"Hydralisk";"Larva";220;2
"Unit";"Hydralisk";"Larva";220;2
"Unit";"Hydralisk";"Larva";220;2
"Unit";"Hydralisk";"Larva";220;2
"Unit";"Hydralisk";"Larva";220;2
"Unit";"Hydralisk";"Larva";220;2
"Unit";"Hydralisk";"Larva";220;2
"Unit";"Hydralisk";"Larva";220;2
"Unit";"Hydralisk";"Larva";220;2
"Unit";"Hydralisk";"Larva";220;2
"Building";"CreepTumorQueen";NA;220;0
"Unit";"Queen";"Hatchery";220;2
"Building";"CreepTumorQueen";NA;263;0
"Unit";"Hydralisk";"Larva";255;2
"Upgrade";"ZergMissileWeaponsLevel2";"EvolutionChamber";220;0
"Upgrade";"ZergGroundArmorsLevel2";"EvolutionChamber";220;0
"Unit";"Queen";"Hatchery";253;2
"Building";"InfestationPit";NA;255;0
"Unit";"Hydralisk";"Larva";264;2
"Unit";"Hydralisk";"Larva";264;2
"Unit";"Hydralisk";"Larva";264;2
"Unit";"Hydralisk";"Larva";264;2
"Unit";"Hydralisk";"Larva";264;2
"Building";"Hatchery";NA;221;0
"Building";"CreepTumor";NA;289;0
"Building";"CreepTumor";NA;289;0
"Unit";"Roach";"Larva";289;2
"Building";"Extractor";NA;289;0
"Building";"CreepTumor";NA;289;0
"Building";"Extractor";NA;289;0
"Unit";"Hydralisk";"Larva";289;2
"Unit";"Hydralisk";"Larva";289;2
"Unit";"Overlord";"Larva";291;0
"Upgrade";"EvolveMuscularAugments";"HydraliskDen";268;0
"Unit";"Hydralisk";"Larva";289;2
"Unit";"Hydralisk";"Larva";289;2
"Unit";"Hydralisk";"Larva";289;2
"Unit";"Overlord";"Larva";294;0
"Unit";"Overlord";"Larva";298;0
"Unit";"Overlord";"Larva";298;0
"Unit";"Overlord";"Larva";298;0
"Unit";"Overlord";"Larva";298;0
"Unit";"Overlord";"Larva";304;0
"Unit";"Hydralisk";"Larva";304;2
"Unit";"Hydralisk";"Larva";304;2
"Unit";"Hydralisk";"Larva";304;2
"Unit";"Hydralisk";"Larva";304;2
"Unit";"Hydralisk";"Larva";304;2
"Unit";"Hydralisk";"Larva";304;2
"Unit";"Overlord";"Larva";326;0
"Unit";"Viper";"Larva";314;3
"Unit";"Viper";"Larva";314;3
"Upgrade";"EvolveGroovedSpines";"HydraliskDen";304;0
"Unit";"Hydralisk";"Larva";326;2
"Unit";"Hydralisk";"Larva";326;2
"Unit";"Overlord";"Larva";326;0
"Unit";"Hydralisk";"Larva";326;2
"Unit";"Hydralisk";"Larva";326;2
"Unit";"Hydralisk";"Larva";326;2
"Unit";"Hydralisk";"Larva";326;2
"Unit";"Hydralisk";"Larva";326;2
"Unit";"Hydralisk";"Larva";326;2
"Building";"Spire";NA;304;0
"Unit";"Hydralisk";"Larva";326;2
"Unit";"Hydralisk";"Larva";326;2
"Unit";"Hydralisk";"Larva";352;2
"Unit";"Hydralisk";"Larva";352;2
"Unit";"Hydralisk";"Larva";352;2
"Unit";"Hydralisk";"Larva";352;2
"Unit";"Hydralisk";"Larva";352;2
"Unit";"Hydralisk";"Larva";352;2
"Unit";"Hydralisk";"Larva";352;2
"Unit";"Hydralisk";"Larva";352;2
"Unit";"Zergling";"Larva";352;1
"Unit";"Zergling";"Larva";352;1
"Unit";"Zergling";"Larva";352;1
"Unit";"Zergling";"Larva";352;1
"Unit";"Zergling";"Larva";352;1
"Unit";"Zergling";"Larva";352;1
"Unit";"Zergling";"Larva";352;1
"Unit";"Zergling";"Larva";352;1
"Unit";"Zergling";"Larva";368;1
"Unit";"Zergling";"Larva";368;1
"Unit";"Mutalisk";"Larva";354;2
"Unit";"Mutalisk";"Larva";360;2
"Unit";"Mutalisk";"Larva";368;2
"Unit";"Mutalisk";"Larva";368;2
"Unit";"Mutalisk";"Larva";376;2
"Unit";"Mutalisk";"Larva";376;2
"Unit";"Hydralisk";"Larva";376;2
"Unit";"Hydralisk";"Larva";376;2
"Unit";"Mutalisk";"Larva";386;2
"Unit";"Mutalisk";"Larva";386;2
"Unit";"Mutalisk";"Larva";386;2
"Building";"Extractor";NA;394;0
"Building";"Extractor";NA;394;0
"Unit";"Mutalisk";"Larva";397;2
"Unit";"Mutalisk";"Larva";397;2
"Building";"Hatchery";NA;376;0
"Unit";"Zergling";"Larva";407;1
"Unit";"Zergling";"Larva";407;1
"Unit";"Zergling";"Larva";407;1
"Unit";"Zergling";"Larva";407;1
"Unit";"Zergling";"Larva";407;1
"Unit";"Zergling";"Larva";407;1
"Unit";"Zergling";"Larva";407;1
"Unit";"Zergling";"Larva";407;1
"Unit";"Zergling";"Larva";407;1
"Unit";"Zergling";"Larva";407;1
"Unit";"Zergling";"Larva";407;1
"Unit";"Zergling";"Larva";407;1
"Building";"CreepTumor";NA;412;0
"Unit";"Viper";"Larva";412;3
"Unit";"Viper";"Larva";412;3
"Unit";"Hydralisk";"Larva";424;2
"Unit";"Hydralisk";"Larva";424;2
"Unit";"Hydralisk";"Larva";424;2
"Unit";"Hydralisk";"Larva";424;2
"Unit";"Hydralisk";"Larva";424;2
"Unit";"Hydralisk";"Larva";424;2
"Unit";"Hydralisk";"Larva";424;2
"Unit";"Hydralisk";"Larva";424;2
"Unit";"Hydralisk";"Larva";446;2
"Unit";"Hydralisk";"Larva";446;2
"Unit";"Hydralisk";"Larva";446;2
"Unit";"Hydralisk";"Larva";446;2
"Unit";"Hydralisk";"Larva";446;2
"Unit";"Hydralisk";"Larva";450;2
"Building";"Hatchery";NA;412;0
"Unit";"Hydralisk";"Larva";450;2
"Building";"CreepTumor";NA;456;0
"Building";"CreepTumorQueen";NA;460;0
"Building";"CreepTumorQueen";NA;462;0
"Unit";"Hydralisk";"Larva";450;2
"Unit";"Hydralisk";"Larva";450;2
"Building";"CreepTumorQueen";NA;464;0
"Building";"Extractor";NA;460;0
"Building";"Extractor";NA;462;0
"Unit";"Overlord";"Larva";464;0
"Unit";"Hydralisk";"Larva";464;2
"Unit";"Hydralisk";"Larva";464;2
"Unit";"Hydralisk";"Larva";472;2
"Unit";"Hydralisk";"Larva";472;2
"Unit";"Hydralisk";"Larva";472;2
"Unit";"Hydralisk";"Larva";472;2
"Unit";"Hydralisk";"Larva";472;2
"Unit";"Hydralisk";"Larva";472;2
"Unit";"Zergling";"Larva";476;1
"Unit";"Zergling";"Larva";476;1
"Unit";"Zergling";"Larva";476;1
"Unit";"Zergling";"Larva";476;1
"Unit";"Zergling";"Larva";476;1
"Unit";"Zergling";"Larva";476;1
"Unit";"Zergling";"Larva";476;1
"Unit";"Zergling";"Larva";476;1
"Unit";"Zergling";"Larva";476;1
"Unit";"Zergling";"Larva";476;1
"Unit";"Overlord";"Larva";482;0
"Unit";"Hydralisk";"Larva";480;2
"Unit";"Hydralisk";"Larva";480;2
"Unit";"Hydralisk";"Larva";482;2
"Unit";"Hydralisk";"Larva";482;2
"Building";"CreepTumor";NA;502;0
"Building";"CreepTumor";NA;502;0
"Unit";"Hydralisk";"Larva";498;2
"Unit";"Hydralisk";"Larva";498;2
"Unit";"Hydralisk";"Larva";498;2
"Unit";"Hydralisk";"Larva";498;2
"Unit";"Hydralisk";"Larva";498;2
"Building";"CreepTumor";NA;525;0
"Unit";"Hydralisk";"Larva";525;2
"Unit";"Hydralisk";"Larva";525;2
