"type";"unit_name";"on_building";"total_supply";"supply"
"Unit";"Overlord";"Larva";12;0
"Building";"SpawningPool";NA;16;0
"Building";"Extractor";NA;19;0
"Unit";"Zergling";"Larva";21;1
"Unit";"Zergling";"Larva";21;1
"Unit";"Zergling";"Larva";21;1
"Unit";"Zergling";"Larva";21;1
"Unit";"Queen";"Hatchery";20;2
"Unit";"Overlord";"Larva";21;0
"Building";"Hatchery";NA;19;0
"Unit";"Overlord";"Larva";27;0
"Unit";"Queen";"Hatchery";27;2
"Unit";"Overlord";"Larva";30;0
"Building";"RoachWarren";NA;27;0
"Unit";"Zergling";"Larva";34;1
"Unit";"Zergling";"Larva";34;1
"Unit";"Zergling";"Larva";34;1
"Unit";"Zergling";"Larva";34;1
"Unit";"Zergling";"Larva";34;1
"Unit";"Zergling";"Larva";34;1
"Unit";"Zergling";"Larva";34;1
"Unit";"Zergling";"Larva";34;1
"Unit";"Roach";"Larva";42;2
"Unit";"Roach";"Larva";42;2
"Unit";"Roach";"Larva";42;2
"Unit";"Roach";"Larva";42;2
"Unit";"Roach";"Larva";42;2
"Unit";"Roach";"Larva";42;2
"Unit";"Overlord";"Larva";42;0
"Unit";"Overlord";"Larva";42;0
"Unit";"Overlord";"Larva";54;0
"Unit";"Roach";"Larva";54;2
"Unit";"Zergling";"Larva";54;1
"Unit";"Zergling";"Larva";54;1
"Unit";"Zergling";"Larva";54;1
"Unit";"Zergling";"Larva";54;1
"Unit";"Zergling";"Larva";54;1
"Unit";"Zergling";"Larva";54;1
"Unit";"Zergling";"Larva";54;1
"Unit";"Zergling";"Larva";54;1
"Unit";"Zergling";"Larva";54;1
"Unit";"Zergling";"Larva";54;1
"Unit";"Zergling";"Larva";54;1
"Unit";"Zergling";"Larva";54;1
"Unit";"Zergling";"Larva";56;1
"Unit";"Zergling";"Larva";56;1
"Unit";"Overlord";"Larva";56;0
"Unit";"Overlord";"Larva";56;0
"Unit";"Zergling";"Larva";56;1
"Unit";"Zergling";"Larva";56;1
"Unit";"Zergling";"Larva";56;1
"Unit";"Zergling";"Larva";56;1
"Unit";"Zergling";"Larva";68;1
"Unit";"Zergling";"Larva";68;1
"Unit";"Zergling";"Larva";68;1
"Unit";"Zergling";"Larva";68;1
"Unit";"Zergling";"Larva";72;1
"Unit";"Zergling";"Larva";72;1
"Unit";"Zergling";"Larva";72;1
"Unit";"Zergling";"Larva";72;1
"Unit";"Zergling";"Larva";78;1
"Unit";"Zergling";"Larva";78;1
"Unit";"Zergling";"Larva";78;1
"Unit";"Zergling";"Larva";78;1
"Unit";"Zergling";"Larva";78;1
"Unit";"Zergling";"Larva";78;1
"Unit";"Roach";"Larva";82;2
"Unit";"Roach";"Larva";82;2
"Unit";"Queen";"Hatchery";96;2
"Unit";"Queen";"Hatchery";96;2
"Building";"CreepTumorQueen";NA;104;0
"Unit";"Overlord";"Larva";106;0
"Unit";"Roach";"Larva";110;2
"Unit";"Roach";"Larva";110;2
"Unit";"Roach";"Larva";110;2
"Building";"EvolutionChamber";NA;110;0
"Building";"CreepTumorQueen";NA;119;0
"Building";"CreepTumorQueen";NA;119;0
"Building";"CreepTumor";NA;119;0
"Building";"Extractor";NA;119;0
"Building";"Extractor";NA;119;0
"Building";"EvolutionChamber";NA;119;0
"Unit";"Overlord";"Larva";124;0
"Building";"CreepTumorQueen";NA;125;0
"Building";"CreepTumor";NA;125;0
"Building";"CreepTumor";NA;125;0
"Unit";"Overlord";"Larva";125;0
"Building";"CreepTumor";NA;125;0
"Building";"Hatchery";NA;104;0
"Unit";"Overlord";"Larva";125;0
"Building";"CreepTumor";NA;131;0
"Building";"CreepTumor";NA;131;0
"Building";"CreepTumor";NA;131;0
"Building";"CreepTumor";NA;131;0
"Building";"Extractor";NA;131;0
"Building";"CreepTumor";NA;141;0
"Building";"CreepTumor";NA;141;0
"Building";"CreepTumor";NA;141;0
"Building";"CreepTumor";NA;142;0
"Unit";"Overlord";"Larva";141;0
"Building";"CreepTumorQueen";NA;144;0
"Building";"CreepTumorQueen";NA;144;0
"Unit";"Roach";"Larva";144;2
"Unit";"Roach";"Larva";144;2
"Unit";"Roach";"Larva";144;2
"Unit";"Roach";"Larva";144;2
"Unit";"Roach";"Larva";144;2
"Unit";"Roach";"Larva";144;2
"Unit";"Roach";"Larva";144;2
"Unit";"Roach";"Larva";144;2
"Unit";"Roach";"Larva";144;2
"Building";"CreepTumor";NA;164;0
"Building";"CreepTumor";NA;164;0
"Unit";"Roach";"Larva";164;2
"Unit";"Roach";"Larva";164;2
"Unit";"Roach";"Larva";164;2
"Unit";"Overlord";"Larva";164;0
"Unit";"Overlord";"Larva";164;0
"Upgrade";"ZergGroundArmorsLevel1";"EvolutionChamber";131;0
"Unit";"Overlord";"Larva";170;0
"Building";"Extractor";NA;164;0
"Unit";"Overlord";"Larva";170;0
"Upgrade";"ZergMissileWeaponsLevel1";"EvolutionChamber";131;0
"Building";"HydraliskDen";NA;164;0
"Unit";"Roach";"Larva";170;2
"Unit";"Roach";"Larva";171;2
"Building";"CreepTumor";NA;178;0
"Building";"SporeCrawler";NA;171;0
"Building";"CreepTumor";NA;178;0
"Building";"SporeCrawler";NA;174;0
"Unit";"Roach";"Larva";184;2
"Unit";"Roach";"Larva";184;2
"Unit";"Roach";"Larva";184;2
"Unit";"Roach";"Larva";184;2
"Unit";"Roach";"Larva";184;2
"Unit";"Roach";"Larva";184;2
"Unit";"Roach";"Larva";184;2
"Unit";"Roach";"Larva";184;2
"Building";"Hatchery";NA;164;0
"Unit";"Roach";"Larva";184;2
"Unit";"Roach";"Larva";184;2
"Unit";"Roach";"Larva";184;2
"Unit";"Roach";"Larva";184;2
"Unit";"Roach";"Larva";184;2
"Unit";"Roach";"Larva";184;2
"Unit";"Roach";"Larva";184;2
"Unit";"Roach";"Larva";184;2
"Unit";"Roach";"Larva";184;2
"Unit";"Roach";"Larva";184;2
"Unit";"Roach";"Larva";200;2
"Unit";"Roach";"Larva";200;2
"Unit";"Roach";"Larva";200;2
"Unit";"Roach";"Larva";200;2
"Upgrade";"GlialReconstitution";"RoachWarren";181;0
"Building";"CreepTumor";NA;222;0
"Building";"CreepTumor";NA;227;0
"Building";"CreepTumor";NA;233;0
"Unit";"Hydralisk";"Larva";236;2
"Unit";"Hydralisk";"Larva";236;2
"Unit";"Hydralisk";"Larva";236;2
"Unit";"Hydralisk";"Larva";236;2
"Unit";"Hydralisk";"Larva";236;2
"Unit";"Hydralisk";"Larva";246;2
"Unit";"Hydralisk";"Larva";246;2
"Unit";"Hydralisk";"Larva";246;2
"Unit";"Hydralisk";"Larva";246;2
"Unit";"Hydralisk";"Larva";246;2
"Unit";"Hydralisk";"Larva";246;2
"Unit";"Hydralisk";"Larva";246;2
"Upgrade";"ZergGroundArmorsLevel2";"EvolutionChamber";186;0
"Unit";"Hydralisk";"Larva";246;2
"Unit";"Hydralisk";"Larva";246;2
"Unit";"Hydralisk";"Larva";246;2
"Unit";"Hydralisk";"Larva";260;2
"Unit";"Hydralisk";"Larva";260;2
"Unit";"Hydralisk";"Larva";266;2
"Unit";"Hydralisk";"Larva";266;2
