"type";"unit_name";"on_building";"total_supply_lag";"supply"
"Unit";"Overlord";"Larva";14;0
"Building";"SpawningPool";NA;17;0
"Building";"Hatchery";NA;18;0
"Building";"Extractor";NA;19;0
"Unit";"Zergling";"Larva";19;1
"Unit";"Zergling";"Larva";20;1
"Unit";"Zergling";"Larva";21;1
"Unit";"Zergling";"Larva";22;1
"Unit";"Zergling";"Larva";23;1
"Unit";"Zergling";"Larva";24;1
"Unit";"Queen";"Hatchery";25;2
"Unit";"Overlord";"Larva";27;0
"Unit";"Queen";"Hatchery";30;2
"Unit";"Zergling";"Larva";41;1
"Unit";"Zergling";"Larva";42;1
"Building";"Hatchery";NA;43;0
"Unit";"Zergling";"Larva";43;1
"Unit";"Zergling";"Larva";44;1
"Unit";"Overlord";"Larva";45;0
"Unit";"Zergling";"Larva";45;1
"Unit";"Zergling";"Larva";46;1
"Unit";"Zergling";"Larva";47;1
"Unit";"Zergling";"Larva";48;1
"Unit";"Overlord";"Larva";50;0
"Unit";"Zergling";"Larva";50;1
"Unit";"Zergling";"Larva";51;1
"Unit";"Zergling";"Larva";52;1
"Unit";"Zergling";"Larva";53;1
"Unit";"Zergling";"Larva";54;1
"Unit";"Zergling";"Larva";55;1
"Unit";"Zergling";"Larva";60;1
"Unit";"Zergling";"Larva";61;1
"Unit";"Queen";"Hatchery";62;2
"Unit";"Overlord";"Larva";64;0
"Unit";"Zergling";"Larva";64;1
"Unit";"Zergling";"Larva";65;1
"Unit";"Zergling";"Larva";66;1
"Unit";"Zergling";"Larva";67;1
"Unit";"Overlord";"Larva";72;0
"Building";"BanelingNest";NA;72;0
"Unit";"Overlord";"Larva";75;0
"Unit";"Queen";"Hatchery";76;2
"Unit";"Queen";"Hatchery";78;2
"Building";"CreepTumorQueen";NA;80;0
"Unit";"Zergling";"Larva";81;1
"Unit";"Zergling";"Larva";82;1
"Unit";"Zergling";"Larva";83;1
"Unit";"Zergling";"Larva";84;1
"Unit";"Zergling";"Larva";85;1
"Unit";"Zergling";"Larva";86;1
"Building";"Extractor";NA;87;0
"Unit";"Zergling";"Larva";89;1
"Unit";"Zergling";"Larva";90;1
"Unit";"Zergling";"Larva";91;1
"Unit";"Zergling";"Larva";92;1
"Unit";"Overlord";"Larva";93;0
"Building";"CreepTumor";NA;97;0
"Unit";"Queen";"Hatchery";97;2
"Unit";"Baneling";"Zergling";99;0
"Unit";"Baneling";"Zergling";99;0
"Unit";"Baneling";"Zergling";99;0
"Unit";"Baneling";"Zergling";99;0
"Unit";"Baneling";"Zergling";99;0
"Unit";"Queen";"Hatchery";99;2
"Building";"CreepTumorQueen";NA;101;0
"Building";"SporeCrawler";NA;101;0
"Building";"SporeCrawler";NA;101;0
"Building";"SporeCrawler";NA;104;0
"Unit";"Overlord";"Larva";104;0
"Building";"SporeCrawler";NA;105;0
"Unit";"Zergling";"Larva";106;1
"Unit";"Zergling";"Larva";107;1
"Unit";"Overlord";"Larva";108;0
"Unit";"Queen";"Hatchery";108;2
"Building";"Extractor";NA;113;0
"Building";"CreepTumorQueen";NA;115;0
"Building";"CreepTumorQueen";NA;115;0
"Building";"CreepTumorQueen";NA;117;0
"Building";"Extractor";NA;117;0
"Unit";"Overlord";"Larva";118;0
"Building";"EvolutionChamber";NA;123;0
"Building";"CreepTumorQueen";NA;123;0
"Building";"CreepTumorQueen";NA;123;0
"Building";"EvolutionChamber";NA;123;0
"Unit";"Zergling";"Larva";123;1
"Unit";"Zergling";"Larva";124;1
"Unit";"Zergling";"Larva";125;1
"Unit";"Zergling";"Larva";126;1
"Unit";"Zergling";"Larva";127;1
"Unit";"Zergling";"Larva";128;1
"Building";"CreepTumorQueen";NA;129;0
"Building";"CreepTumor";NA;129;0
"Building";"CreepTumor";NA;129;0
"Building";"CreepTumorQueen";NA;132;0
"Building";"Extractor";NA;134;0
"Unit";"Overlord";"Larva";134;0
"Unit";"Zergling";"Larva";134;1
"Unit";"Zergling";"Larva";135;1
"Unit";"Zergling";"Larva";136;1
"Unit";"Zergling";"Larva";137;1
"Unit";"Zergling";"Larva";138;1
"Unit";"Zergling";"Larva";139;1
"Unit";"Zergling";"Larva";140;1
"Unit";"Zergling";"Larva";141;1
"Unit";"Zergling";"Larva";142;1
"Unit";"Zergling";"Larva";143;1
"Unit";"Overlord";"Larva";144;0
"Unit";"Zergling";"Larva";144;1
"Unit";"Zergling";"Larva";145;1
"Unit";"Zergling";"Larva";146;1
"Unit";"Zergling";"Larva";147;1
"Unit";"Zergling";"Larva";148;1
"Unit";"Zergling";"Larva";149;1
"Building";"CreepTumor";NA;150;0
"Building";"HydraliskDen";NA;158;0
"Unit";"Zergling";"Larva";158;1
"Unit";"Zergling";"Larva";159;1
"Unit";"Zergling";"Larva";160;1
"Unit";"Zergling";"Larva";161;1
"Unit";"Zergling";"Larva";162;1
"Unit";"Zergling";"Larva";163;1
"Unit";"Zergling";"Larva";164;1
"Unit";"Zergling";"Larva";165;1
"Unit";"Zergling";"Larva";166;1
"Unit";"Zergling";"Larva";167;1
"Unit";"Zergling";"Larva";168;1
"Unit";"Zergling";"Larva";169;1
"Unit";"Zergling";"Larva";170;1
"Unit";"Zergling";"Larva";171;1
"Unit";"Zergling";"Larva";172;1
"Unit";"Zergling";"Larva";173;1
"Unit";"Zergling";"Larva";174;1
"Unit";"Zergling";"Larva";175;1
"Unit";"Zergling";"Larva";176;1
"Unit";"Zergling";"Larva";177;1
"Unit";"Baneling";"Zergling";178;0
"Unit";"Baneling";"Zergling";178;0
"Unit";"Baneling";"Zergling";178;0
"Building";"CreepTumorQueen";NA;178;0
"Unit";"Overlord";"Larva";178;0
"Building";"CreepTumorQueen";NA;178;0
"Unit";"Hydralisk";"Larva";178;2
"Unit";"Hydralisk";"Larva";180;2
"Unit";"Hydralisk";"Larva";182;2
"Unit";"Hydralisk";"Larva";184;2
"Unit";"Hydralisk";"Larva";186;2
"Unit";"Overlord";"Larva";188;0
"Unit";"Overlord";"Larva";188;0
"Unit";"Overlord";"Larva";188;0
"Unit";"Overlord";"Larva";188;0
"Building";"Extractor";NA;188;0
"Unit";"Baneling";"Zergling";188;0
"Unit";"Baneling";"Zergling";188;0
"Unit";"Baneling";"Zergling";188;0
"Unit";"Hydralisk";"Larva";188;2
"Unit";"Hydralisk";"Larva";190;2
"Building";"CreepTumorQueen";NA;192;0
"Building";"CreepTumor";NA;192;0
"Building";"CreepTumorQueen";NA;192;0
"Building";"CreepTumorQueen";NA;192;0
"Building";"CreepTumorQueen";NA;192;0
"Building";"CreepTumorQueen";NA;192;0
"Unit";"Hydralisk";"Larva";193;2
"Unit";"Hydralisk";"Larva";195;2
"Unit";"Hydralisk";"Larva";197;2
"Unit";"Hydralisk";"Larva";199;2
"Unit";"Zergling";"Larva";201;1
"Unit";"Zergling";"Larva";202;1
"Unit";"Zergling";"Larva";203;1
"Unit";"Zergling";"Larva";204;1
"Building";"CreepTumor";NA;209;0
"Building";"Hatchery";NA;209;0
"Building";"CreepTumorQueen";NA;209;0
"Building";"CreepTumorQueen";NA;209;0
"Unit";"Baneling";"Zergling";209;0
"Unit";"Baneling";"Zergling";209;0
"Unit";"Baneling";"Zergling";209;0
"Building";"CreepTumorQueen";NA;209;0
"Building";"CreepTumorQueen";NA;209;0
"Building";"CreepTumor";NA;212;0
"Building";"CreepTumorQueen";NA;212;0
"Building";"CreepTumorQueen";NA;215;0
"Unit";"Zergling";"Larva";215;1
"Unit";"Zergling";"Larva";216;1
"Unit";"Zergling";"Larva";217;1
"Unit";"Zergling";"Larva";218;1
"Unit";"Zergling";"Larva";219;1
"Unit";"Zergling";"Larva";220;1
"Building";"CreepTumor";NA;221;0
"Building";"CreepTumor";NA;221;0
"Building";"CreepTumorQueen";NA;221;0
"Unit";"Baneling";"Zergling";221;0
"Unit";"Baneling";"Zergling";221;0
"Unit";"Baneling";"Zergling";221;0
"Building";"CreepTumorQueen";NA;221;0
"Unit";"Hydralisk";"Larva";221;2
"Unit";"Zergling";"Larva";223;1
"Unit";"Zergling";"Larva";224;1
"Building";"CreepTumor";NA;225;0
"Building";"CreepTumor";NA;225;0
"Building";"CreepTumor";NA;225;0
"Building";"CreepTumor";NA;225;0
"Unit";"Overlord";"Larva";225;0
"Building";"Extractor";NA;229;0
"Building";"Extractor";NA;229;0
"Building";"InfestationPit";NA;229;0
"Unit";"Hydralisk";"Larva";229;2
"Unit";"Hydralisk";"Larva";231;2
"Unit";"Hydralisk";"Larva";233;2
"Unit";"Zergling";"Larva";241;1
"Unit";"Zergling";"Larva";242;1
"Unit";"Zergling";"Larva";243;1
"Unit";"Zergling";"Larva";244;1
"Unit";"Zergling";"Larva";245;1
"Unit";"Zergling";"Larva";246;1
"Unit";"Overlord";"Larva";247;0
"Unit";"Overlord";"Larva";247;0
"Building";"CreepTumor";NA;247;0
"Building";"CreepTumor";NA;247;0
"Building";"CreepTumor";NA;247;0
"Building";"CreepTumor";NA;247;0
"Building";"CreepTumor";NA;247;0
"Building";"CreepTumor";NA;247;0
"Building";"CreepTumor";NA;247;0
"Building";"CreepTumor";NA;247;0
"Building";"CreepTumor";NA;247;0
"Building";"CreepTumor";NA;247;0
"Building";"CreepTumorQueen";NA;247;0
"Building";"CreepTumorQueen";NA;247;0
"Building";"CreepTumor";NA;247;0
"Building";"CreepTumor";NA;247;0
"Building";"CreepTumor";NA;247;0
"Unit";"Overlord";"Larva";247;0
"Unit";"Overlord";"Larva";247;0
"Unit";"Hydralisk";"Larva";247;2
"Unit";"Hydralisk";"Larva";249;2
"Unit";"Hydralisk";"Larva";251;2
"Unit";"Zergling";"Larva";253;1
"Unit";"Zergling";"Larva";254;1
"Unit";"Overlord";"Larva";255;0
"Unit";"Baneling";"Zergling";255;0
"Unit";"Baneling";"Zergling";255;0
"Unit";"Baneling";"Zergling";255;0
"Unit";"Baneling";"Zergling";255;0
"Unit";"Baneling";"Zergling";255;0
"Unit";"Baneling";"Zergling";255;0
"Unit";"Hydralisk";"Larva";255;2
"Unit";"Hydralisk";"Larva";257;2
"Unit";"Zergling";"Larva";259;1
"Unit";"Zergling";"Larva";260;1
"Unit";"Zergling";"Larva";261;1
"Unit";"Zergling";"Larva";262;1
"Building";"CreepTumor";NA;263;0
"Building";"CreepTumor";NA;263;0
"Building";"CreepTumor";NA;263;0
"Building";"CreepTumor";NA;263;0
"Building";"CreepTumor";NA;263;0
"Building";"CreepTumor";NA;263;0
"Building";"CreepTumor";NA;263;0
"Building";"CreepTumor";NA;263;0
"Building";"CreepTumor";NA;263;0
"Building";"CreepTumor";NA;263;0
"Building";"CreepTumor";NA;263;0
"Building";"CreepTumor";NA;263;0
"Unit";"Zergling";"Larva";263;1
"Unit";"Zergling";"Larva";264;1
"Unit";"Zergling";"Larva";265;1
"Unit";"Zergling";"Larva";266;1
"Unit";"Zergling";"Larva";267;1
"Unit";"Zergling";"Larva";268;1
"Unit";"Zergling";"Larva";269;1
"Unit";"Zergling";"Larva";270;1
"Unit";"Zergling";"Larva";271;1
"Unit";"Zergling";"Larva";272;1
"Building";"CreepTumor";NA;273;0
"Building";"CreepTumor";NA;273;0
"Building";"CreepTumor";NA;273;0
"Building";"CreepTumorQueen";NA;273;0
"Building";"CreepTumorQueen";NA;273;0
"Building";"CreepTumorQueen";NA;273;0
"Unit";"Zergling";"Larva";273;1
"Unit";"Zergling";"Larva";274;1
"Unit";"Zergling";"Larva";275;1
"Unit";"Zergling";"Larva";276;1
"Building";"CreepTumorQueen";NA;277;0
"Unit";"Hydralisk";"Larva";277;2
"Building";"Spire";NA;280;0
"Unit";"Zergling";"Larva";280;1
"Unit";"Zergling";"Larva";281;1
"Unit";"Zergling";"Larva";282;1
"Unit";"Zergling";"Larva";283;1
"Unit";"Zergling";"Larva";284;1
"Unit";"Zergling";"Larva";285;1
"Unit";"Zergling";"Larva";286;1
"Unit";"Zergling";"Larva";287;1
"Unit";"Hydralisk";"Larva";288;2
"Unit";"Zergling";"Larva";290;1
"Unit";"Zergling";"Larva";291;1
"Unit";"Zergling";"Larva";292;1
"Unit";"Zergling";"Larva";293;1
"Unit";"Zergling";"Larva";294;1
"Unit";"Zergling";"Larva";295;1
"Unit";"Baneling";"Zergling";296;0
"Unit";"Baneling";"Zergling";296;0
"Unit";"Baneling";"Zergling";296;0
"Building";"CreepTumor";NA;296;0
"Building";"CreepTumor";NA;296;0
"Unit";"Hydralisk";"Larva";296;2
"Unit";"Hydralisk";"Larva";298;2
"Unit";"Hydralisk";"Larva";300;2
"Unit";"Hydralisk";"Larva";302;2
"Unit";"Hydralisk";"Larva";304;2
"Unit";"Hydralisk";"Larva";306;2
"Unit";"Hydralisk";"Larva";308;2
"Unit";"Hydralisk";"Larva";310;2
"Unit";"Hydralisk";"Larva";312;2
"Unit";"Zergling";"Larva";314;1
"Unit";"Zergling";"Larva";315;1
"Unit";"Baneling";"Zergling";316;0
"Unit";"Baneling";"Zergling";316;0
"Unit";"Baneling";"Zergling";316;0
"Unit";"Baneling";"Zergling";316;0
"Unit";"Baneling";"Zergling";316;0
"Unit";"Baneling";"Zergling";316;0
"Unit";"Baneling";"Zergling";316;0
"Unit";"Baneling";"Zergling";316;0
"Unit";"Overlord";"Larva";316;0
"Unit";"Overlord";"Larva";316;0
"Building";"CreepTumor";NA;316;0
"Building";"CreepTumor";NA;316;0
"Building";"CreepTumor";NA;316;0
"Building";"CreepTumor";NA;316;0
"Building";"CreepTumor";NA;316;0
"Building";"CreepTumor";NA;316;0
"Building";"CreepTumor";NA;316;0
"Building";"CreepTumor";NA;316;0
"Building";"CreepTumor";NA;316;0
"Building";"CreepTumor";NA;316;0
"Building";"UltraliskCavern";NA;316;0
"Unit";"Baneling";"Zergling";316;0
"Unit";"Baneling";"Zergling";316;0
"Unit";"Baneling";"Zergling";316;0
"Unit";"Baneling";"Zergling";316;0
"Unit";"Baneling";"Zergling";316;0
"Unit";"Baneling";"Zergling";316;0
"Unit";"Baneling";"Zergling";316;0
"Unit";"Baneling";"Zergling";316;0
"Unit";"Baneling";"Zergling";316;0
"Building";"CreepTumor";NA;317;0
"Building";"CreepTumor";NA;317;0
"Building";"CreepTumor";NA;317;0
"Building";"CreepTumor";NA;317;0
"Building";"CreepTumor";NA;317;0
"Building";"CreepTumor";NA;317;0
"Building";"CreepTumorQueen";NA;317;0
"Building";"CreepTumor";NA;317;0
"Building";"CreepTumor";NA;317;0
"Building";"CreepTumorQueen";NA;317;0
"Building";"CreepTumor";NA;317;0
"Building";"CreepTumor";NA;317;0
"Building";"CreepTumorQueen";NA;317;0
"Building";"CreepTumorQueen";NA;317;0
"Building";"CreepTumor";NA;317;0
"Building";"CreepTumorQueen";NA;317;0
"Building";"CreepTumor";NA;317;0
"Building";"CreepTumorQueen";NA;317;0
"Building";"CreepTumorQueen";NA;317;0
"Building";"Hatchery";NA;317;0
"Unit";"Ultralisk";"Larva";317;6
"Unit";"Ultralisk";"Larva";323;6
"Building";"CreepTumor";NA;329;0
"Building";"CreepTumor";NA;329;0
"Building";"CreepTumor";NA;329;0
"Building";"CreepTumor";NA;329;0
"Building";"CreepTumor";NA;329;0
"Building";"CreepTumorQueen";NA;329;0
"Building";"CreepTumorQueen";NA;329;0
"Building";"CreepTumorQueen";NA;329;0
"Building";"CreepTumorQueen";NA;329;0
"Building";"CreepTumorQueen";NA;329;0
"Building";"CreepTumorQueen";NA;329;0
"Building";"CreepTumorQueen";NA;329;0
"Building";"CreepTumorQueen";NA;329;0
"Building";"CreepTumorQueen";NA;329;0
"Upgrade";"ChitinousPlating";"UltraliskCavern";329;0
"Building";"CreepTumor";NA;329;0
"Building";"Hatchery";NA;329;0
"Unit";"Ultralisk";"Larva";329;6
"Unit";"Ultralisk";"Larva";335;6
"Unit";"Ultralisk";"Larva";341;6
"Unit";"Ultralisk";"Larva";347;6
"Unit";"Zergling";"Larva";353;1
"Unit";"Zergling";"Larva";354;1
"Building";"CreepTumor";NA;355;0
"Building";"CreepTumor";NA;355;0
"Building";"CreepTumor";NA;355;0
"Unit";"Corruptor";"Larva";355;2
"Unit";"Corruptor";"Larva";357;2
"Building";"CreepTumor";NA;359;0
"Building";"CreepTumor";NA;359;0
"Building";"CreepTumor";NA;359;0
"Building";"CreepTumor";NA;359;0
"Building";"CreepTumor";NA;359;0
"Building";"CreepTumor";NA;359;0
"Building";"CreepTumor";NA;359;0
"Building";"CreepTumor";NA;359;0
"Building";"CreepTumor";NA;359;0
"Building";"CreepTumor";NA;359;0
"Building";"CreepTumor";NA;359;0
"Building";"SporeCrawler";NA;359;0
"Building";"CreepTumor";NA;359;0
"Building";"CreepTumor";NA;359;0
"Building";"SpineCrawler";NA;359;0
"Building";"SpineCrawler";NA;359;0
"Building";"SporeCrawler";NA;359;0
"Unit";"Corruptor";"Larva";359;2
"Unit";"Corruptor";"Larva";361;2
"Building";"CreepTumor";NA;363;0
"Unit";"Baneling";"Zergling";363;0
"Unit";"Baneling";"Zergling";363;0
"Building";"CreepTumor";NA;363;0
"Building";"CreepTumor";NA;363;0
"Building";"CreepTumor";NA;363;0
"Building";"CreepTumor";NA;363;0
"Building";"CreepTumor";NA;363;0
"Building";"Extractor";NA;363;0
"Building";"Extractor";NA;363;0
"Unit";"Corruptor";"Larva";363;2
"Unit";"Corruptor";"Larva";365;2
"Unit";"Corruptor";"Larva";367;2
"Unit";"Corruptor";"Larva";369;2
"Building";"CreepTumor";NA;371;0
"Building";"CreepTumor";NA;371;0
"Building";"CreepTumor";NA;371;0
"Building";"CreepTumor";NA;371;0
"Building";"CreepTumor";NA;371;0
"Building";"CreepTumor";NA;371;0
"Building";"CreepTumor";NA;371;0
"Building";"CreepTumor";NA;371;0
"Unit";"Corruptor";"Larva";371;2
"Unit";"Corruptor";"Larva";373;2
"Unit";"Corruptor";"Larva";375;2
"Building";"CreepTumor";NA;383;0
"Building";"CreepTumor";NA;383;0
"Building";"CreepTumor";NA;383;0
"Building";"CreepTumor";NA;383;0
"Building";"CreepTumor";NA;383;0
"Building";"CreepTumor";NA;383;0
"Unit";"Overlord";"Larva";383;0
"Unit";"Overlord";"Larva";383;0
"Unit";"Overlord";"Larva";383;0
"Upgrade";"Burrow";"Hatchery";383;0
"Unit";"Corruptor";"Larva";384;2
"Unit";"Corruptor";"Larva";386;2
"Unit";"Corruptor";"Larva";388;2
"Unit";"Corruptor";"Larva";390;2
"Building";"CreepTumor";NA;392;0
"Building";"CreepTumor";NA;392;0
"Building";"CreepTumor";NA;392;0
"Building";"CreepTumor";NA;392;0
"Building";"Hatchery";NA;392;0
"Building";"CreepTumor";NA;392;0
"Building";"CreepTumor";NA;392;0
"Building";"CreepTumor";NA;392;0
"Building";"CreepTumor";NA;392;0
"Building";"CreepTumor";NA;392;0
"Unit";"Overlord";"Larva";392;0
"Unit";"Overlord";"Larva";392;0
"Unit";"Overlord";"Larva";392;0
"Unit";"Corruptor";"Larva";392;2
"Building";"CreepTumor";NA;394;0
"Unit";"Corruptor";"Larva";394;2
"Unit";"Corruptor";"Larva";396;2
"Building";"Extractor";NA;398;0
"Building";"Extractor";NA;398;0
"Building";"CreepTumor";NA;398;0
"Building";"CreepTumor";NA;398;0
"Building";"CreepTumor";NA;398;0
"Building";"CreepTumor";NA;398;0
"Building";"CreepTumor";NA;398;0
"Building";"CreepTumor";NA;398;0
"Building";"Hatchery";NA;406;0
"Building";"CreepTumor";NA;410;0
"Unit";"Corruptor";"Larva";410;2
"Unit";"Corruptor";"Larva";412;2
"Unit";"Corruptor";"Larva";414;2
"Building";"CreepTumor";NA;416;0
"Building";"CreepTumor";NA;416;0
"Building";"SporeCrawler";NA;416;0
"Building";"SporeCrawler";NA;416;0
"Building";"SpineCrawler";NA;416;0
"Building";"SpineCrawler";NA;416;0
"Unit";"Zergling";"Larva";416;1
"Unit";"Zergling";"Larva";417;1
"Unit";"Zergling";"Larva";418;1
"Unit";"Zergling";"Larva";419;1
"Unit";"Zergling";"Larva";420;1
"Unit";"Zergling";"Larva";421;1
"Unit";"Zergling";"Larva";422;1
"Unit";"Zergling";"Larva";423;1
"Unit";"Zergling";"Larva";424;1
"Unit";"Zergling";"Larva";425;1
"Unit";"Zergling";"Larva";426;1
"Unit";"Zergling";"Larva";427;1
"Unit";"Zergling";"Larva";428;1
"Unit";"Zergling";"Larva";429;1
"Unit";"Zergling";"Larva";430;1
"Unit";"Zergling";"Larva";431;1
"Unit";"Zergling";"Larva";432;1
"Unit";"Zergling";"Larva";433;1
"Unit";"Zergling";"Larva";434;1
"Unit";"Zergling";"Larva";435;1
"Unit";"Corruptor";"Larva";436;2
"Unit";"Corruptor";"Larva";438;2
"Unit";"Corruptor";"Larva";440;2
"Unit";"Corruptor";"Larva";442;2
"Building";"CreepTumor";NA;444;0
"Building";"CreepTumor";NA;444;0
"Building";"CreepTumor";NA;444;0
"Building";"CreepTumor";NA;444;0
"Building";"CreepTumor";NA;444;0
"Unit";"Baneling";"Zergling";444;0
"Unit";"Baneling";"Zergling";444;0
"Unit";"Baneling";"Zergling";444;0
"Unit";"Baneling";"Zergling";444;0
"Unit";"Baneling";"Zergling";444;0
"Unit";"Baneling";"Zergling";444;0
"Unit";"Baneling";"Zergling";444;0
"Unit";"Baneling";"Zergling";444;0
"Unit";"Baneling";"Zergling";444;0
"Unit";"Baneling";"Zergling";444;0
"Unit";"Baneling";"Zergling";444;0
"Unit";"Baneling";"Zergling";444;0
"Unit";"Baneling";"Zergling";444;0
"Unit";"Baneling";"Zergling";444;0
"Unit";"Baneling";"Zergling";444;0
"Unit";"Baneling";"Zergling";444;0
"Unit";"Baneling";"Zergling";444;0
"Unit";"Baneling";"Zergling";444;0
"Unit";"Baneling";"Zergling";444;0
"Unit";"Baneling";"Zergling";444;0
"Building";"SporeCrawler";NA;444;0
"Building";"SporeCrawler";NA;444;0
"Building";"SporeCrawler";NA;444;0
"Unit";"Corruptor";"Larva";444;2
"Unit";"Corruptor";"Larva";446;2
"Unit";"Corruptor";"Larva";448;2
"Unit";"Corruptor";"Larva";450;2
"Unit";"Corruptor";"Larva";452;2
"Unit";"Overlord";"Larva";454;0
"Unit";"Overlord";"Larva";454;0
"Upgrade";"SprayZerg";NA;454;0
"Upgrade";"SprayZerg";NA;454;0
"Upgrade";"SprayZerg";NA;454;0
"Upgrade";"zerglingmovementspeed";NA;454;0
"Upgrade";"SprayZerg";NA;454;0
"Upgrade";"SprayZerg";NA;454;0
"Upgrade";"ZergMeleeWeaponsLevel1";NA;454;0
"Upgrade";"ZergGroundArmorsLevel1";NA;454;0
"Upgrade";"EvolveMuscularAugments";NA;454;0
"Upgrade";"SprayZerg";NA;454;0
"Upgrade";"CentrificalHooks";NA;454;0
"Upgrade";"ZergMeleeWeaponsLevel2";NA;454;0
"Upgrade";"SprayZerg";NA;454;0
"Upgrade";"ZergGroundArmorsLevel2";NA;454;0
"Upgrade";"SprayZerg";NA;454;0
"Upgrade";"zerglingattackspeed";NA;454;0
"Upgrade";"SprayZerg";NA;454;0
"Upgrade";"SprayZerg";NA;454;0
"Upgrade";"SprayZerg";NA;454;0
"Upgrade";"ZergMeleeWeaponsLevel3";NA;454;0
"Upgrade";"overlordspeed";NA;454;0
"Upgrade";"ZergGroundArmorsLevel3";NA;454;0
"Upgrade";"ZergFlyerWeaponsLevel1";NA;454;0
"Upgrade";"SprayZerg";NA;454;0
"Upgrade";"SprayZerg";NA;454;0
"Upgrade";"SprayZerg";NA;454;0
"Upgrade";"ZergFlyerArmorsLevel1";NA;454;0
"Upgrade";"SprayZerg";NA;454;0
