"type";"unit_name";"on_building";"total_supply";"supply"
"Unit";"Overlord";"Larva";12;0
"Building";"Extractor";NA;18;0
"Building";"SpawningPool";NA;16;0
"Unit";"Zergling";"Larva";21;1
"Unit";"Zergling";"Larva";21;1
"Unit";"Overlord";"Larva";21;0
"Unit";"Queen";"Hatchery";21;2
"Building";"Hatchery";NA;19;0
"Unit";"Queen";"Hatchery";24;2
"Building";"CreepTumorQueen";NA;32;0
"Unit";"Queen";"Hatchery";28;2
"Unit";"Overlord";"Larva";34;0
"Building";"CreepTumorQueen";NA;39;0
"Building";"CreepTumor";NA;39;0
"Unit";"Queen";"Hatchery";39;2
"Building";"Hatchery";NA;32;0
"Unit";"Overlord";"Larva";46;0
"Building";"CreepTumor";NA;46;0
"Unit";"Overlord";"Larva";50;0
"Building";"RoachWarren";NA;46;0
"Building";"CreepTumorQueen";NA;54;0
"Unit";"Queen";"Hatchery";50;2
"Unit";"Queen";"Hatchery";50;2
"Building";"Extractor";NA;54;0
"Building";"Extractor";NA;54;0
"Unit";"Roach";"Larva";54;2
"Unit";"Roach";"Larva";54;2
"Unit";"Roach";"Larva";54;2
"Unit";"Roach";"Larva";58;2
"Building";"SporeCrawler";NA;61;0
"Building";"CreepTumor";NA;67;0
"Building";"CreepTumorQueen";NA;67;0
"Building";"CreepTumor";NA;67;0
"Unit";"Roach";"Larva";72;2
"Building";"EvolutionChamber";NA;67;0
"Building";"EvolutionChamber";NA;67;0
"Unit";"Overlord";"Larva";74;0
"Unit";"Overlord";"Larva";74;0
"Unit";"Overlord";"Larva";76;0
"Unit";"Overlord";"Larva";76;0
"Unit";"Overlord";"Larva";76;0
"Unit";"Overlord";"Larva";76;0
"Unit";"Queen";"Hatchery";76;2
"Unit";"Queen";"Hatchery";76;2
"Unit";"Roach";"Larva";76;2
"Unit";"Roach";"Larva";76;2
"Unit";"Roach";"Larva";76;2
"Unit";"Roach";"Larva";76;2
"Unit";"Roach";"Larva";76;2
"Unit";"Zergling";"Larva";76;1
"Unit";"Zergling";"Larva";76;1
"Unit";"Zergling";"Larva";76;1
"Unit";"Zergling";"Larva";76;1
"Unit";"Zergling";"Larva";76;1
"Unit";"Zergling";"Larva";76;1
"Unit";"Zergling";"Larva";76;1
"Unit";"Zergling";"Larva";76;1
"Unit";"Zergling";"Larva";76;1
"Unit";"Zergling";"Larva";76;1
"Unit";"Zergling";"Larva";76;1
"Unit";"Zergling";"Larva";76;1
"Unit";"Zergling";"Larva";76;1
"Unit";"Zergling";"Larva";76;1
"Unit";"Zergling";"Larva";76;1
"Unit";"Zergling";"Larva";76;1
"Unit";"Zergling";"Larva";76;1
"Unit";"Zergling";"Larva";76;1
"Unit";"Zergling";"Larva";76;1
"Unit";"Zergling";"Larva";76;1
"Unit";"Zergling";"Larva";76;1
"Unit";"Zergling";"Larva";76;1
"Unit";"Zergling";"Larva";90;1
"Unit";"Zergling";"Larva";90;1
"Unit";"Zergling";"Larva";90;1
"Unit";"Zergling";"Larva";90;1
"Unit";"Zergling";"Larva";90;1
"Unit";"Zergling";"Larva";90;1
"Unit";"Zergling";"Larva";90;1
"Unit";"Zergling";"Larva";90;1
"Building";"CreepTumor";NA;120;0
"Building";"CreepTumor";NA;120;0
"Upgrade";"GlialReconstitution";"RoachWarren";76;0
"Building";"InfestationPit";NA;120;0
"Unit";"Overlord";"Larva";126;0
"Building";"Extractor";NA;126;0
"Unit";"Overlord";"Larva";132;0
"Unit";"Overlord";"Larva";132;0
"Upgrade";"ZergGroundArmorsLevel1";"EvolutionChamber";80;0
"Building";"CreepTumor";NA;132;0
"Building";"CreepTumor";NA;132;0
"Building";"CreepTumorQueen";NA;132;0
"Building";"Hatchery";NA;121;0
"Unit";"Roach";"Larva";132;2
"Building";"CreepTumor";NA;132;0
"Building";"Hatchery";NA;126;0
"Unit";"Queen";"Hatchery";132;2
"Unit";"Roach";"Larva";132;2
"Unit";"Roach";"Larva";132;2
"Building";"SporeCrawler";NA;137;0
"Unit";"Queen";"Hatchery";132;2
"Unit";"Roach";"Larva";143;2
"Unit";"Roach";"Larva";143;2
"Unit";"Roach";"Larva";143;2
"Unit";"Roach";"Larva";143;2
"Upgrade";"ZergMissileWeaponsLevel1";"EvolutionChamber";132;0
"Unit";"Queen";"Hatchery";137;2
"Building";"SporeCrawler";NA;149;0
"Building";"CreepTumorQueen";NA;161;0
"Building";"CreepTumor";NA;161;0
"Building";"CreepTumor";NA;161;0
"Building";"CreepTumor";NA;161;0
"Building";"Extractor";NA;161;0
"Building";"Extractor";NA;161;0
"Unit";"Roach";"Larva";161;2
"Unit";"Overlord";"Larva";172;0
"Unit";"Overlord";"Larva";172;0
"Unit";"Overlord";"Larva";172;0
"Unit";"Roach";"Larva";197;2
"Unit";"Roach";"Larva";197;2
"Unit";"Roach";"Larva";197;2
"Unit";"Roach";"Larva";197;2
"Unit";"Roach";"Larva";197;2
"Unit";"Roach";"Larva";197;2
"Unit";"Roach";"Larva";197;2
"Building";"Extractor";NA;197;0
"Building";"Extractor";NA;197;0
"Building";"SpineCrawler";NA;197;0
"Building";"SpineCrawler";NA;197;0
"Unit";"Overlord";"Larva";197;0
"Unit";"Overlord";"Larva";197;0
"Building";"HydraliskDen";NA;197;0
"Unit";"Roach";"Larva";197;2
"Unit";"Roach";"Larva";197;2
"Unit";"Roach";"Larva";197;2
"Unit";"Roach";"Larva";197;2
"Building";"SpineCrawler";NA;197;0
"Building";"SpineCrawler";NA;197;0
"Unit";"Roach";"Larva";219;2
"Building";"CreepTumor";NA;219;0
"Unit";"Roach";"Larva";219;2
"Unit";"Roach";"Larva";219;2
"Unit";"Roach";"Larva";219;2
"Unit";"Roach";"Larva";219;2
"Unit";"Roach";"Larva";219;2
"Unit";"Roach";"Larva";219;2
"Unit";"Roach";"Larva";219;2
"Unit";"Roach";"Larva";219;2
"Unit";"Roach";"Larva";219;2
"Unit";"Roach";"Larva";219;2
"Unit";"Roach";"Larva";219;2
"Building";"CreepTumor";NA;219;0
"Building";"CreepTumor";NA;243;0
"Unit";"Roach";"Larva";243;2
"Unit";"Roach";"Larva";243;2
"Unit";"Overlord";"Larva";243;0
"Unit";"Overlord";"Larva";243;0
"Unit";"Overlord";"Larva";243;0
"Unit";"Overlord";"Larva";243;0
"Unit";"Roach";"Larva";250;2
"Unit";"Roach";"Larva";250;2
"Unit";"Roach";"Larva";250;2
"Unit";"Roach";"Larva";250;2
"Unit";"Roach";"Larva";250;2
"Unit";"Roach";"Larva";250;2
"Unit";"Roach";"Larva";250;2
"Unit";"Roach";"Larva";250;2
"Unit";"Roach";"Larva";250;2
"Unit";"Roach";"Larva";250;2
"Unit";"Roach";"Larva";250;2
"Unit";"Roach";"Larva";250;2
"Unit";"Roach";"Larva";250;2
"Unit";"Roach";"Larva";250;2
"Unit";"Roach";"Larva";250;2
"Unit";"Roach";"Larva";250;2
"Unit";"Roach";"Larva";250;2
"Unit";"Roach";"Larva";250;2
"Unit";"Roach";"Larva";250;2
"Unit";"Roach";"Larva";288;2
"Unit";"Roach";"Larva";288;2
"Unit";"Roach";"Larva";288;2
"Unit";"Roach";"Larva";288;2
"Unit";"Roach";"Larva";288;2
"Unit";"Roach";"Larva";288;2
"Unit";"Roach";"Larva";288;2
"Unit";"Roach";"Larva";288;2
"Unit";"Roach";"Larva";288;2
"Building";"CreepTumor";NA;288;0
"Building";"CreepTumor";NA;288;0
"Building";"CreepTumor";NA;288;0
"Building";"CreepTumor";NA;306;0
"Building";"CreepTumor";NA;306;0
"Building";"CreepTumorQueen";NA;306;0
"Building";"CreepTumorQueen";NA;306;0
"Unit";"Hydralisk";"Larva";306;2
"Unit";"Hydralisk";"Larva";306;2
"Unit";"Hydralisk";"Larva";306;2
"Unit";"Hydralisk";"Larva";306;2
"Unit";"Hydralisk";"Larva";306;2
"Unit";"Hydralisk";"Larva";306;2
"Building";"CreepTumor";NA;306;0
"Building";"CreepTumor";NA;318;0
"Unit";"Roach";"Larva";306;2
"Unit";"Roach";"Larva";306;2
"Unit";"Roach";"Larva";306;2
"Unit";"Roach";"Larva";306;2
"Unit";"Roach";"Larva";306;2
"Unit";"Roach";"Larva";306;2
"Unit";"Roach";"Larva";306;2
"Unit";"Roach";"Larva";306;2
"Unit";"Roach";"Larva";306;2
"Unit";"Roach";"Larva";306;2
"Building";"CreepTumor";NA;318;0
"Building";"CreepTumor";NA;318;0
"Building";"CreepTumor";NA;318;0
"Upgrade";"EvolveGroovedSpines";"HydraliskDen";306;0
"Building";"Spire";NA;288;0
"Unit";"Viper";"Larva";318;3
"Unit";"Viper";"Larva";318;3
"Unit";"Viper";"Larva";318;3
"Building";"CreepTumor";NA;338;0
"Unit";"Viper";"Larva";338;3
"Unit";"Viper";"Larva";338;3
"Building";"CreepTumor";NA;347;0
"Building";"Hatchery";NA;306;0
"Building";"Extractor";NA;347;0
"Building";"Extractor";NA;347;0
"Building";"SpineCrawler";NA;353;0
"Building";"Hatchery";NA;338;0
"Unit";"Hydralisk";"Larva";353;2
"Unit";"Hydralisk";"Larva";353;2
"Unit";"Hydralisk";"Larva";353;2
"Unit";"Hydralisk";"Larva";353;2
"Unit";"Hydralisk";"Larva";353;2
"Unit";"Hydralisk";"Larva";353;2
"Unit";"Hydralisk";"Larva";353;2
"Unit";"Hydralisk";"Larva";353;2
"Unit";"Hydralisk";"Larva";353;2
"Unit";"Hydralisk";"Larva";353;2
"Unit";"Hydralisk";"Larva";353;2
"Unit";"Hydralisk";"Larva";353;2
"Upgrade";"EvolveMuscularAugments";"HydraliskDen";353;0
"Building";"CreepTumor";NA;377;0
"Building";"SpineCrawler";NA;353;0
"Building";"SpineCrawler";NA;353;0
"Building";"SpineCrawler";NA;353;0
"Building";"CreepTumor";NA;377;0
"Upgrade";"ZergMissileWeaponsLevel2";"EvolutionChamber";353;0
"Building";"CreepTumor";NA;380;0
"Unit";"Hydralisk";"Larva";380;2
"Unit";"Hydralisk";"Larva";380;2
"Unit";"Hydralisk";"Larva";380;2
"Unit";"Hydralisk";"Larva";380;2
"Unit";"Hydralisk";"Larva";380;2
"Unit";"Hydralisk";"Larva";380;2
"Unit";"Hydralisk";"Larva";380;2
"Unit";"Hydralisk";"Larva";380;2
"Unit";"Hydralisk";"Larva";380;2
"Unit";"Hydralisk";"Larva";380;2
"Unit";"Hydralisk";"Larva";380;2
"Unit";"Hydralisk";"Larva";380;2
"Building";"SpineCrawler";NA;380;0
"Building";"SpineCrawler";NA;380;0
"Unit";"Corruptor";"Larva";410;2
"Unit";"Corruptor";"Larva";410;2
"Unit";"Corruptor";"Larva";410;2
"Unit";"Corruptor";"Larva";410;2
"Unit";"Corruptor";"Larva";410;2
"Unit";"Corruptor";"Larva";410;2
"Unit";"Corruptor";"Larva";410;2
"Unit";"Corruptor";"Larva";410;2
"Building";"Extractor";NA;410;0
"Building";"CreepTumor";NA;436;0
"Unit";"Roach";"Larva";436;2
"Unit";"Roach";"Larva";436;2
"Unit";"Roach";"Larva";436;2
"Unit";"Roach";"Larva";436;2
"Unit";"Roach";"Larva";436;2
"Unit";"Roach";"Larva";436;2
"Unit";"Roach";"Larva";436;2
"Unit";"Roach";"Larva";436;2
"Unit";"Roach";"Larva";436;2
"Unit";"Roach";"Larva";436;2
"Unit";"Roach";"Larva";436;2
"Unit";"Roach";"Larva";436;2
"Building";"CreepTumor";NA;460;0
"Unit";"Hydralisk";"Larva";460;2
"Unit";"Hydralisk";"Larva";460;2
"Unit";"Hydralisk";"Larva";460;2
"Unit";"Hydralisk";"Larva";460;2
"Unit";"Hydralisk";"Larva";460;2
"Unit";"Hydralisk";"Larva";460;2
"Unit";"Hydralisk";"Larva";460;2
"Building";"Hatchery";NA;460;0
"Unit";"Roach";"Larva";474;2
"Unit";"Roach";"Larva";474;2
"Unit";"Roach";"Larva";474;2
"Unit";"Roach";"Larva";474;2
"Unit";"Roach";"Larva";474;2
"Unit";"Roach";"Larva";474;2
"Unit";"Roach";"Larva";474;2
"Unit";"Roach";"Larva";474;2
"Unit";"Roach";"Larva";474;2
"Unit";"Roach";"Larva";474;2
"Unit";"Roach";"Larva";474;2
"Unit";"Hydralisk";"Larva";496;2
"Unit";"Hydralisk";"Larva";496;2
"Unit";"Hydralisk";"Larva";496;2
"Unit";"Hydralisk";"Larva";496;2
"Unit";"Hydralisk";"Larva";496;2
"Unit";"Hydralisk";"Larva";496;2
"Unit";"Hydralisk";"Larva";496;2
"Unit";"Hydralisk";"Larva";496;2
"Unit";"Hydralisk";"Larva";496;2
"Unit";"Hydralisk";"Larva";496;2
"Unit";"Hydralisk";"Larva";496;2
"Unit";"Hydralisk";"Larva";496;2
"Unit";"Roach";"Larva";520;2
"Unit";"Roach";"Larva";520;2
"Unit";"Roach";"Larva";520;2
"Unit";"Roach";"Larva";520;2
"Unit";"Roach";"Larva";520;2
"Unit";"Roach";"Larva";520;2
"Unit";"Roach";"Larva";520;2
"Unit";"Roach";"Larva";520;2
"Unit";"Roach";"Larva";520;2
"Building";"CreepTumor";NA;538;0
"Building";"CreepTumor";NA;539;0
