"type";"unit_name";"on_building";"total_supply";"supply"
"Unit";"Overlord";"Larva";13;0
"Building";"Extractor";NA;18;0
"Unit";"Overlord";"Larva";21;0
"Building";"SpawningPool";NA;19;0
"Building";"Hatchery";NA;17;0
"Unit";"Zergling";"Larva";22;1
"Unit";"Zergling";"Larva";22;1
"Unit";"Zergling";"Larva";22;1
"Unit";"Zergling";"Larva";22;1
"Unit";"Queen";"Hatchery";22;2
"Unit";"Queen";"Hatchery";22;2
"Unit";"Overlord";"Larva";35;0
"Unit";"Queen";"Hatchery";33;2
"Unit";"Overlord";"Larva";38;0
"Building";"Extractor";NA;41;0
"Building";"Extractor";NA;41;0
"Unit";"Overlord";"Larva";51;0
"Unit";"Zergling";"Larva";52;1
"Unit";"Zergling";"Larva";52;1
"Unit";"Zergling";"Larva";52;1
"Unit";"Zergling";"Larva";52;1
"Unit";"Zergling";"Larva";52;1
"Unit";"Zergling";"Larva";52;1
"Unit";"Zergling";"Larva";52;1
"Unit";"Zergling";"Larva";52;1
"Unit";"Overlord";"Larva";53;0
"Building";"CreepTumorQueen";NA;59;0
"Building";"CreepTumorQueen";NA;61;0
"Building";"Extractor";NA;53;0
"Building";"CreepTumorQueen";NA;66;0
"Building";"RoachWarren";NA;63;0
"Unit";"Overlord";"Larva";68;0
"Unit";"Overlord";"Larva";68;0
"Building";"CreepTumor";NA;69;0
"Building";"CreepTumor";NA;68;0
"Unit";"Overlord";"Larva";68;0
"Building";"CreepTumor";NA;71;0
"Building";"Spire";NA;53;0
"Building";"CreepTumorQueen";NA;72;0
"Building";"CreepTumor";NA;72;0
"Building";"CreepTumor";NA;72;0
"Unit";"Zergling";"Larva";73;1
"Unit";"Zergling";"Larva";73;1
"Unit";"Zergling";"Larva";73;1
"Unit";"Zergling";"Larva";73;1
"Unit";"Zergling";"Larva";73;1
"Unit";"Zergling";"Larva";73;1
"Building";"EvolutionChamber";NA;72;0
"Unit";"Mutalisk";"Larva";72;2
"Unit";"Mutalisk";"Larva";72;2
"Unit";"Mutalisk";"Larva";72;2
"Unit";"Mutalisk";"Larva";72;2
"Unit";"Mutalisk";"Larva";72;2
"Unit";"Mutalisk";"Larva";72;2
"Unit";"Mutalisk";"Larva";73;2
"Unit";"Overlord";"Larva";73;0
"Building";"CreepTumor";NA;79;0
"Building";"CreepTumor";NA;79;0
"Building";"CreepTumor";NA;79;0
"Building";"CreepTumor";NA;81;0
"Building";"CreepTumorQueen";NA;93;0
"Building";"CreepTumorQueen";NA;93;0
"Unit";"Queen";"Hatchery";73;2
"Building";"Hatchery";NA;71;0
"Building";"BanelingNest";NA;73;0
"Unit";"Overlord";"Larva";98;0
"Building";"CreepTumor";NA;106;0
"Building";"CreepTumor";NA;106;0
"Building";"CreepTumor";NA;106;0
"Building";"CreepTumor";NA;106;0
"Unit";"Roach";"Larva";106;2
"Unit";"Roach";"Larva";106;2
"Unit";"Overlord";"Larva";106;0
"Unit";"Overlord";"Larva";106;0
"Building";"CreepTumorQueen";NA;107;0
"Building";"CreepTumorQueen";NA;110;0
"Unit";"Baneling";"Zergling";110;0
"Unit";"Baneling";"Zergling";110;0
"Unit";"Baneling";"Zergling";110;0
"Unit";"Baneling";"Zergling";110;0
"Unit";"Baneling";"Zergling";110;0
"Unit";"Baneling";"Zergling";110;0
"Unit";"Baneling";"Zergling";110;0
"Unit";"Baneling";"Zergling";110;0
"Unit";"Roach";"Larva";107;2
"Upgrade";"GlialReconstitution";"RoachWarren";97;0
"Unit";"Roach";"Larva";110;2
"Unit";"Roach";"Larva";110;2
"Unit";"Roach";"Larva";114;2
"Unit";"Roach";"Larva";114;2
"Unit";"Roach";"Larva";114;2
"Unit";"Overlord";"Larva";116;0
"Unit";"Roach";"Larva";114;2
"Unit";"Roach";"Larva";116;2
"Unit";"Roach";"Larva";116;2
"Unit";"Zergling";"Larva";122;1
"Unit";"Zergling";"Larva";122;1
"Unit";"Roach";"Larva";122;2
"Unit";"Roach";"Larva";122;2
"Unit";"Roach";"Larva";122;2
"Unit";"Roach";"Larva";122;2
"Unit";"Roach";"Larva";122;2
"Unit";"Roach";"Larva";122;2
"Building";"CreepTumor";NA;146;0
"Unit";"Zergling";"Larva";132;1
"Unit";"Zergling";"Larva";132;1
"Unit";"Zergling";"Larva";132;1
"Unit";"Zergling";"Larva";132;1
"Unit";"Zergling";"Larva";132;1
"Unit";"Zergling";"Larva";132;1
"Unit";"Zergling";"Larva";132;1
"Unit";"Zergling";"Larva";132;1
"Unit";"Zergling";"Larva";132;1
"Unit";"Zergling";"Larva";132;1
"Upgrade";"ZergMeleeWeaponsLevel1";"EvolutionChamber";106;0
"Unit";"Zergling";"Larva";156;1
"Unit";"Zergling";"Larva";156;1
"Unit";"Zergling";"Larva";156;1
"Unit";"Zergling";"Larva";156;1
"Unit";"Zergling";"Larva";156;1
"Unit";"Zergling";"Larva";156;1
"Unit";"Zergling";"Larva";156;1
"Unit";"Zergling";"Larva";156;1
"Unit";"Zergling";"Larva";156;1
"Unit";"Zergling";"Larva";156;1
"Unit";"Zergling";"Larva";156;1
"Unit";"Zergling";"Larva";156;1
"Unit";"Zergling";"Larva";156;1
"Unit";"Zergling";"Larva";156;1
"Unit";"Zergling";"Larva";156;1
"Unit";"Zergling";"Larva";156;1
"Unit";"Zergling";"Larva";156;1
"Unit";"Zergling";"Larva";156;1
"Unit";"Zergling";"Larva";156;1
"Unit";"Zergling";"Larva";156;1
"Unit";"Zergling";"Larva";156;1
"Unit";"Zergling";"Larva";156;1
"Unit";"Zergling";"Larva";156;1
"Unit";"Zergling";"Larva";156;1
"Building";"Extractor";NA;156;0
"Unit";"Mutalisk";"Larva";156;2
"Unit";"Mutalisk";"Larva";168;2
"Unit";"Mutalisk";"Larva";178;2
"Building";"CreepTumor";NA;182;0
"Building";"CreepTumor";NA;182;0
"Building";"CreepTumor";NA;182;0
"Building";"CreepTumor";NA;182;0
"Unit";"Mutalisk";"Larva";182;2
"Unit";"Mutalisk";"Larva";182;2
"Building";"Extractor";NA;182;0
"Building";"CreepTumor";NA;194;0
"Unit";"Zergling";"Larva";194;1
"Unit";"Zergling";"Larva";194;1
"Unit";"Overlord";"Larva";194;0
"Unit";"Overlord";"Larva";194;0
"Unit";"Overlord";"Larva";194;0
"Unit";"Overlord";"Larva";194;0
"Unit";"Overlord";"Larva";194;0
"Unit";"Baneling";"Zergling";200;0
"Unit";"Baneling";"Zergling";202;0
"Unit";"Baneling";"Zergling";202;0
"Unit";"Baneling";"Zergling";202;0
"Unit";"Baneling";"Zergling";202;0
"Unit";"Baneling";"Zergling";202;0
"Unit";"Baneling";"Zergling";202;0
"Building";"HydraliskDen";NA;194;0
"Unit";"Baneling";"Zergling";202;0
"Unit";"Baneling";"Zergling";202;0
"Unit";"Baneling";"Zergling";202;0
"Unit";"Baneling";"Zergling";202;0
"Unit";"Baneling";"Zergling";202;0
"Unit";"Overlord";"Larva";195;0
"Building";"CreepTumor";NA;202;0
"Building";"CreepTumor";NA;204;0
"Building";"CreepTumor";NA;204;0
"Unit";"Overlord";"Larva";202;0
"Unit";"Overlord";"Larva";202;0
"Building";"Hatchery";NA;156;0
"Unit";"Zergling";"Larva";204;1
"Unit";"Zergling";"Larva";204;1
"Unit";"Zergling";"Larva";204;1
"Unit";"Zergling";"Larva";204;1
"Unit";"Zergling";"Larva";204;1
"Unit";"Zergling";"Larva";204;1
"Unit";"Zergling";"Larva";204;1
"Unit";"Zergling";"Larva";204;1
"Unit";"Zergling";"Larva";204;1
"Unit";"Zergling";"Larva";204;1
"Unit";"Hydralisk";"Larva";204;2
"Building";"Hatchery";NA;182;0
"Unit";"Hydralisk";"Larva";204;2
"Unit";"Hydralisk";"Larva";204;2
"Unit";"Hydralisk";"Larva";204;2
"Unit";"Queen";"Hatchery";204;2
"Unit";"Baneling";"Zergling";214;0
"Unit";"Baneling";"Zergling";214;0
"Unit";"Zergling";"Larva";204;1
"Unit";"Zergling";"Larva";204;1
"Unit";"Zergling";"Larva";204;1
"Unit";"Zergling";"Larva";204;1
"Unit";"Zergling";"Larva";204;1
"Unit";"Zergling";"Larva";204;1
"Unit";"Zergling";"Larva";204;1
"Unit";"Zergling";"Larva";204;1
"Unit";"Zergling";"Larva";214;1
"Unit";"Zergling";"Larva";214;1
"Unit";"Zergling";"Larva";214;1
"Unit";"Zergling";"Larva";214;1
"Unit";"Hydralisk";"Larva";204;2
"Unit";"Hydralisk";"Larva";204;2
"Unit";"Hydralisk";"Larva";204;2
"Unit";"Hydralisk";"Larva";204;2
"Unit";"Hydralisk";"Larva";204;2
"Unit";"Zergling";"Larva";222;1
"Unit";"Zergling";"Larva";222;1
"Unit";"Zergling";"Larva";222;1
"Unit";"Zergling";"Larva";222;1
"Unit";"Zergling";"Larva";222;1
"Unit";"Zergling";"Larva";222;1
"Unit";"Zergling";"Larva";222;1
"Unit";"Zergling";"Larva";222;1
"Unit";"Zergling";"Larva";222;1
"Unit";"Zergling";"Larva";222;1
"Unit";"Zergling";"Larva";222;1
"Unit";"Zergling";"Larva";222;1
"Unit";"Zergling";"Larva";232;1
"Unit";"Zergling";"Larva";232;1
"Unit";"Zergling";"Larva";232;1
"Unit";"Zergling";"Larva";232;1
"Building";"CreepTumor";NA;246;0
"Unit";"Zergling";"Larva";246;1
"Unit";"Zergling";"Larva";246;1
"Unit";"Zergling";"Larva";246;1
"Unit";"Zergling";"Larva";246;1
"Unit";"Zergling";"Larva";246;1
"Unit";"Zergling";"Larva";246;1
"Unit";"Baneling";"Zergling";259;0
"Unit";"Baneling";"Zergling";259;0
"Unit";"Baneling";"Zergling";259;0
"Unit";"Baneling";"Zergling";259;0
"Unit";"Baneling";"Zergling";259;0
"Unit";"Baneling";"Zergling";259;0
"Unit";"Baneling";"Zergling";259;0
"Unit";"Baneling";"Zergling";259;0
"Unit";"Baneling";"Zergling";259;0
"Unit";"Zergling";"Larva";259;1
"Unit";"Zergling";"Larva";259;1
"Unit";"Baneling";"Zergling";259;0
"Unit";"Baneling";"Zergling";259;0
"Unit";"Baneling";"Zergling";259;0
"Unit";"Zergling";"Larva";259;1
"Unit";"Zergling";"Larva";259;1
"Unit";"Zergling";"Larva";259;1
"Unit";"Zergling";"Larva";259;1
"Building";"CreepTumor";NA;263;0
"Upgrade";"EvolveGroovedSpines";"HydraliskDen";214;0
"Unit";"Zergling";"Larva";259;1
"Unit";"Zergling";"Larva";259;1
"Unit";"Zergling";"Larva";261;1
"Unit";"Zergling";"Larva";261;1
"Building";"CreepTumor";NA;265;0
"Building";"CreepTumor";NA;269;0
"Upgrade";"ZergMeleeWeaponsLevel2";"EvolutionChamber";194;0
"Unit";"Zergling";"Larva";275;1
"Unit";"Zergling";"Larva";275;1
"Unit";"Zergling";"Larva";275;1
"Unit";"Zergling";"Larva";275;1
"Unit";"Zergling";"Larva";275;1
"Unit";"Zergling";"Larva";275;1
"Unit";"Zergling";"Larva";275;1
"Unit";"Zergling";"Larva";275;1
"Unit";"Zergling";"Larva";275;1
"Unit";"Zergling";"Larva";275;1
"Unit";"Zergling";"Larva";275;1
"Unit";"Zergling";"Larva";275;1
"Unit";"Zergling";"Larva";275;1
"Unit";"Zergling";"Larva";275;1
"Building";"CreepTumor";NA;284;0
"Unit";"Zergling";"Larva";284;1
"Unit";"Zergling";"Larva";284;1
"Unit";"Zergling";"Larva";284;1
"Unit";"Zergling";"Larva";284;1
"Unit";"Zergling";"Larva";284;1
"Unit";"Zergling";"Larva";284;1
"Unit";"Zergling";"Larva";284;1
"Unit";"Zergling";"Larva";284;1
"Unit";"Zergling";"Larva";284;1
"Unit";"Zergling";"Larva";284;1
"Unit";"Zergling";"Larva";284;1
"Unit";"Zergling";"Larva";284;1
"Unit";"Zergling";"Larva";284;1
"Unit";"Zergling";"Larva";284;1
"Unit";"Zergling";"Larva";284;1
"Unit";"Zergling";"Larva";284;1
"Unit";"Queen";"Hatchery";269;2
