"type";"unit_name";"on_building";"total_supply";"supply"
"Unit";"Overlord";"Larva";12;0
"Building";"Extractor";NA;17;0
"Building";"SpawningPool";NA;19;0
"Building";"Hatchery";NA;17;0
"Unit";"Zergling";"Larva";23;1
"Unit";"Zergling";"Larva";23;1
"Unit";"Zergling";"Larva";23;1
"Unit";"Zergling";"Larva";23;1
"Unit";"Zergling";"Larva";23;1
"Unit";"Zergling";"Larva";23;1
"Unit";"Queen";"Hatchery";23;2
"Unit";"Overlord";"Larva";23;0
"Unit";"Queen";"Hatchery";23;2
"Unit";"Overlord";"Larva";34;0
"Unit";"Zergling";"Larva";48;1
"Unit";"Zergling";"Larva";48;1
"Unit";"Zergling";"Larva";48;1
"Unit";"Zergling";"Larva";48;1
"Unit";"Zergling";"Larva";48;1
"Unit";"Zergling";"Larva";48;1
"Unit";"Queen";"Hatchery";40;2
"Unit";"Overlord";"Larva";48;0
"Building";"CreepTumorQueen";NA;54;0
"Building";"CreepTumorQueen";NA;56;0
"Building";"Extractor";NA;54;0
"Building";"Extractor";NA;56;0
"Building";"RoachWarren";NA;48;0
"Building";"Hatchery";NA;40;0
"Building";"CreepTumor";NA;60;0
"Unit";"Overlord";"Larva";57;0
"Unit";"Roach";"Larva";63;2
"Unit";"Overlord";"Larva";63;0
"Unit";"Roach";"Larva";63;2
"Unit";"Roach";"Larva";63;2
"Unit";"Roach";"Larva";63;2
"Unit";"Roach";"Larva";63;2
"Unit";"Roach";"Larva";63;2
"Unit";"Roach";"Larva";63;2
"Unit";"Roach";"Larva";63;2
"Building";"CreepTumor";NA;77;0
"Building";"CreepTumor";NA;79;0
"Unit";"Overlord";"Larva";79;0
"Unit";"Roach";"Larva";80;2
"Unit";"Roach";"Larva";80;2
"Unit";"Roach";"Larva";80;2
"Unit";"Roach";"Larva";80;2
"Unit";"Roach";"Larva";80;2
"Unit";"Overlord";"Larva";80;0
"Unit";"Overlord";"Larva";80;0
"Building";"CreepTumor";NA;80;0
"Unit";"Overlord";"Larva";80;0
"Unit";"Overlord";"Larva";80;0
"Unit";"Roach";"Larva";90;2
"Unit";"Roach";"Larva";90;2
"Unit";"Roach";"Larva";90;2
"Building";"Extractor";NA;90;0
"Unit";"Overlord";"Larva";90;0
"Unit";"Overlord";"Larva";90;0
"Unit";"Zergling";"Larva";90;1
"Unit";"Zergling";"Larva";90;1
"Unit";"Zergling";"Larva";90;1
"Unit";"Zergling";"Larva";90;1
"Unit";"Zergling";"Larva";90;1
"Unit";"Zergling";"Larva";90;1
"Upgrade";"GlialReconstitution";"RoachWarren";80;0
"Unit";"Zergling";"Larva";102;1
"Unit";"Zergling";"Larva";102;1
"Unit";"Zergling";"Larva";102;1
"Unit";"Zergling";"Larva";102;1
"Unit";"Zergling";"Larva";102;1
"Unit";"Zergling";"Larva";102;1
"Unit";"Zergling";"Larva";102;1
"Unit";"Zergling";"Larva";102;1
"Unit";"Zergling";"Larva";102;1
"Unit";"Zergling";"Larva";102;1
"Unit";"Zergling";"Larva";102;1
"Unit";"Zergling";"Larva";102;1
"Unit";"Zergling";"Larva";102;1
"Unit";"Zergling";"Larva";102;1
"Unit";"Zergling";"Larva";102;1
"Unit";"Zergling";"Larva";102;1
"Unit";"Zergling";"Larva";102;1
"Unit";"Zergling";"Larva";102;1
"Unit";"Zergling";"Larva";102;1
"Unit";"Zergling";"Larva";102;1
"Unit";"Zergling";"Larva";102;1
"Unit";"Zergling";"Larva";102;1
"Unit";"Overlord";"Larva";118;0
"Unit";"Overlord";"Larva";124;0
"Building";"EvolutionChamber";NA;124;0
"Building";"EvolutionChamber";NA;124;0
"Unit";"Overlord";"Larva";137;0
"Unit";"Overlord";"Larva";137;0
"Building";"CreepTumor";NA;137;0
"Building";"CreepTumor";NA;142;0
"Building";"BanelingNest";NA;131;0
"Building";"CreepTumor";NA;142;0
"Unit";"Overlord";"Larva";142;0
"Unit";"Overlord";"Larva";142;0
"Building";"Extractor";NA;142;0
"Unit";"Overlord";"Larva";142;0
"Unit";"Overlord";"Larva";142;0
"Building";"Extractor";NA;142;0
"Unit";"Overlord";"Larva";142;0
"Unit";"Overlord";"Larva";142;0
"Building";"CreepTumorQueen";NA;153;0
"Building";"CreepTumorQueen";NA;153;0
"Building";"CreepTumorQueen";NA;153;0
"Building";"Hatchery";NA;142;0
"Building";"CreepTumor";NA;153;0
"Unit";"Overlord";"Larva";153;0
"Unit";"Baneling";"Zergling";153;0
"Unit";"Baneling";"Zergling";153;0
"Unit";"Baneling";"Zergling";153;0
"Unit";"Baneling";"Zergling";153;0
"Unit";"Baneling";"Zergling";153;0
"Unit";"Baneling";"Zergling";153;0
"Unit";"Baneling";"Zergling";153;0
"Building";"HydraliskDen";NA;153;0
"Unit";"Zergling";"Larva";159;1
"Unit";"Zergling";"Larva";159;1
"Unit";"Zergling";"Larva";159;1
"Unit";"Zergling";"Larva";159;1
"Unit";"Zergling";"Larva";159;1
"Unit";"Zergling";"Larva";159;1
"Unit";"Zergling";"Larva";159;1
"Unit";"Zergling";"Larva";159;1
"Unit";"Zergling";"Larva";159;1
"Unit";"Zergling";"Larva";159;1
"Unit";"Zergling";"Larva";159;1
"Unit";"Zergling";"Larva";159;1
"Unit";"Zergling";"Larva";159;1
"Unit";"Zergling";"Larva";159;1
"Unit";"Zergling";"Larva";159;1
"Unit";"Zergling";"Larva";159;1
"Unit";"Zergling";"Larva";159;1
"Unit";"Zergling";"Larva";159;1
"Unit";"Zergling";"Larva";159;1
"Unit";"Zergling";"Larva";159;1
"Unit";"Zergling";"Larva";159;1
"Unit";"Zergling";"Larva";159;1
"Unit";"Zergling";"Larva";159;1
"Unit";"Zergling";"Larva";159;1
"Unit";"Zergling";"Larva";159;1
"Unit";"Zergling";"Larva";159;1
"Unit";"Zergling";"Larva";159;1
"Unit";"Zergling";"Larva";159;1
"Unit";"Zergling";"Larva";159;1
"Unit";"Zergling";"Larva";159;1
"Unit";"Zergling";"Larva";159;1
"Unit";"Zergling";"Larva";159;1
"Unit";"Zergling";"Larva";159;1
"Unit";"Zergling";"Larva";159;1
"Upgrade";"ZergMeleeWeaponsLevel1";"EvolutionChamber";142;0
"Upgrade";"ZergGroundArmorsLevel1";"EvolutionChamber";142;0
"Unit";"Overlord";"Larva";193;0
"Unit";"Hydralisk";"Larva";193;2
"Unit";"Hydralisk";"Larva";193;2
"Unit";"Hydralisk";"Larva";193;2
"Unit";"Hydralisk";"Larva";193;2
"Unit";"Hydralisk";"Larva";193;2
"Unit";"Hydralisk";"Larva";193;2
"Unit";"Hydralisk";"Larva";193;2
"Unit";"Zergling";"Larva";193;1
"Unit";"Zergling";"Larva";193;1
"Unit";"Zergling";"Larva";193;1
"Unit";"Zergling";"Larva";193;1
"Unit";"Zergling";"Larva";193;1
"Unit";"Zergling";"Larva";193;1
"Unit";"Zergling";"Larva";193;1
"Unit";"Zergling";"Larva";193;1
"Unit";"Zergling";"Larva";193;1
"Unit";"Zergling";"Larva";193;1
"Unit";"Zergling";"Larva";193;1
"Unit";"Zergling";"Larva";193;1
"Unit";"Zergling";"Larva";193;1
"Unit";"Zergling";"Larva";193;1
"Unit";"Zergling";"Larva";193;1
"Unit";"Zergling";"Larva";193;1
"Unit";"Zergling";"Larva";193;1
"Unit";"Zergling";"Larva";193;1
"Building";"CreepTumor";NA;207;0
"Unit";"Zergling";"Larva";207;1
"Unit";"Zergling";"Larva";207;1
"Unit";"Zergling";"Larva";207;1
"Unit";"Zergling";"Larva";207;1
"Unit";"Zergling";"Larva";207;1
"Unit";"Zergling";"Larva";207;1
"Unit";"Zergling";"Larva";207;1
"Unit";"Zergling";"Larva";207;1
"Unit";"Baneling";"Zergling";225;0
"Unit";"Baneling";"Zergling";225;0
"Unit";"Baneling";"Zergling";225;0
"Unit";"Baneling";"Zergling";225;0
"Unit";"Baneling";"Zergling";225;0
"Unit";"Baneling";"Zergling";225;0
"Upgrade";"EvolveMuscularAugments";"HydraliskDen";193;0
"Unit";"Hydralisk";"Larva";234;2
"Unit";"Hydralisk";"Larva";234;2
"Unit";"Hydralisk";"Larva";234;2
"Unit";"Hydralisk";"Larva";234;2
"Unit";"Hydralisk";"Larva";234;2
"Unit";"Zergling";"Larva";234;1
"Unit";"Zergling";"Larva";234;1
"Unit";"Zergling";"Larva";234;1
"Unit";"Zergling";"Larva";234;1
"Unit";"Zergling";"Larva";234;1
"Unit";"Zergling";"Larva";234;1
"Unit";"Zergling";"Larva";234;1
"Unit";"Zergling";"Larva";234;1
"Unit";"Zergling";"Larva";234;1
"Unit";"Zergling";"Larva";234;1
"Unit";"Zergling";"Larva";234;1
"Unit";"Zergling";"Larva";234;1
"Unit";"Zergling";"Larva";234;1
"Unit";"Zergling";"Larva";234;1
"Unit";"Zergling";"Larva";234;1
"Unit";"Zergling";"Larva";234;1
"Unit";"Zergling";"Larva";234;1
"Unit";"Zergling";"Larva";234;1
"Building";"CreepTumor";NA;244;0
"Building";"CreepTumor";NA;246;0
"Building";"CreepTumor";NA;262;0
"Unit";"Zergling";"Larva";262;1
"Unit";"Zergling";"Larva";262;1
"Unit";"Zergling";"Larva";262;1
"Unit";"Zergling";"Larva";262;1
"Unit";"Zergling";"Larva";262;1
"Unit";"Zergling";"Larva";262;1
"Unit";"Zergling";"Larva";262;1
"Unit";"Zergling";"Larva";262;1
"Unit";"Zergling";"Larva";262;1
"Unit";"Zergling";"Larva";262;1
"Unit";"Zergling";"Larva";262;1
"Unit";"Zergling";"Larva";262;1
"Unit";"Zergling";"Larva";262;1
"Unit";"Zergling";"Larva";262;1
"Unit";"Baneling";"Zergling";262;0
"Unit";"Zergling";"Larva";262;1
"Unit";"Zergling";"Larva";262;1
"Unit";"Zergling";"Larva";262;1
"Unit";"Zergling";"Larva";262;1
"Unit";"Baneling";"Zergling";262;0
"Unit";"Baneling";"Zergling";262;0
"Unit";"Baneling";"Zergling";262;0
"Unit";"Baneling";"Zergling";262;0
"Unit";"Baneling";"Zergling";262;0
"Unit";"Baneling";"Zergling";262;0
"Unit";"Baneling";"Zergling";262;0
"Unit";"Baneling";"Zergling";262;0
"Unit";"Baneling";"Zergling";262;0
"Unit";"Baneling";"Zergling";262;0
"Unit";"Baneling";"Zergling";262;0
"Building";"Hatchery";NA;234;0
"Upgrade";"EvolveGroovedSpines";"HydraliskDen";244;0
"Unit";"Overlord";"Larva";280;0
"Unit";"Overlord";"Larva";280;0
"Unit";"Zergling";"Larva";280;1
"Unit";"Zergling";"Larva";280;1
"Unit";"Zergling";"Larva";280;1
"Unit";"Zergling";"Larva";280;1
"Unit";"Zergling";"Larva";280;1
"Unit";"Zergling";"Larva";280;1
"Unit";"Zergling";"Larva";280;1
"Unit";"Zergling";"Larva";280;1
"Unit";"Zergling";"Larva";280;1
"Unit";"Zergling";"Larva";280;1
"Unit";"Zergling";"Larva";280;1
"Unit";"Zergling";"Larva";280;1
"Unit";"Zergling";"Larva";280;1
"Unit";"Zergling";"Larva";280;1
"Unit";"Zergling";"Larva";280;1
"Unit";"Zergling";"Larva";280;1
"Unit";"Zergling";"Larva";280;1
"Unit";"Zergling";"Larva";280;1
"Unit";"Zergling";"Larva";280;1
"Unit";"Zergling";"Larva";280;1
"Unit";"Zergling";"Larva";280;1
"Unit";"Zergling";"Larva";280;1
"Unit";"Zergling";"Larva";280;1
"Unit";"Zergling";"Larva";280;1
"Unit";"Zergling";"Larva";280;1
"Unit";"Zergling";"Larva";280;1
"Unit";"Zergling";"Larva";280;1
"Unit";"Zergling";"Larva";280;1
"Unit";"Zergling";"Larva";280;1
"Unit";"Zergling";"Larva";280;1
"Unit";"Zergling";"Larva";280;1
"Unit";"Zergling";"Larva";280;1
"Building";"InfestationPit";NA;280;0
"Unit";"Baneling";"Zergling";312;0
"Unit";"Baneling";"Zergling";312;0
"Unit";"Baneling";"Zergling";312;0
"Unit";"Baneling";"Zergling";312;0
"Unit";"Baneling";"Zergling";312;0
"Unit";"Baneling";"Zergling";312;0
"Unit";"Baneling";"Zergling";312;0
"Unit";"Baneling";"Zergling";312;0
"Unit";"Baneling";"Zergling";312;0
"Unit";"Baneling";"Zergling";312;0
"Unit";"Zergling";"Larva";312;1
"Unit";"Zergling";"Larva";312;1
"Unit";"Zergling";"Larva";312;1
"Unit";"Zergling";"Larva";312;1
"Unit";"Zergling";"Larva";312;1
"Unit";"Zergling";"Larva";312;1
"Unit";"Zergling";"Larva";312;1
"Unit";"Zergling";"Larva";312;1
"Unit";"Zergling";"Larva";312;1
"Unit";"Zergling";"Larva";312;1
"Unit";"Zergling";"Larva";312;1
"Unit";"Zergling";"Larva";312;1
"Unit";"Zergling";"Larva";312;1
"Unit";"Zergling";"Larva";312;1
"Unit";"Zergling";"Larva";312;1
"Unit";"Zergling";"Larva";312;1
"Unit";"Zergling";"Larva";312;1
"Unit";"Zergling";"Larva";312;1
"Unit";"Zergling";"Larva";312;1
"Unit";"Zergling";"Larva";312;1
"Unit";"Zergling";"Larva";312;1
"Unit";"Zergling";"Larva";312;1
"Unit";"Zergling";"Larva";312;1
"Unit";"Zergling";"Larva";312;1
"Unit";"Zergling";"Larva";312;1
"Unit";"Zergling";"Larva";312;1
"Unit";"Zergling";"Larva";312;1
"Unit";"Zergling";"Larva";312;1
"Unit";"Zergling";"Larva";312;1
"Unit";"Zergling";"Larva";312;1
"Unit";"Zergling";"Larva";312;1
"Unit";"Zergling";"Larva";312;1
"Building";"CreepTumorQueen";NA;312;0
"Building";"CreepTumor";NA;312;0
"Building";"CreepTumor";NA;344;0
"Building";"CreepTumorQueen";NA;344;0
"Building";"Extractor";NA;312;0
"Building";"Extractor";NA;312;0
"Unit";"Baneling";"Zergling";344;0
"Unit";"Baneling";"Zergling";344;0
"Unit";"Baneling";"Zergling";344;0
"Unit";"Baneling";"Zergling";344;0
"Unit";"Baneling";"Zergling";344;0
"Unit";"Baneling";"Zergling";344;0
"Unit";"Baneling";"Zergling";344;0
"Unit";"Baneling";"Zergling";344;0
"Unit";"Baneling";"Zergling";344;0
"Unit";"Baneling";"Zergling";344;0
"Unit";"Hydralisk";"Larva";344;2
"Unit";"Hydralisk";"Larva";344;2
"Unit";"Hydralisk";"Larva";344;2
"Unit";"Hydralisk";"Larva";344;2
"Unit";"Hydralisk";"Larva";344;2
"Unit";"Hydralisk";"Larva";344;2
"Unit";"Infestor";"Larva";344;2
"Unit";"Infestor";"Larva";344;2
"Unit";"Infestor";"Larva";344;2
"Building";"CreepTumor";NA;356;0
"Unit";"Infestor";"Larva";344;2
"Unit";"Infestor";"Larva";344;2
"Unit";"Infestor";"Larva";344;2
"Unit";"Infestor";"Larva";344;2
"Unit";"Infestor";"Larva";356;2
"Unit";"Infestor";"Larva";356;2
"Unit";"Infestor";"Larva";356;2
"Unit";"Infestor";"Larva";356;2
"Upgrade";"ZergMeleeWeaponsLevel2";"EvolutionChamber";312;0
"Upgrade";"ZergGroundArmorsLevel2";"EvolutionChamber";312;0
"Unit";"Zergling";"Larva";383;1
"Unit";"Zergling";"Larva";383;1
"Unit";"Zergling";"Larva";383;1
"Unit";"Zergling";"Larva";383;1
"Unit";"Zergling";"Larva";383;1
"Unit";"Zergling";"Larva";383;1
"Unit";"Zergling";"Larva";383;1
"Unit";"Zergling";"Larva";383;1
"Building";"CreepTumor";NA;383;0
"Building";"CreepTumor";NA;398;0
"Building";"CreepTumor";NA;398;0
"Building";"CreepTumorQueen";NA;398;0
"Unit";"Zergling";"Larva";398;1
"Unit";"Zergling";"Larva";398;1
"Unit";"Zergling";"Larva";398;1
"Unit";"Zergling";"Larva";398;1
"Building";"UltraliskCavern";NA;391;0
"Unit";"Zergling";"Larva";402;1
"Unit";"Zergling";"Larva";402;1
"Unit";"Zergling";"Larva";402;1
"Unit";"Zergling";"Larva";402;1
"Unit";"Zergling";"Larva";402;1
"Unit";"Zergling";"Larva";402;1
"Unit";"Zergling";"Larva";402;1
"Unit";"Zergling";"Larva";402;1
"Unit";"Zergling";"Larva";402;1
"Unit";"Zergling";"Larva";402;1
"Unit";"Zergling";"Larva";402;1
"Unit";"Zergling";"Larva";402;1
"Unit";"Zergling";"Larva";402;1
"Unit";"Zergling";"Larva";402;1
"Unit";"Zergling";"Larva";402;1
"Unit";"Zergling";"Larva";402;1
"Unit";"Zergling";"Larva";402;1
"Unit";"Zergling";"Larva";402;1
"Unit";"Zergling";"Larva";402;1
"Unit";"Zergling";"Larva";402;1
"Unit";"Zergling";"Larva";402;1
"Unit";"Zergling";"Larva";402;1
"Unit";"Infestor";"Larva";402;2
"Unit";"Ultralisk";"Larva";402;6
"Unit";"Ultralisk";"Larva";402;6
"Unit";"Ultralisk";"Larva";402;6
"Unit";"Ultralisk";"Larva";402;6
"Unit";"Ultralisk";"Larva";402;6
"Unit";"Ultralisk";"Larva";402;6
"Unit";"Ultralisk";"Larva";402;6
"Upgrade";"ZergMissileWeaponsLevel1";"EvolutionChamber";398;0
"Unit";"Zergling";"Larva";468;1
"Unit";"Zergling";"Larva";468;1
"Unit";"Zergling";"Larva";468;1
"Unit";"Zergling";"Larva";468;1
"Unit";"Zergling";"Larva";468;1
"Unit";"Zergling";"Larva";468;1
"Unit";"Zergling";"Larva";468;1
"Unit";"Zergling";"Larva";468;1
"Unit";"Zergling";"Larva";468;1
"Unit";"Zergling";"Larva";468;1
"Unit";"Zergling";"Larva";468;1
"Unit";"Zergling";"Larva";468;1
"Unit";"Zergling";"Larva";468;1
"Unit";"Zergling";"Larva";468;1
"Unit";"Zergling";"Larva";468;1
"Unit";"Zergling";"Larva";468;1
"Unit";"Zergling";"Larva";468;1
"Unit";"Zergling";"Larva";468;1
"Unit";"Zergling";"Larva";468;1
"Unit";"Zergling";"Larva";468;1
"Unit";"Zergling";"Larva";468;1
"Unit";"Zergling";"Larva";468;1
"Unit";"Zergling";"Larva";468;1
"Unit";"Zergling";"Larva";468;1
"Unit";"Zergling";"Larva";468;1
"Unit";"Zergling";"Larva";468;1
"Unit";"Zergling";"Larva";468;1
"Unit";"Zergling";"Larva";468;1
"Unit";"Zergling";"Larva";468;1
"Unit";"Zergling";"Larva";468;1
"Unit";"Zergling";"Larva";468;1
"Unit";"Zergling";"Larva";468;1
"Unit";"Zergling";"Larva";468;1
"Unit";"Zergling";"Larva";468;1
"Unit";"Zergling";"Larva";468;1
"Unit";"Zergling";"Larva";468;1
"Unit";"Ultralisk";"Larva";468;6
"Unit";"Ultralisk";"Larva";468;6
"Unit";"Ultralisk";"Larva";468;6
"Unit";"Ultralisk";"Larva";468;6
"Unit";"Zergling";"Larva";470;1
"Unit";"Zergling";"Larva";470;1
"Unit";"Zergling";"Larva";482;1
"Unit";"Zergling";"Larva";482;1
"Unit";"Zergling";"Larva";486;1
"Unit";"Zergling";"Larva";486;1
"Unit";"Zergling";"Larva";486;1
"Unit";"Zergling";"Larva";486;1
"Unit";"Zergling";"Larva";488;1
"Unit";"Zergling";"Larva";488;1
"Unit";"Zergling";"Larva";488;1
"Unit";"Zergling";"Larva";488;1
"Unit";"Zergling";"Larva";488;1
"Unit";"Zergling";"Larva";488;1
"Unit";"Zergling";"Larva";492;1
"Unit";"Zergling";"Larva";492;1
"Unit";"Zergling";"Larva";498;1
"Unit";"Zergling";"Larva";498;1
"Upgrade";"ZergGroundArmorsLevel3";"EvolutionChamber";402;0
"Building";"Extractor";NA;528;0
"Unit";"Baneling";"Zergling";528;0
"Unit";"Baneling";"Zergling";528;0
"Unit";"Baneling";"Zergling";528;0
"Unit";"Baneling";"Zergling";528;0
"Unit";"Baneling";"Zergling";528;0
"Unit";"Baneling";"Zergling";528;0
"Unit";"Baneling";"Zergling";528;0
"Unit";"Roach";"Larva";546;2
"Unit";"Zergling";"Larva";546;1
"Unit";"Zergling";"Larva";546;1
"Unit";"Zergling";"Larva";546;1
"Unit";"Zergling";"Larva";546;1
"Unit";"Zergling";"Larva";546;1
"Unit";"Zergling";"Larva";546;1
"Unit";"Zergling";"Larva";546;1
"Unit";"Zergling";"Larva";546;1
"Unit";"Zergling";"Larva";546;1
"Unit";"Zergling";"Larva";546;1
"Unit";"Zergling";"Larva";546;1
"Unit";"Zergling";"Larva";546;1
"Unit";"Zergling";"Larva";546;1
"Unit";"Zergling";"Larva";546;1
"Unit";"Infestor";"Larva";546;2
"Unit";"Infestor";"Larva";546;2
"Unit";"Infestor";"Larva";546;2
"Unit";"Infestor";"Larva";546;2
"Unit";"Infestor";"Larva";546;2
"Unit";"Infestor";"Larva";546;2
"Building";"Hatchery";NA;528;0
"Unit";"Zergling";"Larva";574;1
"Unit";"Zergling";"Larva";574;1
"Unit";"Zergling";"Larva";574;1
"Unit";"Zergling";"Larva";574;1
"Unit";"Zergling";"Larva";574;1
"Unit";"Zergling";"Larva";574;1
"Unit";"Zergling";"Larva";574;1
"Unit";"Zergling";"Larva";574;1
"Unit";"Zergling";"Larva";574;1
"Unit";"Zergling";"Larva";574;1
"Unit";"Zergling";"Larva";574;1
"Unit";"Zergling";"Larva";574;1
"Unit";"Zergling";"Larva";574;1
"Unit";"Zergling";"Larva";574;1
"Unit";"Zergling";"Larva";574;1
"Unit";"Zergling";"Larva";574;1
"Unit";"Zergling";"Larva";574;1
"Unit";"Zergling";"Larva";574;1
"Unit";"Zergling";"Larva";574;1
"Unit";"Zergling";"Larva";574;1
"Unit";"Hydralisk";"Larva";574;2
"Unit";"Hydralisk";"Larva";574;2
"Unit";"Hydralisk";"Larva";574;2
"Unit";"Hydralisk";"Larva";574;2
"Upgrade";"ChitinousPlating";"UltraliskCavern";574;0
"Unit";"Ultralisk";"Larva";574;6
"Unit";"Ultralisk";"Larva";574;6
"Unit";"Baneling";"Zergling";602;0
"Unit";"Baneling";"Zergling";602;0
"Unit";"Baneling";"Zergling";602;0
"Unit";"Baneling";"Zergling";602;0
"Unit";"Baneling";"Zergling";602;0
"Unit";"Baneling";"Zergling";602;0
"Unit";"Baneling";"Zergling";602;0
"Unit";"Hydralisk";"Larva";602;2
"Unit";"Hydralisk";"Larva";602;2
"Unit";"Hydralisk";"Larva";602;2
"Unit";"Hydralisk";"Larva";602;2
"Unit";"Hydralisk";"Larva";602;2
"Unit";"Hydralisk";"Larva";602;2
"Unit";"Hydralisk";"Larva";602;2
"Unit";"Zergling";"Larva";633;1
"Unit";"Zergling";"Larva";633;1
"Unit";"Zergling";"Larva";633;1
"Unit";"Zergling";"Larva";633;1
"Unit";"Zergling";"Larva";633;1
"Unit";"Zergling";"Larva";633;1
"Unit";"Zergling";"Larva";633;1
"Unit";"Zergling";"Larva";633;1
"Unit";"Zergling";"Larva";633;1
"Unit";"Zergling";"Larva";633;1
"Unit";"Zergling";"Larva";633;1
"Unit";"Zergling";"Larva";633;1
"Unit";"Zergling";"Larva";633;1
"Unit";"Zergling";"Larva";633;1
"Unit";"Zergling";"Larva";633;1
"Unit";"Zergling";"Larva";633;1
"Unit";"Zergling";"Larva";633;1
"Unit";"Zergling";"Larva";633;1
"Unit";"Zergling";"Larva";633;1
"Unit";"Zergling";"Larva";633;1
"Unit";"Zergling";"Larva";633;1
"Unit";"Zergling";"Larva";633;1
"Upgrade";"ZergMeleeWeaponsLevel3";"EvolutionChamber";574;0
"Unit";"Infestor";"Larva";636;2
"Unit";"Zergling";"Larva";660;1
"Unit";"Zergling";"Larva";660;1
"Unit";"Zergling";"Larva";660;1
"Unit";"Zergling";"Larva";660;1
"Unit";"Zergling";"Larva";660;1
"Unit";"Zergling";"Larva";660;1
"Unit";"Zergling";"Larva";660;1
"Unit";"Zergling";"Larva";660;1
"Unit";"Zergling";"Larva";660;1
"Unit";"Zergling";"Larva";660;1
"Unit";"Zergling";"Larva";660;1
"Unit";"Zergling";"Larva";660;1
"Unit";"Zergling";"Larva";660;1
"Unit";"Zergling";"Larva";660;1
"Unit";"Zergling";"Larva";660;1
"Unit";"Zergling";"Larva";660;1
"Unit";"Zergling";"Larva";660;1
"Unit";"Zergling";"Larva";660;1
"Unit";"Zergling";"Larva";660;1
"Unit";"Zergling";"Larva";660;1
"Building";"Extractor";NA;660;0
"Building";"Extractor";NA;660;0
"Unit";"Infestor";"Larva";660;2
"Unit";"Infestor";"Larva";660;2
"Unit";"Infestor";"Larva";660;2
"Unit";"Infestor";"Larva";660;2
"Unit";"Infestor";"Larva";660;2
"Unit";"Zergling";"Larva";680;1
"Unit";"Zergling";"Larva";680;1
"Unit";"Zergling";"Larva";680;1
"Unit";"Zergling";"Larva";680;1
"Unit";"Zergling";"Larva";680;1
"Unit";"Zergling";"Larva";680;1
"Unit";"Zergling";"Larva";680;1
"Unit";"Zergling";"Larva";680;1
"Unit";"Zergling";"Larva";680;1
"Unit";"Zergling";"Larva";680;1
"Unit";"Zergling";"Larva";680;1
"Unit";"Zergling";"Larva";680;1
"Unit";"Zergling";"Larva";680;1
"Unit";"Zergling";"Larva";680;1
"Unit";"Zergling";"Larva";680;1
"Unit";"Zergling";"Larva";680;1
"Unit";"Zergling";"Larva";680;1
"Unit";"Zergling";"Larva";680;1
"Unit";"Zergling";"Larva";680;1
"Unit";"Zergling";"Larva";680;1
"Unit";"Ultralisk";"Larva";660;6
"Unit";"Ultralisk";"Larva";660;6
"Unit";"Ultralisk";"Larva";660;6
