"type";"unit_name";"on_building";"total_supply";"supply"
"Unit";"Overlord";"Larva";13;0
"Building";"Extractor";NA;18;0
"Building";"Hatchery";NA;16;0
"Building";"SpawningPool";NA;19;0
"Unit";"Overlord";"Larva";22;0
"Unit";"Zergling";"Larva";23;1
"Unit";"Zergling";"Larva";23;1
"Unit";"Queen";"Hatchery";23;2
"Unit";"Queen";"Hatchery";23;2
"Unit";"Overlord";"Larva";35;0
"Unit";"Overlord";"Larva";35;0
"Building";"CreepTumorQueen";NA;36;0
"Unit";"Queen";"Hatchery";35;2
"Unit";"Overlord";"Larva";39;0
"Building";"CreepTumor";NA;48;0
"Building";"CreepTumorQueen";NA;49;0
"Unit";"Overlord";"Larva";48;0
"Unit";"Zergling";"Larva";48;1
"Unit";"Zergling";"Larva";48;1
"Building";"CreepTumorQueen";NA;49;0
"Building";"Hatchery";NA;34;0
"Building";"Extractor";NA;48;0
"Unit";"Zergling";"Larva";49;1
"Unit";"Zergling";"Larva";49;1
"Unit";"Queen";"Hatchery";49;2
"Unit";"Zergling";"Larva";55;1
"Unit";"Zergling";"Larva";55;1
"Unit";"Zergling";"Larva";55;1
"Unit";"Zergling";"Larva";55;1
"Unit";"Zergling";"Larva";55;1
"Unit";"Zergling";"Larva";55;1
"Unit";"Zergling";"Larva";55;1
"Unit";"Zergling";"Larva";55;1
"Unit";"Zergling";"Larva";55;1
"Unit";"Zergling";"Larva";55;1
"Building";"CreepTumor";NA;57;0
"Unit";"Queen";"Hatchery";51;2
"Unit";"Overlord";"Larva";57;0
"Building";"RoachWarren";NA;55;0
"Unit";"Queen";"Hatchery";57;2
"Unit";"Zergling";"Larva";69;1
"Unit";"Zergling";"Larva";69;1
"Unit";"Zergling";"Larva";69;1
"Unit";"Zergling";"Larva";69;1
"Unit";"Zergling";"Larva";69;1
"Unit";"Zergling";"Larva";69;1
"Unit";"Zergling";"Larva";69;1
"Unit";"Zergling";"Larva";69;1
"Unit";"Zergling";"Larva";69;1
"Unit";"Zergling";"Larva";69;1
"Unit";"Zergling";"Larva";69;1
"Unit";"Zergling";"Larva";69;1
"Unit";"Overlord";"Larva";69;0
"Unit";"Queen";"Hatchery";57;2
"Building";"CreepTumor";NA;87;0
"Unit";"Overlord";"Larva";87;0
"Building";"Extractor";NA;87;0
"Building";"SporeCrawler";NA;91;0
"Building";"EvolutionChamber";NA;91;0
"Building";"EvolutionChamber";NA;91;0
"Building";"CreepTumorQueen";NA;95;0
"Building";"CreepTumor";NA;95;0
"Building";"CreepTumorQueen";NA;99;0
"Building";"CreepTumor";NA;97;0
"Building";"CreepTumorQueen";NA;99;0
"Building";"CreepTumorQueen";NA;101;0
"Building";"CreepTumorQueen";NA;101;0
"Unit";"Zergling";"Larva";99;1
"Unit";"Zergling";"Larva";99;1
"Unit";"Roach";"Larva";101;2
"Building";"Extractor";NA;99;0
"Unit";"Roach";"Larva";101;2
"Unit";"Zergling";"Larva";101;1
"Unit";"Zergling";"Larva";101;1
"Unit";"Roach";"Larva";101;2
"Building";"CreepTumorQueen";NA;103;0
"Unit";"Overlord";"Larva";103;0
"Building";"CreepTumor";NA;105;0
"Building";"CreepTumor";NA;105;0
"Unit";"Roach";"Larva";103;2
"Unit";"Roach";"Larva";103;2
"Building";"CreepTumor";NA;111;0
"Building";"CreepTumor";NA;111;0
"Building";"CreepTumor";NA;113;0
"Building";"CreepTumor";NA;115;0
"Building";"CreepTumorQueen";NA;120;0
"Building";"CreepTumor";NA;115;0
"Building";"Hatchery";NA;95;0
"Building";"InfestationPit";NA;113;0
"Building";"CreepTumor";NA;127;0
"Building";"CreepTumor";NA;127;0
"Building";"CreepTumor";NA;127;0
"Building";"CreepTumor";NA;127;0
"Building";"CreepTumor";NA;127;0
"Building";"CreepTumor";NA;127;0
"Building";"CreepTumorQueen";NA;129;0
"Building";"CreepTumor";NA;127;0
"Building";"CreepTumor";NA;127;0
"Unit";"Roach";"Larva";134;2
"Unit";"Zergling";"Larva";135;1
"Unit";"Zergling";"Larva";135;1
"Unit";"Roach";"Larva";135;2
"Building";"SporeCrawler";NA;135;0
"Building";"CreepTumor";NA;138;0
"Building";"CreepTumor";NA;138;0
"Upgrade";"GlialReconstitution";"RoachWarren";125;0
"Building";"CreepTumor";NA;140;0
"Building";"Extractor";NA;138;0
"Building";"Extractor";NA;138;0
"Upgrade";"ZergGroundArmorsLevel1";"EvolutionChamber";113;0
"Upgrade";"ZergMissileWeaponsLevel1";"EvolutionChamber";113;0
"Building";"CreepTumor";NA;147;0
"Building";"CreepTumor";NA;147;0
"Building";"CreepTumor";NA;147;0
"Unit";"Overlord";"Larva";144;0
"Unit";"Overlord";"Larva";144;0
"Building";"CreepTumor";NA;147;0
"Unit";"Overlord";"Larva";147;0
"Unit";"Overlord";"Larva";147;0
"Building";"Hatchery";NA;127;0
"Building";"HydraliskDen";NA;147;0
"Building";"CreepTumor";NA;152;0
"Unit";"Roach";"Larva";152;2
"Unit";"Roach";"Larva";152;2
"Unit";"Roach";"Larva";152;2
"Building";"CreepTumor";NA;152;0
"Building";"Extractor";NA;152;0
"Building";"CreepTumor";NA;155;0
"Building";"Extractor";NA;152;0
"Building";"SporeCrawler";NA;152;0
"Unit";"Hydralisk";"Larva";155;2
"Unit";"Hydralisk";"Larva";155;2
"Unit";"Hydralisk";"Larva";155;2
"Unit";"Hydralisk";"Larva";155;2
"Building";"CreepTumor";NA;164;0
"Building";"CreepTumor";NA;167;0
"Unit";"Overlord";"Larva";167;0
"Unit";"Overlord";"Larva";167;0
"Unit";"Overlord";"Larva";167;0
"Building";"CreepTumor";NA;175;0
"Unit";"Viper";"Larva";167;3
"Unit";"Viper";"Larva";167;3
"Unit";"Viper";"Larva";167;3
"Unit";"Overlord";"Larva";175;0
"Unit";"Overlord";"Larva";175;0
"Unit";"Overlord";"Larva";175;0
"Building";"CreepTumor";NA;179;0
"Building";"CreepTumor";NA;193;0
"Unit";"Overlord";"Larva";184;0
"Building";"CreepTumor";NA;193;0
"Unit";"Overlord";"Larva";184;0
"Building";"CreepTumor";NA;193;0
"Upgrade";"EvolveMuscularAugments";"HydraliskDen";167;0
"Unit";"Viper";"Larva";179;3
"Unit";"Viper";"Larva";180;3
"Building";"CreepTumor";NA;193;0
"Unit";"Viper";"Larva";193;3
"Unit";"Viper";"Larva";193;3
"Building";"CreepTumor";NA;207;0
"Building";"SpineCrawler";NA;193;0
"Building";"SpineCrawler";NA;193;0
"Building";"CreepTumor";NA;207;0
"Unit";"Hydralisk";"Larva";216;2
"Unit";"Hydralisk";"Larva";216;2
"Building";"Extractor";NA;216;0
"Unit";"Hydralisk";"Larva";216;2
"Unit";"Hydralisk";"Larva";216;2
"Building";"Extractor";NA;216;0
"Unit";"Roach";"Larva";216;2
"Unit";"Roach";"Larva";216;2
"Unit";"Roach";"Larva";216;2
"Unit";"Roach";"Larva";216;2
"Unit";"Roach";"Larva";216;2
"Building";"SporeCrawler";NA;216;0
"Building";"EvolutionChamber";NA;216;0
"Building";"CreepTumor";NA;216;0
"Upgrade";"ZergMissileWeaponsLevel2";"EvolutionChamber";175;0
"Upgrade";"ZergGroundArmorsLevel2";"EvolutionChamber";175;0
"Building";"EvolutionChamber";NA;216;0
"Building";"EvolutionChamber";NA;216;0
"Building";"EvolutionChamber";NA;216;0
"Building";"CreepTumor";NA;216;0
"Building";"EvolutionChamber";NA;216;0
"Building";"Hatchery";NA;193;0
"Building";"SpineCrawler";NA;216;0
"Unit";"Hydralisk";"Larva";216;2
"Unit";"Hydralisk";"Larva";216;2
"Unit";"Hydralisk";"Larva";216;2
"Unit";"Hydralisk";"Larva";216;2
"Unit";"Hydralisk";"Larva";216;2
"Unit";"Hydralisk";"Larva";216;2
"Unit";"Hydralisk";"Larva";216;2
"Building";"CreepTumor";NA;234;0
"Building";"CreepTumor";NA;234;0
"Building";"CreepTumorQueen";NA;250;0
"Building";"CreepTumorQueen";NA;250;0
"Upgrade";"EvolveGroovedSpines";"HydraliskDen";216;0
"Building";"CreepTumor";NA;250;0
"Building";"CreepTumor";NA;250;0
"Unit";"Hydralisk";"Larva";250;2
"Unit";"Hydralisk";"Larva";250;2
"Unit";"Hydralisk";"Larva";250;2
"Unit";"Hydralisk";"Larva";250;2
"Unit";"Hydralisk";"Larva";250;2
"Unit";"Hydralisk";"Larva";250;2
"Unit";"Hydralisk";"Larva";250;2
"Unit";"Hydralisk";"Larva";250;2
"Unit";"Hydralisk";"Larva";250;2
"Unit";"Hydralisk";"Larva";250;2
"Unit";"Hydralisk";"Larva";250;2
"Building";"CreepTumorQueen";NA;272;0
"Building";"CreepTumorQueen";NA;272;0
"Building";"CreepTumor";NA;272;0
"Building";"CreepTumor";NA;272;0
"Unit";"Viper";"Larva";250;3
"Unit";"Viper";"Larva";250;3
"Unit";"Viper";"Larva";250;3
"Unit";"Viper";"Larva";250;3
"Building";"Spire";NA;234;0
"Unit";"Roach";"Larva";272;2
"Unit";"Hydralisk";"Larva";272;2
"Unit";"Hydralisk";"Larva";272;2
"Unit";"Hydralisk";"Larva";272;2
"Unit";"Hydralisk";"Larva";272;2
"Unit";"Hydralisk";"Larva";272;2
"Unit";"Hydralisk";"Larva";272;2
"Building";"CreepTumor";NA;286;0
"Building";"CreepTumorQueen";NA;298;0
"Building";"CreepTumorQueen";NA;298;0
"Building";"CreepTumorQueen";NA;298;0
"Upgrade";"Burrow";"Hatchery";272;0
"Building";"Hatchery";NA;272;0
"Upgrade";"TunnelingClaws";"RoachWarren";298;0
"Building";"CreepTumor";NA;298;0
"Building";"CreepTumor";NA;298;0
"Building";"CreepTumor";NA;310;0
"Building";"CreepTumor";NA;310;0
"Building";"CreepTumor";NA;310;0
"Building";"CreepTumor";NA;310;0
"Building";"CreepTumor";NA;310;0
"Unit";"Roach";"Larva";310;2
"Unit";"Roach";"Larva";310;2
"Unit";"Roach";"Larva";310;2
"Unit";"Roach";"Larva";310;2
"Unit";"Roach";"Larva";310;2
"Unit";"Roach";"Larva";310;2
"Unit";"Roach";"Larva";310;2
"Unit";"Viper";"Larva";310;3
"Unit";"Viper";"Larva";310;3
"Unit";"Viper";"Larva";310;3
"Unit";"Viper";"Larva";310;3
"Building";"Hatchery";NA;310;0
"Upgrade";"ZergMeleeWeaponsLevel1";"EvolutionChamber";298;0
"Building";"CreepTumor";NA;336;0
"Building";"CreepTumor";NA;336;0
"Building";"CreepTumorQueen";NA;336;0
"Unit";"Viper";"Larva";336;3
"Unit";"Viper";"Larva";336;3
"Unit";"Viper";"Larva";336;3
"Unit";"Hydralisk";"Larva";336;2
"Unit";"Hydralisk";"Larva";336;2
"Unit";"Hydralisk";"Larva";336;2
"Unit";"Hydralisk";"Larva";336;2
"Unit";"Viper";"Larva";336;3
"Unit";"Viper";"Larva";336;3
"Upgrade";"ZergMissileWeaponsLevel3";"EvolutionChamber";310;0
"Unit";"Hydralisk";"Larva";353;2
"Unit";"Hydralisk";"Larva";353;2
"Unit";"Hydralisk";"Larva";359;2
"Unit";"Hydralisk";"Larva";359;2
"Unit";"Hydralisk";"Larva";363;2
"Unit";"Hydralisk";"Larva";363;2
"Unit";"Hydralisk";"Larva";363;2
"Unit";"Hydralisk";"Larva";363;2
"Unit";"Hydralisk";"Larva";375;2
"Unit";"Hydralisk";"Larva";375;2
"Unit";"Hydralisk";"Larva";375;2
"Unit";"Hydralisk";"Larva";375;2
"Unit";"Hydralisk";"Larva";375;2
"Unit";"Hydralisk";"Larva";375;2
"Unit";"Hydralisk";"Larva";375;2
"Unit";"Hydralisk";"Larva";375;2
"Unit";"Hydralisk";"Larva";375;2
"Unit";"Hydralisk";"Larva";375;2
"Unit";"Hydralisk";"Larva";375;2
"Unit";"Hydralisk";"Larva";375;2
"Unit";"Hydralisk";"Larva";375;2
"Unit";"Hydralisk";"Larva";375;2
"Unit";"Hydralisk";"Larva";375;2
"Building";"Extractor";NA;375;0
"Building";"SporeCrawler";NA;375;0
"Unit";"Hydralisk";"Larva";375;2
"Unit";"Hydralisk";"Larva";375;2
"Building";"Extractor";NA;375;0
"Unit";"Hydralisk";"Larva";375;2
"Unit";"Hydralisk";"Larva";375;2
"Unit";"Hydralisk";"Larva";375;2
"Unit";"Hydralisk";"Larva";375;2
"Building";"CreepTumor";NA;405;0
"Unit";"Hydralisk";"Larva";375;2
"Unit";"Hydralisk";"Larva";375;2
"Unit";"Hydralisk";"Larva";375;2
"Unit";"Roach";"Larva";405;2
"Unit";"Roach";"Larva";405;2
"Unit";"Roach";"Larva";405;2
"Unit";"Roach";"Larva";405;2
"Unit";"Roach";"Larva";405;2
"Building";"SpineCrawler";NA;375;0
"Building";"Spire";NA;363;0
"Unit";"Hydralisk";"Larva";409;2
"Unit";"Hydralisk";"Larva";409;2
"Unit";"Hydralisk";"Larva";409;2
"Unit";"Hydralisk";"Larva";409;2
"Unit";"Hydralisk";"Larva";409;2
"Unit";"Hydralisk";"Larva";409;2
"Building";"CreepTumor";NA;445;0
"Unit";"Hydralisk";"Larva";445;2
"Unit";"Hydralisk";"Larva";445;2
"Unit";"Hydralisk";"Larva";445;2
"Unit";"Hydralisk";"Larva";445;2
"Unit";"Hydralisk";"Larva";445;2
"Unit";"Hydralisk";"Larva";445;2
"Unit";"Hydralisk";"Larva";445;2
"Unit";"Hydralisk";"Larva";445;2
"Unit";"Hydralisk";"Larva";445;2
"Unit";"Hydralisk";"Larva";445;2
"Unit";"Hydralisk";"Larva";445;2
"Unit";"Hydralisk";"Larva";445;2
"Unit";"Hydralisk";"Larva";445;2
"Building";"CreepTumor";NA;445;0
"Unit";"Hydralisk";"Larva";445;2
"Unit";"Hydralisk";"Larva";445;2
"Unit";"Hydralisk";"Larva";445;2
"Unit";"Hydralisk";"Larva";445;2
"Unit";"Hydralisk";"Larva";445;2
"Unit";"Roach";"Larva";445;2
"Building";"CreepTumor";NA;445;0
"Unit";"Roach";"Larva";445;2
"Unit";"Roach";"Larva";445;2
"Unit";"Roach";"Larva";445;2
"Unit";"Roach";"Larva";445;2
"Unit";"Roach";"Larva";445;2
"Unit";"Roach";"Larva";471;2
"Building";"CreepTumor";NA;481;0
"Upgrade";"ZergMeleeWeaponsLevel2";"EvolutionChamber";375;0
"Building";"CreepTumor";NA;493;0
"Building";"CreepTumor";NA;495;0
"Building";"CreepTumor";NA;495;0
"Upgrade";"ZergGroundArmorsLevel3";"EvolutionChamber";375;0
