"type";"unit_name";"on_building";"total_supply";"supply"
"Unit";"Overlord";"Larva";13;0
"Building";"Extractor";NA;18;0
"Building";"SpawningPool";NA;19;0
"Building";"Hatchery";NA;17;0
"Unit";"Overlord";"Larva";22;0
"Unit";"Queen";"Hatchery";22;2
"Unit";"Queen";"Hatchery";23;2
"Building";"Extractor";NA;33;0
"Unit";"Overlord";"Larva";36;0
"Unit";"Queen";"Hatchery";33;2
"Building";"CreepTumorQueen";NA;38;0
"Unit";"Overlord";"Larva";40;0
"Building";"Extractor";NA;40;0
"Building";"Extractor";NA;40;0
"Building";"CreepTumorQueen";NA;52;0
"Building";"CreepTumor";NA;52;0
"Unit";"Overlord";"Larva";55;0
"Unit";"Overlord";"Larva";56;0
"Unit";"Zergling";"Larva";59;1
"Unit";"Zergling";"Larva";59;1
"Unit";"Zergling";"Larva";59;1
"Unit";"Zergling";"Larva";59;1
"Unit";"Zergling";"Larva";59;1
"Unit";"Zergling";"Larva";59;1
"Unit";"Zergling";"Larva";59;1
"Unit";"Zergling";"Larva";59;1
"Unit";"Zergling";"Larva";59;1
"Unit";"Zergling";"Larva";59;1
"Building";"SporeCrawler";NA;59;0
"Building";"EvolutionChamber";NA;59;0
"Building";"Spire";NA;50;0
"Building";"EvolutionChamber";NA;59;0
"Unit";"Overlord";"Larva";69;0
"Unit";"Zergling";"Larva";73;1
"Unit";"Zergling";"Larva";73;1
"Unit";"Zergling";"Larva";73;1
"Unit";"Zergling";"Larva";73;1
"Unit";"Zergling";"Larva";73;1
"Unit";"Zergling";"Larva";73;1
"Building";"Hatchery";NA;59;0
"Unit";"Mutalisk";"Larva";73;2
"Unit";"Mutalisk";"Larva";73;2
"Unit";"Mutalisk";"Larva";73;2
"Unit";"Mutalisk";"Larva";73;2
"Unit";"Mutalisk";"Larva";73;2
"Unit";"Mutalisk";"Larva";73;2
"Building";"CreepTumor";NA;79;0
"Unit";"Mutalisk";"Larva";79;2
"Unit";"Mutalisk";"Larva";79;2
"Unit";"Mutalisk";"Larva";89;2
"Unit";"Queen";"Hatchery";79;2
"Unit";"Overlord";"Larva";105;0
"Unit";"Overlord";"Larva";105;0
"Building";"CreepTumor";NA;110;0
"Building";"RoachWarren";NA;108;0
"Unit";"Overlord";"Larva";114;0
"Building";"Extractor";NA;116;0
"Building";"Extractor";NA;116;0
"Unit";"Queen";"Hatchery";116;2
"Building";"InfestationPit";NA;120;0
"Unit";"Roach";"Larva";128;2
"Unit";"Roach";"Larva";130;2
"Unit";"Roach";"Larva";130;2
"Unit";"Roach";"Larva";130;2
"Unit";"Roach";"Larva";130;2
"Unit";"Roach";"Larva";131;2
"Unit";"Roach";"Larva";131;2
"Unit";"Roach";"Larva";131;2
"Unit";"Roach";"Larva";131;2
"Unit";"Roach";"Larva";131;2
"Unit";"Roach";"Larva";131;2
"Building";"BanelingNest";NA;121;0
"Unit";"Roach";"Larva";133;2
"Unit";"Roach";"Larva";133;2
"Unit";"Overlord";"Larva";133;0
"Unit";"Overlord";"Larva";133;0
"Unit";"Overlord";"Larva";133;0
"Upgrade";"ZergMissileWeaponsLevel1";"EvolutionChamber";114;0
"Upgrade";"ZergGroundArmorsLevel1";"EvolutionChamber";114;0
"Unit";"Overlord";"Larva";133;0
"Building";"Hatchery";NA;120;0
"Upgrade";"GlialReconstitution";"RoachWarren";123;0
"Unit";"Overlord";"Larva";153;0
"Unit";"Overlord";"Larva";153;0
"Building";"CreepTumor";NA;155;0
"Unit";"Overlord";"Larva";153;0
"Unit";"Overlord";"Larva";153;0
"Unit";"Roach";"Larva";157;2
"Unit";"Roach";"Larva";157;2
"Unit";"Roach";"Larva";157;2
"Unit";"Roach";"Larva";157;2
"Unit";"Roach";"Larva";157;2
"Unit";"Roach";"Larva";157;2
"Unit";"Roach";"Larva";157;2
"Unit";"Roach";"Larva";157;2
"Unit";"Roach";"Larva";157;2
"Unit";"Roach";"Larva";157;2
"Unit";"Overlord";"Larva";157;0
"Unit";"Roach";"Larva";157;2
"Unit";"Roach";"Larva";157;2
"Unit";"Baneling";"Zergling";169;0
"Unit";"Baneling";"Zergling";169;0
"Unit";"Roach";"Larva";157;2
"Unit";"Baneling";"Zergling";169;0
"Unit";"Queen";"Hatchery";157;2
"Unit";"Roach";"Larva";157;2
"Unit";"Baneling";"Zergling";177;0
"Building";"CreepTumor";NA;177;0
"Unit";"Zergling";"Larva";177;1
"Unit";"Zergling";"Larva";177;1
"Unit";"Zergling";"Larva";177;1
"Unit";"Zergling";"Larva";177;1
"Unit";"Zergling";"Larva";177;1
"Unit";"Zergling";"Larva";177;1
"Unit";"Zergling";"Larva";177;1
"Unit";"Zergling";"Larva";177;1
"Unit";"Zergling";"Larva";177;1
"Unit";"Zergling";"Larva";177;1
"Unit";"Zergling";"Larva";177;1
"Unit";"Zergling";"Larva";177;1
"Unit";"Zergling";"Larva";177;1
"Unit";"Zergling";"Larva";177;1
"Unit";"Zergling";"Larva";177;1
"Unit";"Zergling";"Larva";177;1
"Unit";"Roach";"Larva";187;2
"Unit";"Roach";"Larva";187;2
"Unit";"Roach";"Larva";187;2
"Unit";"Roach";"Larva";187;2
"Building";"CreepTumor";NA;211;0
"Unit";"Zergling";"Larva";211;1
"Unit";"Zergling";"Larva";211;1
"Unit";"Zergling";"Larva";211;1
"Unit";"Zergling";"Larva";211;1
"Unit";"Zergling";"Larva";211;1
"Unit";"Zergling";"Larva";211;1
"Unit";"Zergling";"Larva";211;1
"Unit";"Zergling";"Larva";211;1
"Unit";"Zergling";"Larva";211;1
"Unit";"Zergling";"Larva";211;1
"Unit";"Zergling";"Larva";211;1
"Unit";"Zergling";"Larva";211;1
"Unit";"Zergling";"Larva";211;1
"Unit";"Zergling";"Larva";211;1
"Unit";"Zergling";"Larva";211;1
"Unit";"Zergling";"Larva";211;1
"Unit";"Zergling";"Larva";211;1
"Unit";"Zergling";"Larva";211;1
"Unit";"Zergling";"Larva";211;1
"Unit";"Zergling";"Larva";211;1
"Unit";"Zergling";"Larva";211;1
"Unit";"Zergling";"Larva";211;1
"Unit";"Zergling";"Larva";211;1
"Unit";"Zergling";"Larva";211;1
"Unit";"Baneling";"Zergling";211;0
"Unit";"Baneling";"Zergling";211;0
"Unit";"Baneling";"Zergling";211;0
"Unit";"Baneling";"Zergling";211;0
"Unit";"Baneling";"Zergling";211;0
"Unit";"Baneling";"Zergling";211;0
"Unit";"Baneling";"Zergling";211;0
"Unit";"Baneling";"Zergling";211;0
"Unit";"Baneling";"Zergling";211;0
"Unit";"Roach";"Larva";211;2
"Unit";"Roach";"Larva";211;2
"Unit";"Roach";"Larva";211;2
"Unit";"Roach";"Larva";211;2
"Unit";"Overlord";"Larva";211;0
"Unit";"Overlord";"Larva";219;0
"Unit";"Overlord";"Larva";221;0
"Unit";"Overlord";"Larva";221;0
"Building";"UltraliskCavern";NA;211;0
"Unit";"Zergling";"Larva";243;1
"Unit";"Zergling";"Larva";243;1
"Unit";"Zergling";"Larva";243;1
"Unit";"Zergling";"Larva";243;1
"Unit";"Zergling";"Larva";243;1
"Unit";"Zergling";"Larva";243;1
"Unit";"Zergling";"Larva";243;1
"Unit";"Zergling";"Larva";243;1
"Unit";"Zergling";"Larva";243;1
"Unit";"Zergling";"Larva";243;1
"Unit";"Zergling";"Larva";243;1
"Unit";"Zergling";"Larva";243;1
"Unit";"Zergling";"Larva";243;1
"Unit";"Zergling";"Larva";243;1
"Unit";"Zergling";"Larva";243;1
"Unit";"Zergling";"Larva";243;1
"Unit";"Zergling";"Larva";243;1
"Unit";"Zergling";"Larva";243;1
"Unit";"Zergling";"Larva";243;1
"Unit";"Zergling";"Larva";243;1
"Unit";"Zergling";"Larva";243;1
"Unit";"Zergling";"Larva";243;1
"Unit";"Zergling";"Larva";243;1
"Unit";"Zergling";"Larva";243;1
"Unit";"Zergling";"Larva";243;1
"Unit";"Zergling";"Larva";243;1
"Unit";"Zergling";"Larva";243;1
"Unit";"Zergling";"Larva";243;1
"Unit";"Zergling";"Larva";243;1
"Unit";"Zergling";"Larva";243;1
