"type";"unit_name";"on_building";"total_supply";"supply"
"Unit";"Overlord";"Larva";13;0
"Building";"Extractor";NA;17;0
"Unit";"Overlord";"Larva";21;0
"Building";"SpawningPool";NA;19;0
"Building";"Hatchery";NA;17;0
"Unit";"Zergling";"Larva";23;1
"Unit";"Zergling";"Larva";23;1
"Unit";"Zergling";"Larva";23;1
"Unit";"Zergling";"Larva";23;1
"Unit";"Queen";"Hatchery";23;2
"Unit";"Queen";"Hatchery";23;2
"Unit";"Overlord";"Larva";26;0
"Unit";"Overlord";"Larva";26;0
"Unit";"Queen";"Hatchery";31;2
"Building";"CreepTumorQueen";NA;38;0
"Building";"EvolutionChamber";NA;36;0
"Building";"CreepTumorQueen";NA;43;0
"Building";"Extractor";NA;47;0
"Building";"CreepTumor";NA;50;0
"Building";"Extractor";NA;50;0
"Building";"CreepTumorQueen";NA;51;0
"Building";"CreepTumor";NA;51;0
"Unit";"Overlord";"Larva";57;0
"Unit";"Overlord";"Larva";57;0
"Unit";"Zergling";"Larva";57;1
"Unit";"Zergling";"Larva";57;1
"Building";"CreepTumor";NA;57;0
"Building";"CreepTumorQueen";NA;57;0
"Building";"HydraliskDen";NA;54;0
"Unit";"Overlord";"Larva";59;0
"Unit";"Overlord";"Larva";59;0
"Unit";"Hydralisk";"Larva";61;2
"Unit";"Hydralisk";"Larva";61;2
"Building";"Hatchery";NA;51;0
"Unit";"Hydralisk";"Larva";61;2
"Unit";"Hydralisk";"Larva";61;2
"Building";"CreepTumor";NA;61;0
"Building";"Extractor";NA;61;0
"Unit";"Hydralisk";"Larva";61;2
"Unit";"Hydralisk";"Larva";61;2
"Upgrade";"ZergGroundArmorsLevel1";"EvolutionChamber";55;0
"Building";"CreepTumorQueen";NA;85;0
"Building";"SporeCrawler";NA;79;0
"Unit";"Queen";"Hatchery";71;2
"Upgrade";"EvolveMuscularAugments";"HydraliskDen";61;0
"Unit";"Hydralisk";"Larva";83;2
"Unit";"Hydralisk";"Larva";84;2
"Building";"CreepTumor";NA;85;0
"Building";"CreepTumor";NA;92;0
"Unit";"Overlord";"Larva";100;0
"Unit";"Overlord";"Larva";100;0
"Unit";"Zergling";"Larva";100;1
"Unit";"Zergling";"Larva";100;1
"Unit";"Zergling";"Larva";100;1
"Unit";"Zergling";"Larva";100;1
"Unit";"Zergling";"Larva";100;1
"Unit";"Zergling";"Larva";100;1
"Unit";"Zergling";"Larva";100;1
"Unit";"Zergling";"Larva";100;1
"Unit";"Hydralisk";"Larva";100;2
"Unit";"Hydralisk";"Larva";100;2
"Building";"BanelingNest";NA;100;0
"Unit";"Hydralisk";"Larva";102;2
"Unit";"Zergling";"Larva";108;1
"Unit";"Zergling";"Larva";108;1
"Unit";"Zergling";"Larva";108;1
"Unit";"Zergling";"Larva";108;1
"Unit";"Zergling";"Larva";108;1
"Unit";"Zergling";"Larva";108;1
"Unit";"Zergling";"Larva";108;1
"Unit";"Zergling";"Larva";108;1
"Unit";"Hydralisk";"Larva";108;2
"Unit";"Hydralisk";"Larva";108;2
"Unit";"Baneling";"Zergling";112;0
"Unit";"Baneling";"Zergling";112;0
"Unit";"Baneling";"Zergling";112;0
"Unit";"Baneling";"Zergling";112;0
"Unit";"Baneling";"Zergling";112;0
"Building";"CreepTumor";NA;122;0
"Upgrade";"EvolveGroovedSpines";"HydraliskDen";100;0
"Building";"CreepTumorQueen";NA;126;0
"Building";"CreepTumorQueen";NA;126;0
"Building";"CreepTumorQueen";NA;126;0
"Unit";"Overlord";"Larva";126;0
"Unit";"Overlord";"Larva";126;0
"Unit";"Overlord";"Larva";126;0
"Unit";"Overlord";"Larva";126;0
"Unit";"Overlord";"Larva";126;0
"Unit";"Hydralisk";"Larva";124;2
"Building";"CreepTumorQueen";NA;126;0
"Unit";"Zergling";"Larva";128;1
"Unit";"Zergling";"Larva";128;1
"Unit";"Zergling";"Larva";128;1
"Unit";"Zergling";"Larva";128;1
"Unit";"Zergling";"Larva";128;1
"Unit";"Zergling";"Larva";128;1
"Unit";"Zergling";"Larva";128;1
"Unit";"Zergling";"Larva";128;1
"Unit";"Zergling";"Larva";128;1
"Unit";"Zergling";"Larva";128;1
"Unit";"Zergling";"Larva";128;1
"Unit";"Zergling";"Larva";128;1
"Unit";"Hydralisk";"Larva";126;2
"Unit";"Baneling";"Zergling";128;0
"Unit";"Baneling";"Zergling";128;0
"Unit";"Baneling";"Zergling";128;0
"Unit";"Baneling";"Zergling";128;0
"Unit";"Baneling";"Zergling";128;0
"Unit";"Baneling";"Zergling";128;0
"Unit";"Baneling";"Zergling";128;0
"Unit";"Baneling";"Zergling";128;0
"Building";"Hatchery";NA;124;0
"Upgrade";"ZergGroundArmorsLevel2";"EvolutionChamber";108;0
"Unit";"Hydralisk";"Larva";142;2
"Unit";"Hydralisk";"Larva";142;2
"Unit";"Hydralisk";"Larva";142;2
"Unit";"Zergling";"Larva";142;1
"Unit";"Zergling";"Larva";142;1
"Building";"CreepTumorQueen";NA;142;0
"Unit";"Zergling";"Larva";142;1
"Unit";"Zergling";"Larva";142;1
"Unit";"Zergling";"Larva";142;1
"Unit";"Zergling";"Larva";142;1
"Unit";"Zergling";"Larva";142;1
"Unit";"Zergling";"Larva";142;1
"Unit";"Zergling";"Larva";142;1
"Unit";"Zergling";"Larva";142;1
"Unit";"Zergling";"Larva";142;1
"Unit";"Zergling";"Larva";142;1
"Building";"CreepTumorQueen";NA;142;0
"Building";"CreepTumor";NA;142;0
"Building";"CreepTumorQueen";NA;163;0
"Building";"CreepTumor";NA;163;0
"Building";"CreepTumor";NA;163;0
"Building";"CreepTumor";NA;163;0
"Building";"CreepTumorQueen";NA;163;0
"Building";"EvolutionChamber";NA;142;0
"Building";"SporeCrawler";NA;163;0
"Building";"CreepTumor";NA;166;0
"Unit";"Baneling";"Zergling";166;0
"Building";"CreepTumor";NA;166;0
"Unit";"Baneling";"Zergling";166;0
"Unit";"Baneling";"Zergling";166;0
"Unit";"Baneling";"Zergling";166;0
"Unit";"Baneling";"Zergling";166;0
"Unit";"Baneling";"Zergling";166;0
"Unit";"Baneling";"Zergling";166;0
"Unit";"Baneling";"Zergling";166;0
"Unit";"Baneling";"Zergling";166;0
"Unit";"Baneling";"Zergling";166;0
"Building";"CreepTumor";NA;166;0
"Unit";"Queen";"Hatchery";150;2
"Building";"CreepTumor";NA;171;0
"Building";"CreepTumor";NA;171;0
"Building";"CreepTumor";NA;171;0
"Building";"CreepTumorQueen";NA;174;0
"Building";"CreepTumor";NA;171;0
"Building";"CreepTumor";NA;172;0
"Building";"CreepTumorQueen";NA;174;0
"Building";"CreepTumor";NA;174;0
"Building";"CreepTumor";NA;174;0
"Unit";"Hydralisk";"Larva";169;2
"Unit";"Hydralisk";"Larva";170;2
"Unit";"Hydralisk";"Larva";171;2
"Building";"CreepTumor";NA;174;0
"Unit";"Zergling";"Larva";174;1
"Unit";"Zergling";"Larva";174;1
"Unit";"Zergling";"Larva";174;1
"Unit";"Zergling";"Larva";174;1
"Unit";"Zergling";"Larva";174;1
"Unit";"Zergling";"Larva";174;1
"Unit";"Zergling";"Larva";174;1
"Unit";"Zergling";"Larva";174;1
"Unit";"Zergling";"Larva";174;1
"Unit";"Zergling";"Larva";174;1
"Unit";"Zergling";"Larva";174;1
"Unit";"Zergling";"Larva";174;1
"Unit";"Zergling";"Larva";174;1
"Unit";"Zergling";"Larva";174;1
"Unit";"Hydralisk";"Larva";174;2
"Unit";"Zergling";"Larva";174;1
"Unit";"Zergling";"Larva";174;1
"Unit";"Hydralisk";"Larva";174;2
"Unit";"Hydralisk";"Larva";174;2
"Unit";"Overlord";"Larva";174;0
"Building";"SporeCrawler";NA;174;0
"Building";"CreepTumor";NA;180;0
"Building";"CreepTumor";NA;180;0
"Building";"Hatchery";NA;150;0
"Building";"CreepTumor";NA;202;0
"Building";"CreepTumorQueen";NA;202;0
"Building";"CreepTumor";NA;202;0
"Unit";"Hydralisk";"Larva";180;2
"Unit";"Hydralisk";"Larva";180;2
"Unit";"Hydralisk";"Larva";180;2
"Unit";"Hydralisk";"Larva";180;2
"Unit";"Zergling";"Larva";202;1
"Unit";"Zergling";"Larva";202;1
"Unit";"Zergling";"Larva";202;1
"Unit";"Zergling";"Larva";202;1
"Building";"CreepTumorQueen";NA;202;0
"Building";"CreepTumor";NA;202;0
"Building";"CreepTumor";NA;202;0
"Building";"CreepTumor";NA;202;0
"Building";"CreepTumor";NA;202;0
"Building";"CreepTumor";NA;202;0
"Unit";"Overlord";"Larva";202;0
"Unit";"Overlord";"Larva";202;0
"Unit";"Overlord";"Larva";202;0
"Unit";"Overlord";"Larva";202;0
"Unit";"Hydralisk";"Larva";202;2
"Unit";"Hydralisk";"Larva";202;2
"Building";"InfestationPit";NA;202;0
"Building";"Extractor";NA;202;0
"Building";"Extractor";NA;208;0
"Unit";"Overlord";"Larva";214;0
"Unit";"Overlord";"Larva";214;0
"Unit";"Overlord";"Larva";214;0
"Upgrade";"ZergMeleeWeaponsLevel1";"EvolutionChamber";166;0
"Unit";"Baneling";"Zergling";222;0
"Unit";"Baneling";"Zergling";222;0
"Unit";"Baneling";"Zergling";222;0
"Unit";"Baneling";"Zergling";222;0
"Unit";"Baneling";"Zergling";222;0
"Unit";"Baneling";"Zergling";222;0
"Unit";"Baneling";"Zergling";222;0
"Unit";"Baneling";"Zergling";222;0
"Unit";"Baneling";"Zergling";222;0
"Unit";"Baneling";"Zergling";222;0
"Unit";"Baneling";"Zergling";222;0
"Unit";"Hydralisk";"Larva";222;2
"Unit";"Hydralisk";"Larva";222;2
"Building";"CreepTumor";NA;222;0
"Building";"CreepTumor";NA;222;0
"Building";"CreepTumor";NA;222;0
"Building";"CreepTumor";NA;222;0
"Building";"CreepTumor";NA;222;0
"Building";"CreepTumor";NA;222;0
"Unit";"Zergling";"Larva";222;1
"Unit";"Zergling";"Larva";222;1
"Unit";"Zergling";"Larva";222;1
"Unit";"Zergling";"Larva";222;1
"Unit";"Zergling";"Larva";222;1
"Unit";"Zergling";"Larva";222;1
"Unit";"Zergling";"Larva";222;1
"Unit";"Zergling";"Larva";222;1
"Unit";"Zergling";"Larva";222;1
"Unit";"Zergling";"Larva";222;1
"Unit";"Zergling";"Larva";222;1
"Unit";"Zergling";"Larva";222;1
"Unit";"Zergling";"Larva";222;1
"Unit";"Zergling";"Larva";222;1
"Unit";"Zergling";"Larva";222;1
"Unit";"Zergling";"Larva";222;1
"Unit";"Zergling";"Larva";222;1
"Unit";"Zergling";"Larva";222;1
"Upgrade";"ZergMissileWeaponsLevel1";"EvolutionChamber";180;0
"Unit";"Hydralisk";"Larva";222;2
"Unit";"Hydralisk";"Larva";222;2
"Unit";"Zergling";"Larva";226;1
"Unit";"Zergling";"Larva";226;1
"Unit";"Zergling";"Larva";226;1
"Unit";"Zergling";"Larva";226;1
"Unit";"Zergling";"Larva";226;1
"Unit";"Zergling";"Larva";226;1
"Unit";"Zergling";"Larva";226;1
"Unit";"Zergling";"Larva";226;1
"Unit";"Hydralisk";"Larva";226;2
"Unit";"Hydralisk";"Larva";226;2
"Unit";"Hydralisk";"Larva";226;2
"Unit";"Zergling";"Larva";244;1
"Unit";"Zergling";"Larva";244;1
"Unit";"Zergling";"Larva";244;1
"Unit";"Zergling";"Larva";244;1
"Unit";"Zergling";"Larva";244;1
"Unit";"Zergling";"Larva";244;1
"Unit";"Zergling";"Larva";244;1
"Unit";"Zergling";"Larva";244;1
"Unit";"Zergling";"Larva";244;1
"Unit";"Zergling";"Larva";244;1
"Unit";"Zergling";"Larva";244;1
"Unit";"Zergling";"Larva";244;1
"Unit";"Zergling";"Larva";244;1
"Unit";"Zergling";"Larva";244;1
"Unit";"Zergling";"Larva";244;1
"Unit";"Zergling";"Larva";244;1
"Unit";"Zergling";"Larva";248;1
"Unit";"Zergling";"Larva";248;1
"Unit";"Zergling";"Larva";248;1
"Unit";"Zergling";"Larva";248;1
"Building";"CreepTumorQueen";NA;293;0
"Building";"CreepTumorQueen";NA;295;0
"Building";"CreepTumorQueen";NA;295;0
"Building";"CreepTumorQueen";NA;295;0
"Unit";"Queen";"Hatchery";293;2
"Building";"SpineCrawler";NA;293;0
"Building";"SpineCrawler";NA;293;0
"Unit";"Overlord";"Larva";295;0
"Unit";"Overlord";"Larva";295;0
"Building";"SpineCrawler";NA;293;0
"Building";"SpineCrawler";NA;295;0
"Unit";"Viper";"Larva";297;3
"Unit";"Viper";"Larva";297;3
"Unit";"Viper";"Larva";297;3
"Unit";"Viper";"Larva";297;3
"Building";"EvolutionChamber";NA;297;0
"Building";"EvolutionChamber";NA;297;0
"Building";"Extractor";NA;297;0
"Building";"Extractor";NA;297;0
"Building";"Hatchery";NA;295;0
"Unit";"Baneling";"Zergling";319;0
"Unit";"Baneling";"Zergling";319;0
"Unit";"Baneling";"Zergling";319;0
"Unit";"Baneling";"Zergling";319;0
"Unit";"Baneling";"Zergling";319;0
"Building";"Spire";NA;295;0
"Unit";"Baneling";"Zergling";319;0
"Unit";"Baneling";"Zergling";319;0
"Unit";"Baneling";"Zergling";319;0
"Unit";"Baneling";"Zergling";319;0
"Unit";"Baneling";"Zergling";319;0
"Upgrade";"ZergMeleeWeaponsLevel2";"EvolutionChamber";295;0
"Upgrade";"ZergMissileWeaponsLevel2";"EvolutionChamber";295;0
"Building";"CreepTumor";NA;319;0
"Unit";"Zergling";"Larva";319;1
"Unit";"Zergling";"Larva";319;1
"Unit";"Zergling";"Larva";319;1
"Unit";"Zergling";"Larva";319;1
"Unit";"Zergling";"Larva";319;1
"Unit";"Zergling";"Larva";319;1
"Unit";"Zergling";"Larva";319;1
"Unit";"Zergling";"Larva";319;1
"Unit";"Zergling";"Larva";319;1
"Unit";"Zergling";"Larva";319;1
"Unit";"Zergling";"Larva";319;1
"Unit";"Zergling";"Larva";319;1
"Unit";"Zergling";"Larva";319;1
"Unit";"Zergling";"Larva";319;1
"Unit";"Zergling";"Larva";319;1
"Unit";"Zergling";"Larva";319;1
"Unit";"Zergling";"Larva";319;1
"Unit";"Zergling";"Larva";319;1
"Building";"CreepTumor";NA;319;0
"Building";"CreepTumor";NA;319;0
"Building";"CreepTumor";NA;319;0
"Building";"CreepTumor";NA;319;0
"Building";"SporeCrawler";NA;319;0
"Building";"CreepTumor";NA;319;0
"Building";"CreepTumor";NA;319;0
"Unit";"Corruptor";"Larva";319;2
"Unit";"Corruptor";"Larva";319;2
"Unit";"Corruptor";"Larva";319;2
"Unit";"Corruptor";"Larva";319;2
"Unit";"Corruptor";"Larva";319;2
"Unit";"Corruptor";"Larva";319;2
"Building";"SpineCrawler";NA;319;0
"Unit";"Hydralisk";"Larva";319;2
"Unit";"Hydralisk";"Larva";319;2
"Unit";"Hydralisk";"Larva";319;2
"Building";"Hatchery";NA;302;0
"Unit";"Hydralisk";"Larva";319;2
"Building";"SpineCrawler";NA;319;0
"Unit";"Baneling";"Zergling";357;0
"Unit";"Baneling";"Zergling";357;0
"Unit";"Baneling";"Zergling";357;0
"Unit";"Corruptor";"Larva";349;2
"Unit";"Corruptor";"Larva";349;2
"Unit";"Corruptor";"Larva";349;2
"Unit";"Corruptor";"Larva";349;2
"Building";"CreepTumorQueen";NA;359;0
"Unit";"Hydralisk";"Larva";357;2
"Unit";"Hydralisk";"Larva";357;2
"Unit";"Hydralisk";"Larva";357;2
"Building";"CreepTumorQueen";NA;359;0
"Building";"CreepTumorQueen";NA;367;0
"Unit";"Queen";"Hatchery";357;2
"Building";"CreepTumor";NA;377;0
"Unit";"Zergling";"Larva";377;1
"Unit";"Zergling";"Larva";377;1
"Unit";"Zergling";"Larva";377;1
"Unit";"Zergling";"Larva";377;1
"Unit";"Zergling";"Larva";377;1
"Unit";"Zergling";"Larva";377;1
"Unit";"Queen";"Hatchery";367;2
"Unit";"Baneling";"Zergling";381;0
"Unit";"Baneling";"Zergling";383;0
"Unit";"Baneling";"Zergling";383;0
"Unit";"Baneling";"Zergling";383;0
"Unit";"Baneling";"Zergling";383;0
"Unit";"Baneling";"Zergling";383;0
"Unit";"Baneling";"Zergling";383;0
"Unit";"Corruptor";"Larva";377;2
"Unit";"Corruptor";"Larva";377;2
"Unit";"Corruptor";"Larva";377;2
"Building";"UltraliskCavern";NA;377;0
"Building";"SpineCrawler";NA;377;0
"Building";"SpineCrawler";NA;377;0
"Building";"Extractor";NA;386;0
"Building";"Extractor";NA;386;0
"Unit";"Corruptor";"Larva";386;2
"Unit";"Corruptor";"Larva";386;2
"Unit";"Corruptor";"Larva";386;2
"Unit";"Corruptor";"Larva";386;2
"Unit";"Corruptor";"Larva";388;2
"Building";"SporeCrawler";NA;396;0
"Building";"SporeCrawler";NA;396;0
"Unit";"Corruptor";"Larva";396;2
"Building";"SporeCrawler";NA;396;0
"Building";"SporeCrawler";NA;396;0
"Unit";"Zergling";"Larva";409;1
"Unit";"Zergling";"Larva";409;1
"Unit";"Zergling";"Larva";409;1
"Unit";"Zergling";"Larva";409;1
"Unit";"Zergling";"Larva";409;1
"Unit";"Zergling";"Larva";409;1
"Unit";"Zergling";"Larva";409;1
"Unit";"Zergling";"Larva";409;1
"Unit";"Corruptor";"Larva";409;2
"Unit";"Corruptor";"Larva";409;2
"Unit";"Corruptor";"Larva";409;2
"Unit";"Corruptor";"Larva";409;2
"Unit";"Corruptor";"Larva";409;2
"Unit";"Corruptor";"Larva";409;2
"Unit";"Zergling";"Larva";425;1
"Unit";"Zergling";"Larva";425;1
"Unit";"Zergling";"Larva";425;1
"Unit";"Zergling";"Larva";425;1
"Unit";"Zergling";"Larva";425;1
"Unit";"Zergling";"Larva";425;1
"Unit";"Zergling";"Larva";427;1
"Unit";"Zergling";"Larva";427;1
"Unit";"Zergling";"Larva";427;1
"Unit";"Zergling";"Larva";427;1
"Unit";"Corruptor";"Larva";423;2
"Unit";"Corruptor";"Larva";425;2
"Unit";"Zergling";"Larva";427;1
"Unit";"Zergling";"Larva";427;1
"Unit";"Corruptor";"Larva";425;2
"Unit";"Zergling";"Larva";429;1
"Unit";"Zergling";"Larva";429;1
"Unit";"Zergling";"Larva";429;1
"Unit";"Zergling";"Larva";429;1
"Unit";"Zergling";"Larva";429;1
"Unit";"Zergling";"Larva";429;1
"Unit";"Zergling";"Larva";453;1
"Unit";"Zergling";"Larva";453;1
"Unit";"Zergling";"Larva";453;1
"Unit";"Zergling";"Larva";453;1
"Unit";"Zergling";"Larva";453;1
"Unit";"Zergling";"Larva";453;1
"Unit";"Corruptor";"Larva";453;2
"Unit";"Corruptor";"Larva";453;2
"Unit";"Corruptor";"Larva";453;2
"Unit";"Corruptor";"Larva";453;2
"Unit";"Corruptor";"Larva";453;2
