"type";"unit_name";"on_building";"total_supply";"supply"
"Unit";"Overlord";"Larva";12;0
"Building";"Extractor";NA;18;0
"Unit";"Overlord";"Larva";21;0
"Building";"SpawningPool";NA;19;0
"Building";"Hatchery";NA;17;0
"Unit";"Zergling";"Larva";23;1
"Unit";"Zergling";"Larva";23;1
"Unit";"Zergling";"Larva";23;1
"Unit";"Zergling";"Larva";23;1
"Unit";"Queen";"Hatchery";22;2
"Unit";"Queen";"Hatchery";23;2
"Unit";"Overlord";"Larva";35;0
"Unit";"Overlord";"Larva";36;0
"Unit";"Overlord";"Larva";36;0
"Unit";"Queen";"Hatchery";32;2
"Unit";"Queen";"Hatchery";33;2
"Building";"CreepTumorQueen";NA;37;0
"Unit";"Zergling";"Larva";36;1
"Unit";"Zergling";"Larva";36;1
"Unit";"Zergling";"Larva";36;1
"Unit";"Zergling";"Larva";36;1
"Building";"CreepTumorQueen";NA;39;0
"Building";"CreepTumorQueen";NA;55;0
"Unit";"Overlord";"Larva";55;0
"Building";"CreepTumorQueen";NA;65;0
"Building";"Extractor";NA;57;0
"Building";"CreepTumorQueen";NA;65;0
"Building";"CreepTumor";NA;65;0
"Building";"RoachWarren";NA;56;0
"Building";"CreepTumor";NA;65;0
"Unit";"Zergling";"Larva";65;1
"Unit";"Zergling";"Larva";65;1
"Unit";"Zergling";"Larva";65;1
"Unit";"Zergling";"Larva";65;1
"Building";"Extractor";NA;62;0
"Building";"Extractor";NA;65;0
"Building";"Hatchery";NA;54;0
"Unit";"Roach";"Larva";65;2
"Unit";"Roach";"Larva";65;2
"Building";"EvolutionChamber";NA;65;0
"Unit";"Roach";"Larva";69;2
"Unit";"Roach";"Larva";69;2
"Unit";"Roach";"Larva";69;2
"Building";"CreepTumor";NA;71;0
"Building";"CreepTumor";NA;71;0
"Building";"CreepTumor";NA;71;0
"Unit";"Roach";"Larva";71;2
"Unit";"Roach";"Larva";71;2
"Unit";"Roach";"Larva";71;2
"Unit";"Zergling";"Larva";84;1
"Unit";"Zergling";"Larva";84;1
"Unit";"Zergling";"Larva";84;1
"Unit";"Zergling";"Larva";84;1
"Unit";"Zergling";"Larva";84;1
"Unit";"Zergling";"Larva";84;1
"Unit";"Overlord";"Larva";96;0
"Unit";"Overlord";"Larva";96;0
"Unit";"Overlord";"Larva";96;0
"Unit";"Overlord";"Larva";96;0
"Unit";"Queen";"Hatchery";96;2
"Building";"CreepTumor";NA;97;0
"Building";"CreepTumorQueen";NA;102;0
"Building";"CreepTumor";NA;99;0
"Building";"Extractor";NA;97;0
"Building";"Extractor";NA;97;0
"Unit";"Overlord";"Larva";108;0
"Unit";"Overlord";"Larva";108;0
"Building";"CreepTumor";NA;113;0
"Building";"CreepTumorQueen";NA;116;0
"Upgrade";"ZergGroundArmorsLevel1";"EvolutionChamber";96;0
"Building";"CreepTumor";NA;116;0
"Building";"CreepTumor";NA;118;0
"Building";"CreepTumor";NA;124;0
"Unit";"Overlord";"Larva";116;0
"Unit";"Overlord";"Larva";116;0
"Building";"Spire";NA;97;0
"Building";"CreepTumor";NA;124;0
"Building";"CreepTumor";NA;124;0
"Unit";"Mutalisk";"Larva";124;2
"Unit";"Mutalisk";"Larva";124;2
"Unit";"Mutalisk";"Larva";124;2
"Unit";"Mutalisk";"Larva";124;2
"Unit";"Mutalisk";"Larva";124;2
"Unit";"Mutalisk";"Larva";124;2
"Unit";"Mutalisk";"Larva";124;2
"Unit";"Mutalisk";"Larva";124;2
"Unit";"Mutalisk";"Larva";124;2
"Building";"CreepTumor";NA;125;0
"Unit";"Mutalisk";"Larva";124;2
"Building";"CreepTumor";NA;125;0
"Unit";"Overlord";"Larva";125;0
"Unit";"Mutalisk";"Larva";125;2
"Unit";"Overlord";"Larva";125;0
"Building";"CreepTumor";NA;125;0
"Building";"CreepTumor";NA;125;0
"Building";"CreepTumorQueen";NA;139;0
"Building";"BanelingNest";NA;124;0
"Unit";"Zergling";"Larva";141;1
"Unit";"Zergling";"Larva";141;1
"Unit";"Zergling";"Larva";141;1
"Unit";"Zergling";"Larva";141;1
"Unit";"Zergling";"Larva";141;1
"Unit";"Zergling";"Larva";141;1
"Unit";"Zergling";"Larva";141;1
"Unit";"Zergling";"Larva";141;1
"Unit";"Zergling";"Larva";141;1
"Unit";"Zergling";"Larva";141;1
"Unit";"Zergling";"Larva";141;1
"Unit";"Zergling";"Larva";141;1
"Unit";"Zergling";"Larva";141;1
"Unit";"Zergling";"Larva";141;1
"Unit";"Zergling";"Larva";141;1
"Unit";"Zergling";"Larva";141;1
"Unit";"Zergling";"Larva";141;1
"Unit";"Zergling";"Larva";141;1
"Unit";"Zergling";"Larva";141;1
"Unit";"Zergling";"Larva";141;1
"Unit";"Overlord";"Larva";143;0
"Unit";"Overlord";"Larva";145;0
"Unit";"Overlord";"Larva";147;0
"Building";"EvolutionChamber";NA;147;0
"Unit";"Mutalisk";"Larva";168;2
"Unit";"Mutalisk";"Larva";168;2
"Unit";"Mutalisk";"Larva";168;2
"Unit";"Mutalisk";"Larva";168;2
"Unit";"Mutalisk";"Larva";168;2
"Unit";"Mutalisk";"Larva";168;2
"Unit";"Zergling";"Larva";168;1
"Unit";"Zergling";"Larva";168;1
"Unit";"Zergling";"Larva";168;1
"Unit";"Zergling";"Larva";168;1
"Unit";"Zergling";"Larva";168;1
"Unit";"Zergling";"Larva";168;1
"Unit";"Zergling";"Larva";168;1
"Unit";"Zergling";"Larva";168;1
"Unit";"Zergling";"Larva";168;1
"Unit";"Zergling";"Larva";168;1
"Unit";"Zergling";"Larva";168;1
"Unit";"Zergling";"Larva";168;1
"Unit";"Zergling";"Larva";168;1
"Unit";"Zergling";"Larva";168;1
"Unit";"Zergling";"Larva";168;1
"Unit";"Zergling";"Larva";168;1
"Unit";"Zergling";"Larva";168;1
"Unit";"Zergling";"Larva";168;1
"Unit";"Zergling";"Larva";168;1
"Unit";"Zergling";"Larva";168;1
"Unit";"Zergling";"Larva";200;1
"Unit";"Zergling";"Larva";200;1
"Unit";"Zergling";"Larva";200;1
"Unit";"Zergling";"Larva";200;1
"Unit";"Zergling";"Larva";200;1
"Unit";"Zergling";"Larva";200;1
"Unit";"Mutalisk";"Larva";200;2
"Unit";"Mutalisk";"Larva";200;2
"Unit";"Mutalisk";"Larva";200;2
"Unit";"Mutalisk";"Larva";200;2
"Unit";"Mutalisk";"Larva";200;2
"Unit";"Zergling";"Larva";200;1
"Unit";"Zergling";"Larva";200;1
"Unit";"Zergling";"Larva";200;1
"Unit";"Zergling";"Larva";200;1
"Unit";"Zergling";"Larva";200;1
"Unit";"Zergling";"Larva";200;1
"Unit";"Zergling";"Larva";200;1
"Unit";"Zergling";"Larva";200;1
"Building";"CreepTumor";NA;216;0
"Building";"CreepTumor";NA;222;0
"Unit";"Baneling";"Zergling";216;0
"Unit";"Baneling";"Zergling";216;0
"Unit";"Baneling";"Zergling";216;0
"Unit";"Baneling";"Zergling";216;0
"Unit";"Baneling";"Zergling";216;0
"Unit";"Baneling";"Zergling";216;0
"Building";"CreepTumorQueen";NA;222;0
"Unit";"Zergling";"Larva";216;1
"Unit";"Zergling";"Larva";216;1
"Unit";"Zergling";"Larva";216;1
"Unit";"Zergling";"Larva";216;1
"Unit";"Zergling";"Larva";216;1
"Unit";"Zergling";"Larva";216;1
"Building";"CreepTumorQueen";NA;224;0
"Building";"CreepTumorQueen";NA;224;0
"Building";"CreepTumorQueen";NA;224;0
"Unit";"Zergling";"Larva";232;1
"Unit";"Zergling";"Larva";232;1
"Unit";"Zergling";"Larva";233;1
"Unit";"Zergling";"Larva";233;1
"Unit";"Zergling";"Larva";233;1
"Unit";"Zergling";"Larva";233;1
"Unit";"Zergling";"Larva";234;1
"Unit";"Zergling";"Larva";234;1
"Unit";"Zergling";"Larva";234;1
"Unit";"Zergling";"Larva";234;1
"Unit";"Zergling";"Larva";234;1
"Unit";"Zergling";"Larva";234;1
"Unit";"Zergling";"Larva";234;1
"Unit";"Zergling";"Larva";234;1
"Building";"Extractor";NA;234;0
"Building";"Extractor";NA;234;0
"Unit";"Zergling";"Larva";234;1
"Unit";"Zergling";"Larva";234;1
"Unit";"Zergling";"Larva";234;1
"Unit";"Zergling";"Larva";234;1
"Unit";"Zergling";"Larva";234;1
"Unit";"Zergling";"Larva";234;1
"Unit";"Zergling";"Larva";234;1
"Unit";"Zergling";"Larva";234;1
"Unit";"Zergling";"Larva";234;1
"Unit";"Zergling";"Larva";234;1
"Unit";"Mutalisk";"Larva";234;2
"Unit";"Mutalisk";"Larva";234;2
"Unit";"Mutalisk";"Larva";234;2
"Unit";"Mutalisk";"Larva";234;2
"Unit";"Zergling";"Larva";258;1
"Unit";"Zergling";"Larva";258;1
"Unit";"Zergling";"Larva";258;1
"Unit";"Zergling";"Larva";258;1
"Unit";"Zergling";"Larva";258;1
"Unit";"Zergling";"Larva";258;1
"Unit";"Zergling";"Larva";258;1
"Unit";"Zergling";"Larva";258;1
"Unit";"Zergling";"Larva";258;1
"Unit";"Zergling";"Larva";258;1
"Unit";"Baneling";"Zergling";258;0
"Unit";"Baneling";"Zergling";258;0
"Unit";"Baneling";"Zergling";258;0
"Unit";"Baneling";"Zergling";258;0
"Unit";"Baneling";"Zergling";258;0
"Unit";"Baneling";"Zergling";258;0
"Unit";"Baneling";"Zergling";258;0
"Unit";"Baneling";"Zergling";258;0
"Unit";"Baneling";"Zergling";258;0
"Unit";"Baneling";"Zergling";258;0
"Unit";"Baneling";"Zergling";258;0
"Unit";"Baneling";"Zergling";258;0
"Unit";"Baneling";"Zergling";258;0
"Unit";"Baneling";"Zergling";258;0
"Unit";"Baneling";"Zergling";258;0
"Unit";"Baneling";"Zergling";258;0
"Unit";"Baneling";"Zergling";258;0
"Unit";"Baneling";"Zergling";258;0
"Unit";"Baneling";"Zergling";258;0
"Unit";"Baneling";"Zergling";258;0
"Unit";"Zergling";"Larva";258;1
"Unit";"Zergling";"Larva";258;1
"Unit";"Zergling";"Larva";258;1
"Unit";"Zergling";"Larva";258;1
"Unit";"Zergling";"Larva";260;1
"Unit";"Zergling";"Larva";260;1
"Unit";"Zergling";"Larva";262;1
"Unit";"Zergling";"Larva";262;1
"Unit";"Zergling";"Larva";262;1
"Unit";"Zergling";"Larva";262;1
"Unit";"Zergling";"Larva";264;1
"Unit";"Zergling";"Larva";264;1
"Unit";"Zergling";"Larva";266;1
"Unit";"Zergling";"Larva";266;1
"Unit";"Mutalisk";"Larva";266;2
"Unit";"Mutalisk";"Larva";266;2
"Unit";"Mutalisk";"Larva";266;2
"Building";"Hatchery";NA;230;0
"Upgrade";"ZergMeleeWeaponsLevel1";"EvolutionChamber";224;0
"Unit";"Mutalisk";"Larva";276;2
