"type";"unit_name";"on_building";"total_supply";"supply"
"Unit";"Overlord";"Larva";14;0
"Building";"Extractor";NA;15;0
"Building";"SpawningPool";NA;15;0
"Unit";"Zergling";"Larva";19;1
"Unit";"Zergling";"Larva";19;1
"Unit";"Zergling";"Larva";19;1
"Unit";"Zergling";"Larva";19;1
"Unit";"Zergling";"Larva";19;1
"Unit";"Zergling";"Larva";19;1
"Unit";"Overlord";"Larva";25;0
"Unit";"Queen";"Hatchery";25;2
"Building";"Hatchery";NA;19;0
"Building";"CreepTumorQueen";NA;32;0
"Unit";"Queen";"Hatchery";31;2
"Unit";"Overlord";"Larva";42;0
"Building";"CreepTumor";NA;45;0
"Building";"Hatchery";NA;31;0
"Unit";"Zergling";"Larva";46;1
"Unit";"Zergling";"Larva";46;1
"Unit";"Zergling";"Larva";46;1
"Unit";"Zergling";"Larva";46;1
"Unit";"Zergling";"Larva";46;1
"Unit";"Zergling";"Larva";46;1
"Building";"SporeCrawler";NA;46;0
"Building";"SporeCrawler";NA;46;0
"Unit";"Queen";"Hatchery";45;2
"Building";"CreepTumor";NA;62;0
"Building";"CreepTumorQueen";NA;62;0
"Building";"Extractor";NA;60;0
"Unit";"Overlord";"Larva";62;0
"Unit";"Zergling";"Larva";63;1
"Unit";"Zergling";"Larva";63;1
"Unit";"Zergling";"Larva";63;1
"Unit";"Zergling";"Larva";63;1
"Unit";"Zergling";"Larva";63;1
"Unit";"Zergling";"Larva";63;1
"Unit";"Zergling";"Larva";67;1
"Unit";"Zergling";"Larva";67;1
"Unit";"Zergling";"Larva";67;1
"Unit";"Zergling";"Larva";67;1
"Unit";"Zergling";"Larva";67;1
"Unit";"Zergling";"Larva";67;1
"Building";"BanelingNest";NA;57;0
"Unit";"Zergling";"Larva";67;1
"Unit";"Zergling";"Larva";67;1
"Unit";"Zergling";"Larva";67;1
"Unit";"Zergling";"Larva";67;1
"Unit";"Zergling";"Larva";67;1
"Unit";"Zergling";"Larva";67;1
"Building";"CreepTumor";NA;79;0
"Building";"CreepTumor";NA;79;0
"Unit";"Baneling";"Zergling";87;0
"Unit";"Baneling";"Zergling";87;0
"Unit";"Baneling";"Zergling";87;0
"Building";"RoachWarren";NA;67;0
"Building";"EvolutionChamber";NA;87;0
"Building";"CreepTumor";NA;92;0
"Unit";"Overlord";"Larva";92;0
"Unit";"Overlord";"Larva";92;0
"Unit";"Zergling";"Larva";92;1
"Unit";"Zergling";"Larva";92;1
"Unit";"Zergling";"Larva";92;1
"Unit";"Zergling";"Larva";92;1
"Building";"Extractor";NA;92;0
"Building";"Extractor";NA;92;0
"Unit";"Zergling";"Larva";92;1
"Unit";"Zergling";"Larva";92;1
"Unit";"Zergling";"Larva";92;1
"Unit";"Zergling";"Larva";92;1
"Unit";"Zergling";"Larva";92;1
"Unit";"Zergling";"Larva";92;1
"Unit";"Zergling";"Larva";92;1
"Unit";"Zergling";"Larva";92;1
"Unit";"Zergling";"Larva";92;1
"Unit";"Zergling";"Larva";92;1
"Unit";"Zergling";"Larva";92;1
"Unit";"Zergling";"Larva";92;1
"Unit";"Zergling";"Larva";92;1
"Unit";"Zergling";"Larva";92;1
"Unit";"Zergling";"Larva";92;1
"Unit";"Zergling";"Larva";92;1
"Unit";"Zergling";"Larva";92;1
"Unit";"Zergling";"Larva";92;1
"Unit";"Zergling";"Larva";92;1
"Unit";"Zergling";"Larva";92;1
"Unit";"Zergling";"Larva";92;1
"Unit";"Zergling";"Larva";92;1
"Unit";"Zergling";"Larva";92;1
"Unit";"Zergling";"Larva";92;1
"Unit";"Zergling";"Larva";96;1
"Unit";"Zergling";"Larva";96;1
"Unit";"Zergling";"Larva";96;1
"Unit";"Zergling";"Larva";96;1
"Unit";"Zergling";"Larva";96;1
"Unit";"Zergling";"Larva";96;1
"Unit";"Zergling";"Larva";96;1
"Unit";"Zergling";"Larva";96;1
"Unit";"Zergling";"Larva";96;1
"Unit";"Zergling";"Larva";96;1
"Unit";"Zergling";"Larva";96;1
"Unit";"Zergling";"Larva";96;1
"Unit";"Zergling";"Larva";96;1
"Unit";"Zergling";"Larva";96;1
"Unit";"Zergling";"Larva";96;1
"Unit";"Zergling";"Larva";96;1
"Unit";"Zergling";"Larva";120;1
"Unit";"Zergling";"Larva";120;1
"Unit";"Zergling";"Larva";120;1
"Unit";"Zergling";"Larva";120;1
"Unit";"Zergling";"Larva";137;1
"Unit";"Zergling";"Larva";137;1
"Unit";"Zergling";"Larva";137;1
"Unit";"Zergling";"Larva";137;1
"Building";"CreepTumor";NA;141;0
"Building";"CreepTumor";NA;141;0
"Unit";"Baneling";"Zergling";141;0
"Unit";"Baneling";"Zergling";141;0
"Unit";"Baneling";"Zergling";145;0
"Unit";"Baneling";"Zergling";145;0
"Unit";"Baneling";"Zergling";145;0
"Building";"CreepTumor";NA;151;0
"Building";"CreepTumor";NA;151;0
"Unit";"Overlord";"Larva";151;0
"Unit";"Overlord";"Larva";151;0
"Unit";"Roach";"Larva";151;2
"Upgrade";"ZergMissileWeaponsLevel1";"EvolutionChamber";112;0
"Building";"CreepTumorQueen";NA;151;0
"Building";"CreepTumorQueen";NA;153;0
"Unit";"Overlord";"Larva";151;0
"Unit";"Roach";"Larva";151;2
"Upgrade";"GlialReconstitution";"RoachWarren";143;0
"Unit";"Roach";"Larva";153;2
"Unit";"Roach";"Larva";153;2
"Unit";"Roach";"Larva";153;2
"Unit";"Roach";"Larva";153;2
"Building";"Hatchery";NA;139;0
"Unit";"Overlord";"Larva";153;0
"Building";"CreepTumor";NA;153;0
"Building";"CreepTumor";NA;155;0
"Unit";"Roach";"Larva";153;2
"Unit";"Roach";"Larva";153;2
"Unit";"Roach";"Larva";153;2
"Unit";"Roach";"Larva";155;2
"Building";"CreepTumor";NA;163;0
"Building";"CreepTumor";NA;163;0
"Unit";"Baneling";"Zergling";163;0
"Unit";"Baneling";"Zergling";163;0
"Unit";"Roach";"Larva";163;2
"Unit";"Roach";"Larva";163;2
"Unit";"Roach";"Larva";163;2
"Unit";"Roach";"Larva";163;2
"Unit";"Roach";"Larva";163;2
"Unit";"Roach";"Larva";163;2
"Unit";"Roach";"Larva";163;2
"Building";"Hatchery";NA;151;0
"Unit";"Overlord";"Larva";171;0
"Unit";"Overlord";"Larva";171;0
"Building";"CreepTumor";NA;185;0
"Building";"CreepTumor";NA;185;0
"Unit";"Overlord";"Larva";185;0
"Building";"HydraliskDen";NA;185;0
"Building";"CreepTumor";NA;185;0
"Building";"CreepTumor";NA;185;0
"Unit";"Roach";"Larva";185;2
"Unit";"Roach";"Larva";185;2
"Unit";"Roach";"Larva";185;2
"Building";"CreepTumor";NA;185;0
"Unit";"Roach";"Larva";185;2
"Unit";"Roach";"Larva";185;2
"Unit";"Roach";"Larva";185;2
"Unit";"Roach";"Larva";185;2
"Unit";"Roach";"Larva";185;2
"Unit";"Roach";"Larva";185;2
"Unit";"Roach";"Larva";185;2
"Unit";"Roach";"Larva";185;2
"Unit";"Roach";"Larva";185;2
"Unit";"Roach";"Larva";185;2
