"type";"unit_name";"on_building";"total_supply";"supply"
"Unit";"Overlord";"Larva";12;0
"Building";"Extractor";NA;17;0
"Unit";"Overlord";"Larva";20;0
"Building";"SpawningPool";NA;19;0
"Building";"Hatchery";NA;17;0
"Unit";"Zergling";"Larva";22;1
"Unit";"Zergling";"Larva";22;1
"Unit";"Zergling";"Larva";22;1
"Unit";"Zergling";"Larva";22;1
"Unit";"Queen";"Hatchery";22;2
"Unit";"Queen";"Hatchery";22;2
"Unit";"Overlord";"Larva";37;0
"Unit";"Queen";"Hatchery";35;2
"Unit";"Queen";"Hatchery";37;2
"Unit";"Overlord";"Larva";39;0
"Unit";"Overlord";"Larva";41;0
"Building";"CreepTumorQueen";NA;50;0
"Building";"CreepTumorQueen";NA;50;0
"Unit";"Zergling";"Larva";50;1
"Unit";"Zergling";"Larva";50;1
"Unit";"Zergling";"Larva";50;1
"Unit";"Zergling";"Larva";50;1
"Unit";"Zergling";"Larva";50;1
"Unit";"Zergling";"Larva";50;1
"Unit";"Zergling";"Larva";50;1
"Unit";"Zergling";"Larva";50;1
"Unit";"Zergling";"Larva";50;1
"Unit";"Zergling";"Larva";50;1
"Building";"EvolutionChamber";NA;50;0
"Building";"EvolutionChamber";NA;50;0
"Building";"CreepTumor";NA;50;0
"Building";"CreepTumor";NA;60;0
"Building";"CreepTumorQueen";NA;64;0
"Building";"Hatchery";NA;39;0
"Unit";"Overlord";"Larva";65;0
"Building";"Extractor";NA;65;0
"Unit";"Overlord";"Larva";69;0
"Building";"Extractor";NA;69;0
"Building";"SporeCrawler";NA;69;0
"Unit";"Zergling";"Larva";69;1
"Unit";"Zergling";"Larva";69;1
"Unit";"Zergling";"Larva";69;1
"Unit";"Zergling";"Larva";69;1
"Unit";"Zergling";"Larva";70;1
"Unit";"Zergling";"Larva";70;1
"Building";"CreepTumorQueen";NA;83;0
"Building";"CreepTumor";NA;83;0
"Building";"CreepTumor";NA;83;0
"Building";"CreepTumor";NA;83;0
"Unit";"Zergling";"Larva";83;1
"Unit";"Zergling";"Larva";83;1
"Unit";"Queen";"Hatchery";77;2
"Unit";"Queen";"Hatchery";77;2
"Unit";"Zergling";"Larva";83;1
"Unit";"Zergling";"Larva";83;1
"Unit";"Zergling";"Larva";83;1
"Unit";"Zergling";"Larva";83;1
"Unit";"Zergling";"Larva";83;1
"Unit";"Zergling";"Larva";83;1
"Unit";"Zergling";"Larva";83;1
"Unit";"Zergling";"Larva";83;1
"Unit";"Zergling";"Larva";83;1
"Unit";"Zergling";"Larva";83;1
"Unit";"Zergling";"Larva";83;1
"Unit";"Zergling";"Larva";83;1
"Building";"BanelingNest";NA;77;0
"Building";"SporeCrawler";NA;83;0
"Building";"CreepTumor";NA;101;0
"Building";"CreepTumor";NA;101;0
"Building";"CreepTumor";NA;101;0
"Upgrade";"ZergGroundArmorsLevel1";"EvolutionChamber";69;0
"Upgrade";"ZergMeleeWeaponsLevel1";"EvolutionChamber";69;0
"Unit";"Queen";"Hatchery";101;2
"Building";"CreepTumor";NA;101;0
"Unit";"Overlord";"Larva";101;0
"Unit";"Overlord";"Larva";101;0
"Unit";"Overlord";"Larva";101;0
"Unit";"Overlord";"Larva";103;0
"Unit";"Overlord";"Larva";103;0
"Building";"CreepTumorQueen";NA;105;0
"Building";"CreepTumorQueen";NA;105;0
"Building";"HydraliskDen";NA;103;0
"Building";"CreepTumorQueen";NA;105;0
"Unit";"Overlord";"Larva";113;0
"Unit";"Overlord";"Larva";118;0
"Building";"CreepTumor";NA;119;0
"Building";"CreepTumorQueen";NA;123;0
"Building";"Extractor";NA;118;0
"Building";"Extractor";NA;118;0
"Building";"CreepTumor";NA;125;0
"Unit";"Baneling";"Zergling";125;0
"Unit";"Baneling";"Zergling";125;0
"Unit";"Baneling";"Zergling";125;0
"Unit";"Baneling";"Zergling";125;0
"Unit";"Baneling";"Zergling";125;0
"Unit";"Baneling";"Zergling";125;0
"Unit";"Baneling";"Zergling";125;0
"Building";"CreepTumorQueen";NA;125;0
"Building";"CreepTumorQueen";NA;125;0
"Unit";"Baneling";"Zergling";125;0
"Unit";"Baneling";"Zergling";125;0
"Unit";"Baneling";"Zergling";125;0
"Unit";"Baneling";"Zergling";125;0
"Unit";"Baneling";"Zergling";125;0
"Unit";"Baneling";"Zergling";125;0
"Unit";"Zergling";"Larva";125;1
"Unit";"Zergling";"Larva";125;1
"Unit";"Zergling";"Larva";125;1
"Unit";"Zergling";"Larva";125;1
"Unit";"Zergling";"Larva";125;1
"Unit";"Zergling";"Larva";125;1
"Unit";"Zergling";"Larva";125;1
"Unit";"Zergling";"Larva";125;1
"Unit";"Zergling";"Larva";125;1
"Unit";"Zergling";"Larva";125;1
"Unit";"Zergling";"Larva";125;1
"Unit";"Zergling";"Larva";125;1
"Unit";"Zergling";"Larva";125;1
"Unit";"Zergling";"Larva";125;1
"Unit";"Zergling";"Larva";125;1
"Unit";"Zergling";"Larva";125;1
"Unit";"Zergling";"Larva";125;1
"Unit";"Zergling";"Larva";125;1
"Unit";"Zergling";"Larva";125;1
"Unit";"Zergling";"Larva";125;1
"Unit";"Zergling";"Larva";125;1
"Unit";"Zergling";"Larva";125;1
"Unit";"Zergling";"Larva";125;1
"Unit";"Zergling";"Larva";125;1
"Unit";"Zergling";"Larva";125;1
"Unit";"Zergling";"Larva";125;1
"Unit";"Zergling";"Larva";125;1
"Unit";"Zergling";"Larva";125;1
"Unit";"Zergling";"Larva";139;1
"Unit";"Zergling";"Larva";139;1
"Unit";"Zergling";"Larva";139;1
"Unit";"Zergling";"Larva";139;1
"Unit";"Zergling";"Larva";139;1
"Unit";"Zergling";"Larva";139;1
"Unit";"Zergling";"Larva";139;1
"Unit";"Zergling";"Larva";139;1
"Upgrade";"EvolveGroovedSpines";"HydraliskDen";125;0
"Building";"CreepTumorQueen";NA;153;0
"Unit";"Zergling";"Larva";139;1
"Unit";"Zergling";"Larva";139;1
"Unit";"Zergling";"Larva";139;1
"Unit";"Zergling";"Larva";139;1
"Building";"CreepTumorQueen";NA;165;0
"Unit";"Zergling";"Larva";161;1
"Unit";"Zergling";"Larva";161;1
"Unit";"Zergling";"Larva";161;1
"Unit";"Zergling";"Larva";161;1
"Unit";"Zergling";"Larva";161;1
"Unit";"Zergling";"Larva";161;1
"Unit";"Zergling";"Larva";161;1
"Unit";"Zergling";"Larva";161;1
"Unit";"Zergling";"Larva";161;1
"Unit";"Zergling";"Larva";161;1
"Unit";"Zergling";"Larva";161;1
"Unit";"Zergling";"Larva";161;1
"Building";"Hatchery";NA;125;0
"Building";"CreepTumor";NA;177;0
"Unit";"Hydralisk";"Larva";165;2
"Unit";"Hydralisk";"Larva";165;2
"Unit";"Hydralisk";"Larva";165;2
"Unit";"Baneling";"Zergling";177;0
"Unit";"Baneling";"Zergling";177;0
"Unit";"Baneling";"Zergling";177;0
"Unit";"Baneling";"Zergling";177;0
"Unit";"Baneling";"Zergling";177;0
"Unit";"Baneling";"Zergling";177;0
"Unit";"Baneling";"Zergling";177;0
"Building";"CreepTumor";NA;177;0
"Upgrade";"ZergGroundArmorsLevel2";"EvolutionChamber";118;0
"Upgrade";"ZergMeleeWeaponsLevel2";"EvolutionChamber";118;0
"Building";"CreepTumor";NA;177;0
"Building";"Extractor";NA;177;0
"Building";"CreepTumor";NA;177;0
"Unit";"Hydralisk";"Larva";177;2
"Unit";"Hydralisk";"Larva";177;2
"Unit";"Hydralisk";"Larva";177;2
"Unit";"Hydralisk";"Larva";177;2
"Unit";"Hydralisk";"Larva";177;2
"Unit";"Hydralisk";"Larva";177;2
"Unit";"Zergling";"Larva";183;1
"Unit";"Zergling";"Larva";183;1
"Unit";"Zergling";"Larva";183;1
"Unit";"Zergling";"Larva";183;1
"Unit";"Zergling";"Larva";183;1
"Unit";"Zergling";"Larva";183;1
"Unit";"Zergling";"Larva";183;1
"Unit";"Zergling";"Larva";183;1
"Unit";"Zergling";"Larva";183;1
"Unit";"Zergling";"Larva";183;1
"Unit";"Zergling";"Larva";183;1
"Unit";"Zergling";"Larva";183;1
"Unit";"Zergling";"Larva";183;1
"Unit";"Zergling";"Larva";183;1
"Unit";"Zergling";"Larva";183;1
"Unit";"Zergling";"Larva";183;1
"Unit";"Zergling";"Larva";183;1
"Unit";"Zergling";"Larva";183;1
"Unit";"Zergling";"Larva";183;1
"Unit";"Zergling";"Larva";183;1
"Upgrade";"EvolveMuscularAugments";"HydraliskDen";177;0
"Building";"SporeCrawler";NA;183;0
"Building";"InfestationPit";NA;183;0
"Unit";"Zergling";"Larva";195;1
"Unit";"Zergling";"Larva";195;1
"Unit";"Zergling";"Larva";195;1
"Unit";"Zergling";"Larva";195;1
"Unit";"Zergling";"Larva";195;1
"Unit";"Zergling";"Larva";195;1
"Unit";"Zergling";"Larva";195;1
"Unit";"Zergling";"Larva";195;1
"Unit";"Zergling";"Larva";195;1
"Unit";"Zergling";"Larva";195;1
"Unit";"Zergling";"Larva";195;1
"Unit";"Zergling";"Larva";195;1
"Unit";"Zergling";"Larva";195;1
"Unit";"Zergling";"Larva";195;1
"Unit";"Zergling";"Larva";195;1
"Unit";"Zergling";"Larva";195;1
"Unit";"Baneling";"Zergling";215;0
"Unit";"Baneling";"Zergling";215;0
"Unit";"Baneling";"Zergling";215;0
"Unit";"Baneling";"Zergling";215;0
"Unit";"Baneling";"Zergling";215;0
"Unit";"Zergling";"Larva";215;1
"Unit";"Zergling";"Larva";215;1
"Unit";"Zergling";"Larva";215;1
"Unit";"Zergling";"Larva";215;1
"Unit";"Zergling";"Larva";215;1
"Unit";"Zergling";"Larva";215;1
"Unit";"Zergling";"Larva";215;1
"Unit";"Zergling";"Larva";215;1
"Unit";"Zergling";"Larva";215;1
"Unit";"Zergling";"Larva";215;1
"Unit";"Zergling";"Larva";215;1
"Unit";"Zergling";"Larva";215;1
"Unit";"Zergling";"Larva";215;1
"Unit";"Zergling";"Larva";215;1
"Unit";"Zergling";"Larva";215;1
"Unit";"Zergling";"Larva";215;1
"Unit";"Zergling";"Larva";215;1
"Unit";"Zergling";"Larva";215;1
"Unit";"Zergling";"Larva";215;1
"Unit";"Zergling";"Larva";215;1
"Unit";"Zergling";"Larva";215;1
"Unit";"Zergling";"Larva";215;1
"Unit";"Zergling";"Larva";215;1
"Unit";"Zergling";"Larva";215;1
"Unit";"Zergling";"Larva";231;1
"Unit";"Zergling";"Larva";231;1
"Unit";"Zergling";"Larva";231;1
"Unit";"Zergling";"Larva";231;1
"Unit";"Baneling";"Zergling";259;0
"Unit";"Baneling";"Zergling";259;0
"Unit";"Baneling";"Zergling";259;0
"Unit";"Baneling";"Zergling";259;0
"Unit";"Baneling";"Zergling";259;0
"Unit";"Zergling";"Larva";259;1
"Unit";"Zergling";"Larva";259;1
"Unit";"Zergling";"Larva";259;1
"Unit";"Zergling";"Larva";259;1
"Unit";"Zergling";"Larva";259;1
"Unit";"Zergling";"Larva";259;1
"Unit";"Zergling";"Larva";259;1
"Unit";"Zergling";"Larva";259;1
"Unit";"Zergling";"Larva";259;1
"Unit";"Zergling";"Larva";259;1
"Unit";"Zergling";"Larva";259;1
"Unit";"Zergling";"Larva";259;1
"Unit";"Zergling";"Larva";259;1
"Unit";"Zergling";"Larva";259;1
"Unit";"Zergling";"Larva";259;1
"Unit";"Zergling";"Larva";259;1
"Unit";"Zergling";"Larva";259;1
"Unit";"Zergling";"Larva";259;1
"Unit";"Zergling";"Larva";259;1
"Unit";"Zergling";"Larva";259;1
"Unit";"Zergling";"Larva";259;1
"Unit";"Zergling";"Larva";259;1
"Unit";"Zergling";"Larva";259;1
"Unit";"Zergling";"Larva";259;1
"Unit";"Zergling";"Larva";259;1
"Unit";"Zergling";"Larva";259;1
"Unit";"Zergling";"Larva";259;1
"Unit";"Zergling";"Larva";259;1
"Building";"CreepTumor";NA;259;0
"Unit";"Overlord";"Larva";287;0
"Building";"CreepTumor";NA;287;0
"Unit";"Overlord";"Larva";287;0
"Unit";"Overlord";"Larva";287;0
"Unit";"Overlord";"Larva";287;0
"Unit";"Hydralisk";"Larva";287;2
"Unit";"Hydralisk";"Larva";287;2
"Unit";"Hydralisk";"Larva";287;2
"Unit";"Hydralisk";"Larva";287;2
"Unit";"Hydralisk";"Larva";287;2
"Unit";"Hydralisk";"Larva";287;2
"Unit";"Hydralisk";"Larva";287;2
"Building";"CreepTumor";NA;302;0
"Building";"CreepTumor";NA;302;0
"Building";"CreepTumor";NA;302;0
"Building";"CreepTumorQueen";NA;302;0
"Unit";"Zergling";"Larva";302;1
"Unit";"Zergling";"Larva";302;1
"Unit";"Zergling";"Larva";302;1
"Unit";"Zergling";"Larva";302;1
"Unit";"Zergling";"Larva";302;1
"Unit";"Zergling";"Larva";302;1
"Unit";"Zergling";"Larva";302;1
"Unit";"Zergling";"Larva";302;1
"Unit";"Zergling";"Larva";302;1
"Unit";"Zergling";"Larva";302;1
"Unit";"Zergling";"Larva";302;1
"Unit";"Zergling";"Larva";302;1
"Unit";"Zergling";"Larva";302;1
"Unit";"Zergling";"Larva";302;1
"Unit";"Zergling";"Larva";302;1
"Unit";"Zergling";"Larva";302;1
"Unit";"Zergling";"Larva";302;1
"Unit";"Zergling";"Larva";302;1
"Unit";"Zergling";"Larva";302;1
"Unit";"Zergling";"Larva";302;1
"Unit";"Zergling";"Larva";302;1
"Unit";"Zergling";"Larva";302;1
"Unit";"Zergling";"Larva";302;1
"Unit";"Zergling";"Larva";302;1
"Unit";"Baneling";"Zergling";302;0
"Unit";"Baneling";"Zergling";302;0
"Unit";"Baneling";"Zergling";302;0
"Unit";"Baneling";"Zergling";302;0
"Building";"CreepTumor";NA;311;0
"Building";"CreepTumor";NA;311;0
"Building";"CreepTumor";NA;315;0
"Unit";"Zergling";"Larva";335;1
"Unit";"Zergling";"Larva";335;1
"Unit";"Zergling";"Larva";335;1
"Unit";"Zergling";"Larva";335;1
"Unit";"Zergling";"Larva";335;1
"Unit";"Zergling";"Larva";335;1
"Unit";"Zergling";"Larva";335;1
"Unit";"Zergling";"Larva";335;1
"Unit";"Zergling";"Larva";335;1
"Unit";"Zergling";"Larva";335;1
"Unit";"Zergling";"Larva";335;1
"Unit";"Zergling";"Larva";335;1
"Unit";"Zergling";"Larva";335;1
"Unit";"Zergling";"Larva";335;1
"Unit";"Zergling";"Larva";335;1
"Unit";"Zergling";"Larva";335;1
"Unit";"Zergling";"Larva";335;1
"Unit";"Zergling";"Larva";335;1
"Unit";"Zergling";"Larva";335;1
"Unit";"Zergling";"Larva";335;1
"Unit";"Zergling";"Larva";335;1
"Unit";"Zergling";"Larva";335;1
"Unit";"Zergling";"Larva";335;1
"Unit";"Zergling";"Larva";335;1
"Building";"UltraliskCavern";NA;302;0
"Unit";"Baneling";"Zergling";359;0
"Unit";"Baneling";"Zergling";359;0
"Unit";"Baneling";"Zergling";359;0
"Unit";"Baneling";"Zergling";359;0
"Unit";"Baneling";"Zergling";359;0
"Unit";"Baneling";"Zergling";359;0
"Unit";"Baneling";"Zergling";359;0
"Unit";"Zergling";"Larva";359;1
"Unit";"Zergling";"Larva";359;1
"Unit";"Zergling";"Larva";359;1
"Unit";"Zergling";"Larva";359;1
"Unit";"Zergling";"Larva";359;1
"Unit";"Zergling";"Larva";359;1
"Unit";"Zergling";"Larva";359;1
"Unit";"Zergling";"Larva";359;1
"Unit";"Zergling";"Larva";359;1
"Unit";"Zergling";"Larva";359;1
"Unit";"Zergling";"Larva";359;1
"Unit";"Zergling";"Larva";359;1
"Unit";"Zergling";"Larva";359;1
"Unit";"Zergling";"Larva";359;1
"Unit";"Zergling";"Larva";359;1
"Unit";"Zergling";"Larva";359;1
"Unit";"Zergling";"Larva";359;1
"Unit";"Zergling";"Larva";359;1
"Unit";"Zergling";"Larva";359;1
"Unit";"Zergling";"Larva";359;1
"Unit";"Zergling";"Larva";359;1
"Unit";"Zergling";"Larva";359;1
"Unit";"Zergling";"Larva";359;1
"Unit";"Zergling";"Larva";359;1
"Unit";"Baneling";"Zergling";359;0
"Unit";"Baneling";"Zergling";359;0
"Unit";"Baneling";"Zergling";359;0
"Unit";"Baneling";"Zergling";359;0
"Unit";"Hydralisk";"Larva";359;2
"Unit";"Hydralisk";"Larva";359;2
"Unit";"Hydralisk";"Larva";359;2
"Unit";"Baneling";"Zergling";383;0
"Unit";"Baneling";"Zergling";383;0
"Unit";"Baneling";"Zergling";383;0
"Unit";"Baneling";"Zergling";383;0
"Unit";"Baneling";"Zergling";383;0
"Unit";"Baneling";"Zergling";383;0
"Unit";"Baneling";"Zergling";383;0
"Unit";"Baneling";"Zergling";383;0
"Unit";"Zergling";"Larva";383;1
"Unit";"Zergling";"Larva";383;1
"Unit";"Zergling";"Larva";383;1
"Unit";"Zergling";"Larva";383;1
"Unit";"Zergling";"Larva";383;1
"Unit";"Zergling";"Larva";383;1
"Unit";"Zergling";"Larva";383;1
"Unit";"Zergling";"Larva";383;1
"Unit";"Ultralisk";"Larva";359;6
"Unit";"Hydralisk";"Larva";383;2
"Unit";"Zergling";"Larva";397;1
"Unit";"Zergling";"Larva";397;1
"Unit";"Zergling";"Larva";397;1
"Unit";"Zergling";"Larva";397;1
"Unit";"Zergling";"Larva";397;1
"Unit";"Zergling";"Larva";397;1
"Unit";"Zergling";"Larva";397;1
"Unit";"Zergling";"Larva";397;1
"Unit";"Zergling";"Larva";397;1
"Unit";"Zergling";"Larva";397;1
"Unit";"Zergling";"Larva";397;1
"Unit";"Zergling";"Larva";397;1
"Unit";"Zergling";"Larva";397;1
"Unit";"Zergling";"Larva";397;1
"Unit";"Zergling";"Larva";397;1
"Unit";"Zergling";"Larva";397;1
"Unit";"Zergling";"Larva";397;1
"Unit";"Zergling";"Larva";397;1
"Unit";"Zergling";"Larva";397;1
"Unit";"Zergling";"Larva";397;1
"Unit";"Zergling";"Larva";397;1
"Unit";"Zergling";"Larva";397;1
"Unit";"Zergling";"Larva";397;1
"Unit";"Zergling";"Larva";397;1
"Unit";"Zergling";"Larva";397;1
"Unit";"Zergling";"Larva";397;1
"Unit";"Zergling";"Larva";397;1
"Unit";"Zergling";"Larva";397;1
"Unit";"Zergling";"Larva";397;1
"Unit";"Zergling";"Larva";397;1
"Unit";"Zergling";"Larva";403;1
"Unit";"Zergling";"Larva";403;1
"Unit";"Ultralisk";"Larva";383;6
"Unit";"Hydralisk";"Larva";405;2
"Unit";"Hydralisk";"Larva";405;2
"Unit";"Hydralisk";"Larva";405;2
"Unit";"Hydralisk";"Larva";405;2
"Unit";"Zergling";"Larva";437;1
"Unit";"Zergling";"Larva";437;1
"Unit";"Zergling";"Larva";437;1
"Unit";"Zergling";"Larva";437;1
"Unit";"Zergling";"Larva";437;1
"Unit";"Zergling";"Larva";437;1
"Unit";"Zergling";"Larva";437;1
"Unit";"Zergling";"Larva";437;1
"Unit";"Zergling";"Larva";437;1
"Unit";"Zergling";"Larva";437;1
"Unit";"Zergling";"Larva";437;1
"Unit";"Zergling";"Larva";437;1
"Unit";"Zergling";"Larva";437;1
"Unit";"Zergling";"Larva";437;1
"Unit";"Zergling";"Larva";437;1
"Unit";"Zergling";"Larva";437;1
"Unit";"Zergling";"Larva";437;1
"Unit";"Zergling";"Larva";437;1
"Unit";"Zergling";"Larva";437;1
"Unit";"Zergling";"Larva";437;1
"Building";"CreepTumor";NA;443;0
"Building";"CreepTumorQueen";NA;451;0
"Building";"CreepTumorQueen";NA;451;0
"Upgrade";"ZergGroundArmorsLevel3";"EvolutionChamber";359;0
"Building";"CreepTumorQueen";NA;471;0
"Upgrade";"ZergMeleeWeaponsLevel3";"EvolutionChamber";359;0
"Unit";"Hydralisk";"Larva";471;2
"Unit";"Hydralisk";"Larva";471;2
"Unit";"Hydralisk";"Larva";471;2
"Unit";"Hydralisk";"Larva";471;2
"Unit";"Ultralisk";"Larva";451;6
"Unit";"Ultralisk";"Larva";451;6
"Unit";"Baneling";"Zergling";471;0
"Unit";"Baneling";"Zergling";471;0
"Unit";"Baneling";"Zergling";471;0
"Unit";"Baneling";"Zergling";471;0
"Unit";"Zergling";"Larva";471;1
"Unit";"Zergling";"Larva";471;1
"Unit";"Zergling";"Larva";471;1
"Unit";"Zergling";"Larva";471;1
"Unit";"Zergling";"Larva";471;1
"Unit";"Zergling";"Larva";471;1
"Unit";"Zergling";"Larva";471;1
"Unit";"Zergling";"Larva";471;1
"Unit";"Zergling";"Larva";471;1
"Unit";"Zergling";"Larva";471;1
"Unit";"Zergling";"Larva";471;1
"Unit";"Zergling";"Larva";471;1
"Unit";"Zergling";"Larva";471;1
"Unit";"Zergling";"Larva";471;1
"Unit";"Baneling";"Zergling";471;0
"Unit";"Zergling";"Larva";471;1
"Unit";"Zergling";"Larva";471;1
"Unit";"Zergling";"Larva";471;1
"Unit";"Zergling";"Larva";471;1
"Unit";"Zergling";"Larva";471;1
"Unit";"Zergling";"Larva";471;1
"Unit";"Baneling";"Zergling";471;0
"Building";"CreepTumorQueen";NA;479;0
"Unit";"Zergling";"Larva";511;1
"Unit";"Zergling";"Larva";511;1
"Unit";"Zergling";"Larva";511;1
"Unit";"Zergling";"Larva";511;1
"Unit";"Zergling";"Larva";511;1
"Unit";"Zergling";"Larva";511;1
"Unit";"Zergling";"Larva";511;1
"Unit";"Zergling";"Larva";511;1
"Unit";"Zergling";"Larva";511;1
"Unit";"Zergling";"Larva";511;1
"Unit";"Zergling";"Larva";511;1
"Unit";"Zergling";"Larva";511;1
"Unit";"Zergling";"Larva";511;1
"Unit";"Zergling";"Larva";511;1
"Unit";"Zergling";"Larva";511;1
"Unit";"Zergling";"Larva";511;1
"Unit";"Zergling";"Larva";511;1
"Unit";"Zergling";"Larva";511;1
"Unit";"Zergling";"Larva";511;1
"Unit";"Zergling";"Larva";511;1
"Unit";"Zergling";"Larva";511;1
"Unit";"Zergling";"Larva";511;1
"Unit";"Zergling";"Larva";511;1
"Unit";"Zergling";"Larva";511;1
"Upgrade";"ChitinousPlating";"UltraliskCavern";471;0
"Unit";"Ultralisk";"Larva";479;6
"Building";"CreepTumor";NA;511;0
"Building";"CreepTumor";NA;535;0
"Building";"CreepTumor";NA;535;0
"Unit";"Zergling";"Larva";541;1
"Unit";"Zergling";"Larva";541;1
"Unit";"Zergling";"Larva";541;1
"Unit";"Zergling";"Larva";541;1
"Unit";"Zergling";"Larva";541;1
"Unit";"Zergling";"Larva";541;1
"Unit";"Zergling";"Larva";541;1
"Unit";"Zergling";"Larva";541;1
"Unit";"Zergling";"Larva";541;1
"Unit";"Zergling";"Larva";541;1
"Unit";"Zergling";"Larva";541;1
"Unit";"Zergling";"Larva";541;1
"Unit";"Zergling";"Larva";541;1
"Unit";"Zergling";"Larva";541;1
"Unit";"Zergling";"Larva";541;1
"Unit";"Zergling";"Larva";541;1
"Unit";"Zergling";"Larva";541;1
"Unit";"Zergling";"Larva";541;1
"Unit";"Zergling";"Larva";541;1
"Unit";"Zergling";"Larva";541;1
"Unit";"Zergling";"Larva";541;1
"Unit";"Zergling";"Larva";541;1
"Unit";"Zergling";"Larva";541;1
"Unit";"Zergling";"Larva";541;1
"Building";"Hatchery";NA;479;0
"Unit";"Ultralisk";"Larva";535;6
"Unit";"Ultralisk";"Larva";535;6
"Unit";"Hydralisk";"Larva";541;2
"Building";"CreepTumor";NA;565;0
"Unit";"Hydralisk";"Larva";541;2
"Unit";"Hydralisk";"Larva";541;2
"Unit";"Hydralisk";"Larva";541;2
"Unit";"Hydralisk";"Larva";541;2
"Building";"CreepTumor";NA;565;0
"Unit";"Baneling";"Zergling";565;0
"Unit";"Baneling";"Zergling";565;0
"Unit";"Baneling";"Zergling";565;0
"Unit";"Baneling";"Zergling";565;0
"Unit";"Baneling";"Zergling";565;0
"Unit";"Baneling";"Zergling";565;0
"Unit";"Baneling";"Zergling";565;0
"Unit";"Baneling";"Zergling";565;0
"Unit";"Baneling";"Zergling";565;0
"Unit";"Baneling";"Zergling";565;0
"Unit";"Baneling";"Zergling";565;0
"Unit";"Baneling";"Zergling";565;0
"Unit";"Zergling";"Larva";587;1
"Unit";"Zergling";"Larva";587;1
"Unit";"Zergling";"Larva";587;1
"Unit";"Zergling";"Larva";587;1
"Unit";"Zergling";"Larva";587;1
"Unit";"Zergling";"Larva";587;1
"Unit";"Zergling";"Larva";587;1
"Unit";"Zergling";"Larva";587;1
"Unit";"Zergling";"Larva";587;1
"Unit";"Zergling";"Larva";587;1
"Unit";"Zergling";"Larva";587;1
"Unit";"Zergling";"Larva";587;1
"Unit";"Zergling";"Larva";587;1
"Unit";"Zergling";"Larva";587;1
"Unit";"Zergling";"Larva";587;1
"Unit";"Zergling";"Larva";587;1
"Unit";"Zergling";"Larva";587;1
"Unit";"Zergling";"Larva";587;1
"Unit";"Zergling";"Larva";587;1
"Unit";"Zergling";"Larva";587;1
"Unit";"Zergling";"Larva";587;1
"Unit";"Zergling";"Larva";587;1
"Unit";"Zergling";"Larva";587;1
"Unit";"Zergling";"Larva";587;1
"Unit";"Zergling";"Larva";587;1
"Unit";"Zergling";"Larva";587;1
"Unit";"Zergling";"Larva";587;1
"Unit";"Zergling";"Larva";587;1
"Unit";"Zergling";"Larva";587;1
"Unit";"Zergling";"Larva";587;1
"Unit";"Zergling";"Larva";587;1
"Unit";"Zergling";"Larva";587;1
"Unit";"Baneling";"Zergling";619;0
"Unit";"Baneling";"Zergling";619;0
"Unit";"Baneling";"Zergling";619;0
"Unit";"Baneling";"Zergling";619;0
"Unit";"Baneling";"Zergling";619;0
"Unit";"Baneling";"Zergling";619;0
"Unit";"Baneling";"Zergling";619;0
"Unit";"Baneling";"Zergling";619;0
"Unit";"Baneling";"Zergling";619;0
"Building";"Extractor";NA;587;0
"Building";"Extractor";NA;587;0
"Unit";"Overlord";"Larva";619;0
"Unit";"Overlord";"Larva";619;0
"Unit";"Overlord";"Larva";619;0
"Unit";"Overlord";"Larva";619;0
"Unit";"Zergling";"Larva";619;1
"Unit";"Zergling";"Larva";619;1
"Unit";"Zergling";"Larva";619;1
"Unit";"Zergling";"Larva";619;1
"Unit";"Zergling";"Larva";619;1
"Unit";"Zergling";"Larva";619;1
"Upgrade";"ZergMissileWeaponsLevel1";"EvolutionChamber";577;0
"Unit";"Ultralisk";"Larva";619;6
"Unit";"Ultralisk";"Larva";619;6
"Unit";"Ultralisk";"Larva";619;6
"Unit";"Zergling";"Larva";643;1
"Unit";"Zergling";"Larva";643;1
"Unit";"Zergling";"Larva";643;1
"Unit";"Zergling";"Larva";643;1
"Unit";"Zergling";"Larva";643;1
"Unit";"Zergling";"Larva";643;1
"Unit";"Zergling";"Larva";643;1
"Unit";"Zergling";"Larva";643;1
"Unit";"Zergling";"Larva";643;1
"Unit";"Zergling";"Larva";643;1
"Unit";"Zergling";"Larva";643;1
"Unit";"Zergling";"Larva";643;1
"Unit";"Zergling";"Larva";643;1
"Unit";"Zergling";"Larva";643;1
"Unit";"Zergling";"Larva";643;1
"Unit";"Zergling";"Larva";643;1
"Unit";"Zergling";"Larva";643;1
"Unit";"Zergling";"Larva";643;1
"Unit";"Zergling";"Larva";643;1
"Unit";"Zergling";"Larva";643;1
"Unit";"Zergling";"Larva";643;1
"Unit";"Zergling";"Larva";643;1
"Unit";"Zergling";"Larva";643;1
"Unit";"Zergling";"Larva";643;1
"Unit";"Zergling";"Larva";643;1
"Unit";"Zergling";"Larva";643;1
"Unit";"Zergling";"Larva";643;1
"Unit";"Zergling";"Larva";643;1
"Unit";"Zergling";"Larva";643;1
"Unit";"Zergling";"Larva";643;1
"Unit";"Zergling";"Larva";643;1
"Unit";"Zergling";"Larva";643;1
"Unit";"Zergling";"Larva";643;1
"Unit";"Zergling";"Larva";643;1
"Unit";"Zergling";"Larva";643;1
"Unit";"Zergling";"Larva";643;1
"Unit";"Zergling";"Larva";643;1
"Unit";"Zergling";"Larva";643;1
"Building";"CreepTumorQueen";NA;643;0
"Building";"CreepTumor";NA;643;0
"Building";"CreepTumor";NA;643;0
"Building";"CreepTumorQueen";NA;643;0
