"type";"unit_name";"on_building";"total_supply";"supply"
"Unit";"Overlord";"Larva";13;0
"Building";"Extractor";NA;17;0
"Unit";"Overlord";"Larva";21;0
"Building";"Hatchery";NA;17;0
"Building";"SpawningPool";NA;19;0
"Unit";"Zergling";"Larva";23;1
"Unit";"Zergling";"Larva";23;1
"Unit";"Zergling";"Larva";24;1
"Unit";"Zergling";"Larva";24;1
"Unit";"Queen";"Hatchery";23;2
"Unit";"Queen";"Hatchery";23;2
"Building";"CreepTumorQueen";NA;37;0
"Unit";"Overlord";"Larva";37;0
"Unit";"Overlord";"Larva";37;0
"Unit";"Overlord";"Larva";37;0
"Unit";"Queen";"Hatchery";35;2
"Unit";"Queen";"Hatchery";35;2
"Building";"CreepTumor";NA;37;0
"Building";"CreepTumorQueen";NA;37;0
"Building";"CreepTumorQueen";NA;45;0
"Building";"CreepTumor";NA;50;0
"Building";"CreepTumorQueen";NA;51;0
"Building";"CreepTumor";NA;51;0
"Building";"CreepTumorQueen";NA;51;0
"Building";"CreepTumor";NA;51;0
"Building";"Extractor";NA;51;0
"Unit";"Zergling";"Larva";51;1
"Unit";"Zergling";"Larva";51;1
"Unit";"Zergling";"Larva";51;1
"Unit";"Zergling";"Larva";51;1
"Unit";"Zergling";"Larva";51;1
"Unit";"Zergling";"Larva";51;1
"Building";"RoachWarren";NA;48;0
"Unit";"Queen";"Hatchery";51;2
"Building";"CreepTumor";NA;65;0
"Building";"CreepTumor";NA;65;0
"Building";"CreepTumor";NA;65;0
"Building";"CreepTumorQueen";NA;67;0
"Building";"Hatchery";NA;50;0
"Unit";"Overlord";"Larva";67;0
"Unit";"Overlord";"Larva";73;0
"Unit";"Overlord";"Larva";73;0
"Unit";"Overlord";"Larva";73;0
"Building";"CreepTumorQueen";NA;73;0
"Building";"CreepTumor";NA;73;0
"Building";"CreepTumor";NA;73;0
"Building";"CreepTumor";NA;73;0
"Building";"CreepTumorQueen";NA;73;0
"Building";"CreepTumor";NA;73;0
"Building";"EvolutionChamber";NA;73;0
"Building";"CreepTumor";NA;73;0
"Building";"CreepTumor";NA;73;0
"Building";"CreepTumorQueen";NA;73;0
"Building";"EvolutionChamber";NA;73;0
"Unit";"Roach";"Larva";73;2
"Unit";"Roach";"Larva";73;2
"Unit";"Roach";"Larva";73;2
"Unit";"Roach";"Larva";73;2
"Unit";"Roach";"Larva";73;2
"Unit";"Roach";"Larva";73;2
"Unit";"Roach";"Larva";73;2
"Unit";"Roach";"Larva";73;2
"Unit";"Overlord";"Larva";73;0
"Building";"CreepTumor";NA;92;0
"Building";"CreepTumor";NA;92;0
"Building";"CreepTumor";NA;92;0
"Building";"CreepTumor";NA;92;0
"Building";"CreepTumor";NA;92;0
"Building";"CreepTumor";NA;92;0
"Building";"Hatchery";NA;73;0
"Building";"Extractor";NA;92;0
"Building";"Extractor";NA;92;0
"Unit";"Overlord";"Larva";93;0
"Unit";"Overlord";"Larva";96;0
"Unit";"Overlord";"Larva";96;0
"Unit";"Overlord";"Larva";96;0
"Unit";"Overlord";"Larva";96;0
"Building";"CreepTumor";NA;105;0
"Building";"CreepTumor";NA;105;0
"Unit";"Overlord";"Larva";105;0
"Building";"HydraliskDen";NA;105;0
"Unit";"Roach";"Larva";105;2
"Unit";"Roach";"Larva";105;2
"Unit";"Roach";"Larva";105;2
"Building";"Extractor";NA;113;0
"Building";"Extractor";NA;113;0
"Building";"CreepTumor";NA;121;0
"Building";"CreepTumor";NA;124;0
"Building";"CreepTumor";NA;129;0
"Upgrade";"ZergMissileWeaponsLevel1";"EvolutionChamber";93;0
"Unit";"Overlord";"Larva";121;0
"Building";"CreepTumor";NA;137;0
"Upgrade";"ZergGroundArmorsLevel1";"EvolutionChamber";95;0
"Upgrade";"GlialReconstitution";"RoachWarren";113;0
"Building";"Extractor";NA;137;0
"Building";"Extractor";NA;138;0
"Building";"InfestationPit";NA;137;0
"Building";"CreepTumor";NA;150;0
"Upgrade";"EvolveMuscularAugments";"HydraliskDen";137;0
"Building";"CreepTumorQueen";NA;156;0
"Building";"CreepTumorQueen";NA;156;0
"Building";"CreepTumorQueen";NA;156;0
"Unit";"Hydralisk";"Larva";156;2
"Unit";"Hydralisk";"Larva";156;2
"Unit";"Hydralisk";"Larva";156;2
"Unit";"Hydralisk";"Larva";156;2
"Unit";"Hydralisk";"Larva";156;2
"Unit";"Hydralisk";"Larva";156;2
"Unit";"Hydralisk";"Larva";156;2
"Building";"CreepTumorQueen";NA;156;0
"Building";"Extractor";NA;156;0
"Unit";"Hydralisk";"Larva";156;2
"Unit";"Hydralisk";"Larva";156;2
"Unit";"Hydralisk";"Larva";156;2
"Unit";"Overlord";"Larva";170;0
"Unit";"Overlord";"Larva";170;0
"Unit";"Overlord";"Larva";170;0
"Unit";"Overlord";"Larva";170;0
"Unit";"Overlord";"Larva";170;0
"Unit";"Overlord";"Larva";170;0
"Unit";"Overlord";"Larva";172;0
"Unit";"Overlord";"Larva";176;0
"Building";"Extractor";NA;176;0
"Building";"Extractor";NA;176;0
"Building";"CreepTumor";NA;180;0
"Unit";"Hydralisk";"Larva";176;2
"Unit";"Hydralisk";"Larva";176;2
"Unit";"Hydralisk";"Larva";176;2
"Unit";"Hydralisk";"Larva";176;2
"Unit";"Hydralisk";"Larva";176;2
"Unit";"Hydralisk";"Larva";176;2
"Unit";"Hydralisk";"Larva";176;2
"Unit";"Hydralisk";"Larva";176;2
"Unit";"Hydralisk";"Larva";176;2
"Unit";"Hydralisk";"Larva";176;2
"Unit";"Hydralisk";"Larva";176;2
"Unit";"Overlord";"Larva";176;0
"Building";"CreepTumor";NA;181;0
"Unit";"Overlord";"Larva";176;0
"Unit";"Overlord";"Larva";176;0
"Unit";"Overlord";"Larva";176;0
"Building";"CreepTumor";NA;181;0
"Building";"CreepTumor";NA;181;0
"Building";"CreepTumor";NA;181;0
"Upgrade";"EvolveGroovedSpines";"HydraliskDen";170;0
"Unit";"Overlord";"Larva";181;0
"Unit";"Overlord";"Larva";181;0
"Unit";"Overlord";"Larva";181;0
"Unit";"Hydralisk";"Larva";181;2
"Unit";"Hydralisk";"Larva";181;2
"Unit";"Hydralisk";"Larva";181;2
"Unit";"Hydralisk";"Larva";181;2
"Unit";"Hydralisk";"Larva";181;2
"Unit";"Overlord";"Larva";203;0
"Unit";"Hydralisk";"Larva";195;2
"Unit";"Roach";"Larva";203;2
"Unit";"Roach";"Larva";203;2
"Unit";"Roach";"Larva";203;2
"Unit";"Hydralisk";"Larva";203;2
"Unit";"Hydralisk";"Larva";203;2
"Upgrade";"ZergMissileWeaponsLevel2";"EvolutionChamber";156;0
"Upgrade";"ZergGroundArmorsLevel2";"EvolutionChamber";156;0
"Building";"CreepTumor";NA;213;0
"Building";"CreepTumor";NA;213;0
"Building";"CreepTumor";NA;213;0
"Unit";"Hydralisk";"Larva";203;2
"Unit";"Hydralisk";"Larva";203;2
"Unit";"Hydralisk";"Larva";203;2
"Building";"Hatchery";NA;176;0
"Unit";"Hydralisk";"Larva";225;2
"Unit";"Hydralisk";"Larva";231;2
"Unit";"Hydralisk";"Larva";231;2
"Unit";"Hydralisk";"Larva";231;2
"Unit";"Hydralisk";"Larva";231;2
"Unit";"Hydralisk";"Larva";231;2
"Unit";"Hydralisk";"Larva";231;2
"Unit";"Hydralisk";"Larva";231;2
"Unit";"Hydralisk";"Larva";231;2
"Unit";"Hydralisk";"Larva";231;2
"Unit";"Hydralisk";"Larva";231;2
"Unit";"Hydralisk";"Larva";231;2
"Building";"CreepTumor";NA;255;0
"Building";"CreepTumor";NA;255;0
"Building";"CreepTumor";NA;255;0
"Building";"CreepTumor";NA;255;0
"Building";"Extractor";NA;255;0
"Building";"Extractor";NA;255;0
"Building";"Spire";NA;225;0
"Unit";"Viper";"Larva";265;3
"Unit";"Viper";"Larva";265;3
"Building";"Hatchery";NA;255;0
"Building";"CreepTumor";NA;276;0
"Unit";"Overlord";"Larva";275;0
"Unit";"Overlord";"Larva";276;0
"Building";"SpineCrawler";NA;265;0
"Building";"SpineCrawler";NA;265;0
"Unit";"Viper";"Larva";271;3
"Unit";"Viper";"Larva";271;3
"Unit";"Viper";"Larva";271;3
"Unit";"Viper";"Larva";271;3
"Building";"SpineCrawler";NA;265;0
"Building";"CreepTumor";NA;280;0
"Building";"CreepTumor";NA;280;0
"Building";"SpineCrawler";NA;271;0
"Building";"SpineCrawler";NA;271;0
"Building";"Spire";NA;265;0
"Unit";"Overlord";"Larva";292;0
"Unit";"Overlord";"Larva";292;0
"Unit";"Overlord";"Larva";292;0
"Unit";"Overlord";"Larva";292;0
"Unit";"Zergling";"Larva";292;1
"Unit";"Zergling";"Larva";292;1
"Unit";"Zergling";"Larva";292;1
"Unit";"Zergling";"Larva";292;1
"Unit";"Zergling";"Larva";292;1
"Unit";"Zergling";"Larva";292;1
"Unit";"Zergling";"Larva";292;1
"Unit";"Zergling";"Larva";292;1
"Unit";"Zergling";"Larva";292;1
"Unit";"Zergling";"Larva";292;1
"Unit";"Zergling";"Larva";292;1
"Unit";"Zergling";"Larva";292;1
"Unit";"Corruptor";"Larva";292;2
"Unit";"Corruptor";"Larva";292;2
"Unit";"Corruptor";"Larva";292;2
"Unit";"Corruptor";"Larva";292;2
"Unit";"Corruptor";"Larva";292;2
"Unit";"Corruptor";"Larva";292;2
"Unit";"Corruptor";"Larva";292;2
"Unit";"Corruptor";"Larva";292;2
"Unit";"Corruptor";"Larva";292;2
"Unit";"Corruptor";"Larva";292;2
"Unit";"Corruptor";"Larva";292;2
"Unit";"Corruptor";"Larva";292;2
"Unit";"Corruptor";"Larva";292;2
"Unit";"Corruptor";"Larva";292;2
"Unit";"Corruptor";"Larva";292;2
"Unit";"Hydralisk";"Larva";339;2
"Unit";"Hydralisk";"Larva";339;2
"Unit";"Hydralisk";"Larva";339;2
"Unit";"Hydralisk";"Larva";339;2
"Unit";"Hydralisk";"Larva";339;2
"Unit";"Viper";"Larva";311;3
"Unit";"Hydralisk";"Larva";339;2
"Unit";"Viper";"Larva";311;3
"Unit";"Viper";"Larva";317;3
"Upgrade";"ZergGroundArmorsLevel3";"EvolutionChamber";276;0
"Upgrade";"ZergMissileWeaponsLevel3";"EvolutionChamber";276;0
"Unit";"Hydralisk";"Larva";339;2
"Unit";"Hydralisk";"Larva";339;2
"Unit";"Hydralisk";"Larva";339;2
"Building";"CreepTumor";NA;369;0
"Building";"CreepTumor";NA;369;0
"Unit";"Overlord";"Larva";369;0
"Building";"CreepTumorQueen";NA;372;0
"Building";"CreepTumorQueen";NA;372;0
"Building";"Extractor";NA;372;0
"Building";"SpineCrawler";NA;372;0
"Unit";"Corruptor";"Larva";375;2
"Unit";"Corruptor";"Larva";375;2
"Unit";"Corruptor";"Larva";375;2
"Unit";"Corruptor";"Larva";375;2
"Unit";"Corruptor";"Larva";375;2
"Unit";"Corruptor";"Larva";375;2
"Unit";"Corruptor";"Larva";375;2
"Building";"CreepTumorQueen";NA;375;0
"Building";"CreepTumorQueen";NA;375;0
"Unit";"Hydralisk";"Larva";375;2
"Unit";"Hydralisk";"Larva";375;2
"Unit";"Hydralisk";"Larva";375;2
"Unit";"Hydralisk";"Larva";375;2
"Building";"SpineCrawler";NA;375;0
"Upgrade";"ZergMeleeWeaponsLevel1";"EvolutionChamber";369;0
"Unit";"Hydralisk";"Larva";389;2
"Building";"CreepTumor";NA;397;0
"Building";"CreepTumor";NA;397;0
"Unit";"Hydralisk";"Larva";399;2
"Unit";"Hydralisk";"Larva";399;2
"Building";"CreepTumor";NA;399;0
"Building";"CreepTumor";NA;399;0
"Building";"CreepTumorQueen";NA;399;0
"Building";"CreepTumorQueen";NA;399;0
"Building";"Extractor";NA;403;0
"Unit";"Corruptor";"Larva";403;2
"Unit";"Corruptor";"Larva";403;2
"Unit";"Corruptor";"Larva";403;2
"Unit";"Corruptor";"Larva";403;2
"Unit";"Corruptor";"Larva";403;2
"Unit";"Hydralisk";"Larva";403;2
"Unit";"Hydralisk";"Larva";403;2
"Unit";"Hydralisk";"Larva";403;2
"Unit";"Hydralisk";"Larva";403;2
"Unit";"Hydralisk";"Larva";403;2
"Unit";"Hydralisk";"Larva";403;2
"Unit";"Hydralisk";"Larva";403;2
"Unit";"Hydralisk";"Larva";403;2
"Unit";"Hydralisk";"Larva";403;2
"Unit";"Hydralisk";"Larva";403;2
"Unit";"Hydralisk";"Larva";403;2
"Unit";"Hydralisk";"Larva";403;2
"Unit";"Hydralisk";"Larva";403;2
"Building";"CreepTumorQueen";NA;427;0
"Building";"CreepTumorQueen";NA;427;0
"Building";"CreepTumorQueen";NA;427;0
"Building";"Hatchery";NA;403;0
"Building";"CreepTumor";NA;439;0
"Building";"Extractor";NA;442;0
"Building";"Extractor";NA;442;0
"Unit";"Hydralisk";"Larva";442;2
"Unit";"Hydralisk";"Larva";442;2
"Unit";"Hydralisk";"Larva";442;2
"Unit";"Hydralisk";"Larva";442;2
"Unit";"Hydralisk";"Larva";442;2
"Unit";"Hydralisk";"Larva";442;2
"Unit";"Hydralisk";"Larva";442;2
"Unit";"Hydralisk";"Larva";442;2
"Unit";"Hydralisk";"Larva";442;2
"Unit";"Hydralisk";"Larva";442;2
"Unit";"Hydralisk";"Larva";442;2
"Unit";"Hydralisk";"Larva";442;2
"Building";"Hatchery";NA;427;0
"Upgrade";"ZergMeleeWeaponsLevel2";"EvolutionChamber";403;0
"Building";"Extractor";NA;442;0
"Unit";"Hydralisk";"Larva";442;2
"Unit";"Hydralisk";"Larva";442;2
"Unit";"Hydralisk";"Larva";442;2
"Unit";"Hydralisk";"Larva";442;2
"Unit";"Hydralisk";"Larva";442;2
"Unit";"Hydralisk";"Larva";442;2
"Unit";"Hydralisk";"Larva";442;2
"Unit";"Hydralisk";"Larva";442;2
"Unit";"Hydralisk";"Larva";442;2
"Unit";"Hydralisk";"Larva";442;2
"Unit";"Hydralisk";"Larva";466;2
"Unit";"Hydralisk";"Larva";466;2
"Unit";"Hydralisk";"Larva";466;2
"Unit";"Queen";"Hatchery";466;2
"Unit";"Queen";"Hatchery";466;2
"Unit";"Queen";"Hatchery";466;2
"Unit";"Hydralisk";"Larva";487;2
"Unit";"Hydralisk";"Larva";487;2
"Unit";"Hydralisk";"Larva";487;2
"Building";"Hatchery";NA;442;0
