"type";"unit_name";"on_building";"total_supply";"supply"
"Unit";"Overlord";"Larva";12;0
"Building";"Extractor";NA;18;0
"Unit";"Overlord";"Larva";21;0
"Building";"SpawningPool";NA;19;0
"Building";"Hatchery";NA;17;0
"Unit";"Zergling";"Larva";23;1
"Unit";"Zergling";"Larva";23;1
"Unit";"Zergling";"Larva";23;1
"Unit";"Zergling";"Larva";23;1
"Unit";"Queen";"Hatchery";23;2
"Unit";"Queen";"Hatchery";23;2
"Building";"CreepTumorQueen";NA;33;0
"Unit";"Overlord";"Larva";35;0
"Building";"CreepTumor";NA;39;0
"Unit";"Overlord";"Larva";42;0
"Building";"Hatchery";NA;29;0
"Unit";"Overlord";"Larva";46;0
"Unit";"Queen";"Hatchery";41;2
"Building";"Extractor";NA;47;0
"Unit";"Overlord";"Larva";49;0
"Unit";"Queen";"Hatchery";47;2
"Building";"CreepTumor";NA;54;0
"Unit";"Zergling";"Larva";54;1
"Unit";"Zergling";"Larva";54;1
"Unit";"Zergling";"Larva";54;1
"Unit";"Zergling";"Larva";54;1
"Unit";"Zergling";"Larva";54;1
"Unit";"Zergling";"Larva";54;1
"Building";"BanelingNest";NA;47;0
"Unit";"Zergling";"Larva";55;1
"Unit";"Zergling";"Larva";55;1
"Unit";"Zergling";"Larva";55;1
"Unit";"Zergling";"Larva";55;1
"Unit";"Zergling";"Larva";55;1
"Unit";"Zergling";"Larva";55;1
"Unit";"Zergling";"Larva";55;1
"Unit";"Zergling";"Larva";55;1
"Unit";"Zergling";"Larva";55;1
"Unit";"Zergling";"Larva";55;1
"Unit";"Zergling";"Larva";55;1
"Unit";"Zergling";"Larva";55;1
"Building";"CreepTumorQueen";NA;66;0
"Unit";"Zergling";"Larva";66;1
"Unit";"Zergling";"Larva";66;1
"Unit";"Zergling";"Larva";66;1
"Unit";"Zergling";"Larva";66;1
"Unit";"Zergling";"Larva";66;1
"Unit";"Zergling";"Larva";66;1
"Unit";"Zergling";"Larva";66;1
"Unit";"Zergling";"Larva";66;1
"Unit";"Zergling";"Larva";66;1
"Unit";"Zergling";"Larva";66;1
"Unit";"Overlord";"Larva";66;0
"Unit";"Baneling";"Zergling";66;0
"Unit";"Baneling";"Zergling";66;0
"Unit";"Baneling";"Zergling";66;0
"Unit";"Baneling";"Zergling";66;0
"Unit";"Baneling";"Zergling";66;0
"Unit";"Baneling";"Zergling";66;0
"Building";"CreepTumor";NA;88;0
"Unit";"Zergling";"Larva";88;1
"Unit";"Zergling";"Larva";88;1
"Unit";"Zergling";"Larva";88;1
"Unit";"Zergling";"Larva";88;1
"Unit";"Zergling";"Larva";88;1
"Unit";"Zergling";"Larva";88;1
"Unit";"Zergling";"Larva";88;1
"Unit";"Zergling";"Larva";88;1
"Unit";"Zergling";"Larva";88;1
"Unit";"Zergling";"Larva";88;1
"Unit";"Zergling";"Larva";88;1
"Unit";"Zergling";"Larva";88;1
"Unit";"Overlord";"Larva";88;0
"Unit";"Overlord";"Larva";88;0
"Unit";"Zergling";"Larva";88;1
"Unit";"Zergling";"Larva";88;1
"Unit";"Zergling";"Larva";88;1
"Unit";"Zergling";"Larva";88;1
"Unit";"Zergling";"Larva";88;1
"Unit";"Zergling";"Larva";88;1
"Unit";"Zergling";"Larva";88;1
"Unit";"Zergling";"Larva";88;1
"Unit";"Zergling";"Larva";88;1
"Unit";"Zergling";"Larva";88;1
"Unit";"Zergling";"Larva";88;1
"Unit";"Zergling";"Larva";88;1
"Unit";"Zergling";"Larva";88;1
"Unit";"Zergling";"Larva";88;1
"Unit";"Baneling";"Zergling";100;0
"Unit";"Baneling";"Zergling";100;0
"Unit";"Baneling";"Zergling";100;0
"Building";"CreepTumorQueen";NA;100;0
"Unit";"Zergling";"Larva";100;1
"Unit";"Zergling";"Larva";100;1
"Unit";"Zergling";"Larva";100;1
"Unit";"Zergling";"Larva";100;1
"Unit";"Zergling";"Larva";100;1
"Unit";"Zergling";"Larva";100;1
"Unit";"Baneling";"Zergling";114;0
"Unit";"Baneling";"Zergling";114;0
"Unit";"Baneling";"Zergling";114;0
"Unit";"Baneling";"Zergling";114;0
"Unit";"Baneling";"Zergling";114;0
"Unit";"Baneling";"Zergling";114;0
"Unit";"Baneling";"Zergling";114;0
"Unit";"Baneling";"Zergling";114;0
"Unit";"Baneling";"Zergling";114;0
"Unit";"Baneling";"Zergling";114;0
"Unit";"Baneling";"Zergling";114;0
"Unit";"Zergling";"Larva";114;1
"Unit";"Zergling";"Larva";114;1
"Unit";"Zergling";"Larva";114;1
"Unit";"Zergling";"Larva";114;1
"Unit";"Zergling";"Larva";114;1
"Unit";"Zergling";"Larva";114;1
"Unit";"Zergling";"Larva";114;1
"Unit";"Zergling";"Larva";114;1
"Unit";"Zergling";"Larva";114;1
"Unit";"Zergling";"Larva";114;1
"Unit";"Zergling";"Larva";114;1
"Unit";"Zergling";"Larva";114;1
"Unit";"Zergling";"Larva";114;1
"Unit";"Zergling";"Larva";114;1
"Unit";"Zergling";"Larva";114;1
"Unit";"Zergling";"Larva";114;1
"Unit";"Zergling";"Larva";114;1
"Unit";"Zergling";"Larva";114;1
"Unit";"Zergling";"Larva";114;1
"Unit";"Zergling";"Larva";114;1
"Building";"CreepTumorQueen";NA;120;0
"Unit";"Baneling";"Zergling";120;0
"Unit";"Baneling";"Zergling";120;0
"Unit";"Baneling";"Zergling";120;0
"Unit";"Zergling";"Larva";120;1
"Unit";"Zergling";"Larva";120;1
"Unit";"Zergling";"Larva";120;1
"Unit";"Zergling";"Larva";120;1
"Unit";"Zergling";"Larva";120;1
"Unit";"Zergling";"Larva";120;1
"Unit";"Zergling";"Larva";120;1
"Unit";"Zergling";"Larva";120;1
"Unit";"Zergling";"Larva";120;1
"Unit";"Zergling";"Larva";120;1
"Unit";"Baneling";"Zergling";140;0
"Unit";"Baneling";"Zergling";140;0
"Unit";"Baneling";"Zergling";140;0
"Unit";"Zergling";"Larva";140;1
"Unit";"Zergling";"Larva";140;1
"Unit";"Zergling";"Larva";140;1
"Unit";"Zergling";"Larva";140;1
"Unit";"Zergling";"Larva";140;1
"Unit";"Zergling";"Larva";140;1
"Unit";"Baneling";"Zergling";150;0
"Unit";"Baneling";"Zergling";150;0
"Unit";"Baneling";"Zergling";150;0
"Unit";"Zergling";"Larva";156;1
"Unit";"Zergling";"Larva";156;1
"Unit";"Zergling";"Larva";156;1
"Unit";"Zergling";"Larva";156;1
"Unit";"Zergling";"Larva";156;1
"Unit";"Zergling";"Larva";156;1
"Unit";"Zergling";"Larva";156;1
"Unit";"Zergling";"Larva";156;1
"Unit";"Zergling";"Larva";156;1
"Unit";"Zergling";"Larva";156;1
"Unit";"Zergling";"Larva";156;1
"Unit";"Zergling";"Larva";156;1
"Unit";"Zergling";"Larva";156;1
"Unit";"Zergling";"Larva";156;1
"Unit";"Zergling";"Larva";156;1
"Unit";"Zergling";"Larva";156;1
"Unit";"Zergling";"Larva";156;1
"Unit";"Zergling";"Larva";156;1
"Unit";"Zergling";"Larva";156;1
"Unit";"Zergling";"Larva";156;1
"Unit";"Zergling";"Larva";156;1
"Unit";"Zergling";"Larva";156;1
"Unit";"Zergling";"Larva";156;1
"Unit";"Zergling";"Larva";156;1
"Unit";"Zergling";"Larva";156;1
"Unit";"Zergling";"Larva";156;1
"Unit";"Zergling";"Larva";156;1
"Unit";"Zergling";"Larva";156;1
"Unit";"Zergling";"Larva";156;1
"Unit";"Zergling";"Larva";156;1
"Unit";"Zergling";"Larva";156;1
"Unit";"Zergling";"Larva";156;1
"Unit";"Zergling";"Larva";156;1
"Unit";"Zergling";"Larva";156;1
"Unit";"Zergling";"Larva";156;1
"Unit";"Zergling";"Larva";156;1
"Unit";"Zergling";"Larva";176;1
"Unit";"Zergling";"Larva";176;1
"Unit";"Zergling";"Larva";176;1
"Unit";"Zergling";"Larva";176;1
"Unit";"Zergling";"Larva";176;1
"Unit";"Zergling";"Larva";176;1
"Unit";"Zergling";"Larva";176;1
"Unit";"Zergling";"Larva";176;1
"Unit";"Zergling";"Larva";176;1
"Unit";"Zergling";"Larva";176;1
"Unit";"Zergling";"Larva";176;1
"Unit";"Zergling";"Larva";176;1
"Unit";"Baneling";"Zergling";192;0
"Unit";"Baneling";"Zergling";192;0
"Unit";"Baneling";"Zergling";192;0
"Unit";"Baneling";"Zergling";192;0
"Unit";"Baneling";"Zergling";192;0
"Unit";"Baneling";"Zergling";192;0
"Unit";"Zergling";"Larva";192;1
"Unit";"Zergling";"Larva";192;1
"Unit";"Zergling";"Larva";192;1
"Unit";"Zergling";"Larva";192;1
"Unit";"Zergling";"Larva";192;1
"Unit";"Zergling";"Larva";192;1
"Unit";"Baneling";"Zergling";204;0
"Unit";"Baneling";"Zergling";204;0
"Unit";"Baneling";"Zergling";204;0
"Unit";"Baneling";"Zergling";204;0
"Unit";"Baneling";"Zergling";204;0
"Unit";"Baneling";"Zergling";204;0
"Unit";"Baneling";"Zergling";204;0
"Unit";"Zergling";"Larva";204;1
"Unit";"Zergling";"Larva";204;1
"Unit";"Zergling";"Larva";204;1
"Unit";"Zergling";"Larva";204;1
"Unit";"Zergling";"Larva";204;1
"Unit";"Zergling";"Larva";204;1
"Unit";"Zergling";"Larva";204;1
"Unit";"Zergling";"Larva";204;1
"Unit";"Zergling";"Larva";204;1
"Unit";"Zergling";"Larva";204;1
"Unit";"Zergling";"Larva";204;1
"Unit";"Zergling";"Larva";204;1
"Unit";"Zergling";"Larva";204;1
"Unit";"Zergling";"Larva";204;1
"Unit";"Zergling";"Larva";204;1
"Unit";"Zergling";"Larva";204;1
"Building";"EvolutionChamber";NA;226;0
"Building";"EvolutionChamber";NA;226;0
"Building";"CreepTumor";NA;237;0
"Building";"CreepTumor";NA;237;0
"Unit";"Overlord";"Larva";237;0
"Building";"Extractor";NA;237;0
"Building";"Extractor";NA;237;0
"Building";"Extractor";NA;237;0
"Unit";"Zergling";"Larva";237;1
"Unit";"Zergling";"Larva";237;1
"Unit";"Zergling";"Larva";237;1
"Unit";"Zergling";"Larva";237;1
"Unit";"Zergling";"Larva";237;1
"Unit";"Zergling";"Larva";237;1
"Unit";"Zergling";"Larva";237;1
"Unit";"Zergling";"Larva";237;1
"Unit";"Zergling";"Larva";237;1
"Unit";"Zergling";"Larva";237;1
"Building";"SporeCrawler";NA;237;0
"Unit";"Zergling";"Larva";237;1
"Unit";"Zergling";"Larva";237;1
"Unit";"Zergling";"Larva";237;1
"Unit";"Zergling";"Larva";237;1
"Unit";"Zergling";"Larva";237;1
"Unit";"Zergling";"Larva";237;1
"Unit";"Zergling";"Larva";237;1
"Unit";"Zergling";"Larva";237;1
"Unit";"Zergling";"Larva";237;1
"Unit";"Zergling";"Larva";237;1
"Unit";"Zergling";"Larva";237;1
"Unit";"Zergling";"Larva";237;1
"Unit";"Zergling";"Larva";237;1
"Unit";"Zergling";"Larva";237;1
"Unit";"Zergling";"Larva";237;1
"Unit";"Zergling";"Larva";237;1
"Unit";"Baneling";"Zergling";240;0
"Unit";"Baneling";"Zergling";240;0
"Building";"CreepTumor";NA;240;0
"Building";"CreepTumorQueen";NA;240;0
"Building";"CreepTumorQueen";NA;240;0
"Building";"CreepTumorQueen";NA;266;0
"Unit";"Zergling";"Larva";266;1
"Unit";"Zergling";"Larva";266;1
"Unit";"Zergling";"Larva";266;1
"Unit";"Zergling";"Larva";266;1
"Unit";"Zergling";"Larva";266;1
"Unit";"Zergling";"Larva";266;1
"Unit";"Zergling";"Larva";266;1
"Unit";"Zergling";"Larva";266;1
"Unit";"Zergling";"Larva";266;1
"Unit";"Zergling";"Larva";266;1
"Unit";"Zergling";"Larva";266;1
"Unit";"Zergling";"Larva";266;1
"Unit";"Baneling";"Zergling";266;0
"Unit";"Baneling";"Zergling";266;0
"Unit";"Baneling";"Zergling";266;0
"Unit";"Baneling";"Zergling";266;0
"Unit";"Baneling";"Zergling";266;0
"Unit";"Baneling";"Zergling";266;0
"Building";"Hatchery";NA;237;0
"Unit";"Zergling";"Larva";266;1
"Unit";"Zergling";"Larva";266;1
"Unit";"Zergling";"Larva";266;1
"Unit";"Zergling";"Larva";266;1
"Unit";"Zergling";"Larva";266;1
"Unit";"Zergling";"Larva";266;1
"Unit";"Zergling";"Larva";266;1
"Unit";"Zergling";"Larva";266;1
"Unit";"Zergling";"Larva";268;1
"Unit";"Zergling";"Larva";268;1
"Unit";"Zergling";"Larva";268;1
"Unit";"Zergling";"Larva";268;1
"Unit";"Zergling";"Larva";268;1
"Unit";"Zergling";"Larva";268;1
"Unit";"Zergling";"Larva";268;1
"Unit";"Zergling";"Larva";268;1
"Unit";"Zergling";"Larva";278;1
"Unit";"Zergling";"Larva";278;1
"Unit";"Zergling";"Larva";278;1
"Unit";"Zergling";"Larva";278;1
"Unit";"Zergling";"Larva";278;1
"Unit";"Zergling";"Larva";278;1
"Unit";"Zergling";"Larva";278;1
"Unit";"Zergling";"Larva";278;1
"Unit";"Zergling";"Larva";278;1
"Unit";"Zergling";"Larva";278;1
"Unit";"Zergling";"Larva";278;1
"Unit";"Zergling";"Larva";278;1
"Unit";"Baneling";"Zergling";294;0
"Building";"CreepTumor";NA;294;0
"Building";"CreepTumor";NA;294;0
"Building";"CreepTumor";NA;294;0
"Building";"CreepTumor";NA;294;0
"Unit";"Zergling";"Larva";306;1
"Unit";"Zergling";"Larva";306;1
"Unit";"Zergling";"Larva";306;1
"Unit";"Zergling";"Larva";306;1
"Unit";"Zergling";"Larva";306;1
"Unit";"Zergling";"Larva";306;1
"Unit";"Zergling";"Larva";306;1
"Unit";"Zergling";"Larva";306;1
"Unit";"Zergling";"Larva";306;1
"Unit";"Zergling";"Larva";306;1
"Unit";"Zergling";"Larva";306;1
"Unit";"Zergling";"Larva";306;1
"Unit";"Zergling";"Larva";306;1
"Unit";"Zergling";"Larva";306;1
"Unit";"Zergling";"Larva";306;1
"Unit";"Zergling";"Larva";306;1
"Unit";"Zergling";"Larva";306;1
"Unit";"Zergling";"Larva";306;1
"Unit";"Zergling";"Larva";306;1
"Unit";"Zergling";"Larva";306;1
"Unit";"Zergling";"Larva";306;1
"Unit";"Zergling";"Larva";306;1
"Building";"Hatchery";NA;240;0
"Building";"CreepTumorQueen";NA;306;0
"Building";"CreepTumorQueen";NA;306;0
"Upgrade";"ZergGroundArmorsLevel1";"EvolutionChamber";266;0
"Upgrade";"ZergMeleeWeaponsLevel1";"EvolutionChamber";266;0
"Unit";"Zergling";"Larva";334;1
"Unit";"Zergling";"Larva";334;1
"Unit";"Zergling";"Larva";334;1
"Unit";"Zergling";"Larva";334;1
"Unit";"Zergling";"Larva";334;1
"Unit";"Zergling";"Larva";334;1
"Unit";"Zergling";"Larva";334;1
"Unit";"Zergling";"Larva";334;1
"Unit";"Zergling";"Larva";334;1
"Unit";"Zergling";"Larva";334;1
"Unit";"Zergling";"Larva";334;1
"Unit";"Zergling";"Larva";334;1
"Unit";"Zergling";"Larva";334;1
"Unit";"Zergling";"Larva";334;1
"Unit";"Zergling";"Larva";334;1
"Unit";"Zergling";"Larva";334;1
"Unit";"Zergling";"Larva";334;1
"Unit";"Zergling";"Larva";334;1
"Building";"CreepTumor";NA;355;0
"Unit";"Zergling";"Larva";355;1
"Unit";"Zergling";"Larva";355;1
"Unit";"Zergling";"Larva";355;1
"Unit";"Zergling";"Larva";355;1
"Unit";"Zergling";"Larva";355;1
"Unit";"Zergling";"Larva";355;1
"Unit";"Zergling";"Larva";355;1
"Unit";"Zergling";"Larva";355;1
"Unit";"Zergling";"Larva";355;1
"Unit";"Zergling";"Larva";355;1
"Unit";"Zergling";"Larva";355;1
"Unit";"Zergling";"Larva";355;1
"Unit";"Zergling";"Larva";355;1
"Unit";"Zergling";"Larva";355;1
"Unit";"Zergling";"Larva";355;1
"Unit";"Zergling";"Larva";355;1
"Unit";"Zergling";"Larva";355;1
"Unit";"Zergling";"Larva";355;1
"Unit";"Zergling";"Larva";355;1
"Unit";"Zergling";"Larva";355;1
"Building";"CreepTumor";NA;355;0
"Building";"InfestationPit";NA;334;0
"Unit";"Zergling";"Larva";355;1
"Unit";"Zergling";"Larva";355;1
"Unit";"Zergling";"Larva";359;1
"Unit";"Zergling";"Larva";359;1
"Unit";"Zergling";"Larva";359;1
"Unit";"Zergling";"Larva";359;1
"Unit";"Zergling";"Larva";359;1
"Unit";"Zergling";"Larva";359;1
"Unit";"Zergling";"Larva";363;1
"Unit";"Zergling";"Larva";363;1
"Unit";"Zergling";"Larva";363;1
"Unit";"Zergling";"Larva";363;1
"Unit";"Zergling";"Larva";365;1
"Unit";"Zergling";"Larva";365;1
"Unit";"Zergling";"Larva";373;1
"Unit";"Zergling";"Larva";373;1
"Unit";"Zergling";"Larva";373;1
"Unit";"Zergling";"Larva";373;1
"Unit";"Zergling";"Larva";375;1
"Unit";"Zergling";"Larva";375;1
"Unit";"Zergling";"Larva";375;1
"Unit";"Zergling";"Larva";375;1
"Unit";"Zergling";"Larva";375;1
"Unit";"Zergling";"Larva";375;1
"Unit";"Overlord";"Larva";375;0
"Unit";"Overlord";"Larva";375;0
"Unit";"Overlord";"Larva";375;0
"Unit";"Baneling";"Zergling";399;0
"Unit";"Baneling";"Zergling";399;0
"Unit";"Baneling";"Zergling";399;0
"Unit";"Baneling";"Zergling";399;0
"Unit";"Baneling";"Zergling";399;0
"Unit";"Baneling";"Zergling";399;0
"Unit";"Baneling";"Zergling";399;0
"Unit";"Zergling";"Larva";399;1
"Unit";"Zergling";"Larva";399;1
"Unit";"Zergling";"Larva";399;1
"Unit";"Zergling";"Larva";399;1
"Unit";"Zergling";"Larva";399;1
"Unit";"Zergling";"Larva";399;1
"Unit";"Zergling";"Larva";399;1
"Unit";"Zergling";"Larva";399;1
"Unit";"Zergling";"Larva";399;1
"Unit";"Zergling";"Larva";399;1
"Unit";"Zergling";"Larva";399;1
"Unit";"Zergling";"Larva";399;1
"Unit";"Zergling";"Larva";399;1
"Unit";"Zergling";"Larva";399;1
"Unit";"Zergling";"Larva";399;1
"Unit";"Zergling";"Larva";399;1
"Unit";"Zergling";"Larva";399;1
"Unit";"Zergling";"Larva";399;1
"Unit";"Zergling";"Larva";399;1
"Unit";"Zergling";"Larva";399;1
"Unit";"Zergling";"Larva";399;1
"Unit";"Zergling";"Larva";399;1
"Unit";"Zergling";"Larva";399;1
"Unit";"Zergling";"Larva";399;1
"Unit";"Zergling";"Larva";399;1
"Unit";"Zergling";"Larva";399;1
"Unit";"Zergling";"Larva";399;1
"Unit";"Zergling";"Larva";399;1
"Unit";"Zergling";"Larva";399;1
"Unit";"Zergling";"Larva";399;1
"Building";"CreepTumor";NA;399;0
"Building";"Hatchery";NA;355;0
"Unit";"Baneling";"Zergling";399;0
"Unit";"Baneling";"Zergling";399;0
"Unit";"Baneling";"Zergling";399;0
"Unit";"Zergling";"Larva";401;1
"Unit";"Zergling";"Larva";401;1
"Unit";"Zergling";"Larva";415;1
"Unit";"Zergling";"Larva";415;1
"Unit";"Zergling";"Larva";415;1
"Unit";"Zergling";"Larva";415;1
"Unit";"Zergling";"Larva";419;1
"Unit";"Zergling";"Larva";419;1
"Unit";"Zergling";"Larva";419;1
"Unit";"Zergling";"Larva";419;1
"Unit";"Zergling";"Larva";423;1
"Unit";"Zergling";"Larva";423;1
"Unit";"Zergling";"Larva";423;1
"Unit";"Zergling";"Larva";423;1
"Unit";"Zergling";"Larva";425;1
"Unit";"Zergling";"Larva";425;1
"Unit";"Zergling";"Larva";425;1
"Unit";"Zergling";"Larva";425;1
"Unit";"Zergling";"Larva";429;1
"Unit";"Zergling";"Larva";429;1
"Unit";"Zergling";"Larva";429;1
"Unit";"Zergling";"Larva";429;1
"Unit";"Zergling";"Larva";429;1
"Unit";"Zergling";"Larva";429;1
"Unit";"Zergling";"Larva";429;1
"Unit";"Zergling";"Larva";429;1
