"type";"unit_name";"on_building";"total_supply";"supply"
"Unit";"Overlord";"Larva";13;0
"Building";"Extractor";NA;18;0
"Building";"SpawningPool";NA;19;0
"Unit";"Overlord";"Larva";22;0
"Building";"Hatchery";NA;17;0
"Unit";"Zergling";"Larva";22;1
"Unit";"Zergling";"Larva";22;1
"Unit";"Zergling";"Larva";22;1
"Unit";"Zergling";"Larva";22;1
"Unit";"Queen";"Hatchery";22;2
"Unit";"Queen";"Hatchery";22;2
"Unit";"Zergling";"Larva";29;1
"Unit";"Zergling";"Larva";29;1
"Building";"CreepTumorQueen";NA;34;0
"Unit";"Overlord";"Larva";36;0
"Unit";"Queen";"Hatchery";34;2
"Building";"CreepTumorQueen";NA;39;0
"Building";"CreepTumor";NA;39;0
"Unit";"Overlord";"Larva";51;0
"Building";"CreepTumor";NA;51;0
"Building";"CreepTumorQueen";NA;52;0
"Building";"CreepTumorQueen";NA;52;0
"Building";"Hatchery";NA;39;0
"Unit";"Overlord";"Larva";52;0
"Unit";"Overlord";"Larva";52;0
"Building";"CreepTumor";NA;52;0
"Unit";"Zergling";"Larva";52;1
"Unit";"Zergling";"Larva";52;1
"Unit";"Zergling";"Larva";52;1
"Unit";"Zergling";"Larva";52;1
"Unit";"Zergling";"Larva";52;1
"Unit";"Zergling";"Larva";52;1
"Unit";"Zergling";"Larva";52;1
"Unit";"Zergling";"Larva";52;1
"Unit";"Zergling";"Larva";52;1
"Unit";"Zergling";"Larva";52;1
"Unit";"Zergling";"Larva";52;1
"Unit";"Zergling";"Larva";52;1
"Building";"CreepTumorQueen";NA;54;0
"Building";"Extractor";NA;52;0
"Unit";"Queen";"Hatchery";52;2
"Building";"RoachWarren";NA;52;0
"Building";"CreepTumor";NA;69;0
"Building";"CreepTumor";NA;69;0
"Building";"CreepTumor";NA;72;0
"Unit";"Queen";"Hatchery";52;2
"Building";"CreepTumor";NA;72;0
"Unit";"Overlord";"Larva";77;0
"Building";"CreepTumor";NA;79;0
"Building";"Extractor";NA;76;0
"Unit";"Overlord";"Larva";77;0
"Building";"CreepTumor";NA;79;0
"Unit";"Overlord";"Larva";79;0
"Unit";"Overlord";"Larva";79;0
"Unit";"Overlord";"Larva";79;0
"Building";"CreepTumor";NA;80;0
"Building";"CreepTumor";NA;80;0
"Building";"CreepTumor";NA;80;0
"Building";"CreepTumorQueen";NA;80;0
"Building";"CreepTumorQueen";NA;80;0
"Unit";"Roach";"Larva";80;2
"Unit";"Roach";"Larva";80;2
"Unit";"Roach";"Larva";80;2
"Unit";"Roach";"Larva";80;2
"Building";"CreepTumor";NA;94;0
"Building";"CreepTumor";NA;94;0
"Building";"CreepTumor";NA;94;0
"Building";"CreepTumor";NA;94;0
"Building";"CreepTumor";NA;94;0
"Building";"CreepTumor";NA;94;0
"Building";"SporeCrawler";NA;94;0
"Building";"SporeCrawler";NA;94;0
"Building";"SporeCrawler";NA;94;0
"Building";"CreepTumor";NA;100;0
"Unit";"Queen";"Hatchery";94;2
"Building";"CreepTumorQueen";NA;111;0
"Building";"CreepTumor";NA;113;0
"Building";"CreepTumor";NA;116;0
"Building";"CreepTumor";NA;116;0
"Building";"CreepTumor";NA;116;0
"Building";"CreepTumor";NA;116;0
"Building";"CreepTumor";NA;116;0
"Building";"CreepTumorQueen";NA;122;0
"Building";"CreepTumorQueen";NA;122;0
"Building";"Extractor";NA;122;0
"Building";"EvolutionChamber";NA;122;0
"Building";"EvolutionChamber";NA;122;0
"Building";"Extractor";NA;125;0
"Building";"Extractor";NA;127;0
"Building";"CreepTumor";NA;133;0
"Building";"CreepTumor";NA;133;0
"Building";"CreepTumor";NA;133;0
"Building";"CreepTumor";NA;133;0
"Unit";"Overlord";"Larva";129;0
"Building";"CreepTumor";NA;133;0
"Building";"CreepTumor";NA;140;0
"Building";"CreepTumor";NA;140;0
"Building";"BanelingNest";NA;124;0
"Building";"CreepTumorQueen";NA;140;0
"Building";"CreepTumorQueen";NA;140;0
"Unit";"Zergling";"Larva";140;1
"Unit";"Zergling";"Larva";140;1
"Unit";"Zergling";"Larva";140;1
"Unit";"Zergling";"Larva";140;1
"Unit";"Zergling";"Larva";140;1
"Unit";"Zergling";"Larva";140;1
"Unit";"Zergling";"Larva";140;1
"Unit";"Zergling";"Larva";140;1
"Unit";"Zergling";"Larva";140;1
"Unit";"Zergling";"Larva";140;1
"Unit";"Zergling";"Larva";140;1
"Unit";"Zergling";"Larva";140;1
"Unit";"Zergling";"Larva";140;1
"Unit";"Zergling";"Larva";140;1
"Building";"CreepTumor";NA;140;0
"Building";"CreepTumorQueen";NA;140;0
"Building";"CreepTumorQueen";NA;140;0
"Unit";"Zergling";"Larva";140;1
"Unit";"Zergling";"Larva";140;1
"Unit";"Zergling";"Larva";140;1
"Unit";"Zergling";"Larva";140;1
"Unit";"Zergling";"Larva";140;1
"Unit";"Zergling";"Larva";140;1
"Unit";"Zergling";"Larva";140;1
"Unit";"Zergling";"Larva";140;1
"Unit";"Zergling";"Larva";140;1
"Unit";"Zergling";"Larva";140;1
"Unit";"Zergling";"Larva";140;1
"Unit";"Zergling";"Larva";140;1
"Unit";"Zergling";"Larva";140;1
"Unit";"Zergling";"Larva";140;1
"Building";"CreepTumor";NA;140;0
"Unit";"Overlord";"Larva";140;0
"Unit";"Zergling";"Larva";154;1
"Unit";"Zergling";"Larva";154;1
"Unit";"Zergling";"Larva";154;1
"Unit";"Zergling";"Larva";154;1
"Building";"Hatchery";NA;127;0
"Unit";"Zergling";"Larva";168;1
"Unit";"Zergling";"Larva";168;1
"Unit";"Zergling";"Larva";168;1
"Unit";"Zergling";"Larva";168;1
"Unit";"Zergling";"Larva";168;1
"Unit";"Zergling";"Larva";168;1
"Unit";"Zergling";"Larva";168;1
"Unit";"Zergling";"Larva";168;1
"Unit";"Roach";"Larva";168;2
"Building";"CreepTumor";NA;172;0
"Building";"CreepTumor";NA;172;0
"Building";"CreepTumor";NA;172;0
"Unit";"Overlord";"Larva";168;0
"Unit";"Overlord";"Larva";168;0
"Building";"CreepTumor";NA;172;0
"Building";"CreepTumor";NA;172;0
"Building";"CreepTumor";NA;172;0
"Building";"CreepTumor";NA;172;0
"Building";"CreepTumor";NA;182;0
"Unit";"Overlord";"Larva";172;0
"Unit";"Zergling";"Larva";182;1
"Unit";"Zergling";"Larva";182;1
"Unit";"Overlord";"Larva";182;0
"Unit";"Zergling";"Larva";182;1
"Unit";"Zergling";"Larva";182;1
"Unit";"Zergling";"Larva";182;1
"Unit";"Zergling";"Larva";182;1
"Unit";"Zergling";"Larva";182;1
"Unit";"Zergling";"Larva";182;1
"Unit";"Zergling";"Larva";182;1
"Unit";"Zergling";"Larva";182;1
"Unit";"Zergling";"Larva";182;1
"Unit";"Zergling";"Larva";182;1
"Building";"Hatchery";NA;140;0
"Building";"CreepTumorQueen";NA;194;0
"Unit";"Queen";"Hatchery";182;2
"Building";"CreepTumorQueen";NA;194;0
"Building";"CreepTumor";NA;194;0
"Building";"CreepTumorQueen";NA;194;0
"Building";"CreepTumorQueen";NA;194;0
"Upgrade";"ZergMeleeWeaponsLevel1";"EvolutionChamber";140;0
"Upgrade";"ZergGroundArmorsLevel1";"EvolutionChamber";142;0
"Building";"CreepTumor";NA;194;0
"Unit";"Zergling";"Larva";194;1
"Unit";"Zergling";"Larva";194;1
"Unit";"Zergling";"Larva";194;1
"Unit";"Zergling";"Larva";194;1
"Unit";"Zergling";"Larva";194;1
"Unit";"Zergling";"Larva";194;1
"Unit";"Zergling";"Larva";194;1
"Unit";"Zergling";"Larva";194;1
"Unit";"Zergling";"Larva";194;1
"Unit";"Zergling";"Larva";194;1
"Unit";"Zergling";"Larva";194;1
"Unit";"Zergling";"Larva";194;1
"Unit";"Zergling";"Larva";194;1
"Unit";"Zergling";"Larva";194;1
"Unit";"Zergling";"Larva";194;1
"Unit";"Zergling";"Larva";194;1
"Unit";"Zergling";"Larva";194;1
"Unit";"Zergling";"Larva";194;1
"Unit";"Zergling";"Larva";194;1
"Unit";"Zergling";"Larva";194;1
"Unit";"Zergling";"Larva";194;1
"Unit";"Zergling";"Larva";194;1
"Unit";"Zergling";"Larva";194;1
"Unit";"Zergling";"Larva";194;1
"Unit";"Zergling";"Larva";194;1
"Unit";"Zergling";"Larva";194;1
"Unit";"Zergling";"Larva";194;1
"Unit";"Zergling";"Larva";194;1
"Unit";"Zergling";"Larva";194;1
"Unit";"Zergling";"Larva";194;1
"Unit";"Zergling";"Larva";194;1
"Unit";"Zergling";"Larva";194;1
"Unit";"Zergling";"Larva";194;1
"Unit";"Zergling";"Larva";194;1
"Unit";"Zergling";"Larva";194;1
"Unit";"Zergling";"Larva";194;1
"Unit";"Zergling";"Larva";194;1
"Unit";"Zergling";"Larva";194;1
"Unit";"Zergling";"Larva";197;1
"Unit";"Zergling";"Larva";197;1
"Unit";"Zergling";"Larva";197;1
"Unit";"Zergling";"Larva";197;1
"Unit";"Zergling";"Larva";197;1
"Unit";"Zergling";"Larva";197;1
"Unit";"Zergling";"Larva";197;1
"Unit";"Zergling";"Larva";197;1
"Unit";"Zergling";"Larva";197;1
"Unit";"Zergling";"Larva";197;1
"Unit";"Zergling";"Larva";197;1
"Unit";"Zergling";"Larva";197;1
"Building";"CreepTumor";NA;197;0
"Building";"CreepTumor";NA;197;0
"Building";"CreepTumor";NA;197;0
"Unit";"Zergling";"Larva";197;1
"Unit";"Zergling";"Larva";197;1
"Unit";"Zergling";"Larva";197;1
"Unit";"Zergling";"Larva";197;1
"Building";"CreepTumor";NA;197;0
"Building";"CreepTumor";NA;197;0
"Unit";"Queen";"Hatchery";194;2
"Building";"CreepTumor";NA;253;0
"Building";"SporeCrawler";NA;235;0
"Unit";"Baneling";"Zergling";253;0
"Unit";"Baneling";"Zergling";253;0
"Unit";"Baneling";"Zergling";253;0
"Unit";"Baneling";"Zergling";253;0
"Unit";"Baneling";"Zergling";253;0
"Unit";"Baneling";"Zergling";253;0
"Unit";"Baneling";"Zergling";253;0
"Unit";"Baneling";"Zergling";253;0
"Unit";"Baneling";"Zergling";253;0
"Unit";"Baneling";"Zergling";253;0
"Unit";"Baneling";"Zergling";253;0
"Unit";"Baneling";"Zergling";253;0
"Unit";"Baneling";"Zergling";253;0
"Unit";"Baneling";"Zergling";253;0
"Unit";"Baneling";"Zergling";253;0
"Unit";"Baneling";"Zergling";253;0
"Unit";"Zergling";"Larva";254;1
"Unit";"Zergling";"Larva";254;1
"Unit";"Zergling";"Larva";261;1
"Unit";"Zergling";"Larva";261;1
"Unit";"Zergling";"Larva";262;1
"Unit";"Zergling";"Larva";262;1
"Unit";"Zergling";"Larva";262;1
"Unit";"Zergling";"Larva";262;1
"Unit";"Zergling";"Larva";262;1
"Unit";"Zergling";"Larva";262;1
"Unit";"Zergling";"Larva";262;1
"Unit";"Zergling";"Larva";262;1
"Unit";"Zergling";"Larva";262;1
"Unit";"Zergling";"Larva";262;1
"Unit";"Zergling";"Larva";262;1
"Unit";"Zergling";"Larva";262;1
"Building";"HydraliskDen";NA;251;0
"Building";"CreepTumor";NA;262;0
"Unit";"Zergling";"Larva";262;1
"Unit";"Zergling";"Larva";262;1
"Unit";"Zergling";"Larva";262;1
"Unit";"Zergling";"Larva";262;1
"Unit";"Zergling";"Larva";262;1
"Unit";"Zergling";"Larva";262;1
"Unit";"Zergling";"Larva";262;1
"Unit";"Zergling";"Larva";262;1
"Building";"CreepTumorQueen";NA;262;0
"Unit";"Zergling";"Larva";262;1
"Unit";"Zergling";"Larva";262;1
"Building";"CreepTumor";NA;262;0
"Building";"CreepTumorQueen";NA;262;0
"Building";"CreepTumor";NA;262;0
"Unit";"Baneling";"Zergling";278;0
"Unit";"Baneling";"Zergling";278;0
"Unit";"Baneling";"Zergling";278;0
"Unit";"Baneling";"Zergling";278;0
"Unit";"Baneling";"Zergling";278;0
"Unit";"Baneling";"Zergling";278;0
"Unit";"Baneling";"Zergling";278;0
"Unit";"Baneling";"Zergling";278;0
"Unit";"Baneling";"Zergling";278;0
"Unit";"Baneling";"Zergling";278;0
"Unit";"Baneling";"Zergling";278;0
"Unit";"Baneling";"Zergling";278;0
"Unit";"Baneling";"Zergling";278;0
"Unit";"Baneling";"Zergling";278;0
"Unit";"Baneling";"Zergling";278;0
"Unit";"Baneling";"Zergling";278;0
"Unit";"Baneling";"Zergling";278;0
"Unit";"Baneling";"Zergling";278;0
"Unit";"Baneling";"Zergling";278;0
"Building";"CreepTumor";NA;288;0
"Unit";"Baneling";"Zergling";288;0
"Unit";"Baneling";"Zergling";288;0
"Unit";"Baneling";"Zergling";288;0
"Unit";"Overlord";"Larva";288;0
"Unit";"Baneling";"Zergling";288;0
"Unit";"Baneling";"Zergling";288;0
"Unit";"Baneling";"Zergling";288;0
"Unit";"Baneling";"Zergling";288;0
"Unit";"Baneling";"Zergling";288;0
"Unit";"Overlord";"Larva";288;0
"Unit";"Baneling";"Zergling";288;0
"Unit";"Baneling";"Zergling";288;0
"Unit";"Overlord";"Larva";288;0
"Unit";"Overlord";"Larva";288;0
"Unit";"Overlord";"Larva";288;0
"Unit";"Zergling";"Larva";288;1
"Unit";"Zergling";"Larva";288;1
"Unit";"Zergling";"Larva";288;1
"Unit";"Zergling";"Larva";288;1
"Unit";"Zergling";"Larva";288;1
"Unit";"Zergling";"Larva";288;1
"Unit";"Zergling";"Larva";288;1
"Unit";"Zergling";"Larva";288;1
"Unit";"Zergling";"Larva";288;1
"Unit";"Zergling";"Larva";288;1
"Unit";"Zergling";"Larva";288;1
"Unit";"Zergling";"Larva";288;1
"Unit";"Zergling";"Larva";288;1
"Unit";"Zergling";"Larva";288;1
"Unit";"Zergling";"Larva";288;1
"Unit";"Zergling";"Larva";288;1
"Building";"Hatchery";NA;253;0
"Unit";"Zergling";"Larva";288;1
"Unit";"Zergling";"Larva";288;1
"Unit";"Zergling";"Larva";288;1
"Unit";"Zergling";"Larva";288;1
"Unit";"Zergling";"Larva";288;1
"Unit";"Zergling";"Larva";288;1
"Unit";"Zergling";"Larva";288;1
"Unit";"Zergling";"Larva";288;1
"Unit";"Zergling";"Larva";288;1
"Unit";"Zergling";"Larva";288;1
"Unit";"Zergling";"Larva";288;1
"Unit";"Zergling";"Larva";288;1
"Unit";"Zergling";"Larva";288;1
"Unit";"Zergling";"Larva";288;1
"Unit";"Zergling";"Larva";288;1
"Unit";"Zergling";"Larva";288;1
"Unit";"Zergling";"Larva";288;1
"Unit";"Zergling";"Larva";288;1
"Unit";"Zergling";"Larva";288;1
"Unit";"Zergling";"Larva";288;1
"Unit";"Zergling";"Larva";288;1
"Unit";"Zergling";"Larva";288;1
"Unit";"Zergling";"Larva";288;1
"Unit";"Zergling";"Larva";288;1
"Unit";"Zergling";"Larva";288;1
"Unit";"Zergling";"Larva";288;1
"Unit";"Zergling";"Larva";288;1
"Unit";"Zergling";"Larva";288;1
"Unit";"Zergling";"Larva";288;1
"Unit";"Zergling";"Larva";288;1
"Unit";"Zergling";"Larva";288;1
"Unit";"Zergling";"Larva";288;1
"Unit";"Zergling";"Larva";302;1
"Unit";"Zergling";"Larva";302;1
"Unit";"Zergling";"Larva";302;1
"Unit";"Zergling";"Larva";302;1
"Unit";"Zergling";"Larva";302;1
"Unit";"Zergling";"Larva";302;1
"Unit";"Zergling";"Larva";302;1
"Unit";"Zergling";"Larva";302;1
"Unit";"Zergling";"Larva";302;1
"Unit";"Zergling";"Larva";302;1
"Unit";"Zergling";"Larva";302;1
"Unit";"Zergling";"Larva";302;1
"Unit";"Zergling";"Larva";302;1
"Unit";"Zergling";"Larva";302;1
"Unit";"Zergling";"Larva";308;1
"Unit";"Zergling";"Larva";308;1
"Unit";"Zergling";"Larva";328;1
"Unit";"Zergling";"Larva";328;1
"Unit";"Zergling";"Larva";330;1
"Unit";"Zergling";"Larva";330;1
"Unit";"Zergling";"Larva";330;1
"Unit";"Zergling";"Larva";330;1
"Building";"CreepTumor";NA;336;0
"Building";"CreepTumor";NA;336;0
"Unit";"Zergling";"Larva";336;1
"Unit";"Zergling";"Larva";336;1
"Unit";"Zergling";"Larva";336;1
"Unit";"Zergling";"Larva";336;1
"Building";"CreepTumorQueen";NA;350;0
"Building";"CreepTumorQueen";NA;350;0
"Unit";"Zergling";"Larva";350;1
"Unit";"Zergling";"Larva";350;1
"Unit";"Zergling";"Larva";350;1
"Unit";"Zergling";"Larva";350;1
"Unit";"Zergling";"Larva";350;1
"Unit";"Zergling";"Larva";350;1
"Unit";"Zergling";"Larva";350;1
"Unit";"Zergling";"Larva";350;1
"Unit";"Zergling";"Larva";350;1
"Unit";"Zergling";"Larva";350;1
"Unit";"Zergling";"Larva";350;1
"Unit";"Zergling";"Larva";350;1
"Unit";"Zergling";"Larva";350;1
"Unit";"Zergling";"Larva";350;1
"Unit";"Zergling";"Larva";350;1
"Unit";"Zergling";"Larva";350;1
"Unit";"Zergling";"Larva";350;1
"Unit";"Zergling";"Larva";350;1
"Unit";"Zergling";"Larva";350;1
"Unit";"Zergling";"Larva";350;1
"Unit";"Zergling";"Larva";350;1
"Unit";"Zergling";"Larva";350;1
"Unit";"Zergling";"Larva";350;1
"Unit";"Zergling";"Larva";350;1
"Building";"CreepTumorQueen";NA;358;0
"Building";"CreepTumorQueen";NA;362;0
"Unit";"Zergling";"Larva";350;1
"Unit";"Zergling";"Larva";350;1
"Unit";"Zergling";"Larva";350;1
"Unit";"Zergling";"Larva";350;1
"Unit";"Zergling";"Larva";350;1
"Unit";"Zergling";"Larva";350;1
"Unit";"Zergling";"Larva";350;1
"Unit";"Zergling";"Larva";350;1
"Unit";"Zergling";"Larva";352;1
"Unit";"Zergling";"Larva";352;1
"Unit";"Zergling";"Larva";352;1
"Unit";"Zergling";"Larva";352;1
"Upgrade";"ZergMeleeWeaponsLevel2";"EvolutionChamber";262;0
"Upgrade";"ZergGroundArmorsLevel2";"EvolutionChamber";262;0
"Unit";"Zergling";"Larva";362;1
"Unit";"Zergling";"Larva";362;1
"Unit";"Zergling";"Larva";362;1
"Unit";"Zergling";"Larva";362;1
"Unit";"Zergling";"Larva";362;1
"Unit";"Zergling";"Larva";362;1
"Unit";"Zergling";"Larva";362;1
"Unit";"Zergling";"Larva";362;1
"Unit";"Zergling";"Larva";362;1
"Unit";"Zergling";"Larva";362;1
"Unit";"Zergling";"Larva";362;1
"Unit";"Zergling";"Larva";362;1
"Unit";"Zergling";"Larva";386;1
"Unit";"Zergling";"Larva";386;1
"Building";"CreepTumor";NA;398;0
"Unit";"Zergling";"Larva";394;1
"Unit";"Zergling";"Larva";394;1
"Unit";"Zergling";"Larva";394;1
"Unit";"Zergling";"Larva";394;1
"Unit";"Zergling";"Larva";398;1
"Unit";"Zergling";"Larva";398;1
"Unit";"Zergling";"Larva";398;1
"Unit";"Zergling";"Larva";398;1
"Unit";"Zergling";"Larva";398;1
"Unit";"Zergling";"Larva";398;1
"Unit";"Zergling";"Larva";398;1
"Unit";"Zergling";"Larva";398;1
"Unit";"Zergling";"Larva";398;1
"Unit";"Zergling";"Larva";398;1
"Unit";"Zergling";"Larva";398;1
"Unit";"Zergling";"Larva";398;1
"Unit";"Zergling";"Larva";398;1
"Unit";"Zergling";"Larva";398;1
"Unit";"Zergling";"Larva";398;1
"Unit";"Zergling";"Larva";398;1
"Unit";"Baneling";"Zergling";398;0
"Unit";"Baneling";"Zergling";398;0
"Unit";"Baneling";"Zergling";398;0
"Unit";"Baneling";"Zergling";398;0
"Unit";"Baneling";"Zergling";398;0
"Unit";"Baneling";"Zergling";398;0
"Unit";"Baneling";"Zergling";398;0
"Unit";"Baneling";"Zergling";398;0
"Unit";"Baneling";"Zergling";398;0
"Unit";"Baneling";"Zergling";398;0
"Unit";"Zergling";"Larva";398;1
"Unit";"Zergling";"Larva";398;1
"Unit";"Baneling";"Zergling";398;0
"Building";"CreepTumor";NA;410;0
"Unit";"Baneling";"Zergling";398;0
"Unit";"Baneling";"Zergling";398;0
"Unit";"Baneling";"Zergling";398;0
"Unit";"Zergling";"Larva";410;1
"Unit";"Zergling";"Larva";410;1
"Unit";"Zergling";"Larva";410;1
"Unit";"Zergling";"Larva";410;1
"Unit";"Zergling";"Larva";410;1
"Unit";"Zergling";"Larva";410;1
"Unit";"Baneling";"Zergling";416;0
"Unit";"Baneling";"Zergling";416;0
"Unit";"Baneling";"Zergling";416;0
"Unit";"Baneling";"Zergling";416;0
"Unit";"Baneling";"Zergling";416;0
"Unit";"Baneling";"Zergling";416;0
"Unit";"Queen";"Hatchery";394;2
"Unit";"Zergling";"Larva";418;1
"Unit";"Zergling";"Larva";418;1
"Unit";"Zergling";"Larva";422;1
"Unit";"Zergling";"Larva";422;1
"Unit";"Zergling";"Larva";424;1
"Unit";"Zergling";"Larva";424;1
"Unit";"Zergling";"Larva";424;1
"Unit";"Zergling";"Larva";424;1
"Unit";"Zergling";"Larva";424;1
"Unit";"Zergling";"Larva";424;1
"Upgrade";"EvolveMuscularAugments";"HydraliskDen";362;0
"Unit";"Hydralisk";"Larva";434;2
"Unit";"Hydralisk";"Larva";434;2
"Unit";"Hydralisk";"Larva";434;2
"Unit";"Hydralisk";"Larva";434;2
"Unit";"Hydralisk";"Larva";440;2
"Unit";"Hydralisk";"Larva";442;2
"Unit";"Hydralisk";"Larva";442;2
"Unit";"Hydralisk";"Larva";466;2
"Unit";"Hydralisk";"Larva";466;2
"Unit";"Hydralisk";"Larva";466;2
"Unit";"Hydralisk";"Larva";466;2
"Unit";"Hydralisk";"Larva";466;2
"Unit";"Hydralisk";"Larva";466;2
"Unit";"Hydralisk";"Larva";466;2
"Unit";"Hydralisk";"Larva";466;2
"Unit";"Hydralisk";"Larva";466;2
"Unit";"Hydralisk";"Larva";466;2
"Unit";"Zergling";"Larva";466;1
"Unit";"Zergling";"Larva";466;1
"Unit";"Queen";"Hatchery";452;2
"Unit";"Zergling";"Larva";466;1
"Unit";"Zergling";"Larva";466;1
"Unit";"Zergling";"Larva";466;1
"Unit";"Zergling";"Larva";466;1
"Unit";"Queen";"Hatchery";454;2
"Unit";"Zergling";"Larva";466;1
"Unit";"Zergling";"Larva";466;1
"Unit";"Zergling";"Larva";466;1
"Unit";"Zergling";"Larva";466;1
"Unit";"Zergling";"Larva";466;1
"Unit";"Zergling";"Larva";466;1
"Unit";"Zergling";"Larva";466;1
"Unit";"Zergling";"Larva";466;1
"Unit";"Zergling";"Larva";466;1
"Unit";"Zergling";"Larva";466;1
"Upgrade";"EvolveGroovedSpines";"HydraliskDen";466;0
"Unit";"Baneling";"Zergling";506;0
"Unit";"Baneling";"Zergling";506;0
"Unit";"Baneling";"Zergling";506;0
"Unit";"Baneling";"Zergling";506;0
"Unit";"Baneling";"Zergling";506;0
"Unit";"Baneling";"Zergling";506;0
"Unit";"Baneling";"Zergling";506;0
"Unit";"Baneling";"Zergling";506;0
"Unit";"Baneling";"Zergling";506;0
"Unit";"Baneling";"Zergling";506;0
"Unit";"Baneling";"Zergling";506;0
"Unit";"Zergling";"Larva";506;1
"Unit";"Zergling";"Larva";506;1
"Building";"CreepTumor";NA;506;0
"Unit";"Zergling";"Larva";506;1
"Unit";"Zergling";"Larva";506;1
"Unit";"Zergling";"Larva";506;1
"Unit";"Zergling";"Larva";506;1
"Unit";"Zergling";"Larva";506;1
"Unit";"Zergling";"Larva";506;1
"Unit";"Zergling";"Larva";506;1
"Unit";"Zergling";"Larva";506;1
"Unit";"Zergling";"Larva";506;1
"Unit";"Zergling";"Larva";506;1
"Unit";"Zergling";"Larva";506;1
"Unit";"Zergling";"Larva";506;1
"Unit";"Zergling";"Larva";506;1
"Unit";"Zergling";"Larva";506;1
"Unit";"Zergling";"Larva";506;1
"Unit";"Zergling";"Larva";506;1
"Building";"CreepTumorQueen";NA;506;0
"Building";"CreepTumorQueen";NA;506;0
"Unit";"Zergling";"Larva";506;1
"Unit";"Zergling";"Larva";506;1
"Unit";"Zergling";"Larva";506;1
"Unit";"Zergling";"Larva";506;1
"Unit";"Zergling";"Larva";506;1
"Unit";"Zergling";"Larva";506;1
"Unit";"Zergling";"Larva";506;1
"Unit";"Zergling";"Larva";506;1
"Unit";"Zergling";"Larva";506;1
"Unit";"Zergling";"Larva";506;1
"Unit";"Zergling";"Larva";506;1
"Unit";"Zergling";"Larva";506;1
"Building";"CreepTumor";NA;506;0
"Unit";"Zergling";"Larva";506;1
"Unit";"Zergling";"Larva";506;1
"Unit";"Zergling";"Larva";506;1
"Unit";"Zergling";"Larva";506;1
"Unit";"Zergling";"Larva";506;1
"Unit";"Zergling";"Larva";506;1
"Unit";"Zergling";"Larva";506;1
"Unit";"Zergling";"Larva";506;1
"Unit";"Zergling";"Larva";506;1
"Unit";"Zergling";"Larva";506;1
"Unit";"Zergling";"Larva";506;1
"Unit";"Zergling";"Larva";506;1
"Unit";"Zergling";"Larva";536;1
"Unit";"Zergling";"Larva";536;1
"Unit";"Zergling";"Larva";536;1
"Unit";"Zergling";"Larva";536;1
"Unit";"Zergling";"Larva";536;1
"Unit";"Zergling";"Larva";536;1
"Unit";"Zergling";"Larva";536;1
"Unit";"Zergling";"Larva";536;1
"Unit";"Zergling";"Larva";536;1
"Unit";"Zergling";"Larva";536;1
"Unit";"Zergling";"Larva";536;1
"Unit";"Zergling";"Larva";536;1
"Unit";"Zergling";"Larva";538;1
"Unit";"Zergling";"Larva";538;1
"Unit";"Zergling";"Larva";538;1
"Unit";"Zergling";"Larva";538;1
"Unit";"Zergling";"Larva";538;1
"Unit";"Zergling";"Larva";538;1
"Unit";"Zergling";"Larva";538;1
"Unit";"Zergling";"Larva";538;1
"Unit";"Zergling";"Larva";538;1
"Unit";"Zergling";"Larva";538;1
"Unit";"Zergling";"Larva";538;1
"Unit";"Zergling";"Larva";538;1
"Unit";"Zergling";"Larva";538;1
"Unit";"Zergling";"Larva";538;1
"Unit";"Zergling";"Larva";538;1
"Unit";"Zergling";"Larva";538;1
"Unit";"Zergling";"Larva";538;1
"Unit";"Zergling";"Larva";538;1
