"type";"unit_name";"on_building";"total_supply";"supply"
"Unit";"Overlord";"Larva";12;0
"Building";"Extractor";NA;18;0
"Unit";"Overlord";"Larva";21;0
"Building";"SpawningPool";NA;19;0
"Building";"Hatchery";NA;17;0
"Unit";"Zergling";"Larva";22;1
"Unit";"Zergling";"Larva";22;1
"Unit";"Zergling";"Larva";22;1
"Unit";"Zergling";"Larva";22;1
"Unit";"Queen";"Hatchery";22;2
"Unit";"Queen";"Hatchery";22;2
"Unit";"Overlord";"Larva";35;0
"Building";"CreepTumorQueen";NA;38;0
"Unit";"Overlord";"Larva";38;0
"Unit";"Queen";"Hatchery";38;2
"Building";"Hatchery";NA;32;0
"Unit";"Overlord";"Larva";40;0
"Building";"CreepTumor";NA;47;0
"Building";"EvolutionChamber";NA;47;0
"Building";"EvolutionChamber";NA;49;0
"Building";"CreepTumorQueen";NA;55;0
"Building";"CreepTumor";NA;55;0
"Building";"CreepTumorQueen";NA;59;0
"Building";"CreepTumorQueen";NA;59;0
"Unit";"Queen";"Hatchery";55;2
"Unit";"Queen";"Hatchery";55;2
"Unit";"Zergling";"Larva";59;1
"Unit";"Zergling";"Larva";59;1
"Unit";"Zergling";"Larva";59;1
"Unit";"Zergling";"Larva";59;1
"Unit";"Zergling";"Larva";59;1
"Unit";"Zergling";"Larva";59;1
"Unit";"Overlord";"Larva";59;0
"Unit";"Overlord";"Larva";59;0
"Unit";"Queen";"Hatchery";59;2
"Unit";"Zergling";"Larva";69;1
"Unit";"Zergling";"Larva";69;1
"Unit";"Zergling";"Larva";69;1
"Unit";"Zergling";"Larva";69;1
"Unit";"Zergling";"Larva";69;1
"Unit";"Zergling";"Larva";69;1
"Unit";"Zergling";"Larva";69;1
"Unit";"Zergling";"Larva";69;1
"Unit";"Zergling";"Larva";69;1
"Unit";"Zergling";"Larva";69;1
"Building";"CreepTumorQueen";NA;71;0
"Building";"CreepTumorQueen";NA;71;0
"Building";"CreepTumor";NA;71;0
"Building";"CreepTumor";NA;75;0
"Building";"CreepTumor";NA;75;0
"Building";"CreepTumorQueen";NA;86;0
"Building";"CreepTumorQueen";NA;88;0
"Building";"Extractor";NA;88;0
"Building";"Extractor";NA;88;0
"Building";"CreepTumorQueen";NA;91;0
"Building";"SporeCrawler";NA;91;0
"Building";"SporeCrawler";NA;91;0
"Building";"SporeCrawler";NA;91;0
"Building";"CreepTumor";NA;95;0
"Building";"BanelingNest";NA;88;0
"Building";"CreepTumor";NA;100;0
"Building";"CreepTumorQueen";NA;100;0
"Building";"CreepTumor";NA;100;0
"Building";"CreepTumor";NA;100;0
"Building";"CreepTumor";NA;101;0
"Upgrade";"ZergMeleeWeaponsLevel1";"EvolutionChamber";69;0
"Upgrade";"ZergGroundArmorsLevel1";"EvolutionChamber";71;0
"Building";"CreepTumor";NA;108;0
"Building";"CreepTumor";NA;108;0
"Building";"CreepTumor";NA;108;0
"Building";"CreepTumor";NA;108;0
"Unit";"Overlord";"Larva";108;0
"Unit";"Overlord";"Larva";108;0
"Unit";"Overlord";"Larva";108;0
"Unit";"Overlord";"Larva";108;0
"Unit";"Overlord";"Larva";108;0
"Building";"CreepTumor";NA;110;0
"Building";"CreepTumor";NA;110;0
"Building";"CreepTumorQueen";NA;111;0
"Building";"Extractor";NA;108;0
"Building";"CreepTumorQueen";NA;111;0
"Building";"CreepTumor";NA;113;0
"Building";"CreepTumor";NA;114;0
"Unit";"Zergling";"Larva";113;1
"Unit";"Zergling";"Larva";113;1
"Building";"CreepTumor";NA;121;0
"Unit";"Zergling";"Larva";113;1
"Unit";"Zergling";"Larva";113;1
"Unit";"Zergling";"Larva";113;1
"Unit";"Zergling";"Larva";113;1
"Unit";"Zergling";"Larva";113;1
"Unit";"Zergling";"Larva";113;1
"Building";"InfestationPit";NA;111;0
"Building";"CreepTumor";NA;124;0
"Building";"CreepTumor";NA;124;0
"Building";"CreepTumorQueen";NA;124;0
"Building";"CreepTumorQueen";NA;124;0
"Building";"CreepTumor";NA;124;0
"Building";"CreepTumor";NA;124;0
"Building";"CreepTumor";NA;124;0
"Unit";"Zergling";"Larva";121;1
"Unit";"Zergling";"Larva";121;1
"Building";"CreepTumorQueen";NA;124;0
"Building";"CreepTumor";NA;124;0
"Unit";"Zergling";"Larva";124;1
"Unit";"Zergling";"Larva";124;1
"Unit";"Zergling";"Larva";124;1
"Unit";"Zergling";"Larva";124;1
"Unit";"Zergling";"Larva";124;1
"Unit";"Zergling";"Larva";124;1
"Unit";"Zergling";"Larva";124;1
"Unit";"Zergling";"Larva";124;1
"Unit";"Zergling";"Larva";124;1
"Unit";"Zergling";"Larva";124;1
"Building";"CreepTumorQueen";NA;134;0
"Unit";"Zergling";"Larva";132;1
"Unit";"Zergling";"Larva";132;1
"Building";"Extractor";NA;124;0
"Building";"CreepTumorQueen";NA;134;0
"Unit";"Zergling";"Larva";144;1
"Unit";"Zergling";"Larva";144;1
"Unit";"Zergling";"Larva";144;1
"Unit";"Zergling";"Larva";144;1
"Unit";"Zergling";"Larva";144;1
"Unit";"Zergling";"Larva";144;1
"Unit";"Zergling";"Larva";144;1
"Unit";"Zergling";"Larva";144;1
"Unit";"Zergling";"Larva";144;1
"Unit";"Zergling";"Larva";144;1
"Unit";"Zergling";"Larva";144;1
"Unit";"Zergling";"Larva";144;1
"Building";"CreepTumor";NA;158;0
"Building";"CreepTumor";NA;158;0
"Unit";"Zergling";"Larva";158;1
"Unit";"Zergling";"Larva";158;1
"Unit";"Zergling";"Larva";158;1
"Unit";"Zergling";"Larva";158;1
"Unit";"Zergling";"Larva";158;1
"Unit";"Zergling";"Larva";158;1
"Unit";"Zergling";"Larva";158;1
"Unit";"Zergling";"Larva";158;1
"Unit";"Zergling";"Larva";158;1
"Unit";"Zergling";"Larva";158;1
"Unit";"Zergling";"Larva";158;1
"Unit";"Zergling";"Larva";158;1
"Unit";"Zergling";"Larva";158;1
"Unit";"Zergling";"Larva";158;1
"Unit";"Zergling";"Larva";158;1
"Unit";"Zergling";"Larva";158;1
"Building";"CreepTumor";NA;158;0
"Building";"CreepTumor";NA;158;0
"Building";"CreepTumor";NA;158;0
"Building";"CreepTumor";NA;158;0
"Building";"CreepTumorQueen";NA;158;0
"Building";"CreepTumorQueen";NA;158;0
"Building";"CreepTumor";NA;158;0
"Building";"CreepTumor";NA;158;0
"Building";"CreepTumorQueen";NA;158;0
"Building";"CreepTumorQueen";NA;158;0
"Building";"Hatchery";NA;124;0
"Building";"CreepTumorQueen";NA;180;0
"Unit";"Zergling";"Larva";174;1
"Unit";"Zergling";"Larva";174;1
"Unit";"Zergling";"Larva";174;1
"Unit";"Zergling";"Larva";174;1
"Unit";"Zergling";"Larva";174;1
"Unit";"Zergling";"Larva";174;1
"Unit";"Zergling";"Larva";174;1
"Unit";"Zergling";"Larva";174;1
"Unit";"Zergling";"Larva";180;1
"Unit";"Zergling";"Larva";180;1
"Unit";"Zergling";"Larva";180;1
"Unit";"Zergling";"Larva";180;1
"Unit";"Zergling";"Larva";180;1
"Unit";"Zergling";"Larva";180;1
"Unit";"Zergling";"Larva";180;1
"Unit";"Zergling";"Larva";180;1
"Unit";"Zergling";"Larva";180;1
"Unit";"Zergling";"Larva";180;1
"Unit";"Zergling";"Larva";180;1
"Unit";"Zergling";"Larva";180;1
"Unit";"Zergling";"Larva";180;1
"Unit";"Zergling";"Larva";180;1
"Building";"CreepTumor";NA;188;0
"Building";"CreepTumor";NA;202;0
"Building";"CreepTumor";NA;202;0
"Building";"CreepTumor";NA;202;0
"Building";"CreepTumor";NA;202;0
"Unit";"Overlord";"Larva";188;0
"Building";"CreepTumor";NA;202;0
"Building";"CreepTumor";NA;202;0
"Building";"CreepTumor";NA;202;0
"Unit";"Queen";"Hatchery";188;2
"Unit";"Queen";"Hatchery";188;2
"Unit";"Queen";"Hatchery";188;2
"Building";"CreepTumor";NA;202;0
"Building";"CreepTumor";NA;202;0
"Unit";"Overlord";"Larva";202;0
"Unit";"Overlord";"Larva";202;0
"Unit";"Overlord";"Larva";202;0
"Unit";"Overlord";"Larva";202;0
"Unit";"Overlord";"Larva";202;0
"Building";"CreepTumor";NA;202;0
"Building";"CreepTumor";NA;202;0
"Building";"CreepTumor";NA;202;0
"Building";"CreepTumor";NA;204;0
"Building";"CreepTumor";NA;204;0
"Building";"CreepTumor";NA;204;0
"Building";"Extractor";NA;202;0
"Building";"Hatchery";NA;180;0
"Unit";"Baneling";"Zergling";208;0
"Unit";"Baneling";"Zergling";208;0
"Unit";"Baneling";"Zergling";208;0
"Unit";"Baneling";"Zergling";208;0
"Unit";"Baneling";"Zergling";208;0
"Unit";"Baneling";"Zergling";208;0
"Unit";"Baneling";"Zergling";208;0
"Unit";"Baneling";"Zergling";208;0
"Unit";"Baneling";"Zergling";208;0
"Unit";"Baneling";"Zergling";208;0
"Unit";"Baneling";"Zergling";208;0
"Unit";"Baneling";"Zergling";208;0
"Unit";"Baneling";"Zergling";208;0
"Unit";"Baneling";"Zergling";208;0
"Unit";"Baneling";"Zergling";208;0
"Unit";"Baneling";"Zergling";208;0
"Unit";"Baneling";"Zergling";208;0
"Unit";"Baneling";"Zergling";208;0
"Upgrade";"ZergMeleeWeaponsLevel2";"EvolutionChamber";158;0
"Upgrade";"ZergGroundArmorsLevel2";"EvolutionChamber";158;0
"Unit";"Overlord";"Larva";208;0
"Unit";"Queen";"Hatchery";202;2
"Unit";"Zergling";"Larva";208;1
"Unit";"Zergling";"Larva";208;1
"Unit";"Zergling";"Larva";208;1
"Unit";"Zergling";"Larva";208;1
"Unit";"Zergling";"Larva";208;1
"Unit";"Zergling";"Larva";208;1
"Unit";"Zergling";"Larva";208;1
"Unit";"Zergling";"Larva";208;1
"Unit";"Zergling";"Larva";208;1
"Unit";"Zergling";"Larva";208;1
"Unit";"Zergling";"Larva";208;1
"Unit";"Zergling";"Larva";208;1
"Unit";"Zergling";"Larva";208;1
"Unit";"Zergling";"Larva";208;1
"Unit";"Zergling";"Larva";208;1
"Unit";"Zergling";"Larva";208;1
"Unit";"Zergling";"Larva";208;1
"Unit";"Zergling";"Larva";208;1
"Unit";"Zergling";"Larva";208;1
"Unit";"Zergling";"Larva";208;1
"Unit";"Zergling";"Larva";208;1
"Unit";"Zergling";"Larva";208;1
"Unit";"Queen";"Hatchery";204;2
"Building";"CreepTumorQueen";NA;211;0
"Building";"CreepTumorQueen";NA;211;0
"Unit";"Zergling";"Larva";213;1
"Unit";"Zergling";"Larva";213;1
"Unit";"Zergling";"Larva";213;1
"Unit";"Zergling";"Larva";213;1
"Unit";"Zergling";"Larva";213;1
"Unit";"Zergling";"Larva";213;1
"Unit";"Zergling";"Larva";213;1
"Unit";"Zergling";"Larva";213;1
"Unit";"Zergling";"Larva";213;1
"Unit";"Zergling";"Larva";213;1
"Building";"CreepTumor";NA;239;0
"Building";"CreepTumor";NA;239;0
"Upgrade";"Burrow";"Hatchery";208;0
"Building";"CreepTumor";NA;249;0
"Building";"CreepTumor";NA;249;0
"Building";"CreepTumor";NA;249;0
"Unit";"Baneling";"Zergling";249;0
"Unit";"Baneling";"Zergling";249;0
"Unit";"Baneling";"Zergling";249;0
"Unit";"Baneling";"Zergling";249;0
"Unit";"Baneling";"Zergling";249;0
"Building";"CreepTumor";NA;249;0
"Unit";"Zergling";"Larva";249;1
"Unit";"Zergling";"Larva";249;1
"Unit";"Zergling";"Larva";249;1
"Unit";"Zergling";"Larva";249;1
"Unit";"Zergling";"Larva";249;1
"Unit";"Zergling";"Larva";249;1
"Unit";"Zergling";"Larva";249;1
"Unit";"Zergling";"Larva";249;1
"Unit";"Zergling";"Larva";249;1
"Unit";"Zergling";"Larva";249;1
"Unit";"Zergling";"Larva";249;1
"Unit";"Zergling";"Larva";249;1
"Unit";"Zergling";"Larva";249;1
"Unit";"Zergling";"Larva";249;1
"Unit";"Zergling";"Larva";249;1
"Unit";"Zergling";"Larva";249;1
"Unit";"Zergling";"Larva";249;1
"Unit";"Zergling";"Larva";249;1
"Unit";"Zergling";"Larva";249;1
"Unit";"Zergling";"Larva";249;1
"Unit";"Zergling";"Larva";249;1
"Unit";"Zergling";"Larva";249;1
"Unit";"Zergling";"Larva";249;1
"Unit";"Zergling";"Larva";249;1
"Unit";"Zergling";"Larva";249;1
"Unit";"Zergling";"Larva";249;1
"Building";"CreepTumor";NA;249;0
"Building";"CreepTumor";NA;249;0
"Building";"CreepTumor";NA;249;0
"Building";"Extractor";NA;249;0
"Building";"CreepTumor";NA;252;0
"Building";"CreepTumor";NA;252;0
"Building";"Extractor";NA;249;0
"Building";"CreepTumor";NA;252;0
"Building";"CreepTumor";NA;252;0
"Building";"UltraliskCavern";NA;239;0
"Unit";"Queen";"Hatchery";249;2
"Unit";"Queen";"Hatchery";249;2
"Unit";"Zergling";"Larva";282;1
"Unit";"Zergling";"Larva";282;1
"Unit";"Overlord";"Larva";282;0
"Unit";"Overlord";"Larva";282;0
"Building";"Spire";NA;249;0
"Unit";"Queen";"Hatchery";282;2
"Unit";"Queen";"Hatchery";282;2
"Unit";"Ultralisk";"Larva";282;6
"Unit";"Ultralisk";"Larva";282;6
"Unit";"Ultralisk";"Larva";282;6
"Unit";"Baneling";"Zergling";284;0
"Unit";"Baneling";"Zergling";284;0
"Unit";"Baneling";"Zergling";284;0
"Unit";"Zergling";"Larva";284;1
"Unit";"Zergling";"Larva";284;1
"Unit";"Zergling";"Larva";284;1
"Unit";"Zergling";"Larva";284;1
"Unit";"Zergling";"Larva";284;1
"Unit";"Zergling";"Larva";284;1
"Unit";"Zergling";"Larva";284;1
"Unit";"Zergling";"Larva";284;1
"Unit";"Zergling";"Larva";284;1
"Unit";"Zergling";"Larva";284;1
"Unit";"Zergling";"Larva";284;1
"Unit";"Zergling";"Larva";284;1
"Unit";"Zergling";"Larva";284;1
"Unit";"Zergling";"Larva";284;1
"Unit";"Zergling";"Larva";286;1
"Unit";"Zergling";"Larva";286;1
"Unit";"Zergling";"Larva";286;1
"Unit";"Zergling";"Larva";286;1
"Unit";"Zergling";"Larva";286;1
"Unit";"Zergling";"Larva";286;1
"Unit";"Zergling";"Larva";286;1
"Unit";"Zergling";"Larva";286;1
"Unit";"Zergling";"Larva";288;1
"Unit";"Zergling";"Larva";288;1
"Unit";"Zergling";"Larva";288;1
"Unit";"Zergling";"Larva";288;1
"Unit";"Zergling";"Larva";288;1
"Unit";"Zergling";"Larva";288;1
"Unit";"Zergling";"Larva";288;1
"Unit";"Zergling";"Larva";288;1
"Unit";"Zergling";"Larva";288;1
"Unit";"Zergling";"Larva";288;1
"Unit";"Zergling";"Larva";288;1
"Unit";"Zergling";"Larva";288;1
"Unit";"Zergling";"Larva";288;1
"Unit";"Zergling";"Larva";288;1
"Unit";"Zergling";"Larva";288;1
"Unit";"Zergling";"Larva";288;1
"Unit";"Zergling";"Larva";288;1
"Unit";"Zergling";"Larva";288;1
"Building";"CreepTumorQueen";NA;346;0
"Building";"CreepTumorQueen";NA;346;0
"Building";"CreepTumorQueen";NA;347;0
"Building";"CreepTumor";NA;347;0
"Building";"CreepTumor";NA;347;0
"Building";"CreepTumorQueen";NA;347;0
"Building";"CreepTumorQueen";NA;347;0
"Building";"CreepTumorQueen";NA;347;0
"Building";"CreepTumorQueen";NA;347;0
"Building";"CreepTumorQueen";NA;347;0
"Building";"CreepTumorQueen";NA;347;0
"Unit";"Baneling";"Zergling";347;0
"Unit";"Baneling";"Zergling";347;0
"Unit";"Baneling";"Zergling";347;0
"Unit";"Overlord";"Larva";347;0
"Unit";"Queen";"Hatchery";288;2
"Unit";"Baneling";"Zergling";347;0
"Unit";"Baneling";"Zergling";347;0
"Unit";"Baneling";"Zergling";347;0
"Unit";"Baneling";"Zergling";347;0
"Unit";"Baneling";"Zergling";347;0
"Unit";"Baneling";"Zergling";347;0
"Unit";"Overlord";"Larva";347;0
"Unit";"Baneling";"Zergling";347;0
"Unit";"Baneling";"Zergling";347;0
"Unit";"Baneling";"Zergling";347;0
"Unit";"Baneling";"Zergling";347;0
"Building";"CreepTumorQueen";NA;347;0
"Unit";"Queen";"Hatchery";306;2
"Building";"CreepTumorQueen";NA;347;0
"Upgrade";"ZergMeleeWeaponsLevel3";"EvolutionChamber";278;0
"Upgrade";"ZergGroundArmorsLevel3";"EvolutionChamber";278;0
"Unit";"Zergling";"Larva";351;1
"Unit";"Zergling";"Larva";351;1
"Unit";"Zergling";"Larva";351;1
"Unit";"Zergling";"Larva";351;1
"Unit";"Zergling";"Larva";351;1
"Unit";"Zergling";"Larva";351;1
"Unit";"Zergling";"Larva";351;1
"Unit";"Zergling";"Larva";351;1
"Unit";"Zergling";"Larva";351;1
"Unit";"Zergling";"Larva";351;1
"Unit";"Zergling";"Larva";351;1
"Unit";"Zergling";"Larva";351;1
"Unit";"Zergling";"Larva";351;1
"Unit";"Zergling";"Larva";351;1
"Unit";"Zergling";"Larva";351;1
"Unit";"Zergling";"Larva";351;1
"Unit";"Zergling";"Larva";351;1
"Unit";"Zergling";"Larva";351;1
"Unit";"Zergling";"Larva";351;1
"Unit";"Zergling";"Larva";351;1
"Unit";"Zergling";"Larva";351;1
"Unit";"Zergling";"Larva";351;1
"Unit";"Zergling";"Larva";351;1
"Unit";"Zergling";"Larva";351;1
"Unit";"Zergling";"Larva";351;1
"Unit";"Zergling";"Larva";351;1
"Unit";"Zergling";"Larva";351;1
"Unit";"Zergling";"Larva";351;1
"Unit";"Zergling";"Larva";351;1
"Unit";"Zergling";"Larva";351;1
"Unit";"Zergling";"Larva";351;1
"Unit";"Zergling";"Larva";351;1
"Unit";"Zergling";"Larva";351;1
"Unit";"Zergling";"Larva";351;1
"Unit";"Zergling";"Larva";351;1
"Unit";"Zergling";"Larva";351;1
"Unit";"Zergling";"Larva";351;1
"Unit";"Zergling";"Larva";351;1
"Unit";"Zergling";"Larva";351;1
"Unit";"Zergling";"Larva";351;1
"Unit";"Zergling";"Larva";351;1
"Unit";"Zergling";"Larva";351;1
"Unit";"Zergling";"Larva";351;1
"Unit";"Zergling";"Larva";351;1
"Unit";"Zergling";"Larva";351;1
"Unit";"Zergling";"Larva";351;1
"Unit";"Zergling";"Larva";351;1
"Unit";"Zergling";"Larva";351;1
"Unit";"Zergling";"Larva";351;1
"Unit";"Zergling";"Larva";351;1
"Unit";"Zergling";"Larva";351;1
"Unit";"Zergling";"Larva";351;1
"Unit";"Zergling";"Larva";351;1
"Unit";"Zergling";"Larva";351;1
