"type";"unit_name";"on_building";"total_supply";"supply"
"Unit";"Overlord";"Larva";12;0
"Building";"SpawningPool";NA;19;0
"Building";"Hatchery";NA;17;0
"Unit";"Zergling";"Larva";24;1
"Unit";"Zergling";"Larva";24;1
"Unit";"Zergling";"Larva";25;1
"Unit";"Zergling";"Larva";25;1
"Unit";"Overlord";"Larva";25;0
"Unit";"Queen";"Hatchery";24;2
"Unit";"Queen";"Hatchery";24;2
"Building";"Extractor";NA;25;0
"Building";"Hatchery";NA;22;0
"Unit";"Overlord";"Larva";37;0
"Unit";"Queen";"Hatchery";34;2
"Unit";"Queen";"Hatchery";35;2
"Unit";"Queen";"Hatchery";37;2
"Building";"CreepTumorQueen";NA;46;0
"Building";"CreepTumorQueen";NA;50;0
"Unit";"Overlord";"Larva";52;0
"Building";"CreepTumor";NA;52;0
"Building";"CreepTumor";NA;52;0
"Unit";"Queen";"Hatchery";50;2
"Building";"Extractor";NA;52;0
"Building";"CreepTumorQueen";NA;54;0
"Building";"CreepTumorQueen";NA;54;0
"Unit";"Overlord";"Larva";54;0
"Building";"CreepTumorQueen";NA;58;0
"Unit";"Overlord";"Larva";58;0
"Unit";"Overlord";"Larva";58;0
"Building";"BanelingNest";NA;53;0
"Building";"CreepTumor";NA;71;0
"Building";"CreepTumor";NA;71;0
"Building";"SporeCrawler";NA;71;0
"Building";"CreepTumor";NA;74;0
"Building";"CreepTumor";NA;74;0
"Building";"SporeCrawler";NA;71;0
"Building";"SporeCrawler";NA;71;0
"Unit";"Zergling";"Larva";75;1
"Unit";"Zergling";"Larva";75;1
"Unit";"Zergling";"Larva";75;1
"Unit";"Zergling";"Larva";75;1
"Unit";"Zergling";"Larva";75;1
"Unit";"Zergling";"Larva";75;1
"Unit";"Baneling";"Zergling";75;0
"Unit";"Baneling";"Zergling";75;0
"Unit";"Baneling";"Zergling";75;0
"Unit";"Overlord";"Larva";80;0
"Unit";"Overlord";"Larva";81;0
"Building";"CreepTumor";NA;88;0
"Building";"CreepTumor";NA;88;0
"Unit";"Overlord";"Larva";88;0
"Building";"EvolutionChamber";NA;82;0
"Building";"EvolutionChamber";NA;82;0
"Building";"CreepTumor";NA;88;0
"Building";"CreepTumorQueen";NA;88;0
"Building";"CreepTumor";NA;88;0
"Building";"Extractor";NA;88;0
"Building";"CreepTumorQueen";NA;88;0
"Building";"CreepTumor";NA;94;0
"Building";"CreepTumorQueen";NA;97;0
"Building";"CreepTumorQueen";NA;100;0
"Building";"Extractor";NA;101;0
"Unit";"Zergling";"Larva";104;1
"Unit";"Zergling";"Larva";104;1
"Unit";"Zergling";"Larva";104;1
"Unit";"Zergling";"Larva";104;1
"Building";"Extractor";NA;104;0
"Building";"Extractor";NA;104;0
"Building";"HydraliskDen";NA;104;0
"Building";"CreepTumor";NA;114;0
"Building";"CreepTumor";NA;114;0
"Building";"CreepTumor";NA;114;0
"Building";"CreepTumor";NA;114;0
"Building";"CreepTumor";NA;114;0
"Building";"CreepTumor";NA;114;0
"Building";"Hatchery";NA;88;0
"Unit";"Overlord";"Larva";114;0
"Unit";"Overlord";"Larva";114;0
"Unit";"Overlord";"Larva";114;0
"Unit";"Overlord";"Larva";114;0
"Unit";"Overlord";"Larva";114;0
"Unit";"Overlord";"Larva";114;0
"Unit";"Overlord";"Larva";114;0
"Unit";"Overlord";"Larva";114;0
"Unit";"Zergling";"Larva";114;1
"Unit";"Zergling";"Larva";114;1
"Unit";"Zergling";"Larva";114;1
"Unit";"Zergling";"Larva";114;1
"Unit";"Zergling";"Larva";114;1
"Unit";"Zergling";"Larva";114;1
"Unit";"Zergling";"Larva";114;1
"Unit";"Zergling";"Larva";114;1
"Unit";"Zergling";"Larva";114;1
"Unit";"Zergling";"Larva";114;1
"Unit";"Zergling";"Larva";114;1
"Unit";"Zergling";"Larva";114;1
"Unit";"Zergling";"Larva";114;1
"Unit";"Zergling";"Larva";114;1
"Unit";"Zergling";"Larva";114;1
"Unit";"Zergling";"Larva";114;1
"Unit";"Zergling";"Larva";114;1
"Unit";"Zergling";"Larva";114;1
"Unit";"Zergling";"Larva";114;1
"Unit";"Zergling";"Larva";114;1
"Unit";"Zergling";"Larva";114;1
"Unit";"Zergling";"Larva";114;1
"Unit";"Overlord";"Larva";114;0
"Unit";"Overlord";"Larva";114;0
"Unit";"Overlord";"Larva";114;0
"Unit";"Queen";"Hatchery";114;2
"Unit";"Zergling";"Larva";114;1
"Unit";"Zergling";"Larva";114;1
"Building";"InfestationPit";NA;114;0
"Building";"CreepTumor";NA;136;0
"Building";"CreepTumor";NA;136;0
"Building";"CreepTumor";NA;136;0
"Building";"CreepTumor";NA;136;0
"Building";"CreepTumor";NA;138;0
"Building";"CreepTumor";NA;140;0
"Building";"CreepTumorQueen";NA;140;0
"Upgrade";"ZergMeleeWeaponsLevel1";"EvolutionChamber";114;0
"Upgrade";"ZergGroundArmorsLevel1";"EvolutionChamber";114;0
"Unit";"Baneling";"Zergling";140;0
"Unit";"Baneling";"Zergling";140;0
"Unit";"Baneling";"Zergling";140;0
"Upgrade";"EvolveGroovedSpines";"HydraliskDen";114;0
"Unit";"Zergling";"Larva";140;1
"Unit";"Zergling";"Larva";140;1
"Unit";"Zergling";"Larva";140;1
"Unit";"Zergling";"Larva";140;1
"Unit";"Zergling";"Larva";140;1
"Unit";"Zergling";"Larva";140;1
"Unit";"Zergling";"Larva";140;1
"Unit";"Zergling";"Larva";140;1
"Unit";"Zergling";"Larva";140;1
"Unit";"Zergling";"Larva";140;1
"Unit";"Zergling";"Larva";140;1
"Unit";"Zergling";"Larva";140;1
"Building";"CreepTumor";NA;150;0
"Unit";"Hydralisk";"Larva";150;2
"Unit";"Hydralisk";"Larva";162;2
"Unit";"Hydralisk";"Larva";162;2
"Unit";"Hydralisk";"Larva";162;2
"Unit";"Hydralisk";"Larva";162;2
"Unit";"Hydralisk";"Larva";162;2
"Unit";"Hydralisk";"Larva";162;2
"Unit";"Hydralisk";"Larva";165;2
"Unit";"Hydralisk";"Larva";165;2
"Unit";"Hydralisk";"Larva";165;2
"Unit";"Hydralisk";"Larva";165;2
"Unit";"Overlord";"Larva";165;0
"Unit";"Overlord";"Larva";165;0
"Building";"SporeCrawler";NA;165;0
"Unit";"Zergling";"Larva";165;1
"Unit";"Zergling";"Larva";165;1
"Unit";"Zergling";"Larva";187;1
"Unit";"Zergling";"Larva";187;1
"Unit";"Zergling";"Larva";187;1
"Unit";"Zergling";"Larva";187;1
"Unit";"Zergling";"Larva";187;1
"Unit";"Zergling";"Larva";187;1
"Unit";"Zergling";"Larva";187;1
"Unit";"Zergling";"Larva";187;1
"Unit";"Zergling";"Larva";187;1
"Unit";"Zergling";"Larva";187;1
"Unit";"Zergling";"Larva";187;1
"Unit";"Zergling";"Larva";187;1
"Unit";"Zergling";"Larva";187;1
"Unit";"Zergling";"Larva";187;1
"Unit";"Zergling";"Larva";187;1
"Unit";"Zergling";"Larva";187;1
"Unit";"Overlord";"Larva";189;0
"Unit";"Overlord";"Larva";189;0
"Building";"CreepTumor";NA;189;0
"Building";"CreepTumor";NA;189;0
"Building";"CreepTumorQueen";NA;205;0
"Upgrade";"EvolveMuscularAugments";"HydraliskDen";165;0
"Unit";"Hydralisk";"Larva";189;2
"Unit";"Hydralisk";"Larva";189;2
"Unit";"Hydralisk";"Larva";189;2
"Unit";"Hydralisk";"Larva";189;2
"Unit";"Hydralisk";"Larva";189;2
"Building";"SporeCrawler";NA;205;0
"Building";"Hatchery";NA;162;0
"Unit";"Baneling";"Zergling";205;0
"Unit";"Baneling";"Zergling";205;0
"Unit";"Baneling";"Zergling";205;0
"Unit";"Baneling";"Zergling";205;0
"Unit";"Baneling";"Zergling";205;0
"Unit";"Baneling";"Zergling";205;0
"Unit";"Baneling";"Zergling";205;0
"Unit";"Baneling";"Zergling";205;0
"Building";"Hatchery";NA;165;0
"Unit";"Baneling";"Zergling";205;0
"Unit";"Baneling";"Zergling";205;0
"Unit";"Baneling";"Zergling";205;0
"Unit";"Baneling";"Zergling";205;0
"Unit";"Zergling";"Larva";205;1
"Unit";"Zergling";"Larva";205;1
"Unit";"Hydralisk";"Larva";205;2
"Unit";"Hydralisk";"Larva";205;2
"Unit";"Hydralisk";"Larva";205;2
"Unit";"Hydralisk";"Larva";205;2
"Unit";"Hydralisk";"Larva";205;2
"Building";"Spire";NA;179;0
"Building";"CreepTumor";NA;227;0
"Building";"CreepTumor";NA;227;0
"Unit";"Zergling";"Larva";233;1
"Unit";"Zergling";"Larva";233;1
"Unit";"Zergling";"Larva";233;1
"Unit";"Zergling";"Larva";233;1
"Unit";"Zergling";"Larva";233;1
"Unit";"Zergling";"Larva";233;1
"Unit";"Zergling";"Larva";233;1
"Unit";"Zergling";"Larva";233;1
"Unit";"Zergling";"Larva";233;1
"Unit";"Zergling";"Larva";233;1
"Unit";"Zergling";"Larva";233;1
"Unit";"Zergling";"Larva";233;1
"Unit";"Zergling";"Larva";233;1
"Unit";"Zergling";"Larva";233;1
"Unit";"Zergling";"Larva";233;1
"Unit";"Zergling";"Larva";233;1
"Unit";"Zergling";"Larva";233;1
"Unit";"Zergling";"Larva";233;1
"Unit";"Zergling";"Larva";233;1
"Unit";"Zergling";"Larva";233;1
"Unit";"Zergling";"Larva";233;1
"Unit";"Zergling";"Larva";233;1
"Unit";"Zergling";"Larva";233;1
"Unit";"Zergling";"Larva";233;1
"Unit";"Zergling";"Larva";233;1
"Unit";"Zergling";"Larva";233;1
"Unit";"Zergling";"Larva";233;1
"Unit";"Zergling";"Larva";233;1
"Upgrade";"ZergMeleeWeaponsLevel2";"EvolutionChamber";179;0
"Upgrade";"ZergGroundArmorsLevel2";"EvolutionChamber";183;0
"Building";"SporeCrawler";NA;233;0
"Building";"SporeCrawler";NA;233;0
"Unit";"Zergling";"Larva";233;1
"Unit";"Zergling";"Larva";233;1
"Unit";"Zergling";"Larva";233;1
"Unit";"Zergling";"Larva";233;1
"Unit";"Zergling";"Larva";233;1
"Unit";"Zergling";"Larva";233;1
"Unit";"Zergling";"Larva";233;1
"Unit";"Zergling";"Larva";233;1
"Unit";"Zergling";"Larva";233;1
"Unit";"Zergling";"Larva";233;1
"Unit";"Zergling";"Larva";233;1
"Unit";"Zergling";"Larva";233;1
"Unit";"Zergling";"Larva";233;1
"Unit";"Zergling";"Larva";233;1
"Unit";"Zergling";"Larva";233;1
"Unit";"Zergling";"Larva";233;1
"Building";"Extractor";NA;233;0
"Building";"Extractor";NA;233;0
"Unit";"Baneling";"Zergling";261;0
"Unit";"Baneling";"Zergling";261;0
"Unit";"Baneling";"Zergling";261;0
"Unit";"Baneling";"Zergling";261;0
"Unit";"Baneling";"Zergling";261;0
"Unit";"Zergling";"Larva";261;1
"Unit";"Zergling";"Larva";261;1
"Unit";"Zergling";"Larva";261;1
"Unit";"Zergling";"Larva";261;1
"Unit";"Zergling";"Larva";261;1
"Unit";"Zergling";"Larva";261;1
"Unit";"Zergling";"Larva";261;1
"Unit";"Zergling";"Larva";261;1
"Building";"SpineCrawler";NA;233;0
"Unit";"Zergling";"Larva";261;1
"Unit";"Zergling";"Larva";261;1
"Unit";"Zergling";"Larva";261;1
"Unit";"Zergling";"Larva";261;1
"Unit";"Zergling";"Larva";261;1
"Unit";"Zergling";"Larva";261;1
"Unit";"Zergling";"Larva";261;1
"Unit";"Zergling";"Larva";261;1
"Unit";"Zergling";"Larva";261;1
"Unit";"Zergling";"Larva";261;1
"Building";"SpineCrawler";NA;233;0
"Unit";"Baneling";"Zergling";277;0
"Unit";"Baneling";"Zergling";277;0
"Unit";"Baneling";"Zergling";277;0
"Unit";"Baneling";"Zergling";277;0
"Unit";"Baneling";"Zergling";277;0
"Unit";"Zergling";"Larva";277;1
"Unit";"Zergling";"Larva";277;1
"Unit";"Zergling";"Larva";277;1
"Unit";"Zergling";"Larva";277;1
"Unit";"Zergling";"Larva";277;1
"Unit";"Zergling";"Larva";277;1
"Unit";"Zergling";"Larva";277;1
"Unit";"Zergling";"Larva";277;1
"Unit";"Zergling";"Larva";277;1
"Unit";"Zergling";"Larva";277;1
"Unit";"Zergling";"Larva";277;1
"Unit";"Zergling";"Larva";277;1
"Unit";"Zergling";"Larva";277;1
"Unit";"Zergling";"Larva";277;1
"Unit";"Zergling";"Larva";277;1
"Unit";"Zergling";"Larva";277;1
"Unit";"Zergling";"Larva";295;1
"Unit";"Zergling";"Larva";295;1
"Unit";"Zergling";"Larva";295;1
"Unit";"Zergling";"Larva";295;1
"Unit";"Zergling";"Larva";295;1
"Unit";"Zergling";"Larva";295;1
"Unit";"Zergling";"Larva";295;1
"Unit";"Zergling";"Larva";295;1
"Unit";"Zergling";"Larva";295;1
"Unit";"Zergling";"Larva";295;1
"Unit";"Zergling";"Larva";295;1
"Unit";"Zergling";"Larva";295;1
"Unit";"Zergling";"Larva";295;1
"Unit";"Zergling";"Larva";295;1
"Unit";"Zergling";"Larva";295;1
"Unit";"Zergling";"Larva";295;1
"Unit";"Zergling";"Larva";295;1
"Unit";"Zergling";"Larva";295;1
"Unit";"Zergling";"Larva";295;1
"Unit";"Zergling";"Larva";295;1
"Unit";"Zergling";"Larva";295;1
"Unit";"Zergling";"Larva";295;1
"Unit";"Zergling";"Larva";295;1
"Unit";"Zergling";"Larva";295;1
"Unit";"Zergling";"Larva";295;1
"Unit";"Zergling";"Larva";295;1
"Unit";"Zergling";"Larva";295;1
"Unit";"Zergling";"Larva";295;1
"Unit";"Zergling";"Larva";295;1
"Unit";"Zergling";"Larva";295;1
"Unit";"Zergling";"Larva";295;1
"Unit";"Zergling";"Larva";295;1
"Unit";"Zergling";"Larva";295;1
"Unit";"Zergling";"Larva";295;1
"Unit";"Zergling";"Larva";354;1
"Unit";"Zergling";"Larva";354;1
"Unit";"Zergling";"Larva";354;1
"Unit";"Zergling";"Larva";354;1
"Unit";"Zergling";"Larva";354;1
"Unit";"Zergling";"Larva";354;1
"Unit";"Zergling";"Larva";354;1
"Unit";"Zergling";"Larva";354;1
"Unit";"Zergling";"Larva";354;1
"Unit";"Zergling";"Larva";354;1
"Unit";"Zergling";"Larva";355;1
"Unit";"Zergling";"Larva";355;1
"Unit";"Zergling";"Larva";367;1
"Unit";"Zergling";"Larva";367;1
"Unit";"Zergling";"Larva";367;1
"Unit";"Zergling";"Larva";367;1
"Unit";"Zergling";"Larva";367;1
"Unit";"Zergling";"Larva";367;1
"Unit";"Zergling";"Larva";367;1
"Unit";"Zergling";"Larva";367;1
"Unit";"Zergling";"Larva";367;1
"Unit";"Zergling";"Larva";367;1
"Unit";"Zergling";"Larva";367;1
"Unit";"Zergling";"Larva";367;1
"Unit";"Zergling";"Larva";367;1
"Unit";"Zergling";"Larva";367;1
"Unit";"Zergling";"Larva";367;1
"Unit";"Zergling";"Larva";367;1
"Unit";"Zergling";"Larva";367;1
"Unit";"Zergling";"Larva";367;1
"Unit";"Zergling";"Larva";367;1
"Unit";"Zergling";"Larva";367;1
"Unit";"Zergling";"Larva";367;1
"Unit";"Zergling";"Larva";367;1
"Unit";"Zergling";"Larva";367;1
"Unit";"Zergling";"Larva";367;1
"Unit";"Zergling";"Larva";367;1
"Unit";"Zergling";"Larva";367;1
"Unit";"Zergling";"Larva";367;1
"Unit";"Zergling";"Larva";367;1
"Unit";"Zergling";"Larva";367;1
"Unit";"Zergling";"Larva";367;1
"Unit";"Zergling";"Larva";367;1
"Unit";"Zergling";"Larva";367;1
"Unit";"Zergling";"Larva";367;1
"Unit";"Zergling";"Larva";367;1
"Building";"SporeCrawler";NA;367;0
"Building";"UltraliskCavern";NA;355;0
"Building";"SporeCrawler";NA;367;0
"Building";"CreepTumor";NA;406;0
"Building";"CreepTumor";NA;406;0
"Unit";"Hydralisk";"Larva";406;2
"Unit";"Hydralisk";"Larva";406;2
"Unit";"Hydralisk";"Larva";406;2
"Unit";"Hydralisk";"Larva";406;2
"Unit";"Hydralisk";"Larva";406;2
"Unit";"Hydralisk";"Larva";406;2
"Unit";"Hydralisk";"Larva";406;2
"Building";"CreepTumorQueen";NA;406;0
"Building";"CreepTumorQueen";NA;406;0
"Building";"CreepTumorQueen";NA;406;0
"Unit";"Zergling";"Larva";416;1
"Unit";"Zergling";"Larva";416;1
"Unit";"Zergling";"Larva";420;1
"Unit";"Zergling";"Larva";420;1
"Unit";"Zergling";"Larva";420;1
"Unit";"Zergling";"Larva";420;1
"Unit";"Zergling";"Larva";420;1
"Unit";"Zergling";"Larva";420;1
"Unit";"Zergling";"Larva";420;1
"Unit";"Zergling";"Larva";420;1
"Building";"CreepTumorQueen";NA;420;0
"Unit";"Zergling";"Larva";420;1
"Unit";"Zergling";"Larva";420;1
"Building";"CreepTumor";NA;420;0
"Building";"CreepTumorQueen";NA;420;0
"Building";"CreepTumorQueen";NA;420;0
"Unit";"Queen";"Hatchery";406;2
"Unit";"Queen";"Hatchery";406;2
"Unit";"Queen";"Hatchery";406;2
"Building";"CreepTumor";NA;420;0
"Building";"CreepTumor";NA;420;0
"Building";"CreepTumor";NA;420;0
"Building";"CreepTumor";NA;428;0
"Unit";"Ultralisk";"Larva";406;6
"Unit";"Baneling";"Zergling";432;0
"Unit";"Baneling";"Zergling";432;0
"Unit";"Baneling";"Zergling";432;0
"Unit";"Baneling";"Zergling";432;0
"Unit";"Baneling";"Zergling";432;0
"Unit";"Baneling";"Zergling";432;0
"Unit";"Baneling";"Zergling";432;0
"Unit";"Baneling";"Zergling";432;0
"Unit";"Baneling";"Zergling";432;0
"Unit";"Baneling";"Zergling";432;0
"Unit";"Baneling";"Zergling";432;0
"Unit";"Baneling";"Zergling";432;0
"Unit";"Baneling";"Zergling";432;0
"Unit";"Baneling";"Zergling";432;0
"Building";"CreepTumor";NA;438;0
"Unit";"Baneling";"Zergling";444;0
"Unit";"Baneling";"Zergling";444;0
"Unit";"Baneling";"Zergling";444;0
"Unit";"Baneling";"Zergling";444;0
"Unit";"Baneling";"Zergling";444;0
"Unit";"Ultralisk";"Larva";420;6
"Unit";"Baneling";"Zergling";444;0
"Upgrade";"ZergMissileWeaponsLevel1";"EvolutionChamber";367;0
"Building";"CreepTumor";NA;450;0
"Building";"CreepTumor";NA;450;0
"Building";"CreepTumor";NA;450;0
"Building";"CreepTumor";NA;450;0
"Upgrade";"ChitinousPlating";"UltraliskCavern";420;0
"Unit";"Zergling";"Larva";451;1
"Unit";"Zergling";"Larva";451;1
"Unit";"Zergling";"Larva";451;1
"Unit";"Zergling";"Larva";451;1
"Unit";"Zergling";"Larva";451;1
"Unit";"Zergling";"Larva";451;1
"Unit";"Zergling";"Larva";451;1
"Unit";"Zergling";"Larva";451;1
"Unit";"Zergling";"Larva";451;1
"Unit";"Zergling";"Larva";451;1
"Unit";"Zergling";"Larva";451;1
"Unit";"Zergling";"Larva";451;1
"Unit";"Zergling";"Larva";451;1
"Unit";"Zergling";"Larva";451;1
"Unit";"Zergling";"Larva";451;1
"Unit";"Zergling";"Larva";451;1
"Unit";"Zergling";"Larva";451;1
"Unit";"Zergling";"Larva";451;1
"Unit";"Zergling";"Larva";451;1
"Unit";"Zergling";"Larva";451;1
"Unit";"Zergling";"Larva";451;1
"Unit";"Zergling";"Larva";451;1
"Unit";"Zergling";"Larva";451;1
"Unit";"Zergling";"Larva";451;1
"Unit";"Zergling";"Larva";451;1
"Unit";"Zergling";"Larva";451;1
"Unit";"Zergling";"Larva";451;1
"Unit";"Zergling";"Larva";451;1
"Unit";"Zergling";"Larva";451;1
"Unit";"Zergling";"Larva";451;1
"Unit";"Zergling";"Larva";451;1
"Unit";"Zergling";"Larva";451;1
"Unit";"Zergling";"Larva";451;1
"Unit";"Zergling";"Larva";451;1
"Unit";"Zergling";"Larva";451;1
"Unit";"Zergling";"Larva";451;1
"Unit";"Zergling";"Larva";451;1
"Unit";"Zergling";"Larva";451;1
"Unit";"Zergling";"Larva";451;1
"Unit";"Zergling";"Larva";451;1
"Unit";"Zergling";"Larva";451;1
"Unit";"Zergling";"Larva";451;1
"Building";"Extractor";NA;451;0
"Unit";"Baneling";"Zergling";451;0
"Building";"Extractor";NA;451;0
"Unit";"Baneling";"Zergling";451;0
"Unit";"Baneling";"Zergling";451;0
"Unit";"Baneling";"Zergling";451;0
"Unit";"Baneling";"Zergling";451;0
"Unit";"Baneling";"Zergling";451;0
"Unit";"Baneling";"Zergling";451;0
"Unit";"Baneling";"Zergling";451;0
"Unit";"Baneling";"Zergling";451;0
"Unit";"Baneling";"Zergling";451;0
"Unit";"Baneling";"Zergling";451;0
"Unit";"Baneling";"Zergling";451;0
"Unit";"Baneling";"Zergling";451;0
"Unit";"Baneling";"Zergling";451;0
"Unit";"Baneling";"Zergling";451;0
"Unit";"Baneling";"Zergling";451;0
"Unit";"Baneling";"Zergling";451;0
"Unit";"Baneling";"Zergling";451;0
"Unit";"Baneling";"Zergling";451;0
"Upgrade";"ZergGroundArmorsLevel3";"EvolutionChamber";406;0
"Unit";"Zergling";"Larva";451;1
"Unit";"Zergling";"Larva";451;1
"Unit";"Zergling";"Larva";451;1
"Unit";"Zergling";"Larva";451;1
"Unit";"Zergling";"Larva";451;1
"Unit";"Zergling";"Larva";451;1
"Unit";"Zergling";"Larva";451;1
"Unit";"Zergling";"Larva";451;1
"Unit";"Zergling";"Larva";451;1
"Unit";"Zergling";"Larva";451;1
"Unit";"Zergling";"Larva";451;1
"Unit";"Zergling";"Larva";451;1
"Unit";"Zergling";"Larva";451;1
"Unit";"Zergling";"Larva";451;1
"Unit";"Zergling";"Larva";451;1
"Unit";"Zergling";"Larva";451;1
"Unit";"Zergling";"Larva";451;1
"Unit";"Zergling";"Larva";451;1
"Unit";"Zergling";"Larva";451;1
"Unit";"Zergling";"Larva";451;1
"Unit";"Zergling";"Larva";451;1
"Unit";"Zergling";"Larva";451;1
"Unit";"Zergling";"Larva";451;1
"Unit";"Zergling";"Larva";451;1
"Unit";"Zergling";"Larva";451;1
"Unit";"Zergling";"Larva";451;1
"Unit";"Zergling";"Larva";451;1
"Unit";"Zergling";"Larva";451;1
"Unit";"Zergling";"Larva";493;1
"Unit";"Zergling";"Larva";493;1
"Unit";"Zergling";"Larva";493;1
"Unit";"Zergling";"Larva";493;1
"Unit";"Zergling";"Larva";493;1
"Unit";"Zergling";"Larva";493;1
"Unit";"Zergling";"Larva";493;1
"Unit";"Zergling";"Larva";493;1
"Unit";"Zergling";"Larva";493;1
"Unit";"Zergling";"Larva";493;1
"Unit";"Zergling";"Larva";493;1
"Unit";"Zergling";"Larva";493;1
"Building";"Hatchery";NA;444;0
"Unit";"Zergling";"Larva";521;1
"Unit";"Zergling";"Larva";521;1
"Unit";"Zergling";"Larva";521;1
"Unit";"Zergling";"Larva";521;1
"Unit";"Zergling";"Larva";521;1
"Unit";"Zergling";"Larva";521;1
"Unit";"Zergling";"Larva";521;1
"Unit";"Zergling";"Larva";521;1
"Unit";"Zergling";"Larva";521;1
"Unit";"Zergling";"Larva";521;1
"Unit";"Zergling";"Larva";521;1
"Unit";"Zergling";"Larva";521;1
"Unit";"Zergling";"Larva";521;1
"Unit";"Zergling";"Larva";521;1
"Unit";"Zergling";"Larva";521;1
"Unit";"Zergling";"Larva";521;1
"Unit";"Zergling";"Larva";521;1
"Unit";"Zergling";"Larva";521;1
"Unit";"Corruptor";"Larva";521;2
"Unit";"Corruptor";"Larva";521;2
"Unit";"Corruptor";"Larva";521;2
"Unit";"Corruptor";"Larva";521;2
"Unit";"Corruptor";"Larva";521;2
"Unit";"Corruptor";"Larva";521;2
"Building";"CreepTumor";NA;569;0
"Building";"SporeCrawler";NA;569;0
"Unit";"Corruptor";"Larva";569;2
"Unit";"Corruptor";"Larva";569;2
"Unit";"Corruptor";"Larva";569;2
"Unit";"Corruptor";"Larva";569;2
"Unit";"Baneling";"Zergling";569;0
"Unit";"Baneling";"Zergling";569;0
"Unit";"Baneling";"Zergling";569;0
"Unit";"Baneling";"Zergling";569;0
"Unit";"Baneling";"Zergling";569;0
"Unit";"Baneling";"Zergling";569;0
"Unit";"Baneling";"Zergling";569;0
"Unit";"Baneling";"Zergling";569;0
"Unit";"Baneling";"Zergling";569;0
"Unit";"Baneling";"Zergling";569;0
"Unit";"Baneling";"Zergling";569;0
"Unit";"Baneling";"Zergling";569;0
"Unit";"Baneling";"Zergling";569;0
"Unit";"Baneling";"Zergling";569;0
"Unit";"Baneling";"Zergling";569;0
"Unit";"Baneling";"Zergling";569;0
"Unit";"Baneling";"Zergling";569;0
"Unit";"Baneling";"Zergling";569;0
"Building";"SporeCrawler";NA;577;0
"Building";"SporeCrawler";NA;577;0
"Building";"CreepTumor";NA;577;0
"Building";"SporeCrawler";NA;577;0
"Building";"SporeCrawler";NA;577;0
"Building";"SporeCrawler";NA;577;0
"Building";"Hatchery";NA;569;0
"Building";"SporeCrawler";NA;577;0
"Building";"CreepTumor";NA;585;0
"Unit";"Corruptor";"Larva";577;2
"Unit";"Corruptor";"Larva";577;2
"Building";"CreepTumor";NA;585;0
"Building";"CreepTumorQueen";NA;585;0
"Building";"CreepTumorQueen";NA;585;0
"Building";"CreepTumorQueen";NA;585;0
"Unit";"Ultralisk";"Larva";577;6
"Unit";"Ultralisk";"Larva";577;6
"Upgrade";"ZergMissileWeaponsLevel2";"EvolutionChamber";569;0
"Unit";"Zergling";"Larva";601;1
"Unit";"Zergling";"Larva";601;1
"Unit";"Zergling";"Larva";601;1
"Unit";"Zergling";"Larva";601;1
"Unit";"Zergling";"Larva";601;1
"Unit";"Zergling";"Larva";601;1
"Unit";"Zergling";"Larva";601;1
"Unit";"Zergling";"Larva";601;1
"Unit";"Zergling";"Larva";601;1
"Unit";"Zergling";"Larva";601;1
"Unit";"Zergling";"Larva";601;1
"Unit";"Zergling";"Larva";601;1
"Unit";"Zergling";"Larva";601;1
"Unit";"Zergling";"Larva";601;1
"Unit";"Zergling";"Larva";601;1
"Unit";"Zergling";"Larva";601;1
"Upgrade";"ZergMeleeWeaponsLevel3";"EvolutionChamber";569;0
"Unit";"Zergling";"Larva";617;1
"Unit";"Zergling";"Larva";617;1
"Unit";"Zergling";"Larva";617;1
"Unit";"Zergling";"Larva";617;1
"Unit";"Zergling";"Larva";617;1
"Unit";"Zergling";"Larva";617;1
"Unit";"Zergling";"Larva";617;1
"Unit";"Zergling";"Larva";617;1
"Unit";"Zergling";"Larva";617;1
"Unit";"Zergling";"Larva";617;1
"Unit";"Zergling";"Larva";617;1
"Unit";"Zergling";"Larva";617;1
"Unit";"Ultralisk";"Larva";601;6
"Unit";"Ultralisk";"Larva";601;6
"Unit";"Ultralisk";"Larva";601;6
"Unit";"Ultralisk";"Larva";601;6
"Unit";"Baneling";"Zergling";629;0
"Unit";"Baneling";"Zergling";629;0
"Unit";"Baneling";"Zergling";629;0
"Unit";"Baneling";"Zergling";629;0
"Unit";"Baneling";"Zergling";629;0
"Unit";"Baneling";"Zergling";629;0
"Unit";"Ultralisk";"Larva";617;6
"Unit";"Ultralisk";"Larva";617;6
"Unit";"Ultralisk";"Larva";617;6
"Unit";"Zergling";"Larva";653;1
"Unit";"Zergling";"Larva";653;1
"Unit";"Zergling";"Larva";653;1
"Unit";"Zergling";"Larva";653;1
"Unit";"Zergling";"Larva";653;1
"Unit";"Zergling";"Larva";653;1
"Unit";"Zergling";"Larva";653;1
"Unit";"Zergling";"Larva";653;1
"Unit";"Zergling";"Larva";653;1
"Unit";"Zergling";"Larva";653;1
"Unit";"Zergling";"Larva";653;1
"Unit";"Zergling";"Larva";653;1
"Unit";"Zergling";"Larva";653;1
"Unit";"Zergling";"Larva";653;1
"Unit";"Zergling";"Larva";653;1
"Unit";"Zergling";"Larva";653;1
"Unit";"Zergling";"Larva";653;1
"Unit";"Zergling";"Larva";653;1
"Unit";"Zergling";"Larva";653;1
"Unit";"Zergling";"Larva";653;1
"Unit";"Zergling";"Larva";653;1
"Unit";"Zergling";"Larva";653;1
"Unit";"Zergling";"Larva";653;1
"Unit";"Zergling";"Larva";653;1
"Unit";"Zergling";"Larva";653;1
"Unit";"Zergling";"Larva";653;1
"Unit";"Zergling";"Larva";653;1
"Unit";"Zergling";"Larva";653;1
"Unit";"Zergling";"Larva";653;1
"Unit";"Zergling";"Larva";653;1
"Unit";"Zergling";"Larva";653;1
"Unit";"Zergling";"Larva";653;1
"Unit";"Zergling";"Larva";671;1
"Unit";"Zergling";"Larva";671;1
"Unit";"Zergling";"Larva";671;1
"Unit";"Zergling";"Larva";671;1
"Unit";"Zergling";"Larva";671;1
"Unit";"Zergling";"Larva";671;1
"Unit";"Zergling";"Larva";671;1
"Unit";"Zergling";"Larva";671;1
"Unit";"Zergling";"Larva";671;1
"Unit";"Zergling";"Larva";671;1
"Unit";"Zergling";"Larva";671;1
"Unit";"Zergling";"Larva";671;1
"Unit";"Zergling";"Larva";671;1
"Unit";"Zergling";"Larva";671;1
"Unit";"Zergling";"Larva";671;1
"Unit";"Zergling";"Larva";671;1
"Unit";"Zergling";"Larva";671;1
"Unit";"Zergling";"Larva";671;1
"Unit";"Zergling";"Larva";671;1
"Unit";"Zergling";"Larva";671;1
"Unit";"Zergling";"Larva";671;1
"Unit";"Zergling";"Larva";671;1
"Unit";"Zergling";"Larva";671;1
"Unit";"Zergling";"Larva";671;1
"Unit";"Zergling";"Larva";671;1
"Unit";"Zergling";"Larva";671;1
"Unit";"Zergling";"Larva";671;1
"Unit";"Zergling";"Larva";671;1
"Unit";"Zergling";"Larva";671;1
"Unit";"Zergling";"Larva";671;1
"Unit";"Zergling";"Larva";671;1
"Unit";"Zergling";"Larva";671;1
"Unit";"Zergling";"Larva";671;1
"Unit";"Zergling";"Larva";671;1
"Unit";"Zergling";"Larva";671;1
"Unit";"Zergling";"Larva";671;1
"Unit";"Zergling";"Larva";671;1
"Unit";"Zergling";"Larva";671;1
"Unit";"Zergling";"Larva";671;1
"Unit";"Zergling";"Larva";671;1
"Unit";"Zergling";"Larva";671;1
"Unit";"Zergling";"Larva";671;1
"Unit";"Zergling";"Larva";703;1
"Unit";"Zergling";"Larva";703;1
"Unit";"Zergling";"Larva";703;1
"Unit";"Zergling";"Larva";703;1
"Unit";"Zergling";"Larva";703;1
"Unit";"Zergling";"Larva";703;1
"Unit";"Zergling";"Larva";703;1
"Unit";"Zergling";"Larva";703;1
"Unit";"Zergling";"Larva";703;1
"Unit";"Zergling";"Larva";703;1
"Unit";"Zergling";"Larva";703;1
"Unit";"Zergling";"Larva";703;1
"Unit";"Zergling";"Larva";703;1
"Unit";"Zergling";"Larva";703;1
"Unit";"Zergling";"Larva";703;1
"Unit";"Zergling";"Larva";703;1
"Unit";"Zergling";"Larva";703;1
"Unit";"Zergling";"Larva";703;1
"Unit";"Zergling";"Larva";703;1
"Unit";"Zergling";"Larva";703;1
"Unit";"Zergling";"Larva";703;1
"Unit";"Zergling";"Larva";703;1
"Unit";"Zergling";"Larva";703;1
"Unit";"Zergling";"Larva";703;1
"Unit";"Zergling";"Larva";703;1
"Unit";"Zergling";"Larva";703;1
"Unit";"Zergling";"Larva";703;1
"Unit";"Zergling";"Larva";703;1
"Unit";"Zergling";"Larva";703;1
"Unit";"Zergling";"Larva";703;1
"Unit";"Baneling";"Zergling";765;0
"Unit";"Baneling";"Zergling";765;0
"Building";"Extractor";NA;745;0
"Unit";"Baneling";"Zergling";765;0
"Unit";"Baneling";"Zergling";765;0
"Unit";"Baneling";"Zergling";765;0
"Unit";"Baneling";"Zergling";765;0
"Unit";"Baneling";"Zergling";765;0
"Unit";"Baneling";"Zergling";765;0
"Unit";"Baneling";"Zergling";765;0
"Unit";"Baneling";"Zergling";765;0
"Unit";"Baneling";"Zergling";765;0
"Unit";"Baneling";"Zergling";765;0
"Unit";"Baneling";"Zergling";765;0
"Unit";"Baneling";"Zergling";765;0
"Unit";"Baneling";"Zergling";765;0
"Building";"Extractor";NA;749;0
"Building";"CreepTumor";NA;778;0
"Unit";"Corruptor";"Larva";765;2
"Unit";"Corruptor";"Larva";765;2
"Unit";"Corruptor";"Larva";765;2
"Unit";"Corruptor";"Larva";765;2
"Unit";"Corruptor";"Larva";765;2
"Unit";"Corruptor";"Larva";765;2
"Unit";"Corruptor";"Larva";765;2
"Unit";"Corruptor";"Larva";765;2
"Unit";"Corruptor";"Larva";765;2
"Unit";"Zergling";"Larva";778;1
"Unit";"Zergling";"Larva";778;1
"Unit";"Zergling";"Larva";778;1
"Unit";"Zergling";"Larva";778;1
"Unit";"Zergling";"Larva";778;1
"Unit";"Zergling";"Larva";778;1
"Unit";"Zergling";"Larva";778;1
"Unit";"Zergling";"Larva";778;1
"Unit";"Zergling";"Larva";778;1
"Unit";"Zergling";"Larva";778;1
"Unit";"Zergling";"Larva";778;1
"Unit";"Zergling";"Larva";778;1
"Unit";"Zergling";"Larva";778;1
"Unit";"Zergling";"Larva";778;1
"Unit";"Overlord";"Larva";796;0
"Unit";"Overlord";"Larva";796;0
"Unit";"Overlord";"Larva";796;0
"Building";"Extractor";NA;796;0
"Building";"Extractor";NA;796;0
"Building";"CreepTumor";NA;810;0
"Building";"CreepTumor";NA;810;0
"Unit";"Infestor";"Larva";778;2
"Unit";"Ultralisk";"Larva";778;6
"Unit";"Ultralisk";"Larva";778;6
"Unit";"Zergling";"Larva";824;1
"Unit";"Zergling";"Larva";824;1
"Unit";"Zergling";"Larva";824;1
"Unit";"Zergling";"Larva";824;1
"Unit";"Zergling";"Larva";824;1
"Unit";"Zergling";"Larva";824;1
"Unit";"Zergling";"Larva";824;1
"Unit";"Zergling";"Larva";824;1
"Unit";"Zergling";"Larva";824;1
"Unit";"Zergling";"Larva";824;1
"Unit";"Ultralisk";"Larva";810;6
"Unit";"Zergling";"Larva";824;1
"Unit";"Zergling";"Larva";824;1
"Unit";"Zergling";"Larva";824;1
"Unit";"Zergling";"Larva";824;1
"Unit";"Zergling";"Larva";824;1
"Unit";"Zergling";"Larva";824;1
"Unit";"Zergling";"Larva";824;1
"Unit";"Zergling";"Larva";824;1
"Unit";"Zergling";"Larva";824;1
"Unit";"Zergling";"Larva";824;1
"Unit";"Zergling";"Larva";824;1
"Unit";"Zergling";"Larva";824;1
"Unit";"Zergling";"Larva";824;1
"Unit";"Zergling";"Larva";824;1
"Unit";"Zergling";"Larva";824;1
"Unit";"Zergling";"Larva";824;1
"Unit";"Zergling";"Larva";824;1
"Unit";"Zergling";"Larva";824;1
"Unit";"Zergling";"Larva";824;1
"Unit";"Zergling";"Larva";824;1
"Unit";"Zergling";"Larva";824;1
"Unit";"Zergling";"Larva";824;1
"Unit";"Zergling";"Larva";824;1
"Unit";"Zergling";"Larva";824;1
"Unit";"Zergling";"Larva";824;1
"Unit";"Zergling";"Larva";824;1
"Unit";"Ultralisk";"Larva";824;6
"Unit";"Ultralisk";"Larva";824;6
"Unit";"Ultralisk";"Larva";824;6
"Unit";"Zergling";"Larva";834;1
"Unit";"Zergling";"Larva";834;1
"Unit";"Zergling";"Larva";840;1
"Unit";"Zergling";"Larva";840;1
"Unit";"Zergling";"Larva";840;1
"Unit";"Zergling";"Larva";840;1
"Unit";"Zergling";"Larva";840;1
"Unit";"Zergling";"Larva";840;1
"Unit";"Zergling";"Larva";840;1
"Unit";"Zergling";"Larva";840;1
"Unit";"Zergling";"Larva";840;1
"Unit";"Zergling";"Larva";840;1
"Unit";"Zergling";"Larva";840;1
"Unit";"Zergling";"Larva";840;1
"Unit";"Zergling";"Larva";840;1
"Unit";"Zergling";"Larva";840;1
"Unit";"Zergling";"Larva";866;1
"Unit";"Zergling";"Larva";866;1
"Unit";"Zergling";"Larva";866;1
"Unit";"Zergling";"Larva";866;1
"Unit";"Zergling";"Larva";866;1
"Unit";"Zergling";"Larva";866;1
"Unit";"Zergling";"Larva";866;1
"Unit";"Zergling";"Larva";866;1
"Unit";"Zergling";"Larva";866;1
"Unit";"Zergling";"Larva";866;1
"Unit";"Zergling";"Larva";866;1
"Unit";"Zergling";"Larva";866;1
"Unit";"Ultralisk";"Larva";834;6
"Unit";"Infestor";"Larva";916;2
"Unit";"Infestor";"Larva";916;2
"Unit";"Infestor";"Larva";916;2
"Building";"CreepTumor";NA;936;0
"Building";"CreepTumor";NA;936;0
"Building";"CreepTumor";NA;936;0
"Unit";"Baneling";"Zergling";936;0
"Unit";"Baneling";"Zergling";936;0
"Unit";"Baneling";"Zergling";936;0
"Unit";"Baneling";"Zergling";936;0
"Unit";"Baneling";"Zergling";936;0
"Unit";"Viper";"Larva";935;3
"Unit";"Viper";"Larva";936;3
"Unit";"Viper";"Larva";936;3
"Unit";"Viper";"Larva";936;3
"Building";"Extractor";NA;936;0
"Building";"Hatchery";NA;916;0
"Unit";"Ultralisk";"Larva";928;6
"Unit";"Ultralisk";"Larva";928;6
"Unit";"Zergling";"Larva";936;1
"Unit";"Zergling";"Larva";936;1
"Unit";"Zergling";"Larva";936;1
"Unit";"Zergling";"Larva";936;1
"Unit";"Zergling";"Larva";936;1
"Unit";"Zergling";"Larva";936;1
"Unit";"Zergling";"Larva";936;1
"Unit";"Zergling";"Larva";936;1
"Unit";"Zergling";"Larva";936;1
"Unit";"Zergling";"Larva";936;1
"Unit";"Zergling";"Larva";936;1
"Unit";"Zergling";"Larva";936;1
"Unit";"Zergling";"Larva";936;1
"Unit";"Zergling";"Larva";936;1
"Unit";"Zergling";"Larva";936;1
"Unit";"Zergling";"Larva";936;1
"Unit";"Zergling";"Larva";936;1
"Unit";"Zergling";"Larva";936;1
"Unit";"Zergling";"Larva";936;1
"Unit";"Zergling";"Larva";936;1
"Unit";"Zergling";"Larva";936;1
"Unit";"Zergling";"Larva";936;1
"Unit";"Zergling";"Larva";936;1
"Unit";"Zergling";"Larva";936;1
"Unit";"Zergling";"Larva";936;1
"Unit";"Zergling";"Larva";936;1
"Unit";"Zergling";"Larva";936;1
"Unit";"Zergling";"Larva";936;1
"Unit";"Zergling";"Larva";988;1
"Unit";"Zergling";"Larva";988;1
"Unit";"Zergling";"Larva";988;1
"Unit";"Zergling";"Larva";988;1
"Unit";"Zergling";"Larva";988;1
"Unit";"Zergling";"Larva";988;1
"Unit";"Zergling";"Larva";988;1
"Unit";"Zergling";"Larva";988;1
"Unit";"Zergling";"Larva";988;1
"Unit";"Zergling";"Larva";988;1
"Unit";"Zergling";"Larva";988;1
"Unit";"Zergling";"Larva";988;1
"Unit";"Zergling";"Larva";988;1
"Unit";"Zergling";"Larva";988;1
"Unit";"Zergling";"Larva";988;1
"Unit";"Zergling";"Larva";988;1
"Unit";"Zergling";"Larva";988;1
"Unit";"Zergling";"Larva";988;1
"Unit";"Zergling";"Larva";988;1
"Unit";"Zergling";"Larva";988;1
"Unit";"Zergling";"Larva";988;1
"Unit";"Zergling";"Larva";988;1
"Unit";"Corruptor";"Larva";988;2
"Unit";"Corruptor";"Larva";988;2
"Unit";"Corruptor";"Larva";988;2
"Unit";"Corruptor";"Larva";988;2
"Unit";"Corruptor";"Larva";988;2
"Building";"Hatchery";NA;936;0
"Unit";"Zergling";"Larva";1020;1
"Unit";"Zergling";"Larva";1020;1
"Unit";"Zergling";"Larva";1020;1
"Unit";"Zergling";"Larva";1020;1
"Unit";"Zergling";"Larva";1020;1
"Unit";"Zergling";"Larva";1020;1
"Unit";"Zergling";"Larva";1020;1
"Unit";"Zergling";"Larva";1020;1
"Unit";"Zergling";"Larva";1020;1
"Unit";"Zergling";"Larva";1020;1
"Unit";"Zergling";"Larva";1020;1
"Unit";"Zergling";"Larva";1020;1
"Unit";"Zergling";"Larva";1020;1
"Unit";"Zergling";"Larva";1020;1
"Unit";"Zergling";"Larva";1020;1
"Unit";"Zergling";"Larva";1020;1
"Unit";"Zergling";"Larva";1020;1
"Unit";"Zergling";"Larva";1020;1
"Unit";"Zergling";"Larva";1020;1
"Unit";"Zergling";"Larva";1020;1
"Unit";"Zergling";"Larva";1020;1
"Unit";"Zergling";"Larva";1020;1
"Unit";"Zergling";"Larva";1020;1
"Unit";"Zergling";"Larva";1020;1
"Unit";"Zergling";"Larva";1020;1
"Unit";"Zergling";"Larva";1020;1
"Unit";"Zergling";"Larva";1020;1
"Unit";"Zergling";"Larva";1020;1
"Unit";"Zergling";"Larva";1020;1
"Unit";"Zergling";"Larva";1020;1
"Unit";"Zergling";"Larva";1020;1
"Unit";"Zergling";"Larva";1020;1
"Unit";"Zergling";"Larva";1020;1
"Unit";"Zergling";"Larva";1020;1
"Unit";"Zergling";"Larva";1020;1
"Unit";"Zergling";"Larva";1020;1
"Unit";"Zergling";"Larva";1020;1
"Unit";"Zergling";"Larva";1020;1
"Unit";"Zergling";"Larva";1020;1
"Unit";"Zergling";"Larva";1020;1
"Unit";"Zergling";"Larva";1020;1
"Unit";"Zergling";"Larva";1020;1
"Unit";"Ultralisk";"Larva";1020;6
"Unit";"Zergling";"Larva";1020;1
"Unit";"Zergling";"Larva";1020;1
"Unit";"Zergling";"Larva";1020;1
"Unit";"Zergling";"Larva";1020;1
"Unit";"Ultralisk";"Larva";1020;6
"Unit";"Baneling";"Zergling";1032;0
"Unit";"Baneling";"Zergling";1034;0
"Unit";"Baneling";"Zergling";1036;0
"Unit";"Baneling";"Zergling";1038;0
"Unit";"Baneling";"Zergling";1038;0
"Unit";"Baneling";"Zergling";1038;0
"Unit";"Baneling";"Zergling";1038;0
