"type";"unit_name";"on_building";"total_supply_lag";"supply"
"Unit";"Overlord";"Larva";13;0
"Building";"SpawningPool";NA;17;0
"Building";"Extractor";NA;19;0
"Building";"Hatchery";NA;20;0
"Unit";"Queen";"Hatchery";20;2
"Unit";"Zergling";"Larva";22;1
"Unit";"Zergling";"Larva";23;1
"Unit";"Overlord";"Larva";25;0
"Building";"BanelingNest";NA;25;0
"Unit";"Zergling";"Larva";25;1
"Unit";"Zergling";"Larva";26;1
"Unit";"Zergling";"Larva";27;1
"Unit";"Zergling";"Larva";28;1
"Unit";"Zergling";"Larva";29;1
"Unit";"Zergling";"Larva";30;1
"Building";"SpineCrawler";NA;31;0
"Unit";"Queen";"Hatchery";31;2
"Unit";"Baneling";"Zergling";34;0
"Unit";"Baneling";"Zergling";34;0
"Unit";"Baneling";"Zergling";34;0
"Unit";"Baneling";"Zergling";34;0
"Building";"CreepTumorQueen";NA;39;0
"Unit";"Zergling";"Larva";40;1
"Unit";"Zergling";"Larva";41;1
"Unit";"Zergling";"Larva";42;1
"Unit";"Zergling";"Larva";43;1
"Building";"Hatchery";NA;45;0
"Building";"CreepTumor";NA;45;0
"Unit";"Overlord";"Larva";45;0
"Unit";"Zergling";"Larva";45;1
"Unit";"Zergling";"Larva";46;1
"Building";"CreepTumor";NA;48;0
"Building";"Hatchery";NA;50;0
"Unit";"Queen";"Hatchery";51;2
"Unit";"Overlord";"Larva";53;0
"Building";"CreepTumor";NA;56;0
"Unit";"Zergling";"Larva";56;1
"Unit";"Zergling";"Larva";57;1
"Unit";"Zergling";"Larva";58;1
"Unit";"Zergling";"Larva";59;1
"Building";"CreepTumorQueen";NA;60;0
"Unit";"Queen";"Hatchery";60;2
"Unit";"Zergling";"Larva";62;1
"Unit";"Zergling";"Larva";63;1
"Building";"CreepTumorQueen";NA;69;0
"Building";"CreepTumor";NA;70;0
"Building";"CreepTumor";NA;70;0
"Building";"EvolutionChamber";NA;70;0
"Building";"RoachWarren";NA;70;0
"Building";"Extractor";NA;76;0
"Building";"Extractor";NA;77;0
"Unit";"Overlord";"Larva";86;0
"Unit";"Zergling";"Larva";86;1
"Unit";"Zergling";"Larva";87;1
"Unit";"Zergling";"Larva";88;1
"Unit";"Zergling";"Larva";89;1
"Unit";"Overlord";"Larva";90;0
"Building";"CreepTumor";NA;90;0
"Building";"CreepTumor";NA;90;0
"Building";"CreepTumor";NA;90;0
"Unit";"Roach";"Larva";90;2
"Unit";"Roach";"Larva";92;2
"Unit";"Roach";"Larva";94;2
"Unit";"Roach";"Larva";96;2
"Unit";"Baneling";"Zergling";98;0
"Unit";"Baneling";"Zergling";98;0
"Unit";"Overlord";"Larva";98;0
"Building";"CreepTumorQueen";NA;98;0
"Unit";"Overlord";"Larva";98;0
"Building";"Extractor";NA;98;0
"Unit";"Overlord";"Larva";98;0
"Building";"Extractor";NA;106;0
"Upgrade";"GlialReconstitution";"RoachWarren";106;0
"Unit";"Overlord";"Larva";111;0
"Building";"InfestationPit";NA;113;0
"Building";"CreepTumor";NA;116;0
"Building";"CreepTumor";NA;116;0
"Building";"CreepTumor";NA;116;0
"Building";"Extractor";NA;121;0
"Building";"EvolutionChamber";NA;121;0
"Unit";"Overlord";"Larva";122;0
"Unit";"Overlord";"Larva";122;0
"Unit";"Roach";"Larva";122;2
"Unit";"Roach";"Larva";124;2
"Unit";"Roach";"Larva";126;2
"Unit";"Roach";"Larva";128;2
"Unit";"Roach";"Larva";130;2
"Unit";"Roach";"Larva";132;2
"Building";"SpineCrawler";NA;134;0
"Unit";"Roach";"Larva";134;2
"Unit";"Roach";"Larva";136;2
"Unit";"Roach";"Larva";138;2
"Unit";"Roach";"Larva";140;2
"Unit";"Roach";"Larva";142;2
"Unit";"Roach";"Larva";144;2
"Unit";"Roach";"Larva";146;2
"Unit";"Roach";"Larva";148;2
"Unit";"Roach";"Larva";150;2
"Unit";"Roach";"Larva";152;2
"Unit";"Roach";"Larva";154;2
"Unit";"Roach";"Larva";156;2
"Unit";"Roach";"Larva";158;2
"Unit";"Roach";"Larva";160;2
"Unit";"Infestor";"Larva";162;2
"Unit";"Infestor";"Larva";164;2
"Building";"HydraliskDen";NA;166;0
"Unit";"Infestor";"Larva";166;2
"Unit";"Infestor";"Larva";168;2
"Building";"CreepTumor";NA;170;0
"Unit";"Overlord";"Larva";170;0
"Building";"CreepTumor";NA;170;0
"Unit";"Overlord";"Larva";170;0
"Unit";"Infestor";"Larva";170;2
"Building";"SporeCrawler";NA;172;0
"Building";"SporeCrawler";NA;172;0
"Building";"SporeCrawler";NA;172;0
"Building";"CreepTumor";NA;172;0
"Building";"CreepTumor";NA;175;0
"Building";"SporeCrawler";NA;175;0
"Building";"CreepTumor";NA;175;0
"Unit";"Hydralisk";"Larva";175;2
"Unit";"Hydralisk";"Larva";177;2
"Building";"SporeCrawler";NA;179;0
"Unit";"Hydralisk";"Larva";179;2
"Unit";"Hydralisk";"Larva";181;2
"Unit";"Hydralisk";"Larva";183;2
"Upgrade";"Burrow";"Hatchery";185;0
"Unit";"Overlord";"Larva";185;0
"Unit";"Overlord";"Larva";185;0
"Unit";"Overlord";"Larva";185;0
"Building";"CreepTumor";NA;198;0
"Building";"Hatchery";NA;198;0
"Unit";"Hydralisk";"Larva";198;2
"Unit";"Roach";"Larva";200;2
"Unit";"Roach";"Larva";202;2
"Unit";"Roach";"Larva";204;2
"Unit";"Roach";"Larva";206;2
"Unit";"Roach";"Larva";208;2
"Unit";"Roach";"Larva";210;2
"Unit";"Roach";"Larva";212;2
"Unit";"Overlord";"Larva";214;0
"Building";"CreepTumor";NA;214;0
"Building";"CreepTumor";NA;214;0
"Unit";"Overlord";"Larva";214;0
"Unit";"Overlord";"Larva";214;0
"Unit";"Overlord";"Larva";214;0
"Unit";"Overlord";"Larva";214;0
"Unit";"Overlord";"Larva";214;0
"Unit";"Overlord";"Larva";214;0
"Unit";"Overlord";"Larva";214;0
"Building";"Extractor";NA;214;0
"Unit";"Roach";"Larva";214;2
"Building";"SporeCrawler";NA;216;0
"Unit";"Overlord";"Larva";216;0
"Unit";"Roach";"Larva";216;2
"Unit";"Roach";"Larva";218;2
"Unit";"Roach";"Larva";220;2
"Unit";"Roach";"Larva";222;2
"Unit";"Hydralisk";"Larva";224;2
"Unit";"Hydralisk";"Larva";226;2
"Unit";"Hydralisk";"Larva";228;2
"Unit";"Hydralisk";"Larva";230;2
"Building";"SporeCrawler";NA;238;0
"Building";"SporeCrawler";NA;238;0
"Building";"SporeCrawler";NA;238;0
"Building";"SporeCrawler";NA;238;0
"Building";"SporeCrawler";NA;238;0
"Unit";"Viper";"Larva";238;3
"Unit";"Viper";"Larva";241;3
"Unit";"Viper";"Larva";244;3
"Unit";"Viper";"Larva";247;3
"Unit";"Hydralisk";"Larva";250;2
"Unit";"Hydralisk";"Larva";252;2
"Unit";"Hydralisk";"Larva";254;2
"Unit";"Hydralisk";"Larva";256;2
"Unit";"Roach";"Larva";258;2
"Unit";"Roach";"Larva";260;2
"Unit";"Roach";"Larva";262;2
"Unit";"Roach";"Larva";264;2
"Unit";"Roach";"Larva";266;2
"Unit";"Roach";"Larva";268;2
"Unit";"Roach";"Larva";270;2
"Unit";"Roach";"Larva";272;2
"Unit";"Roach";"Larva";274;2
"Unit";"Roach";"Larva";276;2
"Unit";"Roach";"Larva";278;2
"Unit";"Roach";"Larva";280;2
"Unit";"Roach";"Larva";282;2
"Unit";"Roach";"Larva";284;2
"Unit";"Roach";"Larva";286;2
"Unit";"Roach";"Larva";288;2
"Unit";"Hydralisk";"Larva";290;2
"Unit";"Hydralisk";"Larva";292;2
"Unit";"Hydralisk";"Larva";294;2
"Unit";"Hydralisk";"Larva";296;2
"Building";"SpawningPool";NA;298;0
"Building";"CreepTumorQueen";NA;298;0
"Building";"CreepTumorQueen";NA;298;0
"Building";"SporeCrawler";NA;304;0
"Building";"SporeCrawler";NA;304;0
"Building";"SporeCrawler";NA;304;0
"Building";"SporeCrawler";NA;304;0
"Building";"SporeCrawler";NA;304;0
"Building";"SporeCrawler";NA;304;0
"Building";"SporeCrawler";NA;305;0
"Building";"SporeCrawler";NA;306;0
"Building";"SporeCrawler";NA;307;0
"Building";"SporeCrawler";NA;313;0
"Unit";"Viper";"Larva";313;3
"Unit";"Viper";"Larva";316;3
"Building";"SporeCrawler";NA;319;0
"Building";"CreepTumor";NA;319;0
"Building";"CreepTumor";NA;319;0
"Building";"SporeCrawler";NA;319;0
"Building";"SporeCrawler";NA;319;0
"Building";"SporeCrawler";NA;319;0
"Building";"SporeCrawler";NA;319;0
"Building";"SporeCrawler";NA;319;0
"Building";"SporeCrawler";NA;319;0
"Building";"SporeCrawler";NA;319;0
"Building";"SporeCrawler";NA;319;0
"Building";"SpineCrawler";NA;319;0
"Unit";"Roach";"Larva";319;2
"Unit";"Roach";"Larva";321;2
"Unit";"Roach";"Larva";323;2
"Unit";"Roach";"Larva";325;2
"Unit";"Roach";"Larva";327;2
"Unit";"Zergling";"Larva";329;1
"Unit";"Zergling";"Larva";330;1
"Unit";"Zergling";"Larva";331;1
"Unit";"Zergling";"Larva";332;1
"Upgrade";"SprayZerg";NA;335;0
"Upgrade";"SprayZerg";NA;335;0
"Upgrade";"SprayZerg";NA;335;0
"Upgrade";"SprayZerg";NA;335;0
"Upgrade";"SprayZerg";NA;335;0
"Upgrade";"zerglingmovementspeed";NA;335;0
"Upgrade";"SprayZerg";NA;335;0
"Upgrade";"SprayZerg";NA;335;0
"Upgrade";"ZergMissileWeaponsLevel1";NA;335;0
"Upgrade";"SprayZerg";NA;335;0
"Upgrade";"EvolveMuscularAugments";NA;335;0
"Upgrade";"ZergGroundArmorsLevel1";NA;335;0
"Upgrade";"overlordspeed";NA;335;0
"Upgrade";"ZergMissileWeaponsLevel2";NA;335;0
"Upgrade";"SprayZerg";NA;335;0
