"type";"unit_name";"on_building";"total_supply_lag";"supply"
"Unit";"Overlord";"Larva";13;0
"Building";"SpawningPool";NA;17;0
"Building";"Extractor";NA;19;0
"Building";"Hatchery";NA;20;0
"Unit";"Queen";"Hatchery";20;2
"Unit";"Zergling";"Larva";22;1
"Unit";"Zergling";"Larva";23;1
"Unit";"Overlord";"Larva";24;0
"Unit";"Zergling";"Larva";25;1
"Unit";"Zergling";"Larva";26;1
"Unit";"Zergling";"Larva";28;1
"Unit";"Zergling";"Larva";29;1
"Unit";"Zergling";"Larva";30;1
"Unit";"Zergling";"Larva";31;1
"Building";"Hatchery";NA;32;0
"Unit";"Zergling";"Larva";37;1
"Unit";"Zergling";"Larva";38;1
"Unit";"Zergling";"Larva";39;1
"Unit";"Zergling";"Larva";40;1
"Building";"Hatchery";NA;41;0
"Unit";"Overlord";"Larva";41;0
"Unit";"Queen";"Hatchery";41;2
"Building";"EvolutionChamber";NA;53;0
"Building";"RoachWarren";NA;56;0
"Building";"Extractor";NA;60;0
"Unit";"Overlord";"Larva";63;0
"Building";"Extractor";NA;67;0
"Unit";"Overlord";"Larva";67;0
"Unit";"Roach";"Larva";69;2
"Unit";"Roach";"Larva";71;2
"Unit";"Roach";"Larva";73;2
"Unit";"Overlord";"Larva";75;0
"Unit";"Roach";"Larva";75;2
"Unit";"Roach";"Larva";77;2
"Unit";"Zergling";"Larva";79;1
"Unit";"Zergling";"Larva";80;1
"Unit";"Zergling";"Larva";81;1
"Unit";"Zergling";"Larva";82;1
"Unit";"Overlord";"Larva";83;0
"Unit";"Overlord";"Larva";83;0
"Unit";"Roach";"Larva";83;2
"Unit";"Zergling";"Larva";85;1
"Unit";"Zergling";"Larva";86;1
"Unit";"Zergling";"Larva";87;1
"Unit";"Zergling";"Larva";88;1
"Unit";"Zergling";"Larva";89;1
"Unit";"Zergling";"Larva";90;1
"Unit";"Zergling";"Larva";91;1
"Unit";"Zergling";"Larva";92;1
"Unit";"Roach";"Larva";93;2
"Unit";"Roach";"Larva";95;2
"Unit";"Roach";"Larva";97;2
"Unit";"Queen";"Hatchery";99;2
"Upgrade";"GlialReconstitution";"RoachWarren";101;0
"Unit";"Roach";"Larva";101;2
"Unit";"Roach";"Larva";103;2
"Unit";"Roach";"Larva";105;2
"Unit";"Roach";"Larva";107;2
"Unit";"Roach";"Larva";109;2
"Unit";"Roach";"Larva";111;2
"Unit";"Roach";"Larva";113;2
"Unit";"Overlord";"Larva";115;0
"Unit";"Roach";"Larva";115;2
"Unit";"Roach";"Larva";117;2
"Unit";"Overlord";"Larva";119;0
"Unit";"Overlord";"Larva";119;0
"Unit";"Overlord";"Larva";119;0
"Unit";"Roach";"Larva";119;2
"Unit";"Roach";"Larva";121;2
"Unit";"Roach";"Larva";123;2
"Unit";"Roach";"Larva";125;2
"Unit";"Roach";"Larva";127;2
"Unit";"Roach";"Larva";129;2
"Unit";"Roach";"Larva";131;2
"Unit";"Roach";"Larva";133;2
"Unit";"Roach";"Larva";135;2
"Unit";"Roach";"Larva";137;2
"Unit";"Roach";"Larva";139;2
"Unit";"Roach";"Larva";141;2
"Unit";"Roach";"Larva";143;2
"Unit";"Zergling";"Larva";145;1
"Unit";"Zergling";"Larva";146;1
"Unit";"Roach";"Larva";147;2
"Unit";"Roach";"Larva";149;2
"Unit";"Roach";"Larva";151;2
"Unit";"Overlord";"Larva";153;0
"Building";"CreepTumorQueen";NA;153;0
"Unit";"Overlord";"Larva";153;0
"Building";"Extractor";NA;153;0
"Unit";"Overlord";"Larva";156;0
"Building";"Extractor";NA;167;0
"Building";"InfestationPit";NA;169;0
"Building";"Extractor";NA;172;0
"Building";"CreepTumor";NA;172;0
"Unit";"Roach";"Larva";172;2
"Unit";"Roach";"Larva";174;2
"Unit";"Roach";"Larva";176;2
"Unit";"Overlord";"Larva";178;0
"Unit";"Roach";"Larva";179;2
"Unit";"Roach";"Larva";181;2
"Unit";"Overlord";"Larva";183;0
"Unit";"Overlord";"Larva";183;0
"Unit";"Overlord";"Larva";183;0
"Unit";"Roach";"Larva";183;2
"Unit";"Roach";"Larva";185;2
"Unit";"Roach";"Larva";187;2
"Unit";"Roach";"Larva";189;2
"Unit";"Overlord";"Larva";191;0
"Building";"CreepTumor";NA;191;0
"Unit";"Infestor";"Larva";191;2
"Unit";"Infestor";"Larva";193;2
"Unit";"Roach";"Larva";195;2
"Unit";"Roach";"Larva";197;2
"Unit";"Roach";"Larva";199;2
"Unit";"Roach";"Larva";201;2
"Unit";"Roach";"Larva";203;2
"Unit";"Roach";"Larva";205;2
"Unit";"Roach";"Larva";207;2
"Unit";"Roach";"Larva";209;2
"Unit";"Roach";"Larva";211;2
"Unit";"Roach";"Larva";213;2
"Unit";"Roach";"Larva";215;2
"Unit";"Roach";"Larva";217;2
"Unit";"Roach";"Larva";219;2
"Unit";"Overlord";"Larva";221;0
"Unit";"Overlord";"Larva";221;0
"Unit";"Overlord";"Larva";221;0
"Unit";"Overlord";"Larva";221;0
"Unit";"Overlord";"Larva";221;0
"Unit";"Overlord";"Larva";221;0
"Unit";"Overlord";"Larva";221;0
"Unit";"Roach";"Larva";221;2
"Unit";"Roach";"Larva";223;2
"Unit";"Roach";"Larva";225;2
"Unit";"Roach";"Larva";227;2
"Unit";"Roach";"Larva";229;2
"Unit";"Roach";"Larva";231;2
"Building";"SpineCrawler";NA;233;0
"Building";"Hatchery";NA;236;0
"Building";"HydraliskDen";NA;236;0
"Upgrade";"Burrow";"Hatchery";236;0
"Unit";"Infestor";"Larva";236;2
"Building";"SporeCrawler";NA;238;0
"Unit";"Hydralisk";"Larva";238;2
"Unit";"Hydralisk";"Larva";240;2
"Building";"SporeCrawler";NA;242;0
"Building";"SporeCrawler";NA;242;0
"Unit";"Hydralisk";"Larva";242;2
"Unit";"Overlord";"Larva";244;0
"Building";"SporeCrawler";NA;244;0
"Building";"Extractor";NA;245;0
"Unit";"Infestor";"Larva";249;2
"Building";"SpineCrawler";NA;251;0
"Building";"SpineCrawler";NA;251;0
"Unit";"Hydralisk";"Larva";251;2
"Unit";"Hydralisk";"Larva";253;2
"Building";"SpineCrawler";NA;255;0
"Building";"SpineCrawler";NA;255;0
"Unit";"Roach";"Larva";255;2
"Building";"SpineCrawler";NA;257;0
"Building";"SpineCrawler";NA;257;0
"Unit";"Hydralisk";"Larva";257;2
"Unit";"Hydralisk";"Larva";259;2
"Unit";"Hydralisk";"Larva";261;2
"Unit";"Hydralisk";"Larva";263;2
"Unit";"Hydralisk";"Larva";265;2
"Unit";"Hydralisk";"Larva";267;2
"Unit";"Roach";"Larva";269;2
"Unit";"Roach";"Larva";271;2
"Unit";"Roach";"Larva";273;2
"Unit";"Roach";"Larva";275;2
"Unit";"Roach";"Larva";277;2
"Unit";"Roach";"Larva";279;2
"Unit";"Roach";"Larva";281;2
"Unit";"Roach";"Larva";283;2
"Unit";"Roach";"Larva";285;2
"Unit";"Roach";"Larva";287;2
"Unit";"Roach";"Larva";289;2
"Unit";"Roach";"Larva";291;2
"Unit";"Roach";"Larva";293;2
"Unit";"Roach";"Larva";295;2
"Unit";"Roach";"Larva";297;2
"Unit";"Roach";"Larva";299;2
"Unit";"Roach";"Larva";301;2
"Unit";"Roach";"Larva";303;2
"Unit";"Roach";"Larva";305;2
"Unit";"Roach";"Larva";307;2
"Unit";"Roach";"Larva";309;2
"Unit";"Roach";"Larva";311;2
"Unit";"Roach";"Larva";313;2
"Unit";"Roach";"Larva";315;2
"Unit";"Roach";"Larva";317;2
"Unit";"Roach";"Larva";319;2
"Unit";"Roach";"Larva";321;2
"Unit";"Roach";"Larva";323;2
"Unit";"Viper";"Larva";325;3
"Unit";"Viper";"Larva";328;3
"Unit";"Viper";"Larva";331;3
"Unit";"Overlord";"Larva";334;0
"Unit";"Overlord";"Larva";334;0
"Unit";"Overlord";"Larva";334;0
"Unit";"Overlord";"Larva";334;0
"Unit";"Hydralisk";"Larva";334;2
"Unit";"Hydralisk";"Larva";336;2
"Unit";"Overlord";"Larva";338;0
"Unit";"Overlord";"Larva";338;0
"Unit";"Hydralisk";"Larva";338;2
"Unit";"Hydralisk";"Larva";340;2
"Unit";"Hydralisk";"Larva";342;2
"Unit";"Hydralisk";"Larva";344;2
"Unit";"Hydralisk";"Larva";346;2
"Unit";"Hydralisk";"Larva";348;2
"Unit";"Hydralisk";"Larva";350;2
"Unit";"Hydralisk";"Larva";352;2
"Upgrade";"SprayZerg";NA;354;0
"Upgrade";"SprayZerg";NA;354;0
"Upgrade";"SprayZerg";NA;354;0
"Upgrade";"SprayZerg";NA;354;0
"Upgrade";"zerglingmovementspeed";NA;354;0
"Upgrade";"SprayZerg";NA;354;0
"Upgrade";"SprayZerg";NA;354;0
"Upgrade";"ZergMissileWeaponsLevel1";NA;354;0
"Upgrade";"ZergMissileWeaponsLevel2";NA;354;0
"Upgrade";"overlordspeed";NA;354;0
"Upgrade";"SprayZerg";NA;354;0
"Upgrade";"SprayZerg";NA;354;0
"Upgrade";"ZergGroundArmorsLevel1";NA;354;0
"Upgrade";"EvolveMuscularAugments";NA;354;0
"Upgrade";"ZergMissileWeaponsLevel3";NA;354;0
