"type";"unit_name";"on_building";"total_supply_lag";"supply"
"Unit";"Overlord";"Larva";13;0
"Building";"Hatchery";NA;17;0
"Building";"Extractor";NA;19;0
"Building";"SpawningPool";NA;19;0
"Unit";"Overlord";"Larva";22;0
"Unit";"Queen";"Hatchery";23;2
"Unit";"Zergling";"Larva";25;1
"Unit";"Zergling";"Larva";26;1
"Unit";"Queen";"Hatchery";27;2
"Unit";"Zergling";"Larva";29;1
"Unit";"Zergling";"Larva";30;1
"Building";"Hatchery";NA;35;0
"Unit";"Queen";"Hatchery";36;2
"Unit";"Overlord";"Larva";39;0
"Building";"CreepTumorQueen";NA;46;0
"Unit";"Overlord";"Larva";46;0
"Unit";"Overlord";"Larva";47;0
"Unit";"Overlord";"Larva";48;0
"Unit";"Queen";"Hatchery";48;2
"Building";"BanelingNest";NA;50;0
"Building";"CreepTumor";NA;52;0
"Building";"CreepTumorQueen";NA;52;0
"Unit";"Zergling";"Larva";62;1
"Unit";"Zergling";"Larva";63;1
"Unit";"Zergling";"Larva";64;1
"Unit";"Zergling";"Larva";65;1
"Unit";"Zergling";"Larva";66;1
"Unit";"Zergling";"Larva";67;1
"Building";"CreepTumor";NA;68;0
"Building";"CreepTumor";NA;68;0
"Unit";"Overlord";"Larva";68;0
"Unit";"Zergling";"Larva";68;1
"Unit";"Zergling";"Larva";69;1
"Unit";"Zergling";"Larva";70;1
"Unit";"Zergling";"Larva";71;1
"Unit";"Queen";"Hatchery";72;2
"Unit";"Overlord";"Larva";74;0
"Unit";"Zergling";"Larva";74;1
"Unit";"Zergling";"Larva";75;1
"Building";"EvolutionChamber";NA;76;0
"Unit";"Overlord";"Larva";76;0
"Unit";"Zergling";"Larva";76;1
"Unit";"Zergling";"Larva";77;1
"Unit";"Zergling";"Larva";78;1
"Unit";"Zergling";"Larva";79;1
"Unit";"Zergling";"Larva";80;1
"Unit";"Zergling";"Larva";81;1
"Unit";"Zergling";"Larva";82;1
"Unit";"Zergling";"Larva";83;1
"Unit";"Zergling";"Larva";84;1
"Unit";"Zergling";"Larva";85;1
"Unit";"Baneling";"Zergling";86;0
"Building";"CreepTumor";NA;86;0
"Unit";"Baneling";"Zergling";86;0
"Unit";"Baneling";"Zergling";86;0
"Unit";"Baneling";"Zergling";86;0
"Unit";"Baneling";"Zergling";86;0
"Unit";"Baneling";"Zergling";86;0
"Unit";"Zergling";"Larva";86;1
"Unit";"Zergling";"Larva";87;1
"Unit";"Zergling";"Larva";88;1
"Unit";"Zergling";"Larva";89;1
"Unit";"Zergling";"Larva";90;1
"Unit";"Zergling";"Larva";91;1
"Unit";"Zergling";"Larva";92;1
"Unit";"Zergling";"Larva";93;1
"Unit";"Overlord";"Larva";97;0
"Unit";"Overlord";"Larva";108;0
"Building";"Extractor";NA;108;0
"Building";"CreepTumorQueen";NA;108;0
"Unit";"Queen";"Hatchery";108;2
"Building";"CreepTumorQueen";NA;110;0
"Building";"Extractor";NA;110;0
"Unit";"Zergling";"Larva";110;1
"Unit";"Zergling";"Larva";111;1
"Unit";"Zergling";"Larva";112;1
"Unit";"Zergling";"Larva";113;1
"Unit";"Zergling";"Larva";114;1
"Unit";"Zergling";"Larva";115;1
"Unit";"Zergling";"Larva";116;1
"Unit";"Zergling";"Larva";117;1
"Unit";"Zergling";"Larva";118;1
"Unit";"Zergling";"Larva";119;1
"Building";"Extractor";NA;121;0
"Building";"Extractor";NA;121;0
"Building";"CreepTumor";NA;121;0
"Unit";"Overlord";"Larva";121;0
"Unit";"Overlord";"Larva";124;0
"Unit";"Overlord";"Larva";124;0
"Building";"Extractor";NA;129;0
"Building";"HydraliskDen";NA;129;0
"Building";"CreepTumor";NA;129;0
"Building";"CreepTumor";NA;129;0
"Building";"Hatchery";NA;129;0
"Building";"SporeCrawler";NA;136;0
"Building";"SporeCrawler";NA;136;0
"Building";"SporeCrawler";NA;136;0
"Building";"SporeCrawler";NA;136;0
"Building";"SporeCrawler";NA;136;0
"Building";"SporeCrawler";NA;136;0
"Building";"SporeCrawler";NA;140;0
"Unit";"Overlord";"Larva";140;0
"Building";"CreepTumor";NA;140;0
"Unit";"Overlord";"Larva";144;0
"Unit";"Baneling";"Zergling";144;0
"Unit";"Baneling";"Zergling";144;0
"Unit";"Baneling";"Zergling";144;0
"Unit";"Zergling";"Larva";144;1
"Unit";"Zergling";"Larva";145;1
"Unit";"Zergling";"Larva";146;1
"Unit";"Zergling";"Larva";147;1
"Unit";"Zergling";"Larva";148;1
"Unit";"Zergling";"Larva";149;1
"Unit";"Zergling";"Larva";150;1
"Unit";"Zergling";"Larva";151;1
"Unit";"Zergling";"Larva";152;1
"Unit";"Zergling";"Larva";153;1
"Unit";"Zergling";"Larva";154;1
"Unit";"Zergling";"Larva";155;1
"Unit";"Zergling";"Larva";156;1
"Unit";"Zergling";"Larva";157;1
"Unit";"Zergling";"Larva";158;1
"Unit";"Zergling";"Larva";159;1
"Unit";"Zergling";"Larva";160;1
"Unit";"Zergling";"Larva";161;1
"Unit";"Zergling";"Larva";162;1
"Unit";"Zergling";"Larva";163;1
"Unit";"Zergling";"Larva";164;1
"Unit";"Zergling";"Larva";165;1
"Unit";"Zergling";"Larva";166;1
"Unit";"Zergling";"Larva";167;1
"Unit";"Queen";"Hatchery";171;2
"Building";"SporeCrawler";NA;173;0
"Unit";"Hydralisk";"Larva";173;2
"Unit";"Hydralisk";"Larva";175;2
"Unit";"Hydralisk";"Larva";177;2
"Unit";"Hydralisk";"Larva";179;2
"Unit";"Hydralisk";"Larva";181;2
"Unit";"Hydralisk";"Larva";183;2
"Unit";"Hydralisk";"Larva";185;2
"Unit";"Hydralisk";"Larva";188;2
"Building";"CreepTumor";NA;192;0
"Unit";"Overlord";"Larva";193;0
"Unit";"Overlord";"Larva";193;0
"Unit";"Overlord";"Larva";193;0
"Unit";"Overlord";"Larva";193;0
"Unit";"Queen";"Hatchery";193;2
"Unit";"Overlord";"Larva";195;0
"Unit";"Hydralisk";"Larva";195;2
"Unit";"Hydralisk";"Larva";197;2
"Unit";"Hydralisk";"Larva";199;2
"Unit";"Hydralisk";"Larva";201;2
"Unit";"Hydralisk";"Larva";203;2
"Unit";"Hydralisk";"Larva";205;2
"Unit";"Hydralisk";"Larva";207;2
"Unit";"Hydralisk";"Larva";209;2
"Unit";"Hydralisk";"Larva";211;2
"Building";"CreepTumor";NA;223;0
"Unit";"Overlord";"Larva";223;0
"Unit";"Overlord";"Larva";223;0
"Unit";"Overlord";"Larva";223;0
"Unit";"Overlord";"Larva";223;0
"Unit";"Queen";"Hatchery";223;2
"Building";"CreepTumor";NA;225;0
"Unit";"Hydralisk";"Larva";225;2
"Unit";"Hydralisk";"Larva";227;2
"Unit";"Hydralisk";"Larva";229;2
"Unit";"Hydralisk";"Larva";231;2
"Unit";"Overlord";"Larva";233;0
"Unit";"Overlord";"Larva";233;0
"Unit";"Overlord";"Larva";233;0
"Unit";"Hydralisk";"Larva";233;2
"Unit";"Hydralisk";"Larva";235;2
"Unit";"Zergling";"Larva";237;1
"Unit";"Zergling";"Larva";238;1
"Unit";"Zergling";"Larva";239;1
"Unit";"Zergling";"Larva";240;1
"Unit";"Zergling";"Larva";241;1
"Unit";"Zergling";"Larva";242;1
"Unit";"Baneling";"Zergling";243;0
"Unit";"Baneling";"Zergling";243;0
"Unit";"Baneling";"Zergling";243;0
"Unit";"Baneling";"Zergling";243;0
"Unit";"Baneling";"Zergling";243;0
"Unit";"Baneling";"Zergling";243;0
"Unit";"Baneling";"Zergling";243;0
"Building";"CreepTumor";NA;243;0
"Unit";"Zergling";"Larva";243;1
"Unit";"Zergling";"Larva";244;1
"Unit";"Zergling";"Larva";245;1
"Unit";"Zergling";"Larva";246;1
"Unit";"Zergling";"Larva";247;1
"Unit";"Zergling";"Larva";248;1
"Unit";"Zergling";"Larva";249;1
"Unit";"Zergling";"Larva";250;1
"Unit";"Zergling";"Larva";251;1
"Unit";"Zergling";"Larva";252;1
"Unit";"Baneling";"Zergling";253;0
"Unit";"Baneling";"Zergling";253;0
"Unit";"Hydralisk";"Larva";253;2
"Unit";"Hydralisk";"Larva";255;2
"Unit";"Hydralisk";"Larva";257;2
"Unit";"Hydralisk";"Larva";259;2
"Unit";"Hydralisk";"Larva";261;2
"Unit";"Zergling";"Larva";263;1
"Unit";"Zergling";"Larva";264;1
"Unit";"Baneling";"Zergling";265;0
"Unit";"Baneling";"Zergling";265;0
"Unit";"Baneling";"Zergling";265;0
"Unit";"Baneling";"Zergling";265;0
"Unit";"Baneling";"Zergling";265;0
"Unit";"Hydralisk";"Larva";265;2
"Unit";"Zergling";"Larva";267;1
"Unit";"Zergling";"Larva";268;1
"Unit";"Zergling";"Larva";269;1
"Unit";"Zergling";"Larva";270;1
"Unit";"Zergling";"Larva";271;1
"Unit";"Zergling";"Larva";272;1
"Unit";"Hydralisk";"Larva";273;2
"Unit";"Zergling";"Larva";275;1
"Unit";"Zergling";"Larva";276;1
"Unit";"Zergling";"Larva";277;1
"Unit";"Zergling";"Larva";278;1
"Unit";"Baneling";"Zergling";279;0
"Unit";"Baneling";"Zergling";279;0
"Unit";"Baneling";"Zergling";279;0
"Unit";"Baneling";"Zergling";279;0
"Unit";"Zergling";"Larva";279;1
"Unit";"Zergling";"Larva";280;1
"Unit";"Zergling";"Larva";281;1
"Unit";"Zergling";"Larva";282;1
"Unit";"Zergling";"Larva";283;1
"Unit";"Zergling";"Larva";284;1
"Unit";"Zergling";"Larva";285;1
"Unit";"Zergling";"Larva";286;1
"Unit";"Zergling";"Larva";287;1
"Unit";"Zergling";"Larva";288;1
"Unit";"Zergling";"Larva";289;1
"Unit";"Zergling";"Larva";290;1
"Unit";"Zergling";"Larva";291;1
"Unit";"Zergling";"Larva";292;1
"Unit";"Zergling";"Larva";293;1
"Unit";"Zergling";"Larva";294;1
"Unit";"Zergling";"Larva";295;1
"Unit";"Zergling";"Larva";296;1
"Unit";"Zergling";"Larva";297;1
"Unit";"Zergling";"Larva";298;1
"Unit";"Zergling";"Larva";299;1
"Unit";"Zergling";"Larva";300;1
"Unit";"Zergling";"Larva";301;1
"Unit";"Zergling";"Larva";302;1
"Unit";"Zergling";"Larva";303;1
"Unit";"Zergling";"Larva";304;1
"Unit";"Hydralisk";"Larva";305;2
"Unit";"Hydralisk";"Larva";307;2
"Unit";"Overlord";"Larva";309;0
"Unit";"Hydralisk";"Larva";309;2
"Unit";"Hydralisk";"Larva";311;2
"Unit";"Zergling";"Larva";313;1
"Unit";"Zergling";"Larva";314;1
"Unit";"Zergling";"Larva";315;1
"Unit";"Zergling";"Larva";316;1
"Unit";"Zergling";"Larva";317;1
"Unit";"Zergling";"Larva";318;1
"Building";"Hatchery";NA;319;0
"Unit";"Zergling";"Larva";319;1
"Unit";"Zergling";"Larva";320;1
"Unit";"Zergling";"Larva";321;1
"Unit";"Zergling";"Larva";322;1
"Unit";"Zergling";"Larva";323;1
"Unit";"Zergling";"Larva";324;1
"Unit";"Zergling";"Larva";325;1
"Unit";"Zergling";"Larva";326;1
"Unit";"Zergling";"Larva";327;1
"Unit";"Zergling";"Larva";328;1
"Unit";"Hydralisk";"Larva";329;2
"Building";"InfestationPit";NA;331;0
"Building";"CreepTumor";NA;331;0
"Unit";"Zergling";"Larva";331;1
"Unit";"Zergling";"Larva";332;1
"Unit";"Zergling";"Larva";333;1
"Unit";"Zergling";"Larva";334;1
"Unit";"Zergling";"Larva";335;1
"Unit";"Zergling";"Larva";336;1
"Unit";"Zergling";"Larva";337;1
"Unit";"Zergling";"Larva";338;1
"Unit";"Zergling";"Larva";339;1
"Unit";"Zergling";"Larva";340;1
"Unit";"Baneling";"Zergling";341;0
"Unit";"Baneling";"Zergling";341;0
"Unit";"Baneling";"Zergling";341;0
"Unit";"Baneling";"Zergling";341;0
"Unit";"Baneling";"Zergling";341;0
"Unit";"Baneling";"Zergling";341;0
"Unit";"Baneling";"Zergling";341;0
"Unit";"Baneling";"Zergling";341;0
"Unit";"Baneling";"Zergling";341;0
"Unit";"Baneling";"Zergling";341;0
"Unit";"Baneling";"Zergling";341;0
"Unit";"Baneling";"Zergling";341;0
"Unit";"Baneling";"Zergling";341;0
"Unit";"Baneling";"Zergling";341;0
"Unit";"Baneling";"Zergling";341;0
"Unit";"Baneling";"Zergling";341;0
"Unit";"Baneling";"Zergling";341;0
"Building";"CreepTumor";NA;341;0
"Unit";"Zergling";"Larva";341;1
"Unit";"Zergling";"Larva";342;1
"Unit";"Zergling";"Larva";343;1
"Unit";"Zergling";"Larva";344;1
"Unit";"Zergling";"Larva";345;1
"Unit";"Zergling";"Larva";346;1
"Unit";"Zergling";"Larva";347;1
"Unit";"Zergling";"Larva";348;1
"Unit";"Zergling";"Larva";349;1
"Unit";"Zergling";"Larva";350;1
"Unit";"Zergling";"Larva";351;1
"Unit";"Zergling";"Larva";352;1
"Unit";"Zergling";"Larva";353;1
"Unit";"Zergling";"Larva";354;1
"Unit";"Baneling";"Zergling";355;0
"Unit";"Baneling";"Zergling";355;0
"Unit";"Baneling";"Zergling";355;0
"Unit";"Baneling";"Zergling";355;0
"Unit";"Baneling";"Zergling";355;0
"Unit";"Baneling";"Zergling";355;0
"Unit";"Baneling";"Zergling";355;0
"Unit";"Zergling";"Larva";355;1
"Unit";"Zergling";"Larva";356;1
"Unit";"Zergling";"Larva";357;1
"Unit";"Zergling";"Larva";358;1
"Unit";"Zergling";"Larva";359;1
"Unit";"Zergling";"Larva";360;1
"Unit";"Zergling";"Larva";361;1
"Unit";"Zergling";"Larva";362;1
"Unit";"Zergling";"Larva";363;1
"Unit";"Zergling";"Larva";364;1
"Unit";"Zergling";"Larva";365;1
"Unit";"Zergling";"Larva";366;1
"Unit";"Zergling";"Larva";367;1
"Unit";"Zergling";"Larva";368;1
"Building";"Spire";NA;369;0
"Unit";"Zergling";"Larva";369;1
"Unit";"Zergling";"Larva";370;1
"Unit";"Zergling";"Larva";371;1
"Unit";"Zergling";"Larva";372;1
"Unit";"Zergling";"Larva";373;1
"Unit";"Zergling";"Larva";374;1
"Unit";"Zergling";"Larva";375;1
"Unit";"Zergling";"Larva";376;1
"Unit";"Hydralisk";"Larva";377;2
"Unit";"Hydralisk";"Larva";379;2
"Unit";"Hydralisk";"Larva";381;2
"Unit";"Zergling";"Larva";383;1
"Unit";"Zergling";"Larva";384;1
"Unit";"Zergling";"Larva";385;1
"Unit";"Zergling";"Larva";386;1
"Unit";"Zergling";"Larva";387;1
"Unit";"Zergling";"Larva";388;1
"Unit";"Zergling";"Larva";389;1
"Unit";"Zergling";"Larva";390;1
"Unit";"Zergling";"Larva";391;1
"Unit";"Zergling";"Larva";392;1
"Unit";"Zergling";"Larva";393;1
"Unit";"Zergling";"Larva";394;1
"Unit";"Zergling";"Larva";395;1
"Unit";"Zergling";"Larva";396;1
"Unit";"Zergling";"Larva";397;1
"Unit";"Zergling";"Larva";398;1
"Unit";"Zergling";"Larva";399;1
"Unit";"Zergling";"Larva";400;1
"Unit";"Zergling";"Larva";401;1
"Unit";"Zergling";"Larva";402;1
"Unit";"Zergling";"Larva";403;1
"Unit";"Zergling";"Larva";404;1
"Unit";"Zergling";"Larva";405;1
"Unit";"Zergling";"Larva";406;1
"Unit";"Baneling";"Zergling";407;0
"Unit";"Baneling";"Zergling";407;0
"Unit";"Baneling";"Zergling";407;0
"Unit";"Zergling";"Larva";409;1
"Unit";"Zergling";"Larva";410;1
"Unit";"Zergling";"Larva";411;1
"Unit";"Zergling";"Larva";412;1
"Unit";"Zergling";"Larva";413;1
"Unit";"Zergling";"Larva";414;1
"Unit";"Zergling";"Larva";415;1
"Unit";"Zergling";"Larva";416;1
"Unit";"Zergling";"Larva";417;1
"Unit";"Zergling";"Larva";418;1
"Unit";"Zergling";"Larva";419;1
"Unit";"Zergling";"Larva";420;1
"Unit";"Hydralisk";"Larva";421;2
"Unit";"Hydralisk";"Larva";423;2
"Unit";"Zergling";"Larva";425;1
"Unit";"Zergling";"Larva";426;1
"Unit";"Zergling";"Larva";427;1
"Unit";"Zergling";"Larva";428;1
"Unit";"Zergling";"Larva";429;1
"Unit";"Zergling";"Larva";430;1
"Unit";"Zergling";"Larva";431;1
"Unit";"Zergling";"Larva";432;1
"Unit";"Zergling";"Larva";433;1
"Unit";"Zergling";"Larva";434;1
"Unit";"Hydralisk";"Larva";435;2
"Unit";"Hydralisk";"Larva";437;2
"Unit";"Zergling";"Larva";439;1
"Unit";"Zergling";"Larva";440;1
"Unit";"Zergling";"Larva";441;1
"Unit";"Zergling";"Larva";442;1
"Unit";"Hydralisk";"Larva";443;2
"Unit";"Hydralisk";"Larva";445;2
"Unit";"Hydralisk";"Larva";447;2
"Unit";"Hydralisk";"Larva";449;2
"Unit";"Hydralisk";"Larva";451;2
"Unit";"Hydralisk";"Larva";453;2
"Unit";"Zergling";"Larva";455;1
"Unit";"Zergling";"Larva";456;1
"Unit";"Zergling";"Larva";457;1
"Unit";"Zergling";"Larva";458;1
"Unit";"Zergling";"Larva";459;1
"Unit";"Zergling";"Larva";460;1
"Unit";"Hydralisk";"Larva";461;2
"Unit";"Hydralisk";"Larva";463;2
"Unit";"Hydralisk";"Larva";465;2
"Unit";"Zergling";"Larva";467;1
"Unit";"Zergling";"Larva";468;1
"Unit";"Zergling";"Larva";469;1
"Unit";"Zergling";"Larva";470;1
"Unit";"Zergling";"Larva";471;1
"Unit";"Zergling";"Larva";472;1
"Unit";"Baneling";"Zergling";473;0
"Unit";"Baneling";"Zergling";473;0
"Unit";"Baneling";"Zergling";473;0
"Unit";"Baneling";"Zergling";473;0
"Unit";"Baneling";"Zergling";473;0
"Unit";"Baneling";"Zergling";473;0
"Unit";"Zergling";"Larva";473;1
"Unit";"Zergling";"Larva";474;1
"Unit";"Zergling";"Larva";475;1
"Unit";"Zergling";"Larva";476;1
"Unit";"Hydralisk";"Larva";477;2
"Unit";"Zergling";"Larva";479;1
"Unit";"Zergling";"Larva";480;1
"Unit";"Zergling";"Larva";481;1
"Unit";"Zergling";"Larva";482;1
"Unit";"Baneling";"Zergling";483;0
"Unit";"Baneling";"Zergling";483;0
"Unit";"Baneling";"Zergling";483;0
"Unit";"Zergling";"Larva";483;1
"Unit";"Zergling";"Larva";484;1
"Unit";"Zergling";"Larva";485;1
"Unit";"Zergling";"Larva";486;1
"Unit";"Zergling";"Larva";487;1
"Unit";"Zergling";"Larva";488;1
"Unit";"Zergling";"Larva";489;1
"Unit";"Zergling";"Larva";490;1
"Unit";"Zergling";"Larva";491;1
"Unit";"Zergling";"Larva";492;1
"Unit";"Zergling";"Larva";493;1
"Unit";"Zergling";"Larva";494;1
"Unit";"Zergling";"Larva";495;1
"Unit";"Zergling";"Larva";496;1
"Unit";"Zergling";"Larva";497;1
"Unit";"Zergling";"Larva";498;1
"Unit";"Hydralisk";"Larva";499;2
"Unit";"Hydralisk";"Larva";501;2
"Unit";"Hydralisk";"Larva";503;2
"Unit";"Zergling";"Larva";505;1
"Unit";"Zergling";"Larva";506;1
"Unit";"Zergling";"Larva";507;1
"Unit";"Zergling";"Larva";508;1
"Unit";"Zergling";"Larva";509;1
"Unit";"Zergling";"Larva";510;1
"Unit";"Hydralisk";"Larva";511;2
"Unit";"Hydralisk";"Larva";513;2
"Unit";"Hydralisk";"Larva";515;2
"Unit";"Hydralisk";"Larva";517;2
"Unit";"Hydralisk";"Larva";519;2
"Unit";"Zergling";"Larva";521;1
"Unit";"Zergling";"Larva";522;1
"Unit";"Zergling";"Larva";523;1
"Unit";"Zergling";"Larva";524;1
"Unit";"Baneling";"Zergling";525;0
"Unit";"Baneling";"Zergling";525;0
"Unit";"Baneling";"Zergling";525;0
"Unit";"Zergling";"Larva";525;1
"Unit";"Zergling";"Larva";526;1
"Unit";"Zergling";"Larva";527;1
"Unit";"Zergling";"Larva";528;1
"Unit";"Baneling";"Zergling";529;0
"Unit";"Baneling";"Zergling";529;0
"Unit";"Baneling";"Zergling";529;0
"Unit";"Baneling";"Zergling";529;0
"Unit";"Baneling";"Zergling";529;0
"Unit";"Baneling";"Zergling";529;0
"Unit";"Zergling";"Larva";529;1
"Unit";"Zergling";"Larva";530;1
"Unit";"Zergling";"Larva";531;1
"Unit";"Zergling";"Larva";532;1
"Unit";"Zergling";"Larva";533;1
"Unit";"Zergling";"Larva";534;1
"Unit";"Hydralisk";"Larva";535;2
"Unit";"Zergling";"Larva";537;1
"Unit";"Zergling";"Larva";538;1
"Unit";"Zergling";"Larva";539;1
"Unit";"Zergling";"Larva";540;1
"Unit";"Zergling";"Larva";541;1
"Unit";"Zergling";"Larva";542;1
"Unit";"Hydralisk";"Larva";543;2
"Unit";"Zergling";"Larva";545;1
"Unit";"Zergling";"Larva";546;1
"Unit";"Zergling";"Larva";547;1
"Unit";"Zergling";"Larva";548;1
"Unit";"Zergling";"Larva";549;1
"Unit";"Zergling";"Larva";550;1
"Unit";"Zergling";"Larva";551;1
"Unit";"Zergling";"Larva";552;1
"Unit";"Zergling";"Larva";553;1
"Unit";"Zergling";"Larva";554;1
"Unit";"Zergling";"Larva";555;1
"Unit";"Zergling";"Larva";556;1
"Unit";"Baneling";"Zergling";557;0
"Unit";"Baneling";"Zergling";557;0
"Unit";"Baneling";"Zergling";557;0
"Unit";"Baneling";"Zergling";557;0
"Unit";"Hydralisk";"Larva";557;2
"Unit";"Hydralisk";"Larva";559;2
"Unit";"Hydralisk";"Larva";561;2
"Unit";"Hydralisk";"Larva";563;2
"Unit";"Hydralisk";"Larva";565;2
"Unit";"Zergling";"Larva";567;1
"Unit";"Zergling";"Larva";568;1
"Unit";"Zergling";"Larva";569;1
"Unit";"Zergling";"Larva";570;1
"Unit";"Baneling";"Zergling";571;0
"Unit";"Baneling";"Zergling";571;0
"Unit";"Baneling";"Zergling";571;0
"Unit";"Hydralisk";"Larva";571;2
"Unit";"Zergling";"Larva";573;1
"Unit";"Zergling";"Larva";574;1
"Unit";"Zergling";"Larva";575;1
"Unit";"Zergling";"Larva";576;1
"Unit";"Zergling";"Larva";577;1
"Unit";"Zergling";"Larva";578;1
"Unit";"Zergling";"Larva";579;1
"Unit";"Zergling";"Larva";580;1
"Unit";"Baneling";"Zergling";581;0
"Unit";"Baneling";"Zergling";581;0
"Unit";"Zergling";"Larva";584;1
"Unit";"Zergling";"Larva";585;1
"Unit";"Hydralisk";"Larva";586;2
"Unit";"Zergling";"Larva";588;1
"Unit";"Zergling";"Larva";589;1
"Unit";"Baneling";"Zergling";590;0
"Unit";"Baneling";"Zergling";590;0
"Unit";"Baneling";"Zergling";590;0
"Unit";"Baneling";"Zergling";590;0
"Unit";"Baneling";"Zergling";590;0
"Unit";"Zergling";"Larva";590;1
"Unit";"Zergling";"Larva";591;1
"Unit";"Zergling";"Larva";592;1
"Unit";"Zergling";"Larva";593;1
"Unit";"Zergling";"Larva";594;1
"Unit";"Zergling";"Larva";595;1
"Unit";"Zergling";"Larva";596;1
"Unit";"Zergling";"Larva";597;1
"Unit";"Zergling";"Larva";598;1
"Unit";"Zergling";"Larva";599;1
"Unit";"Hydralisk";"Larva";600;2
"Unit";"Zergling";"Larva";602;1
"Unit";"Zergling";"Larva";603;1
"Unit";"Zergling";"Larva";604;1
"Unit";"Zergling";"Larva";605;1
"Unit";"Zergling";"Larva";606;1
"Unit";"Zergling";"Larva";607;1
"Unit";"Zergling";"Larva";608;1
"Unit";"Zergling";"Larva";609;1
"Unit";"Zergling";"Larva";610;1
"Unit";"Zergling";"Larva";611;1
"Unit";"Zergling";"Larva";612;1
"Unit";"Zergling";"Larva";613;1
"Unit";"Zergling";"Larva";614;1
"Unit";"Zergling";"Larva";615;1
"Unit";"Zergling";"Larva";616;1
"Unit";"Zergling";"Larva";617;1
"Unit";"Zergling";"Larva";618;1
"Unit";"Zergling";"Larva";619;1
"Unit";"Zergling";"Larva";620;1
"Unit";"Zergling";"Larva";621;1
"Unit";"Zergling";"Larva";622;1
"Unit";"Zergling";"Larva";623;1
"Unit";"Zergling";"Larva";624;1
"Unit";"Zergling";"Larva";625;1
"Unit";"Zergling";"Larva";626;1
"Unit";"Zergling";"Larva";627;1
"Unit";"Zergling";"Larva";628;1
"Unit";"Zergling";"Larva";629;1
"Unit";"Zergling";"Larva";630;1
"Unit";"Zergling";"Larva";631;1
"Unit";"Baneling";"Zergling";632;0
"Unit";"Mutalisk";"Larva";632;2
"Unit";"Mutalisk";"Larva";634;2
"Unit";"Mutalisk";"Larva";636;2
"Unit";"Zergling";"Larva";642;1
"Unit";"Zergling";"Larva";643;1
"Unit";"Zergling";"Larva";644;1
"Unit";"Zergling";"Larva";645;1
"Unit";"Zergling";"Larva";646;1
"Unit";"Zergling";"Larva";647;1
"Unit";"Zergling";"Larva";648;1
"Unit";"Zergling";"Larva";649;1
"Unit";"Zergling";"Larva";650;1
"Unit";"Zergling";"Larva";651;1
"Unit";"Zergling";"Larva";652;1
"Unit";"Zergling";"Larva";653;1
"Unit";"Hydralisk";"Larva";654;2
"Unit";"Hydralisk";"Larva";656;2
"Unit";"Hydralisk";"Larva";658;2
"Unit";"Overlord";"Larva";660;0
"Unit";"Hydralisk";"Larva";660;2
"Unit";"Hydralisk";"Larva";662;2
"Unit";"Zergling";"Larva";664;1
"Unit";"Zergling";"Larva";665;1
"Unit";"Zergling";"Larva";666;1
"Unit";"Zergling";"Larva";667;1
"Unit";"Zergling";"Larva";668;1
"Unit";"Zergling";"Larva";669;1
"Unit";"Zergling";"Larva";670;1
"Unit";"Zergling";"Larva";671;1
"Unit";"Zergling";"Larva";672;1
"Unit";"Zergling";"Larva";673;1
"Building";"CreepTumor";NA;674;0
"Unit";"Corruptor";"Larva";674;2
"Unit";"Corruptor";"Larva";676;2
"Unit";"Baneling";"Zergling";678;0
"Unit";"Baneling";"Zergling";678;0
"Building";"Extractor";NA;678;0
"Building";"Extractor";NA;678;0
"Unit";"Zergling";"Larva";678;1
"Unit";"Zergling";"Larva";679;1
"Unit";"Zergling";"Larva";680;1
"Unit";"Zergling";"Larva";681;1
"Unit";"Zergling";"Larva";682;1
"Unit";"Zergling";"Larva";683;1
"Unit";"Zergling";"Larva";684;1
"Unit";"Zergling";"Larva";685;1
"Unit";"Zergling";"Larva";686;1
"Unit";"Zergling";"Larva";687;1
"Unit";"Zergling";"Larva";688;1
"Unit";"Zergling";"Larva";689;1
"Unit";"Zergling";"Larva";690;1
"Unit";"Zergling";"Larva";691;1
"Unit";"Zergling";"Larva";692;1
"Unit";"Zergling";"Larva";693;1
"Unit";"Zergling";"Larva";694;1
"Unit";"Zergling";"Larva";695;1
"Unit";"Baneling";"Zergling";696;0
"Unit";"Baneling";"Zergling";696;0
"Unit";"Baneling";"Zergling";696;0
"Unit";"Baneling";"Zergling";696;0
"Unit";"Baneling";"Zergling";696;0
"Unit";"Baneling";"Zergling";696;0
"Unit";"Zergling";"Larva";696;1
"Unit";"Zergling";"Larva";697;1
"Unit";"Zergling";"Larva";698;1
"Unit";"Zergling";"Larva";699;1
"Unit";"Corruptor";"Larva";700;2
"Unit";"Corruptor";"Larva";702;2
"Unit";"Zergling";"Larva";704;1
"Unit";"Zergling";"Larva";705;1
"Unit";"Zergling";"Larva";706;1
"Unit";"Zergling";"Larva";707;1
"Unit";"Zergling";"Larva";708;1
"Unit";"Zergling";"Larva";709;1
"Unit";"Zergling";"Larva";710;1
"Unit";"Zergling";"Larva";711;1
"Unit";"Zergling";"Larva";712;1
"Unit";"Zergling";"Larva";713;1
"Unit";"Zergling";"Larva";714;1
"Unit";"Zergling";"Larva";715;1
"Unit";"Zergling";"Larva";716;1
"Unit";"Zergling";"Larva";717;1
"Unit";"Zergling";"Larva";718;1
"Unit";"Zergling";"Larva";719;1
"Unit";"Zergling";"Larva";720;1
"Unit";"Zergling";"Larva";721;1
"Unit";"Zergling";"Larva";722;1
"Unit";"Zergling";"Larva";723;1
"Unit";"Zergling";"Larva";724;1
"Unit";"Zergling";"Larva";725;1
"Unit";"Zergling";"Larva";726;1
"Unit";"Zergling";"Larva";727;1
"Unit";"Zergling";"Larva";728;1
"Unit";"Zergling";"Larva";729;1
"Unit";"Zergling";"Larva";730;1
"Unit";"Zergling";"Larva";731;1
"Unit";"Zergling";"Larva";732;1
"Unit";"Zergling";"Larva";733;1
"Unit";"Zergling";"Larva";734;1
"Unit";"Zergling";"Larva";735;1
"Unit";"Zergling";"Larva";736;1
"Unit";"Zergling";"Larva";737;1
"Unit";"Zergling";"Larva";738;1
"Unit";"Zergling";"Larva";739;1
"Unit";"Zergling";"Larva";740;1
"Unit";"Zergling";"Larva";741;1
"Unit";"Zergling";"Larva";742;1
"Unit";"Zergling";"Larva";743;1
"Unit";"Zergling";"Larva";744;1
"Unit";"Zergling";"Larva";745;1
"Unit";"Zergling";"Larva";746;1
"Unit";"Zergling";"Larva";747;1
"Unit";"Zergling";"Larva";748;1
"Unit";"Zergling";"Larva";749;1
"Unit";"Zergling";"Larva";750;1
"Unit";"Zergling";"Larva";751;1
"Unit";"Zergling";"Larva";752;1
"Unit";"Zergling";"Larva";753;1
"Unit";"Baneling";"Zergling";754;0
"Unit";"Baneling";"Zergling";754;0
"Unit";"Baneling";"Zergling";754;0
"Unit";"Baneling";"Zergling";754;0
"Unit";"Zergling";"Larva";754;1
"Unit";"Zergling";"Larva";755;1
"Unit";"Zergling";"Larva";756;1
"Unit";"Zergling";"Larva";757;1
"Unit";"Zergling";"Larva";758;1
"Unit";"Zergling";"Larva";759;1
"Unit";"Zergling";"Larva";760;1
"Unit";"Zergling";"Larva";761;1
"Unit";"Zergling";"Larva";762;1
"Unit";"Zergling";"Larva";763;1
"Unit";"Zergling";"Larva";764;1
"Unit";"Zergling";"Larva";765;1
"Unit";"Zergling";"Larva";766;1
"Unit";"Zergling";"Larva";767;1
"Unit";"Zergling";"Larva";768;1
"Unit";"Zergling";"Larva";769;1
"Unit";"Zergling";"Larva";770;1
"Unit";"Zergling";"Larva";771;1
"Unit";"Zergling";"Larva";772;1
"Unit";"Zergling";"Larva";773;1
"Unit";"Hydralisk";"Larva";774;2
"Unit";"Hydralisk";"Larva";776;2
"Unit";"Zergling";"Larva";778;1
"Unit";"Zergling";"Larva";779;1
"Unit";"Zergling";"Larva";780;1
"Unit";"Zergling";"Larva";781;1
"Unit";"Zergling";"Larva";782;1
"Unit";"Zergling";"Larva";783;1
"Unit";"Zergling";"Larva";784;1
"Unit";"Zergling";"Larva";785;1
"Unit";"Hydralisk";"Larva";786;2
"Unit";"Hydralisk";"Larva";788;2
"Unit";"Zergling";"Larva";790;1
"Unit";"Zergling";"Larva";791;1
"Unit";"Zergling";"Larva";792;1
"Unit";"Zergling";"Larva";793;1
"Unit";"Zergling";"Larva";794;1
"Unit";"Zergling";"Larva";795;1
"Unit";"Zergling";"Larva";796;1
"Unit";"Zergling";"Larva";797;1
"Upgrade";"SprayZerg";NA;798;0
"Upgrade";"SprayZerg";NA;798;0
"Upgrade";"SprayZerg";NA;798;0
"Upgrade";"zerglingmovementspeed";NA;798;0
"Upgrade";"SprayZerg";NA;798;0
"Upgrade";"SprayZerg";NA;798;0
"Upgrade";"SprayZerg";NA;798;0
"Upgrade";"ZergMeleeWeaponsLevel1";NA;798;0
"Upgrade";"EvolveMuscularAugments";NA;798;0
"Upgrade";"CentrificalHooks";NA;798;0
"Upgrade";"ZergMeleeWeaponsLevel2";NA;798;0
"Upgrade";"SprayZerg";NA;798;0
"Upgrade";"SprayZerg";NA;798;0
"Upgrade";"ZergMissileWeaponsLevel1";NA;798;0
"Upgrade";"overlordspeed";NA;798;0
"Upgrade";"ZergMeleeWeaponsLevel3";NA;798;0
"Upgrade";"zerglingattackspeed";NA;798;0
