"type";"unit_name";"on_building";"total_supply_lag";"supply"
"Unit";"Overlord";"Larva";13;0
"Building";"Hatchery";NA;19;0
"Building";"Extractor";NA;19;0
"Building";"SpawningPool";NA;19;0
"Unit";"Overlord";"Larva";22;0
"Unit";"Queen";"Hatchery";24;2
"Unit";"Zergling";"Larva";26;1
"Unit";"Zergling";"Larva";27;1
"Unit";"Queen";"Hatchery";28;2
"Building";"Hatchery";NA;35;0
"Unit";"Overlord";"Larva";36;0
"Unit";"Queen";"Hatchery";36;2
"Unit";"Zergling";"Larva";38;1
"Unit";"Zergling";"Larva";39;1
"Unit";"Zergling";"Larva";40;1
"Unit";"Zergling";"Larva";41;1
"Unit";"Zergling";"Larva";42;1
"Unit";"Zergling";"Larva";43;1
"Unit";"Zergling";"Larva";44;1
"Unit";"Zergling";"Larva";45;1
"Unit";"Overlord";"Larva";49;0
"Unit";"Zergling";"Larva";49;1
"Unit";"Zergling";"Larva";50;1
"Unit";"Zergling";"Larva";51;1
"Unit";"Zergling";"Larva";52;1
"Unit";"Zergling";"Larva";53;1
"Unit";"Zergling";"Larva";54;1
"Unit";"Overlord";"Larva";56;0
"Unit";"Queen";"Hatchery";57;2
"Unit";"Overlord";"Larva";59;0
"Unit";"Queen";"Hatchery";63;2
"Unit";"Overlord";"Larva";74;0
"Building";"SporeCrawler";NA;74;0
"Unit";"Overlord";"Larva";82;0
"Building";"CreepTumorQueen";NA;82;0
"Building";"Extractor";NA;82;0
"Building";"SporeCrawler";NA;82;0
"Building";"SporeCrawler";NA;83;0
"Building";"EvolutionChamber";NA;94;0
"Building";"CreepTumor";NA;100;0
"Building";"CreepTumorQueen";NA;100;0
"Building";"Hatchery";NA;100;0
"Building";"BanelingNest";NA;100;0
"Unit";"Queen";"Hatchery";105;2
"Building";"Extractor";NA;107;0
"Building";"Extractor";NA;107;0
"Building";"Extractor";NA;107;0
"Unit";"Overlord";"Larva";107;0
"Unit";"Overlord";"Larva";107;0
"Building";"CreepTumorQueen";NA;107;0
"Building";"CreepTumorQueen";NA;107;0
"Unit";"Overlord";"Larva";107;0
"Unit";"Overlord";"Larva";110;0
"Unit";"Overlord";"Larva";110;0
"Building";"CreepTumor";NA;110;0
"Building";"CreepTumorQueen";NA;110;0
"Unit";"Zergling";"Larva";110;1
"Unit";"Zergling";"Larva";111;1
"Unit";"Zergling";"Larva";112;1
"Unit";"Zergling";"Larva";113;1
"Unit";"Zergling";"Larva";114;1
"Unit";"Zergling";"Larva";115;1
"Unit";"Zergling";"Larva";116;1
"Unit";"Zergling";"Larva";117;1
"Unit";"Zergling";"Larva";118;1
"Unit";"Zergling";"Larva";119;1
"Unit";"Zergling";"Larva";120;1
"Unit";"Zergling";"Larva";121;1
"Building";"HydraliskDen";NA;122;0
"Building";"CreepTumorQueen";NA;122;0
"Building";"CreepTumor";NA;122;0
"Building";"CreepTumorQueen";NA;122;0
"Building";"Extractor";NA;123;0
"Unit";"Zergling";"Larva";123;1
"Unit";"Zergling";"Larva";124;1
"Unit";"Zergling";"Larva";125;1
"Unit";"Zergling";"Larva";126;1
"Unit";"Zergling";"Larva";127;1
"Unit";"Zergling";"Larva";128;1
"Unit";"Zergling";"Larva";129;1
"Unit";"Zergling";"Larva";130;1
"Unit";"Zergling";"Larva";131;1
"Unit";"Zergling";"Larva";132;1
"Unit";"Zergling";"Larva";133;1
"Unit";"Zergling";"Larva";134;1
"Unit";"Zergling";"Larva";135;1
"Unit";"Zergling";"Larva";136;1
"Unit";"Zergling";"Larva";137;1
"Unit";"Zergling";"Larva";138;1
"Unit";"Zergling";"Larva";139;1
"Unit";"Zergling";"Larva";140;1
"Building";"CreepTumor";NA;141;0
"Unit";"Queen";"Hatchery";141;2
"Unit";"Queen";"Hatchery";143;2
"Unit";"Overlord";"Larva";145;0
"Unit";"Overlord";"Larva";145;0
"Unit";"Overlord";"Larva";145;0
"Unit";"Hydralisk";"Larva";145;2
"Unit";"Hydralisk";"Larva";147;2
"Unit";"Hydralisk";"Larva";149;2
"Unit";"Baneling";"Zergling";151;0
"Unit";"Baneling";"Zergling";151;0
"Unit";"Baneling";"Zergling";151;0
"Unit";"Baneling";"Zergling";151;0
"Unit";"Baneling";"Zergling";151;0
"Unit";"Hydralisk";"Larva";151;2
"Unit";"Hydralisk";"Larva";153;2
"Unit";"Hydralisk";"Larva";155;2
"Unit";"Hydralisk";"Larva";157;2
"Unit";"Zergling";"Larva";159;1
"Unit";"Zergling";"Larva";160;1
"Unit";"Zergling";"Larva";161;1
"Unit";"Zergling";"Larva";162;1
"Unit";"Zergling";"Larva";163;1
"Unit";"Zergling";"Larva";164;1
"Unit";"Zergling";"Larva";165;1
"Unit";"Zergling";"Larva";166;1
"Unit";"Zergling";"Larva";167;1
"Unit";"Zergling";"Larva";168;1
"Unit";"Zergling";"Larva";169;1
"Unit";"Zergling";"Larva";170;1
"Unit";"Zergling";"Larva";171;1
"Unit";"Zergling";"Larva";172;1
"Unit";"Zergling";"Larva";173;1
"Unit";"Zergling";"Larva";174;1
"Unit";"Baneling";"Zergling";175;0
"Unit";"Baneling";"Zergling";175;0
"Unit";"Baneling";"Zergling";175;0
"Unit";"Baneling";"Zergling";175;0
"Unit";"Hydralisk";"Larva";175;2
"Unit";"Zergling";"Larva";177;1
"Unit";"Zergling";"Larva";178;1
"Unit";"Zergling";"Larva";179;1
"Unit";"Zergling";"Larva";180;1
"Unit";"Zergling";"Larva";181;1
"Unit";"Zergling";"Larva";182;1
"Unit";"Zergling";"Larva";183;1
"Unit";"Zergling";"Larva";184;1
"Unit";"Zergling";"Larva";185;1
"Unit";"Zergling";"Larva";186;1
"Unit";"Zergling";"Larva";187;1
"Unit";"Zergling";"Larva";188;1
"Unit";"Hydralisk";"Larva";189;2
"Unit";"Zergling";"Larva";191;1
"Unit";"Zergling";"Larva";192;1
"Unit";"Zergling";"Larva";193;1
"Unit";"Zergling";"Larva";194;1
"Unit";"Zergling";"Larva";195;1
"Unit";"Zergling";"Larva";196;1
"Unit";"Zergling";"Larva";197;1
"Unit";"Zergling";"Larva";198;1
"Unit";"Hydralisk";"Larva";199;2
"Unit";"Zergling";"Larva";201;1
"Unit";"Zergling";"Larva";202;1
"Unit";"Zergling";"Larva";203;1
"Unit";"Zergling";"Larva";204;1
"Unit";"Zergling";"Larva";205;1
"Unit";"Zergling";"Larva";206;1
"Unit";"Zergling";"Larva";207;1
"Unit";"Zergling";"Larva";208;1
"Unit";"Zergling";"Larva";209;1
"Unit";"Zergling";"Larva";210;1
"Unit";"Hydralisk";"Larva";211;2
"Unit";"Hydralisk";"Larva";213;2
"Unit";"Hydralisk";"Larva";215;2
"Building";"CreepTumor";NA;222;0
"Building";"CreepTumor";NA;222;0
"Building";"CreepTumor";NA;223;0
"Building";"CreepTumor";NA;240;0
"Unit";"Queen";"Hatchery";240;2
"Building";"CreepTumor";NA;246;0
"Building";"CreepTumor";NA;246;0
"Building";"SporeCrawler";NA;249;0
"Unit";"Hydralisk";"Larva";249;2
"Unit";"Hydralisk";"Larva";251;2
"Unit";"Hydralisk";"Larva";253;2
"Building";"CreepTumorQueen";NA;255;0
"Building";"SporeCrawler";NA;261;0
"Unit";"Hydralisk";"Larva";263;2
"Unit";"Hydralisk";"Larva";265;2
"Unit";"Hydralisk";"Larva";267;2
"Unit";"Queen";"Hatchery";270;2
"Unit";"Queen";"Hatchery";272;2
"Building";"CreepTumor";NA;274;0
"Building";"CreepTumor";NA;274;0
"Building";"CreepTumor";NA;277;0
"Building";"CreepTumor";NA;278;0
"Unit";"Hydralisk";"Larva";278;2
"Unit";"Hydralisk";"Larva";280;2
"Unit";"Zergling";"Larva";284;1
"Unit";"Zergling";"Larva";285;1
"Unit";"Zergling";"Larva";286;1
"Unit";"Zergling";"Larva";287;1
"Unit";"Zergling";"Larva";288;1
"Unit";"Zergling";"Larva";289;1
"Unit";"Hydralisk";"Larva";290;2
"Unit";"Hydralisk";"Larva";292;2
"Unit";"Hydralisk";"Larva";294;2
"Building";"CreepTumor";NA;296;0
"Building";"CreepTumor";NA;296;0
"Building";"CreepTumor";NA;296;0
"Building";"CreepTumor";NA;296;0
"Unit";"Zergling";"Larva";296;1
"Unit";"Zergling";"Larva";297;1
"Unit";"Zergling";"Larva";298;1
"Unit";"Zergling";"Larva";299;1
"Unit";"Zergling";"Larva";300;1
"Unit";"Zergling";"Larva";301;1
"Unit";"Zergling";"Larva";302;1
"Unit";"Zergling";"Larva";303;1
"Unit";"Zergling";"Larva";304;1
"Unit";"Zergling";"Larva";305;1
"Unit";"Zergling";"Larva";306;1
"Unit";"Zergling";"Larva";307;1
"Unit";"Zergling";"Larva";308;1
"Unit";"Zergling";"Larva";309;1
"Unit";"Hydralisk";"Larva";310;2
"Unit";"Hydralisk";"Larva";312;2
"Unit";"Hydralisk";"Larva";314;2
"Unit";"Hydralisk";"Larva";316;2
"Unit";"Hydralisk";"Larva";318;2
"Unit";"Hydralisk";"Larva";320;2
"Unit";"Baneling";"Zergling";322;0
"Unit";"Baneling";"Zergling";322;0
"Unit";"Baneling";"Zergling";322;0
"Unit";"Baneling";"Zergling";322;0
"Unit";"Zergling";"Larva";322;1
"Unit";"Zergling";"Larva";323;1
"Unit";"Zergling";"Larva";324;1
"Unit";"Zergling";"Larva";325;1
"Unit";"Zergling";"Larva";326;1
"Unit";"Zergling";"Larva";327;1
"Unit";"Zergling";"Larva";328;1
"Unit";"Zergling";"Larva";329;1
"Unit";"Zergling";"Larva";330;1
"Unit";"Zergling";"Larva";331;1
"Unit";"Zergling";"Larva";332;1
"Unit";"Zergling";"Larva";333;1
"Unit";"Zergling";"Larva";334;1
"Unit";"Zergling";"Larva";335;1
"Unit";"Zergling";"Larva";336;1
"Unit";"Zergling";"Larva";337;1
"Unit";"Baneling";"Zergling";338;0
"Unit";"Baneling";"Zergling";338;0
"Unit";"Baneling";"Zergling";338;0
"Unit";"Baneling";"Zergling";338;0
"Unit";"Baneling";"Zergling";338;0
"Unit";"Baneling";"Zergling";338;0
"Unit";"Baneling";"Zergling";338;0
"Unit";"Baneling";"Zergling";338;0
"Unit";"Baneling";"Zergling";338;0
"Unit";"Baneling";"Zergling";338;0
"Unit";"Zergling";"Larva";338;1
"Unit";"Zergling";"Larva";339;1
"Unit";"Zergling";"Larva";340;1
"Unit";"Zergling";"Larva";341;1
"Unit";"Zergling";"Larva";342;1
"Unit";"Zergling";"Larva";343;1
"Unit";"Zergling";"Larva";344;1
"Unit";"Zergling";"Larva";345;1
"Unit";"Zergling";"Larva";346;1
"Unit";"Zergling";"Larva";347;1
"Unit";"Zergling";"Larva";348;1
"Unit";"Zergling";"Larva";349;1
"Unit";"Zergling";"Larva";350;1
"Unit";"Zergling";"Larva";351;1
"Unit";"Zergling";"Larva";352;1
"Unit";"Zergling";"Larva";353;1
"Unit";"Zergling";"Larva";354;1
"Unit";"Zergling";"Larva";355;1
"Unit";"Zergling";"Larva";356;1
"Unit";"Zergling";"Larva";357;1
"Unit";"Zergling";"Larva";358;1
"Unit";"Zergling";"Larva";359;1
"Unit";"Zergling";"Larva";360;1
"Unit";"Zergling";"Larva";361;1
"Unit";"Zergling";"Larva";362;1
"Unit";"Zergling";"Larva";363;1
"Unit";"Zergling";"Larva";364;1
"Unit";"Zergling";"Larva";365;1
"Unit";"Zergling";"Larva";366;1
"Unit";"Zergling";"Larva";367;1
"Unit";"Zergling";"Larva";368;1
"Unit";"Zergling";"Larva";369;1
"Unit";"Zergling";"Larva";370;1
"Unit";"Zergling";"Larva";371;1
"Unit";"Zergling";"Larva";372;1
"Unit";"Zergling";"Larva";373;1
"Unit";"Overlord";"Larva";375;0
"Unit";"Overlord";"Larva";375;0
"Unit";"Overlord";"Larva";375;0
"Building";"CreepTumor";NA;375;0
"Building";"CreepTumor";NA;375;0
"Building";"CreepTumor";NA;375;0
"Unit";"Baneling";"Zergling";375;0
"Unit";"Baneling";"Zergling";375;0
"Unit";"Baneling";"Zergling";375;0
"Unit";"Baneling";"Zergling";375;0
"Unit";"Baneling";"Zergling";375;0
"Unit";"Baneling";"Zergling";375;0
"Unit";"Baneling";"Zergling";375;0
"Unit";"Baneling";"Zergling";375;0
"Unit";"Baneling";"Zergling";375;0
"Unit";"Baneling";"Zergling";375;0
"Unit";"Baneling";"Zergling";375;0
"Unit";"Baneling";"Zergling";375;0
"Unit";"Baneling";"Zergling";375;0
"Unit";"Baneling";"Zergling";375;0
"Unit";"Baneling";"Zergling";375;0
"Unit";"Hydralisk";"Larva";375;2
"Unit";"Hydralisk";"Larva";377;2
"Unit";"Baneling";"Zergling";379;0
"Unit";"Baneling";"Zergling";379;0
"Unit";"Baneling";"Zergling";379;0
"Unit";"Baneling";"Zergling";379;0
"Unit";"Baneling";"Zergling";379;0
"Unit";"Zergling";"Larva";379;1
"Unit";"Zergling";"Larva";380;1
"Unit";"Zergling";"Larva";381;1
"Unit";"Zergling";"Larva";382;1
"Unit";"Zergling";"Larva";383;1
"Unit";"Zergling";"Larva";384;1
"Unit";"Zergling";"Larva";385;1
"Unit";"Zergling";"Larva";386;1
"Unit";"Zergling";"Larva";387;1
"Unit";"Zergling";"Larva";388;1
"Unit";"Zergling";"Larva";389;1
"Unit";"Zergling";"Larva";390;1
"Unit";"Zergling";"Larva";391;1
"Unit";"Zergling";"Larva";392;1
"Unit";"Zergling";"Larva";393;1
"Unit";"Zergling";"Larva";394;1
"Unit";"Zergling";"Larva";395;1
"Unit";"Zergling";"Larva";396;1
"Unit";"Zergling";"Larva";397;1
"Unit";"Zergling";"Larva";398;1
"Unit";"Zergling";"Larva";399;1
"Unit";"Zergling";"Larva";400;1
"Unit";"Zergling";"Larva";401;1
"Unit";"Zergling";"Larva";402;1
"Unit";"Zergling";"Larva";403;1
"Unit";"Zergling";"Larva";404;1
"Unit";"Zergling";"Larva";405;1
"Unit";"Zergling";"Larva";406;1
"Unit";"Zergling";"Larva";407;1
"Unit";"Zergling";"Larva";408;1
"Unit";"Zergling";"Larva";409;1
"Unit";"Zergling";"Larva";410;1
"Unit";"Zergling";"Larva";411;1
"Unit";"Zergling";"Larva";412;1
"Unit";"Zergling";"Larva";413;1
"Unit";"Zergling";"Larva";414;1
"Unit";"Zergling";"Larva";415;1
"Unit";"Zergling";"Larva";416;1
"Unit";"Zergling";"Larva";417;1
"Unit";"Zergling";"Larva";418;1
"Upgrade";"SprayZerg";NA;419;0
"Upgrade";"SprayZerg";NA;419;0
"Upgrade";"SprayZerg";NA;419;0
"Upgrade";"zerglingmovementspeed";NA;419;0
"Upgrade";"SprayZerg";NA;419;0
"Upgrade";"SprayZerg";NA;419;0
"Upgrade";"SprayZerg";NA;419;0
"Upgrade";"ZergMissileWeaponsLevel1";NA;419;0
"Upgrade";"EvolveMuscularAugments";NA;419;0
