"type";"unit_name";"on_building";"total_supply_lag";"supply"
"Unit";"Overlord";"Larva";13;0
"Building";"Hatchery";NA;17;0
"Building";"Extractor";NA;19;0
"Building";"SpawningPool";NA;19;0
"Unit";"Overlord";"Larva";22;0
"Unit";"Queen";"Hatchery";23;2
"Unit";"Zergling";"Larva";25;1
"Unit";"Zergling";"Larva";26;1
"Unit";"Queen";"Hatchery";27;2
"Unit";"Zergling";"Larva";29;1
"Unit";"Zergling";"Larva";30;1
"Building";"Hatchery";NA;36;0
"Unit";"Queen";"Hatchery";39;2
"Unit";"Overlord";"Larva";41;0
"Unit";"Overlord";"Larva";42;0
"Unit";"Overlord";"Larva";42;0
"Building";"CreepTumorQueen";NA;42;0
"Unit";"Zergling";"Larva";42;1
"Unit";"Zergling";"Larva";43;1
"Unit";"Queen";"Hatchery";50;2
"Building";"SporeCrawler";NA;58;0
"Building";"SporeCrawler";NA;58;0
"Building";"CreepTumor";NA;58;0
"Building";"CreepTumorQueen";NA;58;0
"Unit";"Queen";"Hatchery";60;2
"Building";"CreepTumorQueen";NA;65;0
"Building";"EvolutionChamber";NA;65;0
"Unit";"Overlord";"Larva";65;0
"Unit";"Zergling";"Larva";65;1
"Unit";"Zergling";"Larva";66;1
"Unit";"Zergling";"Larva";67;1
"Unit";"Zergling";"Larva";68;1
"Building";"SporeCrawler";NA;70;0
"Building";"CreepTumor";NA;70;0
"Unit";"Overlord";"Larva";72;0
"Building";"CreepTumorQueen";NA;74;0
"Unit";"Overlord";"Larva";74;0
"Unit";"Zergling";"Larva";74;1
"Unit";"Zergling";"Larva";75;1
"Unit";"Zergling";"Larva";76;1
"Unit";"Zergling";"Larva";77;1
"Unit";"Zergling";"Larva";78;1
"Unit";"Zergling";"Larva";79;1
"Unit";"Zergling";"Larva";80;1
"Unit";"Zergling";"Larva";81;1
"Unit";"Zergling";"Larva";82;1
"Unit";"Zergling";"Larva";83;1
"Unit";"Zergling";"Larva";84;1
"Unit";"Zergling";"Larva";85;1
"Building";"CreepTumor";NA;86;0
"Unit";"Zergling";"Larva";87;1
"Unit";"Zergling";"Larva";88;1
"Unit";"Zergling";"Larva";89;1
"Unit";"Zergling";"Larva";90;1
"Unit";"Overlord";"Larva";91;0
"Building";"CreepTumor";NA;99;0
"Building";"CreepTumorQueen";NA;99;0
"Building";"CreepTumorQueen";NA;99;0
"Building";"Extractor";NA;102;0
"Building";"Extractor";NA;102;0
"Building";"Extractor";NA;102;0
"Unit";"Zergling";"Larva";102;1
"Unit";"Zergling";"Larva";103;1
"Building";"Hatchery";NA;104;0
"Unit";"Zergling";"Larva";104;1
"Unit";"Zergling";"Larva";105;1
"Unit";"Zergling";"Larva";106;1
"Unit";"Zergling";"Larva";107;1
"Unit";"Zergling";"Larva";108;1
"Unit";"Zergling";"Larva";109;1
"Building";"BanelingNest";NA;110;0
"Unit";"Overlord";"Larva";114;0
"Building";"CreepTumor";NA;115;0
"Building";"Extractor";NA;115;0
"Building";"CreepTumor";NA;116;0
"Building";"CreepTumor";NA;116;0
"Building";"CreepTumor";NA;116;0
"Building";"CreepTumor";NA;116;0
"Unit";"Overlord";"Larva";116;0
"Unit";"Overlord";"Larva";121;0
"Unit";"Overlord";"Larva";129;0
"Building";"Extractor";NA;129;0
"Building";"HydraliskDen";NA;129;0
"Building";"Hatchery";NA;129;0
"Building";"CreepTumor";NA;139;0
"Building";"CreepTumor";NA;139;0
"Building";"CreepTumor";NA;139;0
"Building";"CreepTumor";NA;139;0
"Unit";"Queen";"Hatchery";143;2
"Building";"SporeCrawler";NA;145;0
"Unit";"Overlord";"Larva";145;0
"Unit";"Hydralisk";"Larva";145;2
"Unit";"Hydralisk";"Larva";147;2
"Unit";"Hydralisk";"Larva";149;2
"Building";"CreepTumor";NA;151;0
"Building";"CreepTumor";NA;151;0
"Unit";"Hydralisk";"Larva";151;2
"Unit";"Hydralisk";"Larva";153;2
"Unit";"Overlord";"Larva";155;0
"Unit";"Overlord";"Larva";155;0
"Unit";"Hydralisk";"Larva";155;2
"Building";"CreepTumorQueen";NA;157;0
"Unit";"Hydralisk";"Larva";157;2
"Unit";"Hydralisk";"Larva";159;2
"Building";"CreepTumorQueen";NA;161;0
"Building";"CreepTumor";NA;161;0
"Building";"CreepTumor";NA;161;0
"Building";"CreepTumor";NA;161;0
"Unit";"Hydralisk";"Larva";161;2
"Unit";"Hydralisk";"Larva";163;2
"Unit";"Hydralisk";"Larva";165;2
"Unit";"Hydralisk";"Larva";167;2
"Building";"CreepTumorQueen";NA;169;0
"Building";"CreepTumorQueen";NA;169;0
"Unit";"Hydralisk";"Larva";169;2
"Unit";"Hydralisk";"Larva";171;2
"Unit";"Hydralisk";"Larva";173;2
"Unit";"Hydralisk";"Larva";175;2
"Unit";"Hydralisk";"Larva";177;2
"Unit";"Hydralisk";"Larva";179;2
"Unit";"Hydralisk";"Larva";181;2
"Unit";"Hydralisk";"Larva";183;2
"Building";"CreepTumorQueen";NA;186;0
"Building";"CreepTumorQueen";NA;186;0
"Building";"CreepTumorQueen";NA;186;0
"Unit";"Zergling";"Larva";186;1
"Unit";"Zergling";"Larva";187;1
"Unit";"Zergling";"Larva";188;1
"Unit";"Zergling";"Larva";189;1
"Unit";"Zergling";"Larva";190;1
"Unit";"Zergling";"Larva";191;1
"Unit";"Zergling";"Larva";192;1
"Unit";"Zergling";"Larva";193;1
"Unit";"Zergling";"Larva";194;1
"Unit";"Zergling";"Larva";195;1
"Unit";"Zergling";"Larva";196;1
"Unit";"Zergling";"Larva";197;1
"Unit";"Zergling";"Larva";198;1
"Unit";"Zergling";"Larva";199;1
"Building";"CreepTumor";NA;200;0
"Unit";"Overlord";"Larva";200;0
"Unit";"Overlord";"Larva";200;0
"Unit";"Overlord";"Larva";200;0
"Unit";"Overlord";"Larva";200;0
"Unit";"Overlord";"Larva";200;0
"Building";"CreepTumor";NA;200;0
"Building";"CreepTumor";NA;200;0
"Unit";"Overlord";"Larva";200;0
"Unit";"Overlord";"Larva";200;0
"Unit";"Overlord";"Larva";200;0
"Building";"CreepTumor";NA;200;0
"Building";"CreepTumor";NA;200;0
"Building";"CreepTumor";NA;200;0
"Unit";"Overlord";"Larva";200;0
"Unit";"Overlord";"Larva";200;0
"Unit";"Zergling";"Larva";200;1
"Unit";"Zergling";"Larva";201;1
"Unit";"Zergling";"Larva";202;1
"Unit";"Zergling";"Larva";203;1
"Unit";"Zergling";"Larva";204;1
"Unit";"Zergling";"Larva";205;1
"Unit";"Zergling";"Larva";206;1
"Unit";"Zergling";"Larva";207;1
"Unit";"Zergling";"Larva";208;1
"Unit";"Zergling";"Larva";209;1
"Unit";"Baneling";"Zergling";210;0
"Unit";"Baneling";"Zergling";210;0
"Unit";"Baneling";"Zergling";210;0
"Unit";"Baneling";"Zergling";210;0
"Unit";"Baneling";"Zergling";210;0
"Unit";"Baneling";"Zergling";210;0
"Unit";"Baneling";"Zergling";210;0
"Unit";"Baneling";"Zergling";210;0
"Unit";"Baneling";"Zergling";210;0
"Unit";"Baneling";"Zergling";210;0
"Unit";"Baneling";"Zergling";210;0
"Unit";"Baneling";"Zergling";210;0
"Unit";"Baneling";"Zergling";210;0
"Unit";"Baneling";"Zergling";210;0
"Unit";"Baneling";"Zergling";210;0
"Unit";"Baneling";"Zergling";210;0
"Unit";"Baneling";"Zergling";210;0
"Unit";"Baneling";"Zergling";210;0
"Building";"CreepTumor";NA;210;0
"Building";"CreepTumor";NA;210;0
"Building";"CreepTumor";NA;210;0
"Building";"Hatchery";NA;210;0
"Building";"CreepTumorQueen";NA;210;0
"Unit";"Zergling";"Larva";210;1
"Unit";"Zergling";"Larva";211;1
"Unit";"Zergling";"Larva";212;1
"Unit";"Zergling";"Larva";213;1
"Unit";"Zergling";"Larva";214;1
"Unit";"Zergling";"Larva";215;1
"Unit";"Zergling";"Larva";216;1
"Unit";"Zergling";"Larva";217;1
"Unit";"Zergling";"Larva";218;1
"Unit";"Zergling";"Larva";219;1
"Unit";"Zergling";"Larva";220;1
"Unit";"Zergling";"Larva";221;1
"Unit";"Zergling";"Larva";222;1
"Unit";"Zergling";"Larva";223;1
"Unit";"Zergling";"Larva";224;1
"Unit";"Zergling";"Larva";225;1
"Unit";"Zergling";"Larva";226;1
"Unit";"Zergling";"Larva";227;1
"Unit";"Zergling";"Larva";228;1
"Unit";"Zergling";"Larva";229;1
"Unit";"Zergling";"Larva";230;1
"Unit";"Zergling";"Larva";231;1
"Unit";"Zergling";"Larva";232;1
"Unit";"Zergling";"Larva";233;1
"Unit";"Zergling";"Larva";234;1
"Unit";"Zergling";"Larva";235;1
"Unit";"Zergling";"Larva";236;1
"Unit";"Zergling";"Larva";237;1
"Unit";"Zergling";"Larva";238;1
"Unit";"Zergling";"Larva";239;1
"Unit";"Zergling";"Larva";240;1
"Unit";"Zergling";"Larva";241;1
"Unit";"Zergling";"Larva";242;1
"Unit";"Zergling";"Larva";243;1
"Unit";"Zergling";"Larva";244;1
"Unit";"Zergling";"Larva";245;1
"Unit";"Zergling";"Larva";246;1
"Unit";"Zergling";"Larva";247;1
"Unit";"Baneling";"Zergling";248;0
"Unit";"Baneling";"Zergling";248;0
"Unit";"Baneling";"Zergling";248;0
"Unit";"Baneling";"Zergling";248;0
"Unit";"Baneling";"Zergling";248;0
"Unit";"Baneling";"Zergling";248;0
"Building";"CreepTumor";NA;248;0
"Building";"CreepTumor";NA;248;0
"Building";"CreepTumor";NA;248;0
"Unit";"Zergling";"Larva";248;1
"Unit";"Zergling";"Larva";249;1
"Unit";"Zergling";"Larva";250;1
"Unit";"Zergling";"Larva";251;1
"Unit";"Zergling";"Larva";252;1
"Unit";"Zergling";"Larva";253;1
"Unit";"Zergling";"Larva";254;1
"Unit";"Zergling";"Larva";255;1
"Unit";"Zergling";"Larva";256;1
"Unit";"Zergling";"Larva";257;1
"Unit";"Zergling";"Larva";258;1
"Unit";"Zergling";"Larva";259;1
"Unit";"Zergling";"Larva";260;1
"Unit";"Zergling";"Larva";261;1
"Unit";"Zergling";"Larva";262;1
"Unit";"Zergling";"Larva";263;1
"Unit";"Zergling";"Larva";264;1
"Unit";"Zergling";"Larva";265;1
"Unit";"Zergling";"Larva";266;1
"Unit";"Zergling";"Larva";267;1
"Unit";"Zergling";"Larva";268;1
"Unit";"Zergling";"Larva";269;1
"Unit";"Zergling";"Larva";270;1
"Unit";"Zergling";"Larva";271;1
"Unit";"Zergling";"Larva";272;1
"Unit";"Zergling";"Larva";273;1
"Unit";"Zergling";"Larva";274;1
"Unit";"Zergling";"Larva";275;1
"Unit";"Zergling";"Larva";276;1
"Unit";"Zergling";"Larva";277;1
"Unit";"Zergling";"Larva";278;1
"Unit";"Zergling";"Larva";279;1
"Unit";"Baneling";"Zergling";280;0
"Unit";"Baneling";"Zergling";280;0
"Unit";"Baneling";"Zergling";280;0
"Unit";"Baneling";"Zergling";280;0
"Unit";"Baneling";"Zergling";280;0
"Unit";"Baneling";"Zergling";280;0
"Unit";"Baneling";"Zergling";280;0
"Unit";"Baneling";"Zergling";280;0
"Unit";"Baneling";"Zergling";280;0
"Unit";"Baneling";"Zergling";280;0
"Unit";"Baneling";"Zergling";280;0
"Unit";"Baneling";"Zergling";280;0
"Unit";"Baneling";"Zergling";280;0
"Unit";"Baneling";"Zergling";280;0
"Unit";"Baneling";"Zergling";280;0
"Unit";"Baneling";"Zergling";280;0
"Building";"InfestationPit";NA;282;0
"Unit";"Hydralisk";"Larva";282;2
"Unit";"Hydralisk";"Larva";284;2
"Unit";"Hydralisk";"Larva";286;2
"Unit";"Hydralisk";"Larva";288;2
"Unit";"Hydralisk";"Larva";290;2
"Unit";"Zergling";"Larva";292;1
"Unit";"Zergling";"Larva";293;1
"Unit";"Zergling";"Larva";294;1
"Unit";"Zergling";"Larva";295;1
"Unit";"Zergling";"Larva";296;1
"Unit";"Zergling";"Larva";297;1
"Unit";"Zergling";"Larva";298;1
"Unit";"Zergling";"Larva";299;1
"Unit";"Zergling";"Larva";300;1
"Unit";"Zergling";"Larva";301;1
"Unit";"Zergling";"Larva";302;1
"Unit";"Zergling";"Larva";303;1
"Unit";"Zergling";"Larva";304;1
"Unit";"Zergling";"Larva";305;1
"Unit";"Zergling";"Larva";306;1
"Unit";"Zergling";"Larva";307;1
"Unit";"Zergling";"Larva";308;1
"Unit";"Zergling";"Larva";309;1
"Unit";"Zergling";"Larva";310;1
"Unit";"Zergling";"Larva";311;1
"Unit";"Zergling";"Larva";312;1
"Unit";"Zergling";"Larva";313;1
"Unit";"Hydralisk";"Larva";314;2
"Unit";"Hydralisk";"Larva";316;2
"Unit";"Zergling";"Larva";318;1
"Unit";"Zergling";"Larva";319;1
"Unit";"Hydralisk";"Larva";320;2
"Unit";"Zergling";"Larva";322;1
"Unit";"Zergling";"Larva";323;1
"Unit";"Zergling";"Larva";324;1
"Unit";"Zergling";"Larva";325;1
"Unit";"Zergling";"Larva";326;1
"Unit";"Zergling";"Larva";327;1
"Unit";"Zergling";"Larva";328;1
"Unit";"Zergling";"Larva";329;1
"Unit";"Zergling";"Larva";330;1
"Unit";"Zergling";"Larva";331;1
"Unit";"Zergling";"Larva";332;1
"Unit";"Zergling";"Larva";333;1
"Unit";"Baneling";"Zergling";334;0
"Unit";"Baneling";"Zergling";334;0
"Unit";"Baneling";"Zergling";334;0
"Unit";"Baneling";"Zergling";334;0
"Unit";"Baneling";"Zergling";334;0
"Unit";"Baneling";"Zergling";334;0
"Unit";"Baneling";"Zergling";334;0
"Unit";"Baneling";"Zergling";334;0
"Unit";"Baneling";"Zergling";334;0
"Unit";"Baneling";"Zergling";334;0
"Unit";"Baneling";"Zergling";334;0
"Unit";"Baneling";"Zergling";334;0
"Unit";"Baneling";"Zergling";334;0
"Unit";"Baneling";"Zergling";334;0
"Unit";"Queen";"Hatchery";334;2
"Unit";"Zergling";"Larva";338;1
"Unit";"Zergling";"Larva";339;1
"Unit";"Zergling";"Larva";340;1
"Unit";"Zergling";"Larva";341;1
"Unit";"Zergling";"Larva";342;1
"Unit";"Zergling";"Larva";343;1
"Unit";"Zergling";"Larva";344;1
"Unit";"Zergling";"Larva";345;1
"Unit";"Zergling";"Larva";346;1
"Unit";"Zergling";"Larva";347;1
"Unit";"Zergling";"Larva";348;1
"Unit";"Zergling";"Larva";349;1
"Unit";"Zergling";"Larva";350;1
"Unit";"Zergling";"Larva";351;1
"Unit";"Zergling";"Larva";352;1
"Unit";"Zergling";"Larva";353;1
"Unit";"Zergling";"Larva";354;1
"Unit";"Zergling";"Larva";355;1
"Unit";"Zergling";"Larva";356;1
"Unit";"Zergling";"Larva";357;1
"Building";"CreepTumorQueen";NA;358;0
"Building";"CreepTumor";NA;358;0
"Building";"CreepTumorQueen";NA;358;0
"Unit";"Baneling";"Zergling";358;0
"Unit";"Baneling";"Zergling";358;0
"Unit";"Baneling";"Zergling";358;0
"Unit";"Baneling";"Zergling";358;0
"Unit";"Baneling";"Zergling";358;0
"Unit";"Baneling";"Zergling";358;0
"Unit";"Baneling";"Zergling";358;0
"Unit";"Baneling";"Zergling";358;0
"Unit";"Baneling";"Zergling";358;0
"Unit";"Zergling";"Larva";358;1
"Unit";"Zergling";"Larva";359;1
"Unit";"Zergling";"Larva";360;1
"Unit";"Zergling";"Larva";361;1
"Unit";"Zergling";"Larva";362;1
"Unit";"Zergling";"Larva";363;1
"Unit";"Zergling";"Larva";364;1
"Unit";"Zergling";"Larva";365;1
"Unit";"Zergling";"Larva";366;1
"Unit";"Zergling";"Larva";367;1
"Unit";"Zergling";"Larva";368;1
"Unit";"Zergling";"Larva";369;1
"Unit";"Zergling";"Larva";370;1
"Unit";"Zergling";"Larva";371;1
"Building";"CreepTumorQueen";NA;372;0
"Building";"CreepTumorQueen";NA;372;0
"Unit";"Baneling";"Zergling";372;0
"Unit";"Baneling";"Zergling";372;0
"Unit";"Baneling";"Zergling";372;0
"Unit";"Baneling";"Zergling";372;0
"Unit";"Baneling";"Zergling";372;0
"Unit";"Baneling";"Zergling";372;0
"Unit";"Baneling";"Zergling";372;0
"Unit";"Baneling";"Zergling";372;0
"Unit";"Baneling";"Zergling";372;0
"Unit";"Baneling";"Zergling";372;0
"Unit";"Zergling";"Larva";372;1
"Unit";"Zergling";"Larva";373;1
"Unit";"Zergling";"Larva";374;1
"Unit";"Zergling";"Larva";375;1
"Unit";"Zergling";"Larva";376;1
"Unit";"Zergling";"Larva";377;1
"Unit";"Zergling";"Larva";378;1
"Unit";"Zergling";"Larva";379;1
"Unit";"Zergling";"Larva";380;1
"Unit";"Zergling";"Larva";381;1
"Unit";"Zergling";"Larva";382;1
"Unit";"Zergling";"Larva";383;1
"Unit";"Zergling";"Larva";384;1
"Unit";"Zergling";"Larva";385;1
"Unit";"Zergling";"Larva";386;1
"Unit";"Zergling";"Larva";387;1
"Unit";"Zergling";"Larva";388;1
"Unit";"Zergling";"Larva";389;1
"Unit";"Zergling";"Larva";390;1
"Unit";"Zergling";"Larva";391;1
"Unit";"Zergling";"Larva";392;1
"Unit";"Zergling";"Larva";393;1
"Unit";"Baneling";"Zergling";394;0
"Unit";"Baneling";"Zergling";394;0
"Unit";"Baneling";"Zergling";394;0
"Unit";"Baneling";"Zergling";394;0
"Unit";"Baneling";"Zergling";394;0
"Unit";"Baneling";"Zergling";394;0
"Unit";"Baneling";"Zergling";394;0
"Unit";"Baneling";"Zergling";394;0
"Unit";"Baneling";"Zergling";394;0
"Unit";"Baneling";"Zergling";394;0
"Unit";"Baneling";"Zergling";394;0
"Unit";"Baneling";"Zergling";394;0
"Unit";"Baneling";"Zergling";394;0
"Unit";"Zergling";"Larva";394;1
"Unit";"Zergling";"Larva";395;1
"Unit";"Zergling";"Larva";396;1
"Unit";"Zergling";"Larva";397;1
"Unit";"Zergling";"Larva";398;1
"Unit";"Zergling";"Larva";399;1
"Unit";"Zergling";"Larva";400;1
"Unit";"Zergling";"Larva";401;1
"Unit";"Zergling";"Larva";402;1
"Unit";"Zergling";"Larva";403;1
"Unit";"Zergling";"Larva";404;1
"Unit";"Zergling";"Larva";405;1
"Unit";"Zergling";"Larva";406;1
"Unit";"Zergling";"Larva";407;1
"Unit";"Zergling";"Larva";408;1
"Unit";"Zergling";"Larva";409;1
"Unit";"Zergling";"Larva";410;1
"Unit";"Zergling";"Larva";411;1
"Unit";"Hydralisk";"Larva";412;2
"Unit";"Hydralisk";"Larva";414;2
"Unit";"Hydralisk";"Larva";416;2
"Unit";"Hydralisk";"Larva";418;2
"Unit";"Zergling";"Larva";420;1
"Unit";"Zergling";"Larva";421;1
"Unit";"Zergling";"Larva";422;1
"Unit";"Zergling";"Larva";423;1
"Unit";"Zergling";"Larva";424;1
"Unit";"Zergling";"Larva";425;1
"Unit";"Zergling";"Larva";426;1
"Unit";"Zergling";"Larva";427;1
"Unit";"Zergling";"Larva";428;1
"Unit";"Zergling";"Larva";429;1
"Unit";"Zergling";"Larva";430;1
"Unit";"Zergling";"Larva";431;1
"Unit";"Zergling";"Larva";432;1
"Unit";"Zergling";"Larva";433;1
"Unit";"Baneling";"Zergling";434;0
"Unit";"Baneling";"Zergling";434;0
"Unit";"Baneling";"Zergling";434;0
"Unit";"Baneling";"Zergling";434;0
"Unit";"Baneling";"Zergling";434;0
"Unit";"Baneling";"Zergling";434;0
"Unit";"Baneling";"Zergling";434;0
"Unit";"Baneling";"Zergling";434;0
"Unit";"Baneling";"Zergling";434;0
"Unit";"Baneling";"Zergling";434;0
"Unit";"Zergling";"Larva";434;1
"Unit";"Zergling";"Larva";435;1
"Unit";"Zergling";"Larva";436;1
"Unit";"Zergling";"Larva";437;1
"Unit";"Zergling";"Larva";438;1
"Unit";"Zergling";"Larva";439;1
"Unit";"Zergling";"Larva";440;1
"Unit";"Zergling";"Larva";441;1
"Unit";"Zergling";"Larva";442;1
"Unit";"Zergling";"Larva";443;1
"Unit";"Zergling";"Larva";444;1
"Unit";"Zergling";"Larva";445;1
"Building";"CreepTumor";NA;446;0
"Building";"CreepTumor";NA;446;0
"Unit";"Zergling";"Larva";446;1
"Unit";"Zergling";"Larva";447;1
"Unit";"Zergling";"Larva";448;1
"Unit";"Zergling";"Larva";449;1
"Unit";"Zergling";"Larva";450;1
"Unit";"Zergling";"Larva";451;1
"Unit";"Zergling";"Larva";452;1
"Unit";"Zergling";"Larva";453;1
"Unit";"Zergling";"Larva";454;1
"Unit";"Zergling";"Larva";455;1
"Unit";"Zergling";"Larva";456;1
"Unit";"Zergling";"Larva";457;1
"Unit";"Zergling";"Larva";458;1
"Unit";"Zergling";"Larva";459;1
"Unit";"Baneling";"Zergling";460;0
"Unit";"Baneling";"Zergling";460;0
"Unit";"Baneling";"Zergling";460;0
"Unit";"Baneling";"Zergling";460;0
"Unit";"Baneling";"Zergling";460;0
"Unit";"Baneling";"Zergling";460;0
"Unit";"Baneling";"Zergling";460;0
"Unit";"Baneling";"Zergling";460;0
"Unit";"Baneling";"Zergling";460;0
"Unit";"Baneling";"Zergling";460;0
"Unit";"Baneling";"Zergling";460;0
"Unit";"Baneling";"Zergling";460;0
"Unit";"Baneling";"Zergling";460;0
"Unit";"Baneling";"Zergling";460;0
"Unit";"Baneling";"Zergling";460;0
"Unit";"Queen";"Hatchery";460;2
"Unit";"Baneling";"Zergling";462;0
"Unit";"Baneling";"Zergling";462;0
"Unit";"Baneling";"Zergling";462;0
"Unit";"Baneling";"Zergling";462;0
"Unit";"Baneling";"Zergling";462;0
"Unit";"Baneling";"Zergling";462;0
"Unit";"Baneling";"Zergling";462;0
"Unit";"Baneling";"Zergling";462;0
"Unit";"Baneling";"Zergling";462;0
"Unit";"Zergling";"Larva";462;1
"Unit";"Zergling";"Larva";463;1
"Unit";"Zergling";"Larva";464;1
"Unit";"Zergling";"Larva";465;1
"Unit";"Zergling";"Larva";466;1
"Unit";"Zergling";"Larva";467;1
"Unit";"Zergling";"Larva";468;1
"Unit";"Zergling";"Larva";469;1
"Unit";"Zergling";"Larva";470;1
"Unit";"Zergling";"Larva";471;1
"Unit";"Zergling";"Larva";472;1
"Unit";"Zergling";"Larva";473;1
"Unit";"Zergling";"Larva";474;1
"Unit";"Zergling";"Larva";475;1
"Unit";"Zergling";"Larva";476;1
"Unit";"Zergling";"Larva";477;1
"Unit";"Zergling";"Larva";478;1
"Unit";"Zergling";"Larva";479;1
"Unit";"Zergling";"Larva";480;1
"Unit";"Zergling";"Larva";481;1
"Unit";"Zergling";"Larva";482;1
"Unit";"Zergling";"Larva";483;1
"Unit";"Zergling";"Larva";484;1
"Unit";"Zergling";"Larva";485;1
"Unit";"Zergling";"Larva";486;1
"Unit";"Zergling";"Larva";487;1
"Unit";"Zergling";"Larva";488;1
"Unit";"Zergling";"Larva";489;1
"Unit";"Zergling";"Larva";490;1
"Unit";"Zergling";"Larva";491;1
"Unit";"Zergling";"Larva";492;1
"Unit";"Zergling";"Larva";493;1
"Unit";"Zergling";"Larva";494;1
"Unit";"Zergling";"Larva";495;1
"Unit";"Zergling";"Larva";496;1
"Unit";"Zergling";"Larva";497;1
"Unit";"Zergling";"Larva";498;1
"Unit";"Zergling";"Larva";499;1
"Unit";"Zergling";"Larva";500;1
"Unit";"Zergling";"Larva";501;1
"Unit";"Zergling";"Larva";502;1
"Unit";"Zergling";"Larva";503;1
"Unit";"Zergling";"Larva";504;1
"Unit";"Zergling";"Larva";505;1
"Unit";"Zergling";"Larva";506;1
"Unit";"Zergling";"Larva";507;1
"Unit";"Zergling";"Larva";508;1
"Unit";"Zergling";"Larva";509;1
"Unit";"Zergling";"Larva";510;1
"Unit";"Zergling";"Larva";511;1
"Unit";"Zergling";"Larva";512;1
"Unit";"Zergling";"Larva";513;1
"Unit";"Zergling";"Larva";514;1
"Unit";"Zergling";"Larva";515;1
"Unit";"Zergling";"Larva";516;1
"Unit";"Zergling";"Larva";517;1
"Unit";"Zergling";"Larva";518;1
"Unit";"Zergling";"Larva";519;1
"Unit";"Zergling";"Larva";520;1
"Unit";"Zergling";"Larva";521;1
"Unit";"Zergling";"Larva";522;1
"Unit";"Zergling";"Larva";523;1
"Unit";"Zergling";"Larva";524;1
"Unit";"Zergling";"Larva";525;1
"Unit";"Zergling";"Larva";526;1
"Unit";"Zergling";"Larva";527;1
"Unit";"Zergling";"Larva";528;1
"Unit";"Zergling";"Larva";529;1
"Unit";"Zergling";"Larva";530;1
"Unit";"Zergling";"Larva";531;1
"Unit";"Zergling";"Larva";532;1
"Unit";"Zergling";"Larva";533;1
"Unit";"Zergling";"Larva";534;1
"Unit";"Zergling";"Larva";535;1
"Unit";"Zergling";"Larva";536;1
"Unit";"Zergling";"Larva";537;1
"Unit";"Zergling";"Larva";538;1
"Unit";"Zergling";"Larva";539;1
"Unit";"Zergling";"Larva";540;1
"Unit";"Zergling";"Larva";541;1
"Unit";"Baneling";"Zergling";542;0
"Unit";"Baneling";"Zergling";542;0
"Unit";"Baneling";"Zergling";542;0
"Unit";"Baneling";"Zergling";542;0
"Unit";"Baneling";"Zergling";542;0
"Unit";"Baneling";"Zergling";542;0
"Unit";"Baneling";"Zergling";542;0
"Unit";"Baneling";"Zergling";542;0
"Unit";"Baneling";"Zergling";542;0
"Unit";"Baneling";"Zergling";542;0
"Unit";"Baneling";"Zergling";542;0
"Unit";"Baneling";"Zergling";542;0
"Unit";"Zergling";"Larva";542;1
"Unit";"Zergling";"Larva";543;1
"Unit";"Zergling";"Larva";544;1
"Unit";"Zergling";"Larva";545;1
"Unit";"Zergling";"Larva";546;1
"Unit";"Zergling";"Larva";547;1
"Unit";"Zergling";"Larva";548;1
"Unit";"Zergling";"Larva";549;1
"Unit";"Zergling";"Larva";550;1
"Unit";"Zergling";"Larva";551;1
"Unit";"Zergling";"Larva";552;1
"Unit";"Zergling";"Larva";553;1
"Unit";"Zergling";"Larva";554;1
"Unit";"Zergling";"Larva";555;1
"Unit";"Zergling";"Larva";556;1
"Unit";"Zergling";"Larva";557;1
"Unit";"Zergling";"Larva";558;1
"Unit";"Zergling";"Larva";559;1
"Unit";"Zergling";"Larva";560;1
"Unit";"Zergling";"Larva";561;1
"Unit";"Zergling";"Larva";562;1
"Unit";"Zergling";"Larva";563;1
"Unit";"Zergling";"Larva";564;1
"Unit";"Zergling";"Larva";565;1
"Unit";"Zergling";"Larva";566;1
"Unit";"Zergling";"Larva";567;1
"Unit";"Hydralisk";"Larva";568;2
"Unit";"Hydralisk";"Larva";570;2
"Unit";"Hydralisk";"Larva";572;2
"Unit";"Hydralisk";"Larva";574;2
"Unit";"Hydralisk";"Larva";576;2
"Unit";"Zergling";"Larva";578;1
"Unit";"Zergling";"Larva";579;1
"Unit";"Hydralisk";"Larva";580;2
"Unit";"Hydralisk";"Larva";582;2
"Unit";"Hydralisk";"Larva";584;2
"Unit";"Zergling";"Larva";586;1
"Unit";"Zergling";"Larva";587;1
"Unit";"Zergling";"Larva";588;1
"Unit";"Zergling";"Larva";589;1
"Unit";"Zergling";"Larva";590;1
"Unit";"Zergling";"Larva";591;1
"Unit";"Zergling";"Larva";592;1
"Unit";"Zergling";"Larva";593;1
"Unit";"Zergling";"Larva";594;1
"Unit";"Zergling";"Larva";595;1
"Unit";"Zergling";"Larva";596;1
"Unit";"Zergling";"Larva";597;1
"Unit";"Zergling";"Larva";598;1
"Unit";"Zergling";"Larva";599;1
"Unit";"Zergling";"Larva";600;1
"Unit";"Zergling";"Larva";601;1
"Unit";"Zergling";"Larva";602;1
"Unit";"Zergling";"Larva";603;1
"Unit";"Zergling";"Larva";604;1
"Unit";"Zergling";"Larva";605;1
"Upgrade";"SprayZerg";NA;606;0
"Upgrade";"SprayZerg";NA;606;0
"Upgrade";"SprayZerg";NA;606;0
"Upgrade";"zerglingmovementspeed";NA;606;0
"Upgrade";"SprayZerg";NA;606;0
"Upgrade";"SprayZerg";NA;606;0
"Upgrade";"SprayZerg";NA;606;0
"Upgrade";"ZergMeleeWeaponsLevel1";NA;606;0
"Upgrade";"SprayZerg";NA;606;0
"Upgrade";"overlordspeed";NA;606;0
"Upgrade";"SprayZerg";NA;606;0
"Upgrade";"CentrificalHooks";NA;606;0
"Upgrade";"SprayZerg";NA;606;0
"Upgrade";"ZergMeleeWeaponsLevel2";NA;606;0
"Upgrade";"SprayZerg";NA;606;0
"Upgrade";"ZergMissileWeaponsLevel1";NA;606;0
