"type";"unit_name";"on_building";"total_supply_lag";"supply"
"Unit";"Overlord";"Larva";15;0
"Building";"Hatchery";NA;15;0
"Building";"Extractor";NA;19;0
"Building";"SpawningPool";NA;19;0
"Unit";"Overlord";"Larva";23;0
"Unit";"Queen";"Hatchery";24;2
"Unit";"Queen";"Hatchery";26;2
"Unit";"Zergling";"Larva";31;1
"Unit";"Zergling";"Larva";32;1
"Unit";"Overlord";"Larva";33;0
"Unit";"Zergling";"Larva";35;1
"Unit";"Zergling";"Larva";36;1
"Building";"CreepTumorQueen";NA;37;0
"Unit";"Queen";"Hatchery";39;2
"Building";"Hatchery";NA;43;0
"Building";"CreepTumor";NA;43;0
"Unit";"Overlord";"Larva";47;0
"Building";"CreepTumorQueen";NA;47;0
"Unit";"Overlord";"Larva";47;0
"Unit";"Zergling";"Larva";48;1
"Unit";"Zergling";"Larva";49;1
"Unit";"Zergling";"Larva";50;1
"Unit";"Zergling";"Larva";51;1
"Building";"SporeCrawler";NA;52;0
"Building";"CreepTumor";NA;52;0
"Unit";"Zergling";"Larva";52;1
"Unit";"Zergling";"Larva";53;1
"Unit";"Zergling";"Larva";54;1
"Unit";"Zergling";"Larva";55;1
"Unit";"Queen";"Hatchery";56;2
"Building";"EvolutionChamber";NA;60;0
"Building";"SporeCrawler";NA;60;0
"Building";"Extractor";NA;65;0
"Building";"BanelingNest";NA;67;0
"Unit";"Zergling";"Larva";67;1
"Unit";"Zergling";"Larva";68;1
"Unit";"Zergling";"Larva";69;1
"Unit";"Zergling";"Larva";70;1
"Building";"HydraliskDen";NA;78;0
"Unit";"Overlord";"Larva";80;0
"Building";"CreepTumor";NA;80;0
"Unit";"Overlord";"Larva";80;0
"Building";"SporeCrawler";NA;80;0
"Unit";"Overlord";"Larva";80;0
"Unit";"Overlord";"Larva";80;0
"Unit";"Overlord";"Larva";80;0
"Building";"CreepTumor";NA;91;0
"Building";"CreepTumorQueen";NA;91;0
"Building";"CreepTumorQueen";NA;92;0
"Unit";"Baneling";"Zergling";94;0
"Unit";"Baneling";"Zergling";94;0
"Unit";"Baneling";"Zergling";94;0
"Building";"Extractor";NA;98;0
"Building";"Extractor";NA;99;0
"Unit";"Queen";"Hatchery";99;2
"Unit";"Overlord";"Larva";101;0
"Unit";"Hydralisk";"Larva";101;2
"Unit";"Hydralisk";"Larva";103;2
"Building";"Extractor";NA;107;0
"Building";"Extractor";NA;107;0
"Unit";"Overlord";"Larva";107;0
"Building";"CreepTumor";NA;107;0
"Unit";"Hydralisk";"Larva";107;2
"Unit";"Hydralisk";"Larva";109;2
"Building";"Hatchery";NA;111;0
"Building";"CreepTumor";NA;111;0
"Building";"CreepTumor";NA;111;0
"Unit";"Hydralisk";"Larva";115;2
"Unit";"Hydralisk";"Larva";117;2
"Building";"CreepTumorQueen";NA;119;0
"Building";"CreepTumor";NA;125;0
"Building";"CreepTumorQueen";NA;125;0
"Unit";"Hydralisk";"Larva";125;2
"Unit";"Hydralisk";"Larva";127;2
"Unit";"Hydralisk";"Larva";129;2
"Building";"CreepTumor";NA;131;0
"Unit";"Overlord";"Larva";131;0
"Unit";"Overlord";"Larva";131;0
"Unit";"Overlord";"Larva";131;0
"Building";"CreepTumor";NA;131;0
"Building";"SporeCrawler";NA;139;0
"Building";"CreepTumor";NA;139;0
"Building";"CreepTumor";NA;139;0
"Unit";"Hydralisk";"Larva";139;2
"Unit";"Hydralisk";"Larva";141;2
"Unit";"Hydralisk";"Larva";143;2
"Unit";"Hydralisk";"Larva";145;2
"Unit";"Hydralisk";"Larva";147;2
"Unit";"Hydralisk";"Larva";149;2
"Unit";"Hydralisk";"Larva";151;2
"Building";"CreepTumor";NA;153;0
"Building";"CreepTumorQueen";NA;154;0
"Unit";"Baneling";"Zergling";154;0
"Unit";"Baneling";"Zergling";154;0
"Unit";"Baneling";"Zergling";154;0
"Unit";"Baneling";"Zergling";154;0
"Unit";"Baneling";"Zergling";154;0
"Unit";"Baneling";"Zergling";154;0
"Unit";"Baneling";"Zergling";154;0
"Unit";"Baneling";"Zergling";154;0
"Unit";"Baneling";"Zergling";154;0
"Building";"CreepTumorQueen";NA;154;0
"Unit";"Hydralisk";"Larva";154;2
"Building";"Hatchery";NA;156;0
"Unit";"Zergling";"Larva";156;1
"Unit";"Zergling";"Larva";157;1
"Unit";"Zergling";"Larva";158;1
"Unit";"Zergling";"Larva";159;1
"Unit";"Zergling";"Larva";160;1
"Unit";"Zergling";"Larva";161;1
"Unit";"Zergling";"Larva";162;1
"Unit";"Zergling";"Larva";163;1
"Unit";"Zergling";"Larva";164;1
"Unit";"Zergling";"Larva";165;1
"Unit";"Zergling";"Larva";166;1
"Unit";"Zergling";"Larva";167;1
"Building";"CreepTumor";NA;168;0
"Unit";"Hydralisk";"Larva";168;2
"Unit";"Hydralisk";"Larva";170;2
"Building";"CreepTumor";NA;172;0
"Unit";"Hydralisk";"Larva";172;2
"Unit";"Hydralisk";"Larva";174;2
"Unit";"Zergling";"Larva";176;1
"Unit";"Zergling";"Larva";177;1
"Unit";"Zergling";"Larva";178;1
"Unit";"Zergling";"Larva";179;1
"Unit";"Overlord";"Larva";180;0
"Unit";"Overlord";"Larva";180;0
"Unit";"Queen";"Hatchery";180;2
"Unit";"Hydralisk";"Larva";189;2
"Unit";"Hydralisk";"Larva";191;2
"Unit";"Hydralisk";"Larva";193;2
"Unit";"Hydralisk";"Larva";195;2
"Unit";"Zergling";"Larva";197;1
"Unit";"Zergling";"Larva";198;1
"Unit";"Zergling";"Larva";199;1
"Unit";"Zergling";"Larva";200;1
"Unit";"Zergling";"Larva";201;1
"Unit";"Zergling";"Larva";202;1
"Unit";"Zergling";"Larva";203;1
"Unit";"Zergling";"Larva";204;1
"Unit";"Zergling";"Larva";205;1
"Unit";"Zergling";"Larva";206;1
"Unit";"Zergling";"Larva";207;1
"Unit";"Zergling";"Larva";208;1
"Unit";"Queen";"Hatchery";209;2
"Building";"CreepTumor";NA;219;0
"Building";"CreepTumor";NA;219;0
"Unit";"Baneling";"Zergling";219;0
"Unit";"Baneling";"Zergling";219;0
"Unit";"Baneling";"Zergling";219;0
"Unit";"Baneling";"Zergling";219;0
"Unit";"Baneling";"Zergling";219;0
"Unit";"Baneling";"Zergling";219;0
"Unit";"Baneling";"Zergling";219;0
"Unit";"Baneling";"Zergling";219;0
"Unit";"Baneling";"Zergling";219;0
"Unit";"Baneling";"Zergling";219;0
"Unit";"Baneling";"Zergling";219;0
"Unit";"Baneling";"Zergling";219;0
"Building";"CreepTumor";NA;219;0
"Unit";"Zergling";"Larva";219;1
"Unit";"Zergling";"Larva";220;1
"Unit";"Zergling";"Larva";221;1
"Unit";"Zergling";"Larva";222;1
"Unit";"Zergling";"Larva";223;1
"Unit";"Zergling";"Larva";224;1
"Unit";"Zergling";"Larva";225;1
"Unit";"Zergling";"Larva";226;1
"Building";"CreepTumor";NA;227;0
"Building";"CreepTumor";NA;227;0
"Unit";"Hydralisk";"Larva";227;2
"Unit";"Hydralisk";"Larva";229;2
"Unit";"Hydralisk";"Larva";231;2
"Unit";"Hydralisk";"Larva";233;2
"Unit";"Baneling";"Zergling";235;0
"Unit";"Baneling";"Zergling";235;0
"Unit";"Baneling";"Zergling";235;0
"Unit";"Baneling";"Zergling";235;0
"Unit";"Baneling";"Zergling";235;0
"Unit";"Baneling";"Zergling";235;0
"Unit";"Baneling";"Zergling";235;0
"Unit";"Baneling";"Zergling";235;0
"Unit";"Zergling";"Larva";235;1
"Unit";"Zergling";"Larva";236;1
"Unit";"Zergling";"Larva";237;1
"Unit";"Zergling";"Larva";238;1
"Unit";"Zergling";"Larva";239;1
"Unit";"Zergling";"Larva";240;1
"Unit";"Zergling";"Larva";241;1
"Unit";"Zergling";"Larva";242;1
"Unit";"Zergling";"Larva";243;1
"Unit";"Zergling";"Larva";244;1
"Unit";"Zergling";"Larva";245;1
"Unit";"Zergling";"Larva";246;1
"Unit";"Zergling";"Larva";247;1
"Unit";"Zergling";"Larva";248;1
"Unit";"Overlord";"Larva";249;0
"Unit";"Overlord";"Larva";249;0
"Unit";"Overlord";"Larva";249;0
"Unit";"Overlord";"Larva";249;0
"Unit";"Overlord";"Larva";249;0
"Unit";"Hydralisk";"Larva";249;2
"Unit";"Hydralisk";"Larva";251;2
"Unit";"Hydralisk";"Larva";253;2
"Unit";"Hydralisk";"Larva";255;2
"Unit";"Hydralisk";"Larva";257;2
"Unit";"Hydralisk";"Larva";259;2
"Unit";"Hydralisk";"Larva";261;2
"Unit";"Hydralisk";"Larva";263;2
"Unit";"Hydralisk";"Larva";265;2
"Unit";"Hydralisk";"Larva";267;2
"Unit";"Hydralisk";"Larva";269;2
"Unit";"Hydralisk";"Larva";271;2
"Unit";"Hydralisk";"Larva";273;2
"Unit";"Hydralisk";"Larva";275;2
"Unit";"Hydralisk";"Larva";277;2
"Unit";"Hydralisk";"Larva";279;2
"Unit";"Hydralisk";"Larva";281;2
"Unit";"Hydralisk";"Larva";283;2
"Unit";"Hydralisk";"Larva";285;2
"Unit";"Zergling";"Larva";287;1
"Unit";"Zergling";"Larva";288;1
"Building";"Extractor";NA;289;0
"Unit";"Queen";"Hatchery";289;2
"Building";"Extractor";NA;291;0
"Unit";"Hydralisk";"Larva";291;2
"Unit";"Zergling";"Larva";293;1
"Unit";"Zergling";"Larva";294;1
"Unit";"Zergling";"Larva";295;1
"Unit";"Zergling";"Larva";296;1
"Unit";"Zergling";"Larva";297;1
"Unit";"Zergling";"Larva";298;1
"Unit";"Zergling";"Larva";299;1
"Unit";"Zergling";"Larva";300;1
"Unit";"Zergling";"Larva";301;1
"Unit";"Zergling";"Larva";302;1
"Unit";"Zergling";"Larva";303;1
"Unit";"Zergling";"Larva";304;1
"Unit";"Zergling";"Larva";305;1
"Unit";"Zergling";"Larva";306;1
"Unit";"Zergling";"Larva";307;1
"Unit";"Zergling";"Larva";308;1
"Unit";"Zergling";"Larva";309;1
"Unit";"Zergling";"Larva";310;1
"Unit";"Zergling";"Larva";311;1
"Unit";"Zergling";"Larva";312;1
"Unit";"Zergling";"Larva";313;1
"Unit";"Zergling";"Larva";314;1
"Building";"InfestationPit";NA;317;0
"Building";"CreepTumor";NA;323;0
"Unit";"Hydralisk";"Larva";323;2
"Unit";"Hydralisk";"Larva";325;2
"Unit";"Hydralisk";"Larva";327;2
"Unit";"Hydralisk";"Larva";329;2
"Unit";"Hydralisk";"Larva";331;2
"Building";"CreepTumorQueen";NA;333;0
"Building";"CreepTumor";NA;333;0
"Unit";"Baneling";"Zergling";333;0
"Unit";"Baneling";"Zergling";333;0
"Unit";"Baneling";"Zergling";333;0
"Unit";"Baneling";"Zergling";333;0
"Unit";"Baneling";"Zergling";333;0
"Unit";"Baneling";"Zergling";333;0
"Unit";"Baneling";"Zergling";333;0
"Building";"CreepTumor";NA;333;0
"Unit";"Baneling";"Zergling";333;0
"Unit";"Baneling";"Zergling";333;0
"Unit";"Baneling";"Zergling";333;0
"Unit";"Baneling";"Zergling";333;0
"Unit";"Baneling";"Zergling";333;0
"Unit";"Baneling";"Zergling";333;0
"Building";"CreepTumor";NA;333;0
"Unit";"Zergling";"Larva";333;1
"Unit";"Zergling";"Larva";334;1
"Unit";"Zergling";"Larva";335;1
"Unit";"Zergling";"Larva";336;1
"Unit";"Zergling";"Larva";337;1
"Unit";"Zergling";"Larva";338;1
"Unit";"Zergling";"Larva";339;1
"Unit";"Zergling";"Larva";340;1
"Unit";"Zergling";"Larva";341;1
"Unit";"Zergling";"Larva";342;1
"Unit";"Zergling";"Larva";343;1
"Unit";"Zergling";"Larva";344;1
"Unit";"Zergling";"Larva";345;1
"Unit";"Zergling";"Larva";346;1
"Unit";"Zergling";"Larva";347;1
"Unit";"Zergling";"Larva";348;1
"Unit";"Zergling";"Larva";349;1
"Unit";"Zergling";"Larva";350;1
"Unit";"Baneling";"Zergling";351;0
"Unit";"Baneling";"Zergling";351;0
"Unit";"Baneling";"Zergling";351;0
"Unit";"Baneling";"Zergling";351;0
"Unit";"Baneling";"Zergling";351;0
"Unit";"Baneling";"Zergling";351;0
"Unit";"Baneling";"Zergling";351;0
"Unit";"Baneling";"Zergling";351;0
"Unit";"Baneling";"Zergling";351;0
"Unit";"Baneling";"Zergling";351;0
"Unit";"Hydralisk";"Larva";351;2
"Unit";"Hydralisk";"Larva";353;2
"Unit";"Hydralisk";"Larva";355;2
"Unit";"Hydralisk";"Larva";357;2
"Unit";"Hydralisk";"Larva";359;2
"Building";"CreepTumor";NA;361;0
"Building";"CreepTumor";NA;361;0
"Unit";"Zergling";"Larva";361;1
"Unit";"Zergling";"Larva";362;1
"Unit";"Zergling";"Larva";363;1
"Unit";"Zergling";"Larva";364;1
"Unit";"Zergling";"Larva";365;1
"Unit";"Zergling";"Larva";366;1
"Unit";"Zergling";"Larva";367;1
"Unit";"Zergling";"Larva";368;1
"Unit";"Zergling";"Larva";369;1
"Unit";"Zergling";"Larva";370;1
"Unit";"Zergling";"Larva";371;1
"Unit";"Zergling";"Larva";372;1
"Unit";"Hydralisk";"Larva";373;2
"Unit";"Hydralisk";"Larva";375;2
"Unit";"Hydralisk";"Larva";377;2
"Unit";"Hydralisk";"Larva";379;2
"Unit";"Hydralisk";"Larva";381;2
"Unit";"Hydralisk";"Larva";383;2
"Unit";"Zergling";"Larva";385;1
"Unit";"Zergling";"Larva";386;1
"Unit";"Zergling";"Larva";387;1
"Unit";"Zergling";"Larva";388;1
"Unit";"Hydralisk";"Larva";389;2
"Unit";"Hydralisk";"Larva";391;2
"Unit";"Hydralisk";"Larva";393;2
"Building";"SpineCrawler";NA;395;0
"Unit";"Baneling";"Zergling";395;0
"Unit";"Baneling";"Zergling";395;0
"Unit";"Baneling";"Zergling";395;0
"Unit";"Baneling";"Zergling";395;0
"Unit";"Baneling";"Zergling";395;0
"Unit";"Baneling";"Zergling";395;0
"Unit";"Zergling";"Larva";395;1
"Unit";"Zergling";"Larva";396;1
"Unit";"Zergling";"Larva";397;1
"Unit";"Zergling";"Larva";398;1
"Unit";"Zergling";"Larva";399;1
"Unit";"Zergling";"Larva";400;1
"Unit";"Zergling";"Larva";401;1
"Unit";"Zergling";"Larva";402;1
"Unit";"Zergling";"Larva";403;1
"Unit";"Zergling";"Larva";404;1
"Unit";"Zergling";"Larva";405;1
"Unit";"Zergling";"Larva";406;1
"Unit";"Zergling";"Larva";407;1
"Unit";"Zergling";"Larva";408;1
"Unit";"Zergling";"Larva";409;1
"Unit";"Zergling";"Larva";410;1
"Unit";"Zergling";"Larva";411;1
"Unit";"Zergling";"Larva";412;1
"Unit";"Zergling";"Larva";413;1
"Unit";"Zergling";"Larva";414;1
"Unit";"Zergling";"Larva";415;1
"Unit";"Zergling";"Larva";416;1
"Unit";"Zergling";"Larva";417;1
"Unit";"Zergling";"Larva";418;1
"Unit";"Zergling";"Larva";419;1
"Unit";"Zergling";"Larva";420;1
"Unit";"Zergling";"Larva";421;1
"Unit";"Zergling";"Larva";422;1
"Unit";"Zergling";"Larva";423;1
"Unit";"Zergling";"Larva";424;1
"Unit";"Zergling";"Larva";425;1
"Unit";"Zergling";"Larva";426;1
"Unit";"Zergling";"Larva";427;1
"Unit";"Zergling";"Larva";428;1
"Unit";"Hydralisk";"Larva";429;2
"Unit";"Hydralisk";"Larva";431;2
"Unit";"Hydralisk";"Larva";433;2
"Unit";"Hydralisk";"Larva";435;2
"Unit";"Hydralisk";"Larva";437;2
"Unit";"Hydralisk";"Larva";439;2
"Unit";"Hydralisk";"Larva";441;2
"Unit";"Hydralisk";"Larva";443;2
"Unit";"Hydralisk";"Larva";445;2
"Unit";"Hydralisk";"Larva";447;2
"Unit";"Zergling";"Larva";449;1
"Unit";"Zergling";"Larva";450;1
"Building";"Hatchery";NA;451;0
"Building";"Spire";NA;454;0
"Building";"CreepTumor";NA;454;0
"Unit";"Baneling";"Zergling";454;0
"Unit";"Baneling";"Zergling";454;0
"Building";"Extractor";NA;456;0
"Building";"Extractor";NA;461;0
"Building";"Extractor";NA;463;0
"Unit";"Zergling";"Larva";468;1
"Unit";"Zergling";"Larva";469;1
"Unit";"Zergling";"Larva";470;1
"Unit";"Zergling";"Larva";471;1
"Unit";"Zergling";"Larva";472;1
"Unit";"Zergling";"Larva";473;1
"Unit";"Zergling";"Larva";474;1
"Unit";"Zergling";"Larva";475;1
"Unit";"Zergling";"Larva";476;1
"Unit";"Zergling";"Larva";477;1
"Unit";"Zergling";"Larva";478;1
"Unit";"Zergling";"Larva";479;1
"Unit";"Zergling";"Larva";480;1
"Unit";"Zergling";"Larva";481;1
"Unit";"Zergling";"Larva";482;1
"Unit";"Zergling";"Larva";483;1
"Unit";"Zergling";"Larva";484;1
"Unit";"Zergling";"Larva";485;1
"Unit";"Zergling";"Larva";486;1
"Unit";"Zergling";"Larva";487;1
"Unit";"Zergling";"Larva";488;1
"Unit";"Zergling";"Larva";489;1
"Unit";"Zergling";"Larva";490;1
"Unit";"Zergling";"Larva";491;1
"Building";"CreepTumor";NA;492;0
"Building";"CreepTumor";NA;492;0
"Unit";"Hydralisk";"Larva";492;2
"Unit";"Hydralisk";"Larva";494;2
"Unit";"Hydralisk";"Larva";496;2
"Unit";"Hydralisk";"Larva";498;2
"Unit";"Hydralisk";"Larva";500;2
"Unit";"Hydralisk";"Larva";502;2
"Building";"CreepTumorQueen";NA;504;0
"Unit";"Overlord";"Larva";504;0
"Unit";"Overlord";"Larva";504;0
"Unit";"Overlord";"Larva";504;0
"Unit";"Hydralisk";"Larva";504;2
"Unit";"Hydralisk";"Larva";506;2
"Unit";"Hydralisk";"Larva";508;2
"Unit";"Zergling";"Larva";510;1
"Unit";"Zergling";"Larva";511;1
"Unit";"Zergling";"Larva";512;1
"Unit";"Zergling";"Larva";513;1
"Unit";"Zergling";"Larva";514;1
"Unit";"Zergling";"Larva";515;1
"Unit";"Zergling";"Larva";516;1
"Unit";"Zergling";"Larva";517;1
"Unit";"Zergling";"Larva";518;1
"Unit";"Zergling";"Larva";519;1
"Unit";"Zergling";"Larva";520;1
"Unit";"Zergling";"Larva";521;1
"Unit";"Zergling";"Larva";522;1
"Unit";"Zergling";"Larva";523;1
"Unit";"Zergling";"Larva";524;1
"Unit";"Zergling";"Larva";525;1
"Unit";"Zergling";"Larva";526;1
"Unit";"Zergling";"Larva";527;1
"Unit";"Zergling";"Larva";528;1
"Unit";"Zergling";"Larva";529;1
"Unit";"Overlord";"Larva";530;0
"Unit";"Overlord";"Larva";530;0
"Unit";"Overlord";"Larva";530;0
"Unit";"Corruptor";"Larva";530;2
"Unit";"Corruptor";"Larva";532;2
"Building";"CreepTumor";NA;534;0
"Unit";"Corruptor";"Larva";534;2
"Unit";"Corruptor";"Larva";536;2
"Unit";"Corruptor";"Larva";538;2
"Unit";"Corruptor";"Larva";540;2
"Building";"CreepTumorQueen";NA;542;0
"Building";"Hatchery";NA;542;0
"Building";"CreepTumor";NA;542;0
"Unit";"Baneling";"Zergling";542;0
"Unit";"Baneling";"Zergling";542;0
"Unit";"Baneling";"Zergling";542;0
"Unit";"Baneling";"Zergling";542;0
"Unit";"Baneling";"Zergling";542;0
"Unit";"Baneling";"Zergling";542;0
"Unit";"Baneling";"Zergling";542;0
"Unit";"Baneling";"Zergling";542;0
"Unit";"Baneling";"Zergling";542;0
"Unit";"Baneling";"Zergling";542;0
"Unit";"Baneling";"Zergling";542;0
"Unit";"Baneling";"Zergling";542;0
"Unit";"Baneling";"Zergling";542;0
"Unit";"Baneling";"Zergling";542;0
"Unit";"Baneling";"Zergling";542;0
"Unit";"Baneling";"Zergling";542;0
"Unit";"Baneling";"Zergling";542;0
"Unit";"Baneling";"Zergling";542;0
"Unit";"Baneling";"Zergling";542;0
"Unit";"Baneling";"Zergling";542;0
"Unit";"Baneling";"Zergling";542;0
"Unit";"Baneling";"Zergling";542;0
"Unit";"Baneling";"Zergling";542;0
"Unit";"Baneling";"Zergling";542;0
"Unit";"Baneling";"Zergling";542;0
"Unit";"Baneling";"Zergling";542;0
"Unit";"Baneling";"Zergling";542;0
"Unit";"Baneling";"Zergling";542;0
"Unit";"Baneling";"Zergling";542;0
"Unit";"Baneling";"Zergling";542;0
"Unit";"Baneling";"Zergling";542;0
"Building";"CreepTumor";NA;542;0
"Building";"CreepTumor";NA;542;0
"Building";"CreepTumor";NA;542;0
"Unit";"Corruptor";"Larva";542;2
"Unit";"Corruptor";"Larva";544;2
"Unit";"Zergling";"Larva";551;1
"Unit";"Zergling";"Larva";552;1
"Unit";"Zergling";"Larva";553;1
"Unit";"Zergling";"Larva";554;1
"Unit";"Zergling";"Larva";555;1
"Unit";"Zergling";"Larva";556;1
"Unit";"Zergling";"Larva";557;1
"Unit";"Zergling";"Larva";558;1
"Unit";"Zergling";"Larva";559;1
"Unit";"Zergling";"Larva";560;1
"Unit";"Zergling";"Larva";561;1
"Unit";"Zergling";"Larva";562;1
"Unit";"Zergling";"Larva";563;1
"Unit";"Zergling";"Larva";564;1
"Unit";"Zergling";"Larva";565;1
"Unit";"Zergling";"Larva";566;1
"Unit";"Zergling";"Larva";567;1
"Unit";"Zergling";"Larva";568;1
"Unit";"Zergling";"Larva";569;1
"Unit";"Zergling";"Larva";570;1
"Unit";"Zergling";"Larva";571;1
"Unit";"Zergling";"Larva";572;1
"Unit";"Zergling";"Larva";573;1
"Unit";"Zergling";"Larva";574;1
"Unit";"Zergling";"Larva";575;1
"Unit";"Zergling";"Larva";576;1
"Unit";"Zergling";"Larva";577;1
"Unit";"Zergling";"Larva";578;1
"Unit";"Corruptor";"Larva";579;2
"Unit";"Corruptor";"Larva";581;2
"Unit";"Zergling";"Larva";583;1
"Unit";"Zergling";"Larva";584;1
"Unit";"Zergling";"Larva";585;1
"Unit";"Zergling";"Larva";586;1
"Unit";"Zergling";"Larva";587;1
"Unit";"Zergling";"Larva";588;1
"Unit";"Zergling";"Larva";589;1
"Unit";"Zergling";"Larva";590;1
"Unit";"Zergling";"Larva";591;1
"Unit";"Zergling";"Larva";592;1
"Unit";"Zergling";"Larva";593;1
"Unit";"Zergling";"Larva";594;1
"Unit";"Zergling";"Larva";595;1
"Unit";"Zergling";"Larva";596;1
"Unit";"Zergling";"Larva";597;1
"Unit";"Zergling";"Larva";598;1
"Unit";"Zergling";"Larva";599;1
"Unit";"Zergling";"Larva";600;1
"Unit";"Zergling";"Larva";601;1
"Unit";"Zergling";"Larva";602;1
"Unit";"Zergling";"Larva";603;1
"Unit";"Zergling";"Larva";604;1
"Unit";"Baneling";"Zergling";605;0
"Unit";"Baneling";"Zergling";605;0
"Unit";"Baneling";"Zergling";605;0
"Unit";"Baneling";"Zergling";605;0
"Unit";"Baneling";"Zergling";605;0
"Unit";"Baneling";"Zergling";605;0
"Unit";"Hydralisk";"Larva";605;2
"Unit";"Hydralisk";"Larva";607;2
"Unit";"Hydralisk";"Larva";609;2
"Unit";"Hydralisk";"Larva";611;2
"Unit";"Hydralisk";"Larva";613;2
"Unit";"Hydralisk";"Larva";615;2
"Unit";"Hydralisk";"Larva";617;2
"Unit";"Hydralisk";"Larva";619;2
"Unit";"Hydralisk";"Larva";621;2
"Unit";"Hydralisk";"Larva";623;2
"Upgrade";"SprayZerg";NA;625;0
"Upgrade";"SprayZerg";NA;625;0
"Upgrade";"SprayZerg";NA;625;0
"Upgrade";"zerglingmovementspeed";NA;625;0
"Upgrade";"SprayZerg";NA;625;0
"Upgrade";"SprayZerg";NA;625;0
"Upgrade";"EvolveMuscularAugments";NA;625;0
"Upgrade";"ZergMissileWeaponsLevel1";NA;625;0
"Upgrade";"SprayZerg";NA;625;0
"Upgrade";"SprayZerg";NA;625;0
"Upgrade";"overlordspeed";NA;625;0
"Upgrade";"CentrificalHooks";NA;625;0
"Upgrade";"SprayZerg";NA;625;0
"Upgrade";"ZergMeleeWeaponsLevel1";NA;625;0
"Upgrade";"ZergMeleeWeaponsLevel2";NA;625;0
"Upgrade";"SprayZerg";NA;625;0
"Upgrade";"SprayZerg";NA;625;0
"Upgrade";"zerglingattackspeed";NA;625;0
"Upgrade";"SprayZerg";NA;625;0
"Upgrade";"ZergMeleeWeaponsLevel3";NA;625;0
"Upgrade";"SprayZerg";NA;625;0
