"type";"unit_name";"on_building";"total_supply_lag";"supply"
"Unit";"Overlord";"Larva";14;0
"Building";"Hatchery";NA;15;0
"Building";"Extractor";NA;19;0
"Building";"SpawningPool";NA;19;0
"Unit";"Overlord";"Larva";23;0
"Unit";"Queen";"Hatchery";24;2
"Unit";"Queen";"Hatchery";26;2
"Unit";"Zergling";"Larva";28;1
"Unit";"Zergling";"Larva";29;1
"Unit";"Zergling";"Larva";30;1
"Unit";"Zergling";"Larva";31;1
"Building";"Hatchery";NA;35;0
"Unit";"Queen";"Hatchery";36;2
"Unit";"Overlord";"Larva";39;0
"Unit";"Overlord";"Larva";42;0
"Building";"CreepTumorQueen";NA;44;0
"Unit";"Queen";"Hatchery";49;2
"Building";"RoachWarren";NA;53;0
"Unit";"Overlord";"Larva";53;0
"Building";"CreepTumor";NA;57;0
"Building";"CreepTumorQueen";NA;57;0
"Unit";"Overlord";"Larva";57;0
"Building";"CreepTumorQueen";NA;57;0
"Building";"Extractor";NA;58;0
"Unit";"Overlord";"Larva";63;0
"Building";"CreepTumorQueen";NA;65;0
"Unit";"Roach";"Larva";65;2
"Unit";"Roach";"Larva";67;2
"Unit";"Roach";"Larva";69;2
"Unit";"Roach";"Larva";71;2
"Unit";"Roach";"Larva";73;2
"Building";"CreepTumor";NA;75;0
"Unit";"Roach";"Larva";75;2
"Unit";"Zergling";"Larva";77;1
"Unit";"Zergling";"Larva";78;1
"Unit";"Roach";"Larva";79;2
"Unit";"Zergling";"Larva";81;1
"Unit";"Zergling";"Larva";82;1
"Unit";"Zergling";"Larva";83;1
"Unit";"Zergling";"Larva";84;1
"Unit";"Zergling";"Larva";85;1
"Unit";"Zergling";"Larva";86;1
"Unit";"Zergling";"Larva";87;1
"Unit";"Zergling";"Larva";88;1
"Unit";"Roach";"Larva";89;2
"Unit";"Roach";"Larva";91;2
"Unit";"Roach";"Larva";93;2
"Building";"Extractor";NA;95;0
"Building";"CreepTumor";NA;95;0
"Unit";"Overlord";"Larva";96;0
"Unit";"Overlord";"Larva";96;0
"Unit";"Overlord";"Larva";96;0
"Unit";"Overlord";"Larva";96;0
"Building";"EvolutionChamber";NA;97;0
"Building";"Extractor";NA;98;0
"Building";"CreepTumor";NA;102;0
"Building";"CreepTumorQueen";NA;102;0
"Unit";"Overlord";"Larva";102;0
"Unit";"Zergling";"Larva";103;1
"Unit";"Zergling";"Larva";104;1
"Unit";"Zergling";"Larva";105;1
"Unit";"Zergling";"Larva";106;1
"Unit";"Zergling";"Larva";107;1
"Unit";"Zergling";"Larva";108;1
"Unit";"Zergling";"Larva";109;1
"Unit";"Zergling";"Larva";110;1
"Upgrade";"GlialReconstitution";"RoachWarren";111;0
"Unit";"Overlord";"Larva";111;0
"Unit";"Overlord";"Larva";111;0
"Building";"Extractor";NA;116;0
"Building";"Spire";NA;116;0
"Building";"CreepTumor";NA;119;0
"Building";"CreepTumor";NA;119;0
"Building";"Extractor";NA;119;0
"Building";"CreepTumor";NA;122;0
"Building";"CreepTumorQueen";NA;122;0
"Building";"CreepTumor";NA;122;0
"Building";"Hatchery";NA;127;0
"Unit";"Overlord";"Larva";130;0
"Building";"BanelingNest";NA;130;0
"Unit";"Roach";"Larva";131;2
"Unit";"Roach";"Larva";133;2
"Unit";"Zergling";"Larva";135;1
"Unit";"Zergling";"Larva";136;1
"Unit";"Zergling";"Larva";137;1
"Unit";"Zergling";"Larva";138;1
"Unit";"Zergling";"Larva";139;1
"Unit";"Zergling";"Larva";140;1
"Building";"CreepTumor";NA;141;0
"Building";"CreepTumor";NA;141;0
"Building";"CreepTumor";NA;141;0
"Building";"CreepTumor";NA;141;0
"Unit";"Overlord";"Larva";141;0
"Unit";"Zergling";"Larva";141;1
"Unit";"Zergling";"Larva";142;1
"Unit";"Zergling";"Larva";143;1
"Unit";"Zergling";"Larva";144;1
"Unit";"Zergling";"Larva";145;1
"Unit";"Zergling";"Larva";146;1
"Unit";"Roach";"Larva";147;2
"Unit";"Roach";"Larva";149;2
"Unit";"Roach";"Larva";151;2
"Building";"CreepTumor";NA;153;0
"Unit";"Overlord";"Larva";153;0
"Unit";"Zergling";"Larva";153;1
"Unit";"Zergling";"Larva";154;1
"Unit";"Zergling";"Larva";155;1
"Unit";"Zergling";"Larva";156;1
"Unit";"Zergling";"Larva";157;1
"Unit";"Zergling";"Larva";158;1
"Unit";"Zergling";"Larva";159;1
"Unit";"Zergling";"Larva";160;1
"Unit";"Zergling";"Larva";161;1
"Unit";"Zergling";"Larva";162;1
"Unit";"Overlord";"Larva";163;0
"Building";"CreepTumorQueen";NA;163;0
"Unit";"Mutalisk";"Larva";163;2
"Unit";"Mutalisk";"Larva";165;2
"Unit";"Mutalisk";"Larva";167;2
"Unit";"Mutalisk";"Larva";169;2
"Unit";"Mutalisk";"Larva";171;2
"Building";"CreepTumor";NA;173;0
"Unit";"Mutalisk";"Larva";173;2
"Unit";"Mutalisk";"Larva";175;2
"Unit";"Mutalisk";"Larva";177;2
"Unit";"Overlord";"Larva";182;0
"Unit";"Zergling";"Larva";185;1
"Unit";"Zergling";"Larva";186;1
"Unit";"Zergling";"Larva";187;1
"Unit";"Zergling";"Larva";188;1
"Unit";"Zergling";"Larva";189;1
"Unit";"Zergling";"Larva";190;1
"Unit";"Zergling";"Larva";191;1
"Unit";"Zergling";"Larva";192;1
"Unit";"Zergling";"Larva";193;1
"Unit";"Zergling";"Larva";194;1
"Unit";"Zergling";"Larva";195;1
"Unit";"Zergling";"Larva";196;1
"Unit";"Zergling";"Larva";197;1
"Unit";"Zergling";"Larva";198;1
"Unit";"Zergling";"Larva";199;1
"Unit";"Zergling";"Larva";200;1
"Unit";"Zergling";"Larva";201;1
"Unit";"Zergling";"Larva";202;1
"Unit";"Overlord";"Larva";203;0
"Unit";"Zergling";"Larva";203;1
"Unit";"Zergling";"Larva";204;1
"Unit";"Zergling";"Larva";205;1
"Unit";"Zergling";"Larva";206;1
"Unit";"Zergling";"Larva";207;1
"Unit";"Zergling";"Larva";208;1
"Building";"CreepTumor";NA;209;0
"Building";"CreepTumorQueen";NA;209;0
"Unit";"Queen";"Hatchery";213;2
"Unit";"Overlord";"Larva";215;0
"Unit";"Zergling";"Larva";215;1
"Unit";"Zergling";"Larva";216;1
"Unit";"Zergling";"Larva";217;1
"Unit";"Zergling";"Larva";218;1
"Unit";"Zergling";"Larva";219;1
"Unit";"Zergling";"Larva";220;1
"Unit";"Zergling";"Larva";221;1
"Unit";"Zergling";"Larva";222;1
"Unit";"Zergling";"Larva";223;1
"Unit";"Zergling";"Larva";224;1
"Unit";"Zergling";"Larva";225;1
"Unit";"Zergling";"Larva";226;1
"Unit";"Zergling";"Larva";227;1
"Unit";"Zergling";"Larva";228;1
"Unit";"Overlord";"Larva";229;0
"Unit";"Zergling";"Larva";229;1
"Unit";"Zergling";"Larva";230;1
"Unit";"Zergling";"Larva";231;1
"Unit";"Zergling";"Larva";232;1
"Unit";"Zergling";"Larva";233;1
"Unit";"Zergling";"Larva";234;1
"Unit";"Zergling";"Larva";235;1
"Unit";"Zergling";"Larva";236;1
"Unit";"Zergling";"Larva";237;1
"Unit";"Zergling";"Larva";238;1
"Unit";"Zergling";"Larva";239;1
"Unit";"Zergling";"Larva";240;1
"Unit";"Zergling";"Larva";241;1
"Unit";"Zergling";"Larva";242;1
"Unit";"Zergling";"Larva";243;1
"Unit";"Zergling";"Larva";244;1
"Unit";"Zergling";"Larva";245;1
"Unit";"Zergling";"Larva";246;1
"Unit";"Zergling";"Larva";247;1
"Unit";"Zergling";"Larva";248;1
"Unit";"Zergling";"Larva";249;1
"Unit";"Zergling";"Larva";250;1
"Unit";"Zergling";"Larva";251;1
"Unit";"Zergling";"Larva";252;1
"Unit";"Zergling";"Larva";253;1
"Unit";"Zergling";"Larva";254;1
"Unit";"Zergling";"Larva";255;1
"Unit";"Zergling";"Larva";256;1
"Unit";"Baneling";"Zergling";257;0
"Unit";"Baneling";"Zergling";257;0
"Unit";"Baneling";"Zergling";257;0
"Unit";"Baneling";"Zergling";257;0
"Unit";"Baneling";"Zergling";257;0
"Unit";"Baneling";"Zergling";257;0
"Unit";"Baneling";"Zergling";257;0
"Unit";"Baneling";"Zergling";257;0
"Unit";"Zergling";"Larva";257;1
"Unit";"Zergling";"Larva";258;1
"Unit";"Zergling";"Larva";259;1
"Unit";"Zergling";"Larva";260;1
"Upgrade";"SprayZerg";NA;261;0
"Upgrade";"SprayZerg";NA;261;0
"Upgrade";"SprayZerg";NA;261;0
"Upgrade";"zerglingmovementspeed";NA;261;0
"Upgrade";"SprayZerg";NA;261;0
"Upgrade";"SprayZerg";NA;261;0
"Upgrade";"SprayZerg";NA;261;0
"Upgrade";"ZergMeleeWeaponsLevel1";NA;261;0
"Upgrade";"CentrificalHooks";NA;261;0
"Upgrade";"SprayZerg";NA;261;0
