"type";"unit_name";"on_building";"total_supply_lag";"supply"
"Building";"Pylon";NA;14;0
"Building";"Gateway";NA;16;0
"Building";"Assimilator";NA;17;0
"Building";"Assimilator";NA;17;0
"Building";"Gateway";NA;18;0
"Building";"CyberneticsCore";NA;20;0
"Building";"Pylon";NA;21;0
"Unit";"Stalker";"Gateway";23;2
"Unit";"Stalker";"Gateway";25;2
"Building";"Pylon";NA;28;0
"Building";"Nexus";NA;28;0
"Unit";"Sentry";"Gateway";29;2
"Unit";"Sentry";"Gateway";31;2
"Building";"Pylon";NA;34;0
"Building";"TwilightCouncil";NA;35;0
"Building";"RoboticsFacility";NA;36;0
"Unit";"Phoenix";"Stargate";39;2
"Unit";"Stalker";"Gateway";44;2
"Unit";"Stalker";"Gateway";46;2
"Unit";"Immortal";"Robotics Facility";50;4
"Unit";"Stalker";"Gateway";57;2
"Building";"Pylon";NA;60;0
"Building";"Assimilator";NA;60;0
"Building";"Assimilator";NA;61;0
"Unit";"Observer";"Robotics Facility";61;1
"Building";"Forge";NA;64;0
"Building";"Pylon";NA;64;0
"Unit";"Stalker";"Gateway";65;2
"Unit";"Stalker";"Gateway";67;2
"Unit";"Immortal";"Robotics Facility";71;4
"Building";"Pylon";NA;75;0
"Building";"Pylon";NA;75;0
"Building";"Pylon";NA;77;0
"Upgrade";"ProtossGroundWeaponsLevel1";"Forge";77;0
"Building";"Nexus";NA;77;0
"Unit";"Immortal";"Robotics Facility";77;4
"Upgrade";"Charge";"TwilightCouncil";81;0
"Building";"Gateway";NA;85;0
"Building";"Gateway";NA;85;0
"Building";"Gateway";NA;85;0
"Unit";"Immortal";"Robotics Facility";85;4
"Building";"Gateway";NA;89;0
"Unit";"Phoenix";"Stargate";91;2
"Building";"Gateway";NA;95;0
"Building";"Gateway";NA;95;0
"Building";"TemplarArchive";NA;97;0
"Unit";"Immortal";"Robotics Facility";97;4
"Building";"Pylon";NA;104;0
"Building";"PhotonCannon";NA;104;0
"Building";"HighTemplar";NA;109;0
"Building";"HighTemplar";NA;109;0
"Building";"HighTemplar";NA;109;0
"Building";"HighTemplar";NA;109;0
"Unit";"Zealot";"Gateway";109;2
"Unit";"Zealot";"Gateway";111;2
"Building";"PhotonCannon";NA;113;0
"Building";"Assimilator";NA;113;0
"Upgrade";"ProtossGroundWeaponsLevel2";"Forge";113;0
"Unit";"Archon";"High Templar";113;0
"Unit";"Archon";"High Templar";113;0
"Building";"Assimilator";NA;113;0
"Unit";"Immortal";"Robotics Facility";113;4
"Unit";"Zealot";"Gateway";117;2
"Unit";"Zealot";"Gateway";119;2
"Unit";"Zealot";"Gateway";121;2
"Unit";"Zealot";"Gateway";123;2
"Building";"Nexus";NA;126;0
"Building";"HighTemplar";NA;126;0
"Building";"HighTemplar";NA;126;0
"Building";"Pylon";NA;126;0
"Building";"Pylon";NA;126;0
"Building";"Pylon";NA;126;0
"Unit";"Archon";"High Templar";126;0
"Building";"Pylon";NA;126;0
"Unit";"Phoenix";"Stargate";126;2
"Building";"Pylon";NA;128;0
"Building";"HighTemplar";NA;128;0
"Building";"HighTemplar";NA;128;0
"Building";"HighTemplar";NA;128;0
"Building";"HighTemplar";NA;128;0
"Building";"Pylon";NA;128;0
"Unit";"Zealot";"Gateway";128;2
"Unit";"Archon";"High Templar";130;0
"Unit";"Archon";"High Templar";130;0
"Building";"Pylon";NA;130;0
"Unit";"Zealot";"Gateway";130;2
"Building";"HighTemplar";NA;132;0
"Building";"HighTemplar";NA;132;0
"Unit";"Archon";"High Templar";132;0
"Unit";"Zealot";"Gateway";132;2
"Unit";"Zealot";"Gateway";134;2
"Unit";"Zealot";"Gateway";136;2
"Unit";"Zealot";"Gateway";138;2
"Unit";"Zealot";"Gateway";140;2
"Unit";"Zealot";"Gateway";143;2
"Unit";"Zealot";"Gateway";145;2
"Unit";"Zealot";"Gateway";147;2
"Unit";"Zealot";"Gateway";149;2
"Unit";"Zealot";"Gateway";151;2
"Unit";"Zealot";"Gateway";153;2
"Unit";"Zealot";"Gateway";155;2
"Unit";"Zealot";"Gateway";157;2
"Building";"Assimilator";NA;159;0
"Building";"PhotonCannon";NA;159;0
"Upgrade";"ProtossGroundWeaponsLevel3";"Forge";159;0
"Building";"HighTemplar";NA;159;0
"Building";"HighTemplar";NA;159;0
"Building";"HighTemplar";NA;159;0
"Building";"HighTemplar";NA;159;0
"Unit";"Zealot";"Gateway";159;2
"Unit";"Zealot";"Gateway";161;2
"Unit";"Zealot";"Gateway";163;2
"Unit";"Zealot";"Gateway";165;2
"Unit";"Immortal";"Robotics Facility";167;4
"Unit";"Archon";"High Templar";171;0
"Unit";"Archon";"High Templar";171;0
"Building";"RoboticsBay";NA;173;0
"Building";"Gateway";NA;175;0
"Building";"Gateway";NA;175;0
"Unit";"Zealot";"Gateway";175;2
"Unit";"Zealot";"Gateway";177;2
"Unit";"Zealot";"Gateway";179;2
"Unit";"Zealot";"Gateway";181;2
"Building";"Gateway";NA;183;0
"Building";"HighTemplar";NA;183;0
"Building";"HighTemplar";NA;183;0
"Unit";"Archon";"High Templar";183;0
"Unit";"Zealot";"Gateway";183;2
"Unit";"Zealot";"Gateway";185;2
"Unit";"Zealot";"Gateway";187;2
"Unit";"Zealot";"Gateway";189;2
"Unit";"Zealot";"Gateway";191;2
"Unit";"Zealot";"Gateway";193;2
"Unit";"Zealot";"Gateway";196;2
"Unit";"Zealot";"Gateway";198;2
"Unit";"Zealot";"Gateway";200;2
"Unit";"Zealot";"Gateway";202;2
"Unit";"Zealot";"Gateway";204;2
"Unit";"Zealot";"Gateway";206;2
"Unit";"Zealot";"Gateway";208;2
"Unit";"Zealot";"Gateway";210;2
"Unit";"Disruptor";"Robotics Facility";212;3
"Unit";"Zealot";"Gateway";215;2
"Unit";"Zealot";"Gateway";217;2
"Unit";"Zealot";"Gateway";219;2
"Unit";"Zealot";"Gateway";221;2
"Unit";"Zealot";"Gateway";223;2
"Unit";"Zealot";"Gateway";225;2
"Unit";"Zealot";"Gateway";227;2
"Unit";"Zealot";"Gateway";229;2
"Unit";"Zealot";"Gateway";231;2
"Unit";"Zealot";"Gateway";233;2
"Unit";"Zealot";"Gateway";235;2
"Building";"Pylon";NA;237;0
"Building";"RoboticsFacility";NA;237;0
"Unit";"Disruptor";"Robotics Facility";237;3
"Unit";"Zealot";"Gateway";240;2
"Unit";"Zealot";"Gateway";242;2
"Unit";"Zealot";"Gateway";244;2
"Unit";"Zealot";"Gateway";246;2
"Unit";"Zealot";"Gateway";248;2
"Unit";"Zealot";"Gateway";250;2
"Unit";"Zealot";"Gateway";252;2
"Unit";"Zealot";"Gateway";254;2
"Unit";"Zealot";"Gateway";256;2
"Unit";"Zealot";"Gateway";258;2
"Unit";"Zealot";"Gateway";263;2
"Unit";"Zealot";"Gateway";265;2
"Unit";"Zealot";"Gateway";267;2
"Unit";"Zealot";"Gateway";269;2
"Unit";"Zealot";"Gateway";271;2
"Unit";"Disruptor";"Robotics Facility";273;3
"Building";"Pylon";NA;276;0
"Building";"Pylon";NA;276;0
"Unit";"Zealot";"Gateway";276;2
"Unit";"Zealot";"Gateway";278;2
"Unit";"Zealot";"Gateway";280;2
"Unit";"Zealot";"Gateway";282;2
"Unit";"Zealot";"Gateway";284;2
"Unit";"Zealot";"Gateway";286;2
"Unit";"Zealot";"Gateway";288;2
"Unit";"Disruptor";"Robotics Facility";290;3
"Unit";"Disruptor";"Robotics Facility";293;3
"Building";"HighTemplar";NA;296;0
"Building";"HighTemplar";NA;296;0
"Building";"HighTemplar";NA;296;0
"Building";"HighTemplar";NA;296;0
"Unit";"Archon";"High Templar";296;0
"Unit";"Archon";"High Templar";296;0
"Unit";"Zealot";"Gateway";296;2
"Unit";"Zealot";"Gateway";298;2
"Unit";"Zealot";"Gateway";300;2
"Unit";"Zealot";"Gateway";302;2
"Unit";"Zealot";"Gateway";304;2
"Unit";"Zealot";"Gateway";306;2
"Unit";"Disruptor";"Robotics Facility";308;3
"Building";"HighTemplar";NA;311;0
"Building";"HighTemplar";NA;311;0
"Building";"HighTemplar";NA;311;0
"Building";"HighTemplar";NA;311;0
"Building";"HighTemplar";NA;311;0
"Building";"HighTemplar";NA;311;0
"Building";"HighTemplar";NA;311;0
"Building";"HighTemplar";NA;311;0
"Building";"HighTemplar";NA;311;0
"Building";"HighTemplar";NA;311;0
"Unit";"Archon";"High Templar";311;0
"Unit";"Archon";"High Templar";311;0
"Unit";"Archon";"High Templar";311;0
"Unit";"Archon";"High Templar";311;0
"Building";"Nexus";NA;311;0
"Unit";"Archon";"High Templar";311;0
"Building";"HighTemplar";NA;311;0
"Unit";"Zealot";"Gateway";311;2
"Unit";"Zealot";"Gateway";313;2
"Unit";"Zealot";"Gateway";315;2
"Unit";"Zealot";"Gateway";317;2
"Unit";"Zealot";"Gateway";319;2
"Unit";"Zealot";"Gateway";321;2
"Unit";"Zealot";"Gateway";323;2
"Unit";"Zealot";"Gateway";325;2
"Unit";"Zealot";"Gateway";327;2
"Unit";"Immortal";"Robotics Facility";329;4
"Building";"PhotonCannon";NA;333;0
"Building";"PhotonCannon";NA;333;0
"Building";"PhotonCannon";NA;333;0
"Building";"Pylon";NA;333;0
"Building";"HighTemplar";NA;333;0
"Building";"Pylon";NA;333;0
"Building";"HighTemplar";NA;333;0
"Building";"HighTemplar";NA;333;0
"Building";"Assimilator";NA;333;0
"Unit";"Zealot";"Gateway";333;2
"Unit";"Zealot";"Gateway";335;2
"Unit";"Zealot";"Gateway";337;2
"Unit";"Zealot";"Gateway";339;2
"Unit";"Zealot";"Gateway";341;2
"Unit";"Archon";"High Templar";343;0
"Building";"Assimilator";NA;343;0
"Unit";"Archon";"High Templar";343;0
"Unit";"Immortal";"Robotics Facility";343;4
"Building";"DarkShrine";NA;347;0
"Unit";"Zealot";"Gateway";347;2
"Unit";"Zealot";"Gateway";349;2
"Unit";"Zealot";"Gateway";351;2
"Unit";"Zealot";"Gateway";353;2
"Unit";"Zealot";"Gateway";355;2
"Unit";"Zealot";"Gateway";357;2
"Unit";"Zealot";"Gateway";359;2
"Unit";"Zealot";"Gateway";361;2
"Unit";"Zealot";"Gateway";363;2
"Unit";"Zealot";"Gateway";365;2
"Unit";"Zealot";"Gateway";367;2
"Unit";"Zealot";"Gateway";369;2
"Unit";"Zealot";"Gateway";371;2
"Unit";"Zealot";"Gateway";373;2
"Unit";"Zealot";"Gateway";375;2
"Unit";"Zealot";"Gateway";377;2
"Unit";"Zealot";"Gateway";379;2
"Unit";"Zealot";"Gateway";381;2
"Unit";"Zealot";"Gateway";383;2
"Unit";"Zealot";"Gateway";385;2
"Unit";"Zealot";"Gateway";387;2
"Unit";"Zealot";"Gateway";389;2
"Unit";"Zealot";"Gateway";391;2
"Unit";"Zealot";"Gateway";393;2
"Unit";"Zealot";"Gateway";395;2
"Unit";"Zealot";"Gateway";397;2
"Unit";"Zealot";"Gateway";399;2
"Unit";"Zealot";"Gateway";401;2
"Unit";"Zealot";"Gateway";403;2
"Upgrade";"SprayProtoss";NA;405;0
"Upgrade";"WarpGateResearch";NA;405;0
"Upgrade";"SprayProtoss";NA;405;0
"Upgrade";"BlinkTech";NA;405;0
"Upgrade";"SprayProtoss";NA;405;0
"Upgrade";"SprayProtoss";NA;405;0
"Upgrade";"SprayProtoss";NA;405;0
"Upgrade";"SprayProtoss";NA;405;0
"Upgrade";"SprayProtoss";NA;405;0
"Upgrade";"ProtossGroundArmorsLevel1";NA;405;0
"Upgrade";"SprayProtoss";NA;405;0
"Upgrade";"ProtossGroundArmorsLevel2";NA;405;0
