"Type";"UnitName";"OnBuilding";"TotalSupply";"Supply"
"Unit";"SCV";"Command Center";12;1
"Unit";"SCV";"Command Center";12;1
"Unit";"SCV";"Command Center";13;1
"Building";"SupplyDepot";NA;13;0
"Unit";"SCV";"Command Center";15;1
"Unit";"SCV";"Command Center";15;1
"Building";"Refinery";NA;15;0
"Unit";"SCV";"Command Center";16;1
"Building";"Barracks";NA;15;0
"Unit";"SCV";"Command Center";17;1
"Unit";"Reaper";"Barracks";19;1
"Building";"SupplyDepot";NA;19;0
"Unit";"SCV";"Command Center";20;1
"Unit";"SCV";"Command Center";20;1
"Unit";"SCV";"Command Center";21;1
"Building";"BarracksReactor";NA;20;0
"Building";"Refinery";NA;22;0
"Unit";"SCV";"Command Center";22;1
"Building";"CommandCenter";NA;19;0
"Unit";"SCV";"Command Center";23;1
"Building";"Factory";NA;21;0
"Unit";"Marine";"Barracks";23;1
"Unit";"Marine";"Barracks";23;1
"Unit";"SCV";"Command Center";24;1
"Unit";"SCV";"Command Center";27;1
"Unit";"SCV";"Command Center";28;1
"Building";"BarracksTechLab";NA;27;0
"Unit";"Hellion";"Factory";27;2
"Unit";"Hellion";"Factory";27;2
"Unit";"SCV";"Command Center";28;1
"Unit";"SCV";"Command Center";29;1
"Building";"SupplyDepot";NA;28;0
"Unit";"SCV";"Command Center";34;1
"Building";"Starport";NA;28;0
"Unit";"SCV";"Command Center";36;1
"Unit";"Hellion";"Factory";35;2
"Unit";"Hellion";"Factory";35;2
"Unit";"SCV";"Command Center";36;1
"Building";"Bunker";NA;35;0
"Unit";"SCV";"Command Center";37;1
"Building";"SupplyDepot";NA;36;0
"Building";"SupplyDepot";NA;37;0
"Unit";"SCV";"Command Center";43;1
"Unit";"Marine";"Barracks";38;1
"Unit";"SCV";"Command Center";43;1
"Unit";"Medivac";"Starport";38;2
"Unit";"SCV";"Command Center";45;1
"Unit";"SCV";"Command Center";46;1
"Unit";"Marine";"Barracks";47;1
"Building";"Refinery";NA;46;0
"Unit";"SCV";"Command Center";49;1
"Unit";"SCV";"Command Center";51;1
"Building";"FactoryReactor";NA;44;0
"Unit";"SCV";"Command Center";52;1
"Unit";"SCV";"Command Center";53;1
"Unit";"Marine";"Barracks";52;1
"Unit";"Medivac";"Starport";50;2
"Building";"Barracks";NA;44;0
"Unit";"SCV";"Command Center";54;1
"Unit";"SCV";"Command Center";55;1
"Building";"EngineeringBay";NA;54;0
"Building";"Refinery";NA;54;0
"Building";"Barracks";NA;49;0
"Unit";"SCV";"Command Center";59;1
"Building";"SupplyDepot";NA;57;0
"Unit";"SCV";"Command Center";60;1
"Building";"FactoryTechLab";NA;59;0
"Building";"SupplyDepot";NA;59;0
"Unit";"SCV";"Command Center";61;1
"Unit";"SCV";"Command Center";62;1
"Unit";"SCV";"Command Center";63;1
"Building";"Barracks";NA;55;0
"Unit";"SCV";"Command Center";64;1
"Unit";"SCV";"Command Center";65;1
"Unit";"Marine";"Barracks";65;1
"Unit";"Marine";"Barracks";65;1
"Unit";"Marine";"Barracks";65;1
"Unit";"SCV";"Command Center";66;1
"Upgrade";"Stimpack";"TechLab";50;0
"Unit";"SCV";"Command Center";67;1
"Unit";"Marine";"Barracks";67;1
"Unit";"Marine";"Barracks";67;1
"Building";"SupplyDepot";NA;67;0
"Unit";"SCV";"Command Center";71;1
"Building";"StarportReactor";NA;65;0
"Unit";"Marine";"Barracks";68;1
"Unit";"Marine";"Barracks";72;1
"Unit";"Marine";"Barracks";72;1
"Unit";"SCV";"Command Center";72;1
"Building";"SupplyDepot";NA;72;0
"Building";"BarracksReactor";NA;66;0
"Unit";"SCV";"Command Center";75;1
"Unit";"Marine";"Barracks";73;1
"Unit";"Marine";"Barracks";74;1
"Building";"Barracks";NA;65;0
"Building";"SupplyDepot";NA;76;0
"Unit";"Marine";"Barracks";76;1
"Unit";"Marine";"Barracks";77;1
"Unit";"Marine";"Barracks";78;1
"Unit";"Marine";"Barracks";80;1
"Unit";"Marine";"Barracks";81;1
"Unit";"Marine";"Barracks";81;1
"Unit";"Marine";"Barracks";82;1
"Unit";"Medivac";"Starport";76;2
"Unit";"Medivac";"Starport";76;2
"Building";"SupplyDepot";NA;81;0
"Unit";"SCV";"Command Center";83;1
"Unit";"SCV";"Command Center";83;1
"Unit";"Marine";"Barracks";83;1
"Unit";"Marine";"Barracks";84;1
"Unit";"Marine";"Barracks";85;1
"Building";"SupplyDepot";NA;85;0
"Unit";"Marine";"Barracks";86;1
"Unit";"Marine";"Barracks";88;1
"Unit";"Marine";"Barracks";88;1
"Unit";"Marine";"Barracks";90;1
"Building";"BarracksReactor";NA;83;0
"Unit";"Marine";"Barracks";96;1
"Building";"SupplyDepot";NA;96;0
"Unit";"Marine";"Barracks";97;1
"Unit";"Marine";"Barracks";98;1
"Unit";"Medivac";"Starport";90;2
"Unit";"Medivac";"Starport";94;2
"Unit";"Marine";"Barracks";99;1
"Unit";"Marine";"Barracks";100;1
"Building";"SupplyDepot";NA;99;0
"Unit";"Marine";"Barracks";101;1
"Unit";"Marine";"Barracks";102;1
"Unit";"Marine";"Barracks";103;1
"Unit";"Marine";"Barracks";103;1
"Unit";"Marine";"Barracks";103;1
"Building";"SupplyDepot";NA;106;0
"Upgrade";"TerranInfantryWeaponsLevel1";"EngineeringBay";76;0
"Unit";"Marine";"Barracks";111;1
"Unit";"Marine";"Barracks";112;1
"Unit";"Marine";"Barracks";114;1
"Unit";"Marine";"Barracks";115;1
"Unit";"Marine";"Barracks";116;1
"Unit";"Marine";"Barracks";117;1
"Unit";"Marine";"Barracks";117;1
"Unit";"Marine";"Barracks";117;1
"Unit";"Marine";"Barracks";117;1
"Unit";"Marine";"Barracks";119;1
"Unit";"Marine";"Barracks";119;1
"Unit";"Marine";"Barracks";119;1
"Unit";"Marine";"Barracks";122;1
"Unit";"Medivac";"Starport";117;2
"Unit";"Medivac";"Starport";119;2
"Building";"SupplyDepot";NA;126;0
"Unit";"Marine";"Barracks";129;1
"Unit";"Marine";"Barracks";130;1
"Unit";"Marine";"Barracks";130;1
"Unit";"Marine";"Barracks";130;1
"Unit";"Marine";"Barracks";132;1
"Unit";"Marine";"Barracks";132;1
"Unit";"Marine";"Barracks";132;1
"Unit";"Marine";"Barracks";132;1
"Unit";"Marine";"Barracks";132;1
"Unit";"Marine";"Barracks";134;1
"Unit";"Marine";"Barracks";135;1
"Building";"CommandCenter";NA;117;0
"Unit";"Marine";"Barracks";138;1
"Unit";"Marine";"Barracks";138;1
"Unit";"Marine";"Barracks";139;1
"Building";"EngineeringBay";NA;138;0
"Unit";"Marine";"Barracks";143;1
"Unit";"Marine";"Barracks";143;1
"Unit";"Marine";"Barracks";143;1
"Unit";"Marine";"Barracks";143;1
"Unit";"Marine";"Barracks";143;1
"Unit";"Marine";"Barracks";144;1
