"type";"unit_name";"on_building";"total_supply_lag";"supply"
"Building";"Barracks";NA;16;0
"Building";"Refinery";NA;16;0
"Unit";"Reaper";"Barracks";19;1
"Building";"CommandCenter";NA;20;0
"Unit";"Marine";"Barracks";21;1
"Building";"Factory";NA;23;0
"Building";"Refinery";NA;23;0
"Building";"BarracksReactor";NA;24;0
"Building";"Starport";NA;26;0
"Unit";"Hellion";"Factory";27;2
"Unit";"Hellion";"Factory";29;2
"Building";"BarracksTechLab";NA;32;0
"Unit";"Hellion";"Factory";34;2
"Unit";"Hellion";"Factory";36;2
"Unit";"Medivac";"Starport";38;2
"Unit";"Marine";"Barracks";44;1
"Building";"FactoryTechLab";NA;47;0
"Building";"CommandCenter";NA;47;0
"Unit";"Marine";"Barracks";49;1
"Building";"StarportReactor";NA;50;0
"Upgrade";"Stimpack";"TechLab";50;0
"Building";"Barracks";NA;50;0
"Unit";"Marine";"Barracks";52;1
"Building";"Barracks";NA;53;0
"Building";"EngineeringBay";NA;55;0
"Building";"EngineeringBay";NA;55;0
"Building";"Refinery";NA;55;0
"Building";"Refinery";NA;55;0
"Unit";"Marine";"Barracks";57;1
"Unit";"Marine";"Barracks";60;1
"Building";"StarportReactor";NA;61;0
"Unit";"Marine";"Barracks";63;1
"Unit";"Marine";"Barracks";64;1
"Unit";"Marine";"Barracks";65;1
"Unit";"Marine";"Barracks";66;1
"Unit";"Marine";"Barracks";67;1
"Unit";"Marine";"Barracks";70;1
"Unit";"Marine";"Barracks";71;1
"Unit";"Marine";"Barracks";74;1
"Unit";"Marine";"Barracks";75;1
"Unit";"Marine";"Barracks";76;1
"Unit";"Medivac";"Starport";77;2
"Unit";"Medivac";"Starport";79;2
"Upgrade";"TerranInfantryWeaponsLevel1";"EngineeringBay";81;0
"Unit";"Marine";"Barracks";83;1
"Unit";"Marine";"Barracks";84;1
"Unit";"Marine";"Barracks";85;1
"Unit";"Marine";"Barracks";86;1
"Unit";"Marine";"Barracks";87;1
"Building";"Barracks";NA;90;0
"Building";"Barracks";NA;90;0
"Unit";"Marine";"Barracks";93;1
"Unit";"Marine";"Barracks";94;1
"Unit";"Marine";"Barracks";95;1
"Unit";"Marine";"Barracks";96;1
"Unit";"Marine";"Barracks";97;1
"Unit";"Marine";"Barracks";101;1
"Unit";"Marine";"Barracks";102;1
"Unit";"Marine";"Barracks";103;1
"Unit";"Marine";"Barracks";104;1
"Building";"Armory";NA;105;0
"Unit";"Medivac";"Starport";105;2
"Unit";"Marine";"Barracks";107;1
"Unit";"Medivac";"Starport";111;2
"Building";"BarracksReactor";NA;113;0
"Building";"BarracksReactor";NA;113;0
"Unit";"Marine";"Barracks";113;1
"Unit";"Marine";"Barracks";114;1
"Unit";"Marine";"Barracks";115;1
"Unit";"Marine";"Barracks";118;1
"Unit";"Marine";"Barracks";120;1
"Building";"Refinery";NA;121;0
"Building";"Refinery";NA;121;0
"Unit";"Marine";"Barracks";124;1
"Unit";"Marine";"Barracks";125;1
"Unit";"Marine";"Barracks";126;1
"Unit";"Medivac";"Starport";127;2
"Unit";"Medivac";"Starport";129;2
"Unit";"Marine";"Barracks";131;1
"Unit";"Marine";"Barracks";132;1
"Unit";"Marine";"Barracks";133;1
"Unit";"Marine";"Barracks";134;1
"Unit";"Marine";"Barracks";135;1
"Unit";"Marine";"Barracks";136;1
"Unit";"Marine";"Barracks";137;1
"Unit";"Marine";"Barracks";138;1
"Building";"Factory";NA;139;0
"Unit";"Marine";"Barracks";139;1
"Unit";"Marine";"Barracks";140;1
"Unit";"Marine";"Barracks";141;1
"Unit";"Marine";"Barracks";142;1
"Unit";"Marine";"Barracks";143;1
"Unit";"Marine";"Barracks";144;1
"Unit";"Marine";"Barracks";145;1
"Unit";"Marine";"Barracks";146;1
"Unit";"Marauder";"Barracks";147;2
"Upgrade";"TerranInfantryWeaponsLevel2";"EngineeringBay";152;0
"Unit";"Marine";"Barracks";155;1
"Unit";"Marine";"Barracks";156;1
"Unit";"Marine";"Barracks";157;1
"Unit";"Marine";"Barracks";158;1
"Unit";"Marine";"Barracks";159;1
"Unit";"Marine";"Barracks";160;1
"Unit";"Marine";"Barracks";161;1
"Unit";"Marine";"Barracks";162;1
"Unit";"Marine";"Barracks";163;1
"Unit";"Marine";"Barracks";167;1
"Unit";"Marauder";"Barracks";168;2
"Unit";"Marine";"Barracks";170;1
"Unit";"Marine";"Barracks";171;1
"Unit";"Marine";"Barracks";172;1
"Unit";"Marine";"Barracks";173;1
"Unit";"Marine";"Barracks";174;1
"Unit";"Marine";"Barracks";175;1
"Unit";"Marine";"Barracks";176;1
"Building";"FactoryTechLab";NA;177;0
"Unit";"Marauder";"Barracks";177;2
"Unit";"Medivac";"Starport";179;2
"Unit";"Medivac";"Starport";181;2
"Unit";"Marine";"Barracks";183;1
"Unit";"Marine";"Barracks";184;1
"Unit";"Marine";"Barracks";185;1
"Unit";"Marine";"Barracks";186;1
"Unit";"Marine";"Barracks";187;1
"Unit";"Marauder";"Barracks";191;2
"Building";"CommandCenter";NA;193;0
"Unit";"Marine";"Barracks";193;1
"Unit";"Marine";"Barracks";194;1
"Unit";"Marine";"Barracks";195;1
"Unit";"Marine";"Barracks";196;1
"Unit";"Marine";"Barracks";197;1
"Unit";"Marine";"Barracks";198;1
"Unit";"Marine";"Barracks";199;1
"Unit";"Marine";"Barracks";200;1
"Unit";"Liberator";"Starport";201;3
"Unit";"Liberator";"Starport";204;3
"Unit";"Marine";"Barracks";207;1
"Building";"SensorTower";NA;208;0
"Unit";"Marine";"Barracks";208;1
"Unit";"Marine";"Barracks";209;1
"Unit";"Marine";"Barracks";210;1
"Unit";"Marine";"Barracks";211;1
"Unit";"Marine";"Barracks";212;1
"Unit";"Marine";"Barracks";213;1
"Unit";"Marauder";"Barracks";214;2
"Unit";"Marine";"Barracks";216;1
"Unit";"Marine";"Barracks";217;1
"Unit";"Marine";"Barracks";218;1
"Unit";"Marauder";"Barracks";219;2
"Building";"CommandCenter";NA;224;0
"Unit";"Liberator";"Starport";224;3
"Unit";"Liberator";"Starport";227;3
"Unit";"Marine";"Barracks";230;1
"Unit";"Marine";"Barracks";231;1
"Unit";"Marine";"Barracks";232;1
"Unit";"Marine";"Barracks";233;1
"Unit";"Marine";"Barracks";234;1
"Unit";"Marine";"Barracks";235;1
"Unit";"Marine";"Barracks";236;1
"Upgrade";"TerranInfantryWeaponsLevel3";"EngineeringBay";241;0
"Building";"SensorTower";NA;247;0
"Unit";"Marauder";"Barracks";247;2
"Unit";"Marine";"Barracks";249;1
"Unit";"Marine";"Barracks";250;1
"Unit";"Marine";"Barracks";251;1
"Unit";"Marine";"Barracks";252;1
"Unit";"Marine";"Barracks";253;1
"Unit";"Marine";"Barracks";254;1
"Unit";"Marine";"Barracks";255;1
"Unit";"Marine";"Barracks";256;1
"Unit";"Medivac";"Starport";260;2
"Unit";"Medivac";"Starport";262;2
"Unit";"Marine";"Barracks";264;1
"Unit";"Marine";"Barracks";265;1
"Unit";"Marine";"Barracks";266;1
"Unit";"Marauder";"Barracks";267;2
"Unit";"Marine";"Barracks";269;1
"Unit";"Marine";"Barracks";270;1
"Unit";"Marine";"Barracks";271;1
"Unit";"Marine";"Barracks";272;1
"Unit";"Marine";"Barracks";273;1
"Unit";"Marine";"Barracks";274;1
"Unit";"Marine";"Barracks";275;1
"Unit";"Marine";"Barracks";276;1
"Building";"GhostAcademy";NA;280;0
"Unit";"Marine";"Barracks";280;1
"Unit";"Marine";"Barracks";281;1
"Unit";"Marine";"Barracks";282;1
"Unit";"Marine";"Barracks";283;1
"Unit";"Marine";"Barracks";284;1
"Unit";"Marine";"Barracks";285;1
"Unit";"Marine";"Barracks";286;1
"Unit";"Marine";"Barracks";287;1
"Building";"Barracks";NA;288;0
"Unit";"Marine";"Barracks";288;1
"Building";"Barracks";NA;289;0
"Building";"Barracks";NA;289;0
"Unit";"Marine";"Barracks";292;1
"Unit";"Marine";"Barracks";293;1
"Unit";"Marine";"Barracks";294;1
"Building";"CommandCenter";NA;295;0
"Unit";"Liberator";"Starport";295;3
"Unit";"Liberator";"Starport";298;3
"Unit";"Marauder";"Barracks";301;2
"Unit";"Marine";"Barracks";303;1
"Unit";"Marine";"Barracks";304;1
"Unit";"Marine";"Barracks";305;1
"Unit";"Marine";"Barracks";306;1
"Unit";"Marine";"Barracks";307;1
"Unit";"Marine";"Barracks";308;1
"Unit";"Marine";"Barracks";309;1
"Unit";"Marine";"Barracks";310;1
"Unit";"Marine";"Barracks";311;1
"Unit";"Marine";"Barracks";312;1
"Unit";"Marine";"Barracks";313;1
"Unit";"Marine";"Barracks";314;1
"Building";"GhostAcademy";NA;315;0
"Building";"GhostAcademy";NA;315;0
"Building";"GhostAcademy";NA;315;0
"Building";"BarracksTechLab";NA;315;0
"Building";"BarracksTechLab";NA;315;0
"Building";"BarracksTechLab";NA;315;0
"Building";"Refinery";NA;316;0
"Building";"Refinery";NA;316;0
"Building";"Refinery";NA;316;0
"Building";"Refinery";NA;316;0
"Unit";"Marauder";"Barracks";316;2
"Unit";"Marine";"Barracks";318;1
"Unit";"Marine";"Barracks";320;1
"Unit";"Marine";"Barracks";321;1
"Unit";"Marine";"Barracks";322;1
"Upgrade";"SprayTerran";NA;323;0
"Upgrade";"SprayTerran";NA;323;0
"Upgrade";"SprayTerran";NA;323;0
"Upgrade";"SprayTerran";NA;323;0
"Upgrade";"ShieldWall";NA;323;0
"Upgrade";"TerranInfantryArmorsLevel1";NA;323;0
"Upgrade";"SprayTerran";NA;323;0
"Upgrade";"TerranInfantryArmorsLevel2";NA;323;0
"Upgrade";"SprayTerran";NA;323;0
"Upgrade";"SprayTerran";NA;323;0
"Upgrade";"TerranVehicleAndShipArmorsLevel1";NA;323;0
"Upgrade";"SprayTerran";NA;323;0
"Upgrade";"SprayTerran";NA;323;0
"Upgrade";"TerranInfantryArmorsLevel3";NA;323;0
"Upgrade";"SprayTerran";NA;323;0
"Upgrade";"HiSecAutoTracking";NA;323;0
"Upgrade";"SprayTerran";NA;323;0
