"Type";"UnitName";"OnBuilding";"TotalSupply";"Supply"
"Unit";"SCV";"Command Center";12;1
"Unit";"SCV";"Command Center";12;1
"Unit";"SCV";"Command Center";13;1
"Building";"SupplyDepot";NA;13;0
"Unit";"SCV";"Command Center";15;1
"Unit";"SCV";"Command Center";15;1
"Building";"Refinery";NA;15;0
"Unit";"SCV";"Command Center";16;1
"Building";"Barracks";NA;15;0
"Unit";"SCV";"Command Center";17;1
"Unit";"Reaper";"Barracks";19;1
"Unit";"SCV";"Command Center";19;1
"Building";"SupplyDepot";NA;19;0
"Unit";"Marine";"Barracks";20;1
"Unit";"SCV";"Command Center";21;1
"Unit";"SCV";"Command Center";22;1
"Building";"Refinery";NA;21;0
"Unit";"SCV";"Command Center";23;1
"Building";"CommandCenter";NA;19;0
"Building";"Factory";NA;21;0
"Unit";"SCV";"Command Center";24;1
"Building";"BarracksReactor";NA;23;0
"Unit";"SCV";"Command Center";25;1
"Unit";"SCV";"Command Center";26;1
"Unit";"Hellion";"Factory";26;2
"Unit";"Hellion";"Factory";26;2
"Building";"BarracksTechLab";NA;27;0
"Unit";"SCV";"Command Center";27;1
"Unit";"SCV";"Command Center";28;1
"Building";"Starport";NA;26;0
"Unit";"SCV";"Command Center";32;1
"Building";"SupplyDepot";NA;28;0
"Unit";"SCV";"Command Center";34;1
"Unit";"Hellion";"Factory";34;2
"Unit";"Hellion";"Factory";34;2
"Unit";"SCV";"Command Center";35;1
"Unit";"SCV";"Command Center";36;1
"Unit";"Marine";"Barracks";34;1
"Building";"SupplyDepot";NA;35;0
"Unit";"SCV";"Command Center";40;1
"Unit";"SCV";"Command Center";41;1
"Unit";"Hellion";"Factory";36;2
"Unit";"Hellion";"Factory";38;2
"Building";"BarracksTechLab";NA;43;0
"Unit";"SCV";"Command Center";43;1
"Unit";"SCV";"Command Center";44;1
"Unit";"Raven";"Starport";36;2
"Unit";"SCV";"Command Center";49;1
"Unit";"SCV";"Command Center";50;1
"Unit";"SCV";"Command Center";53;1
"Building";"SupplyDepot";NA;51;0
"Unit";"SCV";"Command Center";54;1
"Building";"Refinery";NA;55;0
"Unit";"Marine";"Barracks";55;1
"Unit";"SCV";"Command Center";55;1
"Unit";"SCV";"Command Center";57;1
"Unit";"SCV";"Command Center";58;1
"Unit";"Marine";"Barracks";57;1
"Unit";"SCV";"Command Center";60;1
"Building";"StarportReactor";NA;57;0
"Building";"SupplyDepot";NA;60;0
"Building";"EngineeringBay";NA;60;0
"Building";"EngineeringBay";NA;60;0
"Building";"CommandCenter";NA;49;0
"Building";"SupplyDepot";NA;60;0
"Building";"SupplyDepot";NA;61;0
"Unit";"Marine";"Barracks";61;1
"Building";"Barracks";NA;57;0
"Unit";"SCV";"Command Center";63;1
"Building";"Barracks";NA;57;0
"Unit";"SCV";"Command Center";63;1
"Unit";"SCV";"Command Center";64;1
"Unit";"Marine";"Barracks";63;1
"Unit";"Marine";"Barracks";65;1
"Unit";"Marine";"Barracks";65;1
"Building";"Refinery";NA;65;0
"Unit";"Marine";"Barracks";66;1
"Unit";"Marine";"Barracks";66;1
"Unit";"Marine";"Barracks";66;1
"Unit";"Marine";"Barracks";68;1
"Building";"StarportReactor";NA;65;0
"Unit";"SCV";"Command Center";72;1
"Unit";"SCV";"Command Center";72;1
"Unit";"Marine";"Barracks";72;1
"Unit";"Marine";"Barracks";72;1
"Unit";"Marine";"Barracks";72;1
"Unit";"Marine";"Barracks";72;1
"Unit";"Marine";"Barracks";73;1
"Upgrade";"Stimpack";"TechLab";61;0
"Building";"Barracks";NA;68;0
"Building";"Barracks";NA;68;0
"Unit";"Marine";"Barracks";76;1
"Unit";"Marine";"Barracks";77;1
"Unit";"Marine";"Barracks";78;1
"Building";"SupplyDepot";NA;80;0
"Unit";"Medivac";"Starport";76;2
"Unit";"Medivac";"Starport";76;2
"Unit";"SCV";"Command Center";84;1
"Unit";"Marine";"Barracks";84;1
"Unit";"Marine";"Barracks";84;1
"Unit";"Marine";"Barracks";84;1
"Unit";"Marine";"Barracks";84;1
"Unit";"Marine";"Barracks";84;1
"Building";"Armory";NA;80;0
"Unit";"Marine";"Barracks";89;1
"Unit";"Marine";"Barracks";90;1
"Unit";"SCV";"Command Center";94;1
"Unit";"Marine";"Barracks";91;1
"Unit";"Marine";"Barracks";92;1
"Unit";"Marine";"Barracks";93;1
"Unit";"SCV";"Command Center";96;1
"Unit";"SCV";"Command Center";96;1
"Unit";"Medivac";"Starport";91;2
"Unit";"Medivac";"Starport";91;2
"Building";"BarracksReactor";NA;89;0
"Building";"MissileTurret";NA;94;0
"Unit";"Marine";"Barracks";94;1
"Unit";"Marine";"Barracks";95;1
"Building";"MissileTurret";NA;97;0
"Building";"SupplyDepot";NA;94;0
"Building";"BarracksReactor";NA;91;0
"Building";"SupplyDepot";NA;96;0
"Unit";"SCV";"Command Center";100;1
"Unit";"SCV";"Command Center";102;1
"Unit";"SCV";"Command Center";102;1
"Upgrade";"TerranInfantryWeaponsLevel1";"EngineeringBay";80;0
"Unit";"Marine";"Barracks";106;1
"Unit";"Marine";"Barracks";106;1
"Upgrade";"TerranInfantryArmorsLevel1";"EngineeringBay";80;0
"Unit";"SCV";"Command Center";108;1
"Unit";"SCV";"Command Center";109;1
"Unit";"SCV";"Command Center";110;1
"Unit";"Marine";"Barracks";108;1
"Unit";"Marine";"Barracks";108;1
"Unit";"Marine";"Barracks";108;1
"Unit";"Marine";"Barracks";108;1
"Unit";"Marine";"Barracks";108;1
"Unit";"Marine";"Barracks";111;1
"Unit";"Marine";"Barracks";111;1
"Unit";"Marine";"Barracks";113;1
"Unit";"Marine";"Barracks";113;1
"Unit";"Marine";"Barracks";116;1
"Unit";"Marine";"Barracks";117;1
"Unit";"Marine";"Barracks";118;1
"Unit";"Marine";"Barracks";119;1
"Unit";"Marine";"Barracks";123;1
"Unit";"Marine";"Barracks";123;1
"Building";"SupplyDepot";NA;125;0
"Building";"SupplyDepot";NA;125;0
"Building";"SupplyDepot";NA;125;0
"Unit";"Marine";"Barracks";131;1
"Unit";"Marine";"Barracks";131;1
"Unit";"Marine";"Barracks";131;1
"Unit";"Marine";"Barracks";131;1
"Unit";"Marine";"Barracks";131;1
"Unit";"Marine";"Barracks";131;1
"Unit";"Marauder";"Barracks";131;2
"Unit";"Marine";"Barracks";131;1
"Unit";"Marine";"Barracks";131;1
"Unit";"Medivac";"Starport";131;2
"Unit";"Medivac";"Starport";131;2
"Unit";"Marine";"Barracks";133;1
"Unit";"Marine";"Barracks";137;1
"Unit";"Marine";"Barracks";137;1
"Unit";"Marine";"Barracks";137;1
"Unit";"Marauder";"Barracks";137;2
"Unit";"SCV";"Command Center";145;1
"Unit";"SCV";"Command Center";145;1
"Building";"SupplyDepot";NA;145;0
"Building";"SupplyDepot";NA;145;0
"Building";"Refinery";NA;145;0
"Building";"Factory";NA;131;0
"Unit";"Marine";"Barracks";149;1
"Unit";"Marine";"Barracks";149;1
"Unit";"Medivac";"Starport";141;2
"Unit";"Medivac";"Starport";141;2
"Unit";"Marine";"Barracks";153;1
"Unit";"Marine";"Barracks";153;1
"Building";"Barracks";NA;133;0
"Building";"Barracks";NA;137;0
"Unit";"Marine";"Barracks";153;1
"Unit";"Marine";"Barracks";153;1
"Unit";"Marine";"Barracks";153;1
"Unit";"Marine";"Barracks";153;1
"Unit";"Marine";"Barracks";153;1
"Building";"SupplyDepot";NA;153;0
"Unit";"Marine";"Barracks";153;1
"Unit";"SCV";"Command Center";166;1
"Unit";"Marine";"Barracks";161;1
"Unit";"Marine";"Barracks";161;1
"Unit";"Marine";"Barracks";161;1
"Unit";"SCV";"Command Center";166;1
"Unit";"SCV";"Command Center";166;1
"Building";"BarracksTechLab";NA;161;0
"Unit";"Marine";"Barracks";161;1
"Unit";"Marine";"Barracks";162;1
"Building";"BarracksTechLab";NA;163;0
"Unit";"Marine";"Barracks";166;1
"Building";"GhostAcademy";NA;166;0
"Unit";"Marine";"Barracks";171;1
"Unit";"Marine";"Barracks";171;1
"Unit";"Marine";"Barracks";171;1
"Unit";"Marine";"Barracks";175;1
"Unit";"Marine";"Barracks";175;1
"Unit";"Marine";"Barracks";175;1
"Unit";"Marine";"Barracks";175;1
"Unit";"Marine";"Barracks";176;1
"Unit";"SCV";"Command Center";179;1
"Unit";"Marauder";"Barracks";176;2
"Unit";"Marine";"Barracks";176;1
"Unit";"Marine";"Barracks";176;1
"Unit";"Marine";"Barracks";176;1
"Unit";"Marine";"Barracks";190;1
"Unit";"Marine";"Barracks";190;1
"Unit";"Marine";"Barracks";190;1
"Unit";"Marine";"Barracks";190;1
"Unit";"Marine";"Barracks";190;1
"Building";"FactoryTechLab";NA;190;0
"Building";"Barracks";NA;176;0
"Unit";"Marine";"Barracks";190;1
"Unit";"Marine";"Barracks";190;1
"Unit";"Marine";"Barracks";190;1
"Unit";"Marine";"Barracks";195;1
"Unit";"Marine";"Barracks";195;1
"Unit";"Marine";"Barracks";195;1
"Upgrade";"TerranInfantryWeaponsLevel2";"EngineeringBay";159;0
"Unit";"Marine";"Barracks";198;1
"Unit";"Marine";"Barracks";198;1
"Unit";"Marine";"Barracks";198;1
"Unit";"Marine";"Barracks";198;1
"Upgrade";"TerranInfantryArmorsLevel2";"EngineeringBay";161;0
"Unit";"Marine";"Barracks";201;1
"Unit";"Marine";"Barracks";201;1
"Unit";"Marine";"Barracks";203;1
"Unit";"Marine";"Barracks";205;1
"Unit";"Marine";"Barracks";205;1
"Unit";"Marine";"Barracks";205;1
"Unit";"Marine";"Barracks";205;1
"Unit";"Marine";"Barracks";205;1
"Unit";"Marine";"Barracks";205;1
"Unit";"Marine";"Barracks";205;1
"Unit";"Marauder";"Barracks";205;2
"Building";"CommandCenter";NA;190;0
"Unit";"Marine";"Barracks";208;1
"Unit";"Marine";"Barracks";208;1
"Unit";"Marine";"Barracks";210;1
"Unit";"Marine";"Barracks";210;1
"Unit";"Marine";"Barracks";210;1
