"Type";"UnitName";"OnBuilding";"TotalSupply";"Supply"
"Unit";"SCV";"Command Center";12;1
"Unit";"SCV";"Command Center";13;1
"Building";"SupplyDepot";NA;13;0
"Unit";"SCV";"Command Center";13;1
"Unit";"SCV";"Command Center";14;1
"Unit";"SCV";"Command Center";15;1
"Building";"Refinery";NA;16;0
"Unit";"SCV";"Command Center";16;1
"Building";"Barracks";NA;15;0
"Unit";"SCV";"Command Center";17;1
"Unit";"SCV";"Command Center";19;1
"Unit";"Reaper";"Barracks";19;1
"Building";"SupplyDepot";NA;19;0
"Unit";"SCV";"Command Center";19;1
"Unit";"Marine";"Barracks";21;1
"Unit";"SCV";"Command Center";21;1
"Unit";"SCV";"Command Center";23;1
"Unit";"SCV";"Command Center";24;1
"Building";"CommandCenter";NA;19;0
"Building";"Factory";NA;21;0
"Unit";"SCV";"Command Center";25;1
"Building";"BarracksReactor";NA;24;0
"Unit";"SCV";"Command Center";27;1
"Unit";"SCV";"Command Center";27;1
"Unit";"Hellion";"Factory";27;2
"Unit";"Hellion";"Factory";27;2
"Building";"Starport";NA;27;0
"Building";"BarracksTechLab";NA;27;0
"Building";"Refinery";NA;27;0
"Unit";"SCV";"Command Center";33;1
"Unit";"SCV";"Command Center";33;1
"Unit";"Hellion";"Factory";29;2
"Unit";"Hellion";"Factory";31;2
"Building";"Bunker";NA;28;0
"Unit";"SCV";"Command Center";34;1
"Building";"CommandCenter";NA;26;0
"Unit";"SCV";"Command Center";35;1
"Unit";"SCV";"Command Center";39;1
"Unit";"SCV";"Command Center";40;1
"Unit";"Hellion";"Factory";40;2
"Unit";"SCV";"Command Center";41;1
"Unit";"Hellion";"Factory";40;2
"Unit";"SCV";"Command Center";42;1
"Unit";"Banshee";"Starport";35;3
"Unit";"SCV";"Command Center";45;1
"Unit";"Hellion";"Factory";43;2
"Unit";"Hellion";"Factory";46;2
"Unit";"SCV";"Command Center";52;1
"Unit";"SCV";"Command Center";52;1
"Unit";"SCV";"Command Center";53;1
"Building";"Refinery";NA;58;0
"Building";"Refinery";NA;58;0
"Building";"SupplyDepot";NA;60;0
"Building";"SupplyDepot";NA;60;0
"Building";"BarracksTechLab";NA;60;0
"Building";"SupplyDepot";NA;60;0
"Unit";"SCV";"Command Center";60;1
"Unit";"SCV";"Command Center";60;1
"Building";"Armory";NA;58;0
"Building";"Armory";NA;58;0
"Unit";"Hellion";"Factory";60;2
"Unit";"Hellion";"Factory";60;2
"Building";"StarportTechLab";NA;60;0
"Building";"SupplyDepot";NA;60;0
"Building";"Factory";NA;60;0
"Unit";"Hellion";"Factory";66;2
"Unit";"Hellion";"Factory";66;2
"Unit";"SCV";"Command Center";66;1
"Unit";"SCV";"Command Center";66;1
"Building";"Factory";NA;60;0
"Unit";"SCV";"Command Center";66;1
"Unit";"SCV";"Command Center";70;1
"Unit";"SCV";"Command Center";72;1
"Unit";"SCV";"Command Center";72;1
"Unit";"Banshee";"Starport";66;3
"Unit";"Hellion";"Factory";72;2
"Unit";"Hellion";"Factory";72;2
"Unit";"SCV";"Command Center";83;1
"Unit";"SCV";"Command Center";83;1
"Unit";"SCV";"Command Center";83;1
"Unit";"SCV";"Command Center";83;1
"Unit";"SCV";"Command Center";84;1
"Unit";"SCV";"Command Center";85;1
"Building";"Refinery";NA;83;0
"Building";"Refinery";NA;83;0
"Unit";"Hellion";"Factory";83;2
"Unit";"Hellion";"Factory";83;2
"Unit";"SCV";"Command Center";86;1
"Unit";"SCV";"Command Center";87;1
"Unit";"SCV";"Command Center";88;1
"Unit";"SCV";"Command Center";93;1
"Unit";"SCV";"Command Center";94;1
"Unit";"SCV";"Command Center";95;1
"Unit";"SCV";"Command Center";96;1
"Unit";"SCV";"Command Center";97;1
"Unit";"SCV";"Command Center";98;1
"Unit";"Hellion";"Factory";99;2
"Unit";"SCV";"Command Center";99;1
"Unit";"SCV";"Command Center";100;1
"Unit";"SCV";"Command Center";101;1
"Building";"StarportReactor";NA;96;0
"Building";"EngineeringBay";NA;99;0
"Building";"Factory";NA;96;0
"Building";"Factory";NA;96;0
"Unit";"SCV";"Command Center";104;1
"Unit";"SCV";"Command Center";105;1
"Building";"SupplyDepot";NA;107;0
"Building";"SupplyDepot";NA;107;0
"Unit";"SCV";"Command Center";109;1
"Unit";"SCV";"Command Center";109;1
"Unit";"SCV";"Command Center";109;1
"Building";"FactoryReactor";NA;107;0
"Unit";"Hellion";"Factory";109;2
"Unit";"Hellion";"Factory";109;2
"Unit";"SCV";"Command Center";109;1
"Unit";"SCV";"Command Center";109;1
"Unit";"SCV";"Command Center";109;1
"Unit";"Hellion";"Factory";109;2
"Building";"SupplyDepot";NA;109;0
"Building";"MissileTurret";NA;109;0
"Building";"SupplyDepot";NA;109;0
"Building";"MissileTurret";NA;109;0
"Building";"MissileTurret";NA;112;0
"Building";"MissileTurret";NA;112;0
"Unit";"SCV";"Command Center";116;1
"Unit";"SCV";"Command Center";116;1
"Building";"MissileTurret";NA;112;0
"Upgrade";"TerranVehicleWeaponsLevel1";"Armory";99;0
"Upgrade";"TerranVehicleAndShipArmorsLevel1";"Armory";99;0
"Unit";"Hellion";"Factory";112;2
"Unit";"Hellion";"Factory";112;2
"Unit";"Hellion";"Factory";112;2
"Unit";"SCV";"Command Center";121;1
"Building";"CommandCenter";NA;107;0
"Building";"SupplyDepot";NA;123;0
"Unit";"SCV";"Command Center";130;1
"Unit";"Hellion";"Factory";130;2
"Unit";"Hellion";"Factory";130;2
"Unit";"SCV";"Command Center";133;1
"Unit";"SCV";"Command Center";133;1
"Unit";"Thor";"Factory";130;6
"Unit";"SCV";"Command Center";135;1
"Unit";"SCV";"Command Center";135;1
"Building";"SensorTower";NA;135;0
"Unit";"Hellion";"Factory";135;2
"Unit";"Hellion";"Factory";135;2
"Unit";"Hellion";"Factory";135;2
"Unit";"Hellion";"Factory";143;2
"Building";"Refinery";NA;149;0
"Building";"Refinery";NA;151;0
"Unit";"Hellion";"Factory";153;2
"Unit";"Hellion";"Factory";153;2
"Unit";"Hellion";"Factory";153;2
"Unit";"Hellion";"Factory";153;2
"Building";"SupplyDepot";NA;153;0
"Building";"SupplyDepot";NA;153;0
"Building";"SupplyDepot";NA;153;0
"Unit";"Hellion";"Factory";153;2
"Unit";"Hellion";"Factory";153;2
"Unit";"Hellion";"Factory";161;2
"Unit";"SCV";"Command Center";163;1
"Unit";"SCV";"Command Center";163;1
"Upgrade";"TerranVehicleWeaponsLevel2";"Armory";133;0
"Unit";"Hellion";"Factory";161;2
"Unit";"Hellion";"Factory";161;2
"Unit";"Hellion";"Factory";163;2
"Upgrade";"TerranVehicleAndShipArmorsLevel2";"Armory";135;0
"Unit";"SCV";"Command Center";175;1
"Unit";"SCV";"Command Center";175;1
"Unit";"Hellion";"Factory";169;2
"Unit";"Hellion";"Factory";169;2
"Unit";"Hellion";"Factory";169;2
"Unit";"SCV";"Command Center";175;1
"Unit";"SCV";"Command Center";175;1
"Building";"Factory";NA;163;0
"Building";"Factory";NA;163;0
"Building";"Factory";NA;163;0
"Building";"FactoryTechLab";NA;185;0
"Building";"FactoryTechLab";NA;185;0
"Unit";"Hellion";"Factory";185;2
"Unit";"Hellion";"Factory";185;2
"Unit";"Hellion";"Factory";185;2
"Unit";"Hellion";"Factory";185;2
"Building";"SupplyDepot";NA;185;0
"Building";"FactoryReactor";NA;185;0
"Unit";"Hellion";"Factory";185;2
"Unit";"Hellion";"Factory";187;2
"Unit";"Hellion";"Factory";193;2
"Unit";"Hellion";"Factory";193;2
"Building";"CommandCenter";NA;185;0
"Unit";"SCV";"Command Center";197;1
"Unit";"SCV";"Command Center";197;1
"Unit";"SCV";"Command Center";197;1
"Unit";"Hellion";"Factory";201;2
"Unit";"Hellion";"Factory";201;2
"Unit";"Hellion";"Factory";201;2
"Unit";"SCV";"Command Center";204;1
"Unit";"SCV";"Command Center";204;1
"Unit";"SCV";"Command Center";210;1
"Building";"Refinery";NA;210;0
"Unit";"SCV";"Command Center";212;1
"Unit";"SCV";"Command Center";212;1
"Upgrade";"TerranVehicleWeaponsLevel3";"Armory";185;0
"Unit";"Hellion";"Factory";212;2
"Upgrade";"TerranVehicleAndShipArmorsLevel3";"Armory";185;0
"Unit";"Hellion";"Factory";212;2
"Unit";"SCV";"Command Center";215;1
"Unit";"SCV";"Command Center";215;1
"Unit";"SCV";"Command Center";215;1
"Building";"Refinery";NA;213;0
