"Type";"UnitName";"OnBuilding";"TotalSupply";"Supply"
"Unit";"SCV";"Command Center";12;1
"Unit";"SCV";"Command Center";12;1
"Unit";"SCV";"Command Center";13;1
"Building";"SupplyDepot";NA;13;0
"Unit";"SCV";"Command Center";15;1
"Unit";"SCV";"Command Center";15;1
"Building";"Refinery";NA;15;0
"Unit";"SCV";"Command Center";16;1
"Unit";"SCV";"Command Center";17;1
"Building";"Barracks";NA;15;0
"Unit";"SCV";"Command Center";18;1
"Unit";"Reaper";"Barracks";19;1
"Building";"SupplyDepot";NA;20;0
"Unit";"Marine";"Barracks";20;1
"Unit";"SCV";"Command Center";22;1
"Building";"Refinery";NA;21;0
"Unit";"SCV";"Command Center";22;1
"Building";"CommandCenter";NA;20;0
"Unit";"SCV";"Command Center";23;1
"Building";"BarracksReactor";NA;22;0
"Unit";"SCV";"Command Center";24;1
"Building";"Factory";NA;22;0
"Building";"SupplyDepot";NA;25;0
"Unit";"SCV";"Command Center";25;1
"Building";"BarracksTechLab";NA;26;0
"Unit";"SCV";"Command Center";27;1
"Unit";"SCV";"Command Center";27;1
"Unit";"Hellion";"Factory";26;2
"Unit";"Hellion";"Factory";26;2
"Building";"Starport";NA;26;0
"Unit";"SCV";"Command Center";29;1
"Unit";"SCV";"Command Center";29;1
"Building";"SupplyDepot";NA;29;0
"Unit";"Hellion";"Factory";33;2
"Unit";"Hellion";"Factory";33;2
"Unit";"SCV";"Command Center";35;1
"Unit";"SCV";"Command Center";35;1
"Building";"BarracksTechLab";NA;33;0
"Unit";"SCV";"Command Center";39;1
"Unit";"SCV";"Command Center";41;1
"Building";"SupplyDepot";NA;41;0
"Unit";"SCV";"Command Center";43;1
"Unit";"SCV";"Command Center";43;1
"Unit";"Marine";"Barracks";43;1
"Unit";"Marine";"Barracks";43;1
"Unit";"SCV";"Command Center";43;1
"Unit";"Banshee";"Starport";41;3
"Unit";"SCV";"Command Center";44;1
"Unit";"SCV";"Command Center";48;1
"Unit";"Marine";"Barracks";48;1
"Unit";"Marine";"Barracks";48;1
"Unit";"SCV";"Command Center";51;1
"Building";"CommandCenter";NA;39;0
"Building";"Refinery";NA;52;0
"Building";"EngineeringBay";NA;51;0
"Building";"EngineeringBay";NA;52;0
"Unit";"SCV";"Command Center";56;1
"Unit";"SCV";"Command Center";56;1
"Building";"Refinery";NA;53;0
"Building";"SupplyDepot";NA;55;0
"Unit";"Marine";"Barracks";56;1
"Unit";"Marine";"Barracks";56;1
"Unit";"SCV";"Command Center";56;1
"Unit";"Banshee";"Starport";51;3
"Unit";"SCV";"Command Center";58;1
"Unit";"Marine";"Barracks";64;1
"Unit";"Marine";"Barracks";64;1
"Unit";"SCV";"Command Center";65;1
"Unit";"SCV";"Command Center";65;1
"Unit";"SCV";"Command Center";69;1
"Unit";"SCV";"Command Center";69;1
"Unit";"Marine";"Barracks";68;1
"Unit";"Marine";"Barracks";68;1
"Building";"StarportReactor";NA;65;0
"Building";"Barracks";NA;64;0
"Unit";"SCV";"Command Center";69;1
"Building";"Barracks";NA;65;0
"Unit";"SCV";"Command Center";71;1
"Unit";"SCV";"Command Center";73;1
"Unit";"SCV";"Command Center";74;1
"Unit";"Marine";"Barracks";73;1
"Unit";"Marine";"Barracks";73;1
"Unit";"SCV";"Command Center";75;1
"Building";"Barracks";NA;69;0
"Unit";"SCV";"Command Center";76;1
"Building";"Barracks";NA;69;0
"Unit";"Marine";"Barracks";76;1
"Unit";"Marine";"Barracks";76;1
"Unit";"SCV";"Command Center";79;1
"Unit";"Marine";"Barracks";79;1
"Unit";"Marine";"Barracks";79;1
"Unit";"Marine";"Barracks";79;1
"Unit";"SCV";"Command Center";80;1
"Building";"StarportReactor";NA;75;0
"Unit";"SCV";"Command Center";83;1
"Building";"Refinery";NA;79;0
"Building";"Refinery";NA;79;0
"Unit";"SCV";"Command Center";83;1
"Building";"BarracksTechLab";NA;81;0
"Upgrade";"TerranInfantryWeaponsLevel1";"EngineeringBay";67;0
"Upgrade";"TerranInfantryArmorsLevel1";"EngineeringBay";67;0
"Unit";"SCV";"Command Center";88;1
"Building";"SupplyDepot";NA;83;0
"Building";"SupplyDepot";NA;83;0
"Unit";"SCV";"Command Center";88;1
"Unit";"Marine";"Barracks";89;1
"Unit";"Marine";"Barracks";89;1
"Unit";"Marine";"Barracks";89;1
"Building";"BarracksReactor";NA;81;0
"Unit";"SCV";"Command Center";91;1
"Unit";"SCV";"Command Center";91;1
"Unit";"SCV";"Command Center";92;1
"Unit";"Marine";"Barracks";92;1
"Building";"Armory";NA;83;0
"Building";"SupplyDepot";NA;92;0
"Building";"SupplyDepot";NA;92;0
"Unit";"Marauder";"Barracks";92;2
"Unit";"Marauder";"Barracks";92;2
"Unit";"Marine";"Barracks";95;1
"Unit";"Marine";"Barracks";95;1
"Unit";"Medivac";"Starport";91;2
"Unit";"Medivac";"Starport";91;2
"Unit";"SCV";"Command Center";98;1
"Unit";"SCV";"Command Center";98;1
"Unit";"SCV";"Command Center";98;1
"Unit";"Marine";"Barracks";98;1
"Unit";"Marine";"Barracks";98;1
"Unit";"Marine";"Barracks";98;1
"Unit";"Marine";"Barracks";103;1
"Unit";"Marine";"Barracks";103;1
"Unit";"Marine";"Barracks";105;1
"Unit";"Marine";"Barracks";105;1
"Unit";"Marauder";"Barracks";103;2
"Unit";"SCV";"Command Center";115;1
"Unit";"SCV";"Command Center";115;1
"Unit";"SCV";"Command Center";115;1
"Unit";"Marine";"Barracks";112;1
"Building";"SupplyDepot";NA;115;0
"Building";"SupplyDepot";NA;115;0
"Upgrade";"Stimpack";"TechLab";83;0
"Unit";"Marine";"Barracks";118;1
"Unit";"Marine";"Barracks";119;1
"Unit";"Marine";"Barracks";119;1
"Unit";"Marauder";"Barracks";117;2
"Unit";"SCV";"Command Center";125;1
"Unit";"SCV";"Command Center";125;1
"Unit";"SCV";"Command Center";125;1
"Building";"SupplyDepot";NA;125;0
"Building";"SupplyDepot";NA;125;0
"Building";"SupplyDepot";NA;125;0
"Unit";"SCV";"Command Center";130;1
"Unit";"Marine";"Barracks";130;1
"Unit";"Marauder";"Barracks";130;2
"Unit";"Marauder";"Barracks";130;2
"Unit";"Medivac";"Starport";125;2
"Building";"CommandCenter";NA;99;0
"Building";"SupplyDepot";NA;133;0
"Building";"SupplyDepot";NA;133;0
"Unit";"Medivac";"Starport";130;2
"Unit";"Marine";"Barracks";135;1
"Unit";"Marine";"Barracks";135;1
"Unit";"Marine";"Barracks";135;1
"Unit";"Marine";"Barracks";135;1
"Unit";"Marauder";"Barracks";135;2
"Unit";"Marauder";"Barracks";137;2
"Unit";"Marine";"Barracks";141;1
"Unit";"Marine";"Barracks";141;1
"Unit";"SCV";"Command Center";147;1
"Unit";"Marine";"Barracks";143;1
"Unit";"Marine";"Barracks";144;1
"Unit";"Marine";"Barracks";147;1
"Unit";"Marine";"Barracks";147;1
"Unit";"Marine";"Barracks";151;1
"Unit";"Marine";"Barracks";152;1
"Unit";"Marauder";"Barracks";147;2
"Unit";"Marauder";"Barracks";149;2
"Unit";"Marine";"Barracks";154;1
"Unit";"Marine";"Barracks";155;1
"Unit";"Marine";"Barracks";156;1
"Unit";"Marine";"Barracks";157;1
"Unit";"Medivac";"Starport";153;2
"Unit";"Marine";"Barracks";164;1
"Unit";"Marine";"Barracks";164;1
"Unit";"Marauder";"Barracks";160;2
"Unit";"Marauder";"Barracks";162;2
"Unit";"Marine";"Barracks";164;1
"Unit";"Marine";"Barracks";165;1
"Unit";"Marine";"Barracks";166;1
"Unit";"Marine";"Barracks";167;1
"Unit";"Medivac";"Starport";164;2
"Unit";"SCV";"Command Center";172;1
"Unit";"SCV";"Command Center";174;1
"Unit";"SCV";"Command Center";174;1
"Unit";"SCV";"Command Center";176;1
"Upgrade";"TerranInfantryArmorsLevel2";"EngineeringBay";130;0
"Unit";"Marine";"Barracks";170;1
"Unit";"Marine";"Barracks";171;1
"Unit";"Marine";"Barracks";172;1
"Unit";"SCV";"Command Center";182;1
"Building";"MissileTurret";NA;180;0
"Unit";"Medivac";"Starport";172;2
"Upgrade";"TerranInfantryWeaponsLevel2";"EngineeringBay";135;0
"Building";"MissileTurret";NA;186;0
"Building";"MissileTurret";NA;186;0
"Building";"MissileTurret";NA;187;0
"Unit";"Marine";"Barracks";189;1
"Unit";"Marine";"Barracks";189;1
"Unit";"Marine";"Barracks";189;1
"Unit";"Marine";"Barracks";189;1
"Unit";"Marine";"Barracks";189;1
"Unit";"Marine";"Barracks";189;1
"Unit";"Marine";"Barracks";189;1
"Unit";"Marine";"Barracks";189;1
"Unit";"Thor";"Factory";172;6
"Unit";"Medivac";"Starport";192;2
"Unit";"Medivac";"Starport";192;2
"Building";"Factory";NA;190;0
"Building";"Factory";NA;200;0
"Building";"Barracks";NA;192;0
"Building";"Barracks";NA;200;0
"Unit";"Marine";"Barracks";210;1
"Unit";"Marine";"Barracks";210;1
"Unit";"Marine";"Barracks";210;1
"Unit";"Marine";"Barracks";210;1
"Unit";"Marine";"Barracks";210;1
"Unit";"Thor";"Factory";206;6
"Building";"FactoryTechLab";NA;210;0
"Unit";"Medivac";"Starport";210;2
"Unit";"Medivac";"Starport";210;2
"Building";"FactoryTechLab";NA;210;0
"Building";"BarracksTechLab";NA;210;0
"Building";"BarracksTechLab";NA;210;0
"Building";"BarracksReactor";NA;210;0
"Unit";"Marine";"Barracks";225;1
"Unit";"Marine";"Barracks";225;1
"Unit";"Marine";"Barracks";225;1
"Unit";"Marine";"Barracks";225;1
"Unit";"Marine";"Barracks";225;1
"Unit";"Marine";"Barracks";225;1
"Unit";"Marine";"Barracks";225;1
"Unit";"Marauder";"Barracks";225;2
"Unit";"Thor";"Factory";225;6
"Unit";"Thor";"Factory";225;6
"Unit";"Thor";"Factory";225;6
"Upgrade";"TerranInfantryArmorsLevel3";"EngineeringBay";208;0
"Unit";"Marine";"Barracks";252;1
"Unit";"Marine";"Barracks";252;1
"Unit";"Marine";"Barracks";252;1
"Unit";"Marine";"Barracks";252;1
"Unit";"Marine";"Barracks";252;1
"Unit";"Marine";"Barracks";252;1
"Unit";"Marine";"Barracks";252;1
"Unit";"Marine";"Barracks";252;1
"Unit";"Marine";"Barracks";252;1
"Unit";"Marine";"Barracks";252;1
"Unit";"Thor";"Factory";234;6
"Upgrade";"TerranVehicleAndShipArmorsLevel1";"Armory";225;0
"Unit";"Liberator";"Starport";240;3
"Unit";"Liberator";"Starport";240;3
"Unit";"Marine";"Barracks";252;1
"Unit";"Marine";"Barracks";253;1
"Unit";"Marine";"Barracks";254;1
"Unit";"Marine";"Barracks";254;1
"Unit";"Marine";"Barracks";256;1
"Unit";"Marine";"Barracks";256;1
"Building";"CommandCenter";NA;232;0
"Unit";"Thor";"Factory";252;6
"Unit";"Marine";"Barracks";280;1
"Unit";"Marine";"Barracks";286;1
"Unit";"Marine";"Barracks";286;1
"Unit";"Marine";"Barracks";286;1
"Unit";"Marine";"Barracks";286;1
"Unit";"Marine";"Barracks";286;1
"Unit";"Marauder";"Barracks";286;2
"Upgrade";"TerranInfantryWeaponsLevel3";"EngineeringBay";225;0
"Unit";"Marine";"Barracks";294;1
"Unit";"Marine";"Barracks";294;1
"Unit";"Marine";"Barracks";294;1
"Unit";"Marine";"Barracks";294;1
"Unit";"Marine";"Barracks";294;1
"Unit";"Marine";"Barracks";294;1
"Unit";"Marine";"Barracks";294;1
"Unit";"Marine";"Barracks";294;1
"Unit";"Marine";"Barracks";294;1
"Unit";"Marauder";"Barracks";294;2
"Unit";"Marine";"Barracks";294;1
"Unit";"Marine";"Barracks";295;1
"Unit";"Marine";"Barracks";303;1
"Unit";"Marine";"Barracks";303;1
"Unit";"Marine";"Barracks";305;1
"Unit";"Marine";"Barracks";305;1
"Unit";"Marine";"Barracks";307;1
"Unit";"Marine";"Barracks";307;1
"Unit";"Marine";"Barracks";313;1
"Unit";"Marine";"Barracks";313;1
"Unit";"Marine";"Barracks";313;1
"Unit";"Marine";"Barracks";316;1
"Unit";"Marauder";"Barracks";316;2
"Unit";"SCV";"Command Center";319;1
"Unit";"SCV";"Command Center";320;1
"Unit";"SCV";"Command Center";320;1
"Unit";"Marine";"Barracks";320;1
"Unit";"Marine";"Barracks";320;1
"Unit";"Marine";"Barracks";320;1
"Unit";"Marine";"Barracks";320;1
"Unit";"Marine";"Barracks";320;1
"Unit";"Marine";"Barracks";320;1
