"type";"unit_name";"on_building";"total_supply_lag";"supply"
"Building";"Barracks";NA;16;0
"Building";"Refinery";NA;16;0
"Unit";"Reaper";"Barracks";19;1
"Building";"CommandCenter";NA;20;0
"Unit";"Marine";"Barracks";21;1
"Building";"Factory";NA;22;0
"Building";"Refinery";NA;23;0
"Building";"BarracksReactor";NA;24;0
"Building";"Starport";NA;26;0
"Unit";"Hellion";"Factory";27;2
"Unit";"Hellion";"Factory";29;2
"Building";"BarracksTechLab";NA;31;0
"Unit";"Hellion";"Factory";33;2
"Unit";"Hellion";"Factory";35;2
"Building";"BarracksTechLab";NA;39;0
"Unit";"Hellion";"Factory";40;2
"Unit";"Hellion";"Factory";42;2
"Unit";"Banshee";"Starport";45;3
"Building";"CommandCenter";NA;53;0
"Unit";"Hellion";"Factory";55;2
"Unit";"Hellion";"Factory";57;2
"Unit";"Banshee";"Starport";60;3
"Building";"Refinery";NA;63;0
"Building";"Refinery";NA;63;0
"Unit";"Hellion";"Factory";68;2
"Unit";"Hellion";"Factory";70;2
"Building";"Factory";NA;73;0
"Building";"Factory";NA;73;0
"Unit";"Raven";"Starport";73;2
"Building";"Armory";NA;77;0
"Building";"Armory";NA;77;0
"Building";"BarracksTechLab";NA;81;0
"Unit";"Hellion";"Factory";81;2
"Unit";"Hellion";"Factory";83;2
"Building";"CommandCenter";NA;87;0
"Unit";"Hellion";"Factory";87;2
"Unit";"Hellion";"Factory";89;2
"Unit";"Banshee";"Starport";91;3
"Building";"Refinery";NA;99;0
"Building";"Refinery";NA;99;0
"Upgrade";"TerranVehicleWeaponsLevel1";"Armory";100;0
"Building";"Starport";NA;101;0
"Building";"Starport";NA;103;0
"Building";"EngineeringBay";NA;104;0
"Unit";"Hellion";"Factory";104;2
"Unit";"Hellion";"Factory";106;2
"Building";"BarracksReactor";NA;109;0
"Unit";"Banshee";"Starport";111;3
"Building";"StarportTechLab";NA;115;0
"Building";"Refinery";NA;117;0
"Unit";"Banshee";"Starport";117;3
"Unit";"Banshee";"Starport";126;3
"Building";"Refinery";NA;129;0
"Building";"SensorTower";NA;132;0
"Building";"Starport";NA;132;0
"Building";"Starport";NA;132;0
"Upgrade";"TerranShipWeaponsLevel1";"Armory";132;0
"Unit";"Banshee";"Starport";132;3
"Unit";"Banshee";"Starport";135;3
"Building";"CommandCenter";NA;138;0
"Building";"StarportTechLab";NA;138;0
"Building";"StarportReactor";NA;138;0
"Building";"Starport";NA;138;0
"Building";"CommandCenter";NA;138;0
"Building";"CommandCenter";NA;138;0
"Unit";"Banshee";"Starport";138;3
"Unit";"Banshee";"Starport";141;3
"Building";"CommandCenter";NA;144;0
"Building";"CommandCenter";NA;144;0
"Unit";"Hellion";"Factory";144;2
"Unit";"Hellion";"Factory";146;2
"Unit";"Banshee";"Starport";148;3
"Building";"StarportReactor";NA;155;0
"Building";"FusionCore";NA;155;0
"Unit";"Raven";"Starport";155;2
"Unit";"Raven";"Starport";157;2
"Unit";"Banshee";"Starport";159;3
"Building";"CommandCenter";NA;162;0
"Building";"CommandCenter";NA;162;0
"Building";"Refinery";NA;162;0
"Building";"Refinery";NA;162;0
"Building";"SensorTower";NA;162;0
"Unit";"Banshee";"Starport";162;3
"Unit";"Banshee";"Starport";165;3
"Building";"CommandCenter";NA;168;0
"Upgrade";"TerranShipWeaponsLevel2";"Armory";168;0
"Building";"MissileTurret";NA;168;0
"Building";"MissileTurret";NA;168;0
"Building";"MissileTurret";NA;168;0
"Building";"MissileTurret";NA;168;0
"Unit";"Banshee";"Starport";168;3
"Building";"SensorTower";NA;172;0
"Unit";"Banshee";"Starport";172;3
"Unit";"Raven";"Starport";178;2
"Upgrade";"TerranVehicleWeaponsLevel2";"Armory";182;0
"Unit";"Raven";"Starport";190;2
"Building";"Refinery";NA;192;0
"Building";"CommandCenter";NA;192;0
"Unit";"Raven";"Starport";193;2
"Building";"BarracksTechLab";NA;195;0
"Building";"Starport";NA;195;0
"Building";"EngineeringBay";NA;195;0
"Unit";"Raven";"Starport";195;2
"Building";"Refinery";NA;197;0
"Building";"Refinery";NA;197;0
"Building";"Barracks";NA;197;0
"Building";"Barracks";NA;197;0
"Building";"Barracks";NA;197;0
"Building";"Barracks";NA;197;0
"Unit";"Hellion";"Factory";197;2
"Unit";"Hellion";"Factory";199;2
"Unit";"Hellion";"Factory";201;2
"Unit";"Hellion";"Factory";203;2
"Unit";"Raven";"Starport";205;2
"Building";"MissileTurret";NA;207;0
"Building";"MissileTurret";NA;207;0
"Building";"GhostAcademy";NA;207;0
"Building";"EngineeringBay";NA;207;0
"Unit";"Raven";"Starport";207;2
"Unit";"Thor";"Factory";209;6
"Unit";"Raven";"Starport";215;2
"Unit";"Raven";"Starport";217;2
"Unit";"Hellion";"Factory";219;2
"Unit";"Hellion";"Factory";221;2
"Unit";"Hellion";"Factory";223;2
"Upgrade";"TerranShipWeaponsLevel3";"Armory";225;0
"Unit";"Raven";"Starport";225;2
"Unit";"Hellion";"Factory";227;2
"Unit";"Hellion";"Factory";229;2
"Unit";"Raven";"Starport";231;2
"Unit";"Banshee";"Starport";233;3
"Unit";"Banshee";"Starport";236;3
"Unit";"Hellion";"Factory";240;2
"Unit";"Hellion";"Factory";242;2
"Unit";"Hellion";"Factory";244;2
"Unit";"Banshee";"Starport";249;3
"Unit";"Hellion";"Factory";252;2
"Unit";"Hellion";"Factory";254;2
"Unit";"Hellion";"Factory";256;2
"Unit";"Hellion";"Factory";258;2
"Building";"CommandCenter";NA;260;0
"Building";"MissileTurret";NA;260;0
"Unit";"Banshee";"Starport";262;3
"Building";"MissileTurret";NA;270;0
"Unit";"Hellion";"Factory";270;2
"Building";"MissileTurret";NA;272;0
"Unit";"Hellion";"Factory";272;2
"Building";"MissileTurret";NA;274;0
"Unit";"Hellion";"Factory";274;2
"Unit";"Raven";"Starport";276;2
"Building";"StarportTechLab";NA;278;0
"Unit";"Hellion";"Factory";278;2
"Unit";"Raven";"Starport";280;2
"Building";"Refinery";NA;282;0
"Building";"Refinery";NA;282;0
"Building";"Refinery";NA;282;0
"Building";"Refinery";NA;282;0
"Unit";"Raven";"Starport";282;2
"Unit";"Hellion";"Factory";284;2
"Unit";"Hellion";"Factory";286;2
"Unit";"Hellion";"Factory";288;2
"Unit";"Hellion";"Factory";290;2
"Unit";"Banshee";"Starport";292;3
"Unit";"Raven";"Starport";295;2
"Unit";"Banshee";"Starport";297;3
"Building";"MissileTurret";NA;300;0
"Building";"MissileTurret";NA;300;0
"Unit";"Ghost";"Barracks";300;2
"Building";"MissileTurret";NA;302;0
"Building";"Barracks";NA;302;0
"Building";"Barracks";NA;302;0
"Unit";"Hellion";"Factory";302;2
"Unit";"Hellion";"Factory";304;2
"Unit";"Hellion";"Factory";306;2
"Building";"Barracks";NA;308;0
"Building";"Barracks";NA;308;0
"Unit";"Raven";"Starport";308;2
"Unit";"Hellion";"Factory";310;2
"Unit";"Hellion";"Factory";312;2
"Building";"MissileTurret";NA;314;0
"Building";"MissileTurret";NA;314;0
"Building";"MissileTurret";NA;314;0
"Building";"MissileTurret";NA;314;0
"Unit";"Raven";"Starport";314;2
"Unit";"Raven";"Starport";316;2
"Unit";"Raven";"Starport";318;2
"Building";"MissileTurret";NA;320;0
"Building";"MissileTurret";NA;320;0
"Building";"MissileTurret";NA;320;0
"Unit";"Hellion";"Factory";320;2
"Unit";"Hellion";"Factory";322;2
"Building";"CommandCenter";NA;324;0
"Unit";"Hellion";"Factory";324;2
"Unit";"Hellion";"Factory";326;2
"Unit";"Hellion";"Factory";328;2
"Unit";"Hellion";"Factory";330;2
"Building";"BarracksTechLab";NA;332;0
"Building";"BarracksTechLab";NA;332;0
"Building";"BarracksTechLab";NA;332;0
"Building";"BarracksTechLab";NA;332;0
"Unit";"Raven";"Starport";333;2
"Unit";"Raven";"Starport";335;2
"Unit";"Raven";"Starport";337;2
"Unit";"Hellion";"Factory";339;2
"Unit";"Hellion";"Factory";341;2
"Unit";"Hellion";"Factory";343;2
"Building";"Refinery";NA;345;0
"Unit";"Liberator";"Starport";345;3
"Building";"Refinery";NA;348;0
"Unit";"Liberator";"Starport";348;3
"Unit";"Liberator";"Starport";351;3
"Unit";"Ghost";"Barracks";354;2
"Unit";"Ghost";"Barracks";356;2
"Unit";"Hellion";"Factory";358;2
"Unit";"Hellion";"Factory";360;2
"Unit";"Hellion";"Factory";362;2
"Unit";"Hellion";"Factory";364;2
"Unit";"Banshee";"Starport";366;3
"Unit";"Banshee";"Starport";369;3
"Unit";"Banshee";"Starport";372;3
"Unit";"Ghost";"Barracks";375;2
"Upgrade";"TerranInfantryWeaponsLevel1";"EngineeringBay";377;0
"Unit";"Hellion";"Factory";377;2
"Unit";"Hellion";"Factory";379;2
"Unit";"Liberator";"Starport";381;3
"Unit";"Liberator";"Starport";384;3
"Unit";"Liberator";"Starport";387;3
"Unit";"Ghost";"Barracks";390;2
"Unit";"Ghost";"Barracks";392;2
"Unit";"Liberator";"Starport";394;3
"Unit";"Liberator";"Starport";397;3
"Unit";"Ghost";"Barracks";405;2
"Unit";"Raven";"Starport";407;2
"Unit";"Banshee";"Starport";409;3
"Building";"SensorTower";NA;412;0
"Unit";"Hellion";"Factory";412;2
"Unit";"Hellion";"Factory";414;2
"Unit";"Raven";"Starport";419;2
"Unit";"Raven";"Starport";421;2
"Unit";"Hellion";"Factory";423;2
"Unit";"Hellion";"Factory";425;2
"Unit";"Hellion";"Factory";427;2
"Unit";"Hellion";"Factory";429;2
"Upgrade";"SprayTerran";NA;431;0
"Upgrade";"SprayTerran";NA;431;0
"Upgrade";"SprayTerran";NA;431;0
"Upgrade";"BansheeCloak";NA;431;0
"Upgrade";"SprayTerran";NA;431;0
"Upgrade";"SprayTerran";NA;431;0
"Upgrade";"SprayTerran";NA;431;0
"Upgrade";"TerranVehicleAndShipArmorsLevel1";NA;431;0
"Upgrade";"BansheeSpeed";NA;431;0
"Upgrade";"SprayTerran";NA;431;0
"Upgrade";"SprayTerran";NA;431;0
"Upgrade";"SprayTerran";NA;431;0
"Upgrade";"SprayTerran";NA;431;0
"Upgrade";"SprayTerran";NA;431;0
"Upgrade";"SprayTerran";NA;431;0
"Upgrade";"TerranVehicleAndShipArmorsLevel2";NA;431;0
"Upgrade";"SprayTerran";NA;431;0
"Upgrade";"SprayTerran";NA;431;0
"Upgrade";"SprayTerran";NA;431;0
"Upgrade";"SprayTerran";NA;431;0
"Upgrade";"SprayTerran";NA;431;0
"Upgrade";"SprayTerran";NA;431;0
"Upgrade";"SprayTerran";NA;431;0
"Upgrade";"HighCapacityBarrels";NA;431;0
"Upgrade";"SmartServos";NA;431;0
"Upgrade";"SprayTerran";NA;431;0
"Upgrade";"SprayTerran";NA;431;0
"Upgrade";"SprayTerran";NA;431;0
"Upgrade";"LiberatorAGRangeUpgrade";NA;431;0
"Upgrade";"SprayTerran";NA;431;0
"Upgrade";"SprayTerran";NA;431;0
"Upgrade";"SprayTerran";NA;431;0
"Upgrade";"RavenCorvidReactor";NA;431;0
"Upgrade";"SprayTerran";NA;431;0
"Upgrade";"SprayTerran";NA;431;0
"Upgrade";"SprayTerran";NA;431;0
"Upgrade";"TerranVehicleAndShipArmorsLevel3";NA;431;0
