"Type";"UnitName";"OnBuilding";"TotalSupply";"Supply"
"Unit";"SCV";"Command Center";12;1
"Unit";"SCV";"Command Center";12;1
"Unit";"SCV";"Command Center";13;1
"Building";"SupplyDepot";NA;13;0
"Unit";"SCV";"Command Center";15;1
"Unit";"SCV";"Command Center";15;1
"Unit";"SCV";"Command Center";16;1
"Building";"Barracks";NA;15;0
"Building";"Refinery";NA;17;0
"Unit";"SCV";"Command Center";17;1
"Unit";"Marine";"Barracks";18;1
"Unit";"Marine";"Barracks";20;1
"Unit";"SCV";"Command Center";20;1
"Building";"SupplyDepot";NA;20;0
"Unit";"Marine";"Barracks";20;1
"Unit";"SCV";"Command Center";22;1
"Unit";"SCV";"Command Center";23;1
"Building";"Refinery";NA;23;0
"Building";"Bunker";NA;22;0
"Building";"CommandCenter";NA;19;0
"Unit";"SCV";"Command Center";24;1
"Building";"Factory";NA;22;0
"Building";"BarracksReactor";NA;23;0
"Unit";"SCV";"Command Center";25;1
"Unit";"SCV";"Command Center";27;1
"Unit";"Marine";"Barracks";27;1
"Unit";"SCV";"Command Center";27;1
"Unit";"SCV";"Command Center";27;1
"Unit";"Hellion";"Factory";27;2
"Unit";"Hellion";"Factory";27;2
"Building";"Starport";NA;27;0
"Unit";"SCV";"Command Center";30;1
"Unit";"SCV";"Command Center";33;1
"Building";"SupplyDepot";NA;28;0
"Unit";"Marine";"Barracks";28;1
"Unit";"Hellion";"Factory";31;2
"Unit";"Hellion";"Factory";33;2
"Unit";"Marine";"Barracks";37;1
"Unit";"SCV";"Command Center";42;1
"Unit";"SCV";"Command Center";42;1
"Unit";"Medivac";"Starport";36;2
"Unit";"Hellion";"Factory";38;2
"Unit";"Hellion";"Factory";40;2
"Unit";"SCV";"Command Center";44;1
"Unit";"SCV";"Command Center";45;1
"Building";"SupplyDepot";NA;42;0
"Building";"BarracksTechLab";NA;43;0
"Building";"SupplyDepot";NA;45;0
"Unit";"SCV";"Command Center";53;1
"Building";"Armory";NA;38;0
"Unit";"SCV";"Command Center";53;1
"Unit";"Marine";"Barracks";53;1
"Unit";"SCV";"Command Center";55;1
"Unit";"SCV";"Command Center";55;1
"Building";"EngineeringBay";NA;53;0
"Building";"Bunker";NA;53;0
"Building";"EngineeringBay";NA;53;0
"Unit";"SCV";"Command Center";56;1
"Unit";"SCV";"Command Center";57;1
"Unit";"SCV";"Command Center";58;1
"Unit";"SCV";"Command Center";59;1
"Unit";"SCV";"Command Center";60;1
"Unit";"SCV";"Command Center";61;1
"Unit";"SCV";"Command Center";62;1
"Unit";"SCV";"Command Center";63;1
"Unit";"Medivac";"Starport";60;2
"Unit";"Marine";"Barracks";64;1
"Unit";"SCV";"Command Center";68;1
"Unit";"SCV";"Command Center";68;1
"Building";"Refinery";NA;68;0
"Building";"Refinery";NA;68;0
"Unit";"Marine";"Barracks";68;1
"Building";"CommandCenter";NA;58;0
"Unit";"SCV";"Command Center";71;1
"Unit";"SCV";"Command Center";71;1
"Unit";"SCV";"Command Center";72;1
"Unit";"Marine";"Barracks";71;1
"Building";"Barracks";NA;68;0
"Building";"Barracks";NA;68;0
"Upgrade";"Stimpack";"TechLab";60;0
"Building";"Barracks";NA;68;0
"Unit";"SCV";"Command Center";74;1
"Building";"SupplyDepot";NA;72;0
"Building";"Barracks";NA;68;0
"Building";"StarportReactor";NA;69;0
"Unit";"SCV";"Command Center";74;1
"Unit";"SCV";"Command Center";76;1
"Unit";"Marine";"Barracks";75;1
"Upgrade";"TerranInfantryWeaponsLevel1";"EngineeringBay";64;0
"Upgrade";"TerranInfantryArmorsLevel1";"EngineeringBay";64;0
"Unit";"SCV";"Command Center";77;1
"Building";"BarracksTechLab";NA;77;0
"Building";"SupplyDepot";NA;77;0
"Unit";"SCV";"Command Center";78;1
"Unit";"SCV";"Command Center";78;1
"Unit";"SCV";"Command Center";80;1
"Unit";"Marine";"Barracks";79;1
"Building";"BarracksReactor";NA;76;0
"Building";"BarracksReactor";NA;76;0
"Building";"BarracksReactor";NA;76;0
"Building";"FactoryTechLab";NA;83;0
"Unit";"Medivac";"Starport";81;2
"Unit";"Medivac";"Starport";81;2
"Unit";"SCV";"Command Center";85;1
"Unit";"SCV";"Command Center";85;1
"Unit";"SCV";"Command Center";85;1
"Unit";"Marine";"Barracks";85;1
"Unit";"Marine";"Barracks";85;1
"Unit";"Marine";"Barracks";85;1
"Unit";"Marine";"Barracks";85;1
"Unit";"Marine";"Barracks";85;1
"Unit";"Marine";"Barracks";85;1
"Unit";"Marine";"Barracks";85;1
"Unit";"Marine";"Barracks";85;1
"Building";"SupplyDepot";NA;85;0
"Unit";"SCV";"Command Center";89;1
"Unit";"Marine";"Barracks";92;1
"Unit";"Marine";"Barracks";93;1
"Unit";"Marine";"Barracks";93;1
"Building";"Barracks";NA;85;0
"Unit";"Marine";"Barracks";100;1
"Building";"SupplyDepot";NA;100;0
"Unit";"Marine";"Barracks";100;1
"Unit";"Marine";"Barracks";100;1
"Unit";"Marine";"Barracks";100;1
"Unit";"Marine";"Barracks";101;1
"Unit";"Marine";"Barracks";102;1
"Unit";"Marine";"Barracks";102;1
"Unit";"Marine";"Barracks";104;1
"Building";"Refinery";NA;101;0
"Building";"Refinery";NA;101;0
"Unit";"Marine";"Barracks";104;1
"Unit";"Marine";"Barracks";105;1
"Building";"Bunker";NA;101;0
"Unit";"SCV";"Command Center";108;1
"Unit";"SCV";"Command Center";108;1
"Unit";"SCV";"Command Center";108;1
"Unit";"Marine";"Barracks";108;1
"Unit";"Marine";"Barracks";108;1
"Unit";"Marine";"Barracks";108;1
"Unit";"Marine";"Barracks";108;1
"Unit";"Marine";"Barracks";108;1
"Unit";"Marine";"Barracks";109;1
"Building";"SupplyDepot";NA;111;0
"Building";"SupplyDepot";NA;112;0
"Building";"SupplyDepot";NA;112;0
"Building";"SupplyDepot";NA;112;0
"Building";"Factory";NA;108;0
"Unit";"Marine";"Barracks";121;1
"Unit";"Marine";"Barracks";121;1
"Unit";"Marine";"Barracks";121;1
"Unit";"Marine";"Barracks";121;1
"Unit";"Marine";"Barracks";121;1
"Unit";"Marine";"Barracks";121;1
"Building";"SupplyDepot";NA;121;0
"Building";"SupplyDepot";NA;123;0
"Building";"SupplyDepot";NA;123;0
"Unit";"Marine";"Barracks";123;1
"Unit";"Marine";"Barracks";123;1
"Unit";"Marine";"Barracks";123;1
"Unit";"Marine";"Barracks";123;1
"Unit";"Marine";"Barracks";123;1
"Unit";"Marine";"Barracks";123;1
"Unit";"Marine";"Barracks";123;1
"Building";"FactoryTechLab";NA;129;0
"Unit";"Marine";"Barracks";129;1
"Unit";"Marine";"Barracks";129;1
"Unit";"Marine";"Barracks";129;1
"Unit";"Marine";"Barracks";129;1
"Unit";"Marine";"Barracks";130;1
"Unit";"Marine";"Barracks";130;1
"Unit";"Marine";"Barracks";132;1
"Building";"SupplyDepot";NA;129;0
"Unit";"Liberator";"Starport";123;3
"Unit";"Liberator";"Starport";123;3
"Unit";"Marine";"Barracks";136;1
"Unit";"Marine";"Barracks";136;1
"Unit";"Marine";"Barracks";136;1
"Unit";"Marine";"Barracks";136;1
"Unit";"Marine";"Barracks";137;1
"Upgrade";"TerranInfantryWeaponsLevel2";"EngineeringBay";101;0
"Upgrade";"TerranInfantryArmorsLevel2";"EngineeringBay";104;0
"Unit";"Marine";"Barracks";139;1
"Unit";"Marine";"Barracks";140;1
