"Type";"UnitName";"OnBuilding";"TotalSupply";"Supply"
"Unit";"SCV";"Command Center";12;1
"Unit";"SCV";"Command Center";12;1
"Unit";"SCV";"Command Center";13;1
"Building";"SupplyDepot";NA;13;0
"Unit";"SCV";"Command Center";15;1
"Unit";"SCV";"Command Center";15;1
"Building";"Refinery";NA;15;0
"Unit";"SCV";"Command Center";16;1
"Unit";"SCV";"Command Center";17;1
"Building";"Barracks";NA;15;0
"Unit";"Reaper";"Barracks";19;1
"Unit";"SCV";"Command Center";19;1
"Building";"SupplyDepot";NA;19;0
"Unit";"SCV";"Command Center";20;1
"Unit";"Marine";"Barracks";19;1
"Unit";"SCV";"Command Center";21;1
"Building";"Refinery";NA;23;0
"Unit";"SCV";"Command Center";23;1
"Building";"CommandCenter";NA;19;0
"Building";"BarracksReactor";NA;23;0
"Unit";"SCV";"Command Center";25;1
"Building";"Factory";NA;21;0
"Unit";"SCV";"Command Center";25;1
"Building";"SupplyDepot";NA;26;0
"Unit";"SCV";"Command Center";26;1
"Building";"BarracksTechLab";NA;26;0
"Unit";"Hellion";"Factory";26;2
"Unit";"Hellion";"Factory";27;2
"Unit";"SCV";"Command Center";28;1
"Unit";"SCV";"Command Center";28;1
"Building";"Starport";NA;26;0
"Building";"SupplyDepot";NA;28;0
"Unit";"SCV";"Command Center";32;1
"Unit";"SCV";"Command Center";33;1
"Unit";"Marine";"Barracks";28;1
"Unit";"Hellion";"Factory";34;2
"Unit";"Hellion";"Factory";34;2
"Unit";"SCV";"Command Center";37;1
"Unit";"SCV";"Command Center";37;1
"Unit";"SCV";"Command Center";41;1
"Unit";"SCV";"Command Center";43;1
"Building";"SupplyDepot";NA;37;0
"Unit";"Hellion";"Factory";43;2
"Unit";"Hellion";"Factory";43;2
"Unit";"SCV";"Command Center";44;1
"Unit";"SCV";"Command Center";44;1
"Unit";"Marine";"Barracks";43;1
"Unit";"SCV";"Command Center";52;1
"Unit";"SCV";"Command Center";52;1
"Unit";"Marine";"Barracks";52;1
"Building";"Refinery";NA;52;0
"Building";"Refinery";NA;52;0
"Unit";"SCV";"Command Center";54;1
"Building";"EngineeringBay";NA;52;0
"Unit";"SCV";"Command Center";55;1
"Building";"EngineeringBay";NA;52;0
"Unit";"Liberator";"Starport";52;3
"Building";"FactoryReactor";NA;52;0
"Unit";"SCV";"Command Center";55;1
"Unit";"SCV";"Command Center";56;1
"Upgrade";"Stimpack";"TechLab";43;0
"Building";"CommandCenter";NA;45;0
"Unit";"SCV";"Command Center";62;1
"Unit";"Marine";"Barracks";62;1
"Unit";"SCV";"Command Center";62;1
"Unit";"SCV";"Command Center";63;1
"Building";"Barracks";NA;57;0
"Unit";"Marine";"Barracks";63;1
"Unit";"SCV";"Command Center";64;1
"Unit";"SCV";"Command Center";66;1
"Building";"Barracks";NA;60;0
"Unit";"SCV";"Command Center";67;1
"Unit";"SCV";"Command Center";68;1
"Unit";"Marine";"Barracks";66;1
"Building";"StarportReactor";NA;64;0
"Building";"FactoryReactor";NA;66;0
"Unit";"SCV";"Command Center";69;1
"Unit";"SCV";"Command Center";70;1
"Building";"Barracks";NA;64;0
"Building";"Barracks";NA;64;0
"Unit";"Marine";"Barracks";72;1
"Unit";"Marine";"Barracks";72;1
"Unit";"Marine";"Barracks";72;1
"Unit";"SCV";"Command Center";72;1
"Unit";"Marine";"Barracks";74;1
"Unit";"Marine";"Barracks";74;1
"Unit";"SCV";"Command Center";78;1
"Unit";"Marine";"Barracks";74;1
"Building";"FactoryTechLab";NA;78;0
"Unit";"Marine";"Barracks";78;1
"Unit";"Marine";"Barracks";78;1
"Unit";"Medivac";"Starport";74;2
"Unit";"Marine";"Barracks";80;1
"Unit";"SCV";"Command Center";81;1
"Upgrade";"TerranInfantryWeaponsLevel1";"EngineeringBay";64;0
"Unit";"SCV";"Command Center";82;1
"Unit";"SCV";"Command Center";82;1
"Building";"BarracksReactor";NA;74;0
"Building";"Bunker";NA;80;0
"Unit";"SCV";"Command Center";88;1
"Unit";"Marine";"Barracks";86;1
"Unit";"Marine";"Barracks";86;1
"Unit";"Marine";"Barracks";86;1
"Unit";"SCV";"Command Center";88;1
"Unit";"Medivac";"Starport";81;2
"Building";"Armory";NA;74;0
"Unit";"SCV";"Command Center";90;1
"Unit";"Marine";"Barracks";89;1
"Unit";"Marine";"Barracks";90;1
"Unit";"Medivac";"Starport";86;2
"Unit";"SCV";"Command Center";99;1
"Unit";"SCV";"Command Center";99;1
"Unit";"SCV";"Command Center";99;1
"Building";"SupplyDepot";NA;94;0
"Building";"SupplyDepot";NA;98;0
"Unit";"Marine";"Barracks";99;1
"Unit";"Marine";"Barracks";99;1
"Unit";"Marine";"Barracks";99;1
"Building";"SupplyDepot";NA;99;0
"Unit";"SCV";"Command Center";105;1
"Unit";"SCV";"Command Center";105;1
"Unit";"Marine";"Barracks";102;1
"Unit";"Marine";"Barracks";102;1
"Unit";"SCV";"Command Center";105;1
"Unit";"Marine";"Barracks";105;1
"Unit";"Marine";"Barracks";105;1
"Unit";"Marine";"Barracks";105;1
"Building";"Refinery";NA;105;0
"Unit";"Marine";"Barracks";108;1
"Unit";"Marine";"Barracks";108;1
"Unit";"Marine";"Barracks";108;1
"Unit";"SCV";"Command Center";108;1
"Building";"Refinery";NA;105;0
"Unit";"Marine";"Barracks";108;1
"Unit";"Medivac";"Starport";105;2
"Unit";"Medivac";"Starport";105;2
"Unit";"SCV";"Command Center";115;1
"Unit";"SCV";"Command Center";115;1
"Unit";"Marine";"Barracks";113;1
"Unit";"Marine";"Barracks";113;1
"Unit";"Marine";"Barracks";115;1
"Unit";"Marine";"Barracks";115;1
"Upgrade";"TerranInfantryArmorsLevel1";"EngineeringBay";88;0
"Unit";"SCV";"Command Center";131;1
"Unit";"SCV";"Command Center";131;1
"Unit";"SCV";"Command Center";131;1
"Building";"SupplyDepot";NA;127;0
"Building";"SupplyDepot";NA;127;0
"Unit";"Marine";"Barracks";131;1
"Unit";"Marine";"Barracks";131;1
"Unit";"Marine";"Barracks";131;1
"Unit";"Marine";"Barracks";131;1
"Unit";"Marine";"Barracks";131;1
"Building";"SupplyDepot";NA;130;0
"Building";"SupplyDepot";NA;131;0
"Unit";"SCV";"Command Center";139;1
"Unit";"SCV";"Command Center";139;1
"Unit";"Marine";"Barracks";134;1
"Unit";"Marine";"Barracks";134;1
"Unit";"Marine";"Barracks";134;1
"Unit";"Marine";"Barracks";134;1
"Unit";"Marine";"Barracks";134;1
"Building";"SupplyDepot";NA;134;0
"Building";"SupplyDepot";NA;139;0
"Unit";"Medivac";"Starport";134;2
"Unit";"SCV";"Command Center";145;1
"Unit";"Marine";"Barracks";141;1
"Unit";"Marine";"Barracks";141;1
"Unit";"Marine";"Barracks";141;1
"Unit";"Marine";"Barracks";141;1
"Unit";"Marine";"Barracks";141;1
"Building";"CommandCenter";NA;116;0
"Unit";"Marine";"Barracks";146;1
"Unit";"Marine";"Barracks";146;1
"Unit";"Marine";"Barracks";146;1
"Unit";"Marine";"Barracks";146;1
"Unit";"Marine";"Barracks";149;1
"Unit";"Marine";"Barracks";150;1
"Unit";"Marine";"Barracks";151;1
"Unit";"Marine";"Barracks";152;1
"Building";"Barracks";NA;139;0
"Building";"Factory";NA;139;0
"Unit";"Marine";"Barracks";154;1
"Building";"Barracks";NA;139;0
"Unit";"Marine";"Barracks";154;1
"Unit";"Marine";"Barracks";157;1
"Unit";"Marine";"Barracks";158;1
"Unit";"Marine";"Barracks";158;1
"Upgrade";"TerranInfantryWeaponsLevel2";"EngineeringBay";120;0
"Unit";"Marine";"Barracks";158;1
"Unit";"Marine";"Barracks";159;1
"Unit";"Marine";"Barracks";160;1
"Unit";"Marine";"Barracks";161;1
"Building";"BarracksTechLab";NA;162;0
"Unit";"Marine";"Barracks";162;1
"Unit";"Marine";"Barracks";163;1
"Unit";"Marine";"Barracks";164;1
"Unit";"Marine";"Barracks";166;1
"Building";"BarracksTechLab";NA;166;0
"Unit";"Thor";"Factory";158;6
"Unit";"Medivac";"Starport";162;2
"Unit";"Medivac";"Starport";162;2
"Unit";"Marine";"Barracks";171;1
"Unit";"Marine";"Barracks";171;1
"Unit";"Marine";"Barracks";171;1
"Unit";"Marine";"Barracks";171;1
"Unit";"Marine";"Barracks";171;1
"Unit";"Marine";"Barracks";171;1
"Unit";"Marauder";"Barracks";171;2
"Unit";"Marine";"Barracks";175;1
"Building";"FactoryReactor";NA;166;0
"Unit";"Marauder";"Barracks";185;2
"Unit";"Marauder";"Barracks";189;2
"Building";"Refinery";NA;190;0
"Building";"Refinery";NA;191;0
"Building";"SupplyDepot";NA;193;0
"Building";"SupplyDepot";NA;193;0
"Unit";"Medivac";"Starport";185;2
"Unit";"Marine";"Barracks";194;1
"Unit";"Marine";"Barracks";194;1
"Unit";"Marine";"Barracks";194;1
"Unit";"Marine";"Barracks";194;1
"Unit";"Marine";"Barracks";194;1
"Unit";"Marine";"Barracks";196;1
"Unit";"Marine";"Barracks";196;1
"Unit";"Marine";"Barracks";196;1
"Unit";"Marauder";"Barracks";196;2
"Unit";"Marauder";"Barracks";196;2
"Unit";"Marauder";"Barracks";198;2
"Unit";"Marine";"Barracks";200;1
"Unit";"Marine";"Barracks";201;1
"Unit";"Marine";"Barracks";202;1
"Unit";"Marine";"Barracks";203;1
"Unit";"Marine";"Barracks";204;1
"Upgrade";"TerranInfantryArmorsLevel2";"EngineeringBay";158;0
"Unit";"Marine";"Barracks";205;1
"Unit";"Marine";"Barracks";206;1
"Building";"MissileTurret";NA;215;0
"Building";"MissileTurret";NA;219;0
"Building";"MissileTurret";NA;219;0
"Building";"MissileTurret";NA;219;0
"Upgrade";"TerranVehicleAndShipArmorsLevel1";"Armory";174;0
"Building";"MissileTurret";NA;219;0
"Building";"MissileTurret";NA;219;0
"Building";"MissileTurret";NA;219;0
"Building";"MissileTurret";NA;219;0
"Building";"MissileTurret";NA;219;0
"Building";"MissileTurret";NA;219;0
"Unit";"Marine";"Barracks";221;1
"Building";"MissileTurret";NA;221;0
"Unit";"Marine";"Barracks";221;1
"Building";"MissileTurret";NA;221;0
"Unit";"Marine";"Barracks";221;1
"Unit";"Marine";"Barracks";221;1
"Unit";"Marine";"Barracks";221;1
"Unit";"Marine";"Barracks";221;1
"Unit";"Marine";"Barracks";221;1
"Unit";"Marine";"Barracks";221;1
"Unit";"Marine";"Barracks";221;1
"Unit";"Marine";"Barracks";221;1
"Unit";"Marauder";"Barracks";221;2
"Unit";"Marine";"Barracks";225;1
"Unit";"Marine";"Barracks";233;1
"Unit";"Marine";"Barracks";233;1
"Unit";"Marine";"Barracks";233;1
"Unit";"Marine";"Barracks";233;1
"Unit";"Marine";"Barracks";233;1
"Unit";"Marine";"Barracks";233;1
"Unit";"Marauder";"Barracks";233;2
"Unit";"Marauder";"Barracks";233;2
"Unit";"Marauder";"Barracks";233;2
"Unit";"Marine";"Barracks";234;1
"Unit";"Marine";"Barracks";234;1
"Unit";"Marine";"Barracks";235;1
"Unit";"Marine";"Barracks";238;1
"Unit";"Marine";"Barracks";240;1
"Unit";"Marine";"Barracks";240;1
"Unit";"Marine";"Barracks";240;1
"Upgrade";"TerranInfantryWeaponsLevel3";"EngineeringBay";196;0
"Unit";"Marine";"Barracks";244;1
"Unit";"Marauder";"Barracks";240;2
"Unit";"Marauder";"Barracks";242;2
"Unit";"Marine";"Barracks";248;1
"Unit";"Marine";"Barracks";248;1
"Unit";"Marine";"Barracks";248;1
"Unit";"Marine";"Barracks";254;1
"Building";"MissileTurret";NA;254;0
"Unit";"Marine";"Barracks";254;1
"Unit";"Marine";"Barracks";258;1
"Unit";"Marine";"Barracks";258;1
"Unit";"Medivac";"Starport";250;2
"Unit";"Medivac";"Starport";250;2
"Unit";"Marine";"Barracks";260;1
"Unit";"Marine";"Barracks";260;1
"Unit";"Marine";"Barracks";261;1
"Unit";"Marine";"Barracks";261;1
"Unit";"Marine";"Barracks";261;1
"Unit";"Marine";"Barracks";261;1
"Unit";"Marauder";"Barracks";261;2
"Unit";"Marine";"Barracks";262;1
"Unit";"Marine";"Barracks";263;1
"Unit";"Marine";"Barracks";265;1
"Unit";"Marine";"Barracks";265;1
"Unit";"Marine";"Barracks";269;1
"Unit";"Marine";"Barracks";270;1
"Unit";"Marine";"Barracks";271;1
"Unit";"Marine";"Barracks";277;1
"Unit";"Marine";"Barracks";277;1
"Unit";"Marine";"Barracks";277;1
"Unit";"Marauder";"Barracks";277;2
"Unit";"Marauder";"Barracks";277;2
"Unit";"Marine";"Barracks";279;1
"Unit";"Marine";"Barracks";279;1
"Unit";"Marine";"Barracks";281;1
"Unit";"Marine";"Barracks";281;1
"Unit";"Marine";"Barracks";284;1
"Unit";"Marine";"Barracks";284;1
"Unit";"Marine";"Barracks";284;1
"Building";"CommandCenter";NA;254;0
"Unit";"Marine";"Barracks";286;1
"Unit";"Marauder";"Barracks";285;2
"Unit";"Marine";"Barracks";293;1
"Unit";"Marine";"Barracks";293;1
"Unit";"Medivac";"Starport";293;2
"Unit";"Medivac";"Starport";293;2
"Building";"MissileTurret";NA;307;0
"Unit";"Thor";"Factory";303;6
"Unit";"Marine";"Barracks";307;1
"Unit";"Marine";"Barracks";307;1
"Unit";"Marine";"Barracks";307;1
"Unit";"Marine";"Barracks";307;1
"Unit";"Marine";"Barracks";307;1
"Unit";"Marine";"Barracks";307;1
"Unit";"Marine";"Barracks";307;1
"Unit";"Marine";"Barracks";307;1
"Unit";"Marauder";"Barracks";307;2
"Unit";"Marauder";"Barracks";307;2
"Unit";"Marauder";"Barracks";307;2
"Unit";"Marine";"Barracks";316;1
"Unit";"Marine";"Barracks";317;1
"Building";"CommandCenter";NA;303;0
"Unit";"Marine";"Barracks";317;1
"Unit";"Marine";"Barracks";318;1
"Unit";"Marine";"Barracks";320;1
"Unit";"Marine";"Barracks";320;1
"Unit";"Marine";"Barracks";325;1
"Unit";"Marine";"Barracks";325;1
"Unit";"Marauder";"Barracks";321;2
"Unit";"Marauder";"Barracks";323;2
"Unit";"Marauder";"Barracks";325;2
"Upgrade";"TerranInfantryArmorsLevel3";"EngineeringBay";286;0
"Unit";"Marine";"Barracks";327;1
"Unit";"Marine";"Barracks";328;1
"Unit";"Marine";"Barracks";329;1
"Unit";"Marine";"Barracks";330;1
"Building";"MissileTurret";NA;339;0
"Unit";"Marine";"Barracks";341;1
"Unit";"Marine";"Barracks";341;1
"Unit";"Thor";"Factory";327;6
"Unit";"Marine";"Barracks";353;1
"Unit";"Marine";"Barracks";353;1
"Unit";"Marine";"Barracks";353;1
"Unit";"Marine";"Barracks";353;1
