"type";"unit_name";"on_building";"total_supply";"supply"
"Building";"Refinery";NA;14;0
"Building";"Barracks";NA;15;0
"Unit";"Reaper";"Barracks";19;1
"Building";"Refinery";NA;19;0
"Building";"Factory";NA;19;0
"Building";"BarracksReactor";NA;20;0
"Building";"CommandCenter";NA;19;0
"Unit";"Hellion";"Factory";23;2
"Unit";"Hellion";"Factory";23;2
"Building";"Starport";NA;23;0
"Unit";"Hellion";"Factory";25;2
"Unit";"Hellion";"Factory";29;2
"Unit";"Medivac";"Starport";36;2
"Unit";"Liberator";"Starport";40;3
"Building";"BarracksTechLab";NA;48;0
"Building";"FactoryReactor";NA;48;0
"Building";"EngineeringBay";NA;53;0
"Building";"EngineeringBay";NA;53;0
"Building";"Barracks";NA;48;0
"Building";"Barracks";NA;48;0
"Building";"CommandCenter";NA;46;0
"Building";"StarportReactor";NA;55;0
"Building";"Refinery";NA;59;0
"Building";"Refinery";NA;59;0
"Building";"FactoryTechLab";NA;61;0
"Unit";"Marine";"Barracks";63;1
"Unit";"Marine";"Barracks";63;1
"Unit";"Marine";"Barracks";63;1
"Unit";"Marine";"Barracks";63;1
"Unit";"Marine";"Barracks";63;1
"Unit";"Marine";"Barracks";67;1
"Unit";"Marine";"Barracks";68;1
"Unit";"Marine";"Barracks";69;1
"Unit";"Marine";"Barracks";70;1
"Unit";"Marine";"Barracks";74;1
"Unit";"Marine";"Barracks";75;1
"Unit";"Marine";"Barracks";76;1
"Unit";"Marine";"Barracks";77;1
"Unit";"Marine";"Barracks";78;1
"Unit";"Medivac";"Starport";74;2
"Unit";"Medivac";"Starport";74;2
"Unit";"Marine";"Barracks";92;1
"Unit";"Marine";"Barracks";92;1
"Unit";"Marine";"Barracks";92;1
"Upgrade";"TerranInfantryWeaponsLevel1";"EngineeringBay";63;0
"Unit";"Marine";"Barracks";92;1
"Unit";"Marine";"Barracks";92;1
"Upgrade";"TerranInfantryArmorsLevel1";"EngineeringBay";63;0
"Building";"Armory";NA;75;0
"Upgrade";"Stimpack";"TechLab";63;0
"Building";"Barracks";NA;81;0
"Building";"Barracks";NA;82;0
"Unit";"Marine";"Barracks";94;1
"Unit";"Marine";"Barracks";95;1
"Unit";"Marine";"Barracks";96;1
"Unit";"Marine";"Barracks";98;1
"Unit";"Medivac";"Starport";94;2
"Unit";"Medivac";"Starport";94;2
"Unit";"Marine";"Barracks";101;1
"Building";"CommandCenter";NA;79;0
"Building";"BarracksTechLab";NA;101;0
"Building";"Refinery";NA;103;0
"Building";"Refinery";NA;103;0
"Building";"BarracksTechLab";NA;110;0
"Unit";"Marine";"Barracks";112;1
"Unit";"Marine";"Barracks";112;1
"Unit";"Marine";"Barracks";112;1
"Unit";"Marine";"Barracks";112;1
"Unit";"Marine";"Barracks";112;1
"Unit";"Marine";"Barracks";119;1
"Unit";"Medivac";"Starport";116;2
"Building";"SensorTower";NA;121;0
"Unit";"Medivac";"Starport";116;2
"Unit";"Marine";"Barracks";127;1
"Unit";"Marine";"Barracks";127;1
"Unit";"Marine";"Barracks";127;1
"Unit";"Marine";"Barracks";127;1
"Unit";"Marine";"Barracks";127;1
"Unit";"Marine";"Barracks";127;1
"Unit";"Marine";"Barracks";127;1
"Building";"SensorTower";NA;132;0
"Unit";"Marine";"Barracks";145;1
"Unit";"Marine";"Barracks";145;1
"Unit";"Marine";"Barracks";145;1
"Building";"MissileTurret";NA;145;0
"Building";"MissileTurret";NA;145;0
"Building";"MissileTurret";NA;145;0
"Unit";"Marine";"Barracks";145;1
"Unit";"Marine";"Barracks";145;1
"Unit";"Marine";"Barracks";145;1
"Unit";"Marine";"Barracks";145;1
"Building";"MissileTurret";NA;148;0
"Unit";"Marine";"Barracks";148;1
"Unit";"Marine";"Barracks";148;1
"Unit";"Marine";"Barracks";148;1
"Building";"MissileTurret";NA;148;0
"Upgrade";"TerranVehicleWeaponsLevel1";"Armory";127;0
"Building";"MissileTurret";NA;151;0
"Unit";"Marine";"Barracks";151;1
"Unit";"Marine";"Barracks";152;1
"Unit";"Marine";"Barracks";153;1
"Unit";"Marine";"Barracks";155;1
"Unit";"Marine";"Barracks";158;1
"Unit";"Thor";"Factory";148;6
"Upgrade";"TerranInfantryWeaponsLevel2";"EngineeringBay";127;0
"Upgrade";"TerranInfantryArmorsLevel2";"EngineeringBay";127;0
"Building";"MissileTurret";NA;161;0
"Unit";"Medivac";"Starport";155;2
"Unit";"Medivac";"Starport";155;2
"Building";"MissileTurret";NA;164;0
"Building";"MissileTurret";NA;164;0
"Building";"Factory";NA;151;0
"Building";"Factory";NA;151;0
"Building";"Refinery";NA;164;0
"Building";"Refinery";NA;164;0
"Building";"Factory";NA;155;0
"Building";"Factory";NA;155;0
"Unit";"Marine";"Barracks";181;1
"Unit";"Marine";"Barracks";182;1
"Unit";"Marine";"Barracks";182;1
"Unit";"Marine";"Barracks";182;1
"Building";"FactoryTechLab";NA;182;0
"Building";"FactoryTechLab";NA;182;0
"Building";"FactoryTechLab";NA;185;0
"Building";"FactoryTechLab";NA;186;0
"Unit";"Thor";"Factory";185;6
"Unit";"Thor";"Factory";189;6
"Unit";"Thor";"Factory";189;6
"Building";"Barracks";NA;189;0
"Building";"Barracks";NA;189;0
"Building";"MissileTurret";NA;195;0
"Building";"MissileTurret";NA;195;0
"Building";"Barracks";NA;189;0
"Unit";"Thor";"Factory";189;6
"Unit";"Marine";"Barracks";207;1
"Unit";"Marine";"Barracks";207;1
"Unit";"Marine";"Barracks";207;1
"Unit";"Marine";"Barracks";207;1
"Unit";"Marine";"Barracks";207;1
"Unit";"Marine";"Barracks";207;1
"Unit";"Marine";"Barracks";207;1
"Unit";"Marine";"Barracks";213;1
"Unit";"Marine";"Barracks";214;1
"Unit";"Marine";"Barracks";215;1
"Unit";"Marine";"Barracks";216;1
"Unit";"Marine";"Barracks";216;1
"Unit";"Medivac";"Starport";220;2
"Building";"CommandCenter";NA;195;0
"Unit";"Thor";"Factory";213;6
"Unit";"Thor";"Factory";213;6
"Unit";"Marine";"Barracks";225;1
"Unit";"Marine";"Barracks";225;1
"Unit";"Marine";"Barracks";225;1
"Unit";"Marine";"Barracks";225;1
"Unit";"Marine";"Barracks";225;1
"Unit";"Marine";"Barracks";225;1
"Unit";"Marine";"Barracks";225;1
"Unit";"Marine";"Barracks";239;1
"Unit";"Marine";"Barracks";240;1
"Unit";"Marine";"Barracks";240;1
"Unit";"Marine";"Barracks";242;1
"Unit";"Marine";"Barracks";243;1
"Unit";"Marine";"Barracks";243;1
"Unit";"Marine";"Barracks";243;1
"Building";"BarracksTechLab";NA;246;0
"Building";"BarracksTechLab";NA;246;0
"Building";"BarracksTechLab";NA;246;0
"Unit";"Marine";"Barracks";246;1
"Unit";"Marine";"Barracks";247;1
"Unit";"Marine";"Barracks";247;1
"Unit";"Marine";"Barracks";249;1
"Unit";"Thor";"Factory";227;6
"Unit";"Thor";"Factory";227;6
"Building";"MissileTurret";NA;253;0
"Unit";"Thor";"Factory";246;6
"Unit";"Thor";"Factory";246;6
"Unit";"Thor";"Factory";246;6
"Building";"MissileTurret";NA;269;0
"Building";"Refinery";NA;269;0
"Building";"Refinery";NA;269;0
"Building";"Refinery";NA;269;0
"Building";"Refinery";NA;269;0
"Unit";"Thor";"Factory";269;6
"Unit";"Thor";"Factory";269;6
"Upgrade";"TerranInfantryWeaponsLevel3";"EngineeringBay";225;0
"Unit";"Marine";"Barracks";287;1
"Unit";"Marine";"Barracks";287;1
"Unit";"Marine";"Barracks";287;1
"Upgrade";"TerranInfantryArmorsLevel3";"EngineeringBay";225;0
"Unit";"Marauder";"Barracks";287;2
"Unit";"Marauder";"Barracks";287;2
"Building";"GhostAcademy";NA;287;0
"Unit";"Marine";"Barracks";302;1
"Unit";"Marine";"Barracks";302;1
"Unit";"Marine";"Barracks";302;1
"Unit";"Marine";"Barracks";302;1
"Unit";"Marine";"Barracks";302;1
"Unit";"Marauder";"Barracks";302;2
"Unit";"Marauder";"Barracks";302;2
"Unit";"Marauder";"Barracks";302;2
"Unit";"Marauder";"Barracks";302;2
"Building";"CommandCenter";NA;287;0
"Building";"CommandCenter";NA;287;0
"Unit";"Marine";"Barracks";319;1
"Unit";"Marine";"Barracks";319;1
"Unit";"Marine";"Barracks";319;1
"Unit";"Marine";"Barracks";319;1
"Unit";"Thor";"Factory";306;6
"Unit";"Marine";"Barracks";319;1
"Unit";"Thor";"Factory";306;6
"Unit";"Marauder";"Barracks";319;2
"Unit";"Marauder";"Barracks";319;2
"Unit";"Marauder";"Barracks";319;2
"Unit";"Marauder";"Barracks";319;2
"Unit";"Marauder";"Barracks";319;2
"Unit";"Marine";"Barracks";319;1
"Unit";"Marine";"Barracks";320;1
"Unit";"Marine";"Barracks";321;1
"Unit";"Marine";"Barracks";322;1
