"type";"unit_name";"on_building";"total_supply";"supply"
"Building";"Refinery";NA;14;0
"Building";"Barracks";NA;15;0
"Unit";"Reaper";"Barracks";19;1
"Building";"Refinery";NA;21;0
"Building";"Factory";NA;19;0
"Building";"BarracksReactor";NA;21;0
"Building";"CommandCenter";NA;19;0
"Building";"BarracksTechLab";NA;24;0
"Unit";"Hellion";"Factory";23;2
"Unit";"Hellion";"Factory";23;2
"Building";"Starport";NA;23;0
"Unit";"Hellion";"Factory";29;2
"Unit";"Hellion";"Factory";29;2
"Unit";"Banshee";"Starport";36;3
"Unit";"Hellion";"Factory";41;2
"Unit";"Hellion";"Factory";42;2
"Unit";"Hellion";"Factory";49;2
"Unit";"Hellion";"Factory";50;2
"Unit";"Banshee";"Starport";46;3
"Building";"CommandCenter";NA;40;0
"Building";"Refinery";NA;57;0
"Building";"Refinery";NA;59;0
"Building";"BarracksTechLab";NA;64;0
"Building";"Armory";NA;56;0
"Building";"Armory";NA;56;0
"Building";"Factory";NA;64;0
"Building";"StarportReactor";NA;66;0
"Building";"Factory";NA;64;0
"Building";"EngineeringBay";NA;71;0
"Unit";"Hellion";"Factory";71;2
"Unit";"Hellion";"Factory";71;2
"Unit";"Medivac";"Starport";71;2
"Unit";"Medivac";"Starport";71;2
"Building";"Refinery";NA;78;0
"Building";"Refinery";NA;78;0
"Unit";"Hellion";"Factory";78;2
"Unit";"Hellion";"Factory";78;2
"Unit";"Thor";"Factory";71;6
"Unit";"Thor";"Factory";78;6
"Unit";"Hellion";"Factory";97;2
"Unit";"Hellion";"Factory";97;2
"Upgrade";"TerranVehicleWeaponsLevel1";"Armory";71;0
"Building";"SensorTower";NA;113;0
"Unit";"Hellion";"Factory";113;2
"Unit";"Hellion";"Factory";116;2
"Building";"MissileTurret";NA;119;0
"Building";"MissileTurret";NA;119;0
"Unit";"Hellion";"Factory";126;2
"Unit";"Hellion";"Factory";126;2
"Building";"CommandCenter";NA;113;0
"Building";"Factory";NA;126;0
"Building";"Factory";NA;126;0
"Building";"Refinery";NA;133;0
"Building";"Refinery";NA;133;0
"Unit";"Hellion";"Factory";133;2
"Unit";"Hellion";"Factory";133;2
"Building";"FactoryTechLab";NA;133;0
"Unit";"Hellion";"Factory";133;2
"Unit";"Hellion";"Factory";133;2
"Building";"FactoryReactor";NA;133;0
"Unit";"Hellion";"Factory";140;2
"Unit";"Hellion";"Factory";140;2
"Building";"MissileTurret";NA;144;0
"Unit";"Hellion";"Factory";144;2
"Unit";"Thor";"Factory";137;6
"Upgrade";"TerranVehicleWeaponsLevel2";"Armory";133;0
"Unit";"Hellion";"Factory";148;2
"Unit";"Hellion";"Factory";148;2
"Unit";"Hellion";"Factory";148;2
"Unit";"Hellion";"Factory";148;2
"Unit";"Hellion";"Factory";156;2
"Unit";"Hellion";"Factory";158;2
"Unit";"Hellion";"Factory";160;2
"Building";"CommandCenter";NA;144;0
"Building";"MissileTurret";NA;164;0
"Building";"MissileTurret";NA;164;0
"Building";"MissileTurret";NA;164;0
"Building";"MissileTurret";NA;164;0
"Unit";"Hellion";"Factory";164;2
"Unit";"Hellion";"Factory";164;2
"Building";"BarracksTechLab";NA;170;0
"Unit";"Hellion";"Factory";164;2
"Building";"Starport";NA;170;0
"Building";"Starport";NA;170;0
"Building";"Starport";NA;170;0
"Building";"SensorTower";NA;176;0
"Building";"MissileTurret";NA;176;0
"Building";"MissileTurret";NA;176;0
"Building";"Refinery";NA;176;0
"Building";"Refinery";NA;176;0
"Unit";"Hellion";"Factory";176;2
"Unit";"Hellion";"Factory";176;2
"Unit";"Hellion";"Factory";176;2
"Unit";"Hellion";"Factory";176;2
"Building";"MissileTurret";NA;188;0
"Building";"MissileTurret";NA;188;0
"Building";"FactoryReactor";NA;188;0
"Building";"StarportTechLab";NA;188;0
"Building";"StarportTechLab";NA;188;0
"Building";"StarportTechLab";NA;188;0
"Unit";"Hellion";"Factory";188;2
"Unit";"Hellion";"Factory";188;2
"Building";"StarportReactor";NA;188;0
"Unit";"Hellion";"Factory";188;2
"Unit";"Hellion";"Factory";188;2
"Unit";"Thor";"Factory";188;6
"Unit";"Thor";"Factory";188;6
"Unit";"Thor";"Factory";188;6
"Unit";"Hellion";"Factory";205;2
"Unit";"Hellion";"Factory";205;2
"Unit";"Hellion";"Factory";205;2
"Unit";"Hellion";"Factory";205;2
"Unit";"Raven";"Starport";205;2
"Unit";"Raven";"Starport";211;2
"Upgrade";"TerranVehicleWeaponsLevel3";"Armory";188;0
"Unit";"Hellion";"Factory";225;2
"Unit";"Hellion";"Factory";225;2
"Unit";"Hellion";"Factory";225;2
"Unit";"Hellion";"Factory";225;2
"Unit";"Hellion";"Factory";229;2
"Unit";"Hellion";"Factory";231;2
"Building";"CommandCenter";NA;217;0
"Unit";"Raven";"Starport";225;2
"Unit";"Hellion";"Factory";237;2
"Unit";"Hellion";"Factory";237;2
"Unit";"Raven";"Starport";225;2
"Unit";"Raven";"Starport";227;2
"Unit";"Thor";"Factory";229;6
"Unit";"Hellion";"Factory";241;2
"Unit";"Hellion";"Factory";241;2
"Building";"Starport";NA;237;0
"Building";"Starport";NA;237;0
"Unit";"Hellion";"Factory";243;2
"Building";"Refinery";NA;257;0
"Building";"Refinery";NA;261;0
"Unit";"Raven";"Starport";241;2
"Unit";"Raven";"Starport";247;2
"Unit";"Hellion";"Factory";268;2
"Unit";"Hellion";"Factory";268;2
"Unit";"Hellion";"Factory";268;2
"Unit";"Hellion";"Factory";268;2
"Unit";"Hellion";"Factory";268;2
"Building";"MissileTurret";NA;275;0
"Unit";"Hellion";"Factory";275;2
"Unit";"Raven";"Starport";273;2
"Unit";"Hellion";"Factory";287;2
"Unit";"Hellion";"Factory";287;2
"Unit";"Hellion";"Factory";287;2
"Unit";"Hellion";"Factory";287;2
"Unit";"Hellion";"Factory";289;2
"Unit";"Hellion";"Factory";289;2
"Unit";"Hellion";"Factory";289;2
"Unit";"Hellion";"Factory";305;2
"Unit";"Hellion";"Factory";305;2
"Unit";"Hellion";"Factory";305;2
"Unit";"Hellion";"Factory";305;2
"Unit";"Hellion";"Factory";305;2
"Unit";"Hellion";"Factory";305;2
"Unit";"Hellion";"Factory";305;2
"Unit";"Raven";"Starport";289;2
"Unit";"Raven";"Starport";289;2
