"Type";"UnitName";"OnBuilding";"TotalSupply";"Supply"
"Unit";"SCV";"Command Center";12;1
"Unit";"SCV";"Command Center";12;1
"Unit";"SCV";"Command Center";13;1
"Building";"SupplyDepot";NA;13;0
"Building";"Refinery";NA;14;0
"Unit";"SCV";"Command Center";15;1
"Unit";"SCV";"Command Center";15;1
"Unit";"SCV";"Command Center";16;1
"Unit";"SCV";"Command Center";17;1
"Building";"Barracks";NA;15;0
"Unit";"Reaper";"Barracks";19;1
"Unit";"SCV";"Command Center";19;1
"Unit";"SCV";"Command Center";20;1
"Unit";"SCV";"Command Center";21;1
"Building";"SupplyDepot";NA;21;0
"Building";"Factory";NA;19;0
"Building";"Refinery";NA;22;0
"Building";"BarracksReactor";NA;20;0
"Unit";"SCV";"Command Center";23;1
"Building";"CommandCenter";NA;19;0
"Unit";"SCV";"Command Center";23;1
"Building";"BarracksTechLab";NA;24;0
"Unit";"Hellion";"Factory";24;2
"Unit";"Hellion";"Factory";24;2
"Unit";"SCV";"Command Center";29;1
"Building";"Starport";NA;24;0
"Unit";"SCV";"Command Center";29;1
"Unit";"Hellion";"Factory";29;2
"Unit";"Hellion";"Factory";29;2
"Unit";"SCV";"Command Center";30;1
"Building";"SupplyDepot";NA;29;0
"Unit";"SCV";"Command Center";30;1
"Unit";"SCV";"Command Center";35;1
"Unit";"SCV";"Command Center";36;1
"Unit";"SCV";"Command Center";37;1
"Building";"SupplyDepot";NA;36;0
"Unit";"Hellion";"Factory";38;2
"Unit";"SCV";"Command Center";38;1
"Unit";"SCV";"Command Center";40;1
"Unit";"Hellion";"Factory";38;2
"Unit";"SCV";"Command Center";42;1
"Unit";"SCV";"Command Center";43;1
"Unit";"SCV";"Command Center";46;1
"Unit";"SCV";"Command Center";48;1
"Unit";"SCV";"Command Center";48;1
"Building";"SupplyDepot";NA;48;0
"Unit";"SCV";"Command Center";49;1
"Building";"FactoryReactor";NA;47;0
"Unit";"SCV";"Command Center";50;1
"Unit";"SCV";"Command Center";51;1
"Unit";"SCV";"Command Center";52;1
"Building";"EngineeringBay";NA;51;0
"Unit";"SCV";"Command Center";53;1
"Building";"StarportReactor";NA;50;0
"Unit";"Marine";"Barracks";53;1
"Building";"Barracks";NA;48;0
"Building";"Barracks";NA;49;0
"Unit";"SCV";"Command Center";54;1
"Building";"SupplyDepot";NA;54;0
"Unit";"SCV";"Command Center";55;1
"Building";"FactoryTechLab";NA;54;0
"Unit";"SCV";"Command Center";57;1
"Building";"CommandCenter";NA;48;0
"Unit";"SCV";"Command Center";58;1
"Unit";"SCV";"Command Center";59;1
"Unit";"Marine";"Barracks";59;1
"Unit";"Marine";"Barracks";59;1
"Unit";"SCV";"Command Center";60;1
"Unit";"Marauder";"Barracks";59;2
"Unit";"Marine";"Barracks";61;1
"Unit";"SCV";"Command Center";61;1
"Building";"Barracks";NA;55;0
"Building";"Barracks";NA;55;0
"Unit";"Medivac";"Starport";59;2
"Unit";"Medivac";"Starport";59;2
"Unit";"SCV";"Command Center";64;1
"Unit";"Marine";"Barracks";64;1
"Unit";"Marine";"Barracks";64;1
"Unit";"SCV";"Command Center";68;1
"Unit";"SCV";"Command Center";73;1
"Building";"Refinery";NA;67;0
"Building";"Refinery";NA;67;0
"Building";"SupplyDepot";NA;67;0
"Unit";"Marauder";"Barracks";67;2
"Unit";"SCV";"Command Center";76;1
"Unit";"SCV";"Command Center";77;1
"Unit";"Marine";"Barracks";76;1
"Unit";"Marine";"Barracks";76;1
"Unit";"Marine";"Barracks";76;1
"Unit";"Marine";"Barracks";76;1
"Unit";"SCV";"Command Center";78;1
"Unit";"Marine";"Barracks";78;1
"Upgrade";"Stimpack";"TechLab";55;0
"Building";"BarracksReactor";NA;74;0
"Building";"BarracksReactor";NA;74;0
"Unit";"Marine";"Barracks";82;1
"Unit";"Marine";"Barracks";83;1
"Unit";"Marine";"Barracks";84;1
"Unit";"Marine";"Barracks";86;1
"Building";"SupplyDepot";NA;87;0
"Building";"SupplyDepot";NA;87;0
"Building";"SupplyDepot";NA;87;0
"Unit";"Marine";"Barracks";88;1
"Unit";"Marine";"Barracks";88;1
"Unit";"Marine";"Barracks";91;1
"Unit";"Marine";"Barracks";92;1
"Unit";"Marine";"Barracks";92;1
"Unit";"Marine";"Barracks";92;1
"Unit";"Marine";"Barracks";92;1
"Unit";"Marine";"Barracks";92;1
"Unit";"Marine";"Barracks";92;1
"Unit";"SCV";"Command Center";98;1
"Unit";"SCV";"Command Center";99;1
"Unit";"Marine";"Barracks";92;1
"Unit";"Marine";"Barracks";93;1
"Unit";"Marine";"Barracks";100;1
"Unit";"Marine";"Barracks";100;1
"Upgrade";"TerranInfantryWeaponsLevel1";"EngineeringBay";76;0
"Unit";"SCV";"Command Center";101;1
"Unit";"SCV";"Command Center";102;1
"Unit";"Marine";"Barracks";102;1
"Unit";"SCV";"Command Center";107;1
"Unit";"SCV";"Command Center";108;1
"Unit";"Marine";"Barracks";105;1
"Building";"SupplyDepot";NA;105;0
"Unit";"SCV";"Command Center";109;1
"Unit";"SCV";"Command Center";110;1
"Unit";"Marine";"Barracks";110;1
"Unit";"Marine";"Barracks";110;1
"Unit";"SCV";"Command Center";114;1
"Unit";"Marine";"Barracks";113;1
"Unit";"Marine";"Barracks";113;1
"Unit";"Marine";"Barracks";113;1
"Unit";"Marine";"Barracks";113;1
"Unit";"SCV";"Command Center";115;1
"Unit";"SCV";"Command Center";115;1
"Building";"SupplyDepot";NA;114;0
"Unit";"Medivac";"Starport";112;2
"Unit";"SCV";"Command Center";117;1
"Unit";"Marine";"Barracks";117;1
"Unit";"Marine";"Barracks";117;1
"Unit";"Marine";"Barracks";117;1
"Building";"SupplyDepot";NA;117;0
"Unit";"SCV";"Command Center";122;1
"Unit";"SCV";"Command Center";123;1
"Unit";"Marine";"Barracks";117;1
"Unit";"SCV";"Command Center";126;1
"Unit";"SCV";"Command Center";130;1
"Building";"SupplyDepot";NA;124;0
"Unit";"Marine";"Barracks";133;1
"Unit";"Marine";"Barracks";133;1
"Unit";"Marine";"Barracks";133;1
"Unit";"SCV";"Command Center";134;1
"Unit";"Marine";"Barracks";134;1
"Unit";"Marine";"Barracks";134;1
"Unit";"Marine";"Barracks";134;1
"Unit";"Marine";"Barracks";135;1
"Unit";"Marine";"Barracks";135;1
"Unit";"Marine";"Barracks";135;1
"Unit";"Marine";"Barracks";136;1
"Unit";"Marine";"Barracks";137;1
"Unit";"Marine";"Barracks";138;1
"Unit";"SCV";"Command Center";142;1
"Unit";"Marine";"Barracks";141;1
"Unit";"Marine";"Barracks";141;1
"Unit";"Marine";"Barracks";142;1
"Unit";"Marine";"Barracks";143;1
"Unit";"Marine";"Barracks";144;1
"Unit";"Marine";"Barracks";144;1
"Unit";"Marine";"Barracks";145;1
"Building";"SupplyDepot";NA;148;0
"Unit";"Marine";"Barracks";152;1
"Unit";"Marine";"Barracks";152;1
"Unit";"Marine";"Barracks";152;1
"Unit";"Marine";"Barracks";152;1
"Building";"EngineeringBay";NA;149;0
"Unit";"SCV";"Command Center";155;1
"Upgrade";"TerranInfantryArmorsLevel1";"EngineeringBay";124;0
"Unit";"Marine";"Barracks";154;1
"Unit";"Marine";"Barracks";154;1
"Unit";"Marine";"Barracks";154;1
"Unit";"SCV";"Command Center";156;1
"Unit";"Marine";"Barracks";154;1
"Unit";"SCV";"Command Center";160;1
"Unit";"SCV";"Command Center";160;1
"Unit";"Medivac";"Starport";152;2
"Unit";"Medivac";"Starport";153;2
"Building";"CommandCenter";NA;134;0
"Unit";"Marine";"Barracks";160;1
"Unit";"Marine";"Barracks";160;1
"Building";"Armory";NA;149;0
"Unit";"SCV";"Command Center";167;1
"Unit";"Marine";"Barracks";166;1
"Unit";"Marine";"Barracks";166;1
"Unit";"SCV";"Command Center";172;1
"Building";"Refinery";NA;172;0
"Building";"SupplyDepot";NA;174;0
"Unit";"Marine";"Barracks";174;1
"Unit";"Marine";"Barracks";174;1
"Unit";"Marine";"Barracks";174;1
"Building";"Barracks";NA;160;0
"Building";"Barracks";NA;160;0
"Building";"Barracks";NA;160;0
"Unit";"Marine";"Barracks";178;1
"Unit";"Marine";"Barracks";178;1
"Unit";"Marine";"Barracks";178;1
"Unit";"Marine";"Barracks";178;1
"Unit";"Marine";"Barracks";178;1
"Unit";"Marine";"Barracks";178;1
"Unit";"Marine";"Barracks";181;1
"Unit";"Marine";"Barracks";181;1
"Unit";"Marine";"Barracks";181;1
"Unit";"Marine";"Barracks";181;1
"Unit";"Marine";"Barracks";181;1
"Unit";"Marine";"Barracks";181;1
"Unit";"Marine";"Barracks";181;1
"Unit";"Marine";"Barracks";182;1
