"type";"unit_name";"on_building";"total_supply";"supply"
"Building";"Refinery";NA;14;0
"Building";"Barracks";NA;15;0
"Unit";"Reaper";"Barracks";19;1
"Building";"Factory";NA;19;0
"Building";"Refinery";NA;21;0
"Building";"BarracksReactor";NA;20;0
"Building";"CommandCenter";NA;19;0
"Building";"BarracksTechLab";NA;23;0
"Unit";"Hellion";"Factory";23;2
"Unit";"Hellion";"Factory";23;2
"Building";"Starport";NA;23;0
"Unit";"Hellion";"Factory";24;2
"Unit";"Hellion";"Factory";26;2
"Unit";"Hellion";"Factory";34;2
"Unit";"Hellion";"Factory";34;2
"Building";"BarracksReactor";NA;35;0
"Building";"FactoryTechLab";NA;43;0
"Unit";"Marine";"Barracks";43;1
"Unit";"Marine";"Barracks";43;1
"Unit";"Liberator";"Starport";42;3
"Unit";"Marine";"Barracks";54;1
"Unit";"Marine";"Barracks";54;1
"Building";"CommandCenter";NA;43;0
"Building";"EngineeringBay";NA;54;0
"Building";"EngineeringBay";NA;54;0
"Unit";"Marine";"Barracks";58;1
"Unit";"Marine";"Barracks";58;1
"Building";"StarportReactor";NA;54;0
"Building";"Barracks";NA;54;0
"Building";"Barracks";NA;54;0
"Unit";"Marine";"Barracks";60;1
"Unit";"Marine";"Barracks";61;1
"Building";"Refinery";NA;64;0
"Unit";"Marine";"Barracks";65;1
"Unit";"Marine";"Barracks";66;1
"Unit";"Marine";"Barracks";67;1
"Unit";"Marine";"Barracks";67;1
"Unit";"Marine";"Barracks";68;1
"Building";"Refinery";NA;69;0
"Unit";"Marine";"Barracks";69;1
"Unit";"Marine";"Barracks";70;1
"Unit";"Marine";"Barracks";76;1
"Building";"Armory";NA;67;0
"Unit";"Marine";"Barracks";76;1
"Unit";"Marine";"Barracks";76;1
"Unit";"Marine";"Barracks";80;1
"Unit";"Marine";"Barracks";80;1
"Unit";"Marine";"Barracks";80;1
"Unit";"Marine";"Barracks";85;1
"Unit";"Marine";"Barracks";85;1
"Unit";"Marine";"Barracks";91;1
"Unit";"Marine";"Barracks";91;1
"Unit";"Medivac";"Starport";86;2
"Unit";"Medivac";"Starport";86;2
"Building";"Barracks";NA;80;0
"Building";"Barracks";NA;80;0
"Building";"MissileTurret";NA;97;0
"Building";"MissileTurret";NA;97;0
"Unit";"Marine";"Barracks";103;1
"Unit";"Marine";"Barracks";103;1
"Unit";"Marine";"Barracks";103;1
"Unit";"Marine";"Barracks";103;1
"Upgrade";"TerranInfantryWeaponsLevel1";"EngineeringBay";76;0
"Upgrade";"TerranInfantryArmorsLevel1";"EngineeringBay";76;0
"Unit";"Marine";"Barracks";103;1
"Upgrade";"Stimpack";"TechLab";79;0
"Unit";"Marine";"Barracks";106;1
"Unit";"Marine";"Barracks";106;1
"Unit";"Marine";"Barracks";110;1
"Unit";"Marine";"Barracks";110;1
"Building";"BarracksReactor";NA;103;0
"Building";"BarracksReactor";NA;103;0
"Building";"Refinery";NA;110;0
"Unit";"Marine";"Barracks";111;1
"Building";"Refinery";NA;110;0
"Unit";"Marine";"Barracks";114;1
"Unit";"Marine";"Barracks";116;1
"Unit";"Medivac";"Starport";111;2
"Unit";"Marine";"Barracks";116;1
"Unit";"Marine";"Barracks";117;1
"Building";"Factory";NA;110;0
"Unit";"Marine";"Barracks";119;1
"Unit";"Marine";"Barracks";119;1
"Unit";"Marine";"Barracks";119;1
"Upgrade";"TerranVehicleWeaponsLevel1";"Armory";97;0
"Unit";"Marine";"Barracks";120;1
"Unit";"Marine";"Barracks";120;1
"Unit";"Marine";"Barracks";120;1
"Unit";"Marine";"Barracks";120;1
"Unit";"Marine";"Barracks";123;1
"Unit";"Marine";"Barracks";124;1
"Unit";"Medivac";"Starport";119;2
"Building";"FactoryTechLab";NA;125;0
"Unit";"Marine";"Barracks";132;1
"Unit";"Marine";"Barracks";132;1
"Unit";"Marine";"Barracks";137;1
"Unit";"Marine";"Barracks";140;1
"Unit";"Marine";"Barracks";140;1
"Unit";"Marine";"Barracks";140;1
"Unit";"Marine";"Barracks";140;1
"Unit";"Marine";"Barracks";140;1
"Unit";"Marine";"Barracks";140;1
"Unit";"Marine";"Barracks";140;1
"Unit";"Marine";"Barracks";140;1
"Unit";"Marine";"Barracks";140;1
"Building";"CommandCenter";NA;125;0
"Unit";"Marine";"Barracks";140;1
"Unit";"Marine";"Barracks";141;1
"Unit";"Medivac";"Starport";140;2
"Unit";"Medivac";"Starport";140;2
"Unit";"Marine";"Barracks";148;1
"Unit";"Marine";"Barracks";149;1
"Unit";"Marine";"Barracks";149;1
"Unit";"Marine";"Barracks";149;1
"Unit";"Marine";"Barracks";149;1
"Upgrade";"TerranInfantryWeaponsLevel2";"EngineeringBay";120;0
"Unit";"Marine";"Barracks";151;1
"Unit";"Marine";"Barracks";151;1
"Unit";"Marine";"Barracks";151;1
"Unit";"Marine";"Barracks";151;1
"Unit";"Marine";"Barracks";160;1
"Unit";"Marine";"Barracks";160;1
"Building";"Barracks";NA;148;0
"Building";"Barracks";NA;149;0
"Unit";"Marine";"Barracks";164;1
"Unit";"Marine";"Barracks";164;1
"Unit";"Marine";"Barracks";164;1
"Unit";"Marine";"Barracks";164;1
"Unit";"Marine";"Barracks";164;1
"Building";"Barracks";NA;149;0
"Unit";"Marine";"Barracks";164;1
"Unit";"Marine";"Barracks";164;1
"Unit";"Marine";"Barracks";164;1
"Unit";"Marine";"Barracks";166;1
"Unit";"Marine";"Barracks";166;1
"Unit";"Marine";"Barracks";167;1
"Unit";"Marine";"Barracks";168;1
"Unit";"Marine";"Barracks";177;1
"Unit";"Marine";"Barracks";177;1
"Unit";"Marine";"Barracks";177;1
"Building";"BarracksTechLab";NA;177;0
"Building";"BarracksTechLab";NA;177;0
"Building";"BarracksTechLab";NA;177;0
"Unit";"Marine";"Barracks";177;1
"Unit";"Marine";"Barracks";177;1
"Unit";"Marine";"Barracks";177;1
"Upgrade";"TerranInfantryArmorsLevel2";"EngineeringBay";140;0
"Unit";"Thor";"Factory";166;6
"Unit";"Marine";"Barracks";179;1
"Unit";"Marine";"Barracks";180;1
"Unit";"Marine";"Barracks";182;1
"Unit";"Marine";"Barracks";182;1
"Unit";"Marine";"Barracks";183;1
"Unit";"Marine";"Barracks";184;1
"Unit";"Marine";"Barracks";187;1
"Unit";"Marine";"Barracks";187;1
"Unit";"Marine";"Barracks";187;1
"Unit";"Marine";"Barracks";187;1
"Unit";"Medivac";"Starport";182;2
"Unit";"Marauder";"Barracks";187;2
"Unit";"Medivac";"Starport";182;2
"Building";"Refinery";NA;197;0
"Unit";"Marine";"Barracks";204;1
"Unit";"Marine";"Barracks";204;1
"Unit";"Marine";"Barracks";204;1
"Unit";"Marine";"Barracks";204;1
"Unit";"Marine";"Barracks";204;1
"Unit";"Marauder";"Barracks";204;2
"Unit";"Marauder";"Barracks";204;2
"Unit";"Medivac";"Starport";204;2
"Unit";"Marine";"Barracks";210;1
"Building";"SensorTower";NA;211;0
