"Type";"UnitName";"OnBuilding";"TotalSupply";"Supply"
"Unit";"SCV";"Command Center";12;1
"Unit";"SCV";"Command Center";12;1
"Unit";"SCV";"Command Center";13;1
"Building";"SupplyDepot";NA;13;0
"Building";"Refinery";NA;14;0
"Unit";"SCV";"Command Center";15;1
"Unit";"SCV";"Command Center";15;1
"Unit";"SCV";"Command Center";17;1
"Unit";"SCV";"Command Center";17;1
"Building";"Barracks";NA;15;0
"Unit";"Reaper";"Barracks";19;1
"Unit";"SCV";"Command Center";19;1
"Unit";"SCV";"Command Center";21;1
"Building";"SupplyDepot";NA;20;0
"Building";"Factory";NA;19;0
"Unit";"SCV";"Command Center";21;1
"Building";"Refinery";NA;21;0
"Building";"BarracksReactor";NA;20;0
"Unit";"SCV";"Command Center";22;1
"Building";"CommandCenter";NA;19;0
"Unit";"SCV";"Command Center";23;1
"Building";"BarracksTechLab";NA;24;0
"Unit";"Hellion";"Factory";24;2
"Unit";"Hellion";"Factory";24;2
"Unit";"SCV";"Command Center";25;1
"Building";"Starport";NA;23;0
"Unit";"SCV";"Command Center";30;1
"Unit";"Hellion";"Factory";25;2
"Unit";"Hellion";"Factory";29;2
"Unit";"SCV";"Command Center";30;1
"Unit";"SCV";"Command Center";31;1
"Building";"SupplyDepot";NA;30;0
"Unit";"SCV";"Command Center";35;1
"Unit";"SCV";"Command Center";36;1
"Unit";"SCV";"Command Center";37;1
"Unit";"Hellion";"Factory";37;2
"Building";"BarracksTechLab";NA;38;0
"Building";"SupplyDepot";NA;38;0
"Unit";"SCV";"Command Center";40;1
"Unit";"SCV";"Command Center";40;1
"Unit";"SCV";"Command Center";42;1
"Unit";"SCV";"Command Center";44;1
"Unit";"SCV";"Command Center";44;1
"Building";"SupplyDepot";NA;44;0
"Unit";"SCV";"Command Center";46;1
"Building";"BarracksReactor";NA;42;0
"Unit";"SCV";"Command Center";46;1
"Unit";"Banshee";"Starport";42;3
"Unit";"SCV";"Command Center";48;1
"Unit";"SCV";"Command Center";49;1
"Building";"EngineeringBay";NA;47;0
"Building";"EngineeringBay";NA;48;0
"Unit";"Marine";"Barracks";49;1
"Unit";"Marine";"Barracks";49;1
"Unit";"SCV";"Command Center";53;1
"Unit";"SCV";"Command Center";53;1
"Unit";"SCV";"Command Center";57;1
"Building";"Refinery";NA;53;0
"Building";"CommandCenter";NA;44;0
"Building";"Barracks";NA;52;0
"Building";"Barracks";NA;53;0
"Unit";"Banshee";"Starport";56;3
"Unit";"Marine";"Barracks";59;1
"Unit";"Marine";"Barracks";59;1
"Building";"SupplyDepot";NA;59;0
"Building";"SupplyDepot";NA;59;0
"Building";"SupplyDepot";NA;59;0
"Unit";"SCV";"Command Center";59;1
"Unit";"SCV";"Command Center";59;1
"Unit";"Marine";"Barracks";64;1
"Unit";"Marine";"Barracks";64;1
"Unit";"Marine";"Barracks";64;1
"Unit";"Marine";"Barracks";64;1
"Building";"Refinery";NA;66;0
"Unit";"Marine";"Barracks";66;1
"Unit";"Marine";"Barracks";67;1
"Unit";"SCV";"Command Center";70;1
"Unit";"SCV";"Command Center";70;1
"Unit";"SCV";"Command Center";70;1
"Unit";"Marine";"Barracks";70;1
"Unit";"Marine";"Barracks";70;1
"Unit";"Marine";"Barracks";70;1
"Unit";"SCV";"Command Center";74;1
"Unit";"SCV";"Command Center";74;1
"Unit";"Marine";"Barracks";70;1
"Building";"Armory";NA;66;0
"Building";"StarportReactor";NA;70;0
"Unit";"SCV";"Command Center";78;1
"Building";"Barracks";NA;68;0
"Unit";"SCV";"Command Center";81;1
"Unit";"Marine";"Barracks";80;1
"Unit";"Marine";"Barracks";80;1
"Unit";"SCV";"Command Center";81;1
"Unit";"SCV";"Command Center";82;1
"Unit";"SCV";"Command Center";85;1
"Upgrade";"TerranInfantryWeaponsLevel1";"EngineeringBay";66;0
"Upgrade";"TerranInfantryArmorsLevel1";"EngineeringBay";66;0
"Unit";"Marine";"Barracks";86;1
"Unit";"Marine";"Barracks";86;1
"Unit";"Marine";"Barracks";86;1
"Building";"SupplyDepot";NA;85;0
"Unit";"Marine";"Barracks";86;1
"Unit";"Marine";"Barracks";86;1
"Building";"Barracks";NA;81;0
"Unit";"SCV";"Command Center";88;1
"Unit";"SCV";"Command Center";88;1
"Unit";"Marine";"Barracks";88;1
"Unit";"Marine";"Barracks";89;1
"Unit";"SCV";"Command Center";93;1
"Building";"BarracksReactor";NA;87;0
"Building";"MissileTurret";NA;93;0
"Building";"SupplyDepot";NA;93;0
"Building";"SupplyDepot";NA;93;0
"Unit";"Medivac";"Starport";88;2
"Unit";"Medivac";"Starport";88;2
"Building";"MissileTurret";NA;93;0
"Building";"Factory";NA;87;0
"Unit";"Marine";"Barracks";97;1
"Unit";"Marine";"Barracks";97;1
"Unit";"SCV";"Command Center";100;1
"Unit";"SCV";"Command Center";100;1
"Building";"MissileTurret";NA;98;0
"Building";"SupplyDepot";NA;102;0
"Building";"SupplyDepot";NA;102;0
"Building";"FactoryTechLab";NA;104;0
"Unit";"SCV";"Command Center";106;1
"Unit";"SCV";"Command Center";106;1
"Unit";"SCV";"Command Center";106;1
"Unit";"Marine";"Barracks";106;1
"Unit";"Marine";"Barracks";106;1
"Unit";"Marine";"Barracks";106;1
"Upgrade";"Stimpack";"TechLab";85;0
"Unit";"Marine";"Barracks";106;1
"Unit";"Marine";"Barracks";106;1
"Unit";"Marine";"Barracks";106;1
"Building";"MissileTurret";NA;106;0
"Building";"BarracksReactor";NA;102;0
"Unit";"Marine";"Barracks";106;1
"Unit";"Marine";"Barracks";109;1
"Unit";"Marine";"Barracks";110;1
"Building";"Refinery";NA;107;0
"Unit";"Marine";"Barracks";114;1
"Unit";"Marine";"Barracks";115;1
"Unit";"Marine";"Barracks";115;1
"Building";"SupplyDepot";NA;107;0
"Building";"Refinery";NA;107;0
"Building";"SupplyDepot";NA;107;0
"Building";"SupplyDepot";NA;109;0
"Unit";"SCV";"Command Center";115;1
"Unit";"SCV";"Command Center";115;1
"Unit";"SCV";"Command Center";115;1
"Unit";"Marine";"Barracks";116;1
"Unit";"Marine";"Barracks";116;1
"Unit";"Marine";"Barracks";116;1
"Unit";"Marine";"Barracks";116;1
"Unit";"SCV";"Command Center";121;1
"Unit";"Marine";"Barracks";121;1
"Unit";"Marine";"Barracks";121;1
"Unit";"Marine";"Barracks";121;1
"Unit";"Marine";"Barracks";121;1
"Unit";"Marine";"Barracks";121;1
"Unit";"Marine";"Barracks";129;1
"Unit";"Marine";"Barracks";129;1
"Unit";"Marine";"Barracks";129;1
"Unit";"Marine";"Barracks";129;1
"Building";"SupplyDepot";NA;128;0
"Building";"SupplyDepot";NA;128;0
"Unit";"Marine";"Barracks";138;1
"Unit";"Marine";"Barracks";138;1
"Unit";"Marine";"Barracks";138;1
"Unit";"Marine";"Barracks";138;1
"Unit";"Marine";"Barracks";138;1
"Unit";"Medivac";"Starport";134;2
"Unit";"Medivac";"Starport";134;2
"Upgrade";"TerranInfantryWeaponsLevel2";"EngineeringBay";106;0
"Unit";"Marine";"Barracks";140;1
"Unit";"Marine";"Barracks";141;1
"Building";"SupplyDepot";NA;143;0
"Building";"SupplyDepot";NA;143;0
"Building";"MissileTurret";NA;147;0
"Building";"SupplyDepot";NA;143;0
"Unit";"Marine";"Barracks";147;1
"Unit";"Marine";"Barracks";147;1
"Unit";"Marine";"Barracks";147;1
"Unit";"Marine";"Barracks";147;1
"Unit";"Marine";"Barracks";149;1
"Unit";"Marine";"Barracks";149;1
"Unit";"Thor";"Factory";138;6
"Unit";"Marine";"Barracks";151;1
"Building";"CommandCenter";NA;138;0
"Unit";"Marine";"Barracks";162;1
"Unit";"Marine";"Barracks";162;1
"Unit";"Marine";"Barracks";162;1
"Unit";"Marine";"Barracks";162;1
"Unit";"Marine";"Barracks";162;1
"Unit";"Marine";"Barracks";162;1
"Unit";"Marine";"Barracks";162;1
"Unit";"Marine";"Barracks";162;1
"Unit";"Marine";"Barracks";162;1
"Upgrade";"TerranInfantryArmorsLevel2";"EngineeringBay";134;0
"Unit";"Thor";"Factory";151;6
"Building";"Barracks";NA;162;0
"Unit";"Marine";"Barracks";177;1
"Unit";"Marine";"Barracks";177;1
"Unit";"Marine";"Barracks";177;1
"Unit";"Marine";"Barracks";177;1
"Unit";"Marine";"Barracks";177;1
"Unit";"Marine";"Barracks";177;1
"Unit";"Marine";"Barracks";177;1
"Unit";"Marauder";"Barracks";177;2
"Unit";"Marine";"Barracks";177;1
"Unit";"Marine";"Barracks";177;1
"Unit";"Marine";"Barracks";180;1
"Unit";"Marine";"Barracks";180;1
"Unit";"Marine";"Barracks";180;1
"Unit";"Marine";"Barracks";180;1
"Unit";"Marine";"Barracks";186;1
"Unit";"Marine";"Barracks";186;1
"Unit";"Marine";"Barracks";186;1
"Building";"Barracks";NA;177;0
"Building";"Barracks";NA;177;0
"Upgrade";"TerranVehicleWeaponsLevel1";"Armory";177;0
"Building";"BarracksTechLab";NA;192;0
"Building";"BarracksTechLab";NA;195;0
"Building";"BarracksTechLab";NA;195;0
"Upgrade";"TerranInfantryWeaponsLevel3";"EngineeringBay";162;0
"Unit";"Thor";"Factory";192;6
"Unit";"Marine";"Barracks";195;1
"Unit";"Medivac";"Starport";195;2
"Unit";"Medivac";"Starport";195;2
"Unit";"Thor";"Factory";195;6
"Unit";"Marine";"Barracks";195;1
"Unit";"Marine";"Barracks";195;1
"Unit";"Marine";"Barracks";195;1
"Unit";"Marine";"Barracks";195;1
"Unit";"Marine";"Barracks";195;1
"Unit";"Marine";"Barracks";195;1
"Unit";"Marine";"Barracks";195;1
"Unit";"Marine";"Barracks";195;1
"Unit";"Marine";"Barracks";195;1
"Unit";"Marine";"Barracks";195;1
"Unit";"Marauder";"Barracks";195;2
"Building";"GhostAcademy";NA;195;0
"Unit";"Marine";"Barracks";224;1
"Unit";"Marine";"Barracks";224;1
"Unit";"Marine";"Barracks";224;1
"Unit";"Marine";"Barracks";224;1
"Unit";"Marine";"Barracks";224;1
"Unit";"Marine";"Barracks";224;1
"Unit";"Thor";"Factory";201;6
"Unit";"Marine";"Barracks";224;1
"Unit";"Marine";"Barracks";224;1
"Unit";"Ghost";"Barracks";224;2
"Unit";"Ghost";"Barracks";224;2
"Unit";"Ghost";"Barracks";224;2
"Unit";"Ghost";"Barracks";224;2
"Unit";"Marine";"Barracks";236;1
"Unit";"Marine";"Barracks";236;1
"Unit";"Marine";"Barracks";236;1
"Unit";"Marine";"Barracks";236;1
"Unit";"Marine";"Barracks";246;1
"Unit";"Marine";"Barracks";246;1
"Unit";"Marine";"Barracks";246;1
"Unit";"Marine";"Barracks";246;1
"Building";"Refinery";NA;238;0
"Building";"Refinery";NA;238;0
"Unit";"Ghost";"Barracks";238;2
"Unit";"Ghost";"Barracks";240;2
"Unit";"Ghost";"Barracks";242;2
"Unit";"Marine";"Barracks";254;1
"Unit";"Marine";"Barracks";254;1
"Unit";"Marine";"Barracks";254;1
"Unit";"Marine";"Barracks";254;1
"Unit";"Marine";"Barracks";254;1
"Unit";"Marine";"Barracks";254;1
"Unit";"Marauder";"Barracks";256;2
"Unit";"Marine";"Barracks";260;1
"Unit";"Marine";"Barracks";260;1
"Unit";"Marine";"Barracks";260;1
"Unit";"Marine";"Barracks";260;1
"Unit";"Marine";"Barracks";260;1
"Unit";"Marine";"Barracks";260;1
"Unit";"Marine";"Barracks";261;1
"Unit";"Marine";"Barracks";266;1
"Unit";"Marine";"Barracks";266;1
"Unit";"Marine";"Barracks";266;1
"Upgrade";"PersonalCloaking";"GhostAcademy";246;0
"Unit";"Marine";"Barracks";268;1
"Unit";"Medivac";"Starport";260;2
"Unit";"Marine";"Barracks";268;1
"Unit";"Marine";"Barracks";269;1
"Unit";"Marine";"Barracks";271;1
"Unit";"Marine";"Barracks";271;1
"Unit";"Ghost";"Barracks";266;2
"Unit";"Marine";"Barracks";273;1
"Building";"CommandCenter";NA;246;0
"Unit";"Marine";"Barracks";277;1
"Unit";"Marine";"Barracks";278;1
"Unit";"Marine";"Barracks";278;1
"Unit";"Marine";"Barracks";278;1
"Unit";"Marine";"Barracks";278;1
"Unit";"Marine";"Barracks";278;1
"Upgrade";"TerranInfantryArmorsLevel3";"EngineeringBay";224;0
"Unit";"Liberator";"Starport";266;3
"Unit";"Marauder";"Barracks";283;2
"Unit";"Marauder";"Barracks";284;2
"Unit";"Marine";"Barracks";293;1
"Unit";"Marine";"Barracks";293;1
"Unit";"Marine";"Barracks";297;1
"Unit";"Marine";"Barracks";297;1
"Unit";"Marine";"Barracks";297;1
"Unit";"Marine";"Barracks";299;1
"Unit";"Marine";"Barracks";299;1
"Unit";"Liberator";"Starport";279;3
"Unit";"Marauder";"Barracks";297;2
"Unit";"Marine";"Barracks";301;1
"Unit";"Marine";"Barracks";301;1
"Unit";"Marine";"Barracks";301;1
"Unit";"Medivac";"Starport";294;2
"Unit";"Marauder";"Barracks";301;2
"Unit";"SCV";"Command Center";311;1
"Unit";"SCV";"Command Center";311;1
"Unit";"Marine";"Barracks";303;1
"Unit";"Marine";"Barracks";303;1
"Unit";"Marine";"Barracks";320;1
"Unit";"Marine";"Barracks";320;1
"Unit";"Medivac";"Starport";308;2
"Building";"Starport";NA;311;0
"Building";"Starport";NA;311;0
"Unit";"Ghost";"Barracks";320;2
"Building";"FusionCore";NA;311;0
"Unit";"Marine";"Barracks";328;1
"Unit";"Marine";"Barracks";328;1
"Unit";"Marine";"Barracks";328;1
"Unit";"Marine";"Barracks";328;1
"Building";"StarportTechLab";NA;330;0
"Building";"MissileTurret";NA;330;0
"Building";"MissileTurret";NA;330;0
"Building";"MissileTurret";NA;330;0
"Unit";"Ghost";"Barracks";328;2
"Unit";"Ghost";"Barracks";328;2
"Unit";"Marine";"Barracks";330;1
"Unit";"Marine";"Barracks";330;1
"Unit";"Marine";"Barracks";330;1
"Unit";"Marauder";"Barracks";330;2
"Unit";"Marauder";"Barracks";330;2
"Building";"StarportReactor";NA;330;0
"Unit";"Marine";"Barracks";338;1
"Unit";"Marine";"Barracks";338;1
"Unit";"Ghost";"Barracks";338;2
"Unit";"Ghost";"Barracks";338;2
"Unit";"Marine";"Barracks";345;1
"Unit";"Marine";"Barracks";345;1
"Unit";"Marine";"Barracks";345;1
"Unit";"Ghost";"Barracks";345;2
"Unit";"Marine";"Barracks";354;1
"Unit";"Marine";"Barracks";354;1
"Unit";"Ghost";"Barracks";354;2
"Unit";"Ghost";"Barracks";354;2
"Upgrade";"TerranShipWeaponsLevel1";"Armory";330;0
"Unit";"Marine";"Barracks";362;1
"Unit";"Marine";"Barracks";362;1
"Unit";"Marine";"Barracks";362;1
"Unit";"Marine";"Barracks";362;1
"Unit";"Marine";"Barracks";362;1
"Unit";"Marine";"Barracks";362;1
"Unit";"Ghost";"Barracks";362;2
"Unit";"Ghost";"Barracks";362;2
"Unit";"Ghost";"Barracks";362;2
"Unit";"Marine";"Barracks";362;1
"Unit";"Marine";"Barracks";362;1
"Unit";"Ghost";"Barracks";362;2
"Unit";"Marine";"Barracks";366;1
"Unit";"Marine";"Barracks";366;1
"Unit";"Marine";"Barracks";366;1
"Unit";"Marine";"Barracks";374;1
"Unit";"Marine";"Barracks";374;1
"Building";"Refinery";NA;374;0
"Building";"Refinery";NA;376;0
"Unit";"Ghost";"Barracks";368;2
"Building";"MissileTurret";NA;378;0
"Unit";"Ghost";"Barracks";374;2
"Building";"MissileTurret";NA;378;0
"Building";"MissileTurret";NA;381;0
"Building";"MissileTurret";NA;381;0
"Building";"MissileTurret";NA;381;0
"Unit";"Marine";"Barracks";382;1
"Unit";"Marine";"Barracks";383;1
"Unit";"Marine";"Barracks";383;1
"Unit";"Marine";"Barracks";383;1
"Unit";"Marine";"Barracks";383;1
"Unit";"Marine";"Barracks";383;1
"Unit";"Marauder";"Barracks";382;2
"Unit";"Marauder";"Barracks";383;2
"Unit";"Marauder";"Barracks";383;2
