"type";"unit_name";"on_building";"total_supply";"supply"
"Building";"Refinery";NA;15;0
"Building";"Barracks";NA;15;0
"Unit";"Reaper";"Barracks";19;1
"Unit";"Marine";"Barracks";20;1
"Building";"Refinery";NA;23;0
"Building";"CommandCenter";NA;19;0
"Building";"BarracksReactor";NA;23;0
"Building";"Factory";NA;23;0
"Building";"BarracksTechLab";NA;27;0
"Unit";"Hellion";"Factory";27;2
"Unit";"Hellion";"Factory";27;2
"Building";"Starport";NA;26;0
"Unit";"Marine";"Barracks";28;1
"Unit";"Hellion";"Factory";34;2
"Unit";"Hellion";"Factory";34;2
"Unit";"Marine";"Barracks";37;1
"Unit";"Hellion";"Factory";42;2
"Unit";"Hellion";"Factory";43;2
"Unit";"Marine";"Barracks";45;1
"Unit";"Marine";"Barracks";54;1
"Unit";"Liberator";"Starport";45;3
"Building";"FactoryReactor";NA;56;0
"Unit";"Marine";"Barracks";62;1
"Building";"Barracks";NA;56;0
"Building";"Refinery";NA;62;0
"Building";"Barracks";NA;56;0
"Building";"Refinery";NA;62;0
"Building";"EngineeringBay";NA;62;0
"Building";"EngineeringBay";NA;62;0
"Building";"CommandCenter";NA;52;0
"Upgrade";"Stimpack";"TechLab";47;0
"Unit";"Marine";"Barracks";66;1
"Building";"FactoryTechLab";NA;67;0
"Building";"StarportReactor";NA;64;0
"Unit";"Marine";"Barracks";67;1
"Unit";"Marine";"Barracks";67;1
"Unit";"Marine";"Barracks";68;1
"Unit";"Marine";"Barracks";68;1
"Building";"Barracks";NA;66;0
"Building";"Barracks";NA;66;0
"Unit";"Marine";"Barracks";76;1
"Unit";"Marine";"Barracks";76;1
"Unit";"Marine";"Barracks";76;1
"Unit";"Marine";"Barracks";76;1
"Unit";"Medivac";"Starport";73;2
"Unit";"Medivac";"Starport";74;2
"Unit";"Marine";"Barracks";78;1
"Unit";"Marine";"Barracks";78;1
"Unit";"Marine";"Barracks";79;1
"Unit";"Marine";"Barracks";86;1
"Unit";"Marine";"Barracks";86;1
"Unit";"Marine";"Barracks";88;1
"Unit";"Medivac";"Starport";86;2
"Unit";"Medivac";"Starport";86;2
"Building";"BarracksReactor";NA;79;0
"Building";"BarracksReactor";NA;80;0
"Building";"Bunker";NA;86;0
"Unit";"Marine";"Barracks";98;1
"Unit";"Marine";"Barracks";98;1
"Unit";"Marine";"Barracks";98;1
"Unit";"Marine";"Barracks";98;1
"Unit";"Marine";"Barracks";98;1
"Unit";"Marine";"Barracks";98;1
"Unit";"Marine";"Barracks";98;1
"Unit";"Marine";"Barracks";98;1
"Unit";"Marine";"Barracks";98;1
"Unit";"Medivac";"Starport";98;2
"Unit";"Medivac";"Starport";98;2
"Unit";"Marine";"Barracks";101;1
"Building";"Refinery";NA;101;0
"Unit";"Marine";"Barracks";110;1
"Building";"Refinery";NA;110;0
"Unit";"Marine";"Barracks";110;1
"Unit";"Marine";"Barracks";110;1
"Upgrade";"TerranInfantryWeaponsLevel1";"EngineeringBay";78;0
"Unit";"Marine";"Barracks";110;1
"Upgrade";"TerranInfantryArmorsLevel1";"EngineeringBay";79;0
"Unit";"Marine";"Barracks";117;1
"Unit";"Marine";"Barracks";117;1
"Unit";"Marine";"Barracks";117;1
"Unit";"Marine";"Barracks";118;1
"Unit";"Marine";"Barracks";118;1
"Unit";"Medivac";"Starport";118;2
"Unit";"Medivac";"Starport";118;2
"Unit";"Marine";"Barracks";131;1
"Unit";"Marine";"Barracks";131;1
"Building";"Armory";NA;113;0
"Unit";"Marine";"Barracks";133;1
"Unit";"Marine";"Barracks";133;1
"Unit";"Marine";"Barracks";133;1
"Building";"CommandCenter";NA;101;0
"Unit";"Marine";"Barracks";138;1
"Unit";"Marine";"Barracks";138;1
"Unit";"Marine";"Barracks";145;1
"Unit";"Marine";"Barracks";145;1
"Building";"Barracks";NA;133;0
"Building";"Factory";NA;138;0
"Building";"Barracks";NA;134;0
"Unit";"Marine";"Barracks";147;1
"Unit";"Marine";"Barracks";147;1
"Unit";"Marine";"Barracks";147;1
"Unit";"Marine";"Barracks";147;1
"Unit";"Marine";"Barracks";147;1
"Unit";"Marine";"Barracks";147;1
"Unit";"Marine";"Barracks";147;1
"Unit";"Marine";"Barracks";147;1
"Unit";"Marine";"Barracks";154;1
"Unit";"Marine";"Barracks";157;1
"Unit";"Marine";"Barracks";158;1
"Building";"BarracksTechLab";NA;159;0
"Building";"FactoryTechLab";NA;159;0
"Building";"BarracksTechLab";NA;159;0
"Unit";"Marine";"Barracks";159;1
"Unit";"Marine";"Barracks";159;1
"Unit";"Marine";"Barracks";159;1
"Unit";"Marine";"Barracks";159;1
"Unit";"Marine";"Barracks";159;1
"Building";"Refinery";NA;159;0
"Building";"Refinery";NA;159;0
"Unit";"Marine";"Barracks";159;1
"Unit";"Marine";"Barracks";160;1
"Unit";"Marine";"Barracks";162;1
"Unit";"Marine";"Barracks";163;1
"Unit";"Marine";"Barracks";163;1
"Unit";"Marine";"Barracks";163;1
"Unit";"Medivac";"Starport";163;2
"Unit";"Medivac";"Starport";163;2
"Unit";"Marine";"Barracks";173;1
"Unit";"Marine";"Barracks";174;1
"Unit";"Marine";"Barracks";174;1
"Unit";"Marine";"Barracks";174;1
"Unit";"Marine";"Barracks";174;1
"Unit";"Marine";"Barracks";174;1
"Unit";"Marauder";"Barracks";172;2
"Unit";"Marauder";"Barracks";176;2
"Unit";"Marauder";"Barracks";176;2
"Unit";"Marine";"Barracks";188;1
"Unit";"Marauder";"Barracks";188;2
"Unit";"Marine";"Barracks";188;1
"Upgrade";"TerranInfantryWeaponsLevel2";"EngineeringBay";159;0
"Upgrade";"TerranInfantryArmorsLevel2";"EngineeringBay";159;0
"Building";"SensorTower";NA;196;0
"Unit";"Marauder";"Barracks";194;2
"Unit";"Marauder";"Barracks";198;2
"Unit";"Marauder";"Barracks";198;2
"Unit";"Marine";"Barracks";198;1
"Unit";"Marine";"Barracks";198;1
"Unit";"Marine";"Barracks";198;1
"Unit";"Marine";"Barracks";198;1
"Unit";"Marine";"Barracks";198;1
"Unit";"Marine";"Barracks";198;1
"Unit";"Marine";"Barracks";198;1
"Unit";"Marauder";"Barracks";198;2
"Building";"Starport";NA;197;0
"Building";"Starport";NA;198;0
"Unit";"Marauder";"Barracks";200;2
"Building";"FusionCore";NA;198;0
"Unit";"Marauder";"Barracks";213;2
"Unit";"Marauder";"Barracks";213;2
"Unit";"Marine";"Barracks";213;1
"Unit";"Marine";"Barracks";213;1
"Unit";"Marine";"Barracks";213;1
"Unit";"Marine";"Barracks";213;1
"Unit";"Marine";"Barracks";213;1
"Unit";"Marine";"Barracks";213;1
"Unit";"Marine";"Barracks";213;1
"Unit";"Marine";"Barracks";213;1
"Unit";"Marauder";"Barracks";213;2
"Building";"StarportTechLab";NA;215;0
"Unit";"Marine";"Barracks";215;1
"Building";"StarportReactor";NA;215;0
"Unit";"Marine";"Barracks";229;1
"Unit";"Marine";"Barracks";230;1
"Unit";"Marine";"Barracks";230;1
"Unit";"Marine";"Barracks";230;1
"Unit";"Marine";"Barracks";230;1
"Unit";"Marine";"Barracks";230;1
"Unit";"Marine";"Barracks";230;1
"Unit";"Marine";"Barracks";230;1
"Unit";"Marine";"Barracks";230;1
"Unit";"Marauder";"Barracks";229;2
"Unit";"Marine";"Barracks";241;1
"Unit";"Marine";"Barracks";241;1
"Unit";"Liberator";"Starport";230;3
"Unit";"Liberator";"Starport";230;3
"Unit";"Liberator";"Starport";230;3
"Unit";"Marauder";"Barracks";241;2
"Unit";"Marauder";"Barracks";241;2
"Unit";"Marauder";"Barracks";241;2
"Unit";"Marine";"Barracks";241;1
"Unit";"Marine";"Barracks";241;1
"Unit";"Marine";"Barracks";241;1
"Unit";"Marine";"Barracks";241;1
"Unit";"Marauder";"Barracks";252;2
"Unit";"Marine";"Barracks";262;1
"Unit";"Marine";"Barracks";262;1
"Unit";"Marine";"Barracks";262;1
"Unit";"Marine";"Barracks";262;1
"Unit";"Marine";"Barracks";262;1
"Unit";"Marine";"Barracks";262;1
"Unit";"Marine";"Barracks";262;1
"Unit";"Marine";"Barracks";262;1
