"Type";"UnitName";"OnBuilding";"TotalSupply";"Supply"
"Unit";"SCV";"Command Center";12;1
"Unit";"SCV";"Command Center";12;1
"Unit";"SCV";"Command Center";13;1
"Building";"SupplyDepot";NA;13;0
"Building";"Refinery";NA;14;0
"Unit";"SCV";"Command Center";15;1
"Unit";"SCV";"Command Center";15;1
"Unit";"SCV";"Command Center";16;1
"Unit";"SCV";"Command Center";17;1
"Building";"Barracks";NA;15;0
"Unit";"SCV";"Command Center";18;1
"Unit";"Reaper";"Barracks";19;1
"Unit";"SCV";"Command Center";21;1
"Unit";"SCV";"Command Center";21;1
"Building";"SupplyDepot";NA;21;0
"Building";"BarracksReactor";NA;21;0
"Building";"Factory";NA;20;0
"Unit";"SCV";"Command Center";23;1
"Unit";"SCV";"Command Center";23;1
"Building";"CommandCenter";NA;20;0
"Building";"Refinery";NA;23;0
"Unit";"Hellion";"Factory";24;2
"Unit";"Hellion";"Factory";24;2
"Unit";"SCV";"Command Center";25;1
"Building";"BarracksTechLab";NA;25;0
"Unit";"SCV";"Command Center";30;1
"Unit";"Hellion";"Factory";30;2
"Unit";"Hellion";"Factory";30;2
"Building";"Factory";NA;24;0
"Unit";"SCV";"Command Center";30;1
"Unit";"SCV";"Command Center";35;1
"Unit";"SCV";"Command Center";36;1
"Unit";"SCV";"Command Center";36;1
"Unit";"Hellion";"Factory";36;2
"Unit";"Hellion";"Factory";36;2
"Unit";"Hellion";"Factory";36;2
"Unit";"Marine";"Barracks";37;1
"Building";"SupplyDepot";NA;39;0
"Building";"SupplyDepot";NA;45;0
"Unit";"SCV";"Command Center";46;1
"Unit";"SCV";"Command Center";46;1
"Unit";"Hellion";"Factory";46;2
"Unit";"Hellion";"Factory";46;2
"Unit";"SCV";"Command Center";46;1
"Unit";"SCV";"Command Center";46;1
"Unit";"Hellion";"Factory";46;2
"Unit";"SCV";"Command Center";52;1
"Unit";"SCV";"Command Center";56;1
"Unit";"Hellion";"Factory";48;2
"Unit";"Hellion";"Factory";50;2
"Unit";"SCV";"Command Center";56;1
"Unit";"Hellion";"Factory";54;2
"Unit";"SCV";"Command Center";63;1
"Unit";"Hellion";"Factory";58;2
"Building";"SupplyDepot";NA;62;0
"Unit";"Hellion";"Factory";63;2
"Unit";"SCV";"Command Center";66;1
"Building";"SupplyDepot";NA;65;0
"Unit";"Hellion";"Factory";65;2
"Building";"Factory";NA;62;0
"Unit";"Hellion";"Factory";68;2
"Building";"Factory";NA;62;0
"Unit";"Hellion";"Factory";71;2
"Unit";"SCV";"Command Center";75;1
"Unit";"Hellion";"Factory";71;2
"Unit";"Hellion";"Factory";73;2
"Building";"CommandCenter";NA;57;0
"Unit";"SCV";"Command Center";75;1
"Unit";"SCV";"Command Center";80;1
"Unit";"Hellion";"Factory";75;2
"Unit";"Hellion";"Factory";80;2
"Unit";"Hellion";"Factory";80;2
"Unit";"SCV";"Command Center";83;1
"Unit";"Hellion";"Factory";80;2
"Unit";"Hellion";"Factory";80;2
"Building";"Refinery";NA;83;0
"Building";"Refinery";NA;83;0
"Unit";"SCV";"Command Center";91;1
"Unit";"SCV";"Command Center";91;1
"Building";"FactoryTechLab";NA;91;0
"Building";"FactoryTechLab";NA;91;0
"Unit";"SCV";"Command Center";95;1
"Unit";"SCV";"Command Center";96;1
"Unit";"Hellion";"Factory";95;2
"Unit";"Hellion";"Factory";95;2
"Building";"Armory";NA;83;0
"Unit";"SCV";"Command Center";99;1
"Unit";"SCV";"Command Center";99;1
"Unit";"SCV";"Command Center";103;1
"Unit";"SCV";"Command Center";105;1
"Unit";"SCV";"Command Center";105;1
"Unit";"Hellion";"Factory";105;2
"Unit";"Hellion";"Factory";105;2
"Unit";"SCV";"Command Center";106;1
"Unit";"SCV";"Command Center";107;1
"Unit";"SCV";"Command Center";112;1
"Unit";"SCV";"Command Center";113;1
"Unit";"SCV";"Command Center";113;1
"Unit";"Hellion";"Factory";108;2
"Unit";"Hellion";"Factory";110;2
"Building";"Refinery";NA;113;0
"Unit";"SCV";"Command Center";114;1
"Building";"Armory";NA;105;0
"Unit";"SCV";"Command Center";116;1
"Unit";"Hellion";"Factory";114;2
"Unit";"SCV";"Command Center";121;1
"Unit";"SCV";"Command Center";123;1
"Building";"SupplyDepot";NA;122;0
"Building";"SupplyDepot";NA;122;0
"Unit";"Hellion";"Factory";125;2
"Unit";"Hellion";"Factory";125;2
"Unit";"SCV";"Command Center";127;1
"Unit";"Hellion";"Factory";126;2
"Unit";"SCV";"Command Center";127;1
"Building";"Factory";NA;121;0
"Unit";"Hellion";"Factory";127;2
"Building";"Factory";NA;122;0
"Unit";"SCV";"Command Center";131;1
"Unit";"SCV";"Command Center";134;1
"Unit";"Hellion";"Factory";132;2
"Unit";"Hellion";"Factory";132;2
"Unit";"SCV";"Command Center";138;1
"Building";"Refinery";NA;135;0
"Building";"Refinery";NA;137;0
"Upgrade";"TerranVehicleWeaponsLevel1";"Armory";114;0
"Unit";"SCV";"Command Center";139;1
"Building";"CommandCenter";NA;113;0
"Building";"EngineeringBay";NA;138;0
"Unit";"Thor";"Factory";132;6
"Unit";"Hellion";"Factory";143;2
"Unit";"Hellion";"Factory";143;2
"Unit";"Hellion";"Factory";144;2
"Unit";"SCV";"Command Center";145;1
"Unit";"SCV";"Command Center";145;1
"Unit";"Hellion";"Factory";144;2
"Building";"SupplyDepot";NA;145;0
"Building";"SupplyDepot";NA;145;0
"Unit";"SCV";"Command Center";157;1
"Building";"FactoryTechLab";NA;153;0
"Building";"SupplyDepot";NA;145;0
"Building";"FactoryTechLab";NA;155;0
"Unit";"SCV";"Command Center";162;1
"Unit";"Hellion";"Factory";161;2
"Building";"MissileTurret";NA;162;0
"Building";"SensorTower";NA;162;0
"Building";"MissileTurret";NA;162;0
"Building";"MissileTurret";NA;162;0
"Unit";"SCV";"Command Center";165;1
"Building";"MissileTurret";NA;163;0
"Building";"MissileTurret";NA;165;0
"Building";"MissileTurret";NA;165;0
"Unit";"SCV";"Command Center";166;1
"Unit";"SCV";"Command Center";166;1
"Unit";"Thor";"Factory";163;6
"Unit";"SCV";"Command Center";166;1
"Unit";"SCV";"Command Center";166;1
"Unit";"Cyclone";"Factory";166;3
"Unit";"SCV";"Command Center";175;1
"Building";"MissileTurret";NA;174;0
"Building";"MissileTurret";NA;174;0
"Building";"Refinery";NA;168;0
"Building";"Refinery";NA;174;0
"Building";"MissileTurret";NA;175;0
"Unit";"SCV";"Command Center";176;1
"Building";"SupplyDepot";NA;175;0
"Unit";"SCV";"Command Center";176;1
"Building";"SupplyDepot";NA;175;0
"Building";"SupplyDepot";NA;175;0
"Building";"MissileTurret";NA;176;0
"Unit";"SCV";"Command Center";180;1
"Upgrade";"TerranVehicleAndShipArmorsLevel1";"Armory";162;0
"Unit";"SCV";"Command Center";181;1
"Building";"MissileTurret";NA;180;0
"Unit";"Cyclone";"Factory";180;3
"Unit";"SCV";"Command Center";183;1
"Unit";"SCV";"Command Center";184;1
"Upgrade";"TerranVehicleWeaponsLevel2";"Armory";163;0
"Unit";"Hellion";"Factory";184;2
"Unit";"Hellion";"Factory";184;2
"Unit";"SCV";"Command Center";193;1
"Unit";"Thor";"Factory";183;6
"Unit";"Hellion";"Factory";189;2
"Unit";"Hellion";"Factory";191;2
"Unit";"Hellion";"Factory";193;2
"Unit";"SCV";"Command Center";204;1
"Unit";"Thor";"Factory";189;6
"Unit";"Hellion";"Factory";200;2
"Building";"CommandCenter";NA;183;0
"Unit";"Hellion";"Factory";204;2
"Unit";"Hellion";"Factory";206;2
"Unit";"Hellion";"Factory";207;2
"Unit";"Hellion";"Factory";213;2
"Building";"Starport";NA;206;0
"Building";"Starport";NA;206;0
"Unit";"Hellion";"Factory";215;2
"Unit";"Hellion";"Factory";219;2
"Unit";"Hellion";"Factory";219;2
"Unit";"Hellion";"Factory";221;2
"Unit";"SCV";"Command Center";225;1
"Unit";"Hellion";"Factory";229;2
"Unit";"Hellion";"Factory";231;2
"Unit";"SCV";"Command Center";232;1
"Building";"StarportReactor";NA;227;0
"Building";"StarportReactor";NA;227;0
"Unit";"Thor";"Factory";225;6
"Unit";"SCV";"Command Center";236;1
"Unit";"Hellion";"Factory";232;2
"Unit";"Hellion";"Factory";234;2
"Unit";"Hellion";"Factory";236;2
"Unit";"SCV";"Command Center";243;1
"Unit";"SCV";"Command Center";244;1
"Unit";"SCV";"Command Center";244;1
"Unit";"Hellion";"Factory";237;2
"Unit";"SCV";"Command Center";248;1
"Unit";"Hellion";"Factory";244;2
"Unit";"Hellion";"Factory";246;2
"Building";"CommandCenter";NA;227;0
"Unit";"Hellion";"Factory";248;2
"Unit";"SCV";"Command Center";255;1
"Building";"Refinery";NA;255;0
"Building";"Refinery";NA;255;0
"Upgrade";"TerranVehicleAndShipArmorsLevel2";"Armory";223;0
"Unit";"Liberator";"Starport";244;3
"Unit";"Liberator";"Starport";244;3
"Unit";"Liberator";"Starport";244;3
"Unit";"Hellion";"Factory";256;2
"Unit";"Hellion";"Factory";258;2
"Unit";"SCV";"Command Center";263;1
"Unit";"Thor";"Factory";253;6
"Unit";"SCV";"Command Center";274;1
"Unit";"Hellion";"Factory";263;2
"Unit";"Hellion";"Factory";263;2
"Upgrade";"TerranVehicleWeaponsLevel3";"Armory";223;0
"Unit";"Liberator";"Starport";255;3
"Building";"MissileTurret";NA;276;0
"Unit";"Hellion";"Factory";272;2
"Unit";"SCV";"Command Center";291;1
"Unit";"SCV";"Command Center";293;1
"Unit";"Hellion";"Factory";288;2
"Unit";"Liberator";"Starport";263;3
"Unit";"Liberator";"Starport";266;3
"Unit";"Liberator";"Starport";269;3
