"type";"unit_name";"on_building";"total_supply";"supply"
"Building";"Refinery";NA;15;0
"Building";"Barracks";NA;15;0
"Unit";"Reaper";"Barracks";19;1
"Building";"Refinery";NA;19;0
"Building";"BarracksReactor";NA;21;0
"Building";"Factory";NA;21;0
"Building";"CommandCenter";NA;19;0
"Unit";"Hellion";"Factory";25;2
"Unit";"Hellion";"Factory";25;2
"Building";"Starport";NA;24;0
"Unit";"Hellion";"Factory";31;2
"Unit";"Hellion";"Factory";31;2
"Building";"Armory";NA;26;0
"Unit";"Hellion";"Factory";38;2
"Unit";"Hellion";"Factory";38;2
"Unit";"Liberator";"Starport";32;3
"Unit";"Hellion";"Factory";44;2
"Unit";"Hellion";"Factory";44;2
"Building";"Factory";NA;40;0
"Building";"Factory";NA;40;0
"Building";"Refinery";NA;49;0
"Building";"Refinery";NA;51;0
"Unit";"Hellion";"Factory";55;2
"Unit";"Hellion";"Factory";55;2
"Building";"FactoryTechLab";NA;55;0
"Unit";"Hellion";"Factory";61;2
"Unit";"Hellion";"Factory";61;2
"Unit";"Hellion";"Factory";61;2
"Building";"FactoryReactor";NA;57;0
"Unit";"Hellion";"Factory";63;2
"Unit";"Hellion";"Factory";71;2
"Unit";"Hellion";"Factory";71;2
"Upgrade";"TerranVehicleWeaponsLevel1";"Armory";55;0
"Unit";"Hellion";"Factory";71;2
"Unit";"Hellion";"Factory";75;2
"Unit";"Hellion";"Factory";75;2
"Building";"CommandCenter";NA;69;0
"Unit";"Cyclone";"Factory";89;3
"Unit";"Cyclone";"Factory";89;3
"Unit";"Cyclone";"Factory";89;3
"Unit";"Cyclone";"Factory";91;3
"Unit";"Cyclone";"Factory";102;3
"Building";"Factory";NA;100;0
"Building";"Factory";NA;102;0
"Building";"StarportReactor";NA;102;0
"Building";"Refinery";NA;108;0
"Building";"Refinery";NA;111;0
"Unit";"Cyclone";"Factory";111;3
"Unit";"Cyclone";"Factory";111;3
"Unit";"Cyclone";"Factory";111;3
"Building";"FactoryTechLab";NA;118;0
"Building";"FactoryTechLab";NA;118;0
"Building";"Refinery";NA;124;0
"Building";"Factory";NA;114;0
"Building";"Refinery";NA;124;0
"Building";"Factory";NA;118;0
"Building";"FactoryTechLab";NA;127;0
"Building";"FactoryTechLab";NA;127;0
"Building";"CommandCenter";NA;120;0
"Building";"Starport";NA;127;0
"Building";"Starport";NA;127;0
"Building";"FusionCore";NA;128;0
"Unit";"Hellion";"Factory";128;2
"Building";"StarportTechLab";NA;128;0
"Upgrade";"TerranVehicleWeaponsLevel2";"Armory";127;0
"Building";"StarportReactor";NA;128;0
"Unit";"Hellion";"Factory";134;2
"Unit";"Hellion";"Factory";134;2
"Building";"Refinery";NA;140;0
"Building";"Refinery";NA;140;0
"Building";"CommandCenter";NA;141;0
"Unit";"Hellion";"Factory";141;2
"Unit";"Hellion";"Factory";141;2
"Unit";"Hellion";"Factory";141;2
"Unit";"Hellion";"Factory";141;2
"Unit";"Hellion";"Factory";141;2
"Unit";"Hellion";"Factory";141;2
"Unit";"Hellion";"Factory";141;2
"Unit";"Hellion";"Factory";151;2
"Unit";"Hellion";"Factory";155;2
"Unit";"Hellion";"Factory";155;2
"Unit";"Hellion";"Factory";155;2
"Unit";"Hellion";"Factory";155;2
"Upgrade";"TerranShipWeaponsLevel1";"Armory";141;0
"Unit";"Hellion";"Factory";161;2
"Unit";"Hellion";"Factory";161;2
"Unit";"Hellion";"Factory";165;2
"Unit";"Hellion";"Factory";165;2
"Building";"Starport";NA;173;0
"Building";"Starport";NA;173;0
"Building";"Starport";NA;173;0
"Building";"Refinery";NA;173;0
"Unit";"Hellion";"Factory";176;2
"Unit";"Hellion";"Factory";176;2
"Unit";"Hellion";"Factory";176;2
"Unit";"Hellion";"Factory";176;2
"Unit";"Hellion";"Factory";176;2
"Unit";"Hellion";"Factory";176;2
"Building";"CommandCenter";NA;173;0
"Unit";"Hellion";"Factory";176;2
"Unit";"Hellion";"Factory";176;2
"Unit";"Hellion";"Factory";188;2
"Unit";"Hellion";"Factory";188;2
"Building";"Refinery";NA;192;0
"Unit";"Hellion";"Factory";192;2
"Unit";"Hellion";"Factory";192;2
"Unit";"Hellion";"Factory";192;2
"Unit";"Hellion";"Factory";196;2
"Building";"StarportReactor";NA;196;0
"Building";"StarportReactor";NA;196;0
"Unit";"Hellion";"Factory";204;2
"Unit";"Hellion";"Factory";204;2
"Unit";"Hellion";"Factory";204;2
"Unit";"Hellion";"Factory";204;2
"Unit";"Hellion";"Factory";204;2
"Unit";"Hellion";"Factory";204;2
"Unit";"Hellion";"Factory";204;2
"Unit";"Hellion";"Factory";204;2
"Unit";"Hellion";"Factory";210;2
"Unit";"Hellion";"Factory";210;2
"Unit";"Hellion";"Factory";210;2
"Unit";"Hellion";"Factory";210;2
"Unit";"Hellion";"Factory";210;2
"Unit";"Hellion";"Factory";220;2
"Unit";"Cyclone";"Factory";232;3
"Unit";"Cyclone";"Factory";232;3
