"Type";"UnitName";"OnBuilding";"TotalSupply";"Supply"
"Unit";"SCV";"Command Center";12;1
"Unit";"SCV";"Command Center";12;1
"Unit";"SCV";"Command Center";13;1
"Building";"SupplyDepot";NA;13;0
"Unit";"SCV";"Command Center";15;1
"Unit";"SCV";"Command Center";16;1
"Building";"Refinery";NA;15;0
"Unit";"SCV";"Command Center";16;1
"Building";"Barracks";NA;15;0
"Unit";"SCV";"Command Center";17;1
"Unit";"Reaper";"Barracks";19;1
"Unit";"SCV";"Command Center";19;1
"Building";"SupplyDepot";NA;19;0
"Unit";"Marine";"Barracks";20;1
"Unit";"SCV";"Command Center";20;1
"Unit";"SCV";"Command Center";22;1
"Building";"Refinery";NA;21;0
"Unit";"SCV";"Command Center";24;1
"Building";"CommandCenter";NA;19;0
"Building";"Factory";NA;21;0
"Building";"BarracksReactor";NA;22;0
"Unit";"SCV";"Command Center";24;1
"Unit";"SCV";"Command Center";25;1
"Building";"SupplyDepot";NA;25;0
"Building";"BarracksTechLab";NA;26;0
"Unit";"SCV";"Command Center";27;1
"Unit";"Hellion";"Factory";26;2
"Unit";"Hellion";"Factory";26;2
"Building";"Starport";NA;25;0
"Unit";"SCV";"Command Center";27;1
"Unit";"SCV";"Command Center";32;1
"Building";"SupplyDepot";NA;27;0
"Unit";"Hellion";"Factory";32;2
"Unit";"SCV";"Command Center";32;1
"Unit";"Hellion";"Factory";32;2
"Building";"BarracksTechLab";NA;33;0
"Unit";"SCV";"Command Center";39;1
"Unit";"SCV";"Command Center";39;1
"Unit";"Hellion";"Factory";39;2
"Unit";"Hellion";"Factory";39;2
"Unit";"SCV";"Command Center";39;1
"Unit";"SCV";"Command Center";40;1
"Building";"SupplyDepot";NA;39;0
"Unit";"Banshee";"Starport";34;3
"Unit";"SCV";"Command Center";47;1
"Unit";"SCV";"Command Center";47;1
"Unit";"SCV";"Command Center";52;1
"Unit";"Marine";"Barracks";50;1
"Unit";"SCV";"Command Center";52;1
"Unit";"Marine";"Barracks";50;1
"Unit";"SCV";"Command Center";52;1
"Unit";"SCV";"Command Center";54;1
"Unit";"Marine";"Barracks";53;1
"Unit";"Marine";"Barracks";56;1
"Unit";"Banshee";"Starport";50;3
"Unit";"SCV";"Command Center";56;1
"Unit";"SCV";"Command Center";57;1
"Building";"EngineeringBay";NA;56;0
"Building";"Refinery";NA;56;0
"Building";"Refinery";NA;56;0
"Building";"EngineeringBay";NA;56;0
"Building";"SupplyDepot";NA;59;0
"Building";"CommandCenter";NA;47;0
"Unit";"SCV";"Command Center";65;1
"Unit";"SCV";"Command Center";65;1
"Building";"StarportReactor";NA;65;0
"Unit";"Marine";"Barracks";65;1
"Unit";"Marine";"Barracks";65;1
"Unit";"SCV";"Command Center";65;1
"Unit";"SCV";"Command Center";66;1
"Building";"Barracks";NA;65;0
"Unit";"SCV";"Command Center";69;1
"Unit";"SCV";"Command Center";70;1
"Unit";"Marine";"Barracks";69;1
"Unit";"Marine";"Barracks";69;1
"Unit";"SCV";"Command Center";71;1
"Building";"Barracks";NA;65;0
"Unit";"SCV";"Command Center";75;1
"Building";"Barracks";NA;67;0
"Unit";"SCV";"Command Center";76;1
"Building";"Barracks";NA;67;0
"Building";"StarportReactor";NA;71;0
"Unit";"Marine";"Barracks";76;1
"Unit";"Marine";"Barracks";76;1
"Unit";"Marine";"Barracks";76;1
"Unit";"SCV";"Command Center";77;1
"Unit";"SCV";"Command Center";77;1
"Unit";"SCV";"Command Center";78;1
"Unit";"Marine";"Barracks";78;1
"Unit";"SCV";"Command Center";81;1
"Building";"SupplyDepot";NA;78;0
"Building";"SupplyDepot";NA;81;0
"Unit";"Marine";"Barracks";81;1
"Unit";"Marine";"Barracks";81;1
"Unit";"Marine";"Barracks";81;1
"Unit";"Marine";"Barracks";81;1
"Unit";"SCV";"Command Center";84;1
"Unit";"Medivac";"Starport";78;2
"Unit";"Medivac";"Starport";78;2
"Unit";"SCV";"Command Center";85;1
"Unit";"Marine";"Barracks";84;1
"Unit";"Marine";"Barracks";84;1
"Unit";"SCV";"Command Center";86;1
"Unit";"SCV";"Command Center";91;1
"Unit";"Marine";"Barracks";87;1
"Unit";"Marine";"Barracks";91;1
"Unit";"Marine";"Barracks";91;1
"Unit";"SCV";"Command Center";96;1
"Upgrade";"TerranInfantryWeaponsLevel1";"EngineeringBay";75;0
"Upgrade";"TerranInfantryArmorsLevel1";"EngineeringBay";75;0
"Unit";"Marine";"Barracks";99;1
"Unit";"Marine";"Barracks";99;1
"Unit";"Marine";"Barracks";99;1
"Unit";"Marine";"Barracks";99;1
"Unit";"Marine";"Barracks";104;1
"Unit";"Marine";"Barracks";104;1
"Building";"Armory";NA;86;0
"Unit";"Marine";"Barracks";104;1
"Unit";"SCV";"Command Center";110;1
"Unit";"SCV";"Command Center";110;1
"Unit";"Marine";"Barracks";110;1
"Unit";"Marine";"Barracks";110;1
"Unit";"Marine";"Barracks";110;1
"Unit";"Marine";"Barracks";110;1
"Unit";"Liberator";"Starport";104;3
"Unit";"Marine";"Barracks";110;1
"Building";"SupplyDepot";NA;110;0
"Unit";"SCV";"Command Center";111;1
"Unit";"SCV";"Command Center";112;1
"Unit";"Liberator";"Starport";104;3
"Building";"BarracksReactor";NA;108;0
"Building";"BarracksReactor";NA;108;0
"Unit";"Marine";"Barracks";117;1
"Unit";"Marine";"Barracks";117;1
"Unit";"Marine";"Barracks";117;1
"Unit";"SCV";"Command Center";121;1
"Unit";"SCV";"Command Center";122;1
"Building";"SupplyDepot";NA;117;0
"Building";"SupplyDepot";NA;117;0
"Unit";"Marine";"Barracks";123;1
"Unit";"Marine";"Barracks";123;1
"Unit";"SCV";"Command Center";129;1
"Unit";"Marine";"Barracks";131;1
"Unit";"Marine";"Barracks";131;1
"Unit";"Marine";"Barracks";131;1
"Unit";"Marine";"Barracks";131;1
"Unit";"Marine";"Barracks";131;1
"Unit";"Marine";"Barracks";131;1
"Unit";"Marine";"Barracks";131;1
"Unit";"Marine";"Barracks";131;1
"Unit";"SCV";"Command Center";134;1
"Unit";"SCV";"Command Center";134;1
"Unit";"SCV";"Command Center";134;1
"Upgrade";"Stimpack";"TechLab";103;0
"Unit";"Marine";"Barracks";134;1
"Unit";"SCV";"Command Center";142;1
"Unit";"SCV";"Command Center";143;1
"Unit";"SCV";"Command Center";145;1
"Building";"SupplyDepot";NA;141;0
"Building";"SupplyDepot";NA;143;0
"Unit";"SCV";"Command Center";146;1
"Unit";"SCV";"Command Center";147;1
"Unit";"SCV";"Command Center";151;1
"Unit";"SCV";"Command Center";151;1
"Unit";"SCV";"Command Center";151;1
"Unit";"Marine";"Barracks";149;1
"Unit";"Marine";"Barracks";149;1
"Unit";"Marine";"Barracks";149;1
"Unit";"Marine";"Barracks";149;1
"Unit";"Marine";"Barracks";149;1
"Unit";"Marine";"Barracks";149;1
"Unit";"Marine";"Barracks";149;1
"Unit";"Marine";"Barracks";149;1
"Unit";"Marine";"Barracks";154;1
"Unit";"Marine";"Barracks";155;1
"Unit";"Marine";"Barracks";156;1
"Unit";"Marine";"Barracks";158;1
"Unit";"Medivac";"Starport";151;2
"Unit";"Marine";"Barracks";162;1
"Unit";"Marine";"Barracks";162;1
"Unit";"Marine";"Barracks";162;1
"Unit";"Marine";"Barracks";162;1
"Unit";"Marine";"Barracks";162;1
"Unit";"Medivac";"Starport";161;2
"Unit";"Marine";"Barracks";162;1
"Unit";"Marine";"Barracks";163;1
"Unit";"Marine";"Barracks";164;1
"Unit";"Marine";"Barracks";165;1
"Upgrade";"TerranInfantryWeaponsLevel2";"EngineeringBay";134;0
"Unit";"Marine";"Barracks";168;1
"Unit";"Marine";"Barracks";169;1
"Unit";"Marine";"Barracks";169;1
"Unit";"Medivac";"Starport";166;2
"Unit";"Marine";"Barracks";175;1
"Unit";"Marine";"Barracks";175;1
"Unit";"Marine";"Barracks";179;1
