"Type";"UnitName";"OnBuilding";"TotalSupply";"Supply"
"Unit";"SCV";"Command Center";12;1
"Unit";"SCV";"Command Center";12;1
"Unit";"SCV";"Command Center";13;1
"Building";"SupplyDepot";NA;13;0
"Unit";"SCV";"Command Center";15;1
"Unit";"SCV";"Command Center";15;1
"Building";"Refinery";NA;15;0
"Unit";"SCV";"Command Center";16;1
"Building";"Barracks";NA;15;0
"Unit";"SCV";"Command Center";18;1
"Unit";"Reaper";"Barracks";18;1
"Unit";"SCV";"Command Center";19;1
"Unit";"Marine";"Barracks";20;1
"Building";"SupplyDepot";NA;19;0
"Unit";"SCV";"Command Center";20;1
"Unit";"SCV";"Command Center";22;1
"Unit";"SCV";"Command Center";24;1
"Building";"Refinery";NA;23;0
"Unit";"SCV";"Command Center";24;1
"Building";"CommandCenter";NA;19;0
"Building";"Factory";NA;21;0
"Building";"BarracksReactor";NA;23;0
"Unit";"SCV";"Command Center";25;1
"Unit";"SCV";"Command Center";26;1
"Unit";"Hellion";"Factory";26;2
"Unit";"Hellion";"Factory";26;2
"Unit";"SCV";"Command Center";27;1
"Building";"SupplyDepot";NA;27;0
"Building";"Starport";NA;26;0
"Unit";"SCV";"Command Center";28;1
"Building";"BarracksTechLab";NA;28;0
"Unit";"SCV";"Command Center";33;1
"Unit";"Hellion";"Factory";28;2
"Unit";"Hellion";"Factory";30;2
"Unit";"SCV";"Command Center";34;1
"Unit";"SCV";"Command Center";34;1
"Building";"SupplyDepot";NA;33;0
"Unit";"SCV";"Command Center";39;1
"Unit";"Hellion";"Factory";40;2
"Unit";"Hellion";"Factory";40;2
"Unit";"SCV";"Command Center";41;1
"Unit";"SCV";"Command Center";42;1
"Building";"SupplyDepot";NA;41;0
"Unit";"SCV";"Command Center";46;1
"Unit";"Banshee";"Starport";35;3
"Unit";"SCV";"Command Center";47;1
"Unit";"Hellion";"Factory";46;2
"Unit";"Hellion";"Factory";47;2
"Unit";"SCV";"Command Center";48;1
"Unit";"SCV";"Command Center";57;1
"Unit";"SCV";"Command Center";58;1
"Unit";"Hellion";"Factory";53;2
"Unit";"Hellion";"Factory";55;2
"Building";"SupplyDepot";NA;58;0
"Unit";"SCV";"Command Center";60;1
"Unit";"SCV";"Command Center";60;1
"Unit";"SCV";"Command Center";64;1
"Unit";"SCV";"Command Center";65;1
"Unit";"Banshee";"Starport";58;3
"Building";"SupplyDepot";NA;64;0
"Unit";"Cyclone";"Factory";64;3
"Unit";"SCV";"Command Center";66;1
"Unit";"SCV";"Command Center";67;1
"Unit";"Cyclone";"Factory";66;3
"Building";"Refinery";NA;66;0
"Building";"Refinery";NA;66;0
"Unit";"SCV";"Command Center";74;1
"Unit";"SCV";"Command Center";75;1
"Building";"Armory";NA;66;0
"Unit";"SCV";"Command Center";79;1
"Unit";"SCV";"Command Center";80;1
"Building";"SupplyDepot";NA;79;0
"Building";"CommandCenter";NA;59;0
"Unit";"Hellion";"Factory";81;2
"Unit";"Hellion";"Factory";81;2
"Unit";"SCV";"Command Center";81;1
"Unit";"SCV";"Command Center";82;1
"Unit";"SCV";"Command Center";83;1
"Building";"BarracksTechLab";NA;83;0
"Unit";"SCV";"Command Center";87;1
"Unit";"SCV";"Command Center";88;1
"Building";"SupplyDepot";NA;83;0
"Unit";"SCV";"Command Center";89;1
"Unit";"SCV";"Command Center";90;1
"Unit";"SCV";"Command Center";91;1
"Unit";"SCV";"Command Center";92;1
"Building";"Factory";NA;83;0
"Unit";"SCV";"Command Center";93;1
"Unit";"SCV";"Command Center";94;1
"Unit";"Hellion";"Factory";92;2
"Unit";"Hellion";"Factory";92;2
"Building";"Factory";NA;83;0
"Unit";"SCV";"Command Center";95;1
"Unit";"SCV";"Command Center";96;1
"Unit";"SCV";"Command Center";97;1
"Building";"StarportReactor";NA;92;0
"Unit";"SCV";"Command Center";102;1
"Unit";"Hellion";"Factory";98;2
"Unit";"Hellion";"Factory";100;2
"Unit";"SCV";"Command Center";103;1
"Unit";"SCV";"Command Center";104;1
"Unit";"SCV";"Command Center";105;1
"Building";"SupplyDepot";NA;105;0
"Unit";"SCV";"Command Center";110;1
"Unit";"SCV";"Command Center";111;1
"Building";"SupplyDepot";NA;105;0
"Building";"EngineeringBay";NA;105;0
"Unit";"Hellion";"Factory";106;2
"Unit";"Hellion";"Factory";108;2
"Unit";"SCV";"Command Center";113;1
"Unit";"SCV";"Command Center";115;1
"Unit";"Thor";"Factory";103;6
"Unit";"Medivac";"Starport";112;2
"Unit";"Medivac";"Starport";112;2
"Building";"SupplyDepot";NA;115;0
"Unit";"Hellion";"Factory";115;2
"Unit";"Hellion";"Factory";117;2
"Unit";"SCV";"Command Center";127;1
"Unit";"SCV";"Command Center";127;1
"Building";"Refinery";NA;127;0
"Building";"Refinery";NA;127;0
"Unit";"Thor";"Factory";115;6
"Unit";"SCV";"Command Center";135;1
"Unit";"SCV";"Command Center";136;1
"Unit";"SCV";"Command Center";143;1
"Unit";"SCV";"Command Center";144;1
"Upgrade";"TerranVehicleWeaponsLevel1";"Armory";105;0
"Building";"SupplyDepot";NA;143;0
"Unit";"SCV";"Command Center";145;1
"Unit";"SCV";"Command Center";146;1
"Building";"SensorTower";NA;145;0
"Unit";"SCV";"Command Center";147;1
"Unit";"SCV";"Command Center";147;1
"Unit";"SCV";"Command Center";148;1
"Unit";"SCV";"Command Center";149;1
"Unit";"Hellion";"Factory";147;2
"Unit";"Hellion";"Factory";147;2
"Unit";"SCV";"Command Center";150;1
"Unit";"SCV";"Command Center";151;1
"Unit";"SCV";"Command Center";152;1
"Building";"Factory";NA;147;0
"Building";"Factory";NA;147;0
"Unit";"SCV";"Command Center";157;1
"Unit";"SCV";"Command Center";158;1
"Unit";"SCV";"Command Center";159;1
"Unit";"Hellion";"Factory";159;2
"Unit";"Hellion";"Factory";159;2
"Unit";"SCV";"Command Center";160;1
"Unit";"SCV";"Command Center";161;1
"Unit";"SCV";"Command Center";162;1
"Unit";"SCV";"Command Center";167;1
"Unit";"SCV";"Command Center";168;1
"Building";"CommandCenter";NA;147;0
"Unit";"SCV";"Command Center";169;1
"Building";"FactoryTechLab";NA;169;0
"Unit";"Thor";"Factory";159;6
"Building";"FactoryTechLab";NA;169;0
"Unit";"Hellion";"Factory";169;2
"Unit";"Hellion";"Factory";169;2
"Unit";"SCV";"Command Center";170;1
"Unit";"SCV";"Command Center";171;1
"Unit";"SCV";"Command Center";172;1
"Unit";"SCV";"Command Center";183;1
"Unit";"SCV";"Command Center";184;1
"Unit";"SCV";"Command Center";185;1
"Unit";"Medivac";"Starport";172;2
"Unit";"Medivac";"Starport";172;2
"Unit";"Hellion";"Factory";185;2
"Unit";"SCV";"Command Center";186;1
"Unit";"Hellion";"Factory";185;2
"Unit";"Hellion";"Factory";185;2
"Building";"SensorTower";NA;189;0
"Building";"Refinery";NA;193;0
"Building";"Refinery";NA;193;0
"Unit";"Medivac";"Starport";189;2
"Unit";"Medivac";"Starport";191;2
"Unit";"Hellion";"Factory";200;2
"Unit";"Hellion";"Factory";200;2
"Unit";"Hellion";"Factory";208;2
"Unit";"Hellion";"Factory";208;2
"Upgrade";"TerranVehicleWeaponsLevel2";"Armory";172;0
"Unit";"SCV";"Command Center";208;1
"Unit";"SCV";"Command Center";208;1
"Unit";"Hellion";"Factory";208;2
"Unit";"Hellion";"Factory";208;2
"Building";"CommandCenter";NA;200;0
"Unit";"Hellion";"Factory";210;2
"Unit";"Hellion";"Factory";218;2
"Unit";"Hellion";"Factory";218;2
"Building";"Armory";NA;218;0
"Building";"Armory";NA;218;0
"Unit";"Hellion";"Factory";224;2
"Unit";"Hellion";"Factory";224;2
"Unit";"Hellion";"Factory";224;2
"Building";"Starport";NA;224;0
"Building";"Starport";NA;224;0
"Building";"Starport";NA;224;0
"Building";"Refinery";NA;224;0
"Building";"Refinery";NA;224;0
"Unit";"Liberator";"Starport";220;3
"Unit";"Liberator";"Starport";220;3
"Building";"FusionCore";NA;224;0
"Unit";"Thor";"Factory";224;6
"Unit";"Hellion";"Factory";230;2
"Building";"CommandCenter";NA;220;0
"Building";"CommandCenter";NA;220;0
"Unit";"Thor";"Factory";224;6
"Unit";"Thor";"Factory";230;6
"Unit";"Hellion";"Factory";244;2
"Unit";"Hellion";"Factory";244;2
"Building";"StarportTechLab";NA;260;0
"Building";"StarportTechLab";NA;260;0
"Building";"StarportTechLab";NA;260;0
"Building";"CommandCenter";NA;242;0
"Unit";"Hellion";"Factory";260;2
"Unit";"Hellion";"Factory";260;2
"Unit";"Hellion";"Factory";260;2
"Upgrade";"TerranVehicleWeaponsLevel3";"Armory";224;0
"Building";"SensorTower";NA;260;0
"Unit";"Hellion";"Factory";266;2
"Unit";"Hellion";"Factory";266;2
"Upgrade";"TerranShipWeaponsLevel1";"Armory";260;0
"Upgrade";"TerranVehicleAndShipArmorsLevel1";"Armory";260;0
"Unit";"Hellion";"Factory";266;2
"Unit";"Hellion";"Factory";268;2
"Unit";"Liberator";"Starport";266;3
"Unit";"Liberator";"Starport";266;3
"Unit";"Liberator";"Starport";266;3
