"Type";"UnitName";"OnBuilding";"TotalSupply";"Supply"
"Unit";"SCV";"Command Center";12;1
"Unit";"SCV";"Command Center";12;1
"Unit";"SCV";"Command Center";14;1
"Building";"SupplyDepot";NA;13;0
"Unit";"SCV";"Command Center";15;1
"Unit";"SCV";"Command Center";15;1
"Building";"Refinery";NA;15;0
"Unit";"SCV";"Command Center";16;1
"Building";"Barracks";NA;15;0
"Unit";"SCV";"Command Center";17;1
"Unit";"Reaper";"Barracks";19;1
"Unit";"SCV";"Command Center";19;1
"Unit";"Marine";"Barracks";19;1
"Building";"SupplyDepot";NA;19;0
"Unit";"SCV";"Command Center";21;1
"Unit";"SCV";"Command Center";22;1
"Unit";"SCV";"Command Center";23;1
"Building";"CommandCenter";NA;19;0
"Building";"Factory";NA;21;0
"Unit";"SCV";"Command Center";24;1
"Building";"BarracksReactor";NA;23;0
"Building";"Refinery";NA;26;0
"Unit";"SCV";"Command Center";26;1
"Unit";"Hellion";"Factory";26;2
"Unit";"Hellion";"Factory";26;2
"Unit";"SCV";"Command Center";26;1
"Unit";"SCV";"Command Center";27;1
"Building";"BarracksTechLab";NA;27;0
"Unit";"Hellion";"Factory";31;2
"Building";"CommandCenter";NA;25;0
"Unit";"SCV";"Command Center";33;1
"Building";"Starport";NA;26;0
"Unit";"SCV";"Command Center";33;1
"Unit";"Hellion";"Factory";32;2
"Unit";"SCV";"Command Center";35;1
"Unit";"SCV";"Command Center";36;1
"Building";"BarracksTechLab";NA;35;0
"Building";"SupplyDepot";NA;35;0
"Unit";"Hellion";"Factory";36;2
"Unit";"SCV";"Command Center";40;1
"Unit";"SCV";"Command Center";40;1
"Unit";"SCV";"Command Center";41;1
"Unit";"Hellion";"Factory";39;2
"Unit";"SCV";"Command Center";45;1
"Building";"Refinery";NA;41;0
"Unit";"SCV";"Command Center";46;1
"Unit";"Hellion";"Factory";41;2
"Unit";"SCV";"Command Center";48;1
"Unit";"Hellion";"Factory";46;2
"Building";"Refinery";NA;48;0
"Unit";"SCV";"Command Center";52;1
"Unit";"SCV";"Command Center";52;1
"Unit";"Hellion";"Factory";50;2
"Unit";"SCV";"Command Center";55;1
"Building";"SupplyDepot";NA;55;0
"Unit";"SCV";"Command Center";56;1
"Unit";"SCV";"Command Center";59;1
"Unit";"SCV";"Command Center";60;1
"Unit";"SCV";"Command Center";60;1
"Unit";"Hellion";"Factory";59;2
"Unit";"Hellion";"Factory";59;2
"Building";"BarracksTechLab";NA;60;0
"Unit";"SCV";"Command Center";61;1
"Unit";"SCV";"Command Center";68;1
"Unit";"SCV";"Command Center";68;1
"Unit";"SCV";"Command Center";71;1
"Unit";"Hellion";"Factory";69;2
"Building";"Armory";NA;60;0
"Building";"Armory";NA;60;0
"Unit";"Liberator";"Starport";61;3
"Unit";"SCV";"Command Center";71;1
"Unit";"SCV";"Command Center";71;1
"Unit";"SCV";"Command Center";71;1
"Building";"SupplyDepot";NA;71;0
"Unit";"Hellion";"Factory";71;2
"Building";"SupplyDepot";NA;71;0
"Building";"SupplyDepot";NA;71;0
"Building";"Refinery";NA;72;0
"Unit";"Hellion";"Factory";72;2
"Building";"Refinery";NA;74;0
"Unit";"SCV";"Command Center";80;1
"Unit";"SCV";"Command Center";80;1
"Building";"SupplyDepot";NA;74;0
"Unit";"SCV";"Command Center";82;1
"Unit";"SCV";"Command Center";84;1
"Unit";"SCV";"Command Center";86;1
"Unit";"SCV";"Command Center";86;1
"Building";"SupplyDepot";NA;87;0
"Unit";"Hellion";"Factory";89;2
"Unit";"Hellion";"Factory";89;2
"Unit";"SCV";"Command Center";90;1
"Unit";"SCV";"Command Center";90;1
"Building";"Factory";NA;86;0
"Building";"Factory";NA;86;0
"Unit";"SCV";"Command Center";96;1
"Unit";"SCV";"Command Center";96;1
"Building";"StarportReactor";NA;89;0
"Unit";"SCV";"Command Center";96;1
"Unit";"Hellion";"Factory";96;2
"Unit";"Hellion";"Factory";96;2
"Unit";"SCV";"Command Center";99;1
"Unit";"SCV";"Command Center";99;1
"Unit";"SCV";"Command Center";99;1
"Building";"Factory";NA;90;0
"Building";"Factory";NA;90;0
"Unit";"SCV";"Command Center";103;1
"Unit";"SCV";"Command Center";104;1
"Unit";"SCV";"Command Center";105;1
"Building";"CommandCenter";NA;89;0
"Building";"SupplyDepot";NA;106;0
"Unit";"SCV";"Command Center";106;1
"Unit";"SCV";"Command Center";107;1
"Building";"EngineeringBay";NA;103;0
"Unit";"SCV";"Command Center";108;1
"Building";"FactoryTechLab";NA;106;0
"Building";"SupplyDepot";NA;106;0
"Building";"SupplyDepot";NA;106;0
"Unit";"Hellion";"Factory";106;2
"Unit";"Thor";"Factory";96;6
"Unit";"Hellion";"Factory";106;2
"Unit";"SCV";"Command Center";109;1
"Unit";"SCV";"Command Center";110;1
"Building";"FactoryReactor";NA;106;0
"Upgrade";"TerranVehicleWeaponsLevel1";"Armory";90;0
"Upgrade";"TerranVehicleAndShipArmorsLevel1";"Armory";90;0
"Building";"Refinery";NA;124;0
"Building";"Refinery";NA;124;0
"Unit";"Hellion";"Factory";124;2
"Unit";"Hellion";"Factory";124;2
"Unit";"Hellion";"Factory";124;2
"Unit";"Hellion";"Factory";124;2
"Unit";"SCV";"Command Center";124;1
"Unit";"SCV";"Command Center";124;1
"Unit";"SCV";"Command Center";124;1
"Building";"MissileTurret";NA;124;0
"Building";"SensorTower";NA;124;0
"Unit";"SCV";"Command Center";132;1
"Unit";"SCV";"Command Center";133;1
"Unit";"SCV";"Command Center";134;1
"Unit";"Hellion";"Factory";135;2
"Unit";"Hellion";"Factory";135;2
"Unit";"SCV";"Command Center";138;1
"Unit";"SCV";"Command Center";138;1
"Unit";"SCV";"Command Center";138;1
"Unit";"Hellion";"Factory";135;2
"Unit";"SCV";"Command Center";147;1
"Unit";"SCV";"Command Center";147;1
"Unit";"SCV";"Command Center";147;1
"Unit";"SCV";"Command Center";147;1
"Unit";"Hellion";"Factory";145;2
"Unit";"Hellion";"Factory";145;2
"Unit";"Hellion";"Factory";145;2
"Building";"Factory";NA;138;0
"Building";"Factory";NA;138;0
"Building";"Factory";NA;138;0
"Building";"FactoryTechLab";NA;157;0
"Building";"FactoryTechLab";NA;157;0
"Unit";"SCV";"Command Center";157;1
"Unit";"SCV";"Command Center";157;1
"Unit";"Hellion";"Factory";157;2
"Unit";"Hellion";"Factory";157;2
"Unit";"Hellion";"Factory";157;2
"Unit";"Hellion";"Factory";157;2
"Unit";"Hellion";"Factory";157;2
"Unit";"Hellion";"Factory";157;2
"Building";"FactoryReactor";NA;157;0
"Building";"MissileTurret";NA;169;0
"Building";"MissileTurret";NA;169;0
"Unit";"Hellion";"Factory";169;2
"Unit";"Hellion";"Factory";169;2
"Unit";"Hellion";"Factory";169;2
"Unit";"Hellion";"Factory";169;2
"Unit";"Hellion";"Factory";171;2
"Unit";"Hellion";"Factory";171;2
"Upgrade";"TerranVehicleWeaponsLevel2";"Armory";147;0
"Upgrade";"TerranVehicleAndShipArmorsLevel2";"Armory";147;0
"Unit";"Hellion";"Factory";171;2
"Building";"Starport";NA;171;0
"Unit";"Hellion";"Factory";179;2
"Unit";"Hellion";"Factory";179;2
"Unit";"Hellion";"Factory";179;2
"Building";"Starport";NA;171;0
"Building";"Starport";NA;171;0
"Building";"CommandCenter";NA;157;0
"Building";"CommandCenter";NA;159;0
"Unit";"Hellion";"Factory";189;2
"Unit";"Hellion";"Factory";191;2
"Building";"StarportTechLab";NA;191;0
"Building";"StarportTechLab";NA;191;0
"Unit";"Hellion";"Factory";191;2
"Unit";"Hellion";"Factory";191;2
"Unit";"Hellion";"Factory";191;2
"Unit";"Hellion";"Factory";191;2
"Unit";"Hellion";"Factory";191;2
"Unit";"Hellion";"Factory";205;2
"Unit";"Hellion";"Factory";205;2
"Unit";"Hellion";"Factory";205;2
"Unit";"Raven";"Starport";205;2
"Unit";"Raven";"Starport";205;2
"Unit";"Raven";"Starport";205;2
"Building";"CommandCenter";NA;195;0
"Unit";"Hellion";"Factory";211;2
"Unit";"Hellion";"Factory";211;2
"Unit";"Hellion";"Factory";211;2
"Unit";"Hellion";"Factory";217;2
"Unit";"Hellion";"Factory";217;2
"Unit";"Hellion";"Factory";223;2
"Unit";"Hellion";"Factory";223;2
"Unit";"Hellion";"Factory";223;2
"Unit";"Hellion";"Factory";223;2
"Unit";"Raven";"Starport";217;2
"Unit";"Raven";"Starport";217;2
"Unit";"Hellion";"Factory";227;2
"Unit";"Hellion";"Factory";227;2
"Unit";"Raven";"Starport";223;2
"Unit";"Hellion";"Factory";245;2
"Unit";"Hellion";"Factory";245;2
"Unit";"Hellion";"Factory";245;2
"Unit";"Hellion";"Factory";245;2
"Unit";"Raven";"Starport";235;2
"Unit";"SCV";"Command Center";245;1
"Unit";"SCV";"Command Center";245;1
"Building";"Refinery";NA;257;0
"Building";"MissileTurret";NA;257;0
"Building";"Refinery";NA;257;0
"Building";"MissileTurret";NA;257;0
"Building";"SensorTower";NA;257;0
"Building";"MissileTurret";NA;257;0
"Building";"MissileTurret";NA;257;0
"Unit";"Hellion";"Factory";257;2
"Unit";"Hellion";"Factory";257;2
"Unit";"Hellion";"Factory";257;2
"Unit";"Hellion";"Factory";257;2
"Unit";"Hellion";"Factory";257;2
"Unit";"Hellion";"Factory";257;2
"Unit";"Hellion";"Factory";257;2
"Building";"MissileTurret";NA;257;0
"Unit";"Hellion";"Factory";257;2
"Unit";"Raven";"Starport";257;2
"Unit";"Raven";"Starport";257;2
"Unit";"Raven";"Starport";257;2
"Building";"Refinery";NA;267;0
"Building";"Refinery";NA;267;0
"Unit";"Hellion";"Factory";267;2
"Unit";"Hellion";"Factory";267;2
"Unit";"Hellion";"Factory";267;2
"Unit";"Hellion";"Factory";267;2
"Unit";"Hellion";"Factory";287;2
"Unit";"Hellion";"Factory";287;2
"Unit";"Hellion";"Factory";287;2
"Upgrade";"TerranVehicleWeaponsLevel3";"Armory";257;0
"Upgrade";"TerranVehicleAndShipArmorsLevel3";"Armory";257;0
"Unit";"Hellion";"Factory";287;2
"Unit";"Hellion";"Factory";287;2
"Unit";"Hellion";"Factory";287;2
"Unit";"Hellion";"Factory";293;2
"Unit";"Hellion";"Factory";293;2
"Unit";"Hellion";"Factory";293;2
"Building";"CommandCenter";NA;279;0
"Unit";"Hellion";"Factory";297;2
"Unit";"Hellion";"Factory";297;2
"Unit";"Hellion";"Factory";299;2
"Unit";"Hellion";"Factory";303;2
"Unit";"Hellion";"Factory";311;2
"Unit";"Hellion";"Factory";311;2
"Unit";"Hellion";"Factory";311;2
"Unit";"Hellion";"Factory";311;2
"Unit";"Hellion";"Factory";311;2
