"Type";"UnitName";"OnBuilding";"TotalSupply";"Supply"
"Unit";"SCV";"Command Center";12;1
"Unit";"SCV";"Command Center";12;1
"Unit";"SCV";"Command Center";13;1
"Building";"SupplyDepot";NA;13;0
"Building";"Refinery";NA;14;0
"Unit";"SCV";"Command Center";15;1
"Unit";"SCV";"Command Center";15;1
"Unit";"SCV";"Command Center";16;1
"Unit";"SCV";"Command Center";17;1
"Building";"Barracks";NA;15;0
"Unit";"Reaper";"Barracks";19;1
"Unit";"SCV";"Command Center";19;1
"Unit";"SCV";"Command Center";20;1
"Building";"SupplyDepot";NA;20;0
"Unit";"SCV";"Command Center";21;1
"Building";"Factory";NA;19;0
"Building";"Refinery";NA;21;0
"Building";"BarracksReactor";NA;20;0
"Unit";"SCV";"Command Center";22;1
"Building";"CommandCenter";NA;19;0
"Unit";"SCV";"Command Center";23;1
"Unit";"SCV";"Command Center";24;1
"Building";"BarracksTechLab";NA;24;0
"Unit";"Hellion";"Factory";24;2
"Unit";"Hellion";"Factory";24;2
"Building";"Starport";NA;23;0
"Unit";"SCV";"Command Center";25;1
"Unit";"SCV";"Command Center";30;1
"Unit";"Hellion";"Factory";30;2
"Unit";"Hellion";"Factory";30;2
"Unit";"SCV";"Command Center";31;1
"Unit";"SCV";"Command Center";32;1
"Unit";"SCV";"Command Center";37;1
"Unit";"Hellion";"Factory";37;2
"Unit";"Hellion";"Factory";37;2
"Building";"BarracksReactor";NA;31;0
"Unit";"SCV";"Command Center";39;1
"Building";"SupplyDepot";NA;38;0
"Unit";"SCV";"Command Center";39;1
"Building";"SupplyDepot";NA;38;0
"Unit";"SCV";"Command Center";44;1
"Unit";"SCV";"Command Center";44;1
"Unit";"Marine";"Barracks";45;1
"Unit";"Marine";"Barracks";45;1
"Unit";"SCV";"Command Center";45;1
"Unit";"SCV";"Command Center";47;1
"Building";"FactoryTechLab";NA;46;0
"Unit";"SCV";"Command Center";49;1
"Unit";"SCV";"Command Center";51;1
"Unit";"Liberator";"Starport";44;3
"Unit";"SCV";"Command Center";52;1
"Unit";"SCV";"Command Center";52;1
"Unit";"Marine";"Barracks";52;1
"Unit";"Marine";"Barracks";52;1
"Unit";"SCV";"Command Center";60;1
"Unit";"SCV";"Command Center";60;1
"Building";"EngineeringBay";NA;60;0
"Building";"EngineeringBay";NA;60;0
"Unit";"SCV";"Command Center";61;1
"Unit";"SCV";"Command Center";61;1
"Building";"CommandCenter";NA;47;0
"Unit";"SCV";"Command Center";62;1
"Unit";"Marine";"Barracks";62;1
"Building";"SupplyDepot";NA;62;0
"Building";"Refinery";NA;62;0
"Building";"Refinery";NA;62;0
"Building";"StarportReactor";NA;61;0
"Building";"MissileTurret";NA;64;0
"Building";"MissileTurret";NA;65;0
"Building";"Barracks";NA;61;0
"Building";"Barracks";NA;61;0
"Unit";"SCV";"Command Center";66;1
"Unit";"Marine";"Barracks";66;1
"Unit";"SCV";"Command Center";66;1
"Building";"MissileTurret";NA;66;0
"Unit";"SCV";"Command Center";66;1
"Unit";"Marine";"Barracks";67;1
"Unit";"Marine";"Barracks";67;1
"Unit";"Marine";"Barracks";67;1
"Unit";"SCV";"Command Center";69;1
"Unit";"SCV";"Command Center";69;1
"Unit";"Marine";"Barracks";69;1
"Unit";"Marine";"Barracks";69;1
"Unit";"Medivac";"Starport";68;2
"Unit";"Marine";"Barracks";70;1
"Unit";"Marine";"Barracks";71;1
"Unit";"SCV";"Command Center";77;1
"Unit";"Marine";"Barracks";74;1
"Unit";"Marine";"Barracks";75;1
"Building";"Armory";NA;66;0
"Building";"SupplyDepot";NA;83;0
"Building";"SupplyDepot";NA;84;0
"Building";"SupplyDepot";NA;84;0
"Building";"SupplyDepot";NA;84;0
"Unit";"SCV";"Command Center";84;1
"Upgrade";"TerranInfantryWeaponsLevel1";"EngineeringBay";66;0
"Upgrade";"Stimpack";"TechLab";66;0
"Unit";"Marine";"Barracks";84;1
"Unit";"Marine";"Barracks";84;1
"Unit";"Marine";"Barracks";84;1
"Unit";"Marine";"Barracks";84;1
"Unit";"Marine";"Barracks";84;1
"Upgrade";"TerranInfantryArmorsLevel1";"EngineeringBay";66;0
"Building";"Barracks";NA;80;0
"Unit";"SCV";"Command Center";84;1
"Building";"Barracks";NA;82;0
"Unit";"SCV";"Command Center";84;1
"Building";"MissileTurret";NA;84;0
"Unit";"Medivac";"Starport";84;2
"Unit";"SCV";"Command Center";90;1
"Unit";"SCV";"Command Center";90;1
"Unit";"Marine";"Barracks";85;1
"Unit";"Marine";"Barracks";85;1
"Unit";"Marine";"Barracks";85;1
"Unit";"SCV";"Command Center";91;1
"Unit";"Medivac";"Starport";84;2
"Unit";"SCV";"Command Center";94;1
"Unit";"SCV";"Command Center";95;1
"Building";"MissileTurret";NA;94;0
"Unit";"Marine";"Barracks";102;1
"Unit";"Marine";"Barracks";102;1
"Unit";"Marine";"Barracks";102;1
"Building";"Refinery";NA;102;0
"Unit";"Marine";"Barracks";102;1
"Building";"BarracksReactor";NA;92;0
"Unit";"Marine";"Barracks";102;1
"Building";"BarracksReactor";NA;92;0
"Building";"Refinery";NA;102;0
"Unit";"Marine";"Barracks";104;1
"Unit";"Marine";"Barracks";105;1
"Unit";"Marine";"Barracks";106;1
"Unit";"Marine";"Barracks";107;1
"Building";"SupplyDepot";NA;109;0
"Unit";"Marine";"Barracks";109;1
"Unit";"Marine";"Barracks";109;1
"Unit";"Marine";"Barracks";109;1
"Unit";"Marine";"Barracks";109;1
"Unit";"Marine";"Barracks";109;1
"Building";"SupplyDepot";NA;109;0
"Building";"SupplyDepot";NA;109;0
"Building";"SupplyDepot";NA;109;0
"Building";"SupplyDepot";NA;109;0
"Unit";"Marine";"Barracks";113;1
"Unit";"Marine";"Barracks";113;1
"Unit";"Marine";"Barracks";113;1
"Unit";"Marine";"Barracks";113;1
"Building";"Factory";NA;109;0
"Unit";"Marine";"Barracks";118;1
"Unit";"Marine";"Barracks";118;1
"Unit";"SCV";"Command Center";118;1
"Unit";"SCV";"Command Center";118;1
"Unit";"Marine";"Barracks";118;1
"Unit";"Marine";"Barracks";118;1
"Unit";"Marine";"Barracks";118;1
"Unit";"Medivac";"Starport";113;2
"Unit";"Marine";"Barracks";118;1
"Upgrade";"TerranVehicleWeaponsLevel1";"Armory";104;0
"Unit";"Marine";"Barracks";124;1
"Unit";"Marine";"Barracks";124;1
"Unit";"SCV";"Command Center";131;1
"Unit";"SCV";"Command Center";131;1
"Unit";"Marine";"Barracks";128;1
"Unit";"Marine";"Barracks";128;1
"Unit";"Marine";"Barracks";129;1
"Unit";"Marine";"Barracks";129;1
"Unit";"Marine";"Barracks";131;1
"Unit";"Marine";"Barracks";131;1
"Building";"FactoryTechLab";NA;131;0
"Unit";"Marine";"Barracks";132;1
"Building";"SensorTower";NA;132;0
"Unit";"Marine";"Barracks";132;1
"Unit";"Marine";"Barracks";133;1
"Upgrade";"TerranInfantryWeaponsLevel2";"EngineeringBay";109;0
"Building";"SupplyDepot";NA;134;0
"Building";"SupplyDepot";NA;134;0
"Unit";"SCV";"Command Center";142;1
"Unit";"Marine";"Barracks";142;1
"Unit";"Marine";"Barracks";142;1
"Unit";"SCV";"Command Center";143;1
"Unit";"Marine";"Barracks";142;1
"Unit";"Marine";"Barracks";142;1
"Unit";"Marine";"Barracks";142;1
"Upgrade";"TerranInfantryArmorsLevel2";"EngineeringBay";113;0
"Unit";"Marine";"Barracks";152;1
"Unit";"Marine";"Barracks";152;1
"Building";"SupplyDepot";NA;146;0
"Building";"CommandCenter";NA;122;0
"Building";"SupplyDepot";NA;152;0
"Building";"SupplyDepot";NA;152;0
"Unit";"Marine";"Barracks";152;1
"Unit";"Marine";"Barracks";152;1
"Unit";"Marine";"Barracks";152;1
"Unit";"Marine";"Barracks";152;1
"Unit";"Marine";"Barracks";154;1
"Unit";"Marine";"Barracks";154;1
"Unit";"Marine";"Barracks";155;1
"Unit";"Marine";"Barracks";156;1
"Unit";"Marine";"Barracks";158;1
"Unit";"Marine";"Barracks";158;1
"Unit";"Marine";"Barracks";158;1
"Unit";"Marine";"Barracks";158;1
"Unit";"Marine";"Barracks";158;1
"Unit";"Marine";"Barracks";159;1
"Unit";"Marine";"Barracks";160;1
"Unit";"Marine";"Barracks";166;1
"Unit";"Marine";"Barracks";166;1
"Unit";"Marine";"Barracks";166;1
"Unit";"Marine";"Barracks";166;1
"Unit";"Marine";"Barracks";169;1
"Unit";"Marine";"Barracks";169;1
"Unit";"Marine";"Barracks";169;1
"Unit";"Medivac";"Starport";166;2
"Unit";"Medivac";"Starport";166;2
"Unit";"Marine";"Barracks";180;1
"Building";"Refinery";NA;176;0
"Unit";"Marine";"Barracks";180;1
"Unit";"Marine";"Barracks";180;1
"Upgrade";"TerranVehicleWeaponsLevel2";"Armory";152;0
"Unit";"Marine";"Barracks";180;1
"Unit";"Marine";"Barracks";180;1
"Unit";"Marine";"Barracks";180;1
"Unit";"Marauder";"Barracks";180;2
"Unit";"SCV";"Command Center";183;1
"Unit";"SCV";"Command Center";183;1
"Unit";"SCV";"Command Center";183;1
"Unit";"SCV";"Command Center";183;1
"Unit";"Marine";"Barracks";186;1
"Building";"Barracks";NA;180;0
"Building";"Barracks";NA;180;0
"Building";"Barracks";NA;180;0
"Unit";"Marauder";"Barracks";186;2
"Unit";"Marine";"Barracks";192;1
"Unit";"Marine";"Barracks";192;1
"Unit";"Marine";"Barracks";192;1
"Unit";"Marine";"Barracks";192;1
"Unit";"Marine";"Barracks";192;1
"Unit";"Marine";"Barracks";192;1
"Unit";"Marauder";"Barracks";193;2
"Unit";"Marine";"Barracks";201;1
"Unit";"Marine";"Barracks";201;1
"Unit";"Marine";"Barracks";201;1
"Building";"BarracksTechLab";NA;201;0
"Building";"BarracksTechLab";NA;201;0
"Building";"BarracksTechLab";NA;201;0
"Building";"SupplyDepot";NA;203;0
"Building";"SupplyDepot";NA;203;0
"Building";"SupplyDepot";NA;203;0
"Building";"GhostAcademy";NA;201;0
"Upgrade";"TerranInfantryWeaponsLevel3";"EngineeringBay";180;0
"Unit";"Marine";"Barracks";206;1
"Unit";"Marine";"Barracks";206;1
"Unit";"Marine";"Barracks";206;1
"Unit";"Marauder";"Barracks";206;2
"Unit";"Marauder";"Barracks";206;2
"Unit";"Marauder";"Barracks";206;2
"Unit";"SCV";"Command Center";208;1
"Unit";"Marine";"Barracks";206;1
"Unit";"SCV";"Command Center";209;1
"Unit";"Marine";"Barracks";206;1
"Unit";"SCV";"Command Center";209;1
"Unit";"SCV";"Command Center";209;1
"Unit";"Ghost";"Barracks";206;2
"Unit";"SCV";"Command Center";215;1
"Unit";"SCV";"Command Center";217;1
