"type";"unit_name";"on_building";"total_supply";"supply"
"Building";"Refinery";NA;15;0
"Building";"Barracks";NA;15;0
"Unit";"Reaper";"Barracks";19;1
"Unit";"Marine";"Barracks";20;1
"Building";"Refinery";NA;23;0
"Building";"CommandCenter";NA;19;0
"Building";"BarracksReactor";NA;23;0
"Building";"Factory";NA;23;0
"Building";"BarracksTechLab";NA;27;0
"Unit";"Hellion";"Factory";27;2
"Unit";"Hellion";"Factory";27;2
"Building";"Starport";NA;27;0
"Unit";"Hellion";"Factory";32;2
"Unit";"Hellion";"Factory";32;2
"Building";"BarracksTechLab";NA;34;0
"Unit";"Hellion";"Factory";40;2
"Unit";"Hellion";"Factory";40;2
"Unit";"Marine";"Barracks";48;1
"Unit";"Marine";"Barracks";48;1
"Unit";"Banshee";"Starport";41;3
"Unit";"Marine";"Barracks";55;1
"Unit";"Marine";"Barracks";55;1
"Unit";"Marine";"Barracks";61;1
"Unit";"Marine";"Barracks";61;1
"Unit";"Banshee";"Starport";55;3
"Building";"CommandCenter";NA;47;0
"Building";"Refinery";NA;62;0
"Building";"Refinery";NA;63;0
"Building";"EngineeringBay";NA;61;0
"Building";"EngineeringBay";NA;62;0
"Unit";"Marine";"Barracks";70;1
"Unit";"Marine";"Barracks";70;1
"Unit";"Marine";"Barracks";74;1
"Unit";"Marine";"Barracks";74;1
"Building";"StarportReactor";NA;71;0
"Building";"Barracks";NA;70;0
"Building";"Barracks";NA;70;0
"Unit";"Marine";"Barracks";79;1
"Unit";"Marine";"Barracks";79;1
"Building";"Bunker";NA;78;0
"Unit";"Marine";"Barracks";80;1
"Unit";"Marine";"Barracks";80;1
"Unit";"Marine";"Barracks";80;1
"Building";"Barracks";NA;77;0
"Building";"Barracks";NA;77;0
"Unit";"Marine";"Barracks";80;1
"Building";"StarportReactor";NA;80;0
"Unit";"Marine";"Barracks";84;1
"Building";"BarracksTechLab";NA;90;0
"Unit";"Marine";"Barracks";91;1
"Unit";"Marine";"Barracks";91;1
"Unit";"Marine";"Barracks";93;1
"Unit";"Marine";"Barracks";93;1
"Unit";"Marine";"Barracks";93;1
"Building";"BarracksReactor";NA;90;0
"Unit";"Marine";"Barracks";95;1
"Building";"Armory";NA;87;0
"Upgrade";"TerranInfantryWeaponsLevel1";"EngineeringBay";80;0
"Upgrade";"TerranInfantryArmorsLevel1";"EngineeringBay";80;0
"Unit";"Medivac";"Starport";95;2
"Unit";"Medivac";"Starport";95;2
"Unit";"Marine";"Barracks";105;1
"Unit";"Marine";"Barracks";105;1
"Unit";"Marine";"Barracks";105;1
"Unit";"Marine";"Barracks";105;1
"Unit";"Marine";"Barracks";105;1
"Unit";"Marine";"Barracks";105;1
"Unit";"Marine";"Barracks";105;1
"Unit";"Marine";"Barracks";105;1
"Unit";"Marine";"Barracks";112;1
"Unit";"Marine";"Barracks";113;1
"Unit";"Marine";"Barracks";114;1
"Unit";"Marine";"Barracks";115;1
"Unit";"Marine";"Barracks";116;1
"Unit";"Marine";"Barracks";117;1
"Building";"Refinery";NA;112;0
"Unit";"Medivac";"Starport";109;2
"Unit";"Medivac";"Starport";109;2
"Unit";"Marine";"Barracks";120;1
"Unit";"Marine";"Barracks";120;1
"Building";"Refinery";NA;120;0
"Upgrade";"Stimpack";"TechLab";91;0
"Unit";"Marine";"Barracks";129;1
"Unit";"Marine";"Barracks";129;1
"Unit";"Marine";"Barracks";129;1
"Unit";"Marine";"Barracks";129;1
"Unit";"Marine";"Barracks";135;1
"Unit";"Marine";"Barracks";135;1
"Unit";"Marine";"Barracks";138;1
"Unit";"Marine";"Barracks";138;1
"Unit";"Marine";"Barracks";138;1
"Unit";"Marine";"Barracks";142;1
"Unit";"Marine";"Barracks";142;1
"Unit";"Marine";"Barracks";142;1
"Unit";"Marine";"Barracks";144;1
"Unit";"Marine";"Barracks";144;1
"Unit";"Medivac";"Starport";144;2
"Unit";"Medivac";"Starport";144;2
"Unit";"Marine";"Barracks";152;1
"Unit";"Marine";"Barracks";152;1
"Unit";"Marine";"Barracks";152;1
"Building";"CommandCenter";NA;123;0
"Unit";"Marine";"Barracks";152;1
"Unit";"Marine";"Barracks";152;1
"Unit";"Marine";"Barracks";152;1
"Unit";"Marine";"Barracks";152;1
"Unit";"Marine";"Barracks";152;1
"Building";"Factory";NA;144;0
"Building";"Barracks";NA;144;0
"Building";"Barracks";NA;144;0
"Unit";"Marine";"Barracks";156;1
"Unit";"Marine";"Barracks";157;1
"Unit";"Marine";"Barracks";157;1
"Unit";"Marine";"Barracks";159;1
"Unit";"Marine";"Barracks";159;1
"Unit";"Marine";"Barracks";165;1
"Unit";"Marine";"Barracks";165;1
"Unit";"Marine";"Barracks";165;1
"Building";"FactoryTechLab";NA;165;0
"Unit";"Marine";"Barracks";165;1
"Unit";"Medivac";"Starport";159;2
"Unit";"Marine";"Barracks";165;1
"Unit";"Marine";"Barracks";166;1
"Unit";"Medivac";"Starport";165;2
"Upgrade";"TerranInfantryWeaponsLevel2";"EngineeringBay";138;0
"Upgrade";"TerranInfantryArmorsLevel2";"EngineeringBay";138;0
"Unit";"Marine";"Barracks";180;1
"Unit";"Marine";"Barracks";180;1
"Unit";"Marine";"Barracks";180;1
"Unit";"Marine";"Barracks";180;1
"Unit";"Marine";"Barracks";180;1
"Building";"BarracksTechLab";NA;180;0
"Unit";"Marauder";"Barracks";180;2
"Unit";"Marauder";"Barracks";180;2
"Unit";"Marine";"Barracks";180;1
"Unit";"Medivac";"Starport";180;2
"Unit";"Medivac";"Starport";180;2
"Unit";"Marine";"Barracks";180;1
"Unit";"Marine";"Barracks";181;1
"Unit";"Marine";"Barracks";182;1
"Unit";"Marine";"Barracks";183;1
"Building";"BarracksReactor";NA;180;0
"Unit";"Marine";"Barracks";189;1
"Unit";"Marine";"Barracks";189;1
"Unit";"Marine";"Barracks";189;1
"Unit";"Marauder";"Barracks";185;2
"Building";"Refinery";NA;189;0
"Building";"Refinery";NA;189;0
"Unit";"Marine";"Barracks";189;1
"Unit";"Marine";"Barracks";194;1
"Unit";"Marine";"Barracks";198;1
"Unit";"Marine";"Barracks";198;1
"Unit";"Marine";"Barracks";198;1
"Unit";"Marine";"Barracks";198;1
"Unit";"Marine";"Barracks";198;1
"Unit";"Marine";"Barracks";203;1
"Unit";"Marine";"Barracks";203;1
"Unit";"Marauder";"Barracks";203;2
"Unit";"Marine";"Barracks";203;1
"Unit";"Marauder";"Barracks";203;2
"Unit";"Medivac";"Starport";198;2
"Unit";"Medivac";"Starport";198;2
"Unit";"Marine";"Barracks";204;1
"Unit";"Marine";"Barracks";212;1
"Unit";"Marine";"Barracks";212;1
"Unit";"Marine";"Barracks";212;1
"Unit";"Marine";"Barracks";212;1
"Unit";"Marine";"Barracks";212;1
"Unit";"Marine";"Barracks";212;1
"Unit";"Marauder";"Barracks";211;2
"Unit";"Marine";"Barracks";212;1
"Unit";"Marine";"Barracks";214;1
"Unit";"Marine";"Barracks";214;1
"Unit";"Marine";"Barracks";221;1
"Unit";"Thor";"Factory";222;6
"Unit";"Thor";"Factory";234;6
"Unit";"Thor";"Factory";234;6
"Unit";"Marine";"Barracks";252;1
"Unit";"Marine";"Barracks";252;1
"Building";"CommandCenter";NA;240;0
"Unit";"Marine";"Barracks";252;1
"Unit";"Marine";"Barracks";252;1
"Unit";"Marine";"Barracks";252;1
"Unit";"Marine";"Barracks";252;1
"Unit";"Marine";"Barracks";252;1
"Unit";"Thor";"Factory";252;6
"Building";"BarracksTechLab";NA;265;0
"Building";"CommandCenter";NA;252;0
"Unit";"Thor";"Factory";265;6
"Unit";"Marine";"Barracks";265;1
"Unit";"Marine";"Barracks";265;1
"Unit";"Marine";"Barracks";265;1
"Unit";"Marine";"Barracks";265;1
"Unit";"Thor";"Factory";265;6
"Unit";"Marauder";"Barracks";265;2
"Unit";"Marine";"Barracks";271;1
"Unit";"Marine";"Barracks";271;1
"Unit";"Marine";"Barracks";271;1
"Unit";"Marine";"Barracks";271;1
"Unit";"Marine";"Barracks";271;1
"Unit";"Marine";"Barracks";272;1
"Unit";"Marine";"Barracks";272;1
"Unit";"Marine";"Barracks";273;1
"Unit";"Marine";"Barracks";281;1
"Unit";"Marine";"Barracks";281;1
"Unit";"Marine";"Barracks";283;1
"Unit";"Marine";"Barracks";284;1
"Unit";"Marine";"Barracks";286;1
"Unit";"Marauder";"Barracks";281;2
"Unit";"Marauder";"Barracks";285;2
"Unit";"Marine";"Barracks";287;1
"Upgrade";"TerranInfantryWeaponsLevel3";"EngineeringBay";252;0
"Upgrade";"TerranInfantryArmorsLevel3";"EngineeringBay";252;0
"Unit";"Marine";"Barracks";288;1
"Unit";"Marine";"Barracks";291;1
"Unit";"Marine";"Barracks";291;1
"Unit";"Marine";"Barracks";292;1
"Unit";"Marine";"Barracks";292;1
"Unit";"Marine";"Barracks";301;1
"Unit";"Marine";"Barracks";301;1
"Unit";"Marine";"Barracks";301;1
"Unit";"Marauder";"Barracks";301;2
"Unit";"Marauder";"Barracks";301;2
"Unit";"Marauder";"Barracks";301;2
"Unit";"Marine";"Barracks";306;1
"Unit";"Marine";"Barracks";306;1
"Unit";"Marine";"Barracks";306;1
"Unit";"Marine";"Barracks";306;1
"Unit";"Marauder";"Barracks";309;2
"Unit";"Marauder";"Barracks";318;2
"Unit";"Liberator";"Starport";309;3
"Unit";"Liberator";"Starport";309;3
"Unit";"Marine";"Barracks";329;1
"Unit";"Marine";"Barracks";329;1
"Unit";"Marauder";"Barracks";329;2
"Unit";"Marauder";"Barracks";329;2
"Unit";"Marauder";"Barracks";329;2
"Unit";"Marauder";"Barracks";337;2
"Unit";"Marine";"Barracks";337;1
"Unit";"Marine";"Barracks";337;1
"Unit";"Marine";"Barracks";337;1
"Unit";"Marine";"Barracks";337;1
"Unit";"Marine";"Barracks";340;1
"Unit";"Marine";"Barracks";340;1
"Unit";"Marine";"Barracks";340;1
"Unit";"Marine";"Barracks";340;1
"Unit";"Marine";"Barracks";340;1
"Unit";"Marine";"Barracks";340;1
"Unit";"Marine";"Barracks";340;1
"Unit";"Marine";"Barracks";340;1
"Unit";"Marine";"Barracks";340;1
"Unit";"Marine";"Barracks";341;1
"Unit";"Marine";"Barracks";342;1
"Unit";"Marine";"Barracks";343;1
"Unit";"Marine";"Barracks";344;1
"Unit";"Marine";"Barracks";344;1
"Unit";"Marine";"Barracks";344;1
"Unit";"Marine";"Barracks";347;1
"Unit";"Marine";"Barracks";348;1
"Unit";"Marine";"Barracks";348;1
"Unit";"Marine";"Barracks";350;1
"Unit";"Marine";"Barracks";354;1
"Unit";"Marine";"Barracks";354;1
"Unit";"Marine";"Barracks";354;1
"Unit";"Marine";"Barracks";354;1
"Unit";"Marine";"Barracks";355;1
"Unit";"Marine";"Barracks";355;1
"Unit";"Marine";"Barracks";355;1
"Unit";"Marine";"Barracks";358;1
"Unit";"Marauder";"Barracks";359;2
"Unit";"Marauder";"Barracks";359;2
"Unit";"Marauder";"Barracks";361;2
"Unit";"Marine";"Barracks";370;1
"Unit";"Marine";"Barracks";376;1
"Unit";"Marine";"Barracks";377;1
