"type";"unit_name";"on_building";"total_supply_lag";"supply"
"Unit";"Overlord";"Larva";13;0
"Building";"Hatchery";NA;17;0
"Building";"SpawningPool";NA;18;0
"Building";"Extractor";NA;18;0
"Unit";"Overlord";"Larva";22;0
"Unit";"Queen";"Hatchery";22;2
"Unit";"Zergling";"Larva";24;1
"Unit";"Zergling";"Larva";25;1
"Unit";"Zergling";"Larva";26;1
"Unit";"Zergling";"Larva";27;1
"Unit";"Queen";"Hatchery";28;2
"Unit";"Zergling";"Larva";30;1
"Unit";"Zergling";"Larva";31;1
"Unit";"Queen";"Hatchery";36;2
"Unit";"Overlord";"Larva";40;0
"Building";"CreepTumorQueen";NA;51;0
"Unit";"Overlord";"Larva";51;0
"Building";"Hatchery";NA;51;0
"Unit";"Queen";"Hatchery";51;2
"Building";"CreepTumor";NA;53;0
"Building";"CreepTumorQueen";NA;53;0
"Unit";"Overlord";"Larva";53;0
"Building";"EvolutionChamber";NA;53;0
"Unit";"Queen";"Hatchery";53;2
"Unit";"Overlord";"Larva";55;0
"Unit";"Overlord";"Larva";55;0
"Unit";"Zergling";"Larva";55;1
"Unit";"Zergling";"Larva";56;1
"Unit";"Zergling";"Larva";57;1
"Unit";"Zergling";"Larva";58;1
"Unit";"Zergling";"Larva";59;1
"Unit";"Zergling";"Larva";60;1
"Unit";"Zergling";"Larva";61;1
"Unit";"Zergling";"Larva";62;1
"Unit";"Zergling";"Larva";63;1
"Unit";"Zergling";"Larva";64;1
"Unit";"Zergling";"Larva";65;1
"Unit";"Zergling";"Larva";66;1
"Building";"CreepTumor";NA;67;0
"Building";"CreepTumor";NA;67;0
"Unit";"Zergling";"Larva";67;1
"Unit";"Zergling";"Larva";68;1
"Unit";"Zergling";"Larva";69;1
"Unit";"Zergling";"Larva";70;1
"Unit";"Zergling";"Larva";71;1
"Unit";"Zergling";"Larva";72;1
"Unit";"Zergling";"Larva";73;1
"Unit";"Zergling";"Larva";74;1
"Unit";"Zergling";"Larva";75;1
"Unit";"Zergling";"Larva";76;1
"Unit";"Queen";"Hatchery";77;2
"Unit";"Zergling";"Larva";79;1
"Unit";"Zergling";"Larva";80;1
"Unit";"Zergling";"Larva";81;1
"Unit";"Zergling";"Larva";82;1
"Unit";"Zergling";"Larva";83;1
"Unit";"Zergling";"Larva";84;1
"Unit";"Zergling";"Larva";85;1
"Unit";"Zergling";"Larva";86;1
"Unit";"Zergling";"Larva";87;1
"Unit";"Zergling";"Larva";88;1
"Unit";"Zergling";"Larva";89;1
"Unit";"Zergling";"Larva";90;1
"Unit";"Zergling";"Larva";91;1
"Unit";"Zergling";"Larva";92;1
"Unit";"Queen";"Hatchery";93;2
"Unit";"Zergling";"Larva";95;1
"Unit";"Zergling";"Larva";96;1
"Unit";"Zergling";"Larva";97;1
"Unit";"Zergling";"Larva";98;1
"Unit";"Zergling";"Larva";99;1
"Unit";"Zergling";"Larva";100;1
"Unit";"Zergling";"Larva";101;1
"Unit";"Zergling";"Larva";102;1
"Unit";"Queen";"Hatchery";103;2
"Unit";"Zergling";"Larva";105;1
"Unit";"Zergling";"Larva";106;1
"Unit";"Zergling";"Larva";107;1
"Unit";"Zergling";"Larva";108;1
"Unit";"Zergling";"Larva";109;1
"Unit";"Zergling";"Larva";110;1
"Unit";"Zergling";"Larva";111;1
"Unit";"Zergling";"Larva";112;1
"Unit";"Zergling";"Larva";113;1
"Unit";"Zergling";"Larva";114;1
"Unit";"Zergling";"Larva";115;1
"Unit";"Zergling";"Larva";116;1
"Unit";"Zergling";"Larva";117;1
"Unit";"Zergling";"Larva";118;1
"Unit";"Zergling";"Larva";119;1
"Unit";"Zergling";"Larva";120;1
"Unit";"Zergling";"Larva";121;1
"Unit";"Zergling";"Larva";122;1
"Unit";"Zergling";"Larva";123;1
"Unit";"Zergling";"Larva";124;1
"Unit";"Zergling";"Larva";125;1
"Unit";"Zergling";"Larva";126;1
"Unit";"Zergling";"Larva";127;1
"Unit";"Zergling";"Larva";128;1
"Unit";"Zergling";"Larva";129;1
"Unit";"Zergling";"Larva";130;1
"Unit";"Zergling";"Larva";131;1
"Unit";"Zergling";"Larva";132;1
"Unit";"Zergling";"Larva";133;1
"Unit";"Zergling";"Larva";134;1
"Building";"CreepTumorQueen";NA;142;0
"Building";"CreepTumor";NA;143;0
"Building";"CreepTumor";NA;143;0
"Building";"CreepTumorQueen";NA;151;0
"Building";"CreepTumor";NA;155;0
"Unit";"Queen";"Hatchery";157;2
"Building";"CreepTumor";NA;166;0
"Building";"CreepTumorQueen";NA;172;0
"Unit";"Queen";"Hatchery";172;2
"Unit";"Queen";"Hatchery";174;2
"Unit";"Overlord";"Larva";179;0
"Building";"CreepTumor";NA;179;0
"Unit";"Overlord";"Larva";179;0
"Unit";"Overlord";"Larva";179;0
"Building";"CreepTumor";NA;179;0
"Building";"CreepTumor";NA;179;0
"Unit";"Overlord";"Larva";179;0
"Unit";"Overlord";"Larva";179;0
"Unit";"Overlord";"Larva";179;0
"Building";"CreepTumor";NA;179;0
"Unit";"Overlord";"Larva";179;0
"Unit";"Overlord";"Larva";179;0
"Building";"Extractor";NA;184;0
"Building";"Extractor";NA;184;0
"Building";"Extractor";NA;185;0
"Building";"EvolutionChamber";NA;187;0
"Building";"CreepTumor";NA;193;0
"Building";"CreepTumor";NA;193;0
"Building";"CreepTumor";NA;193;0
"Unit";"Queen";"Hatchery";193;2
"Building";"BanelingNest";NA;197;0
"Building";"Extractor";NA;197;0
"Building";"CreepTumor";NA;206;0
"Building";"CreepTumor";NA;207;0
"Unit";"Overlord";"Larva";215;0
"Unit";"Queen";"Hatchery";215;2
"Building";"Extractor";NA;217;0
"Unit";"Zergling";"Larva";217;1
"Unit";"Zergling";"Larva";218;1
"Unit";"Zergling";"Larva";219;1
"Unit";"Zergling";"Larva";220;1
"Unit";"Zergling";"Larva";221;1
"Unit";"Zergling";"Larva";222;1
"Unit";"Zergling";"Larva";223;1
"Unit";"Zergling";"Larva";224;1
"Unit";"Zergling";"Larva";225;1
"Unit";"Zergling";"Larva";226;1
"Unit";"Zergling";"Larva";227;1
"Unit";"Zergling";"Larva";228;1
"Unit";"Zergling";"Larva";229;1
"Unit";"Zergling";"Larva";230;1
"Unit";"Zergling";"Larva";231;1
"Unit";"Zergling";"Larva";232;1
"Unit";"Zergling";"Larva";233;1
"Unit";"Zergling";"Larva";234;1
"Building";"CreepTumorQueen";NA;235;0
"Unit";"Zergling";"Larva";235;1
"Unit";"Zergling";"Larva";236;1
"Unit";"Zergling";"Larva";237;1
"Unit";"Zergling";"Larva";238;1
"Unit";"Zergling";"Larva";239;1
"Unit";"Zergling";"Larva";240;1
"Unit";"Overlord";"Larva";241;0
"Unit";"Overlord";"Larva";241;0
"Unit";"Zergling";"Larva";241;1
"Unit";"Zergling";"Larva";242;1
"Unit";"Zergling";"Larva";243;1
"Unit";"Zergling";"Larva";244;1
"Unit";"Zergling";"Larva";245;1
"Unit";"Zergling";"Larva";246;1
"Unit";"Zergling";"Larva";247;1
"Unit";"Zergling";"Larva";248;1
"Unit";"Zergling";"Larva";249;1
"Unit";"Zergling";"Larva";250;1
"Unit";"Zergling";"Larva";251;1
"Unit";"Zergling";"Larva";252;1
"Unit";"Zergling";"Larva";253;1
"Unit";"Zergling";"Larva";254;1
"Unit";"Zergling";"Larva";255;1
"Unit";"Zergling";"Larva";256;1
"Unit";"Zergling";"Larva";257;1
"Unit";"Zergling";"Larva";258;1
"Unit";"Zergling";"Larva";259;1
"Unit";"Zergling";"Larva";260;1
"Unit";"Zergling";"Larva";261;1
"Unit";"Zergling";"Larva";262;1
"Building";"CreepTumor";NA;263;0
"Unit";"Zergling";"Larva";263;1
"Unit";"Zergling";"Larva";264;1
"Unit";"Zergling";"Larva";265;1
"Unit";"Zergling";"Larva";266;1
"Unit";"Zergling";"Larva";267;1
"Unit";"Zergling";"Larva";268;1
"Unit";"Baneling";"Zergling";269;0
"Unit";"Baneling";"Zergling";269;0
"Unit";"Baneling";"Zergling";269;0
"Unit";"Zergling";"Larva";269;1
"Unit";"Zergling";"Larva";270;1
"Unit";"Zergling";"Larva";271;1
"Unit";"Zergling";"Larva";272;1
"Unit";"Zergling";"Larva";273;1
"Unit";"Zergling";"Larva";274;1
"Building";"HydraliskDen";NA;275;0
"Unit";"Zergling";"Larva";275;1
"Unit";"Zergling";"Larva";276;1
"Unit";"Zergling";"Larva";277;1
"Unit";"Zergling";"Larva";278;1
"Unit";"Zergling";"Larva";279;1
"Unit";"Zergling";"Larva";280;1
"Unit";"Zergling";"Larva";281;1
"Unit";"Zergling";"Larva";282;1
"Unit";"Zergling";"Larva";283;1
"Unit";"Zergling";"Larva";284;1
"Unit";"Zergling";"Larva";285;1
"Unit";"Zergling";"Larva";286;1
"Unit";"Zergling";"Larva";287;1
"Unit";"Zergling";"Larva";288;1
"Unit";"Zergling";"Larva";289;1
"Unit";"Zergling";"Larva";290;1
"Unit";"Zergling";"Larva";291;1
"Unit";"Zergling";"Larva";292;1
"Unit";"Zergling";"Larva";293;1
"Unit";"Zergling";"Larva";294;1
"Unit";"Baneling";"Zergling";295;0
"Building";"CreepTumorQueen";NA;295;0
"Unit";"Baneling";"Zergling";295;0
"Unit";"Baneling";"Zergling";295;0
"Unit";"Baneling";"Zergling";295;0
"Unit";"Baneling";"Zergling";295;0
"Unit";"Baneling";"Zergling";295;0
"Unit";"Baneling";"Zergling";295;0
"Unit";"Baneling";"Zergling";295;0
"Building";"CreepTumorQueen";NA;295;0
"Unit";"Zergling";"Larva";295;1
"Unit";"Zergling";"Larva";296;1
"Unit";"Zergling";"Larva";297;1
"Unit";"Zergling";"Larva";298;1
"Unit";"Zergling";"Larva";299;1
"Unit";"Zergling";"Larva";300;1
"Unit";"Zergling";"Larva";301;1
"Unit";"Zergling";"Larva";302;1
"Unit";"Queen";"Hatchery";303;2
"Building";"InfestationPit";NA;305;0
"Unit";"Zergling";"Larva";305;1
"Unit";"Zergling";"Larva";306;1
"Unit";"Zergling";"Larva";307;1
"Unit";"Zergling";"Larva";308;1
"Unit";"Zergling";"Larva";309;1
"Unit";"Zergling";"Larva";310;1
"Unit";"Zergling";"Larva";311;1
"Unit";"Zergling";"Larva";312;1
"Unit";"Zergling";"Larva";313;1
"Unit";"Zergling";"Larva";314;1
"Unit";"Zergling";"Larva";315;1
"Unit";"Zergling";"Larva";316;1
"Unit";"Zergling";"Larva";317;1
"Unit";"Zergling";"Larva";318;1
"Unit";"Zergling";"Larva";319;1
"Unit";"Zergling";"Larva";320;1
"Unit";"Zergling";"Larva";321;1
"Unit";"Zergling";"Larva";322;1
"Unit";"Zergling";"Larva";323;1
"Unit";"Zergling";"Larva";324;1
"Unit";"Zergling";"Larva";325;1
"Unit";"Zergling";"Larva";326;1
"Unit";"Zergling";"Larva";327;1
"Unit";"Zergling";"Larva";328;1
"Building";"CreepTumor";NA;329;0
"Building";"CreepTumorQueen";NA;329;0
"Building";"CreepTumorQueen";NA;329;0
"Unit";"Zergling";"Larva";329;1
"Unit";"Zergling";"Larva";330;1
"Unit";"Zergling";"Larva";331;1
"Unit";"Zergling";"Larva";332;1
"Unit";"Zergling";"Larva";333;1
"Unit";"Zergling";"Larva";334;1
"Unit";"Zergling";"Larva";335;1
"Unit";"Zergling";"Larva";336;1
"Unit";"Zergling";"Larva";337;1
"Unit";"Zergling";"Larva";338;1
"Unit";"Zergling";"Larva";339;1
"Unit";"Zergling";"Larva";340;1
"Unit";"Baneling";"Zergling";341;0
"Unit";"Baneling";"Zergling";341;0
"Unit";"Baneling";"Zergling";341;0
"Unit";"Baneling";"Zergling";341;0
"Unit";"Baneling";"Zergling";341;0
"Unit";"Baneling";"Zergling";341;0
"Unit";"Baneling";"Zergling";341;0
"Unit";"Baneling";"Zergling";341;0
"Unit";"Baneling";"Zergling";341;0
"Unit";"Hydralisk";"Larva";341;2
"Unit";"Hydralisk";"Larva";343;2
"Unit";"Hydralisk";"Larva";345;2
"Unit";"Hydralisk";"Larva";347;2
"Unit";"Hydralisk";"Larva";349;2
"Unit";"Hydralisk";"Larva";351;2
"Building";"Hatchery";NA;353;0
"Unit";"Hydralisk";"Larva";353;2
"Unit";"Hydralisk";"Larva";355;2
"Unit";"Overlord";"Larva";357;0
"Unit";"Overlord";"Larva";357;0
"Unit";"Hydralisk";"Larva";357;2
"Unit";"Overlord";"Larva";359;0
"Unit";"Overlord";"Larva";359;0
"Unit";"Overlord";"Larva";359;0
"Unit";"Overlord";"Larva";359;0
"Unit";"Overlord";"Larva";359;0
"Building";"CreepTumor";NA;359;0
"Unit";"Overlord";"Larva";359;0
"Unit";"Overlord";"Larva";359;0
"Unit";"Zergling";"Larva";359;1
"Unit";"Zergling";"Larva";360;1
"Unit";"Zergling";"Larva";361;1
"Unit";"Zergling";"Larva";362;1
"Unit";"Zergling";"Larva";363;1
"Unit";"Zergling";"Larva";364;1
"Unit";"Zergling";"Larva";365;1
"Unit";"Zergling";"Larva";366;1
"Unit";"Zergling";"Larva";367;1
"Unit";"Zergling";"Larva";368;1
"Unit";"Zergling";"Larva";369;1
"Unit";"Zergling";"Larva";370;1
"Unit";"Zergling";"Larva";371;1
"Unit";"Zergling";"Larva";372;1
"Unit";"Zergling";"Larva";373;1
"Unit";"Zergling";"Larva";374;1
"Unit";"Zergling";"Larva";375;1
"Unit";"Zergling";"Larva";376;1
"Unit";"Hydralisk";"Larva";377;2
"Unit";"Hydralisk";"Larva";379;2
"Unit";"Hydralisk";"Larva";381;2
"Unit";"Hydralisk";"Larva";383;2
"Unit";"Zergling";"Larva";385;1
"Unit";"Zergling";"Larva";386;1
"Unit";"Baneling";"Zergling";387;0
"Unit";"Baneling";"Zergling";387;0
"Unit";"Baneling";"Zergling";387;0
"Unit";"Baneling";"Zergling";387;0
"Unit";"Zergling";"Larva";387;1
"Unit";"Zergling";"Larva";388;1
"Unit";"Zergling";"Larva";389;1
"Unit";"Zergling";"Larva";390;1
"Unit";"Zergling";"Larva";391;1
"Unit";"Zergling";"Larva";392;1
"Unit";"Zergling";"Larva";393;1
"Unit";"Zergling";"Larva";394;1
"Unit";"Zergling";"Larva";395;1
"Unit";"Zergling";"Larva";396;1
"Unit";"Zergling";"Larva";397;1
"Unit";"Zergling";"Larva";398;1
"Unit";"Zergling";"Larva";399;1
"Unit";"Zergling";"Larva";400;1
"Unit";"Zergling";"Larva";401;1
"Unit";"Zergling";"Larva";402;1
"Unit";"Zergling";"Larva";403;1
"Unit";"Zergling";"Larva";404;1
"Unit";"Hydralisk";"Larva";405;2
"Unit";"Hydralisk";"Larva";407;2
"Unit";"Hydralisk";"Larva";409;2
"Unit";"Hydralisk";"Larva";411;2
"Unit";"Hydralisk";"Larva";413;2
"Unit";"Hydralisk";"Larva";415;2
"Unit";"Hydralisk";"Larva";417;2
"Unit";"Hydralisk";"Larva";419;2
"Unit";"Hydralisk";"Larva";421;2
"Unit";"Hydralisk";"Larva";423;2
"Unit";"Hydralisk";"Larva";425;2
"Unit";"Hydralisk";"Larva";427;2
"Unit";"Hydralisk";"Larva";429;2
"Unit";"Viper";"Larva";431;3
"Unit";"Zergling";"Larva";434;1
"Unit";"Zergling";"Larva";435;1
"Unit";"Zergling";"Larva";436;1
"Unit";"Zergling";"Larva";437;1
"Unit";"Zergling";"Larva";438;1
"Unit";"Zergling";"Larva";439;1
"Building";"CreepTumorQueen";NA;440;0
"Unit";"Viper";"Larva";440;3
"Unit";"Zergling";"Larva";443;1
"Unit";"Zergling";"Larva";444;1
"Unit";"Zergling";"Larva";445;1
"Unit";"Zergling";"Larva";446;1
"Building";"Hatchery";NA;447;0
"Unit";"Viper";"Larva";447;3
"Unit";"Viper";"Larva";450;3
"Unit";"Zergling";"Larva";453;1
"Unit";"Zergling";"Larva";454;1
"Unit";"Zergling";"Larva";455;1
"Unit";"Zergling";"Larva";456;1
"Unit";"Baneling";"Zergling";457;0
"Unit";"Baneling";"Zergling";457;0
"Unit";"Baneling";"Zergling";457;0
"Unit";"Baneling";"Zergling";457;0
"Unit";"Baneling";"Zergling";457;0
"Unit";"Baneling";"Zergling";457;0
"Unit";"Zergling";"Larva";457;1
"Unit";"Zergling";"Larva";458;1
"Building";"CreepTumorQueen";NA;459;0
"Unit";"Zergling";"Larva";459;1
"Unit";"Zergling";"Larva";460;1
"Unit";"Zergling";"Larva";461;1
"Unit";"Zergling";"Larva";462;1
"Unit";"Zergling";"Larva";463;1
"Unit";"Zergling";"Larva";464;1
"Unit";"Zergling";"Larva";465;1
"Unit";"Zergling";"Larva";466;1
"Unit";"Zergling";"Larva";467;1
"Unit";"Zergling";"Larva";468;1
"Unit";"Zergling";"Larva";469;1
"Unit";"Zergling";"Larva";470;1
"Unit";"Zergling";"Larva";471;1
"Unit";"Zergling";"Larva";472;1
"Building";"CreepTumor";NA;473;0
"Building";"CreepTumorQueen";NA;473;0
"Unit";"Zergling";"Larva";473;1
"Unit";"Zergling";"Larva";474;1
"Building";"CreepTumorQueen";NA;475;0
"Unit";"Zergling";"Larva";475;1
"Unit";"Zergling";"Larva";476;1
"Unit";"Zergling";"Larva";477;1
"Unit";"Zergling";"Larva";478;1
"Unit";"Zergling";"Larva";479;1
"Unit";"Zergling";"Larva";480;1
"Unit";"Zergling";"Larva";481;1
"Unit";"Zergling";"Larva";482;1
"Unit";"Zergling";"Larva";483;1
"Unit";"Zergling";"Larva";484;1
"Unit";"Zergling";"Larva";485;1
"Unit";"Zergling";"Larva";486;1
"Unit";"Zergling";"Larva";487;1
"Unit";"Zergling";"Larva";488;1
"Unit";"Zergling";"Larva";489;1
"Unit";"Zergling";"Larva";490;1
"Unit";"Zergling";"Larva";491;1
"Unit";"Zergling";"Larva";492;1
"Unit";"Zergling";"Larva";493;1
"Unit";"Zergling";"Larva";494;1
"Unit";"Zergling";"Larva";495;1
"Unit";"Zergling";"Larva";496;1
"Building";"CreepTumor";NA;497;0
"Building";"CreepTumor";NA;497;0
"Building";"CreepTumor";NA;497;0
"Unit";"Zergling";"Larva";497;1
"Unit";"Zergling";"Larva";498;1
"Unit";"Zergling";"Larva";499;1
"Unit";"Zergling";"Larva";500;1
"Unit";"Zergling";"Larva";501;1
"Unit";"Zergling";"Larva";502;1
"Unit";"Zergling";"Larva";503;1
"Unit";"Zergling";"Larva";504;1
"Unit";"Zergling";"Larva";505;1
"Unit";"Zergling";"Larva";506;1
"Unit";"Zergling";"Larva";507;1
"Unit";"Zergling";"Larva";508;1
"Building";"Hatchery";NA;509;0
"Building";"CreepTumor";NA;509;0
"Building";"CreepTumor";NA;509;0
"Building";"CreepTumor";NA;509;0
"Unit";"Hydralisk";"Larva";509;2
"Unit";"Hydralisk";"Larva";511;2
"Unit";"Hydralisk";"Larva";513;2
"Unit";"Hydralisk";"Larva";515;2
"Unit";"Hydralisk";"Larva";517;2
"Unit";"Hydralisk";"Larva";519;2
"Unit";"Hydralisk";"Larva";521;2
"Unit";"Hydralisk";"Larva";523;2
"Building";"CreepTumorQueen";NA;525;0
"Unit";"Viper";"Larva";525;3
"Building";"CreepTumorQueen";NA;528;0
"Unit";"Zergling";"Larva";528;1
"Unit";"Zergling";"Larva";529;1
"Building";"CreepTumorQueen";NA;530;0
"Unit";"Zergling";"Larva";530;1
"Unit";"Zergling";"Larva";531;1
"Unit";"Zergling";"Larva";532;1
"Unit";"Zergling";"Larva";533;1
"Building";"CreepTumorQueen";NA;534;0
"Building";"CreepTumorQueen";NA;534;0
"Unit";"Zergling";"Larva";534;1
"Unit";"Zergling";"Larva";535;1
"Unit";"Zergling";"Larva";536;1
"Unit";"Zergling";"Larva";537;1
"Unit";"Zergling";"Larva";538;1
"Unit";"Zergling";"Larva";539;1
"Building";"CreepTumorQueen";NA;540;0
"Unit";"Zergling";"Larva";540;1
"Unit";"Zergling";"Larva";541;1
"Building";"CreepTumorQueen";NA;542;0
"Unit";"Zergling";"Larva";542;1
"Unit";"Zergling";"Larva";543;1
"Building";"CreepTumorQueen";NA;544;0
"Unit";"Zergling";"Larva";544;1
"Unit";"Zergling";"Larva";545;1
"Unit";"Zergling";"Larva";546;1
"Unit";"Zergling";"Larva";547;1
"Unit";"Zergling";"Larva";548;1
"Unit";"Zergling";"Larva";549;1
"Building";"CreepTumor";NA;550;0
"Building";"CreepTumor";NA;550;0
"Unit";"Zergling";"Larva";550;1
"Unit";"Zergling";"Larva";551;1
"Unit";"Zergling";"Larva";552;1
"Unit";"Zergling";"Larva";553;1
"Building";"CreepTumor";NA;554;0
"Building";"CreepTumor";NA;554;0
"Unit";"Baneling";"Zergling";554;0
"Unit";"Baneling";"Zergling";554;0
"Unit";"Baneling";"Zergling";554;0
"Unit";"Baneling";"Zergling";554;0
"Unit";"Baneling";"Zergling";554;0
"Unit";"Baneling";"Zergling";554;0
"Unit";"Baneling";"Zergling";554;0
"Unit";"Baneling";"Zergling";554;0
"Unit";"Baneling";"Zergling";554;0
"Unit";"Baneling";"Zergling";554;0
"Unit";"Baneling";"Zergling";554;0
"Unit";"Baneling";"Zergling";554;0
"Unit";"Zergling";"Larva";554;1
"Unit";"Zergling";"Larva";555;1
"Unit";"Zergling";"Larva";556;1
"Unit";"Zergling";"Larva";557;1
"Unit";"Zergling";"Larva";558;1
"Unit";"Zergling";"Larva";559;1
"Unit";"Zergling";"Larva";560;1
"Unit";"Zergling";"Larva";561;1
"Unit";"Zergling";"Larva";562;1
"Unit";"Zergling";"Larva";563;1
"Unit";"Zergling";"Larva";564;1
"Unit";"Zergling";"Larva";565;1
"Unit";"Zergling";"Larva";566;1
"Unit";"Zergling";"Larva";567;1
"Unit";"Zergling";"Larva";568;1
"Unit";"Zergling";"Larva";569;1
"Unit";"Zergling";"Larva";570;1
"Unit";"Zergling";"Larva";571;1
"Unit";"Zergling";"Larva";572;1
"Unit";"Zergling";"Larva";573;1
"Building";"CreepTumor";NA;574;0
"Building";"CreepTumor";NA;574;0
"Building";"CreepTumor";NA;574;0
"Building";"CreepTumor";NA;574;0
"Building";"CreepTumor";NA;574;0
"Building";"CreepTumor";NA;574;0
"Building";"CreepTumorQueen";NA;574;0
"Building";"CreepTumor";NA;574;0
"Building";"CreepTumor";NA;574;0
"Building";"CreepTumor";NA;574;0
"Unit";"Baneling";"Zergling";574;0
"Unit";"Baneling";"Zergling";574;0
"Unit";"Baneling";"Zergling";574;0
"Unit";"Baneling";"Zergling";574;0
"Unit";"Baneling";"Zergling";574;0
"Unit";"Baneling";"Zergling";574;0
"Unit";"Baneling";"Zergling";574;0
"Unit";"Baneling";"Zergling";574;0
"Unit";"Zergling";"Larva";574;1
"Unit";"Zergling";"Larva";575;1
"Unit";"Zergling";"Larva";576;1
"Unit";"Zergling";"Larva";577;1
"Unit";"Zergling";"Larva";578;1
"Unit";"Zergling";"Larva";579;1
"Unit";"Zergling";"Larva";580;1
"Unit";"Zergling";"Larva";581;1
"Unit";"Zergling";"Larva";582;1
"Unit";"Zergling";"Larva";583;1
"Unit";"Zergling";"Larva";584;1
"Unit";"Zergling";"Larva";585;1
"Unit";"Zergling";"Larva";586;1
"Unit";"Zergling";"Larva";587;1
"Unit";"Zergling";"Larva";588;1
"Unit";"Zergling";"Larva";589;1
"Unit";"Baneling";"Zergling";590;0
"Unit";"Baneling";"Zergling";590;0
"Unit";"Baneling";"Zergling";590;0
"Unit";"Baneling";"Zergling";590;0
"Unit";"Baneling";"Zergling";590;0
"Unit";"Baneling";"Zergling";590;0
"Unit";"Baneling";"Zergling";590;0
"Unit";"Baneling";"Zergling";590;0
"Unit";"Baneling";"Zergling";590;0
"Unit";"Baneling";"Zergling";590;0
"Unit";"Zergling";"Larva";590;1
"Unit";"Zergling";"Larva";591;1
"Unit";"Zergling";"Larva";592;1
"Unit";"Zergling";"Larva";593;1
"Unit";"Zergling";"Larva";594;1
"Unit";"Zergling";"Larva";595;1
"Unit";"Zergling";"Larva";596;1
"Unit";"Zergling";"Larva";597;1
"Unit";"Zergling";"Larva";598;1
"Unit";"Zergling";"Larva";599;1
"Unit";"Zergling";"Larva";600;1
"Unit";"Zergling";"Larva";601;1
"Unit";"Zergling";"Larva";602;1
"Unit";"Zergling";"Larva";603;1
"Unit";"Zergling";"Larva";604;1
"Unit";"Zergling";"Larva";605;1
"Unit";"Zergling";"Larva";606;1
"Unit";"Zergling";"Larva";607;1
"Unit";"Zergling";"Larva";608;1
"Unit";"Zergling";"Larva";609;1
"Unit";"Zergling";"Larva";610;1
"Unit";"Zergling";"Larva";611;1
"Unit";"Zergling";"Larva";612;1
"Unit";"Zergling";"Larva";613;1
"Unit";"Zergling";"Larva";614;1
"Unit";"Zergling";"Larva";615;1
"Building";"CreepTumor";NA;616;0
"Building";"CreepTumor";NA;616;0
"Building";"CreepTumor";NA;616;0
"Unit";"Zergling";"Larva";616;1
"Unit";"Zergling";"Larva";617;1
"Unit";"Zergling";"Larva";618;1
"Unit";"Zergling";"Larva";619;1
"Unit";"Zergling";"Larva";620;1
"Unit";"Zergling";"Larva";621;1
"Unit";"Zergling";"Larva";622;1
"Unit";"Zergling";"Larva";623;1
"Unit";"Zergling";"Larva";624;1
"Unit";"Zergling";"Larva";625;1
"Unit";"Zergling";"Larva";626;1
"Unit";"Zergling";"Larva";627;1
"Unit";"Zergling";"Larva";628;1
"Unit";"Zergling";"Larva";629;1
"Unit";"Zergling";"Larva";630;1
"Unit";"Zergling";"Larva";631;1
"Unit";"Zergling";"Larva";632;1
"Unit";"Zergling";"Larva";633;1
"Unit";"Zergling";"Larva";634;1
"Unit";"Zergling";"Larva";635;1
"Unit";"Zergling";"Larva";636;1
"Unit";"Zergling";"Larva";637;1
"Unit";"Zergling";"Larva";638;1
"Unit";"Zergling";"Larva";639;1
"Unit";"Zergling";"Larva";640;1
"Unit";"Zergling";"Larva";641;1
"Unit";"Zergling";"Larva";642;1
"Unit";"Zergling";"Larva";643;1
"Unit";"Zergling";"Larva";644;1
"Unit";"Zergling";"Larva";645;1
"Unit";"Zergling";"Larva";646;1
"Unit";"Zergling";"Larva";647;1
"Unit";"Zergling";"Larva";648;1
"Unit";"Zergling";"Larva";649;1
"Upgrade";"SprayZerg";NA;650;0
"Upgrade";"SprayZerg";NA;650;0
"Upgrade";"zerglingmovementspeed";NA;650;0
"Upgrade";"overlordspeed";NA;650;0
"Upgrade";"SprayZerg";NA;650;0
"Upgrade";"SprayZerg";NA;650;0
"Upgrade";"SprayZerg";NA;650;0
"Upgrade";"ZergGroundArmorsLevel1";NA;650;0
"Upgrade";"SprayZerg";NA;650;0
"Upgrade";"ZergMeleeWeaponsLevel1";NA;650;0
"Upgrade";"SprayZerg";NA;650;0
"Upgrade";"CentrificalHooks";NA;650;0
"Upgrade";"SprayZerg";NA;650;0
"Upgrade";"EvolveMuscularAugments";NA;650;0
"Upgrade";"ZergGroundArmorsLevel2";NA;650;0
"Upgrade";"SprayZerg";NA;650;0
"Upgrade";"ZergMeleeWeaponsLevel2";NA;650;0
"Upgrade";"SprayZerg";NA;650;0
"Upgrade";"zerglingattackspeed";NA;650;0
"Upgrade";"SprayZerg";NA;650;0
"Upgrade";"SprayZerg";NA;650;0
"Upgrade";"SprayZerg";NA;650;0
"Upgrade";"ZergMeleeWeaponsLevel3";NA;650;0
"Upgrade";"ZergGroundArmorsLevel3";NA;650;0
