"type";"unit_name";"on_building";"total_supply_lag";"supply"
"Unit";"Overlord";"Larva";13;0
"Building";"SpawningPool";NA;17;0
"Building";"Hatchery";NA;19;0
"Building";"Extractor";NA;19;0
"Unit";"Zergling";"Larva";21;1
"Unit";"Zergling";"Larva";22;1
"Unit";"Queen";"Hatchery";23;2
"Unit";"Overlord";"Larva";26;0
"Unit";"Queen";"Hatchery";27;2
"Unit";"Queen";"Hatchery";31;2
"Building";"CreepTumorQueen";NA;39;0
"Unit";"Overlord";"Larva";41;0
"Unit";"Overlord";"Larva";41;0
"Building";"Hatchery";NA;41;0
"Building";"CreepTumorQueen";NA;41;0
"Building";"CreepTumor";NA;41;0
"Unit";"Queen";"Hatchery";45;2
"Unit";"Queen";"Hatchery";52;2
"Building";"SporeCrawler";NA;54;0
"Unit";"Overlord";"Larva";54;0
"Building";"CreepTumor";NA;54;0
"Building";"CreepTumorQueen";NA;58;0
"Building";"EvolutionChamber";NA;59;0
"Building";"CreepTumor";NA;59;0
"Unit";"Overlord";"Larva";59;0
"Unit";"Overlord";"Larva";59;0
"Unit";"Zergling";"Larva";59;1
"Unit";"Zergling";"Larva";60;1
"Unit";"Zergling";"Larva";61;1
"Unit";"Zergling";"Larva";62;1
"Unit";"Zergling";"Larva";63;1
"Unit";"Zergling";"Larva";64;1
"Unit";"Zergling";"Larva";65;1
"Unit";"Zergling";"Larva";66;1
"Unit";"Zergling";"Larva";67;1
"Unit";"Zergling";"Larva";68;1
"Unit";"Overlord";"Larva";69;0
"Unit";"Overlord";"Larva";69;0
"Unit";"Queen";"Hatchery";69;2
"Unit";"Zergling";"Larva";71;1
"Unit";"Zergling";"Larva";72;1
"Unit";"Zergling";"Larva";73;1
"Unit";"Zergling";"Larva";74;1
"Building";"CreepTumor";NA;75;0
"Unit";"Overlord";"Larva";75;0
"Building";"CreepTumorQueen";NA;75;0
"Building";"CreepTumor";NA;75;0
"Unit";"Zergling";"Larva";75;1
"Unit";"Zergling";"Larva";76;1
"Building";"CreepTumorQueen";NA;77;0
"Unit";"Zergling";"Larva";77;1
"Unit";"Zergling";"Larva";78;1
"Unit";"Zergling";"Larva";79;1
"Unit";"Zergling";"Larva";80;1
"Unit";"Zergling";"Larva";81;1
"Unit";"Zergling";"Larva";82;1
"Unit";"Zergling";"Larva";83;1
"Unit";"Zergling";"Larva";84;1
"Unit";"Zergling";"Larva";85;1
"Unit";"Zergling";"Larva";86;1
"Unit";"Queen";"Hatchery";87;2
"Unit";"Zergling";"Larva";89;1
"Unit";"Zergling";"Larva";90;1
"Unit";"Zergling";"Larva";91;1
"Unit";"Zergling";"Larva";92;1
"Unit";"Zergling";"Larva";93;1
"Unit";"Zergling";"Larva";94;1
"Unit";"Zergling";"Larva";95;1
"Unit";"Zergling";"Larva";96;1
"Building";"CreepTumor";NA;97;0
"Building";"SporeCrawler";NA;103;0
"Building";"CreepTumor";NA;103;0
"Building";"CreepTumor";NA;104;0
"Building";"CreepTumor";NA;104;0
"Building";"CreepTumor";NA;106;0
"Building";"EvolutionChamber";NA;109;0
"Unit";"Zergling";"Larva";109;1
"Unit";"Zergling";"Larva";110;1
"Unit";"Zergling";"Larva";111;1
"Unit";"Zergling";"Larva";112;1
"Unit";"Zergling";"Larva";113;1
"Unit";"Zergling";"Larva";114;1
"Unit";"Zergling";"Larva";115;1
"Unit";"Zergling";"Larva";116;1
"Building";"CreepTumor";NA;117;0
"Unit";"Zergling";"Larva";117;1
"Unit";"Zergling";"Larva";118;1
"Unit";"Zergling";"Larva";119;1
"Unit";"Zergling";"Larva";120;1
"Unit";"Zergling";"Larva";121;1
"Unit";"Zergling";"Larva";122;1
"Building";"CreepTumor";NA;123;0
"Building";"BanelingNest";NA;123;0
"Unit";"Zergling";"Larva";123;1
"Unit";"Zergling";"Larva";124;1
"Building";"CreepTumor";NA;125;0
"Unit";"Queen";"Hatchery";125;2
"Unit";"Overlord";"Larva";127;0
"Unit";"Zergling";"Larva";127;1
"Unit";"Zergling";"Larva";128;1
"Unit";"Zergling";"Larva";129;1
"Unit";"Zergling";"Larva";130;1
"Unit";"Zergling";"Larva";131;1
"Unit";"Zergling";"Larva";132;1
"Unit";"Zergling";"Larva";133;1
"Unit";"Zergling";"Larva";134;1
"Unit";"Overlord";"Larva";135;0
"Unit";"Overlord";"Larva";135;0
"Unit";"Overlord";"Larva";135;0
"Unit";"Queen";"Hatchery";135;2
"Building";"Extractor";NA;148;0
"Building";"Extractor";NA;148;0
"Building";"Extractor";NA;152;0
"Building";"Extractor";NA;153;0
"Building";"Extractor";NA;153;0
"Building";"CreepTumor";NA;156;0
"Building";"CreepTumor";NA;157;0
"Building";"CreepTumor";NA;157;0
"Building";"CreepTumor";NA;157;0
"Building";"CreepTumorQueen";NA;157;0
"Building";"CreepTumorQueen";NA;157;0
"Building";"RoachWarren";NA;158;0
"Building";"CreepTumorQueen";NA;160;0
"Building";"CreepTumorQueen";NA;160;0
"Building";"SpineCrawler";NA;160;0
"Unit";"Overlord";"Larva";160;0
"Building";"CreepTumorQueen";NA;164;0
"Building";"CreepTumorQueen";NA;164;0
"Unit";"Overlord";"Larva";164;0
"Building";"CreepTumor";NA;164;0
"Building";"CreepTumorQueen";NA;164;0
"Building";"CreepTumorQueen";NA;164;0
"Building";"CreepTumorQueen";NA;164;0
"Building";"CreepTumorQueen";NA;164;0
"Building";"CreepTumor";NA;164;0
"Unit";"Overlord";"Larva";164;0
"Unit";"Roach";"Larva";164;2
"Unit";"Roach";"Larva";166;2
"Unit";"Roach";"Larva";168;2
"Unit";"Roach";"Larva";170;2
"Unit";"Roach";"Larva";172;2
"Unit";"Roach";"Larva";174;2
"Unit";"Roach";"Larva";176;2
"Building";"Hatchery";NA;178;0
"Building";"CreepTumor";NA;178;0
"Building";"CreepTumor";NA;178;0
"Building";"CreepTumor";NA;178;0
"Building";"CreepTumor";NA;178;0
"Unit";"Overlord";"Larva";178;0
"Unit";"Overlord";"Larva";181;0
"Building";"CreepTumor";NA;181;0
"Building";"CreepTumor";NA;181;0
"Building";"CreepTumor";NA;181;0
"Building";"CreepTumorQueen";NA;181;0
"Building";"CreepTumorQueen";NA;181;0
"Building";"CreepTumorQueen";NA;181;0
"Upgrade";"Burrow";"Hatchery";181;0
"Building";"HydraliskDen";NA;186;0
"Building";"CreepTumorQueen";NA;194;0
"Building";"CreepTumorQueen";NA;194;0
"Building";"CreepTumor";NA;194;0
"Building";"CreepTumor";NA;194;0
"Building";"CreepTumor";NA;194;0
"Building";"CreepTumor";NA;194;0
"Building";"CreepTumor";NA;194;0
"Building";"CreepTumor";NA;194;0
"Building";"CreepTumor";NA;194;0
"Building";"CreepTumor";NA;194;0
"Unit";"Roach";"Larva";194;2
"Unit";"Roach";"Larva";196;2
"Unit";"Roach";"Larva";198;2
"Unit";"Roach";"Larva";200;2
"Unit";"Roach";"Larva";202;2
"Unit";"Roach";"Larva";204;2
"Building";"Extractor";NA;206;0
"Upgrade";"GlialReconstitution";"RoachWarren";206;0
"Unit";"Overlord";"Larva";206;0
"Building";"InfestationPit";NA;206;0
"Building";"CreepTumor";NA;206;0
"Building";"CreepTumor";NA;206;0
"Building";"CreepTumor";NA;206;0
"Building";"CreepTumor";NA;206;0
"Building";"CreepTumorQueen";NA;206;0
"Building";"CreepTumorQueen";NA;206;0
"Building";"CreepTumorQueen";NA;206;0
"Building";"CreepTumorQueen";NA;206;0
"Unit";"Hydralisk";"Larva";206;2
"Unit";"Hydralisk";"Larva";208;2
"Unit";"Hydralisk";"Larva";210;2
"Building";"CreepTumor";NA;212;0
"Building";"CreepTumor";NA;212;0
"Building";"CreepTumor";NA;212;0
"Unit";"Overlord";"Larva";212;0
"Building";"CreepTumor";NA;212;0
"Building";"CreepTumorQueen";NA;212;0
"Building";"CreepTumorQueen";NA;212;0
"Unit";"Hydralisk";"Larva";212;2
"Unit";"Hydralisk";"Larva";214;2
"Unit";"Hydralisk";"Larva";216;2
"Unit";"Hydralisk";"Larva";218;2
"Unit";"Hydralisk";"Larva";220;2
"Unit";"Hydralisk";"Larva";222;2
"Unit";"Hydralisk";"Larva";224;2
"Unit";"Hydralisk";"Larva";226;2
"Unit";"Hydralisk";"Larva";228;2
"Unit";"Hydralisk";"Larva";230;2
"Unit";"Hydralisk";"Larva";232;2
"Unit";"Hydralisk";"Larva";234;2
"Unit";"Roach";"Larva";236;2
"Unit";"Roach";"Larva";238;2
"Unit";"Hydralisk";"Larva";240;2
"Unit";"Hydralisk";"Larva";242;2
"Unit";"Hydralisk";"Larva";244;2
"Unit";"Hydralisk";"Larva";246;2
"Unit";"Hydralisk";"Larva";248;2
"Unit";"Hydralisk";"Larva";250;2
"Unit";"Hydralisk";"Larva";252;2
"Unit";"Hydralisk";"Larva";254;2
"Unit";"Hydralisk";"Larva";256;2
"Building";"CreepTumor";NA;258;0
"Building";"CreepTumor";NA;258;0
"Building";"CreepTumor";NA;258;0
"Building";"CreepTumor";NA;258;0
"Building";"CreepTumor";NA;258;0
"Unit";"Overlord";"Larva";258;0
"Unit";"Overlord";"Larva";258;0
"Unit";"Overlord";"Larva";258;0
"Unit";"Overlord";"Larva";258;0
"Unit";"Overlord";"Larva";258;0
"Unit";"Overlord";"Larva";258;0
"Unit";"Overlord";"Larva";258;0
"Unit";"Hydralisk";"Larva";258;2
"Building";"CreepTumor";NA;260;0
"Unit";"Overlord";"Larva";260;0
"Unit";"Overlord";"Larva";260;0
"Unit";"Hydralisk";"Larva";260;2
"Unit";"Hydralisk";"Larva";262;2
"Unit";"Hydralisk";"Larva";264;2
"Unit";"Hydralisk";"Larva";266;2
"Unit";"Hydralisk";"Larva";268;2
"Unit";"Hydralisk";"Larva";270;2
"Unit";"Hydralisk";"Larva";272;2
"Building";"CreepTumorQueen";NA;274;0
"Building";"CreepTumor";NA;274;0
"Building";"CreepTumor";NA;274;0
"Building";"CreepTumor";NA;274;0
"Building";"CreepTumor";NA;274;0
"Building";"CreepTumor";NA;274;0
"Unit";"Hydralisk";"Larva";274;2
"Unit";"Hydralisk";"Larva";276;2
"Unit";"Hydralisk";"Larva";278;2
"Building";"CreepTumorQueen";NA;280;0
"Building";"CreepTumorQueen";NA;282;0
"Building";"Hatchery";NA;282;0
"Building";"Extractor";NA;284;0
"Building";"CreepTumor";NA;284;0
"Building";"CreepTumor";NA;284;0
"Building";"CreepTumor";NA;284;0
"Building";"CreepTumor";NA;284;0
"Building";"CreepTumor";NA;284;0
"Building";"CreepTumor";NA;284;0
"Building";"CreepTumorQueen";NA;284;0
"Building";"CreepTumorQueen";NA;284;0
"Building";"CreepTumorQueen";NA;284;0
"Building";"CreepTumorQueen";NA;284;0
"Building";"BanelingNest";NA;284;0
"Unit";"Roach";"Larva";284;2
"Unit";"Roach";"Larva";286;2
"Unit";"Roach";"Larva";288;2
"Unit";"Roach";"Larva";290;2
"Unit";"Roach";"Larva";292;2
"Unit";"Roach";"Larva";294;2
"Building";"Spire";NA;296;0
"Building";"CreepTumor";NA;296;0
"Building";"CreepTumorQueen";NA;296;0
"Building";"CreepTumorQueen";NA;296;0
"Unit";"Roach";"Larva";296;2
"Unit";"Roach";"Larva";298;2
"Unit";"Roach";"Larva";300;2
"Unit";"Roach";"Larva";302;2
"Unit";"Roach";"Larva";304;2
"Unit";"Roach";"Larva";306;2
"Unit";"Roach";"Larva";308;2
"Unit";"Roach";"Larva";310;2
"Unit";"Roach";"Larva";312;2
"Unit";"Roach";"Larva";314;2
"Unit";"Roach";"Larva";316;2
"Unit";"Roach";"Larva";318;2
"Unit";"Roach";"Larva";320;2
"Unit";"Roach";"Larva";322;2
"Unit";"Roach";"Larva";324;2
"Unit";"Roach";"Larva";326;2
"Unit";"Overlord";"Larva";328;0
"Unit";"Roach";"Larva";328;2
"Unit";"Roach";"Larva";330;2
"Unit";"Roach";"Larva";332;2
"Unit";"Roach";"Larva";334;2
"Unit";"Roach";"Larva";336;2
"Unit";"Roach";"Larva";338;2
"Unit";"Roach";"Larva";340;2
"Unit";"Roach";"Larva";342;2
"Unit";"Roach";"Larva";344;2
"Unit";"Roach";"Larva";346;2
"Unit";"Roach";"Larva";348;2
"Unit";"Roach";"Larva";350;2
"Unit";"Viper";"Larva";352;3
"Unit";"Roach";"Larva";355;2
"Unit";"Zergling";"Larva";357;1
"Unit";"Zergling";"Larva";358;1
"Unit";"Zergling";"Larva";359;1
"Unit";"Zergling";"Larva";360;1
"Unit";"Zergling";"Larva";361;1
"Unit";"Zergling";"Larva";362;1
"Unit";"Roach";"Larva";363;2
"Unit";"Roach";"Larva";365;2
"Unit";"Roach";"Larva";367;2
"Unit";"Roach";"Larva";369;2
"Unit";"Roach";"Larva";371;2
"Unit";"Roach";"Larva";373;2
"Unit";"Roach";"Larva";375;2
"Unit";"Roach";"Larva";377;2
"Unit";"Roach";"Larva";379;2
"Unit";"Roach";"Larva";381;2
"Unit";"Roach";"Larva";383;2
"Unit";"Roach";"Larva";385;2
"Unit";"Roach";"Larva";387;2
"Unit";"Roach";"Larva";389;2
"Unit";"Roach";"Larva";391;2
"Unit";"Roach";"Larva";393;2
"Unit";"Roach";"Larva";395;2
"Unit";"Roach";"Larva";397;2
"Unit";"Roach";"Larva";399;2
"Unit";"Roach";"Larva";401;2
"Unit";"Roach";"Larva";403;2
"Unit";"Roach";"Larva";405;2
"Unit";"Roach";"Larva";407;2
"Unit";"Roach";"Larva";409;2
"Unit";"Roach";"Larva";411;2
"Unit";"Roach";"Larva";413;2
"Unit";"Roach";"Larva";415;2
"Unit";"Roach";"Larva";417;2
"Unit";"Roach";"Larva";419;2
"Unit";"Roach";"Larva";421;2
"Unit";"Roach";"Larva";423;2
"Unit";"Hydralisk";"Larva";425;2
"Unit";"Hydralisk";"Larva";427;2
"Unit";"Hydralisk";"Larva";429;2
"Unit";"Hydralisk";"Larva";431;2
"Unit";"Hydralisk";"Larva";440;2
"Unit";"Hydralisk";"Larva";442;2
"Unit";"Hydralisk";"Larva";444;2
"Unit";"Hydralisk";"Larva";446;2
"Unit";"Hydralisk";"Larva";448;2
"Unit";"Hydralisk";"Larva";450;2
"Unit";"Hydralisk";"Larva";455;2
"Building";"CreepTumor";NA;457;0
"Building";"CreepTumor";NA;457;0
"Building";"CreepTumor";NA;457;0
"Building";"CreepTumorQueen";NA;457;0
"Building";"CreepTumor";NA;457;0
"Unit";"Hydralisk";"Larva";457;2
"Building";"CreepTumor";NA;459;0
"Building";"CreepTumor";NA;459;0
"Building";"CreepTumorQueen";NA;459;0
"Building";"CreepTumorQueen";NA;459;0
"Building";"Extractor";NA;462;0
"Building";"Extractor";NA;462;0
"Unit";"Hydralisk";"Larva";462;2
"Unit";"Hydralisk";"Larva";466;2
"Unit";"Hydralisk";"Larva";468;2
"Building";"CreepTumor";NA;470;0
"Building";"CreepTumor";NA;470;0
"Unit";"Hydralisk";"Larva";470;2
"Unit";"Roach";"Larva";472;2
"Unit";"Hydralisk";"Larva";474;2
"Building";"CreepTumor";NA;476;0
"Building";"CreepTumorQueen";NA;476;0
"Building";"CreepTumor";NA;476;0
"Building";"CreepTumor";NA;476;0
"Unit";"Hydralisk";"Larva";476;2
"Unit";"Hydralisk";"Larva";478;2
"Building";"CreepTumorQueen";NA;480;0
"Building";"CreepTumor";NA;480;0
"Building";"CreepTumor";NA;480;0
"Building";"CreepTumor";NA;480;0
"Building";"CreepTumor";NA;483;0
"Building";"CreepTumor";NA;483;0
"Unit";"Hydralisk";"Larva";483;2
"Unit";"Hydralisk";"Larva";485;2
"Upgrade";"TunnelingClaws";"RoachWarren";487;0
"Unit";"Hydralisk";"Larva";487;2
"Unit";"Hydralisk";"Larva";489;2
"Unit";"Hydralisk";"Larva";491;2
"Building";"Hatchery";NA;493;0
"Unit";"Hydralisk";"Larva";493;2
"Building";"CreepTumorQueen";NA;507;0
"Building";"CreepTumorQueen";NA;508;0
"Building";"CreepTumorQueen";NA;508;0
"Building";"CreepTumor";NA;508;0
"Building";"CreepTumorQueen";NA;508;0
"Building";"CreepTumor";NA;508;0
"Building";"EvolutionChamber";NA;508;0
"Unit";"Viper";"Larva";508;3
"Unit";"Viper";"Larva";511;3
"Unit";"Viper";"Larva";514;3
"Building";"CreepTumor";NA;517;0
"Building";"CreepTumorQueen";NA;517;0
"Unit";"Roach";"Larva";517;2
"Unit";"Roach";"Larva";519;2
"Unit";"Roach";"Larva";521;2
"Unit";"Roach";"Larva";523;2
"Unit";"Roach";"Larva";525;2
"Unit";"Roach";"Larva";527;2
"Unit";"Roach";"Larva";529;2
"Unit";"Roach";"Larva";531;2
"Building";"CreepTumor";NA;533;0
"Building";"CreepTumor";NA;533;0
"Unit";"Roach";"Larva";533;2
"Unit";"Roach";"Larva";535;2
"Unit";"Roach";"Larva";537;2
"Unit";"Roach";"Larva";539;2
"Unit";"Roach";"Larva";541;2
"Unit";"Roach";"Larva";543;2
"Unit";"Roach";"Larva";545;2
"Unit";"Roach";"Larva";547;2
"Unit";"Roach";"Larva";549;2
"Unit";"Roach";"Larva";551;2
"Unit";"Roach";"Larva";553;2
"Unit";"Roach";"Larva";555;2
"Unit";"Roach";"Larva";557;2
"Unit";"Roach";"Larva";559;2
"Unit";"Roach";"Larva";561;2
"Building";"CreepTumorQueen";NA;563;0
"Building";"CreepTumorQueen";NA;563;0
"Building";"CreepTumorQueen";NA;563;0
"Building";"CreepTumorQueen";NA;563;0
"Building";"CreepTumorQueen";NA;563;0
"Building";"CreepTumorQueen";NA;563;0
"Building";"CreepTumor";NA;563;0
"Unit";"Roach";"Larva";563;2
"Unit";"Roach";"Larva";565;2
"Unit";"Roach";"Larva";567;2
"Unit";"Roach";"Larva";569;2
"Unit";"Roach";"Larva";571;2
"Unit";"Roach";"Larva";573;2
"Unit";"Roach";"Larva";575;2
"Unit";"Roach";"Larva";577;2
"Unit";"Viper";"Larva";579;3
"Unit";"Viper";"Larva";582;3
"Unit";"Viper";"Larva";585;3
"Unit";"Roach";"Larva";588;2
"Unit";"Roach";"Larva";590;2
"Unit";"Roach";"Larva";592;2
"Building";"SpineCrawler";NA;594;0
"Building";"SpineCrawler";NA;598;0
"Building";"SpineCrawler";NA;598;0
"Building";"SpineCrawler";NA;598;0
"Building";"SpineCrawler";NA;598;0
"Building";"SpineCrawler";NA;598;0
"Building";"SpineCrawler";NA;600;0
"Building";"Extractor";NA;600;0
"Building";"SpineCrawler";NA;600;0
"Building";"EvolutionChamber";NA;602;0
"Building";"CreepTumorQueen";NA;604;0
"Building";"CreepTumorQueen";NA;604;0
"Building";"CreepTumorQueen";NA;607;0
"Building";"CreepTumorQueen";NA;607;0
"Building";"SpineCrawler";NA;607;0
"Building";"Extractor";NA;607;0
"Building";"SpineCrawler";NA;607;0
"Unit";"Corruptor";"Larva";607;2
"Unit";"Corruptor";"Larva";609;2
"Unit";"Corruptor";"Larva";611;2
"Unit";"Corruptor";"Larva";613;2
"Unit";"Corruptor";"Larva";615;2
"Unit";"Corruptor";"Larva";617;2
"Building";"CreepTumor";NA;619;0
"Building";"CreepTumor";NA;619;0
"Building";"CreepTumor";NA;619;0
"Building";"CreepTumor";NA;619;0
"Building";"CreepTumor";NA;619;0
"Building";"CreepTumor";NA;619;0
"Building";"CreepTumorQueen";NA;619;0
"Building";"CreepTumorQueen";NA;619;0
"Building";"CreepTumorQueen";NA;619;0
"Building";"CreepTumorQueen";NA;619;0
"Unit";"Corruptor";"Larva";619;2
"Unit";"Corruptor";"Larva";621;2
"Unit";"Corruptor";"Larva";623;2
"Building";"CreepTumorQueen";NA;625;0
"Building";"CreepTumorQueen";NA;626;0
"Building";"CreepTumor";NA;632;0
"Building";"CreepTumor";NA;632;0
"Building";"CreepTumor";NA;632;0
"Building";"CreepTumor";NA;632;0
"Building";"CreepTumor";NA;634;0
"Building";"CreepTumor";NA;634;0
"Building";"CreepTumor";NA;634;0
"Building";"CreepTumor";NA;634;0
"Building";"CreepTumor";NA;634;0
"Building";"CreepTumor";NA;634;0
"Building";"CreepTumor";NA;634;0
"Building";"CreepTumor";NA;634;0
"Building";"CreepTumor";NA;634;0
"Building";"Hatchery";NA;634;0
"Building";"Spire";NA;634;0
"Building";"CreepTumor";NA;634;0
"Building";"CreepTumor";NA;634;0
"Building";"CreepTumor";NA;634;0
"Building";"CreepTumor";NA;634;0
"Building";"Extractor";NA;637;0
"Building";"CreepTumor";NA;637;0
"Building";"CreepTumor";NA;637;0
"Building";"Extractor";NA;644;0
"Upgrade";"SprayZerg";NA;644;0
"Upgrade";"SprayZerg";NA;644;0
"Upgrade";"SprayZerg";NA;644;0
"Upgrade";"zerglingmovementspeed";NA;644;0
"Upgrade";"SprayZerg";NA;644;0
"Upgrade";"ZergGroundArmorsLevel1";NA;644;0
"Upgrade";"overlordspeed";NA;644;0
"Upgrade";"SprayZerg";NA;644;0
"Upgrade";"SprayZerg";NA;644;0
"Upgrade";"ZergMeleeWeaponsLevel1";NA;644;0
"Upgrade";"SprayZerg";NA;644;0
"Upgrade";"ZergMissileWeaponsLevel1";NA;644;0
"Upgrade";"EvolveMuscularAugments";NA;644;0
"Upgrade";"SprayZerg";NA;644;0
"Upgrade";"ZergGroundArmorsLevel2";NA;644;0
"Upgrade";"SprayZerg";NA;644;0
"Upgrade";"SprayZerg";NA;644;0
"Upgrade";"SprayZerg";NA;644;0
"Upgrade";"ZergMissileWeaponsLevel2";NA;644;0
"Upgrade";"SprayZerg";NA;644;0
"Upgrade";"SprayZerg";NA;644;0
