"type";"unit_name";"on_building";"total_supply_lag";"supply"
"Building";"Barracks";NA;16;0
"Building";"Refinery";NA;16;0
"Building";"Barracks";NA;17;0
"Building";"Barracks";NA;19;0
"Unit";"Reaper";"Barracks";19;1
"Building";"Refinery";NA;20;0
"Unit";"Reaper";"Barracks";20;1
"Unit";"Reaper";"Barracks";21;1
"Unit";"Reaper";"Barracks";22;1
"Unit";"Reaper";"Barracks";24;1
"Unit";"Reaper";"Barracks";26;1
"Unit";"Reaper";"Barracks";28;1
"Unit";"Reaper";"Barracks";29;1
"Unit";"Reaper";"Barracks";31;1
"Unit";"Reaper";"Barracks";33;1
"Unit";"Reaper";"Barracks";35;1
"Building";"CommandCenter";NA;36;0
"Unit";"Reaper";"Barracks";36;1
"Unit";"Reaper";"Barracks";38;1
"Unit";"Reaper";"Barracks";39;1
"Unit";"Reaper";"Barracks";41;1
"Building";"CommandCenter";NA;43;0
"Unit";"Reaper";"Barracks";43;1
"Unit";"Reaper";"Barracks";44;1
"Unit";"Reaper";"Barracks";46;1
"Unit";"Reaper";"Barracks";48;1
"Building";"Factory";NA;50;0
"Building";"Barracks";NA;50;0
"Unit";"Reaper";"Barracks";50;1
"Building";"Refinery";NA;51;0
"Building";"Refinery";NA;52;0
"Building";"Barracks";NA;53;0
"Unit";"Reaper";"Barracks";54;1
"Unit";"Reaper";"Barracks";56;1
"Unit";"Reaper";"Barracks";59;1
"Building";"EngineeringBay";NA;60;0
"Building";"EngineeringBay";NA;60;0
"Building";"BarracksTechLab";NA;62;0
"Building";"BarracksTechLab";NA;62;0
"Building";"BarracksReactor";NA;63;0
"Building";"BarracksReactor";NA;64;0
"Building";"BarracksReactor";NA;65;0
"Unit";"Marine";"Barracks";68;1
"Unit";"Marine";"Barracks";70;1
"Unit";"Marine";"Barracks";72;1
"Unit";"Marine";"Barracks";73;1
"Building";"Starport";NA;74;0
"Building";"FactoryReactor";NA;74;0
"Upgrade";"TerranInfantryWeaponsLevel1";"EngineeringBay";74;0
"Unit";"Marine";"Barracks";75;1
"Unit";"Marine";"Barracks";76;1
"Unit";"Marine";"Barracks";77;1
"Unit";"Marine";"Barracks";78;1
"Unit";"Marine";"Barracks";79;1
"Unit";"Marine";"Barracks";81;1
"Unit";"Marine";"Barracks";82;1
"Unit";"Marine";"Barracks";83;1
"Building";"Armory";NA;86;0
"Unit";"Marine";"Barracks";86;1
"Unit";"Marine";"Barracks";87;1
"Unit";"Marine";"Barracks";88;1
"Unit";"Marine";"Barracks";89;1
"Unit";"Marauder";"Barracks";90;2
"Upgrade";"Stimpack";"TechLab";92;0
"Unit";"Marine";"Barracks";93;1
"Unit";"Marine";"Barracks";94;1
"Unit";"Marine";"Barracks";95;1
"Unit";"Marine";"Barracks";99;1
"Unit";"Marine";"Barracks";100;1
"Unit";"Medivac";"Starport";101;2
"Unit";"Marauder";"Barracks";104;2
"Building";"FactoryReactor";NA;107;0
"Unit";"Marauder";"Barracks";108;2
"Unit";"Marine";"Barracks";110;1
"Unit";"Marine";"Barracks";111;1
"Unit";"Medivac";"Starport";113;2
"Unit";"Marine";"Barracks";117;1
"Unit";"Marine";"Barracks";118;1
"Unit";"Marauder";"Barracks";119;2
"Unit";"Medivac";"Starport";124;2
"Unit";"Marauder";"Barracks";126;2
"Unit";"Marine";"Barracks";128;1
"Unit";"Marine";"Barracks";129;1
"Unit";"Marine";"Barracks";130;1
"Unit";"Marine";"Barracks";131;1
"Unit";"Marine";"Barracks";132;1
"Unit";"Medivac";"Starport";133;2
"Unit";"Marauder";"Barracks";135;2
"Unit";"Marine";"Barracks";137;1
"Unit";"Marine";"Barracks";138;1
"Unit";"Marauder";"Barracks";139;2
"Unit";"Marine";"Barracks";141;1
"Unit";"Marine";"Barracks";142;1
"Unit";"Medivac";"Starport";143;2
"Building";"Refinery";NA;145;0
"Building";"Barracks";NA;145;0
"Building";"Barracks";NA;145;0
"Unit";"Marine";"Barracks";145;1
"Unit";"Marine";"Barracks";146;1
"Upgrade";"TerranInfantryWeaponsLevel2";"EngineeringBay";147;0
"Unit";"Marauder";"Barracks";147;2
"Unit";"Marine";"Barracks";149;1
"Unit";"Marine";"Barracks";150;1
"Unit";"Marine";"Barracks";151;1
"Unit";"Medivac";"Starport";152;2
"Unit";"Marine";"Barracks";154;1
"Unit";"Marine";"Barracks";155;1
"Unit";"Marine";"Barracks";156;1
"Unit";"Marauder";"Barracks";157;2
"Unit";"Medivac";"Starport";159;2
"Building";"Factory";NA;161;0
"Building";"BarracksTechLab";NA;161;0
"Building";"BarracksReactor";NA;161;0
"Unit";"Marine";"Barracks";162;1
"Unit";"Marine";"Barracks";163;1
"Unit";"Marine";"Barracks";164;1
"Unit";"Marine";"Barracks";165;1
"Unit";"Marine";"Barracks";167;1
"Unit";"Marine";"Barracks";168;1
"Unit";"Marauder";"Barracks";169;2
"Unit";"Marauder";"Barracks";171;2
"Unit";"Medivac";"Starport";173;2
"Unit";"Medivac";"Starport";175;2
"Unit";"Marine";"Barracks";177;1
"Unit";"Marine";"Barracks";178;1
"Unit";"Marine";"Barracks";179;1
"Unit";"Marine";"Barracks";180;1
"Unit";"Marauder";"Barracks";181;2
"Unit";"Marine";"Barracks";183;1
"Unit";"Marine";"Barracks";184;1
"Upgrade";"SprayTerran";NA;185;0
"Upgrade";"SprayTerran";NA;185;0
"Upgrade";"SprayTerran";NA;185;0
"Upgrade";"SprayTerran";NA;185;0
"Upgrade";"ShieldWall";NA;185;0
"Upgrade";"TerranInfantryArmorsLevel1";NA;185;0
"Upgrade";"SprayTerran";NA;185;0
