"type";"unit_name";"on_building";"total_supply";"supply"
"Unit";"Overlord";"Larva";13;0
"Building";"Extractor";NA;17;0
"Unit";"Overlord";"Larva";22;0
"Building";"SpawningPool";NA;19;0
"Building";"Hatchery";NA;17;0
"Unit";"Zergling";"Larva";22;1
"Unit";"Zergling";"Larva";22;1
"Unit";"Zergling";"Larva";22;1
"Unit";"Zergling";"Larva";22;1
"Unit";"Queen";"Hatchery";22;2
"Unit";"Queen";"Hatchery";22;2
"Building";"BanelingNest";NA;29;0
"Unit";"Overlord";"Larva";38;0
"Unit";"Overlord";"Larva";40;0
"Unit";"Overlord";"Larva";48;0
"Building";"EvolutionChamber";NA;48;0
"Building";"Hatchery";NA;38;0
"Unit";"Queen";"Hatchery";48;2
"Building";"Extractor";NA;53;0
"Building";"CreepTumorQueen";NA;58;0
"Unit";"Overlord";"Larva";64;0
"Building";"Extractor";NA;64;0
"Unit";"Overlord";"Larva";71;0
"Unit";"Overlord";"Larva";71;0
"Unit";"Overlord";"Larva";76;0
"Unit";"Overlord";"Larva";76;0
"Building";"CreepTumor";NA;76;0
"Building";"RoachWarren";NA;64;0
"Unit";"Queen";"Hatchery";76;2
"Unit";"Roach";"Larva";76;2
"Unit";"Roach";"Larva";76;2
"Unit";"Roach";"Larva";76;2
"Unit";"Roach";"Larva";76;2
"Unit";"Roach";"Larva";76;2
"Unit";"Roach";"Larva";76;2
"Unit";"Roach";"Larva";76;2
"Unit";"Roach";"Larva";76;2
"Unit";"Roach";"Larva";76;2
"Unit";"Roach";"Larva";76;2
"Building";"Extractor";NA;76;0
"Building";"Extractor";NA;76;0
"Unit";"Roach";"Larva";76;2
"Unit";"Overlord";"Larva";76;0
"Unit";"Overlord";"Larva";76;0
"Unit";"Overlord";"Larva";76;0
"Unit";"Overlord";"Larva";76;0
"Unit";"Roach";"Larva";78;2
"Unit";"Roach";"Larva";98;2
"Unit";"Roach";"Larva";98;2
"Unit";"Roach";"Larva";98;2
"Building";"SpineCrawler";NA;76;0
"Upgrade";"ZergMissileWeaponsLevel1";"EvolutionChamber";70;0
"Unit";"Roach";"Larva";98;2
"Unit";"Roach";"Larva";98;2
"Unit";"Overlord";"Larva";100;0
"Unit";"Overlord";"Larva";100;0
"Unit";"Roach";"Larva";100;2
"Unit";"Roach";"Larva";102;2
"Unit";"Roach";"Larva";102;2
"Unit";"Roach";"Larva";112;2
"Unit";"Roach";"Larva";112;2
"Unit";"Roach";"Larva";112;2
"Unit";"Overlord";"Larva";118;0
"Upgrade";"GlialReconstitution";"RoachWarren";98;0
"Building";"CreepTumor";NA;133;0
"Unit";"Roach";"Larva";133;2
"Unit";"Roach";"Larva";133;2
"Unit";"Roach";"Larva";133;2
"Unit";"Overlord";"Larva";133;0
"Unit";"Roach";"Larva";133;2
"Unit";"Roach";"Larva";133;2
"Unit";"Roach";"Larva";133;2
"Unit";"Roach";"Larva";133;2
"Unit";"Roach";"Larva";133;2
"Unit";"Roach";"Larva";133;2
"Unit";"Roach";"Larva";133;2
"Unit";"Roach";"Larva";133;2
"Unit";"Roach";"Larva";139;2
"Unit";"Roach";"Larva";139;2
"Unit";"Roach";"Larva";139;2
"Unit";"Overlord";"Larva";139;0
"Unit";"Roach";"Larva";145;2
"Unit";"Roach";"Larva";145;2
"Unit";"Roach";"Larva";145;2
"Building";"Extractor";NA;145;0
"Unit";"Roach";"Larva";145;2
"Unit";"Roach";"Larva";145;2
"Unit";"Roach";"Larva";155;2
"Unit";"Roach";"Larva";155;2
"Unit";"Roach";"Larva";157;2
"Building";"EvolutionChamber";NA;155;0
"Unit";"Roach";"Larva";161;2
"Unit";"Roach";"Larva";163;2
"Unit";"Roach";"Larva";163;2
"Unit";"Roach";"Larva";163;2
"Unit";"Roach";"Larva";163;2
"Unit";"Roach";"Larva";171;2
"Unit";"Roach";"Larva";171;2
"Unit";"Roach";"Larva";171;2
"Unit";"Roach";"Larva";171;2
"Unit";"Overlord";"Larva";175;0
"Building";"Hatchery";NA;133;0
"Unit";"Overlord";"Larva";177;0
"Unit";"Overlord";"Larva";177;0
"Unit";"Overlord";"Larva";187;0
"Unit";"Overlord";"Larva";187;0
"Unit";"Roach";"Larva";195;2
"Unit";"Roach";"Larva";195;2
"Unit";"Roach";"Larva";195;2
"Unit";"Roach";"Larva";195;2
"Unit";"Roach";"Larva";195;2
"Unit";"Roach";"Larva";195;2
"Unit";"Roach";"Larva";195;2
"Unit";"Roach";"Larva";195;2
"Unit";"Roach";"Larva";195;2
"Unit";"Roach";"Larva";195;2
"Unit";"Roach";"Larva";195;2
"Unit";"Roach";"Larva";195;2
"Unit";"Roach";"Larva";195;2
"Unit";"Roach";"Larva";195;2
"Unit";"Roach";"Larva";205;2
"Unit";"Roach";"Larva";205;2
"Unit";"Roach";"Larva";205;2
"Unit";"Roach";"Larva";205;2
"Unit";"Roach";"Larva";205;2
"Unit";"Roach";"Larva";223;2
"Upgrade";"ZergMissileWeaponsLevel2";"EvolutionChamber";167;0
"Unit";"Roach";"Larva";223;2
"Unit";"Roach";"Larva";223;2
"Unit";"Roach";"Larva";223;2
"Unit";"Roach";"Larva";223;2
"Unit";"Roach";"Larva";223;2
"Unit";"Roach";"Larva";223;2
"Unit";"Overlord";"Larva";233;0
"Unit";"Roach";"Larva";233;2
"Unit";"Roach";"Larva";233;2
"Unit";"Roach";"Larva";234;2
"Unit";"Roach";"Larva";238;2
"Unit";"Roach";"Larva";238;2
"Unit";"Roach";"Larva";238;2
"Unit";"Roach";"Larva";238;2
"Upgrade";"ZergGroundArmorsLevel1";"EvolutionChamber";195;0
"Building";"SpineCrawler";NA;238;0
"Building";"HydraliskDen";NA;258;0
"Unit";"Roach";"Larva";266;2
"Unit";"Roach";"Larva";266;2
"Unit";"Roach";"Larva";266;2
"Unit";"Roach";"Larva";266;2
"Unit";"Roach";"Larva";266;2
"Unit";"Roach";"Larva";266;2
"Unit";"Roach";"Larva";266;2
"Unit";"Roach";"Larva";266;2
"Unit";"Roach";"Larva";266;2
"Unit";"Roach";"Larva";266;2
"Unit";"Roach";"Larva";266;2
"Building";"CreepTumorQueen";NA;266;0
"Building";"CreepTumorQueen";NA;266;0
"Unit";"Roach";"Larva";266;2
"Unit";"Roach";"Larva";266;2
"Unit";"Roach";"Larva";266;2
"Unit";"Roach";"Larva";266;2
"Unit";"Roach";"Larva";266;2
"Unit";"Roach";"Larva";266;2
"Unit";"Roach";"Larva";266;2
"Unit";"Roach";"Larva";266;2
"Building";"CreepTumorQueen";NA;288;0
"Building";"Extractor";NA;288;0
"Unit";"Roach";"Larva";288;2
"Unit";"Roach";"Larva";288;2
"Unit";"Roach";"Larva";288;2
"Unit";"Roach";"Larva";288;2
"Unit";"Roach";"Larva";298;2
"Unit";"Roach";"Larva";298;2
"Unit";"Roach";"Larva";308;2
"Unit";"Roach";"Larva";308;2
"Unit";"Roach";"Larva";308;2
"Unit";"Hydralisk";"Larva";328;2
"Unit";"Hydralisk";"Larva";328;2
"Unit";"Hydralisk";"Larva";328;2
"Unit";"Hydralisk";"Larva";328;2
"Unit";"Hydralisk";"Larva";328;2
"Unit";"Hydralisk";"Larva";328;2
"Unit";"Hydralisk";"Larva";328;2
"Unit";"Hydralisk";"Larva";328;2
"Building";"LurkerDenMP";NA;288;0
"Building";"Extractor";NA;344;0
"Building";"Hatchery";NA;320;0
"Building";"SpineCrawler";NA;344;0
"Building";"SpineCrawler";NA;344;0
"Upgrade";"EvolveGroovedSpines";"HydraliskDen";344;0
"Building";"InfestationPit";NA;348;0
"Unit";"Roach";"Larva";348;2
"Unit";"Roach";"Larva";348;2
"Unit";"Roach";"Larva";348;2
"Unit";"Roach";"Larva";348;2
"Unit";"Roach";"Larva";348;2
"Unit";"Roach";"Larva";348;2
"Unit";"Roach";"Larva";348;2
"Unit";"Roach";"Larva";348;2
"Unit";"Roach";"Larva";348;2
"Unit";"Roach";"Larva";348;2
"Unit";"Roach";"Larva";348;2
"Unit";"Roach";"Larva";348;2
"Unit";"Roach";"Larva";348;2
"Unit";"Roach";"Larva";348;2
"Unit";"Roach";"Larva";348;2
"Unit";"Roach";"Larva";348;2
"Unit";"Roach";"Larva";348;2
"Unit";"Roach";"Larva";348;2
"Unit";"Roach";"Larva";348;2
"Unit";"Roach";"Larva";348;2
"Unit";"Roach";"Larva";348;2
"Unit";"Roach";"Larva";348;2
"Unit";"Roach";"Larva";348;2
"Upgrade";"EvolveMuscularAugments";"HydraliskDen";348;0
"Unit";"Queen";"Hatchery";348;2
"Unit";"Roach";"Larva";348;2
"Unit";"Roach";"Larva";348;2
"Unit";"Roach";"Larva";348;2
"Unit";"Roach";"Larva";348;2
"Unit";"Roach";"Larva";348;2
"Unit";"Roach";"Larva";348;2
"Unit";"Roach";"Larva";348;2
"Unit";"Roach";"Larva";348;2
"Unit";"Roach";"Larva";348;2
"Unit";"Roach";"Larva";348;2
"Unit";"Roach";"Larva";348;2
"Unit";"Roach";"Larva";348;2
"Unit";"Roach";"Larva";348;2
"Unit";"Roach";"Larva";396;2
"Unit";"Roach";"Larva";398;2
"Unit";"Roach";"Larva";398;2
"Unit";"Roach";"Larva";422;2
"Unit";"Roach";"Larva";422;2
"Unit";"Roach";"Larva";424;2
"Unit";"Roach";"Larva";424;2
"Unit";"Roach";"Larva";424;2
"Unit";"Roach";"Larva";424;2
"Unit";"Roach";"Larva";424;2
"Unit";"Roach";"Larva";424;2
"Unit";"Roach";"Larva";424;2
"Unit";"Roach";"Larva";428;2
"Unit";"Roach";"Larva";428;2
"Unit";"Roach";"Larva";428;2
"Unit";"Roach";"Larva";428;2
"Unit";"Roach";"Larva";428;2
"Unit";"Roach";"Larva";428;2
"Unit";"Roach";"Larva";428;2
"Unit";"Roach";"Larva";428;2
"Unit";"Roach";"Larva";428;2
"Unit";"Roach";"Larva";428;2
"Unit";"Roach";"Larva";428;2
"Unit";"Roach";"Larva";428;2
"Unit";"Roach";"Larva";428;2
"Unit";"Roach";"Larva";428;2
"Unit";"Roach";"Larva";428;2
"Unit";"Roach";"Larva";428;2
"Unit";"Roach";"Larva";428;2
"Unit";"Hydralisk";"Larva";450;2
"Unit";"Hydralisk";"Larva";450;2
"Unit";"Hydralisk";"Larva";450;2
"Unit";"Hydralisk";"Larva";450;2
"Unit";"Hydralisk";"Larva";450;2
"Building";"CreepTumorQueen";NA;480;0
"Building";"CreepTumorQueen";NA;480;0
"Building";"Extractor";NA;480;0
"Building";"Extractor";NA;480;0
"Unit";"Hydralisk";"Larva";480;2
"Unit";"Hydralisk";"Larva";480;2
"Unit";"Hydralisk";"Larva";480;2
"Unit";"Hydralisk";"Larva";480;2
"Unit";"Hydralisk";"Larva";480;2
"Building";"Hatchery";NA;428;0
"Building";"SpineCrawler";NA;490;0
"Building";"SpineCrawler";NA;490;0
"Building";"SpineCrawler";NA;490;0
"Building";"SpineCrawler";NA;490;0
"Unit";"Hydralisk";"Larva";505;2
"Unit";"Hydralisk";"Larva";505;2
"Unit";"Hydralisk";"Larva";505;2
"Unit";"Hydralisk";"Larva";505;2
"Unit";"Hydralisk";"Larva";505;2
"Unit";"Roach";"Larva";515;2
"Unit";"Roach";"Larva";515;2
"Unit";"Roach";"Larva";515;2
"Unit";"Roach";"Larva";515;2
"Unit";"Roach";"Larva";515;2
"Unit";"Roach";"Larva";515;2
"Unit";"Roach";"Larva";515;2
"Unit";"Roach";"Larva";515;2
"Unit";"Roach";"Larva";515;2
"Unit";"Roach";"Larva";515;2
"Unit";"Roach";"Larva";515;2
"Unit";"Roach";"Larva";515;2
"Unit";"Roach";"Larva";515;2
