"type";"unit_name";"on_building";"total_supply";"supply"
"Unit";"Overlord";"Larva";13;0
"Building";"Extractor";NA;17;0
"Building";"SpawningPool";NA;17;0
"Unit";"Overlord";"Larva";22;0
"Unit";"Zergling";"Larva";22;1
"Unit";"Zergling";"Larva";22;1
"Unit";"Queen";"Hatchery";21;2
"Building";"Hatchery";NA;18;0
"Unit";"Queen";"Hatchery";24;2
"Unit";"Zergling";"Larva";32;1
"Unit";"Zergling";"Larva";32;1
"Unit";"Zergling";"Larva";32;1
"Unit";"Zergling";"Larva";32;1
"Unit";"Zergling";"Larva";32;1
"Unit";"Zergling";"Larva";32;1
"Unit";"Zergling";"Larva";34;1
"Unit";"Zergling";"Larva";34;1
"Unit";"Zergling";"Larva";34;1
"Unit";"Zergling";"Larva";34;1
"Unit";"Overlord";"Larva";48;0
"Unit";"Overlord";"Larva";48;0
"Building";"Hatchery";NA;30;0
"Building";"CreepTumorQueen";NA;49;0
"Unit";"Queen";"Hatchery";48;2
"Building";"EvolutionChamber";NA;48;0
"Building";"Extractor";NA;56;0
"Building";"Extractor";NA;58;0
"Unit";"Overlord";"Larva";64;0
"Building";"RoachWarren";NA;58;0
"Building";"Extractor";NA;71;0
"Unit";"Overlord";"Larva";71;0
"Unit";"Overlord";"Larva";71;0
"Building";"CreepTumor";NA;71;0
"Unit";"Roach";"Larva";71;2
"Unit";"Overlord";"Larva";71;0
"Unit";"Roach";"Larva";72;2
"Unit";"Roach";"Larva";79;2
"Unit";"Roach";"Larva";79;2
"Unit";"Roach";"Larva";79;2
"Unit";"Roach";"Larva";79;2
"Unit";"Roach";"Larva";79;2
"Unit";"Overlord";"Larva";83;0
"Unit";"Overlord";"Larva";83;0
"Unit";"Overlord";"Larva";93;0
"Unit";"Overlord";"Larva";94;0
"Unit";"Overlord";"Larva";94;0
"Upgrade";"ZergMissileWeaponsLevel1";"EvolutionChamber";71;0
"Building";"Extractor";NA;99;0
"Building";"Extractor";NA;99;0
"Unit";"Overlord";"Larva";102;0
"Unit";"Roach";"Larva";111;2
"Unit";"Roach";"Larva";111;2
"Unit";"Roach";"Larva";111;2
"Unit";"Roach";"Larva";111;2
"Unit";"Roach";"Larva";111;2
"Unit";"Roach";"Larva";111;2
"Unit";"Roach";"Larva";111;2
"Unit";"Roach";"Larva";111;2
"Unit";"Roach";"Larva";111;2
"Unit";"Overlord";"Larva";111;0
"Unit";"Overlord";"Larva";111;0
"Unit";"Overlord";"Larva";113;0
"Unit";"Overlord";"Larva";115;0
"Unit";"Roach";"Larva";129;2
"Unit";"Roach";"Larva";129;2
"Unit";"Roach";"Larva";129;2
"Unit";"Roach";"Larva";129;2
"Upgrade";"GlialReconstitution";"RoachWarren";111;0
"Unit";"Roach";"Larva";129;2
"Unit";"Roach";"Larva";129;2
"Unit";"Roach";"Larva";129;2
"Unit";"Roach";"Larva";129;2
"Unit";"Roach";"Larva";129;2
"Unit";"Roach";"Larva";137;2
"Unit";"Roach";"Larva";137;2
"Unit";"Roach";"Larva";137;2
"Unit";"Roach";"Larva";137;2
"Unit";"Roach";"Larva";137;2
"Unit";"Roach";"Larva";137;2
"Unit";"Queen";"Hatchery";129;2
"Unit";"Queen";"Hatchery";129;2
"Unit";"Queen";"Hatchery";129;2
"Unit";"Roach";"Larva";173;2
"Unit";"Roach";"Larva";173;2
"Unit";"Roach";"Larva";173;2
"Unit";"Overlord";"Larva";176;0
"Building";"HydraliskDen";NA;173;0
"Unit";"Roach";"Larva";176;2
"Unit";"Roach";"Larva";176;2
"Unit";"Roach";"Larva";176;2
"Unit";"Roach";"Larva";176;2
"Unit";"Roach";"Larva";176;2
"Unit";"Roach";"Larva";176;2
"Unit";"Roach";"Larva";176;2
"Unit";"Roach";"Larva";176;2
"Unit";"Roach";"Larva";176;2
"Building";"CreepTumor";NA;200;0
"Unit";"Queen";"Hatchery";176;2
"Unit";"Queen";"Hatchery";176;2
"Unit";"Queen";"Hatchery";176;2
"Building";"Hatchery";NA;173;0
"Building";"SporeCrawler";NA;207;0
"Building";"SporeCrawler";NA;213;0
"Building";"SporeCrawler";NA;213;0
"Building";"SporeCrawler";NA;213;0
"Building";"CreepTumor";NA;225;0
"Building";"SporeCrawler";NA;225;0
"Building";"SporeCrawler";NA;225;0
"Building";"SporeCrawler";NA;225;0
"Building";"SporeCrawler";NA;225;0
"Upgrade";"EvolveGroovedSpines";"HydraliskDen";206;0
"Upgrade";"ZergMissileWeaponsLevel2";"EvolutionChamber";176;0
"Building";"LurkerDenMP";NA;186;0
"Building";"Extractor";NA;225;0
"Building";"Extractor";NA;225;0
"Unit";"Queen";"Hatchery";225;2
"Unit";"Queen";"Hatchery";225;2
"Unit";"Overlord";"Larva";225;0
"Unit";"Overlord";"Larva";225;0
"Unit";"Overlord";"Larva";225;0
"Unit";"Overlord";"Larva";225;0
"Unit";"Hydralisk";"Larva";225;2
"Unit";"Hydralisk";"Larva";225;2
"Unit";"Hydralisk";"Larva";225;2
"Unit";"Hydralisk";"Larva";225;2
"Unit";"Hydralisk";"Larva";225;2
"Unit";"Hydralisk";"Larva";225;2
"Unit";"Hydralisk";"Larva";225;2
"Unit";"Hydralisk";"Larva";225;2
"Unit";"Hydralisk";"Larva";225;2
"Unit";"Hydralisk";"Larva";225;2
"Unit";"Hydralisk";"Larva";225;2
"Unit";"Overlord";"Larva";229;0
"Unit";"Hydralisk";"Larva";225;2
"Unit";"Hydralisk";"Larva";225;2
"Unit";"Hydralisk";"Larva";247;2
"Unit";"Hydralisk";"Larva";247;2
"Unit";"Hydralisk";"Larva";247;2
"Unit";"Hydralisk";"Larva";251;2
"Unit";"Hydralisk";"Larva";251;2
"Unit";"Hydralisk";"Larva";251;2
"Unit";"Hydralisk";"Larva";251;2
"Unit";"Hydralisk";"Larva";255;2
"Unit";"Hydralisk";"Larva";255;2
"Unit";"Hydralisk";"Larva";255;2
"Unit";"Overlord";"Larva";269;0
"Upgrade";"EvolveMuscularAugments";"HydraliskDen";247;0
"Unit";"Hydralisk";"Larva";269;2
"Unit";"Hydralisk";"Larva";269;2
"Unit";"Overlord";"Larva";275;0
"Unit";"Overlord";"Larva";275;0
"Unit";"Overlord";"Larva";275;0
"Unit";"Overlord";"Larva";275;0
"Unit";"Overlord";"Larva";275;0
"Unit";"Hydralisk";"Larva";275;2
"Unit";"Hydralisk";"Larva";275;2
"Building";"SporeCrawler";NA;279;0
"Upgrade";"ZergGroundArmorsLevel1";"EvolutionChamber";251;0
"Unit";"Hydralisk";"Larva";279;2
"Unit";"Hydralisk";"Larva";279;2
"Building";"SporeCrawler";NA;279;0
"Unit";"Hydralisk";"Larva";283;2
"Unit";"Hydralisk";"Larva";283;2
"Unit";"Hydralisk";"Larva";283;2
