"type";"unit_name";"on_building";"total_supply";"supply"
"Unit";"Overlord";"Larva";13;0
"Building";"Extractor";NA;18;0
"Unit";"Overlord";"Larva";21;0
"Building";"SpawningPool";NA;19;0
"Building";"Hatchery";NA;17;0
"Unit";"Zergling";"Larva";23;1
"Unit";"Zergling";"Larva";23;1
"Unit";"Queen";"Hatchery";22;2
"Unit";"Queen";"Hatchery";23;2
"Unit";"Zergling";"Larva";35;1
"Unit";"Zergling";"Larva";35;1
"Unit";"Zergling";"Larva";35;1
"Unit";"Zergling";"Larva";35;1
"Unit";"Zergling";"Larva";35;1
"Unit";"Zergling";"Larva";35;1
"Building";"BanelingNest";NA;28;0
"Unit";"Overlord";"Larva";35;0
"Building";"Hatchery";NA;35;0
"Unit";"Overlord";"Larva";49;0
"Unit";"Zergling";"Larva";53;1
"Unit";"Zergling";"Larva";53;1
"Unit";"Overlord";"Larva";53;0
"Unit";"Overlord";"Larva";53;0
"Unit";"Zergling";"Larva";54;1
"Unit";"Zergling";"Larva";54;1
"Unit";"Baneling";"Zergling";54;0
"Unit";"Baneling";"Zergling";54;0
"Building";"RoachWarren";NA;49;0
"Unit";"Queen";"Hatchery";54;2
"Unit";"Baneling";"Zergling";58;0
"Unit";"Baneling";"Zergling";58;0
"Unit";"Zergling";"Larva";58;1
"Unit";"Zergling";"Larva";58;1
"Unit";"Zergling";"Larva";58;1
"Unit";"Zergling";"Larva";58;1
"Unit";"Zergling";"Larva";58;1
"Unit";"Zergling";"Larva";58;1
"Unit";"Zergling";"Larva";58;1
"Unit";"Zergling";"Larva";58;1
"Unit";"Zergling";"Larva";58;1
"Unit";"Zergling";"Larva";58;1
"Unit";"Zergling";"Larva";58;1
"Unit";"Zergling";"Larva";58;1
"Unit";"Zergling";"Larva";58;1
"Unit";"Zergling";"Larva";58;1
"Unit";"Zergling";"Larva";58;1
"Unit";"Zergling";"Larva";58;1
"Building";"SpineCrawler";NA;54;0
"Unit";"Zergling";"Larva";58;1
"Unit";"Zergling";"Larva";58;1
"Unit";"Zergling";"Larva";58;1
"Unit";"Zergling";"Larva";58;1
"Unit";"Zergling";"Larva";58;1
"Unit";"Zergling";"Larva";58;1
"Unit";"Baneling";"Zergling";62;0
"Unit";"Baneling";"Zergling";68;0
"Unit";"Baneling";"Zergling";76;0
"Unit";"Baneling";"Zergling";76;0
"Unit";"Baneling";"Zergling";76;0
"Unit";"Baneling";"Zergling";76;0
"Unit";"Zergling";"Larva";77;1
"Unit";"Zergling";"Larva";77;1
"Unit";"Zergling";"Larva";77;1
"Unit";"Zergling";"Larva";77;1
"Unit";"Zergling";"Larva";77;1
"Unit";"Zergling";"Larva";77;1
"Unit";"Zergling";"Larva";77;1
"Unit";"Zergling";"Larva";77;1
"Unit";"Zergling";"Larva";77;1
"Unit";"Zergling";"Larva";77;1
"Unit";"Zergling";"Larva";77;1
"Unit";"Zergling";"Larva";77;1
"Unit";"Zergling";"Larva";77;1
"Unit";"Zergling";"Larva";77;1
"Unit";"Zergling";"Larva";97;1
"Unit";"Zergling";"Larva";97;1
"Unit";"Zergling";"Larva";97;1
"Unit";"Zergling";"Larva";97;1
"Unit";"Zergling";"Larva";97;1
"Unit";"Zergling";"Larva";97;1
"Unit";"Zergling";"Larva";97;1
"Unit";"Zergling";"Larva";97;1
"Unit";"Baneling";"Zergling";99;0
"Unit";"Baneling";"Zergling";99;0
"Unit";"Baneling";"Zergling";99;0
"Unit";"Baneling";"Zergling";99;0
"Unit";"Baneling";"Zergling";99;0
"Building";"Extractor";NA;99;0
"Building";"Extractor";NA;99;0
"Unit";"Baneling";"Zergling";111;0
"Unit";"Baneling";"Zergling";111;0
"Unit";"Overlord";"Larva";111;0
"Unit";"Roach";"Larva";111;2
"Building";"EvolutionChamber";NA;123;0
"Unit";"Roach";"Larva";123;2
"Unit";"Roach";"Larva";123;2
"Unit";"Roach";"Larva";123;2
"Unit";"Roach";"Larva";123;2
"Building";"EvolutionChamber";NA;123;0
"Unit";"Roach";"Larva";125;2
"Unit";"Roach";"Larva";125;2
"Unit";"Baneling";"Zergling";133;0
"Unit";"Baneling";"Zergling";133;0
"Unit";"Overlord";"Larva";125;0
"Unit";"Overlord";"Larva";125;0
"Unit";"Overlord";"Larva";125;0
"Unit";"Overlord";"Larva";125;0
"Unit";"Zergling";"Larva";133;1
"Unit";"Zergling";"Larva";133;1
"Unit";"Zergling";"Larva";133;1
"Unit";"Zergling";"Larva";133;1
"Unit";"Zergling";"Larva";133;1
"Unit";"Zergling";"Larva";133;1
"Unit";"Zergling";"Larva";133;1
"Unit";"Zergling";"Larva";133;1
"Unit";"Zergling";"Larva";133;1
"Unit";"Zergling";"Larva";133;1
"Unit";"Zergling";"Larva";133;1
"Unit";"Zergling";"Larva";133;1
"Unit";"Zergling";"Larva";133;1
"Unit";"Zergling";"Larva";133;1
"Unit";"Overlord";"Larva";133;0
"Building";"Extractor";NA;137;0
"Unit";"Zergling";"Larva";137;1
"Unit";"Zergling";"Larva";137;1
"Unit";"Zergling";"Larva";137;1
"Unit";"Zergling";"Larva";137;1
"Unit";"Zergling";"Larva";137;1
"Unit";"Zergling";"Larva";137;1
"Unit";"Baneling";"Zergling";157;0
"Unit";"Baneling";"Zergling";157;0
"Building";"HydraliskDen";NA;151;0
"Building";"Extractor";NA;167;0
"Building";"Extractor";NA;167;0
"Upgrade";"GlialReconstitution";"RoachWarren";137;0
"Unit";"Baneling";"Zergling";173;0
"Unit";"Baneling";"Zergling";173;0
"Unit";"Hydralisk";"Larva";173;2
"Unit";"Hydralisk";"Larva";173;2
"Building";"Hatchery";NA;151;0
"Unit";"Roach";"Larva";179;2
"Unit";"Overlord";"Larva";183;0
"Unit";"Roach";"Larva";179;2
"Unit";"Roach";"Larva";179;2
"Unit";"Roach";"Larva";179;2
"Unit";"Roach";"Larva";179;2
"Unit";"Roach";"Larva";179;2
"Unit";"Roach";"Larva";179;2
"Unit";"Roach";"Larva";179;2
"Unit";"Roach";"Larva";179;2
"Unit";"Baneling";"Zergling";210;0
"Unit";"Baneling";"Zergling";210;0
"Unit";"Baneling";"Zergling";210;0
"Unit";"Baneling";"Zergling";210;0
"Unit";"Zergling";"Larva";210;1
"Unit";"Zergling";"Larva";210;1
"Unit";"Zergling";"Larva";210;1
"Unit";"Zergling";"Larva";210;1
"Unit";"Overlord";"Larva";210;0
"Unit";"Overlord";"Larva";210;0
"Upgrade";"EvolveGroovedSpines";"HydraliskDen";183;0
"Building";"Extractor";NA;210;0
"Upgrade";"ZergGroundArmorsLevel1";"EvolutionChamber";173;0
"Building";"Extractor";NA;210;0
"Unit";"Roach";"Larva";214;2
"Unit";"Overlord";"Larva";214;0
"Unit";"Overlord";"Larva";214;0
"Building";"SpineCrawler";NA;210;0
"Unit";"Hydralisk";"Larva";214;2
"Unit";"Hydralisk";"Larva";214;2
"Unit";"Hydralisk";"Larva";214;2
"Unit";"Hydralisk";"Larva";214;2
"Unit";"Hydralisk";"Larva";214;2
"Unit";"Hydralisk";"Larva";214;2
"Unit";"Hydralisk";"Larva";214;2
"Unit";"Hydralisk";"Larva";214;2
"Unit";"Hydralisk";"Larva";214;2
"Upgrade";"ZergMissileWeaponsLevel1";"EvolutionChamber";183;0
"Unit";"Baneling";"Zergling";216;0
"Unit";"Baneling";"Zergling";216;0
"Unit";"Baneling";"Zergling";216;0
"Unit";"Hydralisk";"Larva";216;2
"Unit";"Hydralisk";"Larva";216;2
"Unit";"Hydralisk";"Larva";216;2
"Unit";"Hydralisk";"Larva";216;2
"Unit";"Hydralisk";"Larva";216;2
"Unit";"Hydralisk";"Larva";216;2
"Unit";"Hydralisk";"Larva";216;2
"Unit";"Hydralisk";"Larva";216;2
"Building";"LurkerDenMP";NA;183;0
"Unit";"Overlord";"Larva";234;0
"Unit";"Overlord";"Larva";234;0
"Unit";"Overlord";"Larva";234;0
"Building";"SpineCrawler";NA;234;0
"Upgrade";"EvolveMuscularAugments";"HydraliskDen";216;0
"Unit";"Roach";"Larva";251;2
"Unit";"Roach";"Larva";251;2
"Unit";"Roach";"Larva";251;2
"Unit";"Roach";"Larva";251;2
"Unit";"Roach";"Larva";251;2
"Unit";"Roach";"Larva";251;2
"Unit";"Roach";"Larva";251;2
"Unit";"Roach";"Larva";251;2
"Unit";"Roach";"Larva";251;2
"Unit";"Roach";"Larva";251;2
"Unit";"Roach";"Larva";251;2
"Unit";"Roach";"Larva";251;2
"Unit";"Roach";"Larva";251;2
"Unit";"Roach";"Larva";251;2
"Unit";"Roach";"Larva";251;2
"Unit";"Roach";"Larva";251;2
"Unit";"Roach";"Larva";251;2
"Unit";"Roach";"Larva";251;2
"Unit";"Roach";"Larva";251;2
"Unit";"Roach";"Larva";251;2
"Unit";"Roach";"Larva";251;2
"Unit";"Roach";"Larva";251;2
"Unit";"Roach";"Larva";251;2
"Unit";"Roach";"Larva";251;2
"Unit";"Roach";"Larva";283;2
"Unit";"Roach";"Larva";283;2
"Unit";"Roach";"Larva";283;2
"Unit";"Roach";"Larva";283;2
"Unit";"Roach";"Larva";283;2
"Unit";"Roach";"Larva";283;2
"Unit";"Roach";"Larva";299;2
"Unit";"Roach";"Larva";299;2
"Unit";"Roach";"Larva";299;2
"Unit";"Roach";"Larva";299;2
"Unit";"Roach";"Larva";299;2
"Unit";"Roach";"Larva";299;2
"Unit";"Hydralisk";"Larva";311;2
"Unit";"Hydralisk";"Larva";311;2
"Unit";"Hydralisk";"Larva";311;2
"Unit";"Hydralisk";"Larva";311;2
"Unit";"Hydralisk";"Larva";311;2
"Unit";"Queen";"Hatchery";299;2
"Unit";"Roach";"Larva";345;2
"Unit";"Overlord";"Larva";345;0
"Unit";"Overlord";"Larva";345;0
"Unit";"Roach";"Larva";345;2
"Unit";"Roach";"Larva";345;2
"Unit";"Overlord";"Larva";345;0
"Unit";"Overlord";"Larva";345;0
"Unit";"Hydralisk";"Larva";345;2
"Unit";"Hydralisk";"Larva";345;2
"Unit";"Hydralisk";"Larva";345;2
"Unit";"Roach";"Larva";351;2
"Unit";"Roach";"Larva";351;2
"Unit";"Roach";"Larva";351;2
"Unit";"Roach";"Larva";351;2
"Unit";"Roach";"Larva";351;2
"Unit";"Roach";"Larva";351;2
"Unit";"Roach";"Larva";351;2
"Unit";"Roach";"Larva";351;2
"Unit";"Roach";"Larva";351;2
"Unit";"Roach";"Larva";351;2
"Unit";"Roach";"Larva";351;2
"Unit";"Roach";"Larva";351;2
"Unit";"Roach";"Larva";351;2
"Unit";"Roach";"Larva";351;2
"Building";"Hatchery";NA;345;0
"Unit";"Roach";"Larva";353;2
"Unit";"Overlord";"Larva";357;0
"Unit";"Overlord";"Larva";357;0
"Building";"InfestationPit";NA;357;0
"Building";"SpineCrawler";NA;385;0
"Building";"SpineCrawler";NA;385;0
"Building";"SpineCrawler";NA;385;0
"Unit";"Hydralisk";"Larva";387;2
"Unit";"Hydralisk";"Larva";387;2
"Unit";"Hydralisk";"Larva";387;2
"Unit";"Hydralisk";"Larva";387;2
"Unit";"Hydralisk";"Larva";387;2
"Unit";"Hydralisk";"Larva";387;2
"Upgrade";"ZergGroundArmorsLevel2";"EvolutionChamber";345;0
"Upgrade";"ZergMissileWeaponsLevel2";"EvolutionChamber";345;0
"Unit";"Hydralisk";"Larva";399;2
"Unit";"Hydralisk";"Larva";399;2
"Unit";"Hydralisk";"Larva";399;2
"Unit";"Hydralisk";"Larva";399;2
"Unit";"Hydralisk";"Larva";399;2
"Unit";"Hydralisk";"Larva";399;2
"Unit";"Hydralisk";"Larva";399;2
"Unit";"Hydralisk";"Larva";399;2
"Unit";"Hydralisk";"Larva";399;2
"Unit";"Hydralisk";"Larva";399;2
"Unit";"Hydralisk";"Larva";399;2
"Unit";"Hydralisk";"Larva";399;2
"Unit";"Hydralisk";"Larva";399;2
"Unit";"Hydralisk";"Larva";399;2
"Unit";"Hydralisk";"Larva";399;2
"Unit";"Hydralisk";"Larva";399;2
"Unit";"Hydralisk";"Larva";399;2
"Unit";"Hydralisk";"Larva";399;2
"Unit";"Hydralisk";"Larva";399;2
"Unit";"Hydralisk";"Larva";399;2
"Unit";"Hydralisk";"Larva";399;2
"Unit";"Hydralisk";"Larva";441;2
"Unit";"Hydralisk";"Larva";441;2
"Unit";"Hydralisk";"Larva";441;2
"Unit";"Hydralisk";"Larva";441;2
"Unit";"Hydralisk";"Larva";441;2
"Unit";"Hydralisk";"Larva";441;2
"Unit";"Hydralisk";"Larva";441;2
"Unit";"Hydralisk";"Larva";441;2
"Unit";"Hydralisk";"Larva";441;2
"Unit";"Hydralisk";"Larva";441;2
"Unit";"Hydralisk";"Larva";441;2
"Unit";"Hydralisk";"Larva";441;2
"Unit";"Hydralisk";"Larva";441;2
"Unit";"Hydralisk";"Larva";441;2
"Unit";"Hydralisk";"Larva";441;2
"Building";"Spire";NA;421;0
"Unit";"Hydralisk";"Larva";441;2
"Unit";"Hydralisk";"Larva";441;2
"Unit";"Hydralisk";"Larva";441;2
"Unit";"Hydralisk";"Larva";441;2
"Unit";"Hydralisk";"Larva";441;2
"Unit";"Hydralisk";"Larva";441;2
"Unit";"Hydralisk";"Larva";441;2
"Unit";"Roach";"Larva";471;2
"Unit";"Roach";"Larva";471;2
"Unit";"Roach";"Larva";471;2
"Unit";"Roach";"Larva";471;2
"Unit";"Roach";"Larva";471;2
"Building";"Extractor";NA;485;0
