"type";"unit_name";"on_building";"total_supply";"supply"
"Unit";"Overlord";"Larva";13;0
"Building";"Extractor";NA;19;0
"Unit";"Overlord";"Larva";21;0
"Building";"SpawningPool";NA;19;0
"Building";"Hatchery";NA;17;0
"Unit";"Zergling";"Larva";22;1
"Unit";"Zergling";"Larva";22;1
"Unit";"Zergling";"Larva";22;1
"Unit";"Zergling";"Larva";22;1
"Unit";"Zergling";"Larva";22;1
"Unit";"Zergling";"Larva";22;1
"Unit";"Queen";"Hatchery";22;2
"Unit";"Queen";"Hatchery";22;2
"Unit";"Overlord";"Larva";39;0
"Building";"BanelingNest";NA;37;0
"Building";"Hatchery";NA;36;0
"Unit";"Baneling";"Zergling";49;0
"Unit";"Baneling";"Zergling";49;0
"Building";"EvolutionChamber";NA;49;0
"Unit";"Overlord";"Larva";49;0
"Unit";"Overlord";"Larva";50;0
"Unit";"Zergling";"Larva";52;1
"Unit";"Zergling";"Larva";52;1
"Unit";"Zergling";"Larva";52;1
"Unit";"Zergling";"Larva";52;1
"Unit";"Zergling";"Larva";57;1
"Unit";"Zergling";"Larva";57;1
"Unit";"Zergling";"Larva";57;1
"Unit";"Zergling";"Larva";57;1
"Unit";"Zergling";"Larva";57;1
"Unit";"Zergling";"Larva";57;1
"Building";"Extractor";NA;53;0
"Unit";"Zergling";"Larva";57;1
"Unit";"Zergling";"Larva";57;1
"Building";"Extractor";NA;53;0
"Unit";"Zergling";"Larva";61;1
"Unit";"Zergling";"Larva";61;1
"Unit";"Zergling";"Larva";61;1
"Unit";"Zergling";"Larva";61;1
"Unit";"Baneling";"Zergling";69;0
"Building";"RoachWarren";NA;57;0
"Unit";"Queen";"Hatchery";61;2
"Unit";"Overlord";"Larva";79;0
"Unit";"Overlord";"Larva";79;0
"Unit";"Overlord";"Larva";86;0
"Unit";"Baneling";"Zergling";88;0
"Unit";"Baneling";"Zergling";91;0
"Unit";"Baneling";"Zergling";91;0
"Unit";"Roach";"Larva";91;2
"Unit";"Roach";"Larva";91;2
"Unit";"Roach";"Larva";91;2
"Unit";"Roach";"Larva";91;2
"Unit";"Roach";"Larva";91;2
"Building";"EvolutionChamber";NA;91;0
"Upgrade";"ZergMissileWeaponsLevel1";"EvolutionChamber";69;0
"Unit";"Roach";"Larva";101;2
"Unit";"Roach";"Larva";101;2
"Unit";"Roach";"Larva";101;2
"Unit";"Roach";"Larva";101;2
"Building";"Extractor";NA;101;0
"Building";"Extractor";NA;101;0
"Unit";"Overlord";"Larva";101;0
"Unit";"Overlord";"Larva";108;0
"Unit";"Overlord";"Larva";108;0
"Unit";"Queen";"Hatchery";101;2
"Unit";"Roach";"Larva";120;2
"Building";"Extractor";NA;120;0
"Unit";"Roach";"Larva";120;2
"Unit";"Roach";"Larva";120;2
"Unit";"Roach";"Larva";120;2
"Unit";"Roach";"Larva";120;2
"Unit";"Overlord";"Larva";121;0
"Unit";"Overlord";"Larva";123;0
"Building";"HydraliskDen";NA;120;0
"Unit";"Roach";"Larva";125;2
"Unit";"Roach";"Larva";125;2
"Unit";"Roach";"Larva";128;2
"Unit";"Roach";"Larva";128;2
"Unit";"Overlord";"Larva";132;0
"Unit";"Overlord";"Larva";134;0
"Unit";"Overlord";"Larva";136;0
"Upgrade";"GlialReconstitution";"RoachWarren";120;0
"Unit";"Roach";"Larva";138;2
"Unit";"Roach";"Larva";138;2
"Unit";"Roach";"Larva";138;2
"Unit";"Roach";"Larva";138;2
"Unit";"Roach";"Larva";140;2
"Unit";"Roach";"Larva";142;2
"Unit";"Roach";"Larva";146;2
"Unit";"Roach";"Larva";146;2
"Unit";"Roach";"Larva";146;2
"Unit";"Roach";"Larva";146;2
"Unit";"Roach";"Larva";146;2
"Building";"Hatchery";NA;120;0
"Unit";"Roach";"Larva";146;2
"Unit";"Roach";"Larva";146;2
"Unit";"Roach";"Larva";146;2
"Unit";"Roach";"Larva";158;2
"Unit";"Roach";"Larva";158;2
"Unit";"Roach";"Larva";158;2
"Unit";"Overlord";"Larva";158;0
"Upgrade";"ZergGroundArmorsLevel1";"EvolutionChamber";120;0
"Unit";"Roach";"Larva";168;2
"Unit";"Roach";"Larva";168;2
"Unit";"Roach";"Larva";168;2
"Unit";"Roach";"Larva";168;2
"Unit";"Roach";"Larva";168;2
"Unit";"Roach";"Larva";174;2
"Unit";"Roach";"Larva";174;2
"Unit";"Roach";"Larva";180;2
"Unit";"Roach";"Larva";180;2
"Unit";"Roach";"Larva";180;2
"Unit";"Roach";"Larva";180;2
"Unit";"Roach";"Larva";180;2
"Unit";"Overlord";"Larva";180;0
"Unit";"Roach";"Larva";190;2
"Unit";"Roach";"Larva";200;2
"Unit";"Roach";"Larva";200;2
"Unit";"Roach";"Larva";200;2
"Unit";"Roach";"Larva";200;2
"Unit";"Roach";"Larva";200;2
"Unit";"Roach";"Larva";200;2
"Unit";"Roach";"Larva";200;2
"Unit";"Roach";"Larva";200;2
"Upgrade";"ZergMissileWeaponsLevel2";"EvolutionChamber";128;0
"Building";"LurkerDenMP";NA;146;0
"Unit";"Hydralisk";"Larva";204;2
"Unit";"Hydralisk";"Larva";204;2
"Unit";"Hydralisk";"Larva";204;2
"Unit";"Hydralisk";"Larva";206;2
"Unit";"Overlord";"Larva";222;0
"Unit";"Hydralisk";"Larva";222;2
"Unit";"Hydralisk";"Larva";222;2
"Unit";"Hydralisk";"Larva";233;2
"Unit";"Hydralisk";"Larva";233;2
"Unit";"Overlord";"Larva";235;0
"Unit";"Overlord";"Larva";235;0
"Building";"Extractor";NA;239;0
"Building";"Extractor";NA;239;0
"Unit";"Overlord";"Larva";243;0
"Unit";"Overlord";"Larva";243;0
"Unit";"Hydralisk";"Larva";243;2
"Unit";"Hydralisk";"Larva";243;2
"Unit";"Hydralisk";"Larva";243;2
"Unit";"Hydralisk";"Larva";243;2
"Unit";"Hydralisk";"Larva";243;2
"Unit";"Hydralisk";"Larva";243;2
"Unit";"Overlord";"Larva";243;0
"Unit";"Roach";"Larva";243;2
"Unit";"Roach";"Larva";243;2
"Unit";"Roach";"Larva";243;2
"Unit";"Roach";"Larva";243;2
"Unit";"Roach";"Larva";243;2
"Unit";"Roach";"Larva";243;2
"Unit";"Roach";"Larva";243;2
"Unit";"Roach";"Larva";243;2
"Unit";"Roach";"Larva";243;2
"Unit";"Roach";"Larva";243;2
"Unit";"Roach";"Larva";255;2
"Unit";"Roach";"Larva";255;2
"Unit";"Roach";"Larva";255;2
"Unit";"Roach";"Larva";255;2
"Unit";"Roach";"Larva";255;2
"Building";"InfestationPit";NA;243;0
"Unit";"Roach";"Larva";255;2
"Unit";"Roach";"Larva";255;2
"Unit";"Roach";"Larva";255;2
"Unit";"Roach";"Larva";285;2
"Unit";"Roach";"Larva";285;2
"Unit";"Roach";"Larva";285;2
"Unit";"Roach";"Larva";285;2
"Unit";"Roach";"Larva";285;2
"Unit";"Roach";"Larva";285;2
"Unit";"Roach";"Larva";285;2
"Unit";"Roach";"Larva";285;2
"Unit";"Roach";"Larva";291;2
"Unit";"Roach";"Larva";291;2
"Unit";"Roach";"Larva";291;2
"Unit";"Roach";"Larva";291;2
"Unit";"Roach";"Larva";291;2
"Unit";"Roach";"Larva";291;2
"Unit";"Roach";"Larva";291;2
"Upgrade";"EvolveMuscularAugments";"HydraliskDen";255;0
"Unit";"Hydralisk";"Larva";321;2
"Unit";"Hydralisk";"Larva";321;2
"Unit";"Hydralisk";"Larva";321;2
"Unit";"Hydralisk";"Larva";321;2
"Unit";"Hydralisk";"Larva";321;2
"Unit";"Hydralisk";"Larva";321;2
"Unit";"Roach";"Larva";321;2
"Unit";"Roach";"Larva";321;2
"Unit";"Roach";"Larva";321;2
"Unit";"Roach";"Larva";321;2
"Unit";"Roach";"Larva";341;2
"Unit";"Roach";"Larva";341;2
"Unit";"Roach";"Larva";341;2
"Unit";"Roach";"Larva";341;2
"Unit";"Roach";"Larva";341;2
"Unit";"Roach";"Larva";341;2
"Unit";"Roach";"Larva";341;2
"Unit";"Roach";"Larva";341;2
"Unit";"Roach";"Larva";341;2
"Unit";"Roach";"Larva";341;2
"Unit";"Roach";"Larva";341;2
"Unit";"Roach";"Larva";341;2
"Unit";"Roach";"Larva";341;2
"Unit";"Roach";"Larva";341;2
"Unit";"Roach";"Larva";341;2
"Unit";"Roach";"Larva";341;2
"Unit";"Roach";"Larva";341;2
"Unit";"Roach";"Larva";341;2
"Unit";"Roach";"Larva";341;2
"Unit";"Roach";"Larva";341;2
"Unit";"Roach";"Larva";381;2
"Unit";"Roach";"Larva";381;2
"Unit";"Roach";"Larva";381;2
"Unit";"Roach";"Larva";381;2
"Unit";"Roach";"Larva";381;2
"Unit";"Roach";"Larva";381;2
"Unit";"Roach";"Larva";381;2
"Unit";"Roach";"Larva";381;2
"Unit";"Roach";"Larva";381;2
"Unit";"Roach";"Larva";381;2
"Unit";"Hydralisk";"Larva";381;2
"Unit";"Hydralisk";"Larva";381;2
"Unit";"Hydralisk";"Larva";381;2
