"type";"unit_name";"on_building";"total_supply";"supply"
"Unit";"Overlord";"Larva";13;0
"Building";"Extractor";NA;14;0
"Building";"SpawningPool";NA;16;0
"Building";"EvolutionChamber";NA;21;0
"Unit";"Queen";"Hatchery";20;2
"Unit";"Overlord";"Larva";21;0
"Building";"Hatchery";NA;20;0
"Unit";"Zergling";"Larva";25;1
"Unit";"Zergling";"Larva";25;1
"Unit";"Queen";"Hatchery";25;2
"Unit";"Overlord";"Larva";33;0
"Unit";"Overlord";"Larva";42;0
"Building";"BanelingNest";NA;35;0
"Unit";"Zergling";"Larva";44;1
"Unit";"Zergling";"Larva";44;1
"Unit";"Zergling";"Larva";44;1
"Unit";"Zergling";"Larva";44;1
"Unit";"Zergling";"Larva";44;1
"Unit";"Zergling";"Larva";44;1
"Unit";"Zergling";"Larva";46;1
"Unit";"Zergling";"Larva";46;1
"Upgrade";"ZergGroundArmorsLevel1";"EvolutionChamber";29;0
"Unit";"Overlord";"Larva";46;0
"Unit";"Baneling";"Zergling";46;0
"Unit";"Zergling";"Larva";46;1
"Unit";"Zergling";"Larva";46;1
"Unit";"Baneling";"Zergling";46;0
"Unit";"Baneling";"Zergling";52;0
"Unit";"Baneling";"Zergling";52;0
"Unit";"Zergling";"Larva";52;1
"Unit";"Zergling";"Larva";52;1
"Unit";"Zergling";"Larva";52;1
"Unit";"Zergling";"Larva";52;1
"Unit";"Zergling";"Larva";52;1
"Unit";"Zergling";"Larva";52;1
"Unit";"Zergling";"Larva";52;1
"Unit";"Zergling";"Larva";52;1
"Unit";"Zergling";"Larva";52;1
"Unit";"Zergling";"Larva";52;1
"Unit";"Zergling";"Larva";52;1
"Unit";"Zergling";"Larva";52;1
"Unit";"Zergling";"Larva";54;1
"Unit";"Zergling";"Larva";54;1
"Unit";"Zergling";"Larva";70;1
"Unit";"Zergling";"Larva";70;1
"Unit";"Baneling";"Zergling";70;0
"Unit";"Baneling";"Zergling";70;0
"Unit";"Zergling";"Larva";70;1
"Unit";"Zergling";"Larva";70;1
"Unit";"Zergling";"Larva";70;1
"Unit";"Zergling";"Larva";70;1
"Unit";"Zergling";"Larva";70;1
"Unit";"Zergling";"Larva";70;1
"Unit";"Zergling";"Larva";70;1
"Unit";"Zergling";"Larva";70;1
"Unit";"Zergling";"Larva";70;1
"Unit";"Zergling";"Larva";70;1
"Unit";"Zergling";"Larva";70;1
"Unit";"Zergling";"Larva";70;1
"Unit";"Zergling";"Larva";70;1
"Unit";"Zergling";"Larva";70;1
"Unit";"Baneling";"Zergling";70;0
"Unit";"Baneling";"Zergling";70;0
"Unit";"Baneling";"Zergling";72;0
"Unit";"Zergling";"Larva";70;1
"Unit";"Zergling";"Larva";70;1
"Unit";"Baneling";"Zergling";86;0
"Unit";"Queen";"Hatchery";70;2
"Unit";"Zergling";"Larva";86;1
"Unit";"Zergling";"Larva";86;1
"Unit";"Zergling";"Larva";86;1
"Unit";"Zergling";"Larva";86;1
"Unit";"Zergling";"Larva";86;1
"Unit";"Zergling";"Larva";86;1
"Unit";"Zergling";"Larva";88;1
"Unit";"Zergling";"Larva";88;1
"Unit";"Baneling";"Zergling";96;0
"Unit";"Baneling";"Zergling";96;0
"Unit";"Baneling";"Zergling";96;0
"Unit";"Baneling";"Zergling";96;0
"Unit";"Zergling";"Larva";94;1
"Unit";"Zergling";"Larva";94;1
"Unit";"Zergling";"Larva";96;1
"Unit";"Zergling";"Larva";96;1
"Unit";"Zergling";"Larva";96;1
"Unit";"Zergling";"Larva";96;1
"Unit";"Zergling";"Larva";96;1
"Unit";"Zergling";"Larva";96;1
"Building";"CreepTumorQueen";NA;98;0
"Building";"Hatchery";NA;56;0
"Unit";"Overlord";"Larva";98;0
"Unit";"Overlord";"Larva";98;0
"Unit";"Overlord";"Larva";98;0
"Unit";"Baneling";"Zergling";98;0
"Building";"Extractor";NA;98;0
"Building";"RoachWarren";NA;98;0
"Unit";"Zergling";"Larva";116;1
"Unit";"Zergling";"Larva";116;1
"Unit";"Zergling";"Larva";116;1
"Unit";"Zergling";"Larva";116;1
"Unit";"Zergling";"Larva";116;1
"Unit";"Zergling";"Larva";116;1
"Unit";"Zergling";"Larva";116;1
"Unit";"Zergling";"Larva";116;1
"Unit";"Zergling";"Larva";116;1
"Unit";"Zergling";"Larva";116;1
"Unit";"Baneling";"Zergling";118;0
"Unit";"Baneling";"Zergling";118;0
"Unit";"Baneling";"Zergling";118;0
"Unit";"Baneling";"Zergling";118;0
"Unit";"Roach";"Larva";118;2
"Unit";"Roach";"Larva";118;2
"Unit";"Roach";"Larva";118;2
"Unit";"Roach";"Larva";118;2
"Unit";"Roach";"Larva";118;2
"Unit";"Zergling";"Larva";128;1
"Unit";"Zergling";"Larva";128;1
"Unit";"Zergling";"Larva";128;1
"Unit";"Zergling";"Larva";128;1
"Unit";"Zergling";"Larva";128;1
"Unit";"Zergling";"Larva";128;1
"Unit";"Zergling";"Larva";128;1
"Unit";"Zergling";"Larva";128;1
"Unit";"Zergling";"Larva";128;1
"Unit";"Zergling";"Larva";128;1
"Unit";"Baneling";"Zergling";138;0
"Unit";"Baneling";"Zergling";138;0
"Unit";"Baneling";"Zergling";138;0
"Building";"SpineCrawler";NA;118;0
"Unit";"Queen";"Hatchery";138;2
"Building";"Extractor";NA;158;0
"Unit";"Roach";"Larva";158;2
"Unit";"Roach";"Larva";158;2
"Unit";"Roach";"Larva";158;2
"Unit";"Roach";"Larva";158;2
"Unit";"Roach";"Larva";158;2
"Unit";"Roach";"Larva";162;2
"Unit";"Roach";"Larva";162;2
"Unit";"Roach";"Larva";162;2
"Unit";"Roach";"Larva";162;2
"Unit";"Roach";"Larva";162;2
"Unit";"Overlord";"Larva";172;0
"Unit";"Overlord";"Larva";172;0
"Unit";"Overlord";"Larva";184;0
"Unit";"Overlord";"Larva";184;0
"Unit";"Overlord";"Larva";184;0
"Unit";"Overlord";"Larva";184;0
"Unit";"Roach";"Larva";185;2
"Unit";"Roach";"Larva";185;2
"Unit";"Roach";"Larva";185;2
"Unit";"Roach";"Larva";185;2
"Unit";"Roach";"Larva";185;2
"Unit";"Roach";"Larva";185;2
"Unit";"Roach";"Larva";185;2
"Unit";"Queen";"Hatchery";184;2
"Unit";"Overlord";"Larva";185;0
"Unit";"Overlord";"Larva";185;0
"Building";"SpineCrawler";NA;185;0
"Unit";"Roach";"Larva";185;2
"Unit";"Roach";"Larva";185;2
"Unit";"Roach";"Larva";185;2
"Building";"CreepTumor";NA;205;0
"Building";"Extractor";NA;205;0
"Building";"Extractor";NA;205;0
"Building";"Extractor";NA;207;0
"Unit";"Baneling";"Zergling";218;0
"Unit";"Baneling";"Zergling";218;0
"Unit";"Baneling";"Zergling";218;0
"Unit";"Baneling";"Zergling";218;0
"Unit";"Baneling";"Zergling";218;0
"Unit";"Overlord";"Larva";221;0
"Unit";"Overlord";"Larva";221;0
"Unit";"Roach";"Larva";221;2
"Unit";"Roach";"Larva";221;2
"Unit";"Roach";"Larva";221;2
"Unit";"Roach";"Larva";221;2
"Unit";"Roach";"Larva";221;2
"Unit";"Roach";"Larva";221;2
"Unit";"Roach";"Larva";221;2
"Unit";"Roach";"Larva";221;2
"Unit";"Roach";"Larva";221;2
"Unit";"Roach";"Larva";221;2
"Building";"CreepTumor";NA;223;0
"Unit";"Overlord";"Larva";223;0
"Building";"Spire";NA;221;0
"Building";"SpineCrawler";NA;247;0
"Building";"SpineCrawler";NA;247;0
"Unit";"Roach";"Larva";247;2
"Unit";"Roach";"Larva";247;2
"Unit";"Roach";"Larva";247;2
"Unit";"Roach";"Larva";247;2
"Unit";"Roach";"Larva";247;2
"Unit";"Roach";"Larva";247;2
"Unit";"Roach";"Larva";247;2
"Unit";"Roach";"Larva";247;2
"Unit";"Roach";"Larva";247;2
"Unit";"Overlord";"Larva";247;0
"Unit";"Overlord";"Larva";247;0
"Unit";"Baneling";"Zergling";247;0
"Unit";"Baneling";"Zergling";247;0
"Building";"SpineCrawler";NA;247;0
"Upgrade";"ZergMissileWeaponsLevel1";"EvolutionChamber";221;0
"Building";"SpineCrawler";NA;247;0
"Building";"SpineCrawler";NA;247;0
"Unit";"Overlord";"Larva";247;0
"Unit";"Overlord";"Larva";249;0
"Building";"CreepTumor";NA;265;0
"Unit";"Mutalisk";"Larva";265;2
"Unit";"Mutalisk";"Larva";265;2
"Unit";"Mutalisk";"Larva";265;2
"Unit";"Mutalisk";"Larva";265;2
"Unit";"Mutalisk";"Larva";265;2
"Unit";"Mutalisk";"Larva";265;2
"Unit";"Mutalisk";"Larva";265;2
"Unit";"Roach";"Larva";279;2
"Unit";"Roach";"Larva";279;2
"Unit";"Roach";"Larva";279;2
"Unit";"Roach";"Larva";279;2
"Unit";"Roach";"Larva";279;2
"Unit";"Roach";"Larva";279;2
"Unit";"Roach";"Larva";279;2
"Building";"InfestationPit";NA;279;0
"Unit";"Roach";"Larva";279;2
"Unit";"Roach";"Larva";279;2
"Unit";"Roach";"Larva";279;2
"Unit";"Roach";"Larva";279;2
"Unit";"Roach";"Larva";279;2
"Building";"HydraliskDen";NA;293;0
"Unit";"Overlord";"Larva";304;0
"Unit";"Overlord";"Larva";304;0
"Building";"Hatchery";NA;277;0
"Building";"Extractor";NA;305;0
"Building";"Extractor";NA;305;0
"Upgrade";"ZergMissileWeaponsLevel2";"EvolutionChamber";279;0
"Building";"EvolutionChamber";NA;305;0
"Building";"CreepTumor";NA;305;0
"Building";"CreepTumorQueen";NA;307;0
"Unit";"Queen";"Hatchery";305;2
"Upgrade";"GlialReconstitution";"RoachWarren";305;0
"Unit";"Overlord";"Larva";309;0
"Unit";"Overlord";"Larva";309;0
"Building";"Hatchery";NA;305;0
"Upgrade";"EvolveGroovedSpines";"HydraliskDen";307;0
"Building";"LurkerDenMP";NA;307;0
"Upgrade";"Burrow";"Hatchery";309;0
"Upgrade";"TunnelingClaws";"RoachWarren";309;0
"Building";"Extractor";NA;309;0
"Building";"Extractor";NA;309;0
"Unit";"Hydralisk";"Larva";309;2
"Upgrade";"EvolveMuscularAugments";"HydraliskDen";309;0
"Building";"SpineCrawler";NA;309;0
"Building";"SpineCrawler";NA;309;0
"Building";"SpineCrawler";NA;309;0
"Building";"SpineCrawler";NA;309;0
"Upgrade";"ZergGroundArmorsLevel2";"EvolutionChamber";309;0
"Building";"SpineCrawler";NA;309;0
"Unit";"Roach";"Larva";311;2
"Unit";"Roach";"Larva";311;2
"Unit";"Roach";"Larva";311;2
"Unit";"Roach";"Larva";311;2
"Unit";"Roach";"Larva";311;2
"Unit";"Roach";"Larva";311;2
"Unit";"Roach";"Larva";311;2
"Unit";"Roach";"Larva";311;2
"Unit";"Roach";"Larva";311;2
"Unit";"Roach";"Larva";311;2
"Unit";"Roach";"Larva";311;2
"Unit";"Roach";"Larva";311;2
"Unit";"Roach";"Larva";311;2
"Unit";"Roach";"Larva";311;2
"Unit";"Roach";"Larva";311;2
"Unit";"Roach";"Larva";311;2
"Unit";"Roach";"Larva";311;2
"Unit";"Roach";"Larva";311;2
"Unit";"Roach";"Larva";311;2
"Unit";"Roach";"Larva";311;2
"Unit";"Roach";"Larva";311;2
"Unit";"Roach";"Larva";311;2
"Unit";"Roach";"Larva";311;2
"Unit";"Hydralisk";"Larva";311;2
"Unit";"Hydralisk";"Larva";311;2
"Unit";"Hydralisk";"Larva";311;2
"Unit";"Hydralisk";"Larva";311;2
"Unit";"Hydralisk";"Larva";311;2
"Unit";"Hydralisk";"Larva";311;2
"Unit";"Hydralisk";"Larva";311;2
"Unit";"Hydralisk";"Larva";311;2
"Unit";"Hydralisk";"Larva";311;2
"Unit";"Hydralisk";"Larva";311;2
"Unit";"Hydralisk";"Larva";311;2
"Unit";"Hydralisk";"Larva";311;2
"Unit";"Hydralisk";"Larva";311;2
"Unit";"Hydralisk";"Larva";311;2
"Unit";"Hydralisk";"Larva";311;2
"Unit";"Hydralisk";"Larva";311;2
"Unit";"Hydralisk";"Larva";311;2
"Unit";"Hydralisk";"Larva";311;2
"Unit";"Hydralisk";"Larva";311;2
"Unit";"Hydralisk";"Larva";311;2
"Unit";"Hydralisk";"Larva";311;2
"Unit";"Hydralisk";"Larva";311;2
"Upgrade";"ZergMissileWeaponsLevel3";"EvolutionChamber";309;0
"Building";"SpineCrawler";NA;401;0
"Unit";"Overlord";"Larva";407;0
"Building";"SpineCrawler";NA;407;0
"Unit";"Corruptor";"Larva";407;2
"Unit";"Corruptor";"Larva";407;2
"Unit";"Corruptor";"Larva";407;2
"Unit";"Corruptor";"Larva";407;2
"Unit";"Corruptor";"Larva";407;2
"Upgrade";"ZergMeleeWeaponsLevel1";"EvolutionChamber";407;0
"Upgrade";"ZergGroundArmorsLevel3";"EvolutionChamber";417;0
"Unit";"Roach";"Larva";430;2
"Unit";"Roach";"Larva";430;2
"Unit";"Roach";"Larva";430;2
"Unit";"Roach";"Larva";430;2
"Unit";"Roach";"Larva";430;2
"Unit";"Roach";"Larva";430;2
"Unit";"Roach";"Larva";430;2
"Unit";"Hydralisk";"Larva";430;2
"Unit";"Hydralisk";"Larva";446;2
"Unit";"Hydralisk";"Larva";446;2
"Unit";"Hydralisk";"Larva";446;2
"Unit";"Hydralisk";"Larva";446;2
"Unit";"Hydralisk";"Larva";446;2
"Unit";"Hydralisk";"Larva";446;2
"Unit";"Hydralisk";"Larva";446;2
"Unit";"Hydralisk";"Larva";446;2
"Unit";"Hydralisk";"Larva";446;2
"Unit";"Hydralisk";"Larva";446;2
"Unit";"Hydralisk";"Larva";446;2
"Unit";"Hydralisk";"Larva";446;2
"Unit";"Hydralisk";"Larva";446;2
"Unit";"Hydralisk";"Larva";446;2
"Unit";"Viper";"Larva";446;3
"Unit";"Viper";"Larva";446;3
"Unit";"Viper";"Larva";446;3
"Unit";"Viper";"Larva";446;3
"Unit";"Roach";"Larva";486;2
"Unit";"Roach";"Larva";486;2
"Unit";"Roach";"Larva";486;2
"Unit";"Roach";"Larva";486;2
"Unit";"Roach";"Larva";486;2
"Unit";"Roach";"Larva";486;2
"Unit";"Roach";"Larva";486;2
"Unit";"Roach";"Larva";486;2
"Unit";"Roach";"Larva";486;2
"Unit";"Roach";"Larva";486;2
"Unit";"Roach";"Larva";486;2
"Unit";"Roach";"Larva";486;2
"Unit";"Roach";"Larva";486;2
"Unit";"Roach";"Larva";486;2
"Unit";"Roach";"Larva";486;2
"Unit";"Roach";"Larva";486;2
"Building";"Hatchery";NA;486;0
"Unit";"Hydralisk";"Larva";520;2
"Unit";"Hydralisk";"Larva";520;2
"Unit";"Hydralisk";"Larva";520;2
"Unit";"Hydralisk";"Larva";520;2
