"type";"unit_name";"on_building";"total_supply";"supply"
"Unit";"Overlord";"Larva";13;0
"Building";"Extractor";NA;17;0
"Unit";"Overlord";"Larva";21;0
"Building";"Hatchery";NA;16;0
"Building";"SpawningPool";NA;19;0
"Unit";"Zergling";"Larva";22;1
"Unit";"Zergling";"Larva";22;1
"Unit";"Zergling";"Larva";22;1
"Unit";"Zergling";"Larva";22;1
"Unit";"Zergling";"Larva";22;1
"Unit";"Zergling";"Larva";22;1
"Unit";"Queen";"Hatchery";22;2
"Unit";"Queen";"Hatchery";22;2
"Unit";"Overlord";"Larva";38;0
"Unit";"Zergling";"Larva";41;1
"Unit";"Zergling";"Larva";41;1
"Unit";"Overlord";"Larva";41;0
"Unit";"Zergling";"Larva";43;1
"Unit";"Zergling";"Larva";43;1
"Unit";"Zergling";"Larva";43;1
"Unit";"Zergling";"Larva";43;1
"Unit";"Zergling";"Larva";43;1
"Unit";"Zergling";"Larva";43;1
"Unit";"Zergling";"Larva";43;1
"Unit";"Zergling";"Larva";43;1
"Unit";"Zergling";"Larva";43;1
"Unit";"Zergling";"Larva";43;1
"Unit";"Overlord";"Larva";43;0
"Building";"Hatchery";NA;37;0
"Unit";"Overlord";"Larva";56;0
"Building";"EvolutionChamber";NA;57;0
"Building";"Extractor";NA;66;0
"Unit";"Zergling";"Larva";70;1
"Unit";"Zergling";"Larva";70;1
"Unit";"Zergling";"Larva";70;1
"Unit";"Zergling";"Larva";70;1
"Unit";"Zergling";"Larva";70;1
"Unit";"Zergling";"Larva";70;1
"Unit";"Zergling";"Larva";70;1
"Unit";"Zergling";"Larva";70;1
"Unit";"Queen";"Hatchery";66;2
"Unit";"Zergling";"Larva";76;1
"Unit";"Zergling";"Larva";76;1
"Unit";"Overlord";"Larva";88;0
"Building";"Extractor";NA;88;0
"Building";"RoachWarren";NA;76;0
"Unit";"Overlord";"Larva";93;0
"Unit";"Overlord";"Larva";93;0
"Unit";"Roach";"Larva";96;2
"Unit";"Roach";"Larva";96;2
"Unit";"Roach";"Larva";96;2
"Unit";"Roach";"Larva";96;2
"Unit";"Roach";"Larva";96;2
"Unit";"Roach";"Larva";96;2
"Unit";"Roach";"Larva";96;2
"Unit";"Roach";"Larva";96;2
"Unit";"Roach";"Larva";96;2
"Unit";"Roach";"Larva";96;2
"Unit";"Roach";"Larva";96;2
"Unit";"Roach";"Larva";96;2
"Unit";"Roach";"Larva";96;2
"Unit";"Roach";"Larva";96;2
"Unit";"Roach";"Larva";96;2
"Unit";"Roach";"Larva";96;2
"Building";"Extractor";NA;96;0
"Unit";"Roach";"Larva";96;2
"Unit";"Roach";"Larva";96;2
"Unit";"Roach";"Larva";118;2
"Unit";"Roach";"Larva";120;2
"Unit";"Roach";"Larva";128;2
"Unit";"Roach";"Larva";128;2
"Unit";"Roach";"Larva";128;2
"Unit";"Overlord";"Larva";132;0
"Unit";"Overlord";"Larva";132;0
"Unit";"Overlord";"Larva";132;0
"Unit";"Overlord";"Larva";132;0
"Upgrade";"ZergMissileWeaponsLevel1";"EvolutionChamber";90;0
"Unit";"Overlord";"Larva";132;0
"Unit";"Roach";"Larva";144;2
"Unit";"Roach";"Larva";144;2
"Unit";"Roach";"Larva";144;2
"Unit";"Roach";"Larva";144;2
"Unit";"Roach";"Larva";144;2
"Unit";"Roach";"Larva";144;2
"Unit";"Roach";"Larva";144;2
"Unit";"Roach";"Larva";144;2
"Unit";"Roach";"Larva";144;2
"Unit";"Roach";"Larva";144;2
"Unit";"Queen";"Hatchery";144;2
"Unit";"Roach";"Larva";144;2
"Unit";"Overlord";"Larva";154;0
"Unit";"Overlord";"Larva";154;0
"Unit";"Roach";"Larva";154;2
"Unit";"Roach";"Larva";154;2
"Unit";"Roach";"Larva";154;2
"Unit";"Roach";"Larva";156;2
"Unit";"Roach";"Larva";160;2
"Unit";"Roach";"Larva";160;2
"Unit";"Roach";"Larva";162;2
"Unit";"Overlord";"Larva";164;0
"Unit";"Roach";"Larva";168;2
"Unit";"Roach";"Larva";168;2
"Unit";"Roach";"Larva";174;2
"Unit";"Roach";"Larva";180;2
"Unit";"Roach";"Larva";180;2
"Unit";"Roach";"Larva";180;2
"Unit";"Overlord";"Larva";182;0
"Unit";"Roach";"Larva";182;2
"Unit";"Roach";"Larva";182;2
"Unit";"Roach";"Larva";182;2
"Upgrade";"GlialReconstitution";"RoachWarren";144;0
"Unit";"Roach";"Larva";182;2
"Unit";"Overlord";"Larva";188;0
"Unit";"Overlord";"Larva";188;0
"Unit";"Overlord";"Larva";188;0
"Unit";"Roach";"Larva";195;2
"Unit";"Roach";"Larva";201;2
"Unit";"Overlord";"Larva";203;0
"Unit";"Overlord";"Larva";203;0
"Unit";"Roach";"Larva";203;2
"Unit";"Roach";"Larva";203;2
"Unit";"Roach";"Larva";203;2
"Unit";"Roach";"Larva";203;2
"Unit";"Roach";"Larva";203;2
"Unit";"Roach";"Larva";203;2
"Unit";"Roach";"Larva";207;2
"Building";"Extractor";NA;207;0
"Unit";"Roach";"Larva";223;2
"Unit";"Roach";"Larva";223;2
"Unit";"Roach";"Larva";223;2
"Unit";"Roach";"Larva";223;2
"Unit";"Roach";"Larva";223;2
"Unit";"Roach";"Larva";225;2
"Unit";"Roach";"Larva";225;2
"Unit";"Roach";"Larva";225;2
"Unit";"Roach";"Larva";225;2
"Unit";"Roach";"Larva";225;2
"Unit";"Roach";"Larva";225;2
"Unit";"Roach";"Larva";227;2
"Unit";"Roach";"Larva";247;2
"Unit";"Roach";"Larva";247;2
"Unit";"Roach";"Larva";247;2
"Unit";"Roach";"Larva";247;2
"Unit";"Roach";"Larva";247;2
"Unit";"Roach";"Larva";247;2
"Unit";"Roach";"Larva";249;2
"Unit";"Roach";"Larva";249;2
"Unit";"Overlord";"Larva";251;0
"Building";"Hatchery";NA;225;0
"Unit";"Roach";"Larva";265;2
"Unit";"Roach";"Larva";265;2
"Unit";"Roach";"Larva";265;2
"Unit";"Roach";"Larva";265;2
"Unit";"Roach";"Larva";265;2
"Unit";"Roach";"Larva";265;2
"Unit";"Roach";"Larva";265;2
"Unit";"Roach";"Larva";265;2
"Unit";"Roach";"Larva";265;2
"Unit";"Roach";"Larva";265;2
"Unit";"Roach";"Larva";265;2
"Unit";"Roach";"Larva";265;2
"Unit";"Roach";"Larva";265;2
"Unit";"Roach";"Larva";265;2
"Unit";"Roach";"Larva";265;2
"Unit";"Roach";"Larva";265;2
"Upgrade";"ZergMissileWeaponsLevel2";"EvolutionChamber";221;0
"Unit";"Roach";"Larva";265;2
"Unit";"Roach";"Larva";265;2
"Unit";"Roach";"Larva";265;2
"Unit";"Roach";"Larva";265;2
"Unit";"Roach";"Larva";265;2
"Unit";"Roach";"Larva";265;2
"Unit";"Roach";"Larva";297;2
"Unit";"Roach";"Larva";297;2
"Unit";"Roach";"Larva";297;2
"Unit";"Roach";"Larva";297;2
"Unit";"Roach";"Larva";297;2
"Unit";"Roach";"Larva";297;2
"Unit";"Roach";"Larva";297;2
"Unit";"Roach";"Larva";305;2
"Unit";"Roach";"Larva";305;2
"Unit";"Roach";"Larva";305;2
"Unit";"Roach";"Larva";305;2
"Unit";"Roach";"Larva";309;2
"Unit";"Roach";"Larva";309;2
"Unit";"Roach";"Larva";323;2
"Unit";"Roach";"Larva";323;2
"Unit";"Roach";"Larva";329;2
"Unit";"Queen";"Hatchery";305;2
"Unit";"Roach";"Larva";329;2
"Unit";"Roach";"Larva";329;2
"Unit";"Roach";"Larva";329;2
"Unit";"Roach";"Larva";331;2
"Unit";"Roach";"Larva";333;2
"Unit";"Roach";"Larva";335;2
"Unit";"Roach";"Larva";335;2
"Unit";"Roach";"Larva";337;2
"Unit";"Roach";"Larva";339;2
"Unit";"Roach";"Larva";341;2
"Unit";"Roach";"Larva";345;2
"Unit";"Roach";"Larva";345;2
"Unit";"Roach";"Larva";345;2
"Unit";"Roach";"Larva";351;2
"Unit";"Roach";"Larva";371;2
"Unit";"Roach";"Larva";371;2
"Unit";"Roach";"Larva";371;2
"Unit";"Roach";"Larva";371;2
"Unit";"Roach";"Larva";371;2
"Unit";"Roach";"Larva";371;2
"Unit";"Roach";"Larva";371;2
"Unit";"Roach";"Larva";371;2
"Unit";"Roach";"Larva";371;2
"Unit";"Roach";"Larva";371;2
"Unit";"Roach";"Larva";371;2
"Unit";"Roach";"Larva";371;2
"Unit";"Roach";"Larva";371;2
"Unit";"Roach";"Larva";371;2
"Unit";"Roach";"Larva";371;2
"Unit";"Roach";"Larva";371;2
"Unit";"Roach";"Larva";371;2
"Unit";"Roach";"Larva";371;2
"Unit";"Roach";"Larva";373;2
