"type";"unit_name";"on_building";"total_supply";"supply"
"Unit";"Overlord";"Larva";13;0
"Building";"Extractor";NA;17;0
"Building";"SpawningPool";NA;15;0
"Unit";"Zergling";"Larva";21;1
"Unit";"Zergling";"Larva";21;1
"Unit";"Queen";"Hatchery";20;2
"Unit";"Overlord";"Larva";21;0
"Building";"Hatchery";NA;19;0
"Unit";"Queen";"Hatchery";26;2
"Unit";"Queen";"Hatchery";28;2
"Unit";"Zergling";"Larva";37;1
"Unit";"Zergling";"Larva";37;1
"Unit";"Zergling";"Larva";37;1
"Unit";"Zergling";"Larva";37;1
"Unit";"Zergling";"Larva";37;1
"Unit";"Zergling";"Larva";37;1
"Unit";"Overlord";"Larva";37;0
"Building";"CreepTumorQueen";NA;43;0
"Building";"BanelingNest";NA;33;0
"Unit";"Overlord";"Larva";45;0
"Unit";"Baneling";"Zergling";45;0
"Unit";"Baneling";"Zergling";45;0
"Unit";"Overlord";"Larva";45;0
"Unit";"Overlord";"Larva";45;0
"Building";"CreepTumorQueen";NA;51;0
"Building";"CreepTumor";NA;51;0
"Building";"Extractor";NA;51;0
"Unit";"Baneling";"Zergling";51;0
"Unit";"Baneling";"Zergling";51;0
"Building";"Extractor";NA;51;0
"Building";"RoachWarren";NA;51;0
"Building";"Extractor";NA;57;0
"Unit";"Zergling";"Larva";62;1
"Unit";"Zergling";"Larva";62;1
"Unit";"Zergling";"Larva";62;1
"Unit";"Zergling";"Larva";62;1
"Unit";"Zergling";"Larva";62;1
"Unit";"Zergling";"Larva";62;1
"Unit";"Zergling";"Larva";62;1
"Unit";"Zergling";"Larva";62;1
"Unit";"Zergling";"Larva";62;1
"Unit";"Zergling";"Larva";62;1
"Unit";"Zergling";"Larva";62;1
"Unit";"Zergling";"Larva";62;1
"Unit";"Zergling";"Larva";62;1
"Unit";"Zergling";"Larva";62;1
"Unit";"Zergling";"Larva";62;1
"Unit";"Zergling";"Larva";62;1
"Unit";"Zergling";"Larva";62;1
"Unit";"Zergling";"Larva";62;1
"Unit";"Zergling";"Larva";62;1
"Unit";"Zergling";"Larva";62;1
"Unit";"Zergling";"Larva";62;1
"Unit";"Zergling";"Larva";62;1
"Unit";"Zergling";"Larva";72;1
"Unit";"Zergling";"Larva";72;1
"Unit";"Zergling";"Larva";72;1
"Unit";"Zergling";"Larva";72;1
"Unit";"Baneling";"Zergling";84;0
"Unit";"Baneling";"Zergling";84;0
"Unit";"Baneling";"Zergling";84;0
"Unit";"Baneling";"Zergling";86;0
"Building";"CreepTumor";NA;88;0
"Building";"CreepTumor";NA;88;0
"Unit";"Roach";"Larva";88;2
"Unit";"Roach";"Larva";88;2
"Unit";"Roach";"Larva";88;2
"Unit";"Baneling";"Zergling";88;0
"Unit";"Baneling";"Zergling";88;0
"Unit";"Baneling";"Zergling";94;0
"Unit";"Roach";"Larva";94;2
"Unit";"Roach";"Larva";94;2
"Unit";"Roach";"Larva";94;2
"Building";"CreepTumor";NA;94;0
"Building";"CreepTumorQueen";NA;98;0
"Building";"CreepTumor";NA;97;0
"Unit";"Queen";"Hatchery";94;2
"Unit";"Overlord";"Larva";98;0
"Unit";"Overlord";"Larva";104;0
"Unit";"Overlord";"Larva";104;0
"Building";"Hatchery";NA;88;0
"Building";"CreepTumor";NA;106;0
"Building";"CreepTumor";NA;108;0
"Building";"CreepTumor";NA;108;0
"Unit";"Queen";"Hatchery";104;2
"Building";"CreepTumor";NA;114;0
"Building";"CreepTumor";NA;119;0
"Upgrade";"GlialReconstitution";"RoachWarren";106;0
"Building";"SpineCrawler";NA;119;0
"Unit";"Roach";"Larva";129;2
"Unit";"Roach";"Larva";129;2
"Unit";"Overlord";"Larva";129;0
"Unit";"Overlord";"Larva";129;0
"Unit";"Overlord";"Larva";129;0
"Unit";"Overlord";"Larva";129;0
"Unit";"Overlord";"Larva";129;0
"Building";"Extractor";NA;129;0
"Building";"Extractor";NA;129;0
"Building";"EvolutionChamber";NA;129;0
"Building";"EvolutionChamber";NA;129;0
"Building";"CreepTumor";NA;133;0
"Unit";"Roach";"Larva";129;2
"Unit";"Roach";"Larva";133;2
"Unit";"Roach";"Larva";133;2
"Unit";"Roach";"Larva";133;2
"Unit";"Roach";"Larva";133;2
"Unit";"Roach";"Larva";133;2
"Unit";"Roach";"Larva";133;2
"Unit";"Roach";"Larva";133;2
"Unit";"Roach";"Larva";133;2
"Unit";"Roach";"Larva";133;2
"Unit";"Roach";"Larva";133;2
"Building";"CreepTumor";NA;133;0
"Unit";"Overlord";"Larva";135;0
"Unit";"Overlord";"Larva";135;0
"Building";"CreepTumor";NA;158;0
"Unit";"Overlord";"Larva";155;0
"Building";"CreepTumor";NA;161;0
"Building";"CreepTumor";NA;161;0
"Unit";"Roach";"Larva";161;2
"Unit";"Roach";"Larva";161;2
"Unit";"Roach";"Larva";161;2
"Unit";"Roach";"Larva";161;2
"Unit";"Roach";"Larva";161;2
"Unit";"Roach";"Larva";161;2
"Unit";"Roach";"Larva";161;2
"Building";"HydraliskDen";NA;155;0
"Unit";"Overlord";"Larva";161;0
"Unit";"Overlord";"Larva";161;0
"Unit";"Overlord";"Larva";161;0
"Unit";"Overlord";"Larva";161;0
"Unit";"Hydralisk";"Larva";175;2
"Unit";"Hydralisk";"Larva";175;2
"Unit";"Hydralisk";"Larva";175;2
"Unit";"Hydralisk";"Larva";175;2
"Building";"CreepTumor";NA;175;0
"Building";"InfestationPit";NA;175;0
"Building";"SpineCrawler";NA;175;0
"Building";"CreepTumor";NA;183;0
"Upgrade";"ZergMissileWeaponsLevel1";"EvolutionChamber";161;0
"Upgrade";"ZergGroundArmorsLevel1";"EvolutionChamber";161;0
"Upgrade";"EvolveGroovedSpines";"HydraliskDen";175;0
"Unit";"Hydralisk";"Larva";183;2
"Unit";"Hydralisk";"Larva";183;2
"Unit";"Hydralisk";"Larva";183;2
"Unit";"Hydralisk";"Larva";183;2
"Unit";"Hydralisk";"Larva";183;2
"Unit";"Hydralisk";"Larva";183;2
"Unit";"Hydralisk";"Larva";183;2
"Unit";"Hydralisk";"Larva";183;2
"Unit";"Hydralisk";"Larva";183;2
"Unit";"Hydralisk";"Larva";183;2
"Unit";"Hydralisk";"Larva";183;2
"Unit";"Hydralisk";"Larva";183;2
"Unit";"Hydralisk";"Larva";183;2
"Unit";"Hydralisk";"Larva";183;2
"Unit";"Hydralisk";"Larva";183;2
"Unit";"Roach";"Larva";183;2
"Unit";"Roach";"Larva";183;2
"Unit";"Roach";"Larva";183;2
"Unit";"Roach";"Larva";183;2
"Unit";"Roach";"Larva";183;2
"Unit";"Roach";"Larva";183;2
"Unit";"Roach";"Larva";183;2
"Unit";"Roach";"Larva";183;2
"Unit";"Roach";"Larva";183;2
"Building";"Hatchery";NA;183;0
"Unit";"Roach";"Larva";215;2
"Unit";"Roach";"Larva";215;2
"Unit";"Roach";"Larva";225;2
"Unit";"Roach";"Larva";231;2
"Unit";"Roach";"Larva";231;2
"Unit";"Roach";"Larva";231;2
"Unit";"Roach";"Larva";231;2
"Unit";"Roach";"Larva";231;2
"Unit";"Roach";"Larva";231;2
"Building";"CreepTumor";NA;249;0
"Building";"CreepTumor";NA;249;0
"Unit";"Queen";"Hatchery";249;2
"Building";"SpineCrawler";NA;256;0
"Building";"SpineCrawler";NA;256;0
"Unit";"Roach";"Larva";256;2
"Unit";"Roach";"Larva";258;2
"Unit";"Roach";"Larva";258;2
"Unit";"Roach";"Larva";258;2
"Unit";"Roach";"Larva";258;2
"Unit";"Roach";"Larva";258;2
"Unit";"Roach";"Larva";258;2
"Unit";"Roach";"Larva";258;2
"Unit";"Roach";"Larva";258;2
"Unit";"Roach";"Larva";258;2
"Unit";"Roach";"Larva";258;2
"Unit";"Roach";"Larva";258;2
"Unit";"Roach";"Larva";258;2
"Unit";"Roach";"Larva";258;2
"Unit";"Roach";"Larva";258;2
"Unit";"Roach";"Larva";258;2
"Unit";"Roach";"Larva";258;2
"Unit";"Roach";"Larva";258;2
"Unit";"Roach";"Larva";294;2
"Unit";"Roach";"Larva";294;2
"Unit";"Roach";"Larva";294;2
"Unit";"Roach";"Larva";294;2
"Unit";"Roach";"Larva";294;2
"Unit";"Roach";"Larva";294;2
"Unit";"Roach";"Larva";294;2
"Unit";"Roach";"Larva";294;2
"Unit";"Roach";"Larva";294;2
"Unit";"Roach";"Larva";294;2
"Unit";"Roach";"Larva";294;2
"Unit";"Roach";"Larva";294;2
"Unit";"Roach";"Larva";294;2
"Building";"CreepTumor";NA;294;0
"Building";"CreepTumorQueen";NA;294;0
"Building";"Extractor";NA;294;0
"Building";"Extractor";NA;294;0
"Upgrade";"EvolveMuscularAugments";"HydraliskDen";258;0
"Building";"CreepTumor";NA;326;0
"Unit";"Hydralisk";"Larva";320;2
"Unit";"Hydralisk";"Larva";320;2
"Unit";"Hydralisk";"Larva";320;2
"Unit";"Hydralisk";"Larva";320;2
"Building";"CreepTumor";NA;326;0
"Unit";"Hydralisk";"Larva";326;2
"Unit";"Hydralisk";"Larva";326;2
"Unit";"Hydralisk";"Larva";326;2
"Unit";"Hydralisk";"Larva";326;2
"Upgrade";"ZergMissileWeaponsLevel2";"EvolutionChamber";256;0
"Unit";"Hydralisk";"Larva";326;2
"Upgrade";"ZergGroundArmorsLevel2";"EvolutionChamber";256;0
"Unit";"Hydralisk";"Larva";326;2
"Unit";"Hydralisk";"Larva";326;2
"Unit";"Overlord";"Larva";348;0
"Unit";"Overlord";"Larva";348;0
"Unit";"Overlord";"Larva";348;0
"Unit";"Overlord";"Larva";348;0
"Unit";"Overlord";"Larva";348;0
"Building";"CreepTumor";NA;348;0
"Building";"CreepTumor";NA;348;0
"Building";"LurkerDenMP";NA;320;0
"Unit";"Hydralisk";"Larva";348;2
"Unit";"Hydralisk";"Larva";348;2
"Unit";"Hydralisk";"Larva";348;2
"Unit";"Hydralisk";"Larva";348;2
"Unit";"Hydralisk";"Larva";348;2
"Unit";"Hydralisk";"Larva";348;2
"Unit";"Hydralisk";"Larva";348;2
"Unit";"Hydralisk";"Larva";348;2
"Unit";"Hydralisk";"Larva";348;2
"Unit";"Hydralisk";"Larva";350;2
"Unit";"Hydralisk";"Larva";350;2
"Unit";"Hydralisk";"Larva";350;2
"Unit";"Hydralisk";"Larva";350;2
"Unit";"Hydralisk";"Larva";350;2
"Unit";"Hydralisk";"Larva";350;2
"Unit";"Hydralisk";"Larva";350;2
"Unit";"Hydralisk";"Larva";352;2
"Unit";"Hydralisk";"Larva";352;2
"Unit";"Hydralisk";"Larva";356;2
"Unit";"Hydralisk";"Larva";356;2
"Unit";"Hydralisk";"Larva";360;2
"Unit";"Hydralisk";"Larva";360;2
"Unit";"Hydralisk";"Larva";364;2
"Building";"Spire";NA;348;0
"Unit";"Hydralisk";"Larva";364;2
"Unit";"Hydralisk";"Larva";364;2
"Unit";"Hydralisk";"Larva";364;2
"Unit";"Hydralisk";"Larva";364;2
"Unit";"Hydralisk";"Larva";364;2
"Unit";"Hydralisk";"Larva";364;2
"Unit";"Hydralisk";"Larva";394;2
"Building";"SpineCrawler";NA;394;0
"Unit";"Hydralisk";"Larva";408;2
"Unit";"Hydralisk";"Larva";408;2
"Unit";"Hydralisk";"Larva";408;2
"Unit";"Hydralisk";"Larva";408;2
"Building";"SpawningPool";NA;394;0
