"type";"unit_name";"on_building";"total_supply";"supply"
"Unit";"Overlord";"Larva";13;0
"Building";"Extractor";NA;19;0
"Unit";"Overlord";"Larva";20;0
"Building";"SpawningPool";NA;19;0
"Building";"Hatchery";NA;17;0
"Unit";"Zergling";"Larva";22;1
"Unit";"Zergling";"Larva";22;1
"Unit";"Zergling";"Larva";23;1
"Unit";"Zergling";"Larva";23;1
"Unit";"Zergling";"Larva";23;1
"Unit";"Zergling";"Larva";23;1
"Unit";"Overlord";"Larva";23;0
"Unit";"Queen";"Hatchery";22;2
"Unit";"Queen";"Hatchery";23;2
"Unit";"Overlord";"Larva";35;0
"Unit";"Queen";"Hatchery";30;2
"Building";"CreepTumorQueen";NA;46;0
"Building";"EvolutionChamber";NA;51;0
"Building";"CreepTumor";NA;53;0
"Building";"EvolutionChamber";NA;51;0
"Building";"CreepTumorQueen";NA;53;0
"Building";"Extractor";NA;51;0
"Building";"RoachWarren";NA;50;0
"Unit";"Overlord";"Larva";57;0
"Unit";"Roach";"Larva";57;2
"Unit";"Roach";"Larva";57;2
"Unit";"Roach";"Larva";57;2
"Unit";"Roach";"Larva";57;2
"Unit";"Overlord";"Larva";57;0
"Unit";"Overlord";"Larva";57;0
"Building";"Extractor";NA;57;0
"Building";"Extractor";NA;57;0
"Building";"CreepTumor";NA;59;0
"Unit";"Overlord";"Larva";57;0
"Unit";"Zergling";"Larva";73;1
"Unit";"Zergling";"Larva";73;1
"Unit";"Zergling";"Larva";73;1
"Unit";"Zergling";"Larva";73;1
"Building";"CreepTumorQueen";NA;79;0
"Building";"CreepTumorQueen";NA;79;0
"Unit";"Overlord";"Larva";79;0
"Building";"CreepTumor";NA;81;0
"Unit";"Zergling";"Larva";79;1
"Unit";"Zergling";"Larva";79;1
"Unit";"Zergling";"Larva";79;1
"Unit";"Zergling";"Larva";79;1
"Unit";"Overlord";"Larva";79;0
"Unit";"Overlord";"Larva";79;0
"Building";"Spire";NA;65;0
"Building";"CreepTumor";NA;81;0
"Unit";"Overlord";"Larva";81;0
"Building";"Extractor";NA;81;0
"Building";"Extractor";NA;81;0
"Building";"CreepTumor";NA;87;0
"Unit";"Mutalisk";"Larva";91;2
"Unit";"Mutalisk";"Larva";91;2
"Unit";"Mutalisk";"Larva";91;2
"Unit";"Mutalisk";"Larva";91;2
"Unit";"Mutalisk";"Larva";91;2
"Unit";"Mutalisk";"Larva";91;2
"Building";"Hatchery";NA;79;0
"Unit";"Mutalisk";"Larva";91;2
"Building";"CreepTumor";NA;91;0
"Unit";"Mutalisk";"Larva";91;2
"Building";"CreepTumor";NA;91;0
"Unit";"Mutalisk";"Larva";91;2
"Unit";"Overlord";"Larva";91;0
"Unit";"Mutalisk";"Larva";105;2
"Unit";"Mutalisk";"Larva";105;2
"Unit";"Mutalisk";"Larva";111;2
"Unit";"Mutalisk";"Larva";115;2
"Unit";"Mutalisk";"Larva";115;2
"Unit";"Overlord";"Larva";123;0
"Unit";"Overlord";"Larva";123;0
"Unit";"Mutalisk";"Larva";123;2
"Unit";"Zergling";"Larva";131;1
"Unit";"Zergling";"Larva";131;1
"Unit";"Zergling";"Larva";131;1
"Unit";"Zergling";"Larva";131;1
"Unit";"Zergling";"Larva";131;1
"Unit";"Zergling";"Larva";131;1
"Unit";"Zergling";"Larva";131;1
"Unit";"Zergling";"Larva";131;1
"Unit";"Zergling";"Larva";131;1
"Unit";"Zergling";"Larva";131;1
"Unit";"Mutalisk";"Larva";129;2
"Unit";"Mutalisk";"Larva";129;2
"Unit";"Mutalisk";"Larva";129;2
"Unit";"Mutalisk";"Larva";141;2
"Unit";"Zergling";"Larva";149;1
"Unit";"Zergling";"Larva";149;1
"Unit";"Zergling";"Larva";149;1
"Unit";"Zergling";"Larva";149;1
"Unit";"Zergling";"Larva";149;1
"Unit";"Zergling";"Larva";149;1
"Unit";"Zergling";"Larva";149;1
"Unit";"Zergling";"Larva";149;1
"Building";"BanelingNest";NA;131;0
"Unit";"Zergling";"Larva";151;1
"Unit";"Zergling";"Larva";151;1
"Unit";"Zergling";"Larva";151;1
"Unit";"Zergling";"Larva";151;1
"Unit";"Overlord";"Larva";151;0
"Unit";"Mutalisk";"Larva";149;2
"Unit";"Overlord";"Larva";151;0
"Unit";"Mutalisk";"Larva";149;2
"Unit";"Overlord";"Larva";151;0
"Unit";"Mutalisk";"Larva";149;2
"Unit";"Overlord";"Larva";159;0
"Unit";"Baneling";"Zergling";162;0
"Unit";"Baneling";"Zergling";162;0
"Unit";"Baneling";"Zergling";162;0
"Unit";"Baneling";"Zergling";162;0
"Unit";"Baneling";"Zergling";162;0
"Unit";"Baneling";"Zergling";162;0
"Unit";"Baneling";"Zergling";162;0
"Unit";"Baneling";"Zergling";162;0
"Unit";"Baneling";"Zergling";162;0
"Building";"CreepTumorQueen";NA;173;0
"Unit";"Zergling";"Larva";173;1
"Unit";"Zergling";"Larva";173;1
"Unit";"Zergling";"Larva";173;1
"Unit";"Zergling";"Larva";173;1
"Unit";"Zergling";"Larva";173;1
"Unit";"Zergling";"Larva";173;1
"Unit";"Zergling";"Larva";173;1
"Unit";"Zergling";"Larva";173;1
"Unit";"Queen";"Hatchery";159;2
"Building";"Hatchery";NA;149;0
"Unit";"Zergling";"Larva";183;1
"Unit";"Zergling";"Larva";183;1
"Unit";"Zergling";"Larva";183;1
"Unit";"Zergling";"Larva";183;1
"Unit";"Zergling";"Larva";183;1
"Unit";"Zergling";"Larva";183;1
"Unit";"Zergling";"Larva";183;1
"Unit";"Zergling";"Larva";183;1
"Unit";"Zergling";"Larva";183;1
"Unit";"Zergling";"Larva";183;1
"Unit";"Zergling";"Larva";183;1
"Unit";"Zergling";"Larva";183;1
"Unit";"Zergling";"Larva";183;1
"Unit";"Zergling";"Larva";183;1
"Unit";"Zergling";"Larva";183;1
"Unit";"Zergling";"Larva";183;1
"Unit";"Zergling";"Larva";183;1
"Unit";"Zergling";"Larva";183;1
"Unit";"Zergling";"Larva";183;1
"Unit";"Zergling";"Larva";183;1
"Unit";"Mutalisk";"Larva";183;2
"Unit";"Mutalisk";"Larva";183;2
"Unit";"Mutalisk";"Larva";183;2
"Unit";"Mutalisk";"Larva";183;2
"Unit";"Overlord";"Larva";183;0
"Unit";"Mutalisk";"Larva";183;2
"Unit";"Mutalisk";"Larva";183;2
"Upgrade";"ZergMeleeWeaponsLevel1";"EvolutionChamber";151;0
"Unit";"Mutalisk";"Larva";183;2
"Unit";"Queen";"Hatchery";183;2
"Unit";"Zergling";"Larva";209;1
"Unit";"Zergling";"Larva";209;1
"Unit";"Zergling";"Larva";209;1
"Unit";"Zergling";"Larva";209;1
"Unit";"Zergling";"Larva";209;1
"Unit";"Zergling";"Larva";209;1
"Unit";"Zergling";"Larva";209;1
"Unit";"Zergling";"Larva";209;1
"Unit";"Mutalisk";"Larva";207;2
"Unit";"Mutalisk";"Larva";209;2
"Unit";"Mutalisk";"Larva";217;2
"Unit";"Mutalisk";"Larva";217;2
"Unit";"Mutalisk";"Larva";229;2
"Unit";"Mutalisk";"Larva";231;2
"Unit";"Zergling";"Larva";235;1
"Unit";"Zergling";"Larva";235;1
"Unit";"Zergling";"Larva";235;1
"Unit";"Zergling";"Larva";235;1
"Unit";"Zergling";"Larva";235;1
"Unit";"Zergling";"Larva";235;1
"Unit";"Zergling";"Larva";235;1
"Unit";"Zergling";"Larva";235;1
"Unit";"Zergling";"Larva";235;1
"Unit";"Zergling";"Larva";235;1
"Unit";"Zergling";"Larva";235;1
"Unit";"Zergling";"Larva";235;1
"Unit";"Mutalisk";"Larva";231;2
"Unit";"Mutalisk";"Larva";235;2
"Unit";"Mutalisk";"Larva";235;2
"Unit";"Baneling";"Zergling";255;0
"Unit";"Baneling";"Zergling";255;0
"Unit";"Baneling";"Zergling";255;0
"Unit";"Baneling";"Zergling";255;0
"Unit";"Baneling";"Zergling";255;0
"Unit";"Baneling";"Zergling";255;0
"Unit";"Baneling";"Zergling";255;0
"Unit";"Baneling";"Zergling";255;0
"Unit";"Baneling";"Zergling";255;0
"Unit";"Baneling";"Zergling";255;0
"Unit";"Baneling";"Zergling";255;0
"Unit";"Baneling";"Zergling";255;0
"Unit";"Zergling";"Larva";255;1
"Unit";"Zergling";"Larva";255;1
"Unit";"Zergling";"Larva";255;1
"Unit";"Zergling";"Larva";255;1
"Unit";"Zergling";"Larva";255;1
"Unit";"Zergling";"Larva";255;1
"Unit";"Zergling";"Larva";255;1
"Unit";"Zergling";"Larva";255;1
"Unit";"Zergling";"Larva";255;1
"Unit";"Zergling";"Larva";255;1
"Unit";"Baneling";"Zergling";257;0
"Unit";"Baneling";"Zergling";257;0
"Unit";"Baneling";"Zergling";257;0
"Unit";"Baneling";"Zergling";257;0
"Unit";"Baneling";"Zergling";257;0
"Unit";"Baneling";"Zergling";257;0
"Unit";"Baneling";"Zergling";257;0
"Unit";"Zergling";"Larva";257;1
"Unit";"Zergling";"Larva";257;1
