"type";"unit_name";"on_building";"total_supply";"supply"
"Unit";"Overlord";"Larva";12;0
"Building";"SpawningPool";NA;14;0
"Building";"Extractor";NA;18;0
"Unit";"Zergling";"Larva";18;1
"Unit";"Zergling";"Larva";18;1
"Unit";"Zergling";"Larva";18;1
"Unit";"Zergling";"Larva";18;1
"Unit";"Zergling";"Larva";18;1
"Unit";"Zergling";"Larva";18;1
"Unit";"Overlord";"Larva";25;0
"Unit";"Queen";"Hatchery";19;2
"Unit";"Zergling";"Larva";26;1
"Unit";"Zergling";"Larva";26;1
"Building";"Hatchery";NA;18;0
"Building";"BanelingNest";NA;26;0
"Unit";"Queen";"Hatchery";28;2
"Unit";"Baneling";"Zergling";33;0
"Unit";"Baneling";"Zergling";37;0
"Unit";"Zergling";"Larva";37;1
"Unit";"Zergling";"Larva";37;1
"Unit";"Zergling";"Larva";37;1
"Unit";"Zergling";"Larva";37;1
"Unit";"Overlord";"Larva";40;0
"Unit";"Baneling";"Zergling";46;0
"Unit";"Baneling";"Zergling";46;0
"Unit";"Zergling";"Larva";46;1
"Unit";"Zergling";"Larva";46;1
"Unit";"Zergling";"Larva";46;1
"Unit";"Zergling";"Larva";46;1
"Unit";"Zergling";"Larva";46;1
"Unit";"Zergling";"Larva";46;1
"Unit";"Zergling";"Larva";46;1
"Unit";"Zergling";"Larva";46;1
"Unit";"Zergling";"Larva";46;1
"Unit";"Zergling";"Larva";46;1
"Unit";"Zergling";"Larva";46;1
"Unit";"Zergling";"Larva";46;1
"Unit";"Zergling";"Larva";46;1
"Unit";"Zergling";"Larva";46;1
"Unit";"Overlord";"Larva";63;0
"Unit";"Overlord";"Larva";63;0
"Unit";"Baneling";"Zergling";63;0
"Unit";"Baneling";"Zergling";63;0
"Unit";"Baneling";"Zergling";63;0
"Building";"CreepTumorQueen";NA;64;0
"Building";"SpineCrawler";NA;66;0
"Unit";"Zergling";"Larva";72;1
"Unit";"Zergling";"Larva";72;1
"Unit";"Zergling";"Larva";72;1
"Unit";"Zergling";"Larva";72;1
"Unit";"Zergling";"Larva";72;1
"Unit";"Zergling";"Larva";72;1
"Unit";"Zergling";"Larva";72;1
"Unit";"Zergling";"Larva";72;1
"Unit";"Zergling";"Larva";72;1
"Unit";"Zergling";"Larva";72;1
"Unit";"Zergling";"Larva";72;1
"Unit";"Zergling";"Larva";72;1
"Unit";"Zergling";"Larva";72;1
"Unit";"Zergling";"Larva";72;1
"Unit";"Zergling";"Larva";72;1
"Unit";"Zergling";"Larva";72;1
"Unit";"Zergling";"Larva";72;1
"Unit";"Zergling";"Larva";72;1
"Unit";"Zergling";"Larva";72;1
"Unit";"Zergling";"Larva";72;1
"Unit";"Zergling";"Larva";72;1
"Unit";"Zergling";"Larva";72;1
"Unit";"Zergling";"Larva";72;1
"Unit";"Zergling";"Larva";72;1
"Unit";"Zergling";"Larva";82;1
"Unit";"Zergling";"Larva";82;1
"Unit";"Zergling";"Larva";82;1
"Unit";"Zergling";"Larva";82;1
"Building";"Extractor";NA;96;0
"Unit";"Baneling";"Zergling";100;0
"Unit";"Baneling";"Zergling";100;0
"Unit";"Baneling";"Zergling";100;0
"Unit";"Zergling";"Larva";100;1
"Unit";"Zergling";"Larva";100;1
"Unit";"Zergling";"Larva";100;1
"Unit";"Zergling";"Larva";100;1
"Unit";"Zergling";"Larva";100;1
"Unit";"Zergling";"Larva";100;1
"Unit";"Zergling";"Larva";100;1
"Unit";"Zergling";"Larva";100;1
"Unit";"Queen";"Hatchery";82;2
"Building";"Extractor";NA;100;0
"Building";"Extractor";NA;100;0
"Unit";"Overlord";"Larva";114;0
"Unit";"Baneling";"Zergling";115;0
"Unit";"Baneling";"Zergling";115;0
"Unit";"Queen";"Hatchery";112;2
"Unit";"Zergling";"Larva";116;1
"Unit";"Zergling";"Larva";116;1
"Unit";"Zergling";"Larva";116;1
"Unit";"Zergling";"Larva";116;1
"Unit";"Zergling";"Larva";125;1
"Unit";"Zergling";"Larva";125;1
"Unit";"Zergling";"Larva";125;1
"Unit";"Zergling";"Larva";125;1
"Unit";"Zergling";"Larva";125;1
"Unit";"Zergling";"Larva";125;1
"Unit";"Zergling";"Larva";125;1
"Unit";"Zergling";"Larva";125;1
"Unit";"Zergling";"Larva";125;1
"Unit";"Zergling";"Larva";125;1
"Unit";"Zergling";"Larva";125;1
"Unit";"Zergling";"Larva";125;1
"Unit";"Zergling";"Larva";125;1
"Unit";"Zergling";"Larva";125;1
"Unit";"Zergling";"Larva";125;1
"Unit";"Zergling";"Larva";125;1
"Building";"SpineCrawler";NA;119;0
"Building";"Spire";NA;112;0
"Unit";"Mutalisk";"Larva";141;2
"Unit";"Mutalisk";"Larva";141;2
"Unit";"Mutalisk";"Larva";141;2
"Unit";"Mutalisk";"Larva";141;2
"Unit";"Mutalisk";"Larva";141;2
"Unit";"Mutalisk";"Larva";141;2
"Unit";"Mutalisk";"Larva";141;2
"Unit";"Overlord";"Larva";141;0
"Unit";"Mutalisk";"Larva";141;2
"Unit";"Overlord";"Larva";141;0
"Unit";"Overlord";"Larva";145;0
"Unit";"Overlord";"Larva";145;0
"Building";"EvolutionChamber";NA;161;0
"Unit";"Mutalisk";"Larva";161;2
"Unit";"Mutalisk";"Larva";161;2
"Unit";"Mutalisk";"Larva";161;2
"Unit";"Mutalisk";"Larva";161;2
"Unit";"Mutalisk";"Larva";176;2
"Unit";"Mutalisk";"Larva";176;2
"Unit";"Mutalisk";"Larva";176;2
"Unit";"Mutalisk";"Larva";176;2
"Unit";"Baneling";"Zergling";184;0
"Unit";"Baneling";"Zergling";184;0
"Unit";"Baneling";"Zergling";184;0
"Unit";"Baneling";"Zergling";184;0
"Unit";"Zergling";"Larva";184;1
"Unit";"Zergling";"Larva";184;1
"Unit";"Zergling";"Larva";184;1
"Unit";"Zergling";"Larva";184;1
"Unit";"Zergling";"Larva";184;1
"Unit";"Zergling";"Larva";184;1
"Unit";"Zergling";"Larva";184;1
"Unit";"Zergling";"Larva";184;1
"Unit";"Zergling";"Larva";184;1
"Unit";"Zergling";"Larva";184;1
"Unit";"Zergling";"Larva";184;1
"Unit";"Zergling";"Larva";184;1
"Unit";"Zergling";"Larva";184;1
"Unit";"Zergling";"Larva";184;1
"Unit";"Zergling";"Larva";184;1
"Unit";"Zergling";"Larva";184;1
"Unit";"Zergling";"Larva";184;1
"Unit";"Zergling";"Larva";184;1
"Unit";"Zergling";"Larva";202;1
"Unit";"Zergling";"Larva";202;1
"Unit";"Zergling";"Larva";202;1
"Unit";"Zergling";"Larva";202;1
"Unit";"Zergling";"Larva";202;1
"Unit";"Zergling";"Larva";202;1
"Unit";"Zergling";"Larva";202;1
"Unit";"Zergling";"Larva";202;1
"Unit";"Zergling";"Larva";202;1
"Unit";"Zergling";"Larva";202;1
"Unit";"Zergling";"Larva";202;1
"Unit";"Zergling";"Larva";202;1
"Building";"EvolutionChamber";NA;202;0
"Building";"Hatchery";NA;184;0
"Unit";"Overlord";"Larva";214;0
"Unit";"Overlord";"Larva";214;0
