"type";"unit_name";"on_building";"total_supply";"supply"
"Unit";"Overlord";"Larva";13;0
"Building";"Extractor";NA;18;0
"Unit";"Overlord";"Larva";21;0
"Building";"SpawningPool";NA;19;0
"Building";"Hatchery";NA;17;0
"Unit";"Zergling";"Larva";22;1
"Unit";"Zergling";"Larva";22;1
"Unit";"Zergling";"Larva";22;1
"Unit";"Zergling";"Larva";22;1
"Unit";"Queen";"Hatchery";22;2
"Unit";"Queen";"Hatchery";22;2
"Unit";"Overlord";"Larva";36;0
"Unit";"Zergling";"Larva";37;1
"Unit";"Zergling";"Larva";37;1
"Building";"BanelingNest";NA;29;0
"Unit";"Zergling";"Larva";38;1
"Unit";"Zergling";"Larva";38;1
"Unit";"Zergling";"Larva";38;1
"Unit";"Zergling";"Larva";38;1
"Unit";"Zergling";"Larva";38;1
"Unit";"Zergling";"Larva";38;1
"Unit";"Baneling";"Zergling";41;0
"Unit";"Zergling";"Larva";41;1
"Unit";"Zergling";"Larva";41;1
"Unit";"Zergling";"Larva";41;1
"Unit";"Zergling";"Larva";41;1
"Unit";"Zergling";"Larva";41;1
"Unit";"Zergling";"Larva";41;1
"Unit";"Zergling";"Larva";41;1
"Unit";"Zergling";"Larva";41;1
"Unit";"Zergling";"Larva";41;1
"Unit";"Zergling";"Larva";41;1
"Unit";"Zergling";"Larva";41;1
"Unit";"Zergling";"Larva";41;1
"Unit";"Zergling";"Larva";55;1
"Unit";"Zergling";"Larva";55;1
"Unit";"Zergling";"Larva";55;1
"Unit";"Zergling";"Larva";55;1
"Unit";"Zergling";"Larva";55;1
"Unit";"Zergling";"Larva";55;1
"Unit";"Zergling";"Larva";55;1
"Unit";"Zergling";"Larva";55;1
"Unit";"Zergling";"Larva";59;1
"Unit";"Zergling";"Larva";59;1
"Unit";"Zergling";"Larva";59;1
"Unit";"Zergling";"Larva";59;1
"Unit";"Zergling";"Larva";59;1
"Unit";"Zergling";"Larva";59;1
"Unit";"Baneling";"Zergling";59;0
"Unit";"Baneling";"Zergling";73;0
"Unit";"Baneling";"Zergling";73;0
"Building";"Hatchery";NA;41;0
"Unit";"Overlord";"Larva";81;0
"Unit";"Overlord";"Larva";87;0
"Unit";"Zergling";"Larva";91;1
"Unit";"Zergling";"Larva";91;1
"Unit";"Zergling";"Larva";91;1
"Unit";"Zergling";"Larva";91;1
"Building";"Extractor";NA;91;0
"Building";"Extractor";NA;91;0
"Unit";"Baneling";"Zergling";91;0
"Unit";"Baneling";"Zergling";91;0
"Unit";"Baneling";"Zergling";91;0
"Unit";"Zergling";"Larva";91;1
"Unit";"Zergling";"Larva";91;1
"Unit";"Zergling";"Larva";91;1
"Unit";"Zergling";"Larva";91;1
"Building";"EvolutionChamber";NA;91;0
"Unit";"Zergling";"Larva";91;1
"Unit";"Zergling";"Larva";91;1
"Unit";"Zergling";"Larva";91;1
"Unit";"Zergling";"Larva";91;1
"Unit";"Zergling";"Larva";91;1
"Unit";"Zergling";"Larva";91;1
"Unit";"Zergling";"Larva";91;1
"Unit";"Zergling";"Larva";91;1
"Unit";"Zergling";"Larva";99;1
"Unit";"Zergling";"Larva";99;1
"Unit";"Zergling";"Larva";101;1
"Unit";"Zergling";"Larva";101;1
"Unit";"Zergling";"Larva";101;1
"Unit";"Zergling";"Larva";101;1
"Unit";"Zergling";"Larva";101;1
"Unit";"Zergling";"Larva";101;1
"Unit";"Zergling";"Larva";101;1
"Unit";"Zergling";"Larva";101;1
"Unit";"Zergling";"Larva";101;1
"Unit";"Zergling";"Larva";101;1
"Unit";"Zergling";"Larva";119;1
"Unit";"Zergling";"Larva";119;1
"Unit";"Zergling";"Larva";119;1
"Unit";"Zergling";"Larva";119;1
"Unit";"Zergling";"Larva";119;1
"Unit";"Zergling";"Larva";119;1
"Unit";"Zergling";"Larva";119;1
"Unit";"Zergling";"Larva";119;1
"Unit";"Zergling";"Larva";119;1
"Unit";"Zergling";"Larva";119;1
"Unit";"Zergling";"Larva";119;1
"Unit";"Zergling";"Larva";119;1
"Unit";"Zergling";"Larva";119;1
"Unit";"Zergling";"Larva";119;1
"Unit";"Baneling";"Zergling";132;0
"Unit";"Baneling";"Zergling";132;0
"Building";"RoachWarren";NA;107;0
"Unit";"Overlord";"Larva";134;0
"Unit";"Overlord";"Larva";144;0
"Unit";"Queen";"Hatchery";141;2
"Building";"Extractor";NA;144;0
"Unit";"Baneling";"Zergling";153;0
"Unit";"Baneling";"Zergling";153;0
"Unit";"Overlord";"Larva";144;0
"Unit";"Overlord";"Larva";154;0
"Unit";"Roach";"Larva";156;2
"Unit";"Roach";"Larva";156;2
"Unit";"Roach";"Larva";156;2
"Unit";"Roach";"Larva";156;2
"Unit";"Roach";"Larva";156;2
"Unit";"Roach";"Larva";156;2
"Unit";"Roach";"Larva";156;2
"Upgrade";"ZergMissileWeaponsLevel1";"EvolutionChamber";134;0
"Unit";"Roach";"Larva";156;2
"Unit";"Roach";"Larva";156;2
"Unit";"Roach";"Larva";156;2
"Unit";"Roach";"Larva";156;2
"Unit";"Roach";"Larva";156;2
"Unit";"Roach";"Larva";156;2
"Unit";"Roach";"Larva";190;2
"Unit";"Roach";"Larva";190;2
"Unit";"Roach";"Larva";190;2
"Unit";"Overlord";"Larva";190;0
"Upgrade";"GlialReconstitution";"RoachWarren";156;0
"Building";"Extractor";NA;190;0
"Unit";"Overlord";"Larva";190;0
"Building";"EvolutionChamber";NA;190;0
"Unit";"Roach";"Larva";190;2
"Unit";"Roach";"Larva";190;2
"Unit";"Roach";"Larva";196;2
"Unit";"Roach";"Larva";196;2
"Unit";"Roach";"Larva";196;2
"Unit";"Roach";"Larva";196;2
"Unit";"Overlord";"Larva";196;0
"Unit";"Overlord";"Larva";196;0
"Unit";"Overlord";"Larva";196;0
"Unit";"Roach";"Larva";211;2
"Unit";"Roach";"Larva";211;2
"Unit";"Roach";"Larva";211;2
"Unit";"Roach";"Larva";211;2
"Unit";"Roach";"Larva";211;2
"Building";"Hatchery";NA;190;0
"Unit";"Roach";"Larva";211;2
"Unit";"Roach";"Larva";212;2
"Unit";"Roach";"Larva";213;2
"Unit";"Roach";"Larva";214;2
"Unit";"Roach";"Larva";214;2
"Unit";"Overlord";"Larva";214;0
"Unit";"Roach";"Larva";216;2
"Unit";"Roach";"Larva";220;2
"Unit";"Roach";"Larva";224;2
"Unit";"Roach";"Larva";224;2
"Unit";"Roach";"Larva";224;2
"Unit";"Roach";"Larva";232;2
"Unit";"Overlord";"Larva";234;0
"Unit";"Overlord";"Larva";234;0
"Unit";"Overlord";"Larva";234;0
"Unit";"Roach";"Larva";244;2
"Unit";"Roach";"Larva";244;2
"Unit";"Roach";"Larva";244;2
"Unit";"Roach";"Larva";244;2
"Unit";"Overlord";"Larva";244;0
"Unit";"Overlord";"Larva";244;0
"Unit";"Overlord";"Larva";246;0
"Unit";"Overlord";"Larva";246;0
"Unit";"Roach";"Larva";246;2
"Unit";"Roach";"Larva";246;2
"Unit";"Roach";"Larva";246;2
"Unit";"Roach";"Larva";246;2
"Unit";"Roach";"Larva";246;2
"Unit";"Roach";"Larva";246;2
"Unit";"Roach";"Larva";246;2
"Unit";"Roach";"Larva";254;2
"Unit";"Roach";"Larva";254;2
"Unit";"Roach";"Larva";254;2
"Unit";"Roach";"Larva";254;2
"Upgrade";"ZergGroundArmorsLevel1";"EvolutionChamber";214;0
"Unit";"Roach";"Larva";260;2
"Unit";"Roach";"Larva";260;2
"Unit";"Roach";"Larva";268;2
"Unit";"Roach";"Larva";268;2
"Unit";"Roach";"Larva";268;2
"Unit";"Roach";"Larva";268;2
"Unit";"Roach";"Larva";272;2
"Unit";"Roach";"Larva";272;2
"Unit";"Roach";"Larva";272;2
"Upgrade";"ZergMissileWeaponsLevel2";"EvolutionChamber";214;0
"Unit";"Roach";"Larva";294;2
"Unit";"Roach";"Larva";294;2
"Unit";"Roach";"Larva";294;2
"Unit";"Roach";"Larva";294;2
"Unit";"Roach";"Larva";294;2
"Unit";"Roach";"Larva";294;2
"Unit";"Roach";"Larva";294;2
"Unit";"Roach";"Larva";294;2
"Unit";"Roach";"Larva";294;2
"Unit";"Roach";"Larva";294;2
"Unit";"Roach";"Larva";314;2
"Unit";"Roach";"Larva";314;2
"Unit";"Roach";"Larva";314;2
"Unit";"Roach";"Larva";314;2
"Unit";"Roach";"Larva";314;2
"Unit";"Roach";"Larva";315;2
"Unit";"Roach";"Larva";315;2
"Unit";"Roach";"Larva";321;2
"Unit";"Roach";"Larva";321;2
"Unit";"Roach";"Larva";321;2
"Unit";"Queen";"Hatchery";321;2
"Unit";"Roach";"Larva";341;2
