"type";"unit_name";"on_building";"total_supply";"supply"
"Unit";"Overlord";"Larva";13;0
"Building";"Extractor";NA;20;0
"Building";"SpawningPool";NA;19;0
"Unit";"Overlord";"Larva";22;0
"Building";"Hatchery";NA;18;0
"Unit";"Zergling";"Larva";23;1
"Unit";"Zergling";"Larva";23;1
"Unit";"Zergling";"Larva";24;1
"Unit";"Zergling";"Larva";24;1
"Unit";"Queen";"Hatchery";23;2
"Unit";"Queen";"Hatchery";23;2
"Unit";"Overlord";"Larva";36;0
"Unit";"Zergling";"Larva";38;1
"Unit";"Zergling";"Larva";38;1
"Unit";"Zergling";"Larva";38;1
"Unit";"Zergling";"Larva";38;1
"Unit";"Zergling";"Larva";38;1
"Unit";"Zergling";"Larva";38;1
"Unit";"Zergling";"Larva";40;1
"Unit";"Zergling";"Larva";40;1
"Unit";"Zergling";"Larva";40;1
"Unit";"Zergling";"Larva";40;1
"Unit";"Overlord";"Larva";42;0
"Building";"BanelingNest";NA;38;0
"Unit";"Zergling";"Larva";44;1
"Unit";"Zergling";"Larva";44;1
"Unit";"Zergling";"Larva";44;1
"Unit";"Zergling";"Larva";44;1
"Unit";"Zergling";"Larva";44;1
"Unit";"Zergling";"Larva";44;1
"Unit";"Baneling";"Zergling";51;0
"Unit";"Baneling";"Zergling";51;0
"Unit";"Baneling";"Zergling";51;0
"Building";"Hatchery";NA;35;0
"Unit";"Zergling";"Larva";51;1
"Unit";"Zergling";"Larva";51;1
"Unit";"Zergling";"Larva";59;1
"Unit";"Zergling";"Larva";59;1
"Unit";"Zergling";"Larva";59;1
"Unit";"Zergling";"Larva";59;1
"Unit";"Zergling";"Larva";59;1
"Unit";"Zergling";"Larva";59;1
"Unit";"Zergling";"Larva";59;1
"Unit";"Zergling";"Larva";59;1
"Unit";"Baneling";"Zergling";59;0
"Unit";"Zergling";"Larva";61;1
"Unit";"Zergling";"Larva";61;1
"Unit";"Overlord";"Larva";61;0
"Unit";"Zergling";"Larva";61;1
"Unit";"Zergling";"Larva";61;1
"Unit";"Zergling";"Larva";61;1
"Unit";"Zergling";"Larva";61;1
"Unit";"Zergling";"Larva";61;1
"Unit";"Zergling";"Larva";61;1
"Unit";"Baneling";"Zergling";78;0
"Unit";"Baneling";"Zergling";78;0
"Unit";"Zergling";"Larva";78;1
"Unit";"Zergling";"Larva";78;1
"Unit";"Zergling";"Larva";78;1
"Unit";"Zergling";"Larva";78;1
"Unit";"Zergling";"Larva";78;1
"Unit";"Zergling";"Larva";78;1
"Unit";"Baneling";"Zergling";81;0
"Unit";"Baneling";"Zergling";81;0
"Unit";"Zergling";"Larva";81;1
"Unit";"Zergling";"Larva";81;1
"Unit";"Zergling";"Larva";81;1
"Unit";"Zergling";"Larva";81;1
"Unit";"Zergling";"Larva";81;1
"Unit";"Zergling";"Larva";81;1
"Unit";"Queen";"Hatchery";72;2
"Unit";"Zergling";"Larva";81;1
"Unit";"Zergling";"Larva";81;1
"Unit";"Zergling";"Larva";81;1
"Unit";"Zergling";"Larva";81;1
"Unit";"Zergling";"Larva";87;1
"Unit";"Zergling";"Larva";87;1
"Unit";"Zergling";"Larva";87;1
"Unit";"Zergling";"Larva";87;1
"Unit";"Zergling";"Larva";87;1
"Unit";"Zergling";"Larva";87;1
"Unit";"Baneling";"Zergling";99;0
"Unit";"Baneling";"Zergling";99;0
"Unit";"Zergling";"Larva";99;1
"Unit";"Zergling";"Larva";99;1
"Unit";"Zergling";"Larva";99;1
"Unit";"Zergling";"Larva";99;1
"Unit";"Zergling";"Larva";99;1
"Unit";"Zergling";"Larva";99;1
"Unit";"Zergling";"Larva";99;1
"Unit";"Zergling";"Larva";99;1
"Unit";"Baneling";"Zergling";105;0
"Unit";"Baneling";"Zergling";105;0
"Unit";"Zergling";"Larva";105;1
"Unit";"Zergling";"Larva";105;1
"Unit";"Zergling";"Larva";105;1
"Unit";"Zergling";"Larva";105;1
"Unit";"Zergling";"Larva";105;1
"Unit";"Zergling";"Larva";105;1
"Unit";"Zergling";"Larva";105;1
"Unit";"Zergling";"Larva";105;1
"Unit";"Zergling";"Larva";113;1
"Unit";"Zergling";"Larva";113;1
"Unit";"Zergling";"Larva";113;1
"Unit";"Zergling";"Larva";113;1
"Unit";"Zergling";"Larva";113;1
"Unit";"Zergling";"Larva";113;1
"Building";"CreepTumorQueen";NA;121;0
"Unit";"Zergling";"Larva";121;1
"Unit";"Zergling";"Larva";121;1
"Unit";"Zergling";"Larva";121;1
"Unit";"Zergling";"Larva";121;1
"Unit";"Zergling";"Larva";121;1
"Unit";"Zergling";"Larva";121;1
"Unit";"Zergling";"Larva";121;1
"Unit";"Zergling";"Larva";121;1
"Unit";"Zergling";"Larva";127;1
"Unit";"Zergling";"Larva";127;1
"Unit";"Zergling";"Larva";127;1
"Unit";"Zergling";"Larva";127;1
"Unit";"Baneling";"Zergling";135;0
"Unit";"Baneling";"Zergling";135;0
"Unit";"Queen";"Hatchery";121;2
"Unit";"Zergling";"Larva";135;1
"Unit";"Zergling";"Larva";135;1
"Building";"RoachWarren";NA;121;0
"Unit";"Zergling";"Larva";135;1
"Unit";"Zergling";"Larva";135;1
"Unit";"Zergling";"Larva";135;1
"Unit";"Zergling";"Larva";135;1
"Unit";"Zergling";"Larva";135;1
"Unit";"Zergling";"Larva";135;1
"Unit";"Zergling";"Larva";139;1
"Unit";"Zergling";"Larva";139;1
"Unit";"Overlord";"Larva";139;0
"Unit";"Overlord";"Larva";139;0
"Building";"CreepTumor";NA;143;0
"Building";"CreepTumorQueen";NA;149;0
"Unit";"Baneling";"Zergling";149;0
"Unit";"Baneling";"Zergling";149;0
"Unit";"Overlord";"Larva";143;0
"Building";"CreepTumorQueen";NA;151;0
"Unit";"Roach";"Larva";151;2
"Unit";"Roach";"Larva";151;2
"Unit";"Roach";"Larva";151;2
"Unit";"Roach";"Larva";151;2
"Unit";"Roach";"Larva";151;2
"Unit";"Roach";"Larva";151;2
"Unit";"Roach";"Larva";151;2
"Unit";"Roach";"Larva";151;2
"Building";"Extractor";NA;151;0
"Building";"Extractor";NA;151;0
"Unit";"Zergling";"Larva";167;1
"Unit";"Zergling";"Larva";167;1
"Unit";"Zergling";"Larva";167;1
"Unit";"Zergling";"Larva";167;1
"Unit";"Zergling";"Larva";167;1
"Unit";"Zergling";"Larva";167;1
"Unit";"Zergling";"Larva";167;1
"Unit";"Zergling";"Larva";167;1
"Unit";"Zergling";"Larva";167;1
"Unit";"Zergling";"Larva";167;1
"Unit";"Zergling";"Larva";167;1
"Unit";"Zergling";"Larva";167;1
"Unit";"Roach";"Larva";161;2
"Unit";"Roach";"Larva";161;2
"Unit";"Zergling";"Larva";167;1
"Unit";"Zergling";"Larva";167;1
"Unit";"Zergling";"Larva";167;1
"Unit";"Zergling";"Larva";167;1
"Unit";"Zergling";"Larva";167;1
"Unit";"Zergling";"Larva";167;1
"Unit";"Roach";"Larva";189;2
"Unit";"Roach";"Larva";189;2
"Unit";"Zergling";"Larva";189;1
"Unit";"Zergling";"Larva";189;1
"Unit";"Roach";"Larva";189;2
"Unit";"Roach";"Larva";189;2
"Unit";"Roach";"Larva";189;2
"Unit";"Roach";"Larva";189;2
"Unit";"Overlord";"Larva";189;0
"Unit";"Overlord";"Larva";189;0
"Unit";"Overlord";"Larva";189;0
"Unit";"Overlord";"Larva";203;0
"Unit";"Overlord";"Larva";203;0
"Unit";"Roach";"Larva";203;2
"Unit";"Zergling";"Larva";203;1
"Unit";"Zergling";"Larva";203;1
"Unit";"Roach";"Larva";203;2
"Unit";"Zergling";"Larva";203;1
"Unit";"Zergling";"Larva";203;1
"Unit";"Roach";"Larva";203;2
"Unit";"Zergling";"Larva";203;1
"Unit";"Zergling";"Larva";203;1
"Unit";"Roach";"Larva";203;2
"Unit";"Roach";"Larva";203;2
"Unit";"Zergling";"Larva";203;1
"Unit";"Zergling";"Larva";203;1
"Unit";"Zergling";"Larva";203;1
"Unit";"Zergling";"Larva";203;1
"Unit";"Roach";"Larva";203;2
"Unit";"Zergling";"Larva";203;1
"Unit";"Zergling";"Larva";203;1
"Unit";"Zergling";"Larva";203;1
"Unit";"Zergling";"Larva";203;1
"Unit";"Baneling";"Zergling";203;0
"Unit";"Baneling";"Zergling";203;0
"Unit";"Zergling";"Larva";203;1
"Unit";"Zergling";"Larva";203;1
"Unit";"Zergling";"Larva";203;1
"Unit";"Zergling";"Larva";203;1
"Unit";"Zergling";"Larva";203;1
"Unit";"Zergling";"Larva";203;1
"Unit";"Zergling";"Larva";203;1
"Unit";"Zergling";"Larva";203;1
"Unit";"Roach";"Larva";203;2
"Unit";"Roach";"Larva";203;2
"Unit";"Roach";"Larva";229;2
