"type";"unit_name";"on_building";"total_supply";"supply"
"Unit";"Overlord";"Larva";13;0
"Building";"Extractor";NA;18;0
"Unit";"Overlord";"Larva";21;0
"Building";"SpawningPool";NA;19;0
"Building";"Hatchery";NA;17;0
"Unit";"Zergling";"Larva";22;1
"Unit";"Zergling";"Larva";22;1
"Unit";"Queen";"Hatchery";22;2
"Unit";"Queen";"Hatchery";22;2
"Unit";"Overlord";"Larva";35;0
"Unit";"Zergling";"Larva";37;1
"Unit";"Zergling";"Larva";37;1
"Building";"BanelingNest";NA;32;0
"Unit";"Zergling";"Larva";37;1
"Unit";"Zergling";"Larva";37;1
"Unit";"Zergling";"Larva";37;1
"Unit";"Zergling";"Larva";37;1
"Unit";"Zergling";"Larva";37;1
"Unit";"Zergling";"Larva";37;1
"Unit";"Zergling";"Larva";37;1
"Unit";"Zergling";"Larva";37;1
"Unit";"Zergling";"Larva";37;1
"Unit";"Zergling";"Larva";37;1
"Unit";"Zergling";"Larva";37;1
"Unit";"Zergling";"Larva";37;1
"Unit";"Zergling";"Larva";37;1
"Unit";"Zergling";"Larva";37;1
"Unit";"Zergling";"Larva";37;1
"Unit";"Zergling";"Larva";37;1
"Unit";"Zergling";"Larva";37;1
"Unit";"Zergling";"Larva";37;1
"Unit";"Overlord";"Larva";39;0
"Unit";"Overlord";"Larva";39;0
"Building";"Hatchery";NA;28;0
"Unit";"Baneling";"Zergling";59;0
"Unit";"Baneling";"Zergling";59;0
"Building";"EvolutionChamber";NA;57;0
"Unit";"Queen";"Hatchery";59;2
"Unit";"Zergling";"Larva";63;1
"Unit";"Zergling";"Larva";63;1
"Unit";"Zergling";"Larva";63;1
"Unit";"Zergling";"Larva";63;1
"Unit";"Zergling";"Larva";63;1
"Unit";"Zergling";"Larva";63;1
"Unit";"Zergling";"Larva";63;1
"Unit";"Zergling";"Larva";63;1
"Unit";"Zergling";"Larva";63;1
"Unit";"Zergling";"Larva";63;1
"Unit";"Zergling";"Larva";70;1
"Unit";"Zergling";"Larva";70;1
"Unit";"Zergling";"Larva";72;1
"Unit";"Zergling";"Larva";72;1
"Unit";"Zergling";"Larva";72;1
"Unit";"Zergling";"Larva";72;1
"Unit";"Zergling";"Larva";72;1
"Unit";"Zergling";"Larva";72;1
"Building";"Extractor";NA;72;0
"Unit";"Zergling";"Larva";72;1
"Unit";"Zergling";"Larva";72;1
"Unit";"Baneling";"Zergling";82;0
"Unit";"Baneling";"Zergling";82;0
"Unit";"Baneling";"Zergling";82;0
"Unit";"Baneling";"Zergling";82;0
"Unit";"Overlord";"Larva";95;0
"Building";"Extractor";NA;108;0
"Building";"Extractor";NA;109;0
"Unit";"Zergling";"Larva";109;1
"Unit";"Zergling";"Larva";109;1
"Unit";"Zergling";"Larva";109;1
"Unit";"Zergling";"Larva";109;1
"Unit";"Zergling";"Larva";109;1
"Unit";"Zergling";"Larva";109;1
"Unit";"Zergling";"Larva";109;1
"Unit";"Zergling";"Larva";109;1
"Unit";"Zergling";"Larva";109;1
"Unit";"Zergling";"Larva";109;1
"Unit";"Zergling";"Larva";109;1
"Unit";"Zergling";"Larva";109;1
"Unit";"Overlord";"Larva";109;0
"Unit";"Overlord";"Larva";109;0
"Building";"RoachWarren";NA;109;0
"Upgrade";"ZergMissileWeaponsLevel1";"EvolutionChamber";92;0
"Unit";"Roach";"Larva";124;2
"Unit";"Roach";"Larva";124;2
"Unit";"Roach";"Larva";124;2
"Unit";"Roach";"Larva";124;2
"Unit";"Roach";"Larva";124;2
"Unit";"Roach";"Larva";124;2
"Unit";"Roach";"Larva";124;2
"Unit";"Roach";"Larva";124;2
"Unit";"Overlord";"Larva";124;0
"Unit";"Overlord";"Larva";124;0
"Unit";"Baneling";"Zergling";124;0
"Unit";"Baneling";"Zergling";124;0
"Building";"Extractor";NA;124;0
"Unit";"Roach";"Larva";144;2
"Unit";"Roach";"Larva";144;2
"Unit";"Roach";"Larva";144;2
"Unit";"Roach";"Larva";144;2
"Unit";"Roach";"Larva";144;2
"Unit";"Roach";"Larva";144;2
"Unit";"Roach";"Larva";144;2
"Unit";"Roach";"Larva";144;2
"Unit";"Roach";"Larva";144;2
"Unit";"Roach";"Larva";144;2
"Unit";"Overlord";"Larva";144;0
"Unit";"Baneling";"Zergling";144;0
"Unit";"Baneling";"Zergling";144;0
"Unit";"Baneling";"Zergling";144;0
"Unit";"Baneling";"Zergling";144;0
"Unit";"Baneling";"Zergling";144;0
"Unit";"Overlord";"Larva";164;0
"Unit";"Overlord";"Larva";164;0
"Upgrade";"GlialReconstitution";"RoachWarren";140;0
"Unit";"Roach";"Larva";164;2
"Unit";"Roach";"Larva";164;2
"Unit";"Roach";"Larva";164;2
"Unit";"Roach";"Larva";164;2
"Building";"Hatchery";NA;144;0
"Unit";"Roach";"Larva";173;2
"Unit";"Roach";"Larva";173;2
"Unit";"Roach";"Larva";173;2
"Unit";"Roach";"Larva";173;2
"Unit";"Roach";"Larva";173;2
"Unit";"Roach";"Larva";173;2
"Unit";"Roach";"Larva";173;2
"Unit";"Overlord";"Larva";173;0
"Building";"Extractor";NA;195;0
"Unit";"Roach";"Larva";197;2
"Unit";"Roach";"Larva";197;2
"Unit";"Roach";"Larva";197;2
"Unit";"Roach";"Larva";197;2
"Upgrade";"ZergMissileWeaponsLevel2";"EvolutionChamber";144;0
"Unit";"Roach";"Larva";197;2
"Unit";"Overlord";"Larva";197;0
"Unit";"Overlord";"Larva";197;0
"Unit";"Overlord";"Larva";197;0
"Unit";"Overlord";"Larva";197;0
"Unit";"Overlord";"Larva";197;0
"Upgrade";"Burrow";"Hatchery";181;0
"Unit";"Overlord";"Larva";207;0
"Unit";"Overlord";"Larva";207;0
"Unit";"Roach";"Larva";207;2
"Unit";"Roach";"Larva";207;2
"Unit";"Roach";"Larva";207;2
"Unit";"Roach";"Larva";207;2
"Unit";"Roach";"Larva";207;2
"Unit";"Roach";"Larva";207;2
"Unit";"Roach";"Larva";207;2
"Unit";"Roach";"Larva";207;2
"Unit";"Overlord";"Larva";207;0
"Unit";"Overlord";"Larva";207;0
"Unit";"Roach";"Larva";207;2
"Unit";"Roach";"Larva";207;2
"Unit";"Roach";"Larva";207;2
"Unit";"Roach";"Larva";207;2
"Unit";"Roach";"Larva";207;2
"Unit";"Roach";"Larva";207;2
"Upgrade";"TunnelingClaws";"RoachWarren";197;0
"Unit";"Roach";"Larva";235;2
"Unit";"Roach";"Larva";235;2
"Unit";"Roach";"Larva";235;2
"Unit";"Roach";"Larva";235;2
"Unit";"Roach";"Larva";235;2
"Building";"SpineCrawler";NA;223;0
"Building";"SpineCrawler";NA;223;0
"Unit";"Roach";"Larva";235;2
"Unit";"Roach";"Larva";235;2
"Unit";"Roach";"Larva";235;2
"Unit";"Roach";"Larva";235;2
"Unit";"Roach";"Larva";235;2
"Unit";"Roach";"Larva";235;2
"Unit";"Roach";"Larva";235;2
"Unit";"Roach";"Larva";245;2
"Unit";"Roach";"Larva";245;2
"Building";"Hatchery";NA;207;0
"Unit";"Overlord";"Larva";259;0
"Upgrade";"ZergGroundArmorsLevel1";"EvolutionChamber";223;0
"Unit";"Roach";"Larva";263;2
"Unit";"Roach";"Larva";263;2
"Unit";"Roach";"Larva";263;2
"Unit";"Roach";"Larva";263;2
"Unit";"Roach";"Larva";263;2
"Unit";"Roach";"Larva";263;2
"Unit";"Roach";"Larva";263;2
"Unit";"Roach";"Larva";263;2
"Unit";"Roach";"Larva";263;2
"Unit";"Roach";"Larva";263;2
"Unit";"Roach";"Larva";263;2
"Unit";"Roach";"Larva";263;2
"Unit";"Roach";"Larva";263;2
"Unit";"Roach";"Larva";263;2
"Unit";"Roach";"Larva";263;2
"Unit";"Roach";"Larva";263;2
"Unit";"Roach";"Larva";263;2
"Unit";"Roach";"Larva";263;2
"Unit";"Roach";"Larva";263;2
"Unit";"Roach";"Larva";263;2
"Unit";"Roach";"Larva";263;2
"Unit";"Roach";"Larva";263;2
"Unit";"Roach";"Larva";263;2
"Unit";"Roach";"Larva";263;2
"Unit";"Roach";"Larva";271;2
"Unit";"Roach";"Larva";271;2
"Unit";"Roach";"Larva";271;2
"Unit";"Roach";"Larva";271;2
"Unit";"Roach";"Larva";295;2
"Unit";"Roach";"Larva";299;2
"Unit";"Roach";"Larva";299;2
"Unit";"Roach";"Larva";313;2
"Unit";"Roach";"Larva";319;2
"Unit";"Roach";"Larva";319;2
"Unit";"Roach";"Larva";319;2
"Unit";"Roach";"Larva";325;2
"Unit";"Roach";"Larva";325;2
"Unit";"Roach";"Larva";325;2
"Unit";"Roach";"Larva";325;2
"Unit";"Roach";"Larva";325;2
"Unit";"Roach";"Larva";325;2
"Unit";"Roach";"Larva";325;2
