"type";"unit_name";"on_building";"total_supply";"supply"
"Building";"Pylon";NA;13;0
"Building";"Assimilator";NA;16;0
"Building";"Gateway";NA;15;0
"Building";"CyberneticsCore";NA;19;0
"Building";"Assimilator";NA;20;0
"Building";"Pylon";NA;21;0
"Unit";"Adept";"Gateway";21;2
"Unit";"Adept";"Gateway";21;2
"Building";"Nexus";NA;20;0
"Unit";"Adept";"Gateway";25;2
"Building";"Stargate";NA;25;0
"Building";"Pylon";NA;29;0
"Unit";"Oracle";"Stargate";33;3
"Building";"Assimilator";NA;36;0
"Building";"Assimilator";NA;36;0
"Unit";"Adept";"Gateway";36;2
"Unit";"Phoenix";"Stargate";38;2
"Building";"Gateway";NA;36;0
"Building";"TwilightCouncil";NA;46;0
"Building";"RoboticsFacility";NA;43;0
"Unit";"Adept";"Gateway";52;2
"Unit";"Zealot";"Gateway";52;2
"Unit";"Oracle";"Stargate";52;3
"Building";"TemplarArchive";NA;52;0
"Building";"Gateway";NA;51;0
"Building";"Pylon";NA;57;0
"Unit";"Stalker";"Gateway";62;2
"Building";"Gateway";NA;52;0
"Building";"Gateway";NA;52;0
"Building";"Pylon";NA;62;0
"Unit";"Zealot";"Gateway";64;2
"Unit";"Zealot";"Gateway";64;2
"Building";"Gateway";NA;57;0
"Unit";"Observer";"Robotics Facility";64;1
"Building";"HighTemplar";NA;71;0
"Building";"HighTemplar";NA;71;0
"Building";"HighTemplar";NA;71;0
"Building";"Pylon";NA;69;0
"Building";"HighTemplar";NA;73;0
"Unit";"Zealot";"Gateway";73;2
"Unit";"Zealot";"Gateway";73;2
"Unit";"Archon";"High Templar";73;0
"Building";"Pylon";NA;72;0
"Unit";"Archon";"High Templar";73;0
"Upgrade";"Charge";"TwilightCouncil";64;0
"Building";"Pylon";NA;77;0
"Unit";"Zealot";"Gateway";79;2
"Unit";"Zealot";"Gateway";79;2
"Unit";"Zealot";"Gateway";79;2
"Unit";"Zealot";"Gateway";79;2
"Unit";"Zealot";"Gateway";79;2
"Unit";"Zealot";"Gateway";89;2
"Unit";"Immortal";"Robotics Facility";78;4
"Building";"HighTemplar";NA;91;0
"Building";"HighTemplar";NA;91;0
"Building";"HighTemplar";NA;91;0
"Building";"HighTemplar";NA;91;0
"Unit";"Zealot";"Gateway";91;2
"Building";"Nexus";NA;71;0
"Building";"OracleStasisTrap";NA;99;0
"Unit";"Archon";"High Templar";97;0
"Building";"OracleStasisTrap";NA;99;0
"Unit";"Sentry";"Gateway";100;2
"Unit";"Sentry";"Gateway";100;2
"Unit";"Archon";"High Templar";100;0
"Building";"Assimilator";NA;99;0
"Unit";"Zealot";"Gateway";107;2
"Unit";"Zealot";"Gateway";107;2
"Unit";"Zealot";"Gateway";107;2
"Building";"Gateway";NA;97;0
"Unit";"Immortal";"Robotics Facility";97;4
"Building";"Gateway";NA;97;0
"Unit";"Zealot";"Gateway";119;2
"Unit";"Zealot";"Gateway";121;2
"Unit";"Zealot";"Gateway";121;2
"Unit";"Zealot";"Gateway";121;2
"Building";"Gateway";NA;99;0
"Building";"Gateway";NA;99;0
"Building";"HighTemplar";NA;127;0
"Building";"HighTemplar";NA;127;0
"Building";"Pylon";NA;121;0
"Unit";"Archon";"High Templar";128;0
"Unit";"Immortal";"Robotics Facility";119;4
"Building";"Pylon";NA;128;0
"Unit";"Zealot";"Gateway";133;2
"Unit";"Zealot";"Gateway";133;2
"Unit";"Zealot";"Gateway";133;2
"Unit";"Zealot";"Gateway";133;2
"Unit";"Zealot";"Gateway";133;2
"Building";"ShieldBattery";NA;128;0
"Building";"HighTemplar";NA;144;0
"Building";"HighTemplar";NA;144;0
"Building";"HighTemplar";NA;144;0
"Unit";"Zealot";"Gateway";144;2
"Unit";"Zealot";"Gateway";144;2
"Unit";"Zealot";"Gateway";144;2
"Unit";"Zealot";"Gateway";144;2
"Unit";"Zealot";"Gateway";144;2
"Building";"Pylon";NA;154;0
"Building";"Pylon";NA;154;0
"Building";"Pylon";NA;154;0
"Building";"HighTemplar";NA;155;0
"Unit";"Zealot";"Gateway";155;2
"Unit";"Zealot";"Gateway";155;2
"Unit";"Zealot";"Gateway";155;2
"Unit";"Zealot";"Gateway";155;2
"Unit";"Zealot";"Gateway";155;2
"Building";"Assimilator";NA;155;0
"Building";"Pylon";NA;155;0
"Building";"Pylon";NA;155;0
"Building";"Pylon";NA;155;0
"Unit";"Immortal";"Robotics Facility";155;4
"Building";"Forge";NA;155;0
"Unit";"Sentry";"Gateway";173;2
"Unit";"Sentry";"Gateway";173;2
"Unit";"Sentry";"Gateway";173;2
"Unit";"Sentry";"Gateway";173;2
"Building";"HighTemplar";NA;173;0
"Unit";"Zealot";"Gateway";181;2
"Unit";"Zealot";"Gateway";181;2
"Unit";"Zealot";"Gateway";181;2
"Unit";"Immortal";"Robotics Facility";166;4
"Unit";"Zealot";"Gateway";181;2
"Unit";"Zealot";"Gateway";181;2
"Building";"Pylon";NA;187;0
"Building";"Pylon";NA;195;0
"Building";"Pylon";NA;195;0
"Building";"HighTemplar";NA;195;0
"Building";"HighTemplar";NA;195;0
"Unit";"Zealot";"Gateway";195;2
"Unit";"Zealot";"Gateway";195;2
"Unit";"Zealot";"Gateway";195;2
"Unit";"Zealot";"Gateway";195;2
"Unit";"Zealot";"Gateway";195;2
"Unit";"Zealot";"Gateway";195;2
"Unit";"Zealot";"Gateway";195;2
"Unit";"Zealot";"Gateway";195;2
"Unit";"Immortal";"Robotics Facility";195;4
"Building";"Nexus";NA;171;0
"Unit";"Zealot";"Gateway";215;2
"Unit";"Zealot";"Gateway";217;2
"Unit";"Zealot";"Gateway";217;2
"Unit";"Zealot";"Gateway";217;2
"Building";"Assimilator";NA;215;0
"Building";"Assimilator";NA;215;0
"Upgrade";"ProtossGroundWeaponsLevel1";"Forge";195;0
"Unit";"Archon";"High Templar";226;0
"Building";"PhotonCannon";NA;215;0
"Unit";"Zealot";"Gateway";226;2
"Unit";"Zealot";"Gateway";226;2
"Unit";"Zealot";"Gateway";226;2
"Unit";"Zealot";"Gateway";226;2
"Unit";"Zealot";"Gateway";226;2
"Unit";"Zealot";"Gateway";226;2
"Building";"PhotonCannon";NA;215;0
"Building";"PhotonCannon";NA;217;0
"Building";"FleetBeacon";NA;215;0
"Unit";"Zealot";"Gateway";238;2
"Unit";"Zealot";"Gateway";238;2
"Building";"HighTemplar";NA;242;0
"Building";"HighTemplar";NA;242;0
"Building";"HighTemplar";NA;242;0
"Building";"HighTemplar";NA;242;0
"Building";"HighTemplar";NA;242;0
"Building";"HighTemplar";NA;242;0
"Unit";"Archon";"High Templar";242;0
"Unit";"Archon";"High Templar";242;0
"Building";"Pylon";NA;242;0
"Building";"Pylon";NA;242;0
"Building";"PhotonCannon";NA;242;0
"Building";"PhotonCannon";NA;242;0
"Unit";"Zealot";"Gateway";242;2
"Unit";"Zealot";"Gateway";242;2
"Unit";"Zealot";"Gateway";242;2
"Unit";"Zealot";"Gateway";242;2
"Unit";"Zealot";"Gateway";242;2
"Unit";"Zealot";"Gateway";242;2
"Unit";"Zealot";"Gateway";242;2
"Unit";"Zealot";"Gateway";242;2
"Unit";"Zealot";"Gateway";242;2
"Unit";"Zealot";"Gateway";242;2
"Building";"PhotonCannon";NA;242;0
"Building";"PhotonCannon";NA;242;0
"Unit";"Mothership";"Mothership Core";242;6
"Unit";"Archon";"High Templar";262;0
"Building";"HighTemplar";NA;268;0
"Building";"HighTemplar";NA;268;0
"Building";"HighTemplar";NA;268;0
"Building";"HighTemplar";NA;268;0
"Building";"HighTemplar";NA;268;0
"Building";"HighTemplar";NA;268;0
"Building";"HighTemplar";NA;268;0
"Building";"HighTemplar";NA;268;0
"Unit";"Zealot";"Gateway";268;2
"Unit";"Zealot";"Gateway";268;2
"Unit";"Archon";"High Templar";272;0
"Unit";"Archon";"High Templar";272;0
"Unit";"Archon";"High Templar";272;0
"Upgrade";"ProtossGroundWeaponsLevel2";"Forge";242;0
"Unit";"Immortal";"Robotics Facility";268;4
"Building";"Stargate";NA;268;0
"Building";"Stargate";NA;268;0
"Building";"PhotonCannon";NA;276;0
"Building";"Pylon";NA;276;0
"Building";"PhotonCannon";NA;276;0
"Building";"Pylon";NA;276;0
"Building";"PhotonCannon";NA;276;0
"Unit";"Carrier";"Stargate";268;6
"Unit";"Zealot";"Gateway";276;2
"Unit";"Zealot";"Gateway";276;2
"Unit";"Zealot";"Gateway";276;2
"Unit";"Zealot";"Gateway";276;2
"Unit";"Zealot";"Gateway";276;2
"Unit";"Zealot";"Gateway";276;2
"Unit";"Zealot";"Gateway";276;2
"Unit";"Zealot";"Gateway";276;2
"Building";"HighTemplar";NA;298;0
"Building";"HighTemplar";NA;298;0
"Building";"HighTemplar";NA;298;0
"Building";"HighTemplar";NA;298;0
"Building";"Nexus";NA;276;0
"Building";"HighTemplar";NA;298;0
"Building";"HighTemplar";NA;298;0
"Unit";"Carrier";"Stargate";276;6
"Unit";"Carrier";"Stargate";276;6
"Upgrade";"ProtossAirWeaponsLevel1";"CyberneticsCore";276;0
"Unit";"Zealot";"Gateway";310;2
"Unit";"Zealot";"Gateway";310;2
"Unit";"Zealot";"Gateway";310;2
"Unit";"Zealot";"Gateway";310;2
"Unit";"Zealot";"Gateway";310;2
"Building";"ShieldBattery";NA;298;0
"Building";"ShieldBattery";NA;298;0
"Building";"ShieldBattery";NA;310;0
"Unit";"Oracle";"Stargate";298;3
"Building";"PhotonCannon";NA;310;0
"Building";"PhotonCannon";NA;310;0
"Unit";"Carrier";"Stargate";276;6
"Upgrade";"ProtossGroundWeaponsLevel3";"Forge";276;0
"Building";"HighTemplar";NA;329;0
"Building";"HighTemplar";NA;329;0
"Building";"Assimilator";NA;329;0
"Unit";"Zealot";"Gateway";329;2
"Unit";"Zealot";"Gateway";329;2
"Unit";"Zealot";"Gateway";329;2
"Unit";"Zealot";"Gateway";329;2
"Unit";"Zealot";"Gateway";329;2
"Building";"Assimilator";NA;329;0
"Unit";"Zealot";"Gateway";339;2
"Unit";"Zealot";"Gateway";339;2
"Unit";"Zealot";"Gateway";339;2
"Unit";"Archon";"High Templar";345;0
"Unit";"Carrier";"Stargate";320;6
"Building";"Pylon";NA;345;0
"Upgrade";"ProtossShieldsLevel1";"Forge";329;0
"Upgrade";"ProtossAirWeaponsLevel2";"CyberneticsCore";329;0
"Building";"Pylon";NA;351;0
"Building";"PhotonCannon";NA;352;0
"Building";"ShieldBattery";NA;352;0
"Building";"Nexus";NA;345;0
