"type";"unit_name";"on_building";"total_supply";"supply"
"Building";"Pylon";NA;13;0
"Building";"Assimilator";NA;16;0
"Building";"Gateway";NA;14;0
"Building";"Assimilator";NA;20;0
"Building";"Pylon";NA;21;0
"Building";"CyberneticsCore";NA;20;0
"Unit";"Adept";"Gateway";21;2
"Building";"Nexus";NA;19;0
"Unit";"Adept";"Gateway";23;2
"Building";"Stargate";NA;22;0
"Unit";"Phoenix";"Stargate";28;2
"Building";"Pylon";NA;37;0
"Unit";"Adept";"Gateway";34;2
"Unit";"Oracle";"Stargate";37;3
"Building";"Assimilator";NA;39;0
"Building";"Assimilator";NA;40;0
"Building";"Gateway";NA;38;0
"Building";"OracleStasisTrap";NA;53;0
"Building";"RoboticsFacility";NA;43;0
"Building";"TwilightCouncil";NA;48;0
"Building";"Pylon";NA;54;0
"Building";"Gateway";NA;52;0
"Building";"Gateway";NA;52;0
"Unit";"Zealot";"Gateway";54;2
"Unit";"Zealot";"Gateway";54;2
"Building";"TemplarArchive";NA;54;0
"Building";"Pylon";NA;60;0
"Building";"HighTemplar";NA;62;0
"Building";"HighTemplar";NA;62;0
"Building";"HighTemplar";NA;62;0
"Building";"HighTemplar";NA;62;0
"Building";"Pylon";NA;61;0
"Unit";"Observer";"Robotics Facility";61;1
"Unit";"Archon";"High Templar";62;0
"Building";"Pylon";NA;62;0
"Unit";"Archon";"High Templar";62;0
"Building";"Nexus";NA;54;0
"Building";"Forge";NA;62;0
"Unit";"Zealot";"Gateway";66;2
"Unit";"Sentry";"Gateway";68;2
"Building";"OracleStasisTrap";NA;70;0
"Building";"HighTemplar";NA;66;0
"Building";"HighTemplar";NA;66;0
"Building";"ShieldBattery";NA;65;0
"Upgrade";"Charge";"TwilightCouncil";60;0
"Building";"Gateway";NA;62;0
"Building";"Gateway";NA;63;0
"Building";"Gateway";NA;63;0
"Building";"Gateway";NA;63;0
"Building";"HighTemplar";NA;79;0
"Unit";"Zealot";"Gateway";79;2
"Building";"Pylon";NA;79;0
"Building";"Pylon";NA;79;0
"Unit";"Immortal";"Robotics Facility";78;4
"Building";"Assimilator";NA;79;0
"Building";"HighTemplar";NA;88;0
"Building";"Pylon";NA;80;0
"Unit";"Zealot";"Gateway";88;2
"Unit";"Zealot";"Gateway";88;2
"Unit";"Zealot";"Gateway";88;2
"Unit";"Zealot";"Gateway";88;2
"Unit";"Zealot";"Gateway";88;2
"Building";"Assimilator";NA;79;0
"Building";"Pylon";NA;82;0
"Unit";"Immortal";"Robotics Facility";84;4
"Building";"Pylon";NA;103;0
"Building";"PhotonCannon";NA;103;0
"Building";"PhotonCannon";NA;103;0
"Building";"PhotonCannon";NA;103;0
"Building";"Pylon";NA;111;0
"Building";"Pylon";NA;113;0
"Building";"Pylon";NA;113;0
"Upgrade";"ProtossGroundWeaponsLevel1";"Forge";79;0
"Unit";"Immortal";"Robotics Facility";110;4
"Building";"HighTemplar";NA;121;0
"Building";"HighTemplar";NA;121;0
"Building";"HighTemplar";NA;121;0
"Building";"HighTemplar";NA;121;0
"Unit";"Zealot";"Gateway";121;2
"Unit";"Zealot";"Gateway";121;2
"Unit";"Zealot";"Gateway";121;2
"Building";"OracleStasisTrap";NA;127;0
"Unit";"Archon";"High Templar";127;0
"Building";"OracleStasisTrap";NA;129;0
"Unit";"Archon";"High Templar";127;0
"Building";"HighTemplar";NA;129;0
"Building";"HighTemplar";NA;129;0
"Building";"Pylon";NA;129;0
"Building";"Pylon";NA;129;0
"Unit";"Zealot";"Gateway";129;2
"Unit";"Zealot";"Gateway";129;2
"Building";"Pylon";NA;129;0
"Unit";"Zealot";"Gateway";129;2
"Unit";"Zealot";"Gateway";129;2
"Unit";"Zealot";"Gateway";129;2
"Unit";"Zealot";"Gateway";129;2
"Building";"Pylon";NA;129;0
"Building";"FleetBeacon";NA;121;0
"Building";"ShieldBattery";NA;129;0
"Building";"Nexus";NA;121;0
"Building";"OracleStasisTrap";NA;142;0
"Building";"OracleStasisTrap";NA;142;0
"Building";"Assimilator";NA;141;0
"Building";"Assimilator";NA;142;0
"Building";"Stargate";NA;141;0
"Building";"PhotonCannon";NA;142;0
"Building";"PhotonCannon";NA;142;0
"Building";"Stargate";NA;141;0
"Building";"PhotonCannon";NA;142;0
"Upgrade";"ProtossGroundWeaponsLevel2";"Forge";129;0
"Building";"ShieldBattery";NA;142;0
"Building";"Pylon";NA;142;0
"Building";"Pylon";NA;142;0
"Building";"PhotonCannon";NA;142;0
"Building";"PhotonCannon";NA;142;0
"Building";"PhotonCannon";NA;142;0
"Building";"PhotonCannon";NA;142;0
"Unit";"Zealot";"Gateway";142;2
"Unit";"Zealot";"Gateway";142;2
"Unit";"Zealot";"Gateway";142;2
"Unit";"Zealot";"Gateway";142;2
"Unit";"Zealot";"Gateway";142;2
"Unit";"Zealot";"Gateway";142;2
"Unit";"Zealot";"Gateway";142;2
"Building";"PhotonCannon";NA;142;0
"Building";"PhotonCannon";NA;142;0
"Building";"ShieldBattery";NA;142;0
"Building";"PhotonCannon";NA;142;0
"Unit";"Mothership";"Mothership Core";142;6
"Unit";"Zealot";"Gateway";162;2
"Unit";"Zealot";"Gateway";162;2
"Unit";"Zealot";"Gateway";162;2
"Unit";"Zealot";"Gateway";162;2
"Unit";"Zealot";"Gateway";162;2
"Unit";"Zealot";"Gateway";162;2
"Unit";"Zealot";"Gateway";162;2
"Unit";"Zealot";"Gateway";162;2
"Unit";"Carrier";"Stargate";142;6
"Unit";"Carrier";"Stargate";142;6
"Building";"OracleStasisTrap";NA;184;0
"Upgrade";"ProtossAirWeaponsLevel1";"CyberneticsCore";142;0
"Building";"OracleStasisTrap";NA;190;0
"Building";"Pylon";NA;190;0
"Building";"PhotonCannon";NA;190;0
"Building";"PhotonCannon";NA;190;0
"Building";"Pylon";NA;190;0
"Building";"PhotonCannon";NA;190;0
"Unit";"Carrier";"Stargate";162;6
"Unit";"Carrier";"Stargate";162;6
"Upgrade";"ProtossGroundWeaponsLevel3";"Forge";162;0
"Unit";"Zealot";"Gateway";202;2
"Unit";"Carrier";"Stargate";190;6
"Unit";"Zealot";"Gateway";202;2
"Unit";"Zealot";"Gateway";202;2
"Unit";"Zealot";"Gateway";202;2
"Unit";"Zealot";"Gateway";202;2
"Unit";"Zealot";"Gateway";202;2
"Unit";"Zealot";"Gateway";202;2
"Unit";"Zealot";"Gateway";202;2
"Building";"Pylon";NA;224;0
"Unit";"Carrier";"Stargate";190;6
"Unit";"Carrier";"Stargate";196;6
"Upgrade";"ProtossAirWeaponsLevel2";"CyberneticsCore";196;0
"Building";"OracleStasisTrap";NA;236;0
"Building";"Nexus";NA;202;0
"Building";"Pylon";NA;236;0
"Building";"PhotonCannon";NA;230;0
"Building";"PhotonCannon";NA;230;0
"Building";"PhotonCannon";NA;236;0
"Building";"Pylon";NA;236;0
"Building";"Pylon";NA;236;0
"Building";"ShieldBattery";NA;236;0
"Upgrade";"ProtossShieldsLevel1";"Forge";224;0
"Unit";"Carrier";"Stargate";224;6
"Unit";"Oracle";"Stargate";236;3
"Unit";"Zealot";"Gateway";245;2
"Building";"Pylon";NA;242;0
"Building";"Pylon";NA;245;0
"Building";"Pylon";NA;245;0
"Unit";"Tempest";"Stargate";236;4
"Building";"Assimilator";NA;247;0
"Unit";"Carrier";"Stargate";230;6
"Building";"Assimilator";NA;247;0
"Unit";"Archon";"High Templar";257;0
"Building";"Nexus";NA;236;0
"Unit";"Zealot";"Gateway";257;2
"Unit";"Zealot";"Gateway";257;2
"Unit";"Zealot";"Gateway";257;2
"Unit";"Zealot";"Gateway";257;2
"Unit";"Zealot";"Gateway";257;2
"Unit";"Zealot";"Gateway";257;2
"Unit";"Zealot";"Gateway";257;2
"Unit";"Zealot";"Gateway";257;2
