"type";"unit_name";"on_building";"total_supply";"supply"
"Building";"Pylon";NA;13;0
"Building";"Assimilator";NA;16;0
"Building";"Gateway";NA;15;0
"Building";"Pylon";NA;19;0
"Unit";"Zealot";"Gateway";19;2
"Building";"Assimilator";NA;19;0
"Building";"CyberneticsCore";NA;19;0
"Building";"Gateway";NA;19;0
"Unit";"Zealot";"Gateway";19;2
"Unit";"Stalker";"Gateway";23;2
"Building";"ShieldBattery";NA;23;0
"Building";"Pylon";NA;29;0
"Unit";"Sentry";"Gateway";29;2
"Building";"Pylon";NA;31;0
"Building";"RoboticsFacility";NA;29;0
"Unit";"Sentry";"Gateway";30;2
"Building";"Nexus";NA;29;0
"Unit";"Observer";"Robotics Facility";37;1
"Building";"Forge";NA;37;0
"Building";"TwilightCouncil";NA;36;0
"Unit";"Phoenix";"Stargate";43;2
"Building";"Pylon";NA;50;0
"Building";"Assimilator";NA;50;0
"Building";"Assimilator";NA;51;0
"Unit";"Immortal";"Robotics Facility";52;4
"Unit";"Phoenix";"Stargate";55;2
"Building";"Nexus";NA;47;0
"Building";"TemplarArchive";NA;55;0
"Building";"HighTemplar";NA;67;0
"Building";"HighTemplar";NA;67;0
"Upgrade";"Charge";"TwilightCouncil";51;0
"Unit";"Archon";"High Templar";67;0
"Building";"Gateway";NA;56;0
"Building";"Gateway";NA;57;0
"Building";"Pylon";NA;67;0
"Upgrade";"ProtossGroundWeaponsLevel1";"Forge";51;0
"Building";"Gateway";NA;58;0
"Building";"Gateway";NA;59;0
"Building";"Gateway";NA;60;0
"Building";"Gateway";NA;67;0
"Building";"Pylon";NA;73;0
"Unit";"Immortal";"Robotics Facility";69;4
"Building";"Pylon";NA;75;0
"Building";"HighTemplar";NA;83;0
"Unit";"Zealot";"Gateway";85;2
"Building";"Assimilator";NA;78;0
"Building";"HighTemplar";NA;89;0
"Building";"Assimilator";NA;78;0
"Unit";"Zealot";"Gateway";90;2
"Building";"Pylon";NA;89;0
"Unit";"Zealot";"Gateway";94;2
"Unit";"Zealot";"Gateway";94;2
"Unit";"Zealot";"Gateway";94;2
"Building";"PhotonCannon";NA;87;0
"Building";"HighTemplar";NA;100;0
"Building";"HighTemplar";NA;100;0
"Building";"Pylon";NA;100;0
"Building";"Pylon";NA;100;0
"Unit";"Zealot";"Gateway";100;2
"Unit";"Zealot";"Gateway";100;2
"Unit";"Zealot";"Gateway";100;2
"Unit";"Immortal";"Robotics Facility";92;4
"Unit";"Zealot";"Gateway";106;2
"Unit";"Zealot";"Gateway";106;2
"Building";"Pylon";NA;100;0
"Building";"HighTemplar";NA;114;0
"Building";"ShieldBattery";NA;100;0
"Unit";"Zealot";"Gateway";114;2
"Unit";"Zealot";"Gateway";116;2
"Unit";"Zealot";"Gateway";116;2
"Unit";"Zealot";"Gateway";116;2
"Building";"Pylon";NA;114;0
"Building";"HighTemplar";NA;123;0
"Building";"HighTemplar";NA;123;0
"Unit";"Zealot";"Gateway";123;2
"Upgrade";"ProtossGroundWeaponsLevel2";"Forge";78;0
"Unit";"Zealot";"Gateway";125;2
"Unit";"Zealot";"Gateway";127;2
"Unit";"Immortal";"Robotics Facility";114;4
"Building";"HighTemplar";NA;134;0
"Building";"HighTemplar";NA;134;0
"Building";"Pylon";NA;127;0
"Building";"Pylon";NA;127;0
"Building";"Nexus";NA;100;0
"Building";"Pylon";NA;133;0
"Building";"HighTemplar";NA;134;0
"Building";"HighTemplar";NA;134;0
"Unit";"Zealot";"Gateway";134;2
"Unit";"Zealot";"Gateway";134;2
"Building";"Pylon";NA;134;0
"Unit";"Zealot";"Gateway";134;2
"Building";"Assimilator";NA;134;0
"Unit";"Archon";"High Templar";138;0
"Building";"ShieldBattery";NA;134;0
"Building";"Pylon";NA;134;0
"Unit";"Immortal";"Robotics Facility";127;4
"Building";"Pylon";NA;134;0
"Unit";"Zealot";"Gateway";144;2
"Unit";"Zealot";"Gateway";144;2
"Unit";"Zealot";"Gateway";144;2
"Unit";"Zealot";"Gateway";144;2
"Unit";"Zealot";"Gateway";144;2
"Unit";"Zealot";"Gateway";144;2
"Unit";"Observer";"Robotics Facility";140;1
"Unit";"Zealot";"Gateway";157;2
"Unit";"Zealot";"Gateway";157;2
"Unit";"Observer";"Robotics Facility";144;1
"Building";"HighTemplar";NA;161;0
"Building";"HighTemplar";NA;161;0
"Unit";"Zealot";"Gateway";162;2
"Unit";"Zealot";"Gateway";162;2
"Unit";"Zealot";"Gateway";162;2
"Unit";"Zealot";"Gateway";162;2
"Unit";"Archon";"High Templar";168;0
"Building";"Pylon";NA;161;0
"Unit";"Observer";"Robotics Facility";161;1
"Unit";"Zealot";"Gateway";171;2
"Unit";"Zealot";"Gateway";171;2
"Unit";"Zealot";"Gateway";175;2
"Unit";"Zealot";"Gateway";175;2
"Unit";"Zealot";"Gateway";175;2
"Unit";"Zealot";"Gateway";175;2
"Unit";"Zealot";"Gateway";183;2
"Unit";"Zealot";"Gateway";183;2
"Unit";"Observer";"Robotics Facility";175;1
"Unit";"Zealot";"Gateway";187;2
"Unit";"Zealot";"Gateway";187;2
"Building";"HighTemplar";NA;192;0
"Unit";"Zealot";"Gateway";192;2
"Unit";"Zealot";"Gateway";192;2
"Unit";"Zealot";"Gateway";192;2
"Building";"HighTemplar";NA;199;0
"Building";"HighTemplar";NA;199;0
"Unit";"Observer";"Robotics Facility";187;1
"Building";"HighTemplar";NA;199;0
"Building";"HighTemplar";NA;199;0
"Building";"Assimilator";NA;198;0
"Building";"HighTemplar";NA;200;0
"Unit";"Zealot";"Gateway";200;2
"Unit";"Zealot";"Gateway";200;2
"Unit";"Zealot";"Gateway";204;2
"Building";"HighTemplar";NA;206;0
"Building";"HighTemplar";NA;206;0
"Building";"HighTemplar";NA;206;0
"Unit";"Zealot";"Gateway";206;2
"Unit";"Immortal";"Robotics Facility";199;4
"Building";"Gateway";NA;198;0
"Building";"HighTemplar";NA;212;0
"Building";"HighTemplar";NA;212;0
"Unit";"Zealot";"Gateway";212;2
"Building";"Gateway";NA;200;0
"Unit";"Zealot";"Gateway";212;2
"Building";"Pylon";NA;206;0
"Upgrade";"ProtossGroundWeaponsLevel3";"Forge";170;0
"Unit";"Archon";"High Templar";214;0
"Building";"HighTemplar";NA;216;0
"Building";"HighTemplar";NA;216;0
"Unit";"Zealot";"Gateway";216;2
"Unit";"Zealot";"Gateway";216;2
"Unit";"Zealot";"Gateway";216;2
"Unit";"Zealot";"Gateway";216;2
"Unit";"Stalker";"Gateway";216;2
"Unit";"Immortal";"Robotics Facility";208;4
"Unit";"Archon";"High Templar";226;0
"Building";"HighTemplar";NA;226;0
"Unit";"Zealot";"Gateway";226;2
"Unit";"Zealot";"Gateway";226;2
"Unit";"Zealot";"Gateway";234;2
"Unit";"Zealot";"Gateway";234;2
"Unit";"Zealot";"Gateway";234;2
"Unit";"Zealot";"Gateway";234;2
"Unit";"Archon";"High Templar";242;0
"Unit";"Zealot";"Gateway";242;2
"Unit";"Archon";"High Templar";242;0
"Unit";"Zealot";"Gateway";242;2
"Unit";"Archon";"High Templar";242;0
"Unit";"Zealot";"Gateway";242;2
"Unit";"Archon";"High Templar";242;0
"Unit";"Zealot";"Gateway";242;2
"Unit";"Archon";"High Templar";242;0
"Unit";"Archon";"High Templar";242;0
"Unit";"Archon";"High Templar";242;0
"Building";"Stargate";NA;224;0
"Unit";"Zealot";"Gateway";250;2
"Unit";"Zealot";"Gateway";250;2
"Unit";"Zealot";"Gateway";250;2
"Unit";"Zealot";"Gateway";250;2
"Unit";"Zealot";"Gateway";250;2
"Unit";"Zealot";"Gateway";250;2
"Building";"HighTemplar";NA;262;0
"Building";"HighTemplar";NA;262;0
"Unit";"Zealot";"Gateway";262;2
"Unit";"Zealot";"Gateway";262;2
"Unit";"Observer";"Robotics Facility";262;1
"Unit";"Zealot";"Gateway";266;2
"Unit";"Zealot";"Gateway";266;2
"Unit";"Zealot";"Gateway";267;2
"Unit";"Zealot";"Gateway";267;2
"Unit";"Zealot";"Gateway";275;2
"Unit";"Zealot";"Gateway";275;2
"Unit";"Zealot";"Gateway";279;2
"Unit";"Zealot";"Gateway";279;2
