"type";"unit_name";"on_building";"total_supply";"supply"
"Building";"Pylon";NA;13;0
"Building";"Gateway";NA;15;0
"Building";"Assimilator";NA;20;0
"Building";"Assimilator";NA;21;0
"Building";"Pylon";NA;22;0
"Building";"CyberneticsCore";NA;21;0
"Building";"Nexus";NA;20;0
"Unit";"Adept";"Gateway";24;2
"Building";"Forge";NA;24;0
"Building";"Gateway";NA;25;0
"Building";"ShieldBattery";NA;30;0
"Building";"Pylon";NA;30;0
"Building";"Stargate";NA;27;0
"Building";"Assimilator";NA;34;0
"Unit";"Sentry";"Gateway";34;2
"Building";"Pylon";NA;39;0
"Unit";"Oracle";"Stargate";35;3
"Building";"Assimilator";NA;39;0
"Building";"Pylon";NA;43;0
"Building";"RoboticsFacility";NA;43;0
"Unit";"Stalker";"Gateway";52;2
"Unit";"Stalker";"Gateway";53;2
"Building";"Gateway";NA;46;0
"Unit";"Oracle";"Stargate";48;3
"Building";"Pylon";NA;52;0
"Unit";"Observer";"Robotics Facility";53;1
"Building";"Pylon";NA;60;0
"Unit";"Adept";"Gateway";61;2
"Unit";"Immortal";"Robotics Facility";60;4
"Building";"Pylon";NA;61;0
"Building";"TwilightCouncil";NA;61;0
"Building";"ShieldBattery";NA;61;0
"Upgrade";"ProtossGroundWeaponsLevel1";"Forge";52;0
"Building";"Gateway";NA;61;0
"Unit";"Sentry";"Gateway";72;2
"Building";"Nexus";NA;60;0
"Unit";"Immortal";"Robotics Facility";65;4
"Building";"OracleStasisTrap";NA;80;0
"Building";"TemplarArchive";NA;72;0
"Building";"Gateway";NA;72;0
"Building";"Gateway";NA;72;0
"Building";"HighTemplar";NA;83;0
"Building";"OracleStasisTrap";NA;83;0
"Building";"Assimilator";NA;81;0
"Building";"Assimilator";NA;81;0
"Unit";"Immortal";"Robotics Facility";81;4
"Building";"Gateway";NA;80;0
"Building";"Gateway";NA;80;0
"Building";"HighTemplar";NA;85;0
"Building";"HighTemplar";NA;85;0
"Unit";"Zealot";"Gateway";85;2
"Building";"Pylon";NA;83;0
"Building";"HighTemplar";NA;91;0
"Unit";"Zealot";"Gateway";94;2
"Unit";"Zealot";"Gateway";94;2
"Upgrade";"Charge";"TwilightCouncil";80;0
"Building";"Gateway";NA;83;0
"Building";"PhotonCannon";NA;91;0
"Building";"ShieldBattery";NA;91;0
"Building";"Pylon";NA;94;0
"Building";"Pylon";NA;98;0
"Unit";"Zealot";"Gateway";101;2
"Unit";"Zealot";"Gateway";101;2
"Unit";"Zealot";"Gateway";101;2
"Unit";"Zealot";"Gateway";101;2
"Building";"Pylon";NA;99;0
"Building";"Pylon";NA;100;0
"Unit";"Archon";"High Templar";101;0
"Unit";"Archon";"High Templar";101;0
"Unit";"Zealot";"Gateway";109;2
"Unit";"Zealot";"Gateway";109;2
"Unit";"Zealot";"Gateway";109;2
"Unit";"Zealot";"Gateway";115;2
"Unit";"Zealot";"Gateway";117;2
"Unit";"Zealot";"Gateway";117;2
"Unit";"Zealot";"Gateway";117;2
"Unit";"Zealot";"Gateway";117;2
"Building";"HighTemplar";NA;125;0
"Upgrade";"ProtossGroundWeaponsLevel2";"Forge";81;0
"Building";"HighTemplar";NA;128;0
"Building";"HighTemplar";NA;128;0
"Building";"HighTemplar";NA;128;0
"Unit";"Zealot";"Gateway";128;2
"Unit";"Zealot";"Gateway";128;2
"Unit";"Zealot";"Gateway";128;2
"Building";"HighTemplar";NA;128;0
"Building";"HighTemplar";NA;130;0
"Unit";"Zealot";"Gateway";134;2
"Building";"Pylon";NA;134;0
"Unit";"Zealot";"Gateway";138;2
"Building";"ShieldBattery";NA;128;0
"Unit";"Zealot";"Gateway";138;2
"Building";"HighTemplar";NA;138;0
"Building";"HighTemplar";NA;138;0
"Unit";"Zealot";"Gateway";138;2
"Unit";"Zealot";"Gateway";140;2
"Unit";"Immortal";"Robotics Facility";128;4
"Building";"Pylon";NA;137;0
"Unit";"Archon";"High Templar";142;0
"Unit";"Zealot";"Gateway";150;2
"Unit";"Zealot";"Gateway";152;2
"Unit";"Zealot";"Gateway";152;2
"Unit";"Zealot";"Gateway";152;2
"Building";"RoboticsFacility";NA;134;0
"Unit";"Immortal";"Robotics Facility";150;4
"Building";"Pylon";NA;158;0
"Building";"HighTemplar";NA;162;0
"Building";"HighTemplar";NA;162;0
"Building";"HighTemplar";NA;162;0
"Building";"HighTemplar";NA;162;0
"Unit";"Zealot";"Gateway";162;2
"Unit";"Archon";"High Templar";167;0
"Unit";"Archon";"High Templar";167;0
"Building";"Pylon";NA;158;0
"Unit";"Observer";"Robotics Facility";158;1
"Unit";"Zealot";"Gateway";169;2
"Unit";"Zealot";"Gateway";169;2
"Unit";"Zealot";"Gateway";169;2
"Unit";"Zealot";"Gateway";169;2
"Building";"ShieldBattery";NA;167;0
"Unit";"Stalker";"Gateway";177;2
"Unit";"Zealot";"Gateway";177;2
"Unit";"Zealot";"Gateway";177;2
"Unit";"Zealot";"Gateway";177;2
"Building";"PhotonCannon";NA;169;0
"Building";"ShieldBattery";NA;169;0
"Building";"Nexus";NA;158;0
"Building";"Assimilator";NA;185;0
"Building";"Assimilator";NA;185;0
"Unit";"Zealot";"Gateway";188;2
"Unit";"Zealot";"Gateway";188;2
"Unit";"Zealot";"Gateway";188;2
"Upgrade";"ProtossGroundWeaponsLevel3";"Forge";158;0
"Building";"Stargate";NA;185;0
"Building";"FleetBeacon";NA;185;0
"Unit";"Stalker";"Gateway";195;2
"Unit";"Stalker";"Gateway";195;2
"Unit";"Stalker";"Gateway";195;2
"Building";"HighTemplar";NA;195;0
"Building";"HighTemplar";NA;195;0
"Unit";"Zealot";"Gateway";195;2
"Unit";"Observer";"Robotics Facility";193;1
"Unit";"Archon";"High Templar";203;0
"Unit";"Zealot";"Gateway";207;2
"Unit";"Zealot";"Gateway";207;2
"Unit";"Zealot";"Gateway";207;2
"Unit";"Observer";"Robotics Facility";206;1
"Unit";"Zealot";"Gateway";217;2
"Building";"HighTemplar";NA;222;0
"Building";"HighTemplar";NA;222;0
"Building";"Assimilator";NA;222;0
"Building";"HighTemplar";NA;222;0
"Building";"HighTemplar";NA;222;0
"Unit";"Zealot";"Gateway";222;2
"Unit";"Zealot";"Gateway";222;2
"Unit";"Archon";"High Templar";224;0
"Building";"Gateway";NA;222;0
"Building";"Gateway";NA;222;0
"Building";"Gateway";NA;222;0
"Unit";"Zealot";"Gateway";229;2
"Unit";"Zealot";"Gateway";229;2
"Building";"HighTemplar";NA;233;0
"Building";"HighTemplar";NA;233;0
"Unit";"Zealot";"Gateway";233;2
"Unit";"Zealot";"Gateway";233;2
"Building";"HighTemplar";NA;237;0
"Building";"Gateway";NA;226;0
"Building";"HighTemplar";NA;237;0
"Unit";"Zealot";"Gateway";237;2
"Unit";"Observer";"Robotics Facility";237;1
"Unit";"Observer";"Robotics Facility";237;1
"Building";"OracleStasisTrap";NA;241;0
"Unit";"Carrier";"Stargate";226;6
"Unit";"Mothership";"Mothership Core";229;6
"Building";"Pylon";NA;253;0
"Building";"Pylon";NA;253;0
"Building";"Assimilator";NA;253;0
"Building";"Pylon";NA;255;0
"Building";"Pylon";NA;255;0
"Building";"HighTemplar";NA;255;0
"Building";"HighTemplar";NA;255;0
"Building";"HighTemplar";NA;255;0
"Building";"HighTemplar";NA;255;0
"Unit";"Stalker";"Gateway";255;2
"Unit";"Zealot";"Gateway";255;2
"Unit";"Archon";"High Templar";259;0
"Unit";"Archon";"High Templar";259;0
"Unit";"Stalker";"Gateway";263;2
"Unit";"Stalker";"Gateway";263;2
"Unit";"Zealot";"Gateway";263;2
"Unit";"Zealot";"Gateway";263;2
"Unit";"Stalker";"Gateway";274;2
"Unit";"Stalker";"Gateway";274;2
"Building";"Nexus";NA;255;0
"Building";"ShieldBattery";NA;272;0
"Building";"ShieldBattery";NA;272;0
"Building";"ShieldBattery";NA;272;0
"Unit";"Zealot";"Gateway";279;2
"Unit";"Zealot";"Gateway";279;2
"Unit";"Zealot";"Gateway";279;2
"Unit";"Zealot";"Gateway";279;2
"Unit";"Carrier";"Stargate";255;6
"Unit";"Zealot";"Gateway";297;2
"Unit";"Zealot";"Gateway";299;2
"Unit";"Zealot";"Gateway";299;2
"Unit";"Zealot";"Gateway";299;2
