"type";"unit_name";"on_building";"total_supply";"supply"
"Building";"Pylon";NA;13;0
"Building";"Assimilator";NA;16;0
"Building";"Gateway";NA;15;0
"Building";"Assimilator";NA;20;0
"Building";"CyberneticsCore";NA;20;0
"Building";"Pylon";NA;21;0
"Building";"Nexus";NA;19;0
"Unit";"Adept";"Gateway";22;2
"Building";"Stargate";NA;23;0
"Unit";"Adept";"Gateway";27;2
"Unit";"Phoenix";"Stargate";31;2
"Building";"Pylon";NA;37;0
"Unit";"Oracle";"Stargate";41;3
"Building";"Gateway";NA;37;0
"Building";"Assimilator";NA;43;0
"Building";"Assimilator";NA;43;0
"Building";"Gateway";NA;41;0
"Building";"TwilightCouncil";NA;45;0
"Unit";"Adept";"Gateway";45;2
"Building";"Pylon";NA;52;0
"Building";"Pylon";NA;52;0
"Building";"RoboticsFacility";NA;52;0
"Unit";"Zealot";"Gateway";54;2
"Unit";"Zealot";"Gateway";54;2
"Unit";"Zealot";"Gateway";54;2
"Building";"Pylon";NA;54;0
"Building";"TemplarArchive";NA;54;0
"Building";"Gateway";NA;54;0
"Building";"Gateway";NA;54;0
"Building";"Pylon";NA;60;0
"Building";"Gateway";NA;54;0
"Building";"Gateway";NA;54;0
"Unit";"Zealot";"Gateway";60;2
"Unit";"Zealot";"Gateway";60;2
"Unit";"Zealot";"Gateway";60;2
"Upgrade";"Charge";"TwilightCouncil";54;0
"Building";"HighTemplar";NA;66;0
"Building";"HighTemplar";NA;66;0
"Building";"HighTemplar";NA;66;0
"Building";"HighTemplar";NA;66;0
"Building";"Pylon";NA;66;0
"Unit";"Archon";"High Templar";66;0
"Unit";"Archon";"High Templar";66;0
"Building";"ShieldBattery";NA;66;0
"Unit";"Sentry";"Gateway";66;2
"Building";"OracleStasisTrap";NA;66;0
"Building";"Pylon";NA;66;0
"Unit";"Zealot";"Gateway";68;2
"Unit";"Zealot";"Gateway";68;2
"Building";"Pylon";NA;66;0
"Unit";"Zealot";"Gateway";72;2
"Unit";"Zealot";"Gateway";72;2
"Unit";"Zealot";"Gateway";72;2
"Unit";"Zealot";"Gateway";72;2
"Building";"Nexus";NA;66;0
"Unit";"Zealot";"Gateway";80;2
"Unit";"Zealot";"Gateway";80;2
"Unit";"Zealot";"Gateway";80;2
"Unit";"Zealot";"Gateway";80;2
"Unit";"Zealot";"Gateway";80;2
"Unit";"Zealot";"Gateway";80;2
"Unit";"Zealot";"Gateway";80;2
"Unit";"Sentry";"Gateway";94;2
"Unit";"Sentry";"Gateway";94;2
"Building";"HighTemplar";NA;97;0
"Building";"HighTemplar";NA;97;0
"Building";"HighTemplar";NA;97;0
"Building";"HighTemplar";NA;97;0
"Unit";"Archon";"High Templar";101;0
"Unit";"Archon";"High Templar";101;0
"Unit";"Immortal";"Robotics Facility";80;4
"Unit";"Zealot";"Gateway";103;2
"Unit";"Zealot";"Gateway";109;2
"Unit";"Zealot";"Gateway";111;2
"Unit";"Zealot";"Gateway";111;2
"Unit";"Zealot";"Gateway";111;2
"Unit";"Zealot";"Gateway";111;2
"Unit";"Zealot";"Gateway";111;2
"Unit";"Zealot";"Gateway";111;2
"Unit";"Immortal";"Robotics Facility";101;4
"Building";"HighTemplar";NA;127;0
"Building";"HighTemplar";NA;127;0
"Unit";"Sentry";"Gateway";127;2
"Unit";"Zealot";"Gateway";127;2
"Building";"OracleStasisTrap";NA;127;0
"Unit";"Zealot";"Gateway";127;2
"Unit";"Zealot";"Gateway";127;2
"Unit";"Immortal";"Robotics Facility";111;4
"Unit";"Zealot";"Gateway";127;2
"Unit";"Archon";"High Templar";135;0
"Building";"Gateway";NA;127;0
"Building";"Gateway";NA;127;0
"Building";"Forge";NA;144;0
"Unit";"Zealot";"Gateway";150;2
"Building";"Gateway";NA;127;0
"Unit";"Sentry";"Gateway";153;2
"Unit";"Sentry";"Gateway";153;2
"Unit";"Sentry";"Gateway";153;2
"Unit";"Immortal";"Robotics Facility";144;4
"Building";"Pylon";NA;165;0
"Building";"Assimilator";NA;161;0
"Building";"Pylon";NA;168;0
"Building";"HighTemplar";NA;169;0
"Building";"HighTemplar";NA;169;0
"Unit";"Zealot";"Gateway";169;2
"Unit";"Zealot";"Gateway";171;2
"Unit";"Zealot";"Gateway";171;2
"Unit";"Zealot";"Gateway";171;2
"Unit";"Zealot";"Gateway";171;2
"Building";"Pylon";NA;169;0
"Unit";"Archon";"High Templar";171;0
"Building";"Pylon";NA;169;0
"Building";"Pylon";NA;179;0
"Building";"Pylon";NA;179;0
"Building";"HighTemplar";NA;179;0
"Building";"HighTemplar";NA;179;0
"Building";"HighTemplar";NA;179;0
"Building";"HighTemplar";NA;179;0
"Unit";"Zealot";"Gateway";179;2
"Unit";"Zealot";"Gateway";179;2
"Unit";"Zealot";"Gateway";179;2
"Unit";"Zealot";"Gateway";179;2
"Unit";"Zealot";"Gateway";179;2
"Unit";"Zealot";"Gateway";179;2
"Unit";"Archon";"High Templar";191;0
"Unit";"Archon";"High Templar";191;0
"Building";"Pylon";NA;191;0
"Building";"Pylon";NA;191;0
"Building";"Pylon";NA;191;0
"Unit";"Zealot";"Gateway";191;2
"Unit";"Zealot";"Gateway";191;2
"Unit";"Zealot";"Gateway";191;2
"Unit";"Zealot";"Gateway";191;2
"Unit";"Zealot";"Gateway";191;2
"Unit";"Zealot";"Gateway";191;2
"Building";"Assimilator";NA;191;0
"Upgrade";"ProtossGroundWeaponsLevel1";"Forge";169;0
"Unit";"Observer";"Robotics Facility";191;1
"Building";"Pylon";NA;191;0
"Unit";"Zealot";"Gateway";204;2
"Unit";"Zealot";"Gateway";204;2
"Unit";"Zealot";"Gateway";204;2
"Unit";"Zealot";"Gateway";204;2
"Unit";"Zealot";"Gateway";212;2
"Unit";"Zealot";"Gateway";212;2
"Unit";"Zealot";"Gateway";212;2
