"type";"unit_name";"on_building";"total_supply";"supply"
"Building";"Pylon";NA;13;0
"Building";"Forge";NA;14;0
"Building";"Pylon";NA;15;0
"Building";"PhotonCannon";NA;16;0
"Building";"Assimilator";NA;17;0
"Building";"Gateway";NA;16;0
"Building";"Assimilator";NA;18;0
"Building";"Pylon";NA;20;0
"Building";"PhotonCannon";NA;19;0
"Building";"CyberneticsCore";NA;19;0
