"type";"unit_name";"on_building";"total_supply";"supply"
"Building";"Pylon";NA;13;0
"Building";"Assimilator";NA;16;0
"Building";"Gateway";NA;15;0
"Building";"Assimilator";NA;21;0
"Building";"Pylon";NA;22;0
"Building";"CyberneticsCore";NA;21;0
"Unit";"Adept";"Gateway";22;2
"Building";"Nexus";NA;20;0
"Building";"Stargate";NA;23;0
"Unit";"Adept";"Gateway";26;2
"Unit";"Adept";"Gateway";31;2
"Unit";"Oracle";"Stargate";31;3
"Building";"Assimilator";NA;44;0
"Building";"Pylon";NA;44;0
"Building";"Gateway";NA;36;0
"Building";"Assimilator";NA;44;0
"Building";"Pylon";NA;46;0
"Building";"Gateway";NA;44;0
"Unit";"Zealot";"Gateway";50;2
"Building";"Pylon";NA;49;0
"Unit";"Phoenix";"Stargate";48;2
"Building";"TwilightCouncil";NA;48;0
"Building";"RoboticsFacility";NA;48;0
"Building";"Gateway";NA;48;0
"Building";"Gateway";NA;48;0
"Building";"Pylon";NA;58;0
"Building";"Pylon";NA;59;0
"Unit";"Adept";"Gateway";61;2
"Building";"Gateway";NA;59;0
"Building";"Nexus";NA;58;0
"Building";"Forge";NA;65;0
"Building";"Pylon";NA;68;0
"Building";"Pylon";NA;68;0
"Unit";"Zealot";"Gateway";74;2
"Unit";"Zealot";"Gateway";74;2
"Unit";"Zealot";"Gateway";74;2
"Unit";"Zealot";"Gateway";74;2
"Unit";"Zealot";"Gateway";74;2
"Building";"TemplarArchive";NA;66;0
"Upgrade";"Charge";"TwilightCouncil";65;0
"Building";"Assimilator";NA;86;0
"Building";"Assimilator";NA;87;0
"Building";"HighTemplar";NA;93;0
"Building";"HighTemplar";NA;93;0
"Building";"HighTemplar";NA;93;0
"Building";"HighTemplar";NA;93;0
"Building";"HighTemplar";NA;93;0
"Building";"Pylon";NA;90;0
"Building";"Pylon";NA;90;0
"Building";"Gateway";NA;87;0
"Building";"RoboticsFacility";NA;87;0
"Building";"Gateway";NA;87;0
"Building";"Pylon";NA;94;0
"Building";"Pylon";NA;95;0
"Unit";"Immortal";"Robotics Facility";90;4
"Building";"Gateway";NA;90;0
"Building";"HighTemplar";NA;105;0
"Building";"HighTemplar";NA;105;0
"Unit";"Archon";"High Templar";105;0
"Building";"HighTemplar";NA;105;0
"Building";"HighTemplar";NA;105;0
"Building";"HighTemplar";NA;105;0
"Unit";"Archon";"High Templar";105;0
"Building";"Pylon";NA;107;0
"Building";"Pylon";NA;108;0
"Building";"HighTemplar";NA;108;0
"Building";"HighTemplar";NA;108;0
"Unit";"Zealot";"Gateway";108;2
"Unit";"Zealot";"Gateway";108;2
"Building";"Pylon";NA;108;0
"Unit";"Immortal";"Robotics Facility";105;4
"Unit";"Immortal";"Robotics Facility";105;4
"Building";"Pylon";NA;108;0
"Building";"Pylon";NA;108;0
"Upgrade";"ProtossGroundWeaponsLevel1";"Forge";96;0
"Building";"Gateway";NA;108;0
"Unit";"Immortal";"Robotics Facility";108;4
"Building";"Gateway";NA;108;0
"Building";"Gateway";NA;108;0
"Unit";"Immortal";"Robotics Facility";120;4
"Building";"HighTemplar";NA;125;0
"Building";"HighTemplar";NA;125;0
"Building";"HighTemplar";NA;125;0
"Building";"PhotonCannon";NA;121;0
"Building";"PhotonCannon";NA;121;0
"Building";"PhotonCannon";NA;121;0
"Building";"HighTemplar";NA;129;0
"Building";"HighTemplar";NA;129;0
"Unit";"Zealot";"Gateway";129;2
"Unit";"Zealot";"Gateway";129;2
"Building";"ShieldBattery";NA;121;0
"Building";"PhotonCannon";NA;121;0
"Building";"ShieldBattery";NA;121;0
"Building";"PhotonCannon";NA;125;0
"Building";"PhotonCannon";NA;125;0
"Building";"Nexus";NA;121;0
"Building";"PhotonCannon";NA;133;0
"Building";"ShieldBattery";NA;133;0
"Building";"ShieldBattery";NA;133;0
"Unit";"Archon";"High Templar";133;0
"Unit";"Zealot";"Gateway";133;2
"Unit";"Zealot";"Gateway";133;2
"Unit";"Zealot";"Gateway";133;2
"Unit";"Zealot";"Gateway";133;2
"Unit";"Zealot";"Gateway";133;2
"Unit";"Zealot";"Gateway";143;2
"Unit";"Zealot";"Gateway";143;2
"Unit";"Zealot";"Gateway";143;2
"Unit";"Immortal";"Robotics Facility";133;4
"Unit";"Immortal";"Robotics Facility";133;4
"Building";"Assimilator";NA;133;0
"Building";"PhotonCannon";NA;133;0
"Building";"Assimilator";NA;133;0
"Unit";"Zealot";"Gateway";157;2
"Unit";"Zealot";"Gateway";157;2
"Unit";"Zealot";"Gateway";157;2
"Unit";"Zealot";"Gateway";157;2
"Unit";"Zealot";"Gateway";157;2
"Unit";"Zealot";"Gateway";157;2
"Unit";"Zealot";"Gateway";169;2
"Unit";"Zealot";"Gateway";169;2
"Building";"HighTemplar";NA;169;0
"Building";"HighTemplar";NA;169;0
"Building";"Pylon";NA;173;0
"Unit";"Zealot";"Gateway";173;2
"Unit";"Zealot";"Gateway";173;2
"Unit";"Zealot";"Gateway";173;2
"Unit";"Zealot";"Gateway";173;2
"Unit";"Zealot";"Gateway";173;2
"Unit";"Immortal";"Robotics Facility";169;4
"Unit";"Immortal";"Robotics Facility";169;4
"Unit";"Zealot";"Gateway";191;2
"Unit";"Zealot";"Gateway";191;2
"Unit";"Zealot";"Gateway";191;2
"Unit";"Zealot";"Gateway";191;2
"Unit";"Zealot";"Gateway";191;2
"Unit";"Zealot";"Gateway";191;2
"Unit";"Observer";"Robotics Facility";183;1
"Building";"Nexus";NA;169;0
"Unit";"Observer";"Robotics Facility";187;1
"Unit";"Zealot";"Gateway";205;2
"Unit";"Zealot";"Gateway";205;2
"Unit";"Zealot";"Gateway";205;2
"Unit";"Zealot";"Gateway";205;2
"Unit";"Zealot";"Gateway";205;2
"Unit";"Observer";"Robotics Facility";203;1
"Building";"Pylon";NA;205;0
"Building";"HighTemplar";NA;216;0
"Building";"HighTemplar";NA;216;0
"Building";"HighTemplar";NA;216;0
"Building";"HighTemplar";NA;216;0
"Building";"HighTemplar";NA;216;0
"Building";"HighTemplar";NA;216;0
"Unit";"Observer";"Robotics Facility";204;1
"Building";"HighTemplar";NA;217;0
"Building";"HighTemplar";NA;217;0
"Building";"HighTemplar";NA;217;0
"Building";"HighTemplar";NA;217;0
"Building";"HighTemplar";NA;217;0
"Unit";"Immortal";"Robotics Facility";215;4
"Building";"Pylon";NA;217;0
"Unit";"Archon";"High Templar";225;0
"Building";"PhotonCannon";NA;217;0
"Unit";"Archon";"High Templar";225;0
"Building";"PhotonCannon";NA;217;0
"Building";"PhotonCannon";NA;217;0
"Building";"HighTemplar";NA;229;0
"Building";"HighTemplar";NA;229;0
"Building";"HighTemplar";NA;229;0
"Building";"HighTemplar";NA;229;0
"Unit";"Zealot";"Gateway";229;2
"Unit";"Zealot";"Gateway";229;2
"Unit";"Immortal";"Robotics Facility";217;4
"Unit";"Archon";"High Templar";229;0
"Unit";"Archon";"High Templar";233;0
"Building";"PhotonCannon";NA;225;0
"Building";"PhotonCannon";NA;225;0
"Unit";"Zealot";"Gateway";239;2
"Unit";"Zealot";"Gateway";239;2
"Unit";"Zealot";"Gateway";239;2
"Unit";"Zealot";"Gateway";239;2
"Unit";"Zealot";"Gateway";239;2
"Unit";"Zealot";"Gateway";239;2
"Unit";"Zealot";"Gateway";239;2
"Unit";"Zealot";"Gateway";253;2
"Unit";"Zealot";"Gateway";253;2
"Unit";"Zealot";"Gateway";253;2
"Unit";"Zealot";"Gateway";253;2
"Unit";"Zealot";"Gateway";261;2
"Unit";"Zealot";"Gateway";261;2
"Unit";"Zealot";"Gateway";261;2
"Unit";"Zealot";"Gateway";261;2
"Unit";"Zealot";"Gateway";261;2
"Unit";"Zealot";"Gateway";261;2
"Building";"HighTemplar";NA;273;0
"Building";"HighTemplar";NA;273;0
"Building";"HighTemplar";NA;273;0
"Building";"HighTemplar";NA;273;0
"Building";"HighTemplar";NA;273;0
"Building";"HighTemplar";NA;273;0
"Building";"HighTemplar";NA;273;0
"Building";"HighTemplar";NA;273;0
"Building";"HighTemplar";NA;273;0
"Unit";"Zealot";"Gateway";273;2
"Unit";"Zealot";"Gateway";273;2
"Unit";"Archon";"High Templar";277;0
"Building";"Nexus";NA;261;0
"Unit";"Archon";"High Templar";277;0
"Unit";"Archon";"High Templar";277;0
"Unit";"Archon";"High Templar";277;0
"Upgrade";"ProtossGroundWeaponsLevel2";"Forge";239;0
"Building";"HighTemplar";NA;277;0
"Building";"HighTemplar";NA;277;0
"Building";"HighTemplar";NA;279;0
"Building";"HighTemplar";NA;279;0
"Building";"HighTemplar";NA;279;0
"Building";"HighTemplar";NA;279;0
"Building";"HighTemplar";NA;279;0
"Unit";"Zealot";"Gateway";279;2
"Unit";"Zealot";"Gateway";279;2
"Unit";"Zealot";"Gateway";279;2
"Unit";"Zealot";"Gateway";279;2
"Building";"Assimilator";NA;277;0
"Unit";"Archon";"High Templar";287;0
"Unit";"Archon";"High Templar";287;0
"Unit";"Archon";"High Templar";287;0
"Building";"HighTemplar";NA;287;0
"Building";"HighTemplar";NA;287;0
"Unit";"Zealot";"Gateway";287;2
"Unit";"Zealot";"Gateway";287;2
"Unit";"Zealot";"Gateway";287;2
"Unit";"Zealot";"Gateway";287;2
"Unit";"Observer";"Robotics Facility";287;1
"Building";"Pylon";NA;287;0
"Building";"Nexus";NA;277;0
"Building";"Assimilator";NA;287;0
"Building";"Assimilator";NA;287;0
"Building";"HighTemplar";NA;296;0
"Building";"HighTemplar";NA;296;0
"Building";"HighTemplar";NA;296;0
"Unit";"Zealot";"Gateway";296;2
"Unit";"Zealot";"Gateway";296;2
"Unit";"Zealot";"Gateway";296;2
"Unit";"Zealot";"Gateway";296;2
"Unit";"Zealot";"Gateway";296;2
"Unit";"Zealot";"Gateway";296;2
