"type";"unit_name";"on_building";"total_supply";"supply"
"Building";"Pylon";NA;13;0
"Building";"Assimilator";NA;15;0
"Building";"Gateway";NA;15;0
"Building";"Assimilator";NA;20;0
"Building";"CyberneticsCore";NA;20;0
"Building";"Pylon";NA;21;0
"Building";"Nexus";NA;20;0
"Unit";"Adept";"Gateway";23;2
"Building";"Stargate";NA;23;0
"Unit";"Adept";"Gateway";29;2
"Unit";"Oracle";"Stargate";30;3
"Building";"Pylon";NA;42;0
"Unit";"Phoenix";"Stargate";39;2
"Building";"Assimilator";NA;44;0
"Building";"Gateway";NA;37;0
"Building";"Assimilator";NA;44;0
"Building";"RoboticsFacility";NA;43;0
"Building";"TwilightCouncil";NA;47;0
"Building";"Pylon";NA;50;0
"Building";"Pylon";NA;53;0
"Unit";"Zealot";"Gateway";56;2
"Unit";"Zealot";"Gateway";56;2
"Building";"Gateway";NA;51;0
"Building";"Gateway";NA;52;0
"Building";"TemplarArchive";NA;54;0
"Building";"HighTemplar";NA;63;0
"Building";"HighTemplar";NA;63;0
"Building";"HighTemplar";NA;63;0
"Building";"HighTemplar";NA;63;0
"Building";"Pylon";NA;63;0
"Unit";"Archon";"High Templar";63;0
"Unit";"Archon";"High Templar";63;0
"Building";"Pylon";NA;63;0
"Building";"Gateway";NA;62;0
"Building";"Gateway";NA;63;0
"Unit";"Observer";"Robotics Facility";63;1
"Building";"Pylon";NA;65;0
"Building";"Forge";NA;63;0
"Building";"HighTemplar";NA;68;0
"Building";"HighTemplar";NA;70;0
"Building";"ShieldBattery";NA;65;0
"Building";"ShieldBattery";NA;65;0
"Unit";"Zealot";"Gateway";71;2
"Unit";"Zealot";"Gateway";72;2
"Unit";"Zealot";"Gateway";72;2
"Unit";"Zealot";"Gateway";72;2
"Building";"Pylon";NA;70;0
"Building";"Pylon";NA;71;0
"Building";"Gateway";NA;68;0
"Building";"Gateway";NA;68;0
"Building";"Pylon";NA;80;0
"Unit";"Sentry";"Gateway";82;2
"Building";"Nexus";NA;63;0
"Unit";"Sentry";"Gateway";82;2
"Upgrade";"Charge";"TwilightCouncil";65;0
"Building";"Assimilator";NA;86;0
"Building";"HighTemplar";NA;90;0
"Building";"HighTemplar";NA;91;0
"Building";"Assimilator";NA;88;0
"Unit";"Immortal";"Robotics Facility";82;4
"Building";"PhotonCannon";NA;92;0
"Building";"PhotonCannon";NA;92;0
"Building";"PhotonCannon";NA;92;0
"Building";"HighTemplar";NA;98;0
"Building";"HighTemplar";NA;98;0
"Upgrade";"ProtossGroundWeaponsLevel1";"Forge";80;0
"Unit";"Immortal";"Robotics Facility";93;4
"Building";"PhotonCannon";NA;98;0
"Building";"PhotonCannon";NA;98;0
"Building";"PhotonCannon";NA;98;0
"Building";"PhotonCannon";NA;98;0
"Building";"PhotonCannon";NA;98;0
"Building";"Pylon";NA;101;0
"Unit";"Observer";"Robotics Facility";101;1
"Building";"RoboticsFacility";NA;98;0
"Building";"Pylon";NA;106;0
"Building";"Pylon";NA;106;0
"Unit";"Zealot";"Gateway";108;2
"Unit";"Zealot";"Gateway";108;2
"Unit";"Zealot";"Gateway";108;2
"Unit";"Zealot";"Gateway";108;2
"Unit";"Zealot";"Gateway";108;2
"Unit";"Zealot";"Gateway";108;2
"Unit";"Zealot";"Gateway";108;2
"Building";"Pylon";NA;106;0
"Unit";"Zealot";"Gateway";108;2
"Unit";"Immortal";"Robotics Facility";105;4
"Unit";"Immortal";"Robotics Facility";108;4
"Building";"HighTemplar";NA;135;0
"Building";"HighTemplar";NA;135;0
"Building";"HighTemplar";NA;135;0
"Unit";"Immortal";"Robotics Facility";108;4
"Building";"HighTemplar";NA;135;0
"Building";"HighTemplar";NA;135;0
"Building";"HighTemplar";NA;135;0
"Unit";"Archon";"High Templar";139;0
"Building";"Nexus";NA;106;0
"Unit";"Archon";"High Templar";139;0
"Unit";"Archon";"High Templar";139;0
"Unit";"Immortal";"Robotics Facility";128;4
"Unit";"Immortal";"Robotics Facility";135;4
"Upgrade";"ProtossGroundWeaponsLevel2";"Forge";106;0
"Unit";"Phoenix";"Stargate";139;2
"Unit";"Phoenix";"Stargate";139;2
"Building";"PhotonCannon";NA;143;0
"Unit";"Immortal";"Robotics Facility";139;4
"Building";"Gateway";NA;139;0
"Building";"Gateway";NA;139;0
"Building";"PhotonCannon";NA;143;0
"Building";"Gateway";NA;139;0
"Building";"PhotonCannon";NA;143;0
"Building";"Gateway";NA;139;0
"Building";"PhotonCannon";NA;147;0
"Building";"Gateway";NA;139;0
"Building";"Gateway";NA;139;0
"Building";"Assimilator";NA;151;0
"Unit";"Immortal";"Robotics Facility";143;4
"Building";"Assimilator";NA;151;0
"Unit";"Zealot";"Gateway";163;2
"Unit";"Zealot";"Gateway";163;2
"Unit";"Zealot";"Gateway";163;2
"Unit";"Zealot";"Gateway";163;2
"Unit";"Zealot";"Gateway";163;2
"Unit";"Zealot";"Gateway";163;2
"Unit";"Zealot";"Gateway";163;2
"Unit";"Zealot";"Gateway";177;2
"Unit";"Immortal";"Robotics Facility";158;4
"Unit";"Zealot";"Gateway";183;2
"Unit";"Zealot";"Gateway";183;2
"Unit";"Zealot";"Gateway";183;2
"Unit";"Zealot";"Gateway";183;2
"Unit";"Zealot";"Gateway";183;2
"Unit";"Zealot";"Gateway";183;2
"Unit";"Zealot";"Gateway";183;2
"Unit";"Zealot";"Gateway";183;2
"Unit";"Zealot";"Gateway";183;2
"Unit";"Zealot";"Gateway";183;2
"Unit";"Immortal";"Robotics Facility";158;4
"Unit";"Immortal";"Robotics Facility";179;4
"Unit";"Immortal";"Robotics Facility";179;4
"Building";"HighTemplar";NA;211;0
"Building";"HighTemplar";NA;211;0
"Building";"HighTemplar";NA;211;0
"Building";"HighTemplar";NA;211;0
"Building";"HighTemplar";NA;211;0
"Unit";"Zealot";"Gateway";215;2
"Unit";"Zealot";"Gateway";215;2
"Unit";"Zealot";"Gateway";215;2
"Building";"HighTemplar";NA;224;0
"Building";"HighTemplar";NA;224;0
"Building";"HighTemplar";NA;224;0
"Building";"HighTemplar";NA;224;0
"Building";"HighTemplar";NA;224;0
"Building";"HighTemplar";NA;224;0
"Unit";"Archon";"High Templar";224;0
"Unit";"Archon";"High Templar";224;0
"Unit";"Archon";"High Templar";224;0
"Building";"HighTemplar";NA;224;0
"Building";"HighTemplar";NA;224;0
"Building";"HighTemplar";NA;224;0
"Building";"HighTemplar";NA;224;0
"Building";"HighTemplar";NA;224;0
"Unit";"Sentry";"Gateway";224;2
"Upgrade";"ProtossGroundWeaponsLevel3";"Forge";163;0
"Unit";"Archon";"High Templar";224;0
"Unit";"Archon";"High Templar";224;0
"Unit";"Immortal";"Robotics Facility";224;4
"Unit";"Immortal";"Robotics Facility";224;4
"Building";"HighTemplar";NA;226;0
"Building";"PhotonCannon";NA;224;0
"Building";"PhotonCannon";NA;224;0
"Building";"PhotonCannon";NA;224;0
"Building";"Pylon";NA;226;0
"Unit";"Observer";"Robotics Facility";234;1
"Unit";"Observer";"Robotics Facility";234;1
"Unit";"Zealot";"Gateway";240;2
"Unit";"Zealot";"Gateway";240;2
"Unit";"Zealot";"Gateway";240;2
"Unit";"Zealot";"Gateway";240;2
"Unit";"Zealot";"Gateway";240;2
"Unit";"Zealot";"Gateway";240;2
"Unit";"Zealot";"Gateway";240;2
"Unit";"Zealot";"Gateway";240;2
"Unit";"Zealot";"Gateway";240;2
"Unit";"Zealot";"Gateway";240;2
"Unit";"Zealot";"Gateway";240;2
"Unit";"Zealot";"Gateway";240;2
"Unit";"Zealot";"Gateway";240;2
"Building";"Pylon";NA;240;0
"Building";"Pylon";NA;266;0
"Building";"Pylon";NA;266;0
"Building";"Pylon";NA;266;0
"Building";"HighTemplar";NA;266;0
"Building";"HighTemplar";NA;266;0
"Building";"HighTemplar";NA;266;0
"Building";"HighTemplar";NA;266;0
"Building";"HighTemplar";NA;266;0
"Building";"HighTemplar";NA;266;0
"Building";"HighTemplar";NA;266;0
"Building";"HighTemplar";NA;266;0
"Building";"HighTemplar";NA;266;0
"Unit";"Archon";"High Templar";266;0
"Unit";"Archon";"High Templar";266;0
"Unit";"Archon";"High Templar";266;0
"Unit";"Archon";"High Templar";266;0
"Unit";"Zealot";"Gateway";266;2
"Unit";"Zealot";"Gateway";266;2
"Unit";"Zealot";"Gateway";266;2
"Unit";"Zealot";"Gateway";266;2
"Unit";"Zealot";"Gateway";266;2
"Upgrade";"ProtossShieldsLevel1";"Forge";238;0
"Building";"Nexus";NA;240;0
"Unit";"Zealot";"Gateway";276;2
"Unit";"Zealot";"Gateway";276;2
"Unit";"Zealot";"Gateway";276;2
"Unit";"Zealot";"Gateway";276;2
"Unit";"Zealot";"Gateway";276;2
"Unit";"Zealot";"Gateway";276;2
"Unit";"Zealot";"Gateway";276;2
"Building";"Nexus";NA;266;0
"Building";"PhotonCannon";NA;266;0
"Building";"HighTemplar";NA;290;0
"Building";"HighTemplar";NA;290;0
"Building";"PhotonCannon";NA;290;0
"Building";"PhotonCannon";NA;290;0
"Unit";"Zealot";"Gateway";295;2
"Unit";"Zealot";"Gateway";295;2
"Unit";"Zealot";"Gateway";295;2
"Unit";"Zealot";"Gateway";295;2
"Unit";"Zealot";"Gateway";295;2
"Building";"PhotonCannon";NA;290;0
"Building";"PhotonCannon";NA;290;0
"Building";"HighTemplar";NA;305;0
"Building";"HighTemplar";NA;305;0
"Building";"HighTemplar";NA;305;0
"Building";"HighTemplar";NA;305;0
"Building";"HighTemplar";NA;305;0
"Building";"HighTemplar";NA;305;0
"Unit";"Zealot";"Gateway";305;2
"Unit";"Zealot";"Gateway";305;2
"Unit";"Zealot";"Gateway";305;2
"Unit";"Archon";"High Templar";305;0
"Unit";"Archon";"High Templar";305;0
"Unit";"Archon";"High Templar";305;0
"Building";"FleetBeacon";NA;295;0
