"type";"unit_name";"on_building";"total_supply";"supply"
"Building";"Pylon";NA;13;0
"Building";"Assimilator";NA;16;0
"Building";"Gateway";NA;15;0
"Building";"Pylon";NA;20;0
"Building";"Assimilator";NA;20;0
"Building";"CyberneticsCore";NA;20;0
"Building";"Pylon";NA;21;0
"Unit";"Adept";"Gateway";21;2
"Building";"Nexus";NA;19;0
"Unit";"Stalker";"Gateway";24;2
"Building";"TwilightCouncil";NA;24;0
"Unit";"Adept";"Gateway";35;2
"Building";"RoboticsFacility";NA;32;0
"Building";"Assimilator";NA;42;0
"Building";"ShieldBattery";NA;40;0
"Building";"Assimilator";NA;42;0
"Building";"Gateway";NA;38;0
"Building";"Gateway";NA;38;0
"Building";"Gateway";NA;38;0
"Building";"Pylon";NA;45;0
"Unit";"Adept";"Gateway";48;2
"Unit";"Adept";"Gateway";48;2
"Unit";"Zealot";"Gateway";48;2
"Building";"Pylon";NA;48;0
"Building";"DarkShrine";NA;42;0
"Building";"DarkTemplar";NA;56;0
"Building";"DarkTemplar";NA;56;0
"Building";"DarkTemplar";NA;56;0
"Building";"DarkTemplar";NA;56;0
"Building";"Pylon";NA;55;0
"Unit";"Archon";"High Templar";56;0
"Unit";"Archon";"High Templar";56;0
"Building";"DarkTemplar";NA;57;0
"Building";"DarkTemplar";NA;57;0
"Building";"DarkTemplar";NA;57;0
"Building";"Pylon";NA;57;0
"Upgrade";"Charge";"TwilightCouncil";47;0
"Unit";"Zealot";"Gateway";58;2
"Building";"DarkTemplar";NA;62;0
"Building";"DarkTemplar";NA;62;0
"Unit";"Zealot";"Gateway";62;2
"Building";"Nexus";NA;57;0
"Building";"Pylon";NA;64;0
"Building";"ShieldBattery";NA;64;0
"Building";"Forge";NA;64;0
"Building";"DarkTemplar";NA;66;0
"Building";"DarkTemplar";NA;66;0
"Building";"DarkTemplar";NA;66;0
"Unit";"Zealot";"Gateway";66;2
"Unit";"Immortal";"Robotics Facility";64;4
"Building";"Gateway";NA;64;0
"Building";"Gateway";NA;64;0
"Unit";"Archon";"High Templar";75;0
"Unit";"Zealot";"Gateway";75;2
"Building";"Pylon";NA;75;0
"Unit";"Immortal";"Robotics Facility";72;4
"Unit";"Archon";"High Templar";82;0
"Unit";"Archon";"High Templar";82;0
"Building";"Gateway";NA;72;0
"Building";"Gateway";NA;72;0
"Building";"Gateway";NA;72;0
"Building";"DarkTemplar";NA;87;0
"Building";"Gateway";NA;75;0
"Building";"Pylon";NA;88;0
"Building";"Pylon";NA;88;0
"Building";"Assimilator";NA;88;0
"Building";"Assimilator";NA;88;0
"Unit";"Zealot";"Gateway";88;2
"Building";"Pylon";NA;88;0
"Unit";"Zealot";"Gateway";88;2
"Building";"Pylon";NA;88;0
"Unit";"Zealot";"Gateway";88;2
"Unit";"Zealot";"Gateway";88;2
"Unit";"Zealot";"Gateway";88;2
"Unit";"Zealot";"Gateway";88;2
"Unit";"Zealot";"Gateway";88;2
"Building";"Pylon";NA;88;0
"Unit";"Archon";"High Templar";88;0
"Building";"Pylon";NA;88;0
"Unit";"Immortal";"Robotics Facility";86;4
"Building";"DarkTemplar";NA;102;0
"Building";"DarkTemplar";NA;102;0
"Unit";"Sentry";"Gateway";106;2
"Building";"Pylon";NA;88;0
"Unit";"Zealot";"Gateway";108;2
"Unit";"Zealot";"Gateway";108;2
"Unit";"Zealot";"Gateway";108;2
"Unit";"Zealot";"Gateway";108;2
"Unit";"Zealot";"Gateway";108;2
"Unit";"Zealot";"Gateway";108;2
"Unit";"Zealot";"Gateway";108;2
"Unit";"Zealot";"Gateway";122;2
"Upgrade";"ProtossGroundWeaponsLevel1";"Forge";81;0
"Building";"DarkTemplar";NA;124;0
"Building";"DarkTemplar";NA;124;0
"Unit";"Zealot";"Gateway";124;2
"Unit";"Zealot";"Gateway";124;2
"Unit";"Zealot";"Gateway";124;2
"Unit";"Zealot";"Gateway";124;2
"Unit";"Zealot";"Gateway";124;2
"Unit";"Zealot";"Gateway";124;2
"Unit";"Zealot";"Gateway";124;2
"Unit";"Archon";"High Templar";139;0
"Building";"TemplarArchive";NA;124;0
"Unit";"Archon";"High Templar";139;0
"Building";"PhotonCannon";NA;139;0
"Building";"Pylon";NA;140;0
"Building";"PhotonCannon";NA;139;0
"Unit";"Stalker";"Gateway";141;2
"Building";"Pylon";NA;140;0
"Building";"Pylon";NA;140;0
"Building";"Pylon";NA;140;0
"Building";"PhotonCannon";NA;140;0
"Unit";"Immortal";"Robotics Facility";139;4
"Building";"PhotonCannon";NA;140;0
"Unit";"Observer";"Robotics Facility";143;1
"Unit";"Zealot";"Gateway";147;2
"Unit";"Zealot";"Gateway";147;2
"Unit";"Zealot";"Gateway";148;2
"Unit";"Zealot";"Gateway";148;2
"Unit";"Zealot";"Gateway";148;2
"Unit";"Zealot";"Gateway";148;2
"Unit";"Zealot";"Gateway";148;2
"Unit";"Zealot";"Gateway";148;2
"Unit";"Zealot";"Gateway";148;2
"Unit";"Observer";"Robotics Facility";147;1
"Building";"HighTemplar";NA;167;0
"Building";"HighTemplar";NA;167;0
"Building";"HighTemplar";NA;167;0
"Building";"HighTemplar";NA;167;0
"Building";"HighTemplar";NA;167;0
"Building";"HighTemplar";NA;167;0
"Building";"HighTemplar";NA;167;0
"Upgrade";"ProtossGroundWeaponsLevel2";"Forge";140;0
"Building";"Pylon";NA;167;0
"Building";"Pylon";NA;167;0
"Building";"Pylon";NA;167;0
"Building";"Pylon";NA;168;0
"Building";"DarkTemplar";NA;168;0
"Building";"DarkTemplar";NA;168;0
"Building";"DarkTemplar";NA;168;0
"Building";"Nexus";NA;167;0
"Building";"Pylon";NA;168;0
"Building";"PhotonCannon";NA;168;0
"Building";"PhotonCannon";NA;168;0
"Building";"PhotonCannon";NA;168;0
"Building";"PhotonCannon";NA;168;0
"Building";"PhotonCannon";NA;168;0
"Building";"Stargate";NA;168;0
"Building";"DarkTemplar";NA;168;0
"Unit";"Zealot";"Gateway";168;2
"Unit";"Zealot";"Gateway";168;2
"Unit";"Zealot";"Gateway";168;2
"Unit";"Zealot";"Gateway";168;2
"Unit";"Zealot";"Gateway";168;2
"Unit";"Zealot";"Gateway";168;2
"Unit";"Zealot";"Gateway";168;2
"Unit";"Zealot";"Gateway";168;2
"Unit";"Zealot";"Gateway";168;2
"Upgrade";"ProtossGroundWeaponsLevel3";"Forge";168;0
"Building";"DarkTemplar";NA;186;0
"Building";"DarkTemplar";NA;186;0
"Building";"DarkTemplar";NA;186;0
"Building";"DarkTemplar";NA;186;0
"Building";"DarkTemplar";NA;186;0
"Building";"DarkTemplar";NA;186;0
"Building";"DarkTemplar";NA;186;0
"Unit";"Zealot";"Gateway";186;2
"Unit";"Observer";"Robotics Facility";186;1
"Unit";"Zealot";"Gateway";189;2
"Unit";"Zealot";"Gateway";189;2
"Unit";"Zealot";"Gateway";189;2
"Unit";"Zealot";"Gateway";189;2
"Unit";"Zealot";"Gateway";189;2
"Unit";"Zealot";"Gateway";189;2
"Unit";"Zealot";"Gateway";189;2
"Unit";"Oracle";"Stargate";186;3
"Unit";"Zealot";"Gateway";206;2
"Unit";"Zealot";"Gateway";206;2
"Unit";"Zealot";"Gateway";206;2
"Unit";"Zealot";"Gateway";206;2
"Unit";"Zealot";"Gateway";206;2
"Unit";"Zealot";"Gateway";206;2
"Unit";"Zealot";"Gateway";206;2
"Unit";"Zealot";"Gateway";206;2
"Unit";"Zealot";"Gateway";222;2
"Unit";"Zealot";"Gateway";222;2
"Unit";"Zealot";"Gateway";222;2
"Unit";"Zealot";"Gateway";222;2
"Unit";"Zealot";"Gateway";222;2
"Unit";"Zealot";"Gateway";222;2
"Unit";"Zealot";"Gateway";222;2
"Unit";"Zealot";"Gateway";222;2
"Building";"Pylon";NA;222;0
"Unit";"Observer";"Robotics Facility";222;1
"Building";"PhotonCannon";NA;222;0
"Unit";"Zealot";"Gateway";239;2
"Unit";"Zealot";"Gateway";239;2
"Unit";"Zealot";"Gateway";239;2
"Unit";"Zealot";"Gateway";239;2
"Unit";"Zealot";"Gateway";239;2
"Unit";"Zealot";"Gateway";239;2
"Unit";"Zealot";"Gateway";239;2
"Unit";"Zealot";"Gateway";239;2
"Building";"HighTemplar";NA;255;0
"Building";"HighTemplar";NA;255;0
"Building";"HighTemplar";NA;255;0
"Building";"HighTemplar";NA;255;0
"Building";"HighTemplar";NA;255;0
"Building";"HighTemplar";NA;255;0
"Building";"HighTemplar";NA;255;0
"Building";"Nexus";NA;222;0
"Building";"Pylon";NA;255;0
"Building";"PhotonCannon";NA;255;0
"Building";"PhotonCannon";NA;255;0
"Building";"Pylon";NA;255;0
"Building";"PhotonCannon";NA;255;0
"Building";"PhotonCannon";NA;255;0
"Building";"PhotonCannon";NA;255;0
