"type";"unit_name";"on_building";"total_supply";"supply"
"Building";"Pylon";NA;13;0
"Building";"Assimilator";NA;16;0
"Building";"Gateway";NA;15;0
"Building";"CyberneticsCore";NA;20;0
"Building";"Assimilator";NA;21;0
"Building";"Pylon";NA;22;0
"Building";"Nexus";NA;19;0
"Unit";"Adept";"Gateway";23;2
"Unit";"Adept";"Gateway";24;2
"Building";"Stargate";NA;23;0
"Unit";"Adept";"Gateway";32;2
"Building";"ShieldBattery";NA;34;0
"Unit";"Stalker";"Gateway";37;2
"Building";"Pylon";NA;44;0
"Building";"Gateway";NA;39;0
"Building";"Assimilator";NA;44;0
"Building";"Assimilator";NA;44;0
"Building";"Pylon";NA;44;0
"Building";"Gateway";NA;44;0
"Building";"Gateway";NA;44;0
"Building";"TwilightCouncil";NA;49;0
"Building";"Pylon";NA;50;0
"Building";"Pylon";NA;52;0
"Building";"Pylon";NA;52;0
"Building";"Pylon";NA;52;0
"Building";"Pylon";NA;52;0
"Unit";"Adept";"Gateway";53;2
"Unit";"Adept";"Gateway";53;2
"Unit";"Adept";"Gateway";53;2
"Unit";"Adept";"Gateway";53;2
"Building";"ShieldBattery";NA;52;0
"Building";"ShieldBattery";NA;53;0
"Building";"ShieldBattery";NA;53;0
"Building";"DarkShrine";NA;52;0
"Unit";"Sentry";"Gateway";64;2
"Unit";"Sentry";"Gateway";64;2
"Unit";"Sentry";"Gateway";64;2
"Building";"Gateway";NA;63;0
"Building";"Pylon";NA;64;0
"Building";"Pylon";NA;70;0
"Building";"Pylon";NA;70;0
"Building";"DarkTemplar";NA;70;0
"Building";"DarkTemplar";NA;70;0
"Upgrade";"Charge";"TwilightCouncil";63;0
"Building";"DarkTemplar";NA;70;0
"Unit";"Zealot";"Gateway";70;2
"Unit";"Zealot";"Gateway";70;2
"Building";"RoboticsFacility";NA;70;0
"Unit";"Zealot";"Gateway";74;2
"Unit";"Zealot";"Gateway";76;2
"Unit";"Zealot";"Gateway";76;2
"Unit";"Zealot";"Gateway";76;2
"Unit";"Zealot";"Gateway";76;2
"Building";"DarkTemplar";NA;84;0
"Building";"DarkTemplar";NA;84;0
"Building";"DarkTemplar";NA;84;0
"Building";"DarkTemplar";NA;84;0
"Building";"DarkTemplar";NA;84;0
"Unit";"Archon";"High Templar";84;0
"Unit";"Archon";"High Templar";84;0
"Unit";"Archon";"High Templar";84;0
"Building";"Pylon";NA;84;0
"Building";"Gateway";NA;84;0
"Building";"Gateway";NA;84;0
"Building";"Pylon";NA;84;0
"Unit";"Immortal";"Robotics Facility";84;4
"Building";"Forge";NA;84;0
"Building";"DarkTemplar";NA;90;0
"Building";"DarkTemplar";NA;90;0
"Building";"DarkTemplar";NA;90;0
"Unit";"Archon";"High Templar";92;0
"Unit";"Immortal";"Robotics Facility";84;4
"Building";"Nexus";NA;84;0
"Building";"ShieldBattery";NA;90;0
"Unit";"Immortal";"Robotics Facility";92;4
"Building";"RoboticsFacility";NA;92;0
"Building";"Assimilator";NA;96;0
"Building";"Assimilator";NA;96;0
"Building";"DarkTemplar";NA;102;0
"Building";"DarkTemplar";NA;102;0
"Unit";"Archon";"High Templar";102;0
"Building";"Gateway";NA;96;0
"Building";"Gateway";NA;96;0
"Building";"Gateway";NA;96;0
"Unit";"Immortal";"Robotics Facility";98;4
"Upgrade";"ProtossGroundWeaponsLevel1";"Forge";92;0
"Unit";"Immortal";"Robotics Facility";102;4
"Building";"Pylon";NA;104;0
"Building";"PhotonCannon";NA;104;0
"Building";"PhotonCannon";NA;104;0
"Building";"PhotonCannon";NA;104;0
"Unit";"Immortal";"Robotics Facility";109;4
"Building";"Pylon";NA;113;0
"Unit";"Immortal";"Robotics Facility";113;4
"Building";"Pylon";NA;113;0
"Unit";"Immortal";"Robotics Facility";113;4
"Building";"PhotonCannon";NA;121;0
"Building";"PhotonCannon";NA;121;0
"Building";"ShieldBattery";NA;121;0
"Building";"Nexus";NA;113;0
"Building";"PhotonCannon";NA;121;0
"Unit";"Observer";"Robotics Facility";121;1
"Unit";"Zealot";"Gateway";126;2
"Unit";"Zealot";"Gateway";126;2
"Unit";"Zealot";"Gateway";126;2
"Unit";"Zealot";"Gateway";126;2
"Unit";"Zealot";"Gateway";126;2
"Unit";"Zealot";"Gateway";126;2
"Unit";"Zealot";"Gateway";126;2
"Unit";"Immortal";"Robotics Facility";125;4
"Building";"DarkTemplar";NA;144;0
"Building";"DarkTemplar";NA;144;0
"Building";"DarkTemplar";NA;144;0
"Building";"DarkTemplar";NA;144;0
"Upgrade";"ProtossGroundWeaponsLevel2";"Forge";113;0
"Unit";"Immortal";"Robotics Facility";125;4
"Unit";"Archon";"High Templar";144;0
"Unit";"Archon";"High Templar";144;0
"Unit";"Zealot";"Gateway";148;2
"Unit";"Zealot";"Gateway";149;2
"Building";"Assimilator";NA;148;0
"Building";"Assimilator";NA;148;0
"Unit";"Immortal";"Robotics Facility";144;4
"Unit";"Zealot";"Gateway";154;2
"Unit";"Zealot";"Gateway";154;2
"Building";"DarkTemplar";NA;154;0
"Unit";"Immortal";"Robotics Facility";144;4
"Building";"TemplarArchive";NA;148;0
"Unit";"Observer";"Robotics Facility";154;1
"Building";"HighTemplar";NA;167;0
"Building";"HighTemplar";NA;167;0
"Building";"HighTemplar";NA;167;0
"Building";"HighTemplar";NA;167;0
"Building";"HighTemplar";NA;168;0
"Building";"HighTemplar";NA;168;0
"Building";"HighTemplar";NA;168;0
"Building";"HighTemplar";NA;169;0
"Building";"Pylon";NA;166;0
"Unit";"Zealot";"Gateway";171;2
"Unit";"Zealot";"Gateway";171;2
"Unit";"Immortal";"Robotics Facility";175;4
"Unit";"Zealot";"Gateway";179;2
"Unit";"Zealot";"Gateway";179;2
"Unit";"Zealot";"Gateway";179;2
"Unit";"Zealot";"Gateway";179;2
"Unit";"Immortal";"Robotics Facility";175;4
"Upgrade";"ProtossGroundWeaponsLevel3";"Forge";166;0
"Unit";"Zealot";"Gateway";191;2
"Unit";"Zealot";"Gateway";191;2
"Unit";"Zealot";"Gateway";191;2
"Unit";"Zealot";"Gateway";191;2
"Unit";"Zealot";"Gateway";191;2
"Unit";"Immortal";"Robotics Facility";175;4
"Building";"Nexus";NA;179;0
"Unit";"Zealot";"Gateway";205;2
"Building";"HighTemplar";NA;207;0
"Building";"HighTemplar";NA;207;0
"Building";"HighTemplar";NA;207;0
"Building";"PhotonCannon";NA;205;0
"Building";"Pylon";NA;209;0
"Building";"HighTemplar";NA;212;0
"Building";"HighTemplar";NA;212;0
"Building";"HighTemplar";NA;212;0
"Building";"HighTemplar";NA;212;0
"Building";"Nexus";NA;205;0
"Unit";"Zealot";"Gateway";212;2
"Building";"Pylon";NA;212;0
"Building";"Assimilator";NA;212;0
"Building";"HighTemplar";NA;214;0
"Building";"HighTemplar";NA;214;0
"Building";"HighTemplar";NA;214;0
"Building";"HighTemplar";NA;214;0
"Building";"HighTemplar";NA;214;0
"Unit";"Zealot";"Gateway";214;2
"Unit";"Zealot";"Gateway";214;2
"Building";"HighTemplar";NA;218;0
"Building";"HighTemplar";NA;218;0
"Building";"HighTemplar";NA;218;0
"Building";"HighTemplar";NA;218;0
"Building";"HighTemplar";NA;218;0
"Building";"Nexus";NA;214;0
"Unit";"Archon";"High Templar";218;0
"Unit";"Archon";"High Templar";218;0
"Unit";"Zealot";"Gateway";221;2
"Unit";"Zealot";"Gateway";221;2
"Unit";"Zealot";"Gateway";221;2
"Unit";"Zealot";"Gateway";221;2
"Unit";"Zealot";"Gateway";221;2
"Unit";"Zealot";"Gateway";221;2
"Unit";"Immortal";"Robotics Facility";218;4
"Unit";"Immortal";"Robotics Facility";218;4
"Unit";"Zealot";"Gateway";243;2
"Unit";"Zealot";"Gateway";243;2
"Unit";"Zealot";"Gateway";243;2
"Building";"HighTemplar";NA;249;0
"Building";"HighTemplar";NA;249;0
"Building";"HighTemplar";NA;249;0
"Unit";"Archon";"High Templar";249;0
"Building";"HighTemplar";NA;249;0
"Building";"HighTemplar";NA;249;0
"Building";"Pylon";NA;251;0
"Building";"HighTemplar";NA;251;0
"Unit";"Zealot";"Gateway";251;2
"Unit";"Immortal";"Robotics Facility";249;4
"Building";"Assimilator";NA;251;0
"Building";"Pylon";NA;257;0
"Unit";"Zealot";"Gateway";257;2
"Unit";"Zealot";"Gateway";257;2
"Unit";"Zealot";"Gateway";257;2
"Unit";"Zealot";"Gateway";263;2
"Building";"Nexus";NA;257;0
"Unit";"Zealot";"Gateway";265;2
"Unit";"Zealot";"Gateway";265;2
"Unit";"Zealot";"Gateway";265;2
"Unit";"Zealot";"Gateway";265;2
"Building";"HighTemplar";NA;273;0
"Unit";"Zealot";"Gateway";273;2
"Unit";"Zealot";"Gateway";273;2
"Unit";"Zealot";"Gateway";273;2
"Unit";"Zealot";"Gateway";273;2
"Building";"HighTemplar";NA;281;0
"Building";"PhotonCannon";NA;281;0
"Building";"Nexus";NA;281;0
"Unit";"Immortal";"Robotics Facility";281;4
"Unit";"Archon";"High Templar";284;0
"Unit";"Immortal";"Robotics Facility";283;4
"Unit";"Archon";"High Templar";284;0
"Unit";"Archon";"High Templar";284;0
"Building";"HighTemplar";NA;288;0
"Unit";"Zealot";"Gateway";292;2
"Unit";"Zealot";"Gateway";292;2
"Unit";"Zealot";"Gateway";292;2
"Building";"Assimilator";NA;292;0
"Building";"Assimilator";NA;292;0
"Building";"HighTemplar";NA;303;0
"Building";"HighTemplar";NA;303;0
"Building";"HighTemplar";NA;303;0
"Building";"HighTemplar";NA;312;0
"Building";"HighTemplar";NA;312;0
"Unit";"Zealot";"Gateway";312;2
"Unit";"Zealot";"Gateway";312;2
"Unit";"Zealot";"Gateway";312;2
"Building";"Pylon";NA;312;0
"Unit";"Archon";"High Templar";319;0
"Unit";"Archon";"High Templar";319;0
"Building";"HighTemplar";NA;319;0
"Unit";"Archon";"High Templar";319;0
"Unit";"Zealot";"Gateway";319;2
"Unit";"Zealot";"Gateway";319;2
"Unit";"Zealot";"Gateway";319;2
"Unit";"Immortal";"Robotics Facility";312;4
"Building";"HighTemplar";NA;329;0
"Unit";"Immortal";"Robotics Facility";319;4
"Building";"HighTemplar";NA;333;0
"Building";"HighTemplar";NA;333;0
"Building";"Pylon";NA;333;0
