"type";"unit_name";"on_building";"total_supply";"supply"
"Building";"Pylon";NA;14;0
"Building";"Assimilator";NA;15;0
"Building";"Gateway";NA;15;0
"Building";"Assimilator";NA;20;0
"Building";"Pylon";NA;21;0
"Building";"CyberneticsCore";NA;20;0
"Unit";"Adept";"Gateway";21;2
"Building";"Nexus";NA;20;0
"Unit";"Adept";"Gateway";23;2
"Building";"Stargate";NA;22;0
"Unit";"Adept";"Gateway";26;2
"Unit";"Oracle";"Stargate";30;3
"Building";"Gateway";NA;32;0
"Unit";"Oracle";"Stargate";36;3
"Building";"Pylon";NA;43;0
"Building";"Gateway";NA;41;0
"Building";"TwilightCouncil";NA;43;0
"Unit";"Phoenix";"Stargate";49;2
"Building";"Pylon";NA;50;0
"Unit";"Adept";"Gateway";56;2
"Unit";"Adept";"Gateway";56;2
"Unit";"Adept";"Gateway";60;2
"Building";"Assimilator";NA;56;0
"Unit";"Adept";"Gateway";64;2
"Building";"Assimilator";NA;60;0
"Building";"Gateway";NA;52;0
"Building";"Gateway";NA;53;0
"Building";"Pylon";NA;69;0
"Unit";"Adept";"Gateway";72;2
"Unit";"Adept";"Gateway";72;2
"Unit";"Adept";"Gateway";72;2
"Building";"Pylon";NA;72;0
"Building";"Pylon";NA;72;0
"Building";"OracleStasisTrap";NA;80;0
"Unit";"Adept";"Gateway";80;2
"Unit";"Adept";"Gateway";80;2
"Building";"Pylon";NA;80;0
"Unit";"Adept";"Gateway";86;2
"Unit";"Adept";"Gateway";86;2
"Building";"Forge";NA;72;0
"Building";"TemplarArchive";NA;72;0
"Unit";"Adept";"Gateway";90;2
"Building";"Nexus";NA;71;0
"Building";"RoboticsFacility";NA;84;0
"Building";"RoboticsFacility";NA;84;0
"Unit";"Zealot";"Gateway";99;2
"Unit";"Zealot";"Gateway";99;2
"Unit";"Zealot";"Gateway";99;2
"Unit";"Zealot";"Gateway";99;2
"Unit";"Zealot";"Gateway";99;2
"Unit";"Immortal";"Robotics Facility";97;4
"Unit";"Immortal";"Robotics Facility";97;4
"Building";"HighTemplar";NA;111;0
"Building";"HighTemplar";NA;111;0
"Building";"HighTemplar";NA;111;0
"Unit";"Zealot";"Gateway";119;2
"Unit";"Zealot";"Gateway";119;2
"Building";"ShieldBattery";NA;109;0
"Building";"ShieldBattery";NA;109;0
"Upgrade";"Charge";"TwilightCouncil";95;0
"Building";"Assimilator";NA;111;0
"Building";"Assimilator";NA;119;0
"Building";"Pylon";NA;123;0
"Building";"HighTemplar";NA;128;0
"Building";"HighTemplar";NA;128;0
"Building";"Pylon";NA;126;0
"Building";"Pylon";NA;126;0
"Building";"Pylon";NA;126;0
"Building";"HighTemplar";NA;132;0
"Building";"HighTemplar";NA;132;0
"Unit";"Zealot";"Gateway";132;2
"Building";"Pylon";NA;129;0
"Unit";"Archon";"High Templar";132;0
"Building";"HighTemplar";NA;136;0
"Building";"Gateway";NA;126;0
"Building";"HighTemplar";NA;136;0
"Unit";"Zealot";"Gateway";136;2
"Unit";"Archon";"High Templar";136;0
"Building";"Pylon";NA;136;0
"Building";"Gateway";NA;131;0
"Building";"Gateway";NA;131;0
"Upgrade";"ProtossGroundWeaponsLevel1";"Forge";123;0
"Building";"HighTemplar";NA;138;0
"Building";"HighTemplar";NA;138;0
"Unit";"Zealot";"Gateway";138;2
"Unit";"Zealot";"Gateway";138;2
"Unit";"Zealot";"Gateway";138;2
"Unit";"Immortal";"Robotics Facility";136;4
"Unit";"Archon";"High Templar";144;0
"Building";"PhotonCannon";NA;138;0
"Building";"PhotonCannon";NA;138;0
"Building";"Gateway";NA;138;0
"Unit";"Observer";"Robotics Facility";145;1
"Building";"Gateway";NA;138;0
"Building";"Nexus";NA;136;0
"Unit";"Zealot";"Gateway";150;2
"Unit";"Zealot";"Gateway";150;2
"Unit";"Zealot";"Gateway";150;2
"Unit";"Zealot";"Gateway";150;2
"Unit";"Zealot";"Gateway";150;2
"Unit";"Sentry";"Gateway";150;2
"Unit";"Sentry";"Gateway";150;2
"Unit";"Zealot";"Gateway";164;2
"Unit";"Immortal";"Robotics Facility";145;4
"Building";"Assimilator";NA;149;0
"Building";"Assimilator";NA;150;0
"Building";"Pylon";NA;164;0
"Unit";"Zealot";"Gateway";170;2
"Unit";"Zealot";"Gateway";170;2
"Unit";"Zealot";"Gateway";170;2
"Unit";"Zealot";"Gateway";170;2
"Unit";"Zealot";"Gateway";170;2
"Building";"HighTemplar";NA;170;0
"Building";"HighTemplar";NA;170;0
"Unit";"Zealot";"Gateway";170;2
"Building";"Forge";NA;150;0
"Building";"PhotonCannon";NA;164;0
"Unit";"Zealot";"Gateway";182;2
"Unit";"Zealot";"Gateway";182;2
"Unit";"Archon";"High Templar";182;0
"Unit";"Immortal";"Robotics Facility";164;4
"Unit";"Zealot";"Gateway";190;2
"Unit";"Zealot";"Gateway";190;2
"Unit";"Zealot";"Gateway";190;2
"Unit";"Zealot";"Gateway";190;2
"Unit";"Zealot";"Gateway";190;2
"Unit";"Zealot";"Gateway";190;2
"Unit";"Zealot";"Gateway";202;2
"Unit";"Zealot";"Gateway";202;2
"Unit";"Zealot";"Gateway";202;2
"Unit";"Zealot";"Gateway";202;2
"Upgrade";"ProtossGroundWeaponsLevel2";"Forge";149;0
"Building";"HighTemplar";NA;210;0
"Building";"HighTemplar";NA;210;0
"Building";"HighTemplar";NA;210;0
"Building";"HighTemplar";NA;210;0
"Unit";"Zealot";"Gateway";210;2
"Unit";"Zealot";"Gateway";210;2
"Unit";"Zealot";"Gateway";214;2
"Unit";"Zealot";"Gateway";214;2
"Unit";"Zealot";"Gateway";214;2
"Unit";"Zealot";"Gateway";214;2
"Unit";"Archon";"High Templar";214;0
"Unit";"Archon";"High Templar";214;0
"Unit";"Immortal";"Robotics Facility";202;4
"Unit";"Immortal";"Robotics Facility";210;4
"Unit";"Zealot";"Gateway";229;2
"Unit";"Zealot";"Gateway";229;2
"Building";"PhotonCannon";NA;223;0
"Building";"PhotonCannon";NA;223;0
"Building";"Pylon";NA;237;0
"Building";"Pylon";NA;238;0
"Unit";"Zealot";"Gateway";238;2
"Unit";"Zealot";"Gateway";238;2
"Unit";"Zealot";"Gateway";238;2
"Building";"FleetBeacon";NA;224;0
"Unit";"Zealot";"Gateway";238;2
"Unit";"Zealot";"Gateway";238;2
"Unit";"Zealot";"Gateway";238;2
"Upgrade";"ProtossGroundArmorsLevel1";"Forge";210;0
"Unit";"Phoenix";"Stargate";238;2
"Unit";"Immortal";"Robotics Facility";238;4
"Building";"Stargate";NA;238;0
"Building";"Stargate";NA;238;0
"Unit";"Observer";"Robotics Facility";252;1
"Building";"HighTemplar";NA;260;0
"Building";"HighTemplar";NA;260;0
"Building";"HighTemplar";NA;260;0
"Building";"HighTemplar";NA;260;0
"Unit";"Zealot";"Gateway";260;2
"Unit";"Zealot";"Gateway";260;2
"Unit";"Zealot";"Gateway";260;2
"Unit";"Zealot";"Gateway";260;2
"Unit";"Carrier";"Stargate";250;6
"Building";"Pylon";NA;260;0
"Unit";"Carrier";"Stargate";250;6
"Building";"HighTemplar";NA;268;0
"Building";"HighTemplar";NA;268;0
"Building";"Pylon";NA;260;0
"Unit";"Carrier";"Stargate";257;6
"Unit";"Sentry";"Gateway";286;2
"Unit";"Archon";"High Templar";286;0
"Building";"HighTemplar";NA;288;0
"Building";"HighTemplar";NA;288;0
"Building";"HighTemplar";NA;288;0
"Building";"HighTemplar";NA;288;0
"Unit";"Sentry";"Gateway";288;2
"Unit";"Archon";"High Templar";288;0
"Upgrade";"ProtossGroundWeaponsLevel3";"Forge";258;0
"Building";"Pylon";NA;290;0
"Building";"HighTemplar";NA;291;0
"Building";"HighTemplar";NA;291;0
"Unit";"Zealot";"Gateway";291;2
"Unit";"Zealot";"Gateway";291;2
"Unit";"Observer";"Robotics Facility";290;1
"Unit";"Carrier";"Stargate";268;6
"Unit";"Archon";"High Templar";293;0
"Unit";"Archon";"High Templar";295;0
"Unit";"Carrier";"Stargate";268;6
"Unit";"Oracle";"Stargate";290;3
"Building";"HighTemplar";NA;311;0
"Building";"HighTemplar";NA;311;0
"Building";"Nexus";NA;286;0
"Unit";"Archon";"High Templar";311;0
"Building";"Assimilator";NA;308;0
"Building";"Pylon";NA;311;0
"Unit";"Stalker";"Gateway";311;2
"Unit";"Zealot";"Gateway";311;2
"Unit";"Zealot";"Gateway";311;2
"Building";"Pylon";NA;311;0
"Building";"HighTemplar";NA;313;0
"Building";"HighTemplar";NA;317;0
"Building";"Assimilator";NA;311;0
"Unit";"Zealot";"Gateway";317;2
"Upgrade";"ProtossAirWeaponsLevel1";"CyberneticsCore";290;0
"Building";"HighTemplar";NA;319;0
"Building";"HighTemplar";NA;319;0
"Building";"HighTemplar";NA;319;0
"Unit";"Zealot";"Gateway";319;2
"Unit";"Zealot";"Gateway";319;2
"Unit";"Zealot";"Gateway";319;2
"Unit";"Zealot";"Gateway";319;2
"Unit";"Zealot";"Gateway";319;2
"Building";"HighTemplar";NA;319;0
"Unit";"Archon";"High Templar";329;0
"Unit";"Archon";"High Templar";329;0
"Upgrade";"ProtossShieldsLevel1";"Forge";311;0
"Unit";"Zealot";"Gateway";329;2
"Unit";"Zealot";"Gateway";329;2
"Unit";"Zealot";"Gateway";329;2
"Unit";"Zealot";"Gateway";329;2
"Upgrade";"ProtossGroundArmorsLevel2";"Forge";308;0
"Unit";"Zealot";"Gateway";337;2
"Unit";"Zealot";"Gateway";337;2
"Unit";"Zealot";"Gateway";337;2
