"type";"unit_name";"on_building";"total_supply_lag";"supply"
"Unit";"Overlord";"Larva";13;0
"Building";"Extractor";NA;17;0
"Building";"SpawningPool";NA;18;0
"Building";"Hatchery";NA;20;0
"Unit";"Queen";"Hatchery";22;2
"Unit";"Zergling";"Larva";24;1
"Unit";"Zergling";"Larva";25;1
"Building";"SpineCrawler";NA;26;0
"Unit";"Zergling";"Larva";26;1
"Unit";"Zergling";"Larva";27;1
"Unit";"Zergling";"Larva";28;1
"Unit";"Zergling";"Larva";29;1
"Unit";"Zergling";"Larva";30;1
"Unit";"Zergling";"Larva";31;1
"Unit";"Zergling";"Larva";32;1
"Unit";"Zergling";"Larva";33;1
"Unit";"Zergling";"Larva";34;1
"Unit";"Zergling";"Larva";35;1
"Building";"SpineCrawler";NA;36;0
"Unit";"Queen";"Hatchery";36;2
"Building";"SpineCrawler";NA;39;0
"Unit";"Overlord";"Larva";41;0
"Building";"CreepTumorQueen";NA;43;0
"Unit";"Overlord";"Larva";47;0
"Unit";"Overlord";"Larva";49;0
"Building";"CreepTumor";NA;52;0
"Building";"Hatchery";NA;56;0
"Building";"RoachWarren";NA;56;0
"Building";"CreepTumor";NA;61;0
"Unit";"Overlord";"Larva";61;0
"Building";"Extractor";NA;63;0
"Unit";"Queen";"Hatchery";63;2
"Unit";"Overlord";"Larva";65;0
"Unit";"Overlord";"Larva";65;0
"Building";"CreepTumor";NA;65;0
"Building";"Extractor";NA;70;0
"Building";"EvolutionChamber";NA;71;0
"Building";"EvolutionChamber";NA;72;0
"Building";"CreepTumor";NA;73;0
"Unit";"Overlord";"Larva";82;0
"Building";"SporeCrawler";NA;82;0
"Building";"SporeCrawler";NA;82;0
"Building";"SporeCrawler";NA;83;0
"Unit";"Queen";"Hatchery";91;2
"Building";"CreepTumor";NA;98;0
"Building";"Extractor";NA;98;0
"Building";"Extractor";NA;98;0
"Building";"InfestationPit";NA;99;0
"Unit";"Overlord";"Larva";99;0
"Unit";"Queen";"Hatchery";102;2
"Building";"Extractor";NA;105;0
"Upgrade";"GlialReconstitution";"RoachWarren";106;0
"Unit";"Overlord";"Larva";112;0
"Unit";"Overlord";"Larva";112;0
"Unit";"Roach";"Larva";112;2
"Unit";"Roach";"Larva";114;2
"Unit";"Roach";"Larva";116;2
"Unit";"Roach";"Larva";118;2
"Unit";"Overlord";"Larva";120;0
"Upgrade";"Burrow";"Hatchery";120;0
"Unit";"Queen";"Hatchery";120;2
"Unit";"Roach";"Larva";122;2
"Unit";"Roach";"Larva";124;2
"Unit";"Roach";"Larva";126;2
"Unit";"Roach";"Larva";128;2
"Unit";"Roach";"Larva";130;2
"Building";"SporeCrawler";NA;132;0
"Building";"SporeCrawler";NA;132;0
"Unit";"Infestor";"Larva";132;2
"Unit";"Infestor";"Larva";134;2
"Unit";"Infestor";"Larva";136;2
"Building";"CreepTumorQueen";NA;138;0
"Unit";"Roach";"Larva";138;2
"Unit";"Roach";"Larva";140;2
"Unit";"Roach";"Larva";142;2
"Unit";"Roach";"Larva";144;2
"Unit";"Roach";"Larva";146;2
"Unit";"Overlord";"Larva";148;0
"Unit";"Overlord";"Larva";148;0
"Unit";"Overlord";"Larva";148;0
"Building";"Hatchery";NA;148;0
"Building";"CreepTumor";NA;148;0
"Building";"CreepTumorQueen";NA;148;0
"Unit";"Queen";"Hatchery";148;2
"Unit";"Zergling";"Larva";150;1
"Unit";"Zergling";"Larva";151;1
"Unit";"Zergling";"Larva";152;1
"Unit";"Zergling";"Larva";153;1
"Unit";"Zergling";"Larva";154;1
"Unit";"Zergling";"Larva";155;1
"Unit";"Zergling";"Larva";156;1
"Unit";"Zergling";"Larva";157;1
"Unit";"Zergling";"Larva";158;1
"Unit";"Zergling";"Larva";159;1
"Unit";"Zergling";"Larva";160;1
"Unit";"Zergling";"Larva";161;1
"Unit";"Zergling";"Larva";162;1
"Unit";"Zergling";"Larva";163;1
"Unit";"Zergling";"Larva";164;1
"Unit";"Zergling";"Larva";165;1
"Building";"Hatchery";NA;167;0
"Unit";"Overlord";"Larva";168;0
"Building";"UltraliskCavern";NA;168;0
"Unit";"Overlord";"Larva";168;0
"Unit";"Overlord";"Larva";168;0
"Unit";"Overlord";"Larva";168;0
"Unit";"Overlord";"Larva";168;0
"Unit";"Overlord";"Larva";168;0
"Unit";"Queen";"Hatchery";168;2
"Building";"CreepTumor";NA;170;0
"Building";"CreepTumorQueen";NA;170;0
"Unit";"Overlord";"Larva";170;0
"Unit";"Overlord";"Larva";170;0
"Unit";"Overlord";"Larva";170;0
"Unit";"Overlord";"Larva";170;0
"Building";"CreepTumorQueen";NA;170;0
"Building";"CreepTumorQueen";NA;170;0
"Building";"CreepTumorQueen";NA;175;0
"Building";"CreepTumorQueen";NA;175;0
"Unit";"Zergling";"Larva";175;1
"Unit";"Zergling";"Larva";176;1
"Unit";"Zergling";"Larva";177;1
"Unit";"Zergling";"Larva";178;1
"Unit";"Zergling";"Larva";179;1
"Unit";"Zergling";"Larva";180;1
"Unit";"Zergling";"Larva";181;1
"Unit";"Zergling";"Larva";182;1
"Unit";"Zergling";"Larva";183;1
"Unit";"Zergling";"Larva";184;1
"Unit";"Zergling";"Larva";185;1
"Unit";"Zergling";"Larva";186;1
"Unit";"Zergling";"Larva";187;1
"Unit";"Zergling";"Larva";188;1
"Unit";"Zergling";"Larva";189;1
"Unit";"Zergling";"Larva";190;1
"Building";"Extractor";NA;191;0
"Building";"Extractor";NA;191;0
"Unit";"Zergling";"Larva";191;1
"Unit";"Zergling";"Larva";192;1
"Unit";"Zergling";"Larva";193;1
"Unit";"Zergling";"Larva";194;1
"Unit";"Zergling";"Larva";195;1
"Unit";"Zergling";"Larva";196;1
"Unit";"Ultralisk";"Larva";197;6
"Unit";"Ultralisk";"Larva";203;6
"Building";"CreepTumor";NA;209;0
"Building";"CreepTumor";NA;209;0
"Building";"CreepTumor";NA;209;0
"Building";"CreepTumor";NA;209;0
"Building";"CreepTumorQueen";NA;214;0
"Unit";"Ultralisk";"Larva";214;6
"Unit";"Zergling";"Larva";220;1
"Unit";"Zergling";"Larva";221;1
"Upgrade";"ChitinousPlating";"UltraliskCavern";222;0
"Unit";"Zergling";"Larva";222;1
"Unit";"Zergling";"Larva";223;1
"Unit";"Zergling";"Larva";224;1
"Unit";"Zergling";"Larva";225;1
"Unit";"Zergling";"Larva";226;1
"Unit";"Zergling";"Larva";227;1
"Unit";"Zergling";"Larva";228;1
"Unit";"Zergling";"Larva";229;1
"Unit";"Ultralisk";"Larva";230;6
"Building";"CreepTumor";NA;236;0
"Building";"CreepTumor";NA;236;0
"Building";"CreepTumor";NA;236;0
"Unit";"Zergling";"Larva";236;1
"Unit";"Zergling";"Larva";237;1
"Unit";"Zergling";"Larva";238;1
"Unit";"Zergling";"Larva";239;1
"Unit";"Zergling";"Larva";240;1
"Unit";"Zergling";"Larva";241;1
"Unit";"Zergling";"Larva";242;1
"Unit";"Zergling";"Larva";243;1
"Unit";"Zergling";"Larva";244;1
"Unit";"Zergling";"Larva";245;1
"Unit";"Zergling";"Larva";246;1
"Unit";"Zergling";"Larva";247;1
"Unit";"Zergling";"Larva";248;1
"Unit";"Zergling";"Larva";249;1
"Unit";"Zergling";"Larva";250;1
"Unit";"Zergling";"Larva";251;1
"Unit";"Zergling";"Larva";252;1
"Unit";"Zergling";"Larva";253;1
"Unit";"Zergling";"Larva";254;1
"Unit";"Zergling";"Larva";255;1
"Unit";"Zergling";"Larva";256;1
"Unit";"Zergling";"Larva";257;1
"Unit";"Zergling";"Larva";258;1
"Unit";"Zergling";"Larva";259;1
"Unit";"Zergling";"Larva";260;1
"Unit";"Zergling";"Larva";261;1
"Unit";"Zergling";"Larva";262;1
"Unit";"Zergling";"Larva";263;1
"Building";"CreepTumor";NA;264;0
"Building";"CreepTumorQueen";NA;264;0
"Building";"CreepTumorQueen";NA;264;0
"Building";"CreepTumorQueen";NA;264;0
"Unit";"Ultralisk";"Larva";265;6
"Unit";"Ultralisk";"Larva";271;6
"Unit";"Zergling";"Larva";277;1
"Unit";"Zergling";"Larva";278;1
"Unit";"Zergling";"Larva";279;1
"Unit";"Zergling";"Larva";280;1
"Unit";"Zergling";"Larva";281;1
"Unit";"Zergling";"Larva";282;1
"Unit";"Zergling";"Larva";283;1
"Unit";"Zergling";"Larva";284;1
"Unit";"Zergling";"Larva";285;1
"Unit";"Zergling";"Larva";286;1
"Unit";"Zergling";"Larva";287;1
"Unit";"Zergling";"Larva";288;1
"Unit";"Zergling";"Larva";289;1
"Unit";"Zergling";"Larva";290;1
"Building";"CreepTumor";NA;291;0
"Building";"CreepTumor";NA;291;0
"Building";"CreepTumor";NA;291;0
"Building";"Hatchery";NA;291;0
"Unit";"Queen";"Hatchery";291;2
"Building";"CreepTumor";NA;293;0
"Building";"CreepTumor";NA;293;0
"Building";"CreepTumor";NA;293;0
"Building";"CreepTumor";NA;293;0
"Building";"CreepTumorQueen";NA;293;0
"Building";"CreepTumorQueen";NA;293;0
"Building";"CreepTumor";NA;293;0
"Building";"CreepTumor";NA;293;0
"Building";"CreepTumor";NA;293;0
"Unit";"Ultralisk";"Larva";293;6
"Unit";"Ultralisk";"Larva";299;6
"Unit";"Ultralisk";"Larva";305;6
"Unit";"Ultralisk";"Larva";311;6
"Unit";"Ultralisk";"Larva";317;6
"Building";"Spire";NA;323;0
"Building";"Spire";NA;323;0
"Building";"CreepTumor";NA;323;0
"Building";"CreepTumor";NA;323;0
"Unit";"Ultralisk";"Larva";323;6
"Unit";"Ultralisk";"Larva";329;6
"Unit";"Ultralisk";"Larva";335;6
"Building";"CreepTumor";NA;341;0
"Building";"CreepTumor";NA;341;0
"Building";"CreepTumor";NA;341;0
"Building";"CreepTumor";NA;341;0
"Building";"CreepTumor";NA;341;0
"Building";"CreepTumor";NA;341;0
"Unit";"Queen";"Hatchery";342;2
"Unit";"Zergling";"Larva";348;1
"Unit";"Zergling";"Larva";349;1
"Unit";"Zergling";"Larva";350;1
"Unit";"Zergling";"Larva";351;1
"Unit";"Zergling";"Larva";352;1
"Unit";"Zergling";"Larva";353;1
"Unit";"Zergling";"Larva";354;1
"Unit";"Zergling";"Larva";355;1
"Unit";"Zergling";"Larva";356;1
"Unit";"Zergling";"Larva";357;1
"Unit";"Zergling";"Larva";358;1
"Unit";"Zergling";"Larva";359;1
"Unit";"Zergling";"Larva";360;1
"Unit";"Zergling";"Larva";361;1
"Building";"Hatchery";NA;362;0
"Unit";"Infestor";"Larva";362;2
"Building";"Extractor";NA;364;0
"Building";"Hatchery";NA;364;0
"Unit";"Infestor";"Larva";364;2
"Unit";"Infestor";"Larva";366;2
"Unit";"Infestor";"Larva";368;2
"Building";"CreepTumor";NA;370;0
"Building";"CreepTumor";NA;370;0
"Building";"CreepTumor";NA;370;0
"Building";"CreepTumor";NA;370;0
"Building";"CreepTumor";NA;370;0
"Building";"CreepTumor";NA;370;0
"Building";"CreepTumor";NA;370;0
"Building";"CreepTumorQueen";NA;370;0
"Building";"CreepTumorQueen";NA;370;0
"Building";"CreepTumorQueen";NA;370;0
"Building";"CreepTumorQueen";NA;370;0
"Building";"CreepTumor";NA;370;0
"Building";"CreepTumor";NA;370;0
"Building";"CreepTumor";NA;370;0
"Building";"CreepTumor";NA;370;0
"Building";"CreepTumor";NA;370;0
"Building";"CreepTumor";NA;370;0
"Building";"CreepTumor";NA;370;0
"Building";"CreepTumor";NA;370;0
"Building";"CreepTumor";NA;370;0
"Building";"CreepTumor";NA;370;0
"Building";"CreepTumor";NA;370;0
"Unit";"Ultralisk";"Larva";370;6
"Unit";"Ultralisk";"Larva";376;6
"Unit";"Ultralisk";"Larva";382;6
"Unit";"Ultralisk";"Larva";388;6
"Unit";"Ultralisk";"Larva";394;6
"Unit";"Ultralisk";"Larva";400;6
"Unit";"Ultralisk";"Larva";406;6
"Building";"CreepTumor";NA;412;0
"Unit";"Infestor";"Larva";412;2
"Unit";"Infestor";"Larva";414;2
"Unit";"Infestor";"Larva";416;2
"Building";"CreepTumor";NA;418;0
"Building";"CreepTumor";NA;418;0
"Building";"CreepTumor";NA;418;0
"Building";"CreepTumor";NA;418;0
"Building";"CreepTumor";NA;418;0
"Building";"CreepTumorQueen";NA;418;0
"Unit";"Corruptor";"Larva";418;2
"Unit";"Corruptor";"Larva";420;2
"Unit";"Corruptor";"Larva";422;2
"Unit";"Corruptor";"Larva";424;2
"Unit";"Corruptor";"Larva";426;2
"Unit";"Corruptor";"Larva";428;2
"Unit";"Corruptor";"Larva";430;2
"Unit";"Corruptor";"Larva";432;2
"Unit";"Corruptor";"Larva";434;2
"Unit";"Corruptor";"Larva";436;2
"Unit";"Corruptor";"Larva";438;2
"Unit";"Corruptor";"Larva";440;2
"Unit";"Corruptor";"Larva";442;2
"Unit";"Corruptor";"Larva";444;2
"Unit";"Corruptor";"Larva";446;2
"Unit";"Corruptor";"Larva";448;2
"Unit";"Zergling";"Larva";450;1
"Unit";"Zergling";"Larva";451;1
"Unit";"Zergling";"Larva";452;1
"Unit";"Zergling";"Larva";453;1
"Unit";"Zergling";"Larva";454;1
"Unit";"Zergling";"Larva";455;1
"Unit";"Zergling";"Larva";456;1
"Unit";"Zergling";"Larva";457;1
"Unit";"Zergling";"Larva";458;1
"Unit";"Zergling";"Larva";459;1
"Unit";"Zergling";"Larva";460;1
"Unit";"Zergling";"Larva";461;1
"Unit";"Zergling";"Larva";462;1
"Unit";"Zergling";"Larva";463;1
"Unit";"Zergling";"Larva";464;1
"Unit";"Zergling";"Larva";465;1
"Unit";"Zergling";"Larva";466;1
"Unit";"Zergling";"Larva";467;1
"Unit";"Zergling";"Larva";468;1
"Unit";"Zergling";"Larva";469;1
"Unit";"Zergling";"Larva";470;1
"Unit";"Zergling";"Larva";471;1
"Unit";"Zergling";"Larva";472;1
"Unit";"Zergling";"Larva";473;1
"Unit";"Zergling";"Larva";474;1
"Unit";"Zergling";"Larva";475;1
"Upgrade";"SprayZerg";NA;476;0
"Upgrade";"SprayZerg";NA;476;0
"Upgrade";"zerglingmovementspeed";NA;476;0
"Upgrade";"SprayZerg";NA;476;0
"Upgrade";"SprayZerg";NA;476;0
"Upgrade";"ZergMeleeWeaponsLevel1";NA;476;0
"Upgrade";"ZergGroundArmorsLevel1";NA;476;0
"Upgrade";"SprayZerg";NA;476;0
"Upgrade";"SprayZerg";NA;476;0
"Upgrade";"SprayZerg";NA;476;0
"Upgrade";"SprayZerg";NA;476;0
"Upgrade";"SprayZerg";NA;476;0
"Upgrade";"ZergMeleeWeaponsLevel2";NA;476;0
"Upgrade";"overlordspeed";NA;476;0
"Upgrade";"ZergGroundArmorsLevel2";NA;476;0
"Upgrade";"zerglingattackspeed";NA;476;0
"Upgrade";"SprayZerg";NA;476;0
"Upgrade";"InfestorEnergyUpgrade";NA;476;0
"Upgrade";"SprayZerg";NA;476;0
"Upgrade";"SprayZerg";NA;476;0
"Upgrade";"SprayZerg";NA;476;0
"Upgrade";"ZergMeleeWeaponsLevel3";NA;476;0
"Upgrade";"ZergGroundArmorsLevel3";NA;476;0
"Upgrade";"SprayZerg";NA;476;0
"Upgrade";"SprayZerg";NA;476;0
"Upgrade";"ZergMissileWeaponsLevel1";NA;476;0
"Upgrade";"ZergFlyerArmorsLevel1";NA;476;0
"Upgrade";"ZergFlyerWeaponsLevel1";NA;476;0
