"type";"unit_name";"on_building";"total_supply_lag";"supply"
"Unit";"Overlord";"Larva";13;0
"Building";"Hatchery";NA;17;0
"Building";"Extractor";NA;19;0
"Building";"SpawningPool";NA;19;0
"Unit";"Overlord";"Larva";23;0
"Unit";"Queen";"Hatchery";23;2
"Unit";"Queen";"Hatchery";25;2
"Unit";"Zergling";"Larva";27;1
"Unit";"Zergling";"Larva";28;1
"Unit";"Zergling";"Larva";29;1
"Unit";"Zergling";"Larva";30;1
"Building";"Hatchery";NA;36;0
"Unit";"Queen";"Hatchery";38;2
"Unit";"Overlord";"Larva";40;0
"Unit";"Overlord";"Larva";42;0
"Building";"CreepTumorQueen";NA;44;0
"Unit";"Zergling";"Larva";49;1
"Unit";"Zergling";"Larva";50;1
"Unit";"Zergling";"Larva";51;1
"Unit";"Zergling";"Larva";52;1
"Unit";"Queen";"Hatchery";55;2
"Building";"CreepTumor";NA;57;0
"Unit";"Overlord";"Larva";60;0
"Unit";"Queen";"Hatchery";64;2
"Building";"CreepTumor";NA;66;0
"Building";"SporeCrawler";NA;66;0
"Unit";"Overlord";"Larva";66;0
"Building";"SpineCrawler";NA;68;0
"Unit";"Zergling";"Larva";68;1
"Unit";"Zergling";"Larva";69;1
"Unit";"Zergling";"Larva";70;1
"Unit";"Zergling";"Larva";71;1
"Unit";"Zergling";"Larva";72;1
"Unit";"Zergling";"Larva";73;1
"Unit";"Overlord";"Larva";74;0
"Unit";"Overlord";"Larva";77;0
"Unit";"Queen";"Hatchery";80;2
"Unit";"Queen";"Hatchery";84;2
"Building";"SporeCrawler";NA;86;0
"Building";"CreepTumorQueen";NA;88;0
"Building";"CreepTumorQueen";NA;88;0
"Building";"EvolutionChamber";NA;88;0
"Unit";"Zergling";"Larva";88;1
"Unit";"Zergling";"Larva";89;1
"Building";"EvolutionChamber";NA;90;0
"Unit";"Queen";"Hatchery";90;2
"Building";"Extractor";NA;92;0
"Unit";"Overlord";"Larva";92;0
"Building";"BanelingNest";NA;92;0
"Unit";"Overlord";"Larva";93;0
"Building";"CreepTumor";NA;93;0
"Building";"CreepTumor";NA;93;0
"Unit";"Overlord";"Larva";93;0
"Unit";"Overlord";"Larva";93;0
"Unit";"Overlord";"Larva";93;0
"Building";"Extractor";NA;101;0
"Building";"Extractor";NA;101;0
"Building";"Extractor";NA;101;0
"Building";"Spire";NA;108;0
"Building";"Extractor";NA;112;0
"Building";"CreepTumor";NA;120;0
"Building";"CreepTumor";NA;120;0
"Unit";"Overlord";"Larva";121;0
"Building";"HydraliskDen";NA;121;0
"Unit";"Overlord";"Larva";121;0
"Unit";"Baneling";"Zergling";123;0
"Unit";"Baneling";"Zergling";123;0
"Unit";"Baneling";"Zergling";123;0
"Unit";"Baneling";"Zergling";123;0
"Unit";"Baneling";"Zergling";123;0
"Unit";"Baneling";"Zergling";123;0
"Unit";"Zergling";"Larva";123;1
"Unit";"Zergling";"Larva";124;1
"Unit";"Zergling";"Larva";125;1
"Unit";"Zergling";"Larva";126;1
"Unit";"Zergling";"Larva";127;1
"Unit";"Zergling";"Larva";128;1
"Unit";"Zergling";"Larva";129;1
"Unit";"Zergling";"Larva";130;1
"Unit";"Zergling";"Larva";131;1
"Unit";"Zergling";"Larva";132;1
"Unit";"Zergling";"Larva";133;1
"Unit";"Zergling";"Larva";134;1
"Unit";"Zergling";"Larva";135;1
"Unit";"Zergling";"Larva";136;1
"Unit";"Zergling";"Larva";137;1
"Unit";"Zergling";"Larva";138;1
"Unit";"Zergling";"Larva";139;1
"Unit";"Zergling";"Larva";140;1
"Building";"CreepTumorQueen";NA;148;0
"Building";"CreepTumorQueen";NA;149;0
"Unit";"Baneling";"Zergling";151;0
"Unit";"Baneling";"Zergling";151;0
"Unit";"Baneling";"Zergling";151;0
"Unit";"Baneling";"Zergling";151;0
"Building";"CreepTumorQueen";NA;156;0
"Building";"CreepTumorQueen";NA;158;0
"Unit";"Overlord";"Larva";158;0
"Building";"CreepTumorQueen";NA;158;0
"Unit";"Mutalisk";"Larva";158;2
"Unit";"Mutalisk";"Larva";160;2
"Unit";"Overlord";"Larva";162;0
"Building";"CreepTumor";NA;162;0
"Building";"CreepTumor";NA;162;0
"Unit";"Overlord";"Larva";162;0
"Building";"CreepTumor";NA;162;0
"Building";"CreepTumorQueen";NA;162;0
"Building";"CreepTumorQueen";NA;162;0
"Unit";"Overlord";"Larva";162;0
"Building";"CreepTumorQueen";NA;162;0
"Building";"CreepTumorQueen";NA;162;0
"Building";"Hatchery";NA;162;0
"Unit";"Overlord";"Larva";162;0
"Unit";"Overlord";"Larva";162;0
"Building";"CreepTumorQueen";NA;162;0
"Unit";"Hydralisk";"Larva";162;2
"Unit";"Hydralisk";"Larva";164;2
"Unit";"Hydralisk";"Larva";166;2
"Unit";"Hydralisk";"Larva";168;2
"Unit";"Hydralisk";"Larva";170;2
"Unit";"Hydralisk";"Larva";172;2
"Unit";"Hydralisk";"Larva";174;2
"Unit";"Hydralisk";"Larva";176;2
"Building";"CreepTumor";NA;178;0
"Building";"CreepTumor";NA;178;0
"Building";"CreepTumor";NA;178;0
"Building";"CreepTumor";NA;178;0
"Building";"CreepTumor";NA;178;0
"Building";"CreepTumor";NA;178;0
"Building";"CreepTumorQueen";NA;178;0
"Building";"CreepTumor";NA;178;0
"Building";"CreepTumor";NA;178;0
"Building";"CreepTumorQueen";NA;178;0
"Unit";"Hydralisk";"Larva";178;2
"Unit";"Hydralisk";"Larva";180;2
"Building";"CreepTumorQueen";NA;182;0
"Building";"CreepTumorQueen";NA;182;0
"Unit";"Overlord";"Larva";182;0
"Building";"CreepTumorQueen";NA;182;0
"Unit";"Hydralisk";"Larva";182;2
"Unit";"Hydralisk";"Larva";184;2
"Unit";"Hydralisk";"Larva";186;2
"Unit";"Zergling";"Larva";197;1
"Unit";"Zergling";"Larva";198;1
"Unit";"Zergling";"Larva";199;1
"Unit";"Zergling";"Larva";200;1
"Unit";"Zergling";"Larva";201;1
"Unit";"Zergling";"Larva";202;1
"Unit";"Baneling";"Zergling";203;0
"Unit";"Baneling";"Zergling";203;0
"Unit";"Baneling";"Zergling";203;0
"Building";"CreepTumor";NA;203;0
"Building";"CreepTumor";NA;203;0
"Building";"CreepTumor";NA;203;0
"Building";"CreepTumor";NA;203;0
"Unit";"Zergling";"Larva";203;1
"Unit";"Zergling";"Larva";204;1
"Unit";"Zergling";"Larva";205;1
"Unit";"Zergling";"Larva";206;1
"Unit";"Zergling";"Larva";207;1
"Unit";"Zergling";"Larva";208;1
"Unit";"Zergling";"Larva";209;1
"Unit";"Zergling";"Larva";210;1
"Unit";"Zergling";"Larva";211;1
"Unit";"Zergling";"Larva";212;1
"Unit";"Baneling";"Zergling";213;0
"Unit";"Baneling";"Zergling";213;0
"Unit";"Baneling";"Zergling";213;0
"Unit";"Baneling";"Zergling";213;0
"Unit";"Baneling";"Zergling";213;0
"Unit";"Zergling";"Larva";213;1
"Unit";"Zergling";"Larva";214;1
"Unit";"Zergling";"Larva";215;1
"Unit";"Zergling";"Larva";216;1
"Unit";"Zergling";"Larva";217;1
"Unit";"Zergling";"Larva";218;1
"Unit";"Zergling";"Larva";219;1
"Unit";"Zergling";"Larva";220;1
"Unit";"Zergling";"Larva";221;1
"Unit";"Zergling";"Larva";222;1
"Unit";"Zergling";"Larva";223;1
"Unit";"Zergling";"Larva";224;1
"Unit";"Zergling";"Larva";225;1
"Unit";"Zergling";"Larva";226;1
"Unit";"Zergling";"Larva";227;1
"Unit";"Zergling";"Larva";228;1
"Unit";"Zergling";"Larva";229;1
"Unit";"Zergling";"Larva";230;1
"Unit";"Zergling";"Larva";231;1
"Unit";"Zergling";"Larva";232;1
"Unit";"Zergling";"Larva";233;1
"Unit";"Zergling";"Larva";234;1
"Unit";"Zergling";"Larva";235;1
"Unit";"Zergling";"Larva";236;1
"Unit";"Baneling";"Zergling";237;0
"Unit";"Baneling";"Zergling";237;0
"Unit";"Baneling";"Zergling";237;0
"Unit";"Baneling";"Zergling";237;0
"Unit";"Baneling";"Zergling";237;0
"Unit";"Baneling";"Zergling";237;0
"Unit";"Zergling";"Larva";237;1
"Unit";"Zergling";"Larva";238;1
"Unit";"Zergling";"Larva";239;1
"Unit";"Zergling";"Larva";240;1
"Unit";"Zergling";"Larva";241;1
"Unit";"Zergling";"Larva";242;1
"Unit";"Zergling";"Larva";243;1
"Unit";"Zergling";"Larva";244;1
"Unit";"Zergling";"Larva";245;1
"Unit";"Zergling";"Larva";246;1
"Unit";"Zergling";"Larva";247;1
"Unit";"Zergling";"Larva";248;1
"Building";"CreepTumorQueen";NA;249;0
"Building";"CreepTumorQueen";NA;249;0
"Unit";"Zergling";"Larva";249;1
"Unit";"Zergling";"Larva";250;1
"Building";"InfestationPit";NA;251;0
"Unit";"Zergling";"Larva";251;1
"Unit";"Zergling";"Larva";252;1
"Unit";"Zergling";"Larva";253;1
"Unit";"Zergling";"Larva";254;1
"Unit";"Zergling";"Larva";255;1
"Unit";"Zergling";"Larva";256;1
"Unit";"Zergling";"Larva";257;1
"Unit";"Zergling";"Larva";258;1
"Unit";"Zergling";"Larva";259;1
"Unit";"Zergling";"Larva";260;1
"Unit";"Zergling";"Larva";261;1
"Unit";"Zergling";"Larva";262;1
"Unit";"Zergling";"Larva";263;1
"Unit";"Zergling";"Larva";264;1
"Unit";"Zergling";"Larva";265;1
"Unit";"Zergling";"Larva";266;1
"Unit";"Baneling";"Zergling";267;0
"Unit";"Baneling";"Zergling";267;0
"Unit";"Baneling";"Zergling";267;0
"Unit";"Baneling";"Zergling";267;0
"Unit";"Baneling";"Zergling";267;0
"Unit";"Zergling";"Larva";267;1
"Unit";"Zergling";"Larva";268;1
"Unit";"Zergling";"Larva";269;1
"Unit";"Zergling";"Larva";270;1
"Unit";"Zergling";"Larva";271;1
"Unit";"Zergling";"Larva";272;1
"Unit";"Zergling";"Larva";273;1
"Unit";"Zergling";"Larva";274;1
"Unit";"Zergling";"Larva";275;1
"Unit";"Zergling";"Larva";276;1
"Unit";"Zergling";"Larva";277;1
"Unit";"Zergling";"Larva";278;1
"Unit";"Zergling";"Larva";279;1
"Unit";"Zergling";"Larva";280;1
"Unit";"Zergling";"Larva";281;1
"Unit";"Zergling";"Larva";282;1
"Unit";"Zergling";"Larva";283;1
"Unit";"Zergling";"Larva";284;1
"Unit";"Zergling";"Larva";285;1
"Unit";"Zergling";"Larva";286;1
"Building";"Extractor";NA;287;0
"Building";"CreepTumor";NA;287;0
"Unit";"Zergling";"Larva";287;1
"Unit";"Zergling";"Larva";288;1
"Unit";"Zergling";"Larva";289;1
"Unit";"Zergling";"Larva";290;1
"Unit";"Zergling";"Larva";291;1
"Unit";"Zergling";"Larva";292;1
"Unit";"Zergling";"Larva";293;1
"Unit";"Zergling";"Larva";294;1
"Unit";"Zergling";"Larva";295;1
"Unit";"Zergling";"Larva";296;1
"Unit";"Zergling";"Larva";297;1
"Unit";"Zergling";"Larva";298;1
"Unit";"Zergling";"Larva";299;1
"Unit";"Zergling";"Larva";300;1
"Unit";"Zergling";"Larva";301;1
"Unit";"Zergling";"Larva";302;1
"Unit";"Zergling";"Larva";303;1
"Unit";"Zergling";"Larva";304;1
"Unit";"Zergling";"Larva";305;1
"Unit";"Zergling";"Larva";306;1
"Unit";"Zergling";"Larva";307;1
"Unit";"Zergling";"Larva";308;1
"Unit";"Hydralisk";"Larva";309;2
"Unit";"Hydralisk";"Larva";311;2
"Unit";"Hydralisk";"Larva";313;2
"Unit";"Baneling";"Zergling";315;0
"Unit";"Baneling";"Zergling";315;0
"Unit";"Baneling";"Zergling";315;0
"Building";"CreepTumor";NA;315;0
"Building";"CreepTumor";NA;315;0
"Building";"CreepTumor";NA;315;0
"Building";"CreepTumor";NA;315;0
"Building";"CreepTumor";NA;315;0
"Building";"CreepTumor";NA;315;0
"Building";"CreepTumor";NA;315;0
"Building";"CreepTumor";NA;315;0
"Building";"CreepTumor";NA;315;0
"Unit";"Zergling";"Larva";315;1
"Unit";"Zergling";"Larva";316;1
"Unit";"Zergling";"Larva";317;1
"Unit";"Zergling";"Larva";318;1
"Unit";"Zergling";"Larva";319;1
"Unit";"Zergling";"Larva";320;1
"Unit";"Zergling";"Larva";321;1
"Unit";"Zergling";"Larva";322;1
"Building";"CreepTumorQueen";NA;323;0
"Unit";"Overlord";"Larva";323;0
"Building";"CreepTumorQueen";NA;323;0
"Building";"CreepTumorQueen";NA;323;0
"Unit";"Baneling";"Zergling";323;0
"Unit";"Baneling";"Zergling";323;0
"Unit";"Baneling";"Zergling";323;0
"Unit";"Baneling";"Zergling";323;0
"Building";"CreepTumorQueen";NA;323;0
"Building";"CreepTumorQueen";NA;323;0
"Building";"CreepTumorQueen";NA;323;0
"Unit";"Overlord";"Larva";323;0
"Building";"CreepTumorQueen";NA;323;0
"Unit";"Hydralisk";"Larva";323;2
"Unit";"Hydralisk";"Larva";325;2
"Unit";"Hydralisk";"Larva";327;2
"Unit";"Hydralisk";"Larva";329;2
"Building";"Hatchery";NA;331;0
"Unit";"Hydralisk";"Larva";331;2
"Unit";"Overlord";"Larva";333;0
"Unit";"Zergling";"Larva";333;1
"Unit";"Zergling";"Larva";334;1
"Unit";"Zergling";"Larva";335;1
"Unit";"Zergling";"Larva";336;1
"Unit";"Zergling";"Larva";337;1
"Unit";"Zergling";"Larva";338;1
"Unit";"Zergling";"Larva";339;1
"Unit";"Zergling";"Larva";340;1
"Unit";"Zergling";"Larva";341;1
"Unit";"Zergling";"Larva";342;1
"Unit";"Zergling";"Larva";343;1
"Unit";"Zergling";"Larva";344;1
"Unit";"Zergling";"Larva";345;1
"Unit";"Zergling";"Larva";346;1
"Unit";"Zergling";"Larva";347;1
"Unit";"Zergling";"Larva";348;1
"Unit";"Zergling";"Larva";349;1
"Unit";"Zergling";"Larva";350;1
"Unit";"Baneling";"Zergling";351;0
"Unit";"Baneling";"Zergling";351;0
"Unit";"Baneling";"Zergling";351;0
"Unit";"Baneling";"Zergling";351;0
"Unit";"Baneling";"Zergling";351;0
"Unit";"Baneling";"Zergling";351;0
"Unit";"Baneling";"Zergling";351;0
"Unit";"Baneling";"Zergling";351;0
"Unit";"Baneling";"Zergling";351;0
"Unit";"Baneling";"Zergling";351;0
"Unit";"Baneling";"Zergling";351;0
"Unit";"Baneling";"Zergling";351;0
"Unit";"Baneling";"Zergling";351;0
"Unit";"Baneling";"Zergling";351;0
"Unit";"Baneling";"Zergling";351;0
"Unit";"Baneling";"Zergling";351;0
"Unit";"Baneling";"Zergling";351;0
"Unit";"Baneling";"Zergling";351;0
"Unit";"Baneling";"Zergling";351;0
"Unit";"Baneling";"Zergling";351;0
"Unit";"Baneling";"Zergling";351;0
"Unit";"Baneling";"Zergling";351;0
"Unit";"Baneling";"Zergling";351;0
"Unit";"Zergling";"Larva";351;1
"Unit";"Zergling";"Larva";352;1
"Unit";"Zergling";"Larva";353;1
"Unit";"Zergling";"Larva";354;1
"Unit";"Zergling";"Larva";355;1
"Unit";"Zergling";"Larva";356;1
"Unit";"Zergling";"Larva";357;1
"Unit";"Zergling";"Larva";358;1
"Unit";"Zergling";"Larva";359;1
"Unit";"Zergling";"Larva";360;1
"Unit";"Zergling";"Larva";361;1
"Unit";"Zergling";"Larva";362;1
"Unit";"Zergling";"Larva";363;1
"Unit";"Zergling";"Larva";364;1
"Unit";"Zergling";"Larva";365;1
"Unit";"Zergling";"Larva";366;1
"Unit";"Zergling";"Larva";367;1
"Unit";"Zergling";"Larva";368;1
"Unit";"Zergling";"Larva";369;1
"Unit";"Zergling";"Larva";370;1
"Unit";"Zergling";"Larva";371;1
"Unit";"Zergling";"Larva";372;1
"Unit";"Zergling";"Larva";373;1
"Unit";"Zergling";"Larva";374;1
"Unit";"Zergling";"Larva";375;1
"Unit";"Zergling";"Larva";376;1
"Unit";"Zergling";"Larva";377;1
"Unit";"Zergling";"Larva";378;1
"Unit";"Zergling";"Larva";379;1
"Unit";"Zergling";"Larva";380;1
"Unit";"Zergling";"Larva";381;1
"Unit";"Zergling";"Larva";382;1
"Unit";"Zergling";"Larva";383;1
"Unit";"Zergling";"Larva";384;1
"Unit";"Zergling";"Larva";385;1
"Unit";"Zergling";"Larva";386;1
"Unit";"Zergling";"Larva";387;1
"Unit";"Zergling";"Larva";388;1
"Unit";"Zergling";"Larva";389;1
"Unit";"Zergling";"Larva";390;1
"Unit";"Zergling";"Larva";391;1
"Unit";"Zergling";"Larva";392;1
"Unit";"Zergling";"Larva";393;1
"Unit";"Zergling";"Larva";394;1
"Unit";"Zergling";"Larva";395;1
"Unit";"Zergling";"Larva";396;1
"Unit";"Hydralisk";"Larva";397;2
"Unit";"Hydralisk";"Larva";399;2
"Unit";"Hydralisk";"Larva";401;2
"Unit";"Hydralisk";"Larva";403;2
"Building";"UltraliskCavern";NA;405;0
"Building";"Hatchery";NA;405;0
"Building";"CreepTumor";NA;405;0
"Building";"CreepTumor";NA;405;0
"Building";"CreepTumor";NA;405;0
"Building";"CreepTumor";NA;405;0
"Unit";"Zergling";"Larva";405;1
"Unit";"Zergling";"Larva";406;1
"Unit";"Zergling";"Larva";407;1
"Unit";"Zergling";"Larva";408;1
"Unit";"Zergling";"Larva";409;1
"Unit";"Zergling";"Larva";410;1
"Unit";"Zergling";"Larva";411;1
"Unit";"Zergling";"Larva";412;1
"Unit";"Baneling";"Zergling";413;0
"Building";"CreepTumorQueen";NA;413;0
"Unit";"Baneling";"Zergling";413;0
"Unit";"Baneling";"Zergling";413;0
"Unit";"Baneling";"Zergling";413;0
"Unit";"Baneling";"Zergling";413;0
"Unit";"Baneling";"Zergling";413;0
"Unit";"Baneling";"Zergling";413;0
"Unit";"Baneling";"Zergling";413;0
"Unit";"Baneling";"Zergling";413;0
"Unit";"Baneling";"Zergling";413;0
"Unit";"Baneling";"Zergling";413;0
"Unit";"Baneling";"Zergling";413;0
"Unit";"Zergling";"Larva";413;1
"Unit";"Zergling";"Larva";414;1
"Unit";"Zergling";"Larva";415;1
"Unit";"Zergling";"Larva";416;1
"Unit";"Zergling";"Larva";417;1
"Unit";"Zergling";"Larva";418;1
"Unit";"Zergling";"Larva";419;1
"Unit";"Zergling";"Larva";420;1
"Unit";"Zergling";"Larva";421;1
"Unit";"Zergling";"Larva";422;1
"Building";"CreepTumor";NA;423;0
"Building";"CreepTumor";NA;423;0
"Building";"CreepTumor";NA;423;0
"Building";"CreepTumor";NA;423;0
"Building";"CreepTumor";NA;423;0
"Building";"CreepTumor";NA;423;0
"Building";"CreepTumor";NA;423;0
"Unit";"Zergling";"Larva";423;1
"Unit";"Zergling";"Larva";424;1
"Unit";"Viper";"Larva";425;3
"Unit";"Viper";"Larva";428;3
"Unit";"Overlord";"Larva";431;0
"Building";"CreepTumor";NA;431;0
"Building";"CreepTumor";NA;431;0
"Building";"CreepTumor";NA;431;0
"Building";"Extractor";NA;431;0
"Unit";"Ultralisk";"Larva";431;6
"Building";"Extractor";NA;437;0
"Unit";"Overlord";"Larva";437;0
"Building";"CreepTumor";NA;446;0
"Unit";"Corruptor";"Larva";446;2
"Unit";"Baneling";"Zergling";448;0
"Unit";"Baneling";"Zergling";448;0
"Unit";"Baneling";"Zergling";448;0
"Unit";"Baneling";"Zergling";448;0
"Unit";"Baneling";"Zergling";448;0
"Unit";"Baneling";"Zergling";448;0
"Building";"SpineCrawler";NA;448;0
"Unit";"Zergling";"Larva";448;1
"Unit";"Zergling";"Larva";449;1
"Unit";"Zergling";"Larva";450;1
"Unit";"Zergling";"Larva";451;1
"Unit";"Zergling";"Larva";452;1
"Unit";"Zergling";"Larva";453;1
"Unit";"Zergling";"Larva";454;1
"Unit";"Zergling";"Larva";455;1
"Unit";"Zergling";"Larva";456;1
"Unit";"Zergling";"Larva";457;1
"Unit";"Zergling";"Larva";458;1
"Unit";"Zergling";"Larva";459;1
"Unit";"Zergling";"Larva";460;1
"Unit";"Zergling";"Larva";461;1
"Unit";"Zergling";"Larva";462;1
"Unit";"Zergling";"Larva";463;1
"Unit";"Zergling";"Larva";464;1
"Unit";"Zergling";"Larva";465;1
"Unit";"Zergling";"Larva";466;1
"Unit";"Zergling";"Larva";467;1
"Unit";"Zergling";"Larva";468;1
"Unit";"Zergling";"Larva";469;1
"Unit";"Zergling";"Larva";470;1
"Unit";"Zergling";"Larva";471;1
"Unit";"Zergling";"Larva";472;1
"Unit";"Zergling";"Larva";473;1
"Unit";"Zergling";"Larva";474;1
"Unit";"Zergling";"Larva";475;1
"Upgrade";"ChitinousPlating";"UltraliskCavern";476;0
"Building";"CreepTumor";NA;476;0
"Building";"CreepTumor";NA;476;0
"Building";"CreepTumor";NA;476;0
"Building";"CreepTumor";NA;476;0
"Building";"CreepTumorQueen";NA;476;0
"Building";"CreepTumor";NA;476;0
"Unit";"Zergling";"Larva";476;1
"Unit";"Zergling";"Larva";477;1
"Unit";"Zergling";"Larva";478;1
"Unit";"Zergling";"Larva";479;1
"Building";"CreepTumor";NA;480;0
"Building";"CreepTumor";NA;480;0
"Building";"CreepTumor";NA;480;0
"Building";"CreepTumor";NA;480;0
"Unit";"Baneling";"Zergling";480;0
"Unit";"Baneling";"Zergling";480;0
"Unit";"Baneling";"Zergling";480;0
"Unit";"Baneling";"Zergling";480;0
"Unit";"Baneling";"Zergling";480;0
"Unit";"Baneling";"Zergling";480;0
"Unit";"Baneling";"Zergling";480;0
"Unit";"Baneling";"Zergling";480;0
"Unit";"Baneling";"Zergling";480;0
"Unit";"Baneling";"Zergling";480;0
"Unit";"Baneling";"Zergling";480;0
"Building";"Extractor";NA;480;0
"Unit";"Viper";"Larva";480;3
"Building";"CreepTumorQueen";NA;483;0
"Unit";"Ultralisk";"Larva";483;6
"Unit";"Ultralisk";"Larva";489;6
"Unit";"Ultralisk";"Larva";495;6
"Unit";"Zergling";"Larva";501;1
"Unit";"Zergling";"Larva";502;1
"Unit";"Zergling";"Larva";503;1
"Unit";"Zergling";"Larva";504;1
"Unit";"Zergling";"Larva";505;1
"Unit";"Zergling";"Larva";506;1
"Unit";"Zergling";"Larva";507;1
"Unit";"Zergling";"Larva";508;1
"Unit";"Zergling";"Larva";509;1
"Unit";"Zergling";"Larva";510;1
"Unit";"Zergling";"Larva";511;1
"Unit";"Zergling";"Larva";512;1
"Unit";"Zergling";"Larva";513;1
"Unit";"Zergling";"Larva";514;1
"Unit";"Zergling";"Larva";515;1
"Unit";"Zergling";"Larva";516;1
"Unit";"Zergling";"Larva";517;1
"Unit";"Zergling";"Larva";518;1
"Unit";"Zergling";"Larva";519;1
"Unit";"Zergling";"Larva";520;1
"Unit";"Zergling";"Larva";521;1
"Unit";"Zergling";"Larva";522;1
"Unit";"Zergling";"Larva";523;1
"Unit";"Zergling";"Larva";524;1
"Building";"CreepTumor";NA;525;0
"Building";"CreepTumor";NA;525;0
"Building";"CreepTumor";NA;525;0
"Building";"CreepTumor";NA;525;0
"Unit";"Viper";"Larva";525;3
"Unit";"Viper";"Larva";528;3
"Unit";"Zergling";"Larva";531;1
"Unit";"Zergling";"Larva";532;1
"Unit";"Zergling";"Larva";533;1
"Unit";"Zergling";"Larva";534;1
"Unit";"Zergling";"Larva";535;1
"Unit";"Zergling";"Larva";536;1
"Unit";"Zergling";"Larva";537;1
"Unit";"Zergling";"Larva";538;1
"Unit";"Zergling";"Larva";539;1
"Unit";"Zergling";"Larva";540;1
"Unit";"Zergling";"Larva";541;1
"Unit";"Zergling";"Larva";542;1
"Unit";"Zergling";"Larva";543;1
"Unit";"Zergling";"Larva";544;1
"Unit";"Zergling";"Larva";545;1
"Unit";"Zergling";"Larva";546;1
"Unit";"Zergling";"Larva";547;1
"Unit";"Zergling";"Larva";548;1
"Unit";"Zergling";"Larva";549;1
"Unit";"Zergling";"Larva";550;1
"Building";"CreepTumor";NA;551;0
"Building";"CreepTumor";NA;551;0
"Building";"CreepTumor";NA;551;0
"Building";"CreepTumor";NA;551;0
"Building";"CreepTumor";NA;551;0
"Unit";"Baneling";"Zergling";551;0
"Unit";"Baneling";"Zergling";551;0
"Building";"Hatchery";NA;551;0
"Unit";"Zergling";"Larva";551;1
"Unit";"Zergling";"Larva";552;1
"Unit";"Zergling";"Larva";553;1
"Unit";"Zergling";"Larva";554;1
"Unit";"Zergling";"Larva";555;1
"Unit";"Zergling";"Larva";556;1
"Unit";"Zergling";"Larva";557;1
"Unit";"Zergling";"Larva";558;1
"Unit";"Zergling";"Larva";559;1
"Unit";"Zergling";"Larva";560;1
"Unit";"Zergling";"Larva";561;1
"Unit";"Zergling";"Larva";562;1
"Unit";"Zergling";"Larva";563;1
"Unit";"Zergling";"Larva";564;1
"Unit";"Zergling";"Larva";565;1
"Unit";"Zergling";"Larva";566;1
"Unit";"Zergling";"Larva";567;1
"Unit";"Zergling";"Larva";568;1
"Unit";"Zergling";"Larva";569;1
"Unit";"Zergling";"Larva";570;1
"Unit";"Zergling";"Larva";571;1
"Unit";"Zergling";"Larva";572;1
"Unit";"Zergling";"Larva";573;1
"Unit";"Zergling";"Larva";574;1
"Unit";"Zergling";"Larva";575;1
"Unit";"Zergling";"Larva";576;1
"Unit";"Zergling";"Larva";577;1
"Unit";"Zergling";"Larva";578;1
"Unit";"Zergling";"Larva";579;1
"Unit";"Zergling";"Larva";580;1
"Unit";"Zergling";"Larva";581;1
"Unit";"Zergling";"Larva";582;1
"Unit";"Zergling";"Larva";583;1
"Unit";"Zergling";"Larva";584;1
"Unit";"Zergling";"Larva";585;1
"Unit";"Zergling";"Larva";586;1
"Unit";"Zergling";"Larva";587;1
"Unit";"Zergling";"Larva";588;1
"Unit";"Zergling";"Larva";589;1
"Unit";"Zergling";"Larva";590;1
"Unit";"Zergling";"Larva";591;1
"Unit";"Zergling";"Larva";592;1
"Unit";"Hydralisk";"Larva";593;2
"Unit";"Ultralisk";"Larva";595;6
"Unit";"Hydralisk";"Larva";601;2
"Unit";"Hydralisk";"Larva";603;2
"Unit";"Hydralisk";"Larva";605;2
"Unit";"Hydralisk";"Larva";607;2
"Unit";"Zergling";"Larva";609;1
"Unit";"Zergling";"Larva";610;1
"Unit";"Zergling";"Larva";611;1
"Unit";"Zergling";"Larva";612;1
"Unit";"Zergling";"Larva";613;1
"Unit";"Zergling";"Larva";614;1
"Unit";"Zergling";"Larva";615;1
"Unit";"Zergling";"Larva";616;1
"Unit";"Zergling";"Larva";617;1
"Unit";"Zergling";"Larva";618;1
"Unit";"Zergling";"Larva";619;1
"Unit";"Zergling";"Larva";620;1
"Unit";"Zergling";"Larva";621;1
"Unit";"Zergling";"Larva";622;1
"Unit";"Zergling";"Larva";623;1
"Unit";"Zergling";"Larva";624;1
"Unit";"Zergling";"Larva";625;1
"Unit";"Zergling";"Larva";626;1
"Unit";"Zergling";"Larva";627;1
"Unit";"Zergling";"Larva";628;1
"Unit";"Ultralisk";"Larva";629;6
"Unit";"Ultralisk";"Larva";635;6
"Unit";"Ultralisk";"Larva";641;6
"Unit";"Infestor";"Larva";647;2
"Unit";"Infestor";"Larva";649;2
"Unit";"Infestor";"Larva";651;2
"Unit";"Corruptor";"Larva";653;2
"Building";"Extractor";NA;655;0
"Building";"SpineCrawler";NA;655;0
"Building";"Extractor";NA;655;0
"Building";"CreepTumor";NA;655;0
"Building";"CreepTumor";NA;655;0
"Building";"CreepTumor";NA;655;0
"Building";"CreepTumor";NA;655;0
"Building";"CreepTumor";NA;655;0
"Upgrade";"Burrow";"Hatchery";655;0
"Unit";"Corruptor";"Larva";655;2
"Unit";"Corruptor";"Larva";657;2
"Unit";"Corruptor";"Larva";659;2
"Unit";"Corruptor";"Larva";661;2
"Unit";"Corruptor";"Larva";663;2
"Unit";"Corruptor";"Larva";665;2
"Unit";"Corruptor";"Larva";667;2
"Unit";"Corruptor";"Larva";669;2
"Unit";"Corruptor";"Larva";671;2
"Unit";"Corruptor";"Larva";673;2
"Unit";"Corruptor";"Larva";675;2
"Unit";"Corruptor";"Larva";677;2
"Unit";"Corruptor";"Larva";679;2
"Unit";"Corruptor";"Larva";681;2
"Unit";"Corruptor";"Larva";683;2
"Building";"CreepTumorQueen";NA;685;0
"Building";"CreepTumorQueen";NA;685;0
"Building";"CreepTumorQueen";NA;685;0
"Unit";"Zergling";"Larva";685;1
"Unit";"Zergling";"Larva";686;1
"Unit";"Zergling";"Larva";687;1
"Unit";"Zergling";"Larva";688;1
"Unit";"Zergling";"Larva";689;1
"Unit";"Zergling";"Larva";690;1
"Unit";"Zergling";"Larva";691;1
"Unit";"Zergling";"Larva";692;1
"Unit";"Zergling";"Larva";693;1
"Unit";"Zergling";"Larva";694;1
"Unit";"Zergling";"Larva";695;1
"Unit";"Zergling";"Larva";696;1
"Unit";"Zergling";"Larva";697;1
"Unit";"Zergling";"Larva";698;1
"Unit";"Zergling";"Larva";699;1
"Unit";"Zergling";"Larva";700;1
"Unit";"Zergling";"Larva";701;1
"Unit";"Zergling";"Larva";702;1
"Unit";"Zergling";"Larva";703;1
"Unit";"Zergling";"Larva";704;1
"Unit";"Zergling";"Larva";705;1
"Unit";"Zergling";"Larva";706;1
"Building";"CreepTumorQueen";NA;707;0
"Unit";"Infestor";"Larva";707;2
"Unit";"Baneling";"Zergling";709;0
"Unit";"Baneling";"Zergling";709;0
"Unit";"Baneling";"Zergling";709;0
"Unit";"Baneling";"Zergling";709;0
"Unit";"Baneling";"Zergling";709;0
"Unit";"Baneling";"Zergling";709;0
"Building";"Extractor";NA;709;0
"Upgrade";"SprayZerg";NA;709;0
"Upgrade";"SprayZerg";NA;709;0
"Upgrade";"SprayZerg";NA;709;0
"Upgrade";"zerglingmovementspeed";NA;709;0
"Upgrade";"SprayZerg";NA;709;0
"Upgrade";"SprayZerg";NA;709;0
"Upgrade";"ZergGroundArmorsLevel1";NA;709;0
"Upgrade";"CentrificalHooks";NA;709;0
"Upgrade";"SprayZerg";NA;709;0
"Upgrade";"EvolveMuscularAugments";NA;709;0
"Upgrade";"ZergMeleeWeaponsLevel1";NA;709;0
"Upgrade";"SprayZerg";NA;709;0
"Upgrade";"ZergGroundArmorsLevel2";NA;709;0
"Upgrade";"SprayZerg";NA;709;0
"Upgrade";"ZergMeleeWeaponsLevel2";NA;709;0
"Upgrade";"SprayZerg";NA;709;0
"Upgrade";"SprayZerg";NA;709;0
"Upgrade";"zerglingattackspeed";NA;709;0
"Upgrade";"SprayZerg";NA;709;0
"Upgrade";"ZergGroundArmorsLevel3";NA;709;0
"Upgrade";"ZergMeleeWeaponsLevel3";NA;709;0
"Upgrade";"SprayZerg";NA;709;0
"Upgrade";"ZergFlyerWeaponsLevel1";NA;709;0
"Upgrade";"SprayZerg";NA;709;0
"Upgrade";"SprayZerg";NA;709;0
