"type";"unit_name";"on_building";"total_supply";"supply"
"Unit";"Overlord";"Larva";13;0
"Building";"Extractor";NA;18;0
"Unit";"Overlord";"Larva";21;0
"Building";"SpawningPool";NA;19;0
"Building";"Hatchery";NA;17;0
"Unit";"Zergling";"Larva";22;1
"Unit";"Zergling";"Larva";22;1
"Unit";"Zergling";"Larva";23;1
"Unit";"Zergling";"Larva";23;1
"Unit";"Queen";"Hatchery";22;2
"Unit";"Queen";"Hatchery";22;2
"Unit";"Overlord";"Larva";34;0
"Building";"CreepTumorQueen";NA;39;0
"Building";"Hatchery";NA;27;0
"Unit";"Overlord";"Larva";48;0
"Unit";"Queen";"Hatchery";40;2
"Unit";"Zergling";"Larva";48;1
"Unit";"Zergling";"Larva";48;1
"Unit";"Zergling";"Larva";48;1
"Unit";"Zergling";"Larva";48;1
"Unit";"Zergling";"Larva";48;1
"Unit";"Zergling";"Larva";48;1
"Building";"CreepTumor";NA;48;0
"Building";"RoachWarren";NA;48;0
"Building";"CreepTumorQueen";NA;54;0
"Unit";"Queen";"Hatchery";48;2
"Unit";"Queen";"Hatchery";48;2
"Unit";"Overlord";"Larva";59;0
"Unit";"Overlord";"Larva";59;0
"Building";"Extractor";NA;59;0
"Building";"Extractor";NA;59;0
"Unit";"Roach";"Larva";63;2
"Unit";"Roach";"Larva";63;2
"Unit";"Roach";"Larva";63;2
"Building";"SporeCrawler";NA;63;0
"Building";"CreepTumor";NA;67;0
"Building";"SporeCrawler";NA;63;0
"Building";"SporeCrawler";NA;63;0
"Building";"CreepTumor";NA;67;0
"Unit";"Overlord";"Larva";67;0
"Building";"EvolutionChamber";NA;80;0
"Building";"EvolutionChamber";NA;80;0
"Building";"CreepTumorQueen";NA;94;0
"Unit";"Overlord";"Larva";91;0
"Unit";"Overlord";"Larva";91;0
"Building";"CreepTumorQueen";NA;94;0
"Unit";"Overlord";"Larva";91;0
"Building";"CreepTumor";NA;94;0
"Building";"CreepTumor";NA;94;0
"Building";"HydraliskDen";NA;91;0
"Unit";"Overlord";"Larva";94;0
"Unit";"Overlord";"Larva";94;0
"Unit";"Overlord";"Larva";94;0
"Unit";"Overlord";"Larva";94;0
"Building";"BanelingNest";NA;91;0
"Building";"Extractor";NA;94;0
"Building";"Extractor";NA;94;0
"Building";"CreepTumorQueen";NA;108;0
"Building";"CreepTumor";NA;108;0
"Building";"CreepTumorQueen";NA;111;0
"Building";"Extractor";NA;111;0
"Unit";"Hydralisk";"Larva";111;2
"Unit";"Hydralisk";"Larva";111;2
"Unit";"Hydralisk";"Larva";111;2
"Unit";"Hydralisk";"Larva";111;2
"Unit";"Hydralisk";"Larva";111;2
"Unit";"Zergling";"Larva";114;1
"Unit";"Zergling";"Larva";114;1
"Unit";"Zergling";"Larva";114;1
"Unit";"Zergling";"Larva";114;1
"Unit";"Zergling";"Larva";114;1
"Unit";"Zergling";"Larva";114;1
"Unit";"Zergling";"Larva";114;1
"Unit";"Zergling";"Larva";114;1
"Building";"CreepTumor";NA;115;0
"Upgrade";"ZergGroundArmorsLevel1";"EvolutionChamber";94;0
"Building";"CreepTumor";NA;125;0
"Unit";"Zergling";"Larva";115;1
"Unit";"Zergling";"Larva";115;1
"Unit";"Zergling";"Larva";115;1
"Unit";"Zergling";"Larva";115;1
"Unit";"Zergling";"Larva";115;1
"Unit";"Zergling";"Larva";115;1
"Building";"CreepTumor";NA;125;0
"Unit";"Zergling";"Larva";115;1
"Unit";"Zergling";"Larva";115;1
"Unit";"Zergling";"Larva";115;1
"Unit";"Zergling";"Larva";115;1
"Unit";"Zergling";"Larva";115;1
"Unit";"Zergling";"Larva";115;1
"Unit";"Zergling";"Larva";115;1
"Unit";"Zergling";"Larva";115;1
"Unit";"Zergling";"Larva";115;1
"Unit";"Zergling";"Larva";115;1
"Building";"CreepTumorQueen";NA;133;0
"Building";"CreepTumorQueen";NA;150;0
"Unit";"Hydralisk";"Larva";133;2
"Unit";"Hydralisk";"Larva";133;2
"Unit";"Hydralisk";"Larva";133;2
"Building";"CreepTumor";NA;150;0
"Building";"CreepTumorQueen";NA;150;0
"Building";"CreepTumor";NA;150;0
"Unit";"Overlord";"Larva";150;0
"Unit";"Overlord";"Larva";150;0
"Upgrade";"ZergMissileWeaponsLevel1";"EvolutionChamber";108;0
"Unit";"Overlord";"Larva";150;0
"Building";"CreepTumor";NA;150;0
"Upgrade";"EvolveGroovedSpines";"HydraliskDen";115;0
"Building";"InfestationPit";NA;133;0
"Building";"Hatchery";NA;114;0
"Unit";"Zergling";"Larva";156;1
"Unit";"Zergling";"Larva";156;1
"Unit";"Hydralisk";"Larva";150;2
"Unit";"Hydralisk";"Larva";150;2
"Unit";"Hydralisk";"Larva";150;2
"Unit";"Hydralisk";"Larva";150;2
"Unit";"Hydralisk";"Larva";150;2
"Unit";"Hydralisk";"Larva";150;2
"Unit";"Hydralisk";"Larva";150;2
"Unit";"Hydralisk";"Larva";150;2
"Building";"CreepTumorQueen";NA;156;0
"Unit";"Zergling";"Larva";156;1
"Unit";"Zergling";"Larva";156;1
"Unit";"Zergling";"Larva";156;1
"Unit";"Zergling";"Larva";156;1
"Unit";"Zergling";"Larva";156;1
"Unit";"Zergling";"Larva";156;1
"Unit";"Zergling";"Larva";156;1
"Unit";"Zergling";"Larva";156;1
"Unit";"Zergling";"Larva";156;1
"Unit";"Zergling";"Larva";156;1
"Unit";"Baneling";"Zergling";156;0
"Unit";"Baneling";"Zergling";156;0
"Unit";"Baneling";"Zergling";156;0
"Unit";"Baneling";"Zergling";156;0
"Unit";"Baneling";"Zergling";156;0
"Unit";"Baneling";"Zergling";156;0
"Unit";"Baneling";"Zergling";156;0
"Unit";"Baneling";"Zergling";156;0
"Unit";"Baneling";"Zergling";156;0
"Unit";"Baneling";"Zergling";156;0
"Unit";"Baneling";"Zergling";156;0
"Building";"CreepTumor";NA;184;0
"Building";"CreepTumor";NA;184;0
"Building";"CreepTumor";NA;184;0
"Building";"CreepTumorQueen";NA;184;0
"Building";"CreepTumorQueen";NA;184;0
"Unit";"Zergling";"Larva";195;1
"Unit";"Zergling";"Larva";195;1
"Unit";"Zergling";"Larva";195;1
"Unit";"Zergling";"Larva";195;1
"Unit";"Zergling";"Larva";195;1
"Unit";"Zergling";"Larva";195;1
"Unit";"Zergling";"Larva";195;1
"Unit";"Zergling";"Larva";195;1
"Unit";"Zergling";"Larva";195;1
"Unit";"Zergling";"Larva";195;1
"Unit";"Zergling";"Larva";195;1
"Unit";"Zergling";"Larva";195;1
"Unit";"Zergling";"Larva";195;1
"Unit";"Zergling";"Larva";195;1
"Unit";"Zergling";"Larva";195;1
"Unit";"Zergling";"Larva";195;1
"Unit";"Zergling";"Larva";195;1
"Unit";"Zergling";"Larva";195;1
"Unit";"Baneling";"Zergling";195;0
"Unit";"Baneling";"Zergling";195;0
"Unit";"Baneling";"Zergling";195;0
"Unit";"Baneling";"Zergling";195;0
"Unit";"Baneling";"Zergling";195;0
"Unit";"Baneling";"Zergling";195;0
"Unit";"Baneling";"Zergling";195;0
"Building";"CreepTumor";NA;213;0
"Building";"CreepTumor";NA;213;0
"Building";"CreepTumor";NA;213;0
"Upgrade";"EvolveMuscularAugments";"HydraliskDen";184;0
"Building";"CreepTumor";NA;213;0
"Building";"Extractor";NA;195;0
"Building";"Extractor";NA;195;0
"Unit";"Zergling";"Larva";213;1
"Unit";"Zergling";"Larva";213;1
"Unit";"Zergling";"Larva";213;1
"Unit";"Zergling";"Larva";213;1
"Unit";"Zergling";"Larva";213;1
"Unit";"Zergling";"Larva";213;1
"Unit";"Zergling";"Larva";213;1
"Unit";"Zergling";"Larva";213;1
"Unit";"Zergling";"Larva";213;1
"Unit";"Zergling";"Larva";213;1
"Unit";"Zergling";"Larva";213;1
"Unit";"Zergling";"Larva";213;1
"Unit";"Zergling";"Larva";213;1
"Unit";"Zergling";"Larva";213;1
"Unit";"Zergling";"Larva";213;1
"Unit";"Zergling";"Larva";213;1
"Unit";"Zergling";"Larva";213;1
"Unit";"Zergling";"Larva";213;1
"Unit";"Zergling";"Larva";213;1
"Unit";"Zergling";"Larva";213;1
"Unit";"Zergling";"Larva";213;1
"Unit";"Zergling";"Larva";213;1
"Unit";"Queen";"Hatchery";195;2
"Unit";"Zergling";"Larva";213;1
"Unit";"Zergling";"Larva";213;1
"Unit";"Zergling";"Larva";213;1
"Unit";"Zergling";"Larva";213;1
"Unit";"Zergling";"Larva";213;1
"Unit";"Zergling";"Larva";213;1
"Unit";"Zergling";"Larva";213;1
"Unit";"Zergling";"Larva";213;1
"Unit";"Baneling";"Zergling";245;0
"Unit";"Baneling";"Zergling";245;0
"Unit";"Baneling";"Zergling";245;0
"Building";"CreepTumor";NA;245;0
"Building";"CreepTumor";NA;245;0
"Building";"CreepTumorQueen";NA;245;0
"Building";"CreepTumorQueen";NA;245;0
"Unit";"Baneling";"Zergling";245;0
"Unit";"Baneling";"Zergling";245;0
"Unit";"Baneling";"Zergling";245;0
"Unit";"Baneling";"Zergling";245;0
"Unit";"Baneling";"Zergling";245;0
"Unit";"Baneling";"Zergling";245;0
"Unit";"Baneling";"Zergling";245;0
"Unit";"Baneling";"Zergling";245;0
"Unit";"Baneling";"Zergling";245;0
"Unit";"Baneling";"Zergling";245;0
"Unit";"Baneling";"Zergling";245;0
"Unit";"Baneling";"Zergling";245;0
"Unit";"Baneling";"Zergling";245;0
"Unit";"Baneling";"Zergling";245;0
"Unit";"Zergling";"Larva";245;1
"Unit";"Zergling";"Larva";245;1
"Unit";"Zergling";"Larva";245;1
"Unit";"Zergling";"Larva";245;1
"Unit";"Zergling";"Larva";245;1
"Unit";"Zergling";"Larva";245;1
"Unit";"Zergling";"Larva";245;1
"Unit";"Zergling";"Larva";245;1
"Unit";"Zergling";"Larva";245;1
"Unit";"Zergling";"Larva";245;1
"Unit";"Overlord";"Larva";245;0
"Unit";"Overlord";"Larva";245;0
"Unit";"Overlord";"Larva";245;0
"Unit";"Overlord";"Larva";245;0
"Unit";"Overlord";"Larva";245;0
"Unit";"Overlord";"Larva";245;0
"Unit";"Overlord";"Larva";245;0
"Unit";"Overlord";"Larva";245;0
"Unit";"Overlord";"Larva";245;0
"Upgrade";"ZergMeleeWeaponsLevel1";"EvolutionChamber";195;0
"Building";"UltraliskCavern";NA;245;0
"Upgrade";"ZergGroundArmorsLevel2";"EvolutionChamber";197;0
"Unit";"Zergling";"Larva";255;1
"Unit";"Zergling";"Larva";255;1
"Unit";"Zergling";"Larva";255;1
"Unit";"Zergling";"Larva";255;1
"Unit";"Zergling";"Larva";255;1
"Unit";"Zergling";"Larva";255;1
"Unit";"Zergling";"Larva";255;1
"Unit";"Zergling";"Larva";255;1
"Unit";"Zergling";"Larva";255;1
"Unit";"Zergling";"Larva";255;1
"Unit";"Zergling";"Larva";255;1
"Unit";"Zergling";"Larva";255;1
"Unit";"Zergling";"Larva";255;1
"Unit";"Zergling";"Larva";255;1
"Unit";"Zergling";"Larva";255;1
"Unit";"Zergling";"Larva";255;1
"Unit";"Zergling";"Larva";255;1
"Unit";"Zergling";"Larva";255;1
"Unit";"Zergling";"Larva";255;1
"Unit";"Zergling";"Larva";255;1
"Unit";"Zergling";"Larva";255;1
"Unit";"Zergling";"Larva";255;1
"Unit";"Zergling";"Larva";255;1
"Unit";"Zergling";"Larva";255;1
"Unit";"Zergling";"Larva";255;1
"Unit";"Zergling";"Larva";255;1
"Unit";"Zergling";"Larva";255;1
"Unit";"Zergling";"Larva";255;1
"Unit";"Zergling";"Larva";255;1
"Unit";"Zergling";"Larva";255;1
"Unit";"Zergling";"Larva";255;1
"Unit";"Zergling";"Larva";255;1
"Unit";"Zergling";"Larva";255;1
"Unit";"Zergling";"Larva";255;1
"Unit";"Zergling";"Larva";255;1
"Unit";"Zergling";"Larva";255;1
"Building";"CreepTumor";NA;255;0
"Building";"CreepTumorQueen";NA;255;0
"Building";"CreepTumorQueen";NA;255;0
"Building";"CreepTumor";NA;291;0
"Building";"CreepTumor";NA;291;0
"Building";"CreepTumor";NA;291;0
"Unit";"Ultralisk";"Larva";255;6
"Unit";"Ultralisk";"Larva";255;6
"Unit";"Ultralisk";"Larva";255;6
"Unit";"Ultralisk";"Larva";255;6
"Unit";"Zergling";"Larva";291;1
"Unit";"Zergling";"Larva";291;1
"Unit";"Zergling";"Larva";315;1
"Unit";"Zergling";"Larva";315;1
"Unit";"Zergling";"Larva";315;1
"Unit";"Zergling";"Larva";315;1
"Unit";"Zergling";"Larva";315;1
"Unit";"Zergling";"Larva";315;1
"Unit";"Zergling";"Larva";315;1
"Unit";"Zergling";"Larva";315;1
"Unit";"Zergling";"Larva";315;1
"Unit";"Zergling";"Larva";315;1
"Unit";"Zergling";"Larva";315;1
"Unit";"Zergling";"Larva";315;1
"Unit";"Zergling";"Larva";315;1
"Unit";"Zergling";"Larva";315;1
"Unit";"Zergling";"Larva";315;1
"Unit";"Zergling";"Larva";315;1
"Unit";"Zergling";"Larva";315;1
"Unit";"Zergling";"Larva";315;1
"Unit";"Zergling";"Larva";315;1
"Unit";"Zergling";"Larva";315;1
"Unit";"Zergling";"Larva";315;1
"Unit";"Zergling";"Larva";315;1
"Unit";"Zergling";"Larva";315;1
"Unit";"Zergling";"Larva";315;1
"Unit";"Zergling";"Larva";315;1
"Unit";"Zergling";"Larva";315;1
"Unit";"Zergling";"Larva";315;1
"Unit";"Zergling";"Larva";315;1
"Unit";"Zergling";"Larva";315;1
"Unit";"Zergling";"Larva";315;1
"Unit";"Zergling";"Larva";315;1
"Unit";"Zergling";"Larva";315;1
"Unit";"Zergling";"Larva";315;1
"Unit";"Zergling";"Larva";315;1
"Unit";"Zergling";"Larva";315;1
"Unit";"Zergling";"Larva";315;1
"Unit";"Zergling";"Larva";315;1
"Unit";"Zergling";"Larva";315;1
"Unit";"Zergling";"Larva";315;1
"Unit";"Zergling";"Larva";315;1
"Unit";"Zergling";"Larva";315;1
"Unit";"Zergling";"Larva";315;1
"Unit";"Zergling";"Larva";315;1
"Unit";"Zergling";"Larva";315;1
"Unit";"Zergling";"Larva";315;1
"Unit";"Zergling";"Larva";315;1
"Unit";"Zergling";"Larva";315;1
"Unit";"Zergling";"Larva";315;1
"Unit";"Zergling";"Larva";315;1
"Unit";"Zergling";"Larva";315;1
"Unit";"Zergling";"Larva";315;1
"Unit";"Zergling";"Larva";315;1
"Unit";"Zergling";"Larva";315;1
"Unit";"Zergling";"Larva";315;1
"Building";"Hatchery";NA;257;0
"Upgrade";"ChitinousPlating";"UltraliskCavern";291;0
"Unit";"Zergling";"Larva";355;1
"Unit";"Zergling";"Larva";355;1
"Unit";"Zergling";"Larva";355;1
"Unit";"Zergling";"Larva";355;1
"Unit";"Zergling";"Larva";355;1
"Unit";"Zergling";"Larva";355;1
"Unit";"Zergling";"Larva";355;1
"Unit";"Zergling";"Larva";355;1
"Unit";"Zergling";"Larva";355;1
"Unit";"Zergling";"Larva";355;1
"Unit";"Ultralisk";"Larva";291;6
"Unit";"Ultralisk";"Larva";291;6
"Unit";"Ultralisk";"Larva";291;6
"Unit";"Baneling";"Zergling";367;0
"Unit";"Baneling";"Zergling";371;0
"Unit";"Baneling";"Zergling";371;0
"Unit";"Baneling";"Zergling";371;0
"Unit";"Baneling";"Zergling";371;0
"Unit";"Baneling";"Zergling";371;0
"Unit";"Baneling";"Zergling";371;0
"Unit";"Baneling";"Zergling";371;0
"Unit";"Baneling";"Zergling";371;0
"Unit";"Baneling";"Zergling";371;0
"Unit";"Baneling";"Zergling";371;0
"Unit";"Baneling";"Zergling";371;0
"Unit";"Zergling";"Larva";355;1
"Unit";"Zergling";"Larva";355;1
"Unit";"Zergling";"Larva";355;1
"Unit";"Zergling";"Larva";355;1
"Unit";"Zergling";"Larva";371;1
"Unit";"Zergling";"Larva";371;1
"Unit";"Hydralisk";"Larva";371;2
"Unit";"Hydralisk";"Larva";371;2
"Unit";"Hydralisk";"Larva";371;2
"Unit";"Queen";"Hatchery";355;2
"Unit";"Zergling";"Larva";403;1
"Unit";"Zergling";"Larva";403;1
"Unit";"Zergling";"Larva";403;1
"Unit";"Zergling";"Larva";403;1
"Unit";"Zergling";"Larva";403;1
"Unit";"Zergling";"Larva";403;1
"Unit";"Zergling";"Larva";403;1
"Unit";"Zergling";"Larva";403;1
