"type";"unit_name";"on_building";"total_supply";"supply"
"Unit";"Overlord";"Larva";13;0
"Building";"Extractor";NA;15;0
"Building";"SpawningPool";NA;17;0
"Unit";"Zergling";"Larva";21;1
"Unit";"Zergling";"Larva";21;1
"Unit";"Overlord";"Larva";21;0
"Unit";"Queen";"Hatchery";21;2
"Building";"Hatchery";NA;20;0
"Unit";"Queen";"Hatchery";24;2
"Unit";"Overlord";"Larva";29;0
"Unit";"Queen";"Hatchery";28;2
"Unit";"Overlord";"Larva";35;0
"Building";"CreepTumorQueen";NA;40;0
"Unit";"Zergling";"Larva";42;1
"Unit";"Zergling";"Larva";42;1
"Unit";"Zergling";"Larva";42;1
"Unit";"Zergling";"Larva";42;1
"Unit";"Overlord";"Larva";42;0
"Unit";"Zergling";"Larva";42;1
"Unit";"Zergling";"Larva";42;1
"Unit";"Zergling";"Larva";47;1
"Unit";"Zergling";"Larva";47;1
"Unit";"Overlord";"Larva";51;0
"Building";"CreepTumor";NA;55;0
"Building";"CreepTumorQueen";NA;55;0
"Unit";"Queen";"Hatchery";49;2
"Unit";"Overlord";"Larva";55;0
"Building";"Hatchery";NA;41;0
"Building";"Extractor";NA;63;0
"Building";"Extractor";NA;63;0
"Building";"CreepTumorQueen";NA;67;0
"Building";"CreepTumor";NA;67;0
"Building";"CreepTumor";NA;67;0
"Unit";"Queen";"Hatchery";64;2
"Unit";"Overlord";"Larva";73;0
"Building";"BanelingNest";NA;66;0
"Building";"CreepTumorQueen";NA;78;0
"Building";"CreepTumorQueen";NA;78;0
"Building";"CreepTumor";NA;81;0
"Building";"EvolutionChamber";NA;77;0
"Building";"EvolutionChamber";NA;77;0
"Building";"CreepTumor";NA;81;0
"Building";"CreepTumor";NA;82;0
"Building";"Extractor";NA;81;0
"Unit";"Overlord";"Larva";83;0
"Building";"CreepTumor";NA;91;0
"Building";"CreepTumor";NA;91;0
"Building";"CreepTumor";NA;91;0
"Building";"CreepTumor";NA;91;0
"Unit";"Zergling";"Larva";91;1
"Unit";"Zergling";"Larva";91;1
"Building";"CreepTumor";NA;91;0
"Unit";"Zergling";"Larva";91;1
"Unit";"Zergling";"Larva";91;1
"Unit";"Zergling";"Larva";91;1
"Unit";"Zergling";"Larva";91;1
"Unit";"Zergling";"Larva";91;1
"Unit";"Zergling";"Larva";91;1
"Unit";"Zergling";"Larva";91;1
"Unit";"Zergling";"Larva";91;1
"Unit";"Zergling";"Larva";91;1
"Unit";"Zergling";"Larva";91;1
"Building";"CreepTumorQueen";NA;101;0
"Building";"Extractor";NA;91;0
"Building";"Extractor";NA;91;0
"Building";"CreepTumor";NA;111;0
"Building";"HydraliskDen";NA;91;0
"Unit";"Overlord";"Larva";103;0
"Unit";"Overlord";"Larva";103;0
"Building";"CreepTumor";NA;111;0
"Building";"CreepTumor";NA;111;0
"Building";"CreepTumor";NA;111;0
"Building";"SporeCrawler";NA;111;0
"Unit";"Hydralisk";"Larva";111;2
"Unit";"Hydralisk";"Larva";111;2
"Building";"CreepTumor";NA;111;0
"Building";"CreepTumor";NA;111;0
"Building";"SporeCrawler";NA;111;0
"Unit";"Hydralisk";"Larva";111;2
"Unit";"Hydralisk";"Larva";111;2
"Unit";"Hydralisk";"Larva";111;2
"Building";"CreepTumor";NA;119;0
"Building";"CreepTumor";NA;127;0
"Building";"CreepTumor";NA;127;0
"Building";"CreepTumor";NA;127;0
"Building";"CreepTumor";NA;127;0
"Unit";"Hydralisk";"Larva";119;2
"Unit";"Hydralisk";"Larva";119;2
"Unit";"Hydralisk";"Larva";119;2
"Unit";"Hydralisk";"Larva";119;2
"Building";"InfestationPit";NA;119;0
"Building";"Hatchery";NA;111;0
"Unit";"Overlord";"Larva";127;0
"Unit";"Overlord";"Larva";127;0
"Unit";"Overlord";"Larva";127;0
"Building";"CreepTumor";NA;141;0
"Unit";"Baneling";"Zergling";133;0
"Unit";"Baneling";"Zergling";133;0
"Unit";"Baneling";"Zergling";135;0
"Upgrade";"EvolveGroovedSpines";"HydraliskDen";115;0
"Unit";"Overlord";"Larva";141;0
"Unit";"Overlord";"Larva";144;0
"Building";"CreepTumorQueen";NA;144;0
"Upgrade";"ZergMeleeWeaponsLevel1";"EvolutionChamber";111;0
"Upgrade";"ZergGroundArmorsLevel1";"EvolutionChamber";111;0
"Unit";"Zergling";"Larva";144;1
"Unit";"Zergling";"Larva";144;1
"Unit";"Zergling";"Larva";144;1
"Unit";"Zergling";"Larva";144;1
"Unit";"Zergling";"Larva";144;1
"Unit";"Zergling";"Larva";144;1
"Unit";"Zergling";"Larva";144;1
"Unit";"Zergling";"Larva";144;1
"Unit";"Zergling";"Larva";144;1
"Unit";"Zergling";"Larva";144;1
"Unit";"Zergling";"Larva";144;1
"Unit";"Zergling";"Larva";144;1
"Unit";"Zergling";"Larva";144;1
"Unit";"Zergling";"Larva";144;1
"Unit";"Zergling";"Larva";144;1
"Unit";"Zergling";"Larva";144;1
"Unit";"Zergling";"Larva";144;1
"Unit";"Zergling";"Larva";144;1
"Unit";"Zergling";"Larva";144;1
"Unit";"Zergling";"Larva";144;1
"Unit";"Zergling";"Larva";144;1
"Unit";"Zergling";"Larva";144;1
"Unit";"Zergling";"Larva";144;1
"Unit";"Zergling";"Larva";144;1
"Building";"Extractor";NA;144;0
"Building";"Extractor";NA;144;0
"Unit";"Zergling";"Larva";144;1
"Unit";"Zergling";"Larva";144;1
"Building";"CreepTumor";NA;144;0
"Unit";"Overlord";"Larva";144;0
"Building";"CreepTumor";NA;144;0
"Building";"CreepTumor";NA;144;0
"Building";"CreepTumor";NA;144;0
"Unit";"Overlord";"Larva";144;0
"Building";"CreepTumor";NA;144;0
"Unit";"Zergling";"Larva";144;1
"Unit";"Zergling";"Larva";144;1
"Unit";"Zergling";"Larva";144;1
"Unit";"Zergling";"Larva";144;1
"Unit";"Baneling";"Zergling";170;0
"Unit";"Baneling";"Zergling";170;0
"Unit";"Baneling";"Zergling";170;0
"Unit";"Baneling";"Zergling";170;0
"Unit";"Zergling";"Larva";170;1
"Unit";"Zergling";"Larva";170;1
"Unit";"Zergling";"Larva";170;1
"Unit";"Zergling";"Larva";170;1
"Unit";"Zergling";"Larva";170;1
"Unit";"Zergling";"Larva";170;1
"Unit";"Baneling";"Zergling";174;0
"Unit";"Baneling";"Zergling";174;0
"Unit";"Baneling";"Zergling";174;0
"Unit";"Baneling";"Zergling";174;0
"Unit";"Baneling";"Zergling";174;0
"Unit";"Baneling";"Zergling";174;0
"Unit";"Baneling";"Zergling";174;0
"Unit";"Hydralisk";"Larva";170;2
"Unit";"Hydralisk";"Larva";170;2
"Unit";"Hydralisk";"Larva";170;2
"Unit";"Hydralisk";"Larva";170;2
"Unit";"Hydralisk";"Larva";170;2
"Unit";"Hydralisk";"Larva";170;2
"Unit";"Hydralisk";"Larva";170;2
"Unit";"Hydralisk";"Larva";170;2
"Unit";"Zergling";"Larva";174;1
"Unit";"Zergling";"Larva";174;1
"Unit";"Zergling";"Larva";174;1
"Unit";"Zergling";"Larva";174;1
"Unit";"Zergling";"Larva";174;1
"Unit";"Zergling";"Larva";174;1
"Unit";"Zergling";"Larva";174;1
"Unit";"Zergling";"Larva";174;1
"Unit";"Zergling";"Larva";174;1
"Unit";"Zergling";"Larva";174;1
"Unit";"Zergling";"Larva";174;1
"Unit";"Zergling";"Larva";174;1
"Unit";"Zergling";"Larva";174;1
"Unit";"Zergling";"Larva";174;1
"Building";"CreepTumorQueen";NA;210;0
"Upgrade";"EvolveMuscularAugments";"HydraliskDen";170;0
"Building";"CreepTumor";NA;210;0
"Building";"CreepTumorQueen";NA;210;0
"Building";"CreepTumor";NA;210;0
"Building";"CreepTumor";NA;210;0
"Building";"CreepTumor";NA;210;0
"Building";"CreepTumor";NA;210;0
"Unit";"Zergling";"Larva";210;1
"Unit";"Zergling";"Larva";210;1
"Unit";"Zergling";"Larva";210;1
"Unit";"Zergling";"Larva";210;1
"Unit";"Baneling";"Zergling";210;0
"Unit";"Baneling";"Zergling";210;0
"Unit";"Baneling";"Zergling";210;0
"Unit";"Baneling";"Zergling";210;0
"Unit";"Hydralisk";"Larva";210;2
"Unit";"Hydralisk";"Larva";210;2
"Unit";"Hydralisk";"Larva";210;2
"Unit";"Hydralisk";"Larva";210;2
"Building";"CreepTumor";NA;222;0
"Building";"CreepTumor";NA;222;0
"Building";"CreepTumor";NA;222;0
"Building";"CreepTumor";NA;222;0
"Building";"CreepTumor";NA;225;0
"Unit";"Zergling";"Larva";222;1
"Unit";"Zergling";"Larva";222;1
"Unit";"Zergling";"Larva";222;1
"Unit";"Zergling";"Larva";222;1
"Unit";"Zergling";"Larva";222;1
"Unit";"Zergling";"Larva";222;1
"Unit";"Zergling";"Larva";222;1
"Unit";"Zergling";"Larva";222;1
"Unit";"Zergling";"Larva";222;1
"Unit";"Zergling";"Larva";222;1
"Unit";"Zergling";"Larva";222;1
"Unit";"Zergling";"Larva";222;1
"Unit";"Zergling";"Larva";222;1
"Unit";"Zergling";"Larva";222;1
"Unit";"Zergling";"Larva";222;1
"Unit";"Zergling";"Larva";222;1
"Unit";"Zergling";"Larva";222;1
"Unit";"Zergling";"Larva";222;1
"Building";"CreepTumor";NA;225;0
"Building";"CreepTumor";NA;225;0
"Building";"CreepTumorQueen";NA;225;0
"Building";"CreepTumorQueen";NA;225;0
"Building";"UltraliskCavern";NA;210;0
"Building";"CreepTumor";NA;243;0
"Unit";"Infestor";"Larva";225;2
"Unit";"Infestor";"Larva";225;2
"Unit";"Infestor";"Larva";225;2
"Unit";"Infestor";"Larva";227;2
"Building";"CreepTumor";NA;251;0
"Building";"CreepTumor";NA;251;0
"Unit";"Overlord";"Larva";251;0
"Unit";"Overlord";"Larva";251;0
"Unit";"Overlord";"Larva";251;0
"Building";"CreepTumor";NA;251;0
"Building";"Hatchery";NA;225;0
"Building";"CreepTumor";NA;251;0
"Building";"CreepTumor";NA;251;0
"Building";"CreepTumor";NA;251;0
"Unit";"Zergling";"Larva";251;1
"Unit";"Zergling";"Larva";251;1
"Unit";"Zergling";"Larva";251;1
"Unit";"Zergling";"Larva";251;1
"Unit";"Zergling";"Larva";251;1
"Unit";"Zergling";"Larva";251;1
"Unit";"Zergling";"Larva";251;1
"Unit";"Zergling";"Larva";251;1
"Unit";"Zergling";"Larva";251;1
"Unit";"Zergling";"Larva";251;1
"Unit";"Zergling";"Larva";251;1
"Unit";"Zergling";"Larva";251;1
"Unit";"Zergling";"Larva";251;1
"Unit";"Zergling";"Larva";251;1
"Unit";"Zergling";"Larva";251;1
"Unit";"Zergling";"Larva";251;1
"Unit";"Zergling";"Larva";251;1
"Unit";"Zergling";"Larva";251;1
"Building";"CreepTumorQueen";NA;251;0
"Building";"CreepTumorQueen";NA;251;0
"Unit";"Overlord";"Larva";251;0
"Unit";"Overlord";"Larva";251;0
"Unit";"Overlord";"Larva";251;0
"Unit";"Overlord";"Larva";251;0
"Unit";"Ultralisk";"Larva";251;6
"Unit";"Queen";"Hatchery";251;2
"Unit";"Ultralisk";"Larva";251;6
"Unit";"Ultralisk";"Larva";251;6
"Building";"CreepTumorQueen";NA;269;0
"Upgrade";"ZergMeleeWeaponsLevel2";"EvolutionChamber";222;0
"Upgrade";"ZergGroundArmorsLevel2";"EvolutionChamber";222;0
"Unit";"Overlord";"Larva";251;0
"Building";"CreepTumor";NA;269;0
"Unit";"Zergling";"Larva";269;1
"Unit";"Zergling";"Larva";269;1
"Unit";"Zergling";"Larva";269;1
"Unit";"Zergling";"Larva";269;1
"Unit";"Zergling";"Larva";269;1
"Unit";"Zergling";"Larva";269;1
"Unit";"Zergling";"Larva";269;1
"Unit";"Zergling";"Larva";269;1
"Building";"CreepTumor";NA;289;0
"Unit";"Baneling";"Zergling";289;0
"Unit";"Baneling";"Zergling";289;0
"Unit";"Baneling";"Zergling";289;0
"Unit";"Baneling";"Zergling";289;0
"Unit";"Baneling";"Zergling";289;0
"Unit";"Baneling";"Zergling";289;0
"Building";"CreepTumor";NA;289;0
"Building";"CreepTumor";NA;289;0
"Building";"CreepTumor";NA;289;0
"Unit";"Ultralisk";"Larva";251;6
"Unit";"Zergling";"Larva";289;1
"Unit";"Zergling";"Larva";289;1
"Unit";"Zergling";"Larva";289;1
"Unit";"Zergling";"Larva";289;1
"Unit";"Zergling";"Larva";289;1
"Unit";"Zergling";"Larva";289;1
"Unit";"Zergling";"Larva";289;1
"Unit";"Zergling";"Larva";289;1
"Unit";"Ultralisk";"Larva";269;6
"Upgrade";"ChitinousPlating";"UltraliskCavern";251;0
"Upgrade";"Burrow";"Hatchery";269;0
"Building";"CreepTumorQueen";NA;311;0
"Unit";"Ultralisk";"Larva";289;6
"Building";"CreepTumorQueen";NA;317;0
"Unit";"Baneling";"Zergling";311;0
"Building";"CreepTumorQueen";NA;317;0
"Unit";"Baneling";"Zergling";311;0
"Unit";"Baneling";"Zergling";311;0
"Unit";"Baneling";"Zergling";311;0
"Unit";"Baneling";"Zergling";311;0
"Unit";"Zergling";"Larva";311;1
"Unit";"Zergling";"Larva";311;1
"Unit";"Zergling";"Larva";311;1
"Unit";"Zergling";"Larva";311;1
"Unit";"Zergling";"Larva";311;1
"Unit";"Zergling";"Larva";311;1
"Unit";"Baneling";"Zergling";317;0
"Unit";"Zergling";"Larva";311;1
"Unit";"Zergling";"Larva";311;1
"Unit";"Zergling";"Larva";311;1
"Unit";"Zergling";"Larva";311;1
"Unit";"Zergling";"Larva";311;1
"Unit";"Zergling";"Larva";311;1
"Unit";"Zergling";"Larva";311;1
"Unit";"Zergling";"Larva";311;1
"Building";"CreepTumor";NA;317;0
"Building";"CreepTumor";NA;317;0
"Building";"CreepTumor";NA;317;0
"Building";"CreepTumor";NA;317;0
"Building";"CreepTumor";NA;317;0
"Building";"CreepTumor";NA;317;0
"Unit";"Zergling";"Larva";323;1
"Unit";"Zergling";"Larva";323;1
"Unit";"Zergling";"Larva";323;1
"Unit";"Zergling";"Larva";323;1
"Unit";"Zergling";"Larva";323;1
"Unit";"Zergling";"Larva";323;1
"Unit";"Zergling";"Larva";323;1
"Unit";"Zergling";"Larva";323;1
"Unit";"Zergling";"Larva";323;1
"Unit";"Zergling";"Larva";323;1
"Unit";"Zergling";"Larva";323;1
"Unit";"Zergling";"Larva";323;1
"Unit";"Zergling";"Larva";323;1
"Unit";"Zergling";"Larva";323;1
"Unit";"Baneling";"Zergling";337;0
"Unit";"Baneling";"Zergling";337;0
"Unit";"Baneling";"Zergling";337;0
"Unit";"Baneling";"Zergling";337;0
"Unit";"Baneling";"Zergling";337;0
"Unit";"Baneling";"Zergling";337;0
"Unit";"Baneling";"Zergling";337;0
"Unit";"Baneling";"Zergling";337;0
"Unit";"Zergling";"Larva";351;1
"Unit";"Zergling";"Larva";351;1
"Unit";"Zergling";"Larva";351;1
"Unit";"Zergling";"Larva";351;1
"Unit";"Zergling";"Larva";351;1
"Unit";"Zergling";"Larva";351;1
"Unit";"Zergling";"Larva";351;1
"Unit";"Zergling";"Larva";351;1
"Unit";"Zergling";"Larva";351;1
"Unit";"Zergling";"Larva";351;1
"Unit";"Zergling";"Larva";351;1
"Unit";"Zergling";"Larva";351;1
"Unit";"Zergling";"Larva";351;1
"Unit";"Zergling";"Larva";351;1
"Unit";"Zergling";"Larva";351;1
"Unit";"Zergling";"Larva";351;1
"Unit";"Zergling";"Larva";351;1
"Unit";"Zergling";"Larva";351;1
"Unit";"Zergling";"Larva";351;1
"Unit";"Zergling";"Larva";351;1
