"type";"unit_name";"on_building";"total_supply";"supply"
"Unit";"Overlord";"Larva";15;0
"Building";"SpawningPool";NA;12;0
"Unit";"Zergling";"Larva";15;1
"Unit";"Zergling";"Larva";15;1
"Unit";"Zergling";"Larva";15;1
"Unit";"Zergling";"Larva";15;1
"Unit";"Zergling";"Larva";15;1
"Unit";"Zergling";"Larva";15;1
"Unit";"Queen";"Hatchery";15;2
"Unit";"Overlord";"Larva";25;0
"Building";"Hatchery";NA;21;0
"Unit";"Overlord";"Larva";34;0
"Unit";"Queen";"Hatchery";32;2
"Unit";"Overlord";"Larva";39;0
"Building";"CreepTumorQueen";NA;42;0
"Unit";"Queen";"Hatchery";39;2
"Building";"Hatchery";NA;32;0
"Unit";"Queen";"Hatchery";42;2
"Building";"CreepTumorQueen";NA;51;0
"Building";"CreepTumor";NA;51;0
"Building";"CreepTumorQueen";NA;57;0
"Unit";"Queen";"Hatchery";51;2
"Building";"Extractor";NA;57;0
"Building";"Extractor";NA;57;0
"Building";"CreepTumor";NA;63;0
"Building";"SporeCrawler";NA;60;0
"Building";"SporeCrawler";NA;61;0
"Building";"SporeCrawler";NA;62;0
"Building";"CreepTumorQueen";NA;65;0
"Building";"CreepTumorQueen";NA;67;0
"Unit";"Overlord";"Larva";67;0
"Unit";"Overlord";"Larva";67;0
"Unit";"Overlord";"Larva";70;0
"Unit";"Overlord";"Larva";70;0
"Building";"CreepTumorQueen";NA;70;0
"Building";"CreepTumor";NA;70;0
"Building";"CreepTumor";NA;70;0
"Building";"Hatchery";NA;53;0
"Building";"CreepTumor";NA;71;0
"Building";"CreepTumor";NA;71;0
"Building";"CreepTumorQueen";NA;71;0
"Building";"CreepTumor";NA;71;0
"Unit";"Zergling";"Larva";89;1
"Unit";"Zergling";"Larva";89;1
"Unit";"Zergling";"Larva";89;1
"Unit";"Zergling";"Larva";89;1
"Unit";"Zergling";"Larva";89;1
"Unit";"Zergling";"Larva";89;1
"Unit";"Zergling";"Larva";89;1
"Unit";"Zergling";"Larva";89;1
"Unit";"Zergling";"Larva";89;1
"Unit";"Zergling";"Larva";89;1
"Unit";"Zergling";"Larva";89;1
"Unit";"Zergling";"Larva";89;1
"Unit";"Zergling";"Larva";89;1
"Unit";"Zergling";"Larva";89;1
"Unit";"Zergling";"Larva";89;1
"Unit";"Zergling";"Larva";89;1
"Building";"Extractor";NA;89;0
"Building";"Extractor";NA;89;0
"Unit";"Overlord";"Larva";89;0
"Unit";"Overlord";"Larva";89;0
"Building";"CreepTumor";NA;105;0
"Building";"CreepTumor";NA;105;0
"Building";"CreepTumor";NA;105;0
"Building";"BanelingNest";NA;86;0
"Unit";"Zergling";"Larva";99;1
"Unit";"Zergling";"Larva";99;1
"Unit";"Zergling";"Larva";101;1
"Unit";"Zergling";"Larva";101;1
"Unit";"Zergling";"Larva";101;1
"Unit";"Zergling";"Larva";101;1
"Building";"CreepTumor";NA;105;0
"Building";"CreepTumor";NA;105;0
"Building";"CreepTumor";NA;105;0
"Unit";"Queen";"Hatchery";89;2
"Unit";"Queen";"Hatchery";89;2
"Unit";"Queen";"Hatchery";89;2
"Building";"EvolutionChamber";NA;89;0
"Building";"EvolutionChamber";NA;91;0
"Unit";"Baneling";"Zergling";111;0
"Unit";"Baneling";"Zergling";111;0
"Unit";"Baneling";"Zergling";111;0
"Unit";"Baneling";"Zergling";111;0
"Unit";"Baneling";"Zergling";111;0
"Unit";"Baneling";"Zergling";111;0
"Unit";"Baneling";"Zergling";111;0
"Unit";"Baneling";"Zergling";111;0
"Unit";"Baneling";"Zergling";111;0
"Unit";"Baneling";"Zergling";111;0
"Unit";"Baneling";"Zergling";111;0
"Building";"Extractor";NA;117;0
"Building";"Extractor";NA;117;0
"Building";"Extractor";NA;140;0
"Building";"Extractor";NA;140;0
"Building";"InfestationPit";NA;126;0
"Building";"CreepTumor";NA;149;0
"Building";"CreepTumor";NA;149;0
"Building";"CreepTumor";NA;149;0
"Building";"CreepTumor";NA;154;0
"Building";"CreepTumor";NA;155;0
"Building";"CreepTumor";NA;156;0
"Building";"SpineCrawler";NA;140;0
"Building";"SpineCrawler";NA;140;0
"Building";"SpineCrawler";NA;140;0
"Building";"SpineCrawler";NA;140;0
"Building";"SpineCrawler";NA;140;0
"Unit";"Overlord";"Larva";156;0
"Unit";"Overlord";"Larva";156;0
"Unit";"Overlord";"Larva";156;0
"Unit";"Overlord";"Larva";156;0
"Unit";"Overlord";"Larva";156;0
"Unit";"Overlord";"Larva";156;0
"Building";"SpineCrawler";NA;149;0
"Building";"SpineCrawler";NA;149;0
"Building";"CreepTumorQueen";NA;156;0
"Unit";"Zergling";"Larva";156;1
"Unit";"Zergling";"Larva";156;1
"Building";"SpineCrawler";NA;156;0
"Unit";"Zergling";"Larva";156;1
"Unit";"Zergling";"Larva";156;1
"Unit";"Zergling";"Larva";156;1
"Unit";"Zergling";"Larva";156;1
"Unit";"Zergling";"Larva";156;1
"Unit";"Zergling";"Larva";156;1
"Building";"SpineCrawler";NA;156;0
"Building";"CreepTumorQueen";NA;156;0
"Building";"CreepTumorQueen";NA;156;0
"Unit";"Overlord";"Larva";156;0
"Unit";"Zergling";"Larva";156;1
"Unit";"Zergling";"Larva";156;1
"Unit";"Overlord";"Larva";156;0
"Unit";"Zergling";"Larva";156;1
"Unit";"Zergling";"Larva";156;1
"Unit";"Zergling";"Larva";156;1
"Unit";"Zergling";"Larva";156;1
"Unit";"Zergling";"Larva";156;1
"Unit";"Zergling";"Larva";156;1
"Unit";"Zergling";"Larva";156;1
"Unit";"Zergling";"Larva";156;1
"Unit";"Zergling";"Larva";156;1
"Unit";"Zergling";"Larva";156;1
"Unit";"Zergling";"Larva";156;1
"Unit";"Zergling";"Larva";156;1
"Unit";"Zergling";"Larva";156;1
"Unit";"Zergling";"Larva";156;1
"Unit";"Zergling";"Larva";156;1
"Unit";"Zergling";"Larva";156;1
"Unit";"Zergling";"Larva";156;1
"Unit";"Zergling";"Larva";156;1
"Unit";"Zergling";"Larva";156;1
"Unit";"Zergling";"Larva";156;1
"Unit";"Zergling";"Larva";156;1
"Unit";"Zergling";"Larva";156;1
"Upgrade";"Burrow";"Hatchery";143;0
"Building";"Hatchery";NA;140;0
"Unit";"Zergling";"Larva";156;1
"Unit";"Zergling";"Larva";156;1
"Unit";"Zergling";"Larva";156;1
"Unit";"Zergling";"Larva";156;1
"Unit";"Zergling";"Larva";156;1
"Unit";"Zergling";"Larva";156;1
"Unit";"Zergling";"Larva";156;1
"Unit";"Zergling";"Larva";156;1
"Unit";"Zergling";"Larva";164;1
"Unit";"Zergling";"Larva";164;1
"Unit";"Zergling";"Larva";164;1
"Unit";"Zergling";"Larva";164;1
"Unit";"Zergling";"Larva";164;1
"Unit";"Zergling";"Larva";164;1
"Unit";"Zergling";"Larva";164;1
"Unit";"Zergling";"Larva";164;1
"Unit";"Baneling";"Zergling";164;0
"Unit";"Baneling";"Zergling";164;0
"Unit";"Baneling";"Zergling";164;0
"Unit";"Baneling";"Zergling";164;0
"Unit";"Baneling";"Zergling";164;0
"Unit";"Baneling";"Zergling";164;0
"Unit";"Baneling";"Zergling";164;0
"Unit";"Baneling";"Zergling";164;0
"Upgrade";"ZergGroundArmorsLevel1";"EvolutionChamber";140;0
"Building";"CreepTumor";NA;204;0
"Building";"CreepTumor";NA;204;0
"Building";"CreepTumor";NA;204;0
"Building";"CreepTumor";NA;204;0
"Building";"CreepTumor";NA;204;0
"Building";"CreepTumor";NA;210;0
"Upgrade";"ZergMissileWeaponsLevel1";"EvolutionChamber";153;0
"Building";"SpineCrawler";NA;204;0
"Building";"CreepTumor";NA;210;0
"Building";"CreepTumor";NA;210;0
"Building";"CreepTumor";NA;210;0
"Building";"CreepTumor";NA;210;0
"Building";"CreepTumor";NA;210;0
"Building";"CreepTumor";NA;210;0
"Building";"CreepTumorQueen";NA;210;0
"Building";"CreepTumorQueen";NA;210;0
"Building";"CreepTumor";NA;210;0
"Building";"CreepTumor";NA;210;0
"Building";"CreepTumor";NA;210;0
"Building";"UltraliskCavern";NA;210;0
"Building";"Extractor";NA;210;0
"Upgrade";"NeuralParasite";"InfestationPit";210;0
"Building";"CreepTumor";NA;210;0
"Building";"CreepTumor";NA;210;0
"Unit";"Overlord";"Larva";210;0
"Unit";"Overlord";"Larva";210;0
"Unit";"Overlord";"Larva";210;0
"Building";"CreepTumor";NA;210;0
"Building";"CreepTumor";NA;210;0
"Building";"CreepTumor";NA;210;0
"Building";"CreepTumorQueen";NA;210;0
"Building";"CreepTumorQueen";NA;210;0
"Building";"CreepTumorQueen";NA;210;0
"Building";"CreepTumorQueen";NA;210;0
"Building";"CreepTumorQueen";NA;210;0
"Building";"CreepTumorQueen";NA;210;0
"Building";"CreepTumorQueen";NA;210;0
"Building";"CreepTumorQueen";NA;210;0
"Building";"Hatchery";NA;210;0
"Unit";"Ultralisk";"Larva";210;6
"Unit";"Ultralisk";"Larva";210;6
"Building";"CreepTumor";NA;210;0
"Building";"CreepTumor";NA;210;0
"Building";"Hatchery";NA;210;0
"Unit";"Overlord";"Larva";210;0
"Unit";"Overlord";"Larva";210;0
"Unit";"Overlord";"Larva";210;0
"Unit";"Overlord";"Larva";210;0
"Unit";"Overlord";"Larva";210;0
"Upgrade";"ZergGroundArmorsLevel2";"EvolutionChamber";210;0
"Upgrade";"ZergMissileWeaponsLevel2";"EvolutionChamber";210;0
"Upgrade";"ChitinousPlating";"UltraliskCavern";210;0
"Building";"Hatchery";NA;210;0
"Building";"Hatchery";NA;210;0
"Unit";"Ultralisk";"Larva";222;6
"Unit";"Ultralisk";"Larva";222;6
"Unit";"Ultralisk";"Larva";222;6
"Unit";"Ultralisk";"Larva";222;6
"Unit";"Ultralisk";"Larva";222;6
"Unit";"Ultralisk";"Larva";222;6
"Unit";"Ultralisk";"Larva";222;6
"Unit";"Ultralisk";"Larva";222;6
"Unit";"Ultralisk";"Larva";222;6
"Building";"Hatchery";NA;222;0
"Unit";"Ultralisk";"Larva";222;6
"Building";"Extractor";NA;222;0
"Building";"Extractor";NA;222;0
"Building";"Extractor";NA;285;0
"Building";"Extractor";NA;285;0
"Unit";"Zergling";"Larva";285;1
"Unit";"Zergling";"Larva";285;1
"Unit";"Zergling";"Larva";285;1
"Unit";"Zergling";"Larva";285;1
"Unit";"Zergling";"Larva";285;1
"Unit";"Zergling";"Larva";285;1
"Unit";"Zergling";"Larva";285;1
"Unit";"Zergling";"Larva";285;1
"Unit";"Zergling";"Larva";285;1
"Unit";"Zergling";"Larva";285;1
"Unit";"Zergling";"Larva";285;1
"Unit";"Zergling";"Larva";285;1
"Unit";"Zergling";"Larva";285;1
"Unit";"Zergling";"Larva";285;1
"Unit";"Zergling";"Larva";285;1
"Unit";"Zergling";"Larva";285;1
"Unit";"Zergling";"Larva";285;1
"Unit";"Zergling";"Larva";285;1
"Unit";"Zergling";"Larva";285;1
"Unit";"Zergling";"Larva";285;1
"Unit";"Zergling";"Larva";285;1
"Unit";"Zergling";"Larva";285;1
"Unit";"Zergling";"Larva";285;1
"Unit";"Zergling";"Larva";285;1
"Unit";"Zergling";"Larva";285;1
"Unit";"Zergling";"Larva";285;1
"Unit";"Zergling";"Larva";285;1
"Unit";"Zergling";"Larva";285;1
"Unit";"Zergling";"Larva";285;1
"Unit";"Zergling";"Larva";285;1
"Unit";"Zergling";"Larva";285;1
"Unit";"Zergling";"Larva";285;1
"Unit";"Zergling";"Larva";285;1
"Unit";"Zergling";"Larva";285;1
"Unit";"Zergling";"Larva";285;1
"Unit";"Zergling";"Larva";285;1
"Unit";"Zergling";"Larva";285;1
"Unit";"Zergling";"Larva";285;1
"Unit";"Zergling";"Larva";285;1
"Unit";"Zergling";"Larva";285;1
"Unit";"Zergling";"Larva";285;1
"Unit";"Zergling";"Larva";285;1
"Unit";"Zergling";"Larva";285;1
"Unit";"Zergling";"Larva";285;1
"Unit";"Zergling";"Larva";285;1
"Unit";"Zergling";"Larva";285;1
"Unit";"Zergling";"Larva";285;1
"Unit";"Zergling";"Larva";285;1
"Unit";"Zergling";"Larva";285;1
"Unit";"Zergling";"Larva";285;1
"Unit";"Zergling";"Larva";285;1
"Unit";"Zergling";"Larva";285;1
"Unit";"Zergling";"Larva";285;1
"Unit";"Zergling";"Larva";285;1
"Unit";"Zergling";"Larva";285;1
"Unit";"Zergling";"Larva";285;1
"Unit";"Zergling";"Larva";285;1
"Unit";"Zergling";"Larva";285;1
"Unit";"Zergling";"Larva";285;1
"Unit";"Zergling";"Larva";285;1
"Building";"Spire";NA;285;0
"Unit";"Corruptor";"Larva";345;2
"Unit";"Corruptor";"Larva";345;2
"Unit";"Corruptor";"Larva";345;2
"Unit";"Corruptor";"Larva";345;2
"Building";"Extractor";NA;345;0
"Building";"CreepTumor";NA;356;0
"Building";"CreepTumor";NA;356;0
"Building";"Hatchery";NA;345;0
"Building";"CreepTumor";NA;356;0
"Building";"CreepTumor";NA;356;0
"Building";"CreepTumor";NA;356;0
"Building";"CreepTumor";NA;356;0
"Building";"CreepTumor";NA;356;0
"Building";"Extractor";NA;356;0
"Building";"CreepTumor";NA;356;0
"Building";"Extractor";NA;356;0
"Building";"CreepTumor";NA;356;0
"Building";"CreepTumor";NA;356;0
"Building";"CreepTumor";NA;359;0
"Building";"CreepTumor";NA;359;0
"Unit";"Baneling";"Zergling";359;0
"Unit";"Baneling";"Zergling";359;0
"Unit";"Baneling";"Zergling";359;0
"Unit";"Baneling";"Zergling";359;0
"Unit";"Baneling";"Zergling";359;0
"Unit";"Baneling";"Zergling";359;0
"Unit";"Baneling";"Zergling";359;0
"Unit";"Baneling";"Zergling";359;0
"Unit";"Baneling";"Zergling";359;0
"Unit";"Baneling";"Zergling";359;0
"Unit";"Baneling";"Zergling";359;0
"Unit";"Baneling";"Zergling";359;0
"Unit";"Baneling";"Zergling";359;0
"Unit";"Baneling";"Zergling";359;0
"Unit";"Baneling";"Zergling";359;0
"Unit";"Baneling";"Zergling";359;0
"Unit";"Baneling";"Zergling";359;0
"Unit";"Baneling";"Zergling";359;0
"Unit";"Baneling";"Zergling";359;0
"Unit";"Baneling";"Zergling";359;0
"Unit";"Baneling";"Zergling";359;0
"Unit";"Baneling";"Zergling";359;0
"Unit";"Baneling";"Zergling";359;0
"Unit";"Zergling";"Larva";359;1
"Unit";"Zergling";"Larva";359;1
"Unit";"Zergling";"Larva";359;1
"Unit";"Zergling";"Larva";359;1
"Unit";"Zergling";"Larva";359;1
"Unit";"Zergling";"Larva";359;1
"Unit";"Zergling";"Larva";359;1
"Unit";"Zergling";"Larva";359;1
"Unit";"Zergling";"Larva";359;1
"Unit";"Zergling";"Larva";359;1
"Unit";"Zergling";"Larva";359;1
"Unit";"Zergling";"Larva";359;1
"Unit";"Zergling";"Larva";359;1
"Unit";"Zergling";"Larva";359;1
"Unit";"Zergling";"Larva";359;1
"Unit";"Zergling";"Larva";359;1
"Unit";"Zergling";"Larva";359;1
"Unit";"Zergling";"Larva";359;1
"Unit";"Zergling";"Larva";359;1
"Unit";"Zergling";"Larva";359;1
"Unit";"Zergling";"Larva";359;1
"Unit";"Zergling";"Larva";359;1
"Unit";"Zergling";"Larva";359;1
"Unit";"Zergling";"Larva";359;1
"Unit";"Zergling";"Larva";359;1
"Unit";"Zergling";"Larva";359;1
"Unit";"Zergling";"Larva";359;1
"Unit";"Zergling";"Larva";359;1
"Unit";"Zergling";"Larva";359;1
"Unit";"Zergling";"Larva";359;1
"Unit";"Zergling";"Larva";359;1
"Unit";"Zergling";"Larva";359;1
"Unit";"Zergling";"Larva";359;1
"Unit";"Zergling";"Larva";359;1
"Unit";"Zergling";"Larva";359;1
"Unit";"Zergling";"Larva";359;1
"Unit";"Zergling";"Larva";359;1
"Unit";"Zergling";"Larva";359;1
"Unit";"Zergling";"Larva";359;1
"Unit";"Zergling";"Larva";359;1
"Unit";"Ultralisk";"Larva";359;6
"Unit";"Ultralisk";"Larva";359;6
"Unit";"Ultralisk";"Larva";359;6
"Unit";"Ultralisk";"Larva";359;6
"Unit";"Ultralisk";"Larva";359;6
