"type";"unit_name";"on_building";"total_supply";"supply"
"Unit";"Overlord";"Larva";14;0
"Building";"Extractor";NA;16;0
"Building";"Hatchery";NA;16;0
"Building";"SpawningPool";NA;18;0
"Unit";"Overlord";"Larva";22;0
"Unit";"Zergling";"Larva";22;1
"Unit";"Zergling";"Larva";22;1
"Unit";"Zergling";"Larva";22;1
"Unit";"Zergling";"Larva";22;1
"Unit";"Queen";"Hatchery";22;2
"Unit";"Queen";"Hatchery";22;2
"Unit";"Queen";"Hatchery";33;2
"Building";"CreepTumorQueen";NA;42;0
"Unit";"Zergling";"Larva";40;1
"Unit";"Zergling";"Larva";40;1
"Unit";"Zergling";"Larva";40;1
"Unit";"Zergling";"Larva";40;1
"Unit";"Overlord";"Larva";40;0
"Building";"CreepTumorQueen";NA;42;0
"Unit";"Overlord";"Larva";42;0
"Unit";"Overlord";"Larva";42;0
"Building";"CreepTumorQueen";NA;46;0
"Building";"CreepTumor";NA;46;0
"Unit";"Queen";"Hatchery";46;2
"Building";"Hatchery";NA;40;0
"Unit";"Overlord";"Larva";55;0
"Building";"Extractor";NA;55;0
"Building";"CreepTumor";NA;60;0
"Building";"CreepTumorQueen";NA;65;0
"Building";"CreepTumorQueen";NA;66;0
"Building";"BanelingNest";NA;57;0
"Unit";"Zergling";"Larva";66;1
"Unit";"Zergling";"Larva";66;1
"Unit";"Zergling";"Larva";66;1
"Unit";"Zergling";"Larva";66;1
"Unit";"Zergling";"Larva";66;1
"Unit";"Zergling";"Larva";66;1
"Unit";"Zergling";"Larva";66;1
"Unit";"Zergling";"Larva";66;1
"Unit";"Zergling";"Larva";66;1
"Unit";"Zergling";"Larva";66;1
"Unit";"Zergling";"Larva";66;1
"Unit";"Zergling";"Larva";66;1
"Unit";"Queen";"Hatchery";60;2
"Building";"EvolutionChamber";NA;66;0
"Unit";"Zergling";"Larva";66;1
"Unit";"Zergling";"Larva";66;1
"Building";"EvolutionChamber";NA;66;0
"Unit";"Overlord";"Larva";67;0
"Building";"CreepTumor";NA;68;0
"Unit";"Zergling";"Larva";68;1
"Unit";"Zergling";"Larva";68;1
"Unit";"Zergling";"Larva";68;1
"Unit";"Zergling";"Larva";68;1
"Unit";"Zergling";"Larva";68;1
"Unit";"Zergling";"Larva";68;1
"Unit";"Zergling";"Larva";68;1
"Unit";"Zergling";"Larva";68;1
"Unit";"Baneling";"Zergling";82;0
"Unit";"Baneling";"Zergling";82;0
"Unit";"Baneling";"Zergling";82;0
"Unit";"Overlord";"Larva";80;0
"Unit";"Baneling";"Zergling";82;0
"Unit";"Zergling";"Larva";82;1
"Unit";"Zergling";"Larva";82;1
"Unit";"Zergling";"Larva";82;1
"Unit";"Zergling";"Larva";82;1
"Unit";"Zergling";"Larva";84;1
"Unit";"Zergling";"Larva";84;1
"Building";"CreepTumor";NA;92;0
"Building";"CreepTumor";NA;92;0
"Unit";"Overlord";"Larva";92;0
"Unit";"Overlord";"Larva";92;0
"Unit";"Queen";"Hatchery";80;2
"Building";"CreepTumorQueen";NA;98;0
"Building";"CreepTumorQueen";NA;100;0
"Building";"CreepTumor";NA;108;0
"Building";"CreepTumor";NA;108;0
"Building";"CreepTumorQueen";NA;108;0
"Unit";"Queen";"Hatchery";98;2
"Building";"CreepTumor";NA;108;0
"Building";"Extractor";NA;108;0
"Building";"Extractor";NA;108;0
"Unit";"Overlord";"Larva";108;0
"Unit";"Overlord";"Larva";123;0
"Building";"Extractor";NA;123;0
"Building";"Extractor";NA;123;0
"Building";"CreepTumor";NA;126;0
"Building";"CreepTumorQueen";NA;132;0
"Unit";"Baneling";"Zergling";132;0
"Unit";"Baneling";"Zergling";132;0
"Unit";"Zergling";"Larva";132;1
"Unit";"Zergling";"Larva";132;1
"Building";"CreepTumor";NA;132;0
"Unit";"Zergling";"Larva";132;1
"Unit";"Zergling";"Larva";132;1
"Unit";"Zergling";"Larva";132;1
"Unit";"Zergling";"Larva";132;1
"Unit";"Zergling";"Larva";132;1
"Unit";"Zergling";"Larva";132;1
"Unit";"Zergling";"Larva";132;1
"Unit";"Zergling";"Larva";132;1
"Unit";"Zergling";"Larva";132;1
"Unit";"Zergling";"Larva";132;1
"Building";"CreepTumor";NA;132;0
"Building";"CreepTumor";NA;132;0
"Unit";"Zergling";"Larva";132;1
"Unit";"Zergling";"Larva";132;1
"Unit";"Zergling";"Larva";132;1
"Unit";"Zergling";"Larva";132;1
"Unit";"Zergling";"Larva";132;1
"Unit";"Zergling";"Larva";132;1
"Unit";"Zergling";"Larva";132;1
"Unit";"Zergling";"Larva";132;1
"Unit";"Zergling";"Larva";132;1
"Unit";"Zergling";"Larva";132;1
"Unit";"Zergling";"Larva";132;1
"Unit";"Zergling";"Larva";132;1
"Unit";"Zergling";"Larva";132;1
"Unit";"Zergling";"Larva";132;1
"Unit";"Zergling";"Larva";144;1
"Unit";"Zergling";"Larva";144;1
"Unit";"Zergling";"Larva";144;1
"Unit";"Zergling";"Larva";144;1
"Unit";"Zergling";"Larva";144;1
"Unit";"Zergling";"Larva";144;1
"Unit";"Zergling";"Larva";144;1
"Unit";"Zergling";"Larva";144;1
"Upgrade";"ZergMeleeWeaponsLevel1";"EvolutionChamber";108;0
"Unit";"Zergling";"Larva";144;1
"Unit";"Zergling";"Larva";144;1
"Upgrade";"ZergGroundArmorsLevel1";"EvolutionChamber";108;0
"Unit";"Baneling";"Zergling";144;0
"Unit";"Baneling";"Zergling";144;0
"Building";"CreepTumorQueen";NA;158;0
"Building";"CreepTumorQueen";NA;168;0
"Building";"CreepTumorQueen";NA;168;0
"Building";"HydraliskDen";NA;144;0
"Building";"Hatchery";NA;123;0
"Unit";"Baneling";"Zergling";168;0
"Unit";"Baneling";"Zergling";168;0
"Unit";"Baneling";"Zergling";168;0
"Unit";"Baneling";"Zergling";168;0
"Unit";"Baneling";"Zergling";168;0
"Unit";"Baneling";"Zergling";168;0
"Unit";"Zergling";"Larva";168;1
"Unit";"Zergling";"Larva";168;1
"Unit";"Zergling";"Larva";168;1
"Unit";"Zergling";"Larva";168;1
"Unit";"Zergling";"Larva";168;1
"Unit";"Zergling";"Larva";168;1
"Unit";"Zergling";"Larva";168;1
"Unit";"Zergling";"Larva";168;1
"Unit";"Zergling";"Larva";168;1
"Unit";"Zergling";"Larva";168;1
"Unit";"Zergling";"Larva";168;1
"Unit";"Zergling";"Larva";168;1
"Unit";"Zergling";"Larva";168;1
"Unit";"Zergling";"Larva";168;1
"Unit";"Zergling";"Larva";168;1
"Unit";"Zergling";"Larva";168;1
"Unit";"Zergling";"Larva";168;1
"Unit";"Zergling";"Larva";168;1
"Unit";"Zergling";"Larva";168;1
"Unit";"Zergling";"Larva";168;1
"Unit";"Zergling";"Larva";168;1
"Unit";"Zergling";"Larva";168;1
"Unit";"Zergling";"Larva";168;1
"Unit";"Zergling";"Larva";168;1
"Building";"CreepTumor";NA;168;0
"Building";"CreepTumorQueen";NA;168;0
"Building";"CreepTumorQueen";NA;168;0
"Unit";"Baneling";"Zergling";168;0
"Unit";"Baneling";"Zergling";168;0
"Building";"CreepTumor";NA;192;0
"Building";"CreepTumor";NA;192;0
"Building";"CreepTumor";NA;192;0
"Unit";"Overlord";"Larva";192;0
"Unit";"Overlord";"Larva";192;0
"Unit";"Overlord";"Larva";192;0
"Building";"CreepTumor";NA;192;0
"Unit";"Overlord";"Larva";192;0
"Unit";"Zergling";"Larva";192;1
"Unit";"Zergling";"Larva";192;1
"Unit";"Zergling";"Larva";192;1
"Unit";"Zergling";"Larva";192;1
"Unit";"Zergling";"Larva";192;1
"Unit";"Zergling";"Larva";192;1
"Unit";"Zergling";"Larva";192;1
"Unit";"Zergling";"Larva";192;1
"Unit";"Zergling";"Larva";192;1
"Unit";"Zergling";"Larva";192;1
"Unit";"Zergling";"Larva";192;1
"Unit";"Zergling";"Larva";192;1
"Unit";"Zergling";"Larva";192;1
"Unit";"Zergling";"Larva";192;1
"Unit";"Zergling";"Larva";192;1
"Unit";"Zergling";"Larva";192;1
"Unit";"Zergling";"Larva";192;1
"Unit";"Zergling";"Larva";192;1
"Unit";"Zergling";"Larva";192;1
"Unit";"Zergling";"Larva";192;1
"Building";"CreepTumor";NA;192;0
"Building";"Hatchery";NA;144;0
"Unit";"Baneling";"Zergling";192;0
"Unit";"Baneling";"Zergling";192;0
"Unit";"Baneling";"Zergling";192;0
"Unit";"Baneling";"Zergling";192;0
"Unit";"Baneling";"Zergling";192;0
"Unit";"Baneling";"Zergling";192;0
"Unit";"Hydralisk";"Larva";192;2
"Unit";"Hydralisk";"Larva";192;2
"Unit";"Hydralisk";"Larva";192;2
"Unit";"Hydralisk";"Larva";192;2
"Unit";"Hydralisk";"Larva";192;2
"Unit";"Baneling";"Zergling";212;0
"Unit";"Baneling";"Zergling";212;0
"Unit";"Baneling";"Zergling";212;0
"Unit";"Baneling";"Zergling";212;0
"Unit";"Baneling";"Zergling";212;0
"Upgrade";"EvolveGroovedSpines";"HydraliskDen";192;0
"Unit";"Hydralisk";"Larva";212;2
"Unit";"Hydralisk";"Larva";212;2
"Unit";"Hydralisk";"Larva";212;2
"Unit";"Hydralisk";"Larva";212;2
"Unit";"Hydralisk";"Larva";212;2
"Unit";"Hydralisk";"Larva";212;2
"Unit";"Hydralisk";"Larva";214;2
"Unit";"Hydralisk";"Larva";214;2
"Unit";"Zergling";"Larva";222;1
"Unit";"Zergling";"Larva";222;1
"Unit";"Zergling";"Larva";222;1
"Unit";"Zergling";"Larva";222;1
"Unit";"Zergling";"Larva";222;1
"Unit";"Zergling";"Larva";222;1
"Unit";"Zergling";"Larva";222;1
"Unit";"Zergling";"Larva";222;1
"Unit";"Zergling";"Larva";222;1
"Unit";"Zergling";"Larva";222;1
"Unit";"Zergling";"Larva";222;1
"Unit";"Zergling";"Larva";222;1
"Unit";"Zergling";"Larva";222;1
"Unit";"Zergling";"Larva";222;1
"Unit";"Zergling";"Larva";222;1
"Unit";"Zergling";"Larva";222;1
"Unit";"Zergling";"Larva";222;1
"Unit";"Zergling";"Larva";222;1
"Unit";"Zergling";"Larva";222;1
"Unit";"Zergling";"Larva";222;1
"Unit";"Zergling";"Larva";222;1
"Unit";"Zergling";"Larva";222;1
"Unit";"Zergling";"Larva";222;1
"Unit";"Zergling";"Larva";222;1
"Building";"CreepTumorQueen";NA;262;0
"Unit";"Zergling";"Larva";262;1
"Unit";"Zergling";"Larva";262;1
"Unit";"Zergling";"Larva";262;1
"Unit";"Zergling";"Larva";262;1
"Unit";"Zergling";"Larva";262;1
"Unit";"Zergling";"Larva";262;1
"Unit";"Zergling";"Larva";262;1
"Unit";"Zergling";"Larva";262;1
"Unit";"Zergling";"Larva";262;1
"Unit";"Zergling";"Larva";262;1
"Unit";"Zergling";"Larva";262;1
"Unit";"Zergling";"Larva";262;1
"Unit";"Zergling";"Larva";262;1
"Unit";"Zergling";"Larva";262;1
"Unit";"Zergling";"Larva";262;1
"Unit";"Zergling";"Larva";262;1
"Upgrade";"ZergMeleeWeaponsLevel2";"EvolutionChamber";192;0
"Upgrade";"ZergGroundArmorsLevel2";"EvolutionChamber";192;0
"Upgrade";"EvolveMuscularAugments";"HydraliskDen";262;0
"Unit";"Baneling";"Zergling";287;0
"Building";"CreepTumor";NA;292;0
"Unit";"Baneling";"Zergling";287;0
"Unit";"Baneling";"Zergling";287;0
"Unit";"Baneling";"Zergling";287;0
"Unit";"Baneling";"Zergling";287;0
"Unit";"Baneling";"Zergling";287;0
"Unit";"Baneling";"Zergling";287;0
"Unit";"Baneling";"Zergling";287;0
"Building";"CreepTumor";NA;292;0
"Building";"CreepTumorQueen";NA;292;0
"Building";"CreepTumorQueen";NA;292;0
"Building";"CreepTumorQueen";NA;292;0
"Unit";"Baneling";"Zergling";292;0
"Unit";"Hydralisk";"Larva";292;2
"Unit";"Hydralisk";"Larva";292;2
"Unit";"Hydralisk";"Larva";292;2
"Unit";"Hydralisk";"Larva";292;2
"Unit";"Hydralisk";"Larva";292;2
"Unit";"Hydralisk";"Larva";292;2
"Unit";"Zergling";"Larva";292;1
"Unit";"Zergling";"Larva";292;1
"Unit";"Zergling";"Larva";292;1
"Unit";"Zergling";"Larva";292;1
"Unit";"Zergling";"Larva";292;1
"Unit";"Zergling";"Larva";292;1
"Unit";"Zergling";"Larva";292;1
"Unit";"Zergling";"Larva";292;1
"Unit";"Zergling";"Larva";292;1
"Unit";"Zergling";"Larva";292;1
"Unit";"Zergling";"Larva";292;1
"Unit";"Zergling";"Larva";292;1
"Unit";"Zergling";"Larva";292;1
"Unit";"Zergling";"Larva";292;1
"Unit";"Zergling";"Larva";292;1
"Unit";"Zergling";"Larva";292;1
"Unit";"Zergling";"Larva";292;1
"Unit";"Zergling";"Larva";292;1
"Unit";"Zergling";"Larva";294;1
"Unit";"Zergling";"Larva";294;1
"Unit";"Zergling";"Larva";304;1
"Unit";"Zergling";"Larva";304;1
"Unit";"Zergling";"Larva";304;1
"Unit";"Zergling";"Larva";304;1
"Unit";"Zergling";"Larva";304;1
"Unit";"Zergling";"Larva";304;1
"Unit";"Zergling";"Larva";304;1
"Unit";"Zergling";"Larva";304;1
"Unit";"Zergling";"Larva";304;1
"Unit";"Zergling";"Larva";304;1
"Unit";"Baneling";"Zergling";322;0
"Unit";"Baneling";"Zergling";322;0
"Unit";"Baneling";"Zergling";322;0
"Unit";"Baneling";"Zergling";322;0
"Unit";"Baneling";"Zergling";322;0
"Unit";"Baneling";"Zergling";324;0
"Unit";"Baneling";"Zergling";334;0
"Unit";"Baneling";"Zergling";334;0
"Unit";"Baneling";"Zergling";334;0
"Unit";"Baneling";"Zergling";334;0
"Unit";"Baneling";"Zergling";334;0
"Unit";"Baneling";"Zergling";334;0
"Unit";"Baneling";"Zergling";334;0
"Unit";"Baneling";"Zergling";334;0
"Unit";"Baneling";"Zergling";334;0
"Unit";"Baneling";"Zergling";334;0
"Unit";"Baneling";"Zergling";334;0
"Unit";"Baneling";"Zergling";334;0
"Unit";"Hydralisk";"Larva";322;2
"Unit";"Hydralisk";"Larva";322;2
"Unit";"Hydralisk";"Larva";322;2
"Unit";"Hydralisk";"Larva";322;2
"Unit";"Hydralisk";"Larva";322;2
"Unit";"Hydralisk";"Larva";322;2
"Unit";"Hydralisk";"Larva";322;2
"Unit";"Hydralisk";"Larva";322;2
"Unit";"Hydralisk";"Larva";322;2
"Building";"CreepTumor";NA;334;0
"Unit";"Hydralisk";"Larva";322;2
"Building";"CreepTumor";NA;334;0
"Unit";"Hydralisk";"Larva";322;2
"Unit";"Hydralisk";"Larva";322;2
"Unit";"Hydralisk";"Larva";322;2
"Unit";"Hydralisk";"Larva";322;2
"Building";"CreepTumor";NA;334;0
"Building";"CreepTumorQueen";NA;334;0
"Building";"CreepTumorQueen";NA;334;0
"Building";"CreepTumorQueen";NA;334;0
"Building";"Extractor";NA;334;0
"Building";"Extractor";NA;334;0
"Unit";"Zergling";"Larva";334;1
"Unit";"Zergling";"Larva";334;1
"Unit";"Zergling";"Larva";334;1
"Unit";"Zergling";"Larva";334;1
"Unit";"Zergling";"Larva";334;1
"Unit";"Zergling";"Larva";334;1
"Unit";"Zergling";"Larva";334;1
"Unit";"Zergling";"Larva";334;1
"Unit";"Zergling";"Larva";334;1
"Unit";"Zergling";"Larva";334;1
"Unit";"Zergling";"Larva";372;1
"Unit";"Zergling";"Larva";372;1
"Unit";"Zergling";"Larva";372;1
"Unit";"Zergling";"Larva";372;1
"Unit";"Zergling";"Larva";372;1
"Unit";"Zergling";"Larva";372;1
"Unit";"Zergling";"Larva";372;1
"Unit";"Zergling";"Larva";372;1
"Unit";"Zergling";"Larva";372;1
"Unit";"Zergling";"Larva";372;1
"Unit";"Zergling";"Larva";372;1
"Unit";"Zergling";"Larva";372;1
"Unit";"Zergling";"Larva";372;1
"Unit";"Zergling";"Larva";372;1
"Unit";"Zergling";"Larva";372;1
"Unit";"Zergling";"Larva";372;1
"Unit";"Zergling";"Larva";372;1
"Unit";"Zergling";"Larva";372;1
"Unit";"Zergling";"Larva";372;1
"Unit";"Zergling";"Larva";372;1
"Unit";"Zergling";"Larva";372;1
"Unit";"Zergling";"Larva";372;1
"Unit";"Zergling";"Larva";372;1
"Unit";"Zergling";"Larva";372;1
"Unit";"Zergling";"Larva";372;1
"Unit";"Zergling";"Larva";372;1
"Unit";"Zergling";"Larva";372;1
"Unit";"Zergling";"Larva";372;1
"Unit";"Zergling";"Larva";372;1
"Unit";"Zergling";"Larva";372;1
"Unit";"Zergling";"Larva";372;1
"Unit";"Zergling";"Larva";372;1
"Building";"InfestationPit";NA;354;0
"Unit";"Zergling";"Larva";404;1
"Unit";"Zergling";"Larva";404;1
"Unit";"Zergling";"Larva";404;1
"Unit";"Zergling";"Larva";404;1
"Unit";"Zergling";"Larva";404;1
"Unit";"Zergling";"Larva";404;1
"Unit";"Zergling";"Larva";404;1
"Unit";"Zergling";"Larva";404;1
"Unit";"Zergling";"Larva";404;1
"Unit";"Zergling";"Larva";404;1
"Unit";"Zergling";"Larva";404;1
"Unit";"Zergling";"Larva";404;1
"Unit";"Zergling";"Larva";404;1
"Unit";"Zergling";"Larva";404;1
"Unit";"Zergling";"Larva";404;1
"Unit";"Zergling";"Larva";404;1
"Unit";"Zergling";"Larva";404;1
"Unit";"Zergling";"Larva";404;1
"Unit";"Zergling";"Larva";404;1
"Unit";"Zergling";"Larva";404;1
"Unit";"Zergling";"Larva";404;1
"Unit";"Zergling";"Larva";404;1
"Unit";"Zergling";"Larva";404;1
"Unit";"Zergling";"Larva";404;1
"Unit";"Zergling";"Larva";404;1
"Unit";"Zergling";"Larva";404;1
"Unit";"Zergling";"Larva";404;1
"Unit";"Zergling";"Larva";404;1
"Unit";"Zergling";"Larva";404;1
"Unit";"Zergling";"Larva";404;1
"Unit";"Overlord";"Larva";434;0
"Unit";"Overlord";"Larva";434;0
"Building";"CreepTumor";NA;434;0
"Building";"CreepTumor";NA;434;0
"Unit";"Overlord";"Larva";434;0
"Unit";"Overlord";"Larva";434;0
"Unit";"Overlord";"Larva";434;0
"Unit";"Overlord";"Larva";434;0
"Building";"CreepTumor";NA;434;0
"Building";"CreepTumor";NA;434;0
"Building";"CreepTumorQueen";NA;434;0
"Unit";"Baneling";"Zergling";434;0
"Unit";"Baneling";"Zergling";434;0
"Unit";"Baneling";"Zergling";434;0
"Unit";"Baneling";"Zergling";434;0
"Unit";"Baneling";"Zergling";434;0
"Unit";"Baneling";"Zergling";434;0
"Unit";"Baneling";"Zergling";434;0
"Unit";"Baneling";"Zergling";434;0
"Unit";"Baneling";"Zergling";434;0
"Unit";"Baneling";"Zergling";434;0
"Unit";"Baneling";"Zergling";434;0
"Unit";"Baneling";"Zergling";434;0
"Unit";"Baneling";"Zergling";434;0
"Unit";"Baneling";"Zergling";434;0
"Building";"CreepTumorQueen";NA;434;0
"Unit";"Baneling";"Zergling";434;0
"Unit";"Baneling";"Zergling";434;0
"Unit";"Baneling";"Zergling";434;0
"Unit";"Baneling";"Zergling";434;0
"Unit";"Baneling";"Zergling";434;0
"Unit";"Baneling";"Zergling";434;0
"Unit";"Baneling";"Zergling";434;0
"Unit";"Baneling";"Zergling";434;0
"Building";"CreepTumorQueen";NA;434;0
"Building";"CreepTumorQueen";NA;434;0
"Building";"CreepTumorQueen";NA;444;0
"Unit";"Zergling";"Larva";434;1
"Unit";"Zergling";"Larva";434;1
"Unit";"Zergling";"Larva";434;1
"Unit";"Zergling";"Larva";434;1
"Unit";"Zergling";"Larva";434;1
"Unit";"Zergling";"Larva";434;1
"Unit";"Zergling";"Larva";434;1
"Unit";"Zergling";"Larva";434;1
"Unit";"Zergling";"Larva";434;1
"Unit";"Zergling";"Larva";434;1
"Unit";"Zergling";"Larva";435;1
"Unit";"Zergling";"Larva";435;1
"Unit";"Zergling";"Larva";435;1
"Unit";"Zergling";"Larva";435;1
"Unit";"Zergling";"Larva";435;1
"Unit";"Zergling";"Larva";435;1
"Unit";"Zergling";"Larva";435;1
"Unit";"Zergling";"Larva";435;1
"Building";"CreepTumorQueen";NA;444;0
"Unit";"Zergling";"Larva";435;1
"Unit";"Zergling";"Larva";435;1
"Unit";"Zergling";"Larva";436;1
"Unit";"Zergling";"Larva";436;1
"Unit";"Zergling";"Larva";436;1
"Unit";"Zergling";"Larva";436;1
"Building";"CreepTumorQueen";NA;444;0
"Building";"CreepTumorQueen";NA;444;0
"Building";"CreepTumorQueen";NA;468;0
"Upgrade";"ZergMissileWeaponsLevel1";"EvolutionChamber";404;0
"Unit";"Zergling";"Larva";468;1
"Unit";"Zergling";"Larva";468;1
"Unit";"Zergling";"Larva";468;1
"Unit";"Zergling";"Larva";468;1
"Unit";"Zergling";"Larva";468;1
"Unit";"Zergling";"Larva";468;1
"Unit";"Zergling";"Larva";468;1
"Unit";"Zergling";"Larva";468;1
"Unit";"Zergling";"Larva";468;1
"Unit";"Zergling";"Larva";468;1
"Unit";"Zergling";"Larva";468;1
"Unit";"Zergling";"Larva";468;1
"Unit";"Zergling";"Larva";468;1
"Unit";"Zergling";"Larva";468;1
"Unit";"Zergling";"Larva";468;1
"Unit";"Zergling";"Larva";468;1
"Unit";"Zergling";"Larva";468;1
"Unit";"Zergling";"Larva";468;1
"Unit";"Zergling";"Larva";468;1
"Unit";"Zergling";"Larva";468;1
"Unit";"Zergling";"Larva";468;1
"Unit";"Zergling";"Larva";468;1
"Building";"CreepTumor";NA;468;0
"Building";"CreepTumor";NA;468;0
"Building";"CreepTumor";NA;468;0
"Building";"CreepTumor";NA;468;0
"Building";"CreepTumorQueen";NA;468;0
"Building";"CreepTumorQueen";NA;468;0
"Building";"CreepTumor";NA;468;0
"Building";"CreepTumorQueen";NA;468;0
"Building";"CreepTumor";NA;468;0
"Building";"CreepTumor";NA;468;0
"Building";"CreepTumorQueen";NA;490;0
"Unit";"Hydralisk";"Larva";468;2
"Building";"CreepTumorQueen";NA;490;0
"Unit";"Hydralisk";"Larva";468;2
"Unit";"Hydralisk";"Larva";468;2
"Unit";"Hydralisk";"Larva";468;2
"Unit";"Hydralisk";"Larva";468;2
"Unit";"Hydralisk";"Larva";468;2
"Unit";"Hydralisk";"Larva";468;2
"Unit";"Hydralisk";"Larva";468;2
"Building";"CreepTumorQueen";NA;490;0
"Building";"CreepTumorQueen";NA;490;0
