"type";"unit_name";"on_building";"total_supply";"supply"
"Unit";"Overlord";"Larva";12;0
"Building";"Extractor";NA;17;0
"Building";"Hatchery";NA;17;0
"Building";"SpawningPool";NA;20;0
"Unit";"Overlord";"Larva";23;0
"Unit";"Zergling";"Larva";23;1
"Unit";"Zergling";"Larva";23;1
"Unit";"Zergling";"Larva";23;1
"Unit";"Zergling";"Larva";23;1
"Unit";"Queen";"Hatchery";25;2
"Unit";"Queen";"Hatchery";25;2
"Unit";"Overlord";"Larva";34;0
"Unit";"Queen";"Hatchery";34;2
"Building";"CreepTumorQueen";NA;43;0
"Unit";"Overlord";"Larva";41;0
"Building";"CreepTumorQueen";NA;46;0
"Unit";"Overlord";"Larva";48;0
"Unit";"Queen";"Hatchery";49;2
"Building";"CreepTumor";NA;53;0
"Building";"Extractor";NA;53;0
"Building";"Hatchery";NA;39;0
"Building";"Extractor";NA;53;0
"Building";"CreepTumorQueen";NA;56;0
"Unit";"Overlord";"Larva";53;0
"Unit";"Overlord";"Larva";53;0
"Unit";"Overlord";"Larva";53;0
"Building";"BanelingNest";NA;53;0
"Building";"CreepTumor";NA;58;0
"Unit";"Zergling";"Larva";58;1
"Unit";"Zergling";"Larva";58;1
"Unit";"Zergling";"Larva";58;1
"Unit";"Zergling";"Larva";58;1
"Unit";"Zergling";"Larva";58;1
"Unit";"Zergling";"Larva";58;1
"Unit";"Zergling";"Larva";58;1
"Unit";"Zergling";"Larva";58;1
"Unit";"Zergling";"Larva";58;1
"Unit";"Zergling";"Larva";58;1
"Unit";"Zergling";"Larva";58;1
"Unit";"Zergling";"Larva";58;1
"Unit";"Queen";"Hatchery";56;2
"Unit";"Baneling";"Zergling";58;0
"Unit";"Baneling";"Zergling";58;0
"Unit";"Baneling";"Zergling";58;0
"Unit";"Baneling";"Zergling";58;0
"Unit";"Queen";"Hatchery";58;2
"Unit";"Queen";"Hatchery";58;2
"Unit";"Zergling";"Larva";70;1
"Unit";"Zergling";"Larva";70;1
"Unit";"Zergling";"Larva";70;1
"Unit";"Zergling";"Larva";70;1
"Unit";"Zergling";"Larva";70;1
"Unit";"Zergling";"Larva";70;1
"Unit";"Zergling";"Larva";70;1
"Unit";"Zergling";"Larva";70;1
"Unit";"Zergling";"Larva";70;1
"Unit";"Zergling";"Larva";70;1
"Unit";"Zergling";"Larva";70;1
"Unit";"Zergling";"Larva";70;1
"Unit";"Zergling";"Larva";70;1
"Unit";"Zergling";"Larva";70;1
"Unit";"Zergling";"Larva";70;1
"Unit";"Zergling";"Larva";70;1
"Unit";"Zergling";"Larva";70;1
"Unit";"Zergling";"Larva";70;1
"Unit";"Zergling";"Larva";76;1
"Unit";"Zergling";"Larva";76;1
"Unit";"Zergling";"Larva";76;1
"Unit";"Zergling";"Larva";76;1
"Unit";"Zergling";"Larva";76;1
"Unit";"Zergling";"Larva";76;1
"Unit";"Queen";"Hatchery";70;2
"Unit";"Zergling";"Larva";94;1
"Unit";"Zergling";"Larva";94;1
"Unit";"Zergling";"Larva";94;1
"Unit";"Zergling";"Larva";94;1
"Unit";"Zergling";"Larva";94;1
"Unit";"Zergling";"Larva";94;1
"Unit";"Zergling";"Larva";94;1
"Unit";"Zergling";"Larva";94;1
"Building";"CreepTumorQueen";NA;100;0
"Building";"Extractor";NA;102;0
"Building";"CreepTumor";NA;113;0
"Unit";"Baneling";"Zergling";113;0
"Unit";"Baneling";"Zergling";113;0
"Unit";"Baneling";"Zergling";113;0
"Unit";"Baneling";"Zergling";113;0
"Unit";"Baneling";"Zergling";113;0
"Unit";"Baneling";"Zergling";113;0
"Unit";"Baneling";"Zergling";113;0
"Building";"EvolutionChamber";NA;110;0
"Building";"CreepTumor";NA;116;0
"Building";"CreepTumor";NA;116;0
"Unit";"Overlord";"Larva";116;0
"Unit";"Overlord";"Larva";118;0
"Unit";"Overlord";"Larva";118;0
"Unit";"Overlord";"Larva";118;0
"Building";"CreepTumor";NA;120;0
"Building";"CreepTumor";NA;120;0
"Unit";"Queen";"Hatchery";113;2
"Unit";"Queen";"Hatchery";113;2
"Building";"EvolutionChamber";NA;118;0
"Building";"CreepTumorQueen";NA;123;0
"Building";"CreepTumorQueen";NA;123;0
"Building";"CreepTumorQueen";NA;123;0
"Unit";"Zergling";"Larva";132;1
"Unit";"Zergling";"Larva";132;1
"Unit";"Zergling";"Larva";132;1
"Unit";"Zergling";"Larva";132;1
"Unit";"Zergling";"Larva";132;1
"Unit";"Zergling";"Larva";132;1
"Unit";"Zergling";"Larva";132;1
"Unit";"Zergling";"Larva";132;1
"Unit";"Zergling";"Larva";132;1
"Unit";"Zergling";"Larva";132;1
"Unit";"Zergling";"Larva";132;1
"Unit";"Zergling";"Larva";132;1
"Unit";"Zergling";"Larva";132;1
"Unit";"Zergling";"Larva";132;1
"Building";"HydraliskDen";NA;132;0
"Building";"CreepTumor";NA;132;0
"Building";"CreepTumorQueen";NA;146;0
"Building";"CreepTumor";NA;146;0
"Building";"CreepTumor";NA;146;0
"Building";"CreepTumor";NA;147;0
"Building";"Extractor";NA;146;0
"Building";"Extractor";NA;147;0
"Unit";"Baneling";"Zergling";154;0
"Unit";"Baneling";"Zergling";154;0
"Unit";"Baneling";"Zergling";154;0
"Unit";"Baneling";"Zergling";154;0
"Unit";"Baneling";"Zergling";154;0
"Unit";"Baneling";"Zergling";154;0
"Unit";"Hydralisk";"Larva";154;2
"Unit";"Hydralisk";"Larva";154;2
"Unit";"Hydralisk";"Larva";154;2
"Unit";"Hydralisk";"Larva";154;2
"Unit";"Hydralisk";"Larva";154;2
"Unit";"Hydralisk";"Larva";154;2
"Unit";"Hydralisk";"Larva";154;2
"Upgrade";"ZergMissileWeaponsLevel1";"EvolutionChamber";132;0
"Unit";"Zergling";"Larva";168;1
"Unit";"Zergling";"Larva";168;1
"Unit";"Zergling";"Larva";168;1
"Unit";"Zergling";"Larva";168;1
"Unit";"Zergling";"Larva";168;1
"Unit";"Zergling";"Larva";168;1
"Unit";"Zergling";"Larva";168;1
"Unit";"Zergling";"Larva";168;1
"Unit";"Zergling";"Larva";168;1
"Unit";"Zergling";"Larva";168;1
"Unit";"Zergling";"Larva";168;1
"Unit";"Zergling";"Larva";168;1
"Unit";"Zergling";"Larva";168;1
"Unit";"Zergling";"Larva";168;1
"Unit";"Zergling";"Larva";168;1
"Unit";"Zergling";"Larva";168;1
"Unit";"Zergling";"Larva";168;1
"Unit";"Zergling";"Larva";168;1
"Unit";"Zergling";"Larva";168;1
"Unit";"Zergling";"Larva";168;1
"Unit";"Zergling";"Larva";168;1
"Unit";"Zergling";"Larva";168;1
"Unit";"Zergling";"Larva";168;1
"Unit";"Zergling";"Larva";168;1
"Unit";"Zergling";"Larva";168;1
"Unit";"Zergling";"Larva";168;1
"Upgrade";"EvolveGroovedSpines";"HydraliskDen";154;0
"Unit";"Hydralisk";"Larva";168;2
"Unit";"Hydralisk";"Larva";168;2
"Upgrade";"ZergGroundArmorsLevel1";"EvolutionChamber";147;0
"Building";"Hatchery";NA;154;0
"Unit";"Queen";"Hatchery";168;2
"Unit";"Queen";"Hatchery";168;2
"Unit";"Hydralisk";"Larva";194;2
"Unit";"Hydralisk";"Larva";194;2
"Unit";"Zergling";"Larva";198;1
"Unit";"Zergling";"Larva";198;1
"Unit";"Hydralisk";"Larva";194;2
"Unit";"Hydralisk";"Larva";194;2
"Building";"Extractor";NA;198;0
"Building";"CreepTumor";NA;215;0
"Building";"CreepTumor";NA;215;0
"Building";"CreepTumor";NA;215;0
"Building";"Extractor";NA;215;0
"Building";"Extractor";NA;215;0
"Unit";"Hydralisk";"Larva";215;2
"Unit";"Hydralisk";"Larva";215;2
"Unit";"Hydralisk";"Larva";215;2
"Unit";"Hydralisk";"Larva";215;2
"Building";"InfestationPit";NA;215;0
"Unit";"Overlord";"Larva";221;0
"Unit";"Overlord";"Larva";221;0
"Building";"CreepTumor";NA;221;0
"Building";"CreepTumorQueen";NA;231;0
"Building";"Extractor";NA;228;0
"Building";"CreepTumorQueen";NA;231;0
"Unit";"Overlord";"Larva";231;0
"Unit";"Overlord";"Larva";231;0
"Unit";"Queen";"Hatchery";221;2
"Building";"CreepTumor";NA;234;0
"Building";"Hatchery";NA;215;0
"Upgrade";"EvolveMuscularAugments";"HydraliskDen";221;0
"Unit";"Hydralisk";"Larva";231;2
"Unit";"Hydralisk";"Larva";231;2
"Unit";"Hydralisk";"Larva";231;2
"Unit";"Baneling";"Zergling";243;0
"Unit";"Baneling";"Zergling";243;0
"Upgrade";"ZergMissileWeaponsLevel2";"EvolutionChamber";206;0
"Building";"CreepTumor";NA;243;0
"Building";"CreepTumor";NA;243;0
"Building";"CreepTumor";NA;243;0
"Building";"CreepTumor";NA;243;0
"Building";"CreepTumor";NA;249;0
"Building";"CreepTumorQueen";NA;249;0
"Building";"CreepTumor";NA;249;0
"Building";"CreepTumor";NA;249;0
"Building";"CreepTumor";NA;249;0
"Unit";"Overlord";"Larva";249;0
"Unit";"Overlord";"Larva";249;0
"Unit";"Overlord";"Larva";249;0
"Unit";"Overlord";"Larva";249;0
"Unit";"Overlord";"Larva";249;0
"Unit";"Hydralisk";"Larva";249;2
"Unit";"Hydralisk";"Larva";249;2
"Unit";"Hydralisk";"Larva";249;2
"Unit";"Hydralisk";"Larva";249;2
"Unit";"Hydralisk";"Larva";249;2
"Unit";"Hydralisk";"Larva";249;2
"Building";"CreepTumor";NA;249;0
"Building";"CreepTumor";NA;249;0
"Building";"CreepTumor";NA;261;0
"Building";"CreepTumor";NA;261;0
"Upgrade";"ZergGroundArmorsLevel2";"EvolutionChamber";231;0
"Building";"EvolutionChamber";NA;249;0
"Unit";"Hydralisk";"Larva";261;2
"Unit";"Hydralisk";"Larva";261;2
"Unit";"Hydralisk";"Larva";261;2
"Unit";"Hydralisk";"Larva";261;2
"Unit";"Hydralisk";"Larva";261;2
"Building";"CreepTumor";NA;267;0
"Building";"CreepTumor";NA;267;0
"Unit";"Hydralisk";"Larva";267;2
"Building";"CreepTumor";NA;267;0
"Unit";"Hydralisk";"Larva";267;2
"Unit";"Hydralisk";"Larva";267;2
"Unit";"Hydralisk";"Larva";267;2
"Unit";"Hydralisk";"Larva";267;2
"Unit";"Overlord";"Larva";267;0
"Unit";"Overlord";"Larva";267;0
"Unit";"Overlord";"Larva";267;0
"Unit";"Zergling";"Larva";279;1
"Unit";"Zergling";"Larva";279;1
"Unit";"Zergling";"Larva";281;1
"Unit";"Zergling";"Larva";281;1
"Unit";"Zergling";"Larva";281;1
"Unit";"Zergling";"Larva";281;1
"Unit";"Zergling";"Larva";281;1
"Unit";"Zergling";"Larva";281;1
"Unit";"Zergling";"Larva";281;1
"Unit";"Zergling";"Larva";281;1
"Unit";"Zergling";"Larva";281;1
"Unit";"Zergling";"Larva";281;1
"Unit";"Zergling";"Larva";281;1
"Unit";"Zergling";"Larva";281;1
"Unit";"Zergling";"Larva";281;1
"Unit";"Zergling";"Larva";281;1
"Unit";"Zergling";"Larva";281;1
"Unit";"Zergling";"Larva";281;1
"Unit";"Zergling";"Larva";281;1
"Unit";"Zergling";"Larva";281;1
"Unit";"Zergling";"Larva";281;1
"Unit";"Zergling";"Larva";281;1
"Unit";"Zergling";"Larva";281;1
"Unit";"Zergling";"Larva";281;1
"Unit";"Zergling";"Larva";281;1
"Unit";"Zergling";"Larva";281;1
"Unit";"Zergling";"Larva";281;1
"Unit";"Zergling";"Larva";281;1
"Unit";"Zergling";"Larva";281;1
"Unit";"Zergling";"Larva";281;1
"Unit";"Zergling";"Larva";281;1
"Unit";"Zergling";"Larva";281;1
"Unit";"Zergling";"Larva";281;1
"Unit";"Zergling";"Larva";281;1
"Unit";"Zergling";"Larva";281;1
"Unit";"Zergling";"Larva";281;1
"Unit";"Zergling";"Larva";281;1
"Unit";"Zergling";"Larva";281;1
"Unit";"Baneling";"Zergling";311;0
"Unit";"Baneling";"Zergling";311;0
"Unit";"Baneling";"Zergling";311;0
"Unit";"Baneling";"Zergling";311;0
"Unit";"Baneling";"Zergling";311;0
"Unit";"Baneling";"Zergling";311;0
"Unit";"Baneling";"Zergling";311;0
"Unit";"Baneling";"Zergling";311;0
"Unit";"Baneling";"Zergling";311;0
"Unit";"Baneling";"Zergling";311;0
"Unit";"Baneling";"Zergling";311;0
"Unit";"Baneling";"Zergling";311;0
"Unit";"Baneling";"Zergling";311;0
"Unit";"Baneling";"Zergling";311;0
"Unit";"Baneling";"Zergling";311;0
"Unit";"Baneling";"Zergling";311;0
"Unit";"Baneling";"Zergling";311;0
"Unit";"Baneling";"Zergling";311;0
"Unit";"Baneling";"Zergling";311;0
"Unit";"Baneling";"Zergling";311;0
"Unit";"Baneling";"Zergling";311;0
"Unit";"Baneling";"Zergling";311;0
"Unit";"Baneling";"Zergling";311;0
"Unit";"Baneling";"Zergling";311;0
"Unit";"Baneling";"Zergling";311;0
"Unit";"Baneling";"Zergling";311;0
"Upgrade";"ZergMeleeWeaponsLevel1";"EvolutionChamber";261;0
"Unit";"Baneling";"Zergling";311;0
"Unit";"Baneling";"Zergling";311;0
"Unit";"Baneling";"Zergling";311;0
"Unit";"Hydralisk";"Larva";319;2
"Unit";"Hydralisk";"Larva";319;2
"Unit";"Hydralisk";"Larva";319;2
"Unit";"Hydralisk";"Larva";319;2
"Unit";"Hydralisk";"Larva";319;2
"Unit";"Hydralisk";"Larva";319;2
"Unit";"Hydralisk";"Larva";319;2
"Unit";"Hydralisk";"Larva";319;2
"Building";"CreepTumor";NA;319;0
"Building";"CreepTumor";NA;319;0
"Building";"Hatchery";NA;311;0
"Unit";"Hydralisk";"Larva";343;2
"Unit";"Hydralisk";"Larva";344;2
"Unit";"Hydralisk";"Larva";345;2
"Unit";"Hydralisk";"Larva";345;2
"Building";"CreepTumor";NA;345;0
"Building";"CreepTumor";NA;345;0
"Building";"Extractor";NA;345;0
"Building";"Extractor";NA;345;0
"Upgrade";"ZergMissileWeaponsLevel3";"EvolutionChamber";281;0
"Unit";"Viper";"Larva";345;3
"Unit";"Viper";"Larva";345;3
"Unit";"Viper";"Larva";345;3
"Unit";"Hydralisk";"Larva";353;2
"Building";"CreepTumor";NA;353;0
"Unit";"Hydralisk";"Larva";353;2
"Unit";"Hydralisk";"Larva";353;2
"Unit";"Hydralisk";"Larva";353;2
"Unit";"Hydralisk";"Larva";353;2
"Unit";"Hydralisk";"Larva";353;2
"Building";"CreepTumor";NA;353;0
"Building";"CreepTumor";NA;374;0
"Unit";"Hydralisk";"Larva";374;2
"Unit";"Hydralisk";"Larva";374;2
"Unit";"Hydralisk";"Larva";374;2
"Building";"SpineCrawler";NA;362;0
"Building";"SpineCrawler";NA;362;0
"Upgrade";"ZergGroundArmorsLevel3";"EvolutionChamber";319;0
"Unit";"Hydralisk";"Larva";380;2
"Unit";"Hydralisk";"Larva";380;2
"Unit";"Hydralisk";"Larva";380;2
"Unit";"Hydralisk";"Larva";380;2
"Unit";"Hydralisk";"Larva";380;2
"Unit";"Hydralisk";"Larva";380;2
"Building";"CreepTumor";NA;380;0
"Unit";"Hydralisk";"Larva";380;2
"Unit";"Hydralisk";"Larva";380;2
"Unit";"Hydralisk";"Larva";380;2
"Unit";"Hydralisk";"Larva";380;2
"Unit";"Hydralisk";"Larva";380;2
"Unit";"Hydralisk";"Larva";380;2
"Unit";"Hydralisk";"Larva";380;2
"Unit";"Hydralisk";"Larva";380;2
"Unit";"Hydralisk";"Larva";380;2
"Unit";"Hydralisk";"Larva";380;2
"Unit";"Hydralisk";"Larva";380;2
"Building";"CreepTumor";NA;414;0
"Building";"CreepTumor";NA;414;0
"Upgrade";"ZergMeleeWeaponsLevel2";"EvolutionChamber";374;0
"Building";"CreepTumorQueen";NA;414;0
"Building";"CreepTumorQueen";NA;414;0
"Building";"CreepTumorQueen";NA;414;0
"Building";"CreepTumorQueen";NA;414;0
"Building";"CreepTumorQueen";NA;414;0
"Building";"CreepTumorQueen";NA;414;0
"Building";"CreepTumorQueen";NA;414;0
"Building";"CreepTumor";NA;414;0
"Building";"Hatchery";NA;414;0
"Building";"CreepTumor";NA;414;0
"Building";"CreepTumor";NA;414;0
"Building";"CreepTumor";NA;414;0
"Building";"Extractor";NA;414;0
"Building";"Extractor";NA;414;0
"Building";"CreepTumor";NA;414;0
"Building";"CreepTumor";NA;414;0
"Building";"CreepTumor";NA;414;0
"Building";"CreepTumor";NA;414;0
"Building";"CreepTumor";NA;414;0
"Building";"CreepTumor";NA;414;0
"Building";"CreepTumor";NA;414;0
"Building";"CreepTumor";NA;414;0
"Building";"CreepTumorQueen";NA;414;0
"Building";"CreepTumor";NA;414;0
"Building";"CreepTumor";NA;414;0
"Building";"CreepTumorQueen";NA;414;0
"Building";"CreepTumor";NA;414;0
"Building";"CreepTumor";NA;414;0
"Building";"CreepTumor";NA;414;0
"Building";"CreepTumorQueen";NA;414;0
"Building";"CreepTumor";NA;414;0
"Building";"CreepTumor";NA;414;0
"Building";"CreepTumorQueen";NA;414;0
"Building";"CreepTumor";NA;414;0
"Building";"CreepTumorQueen";NA;414;0
"Building";"CreepTumorQueen";NA;414;0
"Building";"CreepTumor";NA;414;0
"Building";"CreepTumor";NA;414;0
"Building";"CreepTumor";NA;414;0
"Building";"CreepTumor";NA;414;0
"Building";"CreepTumor";NA;414;0
"Building";"CreepTumor";NA;414;0
"Building";"CreepTumor";NA;414;0
"Building";"CreepTumor";NA;414;0
"Building";"CreepTumor";NA;414;0
"Building";"CreepTumor";NA;414;0
"Building";"CreepTumor";NA;414;0
"Building";"CreepTumorQueen";NA;414;0
"Building";"CreepTumor";NA;414;0
"Building";"CreepTumorQueen";NA;414;0
"Building";"CreepTumor";NA;414;0
"Building";"CreepTumor";NA;414;0
"Building";"CreepTumor";NA;414;0
"Building";"CreepTumor";NA;414;0
"Building";"CreepTumor";NA;414;0
"Building";"CreepTumor";NA;414;0
"Building";"CreepTumor";NA;414;0
"Building";"CreepTumor";NA;414;0
"Building";"CreepTumor";NA;414;0
"Building";"CreepTumor";NA;414;0
"Building";"CreepTumor";NA;414;0
"Building";"CreepTumorQueen";NA;414;0
"Building";"CreepTumor";NA;414;0
"Building";"CreepTumor";NA;414;0
"Building";"CreepTumor";NA;414;0
"Building";"CreepTumor";NA;414;0
"Building";"CreepTumor";NA;414;0
"Building";"CreepTumor";NA;414;0
"Building";"CreepTumor";NA;414;0
"Building";"CreepTumor";NA;414;0
"Building";"CreepTumor";NA;414;0
"Building";"CreepTumor";NA;414;0
"Building";"Extractor";NA;414;0
"Building";"CreepTumorQueen";NA;414;0
"Building";"Extractor";NA;414;0
"Building";"CreepTumor";NA;414;0
"Building";"CreepTumor";NA;414;0
"Building";"CreepTumor";NA;414;0
"Building";"CreepTumor";NA;414;0
"Building";"CreepTumor";NA;414;0
"Building";"CreepTumor";NA;414;0
"Building";"CreepTumor";NA;414;0
"Building";"CreepTumor";NA;414;0
"Building";"CreepTumor";NA;414;0
"Building";"CreepTumor";NA;414;0
"Building";"CreepTumor";NA;414;0
"Building";"CreepTumor";NA;414;0
"Building";"CreepTumor";NA;414;0
"Building";"CreepTumor";NA;414;0
"Building";"Hatchery";NA;414;0
"Building";"CreepTumor";NA;414;0
"Building";"CreepTumor";NA;414;0
"Building";"CreepTumor";NA;414;0
"Building";"CreepTumor";NA;414;0
"Building";"CreepTumor";NA;414;0
"Building";"CreepTumor";NA;414;0
"Building";"CreepTumor";NA;414;0
"Upgrade";"ZergMeleeWeaponsLevel3";"EvolutionChamber";414;0
"Building";"CreepTumor";NA;414;0
"Building";"CreepTumor";NA;414;0
"Building";"CreepTumor";NA;414;0
"Building";"CreepTumor";NA;414;0
"Building";"CreepTumorQueen";NA;414;0
"Building";"CreepTumorQueen";NA;414;0
"Building";"CreepTumor";NA;414;0
"Building";"CreepTumor";NA;414;0
"Building";"CreepTumor";NA;414;0
"Building";"CreepTumor";NA;414;0
"Building";"CreepTumor";NA;414;0
"Building";"CreepTumor";NA;414;0
"Building";"CreepTumor";NA;414;0
"Building";"CreepTumor";NA;414;0
"Building";"CreepTumor";NA;414;0
"Building";"CreepTumor";NA;414;0
"Building";"CreepTumor";NA;414;0
"Building";"CreepTumor";NA;414;0
"Building";"CreepTumorQueen";NA;414;0
"Building";"CreepTumorQueen";NA;414;0
