"type";"unit_name";"on_building";"total_supply";"supply"
"Building";"Extractor";NA;13;0
"Building";"Extractor";NA;14;0
"Building";"SpawningPool";NA;12;0
"Unit";"Zergling";"Larva";17;1
"Unit";"Zergling";"Larva";17;1
"Unit";"Overlord";"Larva";17;0
"Unit";"Overlord";"Larva";19;0
"Building";"RoachWarren";NA;17;0
"Unit";"Roach";"Larva";19;2
"Unit";"Roach";"Larva";19;2
"Unit";"Roach";"Larva";19;2
"Unit";"Roach";"Larva";19;2
