"type";"unit_name";"on_building";"total_supply";"supply"
"Unit";"Overlord";"Larva";13;0
"Building";"SpawningPool";NA;18;0
"Building";"Hatchery";NA;17;0
"Unit";"Overlord";"Larva";22;0
"Unit";"Overlord";"Larva";23;0
"Unit";"Queen";"Hatchery";23;2
"Unit";"Queen";"Hatchery";23;2
"Building";"Hatchery";NA;22;0
"Unit";"Overlord";"Larva";25;0
"Building";"CreepTumorQueen";NA;30;0
"Unit";"Queen";"Hatchery";28;2
"Unit";"Zergling";"Larva";33;1
"Unit";"Zergling";"Larva";33;1
"Unit";"Queen";"Hatchery";30;2
"Building";"CreepTumorQueen";NA;38;0
"Building";"CreepTumor";NA;42;0
"Building";"CreepTumorQueen";NA;44;0
"Building";"Extractor";NA;36;0
"Unit";"Queen";"Hatchery";33;2
"Building";"Extractor";NA;38;0
"Unit";"Overlord";"Larva";44;0
"Unit";"Overlord";"Larva";53;0
"Unit";"Overlord";"Larva";53;0
"Building";"CreepTumor";NA;57;0
"Building";"CreepTumor";NA;57;0
"Building";"CreepTumor";NA;57;0
"Unit";"Zergling";"Larva";57;1
"Unit";"Zergling";"Larva";57;1
"Building";"RoachWarren";NA;53;0
"Unit";"Overlord";"Larva";57;0
"Unit";"Overlord";"Larva";57;0
"Building";"CreepTumor";NA;59;0
"Building";"CreepTumor";NA;59;0
"Building";"CreepTumor";NA;59;0
"Unit";"Roach";"Larva";59;2
"Unit";"Roach";"Larva";59;2
"Unit";"Roach";"Larva";59;2
"Unit";"Roach";"Larva";59;2
"Unit";"Roach";"Larva";59;2
"Unit";"Roach";"Larva";59;2
"Unit";"Queen";"Hatchery";57;2
"Unit";"Queen";"Hatchery";57;2
"Unit";"Roach";"Larva";59;2
"Unit";"Roach";"Larva";59;2
"Unit";"Roach";"Larva";59;2
"Unit";"Roach";"Larva";59;2
"Unit";"Roach";"Larva";59;2
"Unit";"Roach";"Larva";71;2
"Unit";"Roach";"Larva";71;2
"Unit";"Roach";"Larva";71;2
"Unit";"Overlord";"Larva";79;0
"Unit";"Overlord";"Larva";79;0
"Building";"SpineCrawler";NA;59;0
"Unit";"Overlord";"Larva";91;0
"Unit";"Overlord";"Larva";91;0
"Building";"CreepTumorQueen";NA;91;0
"Building";"CreepTumorQueen";NA;91;0
"Building";"CreepTumorQueen";NA;91;0
"Building";"CreepTumorQueen";NA;91;0
"Unit";"Queen";"Hatchery";91;2
"Unit";"Queen";"Hatchery";91;2
"Building";"CreepTumorQueen";NA;105;0
"Building";"CreepTumorQueen";NA;105;0
"Building";"CreepTumor";NA;114;0
"Building";"CreepTumor";NA;114;0
"Building";"CreepTumor";NA;114;0
"Building";"EvolutionChamber";NA;109;0
"Building";"EvolutionChamber";NA;109;0
"Building";"CreepTumor";NA;114;0
"Building";"CreepTumor";NA;114;0
"Building";"CreepTumor";NA;114;0
"Building";"CreepTumor";NA;114;0
"Building";"CreepTumor";NA;114;0
"Unit";"Overlord";"Larva";117;0
"Unit";"Overlord";"Larva";117;0
"Building";"CreepTumorQueen";NA;130;0
"Building";"CreepTumorQueen";NA;130;0
"Building";"CreepTumorQueen";NA;130;0
"Building";"CreepTumorQueen";NA;130;0
"Building";"CreepTumorQueen";NA;130;0
"Building";"CreepTumorQueen";NA;130;0
"Building";"Extractor";NA;130;0
"Building";"Extractor";NA;130;0
"Building";"CreepTumorQueen";NA;130;0
"Building";"Extractor";NA;130;0
"Building";"Extractor";NA;130;0
"Unit";"Overlord";"Larva";130;0
"Unit";"Overlord";"Larva";130;0
"Unit";"Overlord";"Larva";130;0
"Unit";"Overlord";"Larva";130;0
"Building";"CreepTumor";NA;130;0
"Building";"CreepTumor";NA;130;0
"Building";"CreepTumor";NA;131;0
"Building";"Hatchery";NA;114;0
"Building";"CreepTumor";NA;136;0
"Building";"CreepTumor";NA;136;0
"Building";"CreepTumor";NA;136;0
"Building";"CreepTumor";NA;136;0
"Building";"CreepTumor";NA;136;0
"Building";"CreepTumor";NA;136;0
"Building";"CreepTumor";NA;136;0
"Building";"CreepTumor";NA;136;0
"Building";"CreepTumor";NA;136;0
"Building";"CreepTumor";NA;136;0
"Building";"CreepTumor";NA;136;0
"Building";"CreepTumorQueen";NA;136;0
"Building";"CreepTumorQueen";NA;136;0
"Building";"CreepTumorQueen";NA;136;0
"Building";"CreepTumorQueen";NA;136;0
"Building";"CreepTumorQueen";NA;136;0
"Building";"CreepTumorQueen";NA;136;0
"Building";"CreepTumorQueen";NA;136;0
"Building";"CreepTumorQueen";NA;136;0
"Building";"CreepTumorQueen";NA;136;0
"Building";"CreepTumor";NA;136;0
"Building";"CreepTumor";NA;136;0
"Building";"CreepTumor";NA;136;0
"Building";"CreepTumor";NA;136;0
"Building";"CreepTumor";NA;136;0
"Building";"CreepTumor";NA;136;0
"Building";"CreepTumor";NA;136;0
"Building";"CreepTumor";NA;136;0
"Building";"CreepTumor";NA;136;0
"Building";"CreepTumor";NA;136;0
"Building";"CreepTumor";NA;136;0
"Building";"HydraliskDen";NA;136;0
"Building";"CreepTumor";NA;136;0
"Building";"CreepTumor";NA;136;0
"Building";"CreepTumor";NA;136;0
"Building";"CreepTumor";NA;136;0
"Building";"CreepTumor";NA;136;0
"Building";"CreepTumor";NA;136;0
"Building";"CreepTumor";NA;136;0
"Building";"CreepTumor";NA;136;0
"Building";"InfestationPit";NA;136;0
"Unit";"Overlord";"Larva";143;0
"Unit";"Overlord";"Larva";143;0
"Unit";"Overlord";"Larva";143;0
"Unit";"Overlord";"Larva";143;0
"Upgrade";"ZergMissileWeaponsLevel1";"EvolutionChamber";136;0
"Upgrade";"ZergGroundArmorsLevel1";"EvolutionChamber";136;0
"Unit";"Hydralisk";"Larva";143;2
"Unit";"Hydralisk";"Larva";143;2
"Unit";"Hydralisk";"Larva";143;2
"Unit";"Hydralisk";"Larva";143;2
"Unit";"Hydralisk";"Larva";143;2
"Unit";"Hydralisk";"Larva";143;2
"Unit";"Hydralisk";"Larva";143;2
"Unit";"Hydralisk";"Larva";143;2
"Unit";"Hydralisk";"Larva";143;2
"Unit";"Hydralisk";"Larva";143;2
"Unit";"Hydralisk";"Larva";143;2
"Unit";"Hydralisk";"Larva";143;2
"Unit";"Hydralisk";"Larva";143;2
"Unit";"Hydralisk";"Larva";143;2
"Unit";"Hydralisk";"Larva";143;2
"Unit";"Hydralisk";"Larva";143;2
"Building";"CreepTumor";NA;143;0
"Building";"CreepTumor";NA;143;0
"Building";"CreepTumor";NA;143;0
"Building";"CreepTumor";NA;143;0
"Building";"CreepTumor";NA;143;0
"Building";"CreepTumor";NA;143;0
"Building";"CreepTumor";NA;143;0
"Building";"CreepTumor";NA;143;0
"Building";"CreepTumor";NA;143;0
"Building";"CreepTumor";NA;143;0
"Building";"CreepTumor";NA;143;0
"Building";"Extractor";NA;143;0
"Building";"Extractor";NA;143;0
"Building";"CreepTumor";NA;149;0
"Building";"CreepTumor";NA;149;0
"Building";"CreepTumor";NA;149;0
"Building";"CreepTumor";NA;149;0
"Building";"CreepTumor";NA;149;0
"Building";"CreepTumor";NA;149;0
"Building";"CreepTumor";NA;149;0
"Building";"CreepTumor";NA;175;0
"Building";"CreepTumor";NA;173;0
"Unit";"Overlord";"Larva";181;0
"Unit";"Overlord";"Larva";181;0
"Unit";"Overlord";"Larva";181;0
"Unit";"Hydralisk";"Larva";181;2
"Unit";"Hydralisk";"Larva";181;2
"Unit";"Hydralisk";"Larva";181;2
"Unit";"Hydralisk";"Larva";181;2
"Unit";"Hydralisk";"Larva";181;2
"Unit";"Hydralisk";"Larva";181;2
"Unit";"Hydralisk";"Larva";181;2
"Unit";"Hydralisk";"Larva";181;2
"Unit";"Hydralisk";"Larva";181;2
"Unit";"Hydralisk";"Larva";181;2
"Unit";"Hydralisk";"Larva";181;2
"Unit";"Hydralisk";"Larva";181;2
"Unit";"Hydralisk";"Larva";181;2
"Unit";"Hydralisk";"Larva";181;2
"Building";"CreepTumor";NA;181;0
"Upgrade";"EvolveGroovedSpines";"HydraliskDen";149;0
"Building";"CreepTumorQueen";NA;209;0
"Building";"CreepTumorQueen";NA;209;0
"Building";"SpineCrawler";NA;209;0
"Unit";"Viper";"Larva";209;3
"Unit";"Viper";"Larva";209;3
"Unit";"Viper";"Larva";209;3
"Building";"Hatchery";NA;181;0
"Building";"Extractor";NA;209;0
"Building";"Extractor";NA;209;0
"Unit";"Hydralisk";"Larva";209;2
"Unit";"Viper";"Larva";209;3
"Unit";"Viper";"Larva";209;3
"Unit";"Viper";"Larva";209;3
"Upgrade";"EvolveMuscularAugments";"HydraliskDen";209;0
"Building";"EvolutionChamber";NA;229;0
"Building";"EvolutionChamber";NA;229;0
"Building";"EvolutionChamber";NA;229;0
"Building";"EvolutionChamber";NA;229;0
"Unit";"Hydralisk";"Larva";229;2
"Unit";"Hydralisk";"Larva";229;2
"Unit";"Hydralisk";"Larva";229;2
"Unit";"Hydralisk";"Larva";229;2
"Unit";"Hydralisk";"Larva";229;2
"Unit";"Hydralisk";"Larva";229;2
"Unit";"Hydralisk";"Larva";229;2
"Unit";"Hydralisk";"Larva";229;2
"Unit";"Hydralisk";"Larva";229;2
"Unit";"Hydralisk";"Larva";229;2
"Unit";"Hydralisk";"Larva";229;2
"Unit";"Hydralisk";"Larva";229;2
"Unit";"Hydralisk";"Larva";229;2
"Unit";"Hydralisk";"Larva";229;2
"Unit";"Hydralisk";"Larva";229;2
"Building";"EvolutionChamber";NA;229;0
"Building";"CreepTumor";NA;259;0
"Building";"CreepTumor";NA;259;0
"Building";"CreepTumor";NA;259;0
"Unit";"Hydralisk";"Larva";259;2
"Unit";"Hydralisk";"Larva";259;2
"Unit";"Hydralisk";"Larva";259;2
"Unit";"Hydralisk";"Larva";259;2
"Unit";"Hydralisk";"Larva";259;2
"Building";"CreepTumor";NA;259;0
"Unit";"Hydralisk";"Larva";259;2
"Unit";"Hydralisk";"Larva";259;2
"Unit";"Hydralisk";"Larva";259;2
"Unit";"Hydralisk";"Larva";259;2
"Unit";"Hydralisk";"Larva";259;2
"Unit";"Hydralisk";"Larva";259;2
"Unit";"Hydralisk";"Larva";259;2
"Unit";"Hydralisk";"Larva";259;2
"Building";"CreepTumor";NA;259;0
"Building";"CreepTumor";NA;259;0
"Building";"CreepTumor";NA;259;0
"Building";"CreepTumor";NA;259;0
"Building";"CreepTumor";NA;259;0
"Building";"CreepTumor";NA;259;0
"Building";"CreepTumor";NA;259;0
"Building";"CreepTumor";NA;259;0
"Building";"SpineCrawler";NA;259;0
"Building";"CreepTumor";NA;261;0
"Unit";"Roach";"Larva";288;2
"Unit";"Roach";"Larva";288;2
"Unit";"Roach";"Larva";288;2
"Unit";"Roach";"Larva";288;2
"Unit";"Roach";"Larva";288;2
"Unit";"Roach";"Larva";288;2
"Unit";"Roach";"Larva";288;2
"Unit";"Roach";"Larva";288;2
"Unit";"Roach";"Larva";288;2
"Unit";"Roach";"Larva";288;2
"Unit";"Roach";"Larva";288;2
"Unit";"Roach";"Larva";288;2
"Unit";"Roach";"Larva";288;2
"Unit";"Roach";"Larva";288;2
"Unit";"Roach";"Larva";288;2
"Building";"Hatchery";NA;259;0
"Building";"Spire";NA;259;0
"Building";"SpineCrawler";NA;288;0
"Building";"SpineCrawler";NA;288;0
"Building";"SpineCrawler";NA;288;0
"Building";"SpineCrawler";NA;288;0
"Building";"CreepTumor";NA;323;0
"Building";"CreepTumor";NA;323;0
"Building";"CreepTumor";NA;323;0
"Building";"CreepTumor";NA;323;0
"Building";"CreepTumor";NA;323;0
"Building";"CreepTumor";NA;323;0
"Building";"CreepTumor";NA;323;0
"Building";"CreepTumor";NA;323;0
"Building";"CreepTumor";NA;323;0
"Building";"CreepTumor";NA;323;0
"Upgrade";"ZergMissileWeaponsLevel2";"EvolutionChamber";259;0
"Building";"CreepTumor";NA;323;0
"Building";"CreepTumor";NA;323;0
"Building";"CreepTumor";NA;324;0
"Building";"CreepTumor";NA;324;0
"Building";"CreepTumor";NA;324;0
"Building";"CreepTumor";NA;324;0
"Building";"CreepTumor";NA;324;0
"Unit";"Corruptor";"Larva";324;2
"Unit";"Corruptor";"Larva";324;2
"Unit";"Corruptor";"Larva";324;2
"Unit";"Corruptor";"Larva";324;2
"Unit";"Corruptor";"Larva";324;2
"Unit";"Corruptor";"Larva";324;2
"Unit";"Corruptor";"Larva";324;2
"Unit";"Corruptor";"Larva";324;2
"Unit";"Corruptor";"Larva";324;2
"Unit";"Corruptor";"Larva";324;2
"Building";"Spire";NA;323;0
"Unit";"Hydralisk";"Larva";344;2
"Unit";"Hydralisk";"Larva";344;2
"Unit";"Hydralisk";"Larva";344;2
"Building";"Hatchery";NA;324;0
"Unit";"Corruptor";"Larva";344;2
"Unit";"Corruptor";"Larva";344;2
"Unit";"Corruptor";"Larva";344;2
"Unit";"Corruptor";"Larva";344;2
"Unit";"Hydralisk";"Larva";354;2
"Unit";"Hydralisk";"Larva";354;2
"Unit";"Hydralisk";"Larva";354;2
"Unit";"Hydralisk";"Larva";354;2
"Unit";"Hydralisk";"Larva";354;2
"Unit";"Hydralisk";"Larva";354;2
"Unit";"Hydralisk";"Larva";354;2
"Unit";"Hydralisk";"Larva";354;2
"Unit";"Hydralisk";"Larva";354;2
"Unit";"Hydralisk";"Larva";354;2
"Unit";"Hydralisk";"Larva";354;2
"Unit";"Hydralisk";"Larva";380;2
"Unit";"Hydralisk";"Larva";380;2
"Unit";"Hydralisk";"Larva";380;2
"Unit";"Hydralisk";"Larva";380;2
"Unit";"Hydralisk";"Larva";380;2
"Unit";"Hydralisk";"Larva";380;2
"Unit";"Hydralisk";"Larva";380;2
"Unit";"Hydralisk";"Larva";380;2
"Unit";"Hydralisk";"Larva";380;2
