"type";"unit_name";"on_building";"total_supply";"supply"
"Unit";"Overlord";"Larva";12;0
"Building";"SpawningPool";NA;16;0
"Unit";"Zergling";"Larva";21;1
"Unit";"Zergling";"Larva";21;1
"Unit";"Overlord";"Larva";21;0
"Building";"Extractor";NA;21;0
"Unit";"Queen";"Hatchery";21;2
"Building";"Hatchery";NA;18;0
"Unit";"Queen";"Hatchery";24;2
"Building";"CreepTumorQueen";NA;30;0
"Unit";"Queen";"Hatchery";27;2
"Unit";"Overlord";"Larva";33;0
"Building";"CreepTumor";NA;39;0
"Unit";"Overlord";"Larva";41;0
"Building";"RoachWarren";NA;39;0
"Building";"Extractor";NA;43;0
"Unit";"Queen";"Hatchery";41;2
"Building";"Extractor";NA;43;0
"Unit";"Overlord";"Larva";44;0
"Unit";"Roach";"Larva";48;2
"Unit";"Roach";"Larva";48;2
"Unit";"Roach";"Larva";48;2
"Unit";"Roach";"Larva";48;2
"Building";"CreepTumorQueen";NA;58;0
"Building";"CreepTumorQueen";NA;59;0
"Building";"CreepTumorQueen";NA;59;0
"Unit";"Roach";"Larva";58;2
"Unit";"Roach";"Larva";58;2
"Unit";"Roach";"Larva";58;2
"Unit";"Overlord";"Larva";59;0
"Unit";"Overlord";"Larva";59;0
"Unit";"Overlord";"Larva";59;0
"Unit";"Roach";"Larva";65;2
"Unit";"Roach";"Larva";65;2
"Unit";"Roach";"Larva";65;2
"Unit";"Roach";"Larva";65;2
"Building";"CreepTumor";NA;67;0
"Building";"CreepTumorQueen";NA;67;0
"Building";"CreepTumorQueen";NA;67;0
"Building";"CreepTumor";NA;67;0
"Building";"CreepTumor";NA;67;0
"Building";"EvolutionChamber";NA;67;0
"Building";"EvolutionChamber";NA;67;0
"Upgrade";"GlialReconstitution";"RoachWarren";59;0
"Building";"Hatchery";NA;58;0
"Unit";"Roach";"Larva";81;2
"Unit";"Roach";"Larva";81;2
"Unit";"Roach";"Larva";81;2
"Unit";"Roach";"Larva";81;2
"Building";"CreepTumor";NA;81;0
"Building";"CreepTumor";NA;81;0
"Unit";"Roach";"Larva";81;2
"Unit";"Roach";"Larva";81;2
"Building";"CreepTumor";NA;81;0
"Building";"CreepTumorQueen";NA;89;0
"Building";"CreepTumor";NA;89;0
"Building";"CreepTumor";NA;89;0
"Unit";"Overlord";"Larva";81;0
"Building";"Extractor";NA;89;0
"Building";"HydraliskDen";NA;89;0
"Building";"CreepTumor";NA;102;0
"Building";"CreepTumor";NA;102;0
"Building";"CreepTumor";NA;102;0
"Unit";"Overlord";"Larva";102;0
"Building";"CreepTumorQueen";NA;102;0
"Building";"CreepTumor";NA;102;0
"Building";"CreepTumor";NA;102;0
"Building";"CreepTumorQueen";NA;102;0
"Unit";"Overlord";"Larva";102;0
"Building";"CreepTumor";NA;107;0
"Building";"CreepTumor";NA;112;0
"Building";"CreepTumor";NA;112;0
"Building";"CreepTumor";NA;112;0
"Building";"CreepTumor";NA;112;0
"Upgrade";"Burrow";"Hatchery";102;0
"Building";"Extractor";NA;112;0
"Building";"Extractor";NA;112;0
"Unit";"Overlord";"Larva";112;0
"Unit";"Overlord";"Larva";112;0
"Unit";"Overlord";"Larva";112;0
"Upgrade";"TunnelingClaws";"RoachWarren";105;0
"Upgrade";"ZergMissileWeaponsLevel1";"EvolutionChamber";99;0
"Upgrade";"ZergGroundArmorsLevel1";"EvolutionChamber";99;0
"Building";"CreepTumor";NA;114;0
"Building";"CreepTumor";NA;114;0
"Unit";"Hydralisk";"Larva";112;2
"Unit";"Hydralisk";"Larva";112;2
"Unit";"Hydralisk";"Larva";113;2
"Unit";"Hydralisk";"Larva";114;2
"Unit";"Hydralisk";"Larva";114;2
"Unit";"Hydralisk";"Larva";114;2
"Unit";"Hydralisk";"Larva";114;2
"Upgrade";"EvolveGroovedSpines";"HydraliskDen";112;0
"Building";"CreepTumor";NA;116;0
"Building";"CreepTumor";NA;116;0
"Building";"CreepTumor";NA;116;0
"Building";"SporeCrawler";NA;115;0
"Building";"SporeCrawler";NA;115;0
"Unit";"Hydralisk";"Larva";133;2
"Unit";"Hydralisk";"Larva";133;2
"Unit";"Hydralisk";"Larva";133;2
"Unit";"Roach";"Larva";133;2
"Unit";"Roach";"Larva";133;2
"Unit";"Roach";"Larva";133;2
"Unit";"Roach";"Larva";133;2
"Unit";"Overlord";"Larva";133;0
"Unit";"Roach";"Larva";133;2
"Unit";"Roach";"Larva";133;2
"Building";"Hatchery";NA;114;0
"Building";"CreepTumor";NA;163;0
"Building";"CreepTumor";NA;163;0
"Building";"InfestationPit";NA;151;0
"Building";"SporeCrawler";NA;163;0
"Building";"SporeCrawler";NA;163;0
"Upgrade";"EvolveMuscularAugments";"HydraliskDen";151;0
"Building";"CreepTumor";NA;171;0
"Building";"CreepTumor";NA;171;0
"Building";"CreepTumor";NA;171;0
"Unit";"Hydralisk";"Larva";171;2
"Unit";"Hydralisk";"Larva";171;2
"Unit";"Roach";"Larva";171;2
"Unit";"Overlord";"Larva";171;0
"Unit";"Overlord";"Larva";171;0
"Unit";"Overlord";"Larva";171;0
"Upgrade";"ZergMissileWeaponsLevel2";"EvolutionChamber";139;0
"Upgrade";"ZergGroundArmorsLevel2";"EvolutionChamber";139;0
"Building";"Hatchery";NA;163;0
"Building";"CreepTumor";NA;177;0
"Building";"CreepTumor";NA;177;0
"Unit";"Hydralisk";"Larva";177;2
"Unit";"Hydralisk";"Larva";177;2
"Unit";"Hydralisk";"Larva";177;2
"Unit";"Hydralisk";"Larva";177;2
"Unit";"Hydralisk";"Larva";177;2
"Unit";"Hydralisk";"Larva";177;2
"Unit";"Hydralisk";"Larva";177;2
"Unit";"Hydralisk";"Larva";177;2
"Unit";"Hydralisk";"Larva";177;2
"Unit";"Hydralisk";"Larva";177;2
"Unit";"Hydralisk";"Larva";177;2
"Unit";"Hydralisk";"Larva";177;2
"Unit";"Hydralisk";"Larva";177;2
"Unit";"Hydralisk";"Larva";177;2
"Unit";"Hydralisk";"Larva";177;2
"Building";"CreepTumor";NA;177;0
"Building";"SporeCrawler";NA;177;0
"Unit";"Overlord";"Larva";177;0
"Unit";"Overlord";"Larva";177;0
"Unit";"Roach";"Larva";207;2
"Unit";"Roach";"Larva";207;2
"Unit";"Roach";"Larva";207;2
"Unit";"Roach";"Larva";207;2
"Unit";"Roach";"Larva";207;2
"Unit";"Roach";"Larva";207;2
"Unit";"Roach";"Larva";207;2
"Unit";"Roach";"Larva";207;2
"Unit";"Roach";"Larva";207;2
"Unit";"Roach";"Larva";207;2
"Unit";"Roach";"Larva";207;2
"Unit";"Roach";"Larva";207;2
"Unit";"Roach";"Larva";207;2
"Unit";"Roach";"Larva";207;2
"Unit";"Roach";"Larva";207;2
"Unit";"Roach";"Larva";207;2
"Unit";"Roach";"Larva";207;2
"Unit";"Viper";"Larva";207;3
"Unit";"Roach";"Larva";207;2
"Unit";"Roach";"Larva";207;2
"Unit";"Roach";"Larva";207;2
"Unit";"Roach";"Larva";207;2
"Unit";"Roach";"Larva";207;2
"Unit";"Roach";"Larva";207;2
"Unit";"Roach";"Larva";235;2
"Unit";"Roach";"Larva";235;2
"Building";"Hatchery";NA;177;0
"Unit";"Roach";"Larva";241;2
"Unit";"Roach";"Larva";241;2
"Unit";"Roach";"Larva";241;2
"Unit";"Roach";"Larva";241;2
"Unit";"Roach";"Larva";241;2
"Unit";"Roach";"Larva";244;2
"Unit";"Roach";"Larva";244;2
"Unit";"Hydralisk";"Larva";256;2
"Unit";"Hydralisk";"Larva";256;2
"Unit";"Hydralisk";"Larva";256;2
"Unit";"Hydralisk";"Larva";256;2
"Unit";"Hydralisk";"Larva";256;2
"Building";"CreepTumor";NA;270;0
"Building";"CreepTumor";NA;270;0
"Building";"Extractor";NA;260;0
"Building";"CreepTumor";NA;289;0
"Building";"CreepTumor";NA;289;0
"Unit";"Viper";"Larva";274;3
"Building";"CreepTumorQueen";NA;289;0
"Unit";"Roach";"Larva";292;2
"Unit";"Roach";"Larva";292;2
"Unit";"Hydralisk";"Larva";292;2
"Unit";"Hydralisk";"Larva";292;2
"Unit";"Hydralisk";"Larva";292;2
"Unit";"Hydralisk";"Larva";292;2
"Unit";"Hydralisk";"Larva";292;2
"Unit";"Hydralisk";"Larva";292;2
"Unit";"Hydralisk";"Larva";292;2
"Unit";"Hydralisk";"Larva";292;2
"Unit";"Hydralisk";"Larva";292;2
"Unit";"Hydralisk";"Larva";292;2
"Unit";"Hydralisk";"Larva";292;2
"Building";"Extractor";NA;292;0
"Building";"Extractor";NA;292;0
"Building";"CreepTumor";NA;318;0
"Building";"CreepTumor";NA;318;0
"Unit";"Hydralisk";"Larva";292;2
"Upgrade";"ZergMissileWeaponsLevel3";"EvolutionChamber";235;0
"Upgrade";"ZergGroundArmorsLevel3";"EvolutionChamber";235;0
"Building";"CreepTumor";NA;328;0
"Building";"CreepTumor";NA;332;0
"Building";"CreepTumor";NA;334;0
"Building";"CreepTumor";NA;334;0
"Building";"CreepTumor";NA;334;0
"Building";"CreepTumor";NA;334;0
"Unit";"Roach";"Larva";334;2
"Unit";"Roach";"Larva";334;2
"Unit";"Roach";"Larva";334;2
"Unit";"Roach";"Larva";334;2
"Unit";"Roach";"Larva";334;2
"Unit";"Roach";"Larva";334;2
"Unit";"Roach";"Larva";334;2
"Unit";"Roach";"Larva";334;2
"Unit";"Roach";"Larva";334;2
"Unit";"Roach";"Larva";334;2
"Unit";"Roach";"Larva";334;2
"Unit";"Roach";"Larva";334;2
"Unit";"Roach";"Larva";334;2
"Unit";"Roach";"Larva";334;2
