"type";"unit_name";"on_building";"total_supply";"supply"
"Unit";"Overlord";"Larva";13;0
"Building";"Extractor";NA;18;0
"Unit";"Overlord";"Larva";21;0
"Building";"SpawningPool";NA;19;0
"Building";"Hatchery";NA;17;0
"Unit";"Zergling";"Larva";22;1
"Unit";"Zergling";"Larva";22;1
"Unit";"Zergling";"Larva";22;1
"Unit";"Zergling";"Larva";22;1
"Unit";"Queen";"Hatchery";22;2
"Unit";"Queen";"Hatchery";22;2
"Unit";"Overlord";"Larva";30;0
"Unit";"Queen";"Hatchery";33;2
"Building";"CreepTumorQueen";NA;40;0
"Unit";"Overlord";"Larva";40;0
"Unit";"Queen";"Hatchery";43;2
"Building";"CreepTumorQueen";NA;49;0
"Building";"CreepTumorQueen";NA;51;0
"Building";"CreepTumor";NA;51;0
"Unit";"Overlord";"Larva";49;0
"Unit";"Overlord";"Larva";49;0
"Unit";"Overlord";"Larva";49;0
"Building";"Extractor";NA;49;0
"Unit";"Overlord";"Larva";59;0
"Building";"EvolutionChamber";NA;51;0
"Building";"EvolutionChamber";NA;51;0
"Unit";"Overlord";"Larva";60;0
"Building";"CreepTumor";NA;60;0
"Building";"CreepTumor";NA;60;0
"Unit";"Zergling";"Larva";60;1
"Unit";"Zergling";"Larva";60;1
"Unit";"Zergling";"Larva";60;1
"Unit";"Zergling";"Larva";60;1
"Unit";"Zergling";"Larva";60;1
"Unit";"Zergling";"Larva";60;1
"Building";"SporeCrawler";NA;60;0
"Building";"SporeCrawler";NA;60;0
"Unit";"Queen";"Hatchery";60;2
"Building";"Hatchery";NA;49;0
"Building";"CreepTumor";NA;70;0
"Building";"CreepTumor";NA;84;0
"Building";"CreepTumor";NA;84;0
"Unit";"Queen";"Hatchery";70;2
"Building";"Extractor";NA;84;0
"Building";"CreepTumor";NA;92;0
"Unit";"Queen";"Hatchery";84;2
"Building";"SporeCrawler";NA;92;0
"Building";"SpineCrawler";NA;84;0
"Unit";"Overlord";"Larva";92;0
"Upgrade";"ZergMeleeWeaponsLevel1";"EvolutionChamber";70;0
"Upgrade";"ZergGroundArmorsLevel1";"EvolutionChamber";70;0
"Building";"CreepTumor";NA;94;0
"Building";"CreepTumor";NA;94;0
"Building";"Extractor";NA;94;0
"Building";"CreepTumorQueen";NA;94;0
"Building";"CreepTumorQueen";NA;94;0
"Building";"Extractor";NA;107;0
"Building";"Extractor";NA;107;0
"Building";"CreepTumorQueen";NA;112;0
"Unit";"Overlord";"Larva";112;0
"Unit";"Overlord";"Larva";112;0
"Building";"CreepTumor";NA;112;0
"Unit";"Zergling";"Larva";112;1
"Unit";"Zergling";"Larva";112;1
"Unit";"Zergling";"Larva";112;1
"Unit";"Zergling";"Larva";112;1
"Unit";"Zergling";"Larva";112;1
"Unit";"Zergling";"Larva";112;1
"Unit";"Zergling";"Larva";112;1
"Unit";"Zergling";"Larva";112;1
"Unit";"Zergling";"Larva";112;1
"Unit";"Zergling";"Larva";112;1
"Unit";"Zergling";"Larva";112;1
"Unit";"Zergling";"Larva";112;1
"Unit";"Zergling";"Larva";112;1
"Unit";"Zergling";"Larva";112;1
"Unit";"Zergling";"Larva";112;1
"Unit";"Zergling";"Larva";112;1
"Unit";"Zergling";"Larva";112;1
"Unit";"Zergling";"Larva";112;1
"Unit";"Zergling";"Larva";112;1
"Unit";"Zergling";"Larva";112;1
"Unit";"Zergling";"Larva";112;1
"Unit";"Zergling";"Larva";112;1
"Unit";"Zergling";"Larva";112;1
"Unit";"Zergling";"Larva";112;1
"Unit";"Zergling";"Larva";112;1
"Unit";"Zergling";"Larva";112;1
"Unit";"Zergling";"Larva";112;1
"Unit";"Zergling";"Larva";112;1
"Unit";"Overlord";"Larva";112;0
"Unit";"Overlord";"Larva";112;0
"Building";"BanelingNest";NA;112;0
"Building";"Hatchery";NA;107;0
"Building";"CreepTumor";NA;143;0
"Building";"Spire";NA;112;0
"Building";"CreepTumorQueen";NA;147;0
"Building";"CreepTumorQueen";NA;147;0
"Building";"CreepTumor";NA;147;0
"Unit";"Mutalisk";"Larva";146;2
"Unit";"Mutalisk";"Larva";147;2
"Unit";"Mutalisk";"Larva";147;2
"Building";"CreepTumorQueen";NA;147;0
"Unit";"Mutalisk";"Larva";147;2
"Unit";"Mutalisk";"Larva";147;2
"Unit";"Mutalisk";"Larva";147;2
"Unit";"Mutalisk";"Larva";147;2
"Building";"CreepTumor";NA;147;0
"Unit";"Mutalisk";"Larva";147;2
"Unit";"Mutalisk";"Larva";147;2
"Unit";"Mutalisk";"Larva";147;2
"Building";"CreepTumor";NA;147;0
"Upgrade";"ZergMeleeWeaponsLevel2";"EvolutionChamber";112;0
"Upgrade";"ZergGroundArmorsLevel2";"EvolutionChamber";112;0
"Building";"CreepTumorQueen";NA;167;0
"Unit";"Overlord";"Larva";147;0
"Unit";"Zergling";"Larva";147;1
"Unit";"Zergling";"Larva";147;1
"Unit";"Overlord";"Larva";147;0
"Unit";"Zergling";"Larva";147;1
"Unit";"Zergling";"Larva";147;1
"Unit";"Zergling";"Larva";147;1
"Unit";"Zergling";"Larva";147;1
"Unit";"Zergling";"Larva";147;1
"Unit";"Zergling";"Larva";147;1
"Unit";"Zergling";"Larva";147;1
"Unit";"Zergling";"Larva";147;1
"Unit";"Zergling";"Larva";147;1
"Unit";"Zergling";"Larva";147;1
"Unit";"Zergling";"Larva";147;1
"Unit";"Zergling";"Larva";147;1
"Unit";"Zergling";"Larva";147;1
"Unit";"Zergling";"Larva";147;1
"Building";"CreepTumorQueen";NA;167;0
"Unit";"Zergling";"Larva";147;1
"Unit";"Zergling";"Larva";147;1
"Unit";"Zergling";"Larva";147;1
"Unit";"Zergling";"Larva";147;1
"Unit";"Zergling";"Larva";147;1
"Unit";"Zergling";"Larva";147;1
"Building";"CreepTumorQueen";NA;167;0
"Unit";"Overlord";"Larva";167;0
"Unit";"Zergling";"Larva";189;1
"Unit";"Zergling";"Larva";189;1
"Unit";"Zergling";"Larva";189;1
"Unit";"Zergling";"Larva";189;1
"Unit";"Zergling";"Larva";189;1
"Unit";"Zergling";"Larva";189;1
"Unit";"Zergling";"Larva";189;1
"Unit";"Zergling";"Larva";189;1
"Unit";"Zergling";"Larva";189;1
"Unit";"Zergling";"Larva";189;1
"Unit";"Zergling";"Larva";189;1
"Unit";"Zergling";"Larva";189;1
"Unit";"Zergling";"Larva";189;1
"Unit";"Zergling";"Larva";189;1
"Building";"CreepTumor";NA;189;0
"Building";"CreepTumor";NA;203;0
"Building";"Hatchery";NA;147;0
"Building";"CreepTumorQueen";NA;203;0
"Unit";"Overlord";"Larva";215;0
"Unit";"Overlord";"Larva";215;0
"Unit";"Mutalisk";"Larva";215;2
"Unit";"Mutalisk";"Larva";215;2
"Building";"Extractor";NA;215;0
"Building";"Extractor";NA;215;0
"Building";"CreepTumor";NA;227;0
"Building";"CreepTumor";NA;227;0
"Building";"Hatchery";NA;189;0
"Unit";"Mutalisk";"Larva";227;2
"Unit";"Mutalisk";"Larva";227;2
"Unit";"Mutalisk";"Larva";227;2
"Unit";"Mutalisk";"Larva";227;2
"Unit";"Mutalisk";"Larva";227;2
"Unit";"Mutalisk";"Larva";227;2
"Building";"CreepTumor";NA;227;0
"Building";"InfestationPit";NA;216;0
"Building";"CreepTumorQueen";NA;239;0
"Building";"CreepTumor";NA;239;0
"Building";"CreepTumorQueen";NA;239;0
"Building";"CreepTumorQueen";NA;239;0
"Building";"CreepTumorQueen";NA;239;0
"Unit";"Overlord";"Larva";239;0
"Unit";"Zergling";"Larva";239;1
"Unit";"Zergling";"Larva";239;1
"Unit";"Zergling";"Larva";239;1
"Unit";"Zergling";"Larva";239;1
"Unit";"Zergling";"Larva";239;1
"Unit";"Zergling";"Larva";239;1
"Unit";"Zergling";"Larva";239;1
"Unit";"Zergling";"Larva";239;1
"Unit";"Zergling";"Larva";239;1
"Unit";"Zergling";"Larva";239;1
"Unit";"Zergling";"Larva";239;1
"Unit";"Zergling";"Larva";239;1
"Unit";"Zergling";"Larva";239;1
"Unit";"Zergling";"Larva";239;1
"Unit";"Zergling";"Larva";239;1
"Unit";"Zergling";"Larva";239;1
"Unit";"Zergling";"Larva";239;1
"Unit";"Zergling";"Larva";239;1
"Unit";"Zergling";"Larva";239;1
"Unit";"Zergling";"Larva";239;1
"Unit";"Zergling";"Larva";239;1
"Unit";"Zergling";"Larva";239;1
"Unit";"Zergling";"Larva";239;1
"Unit";"Zergling";"Larva";239;1
"Unit";"Zergling";"Larva";239;1
"Unit";"Zergling";"Larva";239;1
"Unit";"Zergling";"Larva";239;1
"Unit";"Zergling";"Larva";239;1
"Building";"CreepTumor";NA;239;0
"Building";"CreepTumor";NA;239;0
"Unit";"Overlord";"Larva";239;0
"Unit";"Overlord";"Larva";239;0
"Building";"CreepTumor";NA;239;0
"Unit";"Baneling";"Zergling";267;0
"Unit";"Baneling";"Zergling";267;0
"Unit";"Baneling";"Zergling";267;0
"Unit";"Baneling";"Zergling";267;0
"Unit";"Baneling";"Zergling";267;0
"Unit";"Baneling";"Zergling";267;0
"Unit";"Baneling";"Zergling";267;0
"Unit";"Baneling";"Zergling";267;0
"Unit";"Baneling";"Zergling";267;0
"Unit";"Baneling";"Zergling";267;0
"Unit";"Baneling";"Zergling";267;0
"Unit";"Baneling";"Zergling";267;0
"Unit";"Baneling";"Zergling";267;0
"Unit";"Baneling";"Zergling";267;0
"Unit";"Baneling";"Zergling";267;0
"Unit";"Baneling";"Zergling";267;0
"Unit";"Baneling";"Zergling";267;0
"Unit";"Baneling";"Zergling";267;0
"Unit";"Baneling";"Zergling";267;0
"Building";"CreepTumorQueen";NA;267;0
"Unit";"Zergling";"Larva";267;1
"Unit";"Zergling";"Larva";267;1
"Unit";"Zergling";"Larva";267;1
"Unit";"Zergling";"Larva";267;1
"Unit";"Zergling";"Larva";267;1
"Unit";"Zergling";"Larva";267;1
"Unit";"Zergling";"Larva";267;1
"Unit";"Zergling";"Larva";267;1
"Unit";"Zergling";"Larva";267;1
"Unit";"Zergling";"Larva";267;1
"Unit";"Zergling";"Larva";267;1
"Unit";"Zergling";"Larva";267;1
"Unit";"Zergling";"Larva";267;1
"Unit";"Zergling";"Larva";267;1
"Unit";"Zergling";"Larva";267;1
"Unit";"Zergling";"Larva";267;1
"Unit";"Zergling";"Larva";267;1
"Unit";"Zergling";"Larva";267;1
"Unit";"Zergling";"Larva";267;1
"Unit";"Zergling";"Larva";267;1
"Unit";"Zergling";"Larva";267;1
"Unit";"Zergling";"Larva";267;1
"Unit";"Zergling";"Larva";267;1
"Unit";"Zergling";"Larva";267;1
"Unit";"Zergling";"Larva";267;1
"Unit";"Zergling";"Larva";267;1
"Unit";"Baneling";"Zergling";267;0
"Unit";"Baneling";"Zergling";267;0
"Unit";"Baneling";"Zergling";267;0
"Unit";"Baneling";"Zergling";267;0
"Unit";"Baneling";"Zergling";267;0
"Unit";"Baneling";"Zergling";267;0
"Unit";"Baneling";"Zergling";267;0
"Unit";"Zergling";"Larva";267;1
"Unit";"Zergling";"Larva";267;1
"Unit";"Zergling";"Larva";267;1
"Unit";"Zergling";"Larva";267;1
"Unit";"Zergling";"Larva";267;1
"Unit";"Zergling";"Larva";267;1
"Unit";"Zergling";"Larva";267;1
"Unit";"Zergling";"Larva";267;1
"Unit";"Zergling";"Larva";267;1
"Unit";"Zergling";"Larva";267;1
"Unit";"Zergling";"Larva";303;1
"Unit";"Zergling";"Larva";303;1
"Unit";"Zergling";"Larva";303;1
"Unit";"Zergling";"Larva";303;1
"Unit";"Zergling";"Larva";303;1
"Unit";"Zergling";"Larva";303;1
"Unit";"Zergling";"Larva";303;1
"Unit";"Zergling";"Larva";303;1
"Unit";"Zergling";"Larva";303;1
"Unit";"Zergling";"Larva";303;1
"Unit";"Zergling";"Larva";303;1
"Unit";"Zergling";"Larva";303;1
"Unit";"Zergling";"Larva";303;1
"Unit";"Zergling";"Larva";303;1
"Building";"CreepTumor";NA;303;0
"Building";"CreepTumor";NA;303;0
"Building";"CreepTumor";NA;303;0
"Building";"CreepTumor";NA;303;0
"Building";"CreepTumor";NA;303;0
"Unit";"Zergling";"Larva";317;1
"Unit";"Zergling";"Larva";317;1
"Unit";"Zergling";"Larva";317;1
"Unit";"Zergling";"Larva";317;1
"Unit";"Zergling";"Larva";317;1
"Unit";"Zergling";"Larva";317;1
"Unit";"Zergling";"Larva";317;1
"Unit";"Zergling";"Larva";317;1
"Unit";"Zergling";"Larva";317;1
"Unit";"Zergling";"Larva";317;1
"Unit";"Zergling";"Larva";317;1
"Unit";"Zergling";"Larva";317;1
"Building";"CreepTumorQueen";NA;317;0
"Building";"Hatchery";NA;267;0
"Building";"CreepTumorQueen";NA;317;0
"Unit";"Baneling";"Zergling";317;0
"Unit";"Baneling";"Zergling";317;0
"Unit";"Baneling";"Zergling";317;0
"Unit";"Baneling";"Zergling";317;0
"Unit";"Baneling";"Zergling";317;0
"Unit";"Baneling";"Zergling";317;0
"Building";"CreepTumorQueen";NA;317;0
"Building";"CreepTumorQueen";NA;317;0
"Unit";"Baneling";"Zergling";317;0
"Unit";"Baneling";"Zergling";317;0
"Unit";"Baneling";"Zergling";317;0
"Unit";"Baneling";"Zergling";317;0
"Unit";"Baneling";"Zergling";317;0
"Unit";"Baneling";"Zergling";317;0
"Unit";"Baneling";"Zergling";317;0
"Unit";"Baneling";"Zergling";317;0
"Unit";"Baneling";"Zergling";317;0
"Unit";"Overlord";"Larva";329;0
"Building";"UltraliskCavern";NA;317;0
"Building";"CreepTumor";NA;329;0
"Building";"Hatchery";NA;317;0
"Building";"CreepTumorQueen";NA;329;0
"Building";"CreepTumorQueen";NA;329;0
"Building";"CreepTumor";NA;329;0
"Building";"CreepTumor";NA;329;0
"Building";"CreepTumor";NA;329;0
"Building";"CreepTumor";NA;329;0
"Building";"CreepTumorQueen";NA;329;0
"Building";"CreepTumor";NA;329;0
"Unit";"Ultralisk";"Larva";329;6
"Unit";"Ultralisk";"Larva";329;6
"Unit";"Ultralisk";"Larva";329;6
"Unit";"Ultralisk";"Larva";329;6
"Unit";"Ultralisk";"Larva";329;6
"Building";"Extractor";NA;329;0
"Building";"Extractor";NA;329;0
"Unit";"Ultralisk";"Larva";329;6
"Unit";"Ultralisk";"Larva";329;6
"Building";"CreepTumor";NA;359;0
"Upgrade";"ChitinousPlating";"UltraliskCavern";329;0
"Unit";"Zergling";"Larva";371;1
"Unit";"Zergling";"Larva";371;1
"Upgrade";"ZergMeleeWeaponsLevel3";"EvolutionChamber";329;0
"Unit";"Zergling";"Larva";371;1
"Unit";"Zergling";"Larva";371;1
"Unit";"Zergling";"Larva";371;1
"Unit";"Zergling";"Larva";371;1
"Unit";"Zergling";"Larva";371;1
"Unit";"Zergling";"Larva";371;1
"Unit";"Zergling";"Larva";371;1
"Unit";"Zergling";"Larva";371;1
"Unit";"Zergling";"Larva";371;1
"Unit";"Zergling";"Larva";371;1
"Unit";"Zergling";"Larva";371;1
"Unit";"Zergling";"Larva";371;1
"Upgrade";"ZergGroundArmorsLevel3";"EvolutionChamber";329;0
"Building";"CreepTumor";NA;371;0
"Building";"CreepTumor";NA;371;0
"Unit";"Ultralisk";"Larva";371;6
"Unit";"Ultralisk";"Larva";371;6
"Unit";"Ultralisk";"Larva";371;6
"Unit";"Ultralisk";"Larva";371;6
"Unit";"Baneling";"Zergling";409;0
"Unit";"Baneling";"Zergling";409;0
"Unit";"Baneling";"Zergling";409;0
"Unit";"Baneling";"Zergling";409;0
"Unit";"Baneling";"Zergling";409;0
"Unit";"Baneling";"Zergling";409;0
"Unit";"Baneling";"Zergling";409;0
"Unit";"Baneling";"Zergling";409;0
"Unit";"Baneling";"Zergling";409;0
"Unit";"Baneling";"Zergling";409;0
"Unit";"Baneling";"Zergling";409;0
"Unit";"Baneling";"Zergling";409;0
"Unit";"Baneling";"Zergling";409;0
"Unit";"Baneling";"Zergling";409;0
