"type";"unit_name";"on_building";"total_supply";"supply"
"Unit";"Overlord";"Larva";13;0
"Building";"Extractor";NA;18;0
"Unit";"Overlord";"Larva";21;0
"Building";"SpawningPool";NA;19;0
"Building";"Hatchery";NA;17;0
"Unit";"Zergling";"Larva";22;1
"Unit";"Zergling";"Larva";22;1
"Unit";"Zergling";"Larva";22;1
"Unit";"Zergling";"Larva";22;1
"Unit";"Zergling";"Larva";22;1
"Unit";"Zergling";"Larva";22;1
"Unit";"Queen";"Hatchery";22;2
"Unit";"Queen";"Hatchery";22;2
"Unit";"Overlord";"Larva";37;0
"Unit";"Overlord";"Larva";39;0
"Unit";"Queen";"Hatchery";38;2
"Building";"EvolutionChamber";NA;51;0
"Building";"CreepTumorQueen";NA;55;0
"Unit";"Overlord";"Larva";55;0
"Unit";"Overlord";"Larva";56;0
"Building";"Extractor";NA;56;0
"Unit";"Overlord";"Larva";58;0
"Building";"Extractor";NA;58;0
"Unit";"Queen";"Hatchery";55;2
"Building";"CreepTumor";NA;60;0
"Building";"Hatchery";NA;53;0
"Unit";"Queen";"Hatchery";58;2
"Building";"BanelingNest";NA;58;0
"Unit";"Zergling";"Larva";69;1
"Unit";"Zergling";"Larva";69;1
"Unit";"Zergling";"Larva";69;1
"Unit";"Zergling";"Larva";69;1
"Unit";"Zergling";"Larva";69;1
"Unit";"Zergling";"Larva";69;1
"Unit";"Zergling";"Larva";69;1
"Unit";"Zergling";"Larva";69;1
"Unit";"Zergling";"Larva";69;1
"Unit";"Zergling";"Larva";69;1
"Unit";"Zergling";"Larva";69;1
"Unit";"Zergling";"Larva";69;1
"Unit";"Zergling";"Larva";69;1
"Unit";"Zergling";"Larva";69;1
"Unit";"Zergling";"Larva";69;1
"Unit";"Zergling";"Larva";69;1
"Building";"CreepTumorQueen";NA;69;0
"Building";"CreepTumor";NA;69;0
"Building";"CreepTumorQueen";NA;69;0
"Unit";"Zergling";"Larva";69;1
"Unit";"Zergling";"Larva";69;1
"Unit";"Zergling";"Larva";69;1
"Unit";"Zergling";"Larva";69;1
"Unit";"Baneling";"Zergling";87;0
"Unit";"Baneling";"Zergling";87;0
"Unit";"Baneling";"Zergling";87;0
"Unit";"Baneling";"Zergling";87;0
"Unit";"Baneling";"Zergling";87;0
"Unit";"Zergling";"Larva";87;1
"Unit";"Zergling";"Larva";87;1
"Unit";"Overlord";"Larva";87;0
"Unit";"Zergling";"Larva";87;1
"Unit";"Zergling";"Larva";87;1
"Unit";"Zergling";"Larva";87;1
"Unit";"Zergling";"Larva";87;1
"Unit";"Zergling";"Larva";87;1
"Unit";"Zergling";"Larva";87;1
"Unit";"Zergling";"Larva";87;1
"Unit";"Zergling";"Larva";87;1
"Unit";"Queen";"Hatchery";83;2
"Unit";"Baneling";"Zergling";107;0
"Unit";"Baneling";"Zergling";107;0
"Unit";"Baneling";"Zergling";107;0
"Unit";"Overlord";"Larva";105;0
"Building";"CreepTumor";NA;107;0
"Unit";"Overlord";"Larva";105;0
"Unit";"Overlord";"Larva";105;0
"Building";"CreepTumorQueen";NA;110;0
"Unit";"Overlord";"Larva";109;0
"Unit";"Overlord";"Larva";109;0
"Upgrade";"ZergGroundArmorsLevel1";"EvolutionChamber";69;0
"Building";"Extractor";NA;110;0
"Building";"Extractor";NA;110;0
"Building";"EvolutionChamber";NA;110;0
"Building";"Extractor";NA;116;0
"Building";"CreepTumor";NA;124;0
"Unit";"Overlord";"Larva";123;0
"Unit";"Overlord";"Larva";124;0
"Unit";"Overlord";"Larva";124;0
"Unit";"Zergling";"Larva";124;1
"Unit";"Zergling";"Larva";124;1
"Unit";"Zergling";"Larva";124;1
"Unit";"Zergling";"Larva";124;1
"Unit";"Zergling";"Larva";127;1
"Unit";"Zergling";"Larva";127;1
"Unit";"Zergling";"Larva";129;1
"Unit";"Zergling";"Larva";129;1
"Unit";"Zergling";"Larva";131;1
"Unit";"Zergling";"Larva";131;1
"Unit";"Zergling";"Larva";131;1
"Unit";"Zergling";"Larva";131;1
"Unit";"Zergling";"Larva";131;1
"Unit";"Zergling";"Larva";131;1
"Unit";"Zergling";"Larva";131;1
"Unit";"Zergling";"Larva";131;1
"Unit";"Zergling";"Larva";131;1
"Unit";"Zergling";"Larva";131;1
"Building";"CreepTumor";NA;132;0
"Unit";"Zergling";"Larva";131;1
"Unit";"Zergling";"Larva";131;1
"Unit";"Zergling";"Larva";131;1
"Unit";"Zergling";"Larva";131;1
"Unit";"Overlord";"Larva";132;0
"Unit";"Zergling";"Larva";132;1
"Unit";"Zergling";"Larva";132;1
"Unit";"Zergling";"Larva";132;1
"Unit";"Zergling";"Larva";132;1
"Building";"CreepTumor";NA;146;0
"Building";"Spire";NA;110;0
"Unit";"Zergling";"Larva";136;1
"Unit";"Zergling";"Larva";136;1
"Unit";"Zergling";"Larva";144;1
"Unit";"Zergling";"Larva";144;1
"Unit";"Zergling";"Larva";146;1
"Unit";"Zergling";"Larva";146;1
"Unit";"Zergling";"Larva";146;1
"Unit";"Zergling";"Larva";146;1
"Unit";"Zergling";"Larva";150;1
"Unit";"Zergling";"Larva";150;1
"Unit";"Zergling";"Larva";150;1
"Unit";"Zergling";"Larva";150;1
"Building";"CreepTumor";NA;151;0
"Unit";"Baneling";"Zergling";151;0
"Unit";"Baneling";"Zergling";151;0
"Unit";"Baneling";"Zergling";151;0
"Unit";"Baneling";"Zergling";151;0
"Unit";"Zergling";"Larva";151;1
"Unit";"Zergling";"Larva";151;1
"Unit";"Baneling";"Zergling";151;0
"Unit";"Zergling";"Larva";151;1
"Unit";"Zergling";"Larva";151;1
"Unit";"Zergling";"Larva";151;1
"Unit";"Zergling";"Larva";151;1
"Unit";"Zergling";"Larva";151;1
"Unit";"Zergling";"Larva";151;1
"Unit";"Zergling";"Larva";153;1
"Unit";"Zergling";"Larva";153;1
"Unit";"Zergling";"Larva";161;1
"Unit";"Zergling";"Larva";161;1
"Unit";"Baneling";"Zergling";175;0
"Unit";"Baneling";"Zergling";175;0
"Unit";"Baneling";"Zergling";175;0
"Unit";"Baneling";"Zergling";175;0
"Unit";"Baneling";"Zergling";175;0
"Unit";"Mutalisk";"Larva";167;2
"Unit";"Mutalisk";"Larva";167;2
"Unit";"Mutalisk";"Larva";167;2
"Unit";"Mutalisk";"Larva";167;2
"Unit";"Baneling";"Zergling";179;0
"Unit";"Baneling";"Zergling";179;0
"Unit";"Mutalisk";"Larva";177;2
"Unit";"Mutalisk";"Larva";177;2
"Unit";"Overlord";"Larva";179;0
"Unit";"Zergling";"Larva";179;1
"Unit";"Zergling";"Larva";179;1
"Unit";"Zergling";"Larva";179;1
"Unit";"Zergling";"Larva";179;1
"Unit";"Zergling";"Larva";179;1
"Unit";"Zergling";"Larva";179;1
"Unit";"Zergling";"Larva";179;1
"Unit";"Zergling";"Larva";179;1
"Unit";"Zergling";"Larva";179;1
"Unit";"Zergling";"Larva";179;1
"Unit";"Zergling";"Larva";179;1
"Unit";"Zergling";"Larva";179;1
"Unit";"Zergling";"Larva";187;1
"Unit";"Zergling";"Larva";187;1
"Unit";"Zergling";"Larva";187;1
"Unit";"Zergling";"Larva";187;1
"Unit";"Zergling";"Larva";187;1
"Unit";"Zergling";"Larva";187;1
"Unit";"Zergling";"Larva";187;1
"Unit";"Zergling";"Larva";187;1
"Unit";"Zergling";"Larva";187;1
"Unit";"Zergling";"Larva";187;1
"Unit";"Zergling";"Larva";187;1
"Unit";"Zergling";"Larva";187;1
"Unit";"Zergling";"Larva";187;1
"Unit";"Zergling";"Larva";187;1
"Unit";"Zergling";"Larva";187;1
"Unit";"Zergling";"Larva";187;1
"Building";"Hatchery";NA;150;0
"Unit";"Queen";"Hatchery";179;2
"Unit";"Mutalisk";"Larva";187;2
"Unit";"Mutalisk";"Larva";189;2
"Upgrade";"ZergMeleeWeaponsLevel1";"EvolutionChamber";146;0
"Unit";"Zergling";"Larva";219;1
"Unit";"Zergling";"Larva";219;1
"Unit";"Baneling";"Zergling";232;0
"Unit";"Baneling";"Zergling";232;0
"Unit";"Baneling";"Zergling";232;0
"Unit";"Baneling";"Zergling";232;0
"Unit";"Overlord";"Larva";232;0
"Unit";"Mutalisk";"Larva";224;2
"Unit";"Mutalisk";"Larva";224;2
"Unit";"Mutalisk";"Larva";224;2
"Unit";"Zergling";"Larva";232;1
"Unit";"Zergling";"Larva";232;1
"Unit";"Baneling";"Zergling";234;0
"Unit";"Baneling";"Zergling";234;0
"Unit";"Baneling";"Zergling";234;0
"Unit";"Baneling";"Zergling";234;0
"Unit";"Mutalisk";"Larva";232;2
"Unit";"Baneling";"Zergling";234;0
"Unit";"Zergling";"Larva";234;1
"Unit";"Zergling";"Larva";234;1
"Unit";"Zergling";"Larva";234;1
"Unit";"Zergling";"Larva";234;1
"Unit";"Zergling";"Larva";234;1
"Unit";"Zergling";"Larva";234;1
"Unit";"Zergling";"Larva";234;1
"Unit";"Zergling";"Larva";234;1
"Upgrade";"ZergGroundArmorsLevel2";"EvolutionChamber";161;0
"Unit";"Zergling";"Larva";240;1
"Unit";"Zergling";"Larva";240;1
"Unit";"Zergling";"Larva";240;1
"Unit";"Zergling";"Larva";240;1
"Unit";"Zergling";"Larva";240;1
"Unit";"Zergling";"Larva";240;1
"Unit";"Zergling";"Larva";242;1
"Unit";"Zergling";"Larva";242;1
"Unit";"Zergling";"Larva";242;1
"Unit";"Zergling";"Larva";242;1
"Unit";"Zergling";"Larva";244;1
"Unit";"Zergling";"Larva";244;1
"Unit";"Zergling";"Larva";244;1
"Unit";"Zergling";"Larva";244;1
"Unit";"Zergling";"Larva";254;1
"Unit";"Zergling";"Larva";254;1
"Unit";"Zergling";"Larva";254;1
"Unit";"Zergling";"Larva";254;1
"Unit";"Zergling";"Larva";254;1
"Unit";"Zergling";"Larva";254;1
"Unit";"Zergling";"Larva";254;1
"Unit";"Zergling";"Larva";254;1
"Unit";"Zergling";"Larva";254;1
"Unit";"Zergling";"Larva";254;1
"Unit";"Zergling";"Larva";254;1
"Unit";"Zergling";"Larva";254;1
"Unit";"Zergling";"Larva";256;1
"Unit";"Zergling";"Larva";256;1
"Unit";"Zergling";"Larva";256;1
"Unit";"Zergling";"Larva";256;1
"Unit";"Zergling";"Larva";256;1
"Unit";"Zergling";"Larva";256;1
"Unit";"Zergling";"Larva";266;1
"Unit";"Zergling";"Larva";266;1
"Unit";"Zergling";"Larva";266;1
"Unit";"Zergling";"Larva";266;1
"Unit";"Baneling";"Zergling";266;0
"Unit";"Baneling";"Zergling";266;0
"Unit";"Zergling";"Larva";266;1
"Unit";"Zergling";"Larva";266;1
"Unit";"Baneling";"Zergling";266;0
"Unit";"Baneling";"Zergling";266;0
"Unit";"Baneling";"Zergling";266;0
"Unit";"Baneling";"Zergling";266;0
"Unit";"Baneling";"Zergling";266;0
"Unit";"Baneling";"Zergling";266;0
"Unit";"Baneling";"Zergling";266;0
"Unit";"Baneling";"Zergling";266;0
"Unit";"Baneling";"Zergling";266;0
"Unit";"Baneling";"Zergling";266;0
"Unit";"Baneling";"Zergling";266;0
"Unit";"Baneling";"Zergling";266;0
"Unit";"Baneling";"Zergling";266;0
"Unit";"Baneling";"Zergling";266;0
"Unit";"Baneling";"Zergling";266;0
"Unit";"Baneling";"Zergling";266;0
"Unit";"Baneling";"Zergling";266;0
"Unit";"Baneling";"Zergling";266;0
"Unit";"Baneling";"Zergling";266;0
"Unit";"Baneling";"Zergling";266;0
"Unit";"Zergling";"Larva";266;1
"Unit";"Zergling";"Larva";266;1
"Unit";"Zergling";"Larva";284;1
"Unit";"Zergling";"Larva";284;1
"Unit";"Zergling";"Larva";284;1
"Unit";"Zergling";"Larva";284;1
"Unit";"Zergling";"Larva";284;1
"Unit";"Zergling";"Larva";284;1
"Unit";"Zergling";"Larva";292;1
"Unit";"Zergling";"Larva";292;1
"Unit";"Zergling";"Larva";292;1
"Unit";"Zergling";"Larva";292;1
"Unit";"Zergling";"Larva";292;1
"Unit";"Zergling";"Larva";292;1
"Unit";"Zergling";"Larva";292;1
"Unit";"Zergling";"Larva";292;1
"Unit";"Zergling";"Larva";292;1
"Unit";"Zergling";"Larva";292;1
"Unit";"Zergling";"Larva";292;1
"Unit";"Zergling";"Larva";292;1
"Unit";"Zergling";"Larva";292;1
"Unit";"Zergling";"Larva";292;1
"Unit";"Zergling";"Larva";298;1
"Unit";"Zergling";"Larva";298;1
"Unit";"Zergling";"Larva";298;1
"Unit";"Zergling";"Larva";298;1
"Unit";"Zergling";"Larva";298;1
"Unit";"Zergling";"Larva";298;1
"Unit";"Zergling";"Larva";298;1
"Unit";"Zergling";"Larva";298;1
"Unit";"Mutalisk";"Larva";312;2
"Unit";"Mutalisk";"Larva";312;2
"Unit";"Mutalisk";"Larva";312;2
"Unit";"Zergling";"Larva";321;1
"Unit";"Zergling";"Larva";321;1
"Unit";"Zergling";"Larva";321;1
"Unit";"Zergling";"Larva";321;1
"Unit";"Mutalisk";"Larva";316;2
"Unit";"Zergling";"Larva";321;1
"Unit";"Zergling";"Larva";321;1
"Unit";"Mutalisk";"Larva";317;2
"Unit";"Zergling";"Larva";321;1
"Unit";"Zergling";"Larva";321;1
"Unit";"Zergling";"Larva";321;1
"Unit";"Zergling";"Larva";321;1
"Unit";"Zergling";"Larva";321;1
"Unit";"Zergling";"Larva";321;1
"Building";"CreepTumor";NA;337;0
"Unit";"Zergling";"Larva";337;1
"Unit";"Zergling";"Larva";337;1
"Unit";"Zergling";"Larva";337;1
"Unit";"Zergling";"Larva";337;1
"Unit";"Zergling";"Larva";337;1
"Unit";"Zergling";"Larva";337;1
"Unit";"Corruptor";"Larva";327;2
"Unit";"Corruptor";"Larva";333;2
"Unit";"Zergling";"Larva";343;1
"Unit";"Zergling";"Larva";343;1
"Unit";"Zergling";"Larva";343;1
"Unit";"Zergling";"Larva";343;1
"Unit";"Baneling";"Zergling";347;0
"Unit";"Baneling";"Zergling";347;0
"Unit";"Baneling";"Zergling";347;0
"Unit";"Baneling";"Zergling";347;0
"Unit";"Baneling";"Zergling";347;0
"Unit";"Baneling";"Zergling";347;0
"Unit";"Baneling";"Zergling";347;0
"Unit";"Baneling";"Zergling";347;0
"Unit";"Baneling";"Zergling";347;0
"Unit";"Baneling";"Zergling";347;0
"Unit";"Baneling";"Zergling";347;0
"Unit";"Baneling";"Zergling";347;0
"Unit";"Zergling";"Larva";343;1
"Unit";"Zergling";"Larva";343;1
"Unit";"Zergling";"Larva";343;1
"Unit";"Zergling";"Larva";343;1
"Unit";"Zergling";"Larva";343;1
"Unit";"Zergling";"Larva";343;1
"Unit";"Zergling";"Larva";343;1
"Unit";"Zergling";"Larva";343;1
"Unit";"Zergling";"Larva";343;1
"Unit";"Zergling";"Larva";343;1
"Unit";"Zergling";"Larva";343;1
"Unit";"Zergling";"Larva";343;1
"Unit";"Zergling";"Larva";343;1
"Unit";"Zergling";"Larva";343;1
"Unit";"Zergling";"Larva";343;1
"Unit";"Zergling";"Larva";343;1
"Unit";"Zergling";"Larva";347;1
"Unit";"Zergling";"Larva";347;1
"Unit";"Zergling";"Larva";347;1
"Unit";"Zergling";"Larva";347;1
"Unit";"Baneling";"Zergling";373;0
"Unit";"Baneling";"Zergling";373;0
"Unit";"Zergling";"Larva";375;1
"Unit";"Zergling";"Larva";375;1
"Unit";"Zergling";"Larva";379;1
"Unit";"Zergling";"Larva";379;1
"Unit";"Queen";"Hatchery";351;2
"Unit";"Zergling";"Larva";381;1
"Unit";"Zergling";"Larva";381;1
"Unit";"Zergling";"Larva";381;1
"Unit";"Zergling";"Larva";381;1
"Unit";"Zergling";"Larva";381;1
"Unit";"Zergling";"Larva";381;1
"Unit";"Zergling";"Larva";381;1
"Unit";"Zergling";"Larva";381;1
"Unit";"Zergling";"Larva";381;1
"Unit";"Zergling";"Larva";381;1
"Unit";"Zergling";"Larva";381;1
"Unit";"Zergling";"Larva";381;1
"Unit";"Zergling";"Larva";381;1
"Unit";"Zergling";"Larva";381;1
"Unit";"Zergling";"Larva";381;1
"Unit";"Zergling";"Larva";381;1
"Unit";"Zergling";"Larva";381;1
"Unit";"Zergling";"Larva";381;1
"Unit";"Zergling";"Larva";381;1
"Unit";"Zergling";"Larva";381;1
"Unit";"Zergling";"Larva";387;1
"Unit";"Zergling";"Larva";387;1
"Unit";"Zergling";"Larva";387;1
"Unit";"Zergling";"Larva";387;1
"Unit";"Zergling";"Larva";387;1
"Unit";"Zergling";"Larva";387;1
"Unit";"Zergling";"Larva";387;1
"Unit";"Zergling";"Larva";387;1
"Unit";"Baneling";"Zergling";399;0
"Unit";"Baneling";"Zergling";401;0
"Unit";"Baneling";"Zergling";401;0
"Unit";"Baneling";"Zergling";401;0
"Unit";"Baneling";"Zergling";401;0
"Unit";"Baneling";"Zergling";401;0
"Unit";"Baneling";"Zergling";401;0
"Unit";"Baneling";"Zergling";401;0
"Unit";"Baneling";"Zergling";401;0
"Unit";"Baneling";"Zergling";401;0
"Unit";"Baneling";"Zergling";401;0
"Unit";"Baneling";"Zergling";401;0
"Unit";"Baneling";"Zergling";401;0
"Unit";"Baneling";"Zergling";401;0
"Unit";"Baneling";"Zergling";401;0
"Unit";"Baneling";"Zergling";403;0
"Unit";"Zergling";"Larva";397;1
"Unit";"Zergling";"Larva";397;1
"Building";"CreepTumor";NA;415;0
"Unit";"Zergling";"Larva";407;1
"Unit";"Zergling";"Larva";407;1
"Unit";"Zergling";"Larva";407;1
"Unit";"Zergling";"Larva";407;1
"Unit";"Zergling";"Larva";407;1
"Unit";"Zergling";"Larva";407;1
"Unit";"Zergling";"Larva";407;1
"Unit";"Zergling";"Larva";407;1
"Unit";"Baneling";"Zergling";415;0
"Unit";"Zergling";"Larva";415;1
"Unit";"Zergling";"Larva";415;1
"Unit";"Baneling";"Zergling";415;0
"Unit";"Baneling";"Zergling";415;0
"Unit";"Baneling";"Zergling";415;0
"Unit";"Baneling";"Zergling";415;0
"Unit";"Baneling";"Zergling";415;0
"Unit";"Baneling";"Zergling";415;0
"Unit";"Baneling";"Zergling";415;0
"Unit";"Baneling";"Zergling";415;0
"Unit";"Zergling";"Larva";415;1
"Unit";"Zergling";"Larva";415;1
"Unit";"Baneling";"Zergling";415;0
"Unit";"Baneling";"Zergling";415;0
"Unit";"Baneling";"Zergling";415;0
"Unit";"Baneling";"Zergling";415;0
"Unit";"Baneling";"Zergling";415;0
"Unit";"Zergling";"Larva";415;1
"Unit";"Zergling";"Larva";415;1
"Unit";"Zergling";"Larva";415;1
"Unit";"Zergling";"Larva";415;1
"Unit";"Zergling";"Larva";415;1
"Unit";"Zergling";"Larva";415;1
"Unit";"Zergling";"Larva";415;1
"Unit";"Zergling";"Larva";415;1
"Unit";"Zergling";"Larva";415;1
"Unit";"Zergling";"Larva";415;1
"Unit";"Zergling";"Larva";415;1
"Unit";"Zergling";"Larva";415;1
"Unit";"Zergling";"Larva";417;1
"Unit";"Zergling";"Larva";417;1
"Unit";"Zergling";"Larva";417;1
"Unit";"Zergling";"Larva";417;1
"Unit";"Zergling";"Larva";423;1
"Unit";"Zergling";"Larva";423;1
"Unit";"Zergling";"Larva";425;1
"Unit";"Zergling";"Larva";425;1
"Building";"Hatchery";NA;379;0
"Unit";"Zergling";"Larva";445;1
"Unit";"Zergling";"Larva";445;1
"Unit";"Zergling";"Larva";445;1
"Unit";"Zergling";"Larva";445;1
"Unit";"Zergling";"Larva";445;1
"Unit";"Zergling";"Larva";445;1
"Unit";"Zergling";"Larva";445;1
"Unit";"Zergling";"Larva";445;1
"Unit";"Zergling";"Larva";445;1
"Unit";"Zergling";"Larva";445;1
"Unit";"Zergling";"Larva";445;1
"Unit";"Zergling";"Larva";445;1
"Unit";"Zergling";"Larva";445;1
"Unit";"Zergling";"Larva";445;1
"Unit";"Zergling";"Larva";445;1
"Unit";"Zergling";"Larva";445;1
"Unit";"Zergling";"Larva";449;1
"Unit";"Zergling";"Larva";449;1
"Unit";"Zergling";"Larva";449;1
"Unit";"Zergling";"Larva";449;1
"Unit";"Zergling";"Larva";449;1
"Unit";"Zergling";"Larva";449;1
"Unit";"Zergling";"Larva";449;1
"Unit";"Zergling";"Larva";449;1
"Unit";"Zergling";"Larva";449;1
"Unit";"Zergling";"Larva";449;1
"Unit";"Zergling";"Larva";449;1
"Unit";"Zergling";"Larva";449;1
"Unit";"Zergling";"Larva";449;1
"Unit";"Zergling";"Larva";449;1
"Unit";"Baneling";"Zergling";449;0
"Unit";"Baneling";"Zergling";449;0
"Unit";"Zergling";"Larva";449;1
"Unit";"Zergling";"Larva";449;1
"Unit";"Zergling";"Larva";451;1
"Unit";"Zergling";"Larva";451;1
"Building";"CreepTumor";NA;465;0
"Unit";"Baneling";"Zergling";465;0
"Unit";"Baneling";"Zergling";465;0
"Unit";"Baneling";"Zergling";465;0
"Unit";"Baneling";"Zergling";465;0
"Unit";"Baneling";"Zergling";465;0
"Unit";"Baneling";"Zergling";465;0
"Unit";"Baneling";"Zergling";465;0
"Unit";"Baneling";"Zergling";465;0
"Unit";"Baneling";"Zergling";465;0
"Unit";"Baneling";"Zergling";465;0
"Unit";"Zergling";"Larva";465;1
"Unit";"Zergling";"Larva";465;1
"Unit";"Zergling";"Larva";465;1
"Unit";"Zergling";"Larva";465;1
"Unit";"Zergling";"Larva";467;1
"Unit";"Zergling";"Larva";467;1
"Unit";"Baneling";"Zergling";473;0
"Unit";"Baneling";"Zergling";473;0
"Unit";"Baneling";"Zergling";473;0
"Unit";"Baneling";"Zergling";473;0
"Unit";"Baneling";"Zergling";473;0
"Unit";"Baneling";"Zergling";473;0
"Unit";"Corruptor";"Larva";449;2
"Unit";"Baneling";"Zergling";473;0
"Unit";"Baneling";"Zergling";473;0
"Unit";"Corruptor";"Larva";449;2
"Unit";"Corruptor";"Larva";449;2
"Unit";"Zergling";"Larva";479;1
"Unit";"Zergling";"Larva";479;1
"Unit";"Zergling";"Larva";481;1
"Unit";"Zergling";"Larva";481;1
"Unit";"Zergling";"Larva";483;1
"Unit";"Zergling";"Larva";483;1
"Unit";"Zergling";"Larva";483;1
"Unit";"Zergling";"Larva";483;1
"Building";"InfestationPit";NA;465;0
"Unit";"Zergling";"Larva";496;1
"Unit";"Zergling";"Larva";496;1
"Unit";"Zergling";"Larva";496;1
"Unit";"Zergling";"Larva";496;1
"Unit";"Zergling";"Larva";496;1
"Unit";"Zergling";"Larva";496;1
"Unit";"Baneling";"Zergling";502;0
"Upgrade";"ZergMeleeWeaponsLevel2";"EvolutionChamber";407;0
"Unit";"Zergling";"Larva";502;1
"Unit";"Zergling";"Larva";502;1
"Unit";"Zergling";"Larva";502;1
"Unit";"Zergling";"Larva";502;1
"Unit";"Baneling";"Zergling";502;0
"Unit";"Baneling";"Zergling";502;0
"Unit";"Baneling";"Zergling";502;0
"Unit";"Baneling";"Zergling";502;0
"Unit";"Baneling";"Zergling";502;0
"Unit";"Baneling";"Zergling";502;0
"Unit";"Baneling";"Zergling";502;0
"Unit";"Baneling";"Zergling";502;0
"Unit";"Baneling";"Zergling";502;0
"Unit";"Zergling";"Larva";504;1
"Unit";"Zergling";"Larva";504;1
"Unit";"Queen";"Hatchery";479;2
"Unit";"Zergling";"Larva";510;1
"Unit";"Zergling";"Larva";510;1
"Unit";"Zergling";"Larva";510;1
"Unit";"Zergling";"Larva";510;1
"Unit";"Zergling";"Larva";510;1
"Unit";"Zergling";"Larva";510;1
"Unit";"Zergling";"Larva";510;1
"Unit";"Zergling";"Larva";510;1
"Unit";"Zergling";"Larva";510;1
"Unit";"Zergling";"Larva";510;1
"Building";"CreepTumor";NA;548;0
"Unit";"Zergling";"Larva";548;1
"Unit";"Zergling";"Larva";548;1
"Unit";"Baneling";"Zergling";548;0
"Unit";"Zergling";"Larva";548;1
"Unit";"Zergling";"Larva";548;1
"Unit";"Zergling";"Larva";548;1
"Unit";"Zergling";"Larva";548;1
"Unit";"Zergling";"Larva";548;1
"Unit";"Zergling";"Larva";548;1
"Unit";"Baneling";"Zergling";548;0
"Unit";"Baneling";"Zergling";548;0
"Unit";"Baneling";"Zergling";548;0
"Unit";"Baneling";"Zergling";548;0
"Unit";"Baneling";"Zergling";548;0
"Unit";"Baneling";"Zergling";548;0
"Unit";"Zergling";"Larva";548;1
"Unit";"Zergling";"Larva";548;1
"Unit";"Zergling";"Larva";548;1
"Unit";"Zergling";"Larva";548;1
"Unit";"Zergling";"Larva";548;1
"Unit";"Zergling";"Larva";548;1
"Unit";"Zergling";"Larva";548;1
"Unit";"Zergling";"Larva";548;1
"Unit";"Zergling";"Larva";548;1
"Unit";"Zergling";"Larva";548;1
"Unit";"Zergling";"Larva";548;1
"Unit";"Zergling";"Larva";548;1
"Unit";"Zergling";"Larva";548;1
"Unit";"Zergling";"Larva";548;1
"Unit";"Zergling";"Larva";548;1
"Unit";"Zergling";"Larva";548;1
"Unit";"Zergling";"Larva";548;1
"Unit";"Zergling";"Larva";548;1
"Unit";"Zergling";"Larva";548;1
"Unit";"Zergling";"Larva";548;1
"Unit";"Zergling";"Larva";560;1
"Unit";"Zergling";"Larva";560;1
"Unit";"Zergling";"Larva";560;1
"Unit";"Zergling";"Larva";560;1
"Unit";"Zergling";"Larva";560;1
"Unit";"Zergling";"Larva";560;1
"Unit";"Zergling";"Larva";560;1
"Unit";"Zergling";"Larva";560;1
"Unit";"Zergling";"Larva";560;1
"Unit";"Zergling";"Larva";560;1
"Unit";"Zergling";"Larva";560;1
"Unit";"Zergling";"Larva";560;1
"Unit";"Zergling";"Larva";560;1
"Unit";"Zergling";"Larva";560;1
"Unit";"Zergling";"Larva";560;1
"Unit";"Zergling";"Larva";560;1
"Unit";"Zergling";"Larva";560;1
"Unit";"Zergling";"Larva";560;1
"Unit";"Zergling";"Larva";560;1
"Unit";"Zergling";"Larva";560;1
"Unit";"Baneling";"Zergling";564;0
"Unit";"Baneling";"Zergling";564;0
"Unit";"Baneling";"Zergling";564;0
"Unit";"Baneling";"Zergling";564;0
"Unit";"Baneling";"Zergling";564;0
"Unit";"Baneling";"Zergling";564;0
"Unit";"Baneling";"Zergling";564;0
"Unit";"Baneling";"Zergling";564;0
"Unit";"Baneling";"Zergling";564;0
"Unit";"Baneling";"Zergling";564;0
"Unit";"Baneling";"Zergling";564;0
"Unit";"Baneling";"Zergling";564;0
"Unit";"Baneling";"Zergling";566;0
"Unit";"Baneling";"Zergling";570;0
"Unit";"Zergling";"Larva";576;1
"Unit";"Zergling";"Larva";576;1
"Unit";"Zergling";"Larva";576;1
"Unit";"Zergling";"Larva";576;1
"Unit";"Zergling";"Larva";576;1
"Unit";"Zergling";"Larva";576;1
"Unit";"Zergling";"Larva";576;1
"Unit";"Zergling";"Larva";576;1
"Unit";"Zergling";"Larva";576;1
"Unit";"Zergling";"Larva";576;1
"Unit";"Zergling";"Larva";576;1
"Unit";"Zergling";"Larva";576;1
"Unit";"Zergling";"Larva";576;1
"Unit";"Zergling";"Larva";576;1
"Unit";"Zergling";"Larva";576;1
"Unit";"Zergling";"Larva";576;1
"Unit";"Baneling";"Zergling";602;0
"Unit";"Baneling";"Zergling";604;0
"Unit";"Baneling";"Zergling";604;0
"Unit";"Baneling";"Zergling";604;0
"Unit";"Zergling";"Larva";596;1
"Unit";"Zergling";"Larva";596;1
"Unit";"Baneling";"Zergling";604;0
"Unit";"Zergling";"Larva";596;1
"Unit";"Zergling";"Larva";596;1
"Unit";"Zergling";"Larva";596;1
"Unit";"Zergling";"Larva";596;1
"Unit";"Zergling";"Larva";596;1
"Unit";"Zergling";"Larva";596;1
"Unit";"Zergling";"Larva";596;1
"Unit";"Zergling";"Larva";596;1
"Unit";"Zergling";"Larva";596;1
"Unit";"Zergling";"Larva";596;1
"Unit";"Zergling";"Larva";596;1
"Unit";"Zergling";"Larva";596;1
"Unit";"Zergling";"Larva";596;1
"Unit";"Zergling";"Larva";596;1
"Unit";"Zergling";"Larva";596;1
"Unit";"Zergling";"Larva";596;1
"Unit";"Baneling";"Zergling";604;0
"Unit";"Zergling";"Larva";596;1
"Unit";"Zergling";"Larva";596;1
"Unit";"Zergling";"Larva";596;1
"Unit";"Zergling";"Larva";596;1
"Unit";"Zergling";"Larva";596;1
"Unit";"Zergling";"Larva";596;1
"Unit";"Baneling";"Zergling";604;0
"Unit";"Baneling";"Zergling";604;0
"Unit";"Baneling";"Zergling";610;0
"Unit";"Baneling";"Zergling";612;0
"Unit";"Baneling";"Zergling";612;0
"Unit";"Baneling";"Zergling";612;0
"Unit";"Baneling";"Zergling";612;0
"Unit";"Baneling";"Zergling";612;0
"Unit";"Baneling";"Zergling";612;0
"Unit";"Baneling";"Zergling";612;0
"Unit";"Baneling";"Zergling";612;0
"Unit";"Baneling";"Zergling";612;0
"Unit";"Baneling";"Zergling";612;0
"Unit";"Zergling";"Larva";612;1
"Unit";"Zergling";"Larva";612;1
"Unit";"Zergling";"Larva";612;1
"Unit";"Zergling";"Larva";612;1
"Building";"Hatchery";NA;548;0
"Unit";"Zergling";"Larva";636;1
"Unit";"Zergling";"Larva";636;1
"Unit";"Zergling";"Larva";636;1
"Unit";"Zergling";"Larva";636;1
"Unit";"Zergling";"Larva";636;1
"Unit";"Zergling";"Larva";636;1
"Unit";"Zergling";"Larva";636;1
"Unit";"Zergling";"Larva";636;1
"Unit";"Zergling";"Larva";636;1
"Unit";"Zergling";"Larva";636;1
"Unit";"Baneling";"Zergling";640;0
"Building";"UltraliskCavern";NA;612;0
"Unit";"Overlord";"Larva";658;0
"Unit";"Overlord";"Larva";658;0
"Unit";"Overlord";"Larva";658;0
"Building";"CreepTumor";NA;658;0
"Unit";"Overlord";"Larva";658;0
"Unit";"Zergling";"Larva";658;1
"Unit";"Zergling";"Larva";658;1
"Unit";"Zergling";"Larva";658;1
"Unit";"Zergling";"Larva";658;1
"Unit";"Zergling";"Larva";658;1
"Unit";"Zergling";"Larva";658;1
"Unit";"Zergling";"Larva";658;1
"Unit";"Zergling";"Larva";658;1
"Unit";"Zergling";"Larva";658;1
"Unit";"Zergling";"Larva";658;1
"Unit";"Zergling";"Larva";658;1
"Unit";"Zergling";"Larva";658;1
"Unit";"Zergling";"Larva";658;1
"Unit";"Zergling";"Larva";658;1
"Unit";"Zergling";"Larva";658;1
"Unit";"Zergling";"Larva";658;1
"Unit";"Zergling";"Larva";658;1
"Unit";"Zergling";"Larva";658;1
"Unit";"Zergling";"Larva";658;1
"Unit";"Zergling";"Larva";658;1
"Building";"Extractor";NA;658;0
"Building";"Extractor";NA;658;0
"Unit";"Zergling";"Larva";658;1
"Unit";"Zergling";"Larva";658;1
"Unit";"Zergling";"Larva";658;1
"Unit";"Zergling";"Larva";658;1
"Unit";"Zergling";"Larva";658;1
"Unit";"Zergling";"Larva";658;1
"Unit";"Zergling";"Larva";658;1
"Unit";"Zergling";"Larva";658;1
"Unit";"Zergling";"Larva";658;1
"Unit";"Zergling";"Larva";658;1
"Unit";"Zergling";"Larva";658;1
"Unit";"Zergling";"Larva";658;1
"Unit";"Zergling";"Larva";658;1
"Unit";"Zergling";"Larva";658;1
"Unit";"Zergling";"Larva";658;1
"Unit";"Zergling";"Larva";658;1
"Unit";"Zergling";"Larva";658;1
"Unit";"Zergling";"Larva";658;1
"Unit";"Zergling";"Larva";658;1
"Unit";"Zergling";"Larva";658;1
"Building";"CreepTumor";NA;678;0
"Unit";"Ultralisk";"Larva";658;6
"Unit";"Ultralisk";"Larva";658;6
"Unit";"Ultralisk";"Larva";658;6
"Building";"Extractor";NA;678;0
"Unit";"Overlord";"Larva";701;0
"Unit";"Overlord";"Larva";701;0
"Building";"CreepTumorQueen";NA;719;0
"Unit";"Baneling";"Zergling";719;0
"Unit";"Baneling";"Zergling";719;0
"Unit";"Baneling";"Zergling";719;0
"Unit";"Baneling";"Zergling";719;0
"Unit";"Baneling";"Zergling";719;0
"Unit";"Baneling";"Zergling";719;0
"Unit";"Baneling";"Zergling";719;0
"Unit";"Baneling";"Zergling";719;0
"Unit";"Baneling";"Zergling";719;0
"Unit";"Baneling";"Zergling";719;0
"Unit";"Baneling";"Zergling";719;0
"Unit";"Baneling";"Zergling";719;0
"Unit";"Baneling";"Zergling";719;0
"Unit";"Baneling";"Zergling";719;0
"Unit";"Baneling";"Zergling";719;0
"Unit";"Baneling";"Zergling";719;0
"Unit";"Baneling";"Zergling";719;0
"Unit";"Baneling";"Zergling";719;0
"Unit";"Baneling";"Zergling";719;0
"Unit";"Baneling";"Zergling";719;0
"Unit";"Baneling";"Zergling";719;0
"Unit";"Zergling";"Larva";719;1
"Unit";"Zergling";"Larva";719;1
"Unit";"Zergling";"Larva";719;1
"Unit";"Zergling";"Larva";719;1
"Unit";"Zergling";"Larva";719;1
"Unit";"Zergling";"Larva";719;1
"Building";"CreepTumorQueen";NA;719;0
"Unit";"Baneling";"Zergling";719;0
"Unit";"Baneling";"Zergling";719;0
"Unit";"Baneling";"Zergling";719;0
"Unit";"Baneling";"Zergling";719;0
"Unit";"Baneling";"Zergling";719;0
"Unit";"Baneling";"Zergling";719;0
"Building";"Extractor";NA;719;0
"Upgrade";"ChitinousPlating";"UltraliskCavern";701;0
"Unit";"Ultralisk";"Larva";719;6
"Unit";"Baneling";"Zergling";725;0
"Unit";"Baneling";"Zergling";725;0
"Unit";"Baneling";"Zergling";725;0
"Unit";"Baneling";"Zergling";725;0
"Unit";"Baneling";"Zergling";725;0
"Unit";"Baneling";"Zergling";725;0
"Unit";"Baneling";"Zergling";725;0
"Unit";"Baneling";"Zergling";725;0
"Unit";"Baneling";"Zergling";725;0
"Unit";"Baneling";"Zergling";725;0
"Unit";"Baneling";"Zergling";725;0
"Unit";"Baneling";"Zergling";725;0
"Unit";"Baneling";"Zergling";725;0
"Unit";"Baneling";"Zergling";725;0
"Unit";"Ultralisk";"Larva";719;6
"Unit";"Baneling";"Zergling";725;0
"Unit";"Baneling";"Zergling";725;0
"Unit";"Baneling";"Zergling";725;0
"Building";"Hatchery";NA;678;0
"Unit";"Baneling";"Zergling";731;0
"Unit";"Zergling";"Larva";725;1
"Unit";"Zergling";"Larva";725;1
"Unit";"Baneling";"Zergling";731;0
"Unit";"Baneling";"Zergling";731;0
"Unit";"Zergling";"Larva";725;1
"Unit";"Zergling";"Larva";725;1
"Unit";"Zergling";"Larva";725;1
"Unit";"Zergling";"Larva";725;1
"Unit";"Zergling";"Larva";725;1
"Unit";"Zergling";"Larva";725;1
"Unit";"Zergling";"Larva";725;1
"Unit";"Zergling";"Larva";725;1
"Unit";"Zergling";"Larva";725;1
"Unit";"Zergling";"Larva";725;1
"Unit";"Zergling";"Larva";725;1
"Unit";"Zergling";"Larva";725;1
"Unit";"Zergling";"Larva";725;1
"Unit";"Zergling";"Larva";725;1
"Unit";"Zergling";"Larva";725;1
"Unit";"Zergling";"Larva";725;1
"Unit";"Zergling";"Larva";725;1
"Unit";"Zergling";"Larva";725;1
"Unit";"Zergling";"Larva";725;1
"Unit";"Zergling";"Larva";725;1
"Unit";"Zergling";"Larva";725;1
"Unit";"Zergling";"Larva";725;1
"Unit";"Zergling";"Larva";725;1
"Unit";"Zergling";"Larva";725;1
"Unit";"Baneling";"Zergling";737;0
"Unit";"Baneling";"Zergling";739;0
"Unit";"Baneling";"Zergling";739;0
"Unit";"Baneling";"Zergling";739;0
"Unit";"Baneling";"Zergling";739;0
"Unit";"Baneling";"Zergling";739;0
"Unit";"Baneling";"Zergling";739;0
"Unit";"Baneling";"Zergling";741;0
"Unit";"Baneling";"Zergling";745;0
"Unit";"Baneling";"Zergling";749;0
"Unit";"Baneling";"Zergling";757;0
"Unit";"Baneling";"Zergling";757;0
"Unit";"Baneling";"Zergling";757;0
"Unit";"Baneling";"Zergling";761;0
"Unit";"Baneling";"Zergling";761;0
"Unit";"Baneling";"Zergling";763;0
"Unit";"Baneling";"Zergling";763;0
"Upgrade";"ZergMeleeWeaponsLevel3";"EvolutionChamber";678;0
"Upgrade";"ZergGroundArmorsLevel3";"EvolutionChamber";678;0
"Unit";"Zergling";"Larva";763;1
"Unit";"Zergling";"Larva";763;1
"Unit";"Zergling";"Larva";763;1
"Unit";"Zergling";"Larva";763;1
"Unit";"Zergling";"Larva";763;1
"Unit";"Zergling";"Larva";763;1
"Unit";"Zergling";"Larva";765;1
"Unit";"Zergling";"Larva";765;1
"Unit";"Zergling";"Larva";765;1
"Unit";"Zergling";"Larva";765;1
"Unit";"Zergling";"Larva";765;1
"Unit";"Zergling";"Larva";765;1
"Unit";"Zergling";"Larva";765;1
"Unit";"Zergling";"Larva";765;1
"Unit";"Zergling";"Larva";765;1
"Unit";"Zergling";"Larva";765;1
"Unit";"Zergling";"Larva";765;1
"Unit";"Zergling";"Larva";765;1
"Unit";"Zergling";"Larva";765;1
"Unit";"Zergling";"Larva";765;1
"Unit";"Zergling";"Larva";765;1
"Unit";"Zergling";"Larva";765;1
"Unit";"Zergling";"Larva";765;1
"Unit";"Zergling";"Larva";765;1
"Unit";"Zergling";"Larva";765;1
"Unit";"Zergling";"Larva";765;1
"Unit";"Zergling";"Larva";765;1
"Unit";"Zergling";"Larva";765;1
"Unit";"Zergling";"Larva";765;1
"Unit";"Zergling";"Larva";765;1
"Unit";"Zergling";"Larva";765;1
"Unit";"Zergling";"Larva";765;1
"Unit";"Zergling";"Larva";765;1
"Unit";"Zergling";"Larva";765;1
"Unit";"Zergling";"Larva";765;1
"Unit";"Zergling";"Larva";765;1
"Unit";"Zergling";"Larva";765;1
"Unit";"Zergling";"Larva";765;1
"Unit";"Zergling";"Larva";765;1
"Unit";"Zergling";"Larva";765;1
"Unit";"Zergling";"Larva";765;1
"Unit";"Zergling";"Larva";765;1
"Unit";"Zergling";"Larva";765;1
"Unit";"Zergling";"Larva";765;1
"Unit";"Zergling";"Larva";765;1
"Unit";"Zergling";"Larva";765;1
"Unit";"Zergling";"Larva";767;1
"Unit";"Zergling";"Larva";767;1
"Unit";"Zergling";"Larva";767;1
"Unit";"Zergling";"Larva";767;1
"Unit";"Corruptor";"Larva";765;2
"Unit";"Corruptor";"Larva";765;2
"Unit";"Corruptor";"Larva";765;2
"Unit";"Corruptor";"Larva";765;2
"Unit";"Corruptor";"Larva";765;2
"Unit";"Corruptor";"Larva";765;2
"Unit";"Corruptor";"Larva";765;2
"Unit";"Zergling";"Larva";809;1
"Unit";"Zergling";"Larva";809;1
"Unit";"Zergling";"Larva";809;1
"Unit";"Zergling";"Larva";809;1
"Unit";"Corruptor";"Larva";767;2
"Unit";"Corruptor";"Larva";767;2
"Unit";"Zergling";"Larva";809;1
"Unit";"Zergling";"Larva";809;1
"Unit";"Zergling";"Larva";811;1
"Unit";"Zergling";"Larva";811;1
"Unit";"Zergling";"Larva";813;1
"Unit";"Zergling";"Larva";813;1
"Unit";"Corruptor";"Larva";771;2
"Unit";"Corruptor";"Larva";771;2
"Unit";"Corruptor";"Larva";771;2
"Unit";"Corruptor";"Larva";771;2
"Unit";"Zergling";"Larva";813;1
"Unit";"Zergling";"Larva";813;1
"Unit";"Zergling";"Larva";813;1
"Unit";"Zergling";"Larva";813;1
"Unit";"Zergling";"Larva";813;1
"Unit";"Zergling";"Larva";813;1
"Unit";"Zergling";"Larva";827;1
"Unit";"Zergling";"Larva";827;1
"Unit";"Zergling";"Larva";827;1
"Unit";"Zergling";"Larva";827;1
"Unit";"Zergling";"Larva";827;1
"Unit";"Zergling";"Larva";827;1
"Unit";"Zergling";"Larva";835;1
"Unit";"Zergling";"Larva";835;1
"Unit";"Baneling";"Zergling";841;0
"Unit";"Baneling";"Zergling";845;0
"Unit";"Baneling";"Zergling";845;0
"Unit";"Baneling";"Zergling";845;0
"Unit";"Baneling";"Zergling";845;0
"Unit";"Baneling";"Zergling";847;0
"Unit";"Baneling";"Zergling";847;0
"Unit";"Baneling";"Zergling";847;0
"Unit";"Baneling";"Zergling";847;0
"Unit";"Baneling";"Zergling";849;0
"Unit";"Corruptor";"Larva";827;2
"Unit";"Corruptor";"Larva";827;2
"Unit";"Corruptor";"Larva";827;2
"Unit";"Corruptor";"Larva";827;2
