"type";"unit_name";"on_building";"total_supply";"supply"
"Unit";"Overlord";"Larva";13;0
"Building";"Extractor";NA;18;0
"Unit";"Overlord";"Larva";21;0
"Building";"SpawningPool";NA;19;0
"Building";"Hatchery";NA;17;0
"Unit";"Zergling";"Larva";22;1
"Unit";"Zergling";"Larva";22;1
"Unit";"Zergling";"Larva";22;1
"Unit";"Zergling";"Larva";22;1
"Unit";"Zergling";"Larva";22;1
"Unit";"Zergling";"Larva";22;1
"Unit";"Zergling";"Larva";22;1
"Unit";"Zergling";"Larva";22;1
"Unit";"Zergling";"Larva";22;1
"Unit";"Zergling";"Larva";22;1
"Unit";"Queen";"Hatchery";22;2
"Unit";"Queen";"Hatchery";22;2
"Building";"RoachWarren";NA;22;0
"Building";"CreepTumorQueen";NA;36;0
"Building";"SpineCrawler";NA;28;0
"Unit";"Overlord";"Larva";36;0
"Unit";"Roach";"Larva";36;2
"Unit";"Roach";"Larva";36;2
"Unit";"Roach";"Larva";36;2
"Unit";"Roach";"Larva";36;2
"Unit";"Roach";"Larva";36;2
"Unit";"Roach";"Larva";36;2
"Unit";"Roach";"Larva";36;2
"Unit";"Roach";"Larva";42;2
"Unit";"Overlord";"Larva";42;0
"Building";"CreepTumor";NA;50;0
"Building";"Extractor";NA;50;0
"Unit";"Overlord";"Larva";54;0
"Building";"Hatchery";NA;53;0
"Building";"CreepTumor";NA;57;0
"Building";"EvolutionChamber";NA;58;0
"Unit";"Queen";"Hatchery";59;2
"Building";"CreepTumor";NA;68;0
"Building";"CreepTumorQueen";NA;70;0
"Unit";"Overlord";"Larva";70;0
"Unit";"Overlord";"Larva";70;0
"Unit";"Overlord";"Larva";70;0
"Building";"CreepTumor";NA;70;0
"Building";"Spire";NA;60;0
"Building";"CreepTumor";NA;74;0
"Building";"CreepTumorQueen";NA;75;0
"Unit";"Overlord";"Larva";78;0
"Building";"CreepTumor";NA;81;0
"Building";"CreepTumor";NA;81;0
"Building";"Extractor";NA;78;0
"Building";"CreepTumor";NA;81;0
"Unit";"Mutalisk";"Larva";78;2
"Unit";"Mutalisk";"Larva";80;2
"Unit";"Mutalisk";"Larva";81;2
"Upgrade";"GlialReconstitution";"RoachWarren";70;0
"Building";"Extractor";NA;81;0
"Unit";"Mutalisk";"Larva";81;2
"Unit";"Overlord";"Larva";89;0
"Unit";"Zergling";"Larva";90;1
"Unit";"Zergling";"Larva";90;1
"Unit";"Zergling";"Larva";90;1
"Unit";"Zergling";"Larva";90;1
"Unit";"Zergling";"Larva";91;1
"Unit";"Zergling";"Larva";91;1
"Building";"CreepTumor";NA;93;0
"Unit";"Zergling";"Larva";93;1
"Unit";"Zergling";"Larva";93;1
"Unit";"Zergling";"Larva";93;1
"Unit";"Zergling";"Larva";93;1
"Building";"CreepTumor";NA;95;0
"Building";"CreepTumor";NA;95;0
"Unit";"Mutalisk";"Larva";102;2
"Unit";"Mutalisk";"Larva";102;2
"Building";"BanelingNest";NA;93;0
"Building";"CreepTumor";NA;107;0
"Building";"CreepTumor";NA;107;0
"Building";"CreepTumor";NA;107;0
"Building";"CreepTumorQueen";NA;111;0
"Unit";"Zergling";"Larva";111;1
"Unit";"Zergling";"Larva";111;1
"Unit";"Zergling";"Larva";111;1
"Unit";"Zergling";"Larva";111;1
"Unit";"Zergling";"Larva";111;1
"Unit";"Zergling";"Larva";111;1
"Unit";"Zergling";"Larva";111;1
"Unit";"Zergling";"Larva";111;1
"Unit";"Overlord";"Larva";111;0
"Unit";"Overlord";"Larva";111;0
"Unit";"Overlord";"Larva";111;0
"Unit";"Overlord";"Larva";111;0
"Building";"CreepTumor";NA;119;0
"Building";"CreepTumor";NA;119;0
"Building";"CreepTumor";NA;119;0
"Unit";"Zergling";"Larva";119;1
"Unit";"Zergling";"Larva";119;1
"Unit";"Zergling";"Larva";119;1
"Unit";"Zergling";"Larva";119;1
"Unit";"Zergling";"Larva";119;1
"Unit";"Zergling";"Larva";119;1
"Building";"CreepTumorQueen";NA;119;0
"Building";"Hatchery";NA;106;0
"Unit";"Zergling";"Larva";129;1
"Unit";"Zergling";"Larva";129;1
"Unit";"Zergling";"Larva";129;1
"Unit";"Zergling";"Larva";129;1
"Unit";"Zergling";"Larva";129;1
"Unit";"Zergling";"Larva";129;1
"Unit";"Zergling";"Larva";129;1
"Unit";"Zergling";"Larva";129;1
"Unit";"Zergling";"Larva";129;1
"Unit";"Zergling";"Larva";129;1
"Unit";"Mutalisk";"Larva";129;2
"Unit";"Mutalisk";"Larva";129;2
"Unit";"Mutalisk";"Larva";129;2
"Unit";"Mutalisk";"Larva";129;2
"Building";"CreepTumor";NA;129;0
"Building";"CreepTumor";NA;129;0
"Building";"CreepTumor";NA;129;0
"Building";"CreepTumor";NA;129;0
"Building";"CreepTumor";NA;129;0
"Unit";"Queen";"Hatchery";129;2
"Building";"EvolutionChamber";NA;154;0
"Unit";"Zergling";"Larva";156;1
"Unit";"Zergling";"Larva";156;1
"Upgrade";"ZergGroundArmorsLevel1";"EvolutionChamber";119;0
"Unit";"Zergling";"Larva";156;1
"Unit";"Zergling";"Larva";156;1
"Unit";"Zergling";"Larva";156;1
"Unit";"Zergling";"Larva";156;1
"Unit";"Zergling";"Larva";156;1
"Unit";"Zergling";"Larva";156;1
"Unit";"Zergling";"Larva";156;1
"Unit";"Zergling";"Larva";156;1
"Unit";"Zergling";"Larva";156;1
"Unit";"Zergling";"Larva";156;1
"Unit";"Zergling";"Larva";156;1
"Unit";"Zergling";"Larva";156;1
"Building";"Extractor";NA;156;0
"Building";"CreepTumor";NA;156;0
"Unit";"Baneling";"Zergling";156;0
"Unit";"Baneling";"Zergling";156;0
"Unit";"Baneling";"Zergling";156;0
"Unit";"Baneling";"Zergling";156;0
"Unit";"Baneling";"Zergling";156;0
"Unit";"Baneling";"Zergling";156;0
"Unit";"Baneling";"Zergling";156;0
"Unit";"Baneling";"Zergling";156;0
"Building";"CreepTumor";NA;156;0
"Unit";"Baneling";"Zergling";156;0
"Unit";"Baneling";"Zergling";156;0
"Building";"Extractor";NA;156;0
"Unit";"Baneling";"Zergling";156;0
"Unit";"Baneling";"Zergling";156;0
"Unit";"Baneling";"Zergling";156;0
"Unit";"Baneling";"Zergling";156;0
"Unit";"Overlord";"Larva";156;0
"Unit";"Overlord";"Larva";156;0
"Unit";"Overlord";"Larva";156;0
"Building";"CreepTumor";NA;175;0
"Unit";"Zergling";"Larva";175;1
"Unit";"Zergling";"Larva";175;1
"Unit";"Zergling";"Larva";175;1
"Unit";"Zergling";"Larva";175;1
"Unit";"Zergling";"Larva";175;1
"Unit";"Zergling";"Larva";175;1
"Unit";"Zergling";"Larva";175;1
"Unit";"Zergling";"Larva";175;1
"Unit";"Zergling";"Larva";175;1
"Unit";"Zergling";"Larva";175;1
"Unit";"Zergling";"Larva";175;1
"Unit";"Zergling";"Larva";175;1
"Unit";"Zergling";"Larva";175;1
"Unit";"Zergling";"Larva";175;1
"Unit";"Zergling";"Larva";175;1
"Unit";"Zergling";"Larva";175;1
"Unit";"Zergling";"Larva";175;1
"Unit";"Zergling";"Larva";175;1
"Unit";"Zergling";"Larva";175;1
"Unit";"Zergling";"Larva";175;1
"Unit";"Zergling";"Larva";175;1
"Unit";"Zergling";"Larva";175;1
"Unit";"Zergling";"Larva";175;1
"Unit";"Zergling";"Larva";175;1
"Unit";"Zergling";"Larva";175;1
"Unit";"Zergling";"Larva";175;1
"Unit";"Zergling";"Larva";175;1
"Unit";"Zergling";"Larva";175;1
"Unit";"Zergling";"Larva";175;1
"Unit";"Zergling";"Larva";175;1
"Unit";"Zergling";"Larva";175;1
"Unit";"Zergling";"Larva";175;1
"Unit";"Zergling";"Larva";207;1
"Unit";"Zergling";"Larva";207;1
"Unit";"Zergling";"Larva";207;1
"Unit";"Zergling";"Larva";207;1
"Unit";"Zergling";"Larva";207;1
"Unit";"Zergling";"Larva";207;1
"Unit";"Zergling";"Larva";207;1
"Unit";"Zergling";"Larva";207;1
"Unit";"Zergling";"Larva";207;1
"Unit";"Zergling";"Larva";207;1
"Unit";"Zergling";"Larva";207;1
"Unit";"Zergling";"Larva";207;1
"Unit";"Zergling";"Larva";207;1
"Unit";"Zergling";"Larva";207;1
"Unit";"Zergling";"Larva";207;1
"Unit";"Zergling";"Larva";207;1
"Unit";"Zergling";"Larva";207;1
"Unit";"Zergling";"Larva";207;1
"Unit";"Zergling";"Larva";207;1
"Unit";"Zergling";"Larva";207;1
"Unit";"Baneling";"Zergling";207;0
"Unit";"Baneling";"Zergling";207;0
"Unit";"Baneling";"Zergling";207;0
"Unit";"Baneling";"Zergling";207;0
"Unit";"Baneling";"Zergling";207;0
"Unit";"Baneling";"Zergling";207;0
"Unit";"Baneling";"Zergling";207;0
"Unit";"Baneling";"Zergling";207;0
"Unit";"Baneling";"Zergling";207;0
"Unit";"Baneling";"Zergling";207;0
"Unit";"Baneling";"Zergling";207;0
"Unit";"Baneling";"Zergling";207;0
"Unit";"Baneling";"Zergling";207;0
"Unit";"Baneling";"Zergling";207;0
"Unit";"Baneling";"Zergling";207;0
"Unit";"Baneling";"Zergling";207;0
"Unit";"Baneling";"Zergling";207;0
"Unit";"Baneling";"Zergling";207;0
"Unit";"Baneling";"Zergling";207;0
"Unit";"Baneling";"Zergling";207;0
"Unit";"Baneling";"Zergling";207;0
"Unit";"Baneling";"Zergling";207;0
"Unit";"Baneling";"Zergling";207;0
"Unit";"Mutalisk";"Larva";227;2
"Unit";"Mutalisk";"Larva";227;2
"Unit";"Mutalisk";"Larva";227;2
"Unit";"Mutalisk";"Larva";227;2
"Unit";"Mutalisk";"Larva";227;2
"Building";"CreepTumor";NA;229;0
"Building";"CreepTumor";NA;239;0
"Building";"CreepTumor";NA;239;0
"Upgrade";"ZergMeleeWeaponsLevel1";"EvolutionChamber";175;0
"Building";"CreepTumor";NA;239;0
"Building";"CreepTumor";NA;239;0
"Unit";"Zergling";"Larva";239;1
"Unit";"Zergling";"Larva";239;1
"Unit";"Zergling";"Larva";239;1
"Unit";"Zergling";"Larva";239;1
"Unit";"Zergling";"Larva";239;1
"Unit";"Zergling";"Larva";239;1
"Unit";"Zergling";"Larva";239;1
"Unit";"Zergling";"Larva";239;1
"Unit";"Zergling";"Larva";239;1
"Unit";"Zergling";"Larva";239;1
"Unit";"Zergling";"Larva";239;1
"Unit";"Zergling";"Larva";239;1
"Unit";"Zergling";"Larva";239;1
"Unit";"Zergling";"Larva";239;1
"Unit";"Zergling";"Larva";239;1
"Unit";"Zergling";"Larva";239;1
"Building";"InfestationPit";NA;228;0
"Building";"CreepTumor";NA;239;0
"Upgrade";"ZergGroundArmorsLevel2";"EvolutionChamber";175;0
"Building";"CreepTumor";NA;255;0
"Building";"CreepTumor";NA;255;0
"Unit";"Zergling";"Larva";255;1
"Unit";"Zergling";"Larva";255;1
"Unit";"Zergling";"Larva";255;1
"Unit";"Zergling";"Larva";255;1
"Unit";"Zergling";"Larva";255;1
"Unit";"Zergling";"Larva";255;1
"Unit";"Zergling";"Larva";255;1
"Unit";"Zergling";"Larva";255;1
"Unit";"Zergling";"Larva";255;1
"Unit";"Zergling";"Larva";255;1
"Unit";"Zergling";"Larva";255;1
"Unit";"Zergling";"Larva";255;1
"Unit";"Zergling";"Larva";255;1
"Unit";"Zergling";"Larva";255;1
"Unit";"Overlord";"Larva";255;0
"Unit";"Overlord";"Larva";255;0
"Unit";"Overlord";"Larva";255;0
"Unit";"Overlord";"Larva";255;0
"Unit";"Overlord";"Larva";255;0
"Unit";"Overlord";"Larva";255;0
