"type";"unit_name";"on_building";"total_supply";"supply"
"Unit";"Overlord";"Larva";12;0
"Building";"Extractor";NA;18;0
"Unit";"Overlord";"Larva";21;0
"Building";"SpawningPool";NA;19;0
"Building";"Hatchery";NA;17;0
"Unit";"Zergling";"Larva";22;1
"Unit";"Zergling";"Larva";22;1
"Unit";"Zergling";"Larva";23;1
"Unit";"Zergling";"Larva";23;1
"Unit";"Queen";"Hatchery";22;2
"Unit";"Queen";"Hatchery";23;2
"Unit";"Overlord";"Larva";34;0
"Building";"CreepTumorQueen";NA;35;0
"Unit";"Queen";"Hatchery";31;2
"Unit";"Overlord";"Larva";34;0
"Building";"CreepTumorQueen";NA;35;0
"Unit";"Queen";"Hatchery";34;2
"Building";"Hatchery";NA;27;0
"Building";"CreepTumor";NA;42;0
"Building";"CreepTumor";NA;44;0
"Building";"CreepTumorQueen";NA;47;0
"Building";"CreepTumorQueen";NA;48;0
"Building";"BanelingNest";NA;36;0
"Building";"CreepTumor";NA;54;0
"Building";"Extractor";NA;53;0
"Building";"CreepTumor";NA;54;0
"Building";"CreepTumor";NA;54;0
"Unit";"Overlord";"Larva";54;0
"Building";"CreepTumor";NA;57;0
"Unit";"Queen";"Hatchery";51;2
"Unit";"Baneling";"Zergling";57;0
"Unit";"Baneling";"Zergling";57;0
"Unit";"Zergling";"Larva";57;1
"Unit";"Zergling";"Larva";57;1
"Unit";"Zergling";"Larva";57;1
"Unit";"Zergling";"Larva";57;1
"Unit";"Zergling";"Larva";57;1
"Unit";"Zergling";"Larva";57;1
"Unit";"Zergling";"Larva";57;1
"Unit";"Zergling";"Larva";57;1
"Building";"Extractor";NA;57;0
"Building";"SporeCrawler";NA;57;0
"Building";"CreepTumorQueen";NA;71;0
"Building";"CreepTumorQueen";NA;71;0
"Building";"SporeCrawler";NA;58;0
"Building";"CreepTumor";NA;71;0
"Building";"CreepTumor";NA;71;0
"Building";"CreepTumor";NA;71;0
"Building";"CreepTumor";NA;71;0
"Building";"SporeCrawler";NA;63;0
"Building";"CreepTumorQueen";NA;72;0
"Unit";"Zergling";"Larva";73;1
"Unit";"Zergling";"Larva";73;1
"Unit";"Zergling";"Larva";73;1
"Unit";"Zergling";"Larva";73;1
"Unit";"Zergling";"Larva";73;1
"Unit";"Zergling";"Larva";73;1
"Building";"CreepTumorQueen";NA;79;0
"Building";"CreepTumorQueen";NA;79;0
"Unit";"Overlord";"Larva";79;0
"Unit";"Overlord";"Larva";79;0
"Unit";"Overlord";"Larva";79;0
"Building";"CreepTumor";NA;85;0
"Building";"CreepTumor";NA;85;0
"Building";"CreepTumor";NA;87;0
"Building";"CreepTumor";NA;87;0
"Building";"CreepTumor";NA;87;0
"Building";"CreepTumor";NA;89;0
"Building";"EvolutionChamber";NA;87;0
"Building";"Extractor";NA;87;0
"Building";"HydraliskDen";NA;87;0
"Building";"EvolutionChamber";NA;87;0
"Building";"CreepTumor";NA;99;0
"Building";"CreepTumor";NA;100;0
"Building";"Extractor";NA;100;0
"Building";"Extractor";NA;100;0
"Unit";"Zergling";"Larva";105;1
"Unit";"Zergling";"Larva";105;1
"Unit";"Zergling";"Larva";105;1
"Unit";"Zergling";"Larva";105;1
"Unit";"Zergling";"Larva";105;1
"Unit";"Zergling";"Larva";105;1
"Unit";"Zergling";"Larva";105;1
"Unit";"Zergling";"Larva";105;1
"Building";"CreepTumor";NA;105;0
"Building";"CreepTumor";NA;105;0
"Building";"CreepTumor";NA;105;0
"Building";"CreepTumor";NA;117;0
"Unit";"Overlord";"Larva";110;0
"Unit";"Overlord";"Larva";119;0
"Unit";"Overlord";"Larva";119;0
"Unit";"Overlord";"Larva";119;0
"Building";"CreepTumorQueen";NA;119;0
"Unit";"Hydralisk";"Larva";119;2
"Unit";"Hydralisk";"Larva";119;2
"Building";"CreepTumorQueen";NA;119;0
"Upgrade";"EvolveGroovedSpines";"HydraliskDen";105;0
"Building";"Hatchery";NA;100;0
"Unit";"Overlord";"Larva";119;0
"Unit";"Overlord";"Larva";119;0
"Unit";"Overlord";"Larva";119;0
"Unit";"Baneling";"Zergling";123;0
"Unit";"Hydralisk";"Larva";123;2
"Unit";"Baneling";"Zergling";123;0
"Unit";"Baneling";"Zergling";123;0
"Unit";"Baneling";"Zergling";123;0
"Unit";"Baneling";"Zergling";123;0
"Unit";"Baneling";"Zergling";123;0
"Unit";"Baneling";"Zergling";123;0
"Unit";"Baneling";"Zergling";123;0
"Unit";"Baneling";"Zergling";123;0
"Unit";"Baneling";"Zergling";123;0
"Unit";"Hydralisk";"Larva";123;2
"Unit";"Hydralisk";"Larva";123;2
"Unit";"Hydralisk";"Larva";123;2
"Unit";"Hydralisk";"Larva";123;2
"Unit";"Hydralisk";"Larva";123;2
"Unit";"Hydralisk";"Larva";123;2
"Unit";"Hydralisk";"Larva";123;2
"Unit";"Hydralisk";"Larva";123;2
"Unit";"Hydralisk";"Larva";123;2
"Building";"CreepTumorQueen";NA;151;0
"Building";"CreepTumor";NA;151;0
"Building";"CreepTumor";NA;151;0
"Building";"CreepTumorQueen";NA;151;0
"Unit";"Overlord";"Larva";151;0
"Building";"InfestationPit";NA;123;0
"Unit";"Overlord";"Larva";151;0
"Upgrade";"ZergMeleeWeaponsLevel1";"EvolutionChamber";119;0
"Upgrade";"ZergGroundArmorsLevel1";"EvolutionChamber";119;0
"Building";"Extractor";NA;151;0
"Building";"Extractor";NA;151;0
"Unit";"Overlord";"Larva";151;0
"Unit";"Overlord";"Larva";151;0
"Unit";"Zergling";"Larva";151;1
"Unit";"Zergling";"Larva";151;1
"Unit";"Zergling";"Larva";151;1
"Unit";"Zergling";"Larva";151;1
"Unit";"Zergling";"Larva";151;1
"Unit";"Zergling";"Larva";151;1
"Unit";"Zergling";"Larva";151;1
"Unit";"Zergling";"Larva";151;1
"Unit";"Zergling";"Larva";151;1
"Unit";"Zergling";"Larva";151;1
"Unit";"Zergling";"Larva";151;1
"Unit";"Zergling";"Larva";151;1
"Unit";"Zergling";"Larva";151;1
"Unit";"Zergling";"Larva";151;1
"Unit";"Zergling";"Larva";151;1
"Unit";"Zergling";"Larva";151;1
"Unit";"Zergling";"Larva";151;1
"Unit";"Zergling";"Larva";151;1
"Unit";"Zergling";"Larva";151;1
"Unit";"Zergling";"Larva";151;1
"Upgrade";"EvolveMuscularAugments";"HydraliskDen";143;0
"Building";"CreepTumorQueen";NA;177;0
"Building";"CreepTumorQueen";NA;177;0
"Building";"Spire";NA;151;0
"Building";"CreepTumor";NA;180;0
"Building";"CreepTumorQueen";NA;180;0
"Building";"CreepTumor";NA;180;0
"Building";"CreepTumorQueen";NA;180;0
"Unit";"Hydralisk";"Larva";180;2
"Unit";"Hydralisk";"Larva";180;2
"Unit";"Hydralisk";"Larva";180;2
"Unit";"Hydralisk";"Larva";180;2
"Unit";"Hydralisk";"Larva";180;2
"Unit";"Hydralisk";"Larva";180;2
"Unit";"Hydralisk";"Larva";180;2
"Unit";"Hydralisk";"Larva";180;2
"Unit";"Hydralisk";"Larva";180;2
"Unit";"Hydralisk";"Larva";180;2
"Unit";"Hydralisk";"Larva";180;2
"Unit";"Hydralisk";"Larva";180;2
"Unit";"Hydralisk";"Larva";180;2
"Unit";"Hydralisk";"Larva";180;2
"Unit";"Hydralisk";"Larva";180;2
"Unit";"Hydralisk";"Larva";180;2
"Unit";"Hydralisk";"Larva";180;2
"Unit";"Hydralisk";"Larva";180;2
"Building";"CreepTumor";NA;180;0
"Unit";"Overlord";"Larva";180;0
"Building";"CreepTumor";NA;216;0
"Building";"CreepTumor";NA;216;0
"Building";"CreepTumor";NA;216;0
"Building";"CreepTumorQueen";NA;217;0
"Building";"Hatchery";NA;177;0
"Unit";"Overlord";"Larva";217;0
"Unit";"Overlord";"Larva";217;0
"Building";"CreepTumor";NA;217;0
"Unit";"Hydralisk";"Larva";217;2
"Building";"CreepTumor";NA;217;0
"Unit";"Hydralisk";"Larva";217;2
"Unit";"Hydralisk";"Larva";217;2
"Unit";"Hydralisk";"Larva";217;2
"Unit";"Hydralisk";"Larva";217;2
"Unit";"Hydralisk";"Larva";217;2
"Unit";"Hydralisk";"Larva";217;2
"Unit";"Hydralisk";"Larva";217;2
"Unit";"Hydralisk";"Larva";217;2
"Unit";"Hydralisk";"Larva";217;2
"Unit";"Hydralisk";"Larva";217;2
"Unit";"Hydralisk";"Larva";217;2
"Unit";"Hydralisk";"Larva";217;2
"Unit";"Hydralisk";"Larva";217;2
"Unit";"Hydralisk";"Larva";217;2
"Unit";"Hydralisk";"Larva";217;2
"Unit";"Hydralisk";"Larva";217;2
"Unit";"Hydralisk";"Larva";217;2
"Unit";"Hydralisk";"Larva";217;2
"Building";"CreepTumorQueen";NA;217;0
"Building";"CreepTumor";NA;217;0
"Building";"CreepTumor";NA;217;0
"Unit";"Overlord";"Larva";217;0
"Building";"CreepTumorQueen";NA;217;0
"Building";"CreepTumor";NA;217;0
"Building";"CreepTumor";NA;217;0
"Building";"CreepTumor";NA;255;0
"Unit";"Hydralisk";"Larva";255;2
"Building";"CreepTumor";NA;255;0
"Unit";"Hydralisk";"Larva";255;2
"Unit";"Hydralisk";"Larva";255;2
"Unit";"Hydralisk";"Larva";255;2
"Unit";"Hydralisk";"Larva";255;2
"Unit";"Hydralisk";"Larva";255;2
"Unit";"Hydralisk";"Larva";255;2
"Unit";"Hydralisk";"Larva";255;2
"Unit";"Hydralisk";"Larva";255;2
"Unit";"Hydralisk";"Larva";255;2
"Unit";"Hydralisk";"Larva";255;2
"Unit";"Hydralisk";"Larva";255;2
"Unit";"Hydralisk";"Larva";255;2
"Unit";"Hydralisk";"Larva";255;2
"Unit";"Hydralisk";"Larva";255;2
"Building";"CreepTumor";NA;255;0
"Building";"CreepTumor";NA;255;0
"Unit";"Hydralisk";"Larva";255;2
"Unit";"Hydralisk";"Larva";255;2
"Unit";"Hydralisk";"Larva";255;2
"Unit";"Hydralisk";"Larva";255;2
"Unit";"Hydralisk";"Larva";255;2
"Unit";"Hydralisk";"Larva";255;2
"Unit";"Hydralisk";"Larva";255;2
"Unit";"Hydralisk";"Larva";255;2
"Unit";"Hydralisk";"Larva";255;2
"Unit";"Hydralisk";"Larva";255;2
"Unit";"Hydralisk";"Larva";255;2
"Unit";"Zergling";"Larva";285;1
"Unit";"Zergling";"Larva";285;1
"Unit";"Zergling";"Larva";285;1
"Unit";"Zergling";"Larva";285;1
"Unit";"Zergling";"Larva";285;1
"Unit";"Zergling";"Larva";285;1
"Unit";"Zergling";"Larva";285;1
"Unit";"Zergling";"Larva";285;1
"Unit";"Zergling";"Larva";285;1
"Unit";"Zergling";"Larva";285;1
"Unit";"Zergling";"Larva";285;1
"Unit";"Zergling";"Larva";285;1
"Unit";"Zergling";"Larva";285;1
"Unit";"Zergling";"Larva";285;1
"Unit";"Zergling";"Larva";285;1
"Unit";"Zergling";"Larva";285;1
"Building";"CreepTumor";NA;323;0
"Building";"CreepTumor";NA;323;0
"Building";"CreepTumorQueen";NA;328;0
"Building";"CreepTumorQueen";NA;328;0
"Unit";"Corruptor";"Larva";323;2
"Unit";"Corruptor";"Larva";323;2
"Unit";"Corruptor";"Larva";323;2
"Unit";"Corruptor";"Larva";323;2
"Unit";"Corruptor";"Larva";323;2
"Unit";"Corruptor";"Larva";323;2
"Unit";"Corruptor";"Larva";323;2
"Unit";"Corruptor";"Larva";323;2
"Unit";"Corruptor";"Larva";323;2
"Upgrade";"ZergMissileWeaponsLevel1";"EvolutionChamber";255;0
"Building";"CreepTumorQueen";NA;328;0
"Building";"CreepTumorQueen";NA;328;0
"Building";"CreepTumorQueen";NA;346;0
"Unit";"Zergling";"Larva";328;1
"Unit";"Zergling";"Larva";328;1
"Unit";"Zergling";"Larva";328;1
"Unit";"Zergling";"Larva";328;1
"Unit";"Zergling";"Larva";328;1
"Unit";"Zergling";"Larva";328;1
"Unit";"Zergling";"Larva";328;1
"Unit";"Zergling";"Larva";328;1
"Unit";"Zergling";"Larva";328;1
"Unit";"Zergling";"Larva";328;1
"Unit";"Zergling";"Larva";328;1
"Unit";"Zergling";"Larva";328;1
"Unit";"Zergling";"Larva";328;1
"Unit";"Zergling";"Larva";328;1
"Unit";"Zergling";"Larva";328;1
"Unit";"Zergling";"Larva";328;1
"Unit";"Zergling";"Larva";328;1
"Unit";"Zergling";"Larva";328;1
"Unit";"Zergling";"Larva";328;1
"Unit";"Zergling";"Larva";328;1
"Unit";"Zergling";"Larva";328;1
"Unit";"Zergling";"Larva";328;1
"Unit";"Zergling";"Larva";328;1
"Unit";"Zergling";"Larva";328;1
"Unit";"Zergling";"Larva";328;1
"Unit";"Zergling";"Larva";328;1
"Unit";"Zergling";"Larva";328;1
"Unit";"Zergling";"Larva";328;1
"Unit";"Zergling";"Larva";328;1
"Unit";"Zergling";"Larva";328;1
"Unit";"Zergling";"Larva";328;1
"Unit";"Zergling";"Larva";328;1
"Unit";"Zergling";"Larva";328;1
"Unit";"Zergling";"Larva";328;1
"Unit";"Zergling";"Larva";328;1
"Unit";"Zergling";"Larva";328;1
"Unit";"Zergling";"Larva";328;1
"Unit";"Zergling";"Larva";328;1
"Unit";"Zergling";"Larva";328;1
"Unit";"Zergling";"Larva";328;1
"Unit";"Zergling";"Larva";328;1
"Unit";"Zergling";"Larva";328;1
"Unit";"Zergling";"Larva";328;1
"Unit";"Zergling";"Larva";328;1
"Unit";"Zergling";"Larva";328;1
"Unit";"Zergling";"Larva";328;1
"Unit";"Corruptor";"Larva";328;2
"Unit";"Corruptor";"Larva";328;2
"Upgrade";"ZergGroundArmorsLevel2";"EvolutionChamber";255;0
