"type";"unit_name";"on_building";"total_supply";"supply"
"Unit";"Overlord";"Larva";13;0
"Building";"Extractor";NA;18;0
"Unit";"Overlord";"Larva";21;0
"Building";"SpawningPool";NA;19;0
"Building";"Hatchery";NA;17;0
"Unit";"Zergling";"Larva";23;1
"Unit";"Zergling";"Larva";23;1
"Unit";"Zergling";"Larva";23;1
"Unit";"Zergling";"Larva";23;1
"Unit";"Queen";"Hatchery";23;2
"Unit";"Queen";"Hatchery";23;2
"Unit";"Overlord";"Larva";32;0
"Unit";"Queen";"Hatchery";32;2
"Unit";"Overlord";"Larva";35;0
"Building";"CreepTumorQueen";NA;35;0
"Unit";"Overlord";"Larva";38;0
"Unit";"Overlord";"Larva";45;0
"Building";"CreepTumorQueen";NA;47;0
"Unit";"Queen";"Hatchery";42;2
"Building";"CreepTumor";NA;47;0
"Building";"Hatchery";NA;32;0
"Unit";"Overlord";"Larva";48;0
"Building";"CreepTumor";NA;57;0
"Building";"CreepTumor";NA;57;0
"Building";"Extractor";NA;53;0
"Building";"RoachWarren";NA;47;0
"Unit";"Overlord";"Larva";57;0
"Building";"CreepTumorQueen";NA;61;0
"Unit";"Queen";"Hatchery";53;2
"Building";"CreepTumor";NA;62;0
"Unit";"Zergling";"Larva";62;1
"Unit";"Zergling";"Larva";62;1
"Unit";"Zergling";"Larva";62;1
"Unit";"Zergling";"Larva";62;1
"Unit";"Zergling";"Larva";62;1
"Unit";"Zergling";"Larva";62;1
"Unit";"Zergling";"Larva";62;1
"Unit";"Zergling";"Larva";62;1
"Unit";"Zergling";"Larva";62;1
"Unit";"Zergling";"Larva";62;1
"Unit";"Zergling";"Larva";62;1
"Unit";"Zergling";"Larva";62;1
"Unit";"Zergling";"Larva";62;1
"Unit";"Zergling";"Larva";62;1
"Unit";"Zergling";"Larva";62;1
"Unit";"Zergling";"Larva";62;1
"Building";"EvolutionChamber";NA;62;0
"Building";"CreepTumor";NA;64;0
"Building";"Extractor";NA;62;0
"Unit";"Roach";"Larva";64;2
"Unit";"Roach";"Larva";64;2
"Unit";"Roach";"Larva";64;2
"Unit";"Roach";"Larva";64;2
"Unit";"Overlord";"Larva";64;0
"Unit";"Overlord";"Larva";64;0
"Unit";"Zergling";"Larva";80;1
"Unit";"Zergling";"Larva";80;1
"Unit";"Zergling";"Larva";80;1
"Unit";"Zergling";"Larva";80;1
"Building";"CreepTumor";NA;80;0
"Unit";"Zergling";"Larva";80;1
"Unit";"Zergling";"Larva";80;1
"Building";"CreepTumor";NA;88;0
"Unit";"Overlord";"Larva";80;0
"Building";"CreepTumor";NA;94;0
"Building";"CreepTumorQueen";NA;99;0
"Unit";"Queen";"Hatchery";80;2
"Unit";"Overlord";"Larva";99;0
"Building";"CreepTumor";NA;108;0
"Building";"CreepTumor";NA;109;0
"Building";"HydraliskDen";NA;99;0
"Unit";"Overlord";"Larva";109;0
"Building";"BanelingNest";NA;99;0
"Unit";"Zergling";"Larva";113;1
"Unit";"Zergling";"Larva";113;1
"Unit";"Roach";"Larva";113;2
"Unit";"Roach";"Larva";113;2
"Building";"CreepTumor";NA;123;0
"Building";"CreepTumorQueen";NA;127;0
"Building";"CreepTumorQueen";NA;127;0
"Building";"Extractor";NA;123;0
"Building";"CreepTumor";NA;127;0
"Building";"CreepTumorQueen";NA;127;0
"Building";"CreepTumorQueen";NA;127;0
"Building";"CreepTumorQueen";NA;134;0
"Building";"CreepTumorQueen";NA;134;0
"Unit";"Zergling";"Larva";134;1
"Unit";"Zergling";"Larva";134;1
"Unit";"Zergling";"Larva";134;1
"Unit";"Zergling";"Larva";134;1
"Unit";"Zergling";"Larva";134;1
"Unit";"Zergling";"Larva";134;1
"Unit";"Zergling";"Larva";134;1
"Unit";"Zergling";"Larva";134;1
"Unit";"Zergling";"Larva";134;1
"Unit";"Zergling";"Larva";134;1
"Unit";"Zergling";"Larva";134;1
"Unit";"Zergling";"Larva";134;1
"Unit";"Zergling";"Larva";134;1
"Unit";"Zergling";"Larva";134;1
"Unit";"Roach";"Larva";134;2
"Unit";"Roach";"Larva";134;2
"Unit";"Roach";"Larva";134;2
"Building";"CreepTumor";NA;134;0
"Unit";"Zergling";"Larva";134;1
"Unit";"Zergling";"Larva";134;1
"Building";"CreepTumor";NA;134;0
"Building";"EvolutionChamber";NA;134;0
"Building";"Extractor";NA;134;0
"Building";"CreepTumor";NA;148;0
"Building";"CreepTumor";NA;148;0
"Building";"CreepTumor";NA;148;0
"Upgrade";"EvolveGroovedSpines";"HydraliskDen";127;0
"Building";"CreepTumor";NA;162;0
"Building";"Extractor";NA;162;0
"Unit";"Overlord";"Larva";162;0
"Unit";"Overlord";"Larva";162;0
"Unit";"Zergling";"Larva";162;1
"Unit";"Zergling";"Larva";162;1
"Unit";"Zergling";"Larva";162;1
"Unit";"Zergling";"Larva";162;1
"Unit";"Overlord";"Larva";162;0
"Building";"Hatchery";NA;127;0
"Unit";"Baneling";"Zergling";163;0
"Unit";"Baneling";"Zergling";164;0
"Unit";"Baneling";"Zergling";165;0
"Unit";"Baneling";"Zergling";166;0
"Unit";"Baneling";"Zergling";166;0
"Unit";"Baneling";"Zergling";166;0
"Building";"CreepTumor";NA;166;0
"Building";"CreepTumor";NA;166;0
"Building";"CreepTumor";NA;166;0
"Building";"CreepTumor";NA;170;0
"Unit";"Zergling";"Larva";181;1
"Unit";"Zergling";"Larva";181;1
"Unit";"Zergling";"Larva";181;1
"Unit";"Zergling";"Larva";181;1
"Unit";"Zergling";"Larva";181;1
"Unit";"Zergling";"Larva";181;1
"Building";"CreepTumor";NA;181;0
"Unit";"Hydralisk";"Larva";181;2
"Unit";"Hydralisk";"Larva";181;2
"Unit";"Hydralisk";"Larva";181;2
"Unit";"Hydralisk";"Larva";181;2
"Unit";"Hydralisk";"Larva";181;2
"Unit";"Hydralisk";"Larva";181;2
"Unit";"Hydralisk";"Larva";181;2
"Building";"CreepTumor";NA;181;0
"Unit";"Queen";"Hatchery";181;2
"Building";"Hatchery";NA;162;0
"Upgrade";"ZergGroundArmorsLevel1";"EvolutionChamber";162;0
"Building";"CreepTumor";NA;201;0
"Upgrade";"EvolveMuscularAugments";"HydraliskDen";181;0
"Unit";"Overlord";"Larva";203;0
"Building";"SporeCrawler";NA;201;0
"Unit";"Overlord";"Larva";203;0
"Unit";"Overlord";"Larva";203;0
"Building";"SporeCrawler";NA;201;0
"Building";"SporeCrawler";NA;201;0
"Unit";"Overlord";"Larva";203;0
"Unit";"Overlord";"Larva";203;0
"Unit";"Overlord";"Larva";203;0
"Unit";"Zergling";"Larva";203;1
"Unit";"Zergling";"Larva";203;1
"Unit";"Zergling";"Larva";203;1
"Unit";"Zergling";"Larva";203;1
"Unit";"Zergling";"Larva";203;1
"Unit";"Zergling";"Larva";203;1
"Unit";"Zergling";"Larva";203;1
"Unit";"Zergling";"Larva";203;1
"Unit";"Zergling";"Larva";203;1
"Unit";"Zergling";"Larva";203;1
"Unit";"Zergling";"Larva";203;1
"Unit";"Zergling";"Larva";203;1
"Unit";"Zergling";"Larva";203;1
"Unit";"Zergling";"Larva";203;1
"Unit";"Baneling";"Zergling";203;0
"Unit";"Zergling";"Larva";203;1
"Unit";"Zergling";"Larva";203;1
"Unit";"Zergling";"Larva";203;1
"Unit";"Zergling";"Larva";203;1
"Unit";"Baneling";"Zergling";203;0
"Unit";"Baneling";"Zergling";203;0
"Unit";"Baneling";"Zergling";203;0
"Unit";"Baneling";"Zergling";203;0
"Unit";"Zergling";"Larva";203;1
"Unit";"Zergling";"Larva";203;1
"Unit";"Baneling";"Zergling";203;0
"Unit";"Baneling";"Zergling";203;0
"Unit";"Baneling";"Zergling";203;0
"Unit";"Baneling";"Zergling";203;0
"Building";"CreepTumor";NA;203;0
"Building";"SpineCrawler";NA;203;0
"Building";"InfestationPit";NA;203;0
"Building";"SporeCrawler";NA;224;0
"Building";"Extractor";NA;224;0
"Building";"Extractor";NA;224;0
"Unit";"Zergling";"Larva";224;1
"Unit";"Zergling";"Larva";224;1
"Unit";"Zergling";"Larva";224;1
"Unit";"Zergling";"Larva";224;1
"Unit";"Zergling";"Larva";224;1
"Unit";"Zergling";"Larva";224;1
"Unit";"Zergling";"Larva";224;1
"Unit";"Zergling";"Larva";224;1
"Unit";"Zergling";"Larva";224;1
"Unit";"Zergling";"Larva";224;1
"Unit";"Zergling";"Larva";224;1
"Unit";"Zergling";"Larva";224;1
"Unit";"Zergling";"Larva";224;1
"Unit";"Zergling";"Larva";224;1
"Unit";"Zergling";"Larva";224;1
"Unit";"Zergling";"Larva";224;1
"Unit";"Zergling";"Larva";224;1
"Unit";"Zergling";"Larva";224;1
"Unit";"Zergling";"Larva";224;1
"Unit";"Zergling";"Larva";224;1
"Unit";"Zergling";"Larva";224;1
"Unit";"Zergling";"Larva";224;1
"Unit";"Zergling";"Larva";224;1
"Unit";"Zergling";"Larva";224;1
"Unit";"Zergling";"Larva";224;1
"Unit";"Zergling";"Larva";224;1
"Unit";"Zergling";"Larva";224;1
"Unit";"Zergling";"Larva";224;1
"Unit";"Zergling";"Larva";224;1
"Unit";"Zergling";"Larva";224;1
"Unit";"Zergling";"Larva";224;1
"Unit";"Zergling";"Larva";224;1
"Unit";"Zergling";"Larva";224;1
"Unit";"Zergling";"Larva";224;1
"Unit";"Zergling";"Larva";224;1
"Unit";"Zergling";"Larva";224;1
"Unit";"Zergling";"Larva";224;1
"Unit";"Zergling";"Larva";224;1
"Unit";"Zergling";"Larva";224;1
"Unit";"Zergling";"Larva";224;1
"Unit";"Queen";"Hatchery";224;2
"Unit";"Zergling";"Larva";224;1
"Unit";"Zergling";"Larva";224;1
"Unit";"Zergling";"Larva";224;1
"Unit";"Zergling";"Larva";224;1
"Unit";"Zergling";"Larva";224;1
"Unit";"Zergling";"Larva";224;1
"Unit";"Zergling";"Larva";224;1
"Unit";"Zergling";"Larva";224;1
"Unit";"Zergling";"Larva";224;1
"Unit";"Zergling";"Larva";224;1
"Unit";"Zergling";"Larva";224;1
"Unit";"Zergling";"Larva";224;1
"Unit";"Zergling";"Larva";224;1
"Unit";"Zergling";"Larva";224;1
"Unit";"Zergling";"Larva";224;1
"Unit";"Zergling";"Larva";224;1
"Unit";"Zergling";"Larva";224;1
"Unit";"Zergling";"Larva";224;1
"Unit";"Zergling";"Larva";224;1
"Unit";"Zergling";"Larva";224;1
"Unit";"Zergling";"Larva";224;1
"Unit";"Zergling";"Larva";224;1
"Unit";"Baneling";"Zergling";262;0
"Unit";"Baneling";"Zergling";262;0
"Unit";"Baneling";"Zergling";262;0
"Unit";"Baneling";"Zergling";262;0
"Unit";"Baneling";"Zergling";262;0
"Unit";"Baneling";"Zergling";262;0
"Unit";"Baneling";"Zergling";262;0
"Unit";"Baneling";"Zergling";262;0
"Unit";"Baneling";"Zergling";262;0
"Unit";"Baneling";"Zergling";262;0
"Unit";"Zergling";"Larva";264;1
"Unit";"Zergling";"Larva";264;1
"Unit";"Zergling";"Larva";266;1
"Unit";"Zergling";"Larva";266;1
"Unit";"Zergling";"Larva";266;1
"Unit";"Zergling";"Larva";266;1
"Unit";"Zergling";"Larva";266;1
"Unit";"Zergling";"Larva";266;1
"Upgrade";"ZergMeleeWeaponsLevel1";"EvolutionChamber";203;0
"Unit";"Hydralisk";"Larva";288;2
"Unit";"Hydralisk";"Larva";288;2
"Unit";"Hydralisk";"Larva";290;2
"Unit";"Hydralisk";"Larva";292;2
"Unit";"Hydralisk";"Larva";294;2
"Unit";"Hydralisk";"Larva";296;2
"Unit";"Hydralisk";"Larva";296;2
"Unit";"Hydralisk";"Larva";296;2
"Unit";"Hydralisk";"Larva";296;2
"Building";"SpineCrawler";NA;282;0
"Unit";"Zergling";"Larva";296;1
"Unit";"Zergling";"Larva";296;1
"Unit";"Zergling";"Larva";296;1
"Unit";"Zergling";"Larva";296;1
"Unit";"Zergling";"Larva";296;1
"Unit";"Zergling";"Larva";296;1
"Unit";"Zergling";"Larva";296;1
"Unit";"Zergling";"Larva";296;1
"Unit";"Zergling";"Larva";296;1
"Unit";"Zergling";"Larva";296;1
"Unit";"Zergling";"Larva";296;1
"Unit";"Zergling";"Larva";296;1
"Unit";"Zergling";"Larva";296;1
"Unit";"Zergling";"Larva";296;1
"Unit";"Zergling";"Larva";296;1
"Unit";"Zergling";"Larva";296;1
"Unit";"Zergling";"Larva";296;1
"Unit";"Zergling";"Larva";296;1
"Unit";"Zergling";"Larva";296;1
"Unit";"Zergling";"Larva";296;1
"Unit";"Zergling";"Larva";296;1
"Unit";"Zergling";"Larva";296;1
"Unit";"Zergling";"Larva";296;1
"Unit";"Zergling";"Larva";296;1
"Unit";"Zergling";"Larva";296;1
"Unit";"Zergling";"Larva";296;1
"Unit";"Zergling";"Larva";296;1
"Unit";"Zergling";"Larva";296;1
"Unit";"Zergling";"Larva";296;1
"Unit";"Zergling";"Larva";296;1
"Building";"SporeCrawler";NA;296;0
"Unit";"Zergling";"Larva";314;1
"Unit";"Zergling";"Larva";314;1
"Unit";"Zergling";"Larva";314;1
"Unit";"Zergling";"Larva";314;1
"Unit";"Zergling";"Larva";314;1
"Unit";"Zergling";"Larva";314;1
"Unit";"Zergling";"Larva";314;1
"Unit";"Zergling";"Larva";314;1
"Unit";"Zergling";"Larva";314;1
"Unit";"Zergling";"Larva";314;1
"Unit";"Zergling";"Larva";314;1
"Unit";"Zergling";"Larva";314;1
"Unit";"Zergling";"Larva";316;1
"Unit";"Zergling";"Larva";316;1
"Unit";"Zergling";"Larva";316;1
"Unit";"Zergling";"Larva";316;1
"Unit";"Zergling";"Larva";316;1
"Unit";"Zergling";"Larva";316;1
"Unit";"Zergling";"Larva";316;1
"Unit";"Zergling";"Larva";316;1
"Unit";"Zergling";"Larva";316;1
"Unit";"Zergling";"Larva";316;1
"Unit";"Queen";"Hatchery";296;2
"Building";"Hatchery";NA;270;0
"Unit";"Zergling";"Larva";362;1
"Unit";"Zergling";"Larva";362;1
"Upgrade";"ZergGroundArmorsLevel2";"EvolutionChamber";224;0
"Unit";"Zergling";"Larva";366;1
"Unit";"Zergling";"Larva";366;1
"Unit";"Zergling";"Larva";366;1
"Unit";"Zergling";"Larva";366;1
"Unit";"Zergling";"Larva";366;1
"Unit";"Zergling";"Larva";366;1
"Unit";"Zergling";"Larva";366;1
"Unit";"Zergling";"Larva";366;1
"Unit";"Zergling";"Larva";366;1
"Unit";"Zergling";"Larva";366;1
"Unit";"Zergling";"Larva";366;1
"Unit";"Zergling";"Larva";366;1
"Unit";"Zergling";"Larva";366;1
"Unit";"Zergling";"Larva";366;1
"Unit";"Zergling";"Larva";366;1
"Unit";"Zergling";"Larva";366;1
"Unit";"Zergling";"Larva";366;1
"Unit";"Zergling";"Larva";366;1
"Unit";"Zergling";"Larva";366;1
"Unit";"Zergling";"Larva";366;1
"Unit";"Zergling";"Larva";366;1
"Unit";"Zergling";"Larva";366;1
"Unit";"Zergling";"Larva";366;1
"Unit";"Zergling";"Larva";366;1
"Unit";"Zergling";"Larva";366;1
"Unit";"Zergling";"Larva";366;1
"Unit";"Zergling";"Larva";366;1
"Unit";"Zergling";"Larva";366;1
"Unit";"Zergling";"Larva";366;1
"Unit";"Zergling";"Larva";366;1
"Unit";"Zergling";"Larva";366;1
"Unit";"Zergling";"Larva";366;1
"Unit";"Zergling";"Larva";366;1
"Unit";"Zergling";"Larva";366;1
"Unit";"Zergling";"Larva";366;1
"Unit";"Zergling";"Larva";366;1
"Unit";"Zergling";"Larva";366;1
"Unit";"Zergling";"Larva";366;1
"Unit";"Zergling";"Larva";366;1
"Unit";"Zergling";"Larva";366;1
"Unit";"Zergling";"Larva";366;1
"Unit";"Zergling";"Larva";366;1
"Unit";"Zergling";"Larva";366;1
"Unit";"Zergling";"Larva";366;1
"Unit";"Zergling";"Larva";366;1
"Unit";"Zergling";"Larva";366;1
"Unit";"Zergling";"Larva";368;1
"Unit";"Zergling";"Larva";368;1
"Unit";"Zergling";"Larva";368;1
"Unit";"Zergling";"Larva";368;1
"Unit";"Zergling";"Larva";368;1
"Unit";"Zergling";"Larva";368;1
"Building";"CreepTumor";NA;390;0
"Unit";"Zergling";"Larva";390;1
"Unit";"Zergling";"Larva";390;1
"Unit";"Roach";"Larva";390;2
"Unit";"Baneling";"Zergling";416;0
"Unit";"Baneling";"Zergling";416;0
"Unit";"Baneling";"Zergling";416;0
"Unit";"Baneling";"Zergling";416;0
"Unit";"Baneling";"Zergling";416;0
"Unit";"Baneling";"Zergling";416;0
"Unit";"Baneling";"Zergling";416;0
"Unit";"Baneling";"Zergling";416;0
"Unit";"Baneling";"Zergling";416;0
"Unit";"Baneling";"Zergling";416;0
"Unit";"Baneling";"Zergling";416;0
"Unit";"Baneling";"Zergling";416;0
"Unit";"Baneling";"Zergling";416;0
"Unit";"Baneling";"Zergling";416;0
"Unit";"Baneling";"Zergling";416;0
"Unit";"Baneling";"Zergling";416;0
"Unit";"Hydralisk";"Larva";390;2
"Unit";"Hydralisk";"Larva";390;2
"Unit";"Zergling";"Larva";424;1
"Unit";"Zergling";"Larva";424;1
"Unit";"Zergling";"Larva";424;1
"Unit";"Zergling";"Larva";424;1
"Unit";"Zergling";"Larva";424;1
"Unit";"Zergling";"Larva";424;1
"Unit";"Zergling";"Larva";424;1
"Unit";"Zergling";"Larva";424;1
"Unit";"Zergling";"Larva";424;1
"Unit";"Zergling";"Larva";424;1
"Unit";"Zergling";"Larva";424;1
"Unit";"Zergling";"Larva";424;1
"Unit";"Zergling";"Larva";424;1
"Unit";"Zergling";"Larva";424;1
"Unit";"Zergling";"Larva";424;1
"Unit";"Zergling";"Larva";424;1
"Unit";"Zergling";"Larva";424;1
"Unit";"Zergling";"Larva";424;1
"Unit";"Zergling";"Larva";424;1
"Unit";"Zergling";"Larva";424;1
"Unit";"Zergling";"Larva";426;1
"Unit";"Zergling";"Larva";426;1
"Unit";"Zergling";"Larva";426;1
"Unit";"Zergling";"Larva";426;1
"Unit";"Zergling";"Larva";426;1
"Unit";"Zergling";"Larva";426;1
"Unit";"Queen";"Hatchery";422;2
"Unit";"Baneling";"Zergling";458;0
"Unit";"Baneling";"Zergling";458;0
"Building";"CreepTumor";NA;458;0
"Unit";"Baneling";"Zergling";458;0
"Unit";"Baneling";"Zergling";458;0
"Unit";"Baneling";"Zergling";458;0
"Unit";"Baneling";"Zergling";458;0
"Unit";"Baneling";"Zergling";458;0
"Unit";"Baneling";"Zergling";458;0
"Unit";"Baneling";"Zergling";458;0
"Unit";"Zergling";"Larva";458;1
"Unit";"Zergling";"Larva";458;1
"Unit";"Baneling";"Zergling";458;0
"Unit";"Baneling";"Zergling";458;0
"Unit";"Baneling";"Zergling";458;0
"Unit";"Baneling";"Zergling";458;0
"Unit";"Baneling";"Zergling";458;0
"Unit";"Baneling";"Zergling";458;0
"Unit";"Baneling";"Zergling";458;0
"Unit";"Baneling";"Zergling";458;0
"Unit";"Baneling";"Zergling";458;0
"Unit";"Baneling";"Zergling";458;0
"Unit";"Baneling";"Zergling";458;0
"Unit";"Zergling";"Larva";458;1
"Unit";"Zergling";"Larva";458;1
"Unit";"Zergling";"Larva";458;1
"Unit";"Zergling";"Larva";458;1
"Unit";"Zergling";"Larva";458;1
"Unit";"Zergling";"Larva";458;1
"Unit";"Zergling";"Larva";458;1
"Unit";"Zergling";"Larva";458;1
"Unit";"Zergling";"Larva";458;1
"Unit";"Zergling";"Larva";458;1
"Unit";"Zergling";"Larva";458;1
"Unit";"Zergling";"Larva";458;1
"Unit";"Zergling";"Larva";458;1
"Unit";"Zergling";"Larva";458;1
"Unit";"Zergling";"Larva";458;1
"Unit";"Zergling";"Larva";458;1
"Building";"CreepTumorQueen";NA;458;0
"Unit";"Zergling";"Larva";458;1
"Unit";"Zergling";"Larva";458;1
"Unit";"Zergling";"Larva";458;1
"Unit";"Zergling";"Larva";458;1
"Unit";"Zergling";"Larva";458;1
"Unit";"Zergling";"Larva";458;1
"Unit";"Zergling";"Larva";458;1
"Unit";"Zergling";"Larva";458;1
"Unit";"Zergling";"Larva";458;1
"Unit";"Zergling";"Larva";458;1
"Unit";"Zergling";"Larva";458;1
"Unit";"Zergling";"Larva";458;1
"Unit";"Zergling";"Larva";458;1
"Unit";"Zergling";"Larva";458;1
"Unit";"Zergling";"Larva";458;1
"Unit";"Zergling";"Larva";458;1
"Building";"CreepTumorQueen";NA;458;0
"Unit";"Baneling";"Zergling";458;0
"Unit";"Baneling";"Zergling";458;0
"Building";"CreepTumor";NA;458;0
"Unit";"Viper";"Larva";458;3
"Unit";"Viper";"Larva";458;3
"Unit";"Viper";"Larva";458;3
"Unit";"Zergling";"Larva";492;1
"Unit";"Zergling";"Larva";492;1
"Unit";"Zergling";"Larva";492;1
"Unit";"Zergling";"Larva";492;1
"Unit";"Zergling";"Larva";492;1
"Unit";"Zergling";"Larva";492;1
"Unit";"Zergling";"Larva";492;1
"Unit";"Zergling";"Larva";492;1
"Unit";"Zergling";"Larva";492;1
"Unit";"Zergling";"Larva";492;1
"Unit";"Zergling";"Larva";492;1
"Unit";"Zergling";"Larva";492;1
"Unit";"Zergling";"Larva";492;1
"Unit";"Zergling";"Larva";492;1
"Unit";"Zergling";"Larva";492;1
"Unit";"Zergling";"Larva";492;1
"Unit";"Zergling";"Larva";492;1
"Unit";"Zergling";"Larva";492;1
"Upgrade";"ZergMeleeWeaponsLevel2";"EvolutionChamber";390;0
"Building";"UltraliskCavern";NA;458;0
"Building";"SpineCrawler";NA;458;0
"Building";"SpineCrawler";NA;458;0
"Building";"SpineCrawler";NA;458;0
"Unit";"Zergling";"Larva";502;1
"Unit";"Zergling";"Larva";502;1
"Unit";"Zergling";"Larva";502;1
"Unit";"Zergling";"Larva";502;1
"Unit";"Zergling";"Larva";502;1
"Unit";"Zergling";"Larva";502;1
"Unit";"Zergling";"Larva";502;1
"Unit";"Zergling";"Larva";502;1
"Unit";"Zergling";"Larva";502;1
"Unit";"Zergling";"Larva";502;1
"Unit";"Zergling";"Larva";502;1
"Unit";"Zergling";"Larva";502;1
"Unit";"Zergling";"Larva";502;1
"Unit";"Zergling";"Larva";502;1
"Unit";"Zergling";"Larva";502;1
"Unit";"Zergling";"Larva";502;1
"Unit";"Baneling";"Zergling";520;0
"Unit";"Baneling";"Zergling";520;0
"Unit";"Baneling";"Zergling";520;0
"Unit";"Baneling";"Zergling";520;0
"Unit";"Baneling";"Zergling";520;0
"Unit";"Baneling";"Zergling";520;0
"Unit";"Baneling";"Zergling";520;0
"Unit";"Baneling";"Zergling";520;0
"Unit";"Baneling";"Zergling";520;0
"Unit";"Baneling";"Zergling";520;0
"Unit";"Baneling";"Zergling";520;0
"Unit";"Baneling";"Zergling";520;0
"Unit";"Baneling";"Zergling";520;0
"Unit";"Baneling";"Zergling";520;0
"Unit";"Zergling";"Larva";536;1
"Unit";"Zergling";"Larva";536;1
"Unit";"Zergling";"Larva";536;1
"Unit";"Zergling";"Larva";536;1
"Unit";"Zergling";"Larva";536;1
"Unit";"Zergling";"Larva";536;1
"Unit";"Zergling";"Larva";536;1
"Unit";"Zergling";"Larva";536;1
"Unit";"Zergling";"Larva";536;1
"Unit";"Zergling";"Larva";536;1
"Unit";"Zergling";"Larva";536;1
"Unit";"Zergling";"Larva";536;1
"Unit";"Zergling";"Larva";536;1
"Unit";"Zergling";"Larva";536;1
"Unit";"Zergling";"Larva";536;1
"Unit";"Zergling";"Larva";536;1
"Unit";"Zergling";"Larva";536;1
"Unit";"Zergling";"Larva";536;1
"Unit";"Zergling";"Larva";536;1
"Unit";"Zergling";"Larva";536;1
"Unit";"Zergling";"Larva";536;1
"Unit";"Zergling";"Larva";536;1
"Unit";"Zergling";"Larva";536;1
"Unit";"Zergling";"Larva";536;1
"Unit";"Zergling";"Larva";536;1
"Unit";"Zergling";"Larva";536;1
"Building";"CreepTumor";NA;562;0
"Building";"CreepTumorQueen";NA;562;0
"Building";"CreepTumorQueen";NA;562;0
"Building";"CreepTumorQueen";NA;562;0
"Building";"CreepTumorQueen";NA;562;0
"Unit";"Ultralisk";"Larva";562;6
"Unit";"Ultralisk";"Larva";562;6
"Unit";"Ultralisk";"Larva";562;6
"Building";"CreepTumorQueen";NA;562;0
"Building";"CreepTumorQueen";NA;562;0
"Upgrade";"ChitinousPlating";"UltraliskCavern";536;0
"Building";"CreepTumor";NA;562;0
"Building";"CreepTumorQueen";NA;583;0
"Building";"CreepTumorQueen";NA;583;0
"Building";"CreepTumorQueen";NA;583;0
"Building";"SpineCrawler";NA;562;0
"Building";"CreepTumorQueen";NA;583;0
"Upgrade";"ZergGroundArmorsLevel3";"EvolutionChamber";520;0
"Building";"CreepTumor";NA;583;0
"Building";"CreepTumor";NA;583;0
"Building";"CreepTumor";NA;583;0
"Building";"CreepTumor";NA;583;0
"Building";"CreepTumor";NA;583;0
"Building";"CreepTumorQueen";NA;583;0
"Building";"CreepTumor";NA;583;0
"Building";"CreepTumor";NA;583;0
"Building";"CreepTumor";NA;583;0
"Building";"CreepTumor";NA;583;0
"Building";"CreepTumorQueen";NA;583;0
"Building";"CreepTumorQueen";NA;583;0
"Building";"Hatchery";NA;562;0
"Building";"CreepTumorQueen";NA;583;0
"Building";"CreepTumor";NA;583;0
"Unit";"Ultralisk";"Larva";583;6
"Unit";"Ultralisk";"Larva";583;6
"Unit";"Ultralisk";"Larva";583;6
"Unit";"Ultralisk";"Larva";583;6
"Unit";"Ultralisk";"Larva";583;6
"Unit";"Ultralisk";"Larva";583;6
"Unit";"Ultralisk";"Larva";583;6
"Unit";"Zergling";"Larva";583;1
"Unit";"Zergling";"Larva";583;1
"Unit";"Zergling";"Larva";583;1
"Unit";"Zergling";"Larva";583;1
"Unit";"Zergling";"Larva";583;1
"Unit";"Zergling";"Larva";583;1
"Unit";"Zergling";"Larva";583;1
"Unit";"Zergling";"Larva";583;1
"Unit";"Zergling";"Larva";583;1
"Unit";"Zergling";"Larva";583;1
"Unit";"Zergling";"Larva";583;1
"Unit";"Zergling";"Larva";583;1
"Unit";"Zergling";"Larva";583;1
"Unit";"Zergling";"Larva";583;1
"Unit";"Zergling";"Larva";583;1
"Unit";"Zergling";"Larva";583;1
"Unit";"Zergling";"Larva";583;1
"Unit";"Zergling";"Larva";583;1
"Unit";"Zergling";"Larva";583;1
"Unit";"Zergling";"Larva";583;1
"Unit";"Zergling";"Larva";583;1
"Unit";"Zergling";"Larva";583;1
"Unit";"Zergling";"Larva";583;1
"Unit";"Zergling";"Larva";583;1
"Unit";"Zergling";"Larva";583;1
"Unit";"Zergling";"Larva";583;1
"Unit";"Zergling";"Larva";583;1
"Unit";"Zergling";"Larva";583;1
"Unit";"Zergling";"Larva";583;1
"Unit";"Zergling";"Larva";583;1
"Unit";"Zergling";"Larva";583;1
"Unit";"Zergling";"Larva";583;1
"Unit";"Zergling";"Larva";583;1
"Unit";"Zergling";"Larva";583;1
"Unit";"Zergling";"Larva";583;1
"Unit";"Zergling";"Larva";583;1
"Unit";"Zergling";"Larva";583;1
"Unit";"Zergling";"Larva";583;1
"Unit";"Zergling";"Larva";583;1
"Unit";"Zergling";"Larva";583;1
"Unit";"Zergling";"Larva";583;1
"Unit";"Zergling";"Larva";583;1
"Unit";"Zergling";"Larva";583;1
"Unit";"Zergling";"Larva";583;1
"Unit";"Zergling";"Larva";583;1
"Unit";"Zergling";"Larva";583;1
"Unit";"Zergling";"Larva";583;1
"Unit";"Zergling";"Larva";583;1
"Unit";"Zergling";"Larva";583;1
"Unit";"Zergling";"Larva";583;1
"Unit";"Zergling";"Larva";583;1
"Unit";"Zergling";"Larva";583;1
"Unit";"Zergling";"Larva";583;1
"Unit";"Zergling";"Larva";583;1
"Unit";"Zergling";"Larva";583;1
"Unit";"Zergling";"Larva";583;1
"Unit";"Zergling";"Larva";583;1
"Unit";"Zergling";"Larva";583;1
"Unit";"Baneling";"Zergling";583;0
"Unit";"Baneling";"Zergling";583;0
"Unit";"Baneling";"Zergling";583;0
"Unit";"Baneling";"Zergling";583;0
"Building";"Extractor";NA;583;0
"Unit";"Baneling";"Zergling";583;0
"Building";"CreepTumor";NA;583;0
"Building";"CreepTumor";NA;583;0
"Building";"CreepTumor";NA;583;0
"Building";"CreepTumor";NA;625;0
"Building";"CreepTumor";NA;625;0
"Building";"CreepTumor";NA;625;0
"Building";"CreepTumor";NA;683;0
"Upgrade";"ZergMeleeWeaponsLevel3";"EvolutionChamber";562;0
"Building";"CreepTumor";NA;683;0
"Building";"CreepTumor";NA;683;0
"Building";"CreepTumor";NA;683;0
"Building";"CreepTumor";NA;683;0
"Building";"SporeCrawler";NA;683;0
"Unit";"Baneling";"Zergling";683;0
"Unit";"Baneling";"Zergling";683;0
"Unit";"Baneling";"Zergling";683;0
"Unit";"Baneling";"Zergling";683;0
"Unit";"Baneling";"Zergling";683;0
"Unit";"Baneling";"Zergling";683;0
"Unit";"Baneling";"Zergling";683;0
"Unit";"Baneling";"Zergling";683;0
"Unit";"Baneling";"Zergling";683;0
"Unit";"Baneling";"Zergling";683;0
"Unit";"Baneling";"Zergling";683;0
"Unit";"Baneling";"Zergling";683;0
"Unit";"Baneling";"Zergling";683;0
"Unit";"Baneling";"Zergling";683;0
"Unit";"Queen";"Hatchery";683;2
"Unit";"Queen";"Hatchery";683;2
"Building";"SpineCrawler";NA;683;0
"Building";"SpineCrawler";NA;683;0
"Building";"SpineCrawler";NA;683;0
