"type";"unit_name";"on_building";"total_supply";"supply"
"Unit";"Overlord";"Larva";12;0
"Building";"Extractor";NA;17;0
"Building";"SpawningPool";NA;19;0
"Building";"Hatchery";NA;17;0
"Unit";"Zergling";"Larva";23;1
"Unit";"Zergling";"Larva";23;1
"Unit";"Zergling";"Larva";23;1
"Unit";"Zergling";"Larva";23;1
"Unit";"Queen";"Hatchery";23;2
"Unit";"Queen";"Hatchery";23;2
"Unit";"Overlord";"Larva";23;0
"Unit";"Overlord";"Larva";27;0
"Building";"CreepTumorQueen";NA;36;0
"Building";"CreepTumorQueen";NA;36;0
"Building";"Hatchery";NA;23;0
"Unit";"Queen";"Hatchery";31;2
"Unit";"Queen";"Hatchery";31;2
"Unit";"Overlord";"Larva";38;0
"Building";"CreepTumor";NA;43;0
"Unit";"Zergling";"Larva";43;1
"Unit";"Zergling";"Larva";43;1
"Unit";"Zergling";"Larva";43;1
"Unit";"Zergling";"Larva";43;1
"Unit";"Zergling";"Larva";43;1
"Unit";"Zergling";"Larva";43;1
"Unit";"Zergling";"Larva";43;1
"Unit";"Zergling";"Larva";43;1
"Unit";"Queen";"Hatchery";41;2
"Unit";"Queen";"Hatchery";41;2
"Unit";"Queen";"Hatchery";41;2
"Building";"CreepTumor";NA;49;0
"Unit";"Zergling";"Larva";57;1
"Unit";"Zergling";"Larva";57;1
"Building";"CreepTumorQueen";NA;63;0
"Unit";"Zergling";"Larva";59;1
"Unit";"Zergling";"Larva";59;1
"Unit";"Zergling";"Larva";59;1
"Unit";"Zergling";"Larva";59;1
"Unit";"Zergling";"Larva";59;1
"Unit";"Zergling";"Larva";59;1
"Unit";"Zergling";"Larva";61;1
"Unit";"Zergling";"Larva";61;1
"Unit";"Overlord";"Larva";63;0
"Unit";"Overlord";"Larva";63;0
"Building";"CreepTumorQueen";NA;73;0
"Unit";"Zergling";"Larva";73;1
"Unit";"Zergling";"Larva";73;1
"Unit";"Zergling";"Larva";73;1
"Unit";"Zergling";"Larva";73;1
"Unit";"Zergling";"Larva";73;1
"Unit";"Zergling";"Larva";73;1
"Unit";"Zergling";"Larva";73;1
"Unit";"Zergling";"Larva";73;1
"Unit";"Zergling";"Larva";73;1
"Unit";"Zergling";"Larva";73;1
"Unit";"Zergling";"Larva";73;1
"Unit";"Zergling";"Larva";73;1
"Unit";"Zergling";"Larva";73;1
"Unit";"Zergling";"Larva";73;1
"Unit";"Zergling";"Larva";73;1
"Unit";"Zergling";"Larva";73;1
"Unit";"Zergling";"Larva";73;1
"Unit";"Zergling";"Larva";73;1
"Building";"CreepTumor";NA;73;0
"Building";"CreepTumor";NA;73;0
"Building";"CreepTumor";NA;73;0
"Unit";"Queen";"Hatchery";73;2
"Unit";"Queen";"Hatchery";73;2
"Unit";"Queen";"Hatchery";73;2
"Unit";"Zergling";"Larva";91;1
"Unit";"Zergling";"Larva";91;1
"Unit";"Zergling";"Larva";91;1
"Unit";"Zergling";"Larva";91;1
"Unit";"Zergling";"Larva";91;1
"Unit";"Zergling";"Larva";91;1
"Unit";"Overlord";"Larva";91;0
"Unit";"Overlord";"Larva";91;0
"Unit";"Overlord";"Larva";95;0
"Building";"CreepTumor";NA;95;0
"Building";"CreepTumor";NA;97;0
"Building";"CreepTumor";NA;97;0
"Unit";"Zergling";"Larva";97;1
"Unit";"Zergling";"Larva";97;1
"Building";"CreepTumor";NA;103;0
"Unit";"Zergling";"Larva";103;1
"Unit";"Zergling";"Larva";103;1
"Unit";"Zergling";"Larva";103;1
"Unit";"Zergling";"Larva";103;1
"Unit";"Zergling";"Larva";103;1
"Unit";"Zergling";"Larva";103;1
"Unit";"Zergling";"Larva";103;1
"Unit";"Zergling";"Larva";103;1
"Unit";"Zergling";"Larva";103;1
"Unit";"Zergling";"Larva";103;1
"Unit";"Zergling";"Larva";105;1
"Unit";"Zergling";"Larva";105;1
"Unit";"Zergling";"Larva";105;1
"Unit";"Zergling";"Larva";105;1
"Unit";"Zergling";"Larva";105;1
"Unit";"Zergling";"Larva";105;1
"Unit";"Queen";"Hatchery";103;2
"Unit";"Queen";"Hatchery";103;2
"Unit";"Queen";"Hatchery";103;2
"Unit";"Zergling";"Larva";121;1
"Unit";"Zergling";"Larva";121;1
"Unit";"Zergling";"Larva";121;1
"Unit";"Zergling";"Larva";121;1
"Unit";"Zergling";"Larva";121;1
"Unit";"Zergling";"Larva";121;1
"Unit";"Zergling";"Larva";121;1
"Unit";"Zergling";"Larva";121;1
"Unit";"Zergling";"Larva";121;1
"Unit";"Zergling";"Larva";121;1
"Unit";"Zergling";"Larva";121;1
"Unit";"Zergling";"Larva";121;1
"Unit";"Zergling";"Larva";121;1
"Unit";"Zergling";"Larva";121;1
"Building";"CreepTumor";NA;127;0
"Building";"CreepTumorQueen";NA;127;0
"Unit";"Zergling";"Larva";127;1
"Unit";"Zergling";"Larva";127;1
"Unit";"Zergling";"Larva";127;1
"Unit";"Zergling";"Larva";127;1
"Unit";"Zergling";"Larva";127;1
"Unit";"Zergling";"Larva";127;1
"Unit";"Zergling";"Larva";127;1
"Unit";"Zergling";"Larva";127;1
"Unit";"Zergling";"Larva";141;1
"Unit";"Zergling";"Larva";141;1
"Unit";"Zergling";"Larva";141;1
"Unit";"Zergling";"Larva";141;1
"Unit";"Zergling";"Larva";141;1
"Unit";"Zergling";"Larva";141;1
"Unit";"Queen";"Hatchery";141;2
"Unit";"Queen";"Hatchery";141;2
"Unit";"Queen";"Hatchery";141;2
"Unit";"Zergling";"Larva";149;1
"Unit";"Zergling";"Larva";149;1
"Unit";"Zergling";"Larva";149;1
"Unit";"Zergling";"Larva";149;1
"Unit";"Zergling";"Larva";149;1
"Unit";"Zergling";"Larva";149;1
"Building";"CreepTumor";NA;155;0
"Building";"Extractor";NA;149;0
"Unit";"Zergling";"Larva";155;1
"Unit";"Zergling";"Larva";155;1
"Unit";"Zergling";"Larva";155;1
"Unit";"Zergling";"Larva";155;1
"Building";"CreepTumor";NA;155;0
"Building";"CreepTumor";NA;155;0
"Building";"EvolutionChamber";NA;149;0
"Building";"CreepTumor";NA;155;0
"Building";"EvolutionChamber";NA;149;0
"Unit";"Zergling";"Larva";159;1
"Unit";"Zergling";"Larva";159;1
"Unit";"Zergling";"Larva";161;1
"Unit";"Zergling";"Larva";161;1
"Unit";"Zergling";"Larva";161;1
"Unit";"Zergling";"Larva";161;1
"Unit";"Zergling";"Larva";161;1
"Unit";"Zergling";"Larva";161;1
"Unit";"Zergling";"Larva";161;1
"Unit";"Zergling";"Larva";161;1
"Unit";"Zergling";"Larva";161;1
"Unit";"Zergling";"Larva";161;1
"Unit";"Zergling";"Larva";161;1
"Unit";"Zergling";"Larva";161;1
"Unit";"Zergling";"Larva";161;1
"Unit";"Zergling";"Larva";161;1
"Unit";"Zergling";"Larva";161;1
"Unit";"Zergling";"Larva";161;1
"Unit";"Overlord";"Larva";167;0
"Unit";"Overlord";"Larva";167;0
"Unit";"Queen";"Hatchery";155;2
"Unit";"Queen";"Hatchery";157;2
"Building";"Hatchery";NA;141;0
"Building";"CreepTumor";NA;189;0
"Unit";"Overlord";"Larva";189;0
"Unit";"Overlord";"Larva";189;0
"Unit";"Zergling";"Larva";189;1
"Unit";"Zergling";"Larva";189;1
"Unit";"Zergling";"Larva";189;1
"Unit";"Zergling";"Larva";189;1
"Unit";"Zergling";"Larva";189;1
"Unit";"Zergling";"Larva";189;1
"Building";"CreepTumor";NA;193;0
"Unit";"Queen";"Hatchery";189;2
"Unit";"Zergling";"Larva";193;1
"Unit";"Zergling";"Larva";193;1
"Unit";"Zergling";"Larva";193;1
"Unit";"Zergling";"Larva";193;1
"Unit";"Zergling";"Larva";193;1
"Unit";"Zergling";"Larva";193;1
"Unit";"Zergling";"Larva";193;1
"Unit";"Zergling";"Larva";193;1
"Unit";"Zergling";"Larva";193;1
"Unit";"Zergling";"Larva";193;1
"Unit";"Zergling";"Larva";193;1
"Unit";"Zergling";"Larva";193;1
"Unit";"Zergling";"Larva";193;1
"Unit";"Zergling";"Larva";193;1
"Unit";"Zergling";"Larva";201;1
"Unit";"Zergling";"Larva";201;1
"Unit";"Zergling";"Larva";201;1
"Unit";"Zergling";"Larva";201;1
"Unit";"Zergling";"Larva";201;1
"Unit";"Zergling";"Larva";201;1
"Unit";"Zergling";"Larva";201;1
"Unit";"Zergling";"Larva";201;1
"Unit";"Zergling";"Larva";201;1
"Unit";"Zergling";"Larva";201;1
"Unit";"Zergling";"Larva";201;1
"Unit";"Zergling";"Larva";201;1
