"type";"unit_name";"on_building";"total_supply";"supply"
"Unit";"Overlord";"Larva";13;0
"Building";"SpawningPool";NA;19;0
"Building";"Hatchery";NA;17;0
"Unit";"Zergling";"Larva";23;1
"Unit";"Zergling";"Larva";23;1
"Unit";"Zergling";"Larva";23;1
"Unit";"Zergling";"Larva";23;1
"Unit";"Queen";"Hatchery";20;2
"Unit";"Queen";"Hatchery";23;2
"Unit";"Overlord";"Larva";23;0
"Unit";"Overlord";"Larva";33;0
"Building";"Hatchery";NA;20;0
"Building";"CreepTumorQueen";NA;33;0
"Unit";"Queen";"Hatchery";33;2
"Unit";"Queen";"Hatchery";33;2
"Building";"Extractor";NA;33;0
"Building";"Extractor";NA;33;0
"Building";"CreepTumorQueen";NA;43;0
"Building";"CreepTumorQueen";NA;43;0
"Building";"CreepTumor";NA;43;0
"Unit";"Overlord";"Larva";54;0
"Unit";"Overlord";"Larva";56;0
"Unit";"Queen";"Hatchery";47;2
"Building";"CreepTumor";NA;57;0
"Building";"CreepTumor";NA;57;0
"Building";"CreepTumorQueen";NA;57;0
"Building";"CreepTumorQueen";NA;59;0
"Unit";"Zergling";"Larva";59;1
"Unit";"Zergling";"Larva";59;1
"Unit";"Zergling";"Larva";59;1
"Unit";"Zergling";"Larva";59;1
"Unit";"Zergling";"Larva";59;1
"Unit";"Zergling";"Larva";59;1
"Building";"CreepTumor";NA;74;0
"Unit";"Queen";"Hatchery";59;2
"Building";"CreepTumor";NA;74;0
"Unit";"Queen";"Hatchery";67;2
"Unit";"Overlord";"Larva";74;0
"Building";"CreepTumorQueen";NA;74;0
"Unit";"Overlord";"Larva";74;0
"Unit";"Overlord";"Larva";74;0
"Building";"CreepTumor";NA;74;0
"Building";"CreepTumorQueen";NA;74;0
"Building";"CreepTumorQueen";NA;74;0
"Unit";"Overlord";"Larva";74;0
"Unit";"Overlord";"Larva";74;0
"Unit";"Overlord";"Larva";74;0
"Unit";"Overlord";"Larva";74;0
"Building";"CreepTumor";NA;76;0
"Unit";"Overlord";"Larva";78;0
"Building";"CreepTumor";NA;78;0
"Building";"CreepTumor";NA;78;0
"Building";"EvolutionChamber";NA;78;0
"Building";"CreepTumor";NA;79;0
"Building";"EvolutionChamber";NA;78;0
"Building";"CreepTumor";NA;85;0
"Building";"CreepTumor";NA;85;0
"Building";"CreepTumor";NA;85;0
"Building";"CreepTumorQueen";NA;85;0
"Unit";"Overlord";"Larva";85;0
"Unit";"Zergling";"Larva";85;1
"Unit";"Zergling";"Larva";85;1
"Unit";"Zergling";"Larva";85;1
"Unit";"Zergling";"Larva";85;1
"Unit";"Zergling";"Larva";85;1
"Unit";"Zergling";"Larva";85;1
"Unit";"Zergling";"Larva";85;1
"Unit";"Zergling";"Larva";85;1
"Building";"BanelingNest";NA;78;0
"Building";"Extractor";NA;85;0
"Building";"Extractor";NA;85;0
"Building";"Extractor";NA;85;0
"Building";"Extractor";NA;85;0
"Building";"CreepTumor";NA;103;0
"Building";"CreepTumor";NA;103;0
"Building";"CreepTumor";NA;103;0
"Building";"CreepTumor";NA;103;0
"Building";"CreepTumor";NA;103;0
"Unit";"Zergling";"Larva";103;1
"Unit";"Zergling";"Larva";103;1
"Unit";"Zergling";"Larva";104;1
"Unit";"Zergling";"Larva";104;1
"Unit";"Zergling";"Larva";104;1
"Unit";"Zergling";"Larva";104;1
"Unit";"Zergling";"Larva";104;1
"Unit";"Zergling";"Larva";104;1
"Unit";"Zergling";"Larva";108;1
"Unit";"Zergling";"Larva";108;1
"Building";"HydraliskDen";NA;113;0
"Building";"CreepTumor";NA;121;0
"Building";"CreepTumor";NA;123;0
"Building";"CreepTumor";NA;123;0
"Unit";"Overlord";"Larva";113;0
"Unit";"Baneling";"Zergling";123;0
"Unit";"Baneling";"Zergling";123;0
"Unit";"Baneling";"Zergling";123;0
"Unit";"Baneling";"Zergling";123;0
"Unit";"Baneling";"Zergling";123;0
"Unit";"Baneling";"Zergling";123;0
"Unit";"Baneling";"Zergling";123;0
"Unit";"Baneling";"Zergling";123;0
"Unit";"Baneling";"Zergling";123;0
"Unit";"Baneling";"Zergling";123;0
"Unit";"Baneling";"Zergling";123;0
"Unit";"Baneling";"Zergling";123;0
"Unit";"Baneling";"Zergling";123;0
"Unit";"Baneling";"Zergling";123;0
"Unit";"Baneling";"Zergling";123;0
"Unit";"Baneling";"Zergling";123;0
"Unit";"Baneling";"Zergling";123;0
"Unit";"Baneling";"Zergling";123;0
"Unit";"Baneling";"Zergling";123;0
"Unit";"Baneling";"Zergling";123;0
"Unit";"Zergling";"Larva";123;1
"Unit";"Zergling";"Larva";123;1
"Unit";"Zergling";"Larva";123;1
"Unit";"Zergling";"Larva";123;1
"Unit";"Zergling";"Larva";123;1
"Unit";"Zergling";"Larva";123;1
"Unit";"Zergling";"Larva";123;1
"Unit";"Zergling";"Larva";123;1
"Unit";"Zergling";"Larva";123;1
"Unit";"Zergling";"Larva";123;1
"Unit";"Zergling";"Larva";123;1
"Unit";"Zergling";"Larva";123;1
"Unit";"Zergling";"Larva";123;1
"Unit";"Zergling";"Larva";123;1
"Unit";"Zergling";"Larva";123;1
"Unit";"Zergling";"Larva";123;1
"Unit";"Zergling";"Larva";123;1
"Unit";"Zergling";"Larva";123;1
"Unit";"Zergling";"Larva";123;1
"Unit";"Zergling";"Larva";123;1
"Unit";"Zergling";"Larva";123;1
"Unit";"Zergling";"Larva";123;1
"Unit";"Zergling";"Larva";123;1
"Unit";"Zergling";"Larva";123;1
"Building";"Hatchery";NA;103;0
"Building";"CreepTumor";NA;123;0
"Building";"CreepTumor";NA;123;0
"Building";"CreepTumor";NA;127;0
"Building";"CreepTumorQueen";NA;141;0
"Building";"CreepTumorQueen";NA;147;0
"Building";"CreepTumor";NA;141;0
"Building";"CreepTumorQueen";NA;147;0
"Unit";"Overlord";"Larva";147;0
"Unit";"Hydralisk";"Larva";147;2
"Unit";"Hydralisk";"Larva";147;2
"Upgrade";"ZergMeleeWeaponsLevel1";"EvolutionChamber";113;0
"Unit";"Hydralisk";"Larva";147;2
"Unit";"Hydralisk";"Larva";147;2
"Upgrade";"ZergGroundArmorsLevel1";"EvolutionChamber";113;0
"Unit";"Hydralisk";"Larva";147;2
"Unit";"Zergling";"Larva";153;1
"Unit";"Zergling";"Larva";153;1
"Unit";"Zergling";"Larva";153;1
"Unit";"Zergling";"Larva";153;1
"Unit";"Zergling";"Larva";153;1
"Unit";"Zergling";"Larva";153;1
"Unit";"Zergling";"Larva";153;1
"Unit";"Zergling";"Larva";153;1
"Unit";"Hydralisk";"Larva";148;2
"Unit";"Hydralisk";"Larva";148;2
"Unit";"Hydralisk";"Larva";151;2
"Unit";"Hydralisk";"Larva";153;2
"Unit";"Hydralisk";"Larva";153;2
"Unit";"Hydralisk";"Larva";153;2
"Building";"CreepTumor";NA;163;0
"Unit";"Overlord";"Larva";163;0
"Building";"CreepTumor";NA;171;0
"Building";"CreepTumor";NA;171;0
"Building";"CreepTumor";NA;171;0
"Building";"CreepTumorQueen";NA;186;0
"Building";"CreepTumorQueen";NA;186;0
"Unit";"Overlord";"Larva";186;0
"Unit";"Overlord";"Larva";186;0
"Unit";"Overlord";"Larva";186;0
"Unit";"Zergling";"Larva";186;1
"Unit";"Zergling";"Larva";186;1
"Unit";"Overlord";"Larva";186;0
"Unit";"Zergling";"Larva";186;1
"Unit";"Zergling";"Larva";186;1
"Unit";"Zergling";"Larva";186;1
"Unit";"Zergling";"Larva";186;1
"Upgrade";"EvolveGroovedSpines";"HydraliskDen";153;0
"Unit";"Hydralisk";"Larva";186;2
"Unit";"Hydralisk";"Larva";186;2
"Unit";"Hydralisk";"Larva";186;2
"Building";"CreepTumor";NA;192;0
"Unit";"Zergling";"Larva";198;1
"Unit";"Zergling";"Larva";198;1
"Unit";"Overlord";"Larva";194;0
"Unit";"Zergling";"Larva";198;1
"Unit";"Zergling";"Larva";198;1
"Unit";"Zergling";"Larva";198;1
"Unit";"Zergling";"Larva";198;1
"Unit";"Zergling";"Larva";198;1
"Unit";"Zergling";"Larva";198;1
"Unit";"Zergling";"Larva";198;1
"Unit";"Zergling";"Larva";198;1
"Unit";"Hydralisk";"Larva";188;2
"Unit";"Hydralisk";"Larva";188;2
"Building";"Extractor";NA;198;0
"Building";"Extractor";NA;198;0
"Unit";"Baneling";"Zergling";208;0
"Unit";"Baneling";"Zergling";208;0
"Unit";"Baneling";"Zergling";208;0
"Unit";"Baneling";"Zergling";208;0
"Unit";"Baneling";"Zergling";208;0
"Unit";"Baneling";"Zergling";208;0
"Unit";"Baneling";"Zergling";208;0
"Unit";"Baneling";"Zergling";208;0
"Unit";"Baneling";"Zergling";208;0
"Unit";"Baneling";"Zergling";212;0
"Unit";"Zergling";"Larva";204;1
"Unit";"Zergling";"Larva";204;1
"Unit";"Zergling";"Larva";208;1
"Unit";"Zergling";"Larva";208;1
"Unit";"Zergling";"Larva";208;1
"Unit";"Zergling";"Larva";208;1
"Unit";"Zergling";"Larva";208;1
"Unit";"Zergling";"Larva";208;1
"Unit";"Zergling";"Larva";208;1
"Unit";"Zergling";"Larva";208;1
"Building";"CreepTumorQueen";NA;212;0
"Building";"CreepTumorQueen";NA;212;0
"Building";"CreepTumorQueen";NA;212;0
"Building";"CreepTumorQueen";NA;212;0
"Unit";"Hydralisk";"Larva";198;2
"Unit";"Hydralisk";"Larva";198;2
"Unit";"Hydralisk";"Larva";198;2
"Unit";"Hydralisk";"Larva";198;2
"Unit";"Hydralisk";"Larva";198;2
"Unit";"Hydralisk";"Larva";198;2
"Unit";"Hydralisk";"Larva";198;2
"Unit";"Zergling";"Larva";212;1
"Unit";"Zergling";"Larva";212;1
"Unit";"Zergling";"Larva";212;1
"Unit";"Zergling";"Larva";212;1
"Unit";"Zergling";"Larva";212;1
"Unit";"Zergling";"Larva";212;1
"Unit";"Zergling";"Larva";212;1
"Unit";"Zergling";"Larva";212;1
"Unit";"Zergling";"Larva";212;1
"Unit";"Zergling";"Larva";212;1
"Unit";"Zergling";"Larva";214;1
"Unit";"Zergling";"Larva";214;1
"Unit";"Zergling";"Larva";236;1
"Unit";"Zergling";"Larva";236;1
"Unit";"Zergling";"Larva";236;1
"Unit";"Zergling";"Larva";236;1
"Unit";"Zergling";"Larva";236;1
"Unit";"Zergling";"Larva";236;1
"Unit";"Zergling";"Larva";236;1
"Unit";"Zergling";"Larva";236;1
"Unit";"Zergling";"Larva";236;1
"Unit";"Zergling";"Larva";236;1
"Unit";"Zergling";"Larva";236;1
"Unit";"Zergling";"Larva";236;1
"Unit";"Zergling";"Larva";236;1
"Unit";"Zergling";"Larva";236;1
"Unit";"Zergling";"Larva";236;1
"Unit";"Zergling";"Larva";236;1
"Unit";"Zergling";"Larva";236;1
"Unit";"Zergling";"Larva";236;1
"Building";"CreepTumor";NA;248;0
"Building";"Hatchery";NA;198;0
"Unit";"Hydralisk";"Larva";248;2
"Unit";"Hydralisk";"Larva";248;2
"Unit";"Hydralisk";"Larva";248;2
"Building";"CreepTumor";NA;269;0
"Building";"CreepTumor";NA;269;0
"Building";"CreepTumor";NA;269;0
"Building";"CreepTumor";NA;269;0
"Building";"CreepTumorQueen";NA;271;0
"Building";"CreepTumorQueen";NA;273;0
"Upgrade";"ZergMeleeWeaponsLevel2";"EvolutionChamber";186;0
"Building";"InfestationPit";NA;248;0
"Building";"Hatchery";NA;212;0
"Upgrade";"EvolveMuscularAugments";"HydraliskDen";236;0
"Unit";"Zergling";"Larva";275;1
"Unit";"Zergling";"Larva";275;1
"Unit";"Zergling";"Larva";275;1
"Unit";"Zergling";"Larva";275;1
"Unit";"Zergling";"Larva";275;1
"Unit";"Zergling";"Larva";275;1
"Unit";"Zergling";"Larva";275;1
"Unit";"Zergling";"Larva";275;1
"Unit";"Zergling";"Larva";275;1
"Unit";"Zergling";"Larva";275;1
"Unit";"Zergling";"Larva";275;1
"Unit";"Zergling";"Larva";275;1
"Unit";"Zergling";"Larva";275;1
"Unit";"Zergling";"Larva";275;1
"Unit";"Zergling";"Larva";275;1
"Unit";"Zergling";"Larva";275;1
"Unit";"Zergling";"Larva";275;1
"Unit";"Zergling";"Larva";275;1
"Unit";"Zergling";"Larva";275;1
"Unit";"Zergling";"Larva";275;1
"Building";"CreepTumorQueen";NA;275;0
"Building";"CreepTumorQueen";NA;275;0
"Upgrade";"ZergGroundArmorsLevel2";"EvolutionChamber";198;0
"Building";"CreepTumor";NA;275;0
"Unit";"Queen";"Hatchery";275;2
"Unit";"Queen";"Hatchery";275;2
"Unit";"Hydralisk";"Larva";295;2
"Unit";"Hydralisk";"Larva";295;2
"Building";"CreepTumor";NA;298;0
"Building";"CreepTumor";NA;300;0
"Building";"CreepTumor";NA;300;0
"Unit";"Hydralisk";"Larva";298;2
"Unit";"Hydralisk";"Larva";298;2
"Unit";"Hydralisk";"Larva";298;2
"Unit";"Hydralisk";"Larva";298;2
"Unit";"Baneling";"Zergling";302;0
"Unit";"Baneling";"Zergling";302;0
"Unit";"Baneling";"Zergling";302;0
"Unit";"Baneling";"Zergling";302;0
"Unit";"Baneling";"Zergling";302;0
"Unit";"Baneling";"Zergling";302;0
"Unit";"Baneling";"Zergling";302;0
"Unit";"Baneling";"Zergling";302;0
"Unit";"Baneling";"Zergling";302;0
"Unit";"Baneling";"Zergling";302;0
"Unit";"Baneling";"Zergling";302;0
"Unit";"Baneling";"Zergling";302;0
"Unit";"Baneling";"Zergling";302;0
"Unit";"Baneling";"Zergling";302;0
"Unit";"Baneling";"Zergling";302;0
"Unit";"Baneling";"Zergling";302;0
"Unit";"Baneling";"Zergling";302;0
"Unit";"Baneling";"Zergling";302;0
"Unit";"Baneling";"Zergling";302;0
"Unit";"Baneling";"Zergling";302;0
"Unit";"Baneling";"Zergling";302;0
"Unit";"Baneling";"Zergling";302;0
"Unit";"Baneling";"Zergling";302;0
"Unit";"Baneling";"Zergling";302;0
"Unit";"Baneling";"Zergling";302;0
"Unit";"Baneling";"Zergling";302;0
"Unit";"Zergling";"Larva";314;1
"Unit";"Zergling";"Larva";314;1
"Unit";"Zergling";"Larva";314;1
"Unit";"Zergling";"Larva";314;1
"Unit";"Zergling";"Larva";314;1
"Unit";"Zergling";"Larva";314;1
"Unit";"Zergling";"Larva";314;1
"Unit";"Zergling";"Larva";314;1
"Unit";"Zergling";"Larva";314;1
"Unit";"Zergling";"Larva";314;1
"Unit";"Zergling";"Larva";314;1
"Unit";"Zergling";"Larva";314;1
"Unit";"Zergling";"Larva";314;1
"Unit";"Zergling";"Larva";314;1
"Unit";"Zergling";"Larva";314;1
"Unit";"Zergling";"Larva";314;1
"Unit";"Zergling";"Larva";314;1
"Unit";"Zergling";"Larva";314;1
"Unit";"Zergling";"Larva";314;1
"Unit";"Zergling";"Larva";314;1
"Building";"EvolutionChamber";NA;306;0
"Building";"EvolutionChamber";NA;306;0
"Building";"CreepTumor";NA;314;0
"Building";"CreepTumor";NA;314;0
"Building";"CreepTumor";NA;314;0
"Building";"CreepTumor";NA;314;0
"Building";"CreepTumorQueen";NA;314;0
"Building";"CreepTumor";NA;314;0
"Building";"CreepTumorQueen";NA;334;0
"Building";"CreepTumor";NA;326;0
"Building";"CreepTumorQueen";NA;334;0
"Building";"CreepTumorQueen";NA;334;0
"Building";"CreepTumorQueen";NA;334;0
"Building";"CreepTumorQueen";NA;334;0
"Building";"CreepTumorQueen";NA;334;0
"Building";"CreepTumorQueen";NA;334;0
"Building";"Extractor";NA;334;0
"Building";"Extractor";NA;334;0
"Building";"CreepTumorQueen";NA;334;0
"Building";"CreepTumorQueen";NA;334;0
"Unit";"Overlord";"Larva";334;0
"Building";"CreepTumor";NA;334;0
"Building";"CreepTumorQueen";NA;334;0
"Building";"CreepTumorQueen";NA;334;0
"Building";"CreepTumor";NA;334;0
"Building";"CreepTumor";NA;334;0
"Building";"CreepTumorQueen";NA;334;0
"Building";"CreepTumor";NA;334;0
"Building";"CreepTumor";NA;334;0
"Building";"CreepTumor";NA;334;0
"Building";"CreepTumor";NA;334;0
"Building";"CreepTumor";NA;334;0
"Building";"CreepTumor";NA;340;0
"Building";"CreepTumor";NA;340;0
"Building";"CreepTumor";NA;341;0
"Building";"Spire";NA;314;0
"Building";"CreepTumor";NA;341;0
"Unit";"Zergling";"Larva";341;1
"Unit";"Zergling";"Larva";341;1
"Unit";"Zergling";"Larva";341;1
"Unit";"Zergling";"Larva";341;1
"Unit";"Zergling";"Larva";341;1
"Unit";"Zergling";"Larva";341;1
"Unit";"Zergling";"Larva";341;1
"Unit";"Zergling";"Larva";341;1
"Unit";"Zergling";"Larva";341;1
"Unit";"Zergling";"Larva";341;1
"Unit";"Zergling";"Larva";341;1
"Unit";"Zergling";"Larva";341;1
"Unit";"Zergling";"Larva";341;1
"Unit";"Zergling";"Larva";341;1
"Unit";"Zergling";"Larva";341;1
"Unit";"Zergling";"Larva";341;1
"Unit";"Zergling";"Larva";341;1
"Unit";"Zergling";"Larva";341;1
"Unit";"Zergling";"Larva";341;1
"Unit";"Zergling";"Larva";341;1
"Unit";"Zergling";"Larva";341;1
"Unit";"Zergling";"Larva";341;1
"Unit";"Zergling";"Larva";341;1
"Unit";"Zergling";"Larva";341;1
"Unit";"Hydralisk";"Larva";341;2
"Unit";"Hydralisk";"Larva";341;2
"Unit";"Hydralisk";"Larva";341;2
"Unit";"Zergling";"Larva";341;1
"Unit";"Zergling";"Larva";341;1
"Unit";"Zergling";"Larva";341;1
"Unit";"Zergling";"Larva";341;1
"Unit";"Zergling";"Larva";341;1
"Unit";"Zergling";"Larva";341;1
"Unit";"Zergling";"Larva";341;1
"Unit";"Zergling";"Larva";341;1
"Unit";"Zergling";"Larva";341;1
"Unit";"Zergling";"Larva";341;1
"Unit";"Zergling";"Larva";341;1
"Unit";"Zergling";"Larva";341;1
"Unit";"Zergling";"Larva";341;1
"Unit";"Zergling";"Larva";341;1
"Unit";"Zergling";"Larva";341;1
"Unit";"Zergling";"Larva";341;1
"Unit";"Zergling";"Larva";341;1
"Unit";"Zergling";"Larva";341;1
"Unit";"Zergling";"Larva";341;1
"Unit";"Zergling";"Larva";341;1
"Unit";"Zergling";"Larva";341;1
"Unit";"Zergling";"Larva";341;1
"Unit";"Zergling";"Larva";341;1
"Unit";"Zergling";"Larva";341;1
"Unit";"Zergling";"Larva";341;1
"Unit";"Zergling";"Larva";341;1
"Unit";"Zergling";"Larva";341;1
"Unit";"Zergling";"Larva";341;1
"Unit";"Zergling";"Larva";341;1
"Unit";"Zergling";"Larva";341;1
"Unit";"Zergling";"Larva";341;1
"Unit";"Zergling";"Larva";341;1
"Unit";"Zergling";"Larva";341;1
"Unit";"Zergling";"Larva";341;1
"Unit";"Zergling";"Larva";341;1
"Unit";"Zergling";"Larva";341;1
"Unit";"Zergling";"Larva";341;1
"Unit";"Zergling";"Larva";341;1
"Unit";"Zergling";"Larva";341;1
"Unit";"Zergling";"Larva";341;1
"Unit";"Zergling";"Larva";341;1
"Unit";"Zergling";"Larva";341;1
"Unit";"Zergling";"Larva";341;1
"Unit";"Zergling";"Larva";341;1
"Unit";"Zergling";"Larva";341;1
"Unit";"Zergling";"Larva";341;1
"Unit";"Zergling";"Larva";341;1
"Unit";"Zergling";"Larva";341;1
"Unit";"Zergling";"Larva";341;1
"Unit";"Zergling";"Larva";341;1
"Unit";"Zergling";"Larva";341;1
"Unit";"Zergling";"Larva";341;1
"Unit";"Zergling";"Larva";341;1
"Unit";"Zergling";"Larva";341;1
"Unit";"Zergling";"Larva";341;1
"Unit";"Zergling";"Larva";341;1
"Unit";"Zergling";"Larva";341;1
"Unit";"Zergling";"Larva";341;1
"Unit";"Zergling";"Larva";341;1
"Unit";"Zergling";"Larva";341;1
"Unit";"Zergling";"Larva";341;1
"Unit";"Zergling";"Larva";341;1
"Unit";"Zergling";"Larva";341;1
"Unit";"Zergling";"Larva";341;1
"Unit";"Zergling";"Larva";341;1
"Unit";"Zergling";"Larva";341;1
"Unit";"Zergling";"Larva";341;1
"Unit";"Zergling";"Larva";341;1
"Upgrade";"ZergMissileWeaponsLevel1";"EvolutionChamber";334;0
"Building";"CreepTumor";NA;367;0
"Building";"CreepTumor";NA;371;0
"Building";"CreepTumor";NA;371;0
"Building";"CreepTumor";NA;371;0
"Building";"CreepTumor";NA;371;0
"Building";"CreepTumor";NA;371;0
"Building";"CreepTumor";NA;373;0
"Building";"CreepTumor";NA;375;0
"Building";"CreepTumor";NA;375;0
"Building";"CreepTumorQueen";NA;439;0
"Building";"CreepTumor";NA;439;0
"Building";"CreepTumor";NA;439;0
"Building";"CreepTumor";NA;439;0
"Unit";"Baneling";"Zergling";439;0
"Unit";"Baneling";"Zergling";439;0
"Unit";"Hydralisk";"Larva";439;2
"Unit";"Baneling";"Zergling";439;0
"Unit";"Baneling";"Zergling";439;0
"Unit";"Baneling";"Zergling";439;0
"Unit";"Baneling";"Zergling";439;0
"Unit";"Baneling";"Zergling";439;0
"Unit";"Baneling";"Zergling";439;0
"Unit";"Baneling";"Zergling";439;0
"Unit";"Baneling";"Zergling";439;0
"Unit";"Baneling";"Zergling";439;0
"Unit";"Baneling";"Zergling";439;0
"Unit";"Baneling";"Zergling";439;0
"Unit";"Baneling";"Zergling";439;0
"Unit";"Baneling";"Zergling";439;0
"Unit";"Baneling";"Zergling";439;0
"Unit";"Baneling";"Zergling";439;0
"Unit";"Hydralisk";"Larva";439;2
"Unit";"Baneling";"Zergling";439;0
"Unit";"Baneling";"Zergling";439;0
"Unit";"Hydralisk";"Larva";439;2
"Unit";"Hydralisk";"Larva";439;2
"Unit";"Hydralisk";"Larva";439;2
"Unit";"Hydralisk";"Larva";439;2
"Unit";"Hydralisk";"Larva";439;2
"Unit";"Hydralisk";"Larva";439;2
"Unit";"Hydralisk";"Larva";439;2
"Unit";"Hydralisk";"Larva";439;2
"Unit";"Hydralisk";"Larva";439;2
"Unit";"Hydralisk";"Larva";439;2
"Unit";"Hydralisk";"Larva";439;2
"Unit";"Hydralisk";"Larva";439;2
"Unit";"Corruptor";"Larva";439;2
"Unit";"Corruptor";"Larva";439;2
"Unit";"Corruptor";"Larva";439;2
"Unit";"Corruptor";"Larva";439;2
"Unit";"Corruptor";"Larva";439;2
"Unit";"Corruptor";"Larva";439;2
"Unit";"Corruptor";"Larva";471;2
"Unit";"Corruptor";"Larva";471;2
"Building";"UltraliskCavern";NA;439;0
"Building";"CreepTumor";NA;483;0
"Building";"CreepTumor";NA;483;0
"Building";"CreepTumor";NA;483;0
"Building";"CreepTumor";NA;483;0
"Unit";"Zergling";"Larva";483;1
"Unit";"Zergling";"Larva";483;1
"Building";"CreepTumor";NA;483;0
"Unit";"Zergling";"Larva";483;1
"Unit";"Zergling";"Larva";483;1
"Unit";"Zergling";"Larva";483;1
"Unit";"Zergling";"Larva";483;1
"Unit";"Zergling";"Larva";483;1
"Unit";"Zergling";"Larva";483;1
"Unit";"Zergling";"Larva";483;1
"Unit";"Zergling";"Larva";483;1
"Unit";"Zergling";"Larva";483;1
"Unit";"Zergling";"Larva";483;1
"Building";"CreepTumorQueen";NA;483;0
"Building";"CreepTumorQueen";NA;483;0
"Building";"CreepTumor";NA;483;0
"Building";"CreepTumor";NA;483;0
"Unit";"Corruptor";"Larva";483;2
"Unit";"Corruptor";"Larva";483;2
"Building";"CreepTumor";NA;483;0
"Building";"CreepTumor";NA;483;0
"Upgrade";"ZergMeleeWeaponsLevel3";"EvolutionChamber";439;0
"Upgrade";"ZergGroundArmorsLevel3";"EvolutionChamber";439;0
