"type";"unit_name";"on_building";"total_supply";"supply"
"Building";"Extractor";NA;13;0
"Unit";"Overlord";"Larva";15;0
"Building";"SpawningPool";NA;13;0
"Building";"Extractor";NA;16;0
"Unit";"Overlord";"Larva";18;0
"Building";"RoachWarren";NA;16;0
"Unit";"Roach";"Larva";18;2
"Unit";"Roach";"Larva";18;2
"Unit";"Roach";"Larva";18;2
"Unit";"Roach";"Larva";18;2
