"type";"unit_name";"on_building";"total_supply";"supply"
"Unit";"Overlord";"Larva";12;0
"Building";"Extractor";NA;18;0
"Building";"SpawningPool";NA;19;0
"Building";"Hatchery";NA;17;0
"Unit";"Zergling";"Larva";23;1
"Unit";"Zergling";"Larva";23;1
"Unit";"Zergling";"Larva";23;1
"Unit";"Zergling";"Larva";23;1
"Unit";"Overlord";"Larva";23;0
"Unit";"Queen";"Hatchery";23;2
"Building";"Hatchery";NA;22;0
"Unit";"Overlord";"Larva";34;0
"Unit";"Queen";"Hatchery";30;2
"Unit";"Queen";"Hatchery";34;2
"Building";"CreepTumorQueen";NA;40;0
"Unit";"Overlord";"Larva";40;0
"Unit";"Queen";"Hatchery";36;2
"Unit";"Overlord";"Larva";44;0
"Unit";"Queen";"Hatchery";40;2
"Building";"CreepTumorQueen";NA;52;0
"Building";"CreepTumorQueen";NA;52;0
"Building";"Extractor";NA;52;0
"Building";"CreepTumor";NA;52;0
"Unit";"Overlord";"Larva";56;0
"Building";"RoachWarren";NA;46;0
"Unit";"Overlord";"Larva";58;0
"Unit";"Zergling";"Larva";58;1
"Unit";"Zergling";"Larva";58;1
"Unit";"Zergling";"Larva";58;1
"Unit";"Zergling";"Larva";58;1
"Building";"CreepTumor";NA;61;0
"Unit";"Queen";"Hatchery";56;2
"Building";"CreepTumor";NA;61;0
"Building";"SporeCrawler";NA;61;0
"Building";"SporeCrawler";NA;61;0
"Building";"SporeCrawler";NA;61;0
"Unit";"Overlord";"Larva";79;0
"Unit";"Overlord";"Larva";79;0
"Unit";"Overlord";"Larva";79;0
"Unit";"Overlord";"Larva";79;0
"Unit";"Overlord";"Larva";79;0
"Unit";"Overlord";"Larva";79;0
"Building";"EvolutionChamber";NA;83;0
"Building";"EvolutionChamber";NA;83;0
"Unit";"Queen";"Hatchery";83;2
"Building";"BanelingNest";NA;83;0
"Building";"Extractor";NA;87;0
"Building";"Extractor";NA;87;0
"Building";"CreepTumor";NA;97;0
"Building";"CreepTumorQueen";NA;97;0
"Building";"CreepTumor";NA;97;0
"Building";"Extractor";NA;97;0
"Building";"Hatchery";NA;83;0
"Building";"CreepTumor";NA;97;0
"Building";"Extractor";NA;101;0
"Building";"CreepTumor";NA;106;0
"Building";"CreepTumorQueen";NA;116;0
"Unit";"Zergling";"Larva";108;1
"Unit";"Zergling";"Larva";108;1
"Unit";"Zergling";"Larva";108;1
"Unit";"Zergling";"Larva";108;1
"Unit";"Zergling";"Larva";108;1
"Unit";"Zergling";"Larva";108;1
"Unit";"Zergling";"Larva";108;1
"Unit";"Zergling";"Larva";108;1
"Building";"HydraliskDen";NA;102;0
"Building";"CreepTumorQueen";NA;116;0
"Unit";"Zergling";"Larva";116;1
"Unit";"Zergling";"Larva";116;1
"Unit";"Zergling";"Larva";116;1
"Unit";"Zergling";"Larva";116;1
"Unit";"Zergling";"Larva";116;1
"Unit";"Zergling";"Larva";116;1
"Unit";"Zergling";"Larva";116;1
"Unit";"Zergling";"Larva";116;1
"Unit";"Zergling";"Larva";116;1
"Unit";"Zergling";"Larva";116;1
"Building";"CreepTumorQueen";NA;124;0
"Building";"CreepTumorQueen";NA;124;0
"Unit";"Zergling";"Larva";124;1
"Unit";"Zergling";"Larva";124;1
"Unit";"Zergling";"Larva";124;1
"Unit";"Zergling";"Larva";124;1
"Unit";"Zergling";"Larva";124;1
"Unit";"Zergling";"Larva";124;1
"Unit";"Zergling";"Larva";124;1
"Unit";"Zergling";"Larva";124;1
"Unit";"Zergling";"Larva";124;1
"Unit";"Zergling";"Larva";124;1
"Unit";"Zergling";"Larva";124;1
"Unit";"Zergling";"Larva";124;1
"Unit";"Zergling";"Larva";124;1
"Unit";"Zergling";"Larva";124;1
"Unit";"Zergling";"Larva";124;1
"Unit";"Zergling";"Larva";124;1
"Unit";"Zergling";"Larva";124;1
"Unit";"Zergling";"Larva";124;1
"Building";"Extractor";NA;116;0
"Building";"Extractor";NA;124;0
"Building";"CreepTumor";NA;135;0
"Building";"InfestationPit";NA;116;0
"Unit";"Overlord";"Larva";153;0
"Unit";"Overlord";"Larva";153;0
"Unit";"Overlord";"Larva";153;0
"Unit";"Overlord";"Larva";153;0
"Building";"CreepTumor";NA;153;0
"Building";"Hatchery";NA;101;0
"Building";"CreepTumor";NA;153;0
"Unit";"Hydralisk";"Larva";153;2
"Unit";"Hydralisk";"Larva";153;2
"Unit";"Hydralisk";"Larva";153;2
"Unit";"Hydralisk";"Larva";153;2
"Upgrade";"ZergGroundArmorsLevel1";"EvolutionChamber";102;0
"Unit";"Overlord";"Larva";153;0
"Unit";"Overlord";"Larva";153;0
"Unit";"Overlord";"Larva";153;0
"Unit";"Overlord";"Larva";153;0
"Unit";"Zergling";"Larva";153;1
"Unit";"Zergling";"Larva";153;1
"Unit";"Zergling";"Larva";155;1
"Unit";"Zergling";"Larva";155;1
"Unit";"Zergling";"Larva";161;1
"Unit";"Zergling";"Larva";161;1
"Unit";"Zergling";"Larva";161;1
"Unit";"Zergling";"Larva";161;1
"Unit";"Zergling";"Larva";161;1
"Unit";"Zergling";"Larva";161;1
"Unit";"Zergling";"Larva";161;1
"Unit";"Zergling";"Larva";161;1
"Unit";"Zergling";"Larva";161;1
"Unit";"Zergling";"Larva";161;1
"Unit";"Zergling";"Larva";161;1
"Unit";"Zergling";"Larva";161;1
"Unit";"Baneling";"Zergling";161;0
"Unit";"Baneling";"Zergling";161;0
"Unit";"Baneling";"Zergling";161;0
"Unit";"Baneling";"Zergling";161;0
"Unit";"Baneling";"Zergling";161;0
"Unit";"Baneling";"Zergling";161;0
"Unit";"Baneling";"Zergling";161;0
"Unit";"Baneling";"Zergling";161;0
"Upgrade";"Burrow";"Hatchery";135;0
"Unit";"Hydralisk";"Larva";153;2
"Unit";"Hydralisk";"Larva";153;2
"Unit";"Hydralisk";"Larva";153;2
"Unit";"Hydralisk";"Larva";153;2
"Unit";"Hydralisk";"Larva";153;2
"Upgrade";"EvolveMuscularAugments";"HydraliskDen";153;0
"Upgrade";"ZergMeleeWeaponsLevel1";"EvolutionChamber";124;0
"Unit";"Zergling";"Larva";187;1
"Unit";"Zergling";"Larva";187;1
"Unit";"Zergling";"Larva";187;1
"Unit";"Zergling";"Larva";187;1
"Unit";"Zergling";"Larva";187;1
"Unit";"Zergling";"Larva";187;1
"Unit";"Zergling";"Larva";187;1
"Unit";"Zergling";"Larva";187;1
"Unit";"Zergling";"Larva";187;1
"Unit";"Zergling";"Larva";187;1
"Unit";"Zergling";"Larva";187;1
"Unit";"Zergling";"Larva";187;1
"Unit";"Zergling";"Larva";187;1
"Unit";"Zergling";"Larva";187;1
"Unit";"Zergling";"Larva";187;1
"Unit";"Zergling";"Larva";187;1
"Unit";"Zergling";"Larva";187;1
"Unit";"Zergling";"Larva";187;1
"Unit";"Zergling";"Larva";187;1
"Unit";"Zergling";"Larva";187;1
"Unit";"Zergling";"Larva";187;1
"Unit";"Zergling";"Larva";187;1
"Unit";"Zergling";"Larva";187;1
"Unit";"Zergling";"Larva";187;1
"Unit";"Hydralisk";"Larva";187;2
"Unit";"Hydralisk";"Larva";187;2
"Unit";"Hydralisk";"Larva";187;2
"Unit";"Hydralisk";"Larva";187;2
"Building";"CreepTumor";NA;219;0
"Building";"CreepTumor";NA;219;0
"Building";"CreepTumor";NA;219;0
"Building";"CreepTumor";NA;219;0
"Building";"CreepTumor";NA;229;0
"Building";"CreepTumorQueen";NA;229;0
"Unit";"Zergling";"Larva";229;1
"Unit";"Zergling";"Larva";229;1
"Unit";"Zergling";"Larva";229;1
"Unit";"Zergling";"Larva";229;1
"Unit";"Zergling";"Larva";229;1
"Unit";"Zergling";"Larva";229;1
"Unit";"Zergling";"Larva";229;1
"Unit";"Zergling";"Larva";229;1
"Unit";"Zergling";"Larva";229;1
"Unit";"Zergling";"Larva";229;1
"Unit";"Baneling";"Zergling";229;0
"Unit";"Baneling";"Zergling";229;0
"Unit";"Baneling";"Zergling";229;0
"Unit";"Baneling";"Zergling";229;0
"Unit";"Baneling";"Zergling";229;0
"Unit";"Baneling";"Zergling";229;0
"Building";"CreepTumor";NA;240;0
"Building";"CreepTumor";NA;240;0
"Building";"CreepTumor";NA;240;0
"Building";"UltraliskCavern";NA;229;0
"Building";"SporeCrawler";NA;240;0
"Building";"CreepTumorQueen";NA;246;0
"Building";"CreepTumorQueen";NA;246;0
"Building";"Hatchery";NA;229;0
"Unit";"Zergling";"Larva";246;1
"Unit";"Zergling";"Larva";246;1
"Unit";"Zergling";"Larva";246;1
"Unit";"Zergling";"Larva";246;1
"Unit";"Zergling";"Larva";246;1
"Unit";"Zergling";"Larva";246;1
"Unit";"Zergling";"Larva";246;1
"Unit";"Zergling";"Larva";246;1
"Unit";"Zergling";"Larva";246;1
"Unit";"Zergling";"Larva";246;1
"Unit";"Zergling";"Larva";246;1
"Unit";"Zergling";"Larva";246;1
"Unit";"Zergling";"Larva";246;1
"Unit";"Zergling";"Larva";246;1
"Building";"SporeCrawler";NA;246;0
"Building";"SporeCrawler";NA;246;0
"Building";"Spire";NA;229;0
"Unit";"Ultralisk";"Larva";246;6
"Unit";"Ultralisk";"Larva";246;6
"Building";"CreepTumor";NA;264;0
"Building";"CreepTumor";NA;284;0
"Building";"CreepTumor";NA;284;0
"Building";"Extractor";NA;272;0
"Building";"Extractor";NA;284;0
"Building";"CreepTumor";NA;284;0
"Upgrade";"ZergMissileWeaponsLevel1";"EvolutionChamber";245;0
"Unit";"Viper";"Larva";284;3
"Unit";"Viper";"Larva";284;3
"Unit";"Viper";"Larva";284;3
"Unit";"Viper";"Larva";284;3
"Building";"CreepTumor";NA;284;0
"Building";"CreepTumor";NA;284;0
"Building";"CreepTumor";NA;284;0
"Upgrade";"ChitinousPlating";"UltraliskCavern";260;0
"Upgrade";"EvolveGroovedSpines";"HydraliskDen";272;0
"Upgrade";"ZergGroundArmorsLevel2";"EvolutionChamber";246;0
"Upgrade";"GlialReconstitution";"RoachWarren";284;0
"Unit";"Overlord";"Larva";296;0
"Unit";"Overlord";"Larva";296;0
"Unit";"Overlord";"Larva";296;0
"Unit";"Overlord";"Larva";296;0
"Building";"Spire";NA;264;0
"Unit";"Ultralisk";"Larva";284;6
"Unit";"Ultralisk";"Larva";284;6
"Unit";"Baneling";"Zergling";296;0
"Unit";"Baneling";"Zergling";296;0
"Unit";"Baneling";"Zergling";296;0
"Unit";"Baneling";"Zergling";296;0
"Building";"CreepTumor";NA;296;0
"Building";"CreepTumor";NA;296;0
"Building";"CreepTumor";NA;296;0
"Building";"Hatchery";NA;284;0
"Unit";"Baneling";"Zergling";308;0
"Unit";"Baneling";"Zergling";308;0
"Unit";"Baneling";"Zergling";308;0
"Unit";"Baneling";"Zergling";308;0
"Unit";"Baneling";"Zergling";308;0
"Unit";"Baneling";"Zergling";308;0
"Unit";"Baneling";"Zergling";308;0
"Unit";"Baneling";"Zergling";308;0
"Unit";"Baneling";"Zergling";308;0
"Unit";"Baneling";"Zergling";308;0
"Unit";"Zergling";"Larva";308;1
"Unit";"Zergling";"Larva";308;1
"Unit";"Zergling";"Larva";308;1
"Unit";"Zergling";"Larva";308;1
"Unit";"Zergling";"Larva";308;1
"Unit";"Zergling";"Larva";308;1
"Unit";"Zergling";"Larva";308;1
"Unit";"Zergling";"Larva";308;1
"Unit";"Zergling";"Larva";308;1
"Unit";"Zergling";"Larva";308;1
"Unit";"Zergling";"Larva";308;1
"Unit";"Zergling";"Larva";308;1
"Unit";"Zergling";"Larva";308;1
"Unit";"Zergling";"Larva";308;1
"Unit";"Zergling";"Larva";308;1
"Unit";"Zergling";"Larva";308;1
"Unit";"Zergling";"Larva";308;1
"Unit";"Zergling";"Larva";308;1
"Unit";"Zergling";"Larva";308;1
"Unit";"Zergling";"Larva";308;1
"Unit";"Zergling";"Larva";308;1
"Unit";"Zergling";"Larva";308;1
"Unit";"Zergling";"Larva";308;1
"Unit";"Zergling";"Larva";308;1
"Unit";"Zergling";"Larva";308;1
"Unit";"Zergling";"Larva";308;1
"Unit";"Zergling";"Larva";308;1
"Unit";"Zergling";"Larva";308;1
"Unit";"Zergling";"Larva";308;1
"Unit";"Zergling";"Larva";308;1
"Unit";"Zergling";"Larva";308;1
"Unit";"Zergling";"Larva";308;1
"Unit";"Zergling";"Larva";308;1
"Unit";"Zergling";"Larva";308;1
"Unit";"Zergling";"Larva";308;1
"Unit";"Zergling";"Larva";308;1
"Unit";"Zergling";"Larva";308;1
"Unit";"Zergling";"Larva";308;1
"Unit";"Zergling";"Larva";308;1
"Unit";"Zergling";"Larva";308;1
"Unit";"Zergling";"Larva";308;1
"Unit";"Zergling";"Larva";308;1
"Unit";"Zergling";"Larva";308;1
"Unit";"Zergling";"Larva";308;1
"Unit";"Zergling";"Larva";308;1
"Unit";"Zergling";"Larva";308;1
"Building";"Extractor";NA;308;0
"Building";"Extractor";NA;308;0
