"type";"unit_name";"on_building";"total_supply";"supply"
"Unit";"Overlord";"Larva";12;0
"Building";"SpawningPool";NA;16;0
"Building";"Extractor";NA;19;0
"Unit";"Zergling";"Larva";21;1
"Unit";"Zergling";"Larva";21;1
"Unit";"Queen";"Hatchery";21;2
"Unit";"Overlord";"Larva";24;0
"Building";"Hatchery";NA;19;0
"Unit";"Queen";"Hatchery";26;2
"Unit";"Overlord";"Larva";30;0
"Unit";"Queen";"Hatchery";28;2
"Building";"CreepTumorQueen";NA;41;0
"Unit";"Overlord";"Larva";43;0
"Building";"Extractor";NA;47;0
"Building";"CreepTumorQueen";NA;51;0
"Building";"Extractor";NA;47;0
"Building";"CreepTumor";NA;51;0
"Unit";"Zergling";"Larva";48;1
"Unit";"Zergling";"Larva";48;1
"Unit";"Zergling";"Larva";48;1
"Unit";"Zergling";"Larva";48;1
"Unit";"Zergling";"Larva";48;1
"Unit";"Zergling";"Larva";48;1
"Building";"RoachWarren";NA;47;0
"Building";"Extractor";NA;51;0
"Unit";"Overlord";"Larva";58;0
"Building";"CreepTumorQueen";NA;62;0
"Building";"CreepTumor";NA;62;0
"Building";"CreepTumor";NA;62;0
"Unit";"Overlord";"Larva";62;0
"Unit";"Overlord";"Larva";62;0
"Unit";"Overlord";"Larva";64;0
"Unit";"Roach";"Larva";64;2
"Unit";"Roach";"Larva";64;2
"Unit";"Roach";"Larva";65;2
"Building";"CreepTumor";NA;66;0
"Unit";"Roach";"Larva";65;2
"Unit";"Roach";"Larva";65;2
"Building";"CreepTumor";NA;66;0
"Building";"CreepTumor";NA;66;0
"Unit";"Roach";"Larva";66;2
"Unit";"Roach";"Larva";66;2
"Building";"CreepTumorQueen";NA;72;0
"Building";"CreepTumor";NA;81;0
"Building";"Spire";NA;61;0
"Unit";"Roach";"Larva";81;2
"Unit";"Roach";"Larva";81;2
"Unit";"Roach";"Larva";81;2
"Building";"CreepTumor";NA;81;0
"Unit";"Overlord";"Larva";81;0
"Unit";"Overlord";"Larva";81;0
"Upgrade";"GlialReconstitution";"RoachWarren";66;0
"Building";"CreepTumor";NA;87;0
"Building";"CreepTumorQueen";NA;87;0
"Unit";"Mutalisk";"Larva";87;2
"Unit";"Mutalisk";"Larva";87;2
"Unit";"Mutalisk";"Larva";87;2
"Unit";"Mutalisk";"Larva";87;2
"Unit";"Mutalisk";"Larva";87;2
"Unit";"Mutalisk";"Larva";87;2
"Building";"CreepTumorQueen";NA;87;0
"Building";"EvolutionChamber";NA;87;0
"Building";"CreepTumor";NA;103;0
"Building";"EvolutionChamber";NA;87;0
"Building";"CreepTumor";NA;105;0
"Building";"Hatchery";NA;81;0
"Building";"HydraliskDen";NA;107;0
"Building";"CreepTumor";NA;115;0
"Building";"CreepTumor";NA;116;0
"Building";"CreepTumorQueen";NA;116;0
"Unit";"Overlord";"Larva";116;0
"Building";"CreepTumorQueen";NA;120;0
"Building";"Extractor";NA;120;0
"Building";"Extractor";NA;120;0
"Unit";"Roach";"Larva";120;2
"Unit";"Roach";"Larva";120;2
"Unit";"Overlord";"Larva";120;0
"Unit";"Queen";"Hatchery";115;2
"Unit";"Overlord";"Larva";123;0
"Unit";"Hydralisk";"Larva";123;2
"Unit";"Overlord";"Larva";123;0
"Unit";"Hydralisk";"Larva";123;2
"Unit";"Hydralisk";"Larva";123;2
"Unit";"Overlord";"Larva";123;0
"Unit";"Roach";"Larva";123;2
"Unit";"Roach";"Larva";129;2
"Unit";"Roach";"Larva";129;2
"Unit";"Roach";"Larva";129;2
"Building";"CreepTumor";NA;136;0
"Unit";"Roach";"Larva";130;2
"Unit";"Overlord";"Larva";136;0
"Unit";"Roach";"Larva";130;2
"Unit";"Roach";"Larva";136;2
"Unit";"Overlord";"Larva";138;0
"Unit";"Roach";"Larva";138;2
"Building";"CreepTumor";NA;148;0
"Unit";"Roach";"Larva";144;2
"Unit";"Roach";"Larva";144;2
"Unit";"Roach";"Larva";144;2
"Unit";"Roach";"Larva";144;2
"Upgrade";"EvolveGroovedSpines";"HydraliskDen";123;0
"Unit";"Roach";"Larva";144;2
"Upgrade";"ZergMissileWeaponsLevel1";"EvolutionChamber";116;0
"Upgrade";"ZergGroundArmorsLevel1";"EvolutionChamber";116;0
"Building";"Hatchery";NA;121;0
"Unit";"Roach";"Larva";152;2
"Unit";"Roach";"Larva";152;2
"Unit";"Roach";"Larva";152;2
"Unit";"Overlord";"Larva";162;0
"Unit";"Roach";"Larva";160;2
"Unit";"Roach";"Larva";162;2
"Unit";"Roach";"Larva";162;2
"Unit";"Roach";"Larva";162;2
"Unit";"Hydralisk";"Larva";168;2
"Unit";"Hydralisk";"Larva";168;2
"Unit";"Hydralisk";"Larva";168;2
"Unit";"Hydralisk";"Larva";168;2
"Unit";"Hydralisk";"Larva";168;2
"Building";"CreepTumor";NA;198;0
"Building";"CreepTumor";NA;198;0
"Unit";"Roach";"Larva";198;2
"Building";"CreepTumorQueen";NA;198;0
"Building";"CreepTumor";NA;198;0
"Unit";"Roach";"Larva";198;2
"Unit";"Roach";"Larva";198;2
"Unit";"Roach";"Larva";198;2
"Unit";"Roach";"Larva";198;2
"Unit";"Roach";"Larva";198;2
"Unit";"Roach";"Larva";198;2
"Upgrade";"EvolveMuscularAugments";"HydraliskDen";170;0
"Unit";"Queen";"Hatchery";182;2
"Unit";"Overlord";"Larva";198;0
"Unit";"Overlord";"Larva";198;0
"Unit";"Overlord";"Larva";198;0
"Building";"CreepTumorQueen";NA;200;0
"Building";"Extractor";NA;198;0
"Building";"Extractor";NA;198;0
"Building";"CreepTumorQueen";NA;213;0
