"type";"unit_name";"on_building";"total_supply";"supply"
"Unit";"Overlord";"Larva";13;0
"Building";"Extractor";NA;16;0
"Unit";"Overlord";"Larva";21;0
"Building";"SpawningPool";NA;19;0
"Building";"Hatchery";NA;16;0
"Unit";"Zergling";"Larva";23;1
"Unit";"Zergling";"Larva";23;1
"Unit";"Zergling";"Larva";23;1
"Unit";"Zergling";"Larva";23;1
"Unit";"Zergling";"Larva";23;1
"Unit";"Zergling";"Larva";23;1
"Unit";"Queen";"Hatchery";22;2
"Unit";"Queen";"Hatchery";22;2
"Unit";"Overlord";"Larva";40;0
"Building";"CreepTumorQueen";NA;40;0
"Unit";"Overlord";"Larva";40;0
"Unit";"Queen";"Hatchery";38;2
"Unit";"Overlord";"Larva";40;0
"Building";"CreepTumorQueen";NA;51;0
"Building";"Hatchery";NA;36;0
"Building";"CreepTumor";NA;51;0
"Building";"EvolutionChamber";NA;51;0
"Building";"Extractor";NA;53;0
"Building";"Extractor";NA;53;0
"Unit";"Zergling";"Larva";57;1
"Unit";"Zergling";"Larva";57;1
"Unit";"Zergling";"Larva";57;1
"Unit";"Zergling";"Larva";57;1
"Unit";"Zergling";"Larva";57;1
"Unit";"Zergling";"Larva";57;1
"Building";"RoachWarren";NA;51;0
"Unit";"Zergling";"Larva";57;1
"Unit";"Zergling";"Larva";57;1
"Unit";"Zergling";"Larva";57;1
"Unit";"Zergling";"Larva";57;1
"Unit";"Zergling";"Larva";65;1
"Unit";"Zergling";"Larva";65;1
"Unit";"Zergling";"Larva";65;1
"Unit";"Zergling";"Larva";65;1
"Unit";"Zergling";"Larva";65;1
"Unit";"Zergling";"Larva";65;1
"Unit";"Overlord";"Larva";69;0
"Unit";"Zergling";"Larva";69;1
"Unit";"Zergling";"Larva";69;1
"Unit";"Zergling";"Larva";69;1
"Unit";"Zergling";"Larva";69;1
"Building";"CreepTumor";NA;71;0
"Unit";"Queen";"Hatchery";59;2
"Unit";"Zergling";"Larva";69;1
"Unit";"Zergling";"Larva";69;1
"Unit";"Zergling";"Larva";69;1
"Unit";"Zergling";"Larva";69;1
"Building";"CreepTumorQueen";NA;77;0
"Building";"SporeCrawler";NA;90;0
"Building";"SporeCrawler";NA;90;0
"Building";"SporeCrawler";NA;90;0
"Building";"CreepTumorQueen";NA;104;0
"Unit";"Overlord";"Larva";103;0
"Unit";"Overlord";"Larva";103;0
"Unit";"Overlord";"Larva";103;0
"Upgrade";"GlialReconstitution";"RoachWarren";97;0
"Building";"HydraliskDen";NA;111;0
"Upgrade";"ZergGroundArmorsLevel1";"EvolutionChamber";97;0
"Unit";"Overlord";"Larva";122;0
"Building";"CreepTumorQueen";NA;129;0
"Building";"Extractor";NA;122;0
"Building";"Extractor";NA;122;0
"Building";"SporeCrawler";NA;129;0
"Unit";"Queen";"Hatchery";122;2
"Building";"EvolutionChamber";NA;133;0
"Building";"CreepTumor";NA;133;0
"Unit";"Queen";"Hatchery";131;2
"Unit";"Roach";"Larva";133;2
"Unit";"Roach";"Larva";133;2
"Unit";"Roach";"Larva";133;2
"Unit";"Roach";"Larva";133;2
"Unit";"Roach";"Larva";133;2
"Unit";"Queen";"Hatchery";133;2
"Unit";"Overlord";"Larva";135;0
"Unit";"Roach";"Larva";135;2
"Unit";"Roach";"Larva";135;2
"Unit";"Roach";"Larva";135;2
"Unit";"Roach";"Larva";135;2
"Building";"CreepTumor";NA;149;0
"Upgrade";"EvolveGroovedSpines";"HydraliskDen";133;0
"Building";"CreepTumorQueen";NA;149;0
"Building";"CreepTumor";NA;149;0
"Unit";"Roach";"Larva";149;2
"Unit";"Roach";"Larva";149;2
"Building";"SporeCrawler";NA;147;0
"Unit";"Roach";"Larva";149;2
"Unit";"Roach";"Larva";149;2
"Building";"CreepTumorQueen";NA;149;0
"Building";"CreepTumorQueen";NA;155;0
"Building";"CreepTumorQueen";NA;157;0
"Building";"CreepTumorQueen";NA;157;0
"Building";"CreepTumorQueen";NA;157;0
"Building";"CreepTumorQueen";NA;157;0
"Building";"CreepTumorQueen";NA;157;0
"Unit";"Hydralisk";"Larva";149;2
"Unit";"Overlord";"Larva";157;0
"Unit";"Overlord";"Larva";157;0
"Unit";"Overlord";"Larva";157;0
"Unit";"Hydralisk";"Larva";157;2
"Building";"Hatchery";NA;133;0
"Unit";"Overlord";"Larva";168;0
"Unit";"Overlord";"Larva";168;0
"Unit";"Overlord";"Larva";168;0
"Unit";"Overlord";"Larva";168;0
"Unit";"Zergling";"Larva";170;1
"Unit";"Zergling";"Larva";170;1
"Unit";"Roach";"Larva";168;2
"Unit";"Roach";"Larva";168;2
"Building";"CreepTumor";NA;170;0
"Building";"CreepTumor";NA;170;0
"Building";"CreepTumor";NA;170;0
"Building";"CreepTumor";NA;170;0
"Building";"CreepTumor";NA;170;0
"Unit";"Overlord";"Larva";170;0
"Unit";"Overlord";"Larva";170;0
"Building";"CreepTumor";NA;170;0
"Building";"CreepTumor";NA;170;0
"Building";"CreepTumor";NA;170;0
"Building";"CreepTumor";NA;170;0
"Building";"CreepTumorQueen";NA;176;0
"Building";"CreepTumor";NA;176;0
"Building";"CreepTumorQueen";NA;176;0
"Unit";"Roach";"Larva";176;2
"Unit";"Roach";"Larva";176;2
"Unit";"Roach";"Larva";176;2
"Unit";"Roach";"Larva";176;2
"Unit";"Roach";"Larva";176;2
"Unit";"Zergling";"Larva";176;1
"Unit";"Zergling";"Larva";176;1
"Unit";"Zergling";"Larva";176;1
"Unit";"Zergling";"Larva";176;1
"Unit";"Zergling";"Larva";176;1
"Unit";"Zergling";"Larva";176;1
"Unit";"Zergling";"Larva";176;1
"Unit";"Zergling";"Larva";176;1
"Unit";"Zergling";"Larva";176;1
"Unit";"Zergling";"Larva";176;1
"Unit";"Zergling";"Larva";176;1
"Unit";"Zergling";"Larva";176;1
"Unit";"Zergling";"Larva";176;1
"Unit";"Zergling";"Larva";176;1
"Upgrade";"EvolveMuscularAugments";"HydraliskDen";170;0
"Upgrade";"ZergGroundArmorsLevel2";"EvolutionChamber";137;0
"Building";"Extractor";NA;176;0
"Building";"CreepTumor";NA;202;0
"Building";"CreepTumor";NA;202;0
"Building";"CreepTumor";NA;202;0
"Building";"CreepTumor";NA;202;0
"Unit";"Hydralisk";"Larva";186;2
"Unit";"Hydralisk";"Larva";186;2
"Unit";"Hydralisk";"Larva";186;2
"Unit";"Hydralisk";"Larva";202;2
"Unit";"Hydralisk";"Larva";202;2
"Unit";"Hydralisk";"Larva";202;2
"Unit";"Hydralisk";"Larva";202;2
"Upgrade";"ZergMissileWeaponsLevel1";"EvolutionChamber";168;0
"Unit";"Overlord";"Larva";205;0
"Unit";"Overlord";"Larva";205;0
"Unit";"Hydralisk";"Larva";211;2
"Unit";"Hydralisk";"Larva";211;2
"Unit";"Hydralisk";"Larva";211;2
"Unit";"Hydralisk";"Larva";211;2
"Unit";"Hydralisk";"Larva";211;2
"Unit";"Zergling";"Larva";217;1
"Unit";"Zergling";"Larva";217;1
"Unit";"Zergling";"Larva";217;1
"Unit";"Zergling";"Larva";217;1
"Unit";"Hydralisk";"Larva";217;2
"Unit";"Hydralisk";"Larva";217;2
"Unit";"Hydralisk";"Larva";217;2
"Building";"CreepTumor";NA;219;0
"Building";"CreepTumor";NA;219;0
"Building";"CreepTumor";NA;219;0
"Building";"CreepTumor";NA;219;0
"Building";"CreepTumor";NA;219;0
"Building";"CreepTumor";NA;219;0
"Unit";"Overlord";"Larva";233;0
"Unit";"Overlord";"Larva";233;0
"Unit";"Zergling";"Larva";237;1
"Unit";"Zergling";"Larva";237;1
"Unit";"Zergling";"Larva";239;1
"Unit";"Zergling";"Larva";239;1
"Unit";"Zergling";"Larva";239;1
"Unit";"Zergling";"Larva";239;1
"Unit";"Zergling";"Larva";239;1
"Unit";"Zergling";"Larva";239;1
"Unit";"Hydralisk";"Larva";229;2
"Unit";"Zergling";"Larva";239;1
"Unit";"Zergling";"Larva";239;1
"Unit";"Zergling";"Larva";239;1
"Unit";"Zergling";"Larva";239;1
"Unit";"Hydralisk";"Larva";229;2
"Unit";"Zergling";"Larva";239;1
"Unit";"Zergling";"Larva";239;1
"Building";"CreepTumor";NA;239;0
"Building";"Extractor";NA;239;0
"Building";"BanelingNest";NA;219;0
"Building";"Extractor";NA;239;0
"Unit";"Overlord";"Larva";239;0
"Unit";"Overlord";"Larva";239;0
"Unit";"Overlord";"Larva";259;0
"Unit";"Overlord";"Larva";260;0
"Unit";"Hydralisk";"Larva";257;2
"Building";"CreepTumorQueen";NA;266;0
"Building";"CreepTumorQueen";NA;268;0
"Building";"CreepTumorQueen";NA;268;0
"Building";"CreepTumorQueen";NA;268;0
"Unit";"Hydralisk";"Larva";266;2
"Building";"CreepTumorQueen";NA;268;0
"Upgrade";"ZergMeleeWeaponsLevel1";"EvolutionChamber";229;0
"Unit";"Roach";"Larva";270;2
"Unit";"Roach";"Larva";270;2
"Unit";"Roach";"Larva";270;2
"Unit";"Roach";"Larva";270;2
"Unit";"Roach";"Larva";270;2
"Unit";"Roach";"Larva";270;2
"Unit";"Roach";"Larva";270;2
"Unit";"Roach";"Larva";270;2
"Unit";"Roach";"Larva";270;2
"Unit";"Roach";"Larva";270;2
"Unit";"Roach";"Larva";270;2
"Unit";"Hydralisk";"Larva";270;2
"Unit";"Hydralisk";"Larva";270;2
"Unit";"Hydralisk";"Larva";270;2
"Unit";"Hydralisk";"Larva";270;2
"Unit";"Hydralisk";"Larva";270;2
"Unit";"Hydralisk";"Larva";270;2
"Unit";"Hydralisk";"Larva";270;2
"Unit";"Hydralisk";"Larva";270;2
"Unit";"Hydralisk";"Larva";270;2
"Unit";"Hydralisk";"Larva";270;2
"Unit";"Hydralisk";"Larva";270;2
"Unit";"Hydralisk";"Larva";270;2
"Unit";"Zergling";"Larva";270;1
"Unit";"Zergling";"Larva";270;1
"Unit";"Hydralisk";"Larva";270;2
"Unit";"Hydralisk";"Larva";270;2
"Unit";"Hydralisk";"Larva";270;2
"Unit";"Hydralisk";"Larva";270;2
"Unit";"Hydralisk";"Larva";270;2
"Building";"Hatchery";NA;266;0
"Unit";"Hydralisk";"Larva";270;2
"Building";"CreepTumor";NA;292;0
"Building";"CreepTumor";NA;292;0
"Building";"CreepTumor";NA;292;0
"Building";"CreepTumor";NA;294;0
"Building";"CreepTumorQueen";NA;318;0
"Building";"Hatchery";NA;266;0
"Building";"CreepTumorQueen";NA;318;0
"Unit";"Overlord";"Larva";318;0
"Unit";"Overlord";"Larva";318;0
"Building";"InfestationPit";NA;292;0
"Building";"CreepTumor";NA;331;0
"Unit";"Hydralisk";"Larva";331;2
"Unit";"Hydralisk";"Larva";331;2
"Unit";"Hydralisk";"Larva";331;2
"Unit";"Hydralisk";"Larva";331;2
"Unit";"Hydralisk";"Larva";331;2
"Unit";"Hydralisk";"Larva";331;2
"Unit";"Hydralisk";"Larva";331;2
"Unit";"Hydralisk";"Larva";331;2
"Unit";"Hydralisk";"Larva";331;2
"Unit";"Hydralisk";"Larva";331;2
"Unit";"Hydralisk";"Larva";331;2
"Building";"CreepTumorQueen";NA;331;0
"Building";"CreepTumor";NA;331;0
"Building";"CreepTumor";NA;331;0
"Building";"CreepTumor";NA;331;0
"Building";"CreepTumor";NA;331;0
"Building";"CreepTumor";NA;331;0
"Building";"CreepTumor";NA;331;0
"Unit";"Overlord";"Larva";343;0
"Unit";"Overlord";"Larva";351;0
"Unit";"Queen";"Hatchery";331;2
"Unit";"Roach";"Larva";360;2
"Unit";"Roach";"Larva";360;2
"Unit";"Roach";"Larva";360;2
"Unit";"Roach";"Larva";360;2
"Unit";"Roach";"Larva";360;2
"Unit";"Roach";"Larva";360;2
"Unit";"Roach";"Larva";360;2
"Unit";"Roach";"Larva";360;2
"Unit";"Zergling";"Larva";360;1
"Unit";"Zergling";"Larva";360;1
"Unit";"Roach";"Larva";360;2
"Unit";"Roach";"Larva";360;2
"Unit";"Roach";"Larva";360;2
"Unit";"Roach";"Larva";360;2
"Unit";"Roach";"Larva";360;2
"Unit";"Roach";"Larva";360;2
"Unit";"Roach";"Larva";360;2
"Unit";"Zergling";"Larva";360;1
"Unit";"Zergling";"Larva";360;1
"Unit";"Zergling";"Larva";360;1
"Unit";"Zergling";"Larva";360;1
"Unit";"Zergling";"Larva";360;1
"Unit";"Zergling";"Larva";360;1
"Unit";"Zergling";"Larva";360;1
"Unit";"Zergling";"Larva";360;1
"Unit";"Zergling";"Larva";360;1
"Unit";"Zergling";"Larva";360;1
"Unit";"Zergling";"Larva";360;1
"Unit";"Zergling";"Larva";360;1
"Unit";"Zergling";"Larva";360;1
"Unit";"Zergling";"Larva";360;1
"Unit";"Zergling";"Larva";360;1
"Unit";"Zergling";"Larva";360;1
"Building";"CreepTumor";NA;360;0
"Unit";"Zergling";"Larva";360;1
"Unit";"Zergling";"Larva";360;1
"Unit";"Roach";"Larva";360;2
"Unit";"Roach";"Larva";360;2
"Unit";"Roach";"Larva";360;2
"Unit";"Baneling";"Zergling";408;0
"Unit";"Baneling";"Zergling";408;0
"Unit";"Baneling";"Zergling";408;0
"Unit";"Baneling";"Zergling";408;0
"Unit";"Baneling";"Zergling";408;0
"Unit";"Baneling";"Zergling";408;0
"Unit";"Baneling";"Zergling";408;0
"Unit";"Baneling";"Zergling";410;0
"Unit";"Baneling";"Zergling";410;0
"Unit";"Baneling";"Zergling";410;0
"Building";"Hatchery";NA;331;0
"Unit";"Hydralisk";"Larva";408;2
"Unit";"Hydralisk";"Larva";408;2
"Unit";"Hydralisk";"Larva";408;2
"Unit";"Hydralisk";"Larva";408;2
"Unit";"Hydralisk";"Larva";408;2
"Unit";"Hydralisk";"Larva";408;2
"Upgrade";"ZergMeleeWeaponsLevel2";"EvolutionChamber";331;0
"Unit";"Zergling";"Larva";428;1
"Unit";"Zergling";"Larva";428;1
"Unit";"Zergling";"Larva";428;1
"Unit";"Zergling";"Larva";428;1
"Unit";"Zergling";"Larva";428;1
"Unit";"Zergling";"Larva";428;1
"Unit";"Zergling";"Larva";428;1
"Unit";"Zergling";"Larva";428;1
"Building";"UltraliskCavern";NA;428;0
"Unit";"Zergling";"Larva";436;1
"Unit";"Zergling";"Larva";436;1
"Unit";"Zergling";"Larva";436;1
"Unit";"Zergling";"Larva";436;1
"Unit";"Zergling";"Larva";436;1
"Unit";"Zergling";"Larva";436;1
"Unit";"Zergling";"Larva";436;1
"Unit";"Zergling";"Larva";436;1
"Unit";"Zergling";"Larva";436;1
"Unit";"Zergling";"Larva";436;1
"Unit";"Zergling";"Larva";436;1
"Unit";"Zergling";"Larva";436;1
"Unit";"Ultralisk";"Larva";436;6
"Unit";"Ultralisk";"Larva";436;6
"Unit";"Ultralisk";"Larva";436;6
"Unit";"Ultralisk";"Larva";436;6
"Unit";"Ultralisk";"Larva";436;6
"Unit";"Ultralisk";"Larva";436;6
"Unit";"Overlord";"Larva";436;0
"Unit";"Overlord";"Larva";438;0
"Unit";"Baneling";"Zergling";454;0
"Unit";"Baneling";"Zergling";454;0
"Unit";"Baneling";"Zergling";454;0
"Unit";"Baneling";"Zergling";454;0
"Unit";"Baneling";"Zergling";454;0
"Unit";"Baneling";"Zergling";454;0
"Unit";"Baneling";"Zergling";454;0
"Unit";"Baneling";"Zergling";454;0
"Unit";"Baneling";"Zergling";454;0
"Unit";"Baneling";"Zergling";454;0
"Unit";"Baneling";"Zergling";454;0
"Unit";"Baneling";"Zergling";454;0
"Unit";"Baneling";"Zergling";454;0
"Unit";"Baneling";"Zergling";454;0
"Unit";"Baneling";"Zergling";454;0
"Building";"Extractor";NA;472;0
"Building";"Extractor";NA;472;0
"Unit";"Queen";"Hatchery";436;2
"Unit";"Ultralisk";"Larva";436;6
"Building";"SporeCrawler";NA;490;0
"Building";"SporeCrawler";NA;490;0
"Building";"SpineCrawler";NA;490;0
"Building";"SpineCrawler";NA;490;0
"Upgrade";"ChitinousPlating";"UltraliskCavern";436;0
"Building";"SpineCrawler";NA;490;0
"Building";"SpineCrawler";NA;490;0
"Building";"SpineCrawler";NA;490;0
"Building";"SpineCrawler";NA;490;0
"Building";"CreepTumor";NA;507;0
"Upgrade";"ZergGroundArmorsLevel3";"EvolutionChamber";436;0
"Upgrade";"ZergMeleeWeaponsLevel3";"EvolutionChamber";436;0
"Building";"CreepTumor";NA;507;0
"Building";"SporeCrawler";NA;507;0
"Unit";"Ultralisk";"Larva";507;6
"Unit";"Ultralisk";"Larva";507;6
"Building";"SpineCrawler";NA;507;0
"Building";"SpineCrawler";NA;507;0
"Building";"Hatchery";NA;507;0
"Building";"SpineCrawler";NA;507;0
"Building";"SpineCrawler";NA;507;0
"Building";"Hatchery";NA;507;0
"Unit";"Zergling";"Larva";521;1
"Unit";"Zergling";"Larva";521;1
"Unit";"Zergling";"Larva";521;1
"Unit";"Zergling";"Larva";521;1
"Unit";"Zergling";"Larva";521;1
"Unit";"Zergling";"Larva";521;1
"Unit";"Zergling";"Larva";521;1
"Unit";"Zergling";"Larva";521;1
"Unit";"Zergling";"Larva";521;1
"Unit";"Zergling";"Larva";521;1
"Unit";"Zergling";"Larva";521;1
"Unit";"Zergling";"Larva";521;1
"Unit";"Zergling";"Larva";521;1
"Unit";"Zergling";"Larva";521;1
"Unit";"Zergling";"Larva";521;1
"Unit";"Zergling";"Larva";521;1
"Unit";"Zergling";"Larva";521;1
"Unit";"Zergling";"Larva";521;1
"Unit";"Zergling";"Larva";521;1
"Unit";"Zergling";"Larva";521;1
"Unit";"Zergling";"Larva";521;1
"Unit";"Zergling";"Larva";521;1
"Unit";"Zergling";"Larva";521;1
"Unit";"Zergling";"Larva";521;1
"Unit";"Zergling";"Larva";521;1
"Unit";"Zergling";"Larva";521;1
"Unit";"Zergling";"Larva";521;1
"Unit";"Zergling";"Larva";521;1
"Unit";"Zergling";"Larva";521;1
"Unit";"Zergling";"Larva";521;1
"Unit";"Zergling";"Larva";521;1
"Unit";"Zergling";"Larva";521;1
"Unit";"Zergling";"Larva";521;1
"Unit";"Zergling";"Larva";521;1
"Unit";"Zergling";"Larva";521;1
"Unit";"Zergling";"Larva";521;1
"Unit";"Zergling";"Larva";521;1
"Unit";"Zergling";"Larva";521;1
"Unit";"Zergling";"Larva";521;1
"Unit";"Zergling";"Larva";521;1
"Unit";"Zergling";"Larva";521;1
"Unit";"Zergling";"Larva";521;1
"Unit";"Zergling";"Larva";521;1
"Unit";"Zergling";"Larva";521;1
"Unit";"Zergling";"Larva";521;1
"Unit";"Zergling";"Larva";521;1
"Unit";"Zergling";"Larva";521;1
"Unit";"Zergling";"Larva";521;1
"Unit";"Zergling";"Larva";521;1
"Unit";"Zergling";"Larva";521;1
"Unit";"Zergling";"Larva";521;1
"Unit";"Zergling";"Larva";521;1
"Unit";"Zergling";"Larva";521;1
"Unit";"Zergling";"Larva";521;1
"Unit";"Zergling";"Larva";521;1
"Unit";"Zergling";"Larva";521;1
"Unit";"Zergling";"Larva";521;1
"Unit";"Zergling";"Larva";521;1
"Unit";"Zergling";"Larva";521;1
"Unit";"Zergling";"Larva";521;1
"Unit";"Zergling";"Larva";521;1
"Unit";"Zergling";"Larva";521;1
"Unit";"Zergling";"Larva";521;1
"Unit";"Zergling";"Larva";521;1
"Unit";"Zergling";"Larva";521;1
"Unit";"Zergling";"Larva";521;1
"Unit";"Zergling";"Larva";547;1
"Unit";"Zergling";"Larva";547;1
"Unit";"Zergling";"Larva";551;1
"Unit";"Zergling";"Larva";551;1
"Unit";"Zergling";"Larva";551;1
"Unit";"Zergling";"Larva";551;1
"Unit";"Zergling";"Larva";551;1
"Unit";"Zergling";"Larva";551;1
