"type";"unit_name";"on_building";"total_supply";"supply"
"Unit";"Overlord";"Larva";12;0
"Building";"Extractor";NA;18;0
"Building";"SpawningPool";NA;17;0
"Unit";"Zergling";"Larva";21;1
"Unit";"Zergling";"Larva";21;1
"Unit";"Overlord";"Larva";21;0
"Unit";"Queen";"Hatchery";21;2
"Unit";"Zergling";"Larva";23;1
"Unit";"Zergling";"Larva";23;1
"Building";"Hatchery";NA;19;0
"Unit";"Queen";"Hatchery";24;2
"Unit";"Queen";"Hatchery";29;2
"Building";"CreepTumorQueen";NA;33;0
"Unit";"Overlord";"Larva";33;0
"Building";"CreepTumor";NA;40;0
"Building";"CreepTumorQueen";NA;43;0
"Unit";"Overlord";"Larva";47;0
"Building";"Hatchery";NA;33;0
"Unit";"Queen";"Hatchery";43;2
"Building";"CreepTumor";NA;50;0
"Building";"CreepTumor";NA;50;0
"Unit";"Overlord";"Larva";49;0
"Building";"CreepTumorQueen";NA;52;0
"Building";"BanelingNest";NA;49;0
"Unit";"Queen";"Hatchery";52;2
"Unit";"Zergling";"Larva";60;1
"Unit";"Zergling";"Larva";60;1
"Building";"SporeCrawler";NA;60;0
"Unit";"Zergling";"Larva";60;1
"Unit";"Zergling";"Larva";60;1
"Unit";"Overlord";"Larva";64;0
"Unit";"Overlord";"Larva";64;0
"Unit";"Overlord";"Larva";64;0
"Building";"CreepTumor";NA;64;0
"Building";"CreepTumor";NA;66;0
"Building";"CreepTumor";NA;66;0
"Building";"SporeCrawler";NA;64;0
"Building";"CreepTumorQueen";NA;70;0
"Building";"EvolutionChamber";NA;66;0
"Building";"EvolutionChamber";NA;66;0
"Building";"CreepTumor";NA;83;0
"Building";"Extractor";NA;70;0
"Building";"CreepTumor";NA;83;0
"Building";"Extractor";NA;70;0
"Building";"CreepTumor";NA;83;0
"Building";"CreepTumorQueen";NA;83;0
"Unit";"Queen";"Hatchery";70;2
"Unit";"Overlord";"Larva";90;0
"Building";"Extractor";NA;90;0
"Building";"Extractor";NA;90;0
"Building";"CreepTumor";NA;94;0
"Unit";"Zergling";"Larva";94;1
"Unit";"Zergling";"Larva";94;1
"Unit";"Zergling";"Larva";94;1
"Unit";"Zergling";"Larva";94;1
"Unit";"Zergling";"Larva";94;1
"Unit";"Zergling";"Larva";94;1
"Unit";"Zergling";"Larva";94;1
"Unit";"Zergling";"Larva";94;1
"Unit";"Zergling";"Larva";94;1
"Unit";"Zergling";"Larva";94;1
"Building";"CreepTumor";NA;94;0
"Building";"CreepTumor";NA;94;0
"Building";"CreepTumor";NA;94;0
"Building";"HydraliskDen";NA;92;0
"Building";"Extractor";NA;95;0
"Building";"CreepTumor";NA;105;0
"Unit";"Zergling";"Larva";109;1
"Unit";"Zergling";"Larva";109;1
"Unit";"Zergling";"Larva";110;1
"Unit";"Zergling";"Larva";110;1
"Unit";"Zergling";"Larva";110;1
"Unit";"Zergling";"Larva";110;1
"Unit";"Zergling";"Larva";110;1
"Unit";"Zergling";"Larva";110;1
"Unit";"Zergling";"Larva";110;1
"Unit";"Zergling";"Larva";110;1
"Unit";"Overlord";"Larva";110;0
"Unit";"Overlord";"Larva";110;0
"Unit";"Overlord";"Larva";110;0
"Unit";"Overlord";"Larva";110;0
"Unit";"Queen";"Hatchery";105;2
"Unit";"Baneling";"Zergling";110;0
"Unit";"Baneling";"Zergling";110;0
"Unit";"Baneling";"Zergling";110;0
"Unit";"Baneling";"Zergling";110;0
"Unit";"Zergling";"Larva";120;1
"Unit";"Zergling";"Larva";120;1
"Unit";"Zergling";"Larva";120;1
"Unit";"Zergling";"Larva";120;1
"Unit";"Zergling";"Larva";120;1
"Unit";"Zergling";"Larva";120;1
"Unit";"Zergling";"Larva";120;1
"Unit";"Zergling";"Larva";120;1
"Unit";"Zergling";"Larva";120;1
"Unit";"Zergling";"Larva";120;1
"Unit";"Zergling";"Larva";120;1
"Unit";"Zergling";"Larva";120;1
"Unit";"Zergling";"Larva";120;1
"Unit";"Zergling";"Larva";120;1
"Upgrade";"ZergGroundArmorsLevel1";"EvolutionChamber";92;0
"Building";"Hatchery";NA;95;0
"Building";"CreepTumor";NA;136;0
"Upgrade";"EvolveGroovedSpines";"HydraliskDen";120;0
"Building";"CreepTumorQueen";NA;141;0
"Building";"CreepTumor";NA;141;0
"Building";"CreepTumor";NA;141;0
"Building";"Hatchery";NA;110;0
"Building";"CreepTumor";NA;141;0
"Unit";"Hydralisk";"Larva";137;2
"Unit";"Hydralisk";"Larva";137;2
"Unit";"Hydralisk";"Larva";137;2
"Unit";"Hydralisk";"Larva";137;2
"Unit";"Hydralisk";"Larva";137;2
"Unit";"Hydralisk";"Larva";137;2
"Building";"InfestationPit";NA;136;0
"Building";"CreepTumorQueen";NA;141;0
"Building";"CreepTumorQueen";NA;141;0
"Upgrade";"ZergMeleeWeaponsLevel1";"EvolutionChamber";110;0
"Building";"CreepTumorQueen";NA;141;0
"Unit";"Zergling";"Larva";141;1
"Unit";"Zergling";"Larva";141;1
"Unit";"Zergling";"Larva";141;1
"Unit";"Zergling";"Larva";141;1
"Unit";"Zergling";"Larva";141;1
"Unit";"Zergling";"Larva";141;1
"Unit";"Zergling";"Larva";141;1
"Unit";"Zergling";"Larva";141;1
"Unit";"Zergling";"Larva";141;1
"Unit";"Zergling";"Larva";141;1
"Unit";"Zergling";"Larva";141;1
"Unit";"Zergling";"Larva";141;1
"Unit";"Zergling";"Larva";141;1
"Unit";"Zergling";"Larva";141;1
"Unit";"Baneling";"Zergling";141;0
"Unit";"Baneling";"Zergling";141;0
"Unit";"Baneling";"Zergling";141;0
"Unit";"Baneling";"Zergling";141;0
"Building";"CreepTumor";NA;169;0
"Unit";"Queen";"Hatchery";141;2
"Building";"CreepTumor";NA;169;0
"Building";"CreepTumor";NA;169;0
"Unit";"Overlord";"Larva";169;0
"Unit";"Overlord";"Larva";169;0
"Building";"CreepTumor";NA;169;0
"Building";"CreepTumor";NA;169;0
"Building";"CreepTumor";NA;169;0
"Building";"CreepTumor";NA;169;0
"Building";"Extractor";NA;169;0
"Building";"Extractor";NA;169;0
"Building";"SporeCrawler";NA;169;0
"Building";"Hatchery";NA;137;0
"Building";"CreepTumorQueen";NA;171;0
"Building";"CreepTumorQueen";NA;171;0
"Unit";"Baneling";"Zergling";171;0
"Unit";"Baneling";"Zergling";171;0
"Unit";"Baneling";"Zergling";171;0
"Unit";"Baneling";"Zergling";171;0
"Unit";"Baneling";"Zergling";171;0
"Unit";"Baneling";"Zergling";171;0
"Unit";"Baneling";"Zergling";171;0
"Unit";"Hydralisk";"Larva";171;2
"Unit";"Hydralisk";"Larva";171;2
"Unit";"Hydralisk";"Larva";171;2
"Unit";"Hydralisk";"Larva";171;2
"Unit";"Hydralisk";"Larva";171;2
"Unit";"Hydralisk";"Larva";171;2
"Unit";"Zergling";"Larva";172;1
"Unit";"Zergling";"Larva";172;1
"Unit";"Zergling";"Larva";173;1
"Unit";"Zergling";"Larva";173;1
"Unit";"Zergling";"Larva";173;1
"Unit";"Zergling";"Larva";173;1
"Unit";"Zergling";"Larva";173;1
"Unit";"Zergling";"Larva";173;1
"Unit";"Zergling";"Larva";174;1
"Unit";"Zergling";"Larva";174;1
"Unit";"Zergling";"Larva";199;1
"Unit";"Zergling";"Larva";199;1
"Unit";"Zergling";"Larva";199;1
"Unit";"Zergling";"Larva";199;1
"Unit";"Zergling";"Larva";199;1
"Unit";"Zergling";"Larva";199;1
"Unit";"Zergling";"Larva";199;1
"Unit";"Zergling";"Larva";199;1
"Unit";"Zergling";"Larva";199;1
"Unit";"Zergling";"Larva";199;1
"Unit";"Zergling";"Larva";199;1
"Unit";"Zergling";"Larva";199;1
"Unit";"Zergling";"Larva";199;1
"Unit";"Zergling";"Larva";199;1
"Unit";"Zergling";"Larva";199;1
"Unit";"Zergling";"Larva";199;1
"Unit";"Zergling";"Larva";199;1
"Unit";"Zergling";"Larva";199;1
"Unit";"Zergling";"Larva";199;1
"Unit";"Zergling";"Larva";199;1
"Unit";"Zergling";"Larva";199;1
"Unit";"Zergling";"Larva";199;1
"Unit";"Zergling";"Larva";199;1
"Unit";"Zergling";"Larva";199;1
"Unit";"Zergling";"Larva";199;1
"Unit";"Zergling";"Larva";199;1
"Unit";"Zergling";"Larva";199;1
"Unit";"Zergling";"Larva";199;1
"Unit";"Zergling";"Larva";199;1
"Unit";"Zergling";"Larva";199;1
"Unit";"Zergling";"Larva";199;1
"Unit";"Zergling";"Larva";199;1
"Upgrade";"ZergGroundArmorsLevel2";"EvolutionChamber";167;0
"Building";"CreepTumorQueen";NA;231;0
"Unit";"Overlord";"Larva";231;0
"Unit";"Overlord";"Larva";231;0
"Building";"CreepTumorQueen";NA;231;0
"Unit";"Baneling";"Zergling";231;0
"Unit";"Baneling";"Zergling";231;0
"Unit";"Baneling";"Zergling";231;0
"Unit";"Baneling";"Zergling";231;0
"Unit";"Baneling";"Zergling";231;0
"Unit";"Baneling";"Zergling";231;0
"Unit";"Baneling";"Zergling";231;0
"Unit";"Baneling";"Zergling";231;0
"Unit";"Baneling";"Zergling";231;0
"Unit";"Baneling";"Zergling";231;0
"Unit";"Baneling";"Zergling";231;0
"Unit";"Hydralisk";"Larva";231;2
"Unit";"Hydralisk";"Larva";231;2
"Unit";"Hydralisk";"Larva";231;2
"Unit";"Hydralisk";"Larva";231;2
"Unit";"Hydralisk";"Larva";231;2
"Unit";"Hydralisk";"Larva";231;2
"Unit";"Hydralisk";"Larva";231;2
"Unit";"Hydralisk";"Larva";231;2
"Unit";"Hydralisk";"Larva";231;2
"Building";"CreepTumorQueen";NA;231;0
"Unit";"Zergling";"Larva";231;1
"Unit";"Zergling";"Larva";231;1
"Building";"CreepTumorQueen";NA;251;0
"Building";"CreepTumorQueen";NA;251;0
"Building";"CreepTumor";NA;251;0
"Building";"CreepTumor";NA;251;0
"Building";"CreepTumor";NA;251;0
"Building";"CreepTumor";NA;251;0
"Building";"CreepTumor";NA;251;0
"Unit";"Zergling";"Larva";251;1
"Unit";"Zergling";"Larva";251;1
"Unit";"Zergling";"Larva";251;1
"Unit";"Zergling";"Larva";251;1
"Unit";"Zergling";"Larva";251;1
"Unit";"Zergling";"Larva";251;1
"Unit";"Zergling";"Larva";251;1
"Unit";"Zergling";"Larva";251;1
"Unit";"Zergling";"Larva";251;1
"Unit";"Zergling";"Larva";251;1
"Unit";"Zergling";"Larva";251;1
"Unit";"Zergling";"Larva";251;1
"Unit";"Zergling";"Larva";251;1
"Unit";"Zergling";"Larva";251;1
"Unit";"Zergling";"Larva";251;1
"Unit";"Zergling";"Larva";251;1
"Unit";"Zergling";"Larva";251;1
"Unit";"Zergling";"Larva";251;1
"Unit";"Zergling";"Larva";251;1
"Unit";"Zergling";"Larva";251;1
"Unit";"Zergling";"Larva";251;1
"Unit";"Zergling";"Larva";251;1
"Unit";"Zergling";"Larva";251;1
"Unit";"Zergling";"Larva";251;1
"Unit";"Zergling";"Larva";251;1
"Unit";"Zergling";"Larva";251;1
"Unit";"Zergling";"Larva";251;1
"Unit";"Zergling";"Larva";251;1
"Unit";"Zergling";"Larva";251;1
"Unit";"Zergling";"Larva";251;1
"Unit";"Zergling";"Larva";251;1
"Unit";"Zergling";"Larva";251;1
"Unit";"Zergling";"Larva";251;1
"Unit";"Zergling";"Larva";251;1
"Unit";"Zergling";"Larva";251;1
"Unit";"Zergling";"Larva";251;1
"Unit";"Zergling";"Larva";251;1
"Unit";"Zergling";"Larva";251;1
"Unit";"Zergling";"Larva";251;1
"Unit";"Zergling";"Larva";251;1
"Unit";"Zergling";"Larva";251;1
"Unit";"Zergling";"Larva";251;1
"Unit";"Zergling";"Larva";251;1
"Unit";"Zergling";"Larva";251;1
"Unit";"Baneling";"Zergling";295;0
"Unit";"Baneling";"Zergling";295;0
"Unit";"Overlord";"Larva";251;0
"Unit";"Zergling";"Larva";295;1
"Unit";"Zergling";"Larva";295;1
"Unit";"Zergling";"Larva";295;1
"Unit";"Zergling";"Larva";295;1
"Unit";"Zergling";"Larva";295;1
"Unit";"Zergling";"Larva";295;1
"Unit";"Zergling";"Larva";295;1
"Unit";"Zergling";"Larva";295;1
"Unit";"Zergling";"Larva";295;1
"Unit";"Zergling";"Larva";295;1
"Unit";"Queen";"Hatchery";251;2
"Building";"UltraliskCavern";NA;251;0
"Unit";"Zergling";"Larva";299;1
"Unit";"Zergling";"Larva";299;1
"Unit";"Zergling";"Larva";299;1
"Unit";"Zergling";"Larva";299;1
"Unit";"Zergling";"Larva";299;1
"Unit";"Zergling";"Larva";299;1
"Unit";"Zergling";"Larva";299;1
"Unit";"Zergling";"Larva";299;1
"Unit";"Zergling";"Larva";299;1
"Unit";"Zergling";"Larva";299;1
"Unit";"Zergling";"Larva";299;1
"Unit";"Zergling";"Larva";299;1
"Unit";"Zergling";"Larva";299;1
"Unit";"Zergling";"Larva";299;1
"Unit";"Zergling";"Larva";299;1
"Unit";"Zergling";"Larva";299;1
"Unit";"Zergling";"Larva";299;1
"Unit";"Zergling";"Larva";299;1
"Unit";"Zergling";"Larva";299;1
"Unit";"Zergling";"Larva";299;1
"Unit";"Zergling";"Larva";299;1
"Unit";"Zergling";"Larva";299;1
"Unit";"Zergling";"Larva";299;1
"Unit";"Zergling";"Larva";299;1
"Unit";"Baneling";"Zergling";309;0
"Unit";"Baneling";"Zergling";309;0
"Unit";"Baneling";"Zergling";309;0
"Unit";"Baneling";"Zergling";309;0
"Unit";"Baneling";"Zergling";309;0
"Unit";"Baneling";"Zergling";309;0
"Unit";"Baneling";"Zergling";309;0
"Unit";"Baneling";"Zergling";309;0
"Unit";"Baneling";"Zergling";309;0
"Unit";"Baneling";"Zergling";309;0
"Unit";"Baneling";"Zergling";309;0
"Unit";"Baneling";"Zergling";309;0
"Upgrade";"ZergMissileWeaponsLevel1";"EvolutionChamber";251;0
"Unit";"Zergling";"Larva";335;1
"Unit";"Zergling";"Larva";335;1
"Unit";"Zergling";"Larva";335;1
"Unit";"Zergling";"Larva";335;1
"Unit";"Zergling";"Larva";335;1
"Unit";"Zergling";"Larva";335;1
"Unit";"Baneling";"Zergling";339;0
"Unit";"Baneling";"Zergling";339;0
"Unit";"Baneling";"Zergling";339;0
"Unit";"Baneling";"Zergling";339;0
"Unit";"Baneling";"Zergling";339;0
"Unit";"Baneling";"Zergling";339;0
"Unit";"Baneling";"Zergling";339;0
"Unit";"Ultralisk";"Larva";335;6
"Unit";"Ultralisk";"Larva";335;6
"Unit";"Viper";"Larva";335;3
"Unit";"Viper";"Larva";335;3
"Building";"CreepTumor";NA;345;0
"Building";"CreepTumor";NA;345;0
"Building";"CreepTumor";NA;345;0
"Building";"CreepTumor";NA;345;0
"Building";"CreepTumor";NA;351;0
"Building";"CreepTumor";NA;351;0
"Unit";"Zergling";"Larva";363;1
"Unit";"Zergling";"Larva";363;1
"Unit";"Zergling";"Larva";363;1
"Unit";"Zergling";"Larva";363;1
"Unit";"Zergling";"Larva";363;1
"Unit";"Zergling";"Larva";363;1
"Building";"CreepTumor";NA;363;0
"Unit";"Overlord";"Larva";363;0
"Unit";"Overlord";"Larva";363;0
"Unit";"Overlord";"Larva";363;0
"Unit";"Overlord";"Larva";363;0
"Unit";"Baneling";"Zergling";363;0
"Unit";"Overlord";"Larva";363;0
"Unit";"Baneling";"Zergling";363;0
"Building";"CreepTumor";NA;363;0
"Building";"CreepTumor";NA;363;0
"Upgrade";"ChitinousPlating";"UltraliskCavern";339;0
"Building";"Extractor";NA;363;0
"Building";"SporeCrawler";NA;363;0
"Building";"CreepTumor";NA;363;0
"Building";"CreepTumor";NA;363;0
"Building";"CreepTumor";NA;369;0
"Building";"CreepTumor";NA;369;0
"Building";"CreepTumor";NA;369;0
"Building";"CreepTumor";NA;369;0
"Building";"CreepTumor";NA;369;0
"Building";"CreepTumor";NA;369;0
"Unit";"Zergling";"Larva";369;1
"Unit";"Zergling";"Larva";369;1
"Unit";"Zergling";"Larva";369;1
"Unit";"Zergling";"Larva";369;1
"Unit";"Zergling";"Larva";369;1
"Unit";"Zergling";"Larva";369;1
"Unit";"Zergling";"Larva";369;1
"Unit";"Zergling";"Larva";369;1
"Unit";"Zergling";"Larva";369;1
"Unit";"Zergling";"Larva";369;1
"Unit";"Zergling";"Larva";369;1
"Unit";"Zergling";"Larva";369;1
"Unit";"Zergling";"Larva";369;1
"Unit";"Zergling";"Larva";369;1
"Unit";"Zergling";"Larva";369;1
"Unit";"Zergling";"Larva";369;1
"Unit";"Zergling";"Larva";369;1
"Unit";"Zergling";"Larva";369;1
"Unit";"Zergling";"Larva";369;1
"Unit";"Zergling";"Larva";369;1
"Unit";"Zergling";"Larva";369;1
"Unit";"Zergling";"Larva";369;1
"Unit";"Zergling";"Larva";369;1
"Unit";"Zergling";"Larva";369;1
"Unit";"Zergling";"Larva";369;1
"Unit";"Zergling";"Larva";369;1
"Unit";"Zergling";"Larva";369;1
"Unit";"Zergling";"Larva";369;1
"Unit";"Zergling";"Larva";369;1
"Unit";"Zergling";"Larva";369;1
"Unit";"Zergling";"Larva";369;1
"Unit";"Zergling";"Larva";369;1
"Unit";"Zergling";"Larva";369;1
"Unit";"Zergling";"Larva";369;1
"Unit";"Zergling";"Larva";369;1
"Unit";"Zergling";"Larva";369;1
"Unit";"Zergling";"Larva";369;1
"Unit";"Zergling";"Larva";369;1
"Unit";"Zergling";"Larva";369;1
"Unit";"Zergling";"Larva";369;1
"Unit";"Zergling";"Larva";369;1
"Unit";"Zergling";"Larva";369;1
"Unit";"Zergling";"Larva";369;1
"Unit";"Zergling";"Larva";369;1
"Unit";"Zergling";"Larva";369;1
"Unit";"Zergling";"Larva";369;1
"Unit";"Zergling";"Larva";369;1
"Unit";"Zergling";"Larva";369;1
"Unit";"Zergling";"Larva";369;1
"Unit";"Zergling";"Larva";369;1
"Unit";"Zergling";"Larva";369;1
"Unit";"Zergling";"Larva";369;1
"Unit";"Zergling";"Larva";369;1
"Unit";"Zergling";"Larva";369;1
"Unit";"Zergling";"Larva";369;1
"Unit";"Zergling";"Larva";369;1
"Unit";"Zergling";"Larva";369;1
"Unit";"Zergling";"Larva";369;1
"Unit";"Zergling";"Larva";369;1
"Unit";"Zergling";"Larva";369;1
"Unit";"Zergling";"Larva";369;1
"Unit";"Zergling";"Larva";369;1
"Unit";"Zergling";"Larva";369;1
"Unit";"Zergling";"Larva";369;1
"Unit";"Zergling";"Larva";369;1
"Unit";"Zergling";"Larva";369;1
"Unit";"Zergling";"Larva";369;1
"Unit";"Zergling";"Larva";369;1
"Unit";"Zergling";"Larva";369;1
"Unit";"Zergling";"Larva";369;1
"Unit";"Zergling";"Larva";369;1
"Unit";"Zergling";"Larva";369;1
"Unit";"Zergling";"Larva";369;1
"Unit";"Zergling";"Larva";369;1
"Unit";"Zergling";"Larva";369;1
"Unit";"Zergling";"Larva";369;1
"Unit";"Zergling";"Larva";369;1
"Unit";"Zergling";"Larva";369;1
"Unit";"Zergling";"Larva";369;1
"Unit";"Zergling";"Larva";369;1
"Unit";"Zergling";"Larva";369;1
"Unit";"Zergling";"Larva";369;1
"Upgrade";"ZergGroundArmorsLevel3";"EvolutionChamber";311;0
"Unit";"Baneling";"Zergling";451;0
"Unit";"Baneling";"Zergling";451;0
"Unit";"Baneling";"Zergling";451;0
"Unit";"Baneling";"Zergling";451;0
"Unit";"Baneling";"Zergling";451;0
"Unit";"Baneling";"Zergling";451;0
"Building";"CreepTumor";NA;451;0
"Unit";"Baneling";"Zergling";451;0
"Building";"CreepTumor";NA;451;0
"Building";"CreepTumor";NA;451;0
"Unit";"Baneling";"Zergling";451;0
"Unit";"Baneling";"Zergling";451;0
"Unit";"Baneling";"Zergling";451;0
"Unit";"Baneling";"Zergling";451;0
"Unit";"Baneling";"Zergling";451;0
"Building";"Hatchery";NA;363;0
"Building";"CreepTumor";NA;451;0
"Building";"CreepTumor";NA;451;0
"Building";"CreepTumor";NA;451;0
"Unit";"Ultralisk";"Larva";451;6
"Unit";"Ultralisk";"Larva";451;6
"Unit";"Ultralisk";"Larva";451;6
"Unit";"Hydralisk";"Larva";451;2
"Unit";"Hydralisk";"Larva";451;2
"Unit";"Hydralisk";"Larva";451;2
"Unit";"Hydralisk";"Larva";451;2
"Unit";"Hydralisk";"Larva";451;2
"Unit";"Hydralisk";"Larva";463;2
"Unit";"Queen";"Hatchery";469;2
"Unit";"Zergling";"Larva";481;1
"Unit";"Zergling";"Larva";481;1
"Unit";"Zergling";"Larva";481;1
"Unit";"Zergling";"Larva";481;1
"Unit";"Zergling";"Larva";481;1
"Unit";"Zergling";"Larva";481;1
"Unit";"Zergling";"Larva";481;1
"Unit";"Zergling";"Larva";481;1
"Unit";"Zergling";"Larva";481;1
"Unit";"Zergling";"Larva";481;1
"Unit";"Zergling";"Larva";481;1
"Unit";"Zergling";"Larva";481;1
"Unit";"Zergling";"Larva";481;1
"Unit";"Zergling";"Larva";481;1
"Unit";"Zergling";"Larva";481;1
"Unit";"Zergling";"Larva";481;1
"Unit";"Zergling";"Larva";481;1
"Unit";"Zergling";"Larva";481;1
"Unit";"Zergling";"Larva";481;1
"Unit";"Zergling";"Larva";481;1
"Unit";"Zergling";"Larva";481;1
"Unit";"Zergling";"Larva";481;1
"Unit";"Zergling";"Larva";481;1
"Unit";"Zergling";"Larva";481;1
"Unit";"Zergling";"Larva";481;1
"Unit";"Zergling";"Larva";481;1
"Unit";"Zergling";"Larva";481;1
"Unit";"Zergling";"Larva";481;1
"Unit";"Zergling";"Larva";481;1
"Unit";"Zergling";"Larva";481;1
"Unit";"Zergling";"Larva";481;1
"Unit";"Zergling";"Larva";481;1
"Unit";"Zergling";"Larva";481;1
"Unit";"Zergling";"Larva";481;1
"Unit";"Zergling";"Larva";481;1
"Unit";"Zergling";"Larva";481;1
"Unit";"Zergling";"Larva";481;1
"Unit";"Zergling";"Larva";481;1
"Unit";"Zergling";"Larva";481;1
"Unit";"Zergling";"Larva";481;1
"Unit";"Zergling";"Larva";481;1
"Unit";"Zergling";"Larva";481;1
"Unit";"Zergling";"Larva";481;1
"Unit";"Zergling";"Larva";481;1
"Unit";"Zergling";"Larva";481;1
"Unit";"Zergling";"Larva";481;1
"Unit";"Zergling";"Larva";481;1
"Unit";"Zergling";"Larva";481;1
"Unit";"Zergling";"Larva";481;1
"Unit";"Zergling";"Larva";481;1
"Unit";"Zergling";"Larva";481;1
"Unit";"Zergling";"Larva";481;1
