"type";"unit_name";"on_building";"total_supply";"supply"
"Unit";"Overlord";"Larva";13;0
"Building";"Extractor";NA;18;0
"Unit";"Overlord";"Larva";22;0
"Building";"SpawningPool";NA;19;0
"Building";"Hatchery";NA;17;0
"Unit";"Zergling";"Larva";22;1
"Unit";"Zergling";"Larva";22;1
"Unit";"Zergling";"Larva";22;1
"Unit";"Zergling";"Larva";22;1
"Unit";"Queen";"Hatchery";22;2
"Unit";"Queen";"Hatchery";22;2
"Unit";"Overlord";"Larva";31;0
"Unit";"Queen";"Hatchery";33;2
"Unit";"Overlord";"Larva";36;0
"Unit";"Overlord";"Larva";39;0
"Building";"Extractor";NA;49;0
"Building";"Extractor";NA;49;0
"Building";"Extractor";NA;49;0
"Building";"CreepTumorQueen";NA;52;0
"Unit";"Overlord";"Larva";52;0
"Unit";"Queen";"Hatchery";50;2
"Building";"CreepTumor";NA;61;0
"Unit";"Zergling";"Larva";59;1
"Unit";"Zergling";"Larva";59;1
"Unit";"Zergling";"Larva";59;1
"Unit";"Zergling";"Larva";59;1
"Building";"BanelingNest";NA;52;0
"Building";"CreepTumorQueen";NA;63;0
"Building";"CreepTumorQueen";NA;63;0
"Unit";"Zergling";"Larva";63;1
"Unit";"Zergling";"Larva";63;1
"Unit";"Zergling";"Larva";63;1
"Unit";"Zergling";"Larva";63;1
"Unit";"Zergling";"Larva";63;1
"Unit";"Zergling";"Larva";63;1
"Unit";"Overlord";"Larva";69;0
"Unit";"Overlord";"Larva";69;0
"Unit";"Queen";"Hatchery";61;2
"Unit";"Queen";"Hatchery";63;2
"Building";"CreepTumor";NA;75;0
"Building";"CreepTumor";NA;79;0
"Unit";"Baneling";"Zergling";79;0
"Unit";"Baneling";"Zergling";79;0
"Unit";"Baneling";"Zergling";79;0
"Unit";"Baneling";"Zergling";79;0
"Unit";"Baneling";"Zergling";79;0
"Unit";"Baneling";"Zergling";79;0
"Unit";"Baneling";"Zergling";79;0
"Unit";"Zergling";"Larva";79;1
"Unit";"Zergling";"Larva";79;1
"Unit";"Zergling";"Larva";79;1
"Unit";"Zergling";"Larva";79;1
"Unit";"Zergling";"Larva";79;1
"Unit";"Zergling";"Larva";79;1
"Unit";"Zergling";"Larva";79;1
"Unit";"Zergling";"Larva";79;1
"Unit";"Zergling";"Larva";79;1
"Unit";"Zergling";"Larva";79;1
"Unit";"Zergling";"Larva";79;1
"Unit";"Zergling";"Larva";79;1
"Unit";"Zergling";"Larva";79;1
"Unit";"Zergling";"Larva";79;1
"Unit";"Zergling";"Larva";79;1
"Unit";"Zergling";"Larva";79;1
"Unit";"Zergling";"Larva";79;1
"Unit";"Zergling";"Larva";79;1
"Unit";"Zergling";"Larva";79;1
"Unit";"Zergling";"Larva";79;1
"Unit";"Zergling";"Larva";79;1
"Unit";"Zergling";"Larva";79;1
"Building";"Spire";NA;61;0
"Unit";"Zergling";"Larva";79;1
"Unit";"Zergling";"Larva";79;1
"Unit";"Zergling";"Larva";79;1
"Unit";"Zergling";"Larva";79;1
"Unit";"Zergling";"Larva";101;1
"Unit";"Zergling";"Larva";101;1
"Unit";"Zergling";"Larva";101;1
"Unit";"Zergling";"Larva";101;1
"Unit";"Zergling";"Larva";101;1
"Unit";"Zergling";"Larva";101;1
"Unit";"Zergling";"Larva";101;1
"Unit";"Zergling";"Larva";101;1
"Unit";"Zergling";"Larva";101;1
"Unit";"Zergling";"Larva";101;1
"Unit";"Zergling";"Larva";101;1
"Unit";"Zergling";"Larva";101;1
"Unit";"Zergling";"Larva";101;1
"Unit";"Zergling";"Larva";101;1
"Unit";"Mutalisk";"Larva";105;2
"Unit";"Mutalisk";"Larva";105;2
"Building";"CreepTumor";NA;119;0
"Building";"CreepTumor";NA;119;0
"Unit";"Mutalisk";"Larva";119;2
"Unit";"Mutalisk";"Larva";119;2
"Unit";"Queen";"Hatchery";105;2
"Unit";"Queen";"Hatchery";105;2
"Building";"EvolutionChamber";NA;119;0
"Building";"EvolutionChamber";NA;119;0
"Unit";"Mutalisk";"Larva";123;2
"Unit";"Baneling";"Zergling";131;0
"Unit";"Baneling";"Zergling";131;0
"Unit";"Baneling";"Zergling";131;0
"Unit";"Baneling";"Zergling";131;0
"Unit";"Baneling";"Zergling";131;0
"Unit";"Baneling";"Zergling";131;0
"Unit";"Baneling";"Zergling";131;0
"Unit";"Baneling";"Zergling";131;0
"Unit";"Baneling";"Zergling";131;0
"Unit";"Baneling";"Zergling";131;0
"Unit";"Baneling";"Zergling";131;0
"Building";"Hatchery";NA;123;0
"Building";"InfestationPit";NA;140;0
"Building";"RoachWarren";NA;140;0
"Building";"Extractor";NA;155;0
"Building";"Extractor";NA;155;0
"Unit";"Queen";"Hatchery";150;2
"Building";"SpineCrawler";NA;155;0
"Unit";"Overlord";"Larva";161;0
"Unit";"Overlord";"Larva";161;0
"Unit";"Overlord";"Larva";161;0
"Unit";"Overlord";"Larva";161;0
"Upgrade";"ZergMeleeWeaponsLevel1";"EvolutionChamber";140;0
"Upgrade";"ZergGroundArmorsLevel1";"EvolutionChamber";140;0
"Unit";"Roach";"Larva";163;2
"Unit";"Roach";"Larva";163;2
"Unit";"Roach";"Larva";163;2
"Unit";"Roach";"Larva";163;2
"Unit";"Overlord";"Larva";163;0
"Unit";"Overlord";"Larva";163;0
"Unit";"Overlord";"Larva";163;0
"Unit";"Roach";"Larva";163;2
"Unit";"Roach";"Larva";163;2
"Unit";"Roach";"Larva";171;2
"Unit";"Roach";"Larva";171;2
"Unit";"Roach";"Larva";171;2
"Unit";"Roach";"Larva";171;2
"Unit";"Roach";"Larva";171;2
"Unit";"Roach";"Larva";171;2
"Unit";"Roach";"Larva";171;2
"Upgrade";"GlialReconstitution";"RoachWarren";163;0
"Unit";"Roach";"Larva";173;2
"Unit";"Roach";"Larva";173;2
"Unit";"Roach";"Larva";173;2
"Unit";"Roach";"Larva";173;2
"Unit";"Roach";"Larva";176;2
"Unit";"Roach";"Larva";176;2
"Unit";"Roach";"Larva";190;2
"Unit";"Roach";"Larva";190;2
"Unit";"Roach";"Larva";190;2
"Unit";"Roach";"Larva";198;2
"Unit";"Roach";"Larva";198;2
"Unit";"Roach";"Larva";202;2
"Upgrade";"ZergMissileWeaponsLevel1";"EvolutionChamber";176;0
"Building";"HydraliskDen";NA;221;0
"Unit";"Roach";"Larva";221;2
"Unit";"Roach";"Larva";221;2
"Unit";"Roach";"Larva";221;2
"Unit";"Roach";"Larva";221;2
"Unit";"Roach";"Larva";221;2
"Building";"Hatchery";NA;212;0
"Unit";"Roach";"Larva";221;2
"Unit";"Roach";"Larva";221;2
"Unit";"Roach";"Larva";221;2
"Unit";"Roach";"Larva";221;2
"Unit";"Roach";"Larva";221;2
"Building";"Hatchery";NA;214;0
"Unit";"Overlord";"Larva";241;0
"Unit";"Overlord";"Larva";241;0
"Unit";"Overlord";"Larva";241;0
"Unit";"Roach";"Larva";241;2
"Unit";"Roach";"Larva";241;2
"Unit";"Overlord";"Larva";241;0
"Unit";"Queen";"Hatchery";241;2
"Unit";"Hydralisk";"Larva";245;2
"Unit";"Hydralisk";"Larva";245;2
"Unit";"Hydralisk";"Larva";245;2
"Unit";"Hydralisk";"Larva";245;2
"Unit";"Hydralisk";"Larva";245;2
"Unit";"Hydralisk";"Larva";245;2
"Unit";"Hydralisk";"Larva";245;2
"Unit";"Hydralisk";"Larva";245;2
"Unit";"Hydralisk";"Larva";245;2
"Unit";"Hydralisk";"Larva";245;2
"Unit";"Overlord";"Larva";247;0
"Unit";"Overlord";"Larva";247;0
"Unit";"Overlord";"Larva";247;0
"Upgrade";"EvolveGroovedSpines";"HydraliskDen";245;0
"Unit";"Viper";"Larva";247;3
"Unit";"Viper";"Larva";247;3
"Upgrade";"ZergGroundArmorsLevel2";"EvolutionChamber";231;0
"Unit";"Roach";"Larva";267;2
"Unit";"Roach";"Larva";267;2
"Unit";"Roach";"Larva";267;2
"Unit";"Roach";"Larva";267;2
"Unit";"Roach";"Larva";267;2
"Unit";"Roach";"Larva";267;2
"Unit";"Roach";"Larva";267;2
"Unit";"Roach";"Larva";267;2
"Unit";"Roach";"Larva";267;2
"Unit";"Roach";"Larva";267;2
"Unit";"Roach";"Larva";267;2
"Unit";"Roach";"Larva";267;2
"Unit";"Roach";"Larva";267;2
"Unit";"Roach";"Larva";267;2
"Unit";"Roach";"Larva";267;2
"Unit";"Roach";"Larva";267;2
"Unit";"Roach";"Larva";267;2
"Unit";"Roach";"Larva";267;2
"Building";"Extractor";NA;295;0
"Building";"Extractor";NA;295;0
"Building";"SpineCrawler";NA;297;0
