"type";"unit_name";"on_building";"total_supply";"supply"
"Unit";"Overlord";"Larva";12;0
"Building";"SpawningPool";NA;19;0
"Building";"Hatchery";NA;17;0
"Building";"Extractor";NA;22;0
"Unit";"Zergling";"Larva";22;1
"Unit";"Zergling";"Larva";22;1
"Unit";"Zergling";"Larva";22;1
"Unit";"Zergling";"Larva";22;1
"Unit";"Queen";"Hatchery";22;2
"Unit";"Queen";"Hatchery";23;2
"Unit";"Overlord";"Larva";32;0
"Building";"Hatchery";NA;22;0
"Building";"CreepTumorQueen";NA;34;0
"Unit";"Overlord";"Larva";34;0
"Unit";"Queen";"Hatchery";34;2
"Unit";"Queen";"Hatchery";40;2
"Building";"CreepTumorQueen";NA;50;0
"Building";"SporeCrawler";NA;46;0
"Building";"CreepTumor";NA;53;0
"Unit";"Overlord";"Larva";53;0
"Building";"CreepTumor";NA;56;0
"Unit";"Overlord";"Larva";56;0
"Unit";"Queen";"Hatchery";53;2
"Unit";"Overlord";"Larva";56;0
"Unit";"Overlord";"Larva";56;0
"Unit";"Zergling";"Larva";56;1
"Unit";"Zergling";"Larva";56;1
"Unit";"Zergling";"Larva";56;1
"Unit";"Zergling";"Larva";56;1
"Unit";"Zergling";"Larva";56;1
"Unit";"Zergling";"Larva";56;1
"Unit";"Zergling";"Larva";56;1
"Unit";"Zergling";"Larva";56;1
"Building";"BanelingNest";NA;53;0
"Unit";"Zergling";"Larva";58;1
"Unit";"Zergling";"Larva";58;1
"Unit";"Zergling";"Larva";58;1
"Unit";"Zergling";"Larva";58;1
"Unit";"Zergling";"Larva";58;1
"Unit";"Zergling";"Larva";58;1
"Unit";"Zergling";"Larva";58;1
"Unit";"Zergling";"Larva";58;1
"Unit";"Zergling";"Larva";58;1
"Unit";"Zergling";"Larva";58;1
"Unit";"Zergling";"Larva";58;1
"Unit";"Zergling";"Larva";58;1
"Unit";"Queen";"Hatchery";56;2
"Building";"CreepTumorQueen";NA;68;0
"Unit";"Overlord";"Larva";68;0
"Building";"CreepTumor";NA;82;0
"Unit";"Queen";"Hatchery";58;2
"Building";"CreepTumor";NA;87;0
"Building";"Extractor";NA;87;0
"Building";"Extractor";NA;87;0
"Building";"EvolutionChamber";NA;87;0
"Building";"EvolutionChamber";NA;87;0
"Unit";"Zergling";"Larva";95;1
"Unit";"Zergling";"Larva";95;1
"Unit";"Zergling";"Larva";95;1
"Unit";"Zergling";"Larva";95;1
"Unit";"Zergling";"Larva";95;1
"Unit";"Zergling";"Larva";95;1
"Unit";"Zergling";"Larva";95;1
"Unit";"Zergling";"Larva";95;1
"Unit";"Zergling";"Larva";95;1
"Unit";"Zergling";"Larva";95;1
"Unit";"Zergling";"Larva";95;1
"Unit";"Zergling";"Larva";95;1
"Unit";"Zergling";"Larva";95;1
"Unit";"Zergling";"Larva";95;1
"Unit";"Zergling";"Larva";95;1
"Unit";"Zergling";"Larva";95;1
"Unit";"Zergling";"Larva";95;1
"Unit";"Zergling";"Larva";95;1
"Unit";"Zergling";"Larva";95;1
"Unit";"Zergling";"Larva";95;1
"Unit";"Zergling";"Larva";95;1
"Unit";"Zergling";"Larva";95;1
"Unit";"Baneling";"Zergling";97;0
"Building";"CreepTumorQueen";NA;125;0
"Building";"CreepTumor";NA;125;0
"Unit";"Queen";"Hatchery";117;2
"Building";"HydraliskDen";NA;129;0
"Unit";"Overlord";"Larva";132;0
"Unit";"Overlord";"Larva";132;0
"Building";"Extractor";NA;132;0
"Building";"CreepTumorQueen";NA;132;0
"Building";"CreepTumorQueen";NA;133;0
"Building";"CreepTumor";NA;132;0
"Building";"Extractor";NA;132;0
"Building";"Hatchery";NA;117;0
"Building";"CreepTumor";NA;133;0
"Unit";"Overlord";"Larva";135;0
"Unit";"Overlord";"Larva";135;0
"Building";"Extractor";NA;141;0
"Building";"SporeCrawler";NA;141;0
"Unit";"Zergling";"Larva";141;1
"Unit";"Zergling";"Larva";141;1
"Unit";"Zergling";"Larva";141;1
"Unit";"Zergling";"Larva";141;1
"Unit";"Zergling";"Larva";141;1
"Unit";"Zergling";"Larva";141;1
"Unit";"Zergling";"Larva";141;1
"Unit";"Zergling";"Larva";141;1
"Unit";"Zergling";"Larva";141;1
"Unit";"Zergling";"Larva";141;1
"Unit";"Zergling";"Larva";141;1
"Unit";"Zergling";"Larva";141;1
"Unit";"Zergling";"Larva";141;1
"Unit";"Zergling";"Larva";141;1
"Unit";"Zergling";"Larva";141;1
"Unit";"Zergling";"Larva";141;1
"Unit";"Zergling";"Larva";141;1
"Unit";"Zergling";"Larva";141;1
"Unit";"Zergling";"Larva";141;1
"Unit";"Zergling";"Larva";141;1
"Unit";"Zergling";"Larva";141;1
"Unit";"Zergling";"Larva";141;1
"Unit";"Zergling";"Larva";141;1
"Unit";"Zergling";"Larva";141;1
"Unit";"Zergling";"Larva";141;1
"Unit";"Zergling";"Larva";141;1
"Unit";"Zergling";"Larva";141;1
"Unit";"Zergling";"Larva";141;1
"Unit";"Zergling";"Larva";141;1
"Unit";"Zergling";"Larva";141;1
"Unit";"Zergling";"Larva";141;1
"Unit";"Zergling";"Larva";141;1
"Upgrade";"ZergGroundArmorsLevel1";"EvolutionChamber";129;0
"Building";"CreepTumor";NA;141;0
"Upgrade";"ZergMeleeWeaponsLevel1";"EvolutionChamber";131;0
"Unit";"Hydralisk";"Larva";141;2
"Unit";"Hydralisk";"Larva";141;2
"Unit";"Hydralisk";"Larva";141;2
"Unit";"Hydralisk";"Larva";141;2
"Unit";"Hydralisk";"Larva";141;2
"Unit";"Hydralisk";"Larva";141;2
"Building";"CreepTumor";NA;143;0
"Upgrade";"EvolveGroovedSpines";"HydraliskDen";135;0
"Building";"InfestationPit";NA;141;0
"Unit";"Overlord";"Larva";143;0
"Unit";"Overlord";"Larva";145;0
"Unit";"Overlord";"Larva";145;0
"Unit";"Overlord";"Larva";175;0
"Unit";"Baneling";"Zergling";187;0
"Unit";"Baneling";"Zergling";187;0
"Unit";"Baneling";"Zergling";187;0
"Unit";"Baneling";"Zergling";187;0
"Unit";"Baneling";"Zergling";187;0
"Unit";"Baneling";"Zergling";187;0
"Unit";"Baneling";"Zergling";187;0
"Unit";"Baneling";"Zergling";187;0
"Building";"CreepTumor";NA;187;0
"Unit";"Zergling";"Larva";187;1
"Unit";"Zergling";"Larva";187;1
"Unit";"Zergling";"Larva";187;1
"Unit";"Zergling";"Larva";187;1
"Unit";"Zergling";"Larva";187;1
"Unit";"Zergling";"Larva";187;1
"Unit";"Zergling";"Larva";187;1
"Unit";"Zergling";"Larva";187;1
"Unit";"Zergling";"Larva";187;1
"Unit";"Zergling";"Larva";187;1
"Unit";"Zergling";"Larva";187;1
"Unit";"Zergling";"Larva";187;1
"Unit";"Zergling";"Larva";187;1
"Unit";"Zergling";"Larva";187;1
"Unit";"Zergling";"Larva";187;1
"Unit";"Zergling";"Larva";187;1
"Unit";"Zergling";"Larva";187;1
"Unit";"Zergling";"Larva";187;1
"Unit";"Zergling";"Larva";187;1
"Unit";"Zergling";"Larva";187;1
"Unit";"Zergling";"Larva";187;1
"Unit";"Zergling";"Larva";187;1
"Unit";"Zergling";"Larva";187;1
"Unit";"Zergling";"Larva";187;1
"Unit";"Zergling";"Larva";187;1
"Unit";"Zergling";"Larva";187;1
"Unit";"Zergling";"Larva";187;1
"Unit";"Zergling";"Larva";187;1
"Unit";"Zergling";"Larva";187;1
"Unit";"Zergling";"Larva";187;1
"Unit";"Hydralisk";"Larva";187;2
"Unit";"Hydralisk";"Larva";187;2
"Unit";"Hydralisk";"Larva";187;2
"Building";"CreepTumor";NA;187;0
"Building";"CreepTumor";NA;187;0
"Building";"CreepTumorQueen";NA;217;0
"Building";"CreepTumorQueen";NA;217;0
"Unit";"Baneling";"Zergling";223;0
"Unit";"Baneling";"Zergling";223;0
"Unit";"Baneling";"Zergling";223;0
"Unit";"Baneling";"Zergling";223;0
"Unit";"Baneling";"Zergling";223;0
"Unit";"Baneling";"Zergling";223;0
"Unit";"Baneling";"Zergling";223;0
"Unit";"Baneling";"Zergling";223;0
"Building";"Hatchery";NA;145;0
"Unit";"Zergling";"Larva";223;1
"Unit";"Zergling";"Larva";223;1
"Unit";"Zergling";"Larva";223;1
"Unit";"Zergling";"Larva";223;1
"Unit";"Zergling";"Larva";223;1
"Unit";"Zergling";"Larva";223;1
"Unit";"Zergling";"Larva";223;1
"Unit";"Zergling";"Larva";223;1
"Unit";"Zergling";"Larva";223;1
"Unit";"Zergling";"Larva";223;1
"Unit";"Zergling";"Larva";223;1
"Unit";"Zergling";"Larva";223;1
"Unit";"Zergling";"Larva";223;1
"Unit";"Zergling";"Larva";223;1
"Unit";"Zergling";"Larva";223;1
"Unit";"Zergling";"Larva";223;1
"Unit";"Zergling";"Larva";223;1
"Unit";"Zergling";"Larva";223;1
"Unit";"Zergling";"Larva";223;1
"Unit";"Zergling";"Larva";223;1
"Unit";"Zergling";"Larva";223;1
"Unit";"Zergling";"Larva";223;1
"Unit";"Overlord";"Larva";223;0
"Unit";"Overlord";"Larva";223;0
"Unit";"Overlord";"Larva";223;0
"Unit";"Overlord";"Larva";223;0
"Building";"CreepTumorQueen";NA;223;0
"Building";"CreepTumorQueen";NA;245;0
"Unit";"Baneling";"Zergling";245;0
"Unit";"Baneling";"Zergling";245;0
"Unit";"Baneling";"Zergling";245;0
"Unit";"Baneling";"Zergling";245;0
"Unit";"Baneling";"Zergling";245;0
"Unit";"Baneling";"Zergling";245;0
"Unit";"Baneling";"Zergling";245;0
"Unit";"Baneling";"Zergling";245;0
"Unit";"Baneling";"Zergling";245;0
"Unit";"Baneling";"Zergling";245;0
"Unit";"Baneling";"Zergling";245;0
"Unit";"Baneling";"Zergling";245;0
"Unit";"Baneling";"Zergling";245;0
"Unit";"Baneling";"Zergling";245;0
"Unit";"Baneling";"Zergling";245;0
"Unit";"Baneling";"Zergling";245;0
"Unit";"Baneling";"Zergling";245;0
"Unit";"Baneling";"Zergling";245;0
"Unit";"Baneling";"Zergling";245;0
"Unit";"Baneling";"Zergling";245;0
"Unit";"Baneling";"Zergling";245;0
"Unit";"Baneling";"Zergling";245;0
"Unit";"Baneling";"Zergling";245;0
"Unit";"Baneling";"Zergling";245;0
"Unit";"Baneling";"Zergling";245;0
"Unit";"Baneling";"Zergling";245;0
"Unit";"Zergling";"Larva";257;1
"Unit";"Zergling";"Larva";257;1
"Unit";"Zergling";"Larva";257;1
"Unit";"Zergling";"Larva";257;1
"Unit";"Zergling";"Larva";257;1
"Unit";"Zergling";"Larva";257;1
"Unit";"Zergling";"Larva";257;1
"Unit";"Zergling";"Larva";257;1
"Unit";"Zergling";"Larva";257;1
"Unit";"Zergling";"Larva";257;1
"Unit";"Zergling";"Larva";257;1
"Unit";"Zergling";"Larva";257;1
"Unit";"Zergling";"Larva";257;1
"Unit";"Zergling";"Larva";257;1
"Unit";"Zergling";"Larva";257;1
"Unit";"Zergling";"Larva";257;1
"Unit";"Zergling";"Larva";257;1
"Unit";"Zergling";"Larva";257;1
"Unit";"Zergling";"Larva";257;1
"Unit";"Zergling";"Larva";257;1
"Upgrade";"EvolveMuscularAugments";"HydraliskDen";223;0
"Upgrade";"ZergMissileWeaponsLevel1";"EvolutionChamber";187;0
"Upgrade";"ZergGroundArmorsLevel2";"EvolutionChamber";187;0
"Unit";"Zergling";"Larva";277;1
"Unit";"Zergling";"Larva";277;1
"Unit";"Zergling";"Larva";277;1
"Unit";"Zergling";"Larva";277;1
"Unit";"Zergling";"Larva";277;1
"Unit";"Zergling";"Larva";277;1
"Unit";"Zergling";"Larva";277;1
"Unit";"Zergling";"Larva";277;1
"Unit";"Zergling";"Larva";277;1
"Unit";"Zergling";"Larva";277;1
"Unit";"Zergling";"Larva";277;1
"Unit";"Zergling";"Larva";277;1
"Unit";"Zergling";"Larva";277;1
"Unit";"Zergling";"Larva";277;1
"Unit";"Zergling";"Larva";277;1
"Unit";"Zergling";"Larva";277;1
"Unit";"Zergling";"Larva";277;1
"Unit";"Zergling";"Larva";277;1
"Unit";"Zergling";"Larva";277;1
"Unit";"Zergling";"Larva";277;1
"Unit";"Zergling";"Larva";277;1
"Unit";"Zergling";"Larva";277;1
"Unit";"Zergling";"Larva";277;1
"Unit";"Zergling";"Larva";277;1
"Unit";"Zergling";"Larva";277;1
"Unit";"Zergling";"Larva";277;1
"Unit";"Zergling";"Larva";277;1
"Unit";"Zergling";"Larva";277;1
"Unit";"Zergling";"Larva";277;1
"Unit";"Zergling";"Larva";277;1
"Unit";"Zergling";"Larva";277;1
"Unit";"Zergling";"Larva";277;1
"Unit";"Zergling";"Larva";277;1
"Unit";"Zergling";"Larva";277;1
"Unit";"Zergling";"Larva";277;1
"Unit";"Zergling";"Larva";277;1
"Unit";"Zergling";"Larva";277;1
"Unit";"Zergling";"Larva";277;1
"Unit";"Zergling";"Larva";277;1
"Unit";"Zergling";"Larva";277;1
"Unit";"Hydralisk";"Larva";277;2
"Unit";"Hydralisk";"Larva";277;2
"Unit";"Hydralisk";"Larva";277;2
"Unit";"Hydralisk";"Larva";277;2
"Unit";"Hydralisk";"Larva";277;2
"Unit";"Hydralisk";"Larva";277;2
"Unit";"Hydralisk";"Larva";317;2
"Unit";"Hydralisk";"Larva";317;2
"Unit";"Hydralisk";"Larva";317;2
"Building";"SporeCrawler";NA;317;0
"Unit";"Baneling";"Zergling";329;0
"Unit";"Baneling";"Zergling";329;0
"Unit";"Baneling";"Zergling";329;0
"Unit";"Baneling";"Zergling";329;0
"Unit";"Baneling";"Zergling";329;0
"Unit";"Baneling";"Zergling";329;0
"Unit";"Baneling";"Zergling";329;0
"Unit";"Zergling";"Larva";335;1
"Unit";"Zergling";"Larva";335;1
"Unit";"Zergling";"Larva";335;1
"Unit";"Zergling";"Larva";335;1
"Unit";"Zergling";"Larva";335;1
"Unit";"Zergling";"Larva";335;1
"Unit";"Zergling";"Larva";335;1
"Unit";"Zergling";"Larva";335;1
"Unit";"Zergling";"Larva";335;1
"Unit";"Zergling";"Larva";335;1
"Unit";"Zergling";"Larva";335;1
"Unit";"Zergling";"Larva";335;1
"Unit";"Zergling";"Larva";335;1
"Unit";"Zergling";"Larva";335;1
"Unit";"Zergling";"Larva";335;1
"Unit";"Zergling";"Larva";335;1
"Unit";"Zergling";"Larva";335;1
"Unit";"Zergling";"Larva";335;1
"Unit";"Zergling";"Larva";335;1
"Unit";"Zergling";"Larva";335;1
"Unit";"Zergling";"Larva";335;1
"Unit";"Zergling";"Larva";335;1
"Unit";"Zergling";"Larva";335;1
"Unit";"Zergling";"Larva";335;1
"Unit";"Zergling";"Larva";335;1
"Unit";"Zergling";"Larva";335;1
"Unit";"Zergling";"Larva";335;1
"Unit";"Zergling";"Larva";335;1
"Unit";"Zergling";"Larva";335;1
"Unit";"Zergling";"Larva";335;1
"Unit";"Zergling";"Larva";335;1
"Unit";"Zergling";"Larva";335;1
"Building";"Extractor";NA;335;0
"Building";"CreepTumor";NA;335;0
"Building";"CreepTumor";NA;335;0
"Building";"Extractor";NA;335;0
"Unit";"Baneling";"Zergling";335;0
"Unit";"Baneling";"Zergling";335;0
"Unit";"Baneling";"Zergling";335;0
"Unit";"Baneling";"Zergling";335;0
"Unit";"Baneling";"Zergling";335;0
"Unit";"Baneling";"Zergling";335;0
"Unit";"Baneling";"Zergling";335;0
"Unit";"Baneling";"Zergling";335;0
"Unit";"Baneling";"Zergling";335;0
"Unit";"Baneling";"Zergling";335;0
"Unit";"Baneling";"Zergling";335;0
"Unit";"Baneling";"Zergling";335;0
"Unit";"Baneling";"Zergling";335;0
"Unit";"Baneling";"Zergling";335;0
"Unit";"Baneling";"Zergling";335;0
"Unit";"Baneling";"Zergling";335;0
"Unit";"Baneling";"Zergling";335;0
"Unit";"Baneling";"Zergling";335;0
"Unit";"Baneling";"Zergling";335;0
"Unit";"Baneling";"Zergling";335;0
"Unit";"Baneling";"Zergling";335;0
"Building";"SporeCrawler";NA;335;0
"Building";"SporeCrawler";NA;369;0
"Building";"CreepTumor";NA;375;0
"Building";"CreepTumor";NA;375;0
"Building";"CreepTumor";NA;375;0
"Unit";"Baneling";"Zergling";375;0
"Unit";"Baneling";"Zergling";375;0
"Unit";"Baneling";"Zergling";375;0
"Unit";"Baneling";"Zergling";375;0
"Unit";"Baneling";"Zergling";375;0
"Unit";"Baneling";"Zergling";375;0
"Unit";"Baneling";"Zergling";375;0
"Unit";"Baneling";"Zergling";375;0
"Unit";"Baneling";"Zergling";375;0
"Building";"UltraliskCavern";NA;369;0
"Unit";"Zergling";"Larva";375;1
"Unit";"Zergling";"Larva";375;1
"Unit";"Zergling";"Larva";375;1
"Unit";"Zergling";"Larva";375;1
"Unit";"Zergling";"Larva";375;1
"Unit";"Zergling";"Larva";375;1
"Unit";"Zergling";"Larva";375;1
"Unit";"Zergling";"Larva";375;1
"Unit";"Zergling";"Larva";375;1
"Unit";"Zergling";"Larva";375;1
"Unit";"Zergling";"Larva";375;1
"Unit";"Zergling";"Larva";375;1
"Unit";"Zergling";"Larva";375;1
"Unit";"Zergling";"Larva";375;1
"Unit";"Zergling";"Larva";375;1
"Unit";"Zergling";"Larva";375;1
"Unit";"Zergling";"Larva";375;1
"Unit";"Zergling";"Larva";375;1
"Unit";"Zergling";"Larva";375;1
"Unit";"Zergling";"Larva";375;1
"Unit";"Zergling";"Larva";375;1
"Unit";"Zergling";"Larva";375;1
"Unit";"Zergling";"Larva";375;1
"Unit";"Zergling";"Larva";375;1
"Unit";"Zergling";"Larva";375;1
"Unit";"Zergling";"Larva";375;1
"Unit";"Zergling";"Larva";375;1
"Unit";"Zergling";"Larva";375;1
"Unit";"Zergling";"Larva";375;1
"Unit";"Zergling";"Larva";375;1
"Unit";"Zergling";"Larva";375;1
"Unit";"Zergling";"Larva";375;1
"Unit";"Zergling";"Larva";375;1
"Unit";"Zergling";"Larva";375;1
"Unit";"Zergling";"Larva";375;1
"Unit";"Zergling";"Larva";375;1
"Unit";"Zergling";"Larva";375;1
"Unit";"Zergling";"Larva";375;1
"Unit";"Zergling";"Larva";375;1
"Unit";"Zergling";"Larva";375;1
"Unit";"Zergling";"Larva";375;1
"Unit";"Zergling";"Larva";375;1
"Unit";"Zergling";"Larva";375;1
"Unit";"Zergling";"Larva";375;1
"Unit";"Zergling";"Larva";375;1
"Unit";"Zergling";"Larva";375;1
"Unit";"Zergling";"Larva";375;1
"Unit";"Zergling";"Larva";375;1
"Building";"Hatchery";NA;369;0
"Unit";"Zergling";"Larva";375;1
"Unit";"Zergling";"Larva";375;1
"Unit";"Zergling";"Larva";375;1
"Unit";"Zergling";"Larva";375;1
"Unit";"Zergling";"Larva";375;1
"Unit";"Zergling";"Larva";375;1
"Unit";"Zergling";"Larva";375;1
"Unit";"Zergling";"Larva";375;1
"Unit";"Zergling";"Larva";375;1
"Unit";"Zergling";"Larva";375;1
"Unit";"Zergling";"Larva";375;1
"Unit";"Zergling";"Larva";375;1
"Unit";"Zergling";"Larva";375;1
"Unit";"Zergling";"Larva";375;1
"Unit";"Zergling";"Larva";375;1
"Unit";"Zergling";"Larva";375;1
"Unit";"Baneling";"Zergling";423;0
"Upgrade";"ZergMissileWeaponsLevel2";"EvolutionChamber";369;0
"Unit";"Ultralisk";"Larva";375;6
"Unit";"Ultralisk";"Larva";375;6
"Unit";"Ultralisk";"Larva";375;6
"Unit";"Ultralisk";"Larva";375;6
"Unit";"Baneling";"Zergling";439;0
"Unit";"Baneling";"Zergling";439;0
"Unit";"Baneling";"Zergling";439;0
"Unit";"Baneling";"Zergling";439;0
"Unit";"Baneling";"Zergling";439;0
"Unit";"Baneling";"Zergling";439;0
"Unit";"Baneling";"Zergling";439;0
"Unit";"Baneling";"Zergling";439;0
"Unit";"Baneling";"Zergling";439;0
"Unit";"Zergling";"Larva";439;1
"Unit";"Zergling";"Larva";439;1
"Unit";"Zergling";"Larva";439;1
"Unit";"Zergling";"Larva";439;1
"Unit";"Zergling";"Larva";439;1
"Unit";"Zergling";"Larva";439;1
"Unit";"Zergling";"Larva";439;1
"Unit";"Zergling";"Larva";439;1
"Unit";"Zergling";"Larva";439;1
"Unit";"Zergling";"Larva";439;1
"Unit";"Zergling";"Larva";439;1
"Unit";"Zergling";"Larva";439;1
"Unit";"Zergling";"Larva";439;1
"Unit";"Zergling";"Larva";439;1
"Unit";"Zergling";"Larva";439;1
"Unit";"Zergling";"Larva";439;1
"Unit";"Zergling";"Larva";439;1
"Unit";"Zergling";"Larva";439;1
"Unit";"Zergling";"Larva";439;1
"Unit";"Zergling";"Larva";439;1
"Unit";"Zergling";"Larva";439;1
"Unit";"Zergling";"Larva";439;1
"Unit";"Zergling";"Larva";439;1
"Unit";"Zergling";"Larva";439;1
"Unit";"Zergling";"Larva";439;1
"Unit";"Zergling";"Larva";439;1
"Unit";"Zergling";"Larva";439;1
"Unit";"Zergling";"Larva";439;1
"Unit";"Zergling";"Larva";439;1
"Unit";"Zergling";"Larva";439;1
"Unit";"Zergling";"Larva";439;1
"Unit";"Zergling";"Larva";439;1
"Unit";"Zergling";"Larva";439;1
"Unit";"Zergling";"Larva";439;1
"Unit";"Zergling";"Larva";439;1
"Unit";"Zergling";"Larva";439;1
"Unit";"Zergling";"Larva";439;1
"Unit";"Zergling";"Larva";439;1
"Unit";"Baneling";"Zergling";445;0
"Unit";"Baneling";"Zergling";457;0
"Unit";"Baneling";"Zergling";457;0
"Unit";"Baneling";"Zergling";457;0
"Unit";"Baneling";"Zergling";457;0
"Unit";"Zergling";"Larva";463;1
"Unit";"Zergling";"Larva";463;1
"Unit";"Zergling";"Larva";463;1
"Unit";"Zergling";"Larva";463;1
"Unit";"Zergling";"Larva";463;1
"Unit";"Zergling";"Larva";463;1
"Unit";"Zergling";"Larva";463;1
"Unit";"Zergling";"Larva";463;1
"Unit";"Zergling";"Larva";463;1
"Unit";"Zergling";"Larva";463;1
"Unit";"Zergling";"Larva";463;1
"Unit";"Zergling";"Larva";463;1
"Unit";"Zergling";"Larva";463;1
"Unit";"Zergling";"Larva";463;1
"Unit";"Zergling";"Larva";463;1
"Unit";"Zergling";"Larva";463;1
"Upgrade";"ZergMeleeWeaponsLevel2";"EvolutionChamber";375;0
"Unit";"Zergling";"Larva";501;1
"Unit";"Zergling";"Larva";501;1
"Unit";"Zergling";"Larva";501;1
"Unit";"Zergling";"Larva";501;1
"Unit";"Zergling";"Larva";501;1
"Unit";"Zergling";"Larva";501;1
"Unit";"Zergling";"Larva";501;1
"Unit";"Zergling";"Larva";501;1
"Unit";"Zergling";"Larva";501;1
"Unit";"Zergling";"Larva";501;1
"Unit";"Viper";"Larva";501;3
"Unit";"Viper";"Larva";501;3
"Building";"CreepTumorQueen";NA;533;0
"Building";"CreepTumorQueen";NA;533;0
"Building";"CreepTumorQueen";NA;533;0
"Unit";"Ultralisk";"Larva";527;6
"Unit";"Ultralisk";"Larva";527;6
"Unit";"Ultralisk";"Larva";527;6
"Unit";"Ultralisk";"Larva";530;6
"Building";"CreepTumor";NA;533;0
"Building";"CreepTumor";NA;533;0
"Building";"CreepTumor";NA;533;0
"Building";"CreepTumor";NA;551;0
"Unit";"Hydralisk";"Larva";533;2
"Unit";"Hydralisk";"Larva";533;2
"Unit";"Hydralisk";"Larva";533;2
"Unit";"Hydralisk";"Larva";533;2
"Building";"CreepTumorQueen";NA;557;0
"Building";"CreepTumorQueen";NA;557;0
"Unit";"Baneling";"Zergling";557;0
"Unit";"Baneling";"Zergling";557;0
"Unit";"Baneling";"Zergling";557;0
"Unit";"Baneling";"Zergling";557;0
"Unit";"Baneling";"Zergling";557;0
"Unit";"Zergling";"Larva";557;1
"Unit";"Zergling";"Larva";557;1
"Unit";"Zergling";"Larva";557;1
"Unit";"Zergling";"Larva";557;1
"Unit";"Zergling";"Larva";557;1
"Unit";"Zergling";"Larva";557;1
"Unit";"Zergling";"Larva";557;1
"Unit";"Zergling";"Larva";557;1
"Unit";"Zergling";"Larva";557;1
"Unit";"Zergling";"Larva";557;1
"Unit";"Zergling";"Larva";557;1
"Unit";"Zergling";"Larva";557;1
"Unit";"Zergling";"Larva";557;1
"Unit";"Zergling";"Larva";557;1
"Unit";"Ultralisk";"Larva";533;6
"Unit";"Ultralisk";"Larva";533;6
"Unit";"Zergling";"Larva";565;1
"Unit";"Zergling";"Larva";565;1
"Unit";"Zergling";"Larva";565;1
"Unit";"Zergling";"Larva";565;1
"Building";"CreepTumor";NA;591;0
"Unit";"Hydralisk";"Larva";565;2
"Unit";"Hydralisk";"Larva";565;2
"Unit";"Hydralisk";"Larva";565;2
"Unit";"Baneling";"Zergling";601;0
"Unit";"Baneling";"Zergling";601;0
"Unit";"Baneling";"Zergling";601;0
"Unit";"Baneling";"Zergling";601;0
"Unit";"Baneling";"Zergling";601;0
"Unit";"Baneling";"Zergling";601;0
"Unit";"Baneling";"Zergling";601;0
"Unit";"Baneling";"Zergling";601;0
"Unit";"Baneling";"Zergling";601;0
"Unit";"Baneling";"Zergling";601;0
"Unit";"Baneling";"Zergling";601;0
"Unit";"Baneling";"Zergling";601;0
"Unit";"Baneling";"Zergling";601;0
"Unit";"Baneling";"Zergling";601;0
"Unit";"Baneling";"Zergling";601;0
"Building";"Hatchery";NA;533;0
"Building";"Hatchery";NA;533;0
"Unit";"Zergling";"Larva";601;1
"Unit";"Zergling";"Larva";601;1
"Unit";"Zergling";"Larva";601;1
"Unit";"Zergling";"Larva";601;1
"Unit";"Zergling";"Larva";601;1
"Unit";"Zergling";"Larva";601;1
"Unit";"Zergling";"Larva";601;1
"Unit";"Zergling";"Larva";601;1
"Unit";"Zergling";"Larva";601;1
"Unit";"Zergling";"Larva";601;1
"Unit";"Zergling";"Larva";601;1
"Unit";"Zergling";"Larva";601;1
"Unit";"Zergling";"Larva";601;1
"Unit";"Zergling";"Larva";601;1
"Unit";"Zergling";"Larva";601;1
"Unit";"Zergling";"Larva";601;1
"Unit";"Zergling";"Larva";601;1
"Unit";"Zergling";"Larva";601;1
"Unit";"Zergling";"Larva";601;1
"Unit";"Zergling";"Larva";601;1
"Unit";"Zergling";"Larva";601;1
"Unit";"Zergling";"Larva";601;1
"Unit";"Zergling";"Larva";601;1
"Unit";"Zergling";"Larva";601;1
"Unit";"Zergling";"Larva";601;1
"Unit";"Zergling";"Larva";601;1
"Unit";"Zergling";"Larva";601;1
"Unit";"Zergling";"Larva";601;1
"Unit";"Zergling";"Larva";601;1
"Unit";"Zergling";"Larva";601;1
"Unit";"Zergling";"Larva";601;1
"Unit";"Zergling";"Larva";601;1
"Unit";"Zergling";"Larva";601;1
"Unit";"Zergling";"Larva";601;1
"Unit";"Zergling";"Larva";601;1
"Unit";"Zergling";"Larva";601;1
"Unit";"Zergling";"Larva";601;1
"Unit";"Zergling";"Larva";601;1
"Unit";"Zergling";"Larva";601;1
"Unit";"Zergling";"Larva";601;1
"Unit";"Zergling";"Larva";648;1
"Unit";"Zergling";"Larva";648;1
"Unit";"Zergling";"Larva";648;1
"Unit";"Zergling";"Larva";648;1
"Unit";"Zergling";"Larva";648;1
"Unit";"Zergling";"Larva";648;1
"Unit";"Zergling";"Larva";648;1
"Unit";"Zergling";"Larva";648;1
"Unit";"Zergling";"Larva";648;1
"Unit";"Zergling";"Larva";648;1
"Unit";"Zergling";"Larva";648;1
"Unit";"Zergling";"Larva";648;1
"Unit";"Zergling";"Larva";648;1
"Unit";"Zergling";"Larva";648;1
"Unit";"Zergling";"Larva";648;1
"Unit";"Zergling";"Larva";648;1
"Unit";"Zergling";"Larva";648;1
"Unit";"Zergling";"Larva";648;1
"Unit";"Zergling";"Larva";648;1
"Unit";"Zergling";"Larva";648;1
"Unit";"Zergling";"Larva";648;1
"Unit";"Zergling";"Larva";648;1
"Unit";"Zergling";"Larva";648;1
"Unit";"Zergling";"Larva";648;1
"Unit";"Zergling";"Larva";648;1
"Unit";"Zergling";"Larva";648;1
"Unit";"Zergling";"Larva";648;1
"Unit";"Zergling";"Larva";648;1
"Unit";"Zergling";"Larva";648;1
"Unit";"Zergling";"Larva";648;1
"Unit";"Zergling";"Larva";648;1
"Unit";"Zergling";"Larva";648;1
"Unit";"Zergling";"Larva";648;1
"Unit";"Zergling";"Larva";648;1
"Unit";"Zergling";"Larva";648;1
"Unit";"Zergling";"Larva";648;1
"Unit";"Zergling";"Larva";648;1
"Unit";"Zergling";"Larva";648;1
"Unit";"Zergling";"Larva";648;1
"Unit";"Zergling";"Larva";648;1
"Unit";"Zergling";"Larva";648;1
"Unit";"Zergling";"Larva";648;1
"Unit";"Zergling";"Larva";648;1
"Unit";"Zergling";"Larva";648;1
"Unit";"Zergling";"Larva";648;1
"Unit";"Zergling";"Larva";648;1
