"type";"unit_name";"on_building";"total_supply";"supply"
"Unit";"Overlord";"Larva";12;0
"Unit";"Overlord";"Larva";17;0
"Building";"Extractor";NA;17;0
"Building";"Hatchery";NA;16;0
"Building";"SpawningPool";NA;18;0
"Unit";"Overlord";"Larva";21;0
"Unit";"Zergling";"Larva";22;1
"Unit";"Zergling";"Larva";22;1
"Unit";"Zergling";"Larva";22;1
"Unit";"Zergling";"Larva";22;1
"Unit";"Queen";"Hatchery";22;2
"Unit";"Queen";"Hatchery";22;2
"Building";"CreepTumorQueen";NA;35;0
"Unit";"Queen";"Hatchery";33;2
"Unit";"Zergling";"Larva";39;1
"Unit";"Zergling";"Larva";39;1
"Unit";"Queen";"Hatchery";37;2
"Building";"CreepTumor";NA;39;0
"Building";"CreepTumorQueen";NA;43;0
"Building";"CreepTumorQueen";NA;43;0
"Unit";"Overlord";"Larva";39;0
"Unit";"Overlord";"Larva";51;0
"Building";"CreepTumor";NA;51;0
"Building";"CreepTumor";NA;51;0
"Unit";"Zergling";"Larva";51;1
"Unit";"Zergling";"Larva";51;1
"Unit";"Zergling";"Larva";51;1
"Unit";"Zergling";"Larva";51;1
"Building";"CreepTumorQueen";NA;53;0
"Unit";"Overlord";"Larva";53;0
"Building";"CreepTumorQueen";NA;53;0
"Unit";"Overlord";"Larva";53;0
"Unit";"Overlord";"Larva";57;0
"Building";"EvolutionChamber";NA;53;0
"Building";"EvolutionChamber";NA;53;0
"Building";"CreepTumor";NA;59;0
"Building";"CreepTumor";NA;59;0
"Building";"CreepTumor";NA;59;0
"Building";"CreepTumorQueen";NA;61;0
"Building";"Hatchery";NA;43;0
"Building";"CreepTumorQueen";NA;61;0
"Building";"CreepTumor";NA;64;0
"Building";"Extractor";NA;64;0
"Building";"Extractor";NA;64;0
"Unit";"Zergling";"Larva";69;1
"Unit";"Zergling";"Larva";69;1
"Unit";"Zergling";"Larva";69;1
"Unit";"Zergling";"Larva";69;1
"Building";"CreepTumor";NA;75;0
"Unit";"Queen";"Hatchery";64;2
"Unit";"Zergling";"Larva";75;1
"Unit";"Zergling";"Larva";75;1
"Unit";"Zergling";"Larva";75;1
"Unit";"Zergling";"Larva";75;1
"Unit";"Zergling";"Larva";75;1
"Unit";"Zergling";"Larva";75;1
"Unit";"Zergling";"Larva";75;1
"Unit";"Zergling";"Larva";75;1
"Unit";"Zergling";"Larva";75;1
"Unit";"Zergling";"Larva";75;1
"Unit";"Zergling";"Larva";75;1
"Unit";"Zergling";"Larva";75;1
"Unit";"Zergling";"Larva";79;1
"Unit";"Zergling";"Larva";79;1
"Unit";"Zergling";"Larva";79;1
"Unit";"Zergling";"Larva";79;1
"Unit";"Zergling";"Larva";93;1
"Unit";"Zergling";"Larva";93;1
"Unit";"Zergling";"Larva";93;1
"Unit";"Zergling";"Larva";93;1
"Unit";"Zergling";"Larva";93;1
"Unit";"Zergling";"Larva";93;1
"Unit";"Zergling";"Larva";93;1
"Unit";"Zergling";"Larva";93;1
"Unit";"Zergling";"Larva";93;1
"Unit";"Zergling";"Larva";93;1
"Building";"EvolutionChamber";NA;83;0
"Unit";"Zergling";"Larva";97;1
"Unit";"Zergling";"Larva";97;1
"Building";"CreepTumor";NA;97;0
"Unit";"Zergling";"Larva";97;1
"Unit";"Zergling";"Larva";97;1
"Building";"CreepTumor";NA;97;0
"Unit";"Zergling";"Larva";97;1
"Unit";"Zergling";"Larva";97;1
"Unit";"Zergling";"Larva";97;1
"Unit";"Zergling";"Larva";97;1
"Unit";"Zergling";"Larva";97;1
"Unit";"Zergling";"Larva";97;1
"Unit";"Zergling";"Larva";97;1
"Unit";"Zergling";"Larva";97;1
"Building";"CreepTumor";NA;107;0
"Unit";"Zergling";"Larva";97;1
"Unit";"Zergling";"Larva";97;1
"Building";"SporeCrawler";NA;107;0
"Building";"SporeCrawler";NA;107;0
"Building";"SporeCrawler";NA;107;0
"Unit";"Zergling";"Larva";124;1
"Unit";"Zergling";"Larva";124;1
"Unit";"Zergling";"Larva";124;1
"Unit";"Zergling";"Larva";124;1
"Unit";"Zergling";"Larva";124;1
"Unit";"Zergling";"Larva";124;1
"Unit";"Zergling";"Larva";124;1
"Unit";"Zergling";"Larva";124;1
"Unit";"Zergling";"Larva";124;1
"Unit";"Zergling";"Larva";124;1
"Unit";"Zergling";"Larva";124;1
"Unit";"Zergling";"Larva";124;1
"Unit";"Zergling";"Larva";124;1
"Unit";"Zergling";"Larva";124;1
"Unit";"Zergling";"Larva";124;1
"Unit";"Zergling";"Larva";124;1
"Upgrade";"ZergGroundArmorsLevel1";"EvolutionChamber";77;0
"Unit";"Zergling";"Larva";124;1
"Unit";"Zergling";"Larva";124;1
"Unit";"Zergling";"Larva";124;1
"Unit";"Zergling";"Larva";124;1
"Unit";"Zergling";"Larva";124;1
"Unit";"Zergling";"Larva";124;1
"Unit";"Zergling";"Larva";124;1
"Unit";"Zergling";"Larva";124;1
"Building";"BanelingNest";NA;107;0
"Upgrade";"ZergMeleeWeaponsLevel1";"EvolutionChamber";83;0
"Building";"CreepTumor";NA;140;0
"Unit";"Overlord";"Larva";124;0
"Building";"CreepTumor";NA;140;0
"Unit";"Baneling";"Zergling";149;0
"Unit";"Baneling";"Zergling";150;0
"Unit";"Baneling";"Zergling";150;0
"Unit";"Baneling";"Zergling";150;0
"Unit";"Baneling";"Zergling";150;0
"Unit";"Baneling";"Zergling";150;0
"Unit";"Baneling";"Zergling";150;0
"Unit";"Baneling";"Zergling";150;0
"Unit";"Baneling";"Zergling";150;0
"Unit";"Baneling";"Zergling";150;0
"Unit";"Baneling";"Zergling";150;0
"Unit";"Baneling";"Zergling";150;0
"Unit";"Baneling";"Zergling";150;0
"Unit";"Baneling";"Zergling";150;0
"Unit";"Baneling";"Zergling";150;0
"Unit";"Baneling";"Zergling";150;0
"Unit";"Baneling";"Zergling";150;0
"Unit";"Zergling";"Larva";150;1
"Unit";"Zergling";"Larva";150;1
"Unit";"Zergling";"Larva";150;1
"Unit";"Zergling";"Larva";150;1
"Unit";"Queen";"Hatchery";144;2
"Unit";"Zergling";"Larva";150;1
"Unit";"Zergling";"Larva";150;1
"Unit";"Zergling";"Larva";150;1
"Unit";"Zergling";"Larva";150;1
"Unit";"Zergling";"Larva";150;1
"Unit";"Zergling";"Larva";150;1
"Unit";"Zergling";"Larva";150;1
"Unit";"Zergling";"Larva";150;1
"Unit";"Zergling";"Larva";150;1
"Unit";"Zergling";"Larva";150;1
"Unit";"Zergling";"Larva";150;1
"Unit";"Zergling";"Larva";150;1
"Unit";"Zergling";"Larva";150;1
"Unit";"Zergling";"Larva";150;1
"Unit";"Zergling";"Larva";150;1
"Unit";"Zergling";"Larva";150;1
"Unit";"Zergling";"Larva";154;1
"Unit";"Zergling";"Larva";154;1
"Unit";"Zergling";"Larva";154;1
"Unit";"Zergling";"Larva";154;1
"Unit";"Zergling";"Larva";154;1
"Unit";"Zergling";"Larva";154;1
"Unit";"Zergling";"Larva";154;1
"Unit";"Zergling";"Larva";154;1
"Unit";"Zergling";"Larva";154;1
"Unit";"Zergling";"Larva";154;1
"Unit";"Zergling";"Larva";156;1
"Unit";"Zergling";"Larva";156;1
"Unit";"Zergling";"Larva";158;1
"Unit";"Zergling";"Larva";158;1
"Unit";"Zergling";"Larva";158;1
"Unit";"Zergling";"Larva";158;1
"Unit";"Zergling";"Larva";172;1
"Unit";"Zergling";"Larva";172;1
"Unit";"Zergling";"Larva";172;1
"Unit";"Zergling";"Larva";172;1
"Unit";"Zergling";"Larva";172;1
"Unit";"Zergling";"Larva";172;1
"Unit";"Zergling";"Larva";172;1
"Unit";"Zergling";"Larva";172;1
"Unit";"Zergling";"Larva";172;1
"Unit";"Zergling";"Larva";172;1
"Unit";"Baneling";"Zergling";188;0
"Unit";"Baneling";"Zergling";188;0
"Unit";"Zergling";"Larva";188;1
"Unit";"Zergling";"Larva";188;1
"Unit";"Zergling";"Larva";188;1
"Unit";"Zergling";"Larva";188;1
"Unit";"Baneling";"Zergling";188;0
"Unit";"Zergling";"Larva";188;1
"Unit";"Zergling";"Larva";188;1
"Unit";"Zergling";"Larva";188;1
"Unit";"Zergling";"Larva";188;1
"Unit";"Zergling";"Larva";188;1
"Unit";"Zergling";"Larva";188;1
"Unit";"Zergling";"Larva";188;1
"Unit";"Zergling";"Larva";188;1
"Building";"CreepTumor";NA;220;0
"Building";"CreepTumor";NA;220;0
"Building";"HydraliskDen";NA;220;0
"Unit";"Zergling";"Larva";225;1
"Unit";"Zergling";"Larva";225;1
"Unit";"Zergling";"Larva";225;1
"Unit";"Zergling";"Larva";225;1
"Unit";"Zergling";"Larva";225;1
"Unit";"Zergling";"Larva";225;1
"Unit";"Zergling";"Larva";225;1
"Unit";"Zergling";"Larva";225;1
"Building";"CreepTumor";NA;229;0
"Unit";"Zergling";"Larva";225;1
"Unit";"Zergling";"Larva";225;1
"Building";"CreepTumor";NA;229;0
"Building";"CreepTumor";NA;229;0
"Building";"CreepTumor";NA;229;0
"Building";"CreepTumor";NA;229;0
"Unit";"Zergling";"Larva";229;1
"Unit";"Zergling";"Larva";229;1
"Building";"CreepTumor";NA;229;0
"Unit";"Zergling";"Larva";229;1
"Unit";"Zergling";"Larva";229;1
"Unit";"Zergling";"Larva";229;1
"Unit";"Zergling";"Larva";229;1
"Unit";"Baneling";"Zergling";239;0
"Unit";"Baneling";"Zergling";239;0
"Unit";"Baneling";"Zergling";239;0
"Unit";"Baneling";"Zergling";239;0
"Unit";"Baneling";"Zergling";239;0
"Unit";"Baneling";"Zergling";239;0
"Unit";"Baneling";"Zergling";239;0
"Unit";"Hydralisk";"Larva";229;2
"Unit";"Hydralisk";"Larva";229;2
"Unit";"Hydralisk";"Larva";229;2
"Unit";"Overlord";"Larva";241;0
"Unit";"Overlord";"Larva";245;0
"Unit";"Overlord";"Larva";245;0
"Unit";"Overlord";"Larva";245;0
"Building";"Hatchery";NA;221;0
"Unit";"Hydralisk";"Larva";251;2
"Unit";"Hydralisk";"Larva";251;2
"Unit";"Hydralisk";"Larva";251;2
"Unit";"Hydralisk";"Larva";251;2
"Unit";"Hydralisk";"Larva";251;2
"Unit";"Hydralisk";"Larva";251;2
"Building";"CreepTumor";NA;251;0
"Building";"CreepTumor";NA;251;0
"Unit";"Hydralisk";"Larva";251;2
"Unit";"Hydralisk";"Larva";251;2
"Unit";"Hydralisk";"Larva";251;2
"Unit";"Hydralisk";"Larva";251;2
"Unit";"Hydralisk";"Larva";251;2
"Building";"CreepTumor";NA;251;0
"Building";"CreepTumor";NA;251;0
"Building";"CreepTumor";NA;251;0
"Unit";"Overlord";"Larva";251;0
"Building";"CreepTumorQueen";NA;268;0
"Building";"Extractor";NA;268;0
"Building";"Extractor";NA;268;0
"Building";"SporeCrawler";NA;268;0
"Building";"Extractor";NA;268;0
"Building";"SporeCrawler";NA;268;0
"Building";"SporeCrawler";NA;272;0
"Building";"CreepTumor";NA;282;0
"Building";"CreepTumor";NA;282;0
"Building";"CreepTumor";NA;283;0
"Building";"CreepTumor";NA;283;0
"Building";"SporeCrawler";NA;282;0
"Building";"CreepTumor";NA;292;0
"Building";"CreepTumor";NA;292;0
"Building";"CreepTumor";NA;292;0
"Building";"CreepTumor";NA;293;0
"Unit";"Hydralisk";"Larva";283;2
"Building";"InfestationPit";NA;283;0
"Unit";"Zergling";"Larva";295;1
"Unit";"Zergling";"Larva";295;1
"Unit";"Zergling";"Larva";295;1
"Unit";"Zergling";"Larva";295;1
"Unit";"Zergling";"Larva";295;1
"Unit";"Zergling";"Larva";295;1
"Unit";"Zergling";"Larva";295;1
"Unit";"Zergling";"Larva";295;1
"Unit";"Zergling";"Larva";295;1
"Unit";"Zergling";"Larva";295;1
"Unit";"Hydralisk";"Larva";295;2
"Unit";"Hydralisk";"Larva";295;2
"Unit";"Hydralisk";"Larva";295;2
"Unit";"Zergling";"Larva";295;1
"Unit";"Zergling";"Larva";295;1
"Unit";"Hydralisk";"Larva";295;2
"Unit";"Zergling";"Larva";295;1
"Unit";"Zergling";"Larva";295;1
"Unit";"Overlord";"Larva";297;0
"Unit";"Zergling";"Larva";297;1
"Unit";"Zergling";"Larva";297;1
"Unit";"Zergling";"Larva";297;1
"Unit";"Zergling";"Larva";297;1
"Building";"Extractor";NA;297;0
"Building";"Extractor";NA;297;0
"Upgrade";"EvolveMuscularAugments";"HydraliskDen";283;0
"Unit";"Overlord";"Larva";297;0
"Unit";"Hydralisk";"Larva";297;2
"Unit";"Hydralisk";"Larva";297;2
"Unit";"Overlord";"Larva";307;0
"Unit";"Overlord";"Larva";319;0
"Unit";"Overlord";"Larva";319;0
"Unit";"Overlord";"Larva";319;0
"Building";"CreepTumor";NA;327;0
"Unit";"Hydralisk";"Larva";323;2
"Unit";"Hydralisk";"Larva";323;2
"Unit";"Hydralisk";"Larva";323;2
"Unit";"Hydralisk";"Larva";323;2
"Unit";"Queen";"Hatchery";319;2
"Upgrade";"ZergMissileWeaponsLevel1";"EvolutionChamber";283;0
"Unit";"Zergling";"Larva";330;1
"Unit";"Zergling";"Larva";330;1
"Unit";"Zergling";"Larva";330;1
"Unit";"Zergling";"Larva";330;1
"Unit";"Zergling";"Larva";330;1
"Unit";"Zergling";"Larva";330;1
"Unit";"Zergling";"Larva";330;1
"Unit";"Zergling";"Larva";330;1
"Unit";"Hydralisk";"Larva";338;2
"Unit";"Hydralisk";"Larva";338;2
"Unit";"Hydralisk";"Larva";338;2
"Unit";"Hydralisk";"Larva";338;2
"Unit";"Hydralisk";"Larva";338;2
"Building";"CreepTumor";NA;348;0
"Building";"CreepTumor";NA;348;0
"Building";"CreepTumorQueen";NA;351;0
"Unit";"Overlord";"Larva";348;0
"Building";"CreepTumor";NA;357;0
"Building";"CreepTumor";NA;365;0
"Unit";"Baneling";"Zergling";365;0
"Unit";"Baneling";"Zergling";365;0
"Unit";"Baneling";"Zergling";365;0
"Unit";"Baneling";"Zergling";365;0
"Unit";"Baneling";"Zergling";365;0
"Unit";"Baneling";"Zergling";365;0
"Unit";"Baneling";"Zergling";365;0
"Unit";"Baneling";"Zergling";365;0
"Unit";"Baneling";"Zergling";365;0
"Unit";"Baneling";"Zergling";365;0
"Unit";"Zergling";"Larva";365;1
"Unit";"Zergling";"Larva";365;1
"Unit";"Zergling";"Larva";365;1
"Unit";"Zergling";"Larva";365;1
"Unit";"Zergling";"Larva";365;1
"Unit";"Zergling";"Larva";365;1
"Unit";"Zergling";"Larva";365;1
"Unit";"Zergling";"Larva";365;1
"Unit";"Overlord";"Larva";373;0
"Building";"CreepTumorQueen";NA;373;0
"Building";"CreepTumor";NA;373;0
"Building";"Spire";NA;340;0
"Building";"CreepTumor";NA;373;0
"Unit";"Baneling";"Zergling";373;0
"Unit";"Baneling";"Zergling";373;0
"Unit";"Baneling";"Zergling";373;0
"Unit";"Baneling";"Zergling";373;0
"Unit";"Baneling";"Zergling";373;0
"Unit";"Baneling";"Zergling";373;0
"Building";"CreepTumor";NA;373;0
"Building";"CreepTumor";NA;373;0
"Unit";"Queen";"Hatchery";373;2
"Unit";"Hydralisk";"Larva";373;2
"Unit";"Hydralisk";"Larva";373;2
"Unit";"Hydralisk";"Larva";373;2
"Unit";"Hydralisk";"Larva";373;2
"Unit";"Hydralisk";"Larva";373;2
"Unit";"Hydralisk";"Larva";373;2
"Building";"Hatchery";NA;365;0
"Unit";"Hydralisk";"Larva";373;2
"Unit";"Hydralisk";"Larva";373;2
"Unit";"Hydralisk";"Larva";373;2
"Building";"Hatchery";NA;365;0
"Unit";"Zergling";"Larva";375;1
"Unit";"Zergling";"Larva";375;1
"Unit";"Zergling";"Larva";375;1
"Unit";"Zergling";"Larva";375;1
"Unit";"Zergling";"Larva";375;1
"Unit";"Zergling";"Larva";375;1
"Unit";"Zergling";"Larva";375;1
"Unit";"Zergling";"Larva";375;1
"Unit";"Zergling";"Larva";377;1
"Unit";"Zergling";"Larva";377;1
"Unit";"Hydralisk";"Larva";375;2
"Upgrade";"EvolveGroovedSpines";"HydraliskDen";373;0
"Unit";"Hydralisk";"Larva";375;2
"Unit";"Hydralisk";"Larva";375;2
"Unit";"Hydralisk";"Larva";375;2
"Unit";"Hydralisk";"Larva";375;2
"Building";"CreepTumor";NA;393;0
"Building";"CreepTumor";NA;393;0
"Building";"CreepTumor";NA;393;0
"Building";"CreepTumor";NA;403;0
"Building";"Extractor";NA;393;0
"Building";"Extractor";NA;393;0
"Building";"CreepTumorQueen";NA;422;0
"Building";"CreepTumorQueen";NA;424;0
"Building";"SporeCrawler";NA;413;0
"Building";"SporeCrawler";NA;413;0
"Building";"CreepTumor";NA;424;0
"Unit";"Zergling";"Larva";419;1
"Unit";"Zergling";"Larva";419;1
"Building";"CreepTumor";NA;424;0
"Unit";"Zergling";"Larva";419;1
"Unit";"Zergling";"Larva";419;1
"Unit";"Zergling";"Larva";419;1
"Unit";"Zergling";"Larva";419;1
"Unit";"Zergling";"Larva";419;1
"Unit";"Zergling";"Larva";419;1
"Unit";"Zergling";"Larva";419;1
"Unit";"Zergling";"Larva";419;1
"Unit";"Zergling";"Larva";419;1
"Unit";"Zergling";"Larva";419;1
"Building";"CreepTumorQueen";NA;424;0
"Upgrade";"ZergMeleeWeaponsLevel2";"EvolutionChamber";369;0
"Building";"CreepTumor";NA;439;0
"Building";"CreepTumor";NA;439;0
"Building";"CreepTumor";NA;439;0
"Unit";"Infestor";"Larva";424;2
"Unit";"Infestor";"Larva";424;2
"Unit";"Infestor";"Larva";424;2
"Unit";"Infestor";"Larva";424;2
"Unit";"Infestor";"Larva";424;2
"Upgrade";"ZergMissileWeaponsLevel2";"EvolutionChamber";373;0
"Unit";"Overlord";"Larva";439;0
"Unit";"Infestor";"Larva";439;2
"Unit";"Infestor";"Larva";439;2
"Unit";"Overlord";"Larva";449;0
"Unit";"Overlord";"Larva";449;0
"Building";"Extractor";NA;449;0
"Building";"Extractor";NA;449;0
"Unit";"Corruptor";"Larva";449;2
"Unit";"Corruptor";"Larva";449;2
"Unit";"Corruptor";"Larva";449;2
"Unit";"Corruptor";"Larva";449;2
"Unit";"Corruptor";"Larva";449;2
"Unit";"Corruptor";"Larva";449;2
"Unit";"Corruptor";"Larva";449;2
"Unit";"Corruptor";"Larva";449;2
"Unit";"Queen";"Hatchery";449;2
"Unit";"Overlord";"Larva";475;0
"Unit";"Overlord";"Larva";475;0
"Unit";"Corruptor";"Larva";475;2
"Building";"CreepTumorQueen";NA;477;0
"Building";"CreepTumor";NA;477;0
"Unit";"Overlord";"Larva";477;0
"Building";"CreepTumorQueen";NA;479;0
"Unit";"Baneling";"Zergling";479;0
"Unit";"Baneling";"Zergling";479;0
"Unit";"Baneling";"Zergling";479;0
"Unit";"Baneling";"Zergling";479;0
"Unit";"Baneling";"Zergling";479;0
"Unit";"Baneling";"Zergling";479;0
"Unit";"Baneling";"Zergling";479;0
"Unit";"Baneling";"Zergling";479;0
"Unit";"Baneling";"Zergling";479;0
"Unit";"Baneling";"Zergling";479;0
"Unit";"Baneling";"Zergling";479;0
"Unit";"Baneling";"Zergling";479;0
"Building";"CreepTumor";NA;479;0
"Unit";"Corruptor";"Larva";477;2
"Unit";"Corruptor";"Larva";477;2
"Unit";"Corruptor";"Larva";477;2
"Unit";"Corruptor";"Larva";477;2
"Unit";"Corruptor";"Larva";477;2
"Upgrade";"Burrow";"Hatchery";475;0
"Building";"CreepTumorQueen";NA;479;0
"Building";"CreepTumor";NA;479;0
"Building";"CreepTumorQueen";NA;489;0
"Upgrade";"NeuralParasite";"InfestationPit";475;0
"Building";"Hatchery";NA;477;0
"Building";"SporeCrawler";NA;489;0
"Building";"SporeCrawler";NA;489;0
"Building";"SporeCrawler";NA;489;0
"Building";"CreepTumor";NA;489;0
"Building";"CreepTumor";NA;489;0
"Building";"CreepTumorQueen";NA;489;0
"Building";"CreepTumor";NA;489;0
"Unit";"Corruptor";"Larva";489;2
"Unit";"Corruptor";"Larva";489;2
"Unit";"Corruptor";"Larva";489;2
"Unit";"Corruptor";"Larva";489;2
"Unit";"Corruptor";"Larva";489;2
"Unit";"Corruptor";"Larva";489;2
"Unit";"Corruptor";"Larva";489;2
"Unit";"Corruptor";"Larva";489;2
"Unit";"Corruptor";"Larva";489;2
"Unit";"Corruptor";"Larva";489;2
"Unit";"Corruptor";"Larva";489;2
"Unit";"Corruptor";"Larva";489;2
"Unit";"Corruptor";"Larva";489;2
"Unit";"Viper";"Larva";489;3
"Unit";"Viper";"Larva";489;3
"Building";"CreepTumor";NA;515;0
"Unit";"Zergling";"Larva";521;1
"Unit";"Zergling";"Larva";521;1
"Unit";"Zergling";"Larva";521;1
"Unit";"Zergling";"Larva";521;1
"Building";"CreepTumor";NA;526;0
"Building";"CreepTumor";NA;526;0
"Building";"CreepTumor";NA;526;0
"Building";"CreepTumor";NA;526;0
"Upgrade";"ZergGroundArmorsLevel2";"EvolutionChamber";489;0
"Building";"Extractor";NA;526;0
"Building";"SporeCrawler";NA;526;0
"Building";"SporeCrawler";NA;526;0
"Building";"Extractor";NA;526;0
"Building";"Spire";NA;489;0
"Unit";"Infestor";"Larva";526;2
"Unit";"Infestor";"Larva";526;2
"Unit";"Infestor";"Larva";526;2
"Unit";"Infestor";"Larva";526;2
"Upgrade";"ZergMissileWeaponsLevel3";"EvolutionChamber";489;0
"Unit";"Corruptor";"Larva";530;2
"Unit";"Corruptor";"Larva";530;2
"Unit";"Corruptor";"Larva";530;2
"Building";"CreepTumorQueen";NA;538;0
"Building";"CreepTumor";NA;538;0
"Building";"SpineCrawler";NA;538;0
"Building";"SpineCrawler";NA;538;0
"Building";"CreepTumor";NA;544;0
"Building";"CreepTumor";NA;544;0
"Unit";"Overlord";"Larva";544;0
"Unit";"Overlord";"Larva";544;0
"Building";"SporeCrawler";NA;547;0
"Building";"SporeCrawler";NA;547;0
"Building";"CreepTumor";NA;547;0
"Building";"CreepTumor";NA;547;0
"Upgrade";"ZergGroundArmorsLevel3";"EvolutionChamber";544;0
"Building";"SporeCrawler";NA;547;0
"Building";"SporeCrawler";NA;547;0
"Upgrade";"ZergMeleeWeaponsLevel3";"EvolutionChamber";544;0
"Building";"SporeCrawler";NA;547;0
"Building";"CreepTumor";NA;547;0
"Building";"CreepTumor";NA;547;0
"Building";"Spire";NA;547;0
"Building";"CreepTumorQueen";NA;547;0
"Building";"CreepTumorQueen";NA;552;0
"Building";"CreepTumorQueen";NA;552;0
"Building";"CreepTumorQueen";NA;552;0
"Building";"Extractor";NA;552;0
"Unit";"Corruptor";"Larva";552;2
"Unit";"Corruptor";"Larva";552;2
"Unit";"Corruptor";"Larva";552;2
"Unit";"Corruptor";"Larva";552;2
"Unit";"Corruptor";"Larva";552;2
"Unit";"Corruptor";"Larva";552;2
"Unit";"Corruptor";"Larva";552;2
"Building";"Hatchery";NA;547;0
"Building";"CreepTumor";NA;552;0
"Building";"CreepTumor";NA;552;0
"Building";"CreepTumor";NA;552;0
"Building";"CreepTumor";NA;552;0
"Building";"CreepTumor";NA;552;0
"Unit";"Overlord";"Larva";552;0
"Building";"CreepTumor";NA;566;0
"Unit";"Infestor";"Larva";552;2
"Unit";"Infestor";"Larva";552;2
"Unit";"Infestor";"Larva";552;2
"Unit";"Infestor";"Larva";552;2
"Unit";"Infestor";"Larva";552;2
"Unit";"Infestor";"Larva";552;2
"Unit";"Infestor";"Larva";552;2
"Unit";"Infestor";"Larva";552;2
"Unit";"Infestor";"Larva";552;2
"Unit";"Infestor";"Larva";552;2
"Unit";"Infestor";"Larva";552;2
"Unit";"Infestor";"Larva";552;2
"Unit";"Infestor";"Larva";552;2
"Unit";"Infestor";"Larva";552;2
"Unit";"Infestor";"Larva";552;2
"Unit";"Infestor";"Larva";552;2
"Unit";"Zergling";"Larva";566;1
"Unit";"Zergling";"Larva";566;1
"Building";"SporeCrawler";NA;566;0
"Building";"SporeCrawler";NA;566;0
"Building";"SporeCrawler";NA;566;0
"Building";"SporeCrawler";NA;566;0
"Unit";"Zergling";"Larva";601;1
"Unit";"Zergling";"Larva";601;1
"Unit";"Zergling";"Larva";601;1
"Unit";"Zergling";"Larva";601;1
"Unit";"Zergling";"Larva";601;1
"Unit";"Zergling";"Larva";601;1
"Building";"CreepTumorQueen";NA;603;0
"Building";"CreepTumorQueen";NA;603;0
"Building";"CreepTumor";NA;609;0
"Building";"CreepTumor";NA;609;0
"Unit";"Overlord";"Larva";603;0
"Building";"SporeCrawler";NA;609;0
"Building";"SporeCrawler";NA;609;0
"Building";"SporeCrawler";NA;609;0
"Unit";"Overlord";"Larva";609;0
"Building";"CreepTumorQueen";NA;609;0
"Unit";"Overlord";"Larva";609;0
"Building";"CreepTumorQueen";NA;609;0
"Building";"SporeCrawler";NA;609;0
"Building";"SporeCrawler";NA;609;0
"Building";"SporeCrawler";NA;609;0
"Building";"SporeCrawler";NA;609;0
"Building";"SporeCrawler";NA;609;0
"Building";"SporeCrawler";NA;609;0
"Building";"SporeCrawler";NA;609;0
"Unit";"Corruptor";"Larva";609;2
"Unit";"Corruptor";"Larva";609;2
"Unit";"Infestor";"Larva";609;2
"Unit";"Infestor";"Larva";609;2
"Unit";"Infestor";"Larva";609;2
"Unit";"Infestor";"Larva";609;2
"Unit";"Infestor";"Larva";609;2
"Unit";"Infestor";"Larva";609;2
"Unit";"Infestor";"Larva";609;2
"Unit";"Infestor";"Larva";609;2
"Unit";"Infestor";"Larva";609;2
"Unit";"Hydralisk";"Larva";638;2
"Unit";"Hydralisk";"Larva";638;2
"Unit";"Hydralisk";"Larva";638;2
"Unit";"Hydralisk";"Larva";638;2
"Unit";"Hydralisk";"Larva";638;2
"Unit";"Hydralisk";"Larva";638;2
"Unit";"Hydralisk";"Larva";638;2
"Unit";"Hydralisk";"Larva";638;2
"Unit";"Hydralisk";"Larva";638;2
"Unit";"Hydralisk";"Larva";638;2
"Unit";"Hydralisk";"Larva";638;2
"Unit";"Hydralisk";"Larva";638;2
"Unit";"Hydralisk";"Larva";638;2
"Unit";"Hydralisk";"Larva";638;2
"Unit";"Hydralisk";"Larva";638;2
"Unit";"Hydralisk";"Larva";638;2
"Unit";"Hydralisk";"Larva";638;2
"Unit";"Hydralisk";"Larva";638;2
"Unit";"Hydralisk";"Larva";638;2
"Unit";"Hydralisk";"Larva";638;2
"Unit";"Hydralisk";"Larva";638;2
"Unit";"Hydralisk";"Larva";638;2
"Unit";"Hydralisk";"Larva";638;2
"Unit";"Hydralisk";"Larva";638;2
"Unit";"Hydralisk";"Larva";638;2
"Unit";"Hydralisk";"Larva";638;2
"Building";"CreepTumor";NA;700;0
"Building";"CreepTumor";NA;700;0
"Unit";"Viper";"Larva";700;3
"Unit";"Viper";"Larva";700;3
"Unit";"Viper";"Larva";700;3
"Unit";"Viper";"Larva";700;3
"Building";"CreepTumor";NA;700;0
"Unit";"Zergling";"Larva";712;1
"Unit";"Zergling";"Larva";712;1
"Unit";"Zergling";"Larva";712;1
"Unit";"Zergling";"Larva";712;1
"Unit";"Overlord";"Larva";712;0
"Unit";"Zergling";"Larva";716;1
"Unit";"Zergling";"Larva";716;1
"Unit";"Zergling";"Larva";716;1
"Unit";"Zergling";"Larva";716;1
"Unit";"Zergling";"Larva";716;1
"Unit";"Zergling";"Larva";716;1
"Unit";"Zergling";"Larva";716;1
"Unit";"Zergling";"Larva";716;1
"Unit";"Zergling";"Larva";716;1
"Unit";"Zergling";"Larva";716;1
"Unit";"Zergling";"Larva";716;1
"Unit";"Zergling";"Larva";716;1
"Unit";"Zergling";"Larva";716;1
"Unit";"Zergling";"Larva";716;1
"Unit";"Zergling";"Larva";716;1
"Unit";"Zergling";"Larva";716;1
"Unit";"Zergling";"Larva";716;1
"Unit";"Zergling";"Larva";716;1
"Unit";"Zergling";"Larva";716;1
"Unit";"Zergling";"Larva";716;1
"Unit";"Zergling";"Larva";716;1
"Unit";"Zergling";"Larva";716;1
"Unit";"Zergling";"Larva";716;1
"Unit";"Zergling";"Larva";716;1
"Unit";"Zergling";"Larva";716;1
"Unit";"Zergling";"Larva";716;1
"Unit";"Zergling";"Larva";716;1
"Unit";"Zergling";"Larva";716;1
"Unit";"Zergling";"Larva";716;1
"Unit";"Zergling";"Larva";716;1
"Unit";"Zergling";"Larva";716;1
"Unit";"Zergling";"Larva";716;1
"Unit";"Zergling";"Larva";716;1
"Unit";"Zergling";"Larva";716;1
"Unit";"Zergling";"Larva";716;1
"Unit";"Zergling";"Larva";716;1
"Unit";"Zergling";"Larva";716;1
"Unit";"Zergling";"Larva";716;1
"Unit";"Zergling";"Larva";716;1
"Unit";"Zergling";"Larva";716;1
"Unit";"Zergling";"Larva";716;1
"Unit";"Zergling";"Larva";716;1
"Unit";"Zergling";"Larva";716;1
"Unit";"Zergling";"Larva";716;1
"Unit";"Zergling";"Larva";716;1
"Unit";"Zergling";"Larva";716;1
"Unit";"Zergling";"Larva";716;1
"Unit";"Zergling";"Larva";716;1
"Unit";"Zergling";"Larva";716;1
"Unit";"Zergling";"Larva";716;1
"Unit";"Zergling";"Larva";716;1
"Unit";"Zergling";"Larva";716;1
"Unit";"Zergling";"Larva";716;1
"Unit";"Zergling";"Larva";716;1
"Unit";"Zergling";"Larva";716;1
"Unit";"Zergling";"Larva";716;1
"Unit";"Zergling";"Larva";716;1
"Unit";"Zergling";"Larva";716;1
"Unit";"Zergling";"Larva";716;1
"Unit";"Zergling";"Larva";716;1
"Unit";"Zergling";"Larva";716;1
"Unit";"Zergling";"Larva";716;1
"Unit";"Zergling";"Larva";716;1
"Unit";"Zergling";"Larva";716;1
"Unit";"Zergling";"Larva";716;1
"Unit";"Zergling";"Larva";716;1
"Unit";"Zergling";"Larva";716;1
"Unit";"Zergling";"Larva";716;1
"Unit";"Zergling";"Larva";716;1
"Unit";"Zergling";"Larva";716;1
"Unit";"Zergling";"Larva";716;1
"Unit";"Zergling";"Larva";716;1
"Unit";"Zergling";"Larva";716;1
"Unit";"Zergling";"Larva";716;1
"Unit";"Zergling";"Larva";716;1
"Unit";"Zergling";"Larva";716;1
"Unit";"Zergling";"Larva";716;1
"Unit";"Zergling";"Larva";716;1
"Unit";"Zergling";"Larva";716;1
"Unit";"Zergling";"Larva";716;1
"Unit";"Zergling";"Larva";716;1
"Unit";"Zergling";"Larva";716;1
"Unit";"Zergling";"Larva";716;1
"Unit";"Zergling";"Larva";716;1
"Unit";"Zergling";"Larva";716;1
"Unit";"Zergling";"Larva";716;1
"Unit";"Zergling";"Larva";716;1
"Unit";"Zergling";"Larva";716;1
"Unit";"Zergling";"Larva";716;1
"Unit";"Zergling";"Larva";716;1
"Unit";"Infestor";"Larva";716;2
"Unit";"Infestor";"Larva";716;2
"Unit";"Infestor";"Larva";716;2
"Unit";"Infestor";"Larva";716;2
"Unit";"Zergling";"Larva";788;1
"Unit";"Zergling";"Larva";788;1
"Unit";"Zergling";"Larva";788;1
"Unit";"Zergling";"Larva";788;1
"Unit";"Zergling";"Larva";814;1
"Unit";"Zergling";"Larva";814;1
"Unit";"Zergling";"Larva";814;1
"Unit";"Zergling";"Larva";814;1
"Unit";"Zergling";"Larva";814;1
"Unit";"Zergling";"Larva";814;1
"Unit";"Zergling";"Larva";814;1
"Unit";"Zergling";"Larva";814;1
"Unit";"Zergling";"Larva";814;1
"Unit";"Zergling";"Larva";814;1
"Unit";"Zergling";"Larva";814;1
"Unit";"Zergling";"Larva";814;1
"Unit";"Zergling";"Larva";814;1
"Unit";"Zergling";"Larva";814;1
"Unit";"Zergling";"Larva";814;1
"Unit";"Zergling";"Larva";814;1
"Unit";"Zergling";"Larva";814;1
"Unit";"Zergling";"Larva";814;1
"Unit";"Zergling";"Larva";814;1
"Unit";"Zergling";"Larva";814;1
"Unit";"Zergling";"Larva";814;1
"Unit";"Zergling";"Larva";814;1
"Unit";"Zergling";"Larva";814;1
"Unit";"Zergling";"Larva";814;1
"Unit";"Zergling";"Larva";814;1
"Unit";"Zergling";"Larva";814;1
"Unit";"Zergling";"Larva";814;1
"Unit";"Zergling";"Larva";814;1
"Unit";"Zergling";"Larva";814;1
"Unit";"Zergling";"Larva";814;1
"Unit";"Zergling";"Larva";814;1
"Unit";"Zergling";"Larva";814;1
"Unit";"Zergling";"Larva";814;1
"Unit";"Zergling";"Larva";814;1
"Unit";"Zergling";"Larva";814;1
"Unit";"Zergling";"Larva";814;1
"Unit";"Baneling";"Zergling";854;0
"Unit";"Baneling";"Zergling";854;0
"Unit";"Baneling";"Zergling";854;0
"Unit";"Baneling";"Zergling";854;0
"Unit";"Baneling";"Zergling";854;0
"Unit";"Baneling";"Zergling";854;0
"Building";"Hatchery";NA;716;0
"Unit";"Hydralisk";"Larva";854;2
"Unit";"Hydralisk";"Larva";854;2
"Unit";"Hydralisk";"Larva";854;2
"Unit";"Hydralisk";"Larva";854;2
"Unit";"Hydralisk";"Larva";854;2
"Unit";"Hydralisk";"Larva";854;2
"Unit";"Hydralisk";"Larva";854;2
"Unit";"Hydralisk";"Larva";854;2
"Unit";"Hydralisk";"Larva";854;2
"Unit";"Hydralisk";"Larva";854;2
"Unit";"Hydralisk";"Larva";854;2
"Unit";"Hydralisk";"Larva";854;2
"Unit";"Hydralisk";"Larva";854;2
"Unit";"Baneling";"Zergling";854;0
"Unit";"Baneling";"Zergling";854;0
"Unit";"Baneling";"Zergling";854;0
"Unit";"Baneling";"Zergling";854;0
"Unit";"Baneling";"Zergling";854;0
"Unit";"Baneling";"Zergling";854;0
"Unit";"Baneling";"Zergling";854;0
"Unit";"Baneling";"Zergling";854;0
"Unit";"Baneling";"Zergling";854;0
"Unit";"Baneling";"Zergling";854;0
"Unit";"Baneling";"Zergling";854;0
"Unit";"Baneling";"Zergling";854;0
"Unit";"Baneling";"Zergling";854;0
"Unit";"Baneling";"Zergling";854;0
"Unit";"Baneling";"Zergling";854;0
"Unit";"Baneling";"Zergling";854;0
"Unit";"Baneling";"Zergling";854;0
"Unit";"Baneling";"Zergling";854;0
"Unit";"Baneling";"Zergling";854;0
"Unit";"Baneling";"Zergling";854;0
"Unit";"Baneling";"Zergling";854;0
"Unit";"Baneling";"Zergling";854;0
"Unit";"Baneling";"Zergling";854;0
"Unit";"Baneling";"Zergling";854;0
"Unit";"Baneling";"Zergling";854;0
"Unit";"Baneling";"Zergling";854;0
"Unit";"Baneling";"Zergling";854;0
"Unit";"Corruptor";"Larva";854;2
"Unit";"Corruptor";"Larva";854;2
"Unit";"Corruptor";"Larva";854;2
"Unit";"Corruptor";"Larva";854;2
"Unit";"Corruptor";"Larva";854;2
"Unit";"Corruptor";"Larva";854;2
"Unit";"Corruptor";"Larva";854;2
"Unit";"Corruptor";"Larva";854;2
"Unit";"Corruptor";"Larva";854;2
"Unit";"Hydralisk";"Larva";854;2
"Unit";"Hydralisk";"Larva";854;2
"Unit";"Hydralisk";"Larva";854;2
"Building";"CreepTumorQueen";NA;904;0
"Unit";"Infestor";"Larva";904;2
"Unit";"Infestor";"Larva";904;2
"Unit";"Infestor";"Larva";904;2
"Unit";"Infestor";"Larva";904;2
"Unit";"Corruptor";"Larva";904;2
"Unit";"Corruptor";"Larva";904;2
"Unit";"Corruptor";"Larva";904;2
"Unit";"Corruptor";"Larva";904;2
"Building";"Extractor";NA;922;0
"Unit";"Zergling";"Larva";930;1
"Unit";"Zergling";"Larva";930;1
"Unit";"Zergling";"Larva";930;1
"Unit";"Zergling";"Larva";930;1
"Unit";"Zergling";"Larva";930;1
"Unit";"Zergling";"Larva";930;1
"Unit";"Zergling";"Larva";930;1
"Unit";"Zergling";"Larva";930;1
"Unit";"Zergling";"Larva";930;1
"Unit";"Zergling";"Larva";930;1
"Unit";"Zergling";"Larva";930;1
"Unit";"Zergling";"Larva";930;1
"Unit";"Zergling";"Larva";930;1
"Unit";"Zergling";"Larva";930;1
"Unit";"Zergling";"Larva";930;1
"Unit";"Zergling";"Larva";930;1
"Unit";"Zergling";"Larva";930;1
"Unit";"Zergling";"Larva";930;1
"Unit";"Zergling";"Larva";930;1
"Unit";"Zergling";"Larva";930;1
"Unit";"Zergling";"Larva";930;1
"Unit";"Zergling";"Larva";930;1
"Unit";"Zergling";"Larva";930;1
"Unit";"Zergling";"Larva";930;1
"Unit";"Zergling";"Larva";930;1
"Unit";"Zergling";"Larva";930;1
"Unit";"Zergling";"Larva";930;1
"Unit";"Zergling";"Larva";930;1
"Unit";"Zergling";"Larva";930;1
"Unit";"Zergling";"Larva";930;1
"Unit";"Zergling";"Larva";930;1
"Unit";"Zergling";"Larva";930;1
"Unit";"Zergling";"Larva";930;1
"Unit";"Zergling";"Larva";930;1
"Unit";"Zergling";"Larva";930;1
"Unit";"Zergling";"Larva";930;1
"Unit";"Zergling";"Larva";930;1
"Unit";"Zergling";"Larva";930;1
"Unit";"Zergling";"Larva";930;1
"Unit";"Zergling";"Larva";930;1
"Unit";"Zergling";"Larva";930;1
"Unit";"Zergling";"Larva";930;1
"Unit";"Zergling";"Larva";930;1
"Unit";"Zergling";"Larva";930;1
"Unit";"Zergling";"Larva";930;1
"Unit";"Zergling";"Larva";930;1
"Unit";"Zergling";"Larva";930;1
"Unit";"Zergling";"Larva";930;1
"Unit";"Baneling";"Zergling";978;0
"Unit";"Baneling";"Zergling";978;0
"Unit";"Baneling";"Zergling";978;0
"Unit";"Baneling";"Zergling";978;0
"Unit";"Baneling";"Zergling";978;0
"Unit";"Baneling";"Zergling";978;0
"Unit";"Baneling";"Zergling";978;0
"Unit";"Baneling";"Zergling";978;0
"Unit";"Baneling";"Zergling";978;0
"Building";"CreepTumor";NA;978;0
"Building";"SporeCrawler";NA;978;0
"Unit";"Zergling";"Larva";978;1
"Unit";"Zergling";"Larva";978;1
"Unit";"Zergling";"Larva";978;1
"Unit";"Zergling";"Larva";978;1
"Unit";"Zergling";"Larva";978;1
"Unit";"Zergling";"Larva";978;1
"Unit";"Zergling";"Larva";978;1
"Unit";"Zergling";"Larva";978;1
"Unit";"Zergling";"Larva";978;1
"Unit";"Zergling";"Larva";978;1
"Unit";"Viper";"Larva";938;3
"Unit";"Viper";"Larva";950;3
"Building";"SporeCrawler";NA;978;0
"Building";"Hatchery";NA;914;0
"Building";"CreepTumor";NA;988;0
"Building";"Extractor";NA;978;0
"Building";"SpineCrawler";NA;978;0
"Building";"SpineCrawler";NA;978;0
"Building";"SpineCrawler";NA;994;0
"Building";"SpineCrawler";NA;994;0
"Unit";"Zergling";"Larva";994;1
"Unit";"Zergling";"Larva";994;1
"Building";"SporeCrawler";NA;994;0
"Unit";"Zergling";"Larva";994;1
"Unit";"Zergling";"Larva";994;1
"Unit";"Zergling";"Larva";994;1
"Unit";"Zergling";"Larva";994;1
"Unit";"Zergling";"Larva";994;1
"Unit";"Zergling";"Larva";994;1
"Unit";"Zergling";"Larva";994;1
"Unit";"Zergling";"Larva";994;1
"Unit";"Zergling";"Larva";994;1
"Unit";"Zergling";"Larva";994;1
"Unit";"Zergling";"Larva";994;1
"Unit";"Zergling";"Larva";994;1
"Unit";"Zergling";"Larva";994;1
"Unit";"Zergling";"Larva";994;1
"Unit";"Zergling";"Larva";994;1
"Unit";"Zergling";"Larva";994;1
"Unit";"Zergling";"Larva";994;1
"Unit";"Zergling";"Larva";994;1
"Unit";"Zergling";"Larva";994;1
"Unit";"Zergling";"Larva";994;1
"Unit";"Zergling";"Larva";994;1
"Unit";"Zergling";"Larva";994;1
"Unit";"Zergling";"Larva";994;1
"Unit";"Zergling";"Larva";994;1
"Unit";"Zergling";"Larva";994;1
"Unit";"Zergling";"Larva";994;1
"Unit";"Zergling";"Larva";994;1
"Unit";"Zergling";"Larva";994;1
"Unit";"Zergling";"Larva";994;1
"Unit";"Zergling";"Larva";994;1
"Unit";"Zergling";"Larva";994;1
"Unit";"Zergling";"Larva";994;1
"Building";"SporeCrawler";NA;994;0
"Unit";"Zergling";"Larva";994;1
"Unit";"Zergling";"Larva";994;1
"Unit";"Zergling";"Larva";994;1
"Unit";"Zergling";"Larva";994;1
"Unit";"Zergling";"Larva";994;1
"Unit";"Zergling";"Larva";994;1
"Unit";"Zergling";"Larva";994;1
"Unit";"Zergling";"Larva";994;1
"Unit";"Zergling";"Larva";994;1
"Unit";"Zergling";"Larva";994;1
"Unit";"Zergling";"Larva";994;1
"Unit";"Zergling";"Larva";994;1
"Unit";"Zergling";"Larva";994;1
"Unit";"Zergling";"Larva";994;1
"Unit";"Zergling";"Larva";994;1
"Unit";"Zergling";"Larva";994;1
"Unit";"Zergling";"Larva";994;1
"Unit";"Zergling";"Larva";994;1
"Unit";"Zergling";"Larva";994;1
"Unit";"Zergling";"Larva";994;1
"Unit";"Zergling";"Larva";994;1
"Unit";"Zergling";"Larva";994;1
"Unit";"Zergling";"Larva";994;1
"Unit";"Zergling";"Larva";994;1
"Unit";"Zergling";"Larva";994;1
"Unit";"Zergling";"Larva";994;1
"Unit";"Zergling";"Larva";994;1
"Unit";"Zergling";"Larva";994;1
"Unit";"Zergling";"Larva";1056;1
"Unit";"Zergling";"Larva";1056;1
"Unit";"Zergling";"Larva";1056;1
"Unit";"Zergling";"Larva";1056;1
"Unit";"Zergling";"Larva";1056;1
"Unit";"Zergling";"Larva";1056;1
"Unit";"Zergling";"Larva";1056;1
"Unit";"Zergling";"Larva";1056;1
"Unit";"Zergling";"Larva";1056;1
"Unit";"Zergling";"Larva";1056;1
"Unit";"Zergling";"Larva";1056;1
"Unit";"Zergling";"Larva";1056;1
"Unit";"Zergling";"Larva";1056;1
"Unit";"Zergling";"Larva";1056;1
"Unit";"Hydralisk";"Larva";994;2
"Unit";"Zergling";"Larva";1056;1
"Unit";"Zergling";"Larva";1056;1
"Unit";"Hydralisk";"Larva";994;2
"Unit";"Hydralisk";"Larva";994;2
"Unit";"Hydralisk";"Larva";994;2
"Unit";"Hydralisk";"Larva";994;2
"Unit";"Hydralisk";"Larva";994;2
"Unit";"Hydralisk";"Larva";994;2
"Unit";"Hydralisk";"Larva";994;2
"Unit";"Hydralisk";"Larva";994;2
"Unit";"Hydralisk";"Larva";994;2
"Unit";"Baneling";"Zergling";1092;0
"Unit";"Baneling";"Zergling";1092;0
"Unit";"Baneling";"Zergling";1092;0
"Unit";"Baneling";"Zergling";1092;0
"Unit";"Baneling";"Zergling";1092;0
"Unit";"Baneling";"Zergling";1092;0
"Building";"CreepTumor";NA;1099;0
"Unit";"Zergling";"Larva";1099;1
"Unit";"Zergling";"Larva";1099;1
"Unit";"Zergling";"Larva";1099;1
"Unit";"Zergling";"Larva";1099;1
"Unit";"Zergling";"Larva";1099;1
"Unit";"Zergling";"Larva";1099;1
"Unit";"Zergling";"Larva";1099;1
"Unit";"Zergling";"Larva";1099;1
"Unit";"Zergling";"Larva";1099;1
"Unit";"Zergling";"Larva";1099;1
"Unit";"Zergling";"Larva";1099;1
"Unit";"Zergling";"Larva";1099;1
"Unit";"Zergling";"Larva";1099;1
"Unit";"Zergling";"Larva";1099;1
"Unit";"Zergling";"Larva";1099;1
"Unit";"Zergling";"Larva";1099;1
"Unit";"Zergling";"Larva";1099;1
"Unit";"Zergling";"Larva";1099;1
"Unit";"Zergling";"Larva";1099;1
"Unit";"Zergling";"Larva";1099;1
"Unit";"Zergling";"Larva";1099;1
"Unit";"Zergling";"Larva";1099;1
"Unit";"Zergling";"Larva";1099;1
"Unit";"Zergling";"Larva";1099;1
"Unit";"Zergling";"Larva";1099;1
"Unit";"Zergling";"Larva";1099;1
"Unit";"Zergling";"Larva";1099;1
"Unit";"Zergling";"Larva";1099;1
"Unit";"Zergling";"Larva";1099;1
"Unit";"Zergling";"Larva";1099;1
"Unit";"Zergling";"Larva";1099;1
"Unit";"Zergling";"Larva";1099;1
"Unit";"Zergling";"Larva";1099;1
"Unit";"Zergling";"Larva";1099;1
"Unit";"Zergling";"Larva";1099;1
"Unit";"Zergling";"Larva";1099;1
"Unit";"Queen";"Hatchery";1092;2
"Unit";"Queen";"Hatchery";1092;2
"Unit";"Queen";"Hatchery";1092;2
"Unit";"Queen";"Hatchery";1092;2
"Unit";"Zergling";"Larva";1135;1
"Unit";"Zergling";"Larva";1135;1
"Unit";"Zergling";"Larva";1135;1
"Unit";"Zergling";"Larva";1135;1
"Unit";"Zergling";"Larva";1135;1
"Unit";"Zergling";"Larva";1135;1
"Unit";"Zergling";"Larva";1135;1
"Unit";"Zergling";"Larva";1135;1
"Unit";"Zergling";"Larva";1137;1
"Unit";"Zergling";"Larva";1137;1
"Unit";"Zergling";"Larva";1137;1
"Unit";"Zergling";"Larva";1137;1
"Unit";"Zergling";"Larva";1137;1
"Unit";"Zergling";"Larva";1137;1
"Unit";"Zergling";"Larva";1139;1
"Unit";"Zergling";"Larva";1139;1
"Unit";"Zergling";"Larva";1139;1
"Unit";"Zergling";"Larva";1139;1
"Unit";"Zergling";"Larva";1139;1
"Unit";"Zergling";"Larva";1139;1
"Unit";"Zergling";"Larva";1139;1
"Unit";"Zergling";"Larva";1139;1
"Unit";"Zergling";"Larva";1141;1
"Unit";"Zergling";"Larva";1141;1
"Unit";"Zergling";"Larva";1141;1
"Unit";"Zergling";"Larva";1141;1
"Unit";"Zergling";"Larva";1141;1
"Unit";"Zergling";"Larva";1141;1
"Unit";"Zergling";"Larva";1141;1
"Unit";"Zergling";"Larva";1141;1
"Unit";"Zergling";"Larva";1141;1
"Unit";"Zergling";"Larva";1141;1
"Unit";"Zergling";"Larva";1141;1
"Unit";"Zergling";"Larva";1141;1
"Unit";"Zergling";"Larva";1143;1
"Unit";"Zergling";"Larva";1143;1
"Unit";"Zergling";"Larva";1143;1
"Unit";"Zergling";"Larva";1143;1
"Unit";"Zergling";"Larva";1143;1
"Unit";"Zergling";"Larva";1143;1
"Unit";"Zergling";"Larva";1143;1
"Unit";"Zergling";"Larva";1143;1
"Unit";"Zergling";"Larva";1143;1
"Unit";"Zergling";"Larva";1143;1
"Unit";"Baneling";"Zergling";1187;0
"Unit";"Baneling";"Zergling";1187;0
"Unit";"Baneling";"Zergling";1187;0
"Unit";"Baneling";"Zergling";1187;0
"Unit";"Baneling";"Zergling";1187;0
"Unit";"Baneling";"Zergling";1187;0
"Unit";"Baneling";"Zergling";1187;0
"Unit";"Baneling";"Zergling";1187;0
"Unit";"Baneling";"Zergling";1187;0
"Unit";"Baneling";"Zergling";1187;0
"Unit";"Baneling";"Zergling";1187;0
"Unit";"Baneling";"Zergling";1187;0
"Unit";"Baneling";"Zergling";1187;0
"Unit";"Baneling";"Zergling";1187;0
"Unit";"Zergling";"Larva";1187;1
"Unit";"Zergling";"Larva";1187;1
"Unit";"Zergling";"Larva";1187;1
"Unit";"Zergling";"Larva";1187;1
"Unit";"Zergling";"Larva";1187;1
"Unit";"Zergling";"Larva";1187;1
"Unit";"Zergling";"Larva";1187;1
"Unit";"Zergling";"Larva";1187;1
"Unit";"Zergling";"Larva";1187;1
"Unit";"Zergling";"Larva";1187;1
"Unit";"Zergling";"Larva";1187;1
"Unit";"Zergling";"Larva";1187;1
"Unit";"Zergling";"Larva";1187;1
"Unit";"Zergling";"Larva";1187;1
"Unit";"Zergling";"Larva";1187;1
"Unit";"Zergling";"Larva";1187;1
"Unit";"Zergling";"Larva";1187;1
"Unit";"Zergling";"Larva";1187;1
"Unit";"Zergling";"Larva";1187;1
"Unit";"Zergling";"Larva";1187;1
"Unit";"Zergling";"Larva";1187;1
"Unit";"Zergling";"Larva";1187;1
"Unit";"Zergling";"Larva";1187;1
"Unit";"Zergling";"Larva";1187;1
"Unit";"Zergling";"Larva";1187;1
"Unit";"Zergling";"Larva";1187;1
"Unit";"Zergling";"Larva";1187;1
"Unit";"Zergling";"Larva";1187;1
"Unit";"Zergling";"Larva";1187;1
"Unit";"Zergling";"Larva";1187;1
"Unit";"Zergling";"Larva";1187;1
"Unit";"Zergling";"Larva";1187;1
"Unit";"Zergling";"Larva";1187;1
"Unit";"Zergling";"Larva";1187;1
"Unit";"Zergling";"Larva";1187;1
"Unit";"Zergling";"Larva";1187;1
"Building";"SpineCrawler";NA;1187;0
"Building";"SpineCrawler";NA;1187;0
"Building";"SpineCrawler";NA;1187;0
"Building";"SpineCrawler";NA;1187;0
"Building";"SpineCrawler";NA;1187;0
"Building";"SpineCrawler";NA;1187;0
"Unit";"Hydralisk";"Larva";1223;2
"Unit";"Hydralisk";"Larva";1223;2
"Unit";"Hydralisk";"Larva";1223;2
"Unit";"Hydralisk";"Larva";1223;2
"Unit";"Hydralisk";"Larva";1223;2
"Unit";"Hydralisk";"Larva";1223;2
"Unit";"Hydralisk";"Larva";1223;2
"Unit";"Hydralisk";"Larva";1223;2
"Unit";"Hydralisk";"Larva";1223;2
"Unit";"Hydralisk";"Larva";1223;2
"Unit";"Zergling";"Larva";1223;1
"Unit";"Zergling";"Larva";1223;1
"Unit";"Zergling";"Larva";1223;1
"Unit";"Zergling";"Larva";1223;1
"Unit";"Zergling";"Larva";1223;1
"Unit";"Zergling";"Larva";1223;1
"Unit";"Zergling";"Larva";1223;1
"Unit";"Zergling";"Larva";1223;1
"Unit";"Zergling";"Larva";1223;1
"Unit";"Zergling";"Larva";1223;1
"Unit";"Zergling";"Larva";1223;1
"Unit";"Zergling";"Larva";1223;1
"Unit";"Zergling";"Larva";1223;1
"Unit";"Zergling";"Larva";1223;1
"Unit";"Zergling";"Larva";1223;1
"Unit";"Zergling";"Larva";1223;1
"Unit";"Zergling";"Larva";1223;1
"Unit";"Zergling";"Larva";1223;1
"Unit";"Zergling";"Larva";1223;1
"Unit";"Zergling";"Larva";1223;1
"Unit";"Zergling";"Larva";1223;1
"Unit";"Zergling";"Larva";1223;1
"Unit";"Zergling";"Larva";1223;1
"Unit";"Zergling";"Larva";1223;1
"Unit";"Zergling";"Larva";1223;1
"Unit";"Zergling";"Larva";1223;1
"Unit";"Zergling";"Larva";1223;1
"Unit";"Zergling";"Larva";1223;1
"Unit";"Zergling";"Larva";1223;1
"Unit";"Zergling";"Larva";1223;1
"Unit";"Zergling";"Larva";1223;1
"Unit";"Zergling";"Larva";1223;1
"Unit";"Zergling";"Larva";1223;1
"Unit";"Zergling";"Larva";1223;1
"Unit";"Zergling";"Larva";1223;1
"Unit";"Zergling";"Larva";1223;1
"Unit";"Zergling";"Larva";1223;1
"Unit";"Zergling";"Larva";1223;1
"Unit";"Zergling";"Larva";1223;1
"Unit";"Zergling";"Larva";1223;1
"Unit";"Zergling";"Larva";1223;1
"Unit";"Zergling";"Larva";1223;1
"Unit";"Zergling";"Larva";1223;1
"Unit";"Zergling";"Larva";1223;1
"Unit";"Zergling";"Larva";1223;1
"Unit";"Zergling";"Larva";1223;1
"Unit";"Zergling";"Larva";1223;1
"Unit";"Zergling";"Larva";1223;1
"Unit";"Zergling";"Larva";1223;1
"Unit";"Zergling";"Larva";1223;1
"Building";"CreepTumor";NA;1243;0
"Building";"CreepTumorQueen";NA;1243;0
"Unit";"Hydralisk";"Larva";1243;2
"Unit";"Hydralisk";"Larva";1243;2
"Unit";"Hydralisk";"Larva";1243;2
"Unit";"Hydralisk";"Larva";1243;2
"Unit";"Hydralisk";"Larva";1243;2
"Unit";"Hydralisk";"Larva";1245;2
"Unit";"Hydralisk";"Larva";1245;2
"Unit";"Hydralisk";"Larva";1245;2
"Building";"CreepTumorQueen";NA;1293;0
"Unit";"Zergling";"Larva";1293;1
"Unit";"Zergling";"Larva";1293;1
"Unit";"Zergling";"Larva";1293;1
"Unit";"Zergling";"Larva";1293;1
"Unit";"Zergling";"Larva";1293;1
"Unit";"Zergling";"Larva";1293;1
"Unit";"Zergling";"Larva";1293;1
"Unit";"Zergling";"Larva";1293;1
"Unit";"Zergling";"Larva";1293;1
"Unit";"Zergling";"Larva";1293;1
"Unit";"Zergling";"Larva";1293;1
"Unit";"Zergling";"Larva";1293;1
"Unit";"Zergling";"Larva";1293;1
"Unit";"Zergling";"Larva";1293;1
"Unit";"Zergling";"Larva";1293;1
"Unit";"Zergling";"Larva";1293;1
"Unit";"Zergling";"Larva";1293;1
"Unit";"Zergling";"Larva";1293;1
"Unit";"Zergling";"Larva";1293;1
"Unit";"Zergling";"Larva";1293;1
"Unit";"Zergling";"Larva";1293;1
"Unit";"Zergling";"Larva";1293;1
"Unit";"Queen";"Hatchery";1293;2
"Unit";"Queen";"Hatchery";1293;2
"Unit";"Queen";"Hatchery";1293;2
"Unit";"Queen";"Hatchery";1293;2
"Unit";"Queen";"Hatchery";1293;2
"Unit";"Corruptor";"Larva";1293;2
"Unit";"Corruptor";"Larva";1293;2
"Unit";"Hydralisk";"Larva";1331;2
"Unit";"Hydralisk";"Larva";1331;2
"Unit";"Hydralisk";"Larva";1331;2
"Unit";"Hydralisk";"Larva";1331;2
"Unit";"Hydralisk";"Larva";1331;2
"Building";"SpineCrawler";NA;1333;0
