"type";"unit_name";"on_building";"total_supply";"supply"
"Unit";"Overlord";"Larva";13;0
"Building";"Extractor";NA;18;0
"Building";"SpawningPool";NA;19;0
"Building";"Hatchery";NA;16;0
"Unit";"Overlord";"Larva";22;0
"Unit";"Zergling";"Larva";23;1
"Unit";"Zergling";"Larva";23;1
"Unit";"Zergling";"Larva";23;1
"Unit";"Zergling";"Larva";23;1
"Unit";"Queen";"Hatchery";23;2
"Unit";"Queen";"Hatchery";23;2
"Unit";"Overlord";"Larva";32;0
"Unit";"Queen";"Hatchery";35;2
"Unit";"Overlord";"Larva";38;0
"Building";"CreepTumorQueen";NA;44;0
"Unit";"Zergling";"Larva";44;1
"Unit";"Zergling";"Larva";44;1
"Unit";"Zergling";"Larva";44;1
"Unit";"Zergling";"Larva";44;1
"Unit";"Zergling";"Larva";44;1
"Unit";"Zergling";"Larva";44;1
"Unit";"Zergling";"Larva";44;1
"Unit";"Zergling";"Larva";44;1
"Unit";"Zergling";"Larva";44;1
"Unit";"Zergling";"Larva";44;1
"Unit";"Zergling";"Larva";44;1
"Unit";"Zergling";"Larva";44;1
"Building";"Hatchery";NA;35;0
"Building";"EvolutionChamber";NA;57;0
"Building";"CreepTumor";NA;57;0
"Building";"EvolutionChamber";NA;57;0
"Unit";"Overlord";"Larva";57;0
"Unit";"Queen";"Hatchery";57;2
"Building";"BanelingNest";NA;57;0
"Unit";"Overlord";"Larva";67;0
"Unit";"Zergling";"Larva";67;1
"Unit";"Zergling";"Larva";67;1
"Unit";"Zergling";"Larva";67;1
"Unit";"Zergling";"Larva";67;1
"Unit";"Zergling";"Larva";67;1
"Unit";"Zergling";"Larva";67;1
"Unit";"Zergling";"Larva";67;1
"Unit";"Zergling";"Larva";67;1
"Unit";"Zergling";"Larva";67;1
"Unit";"Zergling";"Larva";67;1
"Unit";"Zergling";"Larva";67;1
"Unit";"Zergling";"Larva";67;1
"Unit";"Zergling";"Larva";67;1
"Unit";"Zergling";"Larva";67;1
"Unit";"Zergling";"Larva";67;1
"Unit";"Zergling";"Larva";67;1
"Unit";"Overlord";"Larva";67;0
"Unit";"Zergling";"Larva";69;1
"Unit";"Zergling";"Larva";69;1
"Unit";"Overlord";"Larva";69;0
"Building";"CreepTumorQueen";NA;77;0
"Building";"CreepTumorQueen";NA;77;0
"Unit";"Baneling";"Zergling";77;0
"Unit";"Baneling";"Zergling";77;0
"Unit";"Baneling";"Zergling";77;0
"Unit";"Baneling";"Zergling";77;0
"Unit";"Baneling";"Zergling";77;0
"Unit";"Baneling";"Zergling";77;0
"Unit";"Baneling";"Zergling";77;0
"Unit";"Zergling";"Larva";85;1
"Unit";"Zergling";"Larva";85;1
"Unit";"Zergling";"Larva";85;1
"Unit";"Zergling";"Larva";85;1
"Unit";"Zergling";"Larva";85;1
"Unit";"Zergling";"Larva";85;1
"Unit";"Zergling";"Larva";85;1
"Unit";"Zergling";"Larva";85;1
"Building";"Extractor";NA;85;0
"Building";"Extractor";NA;85;0
"Building";"CreepTumor";NA;89;0
"Unit";"Queen";"Hatchery";104;2
"Building";"Extractor";NA;111;0
"Building";"Extractor";NA;111;0
"Building";"CreepTumorQueen";NA;120;0
"Building";"CreepTumorQueen";NA;120;0
"Building";"CreepTumor";NA;120;0
"Building";"CreepTumor";NA;120;0
"Building";"CreepTumorQueen";NA;125;0
"Building";"CreepTumorQueen";NA;128;0
"Unit";"Overlord";"Larva";123;0
"Unit";"Overlord";"Larva";123;0
"Unit";"Overlord";"Larva";125;0
"Unit";"Overlord";"Larva";126;0
"Unit";"Overlord";"Larva";128;0
"Unit";"Zergling";"Larva";128;1
"Unit";"Zergling";"Larva";128;1
"Unit";"Zergling";"Larva";128;1
"Unit";"Zergling";"Larva";128;1
"Unit";"Zergling";"Larva";128;1
"Unit";"Zergling";"Larva";128;1
"Unit";"Zergling";"Larva";139;1
"Unit";"Zergling";"Larva";139;1
"Unit";"Zergling";"Larva";139;1
"Unit";"Zergling";"Larva";139;1
"Unit";"Zergling";"Larva";139;1
"Unit";"Zergling";"Larva";139;1
"Unit";"Zergling";"Larva";139;1
"Unit";"Zergling";"Larva";139;1
"Unit";"Baneling";"Zergling";144;0
"Unit";"Baneling";"Zergling";144;0
"Unit";"Baneling";"Zergling";144;0
"Unit";"Baneling";"Zergling";144;0
"Unit";"Baneling";"Zergling";144;0
"Building";"CreepTumorQueen";NA;144;0
"Building";"CreepTumor";NA;144;0
"Building";"CreepTumorQueen";NA;144;0
"Building";"CreepTumor";NA;144;0
"Building";"CreepTumor";NA;144;0
"Building";"CreepTumor";NA;144;0
"Building";"CreepTumor";NA;144;0
"Building";"CreepTumorQueen";NA;144;0
"Building";"CreepTumorQueen";NA;152;0
"Building";"CreepTumor";NA;152;0
"Building";"CreepTumor";NA;152;0
"Building";"CreepTumor";NA;152;0
"Building";"Hatchery";NA;128;0
"Building";"HydraliskDen";NA;152;0
"Building";"CreepTumorQueen";NA;160;0
"Building";"CreepTumor";NA;160;0
"Building";"InfestationPit";NA;152;0
"Building";"CreepTumor";NA;160;0
"Building";"CreepTumor";NA;160;0
"Upgrade";"ZergGroundArmorsLevel1";"EvolutionChamber";128;0
"Upgrade";"ZergMeleeWeaponsLevel1";"EvolutionChamber";128;0
"Building";"CreepTumorQueen";NA;160;0
"Unit";"Overlord";"Larva";160;0
"Unit";"Overlord";"Larva";160;0
"Unit";"Overlord";"Larva";160;0
"Unit";"Zergling";"Larva";160;1
"Unit";"Zergling";"Larva";160;1
"Unit";"Zergling";"Larva";160;1
"Unit";"Zergling";"Larva";160;1
"Unit";"Zergling";"Larva";160;1
"Unit";"Zergling";"Larva";160;1
"Unit";"Zergling";"Larva";160;1
"Unit";"Zergling";"Larva";160;1
"Unit";"Zergling";"Larva";160;1
"Unit";"Zergling";"Larva";160;1
"Unit";"Zergling";"Larva";160;1
"Unit";"Zergling";"Larva";160;1
"Unit";"Zergling";"Larva";160;1
"Unit";"Zergling";"Larva";160;1
"Unit";"Zergling";"Larva";160;1
"Unit";"Zergling";"Larva";160;1
"Unit";"Zergling";"Larva";160;1
"Unit";"Zergling";"Larva";160;1
"Building";"CreepTumor";NA;160;0
"Building";"CreepTumor";NA;160;0
"Building";"CreepTumor";NA;160;0
"Building";"Extractor";NA;160;0
"Building";"Extractor";NA;160;0
"Unit";"Zergling";"Larva";184;1
"Unit";"Zergling";"Larva";184;1
"Unit";"Overlord";"Larva";182;0
"Unit";"Zergling";"Larva";184;1
"Unit";"Zergling";"Larva";184;1
"Unit";"Zergling";"Larva";184;1
"Unit";"Zergling";"Larva";184;1
"Unit";"Zergling";"Larva";184;1
"Unit";"Zergling";"Larva";184;1
"Unit";"Zergling";"Larva";184;1
"Unit";"Zergling";"Larva";184;1
"Unit";"Zergling";"Larva";184;1
"Unit";"Zergling";"Larva";184;1
"Unit";"Zergling";"Larva";184;1
"Unit";"Zergling";"Larva";184;1
"Building";"Hatchery";NA;152;0
"Building";"CreepTumor";NA;198;0
"Building";"CreepTumor";NA;198;0
"Building";"CreepTumor";NA;198;0
"Unit";"Hydralisk";"Larva";184;2
"Unit";"Hydralisk";"Larva";184;2
"Unit";"Hydralisk";"Larva";184;2
"Unit";"Hydralisk";"Larva";184;2
"Unit";"Hydralisk";"Larva";184;2
"Unit";"Hydralisk";"Larva";184;2
"Unit";"Hydralisk";"Larva";184;2
"Unit";"Hydralisk";"Larva";184;2
"Building";"CreepTumorQueen";NA;198;0
"Building";"CreepTumor";NA;198;0
"Building";"CreepTumorQueen";NA;198;0
"Unit";"Zergling";"Larva";198;1
"Unit";"Zergling";"Larva";198;1
"Unit";"Zergling";"Larva";198;1
"Unit";"Zergling";"Larva";198;1
"Unit";"Zergling";"Larva";198;1
"Unit";"Zergling";"Larva";198;1
"Unit";"Overlord";"Larva";198;0
"Building";"CreepTumor";NA;214;0
"Building";"CreepTumor";NA;214;0
"Building";"CreepTumorQueen";NA;214;0
"Building";"CreepTumor";NA;214;0
"Building";"Extractor";NA;198;0
"Building";"CreepTumorQueen";NA;220;0
"Unit";"Zergling";"Larva";220;1
"Unit";"Zergling";"Larva";220;1
"Upgrade";"EvolveMuscularAugments";"HydraliskDen";184;0
"Unit";"Zergling";"Larva";220;1
"Unit";"Zergling";"Larva";220;1
"Unit";"Zergling";"Larva";220;1
"Unit";"Zergling";"Larva";220;1
"Unit";"Zergling";"Larva";220;1
"Unit";"Zergling";"Larva";220;1
"Unit";"Zergling";"Larva";220;1
"Unit";"Zergling";"Larva";220;1
"Unit";"Zergling";"Larva";220;1
"Unit";"Zergling";"Larva";220;1
"Unit";"Zergling";"Larva";220;1
"Unit";"Zergling";"Larva";220;1
"Unit";"Zergling";"Larva";220;1
"Unit";"Zergling";"Larva";220;1
"Building";"CreepTumor";NA;220;0
"Unit";"Zergling";"Larva";220;1
"Unit";"Zergling";"Larva";220;1
"Unit";"Queen";"Hatchery";214;2
"Unit";"Baneling";"Zergling";220;0
"Unit";"Baneling";"Zergling";220;0
"Unit";"Baneling";"Zergling";220;0
"Unit";"Baneling";"Zergling";220;0
"Unit";"Baneling";"Zergling";220;0
"Unit";"Baneling";"Zergling";220;0
"Unit";"Baneling";"Zergling";220;0
"Unit";"Baneling";"Zergling";220;0
"Unit";"Baneling";"Zergling";220;0
"Unit";"Baneling";"Zergling";220;0
"Unit";"Baneling";"Zergling";220;0
"Unit";"Baneling";"Zergling";220;0
"Building";"CreepTumor";NA;240;0
"Building";"CreepTumor";NA;240;0
"Building";"CreepTumor";NA;240;0
"Unit";"Overlord";"Larva";240;0
"Unit";"Overlord";"Larva";240;0
"Unit";"Overlord";"Larva";240;0
"Building";"CreepTumor";NA;240;0
"Unit";"Overlord";"Larva";240;0
"Unit";"Overlord";"Larva";240;0
"Unit";"Zergling";"Larva";240;1
"Unit";"Zergling";"Larva";240;1
"Building";"CreepTumor";NA;240;0
"Unit";"Overlord";"Larva";240;0
"Unit";"Overlord";"Larva";240;0
"Building";"CreepTumor";NA;240;0
"Unit";"Zergling";"Larva";240;1
"Unit";"Zergling";"Larva";240;1
"Unit";"Zergling";"Larva";240;1
"Unit";"Zergling";"Larva";240;1
"Unit";"Zergling";"Larva";240;1
"Unit";"Zergling";"Larva";240;1
"Unit";"Zergling";"Larva";240;1
"Unit";"Zergling";"Larva";240;1
"Building";"CreepTumor";NA;240;0
"Unit";"Zergling";"Larva";240;1
"Unit";"Zergling";"Larva";240;1
"Unit";"Zergling";"Larva";240;1
"Unit";"Zergling";"Larva";240;1
"Unit";"Zergling";"Larva";240;1
"Unit";"Zergling";"Larva";240;1
"Unit";"Zergling";"Larva";240;1
"Unit";"Zergling";"Larva";240;1
"Unit";"Zergling";"Larva";240;1
"Unit";"Zergling";"Larva";240;1
"Unit";"Zergling";"Larva";240;1
"Unit";"Zergling";"Larva";240;1
"Building";"CreepTumor";NA;240;0
"Building";"CreepTumor";NA;240;0
"Unit";"Zergling";"Larva";240;1
"Unit";"Zergling";"Larva";240;1
"Unit";"Zergling";"Larva";240;1
"Unit";"Zergling";"Larva";240;1
"Unit";"Zergling";"Larva";240;1
"Unit";"Zergling";"Larva";240;1
"Unit";"Zergling";"Larva";240;1
"Unit";"Zergling";"Larva";240;1
"Unit";"Zergling";"Larva";240;1
"Unit";"Zergling";"Larva";240;1
"Unit";"Zergling";"Larva";240;1
"Unit";"Zergling";"Larva";240;1
"Unit";"Zergling";"Larva";240;1
"Unit";"Zergling";"Larva";240;1
"Unit";"Zergling";"Larva";240;1
"Unit";"Zergling";"Larva";240;1
"Unit";"Zergling";"Larva";240;1
"Unit";"Zergling";"Larva";240;1
"Unit";"Zergling";"Larva";240;1
"Unit";"Zergling";"Larva";240;1
"Unit";"Zergling";"Larva";240;1
"Unit";"Zergling";"Larva";240;1
"Unit";"Zergling";"Larva";240;1
"Unit";"Zergling";"Larva";240;1
"Unit";"Zergling";"Larva";262;1
"Unit";"Zergling";"Larva";262;1
"Unit";"Zergling";"Larva";262;1
"Unit";"Zergling";"Larva";262;1
"Unit";"Zergling";"Larva";262;1
"Unit";"Zergling";"Larva";262;1
"Unit";"Zergling";"Larva";262;1
"Unit";"Zergling";"Larva";262;1
"Unit";"Zergling";"Larva";262;1
"Unit";"Zergling";"Larva";262;1
"Unit";"Zergling";"Larva";262;1
"Unit";"Zergling";"Larva";262;1
"Unit";"Zergling";"Larva";262;1
"Unit";"Zergling";"Larva";262;1
"Unit";"Zergling";"Larva";262;1
"Unit";"Zergling";"Larva";262;1
"Building";"UltraliskCavern";NA;240;0
"Upgrade";"ZergMeleeWeaponsLevel2";"EvolutionChamber";198;0
"Upgrade";"ZergGroundArmorsLevel2";"EvolutionChamber";198;0
"Unit";"Zergling";"Larva";286;1
"Unit";"Zergling";"Larva";286;1
"Unit";"Zergling";"Larva";286;1
"Unit";"Zergling";"Larva";286;1
"Unit";"Zergling";"Larva";286;1
"Unit";"Zergling";"Larva";286;1
"Unit";"Zergling";"Larva";286;1
"Unit";"Zergling";"Larva";286;1
"Unit";"Zergling";"Larva";286;1
"Unit";"Zergling";"Larva";286;1
"Unit";"Zergling";"Larva";286;1
"Unit";"Zergling";"Larva";286;1
"Unit";"Zergling";"Larva";286;1
"Unit";"Zergling";"Larva";286;1
"Upgrade";"EvolveGroovedSpines";"HydraliskDen";240;0
"Unit";"Zergling";"Larva";302;1
"Unit";"Zergling";"Larva";302;1
"Unit";"Zergling";"Larva";302;1
"Unit";"Zergling";"Larva";302;1
"Unit";"Zergling";"Larva";302;1
"Unit";"Zergling";"Larva";302;1
"Unit";"Zergling";"Larva";302;1
"Unit";"Zergling";"Larva";302;1
"Unit";"Zergling";"Larva";302;1
"Unit";"Zergling";"Larva";302;1
"Unit";"Zergling";"Larva";302;1
"Unit";"Zergling";"Larva";302;1
"Unit";"Zergling";"Larva";328;1
"Unit";"Zergling";"Larva";328;1
"Unit";"Zergling";"Larva";328;1
"Unit";"Zergling";"Larva";328;1
"Unit";"Zergling";"Larva";328;1
"Unit";"Zergling";"Larva";328;1
"Unit";"Ultralisk";"Larva";302;6
"Unit";"Ultralisk";"Larva";302;6
"Unit";"Ultralisk";"Larva";302;6
"Unit";"Ultralisk";"Larva";302;6
"Unit";"Ultralisk";"Larva";316;6
"Unit";"Hydralisk";"Larva";328;2
"Unit";"Hydralisk";"Larva";328;2
"Unit";"Ultralisk";"Larva";316;6
"Unit";"Ultralisk";"Larva";328;6
"Unit";"Hydralisk";"Larva";334;2
"Unit";"Hydralisk";"Larva";334;2
"Unit";"Hydralisk";"Larva";334;2
"Unit";"Hydralisk";"Larva";334;2
"Unit";"Hydralisk";"Larva";334;2
"Unit";"Hydralisk";"Larva";334;2
"Unit";"Hydralisk";"Larva";334;2
"Unit";"Hydralisk";"Larva";334;2
"Unit";"Hydralisk";"Larva";334;2
"Unit";"Baneling";"Zergling";374;0
"Unit";"Baneling";"Zergling";374;0
"Unit";"Baneling";"Zergling";374;0
"Unit";"Baneling";"Zergling";380;0
"Unit";"Baneling";"Zergling";380;0
"Unit";"Zergling";"Larva";380;1
"Unit";"Zergling";"Larva";380;1
"Unit";"Zergling";"Larva";380;1
"Unit";"Zergling";"Larva";380;1
"Unit";"Zergling";"Larva";380;1
"Unit";"Zergling";"Larva";380;1
"Unit";"Zergling";"Larva";380;1
"Unit";"Zergling";"Larva";380;1
"Unit";"Zergling";"Larva";380;1
"Unit";"Zergling";"Larva";380;1
"Unit";"Zergling";"Larva";380;1
"Unit";"Zergling";"Larva";380;1
"Unit";"Zergling";"Larva";380;1
"Unit";"Zergling";"Larva";380;1
"Unit";"Zergling";"Larva";380;1
"Unit";"Zergling";"Larva";380;1
"Unit";"Zergling";"Larva";380;1
"Unit";"Zergling";"Larva";380;1
"Unit";"Zergling";"Larva";380;1
"Unit";"Zergling";"Larva";380;1
"Upgrade";"ChitinousPlating";"UltraliskCavern";328;0
"Building";"CreepTumor";NA;418;0
"Building";"CreepTumor";NA;418;0
"Unit";"Ultralisk";"Larva";380;6
"Building";"CreepTumor";NA;418;0
"Building";"CreepTumor";NA;418;0
"Building";"CreepTumor";NA;418;0
"Building";"CreepTumor";NA;418;0
"Building";"CreepTumor";NA;418;0
"Building";"CreepTumor";NA;418;0
"Building";"CreepTumorQueen";NA;418;0
"Unit";"Ultralisk";"Larva";398;6
"Building";"CreepTumorQueen";NA;418;0
"Building";"CreepTumorQueen";NA;424;0
"Building";"CreepTumorQueen";NA;424;0
"Building";"CreepTumorQueen";NA;424;0
"Unit";"Zergling";"Larva";424;1
"Unit";"Zergling";"Larva";424;1
"Building";"CreepTumorQueen";NA;424;0
"Unit";"Zergling";"Larva";424;1
"Unit";"Zergling";"Larva";424;1
"Unit";"Zergling";"Larva";424;1
"Unit";"Zergling";"Larva";424;1
"Unit";"Zergling";"Larva";424;1
"Unit";"Zergling";"Larva";424;1
"Unit";"Zergling";"Larva";424;1
"Unit";"Zergling";"Larva";424;1
"Unit";"Zergling";"Larva";424;1
"Unit";"Zergling";"Larva";424;1
"Unit";"Zergling";"Larva";424;1
"Unit";"Zergling";"Larva";424;1
"Unit";"Zergling";"Larva";424;1
"Unit";"Zergling";"Larva";424;1
"Unit";"Zergling";"Larva";424;1
"Unit";"Zergling";"Larva";424;1
"Unit";"Zergling";"Larva";424;1
"Unit";"Zergling";"Larva";424;1
"Unit";"Zergling";"Larva";424;1
"Unit";"Zergling";"Larva";424;1
"Unit";"Zergling";"Larva";424;1
"Unit";"Zergling";"Larva";424;1
"Unit";"Zergling";"Larva";424;1
"Unit";"Zergling";"Larva";424;1
"Unit";"Zergling";"Larva";424;1
"Unit";"Zergling";"Larva";424;1
"Unit";"Zergling";"Larva";424;1
"Unit";"Zergling";"Larva";424;1
"Unit";"Zergling";"Larva";424;1
"Unit";"Zergling";"Larva";424;1
"Unit";"Zergling";"Larva";424;1
"Unit";"Zergling";"Larva";424;1
"Unit";"Zergling";"Larva";424;1
"Unit";"Zergling";"Larva";424;1
"Unit";"Baneling";"Zergling";424;0
"Unit";"Baneling";"Zergling";424;0
"Unit";"Baneling";"Zergling";424;0
"Unit";"Baneling";"Zergling";424;0
"Unit";"Baneling";"Zergling";424;0
"Unit";"Baneling";"Zergling";424;0
"Unit";"Baneling";"Zergling";424;0
"Unit";"Baneling";"Zergling";424;0
"Unit";"Baneling";"Zergling";424;0
"Unit";"Zergling";"Larva";424;1
"Unit";"Zergling";"Larva";424;1
"Unit";"Zergling";"Larva";424;1
"Unit";"Zergling";"Larva";424;1
"Unit";"Queen";"Hatchery";418;2
"Unit";"Baneling";"Zergling";472;0
"Unit";"Baneling";"Zergling";472;0
"Unit";"Baneling";"Zergling";472;0
"Unit";"Baneling";"Zergling";472;0
"Unit";"Baneling";"Zergling";472;0
"Unit";"Baneling";"Zergling";472;0
"Unit";"Baneling";"Zergling";472;0
"Unit";"Baneling";"Zergling";472;0
"Unit";"Baneling";"Zergling";472;0
"Unit";"Baneling";"Zergling";472;0
"Unit";"Baneling";"Zergling";472;0
"Building";"Extractor";NA;472;0
"Building";"Extractor";NA;472;0
"Upgrade";"ZergMeleeWeaponsLevel3";"EvolutionChamber";374;0
"Upgrade";"ZergGroundArmorsLevel3";"EvolutionChamber";374;0
"Building";"Hatchery";NA;424;0
"Unit";"Zergling";"Larva";472;1
"Unit";"Zergling";"Larva";472;1
"Unit";"Zergling";"Larva";472;1
"Unit";"Zergling";"Larva";472;1
"Unit";"Zergling";"Larva";472;1
"Unit";"Zergling";"Larva";472;1
"Unit";"Zergling";"Larva";472;1
"Unit";"Zergling";"Larva";472;1
"Unit";"Zergling";"Larva";472;1
"Unit";"Zergling";"Larva";472;1
"Unit";"Zergling";"Larva";472;1
"Unit";"Zergling";"Larva";472;1
"Unit";"Zergling";"Larva";472;1
"Unit";"Zergling";"Larva";472;1
"Unit";"Zergling";"Larva";472;1
"Unit";"Zergling";"Larva";472;1
"Unit";"Zergling";"Larva";472;1
"Unit";"Zergling";"Larva";472;1
"Unit";"Ultralisk";"Larva";472;6
"Unit";"Ultralisk";"Larva";472;6
"Unit";"Ultralisk";"Larva";472;6
"Unit";"Ultralisk";"Larva";472;6
"Unit";"Ultralisk";"Larva";472;6
"Unit";"Ultralisk";"Larva";472;6
"Upgrade";"NeuralParasite";"InfestationPit";472;0
"Unit";"Zergling";"Larva";526;1
"Unit";"Zergling";"Larva";526;1
"Unit";"Zergling";"Larva";526;1
"Unit";"Zergling";"Larva";526;1
"Unit";"Zergling";"Larva";526;1
"Unit";"Zergling";"Larva";526;1
"Unit";"Zergling";"Larva";526;1
"Unit";"Zergling";"Larva";526;1
"Unit";"Zergling";"Larva";526;1
"Unit";"Zergling";"Larva";526;1
"Building";"CreepTumor";NA;526;0
"Building";"CreepTumor";NA;526;0
"Building";"CreepTumor";NA;526;0
"Building";"CreepTumor";NA;526;0
"Building";"CreepTumor";NA;526;0
"Building";"CreepTumor";NA;526;0
"Unit";"Ultralisk";"Larva";508;6
"Unit";"Ultralisk";"Larva";508;6
"Unit";"Ultralisk";"Larva";508;6
"Unit";"Ultralisk";"Larva";508;6
"Unit";"Zergling";"Larva";536;1
"Unit";"Zergling";"Larva";536;1
"Unit";"Zergling";"Larva";536;1
"Unit";"Zergling";"Larva";536;1
"Unit";"Zergling";"Larva";536;1
"Unit";"Zergling";"Larva";536;1
"Unit";"Zergling";"Larva";536;1
"Unit";"Zergling";"Larva";536;1
"Unit";"Zergling";"Larva";536;1
"Unit";"Zergling";"Larva";536;1
"Unit";"Zergling";"Larva";536;1
"Unit";"Zergling";"Larva";536;1
"Unit";"Zergling";"Larva";536;1
"Unit";"Zergling";"Larva";536;1
"Unit";"Zergling";"Larva";536;1
"Unit";"Zergling";"Larva";536;1
"Unit";"Baneling";"Zergling";560;0
"Unit";"Baneling";"Zergling";560;0
"Unit";"Baneling";"Zergling";560;0
"Unit";"Baneling";"Zergling";560;0
"Unit";"Baneling";"Zergling";560;0
"Unit";"Baneling";"Zergling";560;0
"Unit";"Baneling";"Zergling";560;0
"Unit";"Baneling";"Zergling";560;0
"Unit";"Baneling";"Zergling";560;0
"Unit";"Baneling";"Zergling";560;0
"Unit";"Baneling";"Zergling";560;0
"Unit";"Baneling";"Zergling";560;0
"Unit";"Baneling";"Zergling";560;0
