"type";"unit_name";"on_building";"total_supply";"supply"
"Unit";"Overlord";"Larva";12;0
"Building";"Extractor";NA;21;0
"Building";"SpawningPool";NA;19;0
"Building";"Hatchery";NA;16;0
"Unit";"Overlord";"Larva";22;0
"Unit";"Zergling";"Larva";23;1
"Unit";"Zergling";"Larva";23;1
"Unit";"Zergling";"Larva";23;1
"Unit";"Zergling";"Larva";23;1
"Unit";"Queen";"Hatchery";23;2
"Unit";"Queen";"Hatchery";23;2
"Building";"RoachWarren";NA;23;0
"Unit";"Overlord";"Larva";29;0
"Unit";"Roach";"Larva";34;2
"Unit";"Roach";"Larva";34;2
"Unit";"Roach";"Larva";34;2
"Unit";"Roach";"Larva";34;2
"Unit";"Roach";"Larva";34;2
"Unit";"Roach";"Larva";34;2
"Unit";"Roach";"Larva";42;2
"Unit";"Roach";"Larva";42;2
"Unit";"Overlord";"Larva";46;0
"Unit";"Overlord";"Larva";51;0
"Unit";"Roach";"Larva";51;2
"Unit";"Roach";"Larva";51;2
"Unit";"Roach";"Larva";51;2
"Building";"Extractor";NA;65;0
"Building";"Extractor";NA;65;0
"Building";"Extractor";NA;65;0
"Unit";"Overlord";"Larva";76;0
"Unit";"Overlord";"Larva";76;0
"Unit";"Roach";"Larva";76;2
"Unit";"Roach";"Larva";76;2
"Unit";"Roach";"Larva";76;2
"Unit";"Roach";"Larva";76;2
"Unit";"Queen";"Hatchery";76;2
"Unit";"Queen";"Hatchery";76;2
"Unit";"Overlord";"Larva";80;0
"Unit";"Overlord";"Larva";81;0
"Unit";"Overlord";"Larva";81;0
"Unit";"Roach";"Larva";93;2
"Unit";"Roach";"Larva";93;2
"Unit";"Roach";"Larva";93;2
"Unit";"Roach";"Larva";93;2
"Unit";"Roach";"Larva";93;2
"Unit";"Roach";"Larva";93;2
"Unit";"Roach";"Larva";93;2
"Building";"CreepTumorQueen";NA;93;0
"Building";"CreepTumorQueen";NA;93;0
"Unit";"Roach";"Larva";107;2
"Unit";"Roach";"Larva";107;2
"Unit";"Roach";"Larva";107;2
"Unit";"Roach";"Larva";107;2
"Unit";"Roach";"Larva";107;2
"Unit";"Roach";"Larva";107;2
"Unit";"Roach";"Larva";107;2
"Unit";"Roach";"Larva";122;2
"Unit";"Roach";"Larva";122;2
"Unit";"Roach";"Larva";122;2
"Unit";"Roach";"Larva";122;2
"Unit";"Roach";"Larva";122;2
"Building";"CreepTumor";NA;122;0
"Building";"CreepTumor";NA;132;0
"Building";"HydraliskDen";NA;122;0
"Unit";"Overlord";"Larva";132;0
"Unit";"Overlord";"Larva";132;0
"Unit";"Overlord";"Larva";132;0
"Unit";"Overlord";"Larva";132;0
"Building";"CreepTumor";NA;132;0
"Building";"CreepTumor";NA;132;0
"Unit";"Overlord";"Larva";132;0
"Unit";"Overlord";"Larva";132;0
"Unit";"Hydralisk";"Larva";132;2
"Unit";"Hydralisk";"Larva";132;2
"Unit";"Hydralisk";"Larva";132;2
"Unit";"Hydralisk";"Larva";132;2
"Unit";"Hydralisk";"Larva";132;2
"Unit";"Hydralisk";"Larva";132;2
"Unit";"Hydralisk";"Larva";132;2
"Unit";"Hydralisk";"Larva";132;2
"Unit";"Hydralisk";"Larva";132;2
"Unit";"Hydralisk";"Larva";132;2
"Upgrade";"GlialReconstitution";"RoachWarren";132;0
"Building";"Hatchery";NA;132;0
"Upgrade";"EvolveMuscularAugments";"HydraliskDen";132;0
"Unit";"Hydralisk";"Larva";152;2
"Unit";"Hydralisk";"Larva";152;2
"Unit";"Hydralisk";"Larva";152;2
"Unit";"Hydralisk";"Larva";152;2
"Unit";"Hydralisk";"Larva";152;2
"Unit";"Hydralisk";"Larva";152;2
"Unit";"Hydralisk";"Larva";152;2
"Unit";"Hydralisk";"Larva";152;2
"Unit";"Hydralisk";"Larva";152;2
"Unit";"Hydralisk";"Larva";152;2
"Unit";"Overlord";"Larva";179;0
"Unit";"Overlord";"Larva";179;0
"Building";"Extractor";NA;179;0
"Building";"Extractor";NA;179;0
"Building";"Spire";NA;152;0
"Unit";"Mutalisk";"Larva";190;2
"Unit";"Mutalisk";"Larva";190;2
"Unit";"Mutalisk";"Larva";190;2
"Unit";"Mutalisk";"Larva";190;2
"Unit";"Mutalisk";"Larva";190;2
"Unit";"Mutalisk";"Larva";190;2
"Unit";"Mutalisk";"Larva";190;2
"Unit";"Mutalisk";"Larva";190;2
"Unit";"Mutalisk";"Larva";190;2
"Unit";"Mutalisk";"Larva";190;2
"Unit";"Mutalisk";"Larva";190;2
"Building";"CreepTumor";NA;190;0
"Unit";"Mutalisk";"Larva";190;2
"Building";"CreepTumor";NA;190;0
"Unit";"Mutalisk";"Larva";212;2
"Unit";"Mutalisk";"Larva";212;2
"Unit";"Mutalisk";"Larva";212;2
"Unit";"Mutalisk";"Larva";212;2
"Building";"CreepTumor";NA;222;0
"Unit";"Mutalisk";"Larva";222;2
"Unit";"Mutalisk";"Larva";222;2
"Unit";"Mutalisk";"Larva";222;2
"Unit";"Mutalisk";"Larva";222;2
"Unit";"Mutalisk";"Larva";222;2
"Building";"CreepTumor";NA;222;0
"Building";"Hatchery";NA;190;0
"Unit";"Overlord";"Larva";222;0
"Unit";"Overlord";"Larva";222;0
"Unit";"Overlord";"Larva";222;0
"Unit";"Overlord";"Larva";222;0
"Unit";"Overlord";"Larva";222;0
"Building";"Extractor";NA;232;0
"Building";"Extractor";NA;232;0
"Unit";"Mutalisk";"Larva";232;2
"Unit";"Mutalisk";"Larva";232;2
"Unit";"Mutalisk";"Larva";232;2
"Unit";"Mutalisk";"Larva";232;2
"Unit";"Mutalisk";"Larva";232;2
"Unit";"Mutalisk";"Larva";232;2
"Unit";"Mutalisk";"Larva";232;2
"Building";"CreepTumor";NA;246;0
"Unit";"Mutalisk";"Larva";232;2
"Unit";"Mutalisk";"Larva";232;2
"Building";"CreepTumor";NA;246;0
"Unit";"Mutalisk";"Larva";232;2
"Building";"CreepTumor";NA;257;0
"Unit";"Mutalisk";"Larva";252;2
"Unit";"Mutalisk";"Larva";252;2
"Unit";"Mutalisk";"Larva";252;2
"Unit";"Mutalisk";"Larva";252;2
"Unit";"Mutalisk";"Larva";252;2
"Building";"CreepTumor";NA;257;0
"Building";"CreepTumorQueen";NA;258;0
"Building";"CreepTumorQueen";NA;258;0
"Building";"CreepTumor";NA;268;0
"Unit";"Mutalisk";"Larva";266;2
"Unit";"Mutalisk";"Larva";268;2
"Unit";"Mutalisk";"Larva";268;2
"Unit";"Mutalisk";"Larva";268;2
"Unit";"Mutalisk";"Larva";268;2
"Building";"Extractor";NA;268;0
"Building";"Extractor";NA;268;0
"Unit";"Mutalisk";"Larva";280;2
"Unit";"Mutalisk";"Larva";280;2
"Unit";"Mutalisk";"Larva";280;2
"Unit";"Mutalisk";"Larva";280;2
"Unit";"Mutalisk";"Larva";280;2
"Unit";"Mutalisk";"Larva";280;2
