"type";"unit_name";"on_building";"total_supply";"supply"
"Unit";"Overlord";"Larva";13;0
"Building";"Extractor";NA;18;0
"Unit";"Overlord";"Larva";21;0
"Building";"SpawningPool";NA;19;0
"Building";"Hatchery";NA;17;0
"Unit";"Zergling";"Larva";23;1
"Unit";"Zergling";"Larva";23;1
"Unit";"Zergling";"Larva";24;1
"Unit";"Zergling";"Larva";24;1
"Unit";"Queen";"Hatchery";22;2
"Unit";"Queen";"Hatchery";23;2
"Unit";"Overlord";"Larva";35;0
"Unit";"Queen";"Hatchery";35;2
"Unit";"Overlord";"Larva";39;0
"Building";"CreepTumorQueen";NA;46;0
"Building";"Hatchery";NA;35;0
"Unit";"Queen";"Hatchery";41;2
"Unit";"Overlord";"Larva";48;0
"Unit";"Overlord";"Larva";48;0
"Building";"CreepTumorQueen";NA;54;0
"Building";"CreepTumor";NA;54;0
"Building";"CreepTumorQueen";NA;54;0
"Unit";"Queen";"Hatchery";48;2
"Unit";"Overlord";"Larva";54;0
"Building";"Extractor";NA;54;0
"Unit";"Overlord";"Larva";62;0
"Building";"CreepTumorQueen";NA;64;0
"Building";"CreepTumorQueen";NA;64;0
"Unit";"Zergling";"Larva";62;1
"Unit";"Zergling";"Larva";62;1
"Unit";"Zergling";"Larva";62;1
"Unit";"Zergling";"Larva";62;1
"Unit";"Zergling";"Larva";62;1
"Unit";"Zergling";"Larva";62;1
"Unit";"Zergling";"Larva";62;1
"Unit";"Zergling";"Larva";62;1
"Unit";"Zergling";"Larva";62;1
"Unit";"Zergling";"Larva";62;1
"Building";"CreepTumor";NA;64;0
"Building";"CreepTumor";NA;64;0
"Building";"CreepTumor";NA;64;0
"Building";"BanelingNest";NA;54;0
"Unit";"Zergling";"Larva";72;1
"Unit";"Zergling";"Larva";72;1
"Unit";"Zergling";"Larva";74;1
"Unit";"Zergling";"Larva";74;1
"Unit";"Zergling";"Larva";74;1
"Unit";"Zergling";"Larva";74;1
"Unit";"Zergling";"Larva";74;1
"Unit";"Zergling";"Larva";74;1
"Unit";"Zergling";"Larva";74;1
"Unit";"Zergling";"Larva";74;1
"Unit";"Zergling";"Larva";76;1
"Unit";"Zergling";"Larva";76;1
"Unit";"Zergling";"Larva";76;1
"Unit";"Zergling";"Larva";76;1
"Unit";"Zergling";"Larva";76;1
"Unit";"Zergling";"Larva";76;1
"Unit";"Zergling";"Larva";76;1
"Unit";"Zergling";"Larva";76;1
"Building";"CreepTumor";NA;87;0
"Building";"CreepTumor";NA;87;0
"Building";"CreepTumor";NA;87;0
"Building";"CreepTumor";NA;87;0
"Building";"CreepTumor";NA;87;0
"Building";"EvolutionChamber";NA;77;0
"Building";"EvolutionChamber";NA;85;0
"Unit";"Baneling";"Zergling";101;0
"Unit";"Baneling";"Zergling";101;0
"Unit";"Baneling";"Zergling";101;0
"Building";"CreepTumor";NA;106;0
"Building";"CreepTumor";NA;106;0
"Building";"CreepTumor";NA;106;0
"Building";"CreepTumor";NA;106;0
"Unit";"Zergling";"Larva";106;1
"Unit";"Zergling";"Larva";106;1
"Unit";"Zergling";"Larva";106;1
"Unit";"Zergling";"Larva";106;1
"Unit";"Overlord";"Larva";106;0
"Unit";"Overlord";"Larva";106;0
"Unit";"Overlord";"Larva";106;0
"Building";"CreepTumorQueen";NA;106;0
"Building";"Extractor";NA;106;0
"Building";"Extractor";NA;106;0
"Building";"CreepTumorQueen";NA;110;0
"Building";"CreepTumorQueen";NA;110;0
"Unit";"Zergling";"Larva";110;1
"Unit";"Zergling";"Larva";110;1
"Unit";"Zergling";"Larva";110;1
"Unit";"Zergling";"Larva";110;1
"Unit";"Zergling";"Larva";110;1
"Unit";"Zergling";"Larva";110;1
"Unit";"Zergling";"Larva";110;1
"Unit";"Zergling";"Larva";110;1
"Unit";"Zergling";"Larva";110;1
"Unit";"Zergling";"Larva";110;1
"Unit";"Zergling";"Larva";110;1
"Unit";"Zergling";"Larva";110;1
"Unit";"Zergling";"Larva";110;1
"Unit";"Zergling";"Larva";110;1
"Unit";"Zergling";"Larva";110;1
"Unit";"Zergling";"Larva";110;1
"Unit";"Zergling";"Larva";110;1
"Unit";"Zergling";"Larva";110;1
"Unit";"Zergling";"Larva";110;1
"Unit";"Zergling";"Larva";110;1
"Unit";"Zergling";"Larva";110;1
"Unit";"Zergling";"Larva";110;1
"Unit";"Zergling";"Larva";110;1
"Unit";"Zergling";"Larva";110;1
"Unit";"Zergling";"Larva";110;1
"Unit";"Zergling";"Larva";110;1
"Building";"CreepTumorQueen";NA;145;0
"Unit";"Zergling";"Larva";140;1
"Unit";"Zergling";"Larva";140;1
"Building";"CreepTumorQueen";NA;145;0
"Building";"CreepTumorQueen";NA;145;0
"Building";"CreepTumor";NA;145;0
"Building";"Hatchery";NA;106;0
"Building";"CreepTumor";NA;145;0
"Building";"CreepTumor";NA;145;0
"Building";"CreepTumor";NA;145;0
"Unit";"Zergling";"Larva";148;1
"Unit";"Zergling";"Larva";148;1
"Unit";"Zergling";"Larva";149;1
"Unit";"Zergling";"Larva";149;1
"Unit";"Zergling";"Larva";150;1
"Unit";"Zergling";"Larva";150;1
"Unit";"Zergling";"Larva";150;1
"Unit";"Zergling";"Larva";150;1
"Unit";"Zergling";"Larva";150;1
"Unit";"Zergling";"Larva";150;1
"Unit";"Zergling";"Larva";150;1
"Unit";"Zergling";"Larva";150;1
"Building";"Extractor";NA;147;0
"Building";"Extractor";NA;150;0
"Building";"CreepTumor";NA;150;0
"Building";"CreepTumor";NA;150;0
"Building";"CreepTumor";NA;150;0
"Unit";"Overlord";"Larva";150;0
"Unit";"Overlord";"Larva";150;0
"Unit";"Baneling";"Zergling";150;0
"Unit";"Baneling";"Zergling";150;0
"Building";"HydraliskDen";NA;147;0
"Building";"CreepTumor";NA;166;0
"Unit";"Queen";"Hatchery";147;2
"Building";"CreepTumor";NA;166;0
"Building";"CreepTumor";NA;166;0
"Unit";"Queen";"Hatchery";150;2
"Building";"CreepTumorQueen";NA;166;0
"Upgrade";"ZergMeleeWeaponsLevel1";"EvolutionChamber";110;0
"Building";"CreepTumorQueen";NA;166;0
"Building";"Hatchery";NA;114;0
"Building";"CreepTumorQueen";NA;180;0
"Building";"CreepTumorQueen";NA;185;0
"Building";"CreepTumor";NA;185;0
"Upgrade";"ZergGroundArmorsLevel1";"EvolutionChamber";145;0
"Building";"CreepTumor";NA;185;0
"Building";"CreepTumor";NA;185;0
"Unit";"Zergling";"Larva";185;1
"Unit";"Zergling";"Larva";185;1
"Unit";"Zergling";"Larva";185;1
"Unit";"Zergling";"Larva";185;1
"Unit";"Zergling";"Larva";185;1
"Unit";"Zergling";"Larva";185;1
"Unit";"Zergling";"Larva";185;1
"Unit";"Zergling";"Larva";185;1
"Unit";"Zergling";"Larva";185;1
"Unit";"Zergling";"Larva";185;1
"Building";"CreepTumor";NA;185;0
"Building";"CreepTumor";NA;185;0
"Building";"Extractor";NA;185;0
"Building";"Extractor";NA;185;0
"Unit";"Hydralisk";"Larva";185;2
"Unit";"Hydralisk";"Larva";185;2
"Unit";"Hydralisk";"Larva";185;2
"Unit";"Hydralisk";"Larva";185;2
"Unit";"Hydralisk";"Larva";185;2
"Unit";"Zergling";"Larva";195;1
"Unit";"Zergling";"Larva";195;1
"Unit";"Zergling";"Larva";195;1
"Unit";"Zergling";"Larva";195;1
"Unit";"Overlord";"Larva";195;0
"Unit";"Overlord";"Larva";195;0
"Unit";"Overlord";"Larva";195;0
"Unit";"Overlord";"Larva";195;0
"Building";"CreepTumor";NA;195;0
"Unit";"Baneling";"Zergling";195;0
"Unit";"Baneling";"Zergling";195;0
"Unit";"Baneling";"Zergling";195;0
"Unit";"Baneling";"Zergling";195;0
"Unit";"Baneling";"Zergling";195;0
"Unit";"Baneling";"Zergling";195;0
"Unit";"Baneling";"Zergling";195;0
"Unit";"Baneling";"Zergling";195;0
"Unit";"Baneling";"Zergling";195;0
"Unit";"Baneling";"Zergling";195;0
"Unit";"Baneling";"Zergling";195;0
"Unit";"Baneling";"Zergling";195;0
"Unit";"Baneling";"Zergling";195;0
"Unit";"Zergling";"Larva";195;1
"Unit";"Zergling";"Larva";195;1
"Building";"InfestationPit";NA;195;0
"Unit";"Zergling";"Larva";209;1
"Unit";"Zergling";"Larva";209;1
"Unit";"Zergling";"Larva";209;1
"Unit";"Zergling";"Larva";209;1
"Unit";"Zergling";"Larva";209;1
"Unit";"Zergling";"Larva";209;1
"Unit";"Zergling";"Larva";209;1
"Unit";"Zergling";"Larva";209;1
"Unit";"Zergling";"Larva";209;1
"Unit";"Zergling";"Larva";209;1
"Unit";"Zergling";"Larva";209;1
"Unit";"Zergling";"Larva";209;1
"Unit";"Zergling";"Larva";209;1
"Unit";"Zergling";"Larva";209;1
"Upgrade";"EvolveGroovedSpines";"HydraliskDen";185;0
"Unit";"Hydralisk";"Larva";209;2
"Unit";"Hydralisk";"Larva";209;2
"Unit";"Hydralisk";"Larva";209;2
"Unit";"Hydralisk";"Larva";209;2
"Unit";"Hydralisk";"Larva";209;2
"Unit";"Hydralisk";"Larva";209;2
"Unit";"Hydralisk";"Larva";209;2
"Unit";"Hydralisk";"Larva";209;2
"Unit";"Hydralisk";"Larva";209;2
"Building";"CreepTumor";NA;225;0
"Building";"CreepTumor";NA;225;0
"Building";"CreepTumorQueen";NA;243;0
"Unit";"Overlord";"Larva";225;0
"Unit";"Overlord";"Larva";225;0
"Unit";"Overlord";"Larva";229;0
"Building";"CreepTumorQueen";NA;243;0
"Unit";"Zergling";"Larva";243;1
"Unit";"Zergling";"Larva";243;1
"Unit";"Zergling";"Larva";243;1
"Unit";"Zergling";"Larva";243;1
"Unit";"Zergling";"Larva";243;1
"Unit";"Zergling";"Larva";243;1
"Unit";"Zergling";"Larva";243;1
"Unit";"Zergling";"Larva";243;1
"Unit";"Zergling";"Larva";243;1
"Unit";"Zergling";"Larva";243;1
"Unit";"Zergling";"Larva";243;1
"Unit";"Zergling";"Larva";243;1
"Unit";"Zergling";"Larva";243;1
"Unit";"Zergling";"Larva";243;1
"Unit";"Zergling";"Larva";243;1
"Unit";"Zergling";"Larva";243;1
"Unit";"Overlord";"Larva";243;0
"Unit";"Overlord";"Larva";243;0
"Unit";"Overlord";"Larva";243;0
"Unit";"Overlord";"Larva";243;0
"Unit";"Overlord";"Larva";243;0
"Unit";"Overlord";"Larva";243;0
"Building";"CreepTumor";NA;259;0
"Building";"CreepTumor";NA;259;0
"Building";"Hatchery";NA;207;0
"Building";"CreepTumor";NA;259;0
"Unit";"Zergling";"Larva";259;1
"Unit";"Zergling";"Larva";259;1
"Unit";"Zergling";"Larva";259;1
"Unit";"Zergling";"Larva";259;1
"Unit";"Zergling";"Larva";259;1
"Unit";"Zergling";"Larva";259;1
"Unit";"Zergling";"Larva";259;1
"Unit";"Zergling";"Larva";259;1
"Unit";"Zergling";"Larva";259;1
"Unit";"Zergling";"Larva";259;1
"Unit";"Zergling";"Larva";259;1
"Unit";"Zergling";"Larva";259;1
"Unit";"Zergling";"Larva";259;1
"Unit";"Zergling";"Larva";259;1
"Unit";"Zergling";"Larva";259;1
"Unit";"Zergling";"Larva";259;1
"Unit";"Zergling";"Larva";259;1
"Unit";"Zergling";"Larva";259;1
"Unit";"Zergling";"Larva";259;1
"Unit";"Zergling";"Larva";259;1
"Unit";"Zergling";"Larva";259;1
"Unit";"Zergling";"Larva";259;1
"Unit";"Zergling";"Larva";259;1
"Unit";"Zergling";"Larva";259;1
"Unit";"Baneling";"Zergling";259;0
"Unit";"Baneling";"Zergling";259;0
"Unit";"Baneling";"Zergling";259;0
"Unit";"Baneling";"Zergling";259;0
"Unit";"Baneling";"Zergling";259;0
"Unit";"Baneling";"Zergling";259;0
"Unit";"Baneling";"Zergling";259;0
"Unit";"Baneling";"Zergling";259;0
"Unit";"Baneling";"Zergling";259;0
"Unit";"Baneling";"Zergling";259;0
"Unit";"Baneling";"Zergling";259;0
"Unit";"Baneling";"Zergling";259;0
"Unit";"Baneling";"Zergling";259;0
"Upgrade";"ZergMeleeWeaponsLevel2";"EvolutionChamber";195;0
"Unit";"Zergling";"Larva";279;1
"Unit";"Zergling";"Larva";279;1
"Unit";"Zergling";"Larva";279;1
"Unit";"Zergling";"Larva";279;1
"Unit";"Zergling";"Larva";279;1
"Unit";"Zergling";"Larva";279;1
"Unit";"Zergling";"Larva";279;1
"Unit";"Zergling";"Larva";279;1
"Unit";"Hydralisk";"Larva";259;2
"Unit";"Hydralisk";"Larva";259;2
"Upgrade";"EvolveMuscularAugments";"HydraliskDen";259;0
"Building";"CreepTumorQueen";NA;299;0
"Unit";"Zergling";"Larva";287;1
"Unit";"Zergling";"Larva";287;1
"Unit";"Zergling";"Larva";287;1
"Unit";"Zergling";"Larva";287;1
"Unit";"Zergling";"Larva";287;1
"Unit";"Zergling";"Larva";287;1
"Unit";"Zergling";"Larva";287;1
"Unit";"Zergling";"Larva";287;1
"Unit";"Zergling";"Larva";287;1
"Unit";"Zergling";"Larva";287;1
"Unit";"Zergling";"Larva";287;1
"Unit";"Zergling";"Larva";287;1
"Unit";"Zergling";"Larva";287;1
"Unit";"Zergling";"Larva";287;1
"Unit";"Zergling";"Larva";287;1
"Unit";"Zergling";"Larva";287;1
"Unit";"Zergling";"Larva";287;1
"Unit";"Zergling";"Larva";287;1
"Unit";"Zergling";"Larva";287;1
"Unit";"Zergling";"Larva";287;1
"Unit";"Zergling";"Larva";287;1
"Unit";"Zergling";"Larva";287;1
"Unit";"Zergling";"Larva";287;1
"Unit";"Zergling";"Larva";287;1
"Building";"CreepTumorQueen";NA;299;0
"Unit";"Queen";"Hatchery";259;2
"Upgrade";"ZergGroundArmorsLevel2";"EvolutionChamber";211;0
"Building";"CreepTumorQueen";NA;299;0
"Building";"CreepTumorQueen";NA;299;0
"Unit";"Zergling";"Larva";299;1
"Unit";"Zergling";"Larva";299;1
"Unit";"Zergling";"Larva";299;1
"Unit";"Zergling";"Larva";299;1
"Unit";"Zergling";"Larva";299;1
"Unit";"Zergling";"Larva";299;1
"Unit";"Zergling";"Larva";299;1
"Unit";"Zergling";"Larva";299;1
"Building";"CreepTumor";NA;323;0
"Building";"CreepTumor";NA;325;0
"Building";"Spire";NA;259;0
"Building";"CreepTumor";NA;342;0
"Building";"CreepTumorQueen";NA;342;0
"Unit";"Zergling";"Larva";342;1
"Unit";"Zergling";"Larva";342;1
"Unit";"Zergling";"Larva";342;1
"Unit";"Zergling";"Larva";342;1
"Unit";"Zergling";"Larva";342;1
"Unit";"Zergling";"Larva";342;1
"Unit";"Zergling";"Larva";342;1
"Unit";"Zergling";"Larva";342;1
"Unit";"Zergling";"Larva";342;1
"Unit";"Zergling";"Larva";342;1
"Unit";"Zergling";"Larva";342;1
"Unit";"Zergling";"Larva";342;1
"Unit";"Zergling";"Larva";342;1
"Unit";"Zergling";"Larva";342;1
"Unit";"Zergling";"Larva";342;1
"Unit";"Zergling";"Larva";342;1
"Unit";"Zergling";"Larva";342;1
"Unit";"Zergling";"Larva";342;1
"Unit";"Zergling";"Larva";342;1
"Unit";"Zergling";"Larva";342;1
"Unit";"Zergling";"Larva";342;1
"Unit";"Zergling";"Larva";342;1
"Unit";"Zergling";"Larva";342;1
"Unit";"Zergling";"Larva";342;1
"Unit";"Zergling";"Larva";342;1
"Unit";"Zergling";"Larva";342;1
"Unit";"Zergling";"Larva";342;1
"Unit";"Zergling";"Larva";342;1
"Unit";"Zergling";"Larva";342;1
"Unit";"Zergling";"Larva";342;1
"Unit";"Zergling";"Larva";342;1
"Unit";"Zergling";"Larva";342;1
"Unit";"Zergling";"Larva";342;1
"Unit";"Zergling";"Larva";342;1
"Unit";"Zergling";"Larva";342;1
"Unit";"Zergling";"Larva";342;1
"Unit";"Zergling";"Larva";342;1
"Unit";"Zergling";"Larva";342;1
"Unit";"Zergling";"Larva";342;1
"Unit";"Zergling";"Larva";342;1
"Unit";"Zergling";"Larva";342;1
"Unit";"Zergling";"Larva";342;1
"Unit";"Zergling";"Larva";342;1
"Unit";"Zergling";"Larva";342;1
"Unit";"Zergling";"Larva";342;1
"Unit";"Zergling";"Larva";342;1
"Unit";"Zergling";"Larva";342;1
"Unit";"Zergling";"Larva";342;1
"Unit";"Zergling";"Larva";342;1
"Unit";"Zergling";"Larva";342;1
"Unit";"Zergling";"Larva";342;1
"Unit";"Zergling";"Larva";342;1
"Unit";"Zergling";"Larva";342;1
"Unit";"Zergling";"Larva";342;1
"Unit";"Zergling";"Larva";342;1
"Unit";"Zergling";"Larva";342;1
"Unit";"Zergling";"Larva";342;1
"Unit";"Zergling";"Larva";342;1
"Unit";"Zergling";"Larva";342;1
"Unit";"Zergling";"Larva";342;1
"Unit";"Zergling";"Larva";342;1
"Unit";"Zergling";"Larva";342;1
"Unit";"Zergling";"Larva";342;1
"Unit";"Zergling";"Larva";342;1
"Building";"Hatchery";NA;342;0
"Building";"CreepTumor";NA;406;0
"Unit";"Corruptor";"Larva";406;2
"Unit";"Corruptor";"Larva";406;2
"Unit";"Corruptor";"Larva";406;2
"Unit";"Corruptor";"Larva";406;2
"Unit";"Corruptor";"Larva";406;2
"Upgrade";"ZergMissileWeaponsLevel1";"EvolutionChamber";342;0
"Building";"Extractor";NA;406;0
"Building";"Extractor";NA;406;0
"Unit";"Baneling";"Zergling";416;0
"Unit";"Baneling";"Zergling";416;0
"Unit";"Baneling";"Zergling";416;0
"Unit";"Baneling";"Zergling";416;0
"Unit";"Baneling";"Zergling";416;0
"Unit";"Baneling";"Zergling";416;0
"Unit";"Baneling";"Zergling";416;0
"Unit";"Baneling";"Zergling";416;0
"Unit";"Baneling";"Zergling";416;0
"Unit";"Baneling";"Zergling";416;0
"Unit";"Baneling";"Zergling";416;0
"Unit";"Baneling";"Zergling";416;0
"Unit";"Baneling";"Zergling";416;0
"Unit";"Baneling";"Zergling";416;0
"Unit";"Baneling";"Zergling";416;0
"Unit";"Baneling";"Zergling";416;0
"Unit";"Baneling";"Zergling";416;0
"Unit";"Baneling";"Zergling";416;0
"Unit";"Baneling";"Zergling";416;0
"Unit";"Baneling";"Zergling";416;0
"Unit";"Baneling";"Zergling";416;0
"Unit";"Hydralisk";"Larva";416;2
"Unit";"Hydralisk";"Larva";416;2
"Unit";"Hydralisk";"Larva";416;2
"Upgrade";"ZergMeleeWeaponsLevel3";"EvolutionChamber";406;0
"Unit";"Zergling";"Larva";416;1
"Unit";"Zergling";"Larva";416;1
"Unit";"Zergling";"Larva";416;1
"Unit";"Zergling";"Larva";416;1
"Unit";"Zergling";"Larva";416;1
"Unit";"Zergling";"Larva";416;1
"Unit";"Zergling";"Larva";416;1
"Unit";"Zergling";"Larva";416;1
"Unit";"Zergling";"Larva";416;1
"Unit";"Zergling";"Larva";416;1
"Unit";"Zergling";"Larva";416;1
"Unit";"Zergling";"Larva";416;1
"Unit";"Zergling";"Larva";416;1
"Unit";"Zergling";"Larva";416;1
"Unit";"Zergling";"Larva";416;1
"Unit";"Zergling";"Larva";416;1
"Unit";"Zergling";"Larva";416;1
"Unit";"Zergling";"Larva";416;1
"Unit";"Zergling";"Larva";416;1
"Unit";"Zergling";"Larva";416;1
"Unit";"Zergling";"Larva";416;1
"Unit";"Zergling";"Larva";416;1
"Unit";"Zergling";"Larva";416;1
"Unit";"Zergling";"Larva";416;1
"Unit";"Zergling";"Larva";416;1
"Unit";"Zergling";"Larva";416;1
"Unit";"Zergling";"Larva";416;1
"Unit";"Zergling";"Larva";416;1
"Unit";"Zergling";"Larva";416;1
"Unit";"Zergling";"Larva";416;1
"Unit";"Zergling";"Larva";416;1
"Unit";"Zergling";"Larva";416;1
"Unit";"Zergling";"Larva";416;1
"Unit";"Zergling";"Larva";416;1
"Unit";"Zergling";"Larva";416;1
"Unit";"Zergling";"Larva";416;1
"Unit";"Zergling";"Larva";416;1
"Unit";"Zergling";"Larva";416;1
"Unit";"Zergling";"Larva";416;1
"Unit";"Zergling";"Larva";416;1
"Unit";"Zergling";"Larva";416;1
"Unit";"Zergling";"Larva";416;1
"Unit";"Zergling";"Larva";416;1
"Unit";"Zergling";"Larva";416;1
"Unit";"Zergling";"Larva";416;1
"Unit";"Zergling";"Larva";416;1
"Unit";"Zergling";"Larva";416;1
"Unit";"Zergling";"Larva";416;1
"Unit";"Zergling";"Larva";416;1
"Unit";"Zergling";"Larva";416;1
"Building";"UltraliskCavern";NA;416;0
"Unit";"Zergling";"Larva";422;1
"Unit";"Zergling";"Larva";422;1
"Unit";"Zergling";"Larva";422;1
"Unit";"Zergling";"Larva";422;1
"Unit";"Zergling";"Larva";422;1
"Unit";"Zergling";"Larva";422;1
"Unit";"Zergling";"Larva";422;1
"Unit";"Zergling";"Larva";422;1
"Unit";"Zergling";"Larva";422;1
"Unit";"Zergling";"Larva";422;1
"Unit";"Zergling";"Larva";422;1
"Unit";"Zergling";"Larva";422;1
"Unit";"Zergling";"Larva";422;1
"Unit";"Zergling";"Larva";422;1
"Unit";"Zergling";"Larva";422;1
"Unit";"Zergling";"Larva";422;1
"Unit";"Zergling";"Larva";422;1
"Unit";"Zergling";"Larva";422;1
"Unit";"Zergling";"Larva";422;1
"Unit";"Zergling";"Larva";422;1
"Unit";"Zergling";"Larva";422;1
"Unit";"Zergling";"Larva";422;1
"Unit";"Zergling";"Larva";422;1
"Unit";"Zergling";"Larva";422;1
"Unit";"Zergling";"Larva";422;1
"Unit";"Zergling";"Larva";422;1
"Unit";"Zergling";"Larva";422;1
"Unit";"Zergling";"Larva";422;1
"Unit";"Zergling";"Larva";422;1
"Unit";"Zergling";"Larva";422;1
"Unit";"Zergling";"Larva";422;1
"Unit";"Zergling";"Larva";422;1
"Unit";"Zergling";"Larva";422;1
"Unit";"Zergling";"Larva";422;1
"Unit";"Zergling";"Larva";422;1
"Unit";"Zergling";"Larva";422;1
"Unit";"Zergling";"Larva";422;1
"Unit";"Zergling";"Larva";422;1
"Unit";"Zergling";"Larva";422;1
"Unit";"Zergling";"Larva";422;1
"Unit";"Zergling";"Larva";422;1
"Unit";"Zergling";"Larva";422;1
"Unit";"Zergling";"Larva";422;1
"Unit";"Zergling";"Larva";422;1
"Unit";"Zergling";"Larva";422;1
"Unit";"Zergling";"Larva";422;1
"Unit";"Zergling";"Larva";422;1
"Unit";"Zergling";"Larva";422;1
"Unit";"Zergling";"Larva";422;1
"Unit";"Zergling";"Larva";422;1
"Unit";"Zergling";"Larva";422;1
"Unit";"Zergling";"Larva";422;1
"Unit";"Zergling";"Larva";422;1
"Unit";"Zergling";"Larva";422;1
"Building";"CreepTumor";NA;484;0
"Building";"CreepTumor";NA;526;0
"Unit";"Baneling";"Zergling";526;0
"Unit";"Baneling";"Zergling";526;0
"Unit";"Baneling";"Zergling";526;0
"Unit";"Baneling";"Zergling";526;0
"Unit";"Baneling";"Zergling";526;0
"Unit";"Baneling";"Zergling";526;0
"Unit";"Baneling";"Zergling";526;0
"Unit";"Baneling";"Zergling";526;0
"Unit";"Baneling";"Zergling";526;0
"Unit";"Baneling";"Zergling";526;0
"Unit";"Baneling";"Zergling";526;0
"Unit";"Baneling";"Zergling";526;0
"Unit";"Baneling";"Zergling";526;0
"Unit";"Baneling";"Zergling";526;0
"Unit";"Baneling";"Zergling";526;0
"Unit";"Baneling";"Zergling";526;0
"Building";"CreepTumor";NA;526;0
"Building";"SporeCrawler";NA;526;0
"Upgrade";"ChitinousPlating";"UltraliskCavern";526;0
"Upgrade";"ZergGroundArmorsLevel3";"EvolutionChamber";416;0
"Unit";"Baneling";"Zergling";526;0
"Unit";"Baneling";"Zergling";526;0
"Building";"SpineCrawler";NA;526;0
"Unit";"Baneling";"Zergling";526;0
"Unit";"Baneling";"Zergling";526;0
"Unit";"Baneling";"Zergling";526;0
"Unit";"Baneling";"Zergling";526;0
"Building";"SpineCrawler";NA;526;0
"Unit";"Baneling";"Zergling";526;0
"Unit";"Baneling";"Zergling";526;0
"Unit";"Baneling";"Zergling";526;0
"Unit";"Baneling";"Zergling";526;0
"Unit";"Baneling";"Zergling";526;0
"Unit";"Baneling";"Zergling";526;0
"Unit";"Baneling";"Zergling";526;0
"Unit";"Baneling";"Zergling";526;0
"Unit";"Baneling";"Zergling";526;0
"Unit";"Baneling";"Zergling";526;0
"Unit";"Baneling";"Zergling";526;0
"Unit";"Baneling";"Zergling";526;0
"Unit";"Baneling";"Zergling";526;0
"Unit";"Baneling";"Zergling";526;0
"Building";"SporeCrawler";NA;526;0
"Unit";"Hydralisk";"Larva";526;2
"Unit";"Hydralisk";"Larva";526;2
"Unit";"Hydralisk";"Larva";526;2
"Unit";"Hydralisk";"Larva";526;2
"Unit";"Hydralisk";"Larva";526;2
"Unit";"Hydralisk";"Larva";526;2
"Unit";"Hydralisk";"Larva";526;2
"Unit";"Hydralisk";"Larva";526;2
"Unit";"Hydralisk";"Larva";526;2
"Unit";"Hydralisk";"Larva";526;2
"Building";"SpineCrawler";NA;526;0
"Upgrade";"ZergMissileWeaponsLevel2";"EvolutionChamber";526;0
"Unit";"Zergling";"Larva";552;1
"Unit";"Zergling";"Larva";552;1
"Unit";"Zergling";"Larva";552;1
"Unit";"Zergling";"Larva";552;1
"Unit";"Zergling";"Larva";552;1
"Unit";"Zergling";"Larva";552;1
"Unit";"Zergling";"Larva";552;1
"Unit";"Zergling";"Larva";552;1
"Unit";"Zergling";"Larva";552;1
"Unit";"Zergling";"Larva";552;1
"Unit";"Zergling";"Larva";552;1
"Unit";"Zergling";"Larva";552;1
"Unit";"Zergling";"Larva";552;1
"Unit";"Zergling";"Larva";552;1
"Unit";"Zergling";"Larva";552;1
"Unit";"Zergling";"Larva";552;1
"Unit";"Zergling";"Larva";552;1
"Unit";"Zergling";"Larva";552;1
"Building";"CreepTumor";NA;552;0
"Building";"Hatchery";NA;526;0
"Building";"Hatchery";NA;552;0
"Unit";"Zergling";"Larva";570;1
"Unit";"Zergling";"Larva";570;1
"Unit";"Zergling";"Larva";570;1
"Unit";"Zergling";"Larva";570;1
"Unit";"Zergling";"Larva";570;1
"Unit";"Zergling";"Larva";570;1
"Unit";"Zergling";"Larva";570;1
"Unit";"Zergling";"Larva";570;1
"Unit";"Zergling";"Larva";570;1
"Unit";"Zergling";"Larva";570;1
"Unit";"Zergling";"Larva";570;1
"Unit";"Zergling";"Larva";570;1
"Unit";"Zergling";"Larva";570;1
"Unit";"Zergling";"Larva";570;1
"Unit";"Zergling";"Larva";570;1
"Unit";"Zergling";"Larva";570;1
"Unit";"Zergling";"Larva";570;1
"Unit";"Zergling";"Larva";570;1
"Unit";"Zergling";"Larva";570;1
"Unit";"Zergling";"Larva";570;1
"Unit";"Zergling";"Larva";570;1
"Unit";"Zergling";"Larva";570;1
"Unit";"Zergling";"Larva";570;1
"Unit";"Zergling";"Larva";570;1
"Unit";"Zergling";"Larva";570;1
"Unit";"Zergling";"Larva";570;1
"Unit";"Zergling";"Larva";570;1
"Unit";"Zergling";"Larva";570;1
"Unit";"Zergling";"Larva";570;1
"Unit";"Zergling";"Larva";570;1
"Unit";"Zergling";"Larva";570;1
"Unit";"Zergling";"Larva";570;1
"Unit";"Zergling";"Larva";570;1
"Unit";"Zergling";"Larva";570;1
"Unit";"Zergling";"Larva";570;1
"Unit";"Zergling";"Larva";570;1
"Unit";"Zergling";"Larva";570;1
"Unit";"Zergling";"Larva";570;1
"Unit";"Zergling";"Larva";570;1
"Unit";"Zergling";"Larva";570;1
"Unit";"Zergling";"Larva";570;1
"Unit";"Zergling";"Larva";570;1
"Unit";"Zergling";"Larva";570;1
"Unit";"Zergling";"Larva";570;1
"Unit";"Zergling";"Larva";570;1
"Unit";"Zergling";"Larva";570;1
"Unit";"Zergling";"Larva";570;1
"Unit";"Zergling";"Larva";570;1
"Unit";"Zergling";"Larva";570;1
"Unit";"Zergling";"Larva";570;1
"Unit";"Zergling";"Larva";570;1
"Unit";"Zergling";"Larva";570;1
"Unit";"Zergling";"Larva";570;1
"Unit";"Zergling";"Larva";570;1
"Unit";"Zergling";"Larva";570;1
"Unit";"Zergling";"Larva";570;1
"Unit";"Zergling";"Larva";570;1
"Unit";"Zergling";"Larva";570;1
"Unit";"Hydralisk";"Larva";570;2
"Building";"CreepTumor";NA;570;0
"Building";"SporeCrawler";NA;630;0
"Building";"SporeCrawler";NA;630;0
"Building";"Extractor";NA;630;0
"Building";"Extractor";NA;630;0
"Building";"CreepTumor";NA;630;0
"Building";"CreepTumor";NA;630;0
"Building";"SpineCrawler";NA;630;0
"Building";"SpineCrawler";NA;630;0
"Building";"SpineCrawler";NA;630;0
"Building";"SpineCrawler";NA;630;0
"Building";"SpineCrawler";NA;630;0
"Building";"SpineCrawler";NA;630;0
"Building";"SpineCrawler";NA;630;0
"Upgrade";"Burrow";"Hatchery";630;0
"Building";"CreepTumor";NA;630;0
"Unit";"Zergling";"Larva";630;1
"Unit";"Zergling";"Larva";630;1
"Unit";"Zergling";"Larva";630;1
"Unit";"Zergling";"Larva";630;1
"Unit";"Zergling";"Larva";630;1
"Unit";"Zergling";"Larva";630;1
"Unit";"Zergling";"Larva";630;1
"Unit";"Zergling";"Larva";630;1
"Unit";"Zergling";"Larva";630;1
"Unit";"Zergling";"Larva";630;1
"Unit";"Zergling";"Larva";630;1
"Unit";"Zergling";"Larva";630;1
"Unit";"Zergling";"Larva";630;1
"Unit";"Zergling";"Larva";630;1
"Unit";"Zergling";"Larva";630;1
"Unit";"Zergling";"Larva";630;1
"Unit";"Baneling";"Zergling";630;0
"Unit";"Baneling";"Zergling";630;0
"Unit";"Baneling";"Zergling";630;0
"Unit";"Baneling";"Zergling";630;0
"Unit";"Baneling";"Zergling";630;0
"Unit";"Baneling";"Zergling";630;0
"Unit";"Baneling";"Zergling";630;0
"Unit";"Baneling";"Zergling";630;0
"Unit";"Baneling";"Zergling";630;0
"Unit";"Baneling";"Zergling";630;0
"Unit";"Baneling";"Zergling";630;0
"Unit";"Baneling";"Zergling";630;0
"Unit";"Baneling";"Zergling";630;0
"Unit";"Baneling";"Zergling";630;0
"Unit";"Baneling";"Zergling";630;0
"Unit";"Baneling";"Zergling";630;0
"Unit";"Baneling";"Zergling";630;0
"Unit";"Baneling";"Zergling";630;0
"Unit";"Baneling";"Zergling";630;0
"Unit";"Baneling";"Zergling";630;0
"Unit";"Baneling";"Zergling";630;0
"Unit";"Baneling";"Zergling";630;0
"Unit";"Baneling";"Zergling";630;0
"Unit";"Baneling";"Zergling";630;0
"Unit";"Baneling";"Zergling";630;0
"Unit";"Baneling";"Zergling";630;0
"Unit";"Baneling";"Zergling";630;0
"Unit";"Baneling";"Zergling";630;0
"Unit";"Baneling";"Zergling";630;0
"Unit";"Viper";"Larva";630;3
"Unit";"Viper";"Larva";630;3
"Unit";"Viper";"Larva";630;3
"Unit";"Viper";"Larva";630;3
"Unit";"Viper";"Larva";630;3
"Unit";"Viper";"Larva";630;3
"Unit";"Viper";"Larva";630;3
"Building";"SporeCrawler";NA;630;0
"Building";"SporeCrawler";NA;630;0
"Building";"SporeCrawler";NA;630;0
"Building";"SporeCrawler";NA;630;0
"Unit";"Baneling";"Zergling";646;0
"Unit";"Baneling";"Zergling";646;0
"Unit";"Baneling";"Zergling";646;0
"Unit";"Baneling";"Zergling";646;0
"Unit";"Baneling";"Zergling";646;0
"Unit";"Baneling";"Zergling";646;0
"Unit";"Baneling";"Zergling";646;0
"Unit";"Baneling";"Zergling";646;0
"Unit";"Zergling";"Larva";667;1
"Unit";"Zergling";"Larva";667;1
"Unit";"Zergling";"Larva";667;1
"Unit";"Zergling";"Larva";667;1
"Unit";"Zergling";"Larva";667;1
"Unit";"Zergling";"Larva";667;1
"Unit";"Zergling";"Larva";667;1
"Unit";"Zergling";"Larva";667;1
"Unit";"Zergling";"Larva";667;1
"Unit";"Zergling";"Larva";667;1
"Building";"SporeCrawler";NA;646;0
"Unit";"Zergling";"Larva";677;1
"Unit";"Zergling";"Larva";677;1
"Unit";"Zergling";"Larva";677;1
"Unit";"Zergling";"Larva";677;1
"Unit";"Zergling";"Larva";677;1
"Unit";"Zergling";"Larva";677;1
"Unit";"Zergling";"Larva";677;1
"Unit";"Zergling";"Larva";677;1
"Unit";"Zergling";"Larva";677;1
"Unit";"Zergling";"Larva";677;1
"Unit";"Zergling";"Larva";677;1
"Unit";"Zergling";"Larva";677;1
"Unit";"Zergling";"Larva";677;1
"Unit";"Zergling";"Larva";677;1
"Unit";"Zergling";"Larva";677;1
"Unit";"Zergling";"Larva";677;1
"Unit";"Zergling";"Larva";677;1
"Unit";"Zergling";"Larva";677;1
"Unit";"Zergling";"Larva";677;1
"Unit";"Zergling";"Larva";677;1
"Unit";"Zergling";"Larva";677;1
"Unit";"Zergling";"Larva";677;1
"Unit";"Zergling";"Larva";677;1
"Unit";"Zergling";"Larva";677;1
"Unit";"Zergling";"Larva";677;1
"Unit";"Zergling";"Larva";677;1
"Unit";"Zergling";"Larva";677;1
"Unit";"Zergling";"Larva";677;1
"Unit";"Zergling";"Larva";677;1
"Unit";"Zergling";"Larva";677;1
"Unit";"Zergling";"Larva";677;1
"Unit";"Zergling";"Larva";677;1
"Unit";"Zergling";"Larva";677;1
"Unit";"Zergling";"Larva";677;1
"Unit";"Zergling";"Larva";677;1
"Unit";"Zergling";"Larva";677;1
"Unit";"Zergling";"Larva";677;1
"Unit";"Zergling";"Larva";677;1
"Unit";"Zergling";"Larva";677;1
"Unit";"Zergling";"Larva";677;1
"Unit";"Zergling";"Larva";677;1
"Unit";"Zergling";"Larva";677;1
"Unit";"Zergling";"Larva";677;1
"Unit";"Zergling";"Larva";677;1
"Unit";"Zergling";"Larva";677;1
"Unit";"Zergling";"Larva";677;1
"Unit";"Zergling";"Larva";677;1
"Unit";"Zergling";"Larva";677;1
"Unit";"Zergling";"Larva";677;1
"Unit";"Zergling";"Larva";677;1
"Unit";"Zergling";"Larva";677;1
"Unit";"Zergling";"Larva";677;1
"Unit";"Zergling";"Larva";677;1
"Unit";"Zergling";"Larva";677;1
"Unit";"Zergling";"Larva";677;1
"Unit";"Zergling";"Larva";677;1
"Unit";"Zergling";"Larva";677;1
"Unit";"Zergling";"Larva";677;1
"Unit";"Zergling";"Larva";677;1
"Unit";"Zergling";"Larva";677;1
"Unit";"Zergling";"Larva";677;1
"Unit";"Zergling";"Larva";677;1
"Unit";"Zergling";"Larva";677;1
"Unit";"Zergling";"Larva";677;1
"Unit";"Zergling";"Larva";677;1
"Unit";"Zergling";"Larva";677;1
"Unit";"Zergling";"Larva";677;1
"Unit";"Zergling";"Larva";677;1
"Unit";"Zergling";"Larva";677;1
"Unit";"Zergling";"Larva";677;1
"Unit";"Hydralisk";"Larva";677;2
"Unit";"Hydralisk";"Larva";677;2
"Unit";"Hydralisk";"Larva";677;2
"Unit";"Hydralisk";"Larva";677;2
"Unit";"Hydralisk";"Larva";677;2
"Unit";"Hydralisk";"Larva";677;2
"Unit";"Hydralisk";"Larva";677;2
"Upgrade";"ZergMissileWeaponsLevel3";"EvolutionChamber";630;0
"Unit";"Zergling";"Larva";747;1
"Unit";"Zergling";"Larva";747;1
"Unit";"Zergling";"Larva";747;1
"Unit";"Zergling";"Larva";747;1
"Unit";"Zergling";"Larva";747;1
"Unit";"Zergling";"Larva";747;1
"Unit";"Zergling";"Larva";747;1
"Unit";"Zergling";"Larva";747;1
"Unit";"Zergling";"Larva";747;1
"Unit";"Zergling";"Larva";747;1
"Unit";"Zergling";"Larva";747;1
"Unit";"Zergling";"Larva";747;1
"Unit";"Zergling";"Larva";747;1
"Unit";"Zergling";"Larva";747;1
"Unit";"Zergling";"Larva";747;1
"Unit";"Zergling";"Larva";747;1
"Building";"CreepTumor";NA;747;0
"Unit";"Baneling";"Zergling";777;0
"Unit";"Baneling";"Zergling";777;0
"Unit";"Baneling";"Zergling";777;0
"Unit";"Baneling";"Zergling";777;0
"Unit";"Baneling";"Zergling";777;0
"Unit";"Baneling";"Zergling";777;0
"Unit";"Baneling";"Zergling";777;0
"Unit";"Baneling";"Zergling";777;0
"Unit";"Baneling";"Zergling";777;0
"Unit";"Baneling";"Zergling";777;0
"Unit";"Baneling";"Zergling";777;0
"Unit";"Baneling";"Zergling";777;0
"Unit";"Baneling";"Zergling";777;0
"Unit";"Baneling";"Zergling";777;0
"Unit";"Baneling";"Zergling";777;0
"Unit";"Baneling";"Zergling";777;0
"Unit";"Baneling";"Zergling";777;0
"Building";"CreepTumor";NA;777;0
"Unit";"Corruptor";"Larva";777;2
"Unit";"Corruptor";"Larva";777;2
"Unit";"Corruptor";"Larva";777;2
