"type";"unit_name";"on_building";"total_supply";"supply"
"Unit";"Overlord";"Larva";13;0
"Building";"Extractor";NA;18;0
"Unit";"Overlord";"Larva";21;0
"Building";"SpawningPool";NA;19;0
"Building";"Hatchery";NA;17;0
"Unit";"Zergling";"Larva";23;1
"Unit";"Zergling";"Larva";23;1
"Unit";"Zergling";"Larva";23;1
"Unit";"Zergling";"Larva";23;1
"Unit";"Queen";"Hatchery";23;2
"Unit";"Queen";"Hatchery";23;2
"Building";"CreepTumorQueen";NA;35;0
"Unit";"Overlord";"Larva";35;0
"Building";"CreepTumor";NA;38;0
"Unit";"Queen";"Hatchery";35;2
"Unit";"Overlord";"Larva";40;0
"Unit";"Queen";"Hatchery";38;2
"Building";"CreepTumor";NA;46;0
"Building";"CreepTumorQueen";NA;46;0
"Building";"Hatchery";NA;35;0
"Unit";"Overlord";"Larva";48;0
"Building";"CreepTumorQueen";NA;50;0
"Unit";"Zergling";"Larva";50;1
"Unit";"Zergling";"Larva";50;1
"Unit";"Zergling";"Larva";50;1
"Unit";"Zergling";"Larva";50;1
"Unit";"Zergling";"Larva";50;1
"Unit";"Zergling";"Larva";50;1
"Unit";"Zergling";"Larva";50;1
"Unit";"Zergling";"Larva";50;1
"Unit";"Zergling";"Larva";50;1
"Unit";"Zergling";"Larva";50;1
"Building";"CreepTumor";NA;50;0
"Unit";"Queen";"Hatchery";48;2
"Unit";"Zergling";"Larva";50;1
"Unit";"Zergling";"Larva";50;1
"Building";"CreepTumorQueen";NA;60;0
"Building";"BanelingNest";NA;50;0
"Unit";"Queen";"Hatchery";50;2
"Unit";"Overlord";"Larva";65;0
"Unit";"Overlord";"Larva";67;0
"Building";"CreepTumor";NA;74;0
"Unit";"Overlord";"Larva";74;0
"Building";"CreepTumor";NA;78;0
"Building";"CreepTumor";NA;78;0
"Unit";"Queen";"Hatchery";71;2
"Building";"SporeCrawler";NA;74;0
"Building";"SporeCrawler";NA;74;0
"Unit";"Overlord";"Larva";74;0
"Building";"SporeCrawler";NA;74;0
"Building";"CreepTumor";NA;78;0
"Building";"CreepTumorQueen";NA;80;0
"Building";"Extractor";NA;78;0
"Building";"Extractor";NA;78;0
"Building";"CreepTumorQueen";NA;80;0
"Building";"CreepTumorQueen";NA;81;0
"Building";"CreepTumor";NA;84;0
"Building";"CreepTumorQueen";NA;91;0
"Building";"CreepTumorQueen";NA;91;0
"Building";"EvolutionChamber";NA;84;0
"Building";"EvolutionChamber";NA;84;0
"Building";"CreepTumor";NA;91;0
"Building";"CreepTumorQueen";NA;92;0
"Building";"CreepTumor";NA;92;0
"Building";"CreepTumorQueen";NA;99;0
"Building";"CreepTumor";NA;93;0
"Building";"CreepTumor";NA;93;0
"Building";"CreepTumor";NA;98;0
"Unit";"Overlord";"Larva";91;0
"Unit";"Overlord";"Larva";99;0
"Building";"CreepTumorQueen";NA;102;0
"Building";"CreepTumorQueen";NA;102;0
"Building";"CreepTumorQueen";NA;102;0
"Building";"Extractor";NA;102;0
"Building";"CreepTumor";NA;102;0
"Building";"CreepTumorQueen";NA;103;0
"Building";"CreepTumor";NA;102;0
"Building";"CreepTumor";NA;102;0
"Building";"CreepTumor";NA;106;0
"Building";"CreepTumor";NA;106;0
"Building";"CreepTumor";NA;106;0
"Building";"Extractor";NA;106;0
"Building";"Extractor";NA;106;0
"Building";"HydraliskDen";NA;106;0
"Building";"CreepTumor";NA;107;0
"Unit";"Overlord";"Larva";107;0
"Building";"CreepTumor";NA;110;0
"Building";"CreepTumor";NA;110;0
"Building";"CreepTumor";NA;110;0
"Building";"CreepTumor";NA;110;0
"Building";"CreepTumor";NA;110;0
"Unit";"Zergling";"Larva";113;1
"Unit";"Zergling";"Larva";113;1
"Unit";"Zergling";"Larva";113;1
"Unit";"Zergling";"Larva";113;1
"Unit";"Zergling";"Larva";113;1
"Unit";"Zergling";"Larva";113;1
"Unit";"Zergling";"Larva";113;1
"Unit";"Zergling";"Larva";113;1
"Building";"Hatchery";NA;102;0
"Unit";"Hydralisk";"Larva";126;2
"Unit";"Hydralisk";"Larva";126;2
"Unit";"Hydralisk";"Larva";126;2
"Unit";"Hydralisk";"Larva";126;2
"Unit";"Hydralisk";"Larva";126;2
"Unit";"Hydralisk";"Larva";126;2
"Unit";"Hydralisk";"Larva";126;2
"Building";"CreepTumor";NA;140;0
"Building";"CreepTumor";NA;140;0
"Building";"CreepTumor";NA;140;0
"Building";"CreepTumor";NA;140;0
"Building";"CreepTumor";NA;140;0
"Building";"CreepTumor";NA;140;0
"Unit";"Overlord";"Larva";140;0
"Unit";"Overlord";"Larva";140;0
"Unit";"Overlord";"Larva";140;0
"Unit";"Hydralisk";"Larva";140;2
"Unit";"Hydralisk";"Larva";140;2
"Unit";"Hydralisk";"Larva";140;2
"Unit";"Hydralisk";"Larva";140;2
"Unit";"Hydralisk";"Larva";140;2
"Upgrade";"ZergMeleeWeaponsLevel1";"EvolutionChamber";107;0
"Building";"CreepTumorQueen";NA;141;0
"Building";"CreepTumorQueen";NA;141;0
"Building";"CreepTumor";NA;141;0
"Building";"CreepTumor";NA;141;0
"Building";"CreepTumorQueen";NA;141;0
"Building";"CreepTumor";NA;141;0
"Building";"CreepTumorQueen";NA;141;0
"Upgrade";"ZergGroundArmorsLevel1";"EvolutionChamber";107;0
"Building";"CreepTumorQueen";NA;141;0
"Upgrade";"EvolveGroovedSpines";"HydraliskDen";126;0
"Building";"CreepTumorQueen";NA;141;0
"Unit";"Zergling";"Larva";151;1
"Unit";"Zergling";"Larva";151;1
"Unit";"Zergling";"Larva";151;1
"Unit";"Zergling";"Larva";151;1
"Unit";"Zergling";"Larva";151;1
"Unit";"Zergling";"Larva";151;1
"Unit";"Zergling";"Larva";151;1
"Unit";"Zergling";"Larva";151;1
"Unit";"Zergling";"Larva";151;1
"Unit";"Zergling";"Larva";151;1
"Unit";"Zergling";"Larva";151;1
"Unit";"Zergling";"Larva";151;1
"Unit";"Zergling";"Larva";151;1
"Unit";"Zergling";"Larva";151;1
"Unit";"Zergling";"Larva";151;1
"Unit";"Zergling";"Larva";151;1
"Unit";"Zergling";"Larva";151;1
"Unit";"Zergling";"Larva";151;1
"Unit";"Zergling";"Larva";151;1
"Unit";"Zergling";"Larva";151;1
"Unit";"Zergling";"Larva";151;1
"Unit";"Zergling";"Larva";151;1
"Unit";"Zergling";"Larva";151;1
"Unit";"Zergling";"Larva";151;1
"Unit";"Zergling";"Larva";151;1
"Unit";"Zergling";"Larva";151;1
"Unit";"Overlord";"Larva";151;0
"Unit";"Overlord";"Larva";151;0
"Unit";"Overlord";"Larva";151;0
"Unit";"Queen";"Hatchery";141;2
"Building";"CreepTumor";NA;177;0
"Building";"CreepTumor";NA;177;0
"Building";"CreepTumor";NA;177;0
"Building";"CreepTumorQueen";NA;177;0
"Building";"CreepTumor";NA;177;0
"Building";"CreepTumor";NA;177;0
"Building";"CreepTumor";NA;177;0
"Building";"CreepTumor";NA;177;0
"Building";"CreepTumorQueen";NA;177;0
"Building";"CreepTumorQueen";NA;180;0
"Building";"CreepTumorQueen";NA;183;0
"Building";"CreepTumor";NA;180;0
"Building";"CreepTumor";NA;180;0
"Building";"CreepTumor";NA;181;0
"Building";"CreepTumorQueen";NA;184;0
"Unit";"Baneling";"Zergling";184;0
"Unit";"Baneling";"Zergling";184;0
"Unit";"Baneling";"Zergling";184;0
"Unit";"Baneling";"Zergling";184;0
"Unit";"Baneling";"Zergling";184;0
"Unit";"Baneling";"Zergling";184;0
"Unit";"Baneling";"Zergling";184;0
"Unit";"Baneling";"Zergling";184;0
"Unit";"Baneling";"Zergling";184;0
"Unit";"Baneling";"Zergling";184;0
"Unit";"Baneling";"Zergling";184;0
"Unit";"Baneling";"Zergling";184;0
"Unit";"Baneling";"Zergling";184;0
"Unit";"Baneling";"Zergling";184;0
"Unit";"Baneling";"Zergling";184;0
"Unit";"Baneling";"Zergling";184;0
"Unit";"Baneling";"Zergling";184;0
"Unit";"Baneling";"Zergling";184;0
"Unit";"Baneling";"Zergling";184;0
"Unit";"Baneling";"Zergling";184;0
"Unit";"Zergling";"Larva";184;1
"Unit";"Zergling";"Larva";184;1
"Unit";"Zergling";"Larva";184;1
"Unit";"Zergling";"Larva";184;1
"Unit";"Zergling";"Larva";184;1
"Unit";"Zergling";"Larva";184;1
"Building";"CreepTumor";NA;196;0
"Unit";"Zergling";"Larva";196;1
"Unit";"Zergling";"Larva";196;1
"Unit";"Zergling";"Larva";196;1
"Unit";"Zergling";"Larva";196;1
"Unit";"Zergling";"Larva";196;1
"Unit";"Zergling";"Larva";196;1
"Unit";"Zergling";"Larva";196;1
"Unit";"Zergling";"Larva";196;1
"Unit";"Zergling";"Larva";196;1
"Unit";"Zergling";"Larva";196;1
"Unit";"Zergling";"Larva";196;1
"Unit";"Zergling";"Larva";196;1
"Unit";"Zergling";"Larva";196;1
"Unit";"Zergling";"Larva";196;1
"Upgrade";"EvolveMuscularAugments";"HydraliskDen";177;0
"Building";"Hatchery";NA;151;0
"Building";"CreepTumorQueen";NA;202;0
"Building";"CreepTumorQueen";NA;202;0
"Unit";"Hydralisk";"Larva";202;2
"Unit";"Hydralisk";"Larva";202;2
"Unit";"Hydralisk";"Larva";202;2
"Unit";"Hydralisk";"Larva";202;2
"Unit";"Hydralisk";"Larva";202;2
"Unit";"Hydralisk";"Larva";202;2
"Unit";"Hydralisk";"Larva";202;2
"Building";"InfestationPit";NA;216;0
"Unit";"Zergling";"Larva";230;1
"Unit";"Zergling";"Larva";230;1
"Unit";"Zergling";"Larva";230;1
"Unit";"Zergling";"Larva";230;1
"Unit";"Zergling";"Larva";230;1
"Unit";"Zergling";"Larva";230;1
"Unit";"Zergling";"Larva";230;1
"Unit";"Zergling";"Larva";230;1
"Unit";"Zergling";"Larva";230;1
"Unit";"Zergling";"Larva";230;1
"Unit";"Zergling";"Larva";230;1
"Unit";"Zergling";"Larva";230;1
"Unit";"Zergling";"Larva";230;1
"Unit";"Zergling";"Larva";230;1
"Unit";"Zergling";"Larva";230;1
"Unit";"Zergling";"Larva";230;1
"Unit";"Zergling";"Larva";230;1
"Unit";"Zergling";"Larva";230;1
"Unit";"Zergling";"Larva";230;1
"Unit";"Zergling";"Larva";230;1
"Unit";"Zergling";"Larva";230;1
"Unit";"Zergling";"Larva";230;1
"Unit";"Zergling";"Larva";230;1
"Unit";"Zergling";"Larva";230;1
"Unit";"Zergling";"Larva";230;1
"Unit";"Zergling";"Larva";230;1
"Unit";"Zergling";"Larva";230;1
"Unit";"Zergling";"Larva";230;1
"Unit";"Zergling";"Larva";230;1
"Unit";"Zergling";"Larva";230;1
"Unit";"Zergling";"Larva";230;1
"Unit";"Zergling";"Larva";230;1
"Unit";"Zergling";"Larva";230;1
"Unit";"Zergling";"Larva";230;1
"Unit";"Zergling";"Larva";230;1
"Unit";"Zergling";"Larva";230;1
"Unit";"Zergling";"Larva";230;1
"Unit";"Zergling";"Larva";230;1
"Unit";"Zergling";"Larva";230;1
"Unit";"Zergling";"Larva";230;1
"Unit";"Zergling";"Larva";230;1
"Unit";"Zergling";"Larva";230;1
"Building";"CreepTumor";NA;256;0
"Unit";"Zergling";"Larva";230;1
"Unit";"Zergling";"Larva";230;1
"Unit";"Baneling";"Zergling";272;0
"Unit";"Baneling";"Zergling";272;0
"Unit";"Baneling";"Zergling";272;0
"Unit";"Baneling";"Zergling";272;0
"Unit";"Baneling";"Zergling";272;0
"Unit";"Baneling";"Zergling";272;0
"Unit";"Baneling";"Zergling";272;0
"Unit";"Baneling";"Zergling";272;0
"Unit";"Baneling";"Zergling";272;0
"Unit";"Baneling";"Zergling";272;0
"Unit";"Baneling";"Zergling";272;0
"Upgrade";"ZergMeleeWeaponsLevel2";"EvolutionChamber";184;0
"Upgrade";"ZergGroundArmorsLevel2";"EvolutionChamber";196;0
"Unit";"Queen";"Hatchery";256;2
"Building";"CreepTumorQueen";NA;278;0
"Unit";"Baneling";"Zergling";278;0
"Building";"CreepTumorQueen";NA;280;0
"Unit";"Baneling";"Zergling";278;0
"Unit";"Baneling";"Zergling";278;0
"Unit";"Baneling";"Zergling";278;0
"Unit";"Baneling";"Zergling";278;0
"Unit";"Baneling";"Zergling";278;0
"Unit";"Baneling";"Zergling";278;0
"Unit";"Baneling";"Zergling";278;0
"Building";"CreepTumor";NA;278;0
"Building";"CreepTumorQueen";NA;284;0
"Unit";"Zergling";"Larva";278;1
"Unit";"Zergling";"Larva";278;1
"Building";"CreepTumor";NA;290;0
"Building";"CreepTumor";NA;290;0
"Building";"CreepTumor";NA;290;0
"Building";"CreepTumor";NA;290;0
"Building";"CreepTumor";NA;290;0
"Building";"CreepTumor";NA;290;0
"Building";"CreepTumor";NA;290;0
"Unit";"Zergling";"Larva";292;1
"Unit";"Zergling";"Larva";292;1
"Unit";"Zergling";"Larva";292;1
"Unit";"Zergling";"Larva";292;1
"Unit";"Zergling";"Larva";292;1
"Unit";"Zergling";"Larva";292;1
"Unit";"Zergling";"Larva";292;1
"Unit";"Zergling";"Larva";292;1
"Building";"CreepTumor";NA;294;0
"Unit";"Hydralisk";"Larva";292;2
"Unit";"Hydralisk";"Larva";292;2
"Unit";"Hydralisk";"Larva";292;2
"Unit";"Overlord";"Larva";294;0
"Building";"CreepTumor";NA;294;0
"Unit";"Overlord";"Larva";294;0
"Unit";"Overlord";"Larva";294;0
"Unit";"Overlord";"Larva";294;0
"Unit";"Hydralisk";"Larva";292;2
"Unit";"Hydralisk";"Larva";292;2
"Unit";"Hydralisk";"Larva";292;2
"Building";"CreepTumorQueen";NA;294;0
"Building";"CreepTumorQueen";NA;294;0
"Building";"SporeCrawler";NA;294;0
"Building";"Hatchery";NA;278;0
"Building";"CreepTumor";NA;314;0
"Building";"CreepTumor";NA;314;0
"Unit";"Hydralisk";"Larva";314;2
"Unit";"Hydralisk";"Larva";314;2
"Unit";"Hydralisk";"Larva";314;2
"Building";"CreepTumor";NA;316;0
"Unit";"Zergling";"Larva";314;1
"Unit";"Zergling";"Larva";314;1
"Building";"CreepTumor";NA;316;0
"Unit";"Zergling";"Larva";314;1
"Unit";"Zergling";"Larva";314;1
"Unit";"Zergling";"Larva";314;1
"Unit";"Zergling";"Larva";314;1
"Unit";"Zergling";"Larva";314;1
"Unit";"Zergling";"Larva";314;1
"Unit";"Zergling";"Larva";314;1
"Unit";"Zergling";"Larva";314;1
"Unit";"Zergling";"Larva";314;1
"Unit";"Zergling";"Larva";314;1
"Unit";"Zergling";"Larva";314;1
"Unit";"Zergling";"Larva";314;1
"Unit";"Zergling";"Larva";314;1
"Unit";"Zergling";"Larva";314;1
"Unit";"Zergling";"Larva";314;1
"Unit";"Zergling";"Larva";314;1
"Unit";"Zergling";"Larva";314;1
"Unit";"Zergling";"Larva";314;1
"Unit";"Zergling";"Larva";314;1
"Unit";"Zergling";"Larva";314;1
"Building";"CreepTumor";NA;316;0
"Unit";"Zergling";"Larva";314;1
"Unit";"Zergling";"Larva";314;1
"Unit";"Zergling";"Larva";314;1
"Unit";"Zergling";"Larva";314;1
"Unit";"Zergling";"Larva";314;1
"Unit";"Zergling";"Larva";314;1
"Building";"CreepTumorQueen";NA;316;0
"Building";"CreepTumorQueen";NA;316;0
"Building";"CreepTumor";NA;322;0
"Building";"CreepTumor";NA;322;0
"Building";"CreepTumor";NA;322;0
"Building";"UltraliskCavern";NA;314;0
"Building";"CreepTumor";NA;350;0
"Unit";"Viper";"Larva";316;3
"Building";"CreepTumor";NA;350;0
"Unit";"Viper";"Larva";316;3
"Unit";"Overlord";"Larva";350;0
"Unit";"Overlord";"Larva";350;0
"Building";"Extractor";NA;350;0
"Building";"Extractor";NA;350;0
"Unit";"Baneling";"Zergling";350;0
"Unit";"Baneling";"Zergling";350;0
"Unit";"Baneling";"Zergling";350;0
"Unit";"Baneling";"Zergling";350;0
"Unit";"Baneling";"Zergling";350;0
"Unit";"Baneling";"Zergling";350;0
"Unit";"Baneling";"Zergling";350;0
"Unit";"Baneling";"Zergling";350;0
"Building";"CreepTumorQueen";NA;356;0
"Building";"CreepTumor";NA;353;0
"Building";"CreepTumor";NA;353;0
"Building";"CreepTumorQueen";NA;356;0
"Building";"CreepTumorQueen";NA;362;0
"Unit";"Zergling";"Larva";362;1
"Unit";"Zergling";"Larva";362;1
"Unit";"Zergling";"Larva";362;1
"Unit";"Zergling";"Larva";362;1
"Unit";"Zergling";"Larva";362;1
"Unit";"Zergling";"Larva";362;1
"Unit";"Zergling";"Larva";362;1
"Unit";"Zergling";"Larva";362;1
"Unit";"Zergling";"Larva";362;1
"Unit";"Zergling";"Larva";362;1
"Unit";"Zergling";"Larva";362;1
"Unit";"Zergling";"Larva";362;1
"Unit";"Zergling";"Larva";362;1
"Unit";"Zergling";"Larva";362;1
"Unit";"Zergling";"Larva";362;1
"Unit";"Zergling";"Larva";362;1
"Unit";"Zergling";"Larva";362;1
"Unit";"Zergling";"Larva";362;1
"Unit";"Zergling";"Larva";362;1
"Unit";"Zergling";"Larva";362;1
"Unit";"Zergling";"Larva";362;1
"Unit";"Zergling";"Larva";362;1
"Unit";"Zergling";"Larva";362;1
"Unit";"Zergling";"Larva";362;1
"Unit";"Zergling";"Larva";362;1
"Unit";"Zergling";"Larva";362;1
"Building";"CreepTumor";NA;362;0
"Unit";"Zergling";"Larva";362;1
"Unit";"Zergling";"Larva";362;1
"Unit";"Zergling";"Larva";362;1
"Unit";"Zergling";"Larva";362;1
"Unit";"Zergling";"Larva";362;1
"Unit";"Zergling";"Larva";362;1
"Unit";"Zergling";"Larva";362;1
"Unit";"Zergling";"Larva";362;1
"Unit";"Zergling";"Larva";362;1
"Unit";"Zergling";"Larva";362;1
"Unit";"Zergling";"Larva";362;1
"Unit";"Zergling";"Larva";362;1
"Unit";"Zergling";"Larva";362;1
"Unit";"Zergling";"Larva";362;1
"Unit";"Zergling";"Larva";362;1
"Unit";"Zergling";"Larva";362;1
"Building";"CreepTumor";NA;362;0
"Building";"CreepTumor";NA;362;0
"Building";"CreepTumor";NA;362;0
"Building";"CreepTumorQueen";NA;362;0
"Building";"CreepTumor";NA;364;0
"Building";"CreepTumor";NA;364;0
"Building";"CreepTumor";NA;382;0
"Unit";"Baneling";"Zergling";404;0
"Unit";"Baneling";"Zergling";404;0
"Unit";"Baneling";"Zergling";404;0
"Unit";"Baneling";"Zergling";404;0
"Unit";"Baneling";"Zergling";404;0
"Unit";"Baneling";"Zergling";404;0
"Unit";"Baneling";"Zergling";404;0
"Unit";"Baneling";"Zergling";404;0
"Unit";"Baneling";"Zergling";404;0
"Unit";"Baneling";"Zergling";404;0
"Building";"Extractor";NA;404;0
"Building";"Extractor";NA;404;0
"Unit";"Ultralisk";"Larva";404;6
"Unit";"Ultralisk";"Larva";404;6
"Unit";"Ultralisk";"Larva";404;6
"Unit";"Ultralisk";"Larva";404;6
"Unit";"Ultralisk";"Larva";404;6
"Unit";"Ultralisk";"Larva";404;6
"Upgrade";"ZergMeleeWeaponsLevel3";"EvolutionChamber";362;0
"Upgrade";"ZergGroundArmorsLevel3";"EvolutionChamber";362;0
"Building";"UltraliskCavern";NA;404;0
"Unit";"Zergling";"Larva";443;1
"Unit";"Zergling";"Larva";443;1
"Unit";"Zergling";"Larva";443;1
"Unit";"Zergling";"Larva";443;1
"Unit";"Zergling";"Larva";443;1
"Unit";"Zergling";"Larva";443;1
"Building";"CreepTumorQueen";NA;445;0
"Building";"CreepTumorQueen";NA;445;0
"Unit";"Zergling";"Larva";445;1
"Unit";"Zergling";"Larva";445;1
"Building";"CreepTumorQueen";NA;445;0
"Unit";"Zergling";"Larva";445;1
"Unit";"Zergling";"Larva";445;1
"Unit";"Zergling";"Larva";445;1
"Unit";"Zergling";"Larva";445;1
"Unit";"Zergling";"Larva";445;1
"Unit";"Zergling";"Larva";445;1
"Unit";"Zergling";"Larva";445;1
"Unit";"Zergling";"Larva";445;1
"Unit";"Zergling";"Larva";445;1
"Unit";"Zergling";"Larva";445;1
"Unit";"Zergling";"Larva";445;1
"Unit";"Zergling";"Larva";445;1
"Unit";"Zergling";"Larva";445;1
"Unit";"Zergling";"Larva";445;1
"Unit";"Zergling";"Larva";445;1
"Unit";"Zergling";"Larva";445;1
"Unit";"Zergling";"Larva";445;1
"Unit";"Zergling";"Larva";445;1
"Unit";"Zergling";"Larva";445;1
"Unit";"Zergling";"Larva";445;1
"Unit";"Zergling";"Larva";445;1
"Unit";"Zergling";"Larva";445;1
"Unit";"Zergling";"Larva";445;1
"Unit";"Zergling";"Larva";445;1
"Unit";"Zergling";"Larva";445;1
"Unit";"Zergling";"Larva";445;1
"Unit";"Zergling";"Larva";445;1
"Unit";"Zergling";"Larva";445;1
"Unit";"Zergling";"Larva";445;1
"Unit";"Zergling";"Larva";445;1
"Unit";"Zergling";"Larva";445;1
"Unit";"Zergling";"Larva";445;1
"Unit";"Zergling";"Larva";445;1
"Unit";"Zergling";"Larva";445;1
"Unit";"Zergling";"Larva";445;1
"Unit";"Zergling";"Larva";445;1
"Unit";"Zergling";"Larva";445;1
"Unit";"Zergling";"Larva";445;1
"Unit";"Zergling";"Larva";445;1
"Unit";"Zergling";"Larva";445;1
"Unit";"Zergling";"Larva";445;1
"Unit";"Zergling";"Larva";445;1
"Unit";"Zergling";"Larva";445;1
"Unit";"Zergling";"Larva";445;1
"Unit";"Zergling";"Larva";445;1
"Unit";"Zergling";"Larva";445;1
"Unit";"Zergling";"Larva";445;1
"Unit";"Zergling";"Larva";445;1
"Unit";"Zergling";"Larva";445;1
"Unit";"Zergling";"Larva";445;1
"Unit";"Zergling";"Larva";445;1
"Unit";"Zergling";"Larva";445;1
"Building";"CreepTumorQueen";NA;451;0
"Building";"CreepTumorQueen";NA;451;0
"Building";"Spire";NA;404;0
"Unit";"Baneling";"Zergling";505;0
"Unit";"Baneling";"Zergling";505;0
"Unit";"Baneling";"Zergling";505;0
"Unit";"Baneling";"Zergling";505;0
"Unit";"Baneling";"Zergling";505;0
"Unit";"Baneling";"Zergling";505;0
"Unit";"Baneling";"Zergling";505;0
"Unit";"Baneling";"Zergling";505;0
"Unit";"Baneling";"Zergling";505;0
"Unit";"Baneling";"Zergling";505;0
"Unit";"Baneling";"Zergling";505;0
"Building";"CreepTumor";NA;508;0
"Building";"CreepTumor";NA;508;0
"Building";"CreepTumor";NA;508;0
"Building";"CreepTumorQueen";NA;510;0
"Unit";"Corruptor";"Larva";510;2
"Unit";"Corruptor";"Larva";510;2
"Building";"CreepTumorQueen";NA;510;0
"Building";"CreepTumorQueen";NA;510;0
"Building";"Hatchery";NA;445;0
"Building";"CreepTumor";NA;514;0
"Building";"CreepTumor";NA;514;0
"Building";"CreepTumor";NA;514;0
"Building";"CreepTumor";NA;514;0
"Building";"CreepTumor";NA;514;0
"Building";"CreepTumor";NA;514;0
"Unit";"Corruptor";"Larva";514;2
"Unit";"Corruptor";"Larva";514;2
"Unit";"Corruptor";"Larva";514;2
"Building";"Hatchery";NA;510;0
"Building";"CreepTumorQueen";NA;514;0
"Upgrade";"ZergMissileWeaponsLevel1";"EvolutionChamber";505;0
"Building";"CreepTumorQueen";NA;514;0
"Building";"CreepTumor";NA;514;0
"Building";"CreepTumor";NA;514;0
"Building";"CreepTumor";NA;514;0
"Unit";"Ultralisk";"Larva";514;6
"Unit";"Ultralisk";"Larva";514;6
"Unit";"Ultralisk";"Larva";514;6
"Unit";"Ultralisk";"Larva";514;6
"Unit";"Ultralisk";"Larva";514;6
"Unit";"Ultralisk";"Larva";514;6
"Unit";"Zergling";"Larva";520;1
"Unit";"Zergling";"Larva";520;1
"Unit";"Zergling";"Larva";520;1
"Unit";"Zergling";"Larva";520;1
"Unit";"Zergling";"Larva";520;1
"Unit";"Zergling";"Larva";520;1
"Unit";"Zergling";"Larva";520;1
"Unit";"Zergling";"Larva";520;1
"Unit";"Zergling";"Larva";520;1
"Unit";"Zergling";"Larva";520;1
"Unit";"Zergling";"Larva";520;1
"Unit";"Zergling";"Larva";520;1
"Unit";"Zergling";"Larva";520;1
"Unit";"Zergling";"Larva";520;1
"Unit";"Zergling";"Larva";520;1
"Unit";"Zergling";"Larva";520;1
"Unit";"Zergling";"Larva";520;1
"Unit";"Zergling";"Larva";520;1
"Unit";"Zergling";"Larva";520;1
"Unit";"Zergling";"Larva";520;1
"Unit";"Zergling";"Larva";520;1
"Unit";"Zergling";"Larva";520;1
"Unit";"Zergling";"Larva";520;1
"Unit";"Zergling";"Larva";520;1
"Unit";"Zergling";"Larva";520;1
"Unit";"Zergling";"Larva";520;1
"Unit";"Zergling";"Larva";520;1
"Unit";"Zergling";"Larva";520;1
"Unit";"Zergling";"Larva";520;1
"Unit";"Zergling";"Larva";520;1
"Unit";"Zergling";"Larva";520;1
"Unit";"Zergling";"Larva";520;1
"Unit";"Zergling";"Larva";520;1
"Unit";"Zergling";"Larva";520;1
"Unit";"Zergling";"Larva";520;1
"Unit";"Zergling";"Larva";520;1
"Unit";"Zergling";"Larva";520;1
"Unit";"Zergling";"Larva";520;1
"Unit";"Zergling";"Larva";520;1
"Unit";"Zergling";"Larva";520;1
"Unit";"Zergling";"Larva";520;1
"Unit";"Zergling";"Larva";520;1
"Unit";"Zergling";"Larva";520;1
"Unit";"Zergling";"Larva";520;1
"Unit";"Zergling";"Larva";520;1
"Unit";"Zergling";"Larva";520;1
"Unit";"Zergling";"Larva";520;1
"Unit";"Zergling";"Larva";520;1
"Unit";"Zergling";"Larva";520;1
"Unit";"Zergling";"Larva";520;1
"Unit";"Zergling";"Larva";520;1
"Unit";"Zergling";"Larva";520;1
"Unit";"Zergling";"Larva";520;1
"Unit";"Zergling";"Larva";520;1
"Unit";"Zergling";"Larva";520;1
"Unit";"Zergling";"Larva";520;1
"Unit";"Zergling";"Larva";520;1
"Unit";"Zergling";"Larva";520;1
"Unit";"Zergling";"Larva";520;1
"Unit";"Zergling";"Larva";520;1
"Unit";"Zergling";"Larva";520;1
"Unit";"Zergling";"Larva";520;1
"Unit";"Zergling";"Larva";520;1
"Unit";"Zergling";"Larva";520;1
"Unit";"Zergling";"Larva";556;1
"Unit";"Zergling";"Larva";556;1
"Unit";"Zergling";"Larva";556;1
"Unit";"Zergling";"Larva";556;1
"Unit";"Zergling";"Larva";556;1
"Unit";"Zergling";"Larva";556;1
"Unit";"Zergling";"Larva";556;1
"Unit";"Zergling";"Larva";556;1
"Unit";"Zergling";"Larva";556;1
"Unit";"Zergling";"Larva";556;1
"Upgrade";"ChitinousPlating";"UltraliskCavern";514;0
"Unit";"Ultralisk";"Larva";520;6
"Unit";"Hydralisk";"Larva";630;2
"Unit";"Hydralisk";"Larva";630;2
"Unit";"Hydralisk";"Larva";630;2
"Unit";"Hydralisk";"Larva";630;2
"Unit";"Hydralisk";"Larva";630;2
"Unit";"Hydralisk";"Larva";630;2
"Building";"CreepTumor";NA;636;0
"Building";"CreepTumor";NA;636;0
"Building";"CreepTumor";NA;636;0
"Building";"CreepTumor";NA;660;0
"Building";"CreepTumor";NA;660;0
"Building";"CreepTumor";NA;660;0
"Unit";"Baneling";"Zergling";660;0
"Unit";"Baneling";"Zergling";660;0
"Unit";"Baneling";"Zergling";660;0
"Unit";"Baneling";"Zergling";660;0
"Unit";"Baneling";"Zergling";660;0
"Unit";"Baneling";"Zergling";660;0
"Unit";"Baneling";"Zergling";660;0
"Unit";"Baneling";"Zergling";660;0
"Building";"CreepTumor";NA;660;0
"Unit";"Viper";"Larva";660;3
"Building";"CreepTumor";NA;660;0
"Building";"CreepTumor";NA;660;0
"Building";"CreepTumor";NA;660;0
"Building";"CreepTumor";NA;660;0
"Unit";"Corruptor";"Larva";660;2
"Unit";"Corruptor";"Larva";660;2
"Unit";"Corruptor";"Larva";660;2
"Unit";"Viper";"Larva";660;3
"Unit";"Viper";"Larva";660;3
"Unit";"Overlord";"Larva";663;0
"Unit";"Overlord";"Larva";663;0
"Unit";"Overlord";"Larva";663;0
"Building";"Hatchery";NA;648;0
"Unit";"Corruptor";"Larva";663;2
"Unit";"Corruptor";"Larva";663;2
"Building";"CreepTumor";NA;679;0
"Building";"CreepTumor";NA;679;0
"Building";"CreepTumor";NA;679;0
"Building";"CreepTumor";NA;679;0
"Building";"CreepTumor";NA;679;0
"Unit";"Zergling";"Larva";679;1
"Unit";"Zergling";"Larva";679;1
"Unit";"Zergling";"Larva";679;1
"Unit";"Zergling";"Larva";679;1
"Unit";"Zergling";"Larva";679;1
"Unit";"Zergling";"Larva";679;1
"Unit";"Zergling";"Larva";679;1
"Unit";"Zergling";"Larva";679;1
"Unit";"Zergling";"Larva";679;1
"Unit";"Zergling";"Larva";679;1
"Unit";"Zergling";"Larva";679;1
"Unit";"Zergling";"Larva";679;1
"Unit";"Zergling";"Larva";679;1
"Unit";"Zergling";"Larva";679;1
"Unit";"Zergling";"Larva";679;1
"Unit";"Zergling";"Larva";679;1
"Unit";"Corruptor";"Larva";679;2
"Unit";"Corruptor";"Larva";679;2
"Unit";"Corruptor";"Larva";679;2
"Unit";"Corruptor";"Larva";679;2
"Building";"Hatchery";NA;675;0
"Building";"Hatchery";NA;679;0
"Building";"CreepTumorQueen";NA;711;0
"Building";"CreepTumor";NA;711;0
"Building";"CreepTumorQueen";NA;711;0
"Building";"CreepTumorQueen";NA;711;0
"Building";"CreepTumorQueen";NA;711;0
"Building";"Hatchery";NA;679;0
"Unit";"Zergling";"Larva";711;1
"Unit";"Zergling";"Larva";711;1
"Unit";"Zergling";"Larva";711;1
"Unit";"Zergling";"Larva";711;1
"Unit";"Zergling";"Larva";711;1
"Unit";"Zergling";"Larva";711;1
"Unit";"Zergling";"Larva";711;1
"Unit";"Zergling";"Larva";711;1
"Unit";"Zergling";"Larva";711;1
"Unit";"Zergling";"Larva";711;1
"Unit";"Zergling";"Larva";711;1
"Unit";"Zergling";"Larva";711;1
"Unit";"Zergling";"Larva";711;1
"Unit";"Zergling";"Larva";711;1
"Unit";"Zergling";"Larva";711;1
"Unit";"Zergling";"Larva";711;1
"Unit";"Zergling";"Larva";711;1
"Unit";"Zergling";"Larva";711;1
"Unit";"Zergling";"Larva";711;1
"Unit";"Zergling";"Larva";711;1
"Unit";"Zergling";"Larva";711;1
"Unit";"Zergling";"Larva";711;1
"Unit";"Zergling";"Larva";711;1
"Unit";"Zergling";"Larva";711;1
"Unit";"Zergling";"Larva";711;1
"Unit";"Zergling";"Larva";711;1
"Unit";"Zergling";"Larva";711;1
"Unit";"Zergling";"Larva";711;1
"Unit";"Zergling";"Larva";711;1
"Unit";"Zergling";"Larva";711;1
"Unit";"Zergling";"Larva";711;1
"Unit";"Zergling";"Larva";711;1
"Building";"CreepTumor";NA;743;0
"Building";"CreepTumor";NA;743;0
"Building";"CreepTumor";NA;743;0
"Building";"CreepTumor";NA;744;0
"Building";"CreepTumor";NA;748;0
"Building";"CreepTumor";NA;753;0
"Building";"CreepTumor";NA;753;0
"Building";"CreepTumor";NA;753;0
"Building";"CreepTumor";NA;753;0
"Building";"CreepTumor";NA;753;0
"Unit";"Baneling";"Zergling";753;0
"Unit";"Baneling";"Zergling";753;0
"Unit";"Baneling";"Zergling";753;0
"Unit";"Baneling";"Zergling";753;0
"Unit";"Baneling";"Zergling";753;0
"Unit";"Baneling";"Zergling";753;0
"Unit";"Baneling";"Zergling";753;0
"Unit";"Baneling";"Zergling";753;0
"Unit";"Baneling";"Zergling";753;0
"Unit";"Baneling";"Zergling";753;0
"Unit";"Baneling";"Zergling";753;0
"Unit";"Baneling";"Zergling";753;0
"Building";"CreepTumorQueen";NA;753;0
"Building";"CreepTumorQueen";NA;753;0
"Building";"Extractor";NA;753;0
"Upgrade";"Burrow";"Hatchery";753;0
"Building";"CreepTumor";NA;753;0
"Building";"Hatchery";NA;753;0
"Unit";"Corruptor";"Larva";753;2
"Unit";"Corruptor";"Larva";753;2
"Unit";"Corruptor";"Larva";753;2
"Unit";"Corruptor";"Larva";753;2
"Unit";"Corruptor";"Larva";753;2
"Unit";"Corruptor";"Larva";753;2
"Unit";"Corruptor";"Larva";753;2
"Unit";"Corruptor";"Larva";753;2
"Unit";"Corruptor";"Larva";753;2
"Building";"Extractor";NA;775;0
"Building";"Extractor";NA;775;0
"Unit";"Overlord";"Larva";775;0
"Unit";"Overlord";"Larva";775;0
"Unit";"Overlord";"Larva";775;0
"Unit";"Overlord";"Larva";775;0
"Unit";"Overlord";"Larva";775;0
"Unit";"Overlord";"Larva";775;0
"Unit";"Overlord";"Larva";775;0
"Unit";"Infestor";"Larva";757;2
"Unit";"Infestor";"Larva";757;2
"Unit";"Infestor";"Larva";757;2
"Unit";"Infestor";"Larva";757;2
"Unit";"Infestor";"Larva";757;2
"Unit";"Infestor";"Larva";757;2
"Building";"Extractor";NA;775;0
"Unit";"Overlord";"Larva";775;0
"Building";"SporeCrawler";NA;775;0
"Building";"SporeCrawler";NA;775;0
"Building";"SporeCrawler";NA;775;0
"Upgrade";"ZergMissileWeaponsLevel2";"EvolutionChamber";753;0
"Building";"Extractor";NA;787;0
"Building";"Extractor";NA;787;0
"Building";"Hatchery";NA;775;0
"Unit";"Queen";"Hatchery";787;2
"Unit";"Zergling";"Larva";787;1
"Unit";"Zergling";"Larva";787;1
"Unit";"Zergling";"Larva";787;1
"Unit";"Zergling";"Larva";787;1
"Unit";"Zergling";"Larva";787;1
"Unit";"Zergling";"Larva";787;1
"Unit";"Zergling";"Larva";787;1
"Unit";"Zergling";"Larva";787;1
"Unit";"Zergling";"Larva";787;1
"Unit";"Zergling";"Larva";787;1
"Unit";"Zergling";"Larva";787;1
"Unit";"Zergling";"Larva";787;1
"Unit";"Zergling";"Larva";787;1
"Unit";"Zergling";"Larva";787;1
"Unit";"Zergling";"Larva";787;1
"Unit";"Zergling";"Larva";787;1
"Unit";"Zergling";"Larva";787;1
"Unit";"Zergling";"Larva";787;1
"Unit";"Zergling";"Larva";787;1
"Unit";"Zergling";"Larva";787;1
"Unit";"Zergling";"Larva";787;1
"Unit";"Zergling";"Larva";787;1
"Unit";"Zergling";"Larva";787;1
"Unit";"Zergling";"Larva";787;1
"Unit";"Zergling";"Larva";787;1
"Unit";"Zergling";"Larva";787;1
"Unit";"Zergling";"Larva";787;1
"Unit";"Zergling";"Larva";787;1
"Unit";"Zergling";"Larva";787;1
"Unit";"Zergling";"Larva";787;1
"Unit";"Zergling";"Larva";787;1
"Unit";"Zergling";"Larva";787;1
"Unit";"Zergling";"Larva";787;1
"Unit";"Zergling";"Larva";787;1
"Unit";"Zergling";"Larva";787;1
"Unit";"Zergling";"Larva";787;1
"Unit";"Zergling";"Larva";787;1
"Unit";"Zergling";"Larva";787;1
"Unit";"Zergling";"Larva";787;1
"Unit";"Zergling";"Larva";787;1
"Unit";"Zergling";"Larva";787;1
"Unit";"Zergling";"Larva";787;1
"Unit";"Zergling";"Larva";787;1
"Unit";"Zergling";"Larva";787;1
"Unit";"Zergling";"Larva";787;1
"Unit";"Zergling";"Larva";787;1
"Unit";"Zergling";"Larva";787;1
"Unit";"Zergling";"Larva";787;1
"Unit";"Zergling";"Larva";787;1
"Unit";"Zergling";"Larva";787;1
"Unit";"Zergling";"Larva";787;1
"Unit";"Zergling";"Larva";787;1
"Unit";"Zergling";"Larva";787;1
"Unit";"Zergling";"Larva";787;1
"Unit";"Zergling";"Larva";787;1
"Unit";"Zergling";"Larva";787;1
"Unit";"Zergling";"Larva";787;1
"Unit";"Zergling";"Larva";787;1
"Unit";"Zergling";"Larva";787;1
"Unit";"Zergling";"Larva";787;1
"Unit";"Zergling";"Larva";787;1
"Unit";"Zergling";"Larva";787;1
"Unit";"Zergling";"Larva";787;1
"Unit";"Zergling";"Larva";787;1
"Unit";"Zergling";"Larva";787;1
"Unit";"Zergling";"Larva";787;1
"Unit";"Zergling";"Larva";787;1
"Unit";"Zergling";"Larva";787;1
"Unit";"Zergling";"Larva";787;1
"Unit";"Zergling";"Larva";787;1
"Unit";"Zergling";"Larva";787;1
"Unit";"Zergling";"Larva";787;1
"Unit";"Zergling";"Larva";787;1
"Unit";"Zergling";"Larva";787;1
"Unit";"Zergling";"Larva";787;1
"Unit";"Zergling";"Larva";787;1
"Unit";"Zergling";"Larva";787;1
"Unit";"Zergling";"Larva";787;1
"Unit";"Hydralisk";"Larva";787;2
"Unit";"Hydralisk";"Larva";787;2
"Unit";"Hydralisk";"Larva";787;2
"Unit";"Hydralisk";"Larva";787;2
"Unit";"Hydralisk";"Larva";787;2
"Unit";"Queen";"Hatchery";789;2
"Unit";"Queen";"Hatchery";789;2
"Unit";"Queen";"Hatchery";789;2
"Unit";"Queen";"Hatchery";789;2
"Unit";"Queen";"Hatchery";789;2
"Unit";"Queen";"Hatchery";789;2
"Building";"CreepTumor";NA;886;0
"Unit";"Hydralisk";"Larva";877;2
"Unit";"Hydralisk";"Larva";877;2
"Unit";"Hydralisk";"Larva";877;2
"Unit";"Hydralisk";"Larva";877;2
"Unit";"Hydralisk";"Larva";877;2
"Unit";"Hydralisk";"Larva";877;2
"Unit";"Hydralisk";"Larva";877;2
"Unit";"Hydralisk";"Larva";877;2
"Unit";"Hydralisk";"Larva";877;2
"Unit";"Hydralisk";"Larva";877;2
"Unit";"Hydralisk";"Larva";877;2
"Unit";"Hydralisk";"Larva";877;2
"Unit";"Hydralisk";"Larva";877;2
"Unit";"Zergling";"Larva";898;1
"Unit";"Zergling";"Larva";898;1
"Unit";"Zergling";"Larva";898;1
"Unit";"Zergling";"Larva";898;1
"Unit";"Zergling";"Larva";898;1
"Unit";"Zergling";"Larva";898;1
"Unit";"Zergling";"Larva";898;1
"Unit";"Zergling";"Larva";898;1
"Unit";"Zergling";"Larva";898;1
"Unit";"Zergling";"Larva";898;1
"Unit";"Zergling";"Larva";898;1
"Unit";"Zergling";"Larva";898;1
"Unit";"Zergling";"Larva";898;1
"Unit";"Zergling";"Larva";898;1
"Unit";"Zergling";"Larva";898;1
"Unit";"Zergling";"Larva";898;1
"Unit";"Zergling";"Larva";898;1
"Unit";"Zergling";"Larva";898;1
"Unit";"Zergling";"Larva";898;1
"Unit";"Zergling";"Larva";898;1
"Unit";"Zergling";"Larva";898;1
"Unit";"Zergling";"Larva";898;1
"Unit";"Zergling";"Larva";898;1
"Unit";"Zergling";"Larva";898;1
"Unit";"Baneling";"Zergling";924;0
"Unit";"Baneling";"Zergling";924;0
"Unit";"Baneling";"Zergling";924;0
"Unit";"Baneling";"Zergling";924;0
"Unit";"Baneling";"Zergling";924;0
"Unit";"Baneling";"Zergling";924;0
"Unit";"Baneling";"Zergling";924;0
"Unit";"Baneling";"Zergling";924;0
"Unit";"Baneling";"Zergling";924;0
"Unit";"Baneling";"Zergling";924;0
"Unit";"Baneling";"Zergling";924;0
"Unit";"Baneling";"Zergling";924;0
"Unit";"Queen";"Hatchery";898;2
"Unit";"Corruptor";"Larva";950;2
"Unit";"Corruptor";"Larva";950;2
"Unit";"Corruptor";"Larva";950;2
"Unit";"Corruptor";"Larva";950;2
"Unit";"Corruptor";"Larva";950;2
"Unit";"Corruptor";"Larva";950;2
"Building";"CreepTumor";NA;950;0
"Building";"CreepTumor";NA;950;0
"Building";"CreepTumor";NA;950;0
"Building";"CreepTumor";NA;950;0
"Building";"CreepTumor";NA;950;0
"Unit";"Baneling";"Zergling";950;0
"Unit";"Baneling";"Zergling";952;0
"Unit";"Baneling";"Zergling";952;0
"Unit";"Baneling";"Zergling";952;0
"Unit";"Baneling";"Zergling";952;0
"Unit";"Baneling";"Zergling";952;0
"Unit";"Baneling";"Zergling";952;0
"Unit";"Baneling";"Zergling";952;0
"Unit";"Baneling";"Zergling";952;0
"Building";"CreepTumorQueen";NA;962;0
"Unit";"Viper";"Larva";962;3
"Unit";"Viper";"Larva";962;3
"Unit";"Viper";"Larva";962;3
"Unit";"Corruptor";"Larva";962;2
"Unit";"Corruptor";"Larva";962;2
"Unit";"Corruptor";"Larva";962;2
"Unit";"Corruptor";"Larva";962;2
"Unit";"Corruptor";"Larva";962;2
"Building";"Hatchery";NA;962;0
"Building";"SporeCrawler";NA;981;0
"Building";"SporeCrawler";NA;981;0
"Building";"SporeCrawler";NA;981;0
"Unit";"Zergling";"Larva";981;1
"Unit";"Zergling";"Larva";981;1
"Unit";"Zergling";"Larva";981;1
"Unit";"Zergling";"Larva";981;1
"Unit";"Zergling";"Larva";981;1
"Unit";"Zergling";"Larva";981;1
"Unit";"Zergling";"Larva";981;1
"Unit";"Zergling";"Larva";981;1
"Unit";"Zergling";"Larva";981;1
"Unit";"Zergling";"Larva";981;1
"Unit";"Zergling";"Larva";981;1
"Unit";"Zergling";"Larva";981;1
"Unit";"Zergling";"Larva";981;1
"Unit";"Zergling";"Larva";981;1
"Unit";"Zergling";"Larva";981;1
"Unit";"Zergling";"Larva";981;1
"Unit";"Zergling";"Larva";981;1
"Unit";"Zergling";"Larva";981;1
"Unit";"Zergling";"Larva";981;1
"Unit";"Zergling";"Larva";981;1
"Unit";"Zergling";"Larva";981;1
"Unit";"Zergling";"Larva";981;1
"Unit";"Zergling";"Larva";981;1
"Unit";"Zergling";"Larva";981;1
"Unit";"Zergling";"Larva";981;1
"Unit";"Zergling";"Larva";981;1
"Unit";"Zergling";"Larva";981;1
"Unit";"Zergling";"Larva";981;1
"Unit";"Zergling";"Larva";981;1
"Unit";"Zergling";"Larva";981;1
"Unit";"Zergling";"Larva";981;1
"Unit";"Zergling";"Larva";981;1
"Unit";"Zergling";"Larva";981;1
"Unit";"Zergling";"Larva";981;1
"Unit";"Zergling";"Larva";981;1
"Unit";"Zergling";"Larva";981;1
"Unit";"Zergling";"Larva";981;1
"Unit";"Zergling";"Larva";981;1
"Unit";"Zergling";"Larva";981;1
"Unit";"Zergling";"Larva";981;1
"Unit";"Zergling";"Larva";981;1
"Unit";"Zergling";"Larva";981;1
"Unit";"Zergling";"Larva";981;1
"Unit";"Zergling";"Larva";981;1
"Unit";"Zergling";"Larva";981;1
"Unit";"Zergling";"Larva";981;1
"Unit";"Zergling";"Larva";981;1
"Unit";"Zergling";"Larva";981;1
"Unit";"Zergling";"Larva";981;1
"Unit";"Zergling";"Larva";981;1
"Unit";"Zergling";"Larva";981;1
"Unit";"Zergling";"Larva";981;1
"Unit";"Zergling";"Larva";981;1
"Unit";"Zergling";"Larva";981;1
"Unit";"Zergling";"Larva";981;1
"Unit";"Zergling";"Larva";981;1
"Unit";"Zergling";"Larva";981;1
"Unit";"Zergling";"Larva";981;1
"Unit";"Zergling";"Larva";981;1
"Unit";"Zergling";"Larva";981;1
"Unit";"Zergling";"Larva";981;1
"Unit";"Zergling";"Larva";981;1
"Unit";"Zergling";"Larva";981;1
"Unit";"Zergling";"Larva";981;1
"Unit";"Zergling";"Larva";981;1
"Unit";"Zergling";"Larva";981;1
"Unit";"Zergling";"Larva";981;1
"Unit";"Zergling";"Larva";981;1
"Unit";"Zergling";"Larva";981;1
"Unit";"Zergling";"Larva";981;1
"Unit";"Zergling";"Larva";981;1
"Unit";"Zergling";"Larva";981;1
"Unit";"Zergling";"Larva";981;1
"Unit";"Zergling";"Larva";981;1
"Unit";"Zergling";"Larva";981;1
"Unit";"Zergling";"Larva";981;1
"Unit";"Zergling";"Larva";981;1
"Unit";"Zergling";"Larva";981;1
"Unit";"Zergling";"Larva";981;1
"Unit";"Zergling";"Larva";981;1
"Unit";"Zergling";"Larva";981;1
"Unit";"Zergling";"Larva";981;1
"Unit";"Zergling";"Larva";981;1
"Unit";"Zergling";"Larva";981;1
"Unit";"Zergling";"Larva";981;1
"Unit";"Zergling";"Larva";981;1
"Unit";"Zergling";"Larva";981;1
"Unit";"Zergling";"Larva";981;1
"Unit";"Zergling";"Larva";981;1
"Unit";"Zergling";"Larva";981;1
"Unit";"Zergling";"Larva";981;1
"Unit";"Zergling";"Larva";981;1
"Unit";"Zergling";"Larva";981;1
"Unit";"Zergling";"Larva";981;1
"Unit";"Zergling";"Larva";981;1
"Unit";"Zergling";"Larva";981;1
"Unit";"Zergling";"Larva";981;1
"Unit";"Zergling";"Larva";981;1
"Building";"Hatchery";NA;981;0
"Unit";"Baneling";"Zergling";1047;0
"Unit";"Baneling";"Zergling";1047;0
"Unit";"Baneling";"Zergling";1047;0
"Unit";"Baneling";"Zergling";1047;0
"Unit";"Baneling";"Zergling";1047;0
"Unit";"Baneling";"Zergling";1047;0
"Unit";"Baneling";"Zergling";1047;0
"Unit";"Baneling";"Zergling";1047;0
"Unit";"Baneling";"Zergling";1047;0
"Unit";"Baneling";"Zergling";1047;0
"Unit";"Baneling";"Zergling";1047;0
"Unit";"Baneling";"Zergling";1047;0
"Unit";"Baneling";"Zergling";1047;0
"Unit";"Zergling";"Larva";1047;1
"Unit";"Zergling";"Larva";1047;1
"Unit";"Zergling";"Larva";1047;1
"Unit";"Zergling";"Larva";1047;1
"Unit";"Zergling";"Larva";1047;1
"Unit";"Zergling";"Larva";1047;1
"Unit";"Zergling";"Larva";1047;1
"Unit";"Zergling";"Larva";1047;1
"Unit";"Zergling";"Larva";1047;1
"Unit";"Zergling";"Larva";1047;1
"Unit";"Zergling";"Larva";1047;1
"Unit";"Zergling";"Larva";1047;1
"Unit";"Zergling";"Larva";1047;1
"Unit";"Zergling";"Larva";1047;1
"Unit";"Ultralisk";"Larva";981;6
"Unit";"Ultralisk";"Larva";981;6
"Unit";"Ultralisk";"Larva";981;6
"Unit";"Ultralisk";"Larva";981;6
"Unit";"Ultralisk";"Larva";981;6
"Unit";"Ultralisk";"Larva";981;6
"Unit";"Ultralisk";"Larva";981;6
"Unit";"Ultralisk";"Larva";981;6
"Building";"CreepTumor";NA;1152;0
