"type";"unit_name";"on_building";"total_supply";"supply"
"Unit";"Overlord";"Larva";13;0
"Building";"Extractor";NA;18;0
"Unit";"Overlord";"Larva";21;0
"Building";"SpawningPool";NA;19;0
"Building";"Hatchery";NA;17;0
"Unit";"Zergling";"Larva";22;1
"Unit";"Zergling";"Larva";22;1
"Unit";"Zergling";"Larva";22;1
"Unit";"Zergling";"Larva";22;1
"Unit";"Queen";"Hatchery";22;2
"Unit";"Queen";"Hatchery";22;2
"Unit";"Overlord";"Larva";37;0
"Unit";"Queen";"Hatchery";37;2
"Building";"CreepTumorQueen";NA;40;0
"Unit";"Overlord";"Larva";50;0
"Building";"Extractor";NA;50;0
"Building";"Extractor";NA;50;0
"Building";"Hatchery";NA;36;0
"Unit";"Overlord";"Larva";50;0
"Building";"CreepTumor";NA;53;0
"Building";"CreepTumorQueen";NA;53;0
"Unit";"Overlord";"Larva";53;0
"Building";"RoachWarren";NA;50;0
"Unit";"Zergling";"Larva";53;1
"Unit";"Zergling";"Larva";53;1
"Unit";"Zergling";"Larva";53;1
"Unit";"Zergling";"Larva";53;1
"Unit";"Zergling";"Larva";53;1
"Unit";"Zergling";"Larva";53;1
"Unit";"Overlord";"Larva";53;0
"Unit";"Zergling";"Larva";53;1
"Unit";"Zergling";"Larva";53;1
"Unit";"Zergling";"Larva";53;1
"Unit";"Zergling";"Larva";53;1
"Unit";"Zergling";"Larva";53;1
"Unit";"Zergling";"Larva";53;1
"Unit";"Zergling";"Larva";53;1
"Unit";"Zergling";"Larva";53;1
"Building";"CreepTumorQueen";NA;67;0
"Unit";"Queen";"Hatchery";53;2
"Unit";"Overlord";"Larva";67;0
"Building";"CreepTumor";NA;67;0
"Building";"CreepTumor";NA;67;0
"Unit";"Roach";"Larva";67;2
"Unit";"Roach";"Larva";67;2
"Unit";"Roach";"Larva";67;2
"Unit";"Roach";"Larva";67;2
"Unit";"Roach";"Larva";67;2
"Unit";"Roach";"Larva";67;2
"Unit";"Roach";"Larva";67;2
"Unit";"Roach";"Larva";67;2
"Unit";"Overlord";"Larva";69;0
"Building";"CreepTumor";NA;85;0
"Unit";"Roach";"Larva";69;2
"Unit";"Roach";"Larva";69;2
"Unit";"Roach";"Larva";69;2
"Unit";"Roach";"Larva";69;2
"Unit";"Roach";"Larva";85;2
"Building";"CreepTumor";NA;85;0
"Unit";"Overlord";"Larva";85;0
"Unit";"Overlord";"Larva";85;0
"Unit";"Roach";"Larva";95;2
"Unit";"Roach";"Larva";95;2
"Unit";"Roach";"Larva";95;2
"Unit";"Roach";"Larva";95;2
"Building";"CreepTumor";NA;95;0
"Building";"CreepTumor";NA;95;0
"Building";"CreepTumor";NA;95;0
"Unit";"Overlord";"Larva";102;0
"Unit";"Overlord";"Larva";111;0
"Unit";"Overlord";"Larva";111;0
"Building";"CreepTumor";NA;111;0
"Building";"CreepTumor";NA;114;0
"Building";"CreepTumor";NA;114;0
"Building";"EvolutionChamber";NA;111;0
"Building";"EvolutionChamber";NA;111;0
"Unit";"Overlord";"Larva";114;0
"Building";"CreepTumor";NA;124;0
"Unit";"Roach";"Larva";123;2
"Unit";"Roach";"Larva";123;2
"Unit";"Roach";"Larva";123;2
"Unit";"Roach";"Larva";124;2
"Unit";"Roach";"Larva";124;2
"Unit";"Roach";"Larva";124;2
"Unit";"Roach";"Larva";124;2
"Unit";"Overlord";"Larva";130;0
"Unit";"Overlord";"Larva";132;0
"Building";"Extractor";NA;136;0
"Building";"Extractor";NA;138;0
"Building";"CreepTumor";NA;145;0
"Building";"CreepTumor";NA;147;0
"Building";"CreepTumor";NA;147;0
"Unit";"Roach";"Larva";141;2
"Unit";"Roach";"Larva";145;2
"Unit";"Roach";"Larva";146;2
"Unit";"Roach";"Larva";147;2
"Unit";"Roach";"Larva";147;2
"Unit";"Overlord";"Larva";159;0
"Building";"Extractor";NA;159;0
"Building";"CreepTumor";NA;168;0
"Upgrade";"GlialReconstitution";"RoachWarren";145;0
"Building";"CreepTumor";NA;170;0
"Building";"HydraliskDen";NA;159;0
"Unit";"Overlord";"Larva";170;0
"Unit";"Overlord";"Larva";170;0
"Building";"InfestationPit";NA;159;0
"Unit";"Overlord";"Larva";171;0
"Building";"CreepTumor";NA;173;0
"Unit";"Overlord";"Larva";173;0
"Unit";"Overlord";"Larva";173;0
"Building";"CreepTumor";NA;173;0
"Building";"CreepTumor";NA;173;0
"Unit";"Overlord";"Larva";173;0
"Unit";"Roach";"Larva";173;2
"Unit";"Roach";"Larva";173;2
"Unit";"Roach";"Larva";173;2
"Upgrade";"ZergMissileWeaponsLevel1";"EvolutionChamber";159;0
"Unit";"Roach";"Larva";173;2
"Unit";"Roach";"Larva";173;2
"Unit";"Roach";"Larva";173;2
"Upgrade";"ZergGroundArmorsLevel1";"EvolutionChamber";159;0
"Building";"CreepTumor";NA;188;0
"Building";"Hatchery";NA;170;0
"Unit";"Overlord";"Larva";192;0
"Unit";"Overlord";"Larva";198;0
"Building";"Extractor";NA;188;0
"Building";"Extractor";NA;188;0
"Unit";"Overlord";"Larva";198;0
"Unit";"Overlord";"Larva";201;0
"Upgrade";"Burrow";"Hatchery";173;0
"Upgrade";"EvolveMuscularAugments";"HydraliskDen";173;0
"Upgrade";"TunnelingClaws";"RoachWarren";173;0
"Building";"CreepTumor";NA;201;0
"Unit";"Overlord";"Larva";201;0
"Unit";"Overlord";"Larva";201;0
"Unit";"Overlord";"Larva";201;0
"Unit";"Overlord";"Larva";201;0
"Unit";"Hydralisk";"Larva";201;2
"Unit";"Hydralisk";"Larva";201;2
"Unit";"Hydralisk";"Larva";201;2
"Unit";"Hydralisk";"Larva";201;2
"Unit";"Hydralisk";"Larva";201;2
"Unit";"Hydralisk";"Larva";201;2
"Unit";"Hydralisk";"Larva";201;2
"Unit";"Hydralisk";"Larva";201;2
"Unit";"Hydralisk";"Larva";201;2
"Unit";"Hydralisk";"Larva";201;2
"Unit";"Hydralisk";"Larva";201;2
"Unit";"Hydralisk";"Larva";201;2
"Building";"CreepTumor";NA;225;0
"Unit";"Roach";"Larva";225;2
"Unit";"Roach";"Larva";225;2
"Unit";"Hydralisk";"Larva";225;2
"Unit";"Hydralisk";"Larva";225;2
"Unit";"Hydralisk";"Larva";225;2
"Unit";"Hydralisk";"Larva";225;2
"Unit";"Hydralisk";"Larva";225;2
"Unit";"Hydralisk";"Larva";225;2
"Unit";"Hydralisk";"Larva";225;2
"Unit";"Hydralisk";"Larva";225;2
"Building";"CreepTumor";NA;229;0
"Upgrade";"EvolveGroovedSpines";"HydraliskDen";217;0
"Building";"Hatchery";NA;201;0
"Unit";"Roach";"Larva";245;2
"Unit";"Roach";"Larva";245;2
"Unit";"Roach";"Larva";245;2
"Unit";"Roach";"Larva";245;2
"Unit";"Roach";"Larva";245;2
"Unit";"Hydralisk";"Larva";245;2
"Unit";"Hydralisk";"Larva";245;2
"Unit";"Hydralisk";"Larva";245;2
"Unit";"Hydralisk";"Larva";245;2
"Unit";"Hydralisk";"Larva";245;2
"Unit";"Hydralisk";"Larva";245;2
"Unit";"Hydralisk";"Larva";245;2
"Unit";"Roach";"Larva";245;2
"Unit";"Roach";"Larva";245;2
"Unit";"Roach";"Larva";245;2
"Unit";"Roach";"Larva";245;2
"Unit";"Roach";"Larva";245;2
"Unit";"Hydralisk";"Larva";245;2
"Unit";"Hydralisk";"Larva";245;2
"Unit";"Hydralisk";"Larva";245;2
"Unit";"Hydralisk";"Larva";245;2
"Unit";"Hydralisk";"Larva";245;2
"Unit";"Hydralisk";"Larva";245;2
"Unit";"Hydralisk";"Larva";245;2
"Unit";"Hydralisk";"Larva";245;2
"Unit";"Overlord";"Larva";269;0
"Building";"CreepTumor";NA;295;0
"Unit";"Viper";"Larva";269;3
"Unit";"Viper";"Larva";269;3
"Unit";"Viper";"Larva";269;3
"Building";"CreepTumor";NA;314;0
"Upgrade";"ZergMissileWeaponsLevel2";"EvolutionChamber";225;0
"Building";"CreepTumor";NA;325;0
"Upgrade";"ZergGroundArmorsLevel2";"EvolutionChamber";225;0
"Unit";"Hydralisk";"Larva";314;2
"Unit";"Hydralisk";"Larva";314;2
"Unit";"Hydralisk";"Larva";314;2
"Unit";"Hydralisk";"Larva";314;2
"Building";"Extractor";NA;325;0
"Building";"Extractor";NA;325;0
"Building";"CreepTumor";NA;333;0
"Unit";"Roach";"Larva";333;2
"Unit";"Roach";"Larva";333;2
"Unit";"Roach";"Larva";333;2
"Unit";"Hydralisk";"Larva";333;2
"Unit";"Hydralisk";"Larva";333;2
"Unit";"Hydralisk";"Larva";333;2
"Unit";"Hydralisk";"Larva";333;2
"Building";"CreepTumorQueen";NA;347;0
"Building";"CreepTumor";NA;347;0
"Building";"CreepTumor";NA;347;0
"Building";"Hatchery";NA;325;0
"Building";"Hatchery";NA;325;0
"Building";"Extractor";NA;347;0
"Building";"Extractor";NA;347;0
"Unit";"Hydralisk";"Larva";347;2
"Building";"Extractor";NA;347;0
"Building";"Extractor";NA;347;0
"Building";"SpineCrawler";NA;347;0
"Building";"SpineCrawler";NA;347;0
"Building";"SpineCrawler";NA;347;0
"Building";"SpineCrawler";NA;347;0
"Building";"SpineCrawler";NA;347;0
"Building";"SpineCrawler";NA;347;0
"Building";"CreepTumor";NA;352;0
"Building";"CreepTumor";NA;354;0
"Building";"Spire";NA;352;0
"Building";"Spire";NA;352;0
"Building";"CreepTumor";NA;357;0
"Upgrade";"ZergMissileWeaponsLevel3";"EvolutionChamber";347;0
"Upgrade";"ZergGroundArmorsLevel3";"EvolutionChamber";347;0
"Unit";"Hydralisk";"Larva";357;2
"Unit";"Hydralisk";"Larva";357;2
"Unit";"Hydralisk";"Larva";361;2
"Unit";"Hydralisk";"Larva";361;2
"Building";"CreepTumor";NA;361;0
"Unit";"Viper";"Larva";359;3
"Unit";"Viper";"Larva";361;3
"Unit";"Viper";"Larva";361;3
"Unit";"Viper";"Larva";361;3
"Unit";"Viper";"Larva";361;3
"Unit";"Hydralisk";"Larva";361;2
"Unit";"Hydralisk";"Larva";361;2
"Unit";"Hydralisk";"Larva";361;2
"Unit";"Hydralisk";"Larva";361;2
"Unit";"Hydralisk";"Larva";361;2
"Unit";"Hydralisk";"Larva";361;2
"Unit";"Hydralisk";"Larva";361;2
"Unit";"Hydralisk";"Larva";361;2
"Unit";"Hydralisk";"Larva";361;2
"Unit";"Hydralisk";"Larva";361;2
"Unit";"Hydralisk";"Larva";361;2
"Unit";"Hydralisk";"Larva";361;2
"Unit";"Hydralisk";"Larva";361;2
"Unit";"Hydralisk";"Larva";361;2
"Unit";"Hydralisk";"Larva";361;2
"Unit";"Hydralisk";"Larva";361;2
"Unit";"Hydralisk";"Larva";361;2
"Unit";"Viper";"Larva";361;3
"Unit";"Viper";"Larva";361;3
"Unit";"Viper";"Larva";361;3
"Unit";"Viper";"Larva";361;3
"Unit";"Viper";"Larva";361;3
"Building";"CreepTumor";NA;392;0
"Building";"CreepTumor";NA;429;0
"Building";"Hatchery";NA;380;0
"Unit";"Hydralisk";"Larva";429;2
"Unit";"Hydralisk";"Larva";429;2
"Unit";"Hydralisk";"Larva";429;2
"Unit";"Hydralisk";"Larva";429;2
"Unit";"Hydralisk";"Larva";429;2
"Building";"CreepTumor";NA;429;0
"Unit";"Hydralisk";"Larva";429;2
"Unit";"Hydralisk";"Larva";429;2
"Unit";"Hydralisk";"Larva";429;2
"Unit";"Hydralisk";"Larva";429;2
"Unit";"Hydralisk";"Larva";429;2
"Unit";"Hydralisk";"Larva";429;2
"Unit";"Hydralisk";"Larva";429;2
"Unit";"Hydralisk";"Larva";429;2
"Unit";"Hydralisk";"Larva";429;2
"Unit";"Hydralisk";"Larva";429;2
"Unit";"Hydralisk";"Larva";429;2
"Unit";"Hydralisk";"Larva";429;2
"Unit";"Hydralisk";"Larva";429;2
"Unit";"Hydralisk";"Larva";429;2
"Unit";"Hydralisk";"Larva";429;2
"Unit";"Hydralisk";"Larva";429;2
"Unit";"Hydralisk";"Larva";429;2
"Unit";"Hydralisk";"Larva";429;2
"Unit";"Hydralisk";"Larva";429;2
"Unit";"Hydralisk";"Larva";429;2
"Unit";"Hydralisk";"Larva";429;2
"Building";"CreepTumor";NA;482;0
"Unit";"Hydralisk";"Larva";482;2
"Unit";"Hydralisk";"Larva";482;2
"Unit";"Hydralisk";"Larva";482;2
"Unit";"Hydralisk";"Larva";482;2
"Building";"Extractor";NA;482;0
"Building";"SpineCrawler";NA;482;0
"Building";"SpineCrawler";NA;482;0
"Building";"SpineCrawler";NA;482;0
"Building";"Extractor";NA;498;0
"Upgrade";"ZergMeleeWeaponsLevel1";"EvolutionChamber";482;0
"Building";"Hatchery";NA;498;0
"Unit";"Hydralisk";"Larva";498;2
"Unit";"Hydralisk";"Larva";498;2
"Unit";"Hydralisk";"Larva";498;2
"Unit";"Hydralisk";"Larva";498;2
"Unit";"Hydralisk";"Larva";498;2
"Unit";"Hydralisk";"Larva";498;2
"Unit";"Hydralisk";"Larva";498;2
"Unit";"Hydralisk";"Larva";498;2
"Unit";"Hydralisk";"Larva";498;2
"Unit";"Hydralisk";"Larva";498;2
"Unit";"Hydralisk";"Larva";498;2
"Unit";"Hydralisk";"Larva";498;2
"Unit";"Hydralisk";"Larva";498;2
"Unit";"Hydralisk";"Larva";498;2
"Unit";"Hydralisk";"Larva";498;2
"Unit";"Hydralisk";"Larva";498;2
"Unit";"Hydralisk";"Larva";498;2
"Unit";"Hydralisk";"Larva";498;2
"Unit";"Hydralisk";"Larva";498;2
"Unit";"Hydralisk";"Larva";498;2
"Unit";"Hydralisk";"Larva";498;2
"Unit";"Hydralisk";"Larva";498;2
"Unit";"Hydralisk";"Larva";498;2
"Unit";"Hydralisk";"Larva";498;2
"Unit";"Hydralisk";"Larva";498;2
"Unit";"Hydralisk";"Larva";498;2
"Unit";"Hydralisk";"Larva";498;2
"Building";"CreepTumor";NA;552;0
"Building";"CreepTumor";NA;552;0
"Building";"SporeCrawler";NA;552;0
"Building";"CreepTumor";NA;552;0
"Building";"Extractor";NA;552;0
"Building";"SporeCrawler";NA;559;0
"Unit";"Hydralisk";"Larva";569;2
"Unit";"Hydralisk";"Larva";569;2
"Unit";"Hydralisk";"Larva";569;2
"Unit";"Hydralisk";"Larva";569;2
"Unit";"Hydralisk";"Larva";569;2
"Unit";"Hydralisk";"Larva";569;2
"Unit";"Hydralisk";"Larva";569;2
"Building";"SporeCrawler";NA;569;0
"Building";"Extractor";NA;569;0
"Building";"SpineCrawler";NA;569;0
"Building";"SpineCrawler";NA;569;0
"Building";"Extractor";NA;589;0
"Upgrade";"ZergMeleeWeaponsLevel2";"EvolutionChamber";586;0
"Building";"SporeCrawler";NA;599;0
"Unit";"Hydralisk";"Larva";599;2
"Unit";"Hydralisk";"Larva";599;2
"Unit";"Hydralisk";"Larva";599;2
"Unit";"Hydralisk";"Larva";599;2
"Unit";"Hydralisk";"Larva";599;2
"Unit";"Hydralisk";"Larva";599;2
"Unit";"Hydralisk";"Larva";599;2
"Unit";"Hydralisk";"Larva";599;2
"Unit";"Hydralisk";"Larva";599;2
"Unit";"Hydralisk";"Larva";599;2
"Unit";"Hydralisk";"Larva";599;2
"Unit";"Hydralisk";"Larva";599;2
"Unit";"Hydralisk";"Larva";599;2
"Unit";"Hydralisk";"Larva";599;2
"Unit";"Hydralisk";"Larva";599;2
"Unit";"Hydralisk";"Larva";599;2
"Unit";"Hydralisk";"Larva";599;2
"Unit";"Hydralisk";"Larva";599;2
"Unit";"Hydralisk";"Larva";599;2
"Unit";"Hydralisk";"Larva";599;2
"Unit";"Hydralisk";"Larva";599;2
"Unit";"Hydralisk";"Larva";599;2
"Unit";"Hydralisk";"Larva";599;2
"Unit";"Hydralisk";"Larva";599;2
"Unit";"Hydralisk";"Larva";599;2
"Unit";"Hydralisk";"Larva";599;2
"Unit";"Hydralisk";"Larva";599;2
"Unit";"Hydralisk";"Larva";599;2
"Unit";"Hydralisk";"Larva";599;2
"Unit";"Hydralisk";"Larva";599;2
"Unit";"Hydralisk";"Larva";599;2
"Unit";"Hydralisk";"Larva";599;2
"Unit";"Hydralisk";"Larva";599;2
"Unit";"Hydralisk";"Larva";599;2
"Unit";"Mutalisk";"Larva";667;2
"Unit";"Mutalisk";"Larva";667;2
"Unit";"Mutalisk";"Larva";667;2
"Unit";"Mutalisk";"Larva";667;2
"Unit";"Mutalisk";"Larva";667;2
"Unit";"Mutalisk";"Larva";667;2
"Unit";"Mutalisk";"Larva";667;2
"Unit";"Mutalisk";"Larva";667;2
"Unit";"Mutalisk";"Larva";667;2
"Unit";"Mutalisk";"Larva";667;2
"Unit";"Mutalisk";"Larva";667;2
"Unit";"Mutalisk";"Larva";667;2
"Unit";"Mutalisk";"Larva";667;2
"Unit";"Mutalisk";"Larva";667;2
"Unit";"Mutalisk";"Larva";667;2
"Unit";"Mutalisk";"Larva";667;2
"Unit";"Mutalisk";"Larva";667;2
"Unit";"Mutalisk";"Larva";667;2
"Unit";"Mutalisk";"Larva";667;2
"Unit";"Mutalisk";"Larva";667;2
"Unit";"Mutalisk";"Larva";667;2
"Unit";"Mutalisk";"Larva";667;2
"Unit";"Mutalisk";"Larva";667;2
"Unit";"Mutalisk";"Larva";667;2
"Unit";"Mutalisk";"Larva";667;2
"Unit";"Mutalisk";"Larva";667;2
"Unit";"Mutalisk";"Larva";667;2
"Unit";"Mutalisk";"Larva";667;2
"Unit";"Mutalisk";"Larva";667;2
"Unit";"Mutalisk";"Larva";667;2
"Unit";"Mutalisk";"Larva";667;2
"Unit";"Mutalisk";"Larva";667;2
"Unit";"Mutalisk";"Larva";667;2
"Unit";"Mutalisk";"Larva";667;2
"Unit";"Mutalisk";"Larva";730;2
"Unit";"Mutalisk";"Larva";730;2
"Unit";"Mutalisk";"Larva";730;2
"Building";"Hatchery";NA;744;0
"Building";"Extractor";NA;744;0
"Building";"BanelingNest";NA;744;0
"Unit";"Corruptor";"Larva";744;2
"Unit";"Corruptor";"Larva";744;2
"Unit";"Corruptor";"Larva";744;2
"Unit";"Corruptor";"Larva";744;2
"Unit";"Corruptor";"Larva";744;2
"Unit";"Corruptor";"Larva";744;2
"Unit";"Corruptor";"Larva";744;2
"Unit";"Corruptor";"Larva";744;2
"Unit";"Corruptor";"Larva";744;2
"Unit";"Corruptor";"Larva";744;2
"Unit";"Corruptor";"Larva";744;2
"Unit";"Corruptor";"Larva";744;2
"Unit";"Corruptor";"Larva";744;2
"Unit";"Corruptor";"Larva";744;2
"Unit";"Corruptor";"Larva";744;2
"Unit";"Corruptor";"Larva";744;2
"Unit";"Corruptor";"Larva";744;2
"Unit";"Corruptor";"Larva";744;2
"Unit";"Corruptor";"Larva";744;2
"Unit";"Corruptor";"Larva";744;2
"Unit";"Corruptor";"Larva";744;2
"Unit";"Corruptor";"Larva";744;2
"Unit";"Corruptor";"Larva";744;2
"Unit";"Corruptor";"Larva";744;2
"Unit";"Corruptor";"Larva";744;2
"Unit";"Corruptor";"Larva";744;2
"Unit";"Corruptor";"Larva";744;2
"Unit";"Corruptor";"Larva";744;2
"Unit";"Corruptor";"Larva";744;2
"Unit";"Corruptor";"Larva";744;2
"Unit";"Corruptor";"Larva";744;2
"Unit";"Corruptor";"Larva";744;2
"Unit";"Corruptor";"Larva";744;2
"Unit";"Corruptor";"Larva";744;2
"Unit";"Corruptor";"Larva";744;2
"Unit";"Corruptor";"Larva";744;2
"Unit";"Corruptor";"Larva";744;2
"Unit";"Corruptor";"Larva";744;2
"Unit";"Zergling";"Larva";744;1
"Unit";"Zergling";"Larva";744;1
"Unit";"Zergling";"Larva";744;1
"Unit";"Zergling";"Larva";744;1
"Unit";"Zergling";"Larva";744;1
"Unit";"Zergling";"Larva";744;1
"Unit";"Zergling";"Larva";744;1
"Unit";"Zergling";"Larva";744;1
"Unit";"Zergling";"Larva";744;1
"Unit";"Zergling";"Larva";744;1
"Unit";"Zergling";"Larva";744;1
"Unit";"Zergling";"Larva";744;1
"Unit";"Zergling";"Larva";744;1
"Unit";"Zergling";"Larva";744;1
"Unit";"Zergling";"Larva";744;1
"Unit";"Zergling";"Larva";744;1
"Unit";"Zergling";"Larva";744;1
"Unit";"Zergling";"Larva";744;1
"Unit";"Zergling";"Larva";744;1
"Unit";"Zergling";"Larva";744;1
"Unit";"Zergling";"Larva";744;1
"Unit";"Zergling";"Larva";744;1
"Unit";"Zergling";"Larva";744;1
"Unit";"Zergling";"Larva";744;1
"Unit";"Zergling";"Larva";744;1
"Unit";"Zergling";"Larva";744;1
"Unit";"Zergling";"Larva";744;1
"Unit";"Zergling";"Larva";744;1
"Unit";"Zergling";"Larva";744;1
"Unit";"Zergling";"Larva";744;1
"Unit";"Zergling";"Larva";850;1
"Unit";"Zergling";"Larva";850;1
"Unit";"Zergling";"Larva";850;1
"Unit";"Zergling";"Larva";850;1
"Unit";"Zergling";"Larva";850;1
"Unit";"Zergling";"Larva";850;1
"Unit";"Zergling";"Larva";850;1
"Unit";"Zergling";"Larva";850;1
"Unit";"Zergling";"Larva";850;1
"Unit";"Zergling";"Larva";850;1
"Unit";"Zergling";"Larva";850;1
"Unit";"Zergling";"Larva";850;1
"Unit";"Zergling";"Larva";850;1
"Unit";"Zergling";"Larva";850;1
"Unit";"Zergling";"Larva";850;1
"Unit";"Zergling";"Larva";850;1
"Unit";"Zergling";"Larva";850;1
"Unit";"Zergling";"Larva";850;1
"Unit";"Zergling";"Larva";850;1
"Unit";"Zergling";"Larva";850;1
"Unit";"Corruptor";"Larva";870;2
"Unit";"Corruptor";"Larva";870;2
"Unit";"Corruptor";"Larva";870;2
"Unit";"Corruptor";"Larva";870;2
"Unit";"Corruptor";"Larva";870;2
"Unit";"Corruptor";"Larva";870;2
"Unit";"Corruptor";"Larva";870;2
"Unit";"Corruptor";"Larva";870;2
"Unit";"Corruptor";"Larva";870;2
"Unit";"Corruptor";"Larva";870;2
"Unit";"Corruptor";"Larva";870;2
"Unit";"Corruptor";"Larva";870;2
"Unit";"Corruptor";"Larva";870;2
"Unit";"Corruptor";"Larva";870;2
"Unit";"Corruptor";"Larva";870;2
"Unit";"Corruptor";"Larva";870;2
"Unit";"Corruptor";"Larva";870;2
"Unit";"Corruptor";"Larva";870;2
"Unit";"Corruptor";"Larva";870;2
"Unit";"Corruptor";"Larva";870;2
"Unit";"Corruptor";"Larva";870;2
"Unit";"Overlord";"Larva";870;0
"Unit";"Overlord";"Larva";870;0
"Unit";"Overlord";"Larva";870;0
"Unit";"Corruptor";"Larva";870;2
"Unit";"Corruptor";"Larva";870;2
"Unit";"Corruptor";"Larva";870;2
"Unit";"Overlord";"Larva";870;0
"Unit";"Corruptor";"Larva";870;2
"Unit";"Corruptor";"Larva";870;2
"Unit";"Corruptor";"Larva";870;2
"Unit";"Infestor";"Larva";912;2
"Unit";"Infestor";"Larva";912;2
"Upgrade";"NeuralParasite";"InfestationPit";870;0
"Upgrade";"ZergMeleeWeaponsLevel3";"EvolutionChamber";850;0
"Building";"Hatchery";NA;912;0
"Unit";"Overlord";"Larva";928;0
"Unit";"Infestor";"Larva";928;2
"Unit";"Infestor";"Larva";928;2
"Unit";"Infestor";"Larva";928;2
"Unit";"Infestor";"Larva";928;2
"Unit";"Infestor";"Larva";928;2
"Unit";"Infestor";"Larva";928;2
"Unit";"Infestor";"Larva";928;2
"Unit";"Infestor";"Larva";928;2
"Unit";"Infestor";"Larva";928;2
"Unit";"Infestor";"Larva";928;2
"Unit";"Infestor";"Larva";928;2
"Unit";"Infestor";"Larva";928;2
"Unit";"Infestor";"Larva";928;2
"Unit";"Infestor";"Larva";928;2
"Unit";"Infestor";"Larva";928;2
"Unit";"Infestor";"Larva";928;2
"Building";"Hatchery";NA;928;0
"Building";"Hatchery";NA;931;0
"Unit";"Zergling";"Larva";963;1
"Unit";"Zergling";"Larva";963;1
"Unit";"Zergling";"Larva";963;1
"Unit";"Zergling";"Larva";963;1
"Unit";"Zergling";"Larva";963;1
"Unit";"Zergling";"Larva";963;1
"Unit";"Zergling";"Larva";963;1
"Unit";"Zergling";"Larva";963;1
"Unit";"Zergling";"Larva";963;1
"Unit";"Zergling";"Larva";963;1
"Unit";"Zergling";"Larva";963;1
"Unit";"Zergling";"Larva";963;1
"Unit";"Zergling";"Larva";963;1
"Unit";"Zergling";"Larva";963;1
"Unit";"Zergling";"Larva";963;1
"Unit";"Zergling";"Larva";963;1
"Unit";"Zergling";"Larva";963;1
"Unit";"Zergling";"Larva";963;1
"Unit";"Zergling";"Larva";963;1
"Unit";"Zergling";"Larva";963;1
"Unit";"Zergling";"Larva";963;1
"Unit";"Zergling";"Larva";963;1
"Unit";"Zergling";"Larva";963;1
"Unit";"Zergling";"Larva";963;1
"Unit";"Zergling";"Larva";963;1
"Unit";"Zergling";"Larva";963;1
"Unit";"Zergling";"Larva";963;1
"Unit";"Zergling";"Larva";963;1
"Unit";"Zergling";"Larva";963;1
"Unit";"Zergling";"Larva";963;1
"Unit";"Zergling";"Larva";963;1
"Unit";"Zergling";"Larva";963;1
"Unit";"Zergling";"Larva";963;1
"Unit";"Zergling";"Larva";963;1
"Unit";"Zergling";"Larva";963;1
"Unit";"Zergling";"Larva";963;1
"Unit";"Zergling";"Larva";963;1
"Unit";"Zergling";"Larva";963;1
"Unit";"Baneling";"Zergling";1001;0
"Unit";"Baneling";"Zergling";1001;0
"Unit";"Baneling";"Zergling";1001;0
"Unit";"Baneling";"Zergling";1001;0
"Unit";"Baneling";"Zergling";1001;0
"Unit";"Baneling";"Zergling";1001;0
"Unit";"Baneling";"Zergling";1001;0
"Unit";"Baneling";"Zergling";1001;0
"Unit";"Baneling";"Zergling";1001;0
"Unit";"Baneling";"Zergling";1001;0
"Unit";"Baneling";"Zergling";1001;0
"Unit";"Baneling";"Zergling";1001;0
"Unit";"Baneling";"Zergling";1001;0
"Unit";"Baneling";"Zergling";1001;0
"Unit";"Baneling";"Zergling";1001;0
"Unit";"Baneling";"Zergling";1001;0
"Unit";"Baneling";"Zergling";1001;0
"Unit";"Baneling";"Zergling";1001;0
"Unit";"Baneling";"Zergling";1001;0
"Unit";"Baneling";"Zergling";1001;0
"Unit";"Zergling";"Larva";999;1
"Unit";"Zergling";"Larva";999;1
"Unit";"Baneling";"Zergling";1001;0
"Unit";"Baneling";"Zergling";1001;0
"Unit";"Baneling";"Zergling";1001;0
"Unit";"Baneling";"Zergling";1001;0
"Unit";"Zergling";"Larva";999;1
"Unit";"Zergling";"Larva";999;1
"Unit";"Baneling";"Zergling";1001;0
"Unit";"Baneling";"Zergling";1001;0
"Unit";"Baneling";"Zergling";1001;0
"Unit";"Baneling";"Zergling";1001;0
"Unit";"Baneling";"Zergling";1001;0
"Unit";"Baneling";"Zergling";1001;0
"Unit";"Baneling";"Zergling";1001;0
"Unit";"Baneling";"Zergling";1001;0
"Unit";"Zergling";"Larva";999;1
"Unit";"Zergling";"Larva";999;1
"Unit";"Baneling";"Zergling";1001;0
"Unit";"Zergling";"Larva";999;1
"Unit";"Zergling";"Larva";999;1
"Unit";"Zergling";"Larva";1001;1
"Unit";"Zergling";"Larva";1001;1
"Unit";"Zergling";"Larva";1001;1
"Unit";"Zergling";"Larva";1001;1
"Unit";"Zergling";"Larva";1001;1
"Unit";"Zergling";"Larva";1001;1
"Unit";"Zergling";"Larva";1003;1
"Unit";"Zergling";"Larva";1003;1
"Unit";"Zergling";"Larva";1004;1
"Unit";"Zergling";"Larva";1004;1
"Unit";"Zergling";"Larva";1007;1
"Unit";"Zergling";"Larva";1007;1
"Unit";"Zergling";"Larva";1010;1
"Unit";"Zergling";"Larva";1010;1
"Unit";"Zergling";"Larva";1010;1
"Unit";"Zergling";"Larva";1010;1
"Unit";"Zergling";"Larva";1010;1
"Unit";"Zergling";"Larva";1010;1
"Unit";"Zergling";"Larva";1010;1
"Unit";"Zergling";"Larva";1010;1
"Unit";"Zergling";"Larva";1010;1
"Unit";"Zergling";"Larva";1010;1
"Unit";"Zergling";"Larva";1010;1
"Unit";"Zergling";"Larva";1010;1
"Unit";"Zergling";"Larva";1010;1
"Unit";"Zergling";"Larva";1010;1
"Unit";"Zergling";"Larva";1010;1
"Unit";"Zergling";"Larva";1010;1
"Unit";"Zergling";"Larva";1018;1
"Unit";"Zergling";"Larva";1018;1
"Building";"CreepTumorQueen";NA;1032;0
"Building";"CreepTumorQueen";NA;1034;0
"Unit";"Zergling";"Larva";1030;1
"Unit";"Zergling";"Larva";1030;1
"Unit";"Zergling";"Larva";1030;1
"Unit";"Zergling";"Larva";1030;1
"Unit";"Zergling";"Larva";1034;1
"Unit";"Zergling";"Larva";1034;1
"Unit";"Zergling";"Larva";1034;1
"Unit";"Zergling";"Larva";1034;1
"Unit";"Zergling";"Larva";1034;1
"Unit";"Zergling";"Larva";1034;1
"Unit";"Zergling";"Larva";1034;1
"Unit";"Zergling";"Larva";1034;1
"Unit";"Zergling";"Larva";1034;1
"Unit";"Zergling";"Larva";1034;1
"Unit";"Zergling";"Larva";1036;1
"Unit";"Zergling";"Larva";1036;1
"Unit";"Zergling";"Larva";1038;1
"Unit";"Zergling";"Larva";1038;1
"Unit";"Zergling";"Larva";1040;1
"Unit";"Zergling";"Larva";1040;1
"Unit";"Zergling";"Larva";1052;1
"Unit";"Zergling";"Larva";1052;1
"Unit";"Zergling";"Larva";1052;1
"Unit";"Zergling";"Larva";1052;1
"Unit";"Zergling";"Larva";1052;1
"Unit";"Zergling";"Larva";1052;1
"Unit";"Zergling";"Larva";1052;1
"Unit";"Zergling";"Larva";1052;1
"Unit";"Zergling";"Larva";1052;1
"Unit";"Zergling";"Larva";1052;1
"Unit";"Zergling";"Larva";1052;1
"Unit";"Zergling";"Larva";1052;1
"Unit";"Zergling";"Larva";1052;1
"Unit";"Zergling";"Larva";1052;1
"Unit";"Zergling";"Larva";1052;1
"Unit";"Zergling";"Larva";1052;1
"Unit";"Zergling";"Larva";1052;1
"Unit";"Zergling";"Larva";1052;1
"Unit";"Zergling";"Larva";1086;1
"Unit";"Zergling";"Larva";1086;1
"Unit";"Zergling";"Larva";1086;1
"Unit";"Zergling";"Larva";1086;1
"Unit";"Zergling";"Larva";1086;1
"Unit";"Zergling";"Larva";1086;1
"Unit";"Zergling";"Larva";1086;1
"Unit";"Zergling";"Larva";1086;1
"Unit";"Zergling";"Larva";1086;1
"Unit";"Zergling";"Larva";1086;1
"Unit";"Zergling";"Larva";1086;1
"Unit";"Zergling";"Larva";1086;1
"Unit";"Zergling";"Larva";1086;1
"Unit";"Zergling";"Larva";1086;1
"Unit";"Zergling";"Larva";1086;1
"Unit";"Zergling";"Larva";1086;1
"Unit";"Zergling";"Larva";1086;1
"Unit";"Zergling";"Larva";1086;1
"Unit";"Zergling";"Larva";1086;1
"Unit";"Zergling";"Larva";1086;1
"Unit";"Zergling";"Larva";1086;1
"Unit";"Zergling";"Larva";1086;1
"Unit";"Zergling";"Larva";1086;1
"Unit";"Zergling";"Larva";1086;1
"Unit";"Zergling";"Larva";1086;1
"Unit";"Zergling";"Larva";1086;1
"Unit";"Zergling";"Larva";1086;1
"Unit";"Zergling";"Larva";1086;1
"Unit";"Zergling";"Larva";1086;1
"Unit";"Zergling";"Larva";1086;1
"Unit";"Zergling";"Larva";1086;1
"Unit";"Zergling";"Larva";1086;1
"Unit";"Zergling";"Larva";1086;1
"Unit";"Zergling";"Larva";1086;1
"Unit";"Zergling";"Larva";1086;1
"Unit";"Zergling";"Larva";1086;1
"Unit";"Zergling";"Larva";1086;1
"Unit";"Zergling";"Larva";1086;1
"Unit";"Zergling";"Larva";1086;1
"Unit";"Zergling";"Larva";1086;1
"Unit";"Zergling";"Larva";1086;1
"Unit";"Zergling";"Larva";1086;1
"Unit";"Zergling";"Larva";1086;1
"Unit";"Zergling";"Larva";1086;1
"Unit";"Zergling";"Larva";1086;1
"Unit";"Zergling";"Larva";1086;1
"Unit";"Zergling";"Larva";1086;1
"Unit";"Zergling";"Larva";1086;1
"Unit";"Zergling";"Larva";1086;1
"Unit";"Zergling";"Larva";1086;1
"Unit";"Zergling";"Larva";1086;1
"Unit";"Zergling";"Larva";1086;1
"Unit";"Zergling";"Larva";1086;1
"Unit";"Zergling";"Larva";1086;1
"Unit";"Zergling";"Larva";1086;1
"Unit";"Zergling";"Larva";1086;1
"Unit";"Zergling";"Larva";1086;1
"Unit";"Zergling";"Larva";1086;1
"Unit";"Zergling";"Larva";1086;1
"Unit";"Zergling";"Larva";1086;1
"Unit";"Zergling";"Larva";1086;1
"Unit";"Zergling";"Larva";1086;1
"Unit";"Zergling";"Larva";1086;1
"Unit";"Zergling";"Larva";1086;1
"Unit";"Zergling";"Larva";1086;1
"Unit";"Zergling";"Larva";1086;1
"Unit";"Zergling";"Larva";1086;1
"Unit";"Zergling";"Larva";1086;1
"Unit";"Zergling";"Larva";1086;1
"Unit";"Zergling";"Larva";1086;1
"Unit";"Zergling";"Larva";1086;1
"Unit";"Zergling";"Larva";1086;1
"Unit";"Zergling";"Larva";1086;1
"Unit";"Zergling";"Larva";1086;1
"Unit";"Zergling";"Larva";1086;1
"Unit";"Zergling";"Larva";1086;1
"Unit";"Zergling";"Larva";1086;1
"Unit";"Zergling";"Larva";1086;1
"Unit";"Zergling";"Larva";1086;1
"Unit";"Zergling";"Larva";1086;1
"Unit";"Zergling";"Larva";1144;1
"Unit";"Zergling";"Larva";1144;1
"Unit";"Zergling";"Larva";1144;1
"Unit";"Zergling";"Larva";1144;1
"Unit";"Zergling";"Larva";1166;1
"Unit";"Zergling";"Larva";1166;1
"Unit";"Zergling";"Larva";1166;1
"Unit";"Zergling";"Larva";1166;1
"Unit";"Zergling";"Larva";1166;1
"Unit";"Zergling";"Larva";1166;1
"Unit";"Zergling";"Larva";1166;1
"Unit";"Zergling";"Larva";1166;1
"Unit";"Baneling";"Zergling";1170;0
"Unit";"Baneling";"Zergling";1170;0
"Unit";"Baneling";"Zergling";1170;0
"Unit";"Baneling";"Zergling";1170;0
"Unit";"Baneling";"Zergling";1170;0
"Unit";"Baneling";"Zergling";1170;0
"Unit";"Baneling";"Zergling";1170;0
"Unit";"Baneling";"Zergling";1170;0
"Unit";"Baneling";"Zergling";1170;0
"Unit";"Baneling";"Zergling";1170;0
"Unit";"Baneling";"Zergling";1170;0
"Unit";"Baneling";"Zergling";1170;0
"Unit";"Baneling";"Zergling";1170;0
"Unit";"Baneling";"Zergling";1170;0
"Unit";"Baneling";"Zergling";1170;0
"Unit";"Baneling";"Zergling";1170;0
"Unit";"Baneling";"Zergling";1170;0
"Unit";"Baneling";"Zergling";1170;0
"Unit";"Baneling";"Zergling";1170;0
"Unit";"Baneling";"Zergling";1170;0
"Unit";"Baneling";"Zergling";1170;0
"Unit";"Baneling";"Zergling";1170;0
"Unit";"Zergling";"Larva";1170;1
"Unit";"Zergling";"Larva";1170;1
"Unit";"Zergling";"Larva";1170;1
"Unit";"Zergling";"Larva";1170;1
"Unit";"Zergling";"Larva";1170;1
"Unit";"Zergling";"Larva";1170;1
"Unit";"Zergling";"Larva";1170;1
"Unit";"Zergling";"Larva";1170;1
"Unit";"Zergling";"Larva";1170;1
"Unit";"Zergling";"Larva";1170;1
"Unit";"Zergling";"Larva";1170;1
"Unit";"Zergling";"Larva";1170;1
"Unit";"Zergling";"Larva";1170;1
"Unit";"Zergling";"Larva";1170;1
"Unit";"Zergling";"Larva";1170;1
"Unit";"Zergling";"Larva";1170;1
"Unit";"Zergling";"Larva";1170;1
"Unit";"Zergling";"Larva";1170;1
"Unit";"Zergling";"Larva";1170;1
"Unit";"Zergling";"Larva";1170;1
"Unit";"Zergling";"Larva";1170;1
"Unit";"Zergling";"Larva";1170;1
"Unit";"Zergling";"Larva";1170;1
"Unit";"Zergling";"Larva";1170;1
"Unit";"Zergling";"Larva";1170;1
"Unit";"Zergling";"Larva";1170;1
"Unit";"Zergling";"Larva";1170;1
"Unit";"Zergling";"Larva";1170;1
"Unit";"Zergling";"Larva";1170;1
"Unit";"Zergling";"Larva";1170;1
"Unit";"Zergling";"Larva";1170;1
"Unit";"Zergling";"Larva";1170;1
"Unit";"Zergling";"Larva";1170;1
"Unit";"Zergling";"Larva";1170;1
"Unit";"Zergling";"Larva";1178;1
"Unit";"Zergling";"Larva";1178;1
"Unit";"Zergling";"Larva";1178;1
"Unit";"Zergling";"Larva";1178;1
"Unit";"Zergling";"Larva";1178;1
"Unit";"Zergling";"Larva";1178;1
"Building";"Extractor";NA;1178;0
"Building";"Extractor";NA;1178;0
"Unit";"Zergling";"Larva";1202;1
"Unit";"Zergling";"Larva";1202;1
"Unit";"Zergling";"Larva";1212;1
"Unit";"Zergling";"Larva";1212;1
"Unit";"Zergling";"Larva";1212;1
"Unit";"Zergling";"Larva";1212;1
"Unit";"Zergling";"Larva";1212;1
"Unit";"Zergling";"Larva";1212;1
"Unit";"Zergling";"Larva";1212;1
"Unit";"Zergling";"Larva";1212;1
"Unit";"Zergling";"Larva";1212;1
"Unit";"Zergling";"Larva";1212;1
"Unit";"Zergling";"Larva";1212;1
"Unit";"Zergling";"Larva";1212;1
"Unit";"Zergling";"Larva";1222;1
"Unit";"Zergling";"Larva";1222;1
"Unit";"Zergling";"Larva";1222;1
"Unit";"Zergling";"Larva";1222;1
"Unit";"Zergling";"Larva";1222;1
"Unit";"Zergling";"Larva";1222;1
"Unit";"Zergling";"Larva";1228;1
"Unit";"Zergling";"Larva";1228;1
"Unit";"Zergling";"Larva";1228;1
"Unit";"Zergling";"Larva";1228;1
"Unit";"Zergling";"Larva";1228;1
"Unit";"Zergling";"Larva";1228;1
"Unit";"Zergling";"Larva";1248;1
"Unit";"Zergling";"Larva";1248;1
"Unit";"Zergling";"Larva";1248;1
"Unit";"Zergling";"Larva";1248;1
"Unit";"Zergling";"Larva";1248;1
"Unit";"Zergling";"Larva";1248;1
"Unit";"Zergling";"Larva";1248;1
"Unit";"Zergling";"Larva";1248;1
"Unit";"Zergling";"Larva";1248;1
"Unit";"Zergling";"Larva";1248;1
"Unit";"Zergling";"Larva";1248;1
"Unit";"Zergling";"Larva";1248;1
"Unit";"Zergling";"Larva";1248;1
"Unit";"Zergling";"Larva";1248;1
"Unit";"Zergling";"Larva";1248;1
"Unit";"Zergling";"Larva";1248;1
"Unit";"Zergling";"Larva";1248;1
"Unit";"Zergling";"Larva";1248;1
"Unit";"Zergling";"Larva";1248;1
"Unit";"Zergling";"Larva";1248;1
"Unit";"Zergling";"Larva";1248;1
"Unit";"Zergling";"Larva";1248;1
"Unit";"Zergling";"Larva";1248;1
"Unit";"Zergling";"Larva";1248;1
"Unit";"Zergling";"Larva";1248;1
"Unit";"Zergling";"Larva";1248;1
"Unit";"Zergling";"Larva";1248;1
"Unit";"Zergling";"Larva";1248;1
"Unit";"Zergling";"Larva";1248;1
"Unit";"Zergling";"Larva";1248;1
"Unit";"Zergling";"Larva";1248;1
"Unit";"Zergling";"Larva";1248;1
"Unit";"Zergling";"Larva";1248;1
"Unit";"Zergling";"Larva";1248;1
"Unit";"Zergling";"Larva";1248;1
"Unit";"Zergling";"Larva";1248;1
"Unit";"Zergling";"Larva";1248;1
"Unit";"Zergling";"Larva";1248;1
"Unit";"Zergling";"Larva";1248;1
"Unit";"Zergling";"Larva";1248;1
"Unit";"Zergling";"Larva";1248;1
"Unit";"Zergling";"Larva";1248;1
"Unit";"Zergling";"Larva";1248;1
"Unit";"Zergling";"Larva";1248;1
"Unit";"Zergling";"Larva";1248;1
"Unit";"Zergling";"Larva";1248;1
"Unit";"Zergling";"Larva";1250;1
"Unit";"Zergling";"Larva";1250;1
"Unit";"Zergling";"Larva";1252;1
"Unit";"Zergling";"Larva";1252;1
"Unit";"Zergling";"Larva";1254;1
"Unit";"Zergling";"Larva";1254;1
"Unit";"Zergling";"Larva";1266;1
"Unit";"Zergling";"Larva";1266;1
"Unit";"Zergling";"Larva";1266;1
"Unit";"Zergling";"Larva";1266;1
"Unit";"Zergling";"Larva";1303;1
"Unit";"Zergling";"Larva";1303;1
"Unit";"Zergling";"Larva";1305;1
"Unit";"Zergling";"Larva";1305;1
"Unit";"Zergling";"Larva";1305;1
"Unit";"Zergling";"Larva";1305;1
"Unit";"Zergling";"Larva";1305;1
"Unit";"Zergling";"Larva";1305;1
"Unit";"Zergling";"Larva";1305;1
"Unit";"Zergling";"Larva";1305;1
"Unit";"Zergling";"Larva";1305;1
"Unit";"Zergling";"Larva";1305;1
"Unit";"Zergling";"Larva";1305;1
"Unit";"Zergling";"Larva";1305;1
"Unit";"Zergling";"Larva";1305;1
"Unit";"Zergling";"Larva";1305;1
"Unit";"Zergling";"Larva";1305;1
"Unit";"Zergling";"Larva";1305;1
"Unit";"Zergling";"Larva";1305;1
"Unit";"Zergling";"Larva";1305;1
"Unit";"Zergling";"Larva";1305;1
"Unit";"Zergling";"Larva";1305;1
"Unit";"Zergling";"Larva";1305;1
"Unit";"Zergling";"Larva";1305;1
"Unit";"Zergling";"Larva";1323;1
"Unit";"Zergling";"Larva";1323;1
"Building";"CreepTumor";NA;1330;0
"Building";"Hatchery";NA;1248;0
"Unit";"Zergling";"Larva";1330;1
"Unit";"Zergling";"Larva";1330;1
"Unit";"Zergling";"Larva";1330;1
"Unit";"Zergling";"Larva";1330;1
"Unit";"Zergling";"Larva";1332;1
"Unit";"Zergling";"Larva";1332;1
"Unit";"Zergling";"Larva";1334;1
"Unit";"Zergling";"Larva";1334;1
"Unit";"Zergling";"Larva";1334;1
"Unit";"Zergling";"Larva";1334;1
