"type";"unit_name";"on_building";"total_supply";"supply"
"Unit";"Overlord";"Larva";12;0
"Building";"Extractor";NA;19;0
"Unit";"Overlord";"Larva";21;0
"Building";"SpawningPool";NA;19;0
"Building";"Hatchery";NA;17;0
"Unit";"Zergling";"Larva";22;1
"Unit";"Zergling";"Larva";22;1
"Unit";"Zergling";"Larva";22;1
"Unit";"Zergling";"Larva";22;1
"Unit";"Queen";"Hatchery";22;2
"Unit";"Queen";"Hatchery";22;2
"Unit";"Overlord";"Larva";35;0
"Building";"CreepTumorQueen";NA;41;0
"Unit";"Overlord";"Larva";46;0
"Building";"CreepTumorQueen";NA;48;0
"Unit";"Overlord";"Larva";48;0
"Building";"Hatchery";NA;35;0
"Unit";"Queen";"Hatchery";43;2
"Unit";"Zergling";"Larva";48;1
"Unit";"Zergling";"Larva";48;1
"Building";"CreepTumorQueen";NA;48;0
"Building";"CreepTumor";NA;48;0
"Unit";"Zergling";"Larva";48;1
"Unit";"Zergling";"Larva";48;1
"Unit";"Zergling";"Larva";48;1
"Unit";"Zergling";"Larva";48;1
"Unit";"Zergling";"Larva";48;1
"Unit";"Zergling";"Larva";48;1
"Unit";"Zergling";"Larva";48;1
"Unit";"Zergling";"Larva";48;1
"Building";"CreepTumor";NA;56;0
"Unit";"Queen";"Hatchery";48;2
"Unit";"Overlord";"Larva";56;0
"Unit";"Overlord";"Larva";56;0
"Building";"BanelingNest";NA;48;0
"Unit";"Queen";"Hatchery";50;2
"Building";"SporeCrawler";NA;64;0
"Unit";"Queen";"Hatchery";56;2
"Unit";"Zergling";"Larva";66;1
"Unit";"Zergling";"Larva";66;1
"Unit";"Zergling";"Larva";66;1
"Unit";"Zergling";"Larva";66;1
"Unit";"Zergling";"Larva";66;1
"Unit";"Zergling";"Larva";66;1
"Unit";"Zergling";"Larva";66;1
"Unit";"Zergling";"Larva";66;1
"Unit";"Zergling";"Larva";66;1
"Unit";"Zergling";"Larva";66;1
"Unit";"Zergling";"Larva";66;1
"Unit";"Zergling";"Larva";66;1
"Building";"CreepTumor";NA;70;0
"Building";"CreepTumor";NA;70;0
"Building";"CreepTumor";NA;70;0
"Building";"Extractor";NA;70;0
"Building";"SporeCrawler";NA;70;0
"Building";"SporeCrawler";NA;70;0
"Unit";"Queen";"Hatchery";68;2
"Building";"CreepTumorQueen";NA;88;0
"Building";"CreepTumorQueen";NA;88;0
"Building";"CreepTumorQueen";NA;88;0
"Building";"CreepTumorQueen";NA;88;0
"Building";"CreepTumorQueen";NA;89;0
"Building";"EvolutionChamber";NA;86;0
"Building";"EvolutionChamber";NA;86;0
"Building";"CreepTumor";NA;89;0
"Building";"CreepTumor";NA;89;0
"Building";"CreepTumor";NA;106;0
"Building";"CreepTumor";NA;106;0
"Building";"CreepTumor";NA;106;0
"Building";"CreepTumor";NA;106;0
"Building";"CreepTumor";NA;106;0
"Unit";"Overlord";"Larva";112;0
"Unit";"Overlord";"Larva";112;0
"Building";"Extractor";NA;112;0
"Building";"Extractor";NA;112;0
"Building";"CreepTumor";NA;116;0
"Building";"CreepTumor";NA;116;0
"Building";"Extractor";NA;112;0
"Building";"Extractor";NA;112;0
"Unit";"Overlord";"Larva";116;0
"Unit";"Overlord";"Larva";116;0
"Building";"CreepTumorQueen";NA;116;0
"Building";"CreepTumorQueen";NA;116;0
"Building";"CreepTumorQueen";NA;116;0
"Building";"CreepTumor";NA;116;0
"Building";"CreepTumor";NA;116;0
"Building";"CreepTumorQueen";NA;116;0
"Building";"CreepTumor";NA;116;0
"Building";"CreepTumor";NA;116;0
"Building";"CreepTumor";NA;116;0
"Building";"CreepTumor";NA;116;0
"Building";"CreepTumorQueen";NA;128;0
"Building";"CreepTumorQueen";NA;128;0
"Building";"CreepTumor";NA;128;0
"Building";"CreepTumor";NA;128;0
"Unit";"Baneling";"Zergling";128;0
"Building";"CreepTumor";NA;128;0
"Building";"CreepTumor";NA;128;0
"Building";"CreepTumor";NA;128;0
"Building";"CreepTumor";NA;128;0
"Unit";"Baneling";"Zergling";128;0
"Building";"CreepTumor";NA;128;0
"Unit";"Baneling";"Zergling";128;0
"Unit";"Baneling";"Zergling";128;0
"Unit";"Baneling";"Zergling";128;0
"Unit";"Baneling";"Zergling";128;0
"Unit";"Baneling";"Zergling";128;0
"Unit";"Baneling";"Zergling";128;0
"Unit";"Baneling";"Zergling";128;0
"Building";"HydraliskDen";NA;128;0
"Building";"Hatchery";NA;112;0
"Unit";"Zergling";"Larva";128;1
"Unit";"Zergling";"Larva";128;1
"Building";"CreepTumor";NA;138;0
"Building";"CreepTumor";NA;138;0
"Building";"CreepTumor";NA;138;0
"Building";"RoachWarren";NA;128;0
"Upgrade";"ZergGroundArmorsLevel1";"EvolutionChamber";112;0
"Upgrade";"ZergMeleeWeaponsLevel1";"EvolutionChamber";116;0
"Unit";"Hydralisk";"Larva";138;2
"Unit";"Hydralisk";"Larva";138;2
"Unit";"Hydralisk";"Larva";138;2
"Unit";"Hydralisk";"Larva";138;2
"Unit";"Hydralisk";"Larva";138;2
"Unit";"Hydralisk";"Larva";138;2
"Unit";"Hydralisk";"Larva";138;2
"Unit";"Hydralisk";"Larva";138;2
"Unit";"Hydralisk";"Larva";140;2
"Unit";"Roach";"Larva";140;2
"Unit";"Roach";"Larva";140;2
"Unit";"Roach";"Larva";140;2
"Unit";"Roach";"Larva";140;2
"Unit";"Baneling";"Zergling";140;0
"Unit";"Baneling";"Zergling";140;0
"Unit";"Overlord";"Larva";140;0
"Unit";"Overlord";"Larva";140;0
"Unit";"Overlord";"Larva";140;0
"Unit";"Overlord";"Larva";140;0
"Unit";"Overlord";"Larva";140;0
"Unit";"Overlord";"Larva";142;0
"Building";"CreepTumorQueen";NA;166;0
"Building";"CreepTumorQueen";NA;166;0
"Building";"CreepTumor";NA;166;0
"Building";"CreepTumor";NA;166;0
"Building";"CreepTumor";NA;166;0
"Building";"CreepTumorQueen";NA;166;0
"Building";"CreepTumor";NA;166;0
"Building";"Extractor";NA;166;0
"Building";"Extractor";NA;166;0
"Building";"CreepTumor";NA;188;0
"Building";"CreepTumor";NA;188;0
"Building";"CreepTumor";NA;188;0
"Unit";"Roach";"Larva";185;2
"Unit";"Hydralisk";"Larva";185;2
"Unit";"Hydralisk";"Larva";185;2
"Unit";"Hydralisk";"Larva";185;2
"Unit";"Roach";"Larva";185;2
"Building";"CreepTumor";NA;193;0
"Building";"InfestationPit";NA;182;0
"Building";"CreepTumor";NA;193;0
"Building";"CreepTumor";NA;193;0
"Building";"CreepTumor";NA;193;0
"Unit";"Roach";"Larva";193;2
"Unit";"Roach";"Larva";193;2
"Unit";"Roach";"Larva";193;2
"Building";"SpineCrawler";NA;182;0
"Building";"SpineCrawler";NA;182;0
"Building";"CreepTumor";NA;193;0
"Building";"SpineCrawler";NA;182;0
"Building";"SpineCrawler";NA;185;0
"Unit";"Roach";"Larva";193;2
"Unit";"Roach";"Larva";193;2
"Building";"SpineCrawler";NA;185;0
"Unit";"Roach";"Larva";193;2
"Building";"SpineCrawler";NA;185;0
"Building";"SpineCrawler";NA;185;0
"Unit";"Hydralisk";"Larva";193;2
"Unit";"Hydralisk";"Larva";195;2
"Unit";"Hydralisk";"Larva";195;2
"Unit";"Roach";"Larva";203;2
"Unit";"Hydralisk";"Larva";195;2
"Unit";"Roach";"Larva";203;2
"Unit";"Hydralisk";"Larva";195;2
"Unit";"Hydralisk";"Larva";195;2
"Unit";"Roach";"Larva";203;2
"Unit";"Overlord";"Larva";209;0
"Unit";"Overlord";"Larva";209;0
"Unit";"Overlord";"Larva";209;0
"Building";"CreepTumor";NA;233;0
"Upgrade";"ZergMissileWeaponsLevel1";"EvolutionChamber";166;0
"Upgrade";"EvolveMuscularAugments";"HydraliskDen";188;0
"Building";"CreepTumorQueen";NA;233;0
"Upgrade";"GlialReconstitution";"RoachWarren";193;0
"Unit";"Hydralisk";"Larva";233;2
"Unit";"Hydralisk";"Larva";233;2
"Unit";"Hydralisk";"Larva";233;2
"Unit";"Hydralisk";"Larva";233;2
"Unit";"Hydralisk";"Larva";233;2
"Unit";"Hydralisk";"Larva";233;2
"Unit";"Hydralisk";"Larva";233;2
"Unit";"Roach";"Larva";233;2
"Unit";"Hydralisk";"Larva";233;2
"Unit";"Hydralisk";"Larva";233;2
"Unit";"Hydralisk";"Larva";233;2
"Unit";"Hydralisk";"Larva";233;2
"Unit";"Hydralisk";"Larva";233;2
"Unit";"Hydralisk";"Larva";233;2
"Unit";"Hydralisk";"Larva";233;2
"Unit";"Overlord";"Larva";233;0
"Unit";"Overlord";"Larva";233;0
"Unit";"Overlord";"Larva";233;0
"Unit";"Overlord";"Larva";233;0
"Unit";"Overlord";"Larva";233;0
"Building";"CreepTumorQueen";NA;235;0
"Building";"CreepTumor";NA;233;0
"Building";"CreepTumor";NA;233;0
"Building";"CreepTumorQueen";NA;261;0
"Upgrade";"EvolveGroovedSpines";"HydraliskDen";233;0
"Building";"CreepTumor";NA;263;0
"Building";"CreepTumor";NA;263;0
"Building";"CreepTumor";NA;263;0
"Building";"Hatchery";NA;263;0
"Building";"CreepTumor";NA;263;0
"Unit";"Roach";"Larva";263;2
"Unit";"Roach";"Larva";263;2
"Unit";"Roach";"Larva";263;2
"Unit";"Roach";"Larva";263;2
"Unit";"Roach";"Larva";263;2
"Unit";"Roach";"Larva";263;2
"Unit";"Roach";"Larva";263;2
"Unit";"Roach";"Larva";263;2
"Unit";"Roach";"Larva";263;2
"Unit";"Roach";"Larva";263;2
"Unit";"Roach";"Larva";263;2
"Unit";"Roach";"Larva";263;2
"Building";"CreepTumorQueen";NA;263;0
"Building";"CreepTumorQueen";NA;263;0
"Building";"CreepTumor";NA;263;0
"Building";"Hatchery";NA;263;0
"Upgrade";"ZergGroundArmorsLevel2";"EvolutionChamber";263;0
"Upgrade";"ZergMissileWeaponsLevel2";"EvolutionChamber";263;0
"Building";"Extractor";NA;287;0
"Building";"Extractor";NA;287;0
"Unit";"Hydralisk";"Larva";287;2
"Unit";"Hydralisk";"Larva";287;2
"Unit";"Hydralisk";"Larva";287;2
"Unit";"Hydralisk";"Larva";287;2
"Unit";"Hydralisk";"Larva";287;2
"Unit";"Hydralisk";"Larva";287;2
"Unit";"Hydralisk";"Larva";287;2
"Building";"SpineCrawler";NA;287;0
"Unit";"Hydralisk";"Larva";287;2
"Building";"SpineCrawler";NA;287;0
"Building";"SpineCrawler";NA;287;0
"Building";"SpineCrawler";NA;287;0
"Building";"SpineCrawler";NA;287;0
"Building";"SpineCrawler";NA;287;0
"Unit";"Hydralisk";"Larva";303;2
"Unit";"Hydralisk";"Larva";303;2
"Unit";"Hydralisk";"Larva";303;2
"Unit";"Hydralisk";"Larva";303;2
"Unit";"Hydralisk";"Larva";303;2
"Unit";"Hydralisk";"Larva";303;2
"Unit";"Hydralisk";"Larva";303;2
"Unit";"Hydralisk";"Larva";303;2
"Unit";"Hydralisk";"Larva";303;2
"Unit";"Hydralisk";"Larva";303;2
"Unit";"Hydralisk";"Larva";303;2
"Unit";"Hydralisk";"Larva";303;2
"Unit";"Hydralisk";"Larva";303;2
"Unit";"Hydralisk";"Larva";303;2
"Unit";"Hydralisk";"Larva";303;2
"Unit";"Hydralisk";"Larva";303;2
"Unit";"Hydralisk";"Larva";303;2
"Unit";"Roach";"Larva";303;2
"Unit";"Roach";"Larva";303;2
"Unit";"Roach";"Larva";303;2
"Unit";"Roach";"Larva";303;2
"Unit";"Roach";"Larva";303;2
"Unit";"Roach";"Larva";303;2
"Unit";"Roach";"Larva";303;2
"Unit";"Roach";"Larva";303;2
"Building";"CreepTumorQueen";NA;337;0
"Building";"CreepTumorQueen";NA;337;0
"Building";"CreepTumorQueen";NA;337;0
"Building";"CreepTumorQueen";NA;353;0
"Building";"CreepTumorQueen";NA;353;0
"Unit";"Roach";"Larva";353;2
"Unit";"Roach";"Larva";353;2
"Unit";"Roach";"Larva";353;2
"Unit";"Roach";"Larva";353;2
"Unit";"Roach";"Larva";353;2
"Unit";"Roach";"Larva";353;2
"Unit";"Roach";"Larva";353;2
"Unit";"Roach";"Larva";353;2
"Unit";"Roach";"Larva";353;2
"Unit";"Roach";"Larva";353;2
"Unit";"Roach";"Larva";353;2
"Unit";"Roach";"Larva";353;2
"Building";"CreepTumor";NA;377;0
"Building";"CreepTumor";NA;377;0
"Building";"CreepTumor";NA;377;0
"Building";"CreepTumor";NA;377;0
"Building";"CreepTumor";NA;377;0
"Unit";"Overlord";"Larva";377;0
"Unit";"Overlord";"Larva";377;0
"Unit";"Overlord";"Larva";377;0
"Unit";"Overlord";"Larva";377;0
"Unit";"Roach";"Larva";377;2
"Unit";"Roach";"Larva";377;2
"Unit";"Roach";"Larva";377;2
"Unit";"Roach";"Larva";377;2
"Unit";"Roach";"Larva";377;2
"Unit";"Roach";"Larva";377;2
"Unit";"Roach";"Larva";377;2
"Unit";"Roach";"Larva";377;2
"Unit";"Roach";"Larva";377;2
"Unit";"Roach";"Larva";377;2
"Unit";"Roach";"Larva";377;2
"Unit";"Roach";"Larva";377;2
"Unit";"Roach";"Larva";377;2
"Unit";"Roach";"Larva";377;2
"Unit";"Roach";"Larva";377;2
"Unit";"Roach";"Larva";377;2
"Unit";"Roach";"Larva";377;2
"Building";"Spire";NA;377;0
"Unit";"Hydralisk";"Larva";377;2
"Unit";"Hydralisk";"Larva";377;2
"Unit";"Hydralisk";"Larva";377;2
"Unit";"Hydralisk";"Larva";377;2
"Unit";"Hydralisk";"Larva";377;2
"Unit";"Hydralisk";"Larva";377;2
"Unit";"Hydralisk";"Larva";377;2
"Unit";"Hydralisk";"Larva";377;2
"Unit";"Hydralisk";"Larva";377;2
"Unit";"Hydralisk";"Larva";377;2
"Unit";"Roach";"Larva";377;2
"Unit";"Roach";"Larva";377;2
"Unit";"Roach";"Larva";377;2
"Unit";"Hydralisk";"Larva";440;2
"Unit";"Hydralisk";"Larva";440;2
"Unit";"Hydralisk";"Larva";440;2
"Unit";"Viper";"Larva";437;3
"Unit";"Viper";"Larva";437;3
"Unit";"Viper";"Larva";437;3
"Unit";"Viper";"Larva";437;3
"Unit";"Viper";"Larva";437;3
"Unit";"Hydralisk";"Larva";461;2
"Unit";"Hydralisk";"Larva";461;2
"Building";"CreepTumor";NA;461;0
"Building";"CreepTumor";NA;461;0
"Building";"EvolutionChamber";NA;461;0
"Building";"Hatchery";NA;440;0
"Unit";"Hydralisk";"Larva";465;2
"Unit";"Hydralisk";"Larva";465;2
"Unit";"Hydralisk";"Larva";465;2
"Unit";"Hydralisk";"Larva";465;2
"Unit";"Hydralisk";"Larva";465;2
"Unit";"Hydralisk";"Larva";465;2
"Unit";"Hydralisk";"Larva";465;2
"Unit";"Roach";"Larva";465;2
"Unit";"Roach";"Larva";465;2
"Unit";"Roach";"Larva";465;2
"Unit";"Roach";"Larva";465;2
"Unit";"Roach";"Larva";465;2
"Unit";"Hydralisk";"Larva";465;2
"Unit";"Hydralisk";"Larva";465;2
"Unit";"Hydralisk";"Larva";465;2
"Unit";"Hydralisk";"Larva";465;2
"Unit";"Hydralisk";"Larva";465;2
"Unit";"Hydralisk";"Larva";465;2
"Unit";"Hydralisk";"Larva";465;2
"Unit";"Hydralisk";"Larva";465;2
"Unit";"Hydralisk";"Larva";465;2
"Building";"Hatchery";NA;461;0
"Building";"SpineCrawler";NA;507;0
"Building";"SpineCrawler";NA;507;0
"Unit";"Roach";"Larva";508;2
"Unit";"Roach";"Larva";508;2
"Unit";"Roach";"Larva";508;2
"Unit";"Roach";"Larva";508;2
"Unit";"Roach";"Larva";508;2
"Unit";"Roach";"Larva";508;2
"Unit";"Roach";"Larva";508;2
"Unit";"Roach";"Larva";508;2
"Unit";"Roach";"Larva";508;2
"Unit";"Roach";"Larva";508;2
"Unit";"Roach";"Larva";508;2
"Unit";"Roach";"Larva";508;2
"Unit";"Roach";"Larva";508;2
"Unit";"Roach";"Larva";508;2
"Unit";"Roach";"Larva";508;2
"Unit";"Roach";"Larva";508;2
"Unit";"Roach";"Larva";508;2
"Unit";"Roach";"Larva";508;2
"Unit";"Hydralisk";"Larva";544;2
"Unit";"Hydralisk";"Larva";544;2
"Unit";"Hydralisk";"Larva";544;2
"Unit";"Hydralisk";"Larva";544;2
"Unit";"Hydralisk";"Larva";544;2
"Unit";"Hydralisk";"Larva";544;2
"Unit";"Hydralisk";"Larva";544;2
"Unit";"Hydralisk";"Larva";544;2
"Unit";"Hydralisk";"Larva";544;2
"Unit";"Hydralisk";"Larva";544;2
"Unit";"Hydralisk";"Larva";544;2
"Unit";"Hydralisk";"Larva";544;2
"Unit";"Hydralisk";"Larva";544;2
"Unit";"Hydralisk";"Larva";544;2
"Unit";"Hydralisk";"Larva";544;2
"Unit";"Hydralisk";"Larva";544;2
"Unit";"Hydralisk";"Larva";576;2
"Unit";"Hydralisk";"Larva";576;2
"Unit";"Hydralisk";"Larva";576;2
"Unit";"Hydralisk";"Larva";576;2
"Unit";"Hydralisk";"Larva";576;2
"Unit";"Hydralisk";"Larva";576;2
"Unit";"Hydralisk";"Larva";576;2
"Unit";"Hydralisk";"Larva";576;2
"Unit";"Hydralisk";"Larva";576;2
"Unit";"Hydralisk";"Larva";576;2
"Unit";"Hydralisk";"Larva";576;2
"Unit";"Hydralisk";"Larva";576;2
"Unit";"Hydralisk";"Larva";576;2
"Unit";"Hydralisk";"Larva";576;2
"Unit";"Hydralisk";"Larva";576;2
"Unit";"Hydralisk";"Larva";576;2
"Unit";"Roach";"Larva";608;2
"Unit";"Roach";"Larva";608;2
"Unit";"Roach";"Larva";608;2
"Unit";"Roach";"Larva";608;2
"Unit";"Roach";"Larva";608;2
"Unit";"Roach";"Larva";608;2
"Unit";"Roach";"Larva";608;2
"Unit";"Roach";"Larva";608;2
"Unit";"Roach";"Larva";608;2
"Unit";"Roach";"Larva";608;2
"Unit";"Roach";"Larva";608;2
"Unit";"Roach";"Larva";608;2
"Unit";"Roach";"Larva";608;2
"Unit";"Roach";"Larva";608;2
"Unit";"Roach";"Larva";608;2
"Unit";"Roach";"Larva";608;2
"Unit";"Roach";"Larva";608;2
"Unit";"Hydralisk";"Larva";608;2
"Unit";"Hydralisk";"Larva";608;2
"Unit";"Hydralisk";"Larva";608;2
"Unit";"Hydralisk";"Larva";608;2
"Unit";"Hydralisk";"Larva";608;2
"Unit";"Hydralisk";"Larva";638;2
"Unit";"Hydralisk";"Larva";638;2
"Unit";"Hydralisk";"Larva";638;2
"Unit";"Hydralisk";"Larva";638;2
"Unit";"Hydralisk";"Larva";638;2
"Unit";"Hydralisk";"Larva";638;2
"Unit";"Hydralisk";"Larva";638;2
"Unit";"Hydralisk";"Larva";638;2
"Unit";"Hydralisk";"Larva";642;2
"Unit";"Hydralisk";"Larva";642;2
"Unit";"Hydralisk";"Larva";642;2
"Unit";"Hydralisk";"Larva";642;2
"Upgrade";"ZergMissileWeaponsLevel3";"EvolutionChamber";544;0
"Upgrade";"ZergGroundArmorsLevel3";"EvolutionChamber";544;0
"Unit";"Roach";"Larva";668;2
"Unit";"Roach";"Larva";668;2
"Unit";"Roach";"Larva";668;2
"Unit";"Roach";"Larva";668;2
"Unit";"Roach";"Larva";668;2
"Unit";"Roach";"Larva";668;2
"Unit";"Roach";"Larva";668;2
"Unit";"Roach";"Larva";668;2
"Unit";"Roach";"Larva";668;2
"Unit";"Roach";"Larva";668;2
"Unit";"Roach";"Larva";696;2
"Unit";"Roach";"Larva";696;2
"Unit";"Roach";"Larva";696;2
"Unit";"Roach";"Larva";696;2
"Unit";"Roach";"Larva";696;2
"Unit";"Viper";"Larva";706;3
"Unit";"Viper";"Larva";706;3
"Unit";"Viper";"Larva";706;3
"Unit";"Hydralisk";"Larva";706;2
"Unit";"Hydralisk";"Larva";706;2
"Unit";"Hydralisk";"Larva";706;2
"Unit";"Hydralisk";"Larva";706;2
"Unit";"Hydralisk";"Larva";706;2
"Unit";"Hydralisk";"Larva";706;2
"Unit";"Hydralisk";"Larva";706;2
"Building";"SpineCrawler";NA;715;0
"Unit";"Hydralisk";"Larva";729;2
"Unit";"Hydralisk";"Larva";729;2
"Unit";"Hydralisk";"Larva";729;2
"Unit";"Hydralisk";"Larva";729;2
"Unit";"Hydralisk";"Larva";729;2
"Unit";"Hydralisk";"Larva";729;2
"Unit";"Hydralisk";"Larva";729;2
"Unit";"Hydralisk";"Larva";729;2
"Unit";"Hydralisk";"Larva";729;2
"Unit";"Hydralisk";"Larva";729;2
"Unit";"Hydralisk";"Larva";729;2
"Unit";"Hydralisk";"Larva";729;2
"Unit";"Hydralisk";"Larva";729;2
"Unit";"Hydralisk";"Larva";729;2
"Unit";"Hydralisk";"Larva";729;2
"Unit";"Hydralisk";"Larva";729;2
"Unit";"Hydralisk";"Larva";729;2
"Unit";"Hydralisk";"Larva";729;2
"Unit";"Hydralisk";"Larva";729;2
"Unit";"Roach";"Larva";767;2
"Unit";"Roach";"Larva";767;2
"Unit";"Roach";"Larva";767;2
"Unit";"Roach";"Larva";767;2
"Unit";"Roach";"Larva";767;2
"Unit";"Roach";"Larva";767;2
"Unit";"Roach";"Larva";767;2
"Unit";"Roach";"Larva";767;2
"Unit";"Roach";"Larva";767;2
"Building";"Extractor";NA;767;0
"Building";"Extractor";NA;767;0
"Building";"SpineCrawler";NA;767;0
"Building";"SpineCrawler";NA;767;0
"Building";"SpineCrawler";NA;767;0
"Unit";"Zergling";"Larva";794;1
"Unit";"Zergling";"Larva";794;1
"Unit";"Zergling";"Larva";794;1
"Unit";"Zergling";"Larva";794;1
"Unit";"Corruptor";"Larva";798;2
"Unit";"Corruptor";"Larva";798;2
"Unit";"Corruptor";"Larva";798;2
"Unit";"Corruptor";"Larva";798;2
"Unit";"Corruptor";"Larva";798;2
"Unit";"Corruptor";"Larva";798;2
"Unit";"Corruptor";"Larva";798;2
"Unit";"Corruptor";"Larva";798;2
"Unit";"Roach";"Larva";798;2
"Unit";"Roach";"Larva";798;2
"Unit";"Roach";"Larva";798;2
"Unit";"Roach";"Larva";798;2
"Unit";"Roach";"Larva";798;2
"Unit";"Roach";"Larva";798;2
"Unit";"Roach";"Larva";798;2
"Unit";"Roach";"Larva";798;2
"Unit";"Roach";"Larva";798;2
"Unit";"Roach";"Larva";798;2
"Unit";"Roach";"Larva";798;2
"Unit";"Roach";"Larva";798;2
"Unit";"Roach";"Larva";798;2
"Unit";"Roach";"Larva";798;2
"Unit";"Roach";"Larva";798;2
"Unit";"Roach";"Larva";798;2
"Unit";"Roach";"Larva";798;2
"Unit";"Roach";"Larva";798;2
"Unit";"Hydralisk";"Larva";814;2
"Unit";"Hydralisk";"Larva";814;2
"Unit";"Hydralisk";"Larva";814;2
"Unit";"Hydralisk";"Larva";814;2
"Unit";"Hydralisk";"Larva";814;2
"Unit";"Hydralisk";"Larva";814;2
"Building";"Extractor";NA;832;0
"Building";"Extractor";NA;850;0
"Unit";"Hydralisk";"Larva";850;2
"Unit";"Hydralisk";"Larva";850;2
"Unit";"Hydralisk";"Larva";850;2
"Unit";"Hydralisk";"Larva";850;2
"Unit";"Hydralisk";"Larva";850;2
"Unit";"Hydralisk";"Larva";850;2
