"type";"unit_name";"on_building";"total_supply";"supply"
"Unit";"Overlord";"Larva";12;0
"Building";"Extractor";NA;18;0
"Unit";"Overlord";"Larva";21;0
"Building";"SpawningPool";NA;19;0
"Building";"Hatchery";NA;17;0
"Unit";"Zergling";"Larva";22;1
"Unit";"Zergling";"Larva";22;1
"Unit";"Zergling";"Larva";23;1
"Unit";"Zergling";"Larva";23;1
"Unit";"Queen";"Hatchery";23;2
"Unit";"Queen";"Hatchery";23;2
"Unit";"Queen";"Hatchery";29;2
"Unit";"Overlord";"Larva";35;0
"Building";"CreepTumorQueen";NA;42;0
"Unit";"Overlord";"Larva";42;0
"Unit";"Overlord";"Larva";42;0
"Building";"CreepTumorQueen";NA;49;0
"Building";"CreepTumor";NA;49;0
"Building";"Hatchery";NA;35;0
"Building";"Extractor";NA;49;0
"Building";"Extractor";NA;49;0
"Building";"EvolutionChamber";NA;52;0
"Building";"CreepTumor";NA;56;0
"Building";"CreepTumor";NA;56;0
"Unit";"Zergling";"Larva";59;1
"Unit";"Zergling";"Larva";59;1
"Unit";"Zergling";"Larva";59;1
"Unit";"Zergling";"Larva";59;1
"Building";"RoachWarren";NA;52;0
"Unit";"Overlord";"Larva";63;0
"Unit";"Overlord";"Larva";63;0
"Building";"CreepTumor";NA;67;0
"Building";"CreepTumor";NA;71;0
"Unit";"Roach";"Larva";71;2
"Unit";"Roach";"Larva";71;2
"Unit";"Roach";"Larva";71;2
"Unit";"Roach";"Larva";71;2
"Unit";"Roach";"Larva";71;2
"Unit";"Roach";"Larva";71;2
"Unit";"Roach";"Larva";71;2
"Unit";"Overlord";"Larva";71;0
"Unit";"Overlord";"Larva";71;0
"Unit";"Overlord";"Larva";71;0
"Unit";"Roach";"Larva";71;2
"Unit";"Roach";"Larva";71;2
"Unit";"Roach";"Larva";71;2
"Unit";"Roach";"Larva";85;2
"Unit";"Roach";"Larva";85;2
"Unit";"Roach";"Larva";85;2
"Unit";"Roach";"Larva";85;2
"Unit";"Roach";"Larva";85;2
"Unit";"Roach";"Larva";85;2
"Unit";"Roach";"Larva";91;2
"Unit";"Roach";"Larva";91;2
"Unit";"Roach";"Larva";91;2
"Unit";"Roach";"Larva";91;2
"Upgrade";"GlialReconstitution";"RoachWarren";71;0
"Unit";"Roach";"Larva";103;2
"Unit";"Roach";"Larva";103;2
"Unit";"Roach";"Larva";103;2
"Unit";"Roach";"Larva";111;2
"Unit";"Roach";"Larva";111;2
"Unit";"Roach";"Larva";111;2
"Unit";"Zergling";"Larva";117;1
"Unit";"Zergling";"Larva";117;1
"Unit";"Zergling";"Larva";117;1
"Unit";"Zergling";"Larva";117;1
"Unit";"Roach";"Larva";117;2
"Unit";"Roach";"Larva";117;2
"Unit";"Roach";"Larva";117;2
"Upgrade";"ZergMissileWeaponsLevel1";"EvolutionChamber";81;0
"Unit";"Overlord";"Larva";123;0
"Unit";"Zergling";"Larva";133;1
"Unit";"Zergling";"Larva";133;1
"Unit";"Zergling";"Larva";133;1
"Unit";"Zergling";"Larva";133;1
"Unit";"Zergling";"Larva";133;1
"Unit";"Zergling";"Larva";133;1
"Unit";"Zergling";"Larva";133;1
"Unit";"Zergling";"Larva";133;1
"Unit";"Zergling";"Larva";133;1
"Unit";"Zergling";"Larva";133;1
"Unit";"Zergling";"Larva";133;1
"Unit";"Zergling";"Larva";133;1
"Unit";"Zergling";"Larva";133;1
"Unit";"Zergling";"Larva";133;1
"Unit";"Zergling";"Larva";133;1
"Unit";"Zergling";"Larva";133;1
"Unit";"Roach";"Larva";133;2
"Unit";"Roach";"Larva";133;2
"Unit";"Zergling";"Larva";133;1
"Unit";"Zergling";"Larva";133;1
"Unit";"Zergling";"Larva";133;1
"Unit";"Zergling";"Larva";133;1
"Unit";"Zergling";"Larva";133;1
"Unit";"Zergling";"Larva";133;1
"Unit";"Zergling";"Larva";133;1
"Unit";"Zergling";"Larva";133;1
"Building";"Hatchery";NA;117;0
"Unit";"Zergling";"Larva";161;1
"Unit";"Zergling";"Larva";161;1
"Unit";"Zergling";"Larva";161;1
"Unit";"Zergling";"Larva";161;1
"Unit";"Zergling";"Larva";161;1
"Unit";"Zergling";"Larva";161;1
"Unit";"Roach";"Larva";161;2
"Unit";"Roach";"Larva";161;2
"Unit";"Roach";"Larva";161;2
"Unit";"Roach";"Larva";161;2
"Unit";"Roach";"Larva";161;2
"Unit";"Roach";"Larva";161;2
"Unit";"Roach";"Larva";161;2
"Unit";"Roach";"Larva";161;2
"Unit";"Overlord";"Larva";161;0
"Unit";"Overlord";"Larva";161;0
"Unit";"Queen";"Hatchery";161;2
"Unit";"Overlord";"Larva";185;0
"Unit";"Overlord";"Larva";185;0
"Unit";"Queen";"Hatchery";185;2
"Building";"Extractor";NA;197;0
"Unit";"Roach";"Larva";197;2
"Unit";"Roach";"Larva";197;2
"Unit";"Roach";"Larva";197;2
"Unit";"Roach";"Larva";197;2
"Unit";"Roach";"Larva";197;2
"Unit";"Roach";"Larva";197;2
"Unit";"Roach";"Larva";197;2
"Unit";"Roach";"Larva";197;2
"Unit";"Overlord";"Larva";199;0
"Building";"Extractor";NA;199;0
"Building";"Extractor";NA;199;0
"Unit";"Overlord";"Larva";215;0
"Unit";"Overlord";"Larva";215;0
"Unit";"Overlord";"Larva";215;0
"Unit";"Overlord";"Larva";215;0
"Building";"HydraliskDen";NA;203;0
"Building";"CreepTumor";NA;219;0
"Building";"CreepTumor";NA;219;0
"Unit";"Hydralisk";"Larva";219;2
"Unit";"Hydralisk";"Larva";219;2
"Unit";"Hydralisk";"Larva";219;2
"Unit";"Hydralisk";"Larva";219;2
"Unit";"Hydralisk";"Larva";219;2
"Unit";"Hydralisk";"Larva";219;2
"Unit";"Hydralisk";"Larva";219;2
"Unit";"Hydralisk";"Larva";219;2
"Unit";"Hydralisk";"Larva";225;2
"Unit";"Hydralisk";"Larva";225;2
"Unit";"Hydralisk";"Larva";225;2
"Unit";"Hydralisk";"Larva";225;2
"Building";"CreepTumor";NA;241;0
"Building";"CreepTumor";NA;241;0
"Unit";"Overlord";"Larva";249;0
"Unit";"Overlord";"Larva";249;0
"Unit";"Overlord";"Larva";249;0
"Unit";"Hydralisk";"Larva";249;2
"Unit";"Hydralisk";"Larva";249;2
"Unit";"Hydralisk";"Larva";249;2
"Unit";"Hydralisk";"Larva";249;2
"Unit";"Hydralisk";"Larva";249;2
"Unit";"Hydralisk";"Larva";249;2
"Unit";"Hydralisk";"Larva";249;2
"Unit";"Hydralisk";"Larva";249;2
"Upgrade";"ZergMissileWeaponsLevel2";"EvolutionChamber";215;0
"Building";"Hatchery";NA;225;0
"Upgrade";"EvolveGroovedSpines";"HydraliskDen";249;0
"Unit";"Hydralisk";"Larva";265;2
"Unit";"Hydralisk";"Larva";265;2
"Unit";"Hydralisk";"Larva";265;2
"Unit";"Hydralisk";"Larva";265;2
"Unit";"Hydralisk";"Larva";265;2
"Unit";"Hydralisk";"Larva";265;2
"Unit";"Overlord";"Larva";265;0
"Unit";"Hydralisk";"Larva";265;2
"Unit";"Hydralisk";"Larva";265;2
"Unit";"Overlord";"Larva";265;0
"Unit";"Overlord";"Larva";265;0
