"type";"unit_name";"on_building";"total_supply";"supply"
"Unit";"Overlord";"Larva";13;0
"Building";"Extractor";NA;17;0
"Building";"Hatchery";NA;16;0
"Building";"SpawningPool";NA;19;0
"Unit";"Overlord";"Larva";22;0
"Unit";"Zergling";"Larva";23;1
"Unit";"Zergling";"Larva";23;1
"Unit";"Zergling";"Larva";23;1
"Unit";"Zergling";"Larva";23;1
"Unit";"Queen";"Hatchery";23;2
"Unit";"Queen";"Hatchery";23;2
"Building";"CreepTumorQueen";NA;33;0
"Unit";"Overlord";"Larva";33;0
"Unit";"Queen";"Hatchery";33;2
"Building";"CreepTumor";NA;37;0
"Building";"CreepTumorQueen";NA;39;0
"Unit";"Overlord";"Larva";43;0
"Building";"CreepTumor";NA;47;0
"Building";"Hatchery";NA;29;0
"Unit";"Zergling";"Larva";47;1
"Unit";"Zergling";"Larva";47;1
"Unit";"Queen";"Hatchery";42;2
"Unit";"Overlord";"Larva";49;0
"Unit";"Zergling";"Larva";49;1
"Unit";"Zergling";"Larva";49;1
"Unit";"Zergling";"Larva";49;1
"Unit";"Zergling";"Larva";49;1
"Unit";"Zergling";"Larva";49;1
"Unit";"Zergling";"Larva";49;1
"Building";"CreepTumor";NA;57;0
"Building";"CreepTumorQueen";NA;59;0
"Building";"CreepTumor";NA;59;0
"Building";"Extractor";NA;54;0
"Building";"CreepTumorQueen";NA;68;0
"Unit";"Overlord";"Larva";65;0
"Unit";"Overlord";"Larva";68;0
"Building";"SporeCrawler";NA;68;0
"Building";"CreepTumor";NA;69;0
"Building";"CreepTumor";NA;70;0
"Unit";"Overlord";"Larva";68;0
"Building";"CreepTumor";NA;70;0
"Unit";"Queen";"Hatchery";59;2
"Building";"SporeCrawler";NA;68;0
"Unit";"Overlord";"Larva";70;0
"Unit";"Overlord";"Larva";71;0
"Unit";"Overlord";"Larva";74;0
"Unit";"Zergling";"Larva";75;1
"Unit";"Zergling";"Larva";75;1
"Unit";"Zergling";"Larva";75;1
"Unit";"Zergling";"Larva";75;1
"Building";"BanelingNest";NA;69;0
"Unit";"Zergling";"Larva";81;1
"Unit";"Zergling";"Larva";81;1
"Unit";"Zergling";"Larva";81;1
"Unit";"Zergling";"Larva";81;1
"Unit";"Zergling";"Larva";81;1
"Unit";"Zergling";"Larva";81;1
"Unit";"Zergling";"Larva";81;1
"Unit";"Zergling";"Larva";81;1
"Unit";"Zergling";"Larva";85;1
"Unit";"Zergling";"Larva";85;1
"Unit";"Zergling";"Larva";85;1
"Unit";"Zergling";"Larva";85;1
"Building";"CreepTumor";NA;96;0
"Unit";"Overlord";"Larva";94;0
"Building";"CreepTumor";NA;98;0
"Building";"CreepTumor";NA;98;0
"Building";"CreepTumor";NA;108;0
"Building";"CreepTumor";NA;108;0
"Building";"CreepTumor";NA;108;0
"Building";"Extractor";NA;108;0
"Building";"EvolutionChamber";NA;108;0
"Building";"CreepTumorQueen";NA;119;0
"Building";"CreepTumorQueen";NA;121;0
"Building";"RoachWarren";NA;108;0
"Building";"Extractor";NA;121;0
"Building";"Extractor";NA;122;0
"Unit";"Overlord";"Larva";127;0
"Unit";"Overlord";"Larva";127;0
"Unit";"Roach";"Larva";127;2
"Unit";"Roach";"Larva";127;2
"Unit";"Roach";"Larva";127;2
"Unit";"Roach";"Larva";127;2
"Unit";"Roach";"Larva";127;2
"Unit";"Roach";"Larva";127;2
"Building";"CreepTumor";NA;127;0
"Building";"CreepTumor";NA;128;0
"Building";"CreepTumor";NA;128;0
"Building";"CreepTumor";NA;128;0
"Building";"CreepTumor";NA;128;0
"Building";"CreepTumorQueen";NA;144;0
"Building";"CreepTumorQueen";NA;144;0
"Building";"InfestationPit";NA;127;0
"Building";"CreepTumor";NA;144;0
"Building";"CreepTumor";NA;144;0
"Unit";"Roach";"Larva";144;2
"Building";"CreepTumor";NA;144;0
"Unit";"Roach";"Larva";144;2
"Unit";"Roach";"Larva";144;2
"Unit";"Roach";"Larva";144;2
"Unit";"Roach";"Larva";144;2
"Unit";"Roach";"Larva";144;2
"Unit";"Roach";"Larva";144;2
"Unit";"Roach";"Larva";144;2
"Unit";"Roach";"Larva";144;2
"Unit";"Roach";"Larva";144;2
"Unit";"Roach";"Larva";144;2
"Unit";"Roach";"Larva";144;2
"Building";"CreepTumor";NA;144;0
"Unit";"Roach";"Larva";144;2
"Building";"CreepTumor";NA;144;0
"Unit";"Roach";"Larva";144;2
"Unit";"Roach";"Larva";144;2
"Building";"CreepTumor";NA;170;0
"Building";"CreepTumor";NA;170;0
"Building";"CreepTumor";NA;174;0
"Unit";"Overlord";"Larva";170;0
"Building";"Extractor";NA;170;0
"Building";"CreepTumor";NA;177;0
"Upgrade";"GlialReconstitution";"RoachWarren";144;0
"Building";"Hatchery";NA;142;0
"Unit";"Overlord";"Larva";177;0
"Unit";"Overlord";"Larva";177;0
"Unit";"Overlord";"Larva";177;0
"Unit";"Overlord";"Larva";177;0
"Unit";"Overlord";"Larva";177;0
"Unit";"Overlord";"Larva";177;0
"Upgrade";"ZergMissileWeaponsLevel1";"EvolutionChamber";136;0
"Building";"CreepTumor";NA;177;0
"Building";"CreepTumor";NA;177;0
"Building";"CreepTumor";NA;177;0
"Building";"CreepTumor";NA;177;0
"Building";"CreepTumor";NA;177;0
"Unit";"Roach";"Larva";177;2
"Unit";"Overlord";"Larva";177;0
"Unit";"Overlord";"Larva";177;0
"Unit";"Roach";"Larva";177;2
"Unit";"Roach";"Larva";177;2
"Unit";"Roach";"Larva";177;2
"Unit";"Roach";"Larva";177;2
"Unit";"Roach";"Larva";177;2
"Unit";"Roach";"Larva";177;2
"Unit";"Roach";"Larva";177;2
"Unit";"Roach";"Larva";177;2
"Unit";"Roach";"Larva";177;2
"Building";"CreepTumor";NA;193;0
"Building";"CreepTumor";NA;194;0
"Building";"CreepTumor";NA;194;0
"Building";"CreepTumorQueen";NA;206;0
"Building";"CreepTumorQueen";NA;206;0
"Unit";"Overlord";"Larva";208;0
"Unit";"Roach";"Larva";213;2
"Unit";"Roach";"Larva";213;2
"Unit";"Roach";"Larva";213;2
"Unit";"Roach";"Larva";213;2
"Unit";"Roach";"Larva";213;2
"Unit";"Roach";"Larva";213;2
"Unit";"Roach";"Larva";213;2
"Unit";"Roach";"Larva";213;2
"Unit";"Roach";"Larva";213;2
"Unit";"Roach";"Larva";213;2
"Unit";"Roach";"Larva";213;2
"Unit";"Roach";"Larva";213;2
"Unit";"Roach";"Larva";213;2
"Unit";"Roach";"Larva";213;2
"Unit";"Roach";"Larva";213;2
"Unit";"Roach";"Larva";213;2
"Unit";"Roach";"Larva";227;2
"Unit";"Roach";"Larva";245;2
"Unit";"Roach";"Larva";245;2
"Unit";"Roach";"Larva";245;2
"Unit";"Roach";"Larva";245;2
"Unit";"Roach";"Larva";245;2
"Unit";"Roach";"Larva";245;2
"Building";"CreepTumor";NA;247;0
"Building";"Extractor";NA;245;0
"Building";"Extractor";NA;245;0
