"type";"unit_name";"on_building";"total_supply";"supply"
"Unit";"Overlord";"Larva";12;0
"Building";"Extractor";NA;18;0
"Unit";"Overlord";"Larva";21;0
"Building";"SpawningPool";NA;19;0
"Building";"Hatchery";NA;17;0
"Unit";"Zergling";"Larva";22;1
"Unit";"Zergling";"Larva";22;1
"Unit";"Zergling";"Larva";22;1
"Unit";"Zergling";"Larva";22;1
"Unit";"Queen";"Hatchery";22;2
"Unit";"Queen";"Hatchery";22;2
"Unit";"Overlord";"Larva";32;0
"Unit";"Queen";"Hatchery";32;2
"Unit";"Queen";"Hatchery";32;2
"Building";"CreepTumorQueen";NA;39;0
"Building";"Hatchery";NA;28;0
"Building";"CreepTumorQueen";NA;44;0
"Unit";"Overlord";"Larva";44;0
"Unit";"Overlord";"Larva";44;0
"Unit";"Queen";"Hatchery";42;2
"Unit";"Queen";"Hatchery";44;2
"Building";"CreepTumorQueen";NA;44;0
"Building";"CreepTumorQueen";NA;45;0
"Building";"CreepTumor";NA;44;0
"Building";"CreepTumor";NA;47;0
"Building";"SporeCrawler";NA;51;0
"Building";"SporeCrawler";NA;59;0
"Building";"Extractor";NA;59;0
"Unit";"Overlord";"Larva";61;0
"Building";"SporeCrawler";NA;65;0
"Unit";"Queen";"Hatchery";60;2
"Unit";"Zergling";"Larva";65;1
"Unit";"Zergling";"Larva";65;1
"Unit";"Zergling";"Larva";65;1
"Unit";"Zergling";"Larva";65;1
"Unit";"Overlord";"Larva";65;0
"Unit";"Overlord";"Larva";79;0
"Building";"CreepTumor";NA;79;0
"Building";"CreepTumor";NA;79;0
"Building";"CreepTumor";NA;79;0
"Building";"CreepTumor";NA;79;0
"Unit";"Overlord";"Larva";79;0
"Building";"EvolutionChamber";NA;79;0
"Building";"EvolutionChamber";NA;79;0
"Unit";"Zergling";"Larva";82;1
"Unit";"Zergling";"Larva";82;1
"Unit";"Zergling";"Larva";82;1
"Unit";"Zergling";"Larva";82;1
"Building";"BanelingNest";NA;79;0
"Unit";"Queen";"Hatchery";82;2
"Building";"CreepTumorQueen";NA;90;0
"Building";"CreepTumorQueen";NA;90;0
"Unit";"Queen";"Hatchery";86;2
"Building";"CreepTumor";NA;90;0
"Building";"CreepTumor";NA;90;0
"Building";"Extractor";NA;90;0
"Unit";"Baneling";"Zergling";90;0
"Unit";"Baneling";"Zergling";90;0
"Unit";"Baneling";"Zergling";90;0
"Unit";"Baneling";"Zergling";90;0
"Unit";"Baneling";"Zergling";90;0
"Unit";"Baneling";"Zergling";90;0
"Unit";"Baneling";"Zergling";90;0
"Unit";"Baneling";"Zergling";90;0
"Unit";"Baneling";"Zergling";90;0
"Unit";"Zergling";"Larva";90;1
"Unit";"Zergling";"Larva";90;1
"Unit";"Zergling";"Larva";90;1
"Unit";"Zergling";"Larva";90;1
"Unit";"Zergling";"Larva";90;1
"Unit";"Zergling";"Larva";90;1
"Unit";"Zergling";"Larva";90;1
"Unit";"Zergling";"Larva";90;1
"Unit";"Zergling";"Larva";90;1
"Unit";"Zergling";"Larva";90;1
"Unit";"Zergling";"Larva";90;1
"Unit";"Zergling";"Larva";90;1
"Unit";"Zergling";"Larva";90;1
"Unit";"Zergling";"Larva";90;1
"Building";"RoachWarren";NA;90;0
"Unit";"Overlord";"Larva";115;0
"Unit";"Overlord";"Larva";115;0
"Unit";"Overlord";"Larva";115;0
"Unit";"Overlord";"Larva";123;0
"Building";"Extractor";NA;121;0
"Unit";"Queen";"Hatchery";123;2
"Unit";"Queen";"Hatchery";123;2
"Building";"Spire";NA;115;0
"Unit";"Zergling";"Larva";127;1
"Unit";"Zergling";"Larva";127;1
"Unit";"Zergling";"Larva";127;1
"Unit";"Zergling";"Larva";127;1
"Building";"Extractor";NA;127;0
"Building";"Extractor";NA;127;0
"Building";"CreepTumor";NA;134;0
"Building";"CreepTumor";NA;134;0
"Building";"CreepTumor";NA;134;0
"Building";"CreepTumor";NA;134;0
"Unit";"Queen";"Hatchery";127;2
"Building";"CreepTumor";NA;149;0
"Unit";"Queen";"Hatchery";134;2
"Building";"CreepTumor";NA;149;0
"Unit";"Queen";"Hatchery";134;2
"Upgrade";"ZergMeleeWeaponsLevel1";"EvolutionChamber";123;0
"Unit";"Overlord";"Larva";149;0
"Unit";"Overlord";"Larva";149;0
"Unit";"Overlord";"Larva";149;0
"Unit";"Overlord";"Larva";149;0
"Building";"SpineCrawler";NA;141;0
"Unit";"Overlord";"Larva";153;0
"Unit";"Overlord";"Larva";153;0
"Unit";"Overlord";"Larva";153;0
"Unit";"Overlord";"Larva";153;0
"Upgrade";"ZergGroundArmorsLevel1";"EvolutionChamber";127;0
"Building";"Hatchery";NA;128;0
"Unit";"Roach";"Larva";153;2
"Unit";"Roach";"Larva";153;2
"Unit";"Roach";"Larva";153;2
"Unit";"Roach";"Larva";153;2
"Unit";"Roach";"Larva";153;2
"Unit";"Roach";"Larva";153;2
"Unit";"Roach";"Larva";153;2
"Building";"Hatchery";NA;140;0
"Building";"CreepTumor";NA;153;0
"Building";"CreepTumor";NA;153;0
"Unit";"Roach";"Larva";153;2
"Unit";"Roach";"Larva";153;2
"Building";"CreepTumor";NA;153;0
"Unit";"Overlord";"Larva";153;0
"Building";"HydraliskDen";NA;153;0
"Unit";"Roach";"Larva";167;2
"Unit";"Roach";"Larva";167;2
"Unit";"Roach";"Larva";167;2
"Unit";"Roach";"Larva";167;2
"Unit";"Roach";"Larva";167;2
"Unit";"Roach";"Larva";167;2
"Unit";"Roach";"Larva";167;2
"Unit";"Roach";"Larva";167;2
"Unit";"Roach";"Larva";167;2
"Unit";"Mutalisk";"Larva";167;2
"Unit";"Roach";"Larva";171;2
"Unit";"Roach";"Larva";171;2
"Unit";"Roach";"Larva";171;2
"Building";"CreepTumor";NA;189;0
"Building";"CreepTumor";NA;189;0
"Unit";"Hydralisk";"Larva";171;2
"Unit";"Hydralisk";"Larva";171;2
"Unit";"Hydralisk";"Larva";171;2
"Unit";"Hydralisk";"Larva";171;2
"Unit";"Hydralisk";"Larva";171;2
"Unit";"Hydralisk";"Larva";171;2
"Unit";"Hydralisk";"Larva";171;2
"Unit";"Hydralisk";"Larva";189;2
"Unit";"Hydralisk";"Larva";189;2
"Unit";"Hydralisk";"Larva";189;2
"Building";"InfestationPit";NA;171;0
"Building";"SpineCrawler";NA;191;0
"Building";"CreepTumor";NA;219;0
"Building";"CreepTumor";NA;219;0
"Building";"Extractor";NA;219;0
"Upgrade";"EvolveGroovedSpines";"HydraliskDen";197;0
"Unit";"Overlord";"Larva";230;0
"Unit";"Overlord";"Larva";230;0
"Unit";"Overlord";"Larva";230;0
"Unit";"Overlord";"Larva";230;0
"Unit";"Overlord";"Larva";230;0
"Unit";"Overlord";"Larva";230;0
"Upgrade";"GlialReconstitution";"RoachWarren";197;0
"Upgrade";"ZergMissileWeaponsLevel1";"EvolutionChamber";171;0
"Building";"CreepTumor";NA;231;0
"Building";"CreepTumor";NA;231;0
"Building";"Extractor";NA;230;0
"Unit";"Hydralisk";"Larva";231;2
"Unit";"Hydralisk";"Larva";231;2
"Upgrade";"EvolveMuscularAugments";"HydraliskDen";231;0
"Unit";"Hydralisk";"Larva";235;2
"Unit";"Hydralisk";"Larva";235;2
"Unit";"Hydralisk";"Larva";235;2
"Unit";"Hydralisk";"Larva";235;2
"Unit";"Hydralisk";"Larva";235;2
"Unit";"Hydralisk";"Larva";235;2
"Unit";"Hydralisk";"Larva";235;2
"Unit";"Hydralisk";"Larva";235;2
"Unit";"Hydralisk";"Larva";235;2
"Unit";"Hydralisk";"Larva";235;2
"Unit";"Hydralisk";"Larva";235;2
"Unit";"Hydralisk";"Larva";235;2
"Unit";"Hydralisk";"Larva";235;2
"Unit";"Roach";"Larva";235;2
"Unit";"Roach";"Larva";235;2
"Unit";"Roach";"Larva";235;2
"Unit";"Roach";"Larva";235;2
"Unit";"Roach";"Larva";235;2
"Unit";"Roach";"Larva";235;2
"Unit";"Roach";"Larva";235;2
"Unit";"Roach";"Larva";235;2
"Unit";"Roach";"Larva";235;2
"Unit";"Roach";"Larva";235;2
"Unit";"Roach";"Larva";235;2
"Unit";"Roach";"Larva";235;2
"Unit";"Roach";"Larva";235;2
"Unit";"Roach";"Larva";235;2
"Unit";"Roach";"Larva";294;2
"Building";"CreepTumor";NA;294;0
"Unit";"Roach";"Larva";294;2
"Unit";"Roach";"Larva";294;2
"Unit";"Roach";"Larva";294;2
"Unit";"Roach";"Larva";294;2
"Unit";"Roach";"Larva";294;2
"Unit";"Roach";"Larva";294;2
"Unit";"Roach";"Larva";294;2
"Unit";"Roach";"Larva";294;2
"Building";"CreepTumor";NA;312;0
"Unit";"Corruptor";"Larva";312;2
"Unit";"Corruptor";"Larva";312;2
"Unit";"Corruptor";"Larva";312;2
"Unit";"Corruptor";"Larva";312;2
"Building";"Hatchery";NA;289;0
"Unit";"Roach";"Larva";312;2
"Unit";"Roach";"Larva";312;2
"Unit";"Roach";"Larva";312;2
"Unit";"Roach";"Larva";312;2
"Unit";"Roach";"Larva";312;2
"Unit";"Hydralisk";"Larva";312;2
"Unit";"Hydralisk";"Larva";312;2
"Unit";"Hydralisk";"Larva";312;2
"Unit";"Hydralisk";"Larva";312;2
"Unit";"Hydralisk";"Larva";312;2
"Unit";"Roach";"Larva";340;2
"Unit";"Roach";"Larva";340;2
"Unit";"Roach";"Larva";340;2
"Unit";"Roach";"Larva";340;2
"Unit";"Roach";"Larva";340;2
"Unit";"Roach";"Larva";340;2
"Unit";"Roach";"Larva";340;2
"Unit";"Roach";"Larva";340;2
"Unit";"Roach";"Larva";340;2
"Unit";"Roach";"Larva";340;2
"Building";"Hatchery";NA;312;0
"Unit";"Hydralisk";"Larva";351;2
"Unit";"Hydralisk";"Larva";365;2
"Unit";"Hydralisk";"Larva";369;2
"Unit";"Hydralisk";"Larva";369;2
"Unit";"Hydralisk";"Larva";369;2
"Unit";"Hydralisk";"Larva";369;2
"Unit";"Hydralisk";"Larva";369;2
"Unit";"Hydralisk";"Larva";369;2
"Upgrade";"ZergMissileWeaponsLevel2";"EvolutionChamber";312;0
"Upgrade";"ZergGroundArmorsLevel2";"EvolutionChamber";312;0
"Unit";"Corruptor";"Larva";375;2
"Unit";"Hydralisk";"Larva";385;2
"Unit";"Hydralisk";"Larva";385;2
"Unit";"Hydralisk";"Larva";385;2
"Unit";"Hydralisk";"Larva";385;2
"Unit";"Hydralisk";"Larva";385;2
"Unit";"Hydralisk";"Larva";385;2
"Unit";"Hydralisk";"Larva";385;2
"Unit";"Corruptor";"Larva";387;2
"Unit";"Corruptor";"Larva";387;2
"Unit";"Corruptor";"Larva";387;2
