"type";"unit_name";"on_building";"total_supply";"supply"
"Unit";"Overlord";"Larva";14;0
"Building";"Extractor";NA;18;0
"Building";"SpawningPool";NA;19;0
"Building";"Hatchery";NA;18;0
"Unit";"Overlord";"Larva";24;0
"Unit";"Zergling";"Larva";24;1
"Unit";"Zergling";"Larva";24;1
"Unit";"Zergling";"Larva";24;1
"Unit";"Zergling";"Larva";24;1
"Unit";"Queen";"Hatchery";24;2
"Unit";"Queen";"Hatchery";24;2
"Unit";"Overlord";"Larva";37;0
"Unit";"Queen";"Hatchery";36;2
"Unit";"Queen";"Hatchery";37;2
"Unit";"Overlord";"Larva";38;0
"Building";"CreepTumorQueen";NA;41;0
"Building";"CreepTumorQueen";NA;43;0
"Building";"Hatchery";NA;34;0
"Building";"Extractor";NA;49;0
"Building";"Extractor";NA;51;0
"Unit";"Queen";"Hatchery";44;2
"Building";"CreepTumorQueen";NA;55;0
"Building";"CreepTumorQueen";NA;55;0
"Building";"CreepTumor";NA;55;0
"Building";"CreepTumor";NA;55;0
"Unit";"Queen";"Hatchery";54;2
"Unit";"Overlord";"Larva";59;0
"Unit";"Overlord";"Larva";59;0
"Building";"CreepTumor";NA;65;0
"Building";"RoachWarren";NA;55;0
"Unit";"Overlord";"Larva";65;0
"Unit";"Overlord";"Larva";65;0
"Unit";"Overlord";"Larva";65;0
"Unit";"Overlord";"Larva";65;0
"Unit";"Roach";"Larva";65;2
"Unit";"Roach";"Larva";65;2
"Unit";"Roach";"Larva";65;2
"Unit";"Roach";"Larva";65;2
"Building";"EvolutionChamber";NA;65;0
"Building";"EvolutionChamber";NA;65;0
"Building";"CreepTumor";NA;65;0
"Building";"CreepTumor";NA;65;0
"Unit";"Roach";"Larva";65;2
"Unit";"Roach";"Larva";65;2
"Building";"SpineCrawler";NA;65;0
"Unit";"Roach";"Larva";66;2
"Unit";"Roach";"Larva";72;2
"Building";"SporeCrawler";NA;74;0
"Unit";"Queen";"Hatchery";65;2
"Building";"SporeCrawler";NA;74;0
"Unit";"Roach";"Larva";82;2
"Unit";"Roach";"Larva";82;2
"Unit";"Roach";"Larva";82;2
"Unit";"Roach";"Larva";84;2
"Unit";"Roach";"Larva";84;2
"Unit";"Roach";"Larva";84;2
"Unit";"Roach";"Larva";84;2
"Unit";"Roach";"Larva";84;2
"Unit";"Roach";"Larva";84;2
"Building";"CreepTumor";NA;104;0
"Building";"CreepTumor";NA;105;0
"Building";"CreepTumorQueen";NA;109;0
"Building";"CreepTumorQueen";NA;109;0
"Building";"CreepTumorQueen";NA;109;0
"Building";"CreepTumorQueen";NA;115;0
"Building";"CreepTumorQueen";NA;117;0
"Building";"CreepTumorQueen";NA;118;0
"Building";"CreepTumor";NA;118;0
"Building";"CreepTumorQueen";NA;121;0
"Building";"CreepTumor";NA;118;0
"Building";"CreepTumor";NA;118;0
"Building";"CreepTumor";NA;121;0
"Building";"Extractor";NA;118;0
"Unit";"Overlord";"Larva";121;0
"Unit";"Roach";"Larva";122;2
"Unit";"Roach";"Larva";122;2
"Unit";"Roach";"Larva";122;2
"Unit";"Roach";"Larva";122;2
"Unit";"Roach";"Larva";122;2
"Building";"CreepTumor";NA;122;0
"Building";"CreepTumor";NA;122;0
"Building";"CreepTumor";NA;122;0
"Building";"CreepTumor";NA;122;0
"Building";"CreepTumor";NA;122;0
"Building";"CreepTumor";NA;122;0
"Unit";"Roach";"Larva";122;2
"Unit";"Roach";"Larva";122;2
"Unit";"Roach";"Larva";122;2
"Unit";"Roach";"Larva";122;2
"Unit";"Roach";"Larva";140;2
"Unit";"Roach";"Larva";140;2
"Unit";"Roach";"Larva";140;2
"Unit";"Roach";"Larva";140;2
"Unit";"Roach";"Larva";140;2
"Unit";"Roach";"Larva";140;2
"Unit";"Roach";"Larva";140;2
"Building";"CreepTumor";NA;146;0
"Building";"CreepTumor";NA;146;0
"Building";"CreepTumor";NA;146;0
"Unit";"Roach";"Larva";146;2
"Building";"CreepTumor";NA;150;0
"Building";"Extractor";NA;146;0
"Building";"CreepTumor";NA;150;0
"Building";"CreepTumor";NA;150;0
"Building";"CreepTumor";NA;150;0
"Building";"CreepTumor";NA;150;0
"Unit";"Roach";"Larva";150;2
"Unit";"Roach";"Larva";152;2
"Unit";"Roach";"Larva";154;2
"Building";"Extractor";NA;162;0
"Building";"CreepTumor";NA;168;0
"Building";"CreepTumor";NA;168;0
"Unit";"Roach";"Larva";168;2
"Unit";"Roach";"Larva";168;2
"Unit";"Roach";"Larva";168;2
"Unit";"Roach";"Larva";168;2
"Unit";"Roach";"Larva";168;2
"Unit";"Roach";"Larva";168;2
"Unit";"Overlord";"Larva";168;0
"Unit";"Overlord";"Larva";168;0
"Unit";"Overlord";"Larva";168;0
"Building";"CreepTumorQueen";NA;168;0
"Unit";"Overlord";"Larva";168;0
"Building";"CreepTumorQueen";NA;168;0
"Unit";"Roach";"Larva";180;2
"Unit";"Roach";"Larva";180;2
"Unit";"Roach";"Larva";180;2
"Unit";"Roach";"Larva";180;2
"Building";"Hatchery";NA;168;0
"Unit";"Roach";"Larva";191;2
"Unit";"Roach";"Larva";191;2
"Unit";"Roach";"Larva";191;2
"Unit";"Roach";"Larva";191;2
"Unit";"Roach";"Larva";191;2
"Unit";"Roach";"Larva";191;2
"Unit";"Roach";"Larva";191;2
"Unit";"Roach";"Larva";191;2
"Building";"CreepTumor";NA;192;0
"Building";"CreepTumor";NA;193;0
"Building";"CreepTumor";NA;194;0
"Upgrade";"ZergMissileWeaponsLevel1";"EvolutionChamber";168;0
"Upgrade";"ZergGroundArmorsLevel1";"EvolutionChamber";168;0
"Unit";"Roach";"Larva";199;2
"Unit";"Roach";"Larva";199;2
"Unit";"Roach";"Larva";203;2
"Unit";"Overlord";"Larva";213;0
"Unit";"Overlord";"Larva";213;0
"Unit";"Overlord";"Larva";213;0
"Unit";"Overlord";"Larva";213;0
"Unit";"Overlord";"Larva";213;0
"Building";"CreepTumorQueen";NA;219;0
"Building";"CreepTumorQueen";NA;219;0
"Unit";"Overlord";"Larva";219;0
"Unit";"Overlord";"Larva";219;0
"Building";"CreepTumorQueen";NA;226;0
"Unit";"Zergling";"Larva";219;1
"Unit";"Zergling";"Larva";219;1
"Unit";"Zergling";"Larva";219;1
"Unit";"Zergling";"Larva";219;1
"Unit";"Zergling";"Larva";220;1
"Unit";"Zergling";"Larva";220;1
"Unit";"Roach";"Larva";219;2
"Unit";"Roach";"Larva";219;2
"Unit";"Roach";"Larva";219;2
"Unit";"Roach";"Larva";219;2
"Unit";"Roach";"Larva";219;2
"Unit";"Roach";"Larva";219;2
"Unit";"Roach";"Larva";219;2
"Unit";"Zergling";"Larva";226;1
"Unit";"Zergling";"Larva";226;1
"Building";"Hatchery";NA;203;0
"Building";"CreepTumor";NA;226;0
"Building";"CreepTumor";NA;226;0
"Building";"CreepTumor";NA;226;0
"Unit";"Zergling";"Larva";226;1
"Unit";"Zergling";"Larva";226;1
"Unit";"Zergling";"Larva";226;1
"Unit";"Zergling";"Larva";226;1
"Unit";"Zergling";"Larva";226;1
"Unit";"Zergling";"Larva";226;1
"Unit";"Zergling";"Larva";226;1
"Unit";"Zergling";"Larva";226;1
"Unit";"Zergling";"Larva";226;1
"Unit";"Zergling";"Larva";226;1
"Building";"CreepTumor";NA;226;0
"Building";"CreepTumorQueen";NA;232;0
"Building";"CreepTumorQueen";NA;246;0
"Building";"CreepTumor";NA;246;0
"Building";"CreepTumor";NA;246;0
"Building";"CreepTumorQueen";NA;248;0
"Unit";"Zergling";"Larva";248;1
"Unit";"Zergling";"Larva";248;1
"Unit";"Zergling";"Larva";252;1
"Unit";"Zergling";"Larva";252;1
"Unit";"Zergling";"Larva";256;1
"Unit";"Zergling";"Larva";256;1
"Unit";"Zergling";"Larva";258;1
"Unit";"Zergling";"Larva";258;1
"Unit";"Zergling";"Larva";258;1
"Unit";"Zergling";"Larva";258;1
"Unit";"Zergling";"Larva";258;1
"Unit";"Zergling";"Larva";258;1
"Unit";"Zergling";"Larva";258;1
"Unit";"Zergling";"Larva";258;1
"Unit";"Roach";"Larva";248;2
"Unit";"Roach";"Larva";248;2
"Unit";"Roach";"Larva";248;2
"Unit";"Roach";"Larva";248;2
"Unit";"Zergling";"Larva";280;1
"Unit";"Zergling";"Larva";280;1
"Unit";"Zergling";"Larva";280;1
"Unit";"Zergling";"Larva";280;1
"Unit";"Zergling";"Larva";280;1
"Unit";"Zergling";"Larva";280;1
"Unit";"Zergling";"Larva";280;1
"Unit";"Zergling";"Larva";280;1
"Unit";"Zergling";"Larva";280;1
"Unit";"Zergling";"Larva";280;1
"Unit";"Zergling";"Larva";280;1
"Unit";"Zergling";"Larva";280;1
"Unit";"Zergling";"Larva";280;1
"Unit";"Zergling";"Larva";280;1
"Unit";"Zergling";"Larva";280;1
"Unit";"Zergling";"Larva";280;1
"Unit";"Zergling";"Larva";280;1
"Unit";"Zergling";"Larva";280;1
"Unit";"Zergling";"Larva";280;1
"Unit";"Zergling";"Larva";280;1
"Unit";"Zergling";"Larva";280;1
"Unit";"Zergling";"Larva";280;1
"Unit";"Zergling";"Larva";280;1
"Unit";"Zergling";"Larva";280;1
"Unit";"Zergling";"Larva";280;1
"Unit";"Zergling";"Larva";280;1
"Unit";"Zergling";"Larva";280;1
"Unit";"Zergling";"Larva";280;1
"Unit";"Zergling";"Larva";280;1
"Unit";"Zergling";"Larva";280;1
"Unit";"Zergling";"Larva";280;1
"Unit";"Zergling";"Larva";280;1
"Unit";"Roach";"Larva";280;2
"Building";"CreepTumorQueen";NA;315;0
"Building";"CreepTumorQueen";NA;315;0
"Building";"SporeCrawler";NA;315;0
"Building";"CreepTumor";NA;317;0
"Building";"CreepTumor";NA;317;0
"Building";"CreepTumor";NA;317;0
"Building";"CreepTumor";NA;319;0
"Building";"Extractor";NA;317;0
"Unit";"Overlord";"Larva";326;0
"Unit";"Overlord";"Larva";326;0
"Unit";"Overlord";"Larva";326;0
"Unit";"Overlord";"Larva";326;0
"Unit";"Overlord";"Larva";326;0
"Unit";"Overlord";"Larva";326;0
"Unit";"Overlord";"Larva";326;0
"Unit";"Overlord";"Larva";326;0
"Unit";"Overlord";"Larva";326;0
"Building";"Extractor";NA;328;0
"Upgrade";"GlialReconstitution";"RoachWarren";317;0
"Building";"CreepTumor";NA;328;0
"Building";"CreepTumor";NA;328;0
"Unit";"Roach";"Larva";328;2
"Unit";"Roach";"Larva";328;2
"Unit";"Roach";"Larva";328;2
"Building";"InfestationPit";NA;328;0
"Building";"CreepTumor";NA;349;0
"Building";"CreepTumor";NA;349;0
"Building";"CreepTumor";NA;358;0
"Building";"CreepTumor";NA;358;0
"Upgrade";"ZergMissileWeaponsLevel2";"EvolutionChamber";326;0
"Upgrade";"ZergGroundArmorsLevel2";"EvolutionChamber";326;0
"Building";"CreepTumor";NA;358;0
"Building";"CreepTumorQueen";NA;358;0
"Building";"CreepTumorQueen";NA;358;0
"Building";"CreepTumorQueen";NA;358;0
"Building";"Extractor";NA;358;0
"Building";"CreepTumorQueen";NA;358;0
"Building";"CreepTumorQueen";NA;358;0
"Unit";"Roach";"Larva";358;2
"Unit";"Roach";"Larva";358;2
"Unit";"Roach";"Larva";358;2
"Unit";"Roach";"Larva";358;2
"Unit";"Roach";"Larva";358;2
"Unit";"Roach";"Larva";358;2
"Unit";"Roach";"Larva";358;2
"Unit";"Roach";"Larva";358;2
"Unit";"Roach";"Larva";358;2
"Unit";"Roach";"Larva";358;2
"Unit";"Roach";"Larva";358;2
"Unit";"Roach";"Larva";358;2
"Unit";"Roach";"Larva";358;2
"Unit";"Roach";"Larva";358;2
"Unit";"Roach";"Larva";358;2
"Unit";"Roach";"Larva";358;2
"Unit";"Roach";"Larva";358;2
"Unit";"Roach";"Larva";358;2
"Unit";"Roach";"Larva";358;2
"Unit";"Roach";"Larva";358;2
"Unit";"Roach";"Larva";358;2
"Unit";"Roach";"Larva";358;2
"Unit";"Roach";"Larva";358;2
"Unit";"Roach";"Larva";358;2
"Unit";"Roach";"Larva";358;2
"Unit";"Roach";"Larva";358;2
"Unit";"Roach";"Larva";358;2
"Unit";"Roach";"Larva";358;2
"Unit";"Roach";"Larva";358;2
"Unit";"Roach";"Larva";358;2
"Unit";"Roach";"Larva";358;2
"Unit";"Roach";"Larva";358;2
"Unit";"Roach";"Larva";358;2
"Unit";"Roach";"Larva";358;2
"Unit";"Roach";"Larva";358;2
"Unit";"Roach";"Larva";358;2
"Unit";"Roach";"Larva";358;2
"Unit";"Roach";"Larva";358;2
"Unit";"Roach";"Larva";358;2
"Unit";"Roach";"Larva";358;2
"Building";"CreepTumorQueen";NA;368;0
"Building";"CreepTumor";NA;368;0
"Building";"CreepTumor";NA;368;0
"Building";"CreepTumor";NA;368;0
"Building";"CreepTumor";NA;368;0
"Unit";"Roach";"Larva";358;2
"Building";"CreepTumorQueen";NA;368;0
"Unit";"Roach";"Larva";358;2
"Unit";"Roach";"Larva";364;2
"Unit";"Roach";"Larva";368;2
"Unit";"Roach";"Larva";368;2
"Unit";"Roach";"Larva";368;2
"Unit";"Roach";"Larva";368;2
"Unit";"Roach";"Larva";372;2
"Unit";"Roach";"Larva";372;2
"Unit";"Roach";"Larva";434;2
"Unit";"Roach";"Larva";434;2
"Unit";"Roach";"Larva";438;2
"Unit";"Roach";"Larva";438;2
"Unit";"Roach";"Larva";442;2
"Unit";"Roach";"Larva";442;2
"Unit";"Roach";"Larva";442;2
"Unit";"Roach";"Larva";442;2
"Unit";"Zergling";"Larva";472;1
"Unit";"Zergling";"Larva";472;1
"Unit";"Zergling";"Larva";472;1
"Unit";"Zergling";"Larva";472;1
"Unit";"Zergling";"Larva";472;1
"Unit";"Zergling";"Larva";472;1
"Unit";"Zergling";"Larva";472;1
"Unit";"Zergling";"Larva";472;1
"Unit";"Zergling";"Larva";472;1
"Unit";"Zergling";"Larva";472;1
"Building";"CreepTumor";NA;482;0
"Building";"CreepTumor";NA;482;0
"Building";"CreepTumorQueen";NA;482;0
"Building";"Extractor";NA;482;0
"Building";"CreepTumorQueen";NA;482;0
"Building";"Extractor";NA;482;0
"Building";"Extractor";NA;482;0
"Building";"Hatchery";NA;472;0
"Building";"Hatchery";NA;472;0
"Unit";"Roach";"Larva";482;2
"Unit";"Roach";"Larva";482;2
"Unit";"Roach";"Larva";482;2
"Unit";"Roach";"Larva";482;2
"Unit";"Roach";"Larva";482;2
"Unit";"Roach";"Larva";482;2
"Unit";"Roach";"Larva";482;2
"Unit";"Roach";"Larva";482;2
"Unit";"Roach";"Larva";482;2
"Unit";"Roach";"Larva";482;2
"Unit";"Roach";"Larva";482;2
"Unit";"Roach";"Larva";482;2
"Unit";"Roach";"Larva";482;2
"Unit";"Roach";"Larva";482;2
"Unit";"Roach";"Larva";482;2
"Unit";"Roach";"Larva";482;2
