"type";"unit_name";"on_building";"total_supply";"supply"
"Unit";"Overlord";"Larva";13;0
"Building";"Extractor";NA;19;0
"Unit";"Overlord";"Larva";21;0
"Building";"SpawningPool";NA;18;0
"Building";"Hatchery";NA;17;0
"Unit";"Zergling";"Larva";22;1
"Unit";"Zergling";"Larva";22;1
"Unit";"Zergling";"Larva";23;1
"Unit";"Zergling";"Larva";23;1
"Unit";"Zergling";"Larva";23;1
"Unit";"Zergling";"Larva";23;1
"Unit";"Queen";"Hatchery";22;2
"Unit";"Queen";"Hatchery";23;2
"Building";"CreepTumorQueen";NA;34;0
"Unit";"Overlord";"Larva";35;0
"Building";"Hatchery";NA;27;0
"Unit";"Queen";"Hatchery";38;2
"Building";"CreepTumor";NA;46;0
"Building";"CreepTumorQueen";NA;46;0
"Unit";"Overlord";"Larva";50;0
"Building";"CreepTumor";NA;53;0
"Building";"CreepTumor";NA;53;0
"Unit";"Overlord";"Larva";53;0
"Unit";"Overlord";"Larva";53;0
"Building";"CreepTumorQueen";NA;55;0
"Building";"CreepTumorQueen";NA;55;0
"Unit";"Queen";"Hatchery";53;2
"Building";"Extractor";NA;53;0
"Unit";"Queen";"Hatchery";53;2
"Building";"RoachWarren";NA;53;0
"Building";"CreepTumor";NA;63;0
"Building";"CreepTumor";NA;66;0
"Building";"EvolutionChamber";NA;61;0
"Building";"EvolutionChamber";NA;61;0
"Building";"CreepTumor";NA;67;0
"Building";"CreepTumor";NA;67;0
"Building";"CreepTumorQueen";NA;67;0
"Building";"CreepTumorQueen";NA;69;0
"Building";"CreepTumorQueen";NA;78;0
"Unit";"Queen";"Hatchery";63;2
"Building";"CreepTumor";NA;78;0
"Building";"CreepTumor";NA;79;0
"Building";"Extractor";NA;70;0
"Building";"CreepTumor";NA;79;0
"Building";"CreepTumor";NA;79;0
"Building";"CreepTumor";NA;79;0
"Building";"CreepTumor";NA;79;0
"Unit";"Zergling";"Larva";79;1
"Unit";"Zergling";"Larva";79;1
"Unit";"Zergling";"Larva";79;1
"Unit";"Zergling";"Larva";79;1
"Unit";"Overlord";"Larva";79;0
"Unit";"Overlord";"Larva";79;0
"Unit";"Overlord";"Larva";84;0
"Unit";"Overlord";"Larva";84;0
"Unit";"Overlord";"Larva";84;0
"Building";"CreepTumorQueen";NA;88;0
"Building";"CreepTumorQueen";NA;88;0
"Building";"CreepTumor";NA;88;0
"Building";"CreepTumor";NA;88;0
"Unit";"Roach";"Larva";88;2
"Unit";"Roach";"Larva";88;2
"Unit";"Roach";"Larva";88;2
"Building";"CreepTumor";NA;88;0
"Unit";"Roach";"Larva";88;2
"Building";"Extractor";NA;88;0
"Unit";"Roach";"Larva";92;2
"Unit";"Roach";"Larva";92;2
"Unit";"Roach";"Larva";92;2
"Unit";"Roach";"Larva";92;2
"Unit";"Roach";"Larva";93;2
"Unit";"Roach";"Larva";100;2
"Unit";"Roach";"Larva";109;2
"Unit";"Roach";"Larva";109;2
"Unit";"Roach";"Larva";109;2
"Unit";"Roach";"Larva";109;2
"Unit";"Roach";"Larva";117;2
"Unit";"Roach";"Larva";117;2
"Unit";"Roach";"Larva";117;2
"Unit";"Roach";"Larva";117;2
"Unit";"Roach";"Larva";117;2
"Unit";"Zergling";"Larva";117;1
"Unit";"Zergling";"Larva";117;1
"Unit";"Roach";"Larva";117;2
"Unit";"Roach";"Larva";117;2
"Unit";"Roach";"Larva";117;2
"Upgrade";"ZergMissileWeaponsLevel1";"EvolutionChamber";88;0
"Upgrade";"ZergGroundArmorsLevel1";"EvolutionChamber";88;0
"Unit";"Queen";"Hatchery";117;2
"Unit";"Queen";"Hatchery";117;2
"Unit";"Roach";"Larva";133;2
"Unit";"Roach";"Larva";133;2
"Unit";"Roach";"Larva";133;2
"Unit";"Queen";"Hatchery";125;2
"Unit";"Roach";"Larva";143;2
"Unit";"Roach";"Larva";143;2
"Unit";"Roach";"Larva";143;2
"Unit";"Roach";"Larva";147;2
"Unit";"Roach";"Larva";147;2
"Unit";"Roach";"Larva";147;2
"Unit";"Roach";"Larva";147;2
"Unit";"Roach";"Larva";149;2
"Unit";"Roach";"Larva";153;2
"Unit";"Roach";"Larva";153;2
"Unit";"Roach";"Larva";161;2
"Unit";"Roach";"Larva";161;2
"Unit";"Roach";"Larva";161;2
"Building";"CreepTumorQueen";NA;175;0
"Building";"CreepTumorQueen";NA;175;0
"Building";"CreepTumor";NA;183;0
"Building";"CreepTumor";NA;183;0
"Building";"CreepTumor";NA;183;0
"Building";"Extractor";NA;175;0
"Building";"Extractor";NA;175;0
"Building";"CreepTumorQueen";NA;191;0
"Unit";"Overlord";"Larva";183;0
"Unit";"Overlord";"Larva";191;0
"Unit";"Overlord";"Larva";191;0
"Unit";"Overlord";"Larva";191;0
"Building";"CreepTumor";NA;191;0
"Unit";"Overlord";"Larva";191;0
"Unit";"Zergling";"Larva";191;1
"Unit";"Zergling";"Larva";191;1
"Unit";"Zergling";"Larva";191;1
"Unit";"Zergling";"Larva";191;1
"Unit";"Zergling";"Larva";191;1
"Unit";"Zergling";"Larva";191;1
"Unit";"Zergling";"Larva";191;1
"Unit";"Zergling";"Larva";191;1
"Unit";"Zergling";"Larva";191;1
"Unit";"Zergling";"Larva";191;1
"Unit";"Zergling";"Larva";191;1
"Unit";"Zergling";"Larva";191;1
"Unit";"Zergling";"Larva";191;1
"Unit";"Zergling";"Larva";191;1
"Unit";"Zergling";"Larva";191;1
"Unit";"Zergling";"Larva";191;1
"Unit";"Zergling";"Larva";191;1
"Unit";"Zergling";"Larva";191;1
"Unit";"Zergling";"Larva";191;1
"Unit";"Zergling";"Larva";191;1
"Building";"CreepTumor";NA;191;0
"Building";"HydraliskDen";NA;191;0
"Building";"InfestationPit";NA;191;0
"Upgrade";"GlialReconstitution";"RoachWarren";183;0
