"type";"unit_name";"on_building";"total_supply";"supply"
"Unit";"Overlord";"Larva";12;0
"Building";"Extractor";NA;18;0
"Unit";"Overlord";"Larva";22;0
"Building";"SpawningPool";NA;19;0
"Building";"Hatchery";NA;17;0
"Unit";"Zergling";"Larva";22;1
"Unit";"Zergling";"Larva";22;1
"Unit";"Zergling";"Larva";22;1
"Unit";"Zergling";"Larva";22;1
"Unit";"Queen";"Hatchery";22;2
"Unit";"Queen";"Hatchery";22;2
"Unit";"Queen";"Hatchery";33;2
"Unit";"Overlord";"Larva";36;0
"Building";"CreepTumorQueen";NA;38;0
"Unit";"Overlord";"Larva";43;0
"Building";"CreepTumor";NA;49;0
"Building";"CreepTumorQueen";NA;50;0
"Building";"Hatchery";NA;36;0
"Unit";"Queen";"Hatchery";47;2
"Unit";"Queen";"Hatchery";49;2
"Building";"Extractor";NA;51;0
"Building";"CreepTumor";NA;53;0
"Building";"CreepTumor";NA;56;0
"Building";"EvolutionChamber";NA;51;0
"Unit";"Zergling";"Larva";57;1
"Unit";"Zergling";"Larva";57;1
"Unit";"Zergling";"Larva";57;1
"Unit";"Zergling";"Larva";57;1
"Unit";"Zergling";"Larva";57;1
"Unit";"Zergling";"Larva";57;1
"Unit";"Zergling";"Larva";57;1
"Unit";"Zergling";"Larva";57;1
"Building";"CreepTumorQueen";NA;62;0
"Unit";"Overlord";"Larva";57;0
"Unit";"Overlord";"Larva";60;0
"Building";"CreepTumorQueen";NA;62;0
"Building";"BanelingNest";NA;52;0
"Building";"Extractor";NA;70;0
"Building";"CreepTumorQueen";NA;74;0
"Unit";"Overlord";"Larva";70;0
"Building";"CreepTumorQueen";NA;79;0
"Building";"CreepTumor";NA;79;0
"Unit";"Overlord";"Larva";79;0
"Unit";"Overlord";"Larva";79;0
"Unit";"Overlord";"Larva";79;0
"Building";"CreepTumorQueen";NA;81;0
"Building";"CreepTumor";NA;81;0
"Building";"CreepTumor";NA;81;0
"Building";"SporeCrawler";NA;85;0
"Building";"SporeCrawler";NA;86;0
"Building";"CreepTumorQueen";NA;88;0
"Building";"Extractor";NA;88;0
"Building";"CreepTumor";NA;88;0
"Building";"CreepTumorQueen";NA;88;0
"Unit";"Baneling";"Zergling";88;0
"Unit";"Baneling";"Zergling";88;0
"Unit";"Baneling";"Zergling";88;0
"Building";"CreepTumor";NA;88;0
"Unit";"Baneling";"Zergling";88;0
"Building";"CreepTumor";NA;88;0
"Building";"CreepTumor";NA;88;0
"Building";"EvolutionChamber";NA;88;0
"Building";"HydraliskDen";NA;88;0
"Unit";"Zergling";"Larva";88;1
"Unit";"Zergling";"Larva";88;1
"Unit";"Zergling";"Larva";98;1
"Unit";"Zergling";"Larva";98;1
"Unit";"Zergling";"Larva";98;1
"Unit";"Zergling";"Larva";98;1
"Building";"CreepTumorQueen";NA;100;0
"Unit";"Zergling";"Larva";98;1
"Unit";"Zergling";"Larva";98;1
"Unit";"Zergling";"Larva";98;1
"Unit";"Zergling";"Larva";98;1
"Unit";"Zergling";"Larva";98;1
"Unit";"Zergling";"Larva";98;1
"Unit";"Zergling";"Larva";98;1
"Unit";"Zergling";"Larva";98;1
"Unit";"Zergling";"Larva";98;1
"Unit";"Zergling";"Larva";98;1
"Building";"CreepTumor";NA;104;0
"Building";"CreepTumor";NA;104;0
"Unit";"Zergling";"Larva";100;1
"Unit";"Zergling";"Larva";100;1
"Unit";"Zergling";"Larva";100;1
"Unit";"Zergling";"Larva";100;1
"Unit";"Zergling";"Larva";100;1
"Unit";"Zergling";"Larva";100;1
"Unit";"Zergling";"Larva";100;1
"Unit";"Zergling";"Larva";100;1
"Unit";"Zergling";"Larva";100;1
"Unit";"Zergling";"Larva";100;1
"Building";"CreepTumorQueen";NA;114;0
"Building";"CreepTumorQueen";NA;114;0
"Building";"CreepTumorQueen";NA;114;0
"Unit";"Queen";"Hatchery";98;2
"Unit";"Overlord";"Larva";104;0
"Unit";"Zergling";"Larva";104;1
"Unit";"Zergling";"Larva";104;1
"Unit";"Zergling";"Larva";104;1
"Unit";"Zergling";"Larva";104;1
"Building";"Extractor";NA;104;0
"Building";"Extractor";NA;104;0
"Building";"CreepTumorQueen";NA;130;0
"Building";"CreepTumorQueen";NA;130;0
"Building";"CreepTumor";NA;130;0
"Unit";"Hydralisk";"Larva";130;2
"Unit";"Hydralisk";"Larva";130;2
"Unit";"Hydralisk";"Larva";130;2
"Unit";"Hydralisk";"Larva";130;2
"Unit";"Hydralisk";"Larva";130;2
"Building";"CreepTumor";NA;130;0
"Upgrade";"ZergGroundArmorsLevel1";"EvolutionChamber";88;0
"Building";"CreepTumorQueen";NA;130;0
"Building";"CreepTumor";NA;130;0
"Building";"CreepTumor";NA;130;0
"Building";"CreepTumor";NA;131;0
"Building";"CreepTumor";NA;133;0
"Building";"CreepTumor";NA;133;0
"Building";"CreepTumor";NA;133;0
"Unit";"Overlord";"Larva";143;0
"Unit";"Overlord";"Larva";143;0
"Unit";"Overlord";"Larva";143;0
"Unit";"Overlord";"Larva";143;0
"Unit";"Hydralisk";"Larva";143;2
"Building";"CreepTumor";NA;143;0
"Unit";"Overlord";"Larva";143;0
"Building";"CreepTumor";NA;143;0
"Building";"CreepTumor";NA;143;0
"Building";"CreepTumor";NA;143;0
"Building";"CreepTumor";NA;143;0
"Building";"CreepTumor";NA;143;0
"Building";"CreepTumor";NA;143;0
"Unit";"Overlord";"Larva";143;0
"Upgrade";"EvolveMuscularAugments";"HydraliskDen";130;0
"Unit";"Baneling";"Zergling";145;0
"Unit";"Baneling";"Zergling";145;0
"Unit";"Baneling";"Zergling";145;0
"Unit";"Baneling";"Zergling";146;0
"Unit";"Baneling";"Zergling";146;0
"Unit";"Baneling";"Zergling";146;0
"Unit";"Baneling";"Zergling";146;0
"Unit";"Baneling";"Zergling";147;0
"Unit";"Baneling";"Zergling";147;0
"Unit";"Baneling";"Zergling";147;0
"Unit";"Baneling";"Zergling";147;0
"Unit";"Baneling";"Zergling";147;0
"Unit";"Baneling";"Zergling";147;0
"Building";"CreepTumorQueen";NA;147;0
"Building";"CreepTumor";NA;147;0
"Building";"CreepTumorQueen";NA;156;0
"Building";"CreepTumor";NA;147;0
"Building";"CreepTumorQueen";NA;156;0
"Unit";"Zergling";"Larva";147;1
"Unit";"Zergling";"Larva";147;1
"Unit";"Zergling";"Larva";147;1
"Unit";"Zergling";"Larva";147;1
"Unit";"Zergling";"Larva";147;1
"Unit";"Zergling";"Larva";147;1
"Unit";"Zergling";"Larva";147;1
"Unit";"Zergling";"Larva";147;1
"Building";"CreepTumor";NA;156;0
"Building";"CreepTumor";NA;156;0
"Building";"CreepTumor";NA;156;0
"Building";"CreepTumor";NA;156;0
"Building";"CreepTumorQueen";NA;156;0
"Building";"CreepTumor";NA;156;0
"Building";"CreepTumorQueen";NA;156;0
"Building";"CreepTumor";NA;156;0
"Building";"CreepTumor";NA;156;0
"Building";"Hatchery";NA;130;0
"Unit";"Hydralisk";"Larva";156;2
"Unit";"Hydralisk";"Larva";156;2
"Unit";"Hydralisk";"Larva";156;2
"Unit";"Hydralisk";"Larva";156;2
"Building";"Hatchery";NA;143;0
"Unit";"Hydralisk";"Larva";156;2
"Unit";"Hydralisk";"Larva";156;2
"Unit";"Hydralisk";"Larva";156;2
"Building";"CreepTumor";NA;165;0
"Building";"CreepTumor";NA;165;0
"Building";"CreepTumor";NA;165;0
"Unit";"Zergling";"Larva";164;1
"Unit";"Zergling";"Larva";164;1
"Building";"CreepTumor";NA;165;0
"Unit";"Zergling";"Larva";164;1
"Unit";"Zergling";"Larva";164;1
"Building";"CreepTumor";NA;165;0
"Building";"CreepTumor";NA;165;0
"Unit";"Hydralisk";"Larva";164;2
"Unit";"Hydralisk";"Larva";164;2
"Unit";"Hydralisk";"Larva";164;2
"Unit";"Hydralisk";"Larva";164;2
"Building";"CreepTumor";NA;165;0
"Building";"InfestationPit";NA;156;0
"Upgrade";"ZergMeleeWeaponsLevel1";"EvolutionChamber";143;0
"Unit";"Baneling";"Zergling";179;0
"Unit";"Baneling";"Zergling";179;0
"Unit";"Baneling";"Zergling";179;0
"Unit";"Baneling";"Zergling";179;0
"Unit";"Zergling";"Larva";179;1
"Unit";"Zergling";"Larva";179;1
"Unit";"Zergling";"Larva";179;1
"Unit";"Zergling";"Larva";179;1
"Unit";"Zergling";"Larva";179;1
"Unit";"Zergling";"Larva";179;1
"Unit";"Zergling";"Larva";179;1
"Unit";"Zergling";"Larva";179;1
"Unit";"Zergling";"Larva";179;1
"Unit";"Zergling";"Larva";179;1
"Unit";"Zergling";"Larva";179;1
"Unit";"Zergling";"Larva";179;1
"Unit";"Zergling";"Larva";179;1
"Unit";"Zergling";"Larva";179;1
"Building";"CreepTumorQueen";NA;191;0
"Building";"CreepTumorQueen";NA;191;0
"Building";"CreepTumorQueen";NA;191;0
"Unit";"Zergling";"Larva";183;1
"Unit";"Zergling";"Larva";183;1
"Unit";"Zergling";"Larva";183;1
"Unit";"Zergling";"Larva";183;1
"Unit";"Zergling";"Larva";185;1
"Unit";"Zergling";"Larva";185;1
"Unit";"Zergling";"Larva";187;1
"Unit";"Zergling";"Larva";187;1
"Unit";"Zergling";"Larva";189;1
"Unit";"Zergling";"Larva";189;1
"Unit";"Zergling";"Larva";191;1
"Unit";"Zergling";"Larva";191;1
"Unit";"Zergling";"Larva";191;1
"Unit";"Zergling";"Larva";191;1
"Unit";"Zergling";"Larva";191;1
"Unit";"Zergling";"Larva";191;1
"Unit";"Zergling";"Larva";191;1
"Unit";"Zergling";"Larva";191;1
"Unit";"Zergling";"Larva";191;1
"Unit";"Zergling";"Larva";191;1
"Unit";"Zergling";"Larva";191;1
"Unit";"Zergling";"Larva";191;1
"Unit";"Zergling";"Larva";191;1
"Unit";"Zergling";"Larva";191;1
"Upgrade";"EvolveGroovedSpines";"HydraliskDen";164;0
"Unit";"Zergling";"Larva";217;1
"Unit";"Zergling";"Larva";217;1
"Unit";"Zergling";"Larva";217;1
"Unit";"Zergling";"Larva";217;1
"Unit";"Zergling";"Larva";217;1
"Unit";"Zergling";"Larva";217;1
"Unit";"Zergling";"Larva";217;1
"Unit";"Zergling";"Larva";217;1
"Unit";"Zergling";"Larva";217;1
"Unit";"Zergling";"Larva";217;1
"Unit";"Zergling";"Larva";217;1
"Unit";"Zergling";"Larva";217;1
"Unit";"Zergling";"Larva";217;1
"Unit";"Zergling";"Larva";217;1
"Unit";"Zergling";"Larva";229;1
"Unit";"Zergling";"Larva";229;1
"Unit";"Zergling";"Larva";229;1
"Unit";"Zergling";"Larva";229;1
"Unit";"Zergling";"Larva";229;1
"Unit";"Zergling";"Larva";229;1
"Unit";"Zergling";"Larva";229;1
"Unit";"Zergling";"Larva";229;1
"Unit";"Zergling";"Larva";229;1
"Unit";"Zergling";"Larva";229;1
"Unit";"Zergling";"Larva";229;1
"Unit";"Zergling";"Larva";229;1
"Unit";"Zergling";"Larva";229;1
"Unit";"Zergling";"Larva";229;1
"Unit";"Hydralisk";"Larva";229;2
"Building";"CreepTumor";NA;243;0
"Building";"CreepTumor";NA;243;0
"Building";"CreepTumor";NA;245;0
"Building";"CreepTumor";NA;251;0
"Building";"CreepTumor";NA;245;0
"Building";"CreepTumor";NA;257;0
"Building";"Extractor";NA;243;0
"Building";"Extractor";NA;243;0
"Building";"CreepTumorQueen";NA;259;0
"Building";"CreepTumorQueen";NA;259;0
"Building";"CreepTumorQueen";NA;259;0
"Building";"CreepTumorQueen";NA;259;0
"Building";"CreepTumorQueen";NA;259;0
"Building";"CreepTumor";NA;259;0
"Building";"CreepTumor";NA;259;0
"Building";"CreepTumorQueen";NA;259;0
"Building";"CreepTumor";NA;259;0
"Building";"CreepTumor";NA;259;0
"Building";"CreepTumor";NA;259;0
"Building";"CreepTumor";NA;259;0
"Unit";"Hydralisk";"Larva";257;2
"Unit";"Hydralisk";"Larva";257;2
"Unit";"Hydralisk";"Larva";257;2
"Unit";"Hydralisk";"Larva";257;2
"Unit";"Hydralisk";"Larva";257;2
"Unit";"Hydralisk";"Larva";257;2
"Building";"CreepTumor";NA;259;0
"Building";"CreepTumorQueen";NA;259;0
"Unit";"Overlord";"Larva";259;0
"Unit";"Overlord";"Larva";259;0
"Building";"SporeCrawler";NA;278;0
"Unit";"Overlord";"Larva";278;0
"Unit";"Overlord";"Larva";278;0
"Unit";"Overlord";"Larva";278;0
"Unit";"Overlord";"Larva";278;0
"Unit";"Overlord";"Larva";278;0
"Unit";"Overlord";"Larva";278;0
"Unit";"Overlord";"Larva";278;0
"Building";"CreepTumorQueen";NA;278;0
"Building";"CreepTumorQueen";NA;278;0
"Building";"CreepTumorQueen";NA;278;0
"Building";"CreepTumor";NA;278;0
"Building";"CreepTumor";NA;278;0
"Building";"CreepTumor";NA;278;0
"Building";"CreepTumor";NA;278;0
"Building";"CreepTumor";NA;278;0
"Building";"CreepTumor";NA;278;0
"Building";"CreepTumor";NA;278;0
"Building";"CreepTumor";NA;278;0
"Building";"CreepTumor";NA;278;0
"Building";"CreepTumor";NA;278;0
"Building";"CreepTumor";NA;278;0
"Building";"CreepTumor";NA;278;0
"Building";"CreepTumor";NA;278;0
"Building";"CreepTumor";NA;278;0
"Unit";"Viper";"Larva";278;3
"Unit";"Viper";"Larva";278;3
"Unit";"Viper";"Larva";278;3
"Unit";"Viper";"Larva";278;3
"Unit";"Baneling";"Zergling";278;0
"Building";"Hatchery";NA;257;0
"Unit";"Baneling";"Zergling";278;0
"Unit";"Baneling";"Zergling";278;0
"Unit";"Baneling";"Zergling";278;0
"Unit";"Baneling";"Zergling";278;0
"Unit";"Baneling";"Zergling";278;0
"Unit";"Baneling";"Zergling";278;0
"Unit";"Baneling";"Zergling";278;0
"Unit";"Baneling";"Zergling";278;0
"Unit";"Baneling";"Zergling";278;0
"Unit";"Baneling";"Zergling";278;0
"Unit";"Baneling";"Zergling";278;0
"Unit";"Baneling";"Zergling";278;0
"Unit";"Baneling";"Zergling";278;0
"Unit";"Baneling";"Zergling";278;0
"Unit";"Baneling";"Zergling";278;0
"Unit";"Baneling";"Zergling";278;0
"Unit";"Baneling";"Zergling";278;0
"Unit";"Baneling";"Zergling";278;0
"Unit";"Baneling";"Zergling";278;0
"Unit";"Baneling";"Zergling";278;0
"Unit";"Baneling";"Zergling";278;0
"Unit";"Baneling";"Zergling";278;0
"Unit";"Baneling";"Zergling";278;0
"Unit";"Baneling";"Zergling";278;0
"Unit";"Baneling";"Zergling";278;0
"Unit";"Baneling";"Zergling";278;0
"Building";"CreepTumor";NA;290;0
"Unit";"Zergling";"Larva";290;1
"Unit";"Zergling";"Larva";290;1
"Unit";"Zergling";"Larva";290;1
"Unit";"Zergling";"Larva";290;1
"Unit";"Zergling";"Larva";290;1
"Unit";"Zergling";"Larva";290;1
"Unit";"Zergling";"Larva";290;1
"Unit";"Zergling";"Larva";290;1
"Unit";"Zergling";"Larva";290;1
"Unit";"Zergling";"Larva";290;1
"Unit";"Zergling";"Larva";290;1
"Unit";"Zergling";"Larva";290;1
"Unit";"Zergling";"Larva";290;1
"Unit";"Zergling";"Larva";290;1
"Unit";"Zergling";"Larva";290;1
"Unit";"Zergling";"Larva";290;1
"Unit";"Zergling";"Larva";290;1
"Unit";"Zergling";"Larva";290;1
"Unit";"Zergling";"Larva";290;1
"Unit";"Zergling";"Larva";290;1
"Unit";"Zergling";"Larva";290;1
"Unit";"Zergling";"Larva";290;1
"Unit";"Zergling";"Larva";290;1
"Unit";"Zergling";"Larva";290;1
"Unit";"Zergling";"Larva";290;1
"Unit";"Zergling";"Larva";290;1
"Unit";"Zergling";"Larva";290;1
"Unit";"Zergling";"Larva";290;1
"Unit";"Zergling";"Larva";290;1
"Unit";"Zergling";"Larva";290;1
"Unit";"Zergling";"Larva";290;1
"Unit";"Zergling";"Larva";290;1
"Unit";"Zergling";"Larva";290;1
"Unit";"Zergling";"Larva";290;1
"Unit";"Zergling";"Larva";290;1
"Unit";"Zergling";"Larva";290;1
"Unit";"Zergling";"Larva";290;1
"Unit";"Zergling";"Larva";290;1
"Unit";"Zergling";"Larva";290;1
"Unit";"Zergling";"Larva";290;1
"Unit";"Zergling";"Larva";290;1
"Unit";"Zergling";"Larva";290;1
"Unit";"Zergling";"Larva";290;1
"Unit";"Zergling";"Larva";290;1
"Unit";"Zergling";"Larva";290;1
"Unit";"Zergling";"Larva";290;1
"Building";"CreepTumor";NA;292;0
"Unit";"Zergling";"Larva";291;1
"Unit";"Zergling";"Larva";291;1
"Unit";"Zergling";"Larva";292;1
"Unit";"Zergling";"Larva";292;1
"Unit";"Zergling";"Larva";292;1
"Unit";"Zergling";"Larva";292;1
"Unit";"Zergling";"Larva";292;1
"Unit";"Zergling";"Larva";292;1
"Unit";"Zergling";"Larva";292;1
"Unit";"Zergling";"Larva";292;1
"Building";"CreepTumor";NA;308;0
"Building";"CreepTumor";NA;318;0
"Building";"CreepTumor";NA;328;0
"Building";"CreepTumor";NA;328;0
"Building";"CreepTumor";NA;328;0
"Unit";"Zergling";"Larva";292;1
"Unit";"Zergling";"Larva";292;1
"Unit";"Zergling";"Larva";292;1
"Unit";"Zergling";"Larva";292;1
"Unit";"Zergling";"Larva";292;1
"Unit";"Zergling";"Larva";292;1
"Building";"CreepTumor";NA;328;0
"Unit";"Zergling";"Larva";292;1
"Unit";"Zergling";"Larva";292;1
"Unit";"Zergling";"Larva";338;1
"Unit";"Zergling";"Larva";338;1
"Unit";"Zergling";"Larva";338;1
"Unit";"Zergling";"Larva";338;1
"Unit";"Zergling";"Larva";338;1
"Unit";"Zergling";"Larva";338;1
"Upgrade";"ZergMeleeWeaponsLevel2";"EvolutionChamber";278;0
"Upgrade";"ZergGroundArmorsLevel2";"EvolutionChamber";278;0
"Unit";"Hydralisk";"Larva";356;2
"Unit";"Hydralisk";"Larva";356;2
"Unit";"Hydralisk";"Larva";356;2
"Unit";"Hydralisk";"Larva";356;2
"Unit";"Hydralisk";"Larva";356;2
"Unit";"Hydralisk";"Larva";356;2
"Unit";"Hydralisk";"Larva";356;2
"Unit";"Hydralisk";"Larva";356;2
"Building";"CreepTumor";NA;362;0
"Building";"CreepTumor";NA;362;0
"Building";"Extractor";NA;362;0
"Building";"Extractor";NA;362;0
"Building";"CreepTumor";NA;362;0
"Unit";"Zergling";"Larva";362;1
"Unit";"Zergling";"Larva";362;1
"Unit";"Zergling";"Larva";362;1
"Unit";"Zergling";"Larva";362;1
"Building";"CreepTumor";NA;362;0
"Unit";"Zergling";"Larva";362;1
"Unit";"Zergling";"Larva";362;1
"Unit";"Zergling";"Larva";362;1
"Unit";"Zergling";"Larva";362;1
"Unit";"Zergling";"Larva";362;1
"Unit";"Zergling";"Larva";362;1
"Building";"CreepTumor";NA;384;0
"Building";"CreepTumor";NA;384;0
"Building";"CreepTumor";NA;384;0
"Building";"CreepTumor";NA;384;0
"Building";"CreepTumor";NA;384;0
"Unit";"Hydralisk";"Larva";384;2
"Unit";"Hydralisk";"Larva";384;2
"Unit";"Hydralisk";"Larva";384;2
"Unit";"Hydralisk";"Larva";384;2
"Unit";"Hydralisk";"Larva";384;2
"Unit";"Hydralisk";"Larva";384;2
"Unit";"Zergling";"Larva";394;1
"Unit";"Zergling";"Larva";394;1
"Unit";"Zergling";"Larva";394;1
"Unit";"Zergling";"Larva";394;1
"Unit";"Zergling";"Larva";394;1
"Unit";"Zergling";"Larva";394;1
"Unit";"Zergling";"Larva";394;1
"Unit";"Zergling";"Larva";394;1
"Unit";"Zergling";"Larva";394;1
"Unit";"Zergling";"Larva";394;1
"Unit";"Zergling";"Larva";394;1
"Unit";"Zergling";"Larva";394;1
"Unit";"Hydralisk";"Larva";394;2
"Unit";"Hydralisk";"Larva";394;2
"Unit";"Hydralisk";"Larva";394;2
"Unit";"Hydralisk";"Larva";394;2
"Unit";"Hydralisk";"Larva";394;2
"Unit";"Hydralisk";"Larva";394;2
"Unit";"Hydralisk";"Larva";394;2
"Unit";"Hydralisk";"Larva";394;2
