"type";"unit_name";"on_building";"total_supply";"supply"
"Unit";"Overlord";"Larva";14;0
"Building";"Extractor";NA;19;0
"Building";"SpawningPool";NA;19;0
"Building";"Hatchery";NA;15;0
"Unit";"Overlord";"Larva";22;0
"Unit";"Zergling";"Larva";23;1
"Unit";"Zergling";"Larva";23;1
"Unit";"Zergling";"Larva";23;1
"Unit";"Zergling";"Larva";23;1
"Unit";"Queen";"Hatchery";23;2
"Unit";"Queen";"Hatchery";23;2
"Unit";"Overlord";"Larva";34;0
"Unit";"Queen";"Hatchery";34;2
"Building";"CreepTumorQueen";NA;47;0
"Unit";"Overlord";"Larva";46;0
"Building";"Hatchery";NA;32;0
"Building";"Extractor";NA;50;0
"Building";"Extractor";NA;50;0
"Unit";"Zergling";"Larva";50;1
"Unit";"Zergling";"Larva";50;1
"Unit";"Zergling";"Larva";50;1
"Unit";"Zergling";"Larva";50;1
"Building";"CreepTumorQueen";NA;52;0
"Building";"CreepTumor";NA;52;0
"Unit";"Zergling";"Larva";52;1
"Unit";"Zergling";"Larva";52;1
"Unit";"Zergling";"Larva";52;1
"Unit";"Zergling";"Larva";52;1
"Building";"RoachWarren";NA;50;0
"Unit";"Overlord";"Larva";64;0
"Unit";"Queen";"Hatchery";52;2
"Unit";"Overlord";"Larva";65;0
"Building";"CreepTumorQueen";NA;66;0
"Unit";"Roach";"Larva";66;2
"Building";"SporeCrawler";NA;66;0
"Unit";"Overlord";"Larva";68;0
"Building";"CreepTumor";NA;68;0
"Unit";"Roach";"Larva";68;2
"Building";"SporeCrawler";NA;68;0
"Unit";"Roach";"Larva";69;2
"Unit";"Roach";"Larva";70;2
"Unit";"Roach";"Larva";71;2
"Building";"CreepTumor";NA;84;0
"Unit";"Overlord";"Larva";81;0
"Building";"CreepTumor";NA;84;0
"Building";"CreepTumorQueen";NA;85;0
"Building";"CreepTumor";NA;85;0
"Building";"SporeCrawler";NA;81;0
"Unit";"Overlord";"Larva";85;0
"Building";"CreepTumorQueen";NA;87;0
"Unit";"Overlord";"Larva";87;0
"Building";"CreepTumor";NA;93;0
"Building";"CreepTumor";NA;93;0
"Building";"CreepTumor";NA;94;0
"Building";"EvolutionChamber";NA;93;0
"Building";"EvolutionChamber";NA;93;0
"Building";"CreepTumor";NA;99;0
"Building";"CreepTumor";NA;99;0
"Building";"CreepTumorQueen";NA;107;0
"Unit";"Roach";"Larva";107;2
"Building";"CreepTumor";NA;107;0
"Unit";"Roach";"Larva";107;2
"Upgrade";"GlialReconstitution";"RoachWarren";93;0
"Building";"Extractor";NA;107;0
"Building";"Extractor";NA;107;0
"Building";"CreepTumor";NA;107;0
"Building";"CreepTumor";NA;107;0
"Building";"CreepTumor";NA;107;0
"Building";"CreepTumor";NA;111;0
"Unit";"Overlord";"Larva";107;0
"Unit";"Roach";"Larva";107;2
"Unit";"Overlord";"Larva";107;0
"Unit";"Roach";"Larva";107;2
"Unit";"Roach";"Larva";107;2
"Building";"Extractor";NA;107;0
"Unit";"Overlord";"Larva";111;0
"Unit";"Overlord";"Larva";111;0
"Building";"BanelingNest";NA;107;0
"Unit";"Overlord";"Larva";111;0
"Unit";"Overlord";"Larva";111;0
"Building";"InfestationPit";NA;107;0
"Unit";"Roach";"Larva";117;2
"Unit";"Roach";"Larva";117;2
"Building";"CreepTumorQueen";NA;117;0
"Building";"Hatchery";NA;107;0
"Unit";"Overlord";"Larva";117;0
"Building";"CreepTumor";NA;128;0
"Building";"CreepTumor";NA;128;0
"Unit";"Overlord";"Larva";128;0
"Unit";"Overlord";"Larva";128;0
"Unit";"Baneling";"Zergling";128;0
"Unit";"Baneling";"Zergling";128;0
"Unit";"Baneling";"Zergling";128;0
"Unit";"Baneling";"Zergling";128;0
"Unit";"Baneling";"Zergling";128;0
"Building";"CreepTumor";NA;128;0
"Unit";"Zergling";"Larva";128;1
"Unit";"Zergling";"Larva";128;1
"Unit";"Zergling";"Larva";128;1
"Unit";"Zergling";"Larva";128;1
"Unit";"Zergling";"Larva";128;1
"Unit";"Zergling";"Larva";128;1
"Unit";"Zergling";"Larva";128;1
"Unit";"Zergling";"Larva";128;1
"Building";"CreepTumor";NA;128;0
"Building";"CreepTumor";NA;128;0
"Building";"CreepTumor";NA;132;0
"Unit";"Zergling";"Larva";128;1
"Unit";"Zergling";"Larva";128;1
"Unit";"Zergling";"Larva";128;1
"Unit";"Zergling";"Larva";128;1
"Unit";"Zergling";"Larva";128;1
"Unit";"Zergling";"Larva";128;1
"Unit";"Zergling";"Larva";128;1
"Unit";"Zergling";"Larva";128;1
"Unit";"Zergling";"Larva";128;1
"Unit";"Zergling";"Larva";128;1
"Building";"CreepTumor";NA;142;0
"Upgrade";"ZergMeleeWeaponsLevel1";"EvolutionChamber";111;0
"Building";"CreepTumor";NA;152;0
"Upgrade";"ZergGroundArmorsLevel1";"EvolutionChamber";111;0
"Building";"CreepTumor";NA;152;0
"Unit";"Zergling";"Larva";142;1
"Unit";"Zergling";"Larva";142;1
"Unit";"Baneling";"Zergling";154;0
"Unit";"Zergling";"Larva";142;1
"Unit";"Zergling";"Larva";142;1
"Unit";"Zergling";"Larva";144;1
"Unit";"Zergling";"Larva";144;1
"Building";"Extractor";NA;142;0
"Building";"Extractor";NA;142;0
"Unit";"Zergling";"Larva";154;1
"Unit";"Zergling";"Larva";154;1
"Unit";"Zergling";"Larva";154;1
"Unit";"Zergling";"Larva";154;1
"Unit";"Zergling";"Larva";154;1
"Unit";"Zergling";"Larva";154;1
"Unit";"Zergling";"Larva";154;1
"Unit";"Zergling";"Larva";154;1
"Unit";"Zergling";"Larva";154;1
"Unit";"Zergling";"Larva";154;1
"Unit";"Zergling";"Larva";154;1
"Unit";"Zergling";"Larva";154;1
"Unit";"Baneling";"Zergling";154;0
"Unit";"Baneling";"Zergling";154;0
"Unit";"Zergling";"Larva";157;1
"Unit";"Zergling";"Larva";157;1
"Unit";"Queen";"Hatchery";142;2
"Unit";"Zergling";"Larva";179;1
"Unit";"Zergling";"Larva";179;1
"Unit";"Zergling";"Larva";179;1
"Unit";"Zergling";"Larva";179;1
"Unit";"Zergling";"Larva";179;1
"Unit";"Zergling";"Larva";179;1
"Unit";"Zergling";"Larva";179;1
"Unit";"Zergling";"Larva";179;1
"Unit";"Zergling";"Larva";179;1
"Unit";"Zergling";"Larva";179;1
"Unit";"Zergling";"Larva";179;1
"Unit";"Zergling";"Larva";179;1
"Unit";"Zergling";"Larva";179;1
"Unit";"Zergling";"Larva";179;1
"Unit";"Zergling";"Larva";179;1
"Unit";"Zergling";"Larva";179;1
"Unit";"Zergling";"Larva";179;1
"Unit";"Zergling";"Larva";179;1
"Unit";"Zergling";"Larva";179;1
"Unit";"Zergling";"Larva";179;1
"Unit";"Zergling";"Larva";179;1
"Unit";"Zergling";"Larva";179;1
"Unit";"Zergling";"Larva";179;1
"Unit";"Zergling";"Larva";179;1
"Unit";"Zergling";"Larva";179;1
"Unit";"Zergling";"Larva";179;1
"Unit";"Zergling";"Larva";179;1
"Unit";"Zergling";"Larva";179;1
"Unit";"Zergling";"Larva";179;1
"Unit";"Zergling";"Larva";179;1
"Unit";"Zergling";"Larva";179;1
"Unit";"Zergling";"Larva";179;1
"Unit";"Zergling";"Larva";179;1
"Unit";"Zergling";"Larva";179;1
"Unit";"Zergling";"Larva";179;1
"Unit";"Zergling";"Larva";179;1
"Unit";"Zergling";"Larva";179;1
"Unit";"Zergling";"Larva";179;1
"Unit";"Zergling";"Larva";179;1
"Unit";"Zergling";"Larva";179;1
"Building";"Hatchery";NA;142;0
"Unit";"Zergling";"Larva";179;1
"Unit";"Zergling";"Larva";179;1
"Unit";"Zergling";"Larva";181;1
"Unit";"Zergling";"Larva";181;1
"Unit";"Zergling";"Larva";181;1
"Unit";"Zergling";"Larva";181;1
"Unit";"Zergling";"Larva";193;1
"Unit";"Zergling";"Larva";193;1
"Unit";"Zergling";"Larva";201;1
"Unit";"Zergling";"Larva";201;1
"Unit";"Zergling";"Larva";203;1
"Unit";"Zergling";"Larva";203;1
"Unit";"Zergling";"Larva";203;1
"Unit";"Zergling";"Larva";203;1
"Unit";"Zergling";"Larva";203;1
"Unit";"Zergling";"Larva";203;1
"Unit";"Baneling";"Zergling";219;0
"Unit";"Baneling";"Zergling";219;0
"Unit";"Baneling";"Zergling";219;0
"Unit";"Baneling";"Zergling";219;0
"Building";"CreepTumor";NA;235;0
"Unit";"Baneling";"Zergling";219;0
"Unit";"Baneling";"Zergling";219;0
"Unit";"Baneling";"Zergling";219;0
"Unit";"Baneling";"Zergling";219;0
"Unit";"Zergling";"Larva";219;1
"Unit";"Zergling";"Larva";219;1
"Unit";"Zergling";"Larva";219;1
"Unit";"Zergling";"Larva";219;1
"Unit";"Zergling";"Larva";219;1
"Unit";"Zergling";"Larva";219;1
"Unit";"Zergling";"Larva";219;1
"Unit";"Zergling";"Larva";219;1
"Unit";"Zergling";"Larva";219;1
"Unit";"Zergling";"Larva";219;1
"Unit";"Zergling";"Larva";219;1
"Unit";"Zergling";"Larva";219;1
"Unit";"Baneling";"Zergling";233;0
"Unit";"Baneling";"Zergling";235;0
"Building";"CreepTumorQueen";NA;235;0
"Building";"CreepTumorQueen";NA;235;0
"Unit";"Queen";"Hatchery";179;2
"Unit";"Zergling";"Larva";235;1
"Unit";"Zergling";"Larva";235;1
"Unit";"Zergling";"Larva";235;1
"Unit";"Zergling";"Larva";235;1
"Building";"CreepTumor";NA;235;0
"Building";"CreepTumor";NA;235;0
"Unit";"Zergling";"Larva";235;1
"Unit";"Zergling";"Larva";235;1
"Unit";"Zergling";"Larva";235;1
"Unit";"Zergling";"Larva";235;1
"Unit";"Zergling";"Larva";235;1
"Unit";"Zergling";"Larva";235;1
"Unit";"Zergling";"Larva";235;1
"Unit";"Zergling";"Larva";235;1
"Unit";"Zergling";"Larva";235;1
"Unit";"Zergling";"Larva";235;1
"Unit";"Zergling";"Larva";235;1
"Unit";"Zergling";"Larva";235;1
"Unit";"Zergling";"Larva";237;1
"Unit";"Zergling";"Larva";237;1
"Unit";"Zergling";"Larva";237;1
"Unit";"Zergling";"Larva";237;1
"Unit";"Zergling";"Larva";237;1
"Unit";"Zergling";"Larva";237;1
"Building";"CreepTumor";NA;263;0
"Building";"CreepTumor";NA;265;0
"Unit";"Baneling";"Zergling";261;0
"Unit";"Baneling";"Zergling";261;0
"Unit";"Zergling";"Larva";271;1
"Unit";"Zergling";"Larva";271;1
"Unit";"Zergling";"Larva";271;1
"Unit";"Zergling";"Larva";271;1
"Unit";"Zergling";"Larva";271;1
"Unit";"Zergling";"Larva";271;1
"Unit";"Zergling";"Larva";271;1
"Unit";"Zergling";"Larva";271;1
"Unit";"Zergling";"Larva";271;1
"Unit";"Zergling";"Larva";271;1
"Unit";"Zergling";"Larva";271;1
"Unit";"Zergling";"Larva";271;1
"Unit";"Zergling";"Larva";271;1
"Unit";"Zergling";"Larva";271;1
"Unit";"Zergling";"Larva";271;1
"Unit";"Zergling";"Larva";271;1
"Building";"UltraliskCavern";NA;235;0
"Unit";"Overlord";"Larva";271;0
"Unit";"Overlord";"Larva";271;0
"Unit";"Overlord";"Larva";271;0
"Unit";"Baneling";"Zergling";271;0
"Unit";"Baneling";"Zergling";271;0
"Unit";"Baneling";"Zergling";271;0
"Unit";"Baneling";"Zergling";271;0
"Unit";"Baneling";"Zergling";271;0
"Unit";"Baneling";"Zergling";271;0
"Unit";"Baneling";"Zergling";271;0
"Unit";"Baneling";"Zergling";271;0
"Unit";"Baneling";"Zergling";271;0
"Unit";"Baneling";"Zergling";271;0
"Unit";"Baneling";"Zergling";271;0
"Unit";"Baneling";"Zergling";271;0
"Unit";"Baneling";"Zergling";271;0
"Unit";"Baneling";"Zergling";271;0
"Unit";"Baneling";"Zergling";271;0
"Unit";"Baneling";"Zergling";271;0
"Unit";"Baneling";"Zergling";271;0
"Unit";"Baneling";"Zergling";271;0
"Unit";"Baneling";"Zergling";271;0
"Unit";"Overlord";"Larva";271;0
"Unit";"Baneling";"Zergling";271;0
"Unit";"Baneling";"Zergling";271;0
"Unit";"Baneling";"Zergling";271;0
"Building";"CreepTumor";NA;287;0
"Building";"CreepTumor";NA;287;0
"Building";"CreepTumorQueen";NA;287;0
"Building";"CreepTumorQueen";NA;287;0
"Upgrade";"ZergMeleeWeaponsLevel2";"EvolutionChamber";209;0
"Building";"Hatchery";NA;247;0
"Unit";"Queen";"Hatchery";287;2
"Unit";"Baneling";"Zergling";287;0
"Unit";"Baneling";"Zergling";287;0
"Unit";"Baneling";"Zergling";287;0
"Unit";"Baneling";"Zergling";287;0
"Unit";"Baneling";"Zergling";287;0
"Unit";"Zergling";"Larva";287;1
"Unit";"Zergling";"Larva";287;1
"Unit";"Zergling";"Larva";287;1
"Unit";"Zergling";"Larva";287;1
"Unit";"Zergling";"Larva";287;1
"Unit";"Zergling";"Larva";287;1
"Unit";"Zergling";"Larva";287;1
"Unit";"Zergling";"Larva";287;1
"Unit";"Zergling";"Larva";287;1
"Unit";"Zergling";"Larva";287;1
"Unit";"Zergling";"Larva";287;1
"Unit";"Zergling";"Larva";287;1
"Unit";"Zergling";"Larva";287;1
"Unit";"Zergling";"Larva";287;1
"Unit";"Zergling";"Larva";287;1
"Unit";"Zergling";"Larva";287;1
"Unit";"Zergling";"Larva";287;1
"Unit";"Zergling";"Larva";287;1
"Unit";"Zergling";"Larva";287;1
"Unit";"Zergling";"Larva";287;1
"Unit";"Zergling";"Larva";287;1
"Unit";"Zergling";"Larva";287;1
"Unit";"Zergling";"Larva";287;1
"Unit";"Zergling";"Larva";287;1
"Unit";"Zergling";"Larva";287;1
"Unit";"Zergling";"Larva";287;1
"Unit";"Zergling";"Larva";287;1
"Unit";"Zergling";"Larva";287;1
"Unit";"Zergling";"Larva";287;1
"Unit";"Zergling";"Larva";287;1
"Unit";"Zergling";"Larva";287;1
"Unit";"Zergling";"Larva";287;1
"Unit";"Zergling";"Larva";287;1
"Unit";"Zergling";"Larva";287;1
"Unit";"Zergling";"Larva";287;1
"Unit";"Zergling";"Larva";287;1
"Unit";"Zergling";"Larva";287;1
"Unit";"Zergling";"Larva";287;1
"Unit";"Zergling";"Larva";287;1
"Unit";"Zergling";"Larva";287;1
"Unit";"Zergling";"Larva";287;1
"Unit";"Zergling";"Larva";287;1
"Unit";"Zergling";"Larva";287;1
"Unit";"Zergling";"Larva";287;1
"Unit";"Baneling";"Zergling";287;0
"Unit";"Baneling";"Zergling";287;0
"Unit";"Baneling";"Zergling";287;0
"Building";"CreepTumorQueen";NA;287;0
"Building";"CreepTumorQueen";NA;287;0
"Unit";"Zergling";"Larva";333;1
"Unit";"Zergling";"Larva";333;1
"Unit";"Zergling";"Larva";333;1
"Unit";"Zergling";"Larva";333;1
"Unit";"Zergling";"Larva";333;1
"Unit";"Zergling";"Larva";333;1
"Unit";"Zergling";"Larva";333;1
"Unit";"Zergling";"Larva";333;1
"Unit";"Zergling";"Larva";333;1
"Unit";"Zergling";"Larva";333;1
"Unit";"Zergling";"Larva";333;1
"Unit";"Zergling";"Larva";333;1
"Unit";"Zergling";"Larva";333;1
"Unit";"Zergling";"Larva";333;1
"Unit";"Zergling";"Larva";333;1
"Unit";"Zergling";"Larva";333;1
"Unit";"Zergling";"Larva";333;1
"Unit";"Zergling";"Larva";333;1
"Unit";"Zergling";"Larva";333;1
"Unit";"Zergling";"Larva";333;1
"Unit";"Zergling";"Larva";333;1
"Unit";"Zergling";"Larva";333;1
"Building";"CreepTumorQueen";NA;333;0
"Building";"CreepTumor";NA;333;0
"Unit";"Baneling";"Zergling";333;0
"Unit";"Baneling";"Zergling";333;0
"Unit";"Baneling";"Zergling";333;0
"Unit";"Baneling";"Zergling";333;0
"Unit";"Baneling";"Zergling";333;0
"Unit";"Baneling";"Zergling";333;0
"Unit";"Baneling";"Zergling";333;0
"Unit";"Ultralisk";"Larva";287;6
"Unit";"Baneling";"Zergling";333;0
"Unit";"Baneling";"Zergling";333;0
"Unit";"Baneling";"Zergling";333;0
"Unit";"Baneling";"Zergling";333;0
"Unit";"Baneling";"Zergling";333;0
"Unit";"Queen";"Hatchery";289;2
"Building";"CreepTumor";NA;333;0
"Unit";"Baneling";"Zergling";363;0
"Unit";"Baneling";"Zergling";363;0
"Unit";"Baneling";"Zergling";363;0
"Unit";"Baneling";"Zergling";363;0
"Unit";"Baneling";"Zergling";363;0
"Unit";"Baneling";"Zergling";363;0
"Unit";"Baneling";"Zergling";363;0
"Upgrade";"ZergGroundArmorsLevel2";"EvolutionChamber";271;0
"Upgrade";"ChitinousPlating";"UltraliskCavern";287;0
"Unit";"Baneling";"Zergling";363;0
"Unit";"Ultralisk";"Larva";355;6
"Unit";"Zergling";"Larva";363;1
"Unit";"Zergling";"Larva";363;1
"Unit";"Zergling";"Larva";363;1
"Unit";"Zergling";"Larva";363;1
"Unit";"Zergling";"Larva";363;1
"Unit";"Zergling";"Larva";363;1
"Unit";"Zergling";"Larva";363;1
"Unit";"Zergling";"Larva";363;1
"Unit";"Zergling";"Larva";363;1
"Unit";"Zergling";"Larva";363;1
"Unit";"Zergling";"Larva";363;1
"Unit";"Zergling";"Larva";363;1
"Unit";"Zergling";"Larva";363;1
"Unit";"Zergling";"Larva";363;1
"Unit";"Zergling";"Larva";363;1
"Unit";"Zergling";"Larva";363;1
"Unit";"Zergling";"Larva";363;1
"Unit";"Zergling";"Larva";363;1
"Unit";"Zergling";"Larva";363;1
"Unit";"Zergling";"Larva";363;1
"Unit";"Zergling";"Larva";363;1
"Unit";"Zergling";"Larva";363;1
"Unit";"Zergling";"Larva";363;1
"Unit";"Zergling";"Larva";363;1
"Unit";"Zergling";"Larva";363;1
"Unit";"Zergling";"Larva";363;1
"Unit";"Zergling";"Larva";363;1
"Unit";"Zergling";"Larva";363;1
"Unit";"Ultralisk";"Larva";363;6
"Unit";"Ultralisk";"Larva";363;6
"Unit";"Baneling";"Zergling";409;0
"Unit";"Baneling";"Zergling";409;0
"Unit";"Baneling";"Zergling";409;0
"Unit";"Baneling";"Zergling";409;0
"Unit";"Baneling";"Zergling";409;0
"Unit";"Baneling";"Zergling";409;0
"Building";"CreepTumor";NA;409;0
"Building";"CreepTumor";NA;409;0
"Building";"CreepTumor";NA;409;0
"Building";"CreepTumor";NA;409;0
"Building";"CreepTumorQueen";NA;409;0
"Building";"CreepTumorQueen";NA;409;0
"Building";"CreepTumor";NA;409;0
"Unit";"Ultralisk";"Larva";409;6
"Unit";"Ultralisk";"Larva";409;6
"Unit";"Ultralisk";"Larva";409;6
"Unit";"Ultralisk";"Larva";409;6
"Building";"CreepTumorQueen";NA;409;0
"Unit";"Queen";"Hatchery";409;2
"Building";"Extractor";NA;409;0
"Building";"Extractor";NA;409;0
"Unit";"Zergling";"Larva";433;1
"Unit";"Zergling";"Larva";433;1
"Unit";"Zergling";"Larva";433;1
"Unit";"Zergling";"Larva";433;1
"Unit";"Zergling";"Larva";433;1
"Unit";"Zergling";"Larva";433;1
"Unit";"Zergling";"Larva";433;1
"Unit";"Zergling";"Larva";433;1
"Unit";"Zergling";"Larva";433;1
"Unit";"Zergling";"Larva";433;1
"Unit";"Zergling";"Larva";433;1
"Unit";"Zergling";"Larva";433;1
"Unit";"Zergling";"Larva";433;1
"Unit";"Zergling";"Larva";433;1
"Unit";"Zergling";"Larva";433;1
"Unit";"Zergling";"Larva";433;1
"Unit";"Zergling";"Larva";433;1
"Unit";"Zergling";"Larva";433;1
"Unit";"Zergling";"Larva";433;1
"Unit";"Zergling";"Larva";433;1
"Unit";"Zergling";"Larva";433;1
"Unit";"Zergling";"Larva";433;1
"Building";"CreepTumor";NA;438;0
"Building";"CreepTumor";NA;438;0
"Building";"CreepTumor";NA;438;0
"Unit";"Ultralisk";"Larva";409;6
"Unit";"Ultralisk";"Larva";409;6
"Unit";"Overlord";"Larva";438;0
"Unit";"Overlord";"Larva";438;0
"Building";"CreepTumor";NA;438;0
"Building";"CreepTumor";NA;438;0
"Building";"CreepTumor";NA;438;0
"Unit";"Overlord";"Larva";438;0
"Unit";"Zergling";"Larva";476;1
"Unit";"Zergling";"Larva";476;1
"Unit";"Zergling";"Larva";476;1
"Unit";"Zergling";"Larva";476;1
"Unit";"Zergling";"Larva";476;1
"Unit";"Zergling";"Larva";476;1
"Unit";"Zergling";"Larva";476;1
"Unit";"Zergling";"Larva";476;1
"Unit";"Zergling";"Larva";476;1
"Unit";"Zergling";"Larva";476;1
"Unit";"Zergling";"Larva";476;1
"Unit";"Zergling";"Larva";476;1
"Unit";"Zergling";"Larva";476;1
"Unit";"Zergling";"Larva";476;1
"Unit";"Zergling";"Larva";476;1
"Unit";"Zergling";"Larva";476;1
"Unit";"Zergling";"Larva";476;1
"Unit";"Zergling";"Larva";476;1
"Unit";"Zergling";"Larva";476;1
"Unit";"Zergling";"Larva";476;1
"Unit";"Zergling";"Larva";476;1
"Unit";"Zergling";"Larva";476;1
"Unit";"Zergling";"Larva";476;1
"Unit";"Zergling";"Larva";476;1
"Building";"SporeCrawler";NA;476;0
"Building";"Spire";NA;409;0
"Unit";"Zergling";"Larva";500;1
"Unit";"Zergling";"Larva";500;1
"Unit";"Zergling";"Larva";500;1
"Unit";"Zergling";"Larva";500;1
"Unit";"Zergling";"Larva";500;1
"Unit";"Zergling";"Larva";500;1
"Unit";"Zergling";"Larva";500;1
"Unit";"Zergling";"Larva";500;1
"Unit";"Zergling";"Larva";500;1
"Unit";"Zergling";"Larva";500;1
"Unit";"Zergling";"Larva";500;1
"Unit";"Zergling";"Larva";500;1
"Unit";"Zergling";"Larva";500;1
"Unit";"Zergling";"Larva";500;1
"Building";"CreepTumor";NA;500;0
"Building";"CreepTumor";NA;500;0
"Building";"CreepTumor";NA;500;0
"Building";"CreepTumor";NA;500;0
"Building";"CreepTumor";NA;500;0
"Building";"CreepTumor";NA;500;0
"Unit";"Corruptor";"Larva";500;2
"Unit";"Corruptor";"Larva";500;2
"Unit";"Corruptor";"Larva";500;2
"Unit";"Corruptor";"Larva";500;2
"Unit";"Corruptor";"Larva";500;2
"Unit";"Corruptor";"Larva";500;2
"Unit";"Corruptor";"Larva";500;2
"Unit";"Corruptor";"Larva";500;2
"Unit";"Corruptor";"Larva";500;2
"Unit";"Baneling";"Zergling";514;0
"Unit";"Baneling";"Zergling";514;0
"Unit";"Corruptor";"Larva";514;2
"Unit";"Corruptor";"Larva";514;2
"Unit";"Corruptor";"Larva";514;2
"Unit";"Zergling";"Larva";535;1
"Unit";"Zergling";"Larva";535;1
"Unit";"Zergling";"Larva";535;1
"Unit";"Zergling";"Larva";535;1
"Unit";"Corruptor";"Larva";532;2
"Unit";"Corruptor";"Larva";532;2
"Upgrade";"ZergMeleeWeaponsLevel3";"EvolutionChamber";440;0
"Unit";"Zergling";"Larva";541;1
"Unit";"Zergling";"Larva";541;1
"Unit";"Zergling";"Larva";541;1
"Unit";"Zergling";"Larva";541;1
"Unit";"Zergling";"Larva";541;1
"Unit";"Zergling";"Larva";541;1
"Unit";"Zergling";"Larva";541;1
"Unit";"Zergling";"Larva";541;1
"Unit";"Zergling";"Larva";541;1
"Unit";"Zergling";"Larva";541;1
"Unit";"Zergling";"Larva";541;1
"Unit";"Zergling";"Larva";541;1
"Unit";"Zergling";"Larva";541;1
"Unit";"Zergling";"Larva";541;1
"Unit";"Zergling";"Larva";541;1
"Unit";"Zergling";"Larva";541;1
"Unit";"Zergling";"Larva";541;1
"Unit";"Zergling";"Larva";541;1
"Unit";"Zergling";"Larva";541;1
"Unit";"Zergling";"Larva";541;1
"Unit";"Zergling";"Larva";541;1
"Unit";"Zergling";"Larva";541;1
"Unit";"Zergling";"Larva";541;1
"Unit";"Zergling";"Larva";541;1
"Unit";"Zergling";"Larva";541;1
"Unit";"Zergling";"Larva";541;1
"Unit";"Zergling";"Larva";541;1
"Unit";"Zergling";"Larva";541;1
"Unit";"Zergling";"Larva";541;1
"Unit";"Zergling";"Larva";541;1
"Unit";"Zergling";"Larva";541;1
"Unit";"Zergling";"Larva";541;1
"Unit";"Zergling";"Larva";541;1
"Unit";"Zergling";"Larva";541;1
"Unit";"Zergling";"Larva";541;1
"Unit";"Zergling";"Larva";541;1
"Unit";"Zergling";"Larva";549;1
"Unit";"Zergling";"Larva";549;1
"Unit";"Zergling";"Larva";549;1
"Unit";"Zergling";"Larva";549;1
"Unit";"Zergling";"Larva";549;1
"Unit";"Zergling";"Larva";549;1
"Unit";"Zergling";"Larva";549;1
"Unit";"Zergling";"Larva";549;1
"Unit";"Zergling";"Larva";549;1
"Unit";"Zergling";"Larva";549;1
"Unit";"Zergling";"Larva";549;1
"Unit";"Zergling";"Larva";549;1
"Unit";"Zergling";"Larva";549;1
"Unit";"Zergling";"Larva";549;1
"Unit";"Zergling";"Larva";549;1
"Unit";"Zergling";"Larva";549;1
"Unit";"Zergling";"Larva";549;1
"Unit";"Zergling";"Larva";549;1
"Unit";"Zergling";"Larva";549;1
"Unit";"Zergling";"Larva";549;1
"Unit";"Zergling";"Larva";549;1
"Unit";"Zergling";"Larva";549;1
"Unit";"Zergling";"Larva";549;1
"Unit";"Zergling";"Larva";549;1
"Unit";"Zergling";"Larva";549;1
"Unit";"Zergling";"Larva";549;1
"Unit";"Zergling";"Larva";549;1
"Unit";"Zergling";"Larva";549;1
"Unit";"Zergling";"Larva";549;1
"Unit";"Zergling";"Larva";549;1
"Unit";"Zergling";"Larva";549;1
"Unit";"Zergling";"Larva";549;1
"Unit";"Zergling";"Larva";549;1
"Unit";"Zergling";"Larva";549;1
"Building";"CreepTumor";NA;551;0
"Unit";"Zergling";"Larva";549;1
"Unit";"Zergling";"Larva";549;1
"Building";"CreepTumor";NA;585;0
"Unit";"Zergling";"Larva";549;1
"Unit";"Zergling";"Larva";549;1
"Unit";"Zergling";"Larva";549;1
"Unit";"Zergling";"Larva";549;1
"Unit";"Zergling";"Larva";549;1
"Unit";"Zergling";"Larva";549;1
"Unit";"Zergling";"Larva";549;1
"Unit";"Zergling";"Larva";549;1
"Unit";"Zergling";"Larva";549;1
"Unit";"Zergling";"Larva";549;1
"Unit";"Baneling";"Zergling";585;0
"Unit";"Baneling";"Zergling";585;0
"Unit";"Baneling";"Zergling";585;0
"Unit";"Baneling";"Zergling";585;0
"Unit";"Baneling";"Zergling";585;0
"Unit";"Baneling";"Zergling";585;0
"Unit";"Baneling";"Zergling";585;0
"Unit";"Baneling";"Zergling";585;0
"Unit";"Baneling";"Zergling";585;0
"Unit";"Baneling";"Zergling";585;0
"Unit";"Baneling";"Zergling";585;0
"Unit";"Baneling";"Zergling";585;0
"Unit";"Baneling";"Zergling";585;0
"Unit";"Baneling";"Zergling";585;0
"Unit";"Baneling";"Zergling";585;0
"Unit";"Baneling";"Zergling";585;0
"Unit";"Baneling";"Zergling";631;0
"Unit";"Baneling";"Zergling";631;0
"Unit";"Baneling";"Zergling";631;0
"Unit";"Baneling";"Zergling";631;0
"Unit";"Baneling";"Zergling";631;0
"Unit";"Baneling";"Zergling";631;0
"Unit";"Ultralisk";"Larva";631;6
"Unit";"Ultralisk";"Larva";631;6
"Unit";"Ultralisk";"Larva";631;6
"Unit";"Ultralisk";"Larva";631;6
"Unit";"Ultralisk";"Larva";631;6
"Building";"CreepTumorQueen";NA;661;0
"Building";"CreepTumorQueen";NA;661;0
"Unit";"Zergling";"Larva";661;1
"Unit";"Zergling";"Larva";661;1
"Unit";"Zergling";"Larva";661;1
"Unit";"Zergling";"Larva";661;1
"Unit";"Zergling";"Larva";661;1
"Unit";"Zergling";"Larva";661;1
"Unit";"Zergling";"Larva";661;1
"Unit";"Zergling";"Larva";661;1
"Unit";"Zergling";"Larva";661;1
"Unit";"Zergling";"Larva";661;1
"Unit";"Zergling";"Larva";661;1
"Unit";"Zergling";"Larva";661;1
"Unit";"Zergling";"Larva";661;1
"Unit";"Zergling";"Larva";661;1
"Unit";"Zergling";"Larva";661;1
"Unit";"Zergling";"Larva";661;1
"Unit";"Zergling";"Larva";661;1
"Unit";"Zergling";"Larva";661;1
"Unit";"Zergling";"Larva";661;1
"Unit";"Zergling";"Larva";661;1
"Unit";"Zergling";"Larva";661;1
"Unit";"Zergling";"Larva";661;1
"Unit";"Zergling";"Larva";661;1
"Unit";"Zergling";"Larva";661;1
"Unit";"Baneling";"Zergling";685;0
"Unit";"Baneling";"Zergling";685;0
"Unit";"Baneling";"Zergling";685;0
"Building";"CreepTumorQueen";NA;685;0
"Building";"CreepTumorQueen";NA;685;0
"Building";"CreepTumorQueen";NA;685;0
"Building";"CreepTumorQueen";NA;685;0
"Unit";"Baneling";"Zergling";685;0
"Unit";"Baneling";"Zergling";685;0
"Unit";"Baneling";"Zergling";685;0
"Unit";"Baneling";"Zergling";685;0
"Unit";"Baneling";"Zergling";685;0
"Unit";"Baneling";"Zergling";685;0
"Unit";"Baneling";"Zergling";685;0
"Unit";"Baneling";"Zergling";685;0
"Unit";"Baneling";"Zergling";685;0
"Unit";"Baneling";"Zergling";685;0
"Building";"CreepTumor";NA;685;0
"Building";"CreepTumor";NA;685;0
"Building";"CreepTumor";NA;685;0
"Building";"Hatchery";NA;661;0
"Building";"CreepTumor";NA;685;0
"Building";"CreepTumor";NA;685;0
"Building";"CreepTumor";NA;685;0
"Unit";"Zergling";"Larva";685;1
"Unit";"Zergling";"Larva";685;1
"Unit";"Zergling";"Larva";685;1
"Unit";"Zergling";"Larva";685;1
"Building";"CreepTumor";NA;685;0
"Building";"Hatchery";NA;685;0
"Building";"CreepTumor";NA;685;0
"Unit";"Baneling";"Zergling";685;0
"Unit";"Baneling";"Zergling";685;0
"Unit";"Baneling";"Zergling";685;0
"Unit";"Corruptor";"Larva";689;2
"Unit";"Corruptor";"Larva";689;2
"Unit";"Corruptor";"Larva";689;2
"Unit";"Baneling";"Zergling";695;0
"Unit";"Baneling";"Zergling";695;0
"Unit";"Baneling";"Zergling";695;0
"Unit";"Baneling";"Zergling";695;0
"Unit";"Baneling";"Zergling";695;0
"Unit";"Baneling";"Zergling";695;0
"Unit";"Corruptor";"Larva";689;2
"Unit";"Corruptor";"Larva";689;2
"Building";"CreepTumor";NA;695;0
"Building";"Hatchery";NA;689;0
"Unit";"Zergling";"Larva";699;1
"Unit";"Zergling";"Larva";699;1
"Unit";"Zergling";"Larva";699;1
"Unit";"Zergling";"Larva";699;1
"Building";"CreepTumor";NA;699;0
"Unit";"Corruptor";"Larva";699;2
"Unit";"Corruptor";"Larva";699;2
"Unit";"Zergling";"Larva";708;1
"Unit";"Zergling";"Larva";708;1
"Unit";"Zergling";"Larva";708;1
"Unit";"Zergling";"Larva";708;1
"Unit";"Zergling";"Larva";708;1
"Unit";"Zergling";"Larva";708;1
"Unit";"Zergling";"Larva";708;1
"Unit";"Zergling";"Larva";708;1
"Unit";"Zergling";"Larva";708;1
"Unit";"Zergling";"Larva";708;1
"Unit";"Zergling";"Larva";708;1
"Unit";"Zergling";"Larva";708;1
"Unit";"Zergling";"Larva";708;1
"Unit";"Zergling";"Larva";708;1
"Unit";"Zergling";"Larva";708;1
"Unit";"Zergling";"Larva";708;1
"Unit";"Zergling";"Larva";708;1
"Unit";"Zergling";"Larva";708;1
"Unit";"Zergling";"Larva";708;1
"Unit";"Zergling";"Larva";708;1
"Unit";"Zergling";"Larva";708;1
"Unit";"Zergling";"Larva";708;1
"Unit";"Zergling";"Larva";708;1
"Unit";"Zergling";"Larva";708;1
"Unit";"Zergling";"Larva";708;1
"Unit";"Zergling";"Larva";708;1
"Unit";"Zergling";"Larva";708;1
"Unit";"Zergling";"Larva";708;1
"Unit";"Zergling";"Larva";708;1
"Unit";"Zergling";"Larva";708;1
"Unit";"Zergling";"Larva";708;1
"Unit";"Zergling";"Larva";708;1
"Unit";"Zergling";"Larva";708;1
"Unit";"Zergling";"Larva";708;1
"Unit";"Zergling";"Larva";708;1
"Unit";"Zergling";"Larva";708;1
"Unit";"Zergling";"Larva";708;1
"Unit";"Zergling";"Larva";708;1
"Unit";"Zergling";"Larva";708;1
"Unit";"Zergling";"Larva";708;1
"Unit";"Zergling";"Larva";708;1
"Unit";"Zergling";"Larva";708;1
"Unit";"Zergling";"Larva";708;1
"Unit";"Zergling";"Larva";708;1
"Unit";"Baneling";"Zergling";752;0
"Unit";"Zergling";"Larva";752;1
"Unit";"Zergling";"Larva";752;1
"Unit";"Baneling";"Zergling";752;0
"Unit";"Baneling";"Zergling";752;0
"Unit";"Baneling";"Zergling";752;0
"Unit";"Baneling";"Zergling";752;0
"Unit";"Baneling";"Zergling";752;0
"Unit";"Zergling";"Larva";752;1
"Unit";"Zergling";"Larva";752;1
"Unit";"Zergling";"Larva";752;1
"Unit";"Zergling";"Larva";752;1
"Unit";"Zergling";"Larva";752;1
"Unit";"Zergling";"Larva";752;1
"Unit";"Zergling";"Larva";752;1
"Unit";"Zergling";"Larva";752;1
"Unit";"Zergling";"Larva";752;1
"Unit";"Zergling";"Larva";752;1
"Unit";"Zergling";"Larva";752;1
"Unit";"Zergling";"Larva";752;1
"Unit";"Zergling";"Larva";752;1
"Unit";"Zergling";"Larva";752;1
"Unit";"Zergling";"Larva";752;1
"Unit";"Zergling";"Larva";752;1
"Unit";"Zergling";"Larva";752;1
"Unit";"Zergling";"Larva";752;1
"Unit";"Zergling";"Larva";752;1
"Unit";"Zergling";"Larva";752;1
"Unit";"Baneling";"Zergling";752;0
"Unit";"Baneling";"Zergling";752;0
"Unit";"Baneling";"Zergling";752;0
"Unit";"Baneling";"Zergling";752;0
"Unit";"Baneling";"Zergling";752;0
"Building";"CreepTumor";NA;752;0
"Building";"CreepTumor";NA;774;0
"Building";"CreepTumor";NA;774;0
"Building";"CreepTumor";NA;774;0
"Unit";"Queen";"Hatchery";752;2
"Unit";"Zergling";"Larva";774;1
"Unit";"Zergling";"Larva";774;1
"Unit";"Zergling";"Larva";774;1
"Unit";"Zergling";"Larva";774;1
"Unit";"Zergling";"Larva";774;1
"Unit";"Zergling";"Larva";774;1
"Unit";"Zergling";"Larva";774;1
"Unit";"Zergling";"Larva";774;1
"Unit";"Zergling";"Larva";774;1
"Unit";"Zergling";"Larva";774;1
"Unit";"Zergling";"Larva";774;1
"Unit";"Zergling";"Larva";774;1
"Unit";"Zergling";"Larva";774;1
"Unit";"Zergling";"Larva";774;1
"Unit";"Zergling";"Larva";774;1
"Unit";"Zergling";"Larva";774;1
"Unit";"Zergling";"Larva";774;1
"Unit";"Zergling";"Larva";774;1
"Unit";"Zergling";"Larva";774;1
"Unit";"Zergling";"Larva";774;1
"Unit";"Zergling";"Larva";774;1
"Unit";"Zergling";"Larva";774;1
"Unit";"Zergling";"Larva";774;1
"Unit";"Zergling";"Larva";774;1
"Unit";"Zergling";"Larva";774;1
"Unit";"Zergling";"Larva";774;1
"Unit";"Zergling";"Larva";774;1
"Unit";"Zergling";"Larva";774;1
"Upgrade";"ZergGroundArmorsLevel3";"EvolutionChamber";699;0
"Unit";"Zergling";"Larva";776;1
"Unit";"Zergling";"Larva";776;1
"Unit";"Zergling";"Larva";778;1
"Unit";"Zergling";"Larva";778;1
"Unit";"Zergling";"Larva";778;1
"Unit";"Zergling";"Larva";778;1
"Unit";"Zergling";"Larva";782;1
"Unit";"Zergling";"Larva";782;1
"Unit";"Zergling";"Larva";782;1
"Unit";"Zergling";"Larva";782;1
"Unit";"Zergling";"Larva";786;1
"Unit";"Zergling";"Larva";786;1
"Unit";"Zergling";"Larva";786;1
"Unit";"Zergling";"Larva";786;1
"Unit";"Zergling";"Larva";790;1
"Unit";"Zergling";"Larva";790;1
"Unit";"Zergling";"Larva";790;1
"Unit";"Zergling";"Larva";790;1
"Unit";"Zergling";"Larva";790;1
"Unit";"Zergling";"Larva";790;1
"Unit";"Baneling";"Zergling";804;0
"Unit";"Baneling";"Zergling";804;0
"Unit";"Baneling";"Zergling";804;0
"Unit";"Baneling";"Zergling";804;0
"Unit";"Baneling";"Zergling";804;0
"Unit";"Baneling";"Zergling";804;0
"Unit";"Baneling";"Zergling";804;0
"Unit";"Baneling";"Zergling";804;0
"Unit";"Zergling";"Larva";824;1
"Unit";"Zergling";"Larva";824;1
"Unit";"Zergling";"Larva";824;1
"Unit";"Zergling";"Larva";824;1
"Unit";"Zergling";"Larva";824;1
"Unit";"Zergling";"Larva";824;1
"Unit";"Zergling";"Larva";824;1
"Unit";"Zergling";"Larva";824;1
"Unit";"Zergling";"Larva";824;1
"Unit";"Zergling";"Larva";824;1
"Unit";"Zergling";"Larva";824;1
"Unit";"Zergling";"Larva";824;1
"Unit";"Zergling";"Larva";824;1
"Unit";"Zergling";"Larva";824;1
"Unit";"Zergling";"Larva";824;1
"Unit";"Zergling";"Larva";824;1
"Unit";"Zergling";"Larva";824;1
"Unit";"Zergling";"Larva";824;1
"Unit";"Zergling";"Larva";824;1
"Unit";"Zergling";"Larva";824;1
"Unit";"Zergling";"Larva";824;1
"Unit";"Zergling";"Larva";824;1
"Building";"CreepTumor";NA;846;0
"Building";"CreepTumor";NA;846;0
"Building";"CreepTumor";NA;846;0
"Building";"CreepTumor";NA;846;0
"Unit";"Baneling";"Zergling";846;0
"Unit";"Baneling";"Zergling";846;0
"Unit";"Baneling";"Zergling";846;0
"Unit";"Baneling";"Zergling";846;0
"Unit";"Baneling";"Zergling";846;0
"Unit";"Baneling";"Zergling";846;0
"Unit";"Baneling";"Zergling";846;0
"Building";"CreepTumor";NA;846;0
"Unit";"Corruptor";"Larva";846;2
"Unit";"Corruptor";"Larva";846;2
"Unit";"Corruptor";"Larva";846;2
"Unit";"Corruptor";"Larva";846;2
"Unit";"Baneling";"Zergling";846;0
"Unit";"Baneling";"Zergling";846;0
"Unit";"Baneling";"Zergling";846;0
"Unit";"Baneling";"Zergling";846;0
"Unit";"Baneling";"Zergling";846;0
"Unit";"Baneling";"Zergling";846;0
"Unit";"Baneling";"Zergling";846;0
"Building";"Hatchery";NA;846;0
"Building";"CreepTumor";NA;846;0
"Building";"CreepTumor";NA;846;0
"Building";"CreepTumor";NA;846;0
"Unit";"Baneling";"Zergling";855;0
"Unit";"Baneling";"Zergling";855;0
"Unit";"Baneling";"Zergling";855;0
"Unit";"Baneling";"Zergling";855;0
"Unit";"Baneling";"Zergling";855;0
"Building";"CreepTumor";NA;855;0
"Building";"CreepTumor";NA;855;0
"Unit";"Zergling";"Larva";855;1
"Unit";"Zergling";"Larva";855;1
"Unit";"Zergling";"Larva";855;1
"Unit";"Zergling";"Larva";855;1
"Unit";"Zergling";"Larva";855;1
"Unit";"Zergling";"Larva";855;1
"Unit";"Zergling";"Larva";855;1
"Unit";"Zergling";"Larva";855;1
"Unit";"Zergling";"Larva";855;1
"Unit";"Zergling";"Larva";855;1
"Unit";"Zergling";"Larva";855;1
"Unit";"Zergling";"Larva";855;1
"Unit";"Zergling";"Larva";855;1
"Unit";"Zergling";"Larva";855;1
"Unit";"Zergling";"Larva";855;1
"Unit";"Zergling";"Larva";855;1
"Unit";"Zergling";"Larva";855;1
"Unit";"Zergling";"Larva";855;1
"Unit";"Zergling";"Larva";855;1
"Unit";"Zergling";"Larva";855;1
"Unit";"Zergling";"Larva";855;1
"Unit";"Zergling";"Larva";855;1
"Unit";"Zergling";"Larva";855;1
"Unit";"Zergling";"Larva";855;1
"Unit";"Zergling";"Larva";855;1
"Unit";"Zergling";"Larva";855;1
"Unit";"Zergling";"Larva";855;1
"Unit";"Zergling";"Larva";855;1
