"Type";"UnitName";"OnBuilding";"TotalSupply";"Supply"
"Unit";"SCV";"Command Center";12;1
"Unit";"SCV";"Command Center";12;1
"Unit";"SCV";"Command Center";13;1
"Building";"SupplyDepot";NA;13;0
"Unit";"SCV";"Command Center";15;1
"Unit";"SCV";"Command Center";15;1
"Building";"Refinery";NA;16;0
"Unit";"SCV";"Command Center";16;1
"Unit";"SCV";"Command Center";17;1
"Building";"Barracks";NA;15;0
"Unit";"SCV";"Command Center";19;1
"Unit";"Reaper";"Barracks";19;1
"Unit";"SCV";"Command Center";19;1
"Unit";"Marine";"Barracks";20;1
"Building";"Refinery";NA;22;0
"Building";"SupplyDepot";NA;22;0
"Building";"Factory";NA;21;0
"Unit";"SCV";"Command Center";23;1
"Building";"BarracksReactor";NA;23;0
"Building";"CommandCenter";NA;19;0
"Unit";"SCV";"Command Center";23;1
"Unit";"SCV";"Command Center";24;1
"Unit";"Marine";"Barracks";24;1
"Unit";"Marine";"Barracks";24;1
"Unit";"SCV";"Command Center";25;1
"Building";"FactoryTechLab";NA;25;0
"Building";"Starport";NA;24;0
"Unit";"Marine";"Barracks";28;1
"Unit";"Marine";"Barracks";28;1
"Unit";"SCV";"Command Center";28;1
"Unit";"SCV";"Command Center";29;1
"Unit";"SCV";"Command Center";31;1
"Building";"SupplyDepot";NA;29;0
"Unit";"Marine";"Barracks";31;1
"Unit";"Marine";"Barracks";31;1
"Unit";"SCV";"Command Center";33;1
"Building";"FactoryTechLab";NA;32;0
"Unit";"SCV";"Command Center";33;1
"Unit";"SCV";"Command Center";36;1
"Unit";"Marine";"Barracks";37;1
"Building";"Refinery";NA;37;0
"Unit";"Marine";"Barracks";37;1
"Unit";"SCV";"Command Center";38;1
"Unit";"SCV";"Command Center";39;1
"Unit";"Raven";"Starport";33;2
"Unit";"SCV";"Command Center";41;1
"Unit";"SCV";"Command Center";42;1
"Building";"SupplyDepot";NA;39;0
"Building";"Barracks";NA;34;0
"Unit";"Marine";"Barracks";42;1
"Unit";"Marine";"Barracks";42;1
"Building";"Barracks";NA;37;0
"Unit";"SCV";"Command Center";45;1
"Unit";"SCV";"Command Center";47;1
"Building";"SupplyDepot";NA;47;0
"Unit";"Marine";"Barracks";49;1
"Unit";"Marine";"Barracks";49;1
"Unit";"Marine";"Barracks";50;1
"Unit";"Marine";"Barracks";50;1
"Unit";"SCV";"Command Center";51;1
"Unit";"SCV";"Command Center";51;1
"Building";"StarportReactor";NA;47;0
"Building";"SupplyDepot";NA;51;0
"Building";"SupplyDepot";NA;51;0
"Unit";"Marine";"Barracks";51;1
"Unit";"Marine";"Barracks";54;1
"Unit";"Marine";"Barracks";54;1
"Unit";"SCV";"Command Center";57;1
"Unit";"SCV";"Command Center";57;1
"Unit";"Marine";"Barracks";55;1
"Unit";"SCV";"Command Center";60;1
"Unit";"Marine";"Barracks";57;1
"Unit";"Marine";"Barracks";58;1
"Building";"SupplyDepot";NA;57;0
"Unit";"SCV";"Command Center";63;1
"Unit";"Medivac";"Starport";57;2
"Unit";"Medivac";"Starport";57;2
"Unit";"Marine";"Barracks";63;1
"Building";"Refinery";NA;62;0
"Unit";"Marine";"Barracks";63;1
"Building";"EngineeringBay";NA;63;0
"Unit";"Marine";"Barracks";64;1
"Unit";"SCV";"Command Center";66;1
"Unit";"Marine";"Barracks";66;1
"Unit";"SCV";"Command Center";72;1
"Unit";"Marine";"Barracks";73;1
"Unit";"SCV";"Command Center";76;1
"Unit";"Marine";"Barracks";73;1
"Unit";"SCV";"Command Center";77;1
"Unit";"Marine";"Barracks";76;1
"Unit";"SCV";"Command Center";78;1
"Building";"SupplyDepot";NA;77;0
"Building";"SupplyDepot";NA;77;0
"Building";"BarracksReactor";NA;73;0
"Unit";"Marine";"Barracks";77;1
"Building";"SupplyDepot";NA;80;0
"Unit";"SCV";"Command Center";83;1
"Unit";"Marine";"Barracks";83;1
"Unit";"Marine";"Barracks";83;1
"Unit";"Marine";"Barracks";83;1
"Building";"SupplyDepot";NA;84;0
"Building";"SupplyDepot";NA;84;0
"Unit";"Marine";"Barracks";85;1
"Unit";"Marine";"Barracks";85;1
"Unit";"Marine";"Barracks";87;1
"Unit";"Marine";"Barracks";88;1
"Unit";"Marine";"Barracks";88;1
"Unit";"SCV";"Command Center";91;1
"Unit";"Marine";"Barracks";88;1
"Unit";"Marine";"Barracks";88;1
"Unit";"Marine";"Barracks";90;1
"Unit";"Medivac";"Starport";88;2
"Unit";"Medivac";"Starport";88;2
"Unit";"Marine";"Barracks";91;1
"Unit";"Marine";"Barracks";92;1
"Unit";"Marine";"Barracks";94;1
"Unit";"Marine";"Barracks";94;1
"Unit";"Marine";"Barracks";96;1
"Unit";"SCV";"Command Center";101;1
"Unit";"SCV";"Command Center";101;1
"Unit";"SCV";"Command Center";106;1
"Upgrade";"TerranInfantryWeaponsLevel1";"EngineeringBay";85;0
"Building";"EngineeringBay";NA;108;0
"Unit";"Marine";"Barracks";109;1
"Unit";"Marine";"Barracks";109;1
"Unit";"Liberator";"Starport";101;3
"Unit";"Liberator";"Starport";101;3
"Unit";"SCV";"Command Center";117;1
"Unit";"SCV";"Command Center";117;1
"Unit";"Marine";"Barracks";114;1
"Unit";"Marine";"Barracks";114;1
"Unit";"Marine";"Barracks";114;1
"Unit";"Marine";"Barracks";114;1
"Building";"Armory";NA;108;0
"Building";"CommandCenter";NA;97;0
"Unit";"Marine";"Barracks";117;1
"Unit";"Marine";"Barracks";119;1
"Unit";"Marine";"Barracks";120;1
"Building";"Barracks";NA;109;0
"Building";"Barracks";NA;109;0
"Unit";"Marine";"Barracks";121;1
"Unit";"Marine";"Barracks";122;1
"Unit";"SCV";"Command Center";124;1
"Unit";"SCV";"Command Center";126;1
"Upgrade";"Stimpack";"TechLab";103;0
"Unit";"Marine";"Barracks";124;1
"Unit";"Marine";"Barracks";125;1
"Unit";"Marine";"Barracks";126;1
"Unit";"SCV";"Command Center";128;1
"Unit";"Marine";"Barracks";128;1
"Unit";"Marine";"Barracks";128;1
"Unit";"Marine";"Barracks";130;1
"Unit";"Liberator";"Starport";124;3
"Unit";"Liberator";"Starport";124;3
"Unit";"Marine";"Barracks";135;1
"Unit";"Marine";"Barracks";135;1
"Unit";"SCV";"Command Center";136;1
"Unit";"SCV";"Command Center";136;1
"Building";"BarracksReactor";NA;128;0
"Building";"Factory";NA;128;0
"Building";"BarracksReactor";NA;128;0
"Unit";"SCV";"Command Center";136;1
"Unit";"SCV";"Command Center";145;1
"Unit";"Marine";"Barracks";144;1
"Unit";"Marine";"Barracks";145;1
"Unit";"Marine";"Barracks";148;1
"Unit";"Marine";"Barracks";148;1
"Building";"FactoryTechLab";NA;148;0
"Unit";"Liberator";"Starport";137;3
"Unit";"Liberator";"Starport";140;3
"Unit";"Marine";"Barracks";159;1
"Building";"SupplyDepot";NA;159;0
"Building";"SupplyDepot";NA;159;0
"Building";"SupplyDepot";NA;159;0
"Building";"SupplyDepot";NA;159;0
"Unit";"Marine";"Barracks";159;1
"Unit";"Marine";"Barracks";159;1
"Unit";"Marine";"Barracks";159;1
"Unit";"Marine";"Barracks";160;1
"Unit";"Marine";"Barracks";160;1
"Unit";"Marine";"Barracks";160;1
"Unit";"Marine";"Barracks";160;1
"Unit";"Marine";"Barracks";160;1
"Unit";"Marine";"Barracks";160;1
"Upgrade";"TerranInfantryArmorsLevel1";"EngineeringBay";148;0
"Unit";"Medivac";"Starport";160;2
"Unit";"SCV";"Command Center";169;1
"Unit";"SCV";"Command Center";169;1
"Unit";"Marine";"Barracks";160;1
"Unit";"Marine";"Barracks";161;1
"Unit";"Marine";"Barracks";162;1
"Unit";"Marine";"Barracks";163;1
"Unit";"Marine";"Barracks";163;1
"Unit";"Marine";"Barracks";163;1
"Unit";"Marine";"Barracks";166;1
"Unit";"Marine";"Barracks";169;1
"Unit";"Marine";"Barracks";169;1
"Unit";"SCV";"Command Center";173;1
"Unit";"SCV";"Command Center";173;1
"Unit";"Marine";"Barracks";173;1
"Unit";"Marine";"Barracks";174;1
"Unit";"Marine";"Barracks";175;1
"Unit";"Marine";"Barracks";176;1
"Unit";"Marine";"Barracks";176;1
"Building";"Refinery";NA;176;0
"Building";"Refinery";NA;176;0
"Unit";"Medivac";"Starport";169;2
"Unit";"SCV";"Command Center";184;1
"Unit";"SCV";"Command Center";184;1
"Unit";"SCV";"Command Center";184;1
"Unit";"Marine";"Barracks";184;1
"Unit";"Marine";"Barracks";184;1
"Unit";"Marine";"Barracks";184;1
"Upgrade";"TerranInfantryWeaponsLevel2";"EngineeringBay";153;0
"Unit";"Marine";"Barracks";195;1
"Unit";"Marine";"Barracks";195;1
"Unit";"Marine";"Barracks";195;1
"Building";"Factory";NA;180;0
"Unit";"Marine";"Barracks";195;1
"Unit";"Marine";"Barracks";195;1
"Unit";"Marine";"Barracks";195;1
"Unit";"Marine";"Barracks";197;1
"Unit";"Marine";"Barracks";197;1
"Building";"Barracks";NA;180;0
"Unit";"Marine";"Barracks";197;1
"Unit";"Marine";"Barracks";203;1
"Unit";"Marine";"Barracks";203;1
"Unit";"Marine";"Barracks";203;1
"Unit";"Marine";"Barracks";203;1
"Unit";"Marine";"Barracks";203;1
"Unit";"Medivac";"Starport";203;2
"Unit";"Medivac";"Starport";203;2
"Unit";"Marine";"Barracks";211;1
"Unit";"Marine";"Barracks";211;1
"Unit";"Marine";"Barracks";211;1
"Unit";"SCV";"Command Center";215;1
"Unit";"SCV";"Command Center";215;1
"Unit";"SCV";"Command Center";215;1
"Unit";"Marine";"Barracks";215;1
"Unit";"Marine";"Barracks";215;1
"Unit";"Marine";"Barracks";215;1
"Unit";"Marine";"Barracks";215;1
"Building";"FactoryTechLab";NA;215;0
"Unit";"SCV";"Command Center";218;1
"Unit";"Marine";"Barracks";218;1
"Unit";"Marine";"Barracks";218;1
"Unit";"Marine";"Barracks";218;1
"Unit";"Marine";"Barracks";218;1
"Unit";"Marine";"Barracks";218;1
"Unit";"Marine";"Barracks";224;1
"Unit";"Marine";"Barracks";224;1
"Unit";"Marine";"Barracks";224;1
"Unit";"Medivac";"Starport";215;2
"Unit";"Medivac";"Starport";215;2
"Building";"Refinery";NA;224;0
"Unit";"Marine";"Barracks";226;1
"Unit";"Marine";"Barracks";226;1
"Unit";"Marine";"Barracks";226;1
"Upgrade";"TerranInfantryArmorsLevel2";"EngineeringBay";197;0
"Unit";"Marine";"Barracks";238;1
"Unit";"Marine";"Barracks";238;1
"Unit";"Marine";"Barracks";238;1
"Unit";"Marine";"Barracks";238;1
"Unit";"Marine";"Barracks";238;1
"Unit";"Marine";"Barracks";238;1
"Unit";"Marine";"Barracks";240;1
"Unit";"Marine";"Barracks";240;1
"Unit";"Marine";"Barracks";241;1
"Building";"SupplyDepot";NA;241;0
"Unit";"Marine";"Barracks";241;1
"Building";"BarracksReactor";NA;238;0
"Unit";"Marine";"Barracks";245;1
"Unit";"Marine";"Barracks";245;1
"Unit";"Marine";"Barracks";245;1
"Building";"CommandCenter";NA;215;0
"Building";"CommandCenter";NA;215;0
"Unit";"Medivac";"Starport";249;2
"Unit";"Marine";"Barracks";254;1
"Unit";"Marine";"Barracks";254;1
"Unit";"Marine";"Barracks";254;1
"Unit";"Marine";"Barracks";254;1
"Unit";"Marine";"Barracks";254;1
"Unit";"Marine";"Barracks";254;1
"Unit";"Marine";"Barracks";254;1
"Unit";"Marine";"Barracks";254;1
"Unit";"Hellion";"Factory";254;2
"Unit";"Marine";"Barracks";266;1
"Unit";"Marine";"Barracks";266;1
"Unit";"Marine";"Barracks";266;1
"Unit";"Marine";"Barracks";266;1
"Unit";"Marine";"Barracks";266;1
"Unit";"Marine";"Barracks";266;1
"Unit";"Marine";"Barracks";266;1
"Unit";"Marine";"Barracks";266;1
"Unit";"Marine";"Barracks";266;1
"Unit";"Marine";"Barracks";266;1
"Unit";"Marine";"Barracks";266;1
"Unit";"Marine";"Barracks";266;1
"Upgrade";"TerranVehicleWeaponsLevel1";"Armory";254;0
"Unit";"Marine";"Barracks";267;1
"Unit";"Marine";"Barracks";268;1
"Unit";"Marine";"Barracks";269;1
"Unit";"Marine";"Barracks";270;1
"Unit";"Marine";"Barracks";277;1
"Unit";"Marine";"Barracks";277;1
"Unit";"Marine";"Barracks";277;1
"Unit";"Marine";"Barracks";277;1
"Unit";"Medivac";"Starport";266;2
"Unit";"Medivac";"Starport";266;2
"Unit";"Marine";"Barracks";277;1
"Unit";"Marine";"Barracks";277;1
"Building";"MissileTurret";NA;277;0
"Building";"SensorTower";NA;277;0
"Unit";"Marine";"Barracks";292;1
"Unit";"Marine";"Barracks";292;1
"Unit";"Marine";"Barracks";292;1
"Unit";"Marine";"Barracks";292;1
"Unit";"Marine";"Barracks";292;1
"Unit";"Marine";"Barracks";292;1
"Unit";"Marine";"Barracks";295;1
"Unit";"Marine";"Barracks";296;1
"Unit";"Marine";"Barracks";296;1
"Unit";"Marine";"Barracks";296;1
"Unit";"Marine";"Barracks";296;1
