"type";"unit_name";"on_building";"total_supply";"supply"
"Building";"Refinery";NA;15;0
"Building";"Barracks";NA;15;0
"Building";"Barracks";NA;16;0
"Unit";"Reaper";"Barracks";18;1
"Building";"BarracksTechLab";NA;20;0
"Building";"BarracksTechLab";NA;20;0
"Unit";"Marauder";"Barracks";21;2
"Unit";"Marauder";"Barracks";21;2
"Unit";"Marauder";"Barracks";23;2
"Unit";"Marauder";"Barracks";27;2
"Unit";"Marauder";"Barracks";29;2
