"Type";"UnitName";"OnBuilding";"TotalSupply";"Supply"
"Unit";"SCV";"Command Center";12;1
"Unit";"SCV";"Command Center";12;1
"Unit";"SCV";"Command Center";13;1
"Building";"SupplyDepot";NA;13;0
"Unit";"SCV";"Command Center";15;1
"Unit";"SCV";"Command Center";15;1
"Building";"Refinery";NA;15;0
"Unit";"SCV";"Command Center";16;1
"Building";"Barracks";NA;15;0
"Unit";"SCV";"Command Center";17;1
"Unit";"Reaper";"Barracks";19;1
"Unit";"SCV";"Command Center";19;1
"Building";"SupplyDepot";NA;19;0
"Unit";"Marine";"Barracks";19;1
"Unit";"SCV";"Command Center";20;1
"Unit";"SCV";"Command Center";23;1
"Unit";"SCV";"Command Center";23;1
"Building";"CommandCenter";NA;19;0
"Building";"BarracksReactor";NA;23;0
"Building";"Factory";NA;21;0
"Unit";"SCV";"Command Center";25;1
"Unit";"SCV";"Command Center";25;1
"Unit";"Marine";"Barracks";25;1
"Unit";"SCV";"Command Center";26;1
"Unit";"Marine";"Barracks";26;1
"Unit";"Marine";"Barracks";27;1
"Unit";"SCV";"Command Center";28;1
"Unit";"SCV";"Command Center";30;1
"Unit";"Marine";"Barracks";29;1
"Unit";"SCV";"Command Center";31;1
"Unit";"SCV";"Command Center";32;1
"Unit";"Marine";"Barracks";32;1
"Building";"SupplyDepot";NA;31;0
"Building";"CommandCenter";NA;25;0
"Unit";"Marine";"Barracks";33;1
"Unit";"SCV";"Command Center";34;1
"Unit";"SCV";"Command Center";35;1
"Unit";"SCV";"Command Center";38;1
"Unit";"SCV";"Command Center";39;1
"Unit";"SCV";"Command Center";40;1
"Unit";"SCV";"Command Center";41;1
"Unit";"Marine";"Barracks";40;1
"Unit";"Marine";"Barracks";40;1
"Building";"FactoryTechLab";NA;41;0
"Unit";"SCV";"Command Center";42;1
"Unit";"SCV";"Command Center";42;1
"Unit";"SCV";"Command Center";43;1
"Building";"EngineeringBay";NA;41;0
"Building";"Barracks";NA;37;0
"Building";"Barracks";NA;37;0
"Unit";"SCV";"Command Center";46;1
"Building";"Refinery";NA;44;0
"Unit";"SCV";"Command Center";47;1
"Unit";"SCV";"Command Center";49;1
"Unit";"Marine";"Barracks";46;1
"Unit";"Marine";"Barracks";46;1
"Building";"Refinery";NA;44;0
"Building";"EngineeringBay";NA;46;0
"Unit";"SCV";"Command Center";49;1
"Unit";"SCV";"Command Center";50;1
"Building";"FactoryTechLab";NA;49;0
"Unit";"SCV";"Command Center";54;1
"Unit";"SCV";"Command Center";54;1
"Building";"BarracksTechLab";NA;54;0
"Unit";"Marine";"Barracks";54;1
"Building";"MissileTurret";NA;56;0
"Unit";"SCV";"Command Center";57;1
"Unit";"SCV";"Command Center";57;1
"Building";"Refinery";NA;56;0
"Building";"MissileTurret";NA;57;0
"Unit";"SCV";"Command Center";59;1
"Unit";"SCV";"Command Center";61;1
"Unit";"SCV";"Command Center";61;1
"Unit";"SCV";"Command Center";62;1
"Building";"SupplyDepot";NA;61;0
"Unit";"SCV";"Command Center";62;1
"Unit";"SCV";"Command Center";64;1
"Building";"SupplyDepot";NA;61;0
"Building";"FactoryReactor";NA;59;0
"Unit";"Marine";"Barracks";64;1
"Unit";"Marine";"Barracks";64;1
"Unit";"SCV";"Command Center";67;1
"Unit";"SCV";"Command Center";67;1
"Unit";"Marine";"Barracks";65;1
"Unit";"Marine";"Barracks";65;1
"Building";"Barracks";NA;61;0
"Building";"Starport";NA;62;0
"Building";"SupplyDepot";NA;67;0
"Building";"SupplyDepot";NA;67;0
"Unit";"SCV";"Command Center";69;1
"Unit";"Marine";"Barracks";69;1
"Unit";"Marine";"Barracks";69;1
"Unit";"SCV";"Command Center";73;1
"Building";"Barracks";NA;61;0
"Unit";"Marine";"Barracks";71;1
"Unit";"Marine";"Barracks";71;1
"Unit";"SCV";"Command Center";73;1
"Unit";"SCV";"Command Center";76;1
"Unit";"Marine";"Barracks";74;1
"Unit";"Marine";"Barracks";76;1
"Unit";"SCV";"Command Center";79;1
"Unit";"SCV";"Command Center";79;1
"Unit";"Marine";"Barracks";77;1
"Unit";"Marine";"Barracks";77;1
"Building";"MissileTurret";NA;79;0
"Unit";"SCV";"Command Center";80;1
"Building";"SupplyDepot";NA;77;0
"Building";"SupplyDepot";NA;79;0
"Building";"FactoryReactor";NA;73;0
"Unit";"SCV";"Command Center";83;1
"Unit";"SCV";"Command Center";84;1
"Unit";"Marine";"Barracks";81;1
"Upgrade";"TerranInfantryWeaponsLevel1";"EngineeringBay";62;0
"Unit";"Marine";"Barracks";82;1
"Unit";"SCV";"Command Center";87;1
"Building";"BarracksReactor";NA;79;0
"Upgrade";"Stimpack";"TechLab";62;0
"Unit";"Marine";"Barracks";87;1
"Unit";"Marine";"Barracks";87;1
"Unit";"SCV";"Command Center";88;1
"Unit";"SCV";"Command Center";89;1
"Building";"BarracksReactor";NA;80;0
"Unit";"SCV";"Command Center";92;1
"Unit";"Marine";"Barracks";90;1
"Unit";"Marine";"Barracks";91;1
"Unit";"SCV";"Command Center";95;1
"Building";"SupplyDepot";NA;92;0
"Building";"SupplyDepot";NA;93;0
"Unit";"SCV";"Command Center";99;1
"Unit";"SCV";"Command Center";99;1
"Unit";"Marine";"Barracks";98;1
"Unit";"Marine";"Barracks";98;1
"Unit";"Marine";"Barracks";98;1
"Unit";"SCV";"Command Center";100;1
"Building";"Refinery";NA;100;0
"Building";"Barracks";NA;88;0
"Building";"Barracks";NA;88;0
"Building";"Refinery";NA;101;0
"Unit";"Medivac";"Starport";97;2
"Unit";"Medivac";"Starport";97;2
"Building";"Barracks";NA;91;0
"Unit";"Marauder";"Barracks";101;2
"Unit";"Marauder";"Barracks";101;2
"Upgrade";"TerranInfantryArmorsLevel1";"EngineeringBay";77;0
"Building";"Armory";NA;93;0
"Unit";"Marine";"Barracks";107;1
"Unit";"Marine";"Barracks";107;1
"Unit";"Marine";"Barracks";107;1
"Unit";"Marine";"Barracks";107;1
"Unit";"Marine";"Barracks";107;1
"Building";"BarracksTechLab";NA;111;0
"Unit";"Marine";"Barracks";115;1
"Building";"BarracksReactor";NA;111;0
"Unit";"Marine";"Barracks";120;1
"Unit";"Marine";"Barracks";120;1
"Unit";"Marine";"Barracks";120;1
"Unit";"Marine";"Barracks";120;1
"Unit";"Marine";"Barracks";120;1
"Unit";"Marine";"Barracks";120;1
"Building";"MissileTurret";NA;120;0
"Building";"SupplyDepot";NA;120;0
"Building";"SupplyDepot";NA;120;0
"Unit";"Marine";"Barracks";120;1
"Unit";"Marauder";"Barracks";120;2
"Unit";"Marine";"Barracks";121;1
"Unit";"Marine";"Barracks";127;1
"Unit";"Marine";"Barracks";127;1
"Unit";"Marine";"Barracks";128;1
"Unit";"Marine";"Barracks";128;1
"Unit";"Marine";"Barracks";128;1
"Unit";"Marine";"Barracks";128;1
"Unit";"Marine";"Barracks";128;1
"Unit";"Marine";"Barracks";128;1
"Unit";"Marauder";"Barracks";128;2
"Unit";"Marauder";"Barracks";128;2
"Unit";"Marauder";"Barracks";128;2
"Unit";"Marine";"Barracks";130;1
"Unit";"Marine";"Barracks";131;1
"Unit";"Marine";"Barracks";131;1
"Unit";"Marine";"Barracks";133;1
"Unit";"Marine";"Barracks";134;1
"Unit";"Marauder";"Barracks";139;2
"Unit";"Marauder";"Barracks";141;2
"Unit";"Medivac";"Starport";133;2
"Unit";"Marine";"Barracks";145;1
"Unit";"Marine";"Barracks";145;1
"Unit";"Marine";"Barracks";145;1
"Unit";"Marine";"Barracks";145;1
"Unit";"Marauder";"Barracks";143;2
"Building";"CommandCenter";NA;120;0
"Unit";"Marine";"Barracks";146;1
"Unit";"Marauder";"Barracks";145;2
"Unit";"Marine";"Barracks";150;1
"Unit";"Marine";"Barracks";150;1
"Unit";"Marine";"Barracks";150;1
"Unit";"Marine";"Barracks";152;1
"Unit";"Marine";"Barracks";156;1
"Unit";"Marauder";"Barracks";150;2
"Building";"Starport";NA;148;0
"Unit";"Marine";"Barracks";165;1
"Unit";"Marine";"Barracks";165;1
"Unit";"Medivac";"Starport";150;2
"Unit";"Medivac";"Starport";154;2
"Unit";"Marine";"Barracks";172;1
"Unit";"Marine";"Barracks";172;1
"Unit";"Marine";"Barracks";172;1
"Unit";"Marine";"Barracks";172;1
"Unit";"Marauder";"Barracks";170;2
"Unit";"Marauder";"Barracks";170;2
"Unit";"Marauder";"Barracks";172;2
"Unit";"Marine";"Barracks";178;1
"Unit";"Marine";"Barracks";178;1
"Unit";"Marine";"Barracks";178;1
"Unit";"Marauder";"Barracks";178;2
"Unit";"Medivac";"Starport";174;2
"Unit";"Medivac";"Starport";176;2
"Building";"SupplyDepot";NA;188;0
"Building";"SupplyDepot";NA;188;0
"Building";"SupplyDepot";NA;188;0
"Upgrade";"TerranInfantryArmorsLevel2";"EngineeringBay";133;0
"Building";"SupplyDepot";NA;188;0
"Unit";"Marine";"Barracks";191;1
"Unit";"Marine";"Barracks";191;1
"Unit";"Marine";"Barracks";191;1
"Unit";"Marine";"Barracks";191;1
"Unit";"Marine";"Barracks";191;1
"Upgrade";"TerranInfantryWeaponsLevel2";"EngineeringBay";145;0
"Unit";"Marine";"Barracks";197;1
"Unit";"Marine";"Barracks";197;1
"Unit";"Marine";"Barracks";197;1
"Unit";"Marauder";"Barracks";197;2
"Unit";"Marauder";"Barracks";197;2
"Unit";"Marauder";"Barracks";197;2
"Unit";"Marine";"Barracks";207;1
"Unit";"Marine";"Barracks";207;1
"Unit";"Marine";"Barracks";207;1
"Unit";"Marine";"Barracks";207;1
"Unit";"Marauder";"Barracks";207;2
"Unit";"Marauder";"Barracks";207;2
"Unit";"Marauder";"Barracks";207;2
"Unit";"Marine";"Barracks";211;1
"Unit";"Marine";"Barracks";211;1
"Unit";"Marine";"Barracks";211;1
"Unit";"Marine";"Barracks";211;1
"Unit";"Marauder";"Barracks";211;2
"Unit";"Marine";"Barracks";211;1
"Unit";"Marine";"Barracks";212;1
"Unit";"Marine";"Barracks";213;1
"Unit";"Marine";"Barracks";214;1
