"type";"unit_name";"on_building";"total_supply";"supply"
"Building";"Barracks";NA;14;0
"Building";"Refinery";NA;15;0
"Building";"Barracks";NA;14;0
"Unit";"Marine";"Barracks";16;1
"Unit";"Marine";"Barracks";17;1
"Unit";"Marine";"Barracks";17;1
"Building";"Bunker";NA;17;0
"Unit";"Marine";"Barracks";18;1
"Unit";"Marine";"Barracks";19;1
