"Type";"UnitName";"OnBuilding";"TotalSupply";"Supply"
"Unit";"SCV";"Command Center";12;1
"Building";"SupplyDepot";NA;12;0
"Unit";"SCV";"Command Center";12;1
"Unit";"SCV";"Command Center";13;1
"Building";"Refinery";NA;14;0
"Unit";"SCV";"Command Center";15;1
"Building";"Barracks";NA;13;0
"Unit";"Marine";"Barracks";16;1
"Building";"Barracks";NA;15;0
"Unit";"Marine";"Barracks";17;1
"Unit";"SCV";"Command Center";17;1
"Unit";"Marine";"Barracks";17;1
"Unit";"SCV";"Command Center";18;1
"Unit";"Marine";"Barracks";17;1
"Unit";"Marine";"Barracks";20;1
"Building";"SupplyDepot";NA;22;0
"Building";"SupplyDepot";NA;23;0
"Unit";"SCV";"Command Center";23;1
"Unit";"Marine";"Barracks";23;1
"Unit";"Marine";"Barracks";23;1
"Unit";"SCV";"Command Center";23;1
"Building";"Factory";NA;23;0
"Unit";"Marine";"Barracks";25;1
"Building";"Refinery";NA;24;0
"Unit";"SCV";"Command Center";27;1
"Unit";"Marine";"Barracks";26;1
"Building";"FactoryTechLab";NA;29;0
"Unit";"Marine";"Barracks";29;1
"Unit";"SCV";"Command Center";30;1
"Unit";"Marine";"Barracks";30;1
"Building";"SupplyDepot";NA;30;0
"Unit";"SCV";"Command Center";33;1
"Unit";"SCV";"Command Center";33;1
"Building";"SupplyDepot";NA;34;0
"Unit";"SCV";"Command Center";34;1
"Unit";"Marine";"Barracks";34;1
"Unit";"Marine";"Barracks";34;1
"Unit";"SCV";"Command Center";35;1
"Building";"SupplyDepot";NA;38;0
"Unit";"SCV";"Command Center";39;1
"Unit";"Marine";"Barracks";39;1
"Unit";"SCV";"Command Center";40;1
"Building";"Bunker";NA;39;0
"Building";"SupplyDepot";NA;40;0
"Unit";"Marine";"Barracks";40;1
"Unit";"SCV";"Command Center";42;1
"Unit";"SCV";"Command Center";43;1
"Unit";"Marine";"Barracks";44;1
"Unit";"Marine";"Barracks";44;1
"Unit";"SCV";"Command Center";45;1
"Unit";"SCV";"Command Center";47;1
"Unit";"Marine";"Barracks";47;1
"Unit";"Marine";"Barracks";47;1
"Building";"SupplyDepot";NA;47;0
"Building";"EngineeringBay";NA;47;0
"Unit";"SCV";"Command Center";48;1
"Unit";"Marine";"Barracks";51;1
"Unit";"Marine";"Barracks";51;1
"Building";"Starport";NA;48;0
"Unit";"SCV";"Command Center";52;1
"Building";"SupplyDepot";NA;54;0
"Unit";"SCV";"Command Center";55;1
"Unit";"Marine";"Barracks";55;1
"Unit";"Marine";"Barracks";55;1
"Unit";"SCV";"Command Center";56;1
"Unit";"Medivac";"Starport";55;2
"Unit";"Marine";"Barracks";61;1
"Unit";"Marine";"Barracks";61;1
"Building";"MissileTurret";NA;61;0
"Building";"MissileTurret";NA;61;0
"Building";"MissileTurret";NA;61;0
"Unit";"SCV";"Command Center";63;1
"Unit";"Marine";"Barracks";63;1
"Unit";"Marine";"Barracks";63;1
"Building";"MissileTurret";NA;64;0
"Unit";"SCV";"Command Center";66;1
"Building";"MissileTurret";NA;64;0
"Building";"SupplyDepot";NA;64;0
"Unit";"Marine";"Barracks";65;1
"Building";"Bunker";NA;64;0
"Unit";"SCV";"Command Center";66;1
"Unit";"SCV";"Command Center";68;1
"Unit";"Marine";"Barracks";69;1
"Unit";"SCV";"Command Center";70;1
"Unit";"Marine";"Barracks";69;1
"Building";"FactoryReactor";NA;69;0
"Building";"SupplyDepot";NA;70;0
"Unit";"SCV";"Command Center";72;1
"Building";"SupplyDepot";NA;70;0
"Unit";"Marine";"Barracks";73;1
"Unit";"Marine";"Barracks";73;1
"Unit";"SCV";"Command Center";74;1
"Unit";"Marine";"Barracks";75;1
"Unit";"Marine";"Barracks";77;1
"Unit";"Marine";"Barracks";77;1
"Unit";"SCV";"Command Center";77;1
"Building";"FactoryReactor";NA;75;0
"Unit";"Medivac";"Starport";77;2
"Unit";"Marine";"Barracks";78;1
"Unit";"SCV";"Command Center";80;1
"Unit";"Marine";"Barracks";81;1
"Unit";"Marine";"Barracks";81;1
"Unit";"SCV";"Command Center";84;1
"Unit";"Marine";"Barracks";84;1
"Unit";"SCV";"Command Center";88;1
"Unit";"Marine";"Barracks";88;1
"Unit";"Marine";"Barracks";88;1
"Building";"FactoryReactor";NA;84;0
"Building";"CommandCenter";NA;77;0
"Upgrade";"TerranInfantryWeaponsLevel1";"EngineeringBay";75;0
"Upgrade";"Stimpack";"TechLab";74;0
"Unit";"SCV";"Command Center";89;1
"Building";"MissileTurret";NA;89;0
"Unit";"Medivac";"Starport";88;2
"Unit";"Medivac";"Starport";88;2
"Unit";"Marine";"Barracks";89;1
"Unit";"Marine";"Barracks";98;1
"Unit";"Marine";"Barracks";98;1
"Unit";"SCV";"Command Center";98;1
"Unit";"Marine";"Barracks";98;1
"Building";"SupplyDepot";NA;98;0
"Building";"SupplyDepot";NA;101;0
"Unit";"Marine";"Barracks";102;1
"Unit";"Marine";"Barracks";102;1
"Unit";"Marine";"Barracks";102;1
"Unit";"Marine";"Barracks";105;1
"Unit";"Marine";"Barracks";105;1
"Unit";"Marauder";"Barracks";105;2
"Building";"Barracks";NA;102;0
"Building";"Barracks";NA;102;0
"Building";"SupplyDepot";NA;105;0
"Unit";"Marine";"Barracks";109;1
"Unit";"Marine";"Barracks";109;1
"Building";"BarracksTechLab";NA;109;0
"Unit";"Marauder";"Barracks";109;2
"Building";"Refinery";NA;109;0
"Building";"Refinery";NA;109;0
"Unit";"Marine";"Barracks";111;1
"Unit";"Marine";"Barracks";111;1
"Unit";"Marine";"Barracks";111;1
"Unit";"Marine";"Barracks";113;1
"Building";"FactoryReactor";NA;109;0
"Building";"Barracks";NA;107;0
"Unit";"Liberator";"Starport";109;3
"Unit";"Liberator";"Starport";109;3
"Unit";"Marauder";"Barracks";113;2
"Unit";"Marauder";"Barracks";113;2
"Unit";"Marine";"Barracks";117;1
"Unit";"Marine";"Barracks";117;1
"Unit";"Marine";"Barracks";117;1
"Unit";"Marine";"Barracks";117;1
"Building";"BarracksReactor";NA;117;0
"Building";"MissileTurret";NA;129;0
"Building";"Bunker";NA;128;0
"Unit";"Marine";"Barracks";131;1
"Unit";"Marine";"Barracks";131;1
"Unit";"Marine";"Barracks";131;1
"Unit";"Marauder";"Barracks";131;2
"Unit";"Marauder";"Barracks";131;2
"Upgrade";"TerranInfantryArmorsLevel1";"EngineeringBay";113;0
"Unit";"Marine";"Barracks";131;1
"Unit";"Marine";"Barracks";131;1
"Building";"SupplyDepot";NA;131;0
"Unit";"Liberator";"Starport";130;3
"Unit";"Liberator";"Starport";130;3
"Building";"CommandCenter";NA;117;0
"Building";"SupplyDepot";NA;140;0
"Building";"SupplyDepot";NA;140;0
"Building";"SupplyDepot";NA;146;0
"Unit";"Liberator";"Starport";146;3
"Unit";"Liberator";"Starport";146;3
"Unit";"Marine";"Barracks";146;1
"Unit";"Marine";"Barracks";146;1
"Unit";"Marine";"Barracks";146;1
"Unit";"Marine";"Barracks";146;1
"Unit";"Marine";"Barracks";146;1
"Unit";"Marine";"Barracks";146;1
"Unit";"Marauder";"Barracks";146;2
"Unit";"Marauder";"Barracks";146;2
"Unit";"Marauder";"Barracks";158;2
"Unit";"Marauder";"Barracks";160;2
"Unit";"Liberator";"Starport";146;3
"Unit";"Marine";"Barracks";162;1
"Unit";"Marine";"Barracks";162;1
"Unit";"Marine";"Barracks";162;1
"Unit";"Marine";"Barracks";162;1
"Unit";"Marine";"Barracks";162;1
"Unit";"Marine";"Barracks";162;1
"Unit";"Marine";"Barracks";166;1
"Unit";"Marauder";"Barracks";166;2
"Unit";"Marine";"Barracks";169;1
"Unit";"Marine";"Barracks";170;1
"Unit";"Marine";"Barracks";171;1
"Unit";"Marine";"Barracks";175;1
"Unit";"Marine";"Barracks";175;1
"Unit";"Marine";"Barracks";175;1
