"Type";"UnitName";"OnBuilding";"TotalSupply";"Supply"
"Unit";"SCV";"Command Center";12;1
"Unit";"SCV";"Command Center";12;1
"Unit";"SCV";"Command Center";13;1
"Building";"SupplyDepot";NA;13;0
"Unit";"SCV";"Command Center";15;1
"Unit";"SCV";"Command Center";15;1
"Building";"Refinery";NA;15;0
"Unit";"SCV";"Command Center";16;1
"Building";"Barracks";NA;15;0
"Unit";"SCV";"Command Center";17;1
"Unit";"Marine";"Barracks";19;1
"Building";"BarracksTechLab";NA;20;0
"Unit";"SCV";"Command Center";20;1
"Building";"SupplyDepot";NA;20;0
"Unit";"SCV";"Command Center";21;1
"Unit";"Marauder";"Barracks";20;2
"Unit";"SCV";"Command Center";21;1
"Unit";"Marauder";"Barracks";22;2
"Unit";"SCV";"Command Center";24;1
"Building";"CommandCenter";NA;19;0
"Unit";"SCV";"Command Center";27;1
"Unit";"Marine";"Barracks";25;1
"Unit";"SCV";"Command Center";28;1
"Building";"EngineeringBay";NA;27;0
"Building";"Barracks";NA;25;0
"Building";"Refinery";NA;29;0
"Unit";"Marine";"Barracks";30;1
"Building";"Barracks";NA;25;0
"Unit";"SCV";"Command Center";31;1
"Unit";"SCV";"Command Center";31;1
"Unit";"Marine";"Barracks";31;1
"Unit";"SCV";"Command Center";32;1
"Unit";"SCV";"Command Center";33;1
"Building";"BarracksTechLab";NA;34;0
"Unit";"SCV";"Command Center";35;1
"Unit";"SCV";"Command Center";37;1
"Unit";"Marauder";"Barracks";35;2
"Unit";"SCV";"Command Center";37;1
"Building";"BarracksReactor";NA;33;0
"Unit";"SCV";"Command Center";38;1
"Building";"SupplyDepot";NA;38;0
"Building";"SupplyDepot";NA;38;0
"Unit";"Marine";"Barracks";39;1
"Unit";"Marauder";"Barracks";41;2
"Building";"Refinery";NA;42;0
"Unit";"SCV";"Command Center";43;1
"Unit";"SCV";"Command Center";43;1
"Unit";"Marine";"Barracks";43;1
"Unit";"Marine";"Barracks";43;1
"Building";"Refinery";NA;43;0
"Building";"SupplyDepot";NA;43;0
"Unit";"SCV";"Command Center";46;1
"Unit";"SCV";"Command Center";46;1
"Building";"SupplyDepot";NA;43;0
"Unit";"Marauder";"Barracks";44;2
"Unit";"Marauder";"Barracks";46;2
"Unit";"SCV";"Command Center";50;1
"Unit";"SCV";"Command Center";50;1
"Unit";"Marine";"Barracks";50;1
"Unit";"Marine";"Barracks";50;1
"Unit";"Marine";"Barracks";54;1
"Upgrade";"TerranInfantryWeaponsLevel1";"EngineeringBay";37;0
"Unit";"Marine";"Barracks";54;1
"Unit";"SCV";"Command Center";60;1
"Unit";"SCV";"Command Center";60;1
"Unit";"Marine";"Barracks";58;1
"Unit";"Marine";"Barracks";59;1
"Building";"SupplyDepot";NA;58;0
"Unit";"SCV";"Command Center";62;1
"Unit";"SCV";"Command Center";63;1
"Unit";"Marine";"Barracks";60;1
"Building";"Factory";NA;54;0
"Unit";"SCV";"Command Center";66;1
"Unit";"SCV";"Command Center";67;1
"Unit";"Marine";"Barracks";66;1
"Building";"SupplyDepot";NA;64;0
"Unit";"Marine";"Barracks";66;1
"Building";"SupplyDepot";NA;66;0
"Unit";"Marauder";"Barracks";66;2
"Unit";"Marauder";"Barracks";69;2
"Unit";"Marine";"Barracks";73;1
"Unit";"Marine";"Barracks";73;1
"Unit";"Marauder";"Barracks";75;2
"Upgrade";"Stimpack";"TechLab";48;0
"Building";"FactoryReactor";NA;69;0
"Building";"Starport";NA;71;0
"Unit";"Marine";"Barracks";75;1
"Unit";"Marine";"Barracks";79;1
"Unit";"SCV";"Command Center";79;1
"Unit";"Marine";"Barracks";79;1
"Unit";"Marauder";"Barracks";79;2
"Building";"SupplyDepot";NA;81;0
"Building";"Barracks";NA;75;0
"Building";"SupplyDepot";NA;81;0
"Building";"Barracks";NA;75;0
"Unit";"Marine";"Barracks";82;1
"Unit";"SCV";"Command Center";85;1
"Unit";"Marauder";"Barracks";81;2
"Unit";"Marine";"Barracks";85;1
"Unit";"Marauder";"Barracks";85;2
"Unit";"Medivac";"Starport";85;2
"Unit";"Medivac";"Starport";85;2
"Unit";"Marine";"Barracks";87;1
"Building";"BarracksTechLab";NA;88;0
"Unit";"Marine";"Barracks";91;1
"Building";"FactoryReactor";NA;85;0
"Unit";"Marauder";"Barracks";89;2
"Building";"BarracksReactor";NA;87;0
"Building";"SupplyDepot";NA;92;0
"Building";"SupplyDepot";NA;92;0
"Upgrade";"TerranInfantryArmorsLevel1";"EngineeringBay";75;0
"Unit";"Marauder";"Barracks";92;2
"Unit";"Marine";"Barracks";98;1
"Unit";"Marine";"Barracks";99;1
"Unit";"Marauder";"Barracks";100;2
"Unit";"Medivac";"Starport";99;2
"Unit";"Medivac";"Starport";99;2
"Unit";"Marauder";"Barracks";102;2
"Unit";"Marine";"Barracks";104;1
"Unit";"Marine";"Barracks";105;1
"Unit";"Marine";"Barracks";105;1
"Unit";"Marauder";"Barracks";102;2
"Unit";"Marine";"Barracks";106;1
"Unit";"Marine";"Barracks";106;1
"Unit";"Marine";"Barracks";112;1
"Unit";"Marine";"Barracks";114;1
"Unit";"Marauder";"Barracks";117;2
"Unit";"Marauder";"Barracks";121;2
"Unit";"Marine";"Barracks";122;1
"Unit";"Marauder";"Barracks";121;2
"Unit";"Marine";"Barracks";123;1
"Unit";"Marine";"Barracks";125;1
"Unit";"Marine";"Barracks";125;1
"Unit";"Marauder";"Barracks";123;2
"Unit";"Marine";"Barracks";127;1
"Unit";"Marauder";"Barracks";125;2
"Unit";"Medivac";"Starport";125;2
"Unit";"Marauder";"Barracks";128;2
"Building";"CommandCenter";NA;106;0
"Unit";"Marauder";"Barracks";133;2
"Unit";"Marine";"Barracks";135;1
"Unit";"Marine";"Barracks";135;1
"Unit";"SCV";"Command Center";142;1
"Unit";"SCV";"Command Center";142;1
"Unit";"Marauder";"Barracks";136;2
"Unit";"Marauder";"Barracks";140;2
"Unit";"SCV";"Command Center";146;1
"Unit";"SCV";"Command Center";147;1
"Unit";"Marauder";"Barracks";142;2
"Unit";"Marine";"Barracks";150;1
"Unit";"Marine";"Barracks";150;1
"Unit";"Marauder";"Barracks";150;2
"Unit";"Marauder";"Barracks";150;2
"Unit";"SCV";"Command Center";156;1
"Unit";"SCV";"Command Center";156;1
"Unit";"SCV";"Command Center";162;1
"Unit";"SCV";"Command Center";163;1
"Unit";"Marine";"Barracks";158;1
"Unit";"Marauder";"Barracks";158;2
"Unit";"Marine";"Barracks";160;1
"Unit";"Marine";"Barracks";160;1
"Unit";"Marauder";"Barracks";158;2
"Unit";"Marine";"Barracks";164;1
"Unit";"Marine";"Barracks";166;1
"Unit";"Marine";"Barracks";169;1
"Unit";"Marine";"Barracks";173;1
"Unit";"Marauder";"Barracks";167;2
"Unit";"Marine";"Barracks";174;1
"Unit";"Marauder";"Barracks";174;2
"Unit";"Medivac";"Starport";171;2
"Unit";"Medivac";"Starport";171;2
"Unit";"Marine";"Barracks";174;1
"Unit";"Marauder";"Barracks";174;2
"Unit";"Marine";"Barracks";175;1
"Unit";"Marine";"Barracks";179;1
"Unit";"Marauder";"Barracks";177;2
"Unit";"Marine";"Barracks";179;1
"Unit";"Marauder";"Barracks";180;2
"Unit";"Marauder";"Barracks";187;2
"Unit";"Marine";"Barracks";193;1
"Unit";"Marine";"Barracks";193;1
"Unit";"Marauder";"Barracks";191;2
"Unit";"SCV";"Command Center";198;1
"Unit";"SCV";"Command Center";198;1
"Unit";"SCV";"Command Center";198;1
"Unit";"Marauder";"Barracks";194;2
"Unit";"Medivac";"Starport";193;2
"Unit";"Medivac";"Starport";193;2
"Unit";"Marauder";"Barracks";196;2
"Unit";"Marine";"Barracks";198;1
"Unit";"Marine";"Barracks";198;1
"Unit";"Marine";"Barracks";199;1
"Unit";"Marine";"Barracks";200;1
"Unit";"Marauder";"Barracks";202;2
"Building";"EngineeringBay";NA;202;0
"Building";"SupplyDepot";NA;202;0
"Building";"SupplyDepot";NA;205;0
"Unit";"Marauder";"Barracks";205;2
"Unit";"Marauder";"Barracks";211;2
"Unit";"Marine";"Barracks";217;1
"Building";"Armory";NA;202;0
"Unit";"Marauder";"Barracks";217;2
"Unit";"Marine";"Barracks";219;1
"Unit";"Marine";"Barracks";221;1
"Unit";"Marauder";"Barracks";219;2
"Unit";"Marauder";"Barracks";221;2
