"type";"unit_name";"on_building";"total_supply";"supply"
"Building";"Refinery";NA;15;0
"Building";"Barracks";NA;15;0
"Unit";"Reaper";"Barracks";18;1
"Building";"BarracksReactor";NA;20;0
"Building";"Refinery";NA;21;0
"Building";"Barracks";NA;20;0
"Building";"CommandCenter";NA;19;0
"Unit";"Marine";"Barracks";23;1
"Unit";"Marine";"Barracks";23;1
"Building";"BarracksTechLab";NA;23;0
"Unit";"Marine";"Barracks";24;1
"Unit";"Marine";"Barracks";25;1
"Building";"EngineeringBay";NA;24;0
"Unit";"Marauder";"Barracks";27;2
"Unit";"Marine";"Barracks";30;1
"Unit";"Marine";"Barracks";30;1
"Unit";"Marauder";"Barracks";30;2
"Unit";"Marine";"Barracks";33;1
"Unit";"Marine";"Barracks";37;1
"Unit";"Marauder";"Barracks";39;2
"Unit";"Marine";"Barracks";40;1
"Unit";"Marine";"Barracks";40;1
"Building";"Factory";NA;39;0
"Unit";"Marine";"Barracks";47;1
"Building";"Barracks";NA;40;0
"Unit";"Marauder";"Barracks";47;2
"Unit";"Marine";"Barracks";47;1
"Unit";"Marine";"Barracks";48;1
"Unit";"Marine";"Barracks";50;1
"Upgrade";"TerranInfantryWeaponsLevel1";"EngineeringBay";37;0
"Unit";"Marine";"Barracks";50;1
"Unit";"Marauder";"Barracks";50;2
"Building";"FactoryReactor";NA;47;0
"Building";"Starport";NA;47;0
"Unit";"Marine";"Barracks";53;1
"Building";"BarracksTechLab";NA;56;0
"Unit";"Marine";"Barracks";60;1
"Unit";"Marauder";"Barracks";60;2
"Building";"FactoryTechLab";NA;61;0
"Unit";"Marine";"Barracks";62;1
"Unit";"Marauder";"Barracks";62;2
"Unit";"Medivac";"Starport";61;2
"Unit";"Medivac";"Starport";61;2
"Unit";"Marine";"Barracks";64;1
"Building";"Refinery";NA;63;0
"Building";"Refinery";NA;63;0
"Unit";"Marine";"Barracks";65;1
"Upgrade";"Stimpack";"TechLab";47;0
"Unit";"Marine";"Barracks";68;1
"Unit";"Marine";"Barracks";69;1
"Unit";"Marine";"Barracks";76;1
"Unit";"Medivac";"Starport";72;2
"Unit";"Marine";"Barracks";81;1
"Unit";"Marine";"Barracks";81;1
"Unit";"Marine";"Barracks";82;1
"Unit";"Marine";"Barracks";84;1
"Unit";"Marine";"Barracks";86;1
"Unit";"Marauder";"Barracks";88;2
"Unit";"Marine";"Barracks";89;1
"Unit";"Marine";"Barracks";89;1
"Unit";"Marine";"Barracks";90;1
"Upgrade";"TerranInfantryArmorsLevel1";"EngineeringBay";67;0
"Unit";"Marine";"Barracks";93;1
"Unit";"Marauder";"Barracks";91;2
"Unit";"Marine";"Barracks";94;1
"Unit";"Medivac";"Starport";93;2
"Unit";"Medivac";"Starport";93;2
"Unit";"Marine";"Barracks";99;1
"Unit";"Marine";"Barracks";99;1
"Unit";"Marine";"Barracks";102;1
"Unit";"Marauder";"Barracks";102;2
"Building";"FactoryTechLab";NA;102;0
"Unit";"Marine";"Barracks";108;1
"Unit";"Marine";"Barracks";108;1
"Unit";"Marine";"Barracks";111;1
"Unit";"Marine";"Barracks";113;1
"Unit";"Marine";"Barracks";113;1
"Unit";"Liberator";"Starport";108;3
"Unit";"Liberator";"Starport";109;3
"Unit";"Marine";"Barracks";118;1
"Unit";"Marine";"Barracks";118;1
"Unit";"Marine";"Barracks";118;1
"Unit";"Marine";"Barracks";120;1
"Building";"CommandCenter";NA;102;0
"Building";"Barracks";NA;113;0
"Building";"MissileTurret";NA;129;0
"Building";"EngineeringBay";NA;120;0
"Unit";"Marine";"Barracks";129;1
"Unit";"Marine";"Barracks";129;1
"Unit";"Marauder";"Barracks";128;2
"Unit";"Marine";"Barracks";132;1
"Unit";"Marine";"Barracks";132;1
"Building";"Armory";NA;120;0
