"Type";"UnitName";"OnBuilding";"TotalSupply";"Supply"
"Unit";"SCV";"Command Center";12;1
"Unit";"SCV";"Command Center";12;1
"Unit";"SCV";"Command Center";13;1
"Building";"SupplyDepot";NA;13;0
"Unit";"SCV";"Command Center";15;1
"Unit";"SCV";"Command Center";15;1
"Building";"Refinery";NA;15;0
"Unit";"SCV";"Command Center";16;1
"Building";"Barracks";NA;15;0
"Unit";"SCV";"Command Center";17;1
"Unit";"Reaper";"Barracks";18;1
"Unit";"SCV";"Command Center";19;1
"Unit";"SCV";"Command Center";21;1
"Building";"SupplyDepot";NA;21;0
"Building";"BarracksReactor";NA;20;0
"Unit";"SCV";"Command Center";21;1
"Building";"Refinery";NA;21;0
"Building";"Barracks";NA;20;0
"Unit";"SCV";"Command Center";23;1
"Building";"CommandCenter";NA;19;0
"Unit";"Marine";"Barracks";23;1
"Unit";"Marine";"Barracks";23;1
"Unit";"SCV";"Command Center";23;1
"Building";"BarracksTechLab";NA;23;0
"Unit";"Marine";"Barracks";24;1
"Unit";"Marine";"Barracks";25;1
"Building";"EngineeringBay";NA;24;0
"Unit";"SCV";"Command Center";27;1
"Unit";"Marauder";"Barracks";27;2
"Unit";"SCV";"Command Center";29;1
"Unit";"Marine";"Barracks";30;1
"Unit";"Marine";"Barracks";30;1
"Unit";"SCV";"Command Center";32;1
"Unit";"SCV";"Command Center";33;1
"Unit";"Marauder";"Barracks";30;2
"Unit";"Marine";"Barracks";33;1
"Unit";"Marine";"Barracks";37;1
"Unit";"Marauder";"Barracks";39;2
"Unit";"Marine";"Barracks";40;1
"Unit";"SCV";"Command Center";41;1
"Unit";"SCV";"Command Center";41;1
"Unit";"Marine";"Barracks";40;1
"Building";"SupplyDepot";NA;41;0
"Building";"Factory";NA;39;0
"Unit";"Marine";"Barracks";47;1
"Building";"Barracks";NA;40;0
"Unit";"Marauder";"Barracks";47;2
"Unit";"Marine";"Barracks";47;1
"Unit";"SCV";"Command Center";48;1
"Unit";"SCV";"Command Center";48;1
"Unit";"Marine";"Barracks";48;1
"Unit";"Marine";"Barracks";50;1
"Unit";"SCV";"Command Center";51;1
"Upgrade";"TerranInfantryWeaponsLevel1";"EngineeringBay";37;0
"Building";"SupplyDepot";NA;48;0
"Unit";"Marine";"Barracks";50;1
"Building";"SupplyDepot";NA;50;0
"Unit";"Marauder";"Barracks";50;2
"Building";"FactoryReactor";NA;47;0
"Building";"Starport";NA;47;0
"Unit";"SCV";"Command Center";54;1
"Unit";"Marine";"Barracks";53;1
"Building";"SupplyDepot";NA;53;0
"Unit";"SCV";"Command Center";55;1
"Building";"BarracksTechLab";NA;56;0
"Unit";"SCV";"Command Center";60;1
"Unit";"SCV";"Command Center";61;1
"Unit";"Marine";"Barracks";60;1
"Unit";"Marauder";"Barracks";60;2
"Building";"FactoryTechLab";NA;61;0
"Unit";"Marine";"Barracks";62;1
"Building";"SupplyDepot";NA;62;0
"Unit";"SCV";"Command Center";67;1
"Unit";"Marauder";"Barracks";62;2
"Unit";"SCV";"Command Center";67;1
"Unit";"Medivac";"Starport";61;2
"Unit";"Medivac";"Starport";61;2
"Unit";"Marine";"Barracks";64;1
"Building";"Refinery";NA;63;0
"Building";"Refinery";NA;63;0
"Unit";"Marine";"Barracks";65;1
"Upgrade";"Stimpack";"TechLab";47;0
"Unit";"SCV";"Command Center";68;1
"Unit";"Marine";"Barracks";68;1
"Building";"SupplyDepot";NA;67;0
"Unit";"SCV";"Command Center";77;1
"Unit";"Marine";"Barracks";69;1
"Unit";"Marine";"Barracks";76;1
"Unit";"SCV";"Command Center";78;1
"Unit";"Medivac";"Starport";72;2
"Unit";"Marine";"Barracks";81;1
"Unit";"Marine";"Barracks";81;1
"Unit";"Marine";"Barracks";82;1
"Unit";"Marine";"Barracks";84;1
"Unit";"Marine";"Barracks";86;1
"Unit";"Marauder";"Barracks";88;2
"Unit";"Marine";"Barracks";89;1
"Unit";"Marine";"Barracks";89;1
"Unit";"Marine";"Barracks";90;1
"Unit";"SCV";"Command Center";93;1
"Unit";"SCV";"Command Center";93;1
"Upgrade";"TerranInfantryArmorsLevel1";"EngineeringBay";67;0
"Unit";"Marine";"Barracks";93;1
"Unit";"Marauder";"Barracks";91;2
"Unit";"Marine";"Barracks";94;1
"Unit";"Medivac";"Starport";93;2
"Unit";"Medivac";"Starport";93;2
"Unit";"Marine";"Barracks";99;1
"Unit";"Marine";"Barracks";99;1
"Unit";"SCV";"Command Center";102;1
"Unit";"SCV";"Command Center";102;1
"Unit";"Marine";"Barracks";102;1
"Unit";"Marauder";"Barracks";102;2
"Building";"FactoryTechLab";NA;102;0
"Unit";"Marine";"Barracks";108;1
"Unit";"Marine";"Barracks";108;1
"Unit";"Marine";"Barracks";111;1
"Unit";"SCV";"Command Center";113;1
"Unit";"SCV";"Command Center";113;1
"Unit";"Marine";"Barracks";113;1
"Unit";"Marine";"Barracks";113;1
"Building";"SupplyDepot";NA;115;0
"Unit";"Liberator";"Starport";108;3
"Unit";"Liberator";"Starport";109;3
"Unit";"Marine";"Barracks";118;1
"Unit";"Marine";"Barracks";118;1
"Unit";"Marine";"Barracks";118;1
"Unit";"Marine";"Barracks";120;1
"Building";"CommandCenter";NA;102;0
"Building";"Barracks";NA;113;0
"Building";"MissileTurret";NA;129;0
"Building";"EngineeringBay";NA;120;0
"Unit";"Marine";"Barracks";129;1
"Unit";"Marine";"Barracks";129;1
"Unit";"Marauder";"Barracks";128;2
"Unit";"SCV";"Command Center";130;1
"Unit";"SCV";"Command Center";130;1
"Unit";"Marine";"Barracks";132;1
"Unit";"Marine";"Barracks";132;1
"Building";"Armory";NA;120;0
