"type";"unit_name";"on_building";"total_supply";"supply"
"Building";"Refinery";NA;14;0
"Building";"Barracks";NA;15;0
"Unit";"Marine";"Barracks";19;1
"Building";"BarracksReactor";NA;20;0
"Building";"Factory";NA;19;0
"Unit";"Hellion";"Factory";22;2
"Unit";"Hellion";"Factory";22;2
"Building";"Refinery";NA;23;0
"Building";"CommandCenter";NA;21;0
"Unit";"Cyclone";"Factory";30;3
"Unit";"Cyclone";"Factory";30;3
"Unit";"Hellion";"Factory";31;2
"Unit";"Hellion";"Factory";37;2
"Building";"FactoryTechLab";NA;46;0
"Unit";"Marine";"Barracks";48;1
"Unit";"Marine";"Barracks";48;1
"Building";"Refinery";NA;48;0
"Building";"Refinery";NA;48;0
"Building";"Starport";NA;46;0
"Building";"Bunker";NA;48;0
"Building";"Barracks";NA;46;0
"Building";"Barracks";NA;46;0
"Building";"FactoryTechLab";NA;54;0
"Unit";"Marine";"Barracks";54;1
"Unit";"Marine";"Barracks";54;1
"Unit";"Marine";"Barracks";59;1
"Building";"CommandCenter";NA;46;0
"Unit";"Marine";"Barracks";60;1
"Unit";"Marine";"Barracks";60;1
"Unit";"Marine";"Barracks";60;1
"Building";"StarportReactor";NA;55;0
"Building";"FactoryTechLab";NA;60;0
"Building";"Barracks";NA;55;0
"Unit";"Marine";"Barracks";66;1
"Unit";"Marine";"Barracks";66;1
"Unit";"Marine";"Barracks";66;1
"Building";"Barracks";NA;56;0
"Unit";"Medivac";"Starport";68;2
"Unit";"Medivac";"Starport";68;2
"Unit";"Marine";"Barracks";73;1
"Unit";"Marine";"Barracks";73;1
"Unit";"Marine";"Barracks";73;1
"Building";"BarracksReactor";NA;71;0
"Building";"BarracksReactor";NA;72;0
"Unit";"Medivac";"Starport";80;2
"Unit";"Marine";"Barracks";86;1
"Unit";"Medivac";"Starport";81;2
"Unit";"Marine";"Barracks";87;1
"Unit";"Marine";"Barracks";89;1
"Unit";"Marine";"Barracks";89;1
"Unit";"Marine";"Barracks";89;1
"Unit";"Marine";"Barracks";89;1
"Unit";"Marine";"Barracks";89;1
"Upgrade";"Stimpack";"TechLab";68;0
"Unit";"Marine";"Barracks";105;1
"Unit";"Marine";"Barracks";105;1
"Unit";"Marine";"Barracks";105;1
"Unit";"Marine";"Barracks";105;1
"Unit";"Marine";"Barracks";105;1
"Unit";"Marine";"Barracks";105;1
"Unit";"Marine";"Barracks";106;1
"Unit";"Marine";"Barracks";106;1
"Unit";"Liberator";"Starport";97;3
"Unit";"Liberator";"Starport";99;3
"Building";"EngineeringBay";NA;106;0
"Building";"EngineeringBay";NA;106;0
"Building";"FactoryReactor";NA;106;0
"Unit";"Marine";"Barracks";122;1
"Unit";"Marine";"Barracks";122;1
"Unit";"Marine";"Barracks";122;1
"Unit";"Marine";"Barracks";122;1
"Unit";"Marine";"Barracks";122;1
"Unit";"Marine";"Barracks";122;1
"Building";"Barracks";NA;106;0
"Building";"Armory";NA;106;0
"Building";"Barracks";NA;106;0
"Unit";"Marine";"Barracks";122;1
"Unit";"Marine";"Barracks";122;1
"Unit";"Marine";"Barracks";122;1
"Unit";"Liberator";"Starport";122;3
"Unit";"Liberator";"Starport";122;3
"Unit";"Marine";"Barracks";128;1
"Unit";"Marine";"Barracks";128;1
"Unit";"Marine";"Barracks";128;1
"Unit";"Marine";"Barracks";128;1
"Unit";"Marine";"Barracks";130;1
"Unit";"Marine";"Barracks";130;1
"Unit";"Marauder";"Barracks";131;2
"Unit";"Marauder";"Barracks";131;2
"Unit";"Marine";"Barracks";131;1
"Unit";"Marine";"Barracks";131;1
"Unit";"Marine";"Barracks";137;1
"Unit";"Marauder";"Barracks";142;2
"Unit";"Marine";"Barracks";150;1
"Unit";"Marine";"Barracks";152;1
"Unit";"Marine";"Barracks";152;1
"Unit";"Marine";"Barracks";152;1
"Building";"BarracksTechLab";NA;152;0
"Unit";"Marauder";"Barracks";152;2
"Unit";"Marauder";"Barracks";152;2
"Unit";"Marauder";"Barracks";152;2
"Building";"GhostAcademy";NA;152;0
"Building";"Refinery";NA;153;0
"Building";"Refinery";NA;156;0
"Building";"Starport";NA;153;0
"Unit";"Liberator";"Starport";153;3
"Unit";"Liberator";"Starport";153;3
"Building";"MissileTurret";NA;164;0
"Building";"FusionCore";NA;153;0
"Unit";"Marine";"Barracks";164;1
"Unit";"Marine";"Barracks";164;1
"Upgrade";"TerranInfantryWeaponsLevel1";"EngineeringBay";150;0
"Unit";"Marine";"Barracks";164;1
"Upgrade";"TerranInfantryArmorsLevel1";"EngineeringBay";150;0
"Unit";"Marine";"Barracks";164;1
"Unit";"Marine";"Barracks";164;1
"Unit";"Marine";"Barracks";164;1
"Building";"StarportTechLab";NA;170;0
"Unit";"Medivac";"Starport";170;2
"Unit";"Medivac";"Starport";170;2
"Unit";"Marine";"Barracks";176;1
"Unit";"Marine";"Barracks";176;1
"Unit";"Marine";"Barracks";176;1
"Unit";"Marine";"Barracks";176;1
"Unit";"Marine";"Barracks";176;1
"Unit";"Marine";"Barracks";176;1
"Unit";"Marine";"Barracks";176;1
"Unit";"Marine";"Barracks";176;1
"Unit";"Marine";"Barracks";176;1
"Unit";"Marine";"Barracks";176;1
"Building";"MissileTurret";NA;176;0
"Unit";"Marine";"Barracks";186;1
"Unit";"Marine";"Barracks";186;1
"Unit";"Marine";"Barracks";186;1
"Unit";"Marine";"Barracks";186;1
"Unit";"Marine";"Barracks";186;1
"Unit";"Marine";"Barracks";189;1
"Unit";"Marine";"Barracks";190;1
"Upgrade";"TerranShipWeaponsLevel1";"Armory";164;0
"Unit";"Medivac";"Starport";186;2
"Unit";"Marine";"Barracks";194;1
"Unit";"Marine";"Barracks";194;1
"Unit";"Marine";"Barracks";197;1
"Unit";"Marine";"Barracks";197;1
"Unit";"Marine";"Barracks";197;1
"Unit";"Marine";"Barracks";197;1
"Unit";"Marine";"Barracks";197;1
"Unit";"Marine";"Barracks";197;1
"Unit";"Medivac";"Starport";194;2
"Building";"CommandCenter";NA;176;0
"Unit";"Liberator";"Starport";194;3
"Unit";"Marine";"Barracks";201;1
"Unit";"Marine";"Barracks";201;1
"Unit";"Marine";"Barracks";201;1
"Upgrade";"PersonalCloaking";"GhostAcademy";194;0
"Unit";"Liberator";"Starport";201;3
"Unit";"Liberator";"Starport";209;3
"Upgrade";"TerranInfantryWeaponsLevel2";"EngineeringBay";190;0
"Upgrade";"TerranInfantryArmorsLevel2";"EngineeringBay";190;0
