"Type";"UnitName";"OnBuilding";"TotalSupply";"Supply"
"Unit";"SCV";"Command Center";12;1
"Unit";"SCV";"Command Center";12;1
"Unit";"SCV";"Command Center";13;1
"Building";"SupplyDepot";NA;13;0
"Building";"Refinery";NA;14;0
"Unit";"SCV";"Command Center";15;1
"Unit";"SCV";"Command Center";16;1
"Unit";"SCV";"Command Center";16;1
"Unit";"SCV";"Command Center";17;1
"Building";"Barracks";NA;15;0
"Unit";"Reaper";"Barracks";19;1
"Unit";"SCV";"Command Center";19;1
"Unit";"SCV";"Command Center";21;1
"Building";"SupplyDepot";NA;20;0
"Unit";"SCV";"Command Center";21;1
"Building";"Refinery";NA;21;0
"Building";"Factory";NA;19;0
"Building";"BarracksReactor";NA;20;0
"Unit";"SCV";"Command Center";22;1
"Building";"CommandCenter";NA;19;0
"Unit";"SCV";"Command Center";23;1
"Unit";"Hellion";"Factory";23;2
"Unit";"Hellion";"Factory";23;2
"Unit";"SCV";"Command Center";24;1
"Building";"Starport";NA;23;0
"Building";"BarracksTechLab";NA;25;0
"Unit";"SCV";"Command Center";30;1
"Unit";"Hellion";"Factory";25;2
"Unit";"Hellion";"Factory";29;2
"Unit";"SCV";"Command Center";30;1
"Unit";"SCV";"Command Center";35;1
"Unit";"SCV";"Command Center";36;1
"Unit";"Hellion";"Factory";36;2
"Unit";"Hellion";"Factory";36;2
"Unit";"SCV";"Command Center";37;1
"Unit";"SCV";"Command Center";38;1
"Building";"SupplyDepot";NA;37;0
"Unit";"Banshee";"Starport";31;3
"Unit";"SCV";"Command Center";43;1
"Unit";"SCV";"Command Center";47;1
"Unit";"SCV";"Command Center";47;1
"Building";"SupplyDepot";NA;44;0
"Unit";"Cyclone";"Factory";47;3
"Unit";"Cyclone";"Factory";47;3
"Building";"SupplyDepot";NA;50;0
"Unit";"Banshee";"Starport";47;3
"Unit";"SCV";"Command Center";59;1
"Unit";"SCV";"Command Center";59;1
"Unit";"SCV";"Command Center";60;1
"Unit";"Marine";"Barracks";59;1
"Building";"FactoryReactor";NA;59;0
"Unit";"SCV";"Command Center";61;1
"Building";"StarportReactor";NA;59;0
"Building";"CommandCenter";NA;50;0
"Unit";"SCV";"Command Center";63;1
"Building";"Barracks";NA;59;0
"Building";"Barracks";NA;59;0
"Unit";"SCV";"Command Center";63;1
"Building";"SupplyDepot";NA;63;0
"Building";"EngineeringBay";NA;63;0
"Building";"EngineeringBay";NA;63;0
"Unit";"Marine";"Barracks";63;1
"Unit";"SCV";"Command Center";64;1
"Unit";"SCV";"Command Center";65;1
"Unit";"SCV";"Command Center";68;1
"Unit";"Marine";"Barracks";68;1
"Unit";"Marine";"Barracks";68;1
"Unit";"SCV";"Command Center";69;1
"Unit";"SCV";"Command Center";70;1
"Unit";"SCV";"Command Center";70;1
"Building";"Refinery";NA;69;0
"Building";"FactoryReactor";NA;68;0
"Unit";"SCV";"Command Center";72;1
"Building";"Refinery";NA;70;0
"Unit";"Marine";"Barracks";72;1
"Unit";"Marine";"Barracks";72;1
"Unit";"SCV";"Command Center";73;1
"Building";"StarportReactor";NA;69;0
"Unit";"Marine";"Barracks";72;1
"Unit";"Marine";"Barracks";73;1
"Unit";"Marine";"Barracks";73;1
"Building";"Barracks";NA;68;0
"Building";"Barracks";NA;68;0
"Unit";"SCV";"Command Center";82;1
"Unit";"Marine";"Barracks";76;1
"Unit";"SCV";"Command Center";82;1
"Unit";"SCV";"Command Center";82;1
"Unit";"Marine";"Barracks";79;1
"Building";"FactoryTechLab";NA;80;0
"Unit";"Marine";"Barracks";80;1
"Unit";"Marine";"Barracks";82;1
"Unit";"Marine";"Barracks";82;1
"Unit";"Marine";"Barracks";82;1
"Unit";"Marine";"Barracks";82;1
"Unit";"SCV";"Command Center";84;1
"Unit";"SCV";"Command Center";84;1
"Upgrade";"Stimpack";"TechLab";65;0
"Unit";"Marine";"Barracks";82;1
"Unit";"Marine";"Barracks";82;1
"Unit";"Marine";"Barracks";83;1
"Unit";"Marine";"Barracks";86;1
"Unit";"Marine";"Barracks";91;1
"Unit";"Marine";"Barracks";91;1
"Unit";"Marine";"Barracks";91;1
"Unit";"Marine";"Barracks";92;1
"Unit";"Marine";"Barracks";92;1
"Unit";"SCV";"Command Center";98;1
"Unit";"SCV";"Command Center";98;1
"Unit";"SCV";"Command Center";98;1
"Unit";"Marine";"Barracks";94;1
"Unit";"Marine";"Barracks";95;1
"Unit";"Marine";"Barracks";98;1
"Building";"Armory";NA;82;0
"Building";"Refinery";NA;98;0
"Unit";"SCV";"Command Center";108;1
"Unit";"SCV";"Command Center";108;1
"Unit";"SCV";"Command Center";108;1
"Building";"Refinery";NA;103;0
"Unit";"Marine";"Barracks";108;1
"Unit";"Marine";"Barracks";108;1
"Unit";"Marine";"Barracks";108;1
"Unit";"Marine";"Barracks";108;1
"Upgrade";"TerranInfantryWeaponsLevel1";"EngineeringBay";76;0
"Unit";"SCV";"Command Center";109;1
"Upgrade";"TerranInfantryArmorsLevel1";"EngineeringBay";79;0
"Building";"SupplyDepot";NA;109;0
"Building";"SupplyDepot";NA;109;0
"Building";"Factory";NA;98;0
"Building";"SupplyDepot";NA;112;0
"Unit";"SCV";"Command Center";117;1
"Unit";"SCV";"Command Center";117;1
"Unit";"SCV";"Command Center";117;1
"Unit";"Marine";"Barracks";117;1
"Unit";"Marine";"Barracks";117;1
"Building";"SupplyDepot";NA;117;0
"Unit";"SCV";"Command Center";117;1
"Unit";"SCV";"Command Center";118;1
"Unit";"SCV";"Command Center";118;1
"Building";"SupplyDepot";NA;117;0
"Building";"FactoryTechLab";NA;117;0
"Unit";"Medivac";"Starport";117;2
"Unit";"Medivac";"Starport";117;2
"Unit";"Marine";"Barracks";120;1
"Unit";"Marine";"Barracks";120;1
"Unit";"SCV";"Command Center";122;1
"Unit";"SCV";"Command Center";123;1
"Unit";"SCV";"Command Center";123;1
"Unit";"Marine";"Barracks";122;1
"Building";"SupplyDepot";NA;125;0
"Unit";"Marine";"Barracks";125;1
"Unit";"SCV";"Command Center";131;1
"Unit";"SCV";"Command Center";132;1
"Unit";"SCV";"Command Center";132;1
"Unit";"Marine";"Barracks";129;1
"Unit";"Marine";"Barracks";129;1
"Unit";"Marine";"Barracks";135;1
"Unit";"Marine";"Barracks";135;1
"Unit";"Marine";"Barracks";135;1
"Unit";"Marine";"Barracks";135;1
"Unit";"Marine";"Barracks";135;1
"Unit";"Marine";"Barracks";135;1
"Unit";"Medivac";"Starport";131;2
"Unit";"Marine";"Barracks";136;1
"Unit";"Marine";"Barracks";139;1
"Unit";"Medivac";"Starport";134;2
"Unit";"Marine";"Barracks";141;1
"Unit";"Marine";"Barracks";141;1
"Building";"SupplyDepot";NA;141;0
"Building";"SupplyDepot";NA;141;0
"Unit";"Marine";"Barracks";149;1
"Unit";"Marine";"Barracks";153;1
"Unit";"Marine";"Barracks";155;1
"Unit";"Marine";"Barracks";155;1
"Unit";"Marine";"Barracks";155;1
"Unit";"Marine";"Barracks";155;1
"Unit";"Marine";"Barracks";155;1
"Unit";"Marine";"Barracks";155;1
"Unit";"Marine";"Barracks";155;1
"Unit";"Marine";"Barracks";155;1
"Building";"SupplyDepot";NA;156;0
"Unit";"Marine";"Barracks";156;1
"Building";"SupplyDepot";NA;156;0
"Building";"SupplyDepot";NA;156;0
"Unit";"Marine";"Barracks";157;1
"Unit";"Marine";"Barracks";165;1
"Unit";"Marine";"Barracks";165;1
"Unit";"Marine";"Barracks";165;1
"Unit";"Marine";"Barracks";165;1
"Unit";"Marine";"Barracks";165;1
"Unit";"Marine";"Barracks";165;1
"Unit";"Marine";"Barracks";166;1
"Unit";"Marine";"Barracks";166;1
"Upgrade";"TerranVehicleWeaponsLevel1";"Armory";135;0
"Unit";"Marine";"Barracks";166;1
"Upgrade";"TerranInfantryWeaponsLevel2";"EngineeringBay";134;0
"Upgrade";"TerranInfantryArmorsLevel2";"EngineeringBay";134;0
"Unit";"Medivac";"Starport";165;2
"Unit";"Marine";"Barracks";167;1
"Unit";"Marine";"Barracks";167;1
"Unit";"Marine";"Barracks";167;1
"Unit";"Marine";"Barracks";167;1
"Unit";"Marine";"Barracks";175;1
"Unit";"Marine";"Barracks";175;1
"Unit";"Marine";"Barracks";175;1
"Building";"SupplyDepot";NA;175;0
"Building";"SupplyDepot";NA;175;0
"Unit";"Medivac";"Starport";167;2
