"Type";"UnitName";"OnBuilding";"TotalSupply";"Supply"
"Unit";"SCV";"Command Center";12;1
"Unit";"SCV";"Command Center";12;1
"Unit";"SCV";"Command Center";13;1
"Building";"SupplyDepot";NA;13;0
"Unit";"SCV";"Command Center";15;1
"Unit";"SCV";"Command Center";16;1
"Building";"Refinery";NA;15;0
"Unit";"SCV";"Command Center";16;1
"Unit";"SCV";"Command Center";17;1
"Building";"Barracks";NA;15;0
"Building";"Bunker";NA;19;0
"Unit";"Reaper";"Barracks";19;1
"Building";"SupplyDepot";NA;19;0
"Unit";"SCV";"Command Center";19;1
"Building";"Bunker";NA;19;0
"Unit";"Marine";"Barracks";19;1
"Building";"Refinery";NA;21;0
"Unit";"SCV";"Command Center";22;1
"Unit";"Marine";"Barracks";22;1
"Unit";"SCV";"Command Center";22;1
"Building";"Factory";NA;20;0
"Unit";"Marine";"Barracks";23;1
"Unit";"SCV";"Command Center";24;1
"Building";"SupplyDepot";NA;24;0
"Building";"FactoryTechLab";NA;25;0
"Unit";"SCV";"Command Center";26;1
"Unit";"Marine";"Barracks";27;1
"Unit";"SCV";"Command Center";28;1
"Unit";"Marine";"Barracks";29;1
"Unit";"SCV";"Command Center";30;1
"Building";"SupplyDepot";NA;29;0
"Building";"SupplyDepot";NA;30;0
"Unit";"SCV";"Command Center";32;1
"Building";"SupplyDepot";NA;32;0
"Unit";"SCV";"Command Center";33;1
"Building";"BarracksReactor";NA;32;0
"Unit";"SCV";"Command Center";34;1
"Unit";"SCV";"Command Center";35;1
"Unit";"Marine";"Barracks";34;1
"Unit";"Marine";"Barracks";34;1
"Unit";"SCV";"Command Center";35;1
"Building";"Starport";NA;34;0
"Unit";"SCV";"Command Center";38;1
"Building";"CommandCenter";NA;34;0
"Unit";"SCV";"Command Center";40;1
"Building";"BarracksTechLab";NA;40;0
"Unit";"SCV";"Command Center";40;1
"Unit";"Liberator";"Starport";40;3
"Unit";"Liberator";"Starport";40;3
"Unit";"SCV";"Command Center";41;1
"Building";"Barracks";NA;40;0
"Building";"Barracks";NA;40;0
"Unit";"SCV";"Command Center";48;1
"Building";"EngineeringBay";NA;42;0
"Building";"EngineeringBay";NA;42;0
"Unit";"SCV";"Command Center";49;1
"Unit";"SCV";"Command Center";49;1
"Unit";"SCV";"Command Center";50;1
"Building";"BarracksTechLab";NA;50;0
"Unit";"SCV";"Command Center";51;1
"Unit";"SCV";"Command Center";52;1
"Building";"SupplyDepot";NA;52;0
"Unit";"SCV";"Command Center";53;1
"Building";"Refinery";NA;52;0
"Building";"Refinery";NA;52;0
"Building";"BarracksReactor";NA;50;0
"Unit";"SCV";"Command Center";54;1
"Unit";"Marine";"Barracks";54;1
"Unit";"Marine";"Barracks";54;1
"Unit";"SCV";"Command Center";56;1
"Unit";"SCV";"Command Center";56;1
"Unit";"SCV";"Command Center";60;1
"Unit";"Marine";"Barracks";57;1
"Unit";"SCV";"Command Center";60;1
"Unit";"Marine";"Barracks";60;1
"Unit";"Marine";"Barracks";60;1
"Unit";"Marine";"Barracks";60;1
"Unit";"SCV";"Command Center";61;1
"Building";"SupplyDepot";NA;60;0
"Building";"Barracks";NA;55;0
"Unit";"SCV";"Command Center";63;1
"Building";"Barracks";NA;55;0
"Unit";"Marine";"Barracks";62;1
"Unit";"SCV";"Command Center";67;1
"Unit";"Medivac";"Starport";61;2
"Upgrade";"Stimpack";"TechLab";50;0
"Unit";"SCV";"Command Center";68;1
"Unit";"Marine";"Barracks";68;1
"Unit";"Marine";"Barracks";68;1
"Unit";"Marine";"Barracks";68;1
"Building";"SupplyDepot";NA;68;0
"Building";"MissileTurret";NA;69;0
"Unit";"Marine";"Barracks";69;1
"Building";"BarracksTechLab";NA;70;0
"Building";"MissileTurret";NA;70;0
"Unit";"Marine";"Barracks";74;1
"Unit";"Marine";"Barracks";75;1
"Unit";"Marine";"Barracks";76;1
"Building";"Armory";NA;67;0
"Unit";"Marine";"Barracks";77;1
"Building";"BarracksReactor";NA;70;0
"Unit";"Medivac";"Starport";73;2
"Building";"SupplyDepot";NA;78;0
"Unit";"Marine";"Barracks";78;1
"Unit";"Marine";"Barracks";79;1
"Unit";"Marauder";"Barracks";78;2
"Unit";"Marauder";"Barracks";80;2
"Upgrade";"TerranInfantryWeaponsLevel1";"EngineeringBay";60;0
"Unit";"Marine";"Barracks";82;1
"Unit";"Marine";"Barracks";84;1
"Unit";"Marine";"Barracks";84;1
"Unit";"Marine";"Barracks";84;1
"Unit";"Marine";"Barracks";85;1
"Unit";"Marine";"Barracks";86;1
"Unit";"Marine";"Barracks";88;1
"Building";"SupplyDepot";NA;88;0
"Unit";"Marine";"Barracks";90;1
"Unit";"Marine";"Barracks";91;1
"Upgrade";"TerranInfantryArmorsLevel1";"EngineeringBay";69;0
"Unit";"Marine";"Barracks";92;1
"Unit";"Marine";"Barracks";93;1
"Unit";"Marine";"Barracks";94;1
"Unit";"Marauder";"Barracks";97;2
"Unit";"Marauder";"Barracks";97;2
"Building";"SupplyDepot";NA;97;0
"Unit";"Marauder";"Barracks";97;2
"Unit";"Marine";"Barracks";98;1
"Unit";"Marine";"Barracks";99;1
"Unit";"Medivac";"Starport";97;2
"Building";"SupplyDepot";NA;99;0
"Building";"SupplyDepot";NA;100;0
"Unit";"Medivac";"Starport";98;2
"Unit";"Marine";"Barracks";109;1
"Unit";"Marine";"Barracks";109;1
"Unit";"Marauder";"Barracks";108;2
"Unit";"Marauder";"Barracks";108;2
"Unit";"Marauder";"Barracks";109;2
"Building";"SupplyDepot";NA;112;0
"Unit";"Marine";"Barracks";112;1
"Unit";"Marine";"Barracks";112;1
"Unit";"Marine";"Barracks";114;1
"Unit";"Marine";"Barracks";122;1
"Unit";"Marine";"Barracks";122;1
"Unit";"Marine";"Barracks";122;1
"Unit";"Marine";"Barracks";122;1
"Upgrade";"TerranVehicleWeaponsLevel1";"Armory";97;0
"Unit";"Marine";"Barracks";129;1
"Unit";"Marine";"Barracks";129;1
"Unit";"Marine";"Barracks";129;1
"Unit";"Marine";"Barracks";129;1
"Unit";"Marine";"Barracks";129;1
"Unit";"Marine";"Barracks";129;1
"Unit";"Medivac";"Starport";129;2
"Building";"MissileTurret";NA;129;0
"Building";"SupplyDepot";NA;129;0
"Building";"SupplyDepot";NA;129;0
"Building";"MissileTurret";NA;135;0
"Unit";"Marine";"Barracks";135;1
"Unit";"Marine";"Barracks";135;1
"Unit";"Marine";"Barracks";135;1
"Unit";"Marine";"Barracks";135;1
"Unit";"Marine";"Barracks";135;1
"Unit";"Marine";"Barracks";135;1
"Unit";"Marine";"Barracks";135;1
"Unit";"Marine";"Barracks";137;1
"Unit";"Marine";"Barracks";138;1
"Unit";"Medivac";"Starport";137;2
"Upgrade";"TerranInfantryWeaponsLevel2";"EngineeringBay";114;0
