"Type";"UnitName";"OnBuilding";"TotalSupply";"Supply"
"Unit";"SCV";"Command Center";12;1
"Unit";"SCV";"Command Center";12;1
"Unit";"SCV";"Command Center";13;1
"Building";"SupplyDepot";NA;13;0
"Unit";"SCV";"Command Center";15;1
"Unit";"SCV";"Command Center";15;1
"Building";"Refinery";NA;15;0
"Unit";"SCV";"Command Center";16;1
"Unit";"SCV";"Command Center";17;1
"Building";"Barracks";NA;15;0
"Unit";"Reaper";"Barracks";19;1
"Unit";"SCV";"Command Center";19;1
"Unit";"SCV";"Command Center";21;1
"Building";"Bunker";NA;19;0
"Building";"SupplyDepot";NA;20;0
"Unit";"Marine";"Barracks";21;1
"Unit";"SCV";"Command Center";22;1
"Unit";"Marine";"Barracks";23;1
"Unit";"SCV";"Command Center";23;1
"Building";"CommandCenter";NA;19;0
"Unit";"SCV";"Command Center";25;1
"Building";"Factory";NA;22;0
"Unit";"SCV";"Command Center";26;1
"Building";"Refinery";NA;26;0
"Unit";"SCV";"Command Center";27;1
"Building";"FactoryTechLab";NA;27;0
"Building";"BarracksReactor";NA;26;0
"Unit";"SCV";"Command Center";28;1
"Unit";"SCV";"Command Center";29;1
"Unit";"SCV";"Command Center";30;1
"Unit";"SCV";"Command Center";31;1
"Unit";"SCV";"Command Center";31;1
"Unit";"SCV";"Command Center";32;1
"Unit";"SCV";"Command Center";34;1
"Building";"Factory";NA;30;0
"Building";"SupplyDepot";NA;32;0
"Building";"SupplyDepot";NA;33;0
"Unit";"SCV";"Command Center";34;1
"Unit";"SCV";"Command Center";35;1
"Building";"Refinery";NA;34;0
"Unit";"SCV";"Command Center";36;1
"Unit";"SCV";"Command Center";37;1
"Building";"Refinery";NA;36;0
"Building";"CommandCenter";NA;30;0
"Unit";"SCV";"Command Center";38;1
"Building";"SupplyDepot";NA;38;0
"Unit";"SCV";"Command Center";39;1
"Building";"SupplyDepot";NA;39;0
"Unit";"SCV";"Command Center";40;1
"Building";"BarracksTechLab";NA;40;0
"Unit";"Hellion";"Factory";40;2
"Unit";"SCV";"Command Center";41;1
"Unit";"SCV";"Command Center";42;1
"Building";"SupplyDepot";NA;42;0
"Unit";"SCV";"Command Center";45;1
"Building";"SupplyDepot";NA;42;0
"Building";"SupplyDepot";NA;43;0
"Unit";"SCV";"Command Center";46;1
"Unit";"SCV";"Command Center";47;1
"Unit";"SCV";"Command Center";48;1
"Unit";"SCV";"Command Center";48;1
"Unit";"SCV";"Command Center";50;1
"Building";"SupplyDepot";NA;48;0
"Building";"Factory";NA;46;0
"Building";"Armory";NA;46;0
"Unit";"SCV";"Command Center";52;1
"Building";"Starport";NA;48;0
"Unit";"SCV";"Command Center";53;1
"Building";"SupplyDepot";NA;54;0
"Building";"EngineeringBay";NA;54;0
"Unit";"SCV";"Command Center";55;1
"Building";"SupplyDepot";NA;55;0
"Unit";"SCV";"Command Center";55;1
"Building";"BarracksReactor";NA;54;0
"Unit";"Thor";"Factory";54;6
"Unit";"Hellion";"Factory";55;2
"Unit";"Hellion";"Factory";56;2
"Building";"SupplyDepot";NA;67;0
"Building";"SupplyDepot";NA;67;0
"Unit";"Hellion";"Factory";67;2
"Unit";"SCV";"Command Center";67;1
"Unit";"Hellion";"Factory";67;2
"Unit";"SCV";"Command Center";67;1
"Unit";"SCV";"Command Center";67;1
"Unit";"SCV";"Command Center";69;1
"Unit";"SCV";"Command Center";72;1
"Unit";"SCV";"Command Center";73;1
"Upgrade";"TerranVehicleWeaponsLevel1";"Armory";56;0
"Unit";"Hellion";"Factory";67;2
"Unit";"Hellion";"Factory";69;2
"Building";"SensorTower";NA;74;0
"Unit";"SCV";"Command Center";74;1
"Building";"BarracksTechLab";NA;74;0
"Unit";"SCV";"Command Center";75;1
"Unit";"SCV";"Command Center";76;1
"Building";"MissileTurret";NA;74;0
"Building";"Refinery";NA;74;0
"Building";"MissileTurret";NA;75;0
"Building";"Refinery";NA;75;0
"Unit";"SCV";"Command Center";81;1
"Unit";"SCV";"Command Center";82;1
"Unit";"SCV";"Command Center";83;1
"Unit";"Hellion";"Factory";82;2
"Unit";"SCV";"Command Center";84;1
"Unit";"Hellion";"Factory";84;2
"Unit";"SCV";"Command Center";85;1
"Unit";"SCV";"Command Center";86;1
"Building";"SupplyDepot";NA;87;0
"Building";"SupplyDepot";NA;87;0
"Unit";"Hellion";"Factory";92;2
"Unit";"Hellion";"Factory";94;2
"Building";"MissileTurret";NA;94;0
"Building";"SupplyDepot";NA;94;0
"Building";"SupplyDepot";NA;94;0
"Building";"Armory";NA;87;0
"Unit";"Hellion";"Factory";94;2
"Unit";"Hellion";"Factory";96;2
"Building";"CommandCenter";NA;85;0
"Unit";"Hellion";"Factory";98;2
"Unit";"Hellion";"Factory";100;2
"Unit";"Hellion";"Factory";102;2
"Upgrade";"TerranVehicleAndShipArmorsLevel1";"Armory";94;0
"Unit";"Hellion";"Factory";102;2
"Unit";"Hellion";"Factory";104;2
"Unit";"Hellion";"Factory";106;2
"Unit";"Hellion";"Factory";108;2
"Unit";"Hellion";"Factory";108;2
"Unit";"Hellion";"Factory";110;2
"Unit";"Hellion";"Factory";112;2
"Unit";"SCV";"Command Center";116;1
"Building";"Factory";NA;108;0
"Unit";"Hellion";"Factory";114;2
"Building";"Factory";NA;108;0
"Unit";"Hellion";"Factory";118;2
"Unit";"Hellion";"Factory";120;2
"Building";"Refinery";NA;122;0
"Building";"Refinery";NA;123;0
"Unit";"Hellion";"Factory";123;2
"Unit";"Hellion";"Factory";125;2
"Unit";"Hellion";"Factory";125;2
"Unit";"SCV";"Command Center";135;1
"Unit";"Hellion";"Factory";133;2
"Building";"MissileTurret";NA;135;0
"Unit";"SCV";"Command Center";135;1
"Building";"Factory";NA;135;0
"Building";"MissileTurret";NA;139;0
"Building";"FactoryTechLab";NA;139;0
"Building";"FactoryTechLab";NA;139;0
"Unit";"Thor";"Factory";135;6
"Unit";"SCV";"Command Center";139;1
"Unit";"SCV";"Command Center";139;1
