"type";"unit_name";"on_building";"total_supply";"supply"
"Building";"Refinery";NA;14;0
"Building";"Barracks";NA;15;0
"Unit";"Reaper";"Barracks";19;1
"Building";"Factory";NA;19;0
"Building";"BarracksReactor";NA;20;0
"Building";"CommandCenter";NA;19;0
"Building";"Refinery";NA;25;0
"Unit";"Hellion";"Factory";25;2
"Building";"BarracksTechLab";NA;25;0
"Unit";"Hellion";"Factory";25;2
"Building";"Starport";NA;25;0
"Building";"CommandCenter";NA;24;0
"Unit";"Hellion";"Factory";32;2
"Unit";"Hellion";"Factory";32;2
"Building";"BarracksTechLab";NA;33;0
"Unit";"Marine";"Barracks";39;1
"Unit";"Marine";"Barracks";43;1
"Building";"StarportReactor";NA;41;0
"Building";"FactoryReactor";NA;41;0
"Building";"Barracks";NA;41;0
"Building";"EngineeringBay";NA;45;0
"Building";"EngineeringBay";NA;45;0
"Unit";"Marine";"Barracks";47;1
"Building";"Refinery";NA;45;0
"Building";"Refinery";NA;45;0
"Building";"Barracks";NA;42;0
"Unit";"Marine";"Barracks";56;1
"Unit";"Marine";"Barracks";56;1
"Unit";"Marine";"Barracks";56;1
"Unit";"Marine";"Barracks";56;1
"Unit";"Marine";"Barracks";56;1
"Unit";"Medivac";"Starport";56;2
"Unit";"Medivac";"Starport";56;2
"Upgrade";"Stimpack";"TechLab";45;0
"Unit";"Marine";"Barracks";65;1
"Unit";"Marine";"Barracks";65;1
"Unit";"Marine";"Barracks";65;1
"Unit";"Marine";"Barracks";65;1
"Unit";"Marine";"Barracks";65;1
"Unit";"Marine";"Barracks";80;1
"Unit";"Marine";"Barracks";80;1
"Unit";"Marine";"Barracks";80;1
"Building";"Armory";NA;67;0
"Building";"StarportReactor";NA;78;0
"Building";"Barracks";NA;73;0
"Unit";"Marine";"Barracks";87;1
"Unit";"Marine";"Barracks";87;1
"Unit";"Marine";"Barracks";87;1
"Unit";"Marine";"Barracks";87;1
"Unit";"Marine";"Barracks";87;1
"Building";"Barracks";NA;80;0
"Upgrade";"TerranInfantryWeaponsLevel1";"EngineeringBay";57;0
"Upgrade";"TerranInfantryArmorsLevel1";"EngineeringBay";57;0
"Unit";"Marine";"Barracks";96;1
"Unit";"Marine";"Barracks";96;1
"Unit";"Marine";"Barracks";96;1
"Unit";"Marine";"Barracks";96;1
"Unit";"Marine";"Barracks";96;1
"Unit";"Marine";"Barracks";96;1
"Unit";"Marine";"Barracks";96;1
"Unit";"Marine";"Barracks";105;1
"Unit";"Marine";"Barracks";105;1
"Unit";"Marine";"Barracks";105;1
"Unit";"Marine";"Barracks";105;1
"Unit";"Marine";"Barracks";105;1
"Unit";"Marine";"Barracks";106;1
"Building";"Refinery";NA;105;0
"Unit";"Marauder";"Barracks";105;2
"Building";"Refinery";NA;105;0
"Building";"BarracksReactor";NA;105;0
"Unit";"Marine";"Barracks";116;1
"Unit";"Marine";"Barracks";116;1
"Unit";"Marine";"Barracks";116;1
"Unit";"Marine";"Barracks";116;1
"Unit";"Marauder";"Barracks";116;2
"Unit";"Marine";"Barracks";116;1
"Unit";"Marine";"Barracks";116;1
"Unit";"Medivac";"Starport";113;2
"Unit";"Medivac";"Starport";113;2
"Unit";"Marine";"Barracks";121;1
"Unit";"Marine";"Barracks";121;1
"Unit";"Marine";"Barracks";121;1
"Unit";"Marine";"Barracks";121;1
"Unit";"Marine";"Barracks";121;1
"Unit";"Marine";"Barracks";121;1
"Unit";"Marine";"Barracks";125;1
"Unit";"Marine";"Barracks";125;1
"Unit";"Marauder";"Barracks";123;2
"Unit";"Medivac";"Starport";129;2
"Unit";"Medivac";"Starport";129;2
"Building";"Factory";NA;119;0
"Unit";"Marine";"Barracks";139;1
"Unit";"Marine";"Barracks";139;1
"Unit";"Marine";"Barracks";139;1
"Unit";"Marine";"Barracks";139;1
"Unit";"Marine";"Barracks";139;1
"Unit";"Marine";"Barracks";139;1
"Upgrade";"TerranVehicleWeaponsLevel1";"Armory";108;0
"Unit";"Marine";"Barracks";139;1
"Unit";"Marine";"Barracks";139;1
"Unit";"Marauder";"Barracks";139;2
"Unit";"Marine";"Barracks";153;1
"Unit";"Marine";"Barracks";153;1
"Unit";"Marine";"Barracks";153;1
"Unit";"Marine";"Barracks";153;1
"Unit";"Marine";"Barracks";153;1
"Unit";"Marine";"Barracks";153;1
"Unit";"Marine";"Barracks";153;1
"Building";"FactoryTechLab";NA;153;0
"Unit";"Marauder";"Barracks";153;2
"Unit";"Medivac";"Starport";143;2
"Unit";"Medivac";"Starport";143;2
"Upgrade";"TerranInfantryWeaponsLevel2";"EngineeringBay";116;0
"Upgrade";"TerranInfantryArmorsLevel2";"EngineeringBay";116;0
"Building";"CommandCenter";NA;137;0
"Building";"Barracks";NA;153;0
"Building";"Barracks";NA;153;0
"Building";"Barracks";NA;153;0
"Unit";"Marine";"Barracks";166;1
"Unit";"Marine";"Barracks";166;1
"Unit";"Marine";"Barracks";166;1
"Unit";"Marine";"Barracks";166;1
"Unit";"Marine";"Barracks";166;1
"Unit";"Marine";"Barracks";166;1
"Unit";"Marine";"Barracks";166;1
"Unit";"Marine";"Barracks";166;1
"Unit";"Marauder";"Barracks";166;2
"Unit";"Liberator";"Starport";166;3
"Unit";"Liberator";"Starport";166;3
"Unit";"Marine";"Barracks";166;1
"Unit";"Marine";"Barracks";182;1
"Unit";"Marine";"Barracks";182;1
"Unit";"Marine";"Barracks";183;1
"Unit";"Marine";"Barracks";183;1
"Unit";"Marine";"Barracks";183;1
"Unit";"Marine";"Barracks";183;1
"Unit";"Marine";"Barracks";183;1
"Unit";"Marine";"Barracks";183;1
"Unit";"Marauder";"Barracks";182;2
"Unit";"Marine";"Barracks";183;1
"Unit";"Marine";"Barracks";184;1
"Unit";"Marine";"Barracks";185;1
"Unit";"Marine";"Barracks";186;1
"Unit";"Marine";"Barracks";187;1
"Unit";"Marine";"Barracks";188;1
"Unit";"Marine";"Barracks";189;1
"Unit";"Marine";"Barracks";190;1
"Unit";"Marauder";"Barracks";191;2
"Unit";"Marine";"Barracks";193;1
"Unit";"Marine";"Barracks";194;1
"Unit";"Marine";"Barracks";195;1
"Unit";"Marine";"Barracks";196;1
"Unit";"Marine";"Barracks";203;1
"Unit";"Marauder";"Barracks";201;2
"Unit";"Liberator";"Starport";193;3
"Unit";"Liberator";"Starport";193;3
"Unit";"Marine";"Barracks";203;1
"Unit";"Marine";"Barracks";207;1
"Unit";"Marine";"Barracks";207;1
"Unit";"Marine";"Barracks";207;1
"Unit";"Marine";"Barracks";210;1
"Unit";"Marine";"Barracks";210;1
"Unit";"Marine";"Barracks";210;1
"Unit";"Marine";"Barracks";210;1
"Unit";"Marauder";"Barracks";208;2
"Building";"BarracksTechLab";NA;210;0
"Building";"BarracksTechLab";NA;210;0
"Building";"BarracksTechLab";NA;210;0
"Unit";"Marine";"Barracks";216;1
"Unit";"Marine";"Barracks";224;1
"Unit";"Marine";"Barracks";224;1
"Unit";"Marine";"Barracks";224;1
"Unit";"Marine";"Barracks";224;1
"Unit";"Marine";"Barracks";224;1
"Unit";"Marine";"Barracks";224;1
"Unit";"Marine";"Barracks";224;1
"Unit";"Marine";"Barracks";226;1
"Unit";"Marauder";"Barracks";224;2
"Upgrade";"TerranInfantryArmorsLevel3";"EngineeringBay";182;0
"Upgrade";"TerranInfantryWeaponsLevel3";"EngineeringBay";182;0
"Unit";"Marauder";"Barracks";227;2
"Unit";"Marauder";"Barracks";227;2
"Unit";"Marauder";"Barracks";227;2
"Unit";"Marine";"Barracks";227;1
"Unit";"Marine";"Barracks";228;1
"Unit";"Marine";"Barracks";237;1
"Unit";"Marine";"Barracks";237;1
"Unit";"Liberator";"Starport";224;3
"Unit";"Liberator";"Starport";224;3
"Unit";"Marauder";"Barracks";235;2
