"Type";"UnitName";"OnBuilding";"TotalSupply";"Supply"
"Unit";"SCV";"Command Center";12;1
"Unit";"SCV";"Command Center";12;1
"Unit";"SCV";"Command Center";13;1
"Building";"SupplyDepot";NA;13;0
"Building";"Refinery";NA;14;0
"Unit";"SCV";"Command Center";15;1
"Unit";"SCV";"Command Center";15;1
"Unit";"SCV";"Command Center";16;1
"Unit";"SCV";"Command Center";17;1
"Building";"Barracks";NA;15;0
"Unit";"Reaper";"Barracks";19;1
"Unit";"SCV";"Command Center";19;1
"Building";"SupplyDepot";NA;19;0
"Unit";"SCV";"Command Center";20;1
"Unit";"Marine";"Barracks";20;1
"Unit";"SCV";"Command Center";21;1
"Unit";"SCV";"Command Center";23;1
"Building";"Refinery";NA;23;0
"Building";"Factory";NA;21;0
"Unit";"SCV";"Command Center";25;1
"Building";"CommandCenter";NA;19;0
"Building";"BarracksReactor";NA;23;0
"Unit";"SCV";"Command Center";26;1
"Unit";"SCV";"Command Center";26;1
"Building";"BarracksTechLab";NA;26;0
"Unit";"Hellion";"Factory";26;2
"Unit";"Hellion";"Factory";26;2
"Building";"Starport";NA;26;0
"Unit";"SCV";"Command Center";27;1
"Unit";"SCV";"Command Center";28;1
"Unit";"SCV";"Command Center";32;1
"Unit";"Hellion";"Factory";32;2
"Unit";"Hellion";"Factory";32;2
"Unit";"SCV";"Command Center";34;1
"Unit";"SCV";"Command Center";40;1
"Building";"BarracksTechLab";NA;35;0
"Unit";"SCV";"Command Center";40;1
"Unit";"SCV";"Command Center";41;1
"Building";"SupplyDepot";NA;40;0
"Unit";"Banshee";"Starport";35;3
"Building";"Bunker";NA;41;0
"Unit";"SCV";"Command Center";43;1
"Unit";"SCV";"Command Center";43;1
"Building";"SupplyDepot";NA;43;0
"Unit";"Marine";"Barracks";43;1
"Unit";"Marine";"Barracks";43;1
"Unit";"SCV";"Command Center";46;1
"Unit";"SCV";"Command Center";48;1
"Building";"SupplyDepot";NA;46;0
"Unit";"SCV";"Command Center";50;1
"Building";"SupplyDepot";NA;48;0
"Unit";"Marine";"Barracks";50;1
"Unit";"Marine";"Barracks";50;1
"Unit";"SCV";"Command Center";51;1
"Unit";"Banshee";"Starport";43;3
"Unit";"SCV";"Command Center";52;1
"Unit";"SCV";"Command Center";55;1
"Unit";"SCV";"Command Center";59;1
"Unit";"SCV";"Command Center";61;1
"Unit";"Marine";"Barracks";59;1
"Unit";"Marine";"Barracks";60;1
"Unit";"SCV";"Command Center";61;1
"Unit";"SCV";"Command Center";62;1
"Building";"Refinery";NA;61;0
"Building";"Refinery";NA;61;0
"Unit";"SCV";"Command Center";65;1
"Unit";"SCV";"Command Center";66;1
"Unit";"SCV";"Command Center";67;1
"Building";"CommandCenter";NA;52;0
"Unit";"SCV";"Command Center";69;1
"Unit";"Banshee";"Starport";62;3
"Building";"BarracksTechLab";NA;69;0
"Unit";"SCV";"Command Center";69;1
"Unit";"SCV";"Command Center";74;1
"Building";"EngineeringBay";NA;70;0
"Building";"EngineeringBay";NA;70;0
"Unit";"SCV";"Command Center";75;1
"Unit";"Marine";"Barracks";75;1
"Unit";"SCV";"Command Center";75;1
"Building";"Barracks";NA;68;0
"Unit";"SCV";"Command Center";76;1
"Unit";"SCV";"Command Center";78;1
"Building";"StarportReactor";NA;75;0
"Unit";"Marine";"Barracks";79;1
"Unit";"SCV";"Command Center";80;1
"Unit";"SCV";"Command Center";81;1
"Unit";"Marine";"Barracks";81;1
"Unit";"Marine";"Barracks";81;1
"Unit";"Marine";"Barracks";81;1
"Building";"Barracks";NA;77;0
"Unit";"SCV";"Command Center";84;1
"Unit";"SCV";"Command Center";86;1
"Unit";"Marine";"Barracks";84;1
"Unit";"Marine";"Barracks";85;1
"Building";"SupplyDepot";NA;87;0
"Building";"SupplyDepot";NA;87;0
"Unit";"Medivac";"Starport";86;2
"Unit";"Medivac";"Starport";86;2
"Unit";"Marauder";"Barracks";88;2
"Unit";"Marauder";"Barracks";88;2
"Unit";"SCV";"Command Center";91;1
"Unit";"SCV";"Command Center";91;1
"Unit";"Marine";"Barracks";91;1
"Unit";"Marine";"Barracks";91;1
"Unit";"SCV";"Command Center";99;1
"Unit";"Marine";"Barracks";95;1
"Unit";"Marine";"Barracks";97;1
"Unit";"Marine";"Barracks";101;1
"Unit";"Marine";"Barracks";102;1
"Unit";"SCV";"Command Center";103;1
"Unit";"SCV";"Command Center";103;1
"Unit";"SCV";"Command Center";106;1
"Unit";"Medivac";"Starport";99;2
"Building";"Barracks";NA;91;0
"Upgrade";"Stimpack";"TechLab";81;0
"Unit";"Marauder";"Barracks";104;2
"Unit";"SCV";"Command Center";108;1
"Unit";"SCV";"Command Center";109;1
"Unit";"Marine";"Barracks";108;1
"Unit";"SCV";"Command Center";110;1
"Upgrade";"TerranInfantryWeaponsLevel1";"EngineeringBay";84;0
"Upgrade";"TerranInfantryArmorsLevel1";"EngineeringBay";84;0
"Unit";"Marauder";"Barracks";108;2
"Unit";"SCV";"Command Center";119;1
"Building";"SupplyDepot";NA;117;0
"Unit";"Marine";"Barracks";119;1
"Unit";"Marine";"Barracks";119;1
"Building";"SupplyDepot";NA;119;0
"Building";"BarracksReactor";NA;113;0
"Building";"Barracks";NA;108;0
"Building";"Barracks";NA;108;0
"Building";"Barracks";NA;108;0
"Unit";"Marine";"Barracks";121;1
"Unit";"Marine";"Barracks";121;1
"Unit";"Marine";"Barracks";122;1
"Building";"Barracks";NA;113;0
"Unit";"Marine";"Barracks";124;1
"Unit";"Marine";"Barracks";124;1
"Unit";"Marine";"Barracks";124;1
"Unit";"Marine";"Barracks";124;1
"Unit";"Marine";"Barracks";125;1
"Unit";"SCV";"Command Center";127;1
"Unit";"SCV";"Command Center";127;1
"Unit";"Marine";"Barracks";126;1
"Unit";"SCV";"Command Center";127;1
"Unit";"Marine";"Barracks";128;1
"Unit";"Marauder";"Barracks";127;2
"Unit";"Marine";"Barracks";129;1
"Unit";"SCV";"Command Center";132;1
"Unit";"Marine";"Barracks";130;1
"Unit";"SCV";"Command Center";133;1
"Unit";"SCV";"Command Center";135;1
"Unit";"Marauder";"Barracks";131;2
"Unit";"Marine";"Barracks";134;1
"Building";"BarracksReactor";NA;127;0
"Building";"BarracksReactor";NA;127;0
"Building";"BarracksReactor";NA;127;0
"Unit";"SCV";"Command Center";144;1
"Unit";"SCV";"Command Center";144;1
"Unit";"Marine";"Barracks";136;1
"Unit";"Marine";"Barracks";139;1
"Unit";"Marine";"Barracks";141;1
"Unit";"Marauder";"Barracks";136;2
"Unit";"Marine";"Barracks";144;1
"Unit";"Marine";"Barracks";146;1
"Building";"Armory";NA;130;0
"Unit";"Marine";"Barracks";149;1
"Unit";"Marine";"Barracks";149;1
"Unit";"Marine";"Barracks";149;1
"Unit";"Marine";"Barracks";149;1
"Unit";"Marine";"Barracks";149;1
"Unit";"Marine";"Barracks";150;1
"Unit";"Marine";"Barracks";151;1
"Unit";"Marine";"Barracks";152;1
"Unit";"Medivac";"Starport";147;2
"Unit";"Medivac";"Starport";147;2
"Unit";"Reaper";"Barracks";147;1
"Unit";"Reaper";"Barracks";147;1
"Building";"Refinery";NA;154;0
"Building";"Refinery";NA;154;0
"Unit";"Marine";"Barracks";156;1
"Unit";"Marauder";"Barracks";156;2
"Building";"SupplyDepot";NA;156;0
"Building";"SupplyDepot";NA;156;0
"Unit";"Marine";"Barracks";163;1
"Unit";"Marine";"Barracks";163;1
"Unit";"Marine";"Barracks";163;1
"Building";"BarracksReactor";NA;156;0
"Unit";"SCV";"Command Center";176;1
"Unit";"SCV";"Command Center";176;1
"Unit";"Marine";"Barracks";173;1
"Unit";"Marine";"Barracks";173;1
"Unit";"Marine";"Barracks";173;1
"Unit";"Marine";"Barracks";176;1
"Unit";"Marine";"Barracks";176;1
"Unit";"Marine";"Barracks";176;1
"Unit";"Marine";"Barracks";176;1
"Unit";"Marine";"Barracks";176;1
"Unit";"Marine";"Barracks";176;1
"Unit";"Marine";"Barracks";176;1
"Unit";"Marine";"Barracks";176;1
"Unit";"Marine";"Barracks";176;1
"Unit";"SCV";"Command Center";190;1
"Unit";"SCV";"Command Center";190;1
"Unit";"Marine";"Barracks";189;1
"Unit";"Marine";"Barracks";190;1
"Unit";"Marine";"Barracks";190;1
"Unit";"Marine";"Barracks";190;1
"Unit";"Marine";"Barracks";190;1
"Unit";"Marine";"Barracks";190;1
"Unit";"Marine";"Barracks";190;1
"Unit";"Marine";"Barracks";190;1
"Unit";"Marine";"Barracks";190;1
"Unit";"Marine";"Barracks";190;1
"Unit";"Marine";"Barracks";190;1
"Unit";"Marine";"Barracks";190;1
"Unit";"Marine";"Barracks";190;1
"Unit";"Marine";"Barracks";190;1
"Unit";"SCV";"Command Center";206;1
"Unit";"SCV";"Command Center";206;1
"Unit";"Marine";"Barracks";206;1
"Unit";"Marine";"Barracks";206;1
"Unit";"Marine";"Barracks";206;1
"Unit";"Marine";"Barracks";206;1
"Unit";"Marine";"Barracks";206;1
"Unit";"Marine";"Barracks";206;1
"Unit";"Marine";"Barracks";206;1
"Unit";"Marine";"Barracks";206;1
"Unit";"Marine";"Barracks";206;1
"Unit";"Marine";"Barracks";206;1
"Unit";"Marine";"Barracks";206;1
"Unit";"Marine";"Barracks";206;1
"Unit";"Marine";"Barracks";206;1
"Unit";"Marauder";"Barracks";206;2
"Unit";"Marine";"Barracks";208;1
"Unit";"Marine";"Barracks";209;1
"Unit";"Marine";"Barracks";223;1
"Unit";"Marine";"Barracks";223;1
"Unit";"Marine";"Barracks";223;1
"Unit";"Marine";"Barracks";223;1
"Unit";"Marine";"Barracks";223;1
"Unit";"Marine";"Barracks";223;1
"Unit";"Marine";"Barracks";223;1
"Unit";"Marine";"Barracks";223;1
"Unit";"Marine";"Barracks";223;1
"Unit";"Marine";"Barracks";223;1
"Unit";"Marine";"Barracks";223;1
"Unit";"Marine";"Barracks";223;1
"Upgrade";"TerranInfantryWeaponsLevel2";"EngineeringBay";176;0
"Upgrade";"TerranInfantryArmorsLevel2";"EngineeringBay";176;0
"Unit";"Marine";"Barracks";223;1
"Unit";"Marine";"Barracks";224;1
"Unit";"Marine";"Barracks";225;1
"Unit";"Marine";"Barracks";226;1
"Unit";"SCV";"Command Center";236;1
"Building";"MissileTurret";NA;236;0
"Unit";"Marine";"Barracks";242;1
"Unit";"Marine";"Barracks";242;1
"Unit";"Marine";"Barracks";242;1
"Unit";"Marine";"Barracks";242;1
"Unit";"Marine";"Barracks";242;1
"Building";"MissileTurret";NA;242;0
"Unit";"Medivac";"Starport";242;2
"Unit";"Medivac";"Starport";242;2
"Unit";"SCV";"Command Center";247;1
"Unit";"SCV";"Command Center";247;1
"Unit";"SCV";"Command Center";247;1
