"Type";"UnitName";"OnBuilding";"TotalSupply";"Supply"
"Unit";"SCV";"Command Center";12;1
"Unit";"SCV";"Command Center";12;1
"Unit";"SCV";"Command Center";13;1
"Building";"SupplyDepot";NA;13;0
"Unit";"SCV";"Command Center";15;1
"Building";"Refinery";NA;15;0
"Unit";"SCV";"Command Center";15;1
"Unit";"SCV";"Command Center";16;1
"Unit";"SCV";"Command Center";17;1
"Building";"Barracks";NA;15;0
"Unit";"Reaper";"Barracks";19;1
"Unit";"SCV";"Command Center";19;1
"Unit";"SCV";"Command Center";20;1
"Unit";"SCV";"Command Center";21;1
"Building";"SupplyDepot";NA;21;0
"Building";"Refinery";NA;21;0
"Building";"Factory";NA;19;0
"Unit";"SCV";"Command Center";23;1
"Building";"BarracksReactor";NA;21;0
"Building";"CommandCenter";NA;19;0
"Unit";"SCV";"Command Center";23;1
"Unit";"SCV";"Command Center";25;1
"Building";"BarracksTechLab";NA;25;0
"Unit";"Hellion";"Factory";25;2
"Unit";"Hellion";"Factory";25;2
"Building";"Starport";NA;24;0
"Unit";"SCV";"Command Center";25;1
"Unit";"SCV";"Command Center";30;1
"Unit";"Hellion";"Factory";26;2
"Unit";"SCV";"Command Center";30;1
"Unit";"Hellion";"Factory";28;2
"Unit";"SCV";"Command Center";32;1
"Unit";"SCV";"Command Center";37;1
"Unit";"SCV";"Command Center";37;1
"Building";"SupplyDepot";NA;37;0
"Building";"SupplyDepot";NA;37;0
"Unit";"SCV";"Command Center";38;1
"Unit";"Hellion";"Factory";38;2
"Unit";"Banshee";"Starport";31;3
"Unit";"SCV";"Command Center";41;1
"Building";"BarracksReactor";NA;37;0
"Unit";"Hellion";"Factory";40;2
"Unit";"SCV";"Command Center";47;1
"Unit";"SCV";"Command Center";49;1
"Unit";"Marine";"Barracks";47;1
"Unit";"Marine";"Barracks";47;1
"Unit";"SCV";"Command Center";49;1
"Building";"SupplyDepot";NA;49;0
"Unit";"SCV";"Command Center";53;1
"Unit";"Marine";"Barracks";51;1
"Unit";"SCV";"Command Center";54;1
"Unit";"SCV";"Command Center";55;1
"Unit";"SCV";"Command Center";56;1
"Building";"FactoryTechLab";NA;54;0
"Unit";"Marine";"Barracks";57;1
"Unit";"Marine";"Barracks";57;1
"Unit";"SCV";"Command Center";57;1
"Unit";"SCV";"Command Center";58;1
"Building";"CommandCenter";NA;46;0
"Unit";"SCV";"Command Center";61;1
"Unit";"SCV";"Command Center";62;1
"Unit";"Banshee";"Starport";54;3
"Unit";"SCV";"Command Center";63;1
"Building";"Barracks";NA;57;0
"Unit";"Marine";"Barracks";63;1
"Unit";"Marine";"Barracks";63;1
"Unit";"SCV";"Command Center";64;1
"Building";"Barracks";NA;57;0
"Unit";"SCV";"Command Center";68;1
"Building";"Refinery";NA;69;0
"Building";"Refinery";NA;69;0
"Building";"EngineeringBay";NA;72;0
"Unit";"Marine";"Barracks";73;1
"Unit";"Marine";"Barracks";73;1
"Unit";"SCV";"Command Center";73;1
"Building";"EngineeringBay";NA;72;0
"Building";"BarracksReactor";NA;72;0
"Unit";"Marine";"Barracks";73;1
"Unit";"Marine";"Barracks";73;1
"Building";"Bunker";NA;73;0
"Unit";"SCV";"Command Center";76;1
"Building";"StarportReactor";NA;73;0
"Unit";"Marine";"Barracks";76;1
"Unit";"Marine";"Barracks";76;1
"Unit";"Marine";"Barracks";76;1
"Unit";"Marine";"Barracks";78;1
"Unit";"Marine";"Barracks";78;1
"Unit";"SCV";"Command Center";79;1
"Unit";"SCV";"Command Center";79;1
"Unit";"Marine";"Barracks";79;1
"Unit";"Marine";"Barracks";80;1
"Unit";"Marine";"Barracks";82;1
"Building";"SupplyDepot";NA;82;0
"Building";"SupplyDepot";NA;82;0
"Unit";"Marine";"Barracks";84;1
"Building";"SupplyDepot";NA;86;0
"Unit";"Marine";"Barracks";88;1
"Unit";"Marine";"Barracks";88;1
"Building";"SupplyDepot";NA;86;0
"Building";"SupplyDepot";NA;90;0
"Building";"SupplyDepot";NA;90;0
"Unit";"Marine";"Barracks";90;1
"Unit";"Marine";"Barracks";92;1
"Unit";"Marine";"Barracks";92;1
"Unit";"Marine";"Barracks";92;1
"Unit";"SCV";"Command Center";92;1
"Unit";"Medivac";"Starport";89;2
"Unit";"Medivac";"Starport";89;2
"Unit";"SCV";"Command Center";92;1
"Unit";"SCV";"Command Center";92;1
"Building";"Barracks";NA;86;0
"Building";"Barracks";NA;86;0
"Unit";"Marine";"Barracks";92;1
"Unit";"Marine";"Barracks";92;1
"Unit";"Marine";"Barracks";101;1
"Unit";"Marine";"Barracks";101;1
"Unit";"Marine";"Barracks";101;1
"Unit";"SCV";"Command Center";103;1
"Unit";"SCV";"Command Center";103;1
"Unit";"SCV";"Command Center";103;1
"Unit";"Marine";"Barracks";103;1
"Unit";"Medivac";"Starport";101;2
"Unit";"SCV";"Command Center";108;1
"Unit";"Medivac";"Starport";101;2
"Unit";"SCV";"Command Center";109;1
"Building";"SupplyDepot";NA;103;0
"Building";"SupplyDepot";NA;103;0
"Building";"Factory";NA;92;0
"Unit";"Marine";"Barracks";111;1
"Unit";"Marine";"Barracks";111;1
"Unit";"Marine";"Barracks";111;1
"Unit";"Marine";"Barracks";111;1
"Unit";"Marine";"Barracks";118;1
"Unit";"SCV";"Command Center";118;1
"Unit";"SCV";"Command Center";118;1
"Unit";"SCV";"Command Center";118;1
"Building";"FactoryTechLab";NA;118;0
"Unit";"Marine";"Barracks";118;1
"Unit";"Marine";"Barracks";119;1
"Unit";"Marine";"Barracks";120;1
"Building";"BarracksReactor";NA;111;0
"Building";"BarracksReactor";NA;111;0
"Upgrade";"TerranInfantryWeaponsLevel1";"EngineeringBay";92;0
"Upgrade";"TerranInfantryArmorsLevel1";"EngineeringBay";92;0
"Unit";"Marine";"Barracks";122;1
"Unit";"SCV";"Command Center";123;1
"Building";"Refinery";NA;122;0
"Unit";"Marine";"Barracks";122;1
"Building";"Armory";NA;111;0
"Unit";"SCV";"Command Center";129;1
"Unit";"SCV";"Command Center";129;1
"Unit";"Marine";"Barracks";126;1
"Unit";"Marine";"Barracks";127;1
"Unit";"Marine";"Barracks";131;1
"Unit";"Marine";"Barracks";131;1
"Unit";"Marine";"Barracks";131;1
"Unit";"Marine";"Barracks";131;1
"Unit";"Marine";"Barracks";131;1
"Unit";"Medivac";"Starport";126;2
"Unit";"Medivac";"Starport";126;2
"Unit";"Marine";"Barracks";131;1
"Upgrade";"Stimpack";"TechLab";96;0
"Unit";"Marine";"Barracks";131;1
"Unit";"Marine";"Barracks";134;1
"Unit";"Marine";"Barracks";135;1
"Building";"SupplyDepot";NA;146;0
"Building";"SupplyDepot";NA;147;0
"Building";"SupplyDepot";NA;147;0
"Building";"SupplyDepot";NA;147;0
"Building";"CommandCenter";NA;122;0
"Unit";"Marine";"Barracks";149;1
"Unit";"Marine";"Barracks";149;1
"Unit";"Marine";"Barracks";149;1
"Unit";"Marine";"Barracks";149;1
"Unit";"Marine";"Barracks";149;1
"Unit";"Marine";"Barracks";149;1
"Unit";"Marine";"Barracks";149;1
"Unit";"Marine";"Barracks";149;1
"Unit";"Marine";"Barracks";149;1
"Unit";"Medivac";"Starport";149;2
"Building";"SupplyDepot";NA;149;0
"Building";"SupplyDepot";NA;149;0
"Unit";"Marine";"Barracks";149;1
"Unit";"Marine";"Barracks";161;1
"Unit";"Marine";"Barracks";161;1
"Unit";"Marine";"Barracks";161;1
"Unit";"Marine";"Barracks";161;1
"Unit";"Marine";"Barracks";161;1
"Unit";"Marine";"Barracks";161;1
"Unit";"Marine";"Barracks";161;1
"Unit";"Marine";"Barracks";161;1
"Unit";"Marine";"Barracks";161;1
"Unit";"SCV";"Command Center";161;1
"Unit";"Marine";"Barracks";161;1
"Unit";"Marine";"Barracks";162;1
"Unit";"Marine";"Barracks";163;1
"Unit";"Marine";"Barracks";170;1
"Unit";"Marine";"Barracks";170;1
"Unit";"Marine";"Barracks";170;1
"Unit";"Marine";"Barracks";170;1
"Unit";"Marine";"Barracks";170;1
"Unit";"Marine";"Barracks";171;1
"Unit";"Medivac";"Starport";171;2
"Unit";"Marine";"Barracks";171;1
"Unit";"Marine";"Barracks";174;1
"Unit";"Marine";"Barracks";174;1
"Unit";"Marine";"Barracks";174;1
"Building";"Barracks";NA;161;0
"Building";"Barracks";NA;161;0
"Building";"Barracks";NA;161;0
"Unit";"Marine";"Barracks";179;1
"Unit";"Marine";"Barracks";179;1
"Unit";"Marine";"Barracks";179;1
"Unit";"Marine";"Barracks";179;1
"Unit";"Marine";"Barracks";179;1
"Unit";"Marine";"Barracks";182;1
"Unit";"Marine";"Barracks";183;1
"Unit";"Marine";"Barracks";184;1
"Unit";"Marine";"Barracks";185;1
"Unit";"Medivac";"Starport";179;2
"Unit";"Marine";"Barracks";186;1
"Unit";"Marine";"Barracks";189;1
"Unit";"Marine";"Barracks";189;1
"Unit";"Marine";"Barracks";190;1
"Building";"BarracksTechLab";NA;190;0
"Unit";"Medivac";"Starport";180;2
"Building";"BarracksTechLab";NA;190;0
"Building";"BarracksTechLab";NA;191;0
"Upgrade";"TerranVehicleWeaponsLevel1";"Armory";161;0
"Building";"GhostAcademy";NA;191;0
"Unit";"Marine";"Barracks";203;1
"Unit";"Marine";"Barracks";203;1
"Unit";"Marine";"Barracks";203;1
"Unit";"Marine";"Barracks";203;1
"Unit";"Marine";"Barracks";203;1
"Unit";"Marine";"Barracks";203;1
"Unit";"Marine";"Barracks";203;1
"Unit";"Marauder";"Barracks";203;2
"Unit";"Marauder";"Barracks";203;2
"Unit";"Marauder";"Barracks";203;2
"Upgrade";"TerranInfantryWeaponsLevel2";"EngineeringBay";171;0
"Unit";"Marine";"Barracks";203;1
