"type";"unit_name";"on_building";"total_supply";"supply"
"Building";"Refinery";NA;15;0
"Building";"Barracks";NA;15;0
"Unit";"Reaper";"Barracks";19;1
"Building";"Refinery";NA;21;0
"Building";"Factory";NA;19;0
"Building";"BarracksReactor";NA;21;0
"Building";"CommandCenter";NA;19;0
"Building";"BarracksTechLab";NA;25;0
"Unit";"Hellion";"Factory";25;2
"Unit";"Hellion";"Factory";25;2
"Building";"Starport";NA;24;0
"Unit";"Hellion";"Factory";26;2
"Unit";"Hellion";"Factory";28;2
"Unit";"Hellion";"Factory";38;2
"Unit";"Banshee";"Starport";31;3
"Building";"BarracksReactor";NA;37;0
"Unit";"Hellion";"Factory";40;2
"Unit";"Marine";"Barracks";47;1
"Unit";"Marine";"Barracks";47;1
"Unit";"Marine";"Barracks";51;1
"Building";"FactoryTechLab";NA;54;0
"Unit";"Marine";"Barracks";57;1
"Unit";"Marine";"Barracks";57;1
"Building";"CommandCenter";NA;46;0
"Unit";"Banshee";"Starport";54;3
"Building";"Barracks";NA;57;0
"Unit";"Marine";"Barracks";63;1
"Unit";"Marine";"Barracks";63;1
"Building";"Barracks";NA;57;0
"Building";"Refinery";NA;69;0
"Building";"Refinery";NA;69;0
"Building";"EngineeringBay";NA;72;0
"Unit";"Marine";"Barracks";73;1
"Unit";"Marine";"Barracks";73;1
"Building";"EngineeringBay";NA;72;0
"Building";"BarracksReactor";NA;72;0
"Unit";"Marine";"Barracks";73;1
"Unit";"Marine";"Barracks";73;1
"Building";"Bunker";NA;73;0
"Building";"StarportReactor";NA;73;0
"Unit";"Marine";"Barracks";76;1
"Unit";"Marine";"Barracks";76;1
"Unit";"Marine";"Barracks";76;1
"Unit";"Marine";"Barracks";78;1
"Unit";"Marine";"Barracks";78;1
"Unit";"Marine";"Barracks";79;1
"Unit";"Marine";"Barracks";80;1
"Unit";"Marine";"Barracks";82;1
"Unit";"Marine";"Barracks";84;1
"Unit";"Marine";"Barracks";88;1
"Unit";"Marine";"Barracks";88;1
"Unit";"Marine";"Barracks";90;1
"Unit";"Marine";"Barracks";92;1
"Unit";"Marine";"Barracks";92;1
"Unit";"Marine";"Barracks";92;1
"Unit";"Medivac";"Starport";89;2
"Unit";"Medivac";"Starport";89;2
"Building";"Barracks";NA;86;0
"Building";"Barracks";NA;86;0
"Unit";"Marine";"Barracks";92;1
"Unit";"Marine";"Barracks";92;1
"Unit";"Marine";"Barracks";101;1
"Unit";"Marine";"Barracks";101;1
"Unit";"Marine";"Barracks";101;1
"Unit";"Marine";"Barracks";103;1
"Unit";"Medivac";"Starport";101;2
"Unit";"Medivac";"Starport";101;2
"Building";"Factory";NA;92;0
"Unit";"Marine";"Barracks";111;1
"Unit";"Marine";"Barracks";111;1
"Unit";"Marine";"Barracks";111;1
"Unit";"Marine";"Barracks";111;1
"Unit";"Marine";"Barracks";118;1
"Building";"FactoryTechLab";NA;118;0
"Unit";"Marine";"Barracks";118;1
"Unit";"Marine";"Barracks";119;1
"Unit";"Marine";"Barracks";120;1
"Building";"BarracksReactor";NA;111;0
"Building";"BarracksReactor";NA;111;0
"Upgrade";"TerranInfantryWeaponsLevel1";"EngineeringBay";92;0
"Upgrade";"TerranInfantryArmorsLevel1";"EngineeringBay";92;0
"Unit";"Marine";"Barracks";122;1
"Building";"Refinery";NA;122;0
"Unit";"Marine";"Barracks";122;1
"Building";"Armory";NA;111;0
"Unit";"Marine";"Barracks";126;1
"Unit";"Marine";"Barracks";127;1
"Unit";"Marine";"Barracks";131;1
"Unit";"Marine";"Barracks";131;1
"Unit";"Marine";"Barracks";131;1
"Unit";"Marine";"Barracks";131;1
"Unit";"Marine";"Barracks";131;1
"Unit";"Medivac";"Starport";126;2
"Unit";"Medivac";"Starport";126;2
"Unit";"Marine";"Barracks";131;1
"Upgrade";"Stimpack";"TechLab";96;0
"Unit";"Marine";"Barracks";131;1
"Unit";"Marine";"Barracks";134;1
"Unit";"Marine";"Barracks";135;1
"Building";"CommandCenter";NA;122;0
"Unit";"Marine";"Barracks";149;1
"Unit";"Marine";"Barracks";149;1
"Unit";"Marine";"Barracks";149;1
"Unit";"Marine";"Barracks";149;1
"Unit";"Marine";"Barracks";149;1
"Unit";"Marine";"Barracks";149;1
"Unit";"Marine";"Barracks";149;1
"Unit";"Marine";"Barracks";149;1
"Unit";"Marine";"Barracks";149;1
"Unit";"Medivac";"Starport";149;2
"Unit";"Marine";"Barracks";149;1
"Unit";"Marine";"Barracks";161;1
"Unit";"Marine";"Barracks";161;1
"Unit";"Marine";"Barracks";161;1
"Unit";"Marine";"Barracks";161;1
"Unit";"Marine";"Barracks";161;1
"Unit";"Marine";"Barracks";161;1
"Unit";"Marine";"Barracks";161;1
"Unit";"Marine";"Barracks";161;1
"Unit";"Marine";"Barracks";161;1
"Unit";"Marine";"Barracks";161;1
"Unit";"Marine";"Barracks";162;1
"Unit";"Marine";"Barracks";163;1
"Unit";"Marine";"Barracks";170;1
"Unit";"Marine";"Barracks";170;1
"Unit";"Marine";"Barracks";170;1
"Unit";"Marine";"Barracks";170;1
"Unit";"Marine";"Barracks";170;1
"Unit";"Marine";"Barracks";171;1
"Unit";"Medivac";"Starport";171;2
"Unit";"Marine";"Barracks";171;1
"Unit";"Marine";"Barracks";174;1
"Unit";"Marine";"Barracks";174;1
"Unit";"Marine";"Barracks";174;1
"Building";"Barracks";NA;161;0
"Building";"Barracks";NA;161;0
"Building";"Barracks";NA;161;0
"Unit";"Marine";"Barracks";179;1
"Unit";"Marine";"Barracks";179;1
"Unit";"Marine";"Barracks";179;1
"Unit";"Marine";"Barracks";179;1
"Unit";"Marine";"Barracks";179;1
"Unit";"Marine";"Barracks";182;1
"Unit";"Marine";"Barracks";183;1
"Unit";"Marine";"Barracks";184;1
"Unit";"Marine";"Barracks";185;1
"Unit";"Medivac";"Starport";179;2
"Unit";"Marine";"Barracks";186;1
"Unit";"Marine";"Barracks";189;1
"Unit";"Marine";"Barracks";189;1
"Unit";"Marine";"Barracks";190;1
"Building";"BarracksTechLab";NA;190;0
"Unit";"Medivac";"Starport";180;2
"Building";"BarracksTechLab";NA;190;0
"Building";"BarracksTechLab";NA;191;0
"Upgrade";"TerranVehicleWeaponsLevel1";"Armory";161;0
"Building";"GhostAcademy";NA;191;0
"Unit";"Marine";"Barracks";203;1
"Unit";"Marine";"Barracks";203;1
"Unit";"Marine";"Barracks";203;1
"Unit";"Marine";"Barracks";203;1
"Unit";"Marine";"Barracks";203;1
"Unit";"Marine";"Barracks";203;1
"Unit";"Marine";"Barracks";203;1
"Unit";"Marauder";"Barracks";203;2
"Unit";"Marauder";"Barracks";203;2
"Unit";"Marauder";"Barracks";203;2
"Upgrade";"TerranInfantryWeaponsLevel2";"EngineeringBay";171;0
"Unit";"Marine";"Barracks";203;1
