"type";"unit_name";"on_building";"total_supply";"supply"
"Building";"Refinery";NA;14;0
"Building";"Barracks";NA;15;0
"Unit";"Reaper";"Barracks";19;1
"Building";"Factory";NA;19;0
"Building";"BarracksReactor";NA;21;0
"Building";"CommandCenter";NA;19;0
"Unit";"Hellion";"Factory";24;2
"Unit";"Hellion";"Factory";24;2
"Building";"Starport";NA;23;0
"Building";"BarracksTechLab";NA;24;0
"Unit";"Hellion";"Factory";28;2
"Unit";"Hellion";"Factory";28;2
"Building";"BarracksTechLab";NA;29;0
"Unit";"Hellion";"Factory";35;2
"Unit";"Hellion";"Factory";35;2
"Unit";"Banshee";"Starport";35;3
"Building";"Refinery";NA;45;0
"Unit";"Marine";"Barracks";50;1
"Building";"CommandCenter";NA;43;0
"Building";"Refinery";NA;57;0
"Building";"EngineeringBay";NA;55;0
"Building";"Refinery";NA;57;0
"Building";"Barracks";NA;52;0
"Building";"EngineeringBay";NA;57;0
"Building";"Barracks";NA;52;0
"Unit";"Marine";"Barracks";59;1
"Unit";"Marine";"Barracks";61;1
"Unit";"Marine";"Barracks";61;1
"Unit";"Marine";"Barracks";63;1
"Building";"FactoryReactor";NA;59;0
"Building";"StarportReactor";NA;61;0
"Unit";"Marine";"Barracks";65;1
"Unit";"Marine";"Barracks";70;1
"Unit";"Marine";"Barracks";70;1
"Unit";"Marine";"Barracks";72;1
"Unit";"Marine";"Barracks";72;1
"Unit";"Marine";"Barracks";72;1
"Building";"Barracks";NA;64;0
"Building";"Barracks";NA;64;0
"Unit";"Medivac";"Starport";72;2
"Unit";"Medivac";"Starport";72;2
"Unit";"Marine";"Barracks";80;1
"Unit";"Marine";"Barracks";80;1
"Unit";"Marine";"Barracks";80;1
"Upgrade";"Stimpack";"TechLab";59;0
"Unit";"Marine";"Barracks";80;1
"Unit";"Marine";"Barracks";80;1
"Building";"Refinery";NA;82;0
"Building";"Refinery";NA;82;0
"Unit";"Marine";"Barracks";88;1
"Unit";"Marine";"Barracks";89;1
"Unit";"Marine";"Barracks";89;1
"Building";"MissileTurret";NA;94;0
"Building";"MissileTurret";NA;94;0
"Building";"MissileTurret";NA;94;0
"Unit";"Marine";"Barracks";96;1
"Unit";"Marine";"Barracks";96;1
"Building";"Armory";NA;82;0
"Building";"BarracksReactor";NA;92;0
"Building";"BarracksReactor";NA;92;0
"Unit";"Marine";"Barracks";100;1
"Unit";"Marine";"Barracks";100;1
"Upgrade";"TerranInfantryArmorsLevel1";"EngineeringBay";72;0
"Upgrade";"TerranInfantryWeaponsLevel1";"EngineeringBay";72;0
"Unit";"Marine";"Barracks";101;1
"Unit";"Marine";"Barracks";101;1
"Unit";"Marine";"Barracks";103;1
"Unit";"Marine";"Barracks";103;1
"Unit";"Marine";"Barracks";105;1
"Unit";"Marine";"Barracks";105;1
"Unit";"Marine";"Barracks";109;1
"Unit";"Marine";"Barracks";109;1
"Unit";"Marine";"Barracks";111;1
"Unit";"Marine";"Barracks";111;1
"Unit";"Marine";"Barracks";111;1
"Unit";"Marine";"Barracks";111;1
"Unit";"Marine";"Barracks";111;1
"Unit";"Marine";"Barracks";111;1
"Unit";"Marine";"Barracks";111;1
"Unit";"Marine";"Barracks";111;1
"Unit";"Marine";"Barracks";112;1
"Unit";"Marine";"Barracks";113;1
"Unit";"Medivac";"Starport";113;2
"Unit";"Marine";"Barracks";114;1
"Unit";"Marine";"Barracks";114;1
"Unit";"Medivac";"Starport";113;2
"Unit";"Marine";"Barracks";116;1
"Unit";"Marine";"Barracks";116;1
"Unit";"Marine";"Barracks";118;1
"Unit";"Marine";"Barracks";118;1
"Building";"MissileTurret";NA;120;0
"Unit";"Marine";"Barracks";123;1
"Building";"MissileTurret";NA;126;0
"Unit";"Marine";"Barracks";138;1
"Unit";"Marine";"Barracks";138;1
"Unit";"Marine";"Barracks";138;1
"Unit";"Marine";"Barracks";138;1
"Unit";"Marine";"Barracks";138;1
"Unit";"Marine";"Barracks";138;1
"Unit";"Marine";"Barracks";138;1
"Unit";"Marine";"Barracks";138;1
"Unit";"Marauder";"Barracks";138;2
"Unit";"Medivac";"Starport";138;2
"Unit";"Medivac";"Starport";138;2
"Unit";"Marine";"Barracks";138;1
"Unit";"Marine";"Barracks";146;1
"Unit";"Marine";"Barracks";146;1
"Unit";"Marine";"Barracks";146;1
"Unit";"Marine";"Barracks";146;1
"Unit";"Marine";"Barracks";146;1
"Unit";"Marine";"Barracks";146;1
"Unit";"Marine";"Barracks";146;1
"Unit";"Marine";"Barracks";151;1
"Unit";"Marine";"Barracks";156;1
"Unit";"Marine";"Barracks";157;1
"Unit";"Marine";"Barracks";158;1
"Unit";"Marine";"Barracks";160;1
"Unit";"Marine";"Barracks";161;1
"Unit";"Marine";"Barracks";162;1
"Unit";"Marine";"Barracks";163;1
"Unit";"Marine";"Barracks";164;1
"Unit";"Marine";"Barracks";164;1
"Building";"MissileTurret";NA;165;0
"Unit";"Marine";"Barracks";165;1
"Unit";"Marine";"Barracks";175;1
"Unit";"Marine";"Barracks";175;1
"Unit";"Marine";"Barracks";175;1
"Unit";"Marine";"Barracks";175;1
"Unit";"Marine";"Barracks";175;1
"Unit";"Marine";"Barracks";175;1
"Unit";"Marine";"Barracks";175;1
"Unit";"Marine";"Barracks";176;1
"Unit";"Marine";"Barracks";176;1
"Building";"CommandCenter";NA;151;0
"Unit";"Marine";"Barracks";176;1
"Unit";"Marine";"Barracks";177;1
"Unit";"Marine";"Barracks";177;1
"Unit";"Marine";"Barracks";183;1
"Unit";"Marine";"Barracks";183;1
"Unit";"Marine";"Barracks";183;1
"Unit";"Marine";"Barracks";183;1
"Unit";"Marine";"Barracks";185;1
"Unit";"Marine";"Barracks";185;1
"Upgrade";"TerranInfantryWeaponsLevel2";"EngineeringBay";138;0
"Upgrade";"TerranInfantryArmorsLevel2";"EngineeringBay";138;0
"Unit";"Marine";"Barracks";185;1
"Unit";"Marine";"Barracks";186;1
"Unit";"Marine";"Barracks";186;1
"Unit";"Marine";"Barracks";188;1
"Unit";"Marine";"Barracks";194;1
"Unit";"Marine";"Barracks";194;1
"Unit";"Marine";"Barracks";194;1
"Unit";"Marine";"Barracks";194;1
"Unit";"Medivac";"Starport";185;2
"Unit";"Medivac";"Starport";185;2
"Unit";"Marauder";"Barracks";194;2
"Unit";"Marine";"Barracks";194;1
"Unit";"Marine";"Barracks";202;1
"Unit";"Marine";"Barracks";202;1
"Unit";"Marine";"Barracks";202;1
"Unit";"Marine";"Barracks";202;1
"Unit";"Marine";"Barracks";202;1
"Unit";"Marine";"Barracks";202;1
"Unit";"Marine";"Barracks";202;1
"Unit";"Marine";"Barracks";206;1
"Unit";"Marine";"Barracks";208;1
"Unit";"Medivac";"Starport";208;2
"Unit";"Medivac";"Starport";208;2
"Unit";"Marine";"Barracks";209;1
"Unit";"Marine";"Barracks";210;1
"Unit";"Marine";"Barracks";211;1
"Unit";"Marine";"Barracks";218;1
"Unit";"Marine";"Barracks";218;1
"Unit";"Marine";"Barracks";227;1
"Unit";"Marine";"Barracks";227;1
"Unit";"Marine";"Barracks";227;1
"Unit";"Marine";"Barracks";227;1
"Unit";"Marine";"Barracks";227;1
"Unit";"Marine";"Barracks";227;1
"Unit";"Marine";"Barracks";227;1
"Unit";"Marine";"Barracks";227;1
"Unit";"Marine";"Barracks";227;1
"Unit";"Marine";"Barracks";227;1
"Unit";"Marine";"Barracks";227;1
"Unit";"Marine";"Barracks";227;1
"Unit";"Marine";"Barracks";236;1
"Unit";"Marauder";"Barracks";227;2
"Unit";"Marine";"Barracks";236;1
"Unit";"Marine";"Barracks";236;1
"Unit";"Marine";"Barracks";236;1
"Unit";"Marine";"Barracks";236;1
"Unit";"Marine";"Barracks";236;1
"Unit";"Marine";"Barracks";236;1
"Unit";"Marine";"Barracks";236;1
"Unit";"Marine";"Barracks";239;1
"Unit";"Marine";"Barracks";243;1
"Unit";"Marine";"Barracks";244;1
"Unit";"Marauder";"Barracks";240;2
"Unit";"Marine";"Barracks";246;1
"Unit";"Marine";"Barracks";246;1
