"Type";"UnitName";"OnBuilding";"TotalSupply";"Supply"
"Unit";"SCV";"Command Center";12;1
"Unit";"SCV";"Command Center";12;1
"Unit";"SCV";"Command Center";13;1
"Building";"SupplyDepot";NA;13;0
"Unit";"SCV";"Command Center";15;1
"Unit";"SCV";"Command Center";15;1
"Building";"Refinery";NA;16;0
"Unit";"SCV";"Command Center";16;1
"Building";"Barracks";NA;15;0
"Unit";"SCV";"Command Center";17;1
"Unit";"Reaper";"Barracks";19;1
"Unit";"SCV";"Command Center";19;1
"Unit";"SCV";"Command Center";21;1
"Unit";"Marine";"Barracks";20;1
"Building";"SupplyDepot";NA;19;0
"Unit";"SCV";"Command Center";23;1
"Unit";"Marine";"Barracks";23;1
"Unit";"SCV";"Command Center";23;1
"Building";"CommandCenter";NA;19;0
"Building";"Factory";NA;21;0
"Unit";"SCV";"Command Center";25;1
"Unit";"SCV";"Command Center";26;1
"Building";"BarracksReactor";NA;25;0
"Unit";"SCV";"Command Center";27;1
"Unit";"SCV";"Command Center";28;1
"Unit";"SCV";"Command Center";29;1
"Unit";"SCV";"Command Center";29;1
"Unit";"Hellion";"Factory";29;2
"Unit";"Hellion";"Factory";29;2
"Unit";"SCV";"Command Center";30;1
"Unit";"SCV";"Command Center";31;1
"Building";"SupplyDepot";NA;31;0
"Building";"BarracksTechLab";NA;31;0
"Unit";"SCV";"Command Center";37;1
"Building";"Bunker";NA;30;0
"Unit";"Hellion";"Factory";32;2
"Unit";"Hellion";"Factory";34;2
"Unit";"SCV";"Command Center";37;1
"Unit";"SCV";"Command Center";38;1
"Building";"Starport";NA;31;0
"Building";"SupplyDepot";NA;37;0
"Building";"SupplyDepot";NA;38;0
"Unit";"SCV";"Command Center";43;1
"Building";"SupplyDepot";NA;39;0
"Unit";"SCV";"Command Center";44;1
"Unit";"Hellion";"Factory";39;2
"Unit";"Hellion";"Factory";41;2
"Building";"CommandCenter";NA;29;0
"Unit";"SCV";"Command Center";46;1
"Unit";"SCV";"Command Center";46;1
"Unit";"SCV";"Command Center";51;1
"Unit";"SCV";"Command Center";52;1
"Unit";"Hellion";"Factory";47;2
"Unit";"Hellion";"Factory";49;2
"Building";"Refinery";NA;51;0
"Building";"Refinery";NA;51;0
"Unit";"SCV";"Command Center";53;1
"Unit";"SCV";"Command Center";55;1
"Building";"Refinery";NA;54;0
"Unit";"SCV";"Command Center";59;1
"Unit";"SCV";"Command Center";60;1
"Unit";"Raven";"Starport";53;2
"Unit";"Hellion";"Factory";60;2
"Unit";"Hellion";"Factory";60;2
"Unit";"SCV";"Command Center";61;1
"Unit";"SCV";"Command Center";62;1
"Unit";"SCV";"Command Center";69;1
"Unit";"SCV";"Command Center";70;1
"Unit";"SCV";"Command Center";71;1
"Unit";"Hellion";"Factory";71;2
"Unit";"Hellion";"Factory";71;2
"Unit";"SCV";"Command Center";71;1
"Unit";"SCV";"Command Center";72;1
"Unit";"SCV";"Command Center";73;1
"Unit";"SCV";"Command Center";78;1
"Unit";"SCV";"Command Center";79;1
"Unit";"SCV";"Command Center";80;1
"Unit";"SCV";"Command Center";81;1
"Unit";"SCV";"Command Center";82;1
"Building";"Factory";NA;71;0
"Building";"Factory";NA;71;0
"Unit";"Hellion";"Factory";81;2
"Unit";"Hellion";"Factory";81;2
"Unit";"SCV";"Command Center";83;1
"Unit";"SCV";"Command Center";84;1
"Unit";"SCV";"Command Center";85;1
"Building";"Refinery";NA;83;0
"Building";"Refinery";NA;84;0
"Unit";"SCV";"Command Center";90;1
"Unit";"SCV";"Command Center";91;1
"Unit";"SCV";"Command Center";92;1
"Unit";"Hellion";"Factory";86;2
"Unit";"Hellion";"Factory";88;2
"Unit";"SCV";"Command Center";93;1
"Building";"Factory";NA;84;0
"Building";"Factory";NA;84;0
"Unit";"SCV";"Command Center";100;1
"Unit";"SCV";"Command Center";100;1
"Unit";"SCV";"Command Center";100;1
"Building";"Armory";NA;85;0
"Building";"Armory";NA;86;0
"Building";"SupplyDepot";NA;96;0
"Building";"SupplyDepot";NA;100;0
"Unit";"SCV";"Command Center";101;1
"Building";"FactoryTechLab";NA;101;0
"Building";"FactoryTechLab";NA;101;0
"Building";"FactoryTechLab";NA;101;0
"Unit";"SCV";"Command Center";104;1
"Unit";"SCV";"Command Center";104;1
"Unit";"SCV";"Command Center";104;1
"Unit";"SCV";"Command Center";108;1
"Unit";"SCV";"Command Center";108;1
"Unit";"SCV";"Command Center";108;1
"Building";"Factory";NA;104;0
"Building";"Factory";NA;104;0
"Unit";"Hellion";"Factory";108;2
"Unit";"Hellion";"Factory";108;2
"Building";"Factory";NA;104;0
"Building";"StarportReactor";NA;108;0
"Building";"EngineeringBay";NA;111;0
"Building";"FactoryTechLab";NA;115;0
"Building";"SupplyDepot";NA;115;0
"Building";"SupplyDepot";NA;115;0
"Building";"SupplyDepot";NA;115;0
"Building";"SupplyDepot";NA;115;0
"Building";"SupplyDepot";NA;115;0
"Unit";"SCV";"Command Center";115;1
"Unit";"SCV";"Command Center";115;1
"Unit";"SCV";"Command Center";115;1
"Building";"FactoryReactor";NA;115;0
"Unit";"Hellion";"Factory";115;2
"Unit";"Hellion";"Factory";115;2
"Unit";"Hellion";"Factory";115;2
"Unit";"SCV";"Command Center";115;1
"Unit";"SCV";"Command Center";115;1
"Unit";"SCV";"Command Center";117;1
"Building";"CommandCenter";NA;108;0
"Building";"CommandCenter";NA;108;0
"Unit";"SCV";"Command Center";124;1
"Building";"MissileTurret";NA;127;0
"Building";"MissileTurret";NA;127;0
"Building";"MissileTurret";NA;127;0
"Building";"MissileTurret";NA;127;0
"Building";"MissileTurret";NA;127;0
"Unit";"Thor";"Factory";127;6
"Upgrade";"TerranVehicleWeaponsLevel1";"Armory";115;0
"Upgrade";"TerranVehicleAndShipArmorsLevel1";"Armory";115;0
"Unit";"Hellion";"Factory";128;2
"Unit";"Hellion";"Factory";128;2
"Unit";"Hellion";"Factory";128;2
"Unit";"Hellion";"Factory";128;2
"Building";"Refinery";NA;128;0
"Building";"Refinery";NA;128;0
"Building";"FactoryTechLab";NA;128;0
"Unit";"Thor";"Factory";128;6
"Unit";"Thor";"Factory";128;6
"Unit";"Thor";"Factory";128;6
"Building";"MissileTurret";NA;142;0
"Building";"MissileTurret";NA;142;0
"Building";"MissileTurret";NA;142;0
"Building";"MissileTurret";NA;142;0
"Unit";"SCV";"Command Center";160;1
"Unit";"SCV";"Command Center";160;1
"Unit";"SCV";"Command Center";160;1
"Unit";"Hellion";"Factory";163;2
"Unit";"Hellion";"Factory";163;2
"Unit";"Hellion";"Factory";163;2
"Unit";"Hellion";"Factory";163;2
