"type";"unit_name";"on_building";"total_supply_lag";"supply"
"Unit";"Overlord";"Larva";13;0
"Building";"Hatchery";NA;17;0
"Building";"Extractor";NA;19;0
"Building";"SpawningPool";NA;19;0
"Unit";"Overlord";"Larva";22;0
"Unit";"Queen";"Hatchery";23;2
"Unit";"Zergling";"Larva";25;1
"Unit";"Zergling";"Larva";26;1
"Unit";"Queen";"Hatchery";27;2
"Unit";"Zergling";"Larva";29;1
"Unit";"Zergling";"Larva";30;1
"Building";"Hatchery";NA;37;0
"Building";"CreepTumorQueen";NA;37;0
"Unit";"Queen";"Hatchery";37;2
"Unit";"Overlord";"Larva";39;0
"Building";"CreepTumor";NA;42;0
"Building";"CreepTumorQueen";NA;47;0
"Unit";"Overlord";"Larva";47;0
"Unit";"Queen";"Hatchery";47;2
"Unit";"Overlord";"Larva";49;0
"Building";"CreepTumor";NA;50;0
"Building";"CreepTumor";NA;54;0
"Unit";"Overlord";"Larva";54;0
"Building";"CreepTumorQueen";NA;54;0
"Building";"SporeCrawler";NA;54;0
"Building";"SporeCrawler";NA;54;0
"Building";"CreepTumor";NA;59;0
"Unit";"Queen";"Hatchery";59;2
"Unit";"Overlord";"Larva";63;0
"Unit";"Zergling";"Larva";63;1
"Unit";"Zergling";"Larva";64;1
"Unit";"Zergling";"Larva";65;1
"Unit";"Zergling";"Larva";66;1
"Building";"CreepTumor";NA;69;0
"Building";"CreepTumorQueen";NA;69;0
"Unit";"Overlord";"Larva";69;0
"Building";"RoachWarren";NA;69;0
"Unit";"Zergling";"Larva";69;1
"Unit";"Zergling";"Larva";70;1
"Unit";"Zergling";"Larva";71;1
"Unit";"Zergling";"Larva";72;1
"Unit";"Zergling";"Larva";73;1
"Unit";"Zergling";"Larva";74;1
"Unit";"Overlord";"Larva";75;0
"Building";"CreepTumorQueen";NA;78;0
"Building";"CreepTumorQueen";NA;79;0
"Building";"Extractor";NA;79;0
"Building";"Extractor";NA;80;0
"Building";"CreepTumor";NA;82;0
"Building";"CreepTumor";NA;83;0
"Building";"CreepTumor";NA;83;0
"Unit";"Overlord";"Larva";87;0
"Unit";"Overlord";"Larva";87;0
"Unit";"Roach";"Larva";87;2
"Unit";"Roach";"Larva";89;2
"Unit";"Roach";"Larva";91;2
"Building";"CreepTumor";NA;93;0
"Unit";"Roach";"Larva";93;2
"Unit";"Roach";"Larva";95;2
"Unit";"Roach";"Larva";97;2
"Unit";"Roach";"Larva";99;2
"Unit";"Roach";"Larva";101;2
"Unit";"Roach";"Larva";103;2
"Unit";"Roach";"Larva";105;2
"Building";"CreepTumor";NA;107;0
"Building";"CreepTumor";NA;107;0
"Building";"CreepTumor";NA;107;0
"Unit";"Overlord";"Larva";107;0
"Upgrade";"GlialReconstitution";"RoachWarren";109;0
"Unit";"Overlord";"Larva";109;0
"Building";"CreepTumor";NA;112;0
"Building";"CreepTumor";NA;112;0
"Unit";"Overlord";"Larva";112;0
"Building";"Extractor";NA;112;0
"Building";"EvolutionChamber";NA;112;0
"Building";"BanelingNest";NA;112;0
"Unit";"Roach";"Larva";112;2
"Unit";"Roach";"Larva";114;2
"Unit";"Overlord";"Larva";116;0
"Unit";"Overlord";"Larva";116;0
"Unit";"Overlord";"Larva";123;0
"Building";"Extractor";NA;123;0
"Building";"Extractor";NA;123;0
"Building";"CreepTumor";NA;123;0
"Unit";"Overlord";"Larva";123;0
"Building";"CreepTumorQueen";NA;131;0
"Building";"CreepTumorQueen";NA;131;0
"Unit";"Roach";"Larva";131;2
"Unit";"Roach";"Larva";133;2
"Unit";"Zergling";"Larva";135;1
"Unit";"Zergling";"Larva";136;1
"Unit";"Zergling";"Larva";137;1
"Unit";"Zergling";"Larva";138;1
"Unit";"Zergling";"Larva";139;1
"Unit";"Zergling";"Larva";140;1
"Unit";"Zergling";"Larva";141;1
"Unit";"Zergling";"Larva";142;1
"Unit";"Zergling";"Larva";143;1
"Unit";"Zergling";"Larva";144;1
"Unit";"Zergling";"Larva";145;1
"Unit";"Zergling";"Larva";146;1
"Unit";"Zergling";"Larva";147;1
"Unit";"Zergling";"Larva";148;1
"Unit";"Zergling";"Larva";149;1
"Unit";"Zergling";"Larva";150;1
"Unit";"Zergling";"Larva";151;1
"Unit";"Zergling";"Larva";152;1
"Unit";"Zergling";"Larva";153;1
"Unit";"Zergling";"Larva";154;1
"Building";"CreepTumor";NA;155;0
"Building";"CreepTumor";NA;155;0
"Building";"CreepTumor";NA;155;0
"Building";"Spire";NA;155;0
"Building";"CreepTumor";NA;155;0
"Unit";"Overlord";"Larva";155;0
"Unit";"Zergling";"Larva";155;1
"Unit";"Zergling";"Larva";156;1
"Unit";"Zergling";"Larva";157;1
"Unit";"Zergling";"Larva";158;1
"Building";"CreepTumor";NA;159;0
"Building";"CreepTumor";NA;159;0
"Building";"CreepTumorQueen";NA;159;0
"Building";"CreepTumorQueen";NA;159;0
"Unit";"Overlord";"Larva";159;0
"Building";"Hatchery";NA;159;0
"Unit";"Roach";"Larva";159;2
"Unit";"Roach";"Larva";161;2
"Unit";"Roach";"Larva";163;2
"Unit";"Zergling";"Larva";165;1
"Unit";"Zergling";"Larva";166;1
"Unit";"Zergling";"Larva";167;1
"Unit";"Zergling";"Larva";168;1
"Unit";"Zergling";"Larva";169;1
"Unit";"Zergling";"Larva";170;1
"Unit";"Zergling";"Larva";171;1
"Unit";"Zergling";"Larva";172;1
"Unit";"Overlord";"Larva";173;0
"Building";"CreepTumorQueen";NA;173;0
"Building";"CreepTumor";NA;173;0
"Building";"CreepTumor";NA;173;0
"Building";"CreepTumor";NA;173;0
"Building";"CreepTumor";NA;173;0
"Unit";"Overlord";"Larva";173;0
"Building";"CreepTumorQueen";NA;173;0
"Unit";"Zergling";"Larva";173;1
"Unit";"Zergling";"Larva";174;1
"Unit";"Zergling";"Larva";175;1
"Unit";"Zergling";"Larva";176;1
"Unit";"Zergling";"Larva";177;1
"Unit";"Zergling";"Larva";178;1
"Unit";"Zergling";"Larva";179;1
"Unit";"Zergling";"Larva";180;1
"Unit";"Zergling";"Larva";181;1
"Unit";"Zergling";"Larva";182;1
"Building";"CreepTumor";NA;183;0
"Building";"CreepTumor";NA;183;0
"Unit";"Overlord";"Larva";183;0
"Building";"CreepTumor";NA;191;0
"Building";"CreepTumor";NA;191;0
"Building";"CreepTumor";NA;191;0
"Building";"CreepTumor";NA;191;0
"Building";"CreepTumor";NA;191;0
"Building";"CreepTumor";NA;191;0
"Building";"CreepTumor";NA;191;0
"Unit";"Mutalisk";"Larva";191;2
"Unit";"Mutalisk";"Larva";193;2
"Unit";"Mutalisk";"Larva";195;2
"Unit";"Mutalisk";"Larva";197;2
"Unit";"Mutalisk";"Larva";199;2
"Unit";"Mutalisk";"Larva";201;2
"Unit";"Mutalisk";"Larva";203;2
"Unit";"Mutalisk";"Larva";205;2
"Building";"Extractor";NA;207;0
"Building";"Extractor";NA;207;0
"Unit";"Baneling";"Zergling";207;0
"Unit";"Baneling";"Zergling";207;0
"Unit";"Baneling";"Zergling";207;0
"Unit";"Baneling";"Zergling";207;0
"Unit";"Baneling";"Zergling";207;0
"Unit";"Baneling";"Zergling";207;0
"Unit";"Baneling";"Zergling";207;0
"Unit";"Baneling";"Zergling";207;0
"Unit";"Baneling";"Zergling";207;0
"Unit";"Baneling";"Zergling";207;0
"Unit";"Baneling";"Zergling";207;0
"Unit";"Baneling";"Zergling";207;0
"Unit";"Baneling";"Zergling";207;0
"Unit";"Baneling";"Zergling";207;0
"Unit";"Baneling";"Zergling";207;0
"Unit";"Baneling";"Zergling";207;0
"Unit";"Zergling";"Larva";207;1
"Unit";"Zergling";"Larva";208;1
"Unit";"Zergling";"Larva";209;1
"Unit";"Zergling";"Larva";210;1
"Unit";"Zergling";"Larva";211;1
"Unit";"Zergling";"Larva";212;1
"Unit";"Zergling";"Larva";213;1
"Unit";"Zergling";"Larva";214;1
"Unit";"Zergling";"Larva";215;1
"Unit";"Zergling";"Larva";216;1
"Unit";"Zergling";"Larva";217;1
"Unit";"Zergling";"Larva";218;1
"Unit";"Mutalisk";"Larva";219;2
"Unit";"Mutalisk";"Larva";221;2
"Unit";"Mutalisk";"Larva";223;2
"Unit";"Mutalisk";"Larva";225;2
"Building";"Hatchery";NA;227;0
"Unit";"Mutalisk";"Larva";231;2
"Unit";"Zergling";"Larva";233;1
"Unit";"Zergling";"Larva";234;1
"Unit";"Zergling";"Larva";235;1
"Unit";"Zergling";"Larva";236;1
"Unit";"Zergling";"Larva";237;1
"Unit";"Zergling";"Larva";238;1
"Unit";"Zergling";"Larva";239;1
"Unit";"Zergling";"Larva";240;1
"Unit";"Zergling";"Larva";241;1
"Unit";"Zergling";"Larva";242;1
"Unit";"Zergling";"Larva";243;1
"Unit";"Zergling";"Larva";244;1
"Unit";"Mutalisk";"Larva";245;2
"Unit";"Mutalisk";"Larva";247;2
"Unit";"Mutalisk";"Larva";249;2
"Unit";"Mutalisk";"Larva";251;2
"Unit";"Mutalisk";"Larva";253;2
"Unit";"Mutalisk";"Larva";255;2
"Unit";"Zergling";"Larva";257;1
"Unit";"Zergling";"Larva";258;1
"Unit";"Zergling";"Larva";259;1
"Unit";"Zergling";"Larva";260;1
"Unit";"Zergling";"Larva";261;1
"Unit";"Zergling";"Larva";262;1
"Unit";"Zergling";"Larva";263;1
"Unit";"Zergling";"Larva";264;1
"Unit";"Zergling";"Larva";265;1
"Unit";"Zergling";"Larva";266;1
"Unit";"Zergling";"Larva";267;1
"Unit";"Zergling";"Larva";268;1
"Unit";"Zergling";"Larva";269;1
"Unit";"Zergling";"Larva";270;1
"Unit";"Zergling";"Larva";271;1
"Unit";"Zergling";"Larva";272;1
"Unit";"Zergling";"Larva";273;1
"Unit";"Zergling";"Larva";274;1
"Unit";"Zergling";"Larva";275;1
"Unit";"Zergling";"Larva";276;1
"Unit";"Zergling";"Larva";277;1
"Unit";"Zergling";"Larva";278;1
"Unit";"Zergling";"Larva";279;1
"Unit";"Zergling";"Larva";280;1
"Unit";"Zergling";"Larva";281;1
"Unit";"Zergling";"Larva";282;1
"Unit";"Zergling";"Larva";283;1
"Unit";"Zergling";"Larva";284;1
"Building";"Hatchery";NA;285;0
"Building";"Extractor";NA;285;0
"Building";"HydraliskDen";NA;285;0
"Building";"InfestationPit";NA;285;0
"Building";"Extractor";NA;285;0
"Building";"EvolutionChamber";NA;285;0
"Unit";"Zergling";"Larva";293;1
"Unit";"Zergling";"Larva";294;1
"Unit";"Zergling";"Larva";295;1
"Unit";"Zergling";"Larva";296;1
"Unit";"Zergling";"Larva";297;1
"Unit";"Zergling";"Larva";298;1
"Unit";"Zergling";"Larva";299;1
"Unit";"Zergling";"Larva";300;1
"Unit";"Zergling";"Larva";301;1
"Unit";"Zergling";"Larva";302;1
"Unit";"Zergling";"Larva";303;1
"Unit";"Zergling";"Larva";304;1
"Unit";"Zergling";"Larva";305;1
"Unit";"Zergling";"Larva";306;1
"Unit";"Zergling";"Larva";307;1
"Unit";"Zergling";"Larva";308;1
"Unit";"Zergling";"Larva";309;1
"Unit";"Zergling";"Larva";310;1
"Unit";"Zergling";"Larva";311;1
"Unit";"Zergling";"Larva";312;1
"Unit";"Zergling";"Larva";313;1
"Unit";"Zergling";"Larva";314;1
"Building";"CreepTumor";NA;315;0
"Building";"CreepTumor";NA;315;0
"Unit";"Zergling";"Larva";315;1
"Unit";"Zergling";"Larva";316;1
"Unit";"Zergling";"Larva";317;1
"Unit";"Zergling";"Larva";318;1
"Unit";"Zergling";"Larva";319;1
"Unit";"Zergling";"Larva";320;1
"Unit";"Zergling";"Larva";321;1
"Unit";"Zergling";"Larva";322;1
"Unit";"Zergling";"Larva";323;1
"Unit";"Zergling";"Larva";324;1
"Unit";"Zergling";"Larva";325;1
"Unit";"Zergling";"Larva";326;1
"Unit";"Zergling";"Larva";327;1
"Unit";"Zergling";"Larva";328;1
"Unit";"Zergling";"Larva";329;1
"Unit";"Zergling";"Larva";330;1
"Unit";"Zergling";"Larva";331;1
"Unit";"Zergling";"Larva";332;1
"Unit";"Zergling";"Larva";333;1
"Unit";"Zergling";"Larva";334;1
"Unit";"Zergling";"Larva";335;1
"Unit";"Zergling";"Larva";336;1
"Building";"CreepTumor";NA;337;0
"Building";"CreepTumor";NA;337;0
"Building";"CreepTumor";NA;337;0
"Building";"CreepTumor";NA;337;0
"Building";"CreepTumor";NA;337;0
"Building";"CreepTumor";NA;337;0
"Unit";"Hydralisk";"Larva";337;2
"Unit";"Baneling";"Zergling";339;0
"Unit";"Baneling";"Zergling";339;0
"Unit";"Baneling";"Zergling";339;0
"Unit";"Baneling";"Zergling";339;0
"Unit";"Baneling";"Zergling";339;0
"Unit";"Baneling";"Zergling";339;0
"Unit";"Baneling";"Zergling";339;0
"Unit";"Baneling";"Zergling";339;0
"Unit";"Baneling";"Zergling";339;0
"Unit";"Baneling";"Zergling";339;0
"Unit";"Baneling";"Zergling";339;0
"Unit";"Baneling";"Zergling";339;0
"Unit";"Baneling";"Zergling";339;0
"Unit";"Baneling";"Zergling";339;0
"Unit";"Baneling";"Zergling";339;0
"Unit";"Baneling";"Zergling";339;0
"Unit";"Baneling";"Zergling";339;0
"Unit";"Baneling";"Zergling";339;0
"Unit";"Baneling";"Zergling";339;0
"Unit";"Baneling";"Zergling";339;0
"Unit";"Baneling";"Zergling";339;0
"Unit";"Baneling";"Zergling";339;0
"Unit";"Baneling";"Zergling";339;0
"Unit";"Baneling";"Zergling";339;0
"Unit";"Baneling";"Zergling";339;0
"Unit";"Baneling";"Zergling";339;0
"Unit";"Baneling";"Zergling";339;0
"Unit";"Baneling";"Zergling";339;0
"Unit";"Baneling";"Zergling";339;0
"Unit";"Baneling";"Zergling";339;0
"Unit";"Baneling";"Zergling";339;0
"Unit";"Baneling";"Zergling";339;0
"Unit";"Baneling";"Zergling";339;0
"Unit";"Baneling";"Zergling";339;0
"Unit";"Baneling";"Zergling";339;0
"Unit";"Baneling";"Zergling";339;0
"Unit";"Baneling";"Zergling";339;0
"Unit";"Baneling";"Zergling";339;0
"Unit";"Baneling";"Zergling";339;0
"Unit";"Baneling";"Zergling";339;0
"Unit";"Baneling";"Zergling";339;0
"Unit";"Baneling";"Zergling";339;0
"Unit";"Baneling";"Zergling";339;0
"Unit";"Baneling";"Zergling";339;0
"Unit";"Baneling";"Zergling";339;0
"Unit";"Baneling";"Zergling";339;0
"Unit";"Baneling";"Zergling";339;0
"Unit";"Baneling";"Zergling";339;0
"Unit";"Baneling";"Zergling";339;0
"Unit";"Baneling";"Zergling";339;0
"Unit";"Baneling";"Zergling";339;0
"Unit";"Zergling";"Larva";339;1
"Unit";"Zergling";"Larva";340;1
"Unit";"Zergling";"Larva";341;1
"Unit";"Zergling";"Larva";342;1
"Unit";"Zergling";"Larva";343;1
"Unit";"Zergling";"Larva";344;1
"Unit";"Zergling";"Larva";345;1
"Unit";"Zergling";"Larva";346;1
"Unit";"Zergling";"Larva";347;1
"Unit";"Zergling";"Larva";348;1
"Unit";"Zergling";"Larva";349;1
"Unit";"Zergling";"Larva";350;1
"Unit";"Zergling";"Larva";351;1
"Unit";"Zergling";"Larva";352;1
"Unit";"Zergling";"Larva";353;1
"Unit";"Zergling";"Larva";354;1
"Unit";"Zergling";"Larva";355;1
"Unit";"Zergling";"Larva";356;1
"Unit";"Zergling";"Larva";357;1
"Unit";"Zergling";"Larva";358;1
"Unit";"Zergling";"Larva";359;1
"Unit";"Zergling";"Larva";360;1
"Unit";"Zergling";"Larva";361;1
"Unit";"Zergling";"Larva";362;1
"Unit";"Zergling";"Larva";363;1
"Unit";"Zergling";"Larva";364;1
"Unit";"Zergling";"Larva";365;1
"Unit";"Zergling";"Larva";366;1
"Unit";"Zergling";"Larva";367;1
"Unit";"Zergling";"Larva";368;1
"Unit";"Zergling";"Larva";369;1
"Unit";"Zergling";"Larva";370;1
"Unit";"Zergling";"Larva";371;1
"Unit";"Zergling";"Larva";372;1
"Unit";"Zergling";"Larva";373;1
"Unit";"Zergling";"Larva";374;1
"Unit";"Zergling";"Larva";375;1
"Unit";"Zergling";"Larva";376;1
"Unit";"Zergling";"Larva";377;1
"Unit";"Zergling";"Larva";378;1
"Unit";"Zergling";"Larva";379;1
"Unit";"Zergling";"Larva";380;1
"Unit";"Zergling";"Larva";381;1
"Unit";"Zergling";"Larva";382;1
"Unit";"Zergling";"Larva";383;1
"Unit";"Zergling";"Larva";384;1
"Unit";"Zergling";"Larva";385;1
"Unit";"Zergling";"Larva";386;1
"Unit";"Zergling";"Larva";387;1
"Unit";"Zergling";"Larva";388;1
"Unit";"Zergling";"Larva";389;1
"Unit";"Zergling";"Larva";390;1
"Unit";"Hydralisk";"Larva";391;2
"Unit";"Hydralisk";"Larva";393;2
"Unit";"Hydralisk";"Larva";395;2
"Unit";"Hydralisk";"Larva";397;2
"Unit";"Hydralisk";"Larva";399;2
"Unit";"Hydralisk";"Larva";401;2
"Unit";"Hydralisk";"Larva";403;2
"Unit";"Hydralisk";"Larva";405;2
"Unit";"Hydralisk";"Larva";407;2
"Unit";"Hydralisk";"Larva";409;2
"Unit";"Hydralisk";"Larva";411;2
"Building";"SporeCrawler";NA;413;0
"Unit";"Hydralisk";"Larva";413;2
"Unit";"Hydralisk";"Larva";415;2
"Unit";"Hydralisk";"Larva";417;2
"Building";"SporeCrawler";NA;432;0
"Building";"CreepTumor";NA;432;0
"Building";"CreepTumor";NA;432;0
"Building";"CreepTumor";NA;432;0
"Building";"CreepTumor";NA;432;0
"Building";"CreepTumor";NA;432;0
"Building";"LurkerDenMP";NA;432;0
"Unit";"Overlord";"Larva";442;0
"Unit";"Overlord";"Larva";442;0
"Unit";"Overlord";"Larva";442;0
"Building";"CreepTumor";NA;442;0
"Unit";"Hydralisk";"Larva";442;2
"Unit";"Hydralisk";"Larva";444;2
"Unit";"Hydralisk";"Larva";446;2
"Unit";"Hydralisk";"Larva";448;2
"Unit";"Hydralisk";"Larva";450;2
"Building";"CreepTumor";NA;452;0
"Building";"CreepTumor";NA;452;0
"Unit";"Baneling";"Zergling";452;0
"Unit";"Baneling";"Zergling";452;0
"Unit";"Baneling";"Zergling";452;0
"Unit";"Baneling";"Zergling";452;0
"Unit";"Baneling";"Zergling";452;0
"Unit";"Baneling";"Zergling";452;0
"Unit";"Baneling";"Zergling";452;0
"Unit";"Baneling";"Zergling";452;0
"Unit";"Baneling";"Zergling";452;0
"Unit";"Baneling";"Zergling";452;0
"Unit";"Baneling";"Zergling";452;0
"Unit";"Baneling";"Zergling";452;0
"Unit";"Baneling";"Zergling";452;0
"Unit";"Baneling";"Zergling";452;0
"Unit";"Baneling";"Zergling";452;0
"Building";"Hatchery";NA;452;0
"Unit";"Hydralisk";"Larva";460;2
"Unit";"Hydralisk";"Larva";462;2
"Unit";"Hydralisk";"Larva";464;2
"Unit";"Hydralisk";"Larva";466;2
"Unit";"Overlord";"Larva";468;0
"Unit";"Overlord";"Larva";468;0
"Building";"SporeCrawler";NA;468;0
"Building";"SporeCrawler";NA;468;0
"Building";"SporeCrawler";NA;468;0
"Building";"SporeCrawler";NA;468;0
"Upgrade";"Burrow";"Hatchery";479;0
"Building";"Extractor";NA;481;0
"Unit";"Hydralisk";"Larva";481;2
"Unit";"Hydralisk";"Larva";483;2
"Unit";"Hydralisk";"Larva";485;2
"Unit";"Hydralisk";"Larva";487;2
"Unit";"Hydralisk";"Larva";489;2
"Unit";"Hydralisk";"Larva";493;2
"Unit";"Hydralisk";"Larva";495;2
"Unit";"Zergling";"Larva";497;1
"Unit";"Zergling";"Larva";498;1
"Unit";"Zergling";"Larva";499;1
"Unit";"Zergling";"Larva";500;1
"Unit";"Zergling";"Larva";501;1
"Unit";"Zergling";"Larva";502;1
"Unit";"Zergling";"Larva";503;1
"Unit";"Zergling";"Larva";504;1
"Unit";"Zergling";"Larva";505;1
"Unit";"Zergling";"Larva";506;1
"Unit";"Zergling";"Larva";507;1
"Unit";"Zergling";"Larva";508;1
"Unit";"Zergling";"Larva";509;1
"Unit";"Zergling";"Larva";510;1
"Unit";"Zergling";"Larva";511;1
"Unit";"Zergling";"Larva";512;1
"Unit";"Zergling";"Larva";513;1
"Unit";"Zergling";"Larva";514;1
"Unit";"Zergling";"Larva";515;1
"Unit";"Zergling";"Larva";516;1
"Unit";"Hydralisk";"Larva";527;2
"Unit";"Hydralisk";"Larva";529;2
"Unit";"Hydralisk";"Larva";531;2
"Unit";"Hydralisk";"Larva";533;2
"Unit";"Hydralisk";"Larva";535;2
"Unit";"Hydralisk";"Larva";537;2
"Unit";"Hydralisk";"Larva";539;2
"Unit";"Hydralisk";"Larva";541;2
"Unit";"Hydralisk";"Larva";543;2
"Building";"SpineCrawler";NA;545;0
"Unit";"Hydralisk";"Larva";545;2
"Unit";"Hydralisk";"Larva";547;2
"Unit";"Hydralisk";"Larva";549;2
"Unit";"Zergling";"Larva";551;1
"Unit";"Zergling";"Larva";552;1
"Unit";"Zergling";"Larva";553;1
"Unit";"Zergling";"Larva";554;1
"Unit";"Zergling";"Larva";555;1
"Unit";"Zergling";"Larva";556;1
"Unit";"Zergling";"Larva";557;1
"Unit";"Zergling";"Larva";558;1
"Unit";"Zergling";"Larva";559;1
"Unit";"Zergling";"Larva";560;1
"Unit";"Zergling";"Larva";561;1
"Unit";"Zergling";"Larva";562;1
"Unit";"Zergling";"Larva";563;1
"Unit";"Zergling";"Larva";564;1
"Unit";"Zergling";"Larva";565;1
"Unit";"Zergling";"Larva";566;1
"Unit";"Zergling";"Larva";567;1
"Unit";"Zergling";"Larva";568;1
"Unit";"Zergling";"Larva";569;1
"Unit";"Zergling";"Larva";570;1
"Unit";"Hydralisk";"Larva";576;2
"Unit";"Hydralisk";"Larva";578;2
"Unit";"Hydralisk";"Larva";580;2
"Unit";"Hydralisk";"Larva";582;2
"Building";"Hatchery";NA;584;0
"Unit";"Hydralisk";"Larva";584;2
"Unit";"Hydralisk";"Larva";586;2
"Unit";"Hydralisk";"Larva";588;2
"Unit";"Hydralisk";"Larva";590;2
"Unit";"Hydralisk";"Larva";592;2
"Unit";"Hydralisk";"Larva";594;2
"Unit";"Hydralisk";"Larva";596;2
"Unit";"Hydralisk";"Larva";598;2
"Unit";"Hydralisk";"Larva";600;2
"Unit";"Zergling";"Larva";602;1
"Unit";"Zergling";"Larva";603;1
"Unit";"Zergling";"Larva";604;1
"Unit";"Zergling";"Larva";605;1
"Unit";"Zergling";"Larva";606;1
"Unit";"Zergling";"Larva";607;1
"Unit";"Zergling";"Larva";608;1
"Unit";"Zergling";"Larva";609;1
"Unit";"Zergling";"Larva";610;1
"Unit";"Zergling";"Larva";611;1
"Unit";"Hydralisk";"Larva";612;2
"Unit";"Hydralisk";"Larva";614;2
"Unit";"Hydralisk";"Larva";616;2
"Unit";"Hydralisk";"Larva";618;2
"Unit";"Hydralisk";"Larva";620;2
"Unit";"Zergling";"Larva";622;1
"Unit";"Zergling";"Larva";623;1
"Unit";"Overlord";"Larva";624;0
"Building";"Extractor";NA;624;0
"Building";"SpineCrawler";NA;625;0
"Building";"SpineCrawler";NA;626;0
"Unit";"Hydralisk";"Larva";626;2
"Unit";"Hydralisk";"Larva";628;2
"Unit";"Hydralisk";"Larva";630;2
"Unit";"Hydralisk";"Larva";632;2
"Unit";"Hydralisk";"Larva";634;2
"Unit";"Hydralisk";"Larva";636;2
"Unit";"Hydralisk";"Larva";638;2
"Unit";"Hydralisk";"Larva";640;2
"Unit";"Hydralisk";"Larva";642;2
"Unit";"Hydralisk";"Larva";644;2
"Unit";"Hydralisk";"Larva";646;2
"Unit";"Roach";"Larva";648;2
"Unit";"Roach";"Larva";650;2
"Unit";"Roach";"Larva";652;2
"Unit";"Roach";"Larva";654;2
"Unit";"Roach";"Larva";656;2
"Building";"Spire";NA;658;0
"Unit";"Hydralisk";"Larva";658;2
"Unit";"Zergling";"Larva";660;1
"Unit";"Zergling";"Larva";661;1
"Unit";"Overlord";"Larva";662;0
"Unit";"Hydralisk";"Larva";662;2
"Unit";"Hydralisk";"Larva";664;2
"Unit";"Hydralisk";"Larva";666;2
"Unit";"Hydralisk";"Larva";668;2
"Unit";"Hydralisk";"Larva";670;2
"Unit";"Hydralisk";"Larva";672;2
"Unit";"Hydralisk";"Larva";674;2
"Unit";"Hydralisk";"Larva";676;2
"Unit";"Hydralisk";"Larva";678;2
"Unit";"Hydralisk";"Larva";680;2
"Unit";"Hydralisk";"Larva";682;2
"Unit";"Hydralisk";"Larva";684;2
"Unit";"Hydralisk";"Larva";686;2
"Unit";"Hydralisk";"Larva";688;2
"Unit";"Hydralisk";"Larva";690;2
"Unit";"Hydralisk";"Larva";692;2
"Unit";"Hydralisk";"Larva";694;2
"Unit";"Hydralisk";"Larva";696;2
"Unit";"Hydralisk";"Larva";698;2
"Unit";"Queen";"Hatchery";700;2
"Unit";"Queen";"Hatchery";702;2
"Unit";"Queen";"Hatchery";704;2
"Unit";"Queen";"Hatchery";706;2
"Unit";"Queen";"Hatchery";708;2
"Building";"Extractor";NA;710;0
"Unit";"Hydralisk";"Larva";710;2
"Unit";"Hydralisk";"Larva";712;2
"Unit";"Hydralisk";"Larva";714;2
"Building";"Extractor";NA;716;0
"Unit";"Hydralisk";"Larva";716;2
"Unit";"Hydralisk";"Larva";718;2
"Unit";"Hydralisk";"Larva";720;2
"Unit";"Hydralisk";"Larva";722;2
"Unit";"Hydralisk";"Larva";724;2
"Unit";"Hydralisk";"Larva";726;2
"Unit";"Hydralisk";"Larva";728;2
"Unit";"Hydralisk";"Larva";730;2
"Unit";"Hydralisk";"Larva";732;2
"Unit";"Hydralisk";"Larva";734;2
"Unit";"Hydralisk";"Larva";736;2
"Unit";"Hydralisk";"Larva";738;2
"Unit";"Hydralisk";"Larva";740;2
"Unit";"Hydralisk";"Larva";742;2
"Unit";"Hydralisk";"Larva";744;2
"Unit";"Hydralisk";"Larva";746;2
"Unit";"Hydralisk";"Larva";748;2
"Unit";"Hydralisk";"Larva";750;2
"Unit";"Hydralisk";"Larva";752;2
"Upgrade";"SprayZerg";NA;754;0
"Upgrade";"SprayZerg";NA;754;0
"Upgrade";"SprayZerg";NA;754;0
"Upgrade";"zerglingmovementspeed";NA;754;0
"Upgrade";"SprayZerg";NA;754;0
"Upgrade";"SprayZerg";NA;754;0
"Upgrade";"CentrificalHooks";NA;754;0
"Upgrade";"ZergMeleeWeaponsLevel1";NA;754;0
"Upgrade";"SprayZerg";NA;754;0
"Upgrade";"SprayZerg";NA;754;0
"Upgrade";"SprayZerg";NA;754;0
"Upgrade";"SprayZerg";NA;754;0
"Upgrade";"SprayZerg";NA;754;0
"Upgrade";"SprayZerg";NA;754;0
"Upgrade";"ZergMeleeWeaponsLevel2";NA;754;0
"Upgrade";"EvolveGroovedSpines";NA;754;0
"Upgrade";"ZergMissileWeaponsLevel1";NA;754;0
"Upgrade";"EvolveMuscularAugments";NA;754;0
"Upgrade";"SprayZerg";NA;754;0
"Upgrade";"SprayZerg";NA;754;0
"Upgrade";"zerglingattackspeed";NA;754;0
"Upgrade";"overlordspeed";NA;754;0
"Upgrade";"DiggingClaws";NA;754;0
"Upgrade";"ZergMissileWeaponsLevel2";NA;754;0
"Upgrade";"ZergGroundArmorsLevel1";NA;754;0
"Upgrade";"SprayZerg";NA;754;0
"Upgrade";"SprayZerg";NA;754;0
"Upgrade";"ZergGroundArmorsLevel2";NA;754;0
"Upgrade";"ZergMissileWeaponsLevel3";NA;754;0
"Upgrade";"SprayZerg";NA;754;0
"Upgrade";"SprayZerg";NA;754;0
