"type";"unit_name";"on_building";"total_supply";"supply"
"Unit";"Overlord";"Larva";13;0
"Building";"Extractor";NA;17;0
"Unit";"Overlord";"Larva";21;0
"Building";"SpawningPool";NA;19;0
"Building";"Hatchery";NA;17;0
"Unit";"Queen";"Hatchery";22;2
"Unit";"Queen";"Hatchery";23;2
"Unit";"Overlord";"Larva";31;0
"Unit";"Zergling";"Larva";32;1
"Unit";"Zergling";"Larva";32;1
"Unit";"Zergling";"Larva";35;1
"Unit";"Zergling";"Larva";35;1
"Unit";"Overlord";"Larva";35;0
"Unit";"Queen";"Hatchery";39;2
"Unit";"Queen";"Hatchery";39;2
"Building";"Hatchery";NA;31;0
"Building";"Extractor";NA;48;0
"Unit";"Overlord";"Larva";49;0
"Unit";"Overlord";"Larva";49;0
"Unit";"Overlord";"Larva";49;0
"Building";"CreepTumorQueen";NA;53;0
"Building";"CreepTumorQueen";NA;53;0
"Building";"RoachWarren";NA;49;0
"Building";"CreepTumor";NA;62;0
"Unit";"Queen";"Hatchery";53;2
"Unit";"Overlord";"Larva";53;0
"Unit";"Overlord";"Larva";54;0
"Building";"CreepTumorQueen";NA;64;0
"Building";"CreepTumorQueen";NA;64;0
"Unit";"Queen";"Hatchery";53;2
"Building";"CreepTumor";NA;64;0
"Building";"EvolutionChamber";NA;64;0
"Building";"Extractor";NA;64;0
"Unit";"Overlord";"Larva";64;0
"Building";"CreepTumor";NA;77;0
"Building";"CreepTumor";NA;77;0
"Building";"CreepTumor";NA;77;0
"Building";"CreepTumorQueen";NA;77;0
"Building";"CreepTumorQueen";NA;77;0
"Building";"CreepTumorQueen";NA;77;0
"Unit";"Roach";"Larva";77;2
"Unit";"Roach";"Larva";77;2
"Unit";"Roach";"Larva";77;2
"Unit";"Roach";"Larva";77;2
"Unit";"Roach";"Larva";77;2
"Unit";"Roach";"Larva";77;2
"Unit";"Roach";"Larva";77;2
"Building";"Extractor";NA;77;0
"Unit";"Overlord";"Larva";77;0
"Unit";"Overlord";"Larva";77;0
"Unit";"Overlord";"Larva";77;0
"Building";"HydraliskDen";NA;77;0
"Unit";"Roach";"Larva";77;2
"Unit";"Overlord";"Larva";77;0
"Unit";"Overlord";"Larva";77;0
"Unit";"Overlord";"Larva";77;0
"Building";"CreepTumor";NA;93;0
"Building";"CreepTumor";NA;93;0
"Building";"CreepTumorQueen";NA;93;0
"Building";"CreepTumorQueen";NA;93;0
"Building";"SporeCrawler";NA;91;0
"Building";"CreepTumor";NA;93;0
"Building";"SporeCrawler";NA;91;0
"Building";"SporeCrawler";NA;93;0
"Building";"Extractor";NA;93;0
"Unit";"Roach";"Larva";93;2
"Unit";"Roach";"Larva";93;2
"Unit";"Roach";"Larva";93;2
"Unit";"Roach";"Larva";93;2
"Unit";"Roach";"Larva";93;2
"Unit";"Roach";"Larva";93;2
"Building";"CreepTumor";NA;96;0
"Building";"CreepTumor";NA;98;0
"Unit";"Roach";"Larva";93;2
"Building";"CreepTumor";NA;99;0
"Building";"CreepTumor";NA;99;0
"Building";"CreepTumor";NA;99;0
"Building";"CreepTumorQueen";NA;99;0
"Building";"CreepTumorQueen";NA;99;0
"Building";"CreepTumorQueen";NA;99;0
"Building";"CreepTumor";NA;101;0
"Building";"CreepTumor";NA;101;0
"Unit";"Roach";"Larva";113;2
"Unit";"Roach";"Larva";113;2
"Unit";"Roach";"Larva";113;2
"Unit";"Roach";"Larva";113;2
"Unit";"Roach";"Larva";113;2
"Unit";"Roach";"Larva";113;2
"Unit";"Overlord";"Larva";113;0
"Building";"Extractor";NA;113;0
"Building";"CreepTumorQueen";NA;128;0
"Upgrade";"ZergMissileWeaponsLevel1";"EvolutionChamber";93;0
"Unit";"Hydralisk";"Larva";113;2
"Unit";"Hydralisk";"Larva";113;2
"Unit";"Hydralisk";"Larva";113;2
"Unit";"Hydralisk";"Larva";113;2
"Upgrade";"GlialReconstitution";"RoachWarren";99;0
"Unit";"Hydralisk";"Larva";128;2
"Unit";"Hydralisk";"Larva";128;2
"Unit";"Hydralisk";"Larva";130;2
"Unit";"Hydralisk";"Larva";130;2
"Unit";"Hydralisk";"Larva";130;2
"Unit";"Hydralisk";"Larva";130;2
"Upgrade";"EvolveGroovedSpines";"HydraliskDen";113;0
"Building";"CreepTumor";NA;150;0
"Building";"CreepTumor";NA;150;0
"Building";"InfestationPit";NA;136;0
"Unit";"Overlord";"Larva";150;0
"Unit";"Overlord";"Larva";150;0
"Unit";"Overlord";"Larva";150;0
"Unit";"Overlord";"Larva";150;0
"Unit";"Overlord";"Larva";150;0
"Unit";"Overlord";"Larva";150;0
"Building";"CreepTumor";NA;152;0
"Building";"CreepTumor";NA;153;0
"Building";"CreepTumor";NA;153;0
"Building";"CreepTumor";NA;153;0
"Building";"CreepTumor";NA;153;0
"Building";"CreepTumor";NA;153;0
"Building";"CreepTumorQueen";NA;153;0
"Building";"CreepTumorQueen";NA;153;0
"Building";"CreepTumorQueen";NA;153;0
"Building";"CreepTumor";NA;153;0
"Building";"CreepTumor";NA;153;0
"Building";"CreepTumor";NA;153;0
"Building";"Hatchery";NA;136;0
"Building";"CreepTumor";NA;163;0
"Building";"CreepTumor";NA;163;0
"Unit";"Hydralisk";"Larva";163;2
"Unit";"Hydralisk";"Larva";163;2
"Building";"CreepTumor";NA;163;0
"Building";"CreepTumorQueen";NA;163;0
"Unit";"Hydralisk";"Larva";163;2
"Unit";"Hydralisk";"Larva";163;2
"Building";"CreepTumor";NA;163;0
"Unit";"Hydralisk";"Larva";163;2
"Unit";"Hydralisk";"Larva";163;2
"Building";"CreepTumor";NA;163;0
"Building";"CreepTumorQueen";NA;163;0
"Building";"CreepTumor";NA;163;0
"Building";"CreepTumorQueen";NA;163;0
"Building";"Extractor";NA;163;0
"Building";"Extractor";NA;163;0
"Building";"LurkerDenMP";NA;136;0
"Building";"CreepTumor";NA;163;0
"Building";"CreepTumor";NA;163;0
"Building";"CreepTumor";NA;163;0
"Building";"CreepTumor";NA;163;0
"Building";"CreepTumor";NA;163;0
"Upgrade";"EvolveMuscularAugments";"HydraliskDen";153;0
"Building";"CreepTumor";NA;171;0
"Unit";"Overlord";"Larva";175;0
"Unit";"Overlord";"Larva";175;0
"Unit";"Overlord";"Larva";175;0
"Building";"CreepTumorQueen";NA;181;0
"Building";"CreepTumorQueen";NA;181;0
"Building";"CreepTumorQueen";NA;181;0
"Building";"CreepTumor";NA;181;0
"Building";"CreepTumor";NA;181;0
"Building";"CreepTumor";NA;181;0
"Building";"CreepTumor";NA;181;0
"Building";"CreepTumor";NA;181;0
"Building";"CreepTumor";NA;181;0
"Building";"CreepTumor";NA;181;0
"Building";"CreepTumor";NA;181;0
"Building";"CreepTumor";NA;181;0
"Building";"CreepTumor";NA;181;0
"Building";"CreepTumor";NA;181;0
"Building";"CreepTumor";NA;181;0
"Building";"CreepTumor";NA;181;0
"Building";"CreepTumor";NA;181;0
"Building";"CreepTumor";NA;181;0
"Building";"CreepTumor";NA;181;0
"Building";"CreepTumor";NA;181;0
"Building";"CreepTumor";NA;181;0
"Building";"CreepTumor";NA;181;0
"Building";"CreepTumor";NA;181;0
"Upgrade";"ZergMissileWeaponsLevel2";"EvolutionChamber";163;0
"Unit";"Hydralisk";"Larva";181;2
"Unit";"Hydralisk";"Larva";181;2
"Unit";"Hydralisk";"Larva";181;2
"Unit";"Hydralisk";"Larva";181;2
"Building";"CreepTumor";NA;181;0
"Building";"CreepTumor";NA;181;0
"Building";"CreepTumor";NA;181;0
"Building";"CreepTumor";NA;181;0
"Building";"CreepTumor";NA;181;0
"Building";"CreepTumor";NA;181;0
"Building";"CreepTumorQueen";NA;189;0
"Building";"CreepTumorQueen";NA;189;0
"Building";"CreepTumorQueen";NA;189;0
"Unit";"Hydralisk";"Larva";189;2
"Unit";"Hydralisk";"Larva";189;2
"Unit";"Hydralisk";"Larva";189;2
"Unit";"Hydralisk";"Larva";189;2
"Unit";"Hydralisk";"Larva";189;2
"Unit";"Hydralisk";"Larva";189;2
"Unit";"Hydralisk";"Larva";189;2
"Unit";"Hydralisk";"Larva";189;2
"Unit";"Hydralisk";"Larva";189;2
"Unit";"Hydralisk";"Larva";191;2
"Unit";"Hydralisk";"Larva";191;2
