"type";"unit_name";"on_building";"total_supply";"supply"
"Unit";"Overlord";"Larva";13;0
"Building";"Extractor";NA;18;0
"Building";"SpawningPool";NA;19;0
"Building";"Hatchery";NA;17;0
"Unit";"Queen";"Hatchery";23;2
"Unit";"Overlord";"Larva";25;0
"Building";"Hatchery";NA;23;0
"Unit";"Overlord";"Larva";30;0
"Unit";"Queen";"Hatchery";26;2
"Unit";"Queen";"Hatchery";30;2
"Unit";"Zergling";"Larva";32;1
"Unit";"Zergling";"Larva";32;1
"Unit";"Zergling";"Larva";32;1
"Unit";"Zergling";"Larva";32;1
"Unit";"Zergling";"Larva";32;1
"Unit";"Zergling";"Larva";32;1
"Unit";"Zergling";"Larva";36;1
"Unit";"Zergling";"Larva";36;1
"Unit";"Zergling";"Larva";36;1
"Unit";"Zergling";"Larva";36;1
"Unit";"Zergling";"Larva";36;1
"Unit";"Zergling";"Larva";36;1
"Unit";"Zergling";"Larva";36;1
"Unit";"Zergling";"Larva";36;1
"Building";"CreepTumorQueen";NA;44;0
"Unit";"Overlord";"Larva";42;0
"Unit";"Zergling";"Larva";44;1
"Unit";"Zergling";"Larva";44;1
"Unit";"Overlord";"Larva";52;0
"Unit";"Zergling";"Larva";52;1
"Unit";"Zergling";"Larva";52;1
"Building";"CreepTumorQueen";NA;52;0
"Building";"CreepTumor";NA;57;0
"Building";"CreepTumor";NA;69;0
"Building";"Extractor";NA;69;0
"Building";"Extractor";NA;69;0
"Building";"Extractor";NA;73;0
"Building";"CreepTumor";NA;81;0
"Unit";"Overlord";"Larva";77;0
"Building";"HydraliskDen";NA;76;0
"Building";"SporeCrawler";NA;80;0
"Building";"SporeCrawler";NA;80;0
"Building";"SporeCrawler";NA;81;0
"Unit";"Overlord";"Larva";84;0
"Unit";"Overlord";"Larva";84;0
"Unit";"Overlord";"Larva";84;0
"Building";"CreepTumor";NA;85;0
"Unit";"Hydralisk";"Larva";85;2
"Unit";"Hydralisk";"Larva";86;2
"Unit";"Hydralisk";"Larva";87;2
"Unit";"Overlord";"Larva";89;0
"Unit";"Hydralisk";"Larva";89;2
"Unit";"Hydralisk";"Larva";89;2
"Unit";"Hydralisk";"Larva";89;2
"Unit";"Zergling";"Larva";91;1
"Unit";"Zergling";"Larva";91;1
"Unit";"Zergling";"Larva";93;1
"Unit";"Zergling";"Larva";93;1
"Unit";"Zergling";"Larva";93;1
"Unit";"Zergling";"Larva";93;1
"Unit";"Zergling";"Larva";93;1
"Unit";"Zergling";"Larva";93;1
"Unit";"Zergling";"Larva";93;1
"Unit";"Zergling";"Larva";93;1
"Unit";"Zergling";"Larva";93;1
"Unit";"Zergling";"Larva";93;1
"Unit";"Zergling";"Larva";93;1
"Unit";"Zergling";"Larva";93;1
"Unit";"Hydralisk";"Larva";89;2
"Building";"CreepTumor";NA;95;0
"Building";"CreepTumor";NA;99;0
"Unit";"Hydralisk";"Larva";95;2
"Unit";"Hydralisk";"Larva";95;2
"Unit";"Overlord";"Larva";101;0
"Unit";"Overlord";"Larva";101;0
"Unit";"Overlord";"Larva";101;0
"Unit";"Hydralisk";"Larva";99;2
"Unit";"Overlord";"Larva";117;0
"Unit";"Hydralisk";"Larva";117;2
"Upgrade";"EvolveMuscularAugments";"HydraliskDen";89;0
"Unit";"Zergling";"Larva";117;1
"Unit";"Zergling";"Larva";117;1
"Unit";"Zergling";"Larva";117;1
"Unit";"Zergling";"Larva";117;1
"Unit";"Hydralisk";"Larva";117;2
"Unit";"Zergling";"Larva";121;1
"Unit";"Zergling";"Larva";121;1
"Unit";"Zergling";"Larva";121;1
"Unit";"Zergling";"Larva";121;1
"Unit";"Zergling";"Larva";121;1
"Unit";"Zergling";"Larva";121;1
"Unit";"Hydralisk";"Larva";117;2
"Unit";"Zergling";"Larva";123;1
"Unit";"Zergling";"Larva";123;1
"Unit";"Zergling";"Larva";123;1
"Unit";"Zergling";"Larva";123;1
"Unit";"Zergling";"Larva";123;1
"Unit";"Zergling";"Larva";123;1
"Unit";"Hydralisk";"Larva";123;2
"Building";"CreepTumor";NA;133;0
"Unit";"Hydralisk";"Larva";123;2
"Unit";"Hydralisk";"Larva";127;2
"Unit";"Zergling";"Larva";139;1
"Unit";"Zergling";"Larva";139;1
"Unit";"Zergling";"Larva";139;1
"Unit";"Zergling";"Larva";139;1
"Unit";"Zergling";"Larva";139;1
"Unit";"Zergling";"Larva";139;1
"Unit";"Hydralisk";"Larva";131;2
"Unit";"Zergling";"Larva";139;1
"Unit";"Zergling";"Larva";139;1
"Unit";"Zergling";"Larva";139;1
"Unit";"Zergling";"Larva";139;1
"Unit";"Zergling";"Larva";139;1
"Unit";"Zergling";"Larva";139;1
"Unit";"Zergling";"Larva";139;1
"Unit";"Zergling";"Larva";139;1
"Building";"CreepTumor";NA;147;0
"Unit";"Zergling";"Larva";141;1
"Unit";"Zergling";"Larva";141;1
"Building";"SpineCrawler";NA;123;0
"Unit";"Hydralisk";"Larva";147;2
"Unit";"Hydralisk";"Larva";149;2
"Unit";"Hydralisk";"Larva";149;2
"Unit";"Zergling";"Larva";169;1
"Unit";"Zergling";"Larva";169;1
"Unit";"Hydralisk";"Larva";155;2
"Unit";"Overlord";"Larva";169;0
"Unit";"Overlord";"Larva";169;0
"Unit";"Hydralisk";"Larva";169;2
"Unit";"Hydralisk";"Larva";169;2
"Unit";"Overlord";"Larva";175;0
"Unit";"Zergling";"Larva";179;1
"Unit";"Zergling";"Larva";179;1
"Unit";"Zergling";"Larva";179;1
"Unit";"Zergling";"Larva";179;1
"Unit";"Zergling";"Larva";179;1
"Unit";"Zergling";"Larva";179;1
"Unit";"Zergling";"Larva";179;1
"Unit";"Zergling";"Larva";179;1
"Unit";"Zergling";"Larva";179;1
"Unit";"Zergling";"Larva";179;1
"Unit";"Zergling";"Larva";179;1
"Unit";"Zergling";"Larva";179;1
"Unit";"Zergling";"Larva";179;1
"Unit";"Zergling";"Larva";179;1
"Unit";"Zergling";"Larva";179;1
"Unit";"Zergling";"Larva";179;1
"Unit";"Zergling";"Larva";179;1
"Unit";"Zergling";"Larva";179;1
"Unit";"Zergling";"Larva";179;1
"Unit";"Zergling";"Larva";179;1
"Unit";"Hydralisk";"Larva";181;2
"Unit";"Hydralisk";"Larva";183;2
"Unit";"Hydralisk";"Larva";183;2
"Unit";"Hydralisk";"Larva";185;2
"Unit";"Hydralisk";"Larva";203;2
"Unit";"Hydralisk";"Larva";203;2
"Building";"CreepTumor";NA;207;0
"Unit";"Hydralisk";"Larva";203;2
"Unit";"Zergling";"Larva";209;1
"Unit";"Zergling";"Larva";209;1
"Building";"CreepTumor";NA;211;0
"Unit";"Hydralisk";"Larva";205;2
"Unit";"Hydralisk";"Larva";207;2
"Unit";"Zergling";"Larva";211;1
"Unit";"Zergling";"Larva";211;1
"Unit";"Zergling";"Larva";211;1
"Unit";"Zergling";"Larva";211;1
"Unit";"Zergling";"Larva";211;1
"Unit";"Zergling";"Larva";211;1
"Unit";"Zergling";"Larva";211;1
"Unit";"Zergling";"Larva";211;1
"Unit";"Zergling";"Larva";211;1
"Unit";"Zergling";"Larva";211;1
"Unit";"Zergling";"Larva";211;1
"Unit";"Zergling";"Larva";211;1
"Unit";"Zergling";"Larva";211;1
"Unit";"Zergling";"Larva";211;1
"Unit";"Zergling";"Larva";211;1
"Unit";"Zergling";"Larva";211;1
"Unit";"Hydralisk";"Larva";211;2
"Unit";"Zergling";"Larva";217;1
"Unit";"Zergling";"Larva";217;1
"Unit";"Hydralisk";"Larva";215;2
"Unit";"Hydralisk";"Larva";221;2
"Unit";"Hydralisk";"Larva";221;2
"Unit";"Zergling";"Larva";243;1
"Unit";"Zergling";"Larva";243;1
"Building";"CreepTumor";NA;245;0
"Unit";"Hydralisk";"Larva";239;2
"Unit";"Overlord";"Larva";245;0
"Unit";"Overlord";"Larva";245;0
"Unit";"Hydralisk";"Larva";245;2
"Unit";"Hydralisk";"Larva";245;2
"Building";"Extractor";NA;245;0
"Unit";"Hydralisk";"Larva";245;2
"Unit";"Hydralisk";"Larva";249;2
"Unit";"Overlord";"Larva";259;0
"Building";"CreepTumor";NA;259;0
"Unit";"Hydralisk";"Larva";259;2
"Unit";"Zergling";"Larva";263;1
"Unit";"Zergling";"Larva";263;1
"Unit";"Zergling";"Larva";263;1
"Unit";"Zergling";"Larva";263;1
"Unit";"Zergling";"Larva";263;1
"Unit";"Zergling";"Larva";263;1
"Unit";"Zergling";"Larva";263;1
"Unit";"Zergling";"Larva";263;1
"Unit";"Zergling";"Larva";263;1
"Unit";"Zergling";"Larva";263;1
"Unit";"Zergling";"Larva";263;1
"Unit";"Zergling";"Larva";263;1
"Unit";"Zergling";"Larva";263;1
"Unit";"Zergling";"Larva";263;1
"Unit";"Zergling";"Larva";263;1
"Unit";"Zergling";"Larva";263;1
"Building";"CreepTumor";NA;267;0
"Unit";"Hydralisk";"Larva";263;2
"Unit";"Hydralisk";"Larva";263;2
"Unit";"Hydralisk";"Larva";263;2
"Building";"Hatchery";NA;221;0
"Unit";"Hydralisk";"Larva";269;2
"Unit";"Hydralisk";"Larva";269;2
"Building";"CreepTumor";NA;294;0
"Unit";"Zergling";"Larva";291;1
"Unit";"Zergling";"Larva";291;1
"Unit";"Hydralisk";"Larva";289;2
"Unit";"Zergling";"Larva";294;1
"Unit";"Zergling";"Larva";294;1
"Unit";"Zergling";"Larva";294;1
"Unit";"Zergling";"Larva";294;1
"Unit";"Zergling";"Larva";294;1
"Unit";"Zergling";"Larva";294;1
"Unit";"Hydralisk";"Larva";291;2
"Unit";"Hydralisk";"Larva";294;2
"Unit";"Hydralisk";"Larva";294;2
"Unit";"Overlord";"Larva";299;0
"Unit";"Overlord";"Larva";299;0
"Building";"CreepTumor";NA;309;0
"Unit";"Hydralisk";"Larva";301;2
"Building";"SpineCrawler";NA;299;0
"Unit";"Hydralisk";"Larva";315;2
"Unit";"Hydralisk";"Larva";315;2
"Unit";"Hydralisk";"Larva";315;2
"Unit";"Hydralisk";"Larva";315;2
"Unit";"Hydralisk";"Larva";315;2
"Unit";"Hydralisk";"Larva";315;2
"Unit";"Zergling";"Larva";317;1
"Unit";"Zergling";"Larva";317;1
"Unit";"Zergling";"Larva";317;1
"Unit";"Zergling";"Larva";317;1
"Unit";"Zergling";"Larva";317;1
"Unit";"Zergling";"Larva";317;1
"Unit";"Zergling";"Larva";317;1
"Unit";"Zergling";"Larva";317;1
"Upgrade";"EvolveGroovedSpines";"HydraliskDen";294;0
"Unit";"Overlord";"Larva";317;0
"Unit";"Overlord";"Larva";317;0
"Unit";"Overlord";"Larva";317;0
"Building";"CreepTumor";NA;337;0
"Unit";"Hydralisk";"Larva";337;2
"Unit";"Hydralisk";"Larva";337;2
"Unit";"Hydralisk";"Larva";337;2
"Unit";"Hydralisk";"Larva";337;2
"Unit";"Hydralisk";"Larva";337;2
"Unit";"Hydralisk";"Larva";337;2
"Unit";"Hydralisk";"Larva";337;2
"Building";"EvolutionChamber";NA;337;0
"Unit";"Hydralisk";"Larva";352;2
"Unit";"Hydralisk";"Larva";352;2
"Unit";"Hydralisk";"Larva";352;2
"Unit";"Hydralisk";"Larva";352;2
"Building";"EvolutionChamber";NA;352;0
"Unit";"Zergling";"Larva";360;1
"Unit";"Zergling";"Larva";360;1
