"type";"unit_name";"on_building";"total_supply";"supply"
"Unit";"Overlord";"Larva";13;0
"Building";"Extractor";NA;17;0
"Building";"Hatchery";NA;16;0
"Building";"SpawningPool";NA;20;0
"Unit";"Overlord";"Larva";22;0
"Unit";"Zergling";"Larva";26;1
"Unit";"Zergling";"Larva";26;1
"Unit";"Zergling";"Larva";26;1
"Unit";"Zergling";"Larva";26;1
"Unit";"Zergling";"Larva";26;1
"Unit";"Zergling";"Larva";26;1
"Unit";"Queen";"Hatchery";26;2
"Unit";"Zergling";"Larva";28;1
"Unit";"Zergling";"Larva";28;1
"Unit";"Zergling";"Larva";29;1
"Unit";"Zergling";"Larva";29;1
"Unit";"Zergling";"Larva";34;1
"Unit";"Zergling";"Larva";34;1
"Unit";"Zergling";"Larva";34;1
"Unit";"Zergling";"Larva";34;1
"Unit";"Zergling";"Larva";40;1
"Unit";"Zergling";"Larva";40;1
"Unit";"Overlord";"Larva";44;0
"Unit";"Overlord";"Larva";44;0
"Building";"Extractor";NA;44;0
"Unit";"Queen";"Hatchery";40;2
"Unit";"Overlord";"Larva";47;0
"Building";"BanelingNest";NA;40;0
"Building";"Hatchery";NA;34;0
"Unit";"Queen";"Hatchery";56;2
"Building";"CreepTumorQueen";NA;70;0
"Building";"Extractor";NA;70;0
"Building";"SporeCrawler";NA;74;0
"Building";"SporeCrawler";NA;74;0
"Building";"RoachWarren";NA;70;0
"Building";"EvolutionChamber";NA;74;0
"Unit";"Queen";"Hatchery";70;2
"Building";"CreepTumor";NA;77;0
"Building";"EvolutionChamber";NA;74;0
"Building";"CreepTumorQueen";NA;77;0
"Unit";"Overlord";"Larva";77;0
"Unit";"Overlord";"Larva";77;0
"Unit";"Overlord";"Larva";80;0
"Unit";"Overlord";"Larva";80;0
"Building";"Extractor";NA;80;0
"Unit";"Roach";"Larva";80;2
"Unit";"Roach";"Larva";80;2
"Unit";"Roach";"Larva";80;2
"Unit";"Roach";"Larva";80;2
"Unit";"Roach";"Larva";80;2
"Building";"HydraliskDen";NA;80;0
"Building";"CreepTumor";NA;80;0
"Building";"CreepTumorQueen";NA;84;0
"Unit";"Roach";"Larva";80;2
"Unit";"Roach";"Larva";80;2
"Unit";"Roach";"Larva";80;2
"Unit";"Roach";"Larva";80;2
"Unit";"Roach";"Larva";86;2
"Unit";"Roach";"Larva";86;2
"Unit";"Roach";"Larva";86;2
"Unit";"Overlord";"Larva";90;0
"Building";"CreepTumor";NA;104;0
"Building";"CreepTumor";NA;110;0
"Building";"CreepTumorQueen";NA;110;0
"Unit";"Hydralisk";"Larva";104;2
"Upgrade";"GlialReconstitution";"RoachWarren";86;0
"Unit";"Hydralisk";"Larva";110;2
"Unit";"Hydralisk";"Larva";110;2
"Unit";"Hydralisk";"Larva";110;2
"Unit";"Hydralisk";"Larva";110;2
"Building";"CreepTumor";NA;114;0
"Unit";"Overlord";"Larva";112;0
"Building";"CreepTumor";NA;115;0
"Unit";"Hydralisk";"Larva";112;2
"Unit";"Overlord";"Larva";114;0
"Upgrade";"ZergMissileWeaponsLevel1";"EvolutionChamber";90;0
"Upgrade";"ZergGroundArmorsLevel1";"EvolutionChamber";90;0
"Unit";"Hydralisk";"Larva";121;2
"Unit";"Hydralisk";"Larva";121;2
"Unit";"Hydralisk";"Larva";121;2
"Unit";"Hydralisk";"Larva";121;2
"Upgrade";"EvolveMuscularAugments";"HydraliskDen";110;0
"Unit";"Overlord";"Larva";123;0
"Unit";"Hydralisk";"Larva";123;2
"Unit";"Hydralisk";"Larva";123;2
"Unit";"Hydralisk";"Larva";123;2
"Unit";"Hydralisk";"Larva";123;2
"Unit";"Hydralisk";"Larva";131;2
"Unit";"Hydralisk";"Larva";131;2
"Unit";"Hydralisk";"Larva";131;2
"Unit";"Overlord";"Larva";139;0
"Unit";"Overlord";"Larva";139;0
"Building";"Extractor";NA;139;0
"Building";"CreepTumor";NA;145;0
"Building";"CreepTumor";NA;145;0
"Unit";"Roach";"Larva";139;2
"Building";"Extractor";NA;139;0
"Unit";"Overlord";"Larva";152;0
"Unit";"Overlord";"Larva";152;0
"Unit";"Roach";"Larva";154;2
"Unit";"Roach";"Larva";154;2
"Unit";"Roach";"Larva";154;2
"Unit";"Roach";"Larva";154;2
"Unit";"Roach";"Larva";154;2
"Unit";"Roach";"Larva";154;2
"Unit";"Roach";"Larva";161;2
"Unit";"Roach";"Larva";161;2
"Unit";"Roach";"Larva";161;2
"Unit";"Hydralisk";"Larva";165;2
"Unit";"Hydralisk";"Larva";165;2
"Unit";"Hydralisk";"Larva";165;2
"Upgrade";"EvolveGroovedSpines";"HydraliskDen";161;0
"Unit";"Zergling";"Larva";190;1
"Unit";"Zergling";"Larva";190;1
"Unit";"Zergling";"Larva";190;1
"Unit";"Zergling";"Larva";190;1
"Unit";"Zergling";"Larva";191;1
"Unit";"Zergling";"Larva";191;1
"Unit";"Overlord";"Larva";193;0
"Building";"CreepTumorQueen";NA;199;0
"Unit";"Hydralisk";"Larva";193;2
"Unit";"Hydralisk";"Larva";193;2
"Unit";"Hydralisk";"Larva";193;2
"Unit";"Hydralisk";"Larva";193;2
"Building";"CreepTumor";NA;199;0
"Unit";"Hydralisk";"Larva";199;2
"Unit";"Hydralisk";"Larva";199;2
"Unit";"Hydralisk";"Larva";199;2
"Unit";"Hydralisk";"Larva";199;2
"Unit";"Hydralisk";"Larva";199;2
"Unit";"Hydralisk";"Larva";199;2
"Upgrade";"ZergMissileWeaponsLevel2";"EvolutionChamber";161;0
"Unit";"Hydralisk";"Larva";207;2
"Unit";"Hydralisk";"Larva";207;2
"Unit";"Hydralisk";"Larva";207;2
"Unit";"Hydralisk";"Larva";207;2
"Unit";"Roach";"Larva";207;2
"Unit";"Roach";"Larva";207;2
"Unit";"Roach";"Larva";207;2
"Unit";"Roach";"Larva";207;2
"Building";"Hatchery";NA;190;0
"Unit";"Hydralisk";"Larva";207;2
"Unit";"Roach";"Larva";219;2
"Unit";"Roach";"Larva";219;2
"Unit";"Roach";"Larva";219;2
"Building";"LurkerDenMP";NA;190;0
"Unit";"Roach";"Larva";219;2
"Unit";"Roach";"Larva";219;2
"Unit";"Roach";"Larva";219;2
"Unit";"Roach";"Larva";219;2
"Unit";"Roach";"Larva";227;2
"Unit";"Roach";"Larva";229;2
"Unit";"Roach";"Larva";235;2
"Unit";"Queen";"Hatchery";219;2
"Unit";"Roach";"Larva";235;2
"Unit";"Roach";"Larva";235;2
"Unit";"Roach";"Larva";243;2
"Unit";"Queen";"Hatchery";235;2
"Unit";"Hydralisk";"Larva";251;2
"Unit";"Hydralisk";"Larva";251;2
"Unit";"Hydralisk";"Larva";251;2
"Unit";"Hydralisk";"Larva";251;2
"Unit";"Hydralisk";"Larva";257;2
"Unit";"Hydralisk";"Larva";257;2
"Unit";"Hydralisk";"Larva";263;2
"Unit";"Hydralisk";"Larva";263;2
"Unit";"Overlord";"Larva";275;0
"Unit";"Hydralisk";"Larva";265;2
"Unit";"Hydralisk";"Larva";265;2
"Upgrade";"ZergGroundArmorsLevel2";"EvolutionChamber";199;0
"Building";"Extractor";NA;279;0
"Building";"Extractor";NA;279;0
"Unit";"Hydralisk";"Larva";279;2
"Unit";"Hydralisk";"Larva";279;2
"Unit";"Hydralisk";"Larva";279;2
"Unit";"Hydralisk";"Larva";284;2
"Unit";"Hydralisk";"Larva";284;2
"Unit";"Hydralisk";"Larva";285;2
"Unit";"Overlord";"Larva";293;0
"Unit";"Overlord";"Larva";293;0
"Unit";"Roach";"Larva";293;2
"Unit";"Roach";"Larva";293;2
"Unit";"Roach";"Larva";293;2
"Building";"CreepTumor";NA;303;0
"Unit";"Overlord";"Larva";305;0
"Building";"CreepTumor";NA;316;0
"Unit";"Zergling";"Larva";310;1
"Unit";"Zergling";"Larva";310;1
"Building";"CreepTumor";NA;316;0
"Unit";"Zergling";"Larva";310;1
"Unit";"Zergling";"Larva";310;1
"Unit";"Zergling";"Larva";310;1
"Unit";"Zergling";"Larva";310;1
"Unit";"Zergling";"Larva";310;1
"Unit";"Zergling";"Larva";310;1
"Unit";"Hydralisk";"Larva";310;2
"Unit";"Hydralisk";"Larva";310;2
"Unit";"Hydralisk";"Larva";310;2
"Unit";"Zergling";"Larva";316;1
"Unit";"Zergling";"Larva";316;1
"Unit";"Zergling";"Larva";316;1
"Unit";"Zergling";"Larva";316;1
"Unit";"Zergling";"Larva";316;1
"Unit";"Zergling";"Larva";316;1
"Unit";"Zergling";"Larva";316;1
"Unit";"Zergling";"Larva";316;1
"Unit";"Zergling";"Larva";316;1
"Unit";"Zergling";"Larva";316;1
"Building";"InfestationPit";NA;305;0
"Unit";"Zergling";"Larva";316;1
"Unit";"Zergling";"Larva";316;1
"Unit";"Zergling";"Larva";316;1
"Unit";"Zergling";"Larva";316;1
"Unit";"Zergling";"Larva";316;1
"Unit";"Zergling";"Larva";316;1
"Unit";"Zergling";"Larva";316;1
"Unit";"Zergling";"Larva";316;1
"Unit";"Zergling";"Larva";316;1
"Unit";"Zergling";"Larva";316;1
"Unit";"Zergling";"Larva";316;1
"Unit";"Zergling";"Larva";316;1
"Unit";"Zergling";"Larva";340;1
"Unit";"Zergling";"Larva";340;1
"Unit";"Zergling";"Larva";340;1
"Unit";"Zergling";"Larva";340;1
"Unit";"Zergling";"Larva";340;1
"Unit";"Zergling";"Larva";340;1
"Unit";"Zergling";"Larva";340;1
"Unit";"Zergling";"Larva";340;1
"Unit";"Queen";"Hatchery";316;2
"Unit";"Hydralisk";"Larva";340;2
"Unit";"Hydralisk";"Larva";340;2
"Unit";"Hydralisk";"Larva";352;2
"Unit";"Hydralisk";"Larva";352;2
"Unit";"Hydralisk";"Larva";352;2
"Unit";"Hydralisk";"Larva";352;2
"Building";"Hatchery";NA;316;0
"Unit";"Hydralisk";"Larva";362;2
"Unit";"Hydralisk";"Larva";362;2
"Unit";"Hydralisk";"Larva";362;2
"Unit";"Hydralisk";"Larva";362;2
"Unit";"Hydralisk";"Larva";368;2
"Unit";"Hydralisk";"Larva";368;2
"Unit";"Hydralisk";"Larva";368;2
"Unit";"Hydralisk";"Larva";368;2
"Unit";"Overlord";"Larva";374;0
"Unit";"Overlord";"Larva";374;0
"Unit";"Overlord";"Larva";382;0
"Unit";"Hydralisk";"Larva";382;2
"Unit";"Hydralisk";"Larva";382;2
"Unit";"Hydralisk";"Larva";382;2
"Unit";"Hydralisk";"Larva";382;2
"Unit";"Hydralisk";"Larva";390;2
"Unit";"Hydralisk";"Larva";390;2
"Unit";"Hydralisk";"Larva";390;2
"Unit";"Hydralisk";"Larva";390;2
"Unit";"Hydralisk";"Larva";390;2
"Unit";"Hydralisk";"Larva";398;2
"Unit";"Hydralisk";"Larva";398;2
"Unit";"Hydralisk";"Larva";398;2
"Unit";"Hydralisk";"Larva";398;2
"Unit";"Hydralisk";"Larva";398;2
"Unit";"Hydralisk";"Larva";398;2
"Unit";"Hydralisk";"Larva";398;2
"Unit";"Hydralisk";"Larva";398;2
"Unit";"Hydralisk";"Larva";398;2
"Unit";"Hydralisk";"Larva";398;2
"Unit";"Overlord";"Larva";408;0
"Unit";"Hydralisk";"Larva";418;2
"Unit";"Hydralisk";"Larva";418;2
"Unit";"Hydralisk";"Larva";418;2
"Unit";"Hydralisk";"Larva";418;2
"Unit";"Hydralisk";"Larva";428;2
"Unit";"Hydralisk";"Larva";428;2
"Unit";"Hydralisk";"Larva";428;2
"Unit";"Hydralisk";"Larva";428;2
"Unit";"Hydralisk";"Larva";428;2
"Unit";"Hydralisk";"Larva";428;2
"Unit";"Hydralisk";"Larva";428;2
"Unit";"Hydralisk";"Larva";428;2
"Unit";"Hydralisk";"Larva";428;2
"Unit";"Hydralisk";"Larva";451;2
"Unit";"Hydralisk";"Larva";451;2
"Unit";"Hydralisk";"Larva";451;2
"Unit";"Hydralisk";"Larva";451;2
"Unit";"Hydralisk";"Larva";451;2
"Unit";"Hydralisk";"Larva";451;2
"Unit";"Hydralisk";"Larva";451;2
"Unit";"Hydralisk";"Larva";455;2
"Unit";"Hydralisk";"Larva";455;2
"Unit";"Hydralisk";"Larva";455;2
"Unit";"Hydralisk";"Larva";455;2
"Unit";"Hydralisk";"Larva";455;2
"Unit";"Overlord";"Larva";455;0
"Unit";"Hydralisk";"Larva";455;2
"Unit";"Hydralisk";"Larva";455;2
"Unit";"Hydralisk";"Larva";455;2
"Unit";"Hydralisk";"Larva";455;2
"Unit";"Hydralisk";"Larva";469;2
"Unit";"Hydralisk";"Larva";469;2
"Unit";"Hydralisk";"Larva";469;2
"Unit";"Hydralisk";"Larva";490;2
"Unit";"Hydralisk";"Larva";490;2
"Unit";"Hydralisk";"Larva";490;2
"Unit";"Hydralisk";"Larva";490;2
"Unit";"Hydralisk";"Larva";490;2
"Unit";"Hydralisk";"Larva";490;2
"Building";"Extractor";NA;496;0
"Unit";"Roach";"Larva";496;2
"Building";"Extractor";NA;496;0
"Unit";"Roach";"Larva";496;2
"Unit";"Zergling";"Larva";512;1
"Unit";"Zergling";"Larva";512;1
"Unit";"Zergling";"Larva";512;1
"Unit";"Zergling";"Larva";512;1
"Unit";"Zergling";"Larva";512;1
"Unit";"Zergling";"Larva";512;1
"Unit";"Zergling";"Larva";512;1
"Unit";"Zergling";"Larva";512;1
"Unit";"Hydralisk";"Larva";512;2
"Unit";"Hydralisk";"Larva";516;2
"Unit";"Hydralisk";"Larva";516;2
"Unit";"Hydralisk";"Larva";516;2
"Unit";"Hydralisk";"Larva";516;2
