"type";"unit_name";"on_building";"total_supply";"supply"
"Unit";"Overlord";"Larva";13;0
"Building";"Extractor";NA;19;0
"Building";"Hatchery";NA;17;0
"Building";"SpawningPool";NA;20;0
"Unit";"Overlord";"Larva";23;0
"Unit";"Zergling";"Larva";24;1
"Unit";"Zergling";"Larva";24;1
"Unit";"Queen";"Hatchery";24;2
"Building";"Hatchery";NA;22;0
"Unit";"Zergling";"Larva";28;1
"Unit";"Zergling";"Larva";28;1
"Unit";"Zergling";"Larva";28;1
"Unit";"Zergling";"Larva";28;1
"Unit";"Queen";"Hatchery";24;2
"Unit";"Zergling";"Larva";36;1
"Unit";"Zergling";"Larva";36;1
"Unit";"Zergling";"Larva";37;1
"Unit";"Zergling";"Larva";37;1
"Unit";"Overlord";"Larva";39;0
"Unit";"Zergling";"Larva";39;1
"Unit";"Zergling";"Larva";39;1
"Unit";"Queen";"Hatchery";34;2
"Unit";"Queen";"Hatchery";39;2
"Unit";"Overlord";"Larva";54;0
"Building";"CreepTumorQueen";NA;59;0
"Unit";"Overlord";"Larva";59;0
"Building";"SporeCrawler";NA;61;0
"Building";"CreepTumorQueen";NA;67;0
"Building";"EvolutionChamber";NA;66;0
"Building";"SporeCrawler";NA;73;0
"Unit";"Overlord";"Larva";73;0
"Unit";"Overlord";"Larva";73;0
"Building";"CreepTumor";NA;79;0
"Building";"CreepTumorQueen";NA;79;0
"Building";"Extractor";NA;79;0
"Unit";"Overlord";"Larva";79;0
"Building";"Extractor";NA;79;0
"Building";"Extractor";NA;79;0
"Building";"Extractor";NA;79;0
"Unit";"Queen";"Hatchery";79;2
"Building";"HydraliskDen";NA;79;0
"Unit";"Zergling";"Larva";83;1
"Unit";"Zergling";"Larva";83;1
"Unit";"Zergling";"Larva";83;1
"Unit";"Zergling";"Larva";83;1
"Building";"CreepTumorQueen";NA;91;0
"Building";"CreepTumor";NA;91;0
"Building";"CreepTumor";NA;95;0
"Building";"CreepTumorQueen";NA;95;0
"Building";"Hatchery";NA;79;0
"Building";"Extractor";NA;95;0
"Unit";"Overlord";"Larva";95;0
"Unit";"Overlord";"Larva";106;0
"Unit";"Overlord";"Larva";106;0
"Unit";"Overlord";"Larva";106;0
"Unit";"Zergling";"Larva";106;1
"Unit";"Zergling";"Larva";106;1
"Unit";"Zergling";"Larva";106;1
"Unit";"Zergling";"Larva";106;1
"Unit";"Zergling";"Larva";106;1
"Unit";"Zergling";"Larva";106;1
"Unit";"Zergling";"Larva";106;1
"Unit";"Zergling";"Larva";106;1
"Unit";"Zergling";"Larva";106;1
"Unit";"Zergling";"Larva";106;1
"Unit";"Zergling";"Larva";106;1
"Unit";"Zergling";"Larva";106;1
"Unit";"Zergling";"Larva";107;1
"Unit";"Zergling";"Larva";107;1
"Unit";"Hydralisk";"Larva";107;2
"Building";"Hatchery";NA;83;0
"Unit";"Hydralisk";"Larva";109;2
"Unit";"Hydralisk";"Larva";109;2
"Upgrade";"ZergMissileWeaponsLevel1";"EvolutionChamber";83;0
"Unit";"Hydralisk";"Larva";123;2
"Unit";"Hydralisk";"Larva";123;2
"Unit";"Hydralisk";"Larva";123;2
"Building";"CreepTumorQueen";NA;129;0
"Unit";"Hydralisk";"Larva";123;2
"Building";"SporeCrawler";NA;123;0
"Building";"CreepTumor";NA;129;0
"Unit";"Overlord";"Larva";125;0
"Building";"CreepTumorQueen";NA;129;0
"Upgrade";"EvolveGroovedSpines";"HydraliskDen";107;0
"Unit";"Overlord";"Larva";125;0
"Unit";"Overlord";"Larva";125;0
"Building";"CreepTumor";NA;129;0
"Building";"SporeCrawler";NA;125;0
"Unit";"Hydralisk";"Larva";125;2
"Unit";"Hydralisk";"Larva";125;2
"Unit";"Hydralisk";"Larva";125;2
"Unit";"Hydralisk";"Larva";125;2
"Unit";"Hydralisk";"Larva";125;2
"Unit";"Overlord";"Larva";129;0
"Unit";"Hydralisk";"Larva";130;2
"Unit";"Hydralisk";"Larva";132;2
"Unit";"Hydralisk";"Larva";140;2
"Unit";"Hydralisk";"Larva";151;2
"Unit";"Hydralisk";"Larva";151;2
"Building";"EvolutionChamber";NA;150;0
"Unit";"Hydralisk";"Larva";152;2
"Unit";"Hydralisk";"Larva";152;2
"Unit";"Hydralisk";"Larva";152;2
"Unit";"Hydralisk";"Larva";158;2
"Unit";"Hydralisk";"Larva";158;2
"Unit";"Hydralisk";"Larva";158;2
"Unit";"Hydralisk";"Larva";158;2
"Unit";"Hydralisk";"Larva";158;2
"Unit";"Hydralisk";"Larva";160;2
"Unit";"Hydralisk";"Larva";160;2
"Building";"SpineCrawler";NA;156;0
"Unit";"Hydralisk";"Larva";168;2
"Unit";"Hydralisk";"Larva";168;2
"Unit";"Hydralisk";"Larva";168;2
"Unit";"Hydralisk";"Larva";168;2
"Unit";"Hydralisk";"Larva";168;2
"Unit";"Hydralisk";"Larva";168;2
"Building";"CreepTumorQueen";NA;182;0
"Building";"CreepTumor";NA;182;0
"Building";"CreepTumor";NA;182;0
"Building";"CreepTumor";NA;182;0
"Unit";"Overlord";"Larva";182;0
"Unit";"Overlord";"Larva";182;0
"Unit";"Overlord";"Larva";182;0
"Unit";"Overlord";"Larva";182;0
"Unit";"Overlord";"Larva";182;0
"Building";"CreepTumor";NA;202;0
"Building";"CreepTumor";NA;202;0
"Upgrade";"EvolveMuscularAugments";"HydraliskDen";168;0
"Unit";"Hydralisk";"Larva";202;2
"Unit";"Hydralisk";"Larva";202;2
"Unit";"Hydralisk";"Larva";202;2
"Unit";"Hydralisk";"Larva";202;2
"Unit";"Hydralisk";"Larva";202;2
"Building";"CreepTumor";NA;202;0
"Building";"CreepTumor";NA;202;0
"Building";"Extractor";NA;202;0
"Building";"Extractor";NA;202;0
"Unit";"Overlord";"Larva";210;0
"Unit";"Overlord";"Larva";210;0
"Upgrade";"ZergMissileWeaponsLevel2";"EvolutionChamber";158;0
"Building";"CreepTumor";NA;229;0
"Unit";"Zergling";"Larva";229;1
"Unit";"Zergling";"Larva";229;1
"Unit";"Zergling";"Larva";229;1
"Unit";"Zergling";"Larva";229;1
"Unit";"Zergling";"Larva";229;1
"Unit";"Zergling";"Larva";229;1
"Unit";"Zergling";"Larva";229;1
"Unit";"Zergling";"Larva";229;1
"Unit";"Zergling";"Larva";229;1
"Unit";"Zergling";"Larva";229;1
"Building";"SporeCrawler";NA;219;0
"Building";"SporeCrawler";NA;226;0
"Building";"LurkerDenMP";NA;182;0
"Building";"CreepTumor";NA;229;0
"Building";"Extractor";NA;229;0
"Unit";"Zergling";"Larva";229;1
"Unit";"Zergling";"Larva";229;1
"Unit";"Zergling";"Larva";229;1
"Unit";"Zergling";"Larva";229;1
"Unit";"Zergling";"Larva";229;1
"Unit";"Zergling";"Larva";229;1
"Building";"Extractor";NA;229;0
"Unit";"Zergling";"Larva";229;1
"Unit";"Zergling";"Larva";229;1
"Unit";"Zergling";"Larva";229;1
"Unit";"Zergling";"Larva";229;1
"Building";"CreepTumor";NA;229;0
"Unit";"Zergling";"Larva";229;1
"Unit";"Zergling";"Larva";229;1
"Building";"SpineCrawler";NA;229;0
"Unit";"Zergling";"Larva";241;1
"Unit";"Zergling";"Larva";241;1
"Unit";"Zergling";"Larva";241;1
"Unit";"Zergling";"Larva";241;1
"Unit";"Zergling";"Larva";245;1
"Unit";"Zergling";"Larva";245;1
"Building";"InfestationPit";NA;229;0
"Building";"CreepTumor";NA;257;0
"Building";"CreepTumor";NA;257;0
"Unit";"Hydralisk";"Larva";251;2
"Unit";"Hydralisk";"Larva";251;2
"Unit";"Hydralisk";"Larva";251;2
"Unit";"Hydralisk";"Larva";251;2
"Unit";"Hydralisk";"Larva";251;2
"Unit";"Hydralisk";"Larva";251;2
"Unit";"Hydralisk";"Larva";251;2
"Unit";"Hydralisk";"Larva";257;2
"Unit";"Hydralisk";"Larva";257;2
"Upgrade";"ZergGroundArmorsLevel1";"EvolutionChamber";217;0
"Building";"SporeCrawler";NA;263;0
"Building";"CreepTumor";NA;288;0
"Building";"CreepTumor";NA;288;0
"Building";"CreepTumor";NA;288;0
"Building";"CreepTumor";NA;288;0
"Building";"SpineCrawler";NA;263;0
"Building";"CreepTumor";NA;288;0
"Building";"CreepTumorQueen";NA;288;0
"Unit";"Zergling";"Larva";288;1
"Unit";"Zergling";"Larva";288;1
"Building";"CreepTumorQueen";NA;288;0
"Unit";"Hydralisk";"Larva";290;2
