"type";"unit_name";"on_building";"total_supply";"supply"
"Unit";"Overlord";"Larva";12;0
"Building";"Extractor";NA;18;0
"Unit";"Overlord";"Larva";21;0
"Building";"SpawningPool";NA;19;0
"Building";"Hatchery";NA;17;0
"Unit";"Zergling";"Larva";22;1
"Unit";"Zergling";"Larva";22;1
"Unit";"Zergling";"Larva";22;1
"Unit";"Zergling";"Larva";22;1
"Unit";"Zergling";"Larva";22;1
"Unit";"Zergling";"Larva";22;1
"Unit";"Queen";"Hatchery";22;2
"Unit";"Queen";"Hatchery";22;2
"Unit";"Overlord";"Larva";36;0
"Building";"CreepTumorQueen";NA;41;0
"Unit";"Overlord";"Larva";41;0
"Building";"Hatchery";NA;30;0
"Unit";"Queen";"Hatchery";39;2
"Building";"CreepTumorQueen";NA;47;0
"Unit";"Overlord";"Larva";45;0
"Building";"SporeCrawler";NA;51;0
"Building";"SporeCrawler";NA;51;0
"Building";"CreepTumor";NA;55;0
"Building";"SporeCrawler";NA;53;0
"Unit";"Overlord";"Larva";58;0
"Unit";"Overlord";"Larva";58;0
"Building";"CreepTumor";NA;61;0
"Building";"CreepTumor";NA;68;0
"Building";"Extractor";NA;61;0
"Building";"Extractor";NA;61;0
"Unit";"Zergling";"Larva";68;1
"Unit";"Zergling";"Larva";68;1
"Unit";"Zergling";"Larva";68;1
"Unit";"Zergling";"Larva";68;1
"Unit";"Zergling";"Larva";68;1
"Unit";"Zergling";"Larva";68;1
"Unit";"Zergling";"Larva";68;1
"Unit";"Zergling";"Larva";68;1
"Unit";"Zergling";"Larva";68;1
"Unit";"Zergling";"Larva";68;1
"Unit";"Zergling";"Larva";68;1
"Unit";"Zergling";"Larva";68;1
"Building";"CreepTumorQueen";NA;68;0
"Unit";"Zergling";"Larva";68;1
"Unit";"Zergling";"Larva";68;1
"Building";"CreepTumor";NA;68;0
"Unit";"Queen";"Hatchery";68;2
"Building";"EvolutionChamber";NA;68;0
"Unit";"Overlord";"Larva";82;0
"Unit";"Overlord";"Larva";82;0
"Unit";"Overlord";"Larva";82;0
"Building";"EvolutionChamber";NA;87;0
"Building";"Extractor";NA;87;0
"Building";"BanelingNest";NA;87;0
"Building";"Extractor";NA;100;0
"Building";"Extractor";NA;100;0
"Building";"HydraliskDen";NA;99;0
"Unit";"Zergling";"Larva";106;1
"Unit";"Zergling";"Larva";106;1
"Unit";"Zergling";"Larva";106;1
"Unit";"Zergling";"Larva";106;1
"Unit";"Zergling";"Larva";106;1
"Unit";"Zergling";"Larva";106;1
"Building";"CreepTumor";NA;111;0
"Building";"CreepTumor";NA;111;0
"Unit";"Overlord";"Larva";111;0
"Building";"CreepTumor";NA;111;0
"Building";"CreepTumorQueen";NA;117;0
"Building";"CreepTumorQueen";NA;117;0
"Unit";"Hydralisk";"Larva";117;2
"Unit";"Hydralisk";"Larva";117;2
"Unit";"Hydralisk";"Larva";117;2
"Unit";"Hydralisk";"Larva";117;2
"Unit";"Hydralisk";"Larva";117;2
"Unit";"Hydralisk";"Larva";117;2
"Unit";"Overlord";"Larva";117;0
"Unit";"Overlord";"Larva";117;0
"Unit";"Overlord";"Larva";117;0
"Building";"SporeCrawler";NA;117;0
"Unit";"Overlord";"Larva";128;0
"Unit";"Overlord";"Larva";130;0
"Building";"CreepTumor";NA;130;0
"Building";"CreepTumor";NA;130;0
"Building";"CreepTumor";NA;130;0
"Building";"CreepTumorQueen";NA;130;0
"Building";"CreepTumorQueen";NA;130;0
"Building";"CreepTumorQueen";NA;130;0
"Unit";"Baneling";"Zergling";130;0
"Unit";"Baneling";"Zergling";130;0
"Unit";"Baneling";"Zergling";130;0
"Unit";"Baneling";"Zergling";130;0
"Unit";"Hydralisk";"Larva";130;2
"Unit";"Hydralisk";"Larva";130;2
"Unit";"Hydralisk";"Larva";130;2
"Unit";"Hydralisk";"Larva";130;2
"Unit";"Hydralisk";"Larva";130;2
"Unit";"Hydralisk";"Larva";130;2
"Unit";"Hydralisk";"Larva";130;2
"Unit";"Hydralisk";"Larva";130;2
"Unit";"Hydralisk";"Larva";130;2
"Unit";"Hydralisk";"Larva";130;2
"Upgrade";"ZergMissileWeaponsLevel1";"EvolutionChamber";117;0
"Upgrade";"ZergGroundArmorsLevel1";"EvolutionChamber";117;0
"Unit";"Zergling";"Larva";130;1
"Unit";"Zergling";"Larva";130;1
"Upgrade";"EvolveGroovedSpines";"HydraliskDen";130;0
"Unit";"Hydralisk";"Larva";130;2
"Unit";"Hydralisk";"Larva";130;2
"Unit";"Hydralisk";"Larva";130;2
"Unit";"Hydralisk";"Larva";130;2
"Unit";"Hydralisk";"Larva";130;2
"Unit";"Hydralisk";"Larva";130;2
"Unit";"Zergling";"Larva";150;1
"Unit";"Zergling";"Larva";150;1
"Unit";"Hydralisk";"Larva";130;2
"Unit";"Hydralisk";"Larva";150;2
"Unit";"Zergling";"Larva";150;1
"Unit";"Zergling";"Larva";150;1
"Unit";"Hydralisk";"Larva";150;2
"Unit";"Hydralisk";"Larva";150;2
"Unit";"Zergling";"Larva";152;1
"Unit";"Zergling";"Larva";152;1
"Unit";"Hydralisk";"Larva";152;2
"Unit";"Hydralisk";"Larva";152;2
"Unit";"Zergling";"Larva";172;1
"Unit";"Zergling";"Larva";172;1
"Building";"CreepTumor";NA;182;0
"Building";"CreepTumor";NA;182;0
"Building";"CreepTumor";NA;182;0
"Building";"CreepTumor";NA;182;0
"Building";"CreepTumor";NA;182;0
"Unit";"Hydralisk";"Larva";172;2
"Unit";"Hydralisk";"Larva";172;2
"Unit";"Hydralisk";"Larva";172;2
"Building";"CreepTumor";NA;190;0
"Building";"CreepTumor";NA;190;0
"Building";"CreepTumor";NA;190;0
"Building";"CreepTumor";NA;190;0
"Building";"CreepTumor";NA;190;0
"Building";"CreepTumor";NA;190;0
"Unit";"Zergling";"Larva";190;1
"Unit";"Zergling";"Larva";190;1
"Unit";"Zergling";"Larva";190;1
"Unit";"Zergling";"Larva";190;1
"Unit";"Zergling";"Larva";190;1
"Unit";"Zergling";"Larva";190;1
"Unit";"Zergling";"Larva";190;1
"Unit";"Zergling";"Larva";190;1
"Unit";"Zergling";"Larva";190;1
"Unit";"Zergling";"Larva";190;1
"Unit";"Hydralisk";"Larva";190;2
"Unit";"Hydralisk";"Larva";190;2
"Unit";"Hydralisk";"Larva";190;2
"Unit";"Baneling";"Zergling";192;0
"Unit";"Baneling";"Zergling";192;0
"Unit";"Baneling";"Zergling";192;0
"Building";"SporeCrawler";NA;190;0
"Unit";"Baneling";"Zergling";192;0
"Building";"SporeCrawler";NA;192;0
"Unit";"Overlord";"Larva";192;0
"Unit";"Overlord";"Larva";192;0
"Building";"CreepTumor";NA;202;0
"Building";"CreepTumor";NA;202;0
"Upgrade";"EvolveMuscularAugments";"HydraliskDen";190;0
"Building";"Hatchery";NA;184;0
"Building";"Hatchery";NA;184;0
"Building";"CreepTumor";NA;208;0
"Unit";"Overlord";"Larva";208;0
"Unit";"Overlord";"Larva";208;0
"Building";"CreepTumor";NA;208;0
"Unit";"Zergling";"Larva";208;1
"Unit";"Zergling";"Larva";208;1
"Unit";"Hydralisk";"Larva";208;2
"Unit";"Hydralisk";"Larva";208;2
"Unit";"Hydralisk";"Larva";208;2
"Unit";"Hydralisk";"Larva";208;2
"Unit";"Hydralisk";"Larva";208;2
"Unit";"Hydralisk";"Larva";208;2
"Building";"CreepTumor";NA;208;0
"Unit";"Hydralisk";"Larva";208;2
"Unit";"Hydralisk";"Larva";208;2
"Unit";"Hydralisk";"Larva";208;2
"Upgrade";"ZergMeleeWeaponsLevel1";"EvolutionChamber";208;0
"Unit";"Hydralisk";"Larva";208;2
"Unit";"Hydralisk";"Larva";208;2
"Unit";"Hydralisk";"Larva";208;2
"Unit";"Hydralisk";"Larva";208;2
"Building";"CreepTumor";NA;208;0
"Unit";"Hydralisk";"Larva";208;2
"Unit";"Hydralisk";"Larva";208;2
"Unit";"Hydralisk";"Larva";208;2
"Unit";"Hydralisk";"Larva";208;2
"Building";"InfestationPit";NA;208;0
"Unit";"Queen";"Hatchery";208;2
"Building";"Extractor";NA;208;0
"Building";"Extractor";NA;208;0
"Building";"SporeCrawler";NA;210;0
"Building";"CreepTumor";NA;244;0
"Upgrade";"ZergGroundArmorsLevel2";"EvolutionChamber";208;0
"Unit";"Baneling";"Zergling";252;0
"Unit";"Baneling";"Zergling";252;0
"Unit";"Baneling";"Zergling";252;0
"Unit";"Baneling";"Zergling";252;0
"Unit";"Baneling";"Zergling";252;0
"Unit";"Baneling";"Zergling";252;0
"Building";"CreepTumor";NA;252;0
"Unit";"Baneling";"Zergling";252;0
"Unit";"Baneling";"Zergling";252;0
"Unit";"Baneling";"Zergling";252;0
"Building";"CreepTumor";NA;252;0
"Unit";"Baneling";"Zergling";252;0
"Unit";"Baneling";"Zergling";252;0
"Unit";"Baneling";"Zergling";252;0
"Unit";"Queen";"Hatchery";208;2
"Building";"SpineCrawler";NA;210;0
"Building";"SpineCrawler";NA;210;0
"Unit";"Zergling";"Larva";252;1
"Unit";"Zergling";"Larva";252;1
"Unit";"Zergling";"Larva";252;1
"Unit";"Zergling";"Larva";252;1
"Unit";"Zergling";"Larva";252;1
"Unit";"Zergling";"Larva";252;1
"Unit";"Hydralisk";"Larva";252;2
"Unit";"Hydralisk";"Larva";252;2
"Unit";"Hydralisk";"Larva";252;2
"Unit";"Hydralisk";"Larva";252;2
"Unit";"Hydralisk";"Larva";252;2
"Unit";"Hydralisk";"Larva";252;2
"Unit";"Hydralisk";"Larva";252;2
"Unit";"Hydralisk";"Larva";252;2
"Unit";"Zergling";"Larva";276;1
"Unit";"Zergling";"Larva";276;1
"Unit";"Zergling";"Larva";276;1
"Unit";"Zergling";"Larva";276;1
"Unit";"Zergling";"Larva";276;1
"Unit";"Zergling";"Larva";276;1
"Unit";"Zergling";"Larva";276;1
"Unit";"Zergling";"Larva";276;1
"Unit";"Zergling";"Larva";276;1
"Unit";"Zergling";"Larva";276;1
"Unit";"Zergling";"Larva";276;1
"Unit";"Zergling";"Larva";276;1
"Unit";"Zergling";"Larva";276;1
"Unit";"Zergling";"Larva";276;1
"Unit";"Zergling";"Larva";276;1
"Unit";"Zergling";"Larva";276;1
"Unit";"Zergling";"Larva";276;1
"Unit";"Zergling";"Larva";276;1
"Unit";"Zergling";"Larva";276;1
"Unit";"Zergling";"Larva";276;1
"Unit";"Zergling";"Larva";276;1
"Unit";"Zergling";"Larva";276;1
"Unit";"Hydralisk";"Larva";276;2
"Unit";"Hydralisk";"Larva";276;2
"Unit";"Hydralisk";"Larva";276;2
"Unit";"Zergling";"Larva";276;1
"Unit";"Zergling";"Larva";276;1
"Unit";"Hydralisk";"Larva";276;2
"Unit";"Hydralisk";"Larva";276;2
"Unit";"Hydralisk";"Larva";276;2
