"type";"unit_name";"on_building";"total_supply";"supply"
"Unit";"Overlord";"Larva";12;0
"Building";"Extractor";NA;18;0
"Unit";"Overlord";"Larva";21;0
"Building";"SpawningPool";NA;19;0
"Building";"Hatchery";NA;17;0
"Unit";"Queen";"Hatchery";22;2
"Unit";"Queen";"Hatchery";23;2
"Unit";"Zergling";"Larva";29;1
"Unit";"Zergling";"Larva";29;1
"Unit";"Zergling";"Larva";29;1
"Unit";"Zergling";"Larva";29;1
"Unit";"Zergling";"Larva";31;1
"Unit";"Zergling";"Larva";31;1
"Unit";"Overlord";"Larva";33;0
"Unit";"Overlord";"Larva";39;0
"Unit";"Overlord";"Larva";39;0
"Building";"Hatchery";NA;27;0
"Unit";"Queen";"Hatchery";39;2
"Unit";"Queen";"Hatchery";39;2
"Unit";"Zergling";"Larva";49;1
"Unit";"Zergling";"Larva";49;1
"Building";"CreepTumorQueen";NA;54;0
"Building";"CreepTumorQueen";NA;54;0
"Building";"Extractor";NA;54;0
"Building";"SporeCrawler";NA;65;0
"Building";"SporeCrawler";NA;65;0
"Building";"SporeCrawler";NA;65;0
"Building";"RoachWarren";NA;56;0
"Unit";"Queen";"Hatchery";65;2
"Unit";"Queen";"Hatchery";65;2
"Unit";"Overlord";"Larva";65;0
"Unit";"Overlord";"Larva";65;0
"Building";"Extractor";NA;65;0
"Building";"EvolutionChamber";NA;65;0
"Building";"CreepTumorQueen";NA;78;0
"Unit";"Overlord";"Larva";65;0
"Building";"CreepTumorQueen";NA;78;0
"Building";"CreepTumor";NA;78;0
"Building";"CreepTumorQueen";NA;78;0
"Unit";"Overlord";"Larva";78;0
"Building";"HydraliskDen";NA;78;0
"Building";"CreepTumor";NA;78;0
"Building";"CreepTumor";NA;78;0
"Building";"CreepTumor";NA;78;0
"Building";"CreepTumorQueen";NA;78;0
"Building";"Extractor";NA;78;0
"Building";"CreepTumorQueen";NA;78;0
"Unit";"Overlord";"Larva";78;0
"Building";"CreepTumor";NA;78;0
"Building";"CreepTumorQueen";NA;81;0
"Unit";"Hydralisk";"Larva";88;2
"Unit";"Hydralisk";"Larva";88;2
"Unit";"Hydralisk";"Larva";88;2
"Unit";"Hydralisk";"Larva";88;2
"Unit";"Hydralisk";"Larva";88;2
"Unit";"Hydralisk";"Larva";88;2
"Unit";"Hydralisk";"Larva";88;2
"Unit";"Overlord";"Larva";88;0
"Unit";"Overlord";"Larva";88;0
"Unit";"Overlord";"Larva";88;0
"Unit";"Overlord";"Larva";88;0
"Building";"Extractor";NA;88;0
"Building";"Extractor";NA;88;0
"Unit";"Roach";"Larva";102;2
"Unit";"Roach";"Larva";102;2
"Unit";"Roach";"Larva";102;2
"Unit";"Roach";"Larva";102;2
"Unit";"Roach";"Larva";102;2
"Unit";"Roach";"Larva";102;2
"Unit";"Roach";"Larva";102;2
"Unit";"Overlord";"Larva";102;0
"Unit";"Overlord";"Larva";102;0
"Unit";"Roach";"Larva";102;2
"Unit";"Roach";"Larva";102;2
"Unit";"Roach";"Larva";102;2
"Unit";"Roach";"Larva";102;2
"Unit";"Roach";"Larva";102;2
"Unit";"Roach";"Larva";102;2
"Unit";"Overlord";"Larva";102;0
"Unit";"Overlord";"Larva";102;0
"Unit";"Overlord";"Larva";104;0
"Upgrade";"ZergMissileWeaponsLevel1";"EvolutionChamber";88;0
"Building";"CreepTumorQueen";NA;128;0
"Building";"CreepTumor";NA;128;0
"Building";"CreepTumor";NA;128;0
"Building";"CreepTumorQueen";NA;128;0
"Building";"CreepTumor";NA;128;0
"Building";"CreepTumor";NA;128;0
"Building";"CreepTumor";NA;128;0
"Building";"CreepTumor";NA;128;0
"Upgrade";"EvolveGroovedSpines";"HydraliskDen";102;0
"Building";"CreepTumorQueen";NA;128;0
"Building";"CreepTumorQueen";NA;128;0
"Unit";"Overlord";"Larva";128;0
"Upgrade";"GlialReconstitution";"RoachWarren";102;0
"Unit";"Roach";"Larva";128;2
"Unit";"Roach";"Larva";128;2
"Unit";"Roach";"Larva";128;2
"Unit";"Roach";"Larva";128;2
"Unit";"Roach";"Larva";128;2
"Unit";"Roach";"Larva";128;2
"Unit";"Roach";"Larva";128;2
"Unit";"Roach";"Larva";128;2
"Building";"CreepTumor";NA;151;0
"Building";"CreepTumor";NA;152;0
"Building";"CreepTumor";NA;153;0
"Building";"CreepTumor";NA;153;0
"Building";"CreepTumorQueen";NA;153;0
"Building";"CreepTumor";NA;153;0
"Building";"CreepTumor";NA;153;0
"Building";"CreepTumor";NA;153;0
"Building";"CreepTumorQueen";NA;153;0
"Building";"CreepTumor";NA;153;0
"Building";"CreepTumor";NA;153;0
"Building";"CreepTumorQueen";NA;153;0
"Building";"LurkerDenMP";NA;128;0
"Unit";"Hydralisk";"Larva";153;2
"Unit";"Hydralisk";"Larva";153;2
"Unit";"Hydralisk";"Larva";153;2
"Unit";"Hydralisk";"Larva";153;2
"Unit";"Hydralisk";"Larva";153;2
"Unit";"Hydralisk";"Larva";153;2
"Unit";"Hydralisk";"Larva";153;2
"Unit";"Hydralisk";"Larva";153;2
"Unit";"Hydralisk";"Larva";153;2
"Unit";"Hydralisk";"Larva";153;2
"Unit";"Hydralisk";"Larva";153;2
"Unit";"Hydralisk";"Larva";153;2
"Unit";"Hydralisk";"Larva";153;2
"Unit";"Hydralisk";"Larva";153;2
"Unit";"Overlord";"Larva";182;0
"Unit";"Overlord";"Larva";183;0
"Unit";"Overlord";"Larva";184;0
"Unit";"Overlord";"Larva";185;0
"Unit";"Overlord";"Larva";185;0
"Building";"InfestationPit";NA;153;0
"Upgrade";"EvolveMuscularAugments";"HydraliskDen";153;0
"Unit";"Hydralisk";"Larva";186;2
"Unit";"Hydralisk";"Larva";186;2
"Unit";"Hydralisk";"Larva";186;2
"Unit";"Hydralisk";"Larva";186;2
"Unit";"Hydralisk";"Larva";186;2
"Unit";"Hydralisk";"Larva";186;2
"Unit";"Hydralisk";"Larva";186;2
"Unit";"Hydralisk";"Larva";186;2
"Unit";"Roach";"Larva";186;2
"Unit";"Roach";"Larva";186;2
"Unit";"Roach";"Larva";186;2
"Unit";"Roach";"Larva";186;2
"Unit";"Roach";"Larva";186;2
"Unit";"Roach";"Larva";186;2
"Unit";"Overlord";"Larva";202;0
"Building";"Hatchery";NA;181;0
"Upgrade";"ZergMissileWeaponsLevel2";"EvolutionChamber";153;0
"Unit";"Roach";"Larva";214;2
"Unit";"Roach";"Larva";214;2
"Unit";"Roach";"Larva";214;2
"Unit";"Roach";"Larva";214;2
"Unit";"Roach";"Larva";214;2
