"type";"unit_name";"on_building";"total_supply";"supply"
"Unit";"Overlord";"Larva";13;0
"Building";"Extractor";NA;18;0
"Unit";"Overlord";"Larva";21;0
"Building";"SpawningPool";NA;19;0
"Building";"Hatchery";NA;17;0
"Unit";"Queen";"Hatchery";22;2
"Unit";"Queen";"Hatchery";23;2
"Unit";"Overlord";"Larva";33;0
"Unit";"Zergling";"Larva";33;1
"Unit";"Zergling";"Larva";33;1
"Unit";"Zergling";"Larva";33;1
"Unit";"Zergling";"Larva";33;1
"Unit";"Zergling";"Larva";33;1
"Unit";"Zergling";"Larva";33;1
"Unit";"Zergling";"Larva";33;1
"Unit";"Zergling";"Larva";33;1
"Unit";"Queen";"Hatchery";33;2
"Unit";"Overlord";"Larva";43;0
"Building";"CreepTumorQueen";NA;51;0
"Unit";"Overlord";"Larva";49;0
"Building";"Hatchery";NA;30;0
"Unit";"Zergling";"Larva";52;1
"Unit";"Zergling";"Larva";52;1
"Unit";"Zergling";"Larva";52;1
"Unit";"Zergling";"Larva";52;1
"Unit";"Zergling";"Larva";52;1
"Unit";"Zergling";"Larva";52;1
"Unit";"Zergling";"Larva";52;1
"Unit";"Zergling";"Larva";52;1
"Unit";"Zergling";"Larva";52;1
"Unit";"Zergling";"Larva";52;1
"Unit";"Zergling";"Larva";52;1
"Unit";"Zergling";"Larva";52;1
"Unit";"Queen";"Hatchery";51;2
"Building";"CreepTumorQueen";NA;73;0
"Building";"CreepTumorQueen";NA;73;0
"Unit";"Overlord";"Larva";73;0
"Unit";"Overlord";"Larva";73;0
"Building";"SporeCrawler";NA;73;0
"Building";"SporeCrawler";NA;76;0
"Building";"SporeCrawler";NA;76;0
"Building";"Extractor";NA;76;0
"Building";"Extractor";NA;76;0
"Building";"CreepTumor";NA;77;0
"Unit";"Overlord";"Larva";77;0
"Building";"CreepTumor";NA;81;0
"Building";"CreepTumor";NA;81;0
"Building";"CreepTumorQueen";NA;84;0
"Building";"CreepTumor";NA;87;0
"Building";"CreepTumor";NA;87;0
"Building";"CreepTumor";NA;87;0
"Unit";"Queen";"Hatchery";81;2
"Building";"EvolutionChamber";NA;85;0
"Building";"EvolutionChamber";NA;87;0
"Unit";"Overlord";"Larva";91;0
"Unit";"Overlord";"Larva";91;0
"Building";"BanelingNest";NA;87;0
"Building";"CreepTumor";NA;100;0
"Building";"CreepTumor";NA;100;0
"Building";"CreepTumor";NA;100;0
"Building";"HydraliskDen";NA;100;0
"Unit";"Zergling";"Larva";100;1
"Unit";"Zergling";"Larva";100;1
"Unit";"Zergling";"Larva";100;1
"Unit";"Zergling";"Larva";100;1
"Unit";"Zergling";"Larva";100;1
"Unit";"Zergling";"Larva";100;1
"Unit";"Zergling";"Larva";100;1
"Unit";"Zergling";"Larva";100;1
"Unit";"Baneling";"Zergling";110;0
"Unit";"Baneling";"Zergling";110;0
"Unit";"Baneling";"Zergling";112;0
"Unit";"Baneling";"Zergling";112;0
"Unit";"Zergling";"Larva";112;1
"Unit";"Zergling";"Larva";112;1
"Unit";"Zergling";"Larva";112;1
"Unit";"Zergling";"Larva";112;1
"Unit";"Zergling";"Larva";112;1
"Unit";"Zergling";"Larva";112;1
"Unit";"Zergling";"Larva";112;1
"Unit";"Zergling";"Larva";112;1
"Unit";"Overlord";"Larva";122;0
"Unit";"Overlord";"Larva";122;0
"Unit";"Overlord";"Larva";122;0
"Unit";"Zergling";"Larva";128;1
"Unit";"Zergling";"Larva";128;1
"Unit";"Zergling";"Larva";128;1
"Unit";"Zergling";"Larva";128;1
"Unit";"Zergling";"Larva";128;1
"Unit";"Zergling";"Larva";128;1
"Unit";"Zergling";"Larva";128;1
"Unit";"Zergling";"Larva";128;1
"Unit";"Zergling";"Larva";128;1
"Unit";"Zergling";"Larva";128;1
"Unit";"Zergling";"Larva";128;1
"Unit";"Zergling";"Larva";128;1
"Unit";"Zergling";"Larva";128;1
"Unit";"Zergling";"Larva";128;1
"Unit";"Zergling";"Larva";128;1
"Unit";"Zergling";"Larva";128;1
"Unit";"Zergling";"Larva";128;1
"Unit";"Zergling";"Larva";128;1
"Unit";"Zergling";"Larva";128;1
"Unit";"Zergling";"Larva";128;1
"Upgrade";"ZergMissileWeaponsLevel1";"EvolutionChamber";100;0
"Upgrade";"ZergGroundArmorsLevel1";"EvolutionChamber";100;0
"Building";"CreepTumor";NA;148;0
"Building";"CreepTumor";NA;148;0
"Unit";"Overlord";"Larva";148;0
"Unit";"Overlord";"Larva";148;0
"Unit";"Overlord";"Larva";148;0
"Unit";"Overlord";"Larva";148;0
"Unit";"Overlord";"Larva";148;0
"Building";"CreepTumor";NA;148;0
"Building";"Extractor";NA;148;0
"Building";"CreepTumor";NA;152;0
"Unit";"Queen";"Hatchery";148;2
"Upgrade";"EvolveGroovedSpines";"HydraliskDen";148;0
"Unit";"Hydralisk";"Larva";154;2
"Unit";"Hydralisk";"Larva";154;2
"Unit";"Hydralisk";"Larva";154;2
"Unit";"Hydralisk";"Larva";154;2
"Unit";"Hydralisk";"Larva";154;2
"Unit";"Hydralisk";"Larva";154;2
"Unit";"Hydralisk";"Larva";154;2
"Unit";"Baneling";"Zergling";154;0
"Unit";"Baneling";"Zergling";154;0
"Unit";"Baneling";"Zergling";154;0
"Unit";"Baneling";"Zergling";154;0
"Unit";"Baneling";"Zergling";154;0
"Unit";"Baneling";"Zergling";154;0
"Unit";"Baneling";"Zergling";154;0
"Unit";"Baneling";"Zergling";154;0
"Building";"CreepTumor";NA;156;0
"Building";"CreepTumor";NA;156;0
"Unit";"Zergling";"Larva";154;1
"Unit";"Zergling";"Larva";154;1
"Unit";"Zergling";"Larva";154;1
"Unit";"Zergling";"Larva";154;1
"Unit";"Zergling";"Larva";154;1
"Unit";"Zergling";"Larva";154;1
"Building";"CreepTumor";NA;156;0
"Building";"CreepTumorQueen";NA;170;0
"Building";"CreepTumorQueen";NA;176;0
"Unit";"Zergling";"Larva";176;1
"Unit";"Zergling";"Larva";176;1
"Unit";"Zergling";"Larva";176;1
"Unit";"Zergling";"Larva";176;1
"Unit";"Zergling";"Larva";176;1
"Unit";"Zergling";"Larva";176;1
"Unit";"Zergling";"Larva";176;1
"Unit";"Zergling";"Larva";176;1
"Unit";"Zergling";"Larva";176;1
"Unit";"Zergling";"Larva";176;1
"Unit";"Zergling";"Larva";176;1
"Unit";"Zergling";"Larva";176;1
"Unit";"Zergling";"Larva";176;1
"Unit";"Zergling";"Larva";176;1
"Building";"CreepTumor";NA;176;0
"Building";"CreepTumor";NA;176;0
"Building";"Extractor";NA;176;0
"Building";"Hatchery";NA;148;0
"Building";"Extractor";NA;176;0
"Building";"Hatchery";NA;152;0
"Unit";"Zergling";"Larva";195;1
"Unit";"Zergling";"Larva";195;1
"Unit";"Zergling";"Larva";195;1
"Unit";"Zergling";"Larva";195;1
"Unit";"Zergling";"Larva";195;1
"Unit";"Zergling";"Larva";195;1
"Unit";"Hydralisk";"Larva";192;2
"Unit";"Hydralisk";"Larva";192;2
"Unit";"Hydralisk";"Larva";192;2
"Unit";"Hydralisk";"Larva";192;2
"Unit";"Hydralisk";"Larva";192;2
"Unit";"Hydralisk";"Larva";192;2
"Unit";"Zergling";"Larva";195;1
"Unit";"Zergling";"Larva";195;1
"Unit";"Zergling";"Larva";195;1
"Unit";"Zergling";"Larva";195;1
"Unit";"Zergling";"Larva";195;1
"Unit";"Zergling";"Larva";195;1
"Unit";"Zergling";"Larva";195;1
"Unit";"Zergling";"Larva";195;1
"Unit";"Hydralisk";"Larva";195;2
"Upgrade";"EvolveMuscularAugments";"HydraliskDen";176;0
"Upgrade";"ZergMeleeWeaponsLevel1";"EvolutionChamber";156;0
"Unit";"Zergling";"Larva";213;1
"Unit";"Zergling";"Larva";213;1
"Unit";"Zergling";"Larva";213;1
"Unit";"Zergling";"Larva";213;1
"Unit";"Zergling";"Larva";213;1
"Unit";"Zergling";"Larva";213;1
"Building";"CreepTumor";NA;226;0
"Building";"InfestationPit";NA;195;0
"Unit";"Zergling";"Larva";224;1
"Unit";"Zergling";"Larva";224;1
"Unit";"Zergling";"Larva";226;1
"Unit";"Zergling";"Larva";226;1
"Unit";"Zergling";"Larva";226;1
"Unit";"Zergling";"Larva";226;1
"Unit";"Zergling";"Larva";226;1
"Unit";"Zergling";"Larva";226;1
"Unit";"Zergling";"Larva";226;1
"Unit";"Zergling";"Larva";226;1
"Unit";"Overlord";"Larva";226;0
"Unit";"Overlord";"Larva";226;0
"Unit";"Hydralisk";"Larva";223;2
"Upgrade";"ZergMissileWeaponsLevel2";"EvolutionChamber";156;0
"Unit";"Zergling";"Larva";232;1
"Unit";"Zergling";"Larva";232;1
"Unit";"Zergling";"Larva";246;1
"Unit";"Zergling";"Larva";246;1
"Unit";"Zergling";"Larva";246;1
"Unit";"Zergling";"Larva";246;1
"Unit";"Zergling";"Larva";246;1
"Unit";"Zergling";"Larva";246;1
"Unit";"Zergling";"Larva";246;1
"Unit";"Zergling";"Larva";246;1
"Unit";"Zergling";"Larva";246;1
"Unit";"Zergling";"Larva";246;1
"Unit";"Zergling";"Larva";246;1
"Unit";"Zergling";"Larva";246;1
"Unit";"Zergling";"Larva";246;1
"Unit";"Zergling";"Larva";246;1
"Unit";"Zergling";"Larva";246;1
"Unit";"Zergling";"Larva";246;1
"Unit";"Zergling";"Larva";246;1
"Unit";"Zergling";"Larva";246;1
"Unit";"Zergling";"Larva";246;1
"Unit";"Zergling";"Larva";246;1
"Unit";"Zergling";"Larva";246;1
"Unit";"Zergling";"Larva";246;1
"Unit";"Overlord";"Larva";246;0
"Unit";"Overlord";"Larva";246;0
"Unit";"Overlord";"Larva";246;0
"Unit";"Overlord";"Larva";246;0
"Unit";"Hydralisk";"Larva";246;2
"Unit";"Hydralisk";"Larva";246;2
"Unit";"Hydralisk";"Larva";246;2
"Unit";"Hydralisk";"Larva";246;2
"Unit";"Hydralisk";"Larva";246;2
"Building";"CreepTumor";NA;278;0
"Building";"CreepTumor";NA;278;0
"Building";"CreepTumor";NA;278;0
"Building";"CreepTumor";NA;278;0
"Building";"CreepTumor";NA;278;0
"Building";"Hatchery";NA;232;0
"Unit";"Overlord";"Larva";278;0
"Unit";"Overlord";"Larva";278;0
"Unit";"Overlord";"Larva";278;0
"Building";"Spire";NA;242;0
"Unit";"Zergling";"Larva";278;1
"Unit";"Zergling";"Larva";278;1
"Unit";"Zergling";"Larva";278;1
"Unit";"Zergling";"Larva";278;1
"Unit";"Zergling";"Larva";278;1
"Unit";"Zergling";"Larva";278;1
"Unit";"Zergling";"Larva";278;1
"Unit";"Zergling";"Larva";278;1
"Unit";"Zergling";"Larva";278;1
"Unit";"Zergling";"Larva";278;1
"Unit";"Zergling";"Larva";278;1
"Unit";"Zergling";"Larva";278;1
"Building";"Extractor";NA;278;0
"Building";"Extractor";NA;278;0
"Unit";"Baneling";"Zergling";286;0
"Unit";"Baneling";"Zergling";286;0
"Unit";"Baneling";"Zergling";286;0
"Unit";"Baneling";"Zergling";286;0
"Unit";"Baneling";"Zergling";286;0
"Unit";"Baneling";"Zergling";286;0
"Unit";"Baneling";"Zergling";286;0
"Unit";"Baneling";"Zergling";286;0
"Unit";"Baneling";"Zergling";286;0
"Unit";"Baneling";"Zergling";286;0
"Unit";"Baneling";"Zergling";286;0
"Unit";"Baneling";"Zergling";286;0
"Unit";"Baneling";"Zergling";286;0
"Unit";"Baneling";"Zergling";286;0
"Unit";"Baneling";"Zergling";286;0
"Unit";"Baneling";"Zergling";286;0
"Unit";"Baneling";"Zergling";286;0
"Unit";"Corruptor";"Larva";298;2
"Unit";"Corruptor";"Larva";298;2
"Unit";"Corruptor";"Larva";298;2
"Unit";"Corruptor";"Larva";298;2
"Unit";"Corruptor";"Larva";298;2
"Unit";"Corruptor";"Larva";298;2
"Unit";"Corruptor";"Larva";298;2
"Unit";"Zergling";"Larva";312;1
"Unit";"Zergling";"Larva";312;1
"Unit";"Zergling";"Larva";312;1
"Unit";"Zergling";"Larva";312;1
"Unit";"Zergling";"Larva";312;1
"Unit";"Zergling";"Larva";312;1
"Unit";"Zergling";"Larva";312;1
"Unit";"Zergling";"Larva";312;1
"Unit";"Zergling";"Larva";312;1
"Unit";"Zergling";"Larva";312;1
"Unit";"Zergling";"Larva";312;1
"Unit";"Zergling";"Larva";312;1
"Unit";"Zergling";"Larva";312;1
"Unit";"Zergling";"Larva";312;1
"Unit";"Zergling";"Larva";312;1
"Unit";"Zergling";"Larva";312;1
"Unit";"Zergling";"Larva";312;1
"Unit";"Zergling";"Larva";312;1
"Unit";"Zergling";"Larva";312;1
"Unit";"Zergling";"Larva";312;1
"Unit";"Zergling";"Larva";312;1
"Unit";"Zergling";"Larva";312;1
"Unit";"Zergling";"Larva";312;1
"Unit";"Zergling";"Larva";312;1
"Unit";"Zergling";"Larva";312;1
"Unit";"Zergling";"Larva";312;1
"Unit";"Zergling";"Larva";312;1
"Unit";"Zergling";"Larva";312;1
"Unit";"Zergling";"Larva";312;1
"Unit";"Zergling";"Larva";312;1
"Unit";"Zergling";"Larva";312;1
"Unit";"Zergling";"Larva";312;1
"Unit";"Zergling";"Larva";312;1
"Unit";"Zergling";"Larva";312;1
"Upgrade";"ZergMeleeWeaponsLevel2";"EvolutionChamber";246;0
"Unit";"Corruptor";"Larva";298;2
"Unit";"Corruptor";"Larva";298;2
"Unit";"Corruptor";"Larva";298;2
"Unit";"Corruptor";"Larva";298;2
"Building";"Extractor";NA;312;0
"Building";"Extractor";NA;312;0
"Unit";"Zergling";"Larva";361;1
"Unit";"Zergling";"Larva";361;1
"Unit";"Zergling";"Larva";361;1
"Unit";"Zergling";"Larva";361;1
"Unit";"Zergling";"Larva";361;1
"Unit";"Zergling";"Larva";361;1
"Unit";"Zergling";"Larva";361;1
"Unit";"Zergling";"Larva";361;1
"Unit";"Zergling";"Larva";361;1
"Unit";"Zergling";"Larva";361;1
"Unit";"Corruptor";"Larva";361;2
"Unit";"Corruptor";"Larva";361;2
"Unit";"Corruptor";"Larva";361;2
"Unit";"Corruptor";"Larva";361;2
"Unit";"Corruptor";"Larva";361;2
"Unit";"Corruptor";"Larva";361;2
"Unit";"Corruptor";"Larva";361;2
"Unit";"Zergling";"Larva";371;1
"Unit";"Zergling";"Larva";371;1
"Unit";"Zergling";"Larva";371;1
"Unit";"Zergling";"Larva";371;1
"Unit";"Zergling";"Larva";371;1
"Unit";"Zergling";"Larva";371;1
"Unit";"Zergling";"Larva";371;1
"Unit";"Zergling";"Larva";371;1
"Unit";"Zergling";"Larva";371;1
"Unit";"Zergling";"Larva";371;1
"Unit";"Zergling";"Larva";371;1
"Unit";"Zergling";"Larva";371;1
"Unit";"Zergling";"Larva";371;1
"Unit";"Zergling";"Larva";371;1
"Unit";"Zergling";"Larva";371;1
"Unit";"Zergling";"Larva";371;1
"Unit";"Zergling";"Larva";371;1
"Unit";"Zergling";"Larva";371;1
"Unit";"Zergling";"Larva";371;1
"Unit";"Zergling";"Larva";371;1
"Unit";"Zergling";"Larva";371;1
"Unit";"Zergling";"Larva";371;1
"Unit";"Corruptor";"Larva";371;2
"Unit";"Corruptor";"Larva";371;2
"Unit";"Corruptor";"Larva";371;2
"Unit";"Corruptor";"Larva";371;2
"Unit";"Corruptor";"Larva";371;2
"Unit";"Corruptor";"Larva";371;2
"Unit";"Corruptor";"Larva";371;2
"Unit";"Hydralisk";"Larva";407;2
"Unit";"Hydralisk";"Larva";407;2
"Unit";"Hydralisk";"Larva";407;2
"Unit";"Hydralisk";"Larva";407;2
"Unit";"Hydralisk";"Larva";407;2
"Unit";"Hydralisk";"Larva";407;2
"Unit";"Hydralisk";"Larva";407;2
"Unit";"Hydralisk";"Larva";407;2
"Unit";"Viper";"Larva";421;3
"Unit";"Viper";"Larva";421;3
"Unit";"Viper";"Larva";421;3
"Unit";"Corruptor";"Larva";437;2
"Unit";"Corruptor";"Larva";437;2
"Unit";"Corruptor";"Larva";437;2
"Unit";"Corruptor";"Larva";437;2
"Unit";"Corruptor";"Larva";437;2
"Unit";"Corruptor";"Larva";437;2
"Unit";"Corruptor";"Larva";437;2
"Unit";"Corruptor";"Larva";437;2
"Unit";"Zergling";"Larva";462;1
"Unit";"Zergling";"Larva";462;1
"Unit";"Zergling";"Larva";462;1
"Unit";"Zergling";"Larva";462;1
"Unit";"Zergling";"Larva";462;1
"Unit";"Zergling";"Larva";462;1
"Unit";"Zergling";"Larva";462;1
"Unit";"Zergling";"Larva";462;1
"Unit";"Zergling";"Larva";462;1
"Unit";"Zergling";"Larva";462;1
"Unit";"Zergling";"Larva";462;1
"Unit";"Zergling";"Larva";462;1
"Unit";"Zergling";"Larva";462;1
"Unit";"Zergling";"Larva";462;1
"Unit";"Zergling";"Larva";462;1
"Unit";"Zergling";"Larva";462;1
"Unit";"Zergling";"Larva";462;1
"Unit";"Zergling";"Larva";462;1
"Unit";"Zergling";"Larva";462;1
"Unit";"Zergling";"Larva";462;1
"Unit";"Zergling";"Larva";462;1
"Unit";"Zergling";"Larva";462;1
"Unit";"Zergling";"Larva";462;1
"Unit";"Zergling";"Larva";462;1
"Unit";"Zergling";"Larva";462;1
"Unit";"Zergling";"Larva";462;1
"Unit";"Zergling";"Larva";462;1
"Unit";"Zergling";"Larva";462;1
"Unit";"Zergling";"Larva";462;1
"Unit";"Zergling";"Larva";462;1
"Unit";"Zergling";"Larva";462;1
"Unit";"Zergling";"Larva";462;1
"Unit";"Zergling";"Larva";462;1
"Unit";"Zergling";"Larva";462;1
"Unit";"Zergling";"Larva";462;1
"Unit";"Zergling";"Larva";462;1
"Unit";"Zergling";"Larva";462;1
"Unit";"Zergling";"Larva";462;1
"Unit";"Zergling";"Larva";462;1
"Unit";"Zergling";"Larva";462;1
"Unit";"Zergling";"Larva";462;1
"Unit";"Zergling";"Larva";462;1
"Unit";"Zergling";"Larva";462;1
"Unit";"Zergling";"Larva";462;1
