"type";"unit_name";"on_building";"total_supply";"supply"
"Unit";"Overlord";"Larva";13;0
"Building";"Extractor";NA;18;0
"Unit";"Overlord";"Larva";21;0
"Building";"SpawningPool";NA;19;0
"Building";"Hatchery";NA;17;0
"Unit";"Zergling";"Larva";22;1
"Unit";"Zergling";"Larva";22;1
"Unit";"Zergling";"Larva";22;1
"Unit";"Zergling";"Larva";22;1
"Unit";"Queen";"Hatchery";22;2
"Unit";"Queen";"Hatchery";23;2
"Unit";"Overlord";"Larva";37;0
"Unit";"Overlord";"Larva";39;0
"Building";"EvolutionChamber";NA;42;0
"Unit";"Queen";"Hatchery";40;2
"Unit";"Overlord";"Larva";44;0
"Unit";"Overlord";"Larva";48;0
"Building";"Hatchery";NA;37;0
"Building";"CreepTumorQueen";NA;50;0
"Building";"SporeCrawler";NA;48;0
"Building";"SporeCrawler";NA;50;0
"Unit";"Overlord";"Larva";51;0
"Unit";"Overlord";"Larva";55;0
"Building";"CreepTumorQueen";NA;60;0
"Building";"CreepTumor";NA;60;0
"Building";"Extractor";NA;55;0
"Unit";"Zergling";"Larva";60;1
"Unit";"Zergling";"Larva";60;1
"Building";"SporeCrawler";NA;60;0
"Unit";"Zergling";"Larva";60;1
"Unit";"Zergling";"Larva";60;1
"Unit";"Overlord";"Larva";60;0
"Building";"BanelingNest";NA;55;0
"Building";"CreepTumor";NA;71;0
"Building";"CreepTumor";NA;71;0
"Unit";"Zergling";"Larva";71;1
"Unit";"Zergling";"Larva";71;1
"Unit";"Zergling";"Larva";71;1
"Unit";"Zergling";"Larva";71;1
"Unit";"Zergling";"Larva";71;1
"Unit";"Zergling";"Larva";71;1
"Building";"Extractor";NA;71;0
"Building";"Extractor";NA;71;0
"Building";"HydraliskDen";NA;76;0
"Unit";"Zergling";"Larva";89;1
"Unit";"Zergling";"Larva";89;1
"Unit";"Zergling";"Larva";89;1
"Unit";"Zergling";"Larva";89;1
"Unit";"Zergling";"Larva";89;1
"Unit";"Zergling";"Larva";89;1
"Unit";"Zergling";"Larva";89;1
"Unit";"Zergling";"Larva";89;1
"Unit";"Zergling";"Larva";89;1
"Unit";"Zergling";"Larva";89;1
"Unit";"Zergling";"Larva";89;1
"Unit";"Zergling";"Larva";89;1
"Unit";"Zergling";"Larva";89;1
"Unit";"Zergling";"Larva";89;1
"Unit";"Overlord";"Larva";92;0
"Unit";"Hydralisk";"Larva";92;2
"Building";"CreepTumor";NA;109;0
"Building";"Extractor";NA;107;0
"Building";"Extractor";NA;109;0
"Upgrade";"ZergMeleeWeaponsLevel1";"EvolutionChamber";71;0
"Unit";"Hydralisk";"Larva";109;2
"Unit";"Zergling";"Larva";114;1
"Unit";"Zergling";"Larva";114;1
"Unit";"Zergling";"Larva";114;1
"Unit";"Zergling";"Larva";114;1
"Unit";"Hydralisk";"Larva";114;2
"Unit";"Hydralisk";"Larva";114;2
"Unit";"Hydralisk";"Larva";114;2
"Unit";"Hydralisk";"Larva";118;2
"Building";"Hatchery";NA;92;0
"Upgrade";"EvolveMuscularAugments";"HydraliskDen";116;0
"Unit";"Zergling";"Larva";147;1
"Unit";"Zergling";"Larva";147;1
"Unit";"Baneling";"Zergling";148;0
"Unit";"Overlord";"Larva";148;0
"Unit";"Baneling";"Zergling";148;0
"Unit";"Overlord";"Larva";148;0
"Unit";"Baneling";"Zergling";148;0
"Unit";"Baneling";"Zergling";148;0
"Unit";"Baneling";"Zergling";148;0
"Unit";"Baneling";"Zergling";148;0
"Unit";"Baneling";"Zergling";148;0
"Unit";"Baneling";"Zergling";148;0
"Unit";"Hydralisk";"Larva";144;2
"Unit";"Hydralisk";"Larva";144;2
"Unit";"Overlord";"Larva";148;0
"Unit";"Overlord";"Larva";148;0
"Unit";"Overlord";"Larva";148;0
"Unit";"Zergling";"Larva";154;1
"Unit";"Zergling";"Larva";154;1
"Unit";"Hydralisk";"Larva";154;2
"Unit";"Hydralisk";"Larva";154;2
"Unit";"Hydralisk";"Larva";154;2
"Unit";"Queen";"Hatchery";150;2
"Unit";"Zergling";"Larva";164;1
"Unit";"Zergling";"Larva";164;1
"Unit";"Zergling";"Larva";164;1
"Unit";"Zergling";"Larva";164;1
"Unit";"Zergling";"Larva";164;1
"Unit";"Zergling";"Larva";164;1
"Unit";"Hydralisk";"Larva";164;2
"Unit";"Hydralisk";"Larva";164;2
"Unit";"Hydralisk";"Larva";164;2
"Unit";"Hydralisk";"Larva";164;2
"Unit";"Hydralisk";"Larva";164;2
"Unit";"Hydralisk";"Larva";164;2
"Unit";"Hydralisk";"Larva";164;2
"Unit";"Hydralisk";"Larva";164;2
"Upgrade";"EvolveGroovedSpines";"HydraliskDen";154;0
"Building";"EvolutionChamber";NA;175;0
"Unit";"Overlord";"Larva";197;0
"Unit";"Overlord";"Larva";197;0
"Unit";"Overlord";"Larva";197;0
"Unit";"Hydralisk";"Larva";181;2
"Unit";"Hydralisk";"Larva";181;2
"Unit";"Hydralisk";"Larva";181;2
"Unit";"Baneling";"Zergling";197;0
"Unit";"Hydralisk";"Larva";181;2
"Unit";"Hydralisk";"Larva";181;2
"Unit";"Overlord";"Larva";197;0
"Unit";"Overlord";"Larva";197;0
"Building";"Extractor";NA;197;0
"Unit";"Overlord";"Larva";197;0
"Building";"LurkerDenMP";NA;148;0
"Building";"Extractor";NA;197;0
"Building";"InfestationPit";NA;181;0
"Unit";"Zergling";"Larva";207;1
"Unit";"Zergling";"Larva";207;1
"Unit";"Zergling";"Larva";207;1
"Unit";"Zergling";"Larva";207;1
"Unit";"Zergling";"Larva";207;1
"Unit";"Zergling";"Larva";207;1
"Unit";"Zergling";"Larva";207;1
"Unit";"Zergling";"Larva";207;1
"Unit";"Hydralisk";"Larva";207;2
"Unit";"Hydralisk";"Larva";207;2
"Unit";"Hydralisk";"Larva";207;2
"Unit";"Hydralisk";"Larva";207;2
"Unit";"Hydralisk";"Larva";207;2
"Unit";"Hydralisk";"Larva";207;2
"Unit";"Zergling";"Larva";215;1
"Unit";"Zergling";"Larva";215;1
"Unit";"Zergling";"Larva";219;1
"Unit";"Zergling";"Larva";219;1
"Unit";"Zergling";"Larva";219;1
"Unit";"Zergling";"Larva";219;1
"Unit";"Zergling";"Larva";219;1
"Unit";"Zergling";"Larva";219;1
"Unit";"Zergling";"Larva";219;1
"Unit";"Zergling";"Larva";219;1
"Unit";"Overlord";"Larva";235;0
"Unit";"Zergling";"Larva";235;1
"Unit";"Zergling";"Larva";235;1
"Unit";"Zergling";"Larva";235;1
"Unit";"Zergling";"Larva";235;1
"Building";"CreepTumor";NA;235;0
"Unit";"Zergling";"Larva";235;1
"Unit";"Zergling";"Larva";235;1
"Unit";"Zergling";"Larva";235;1
"Unit";"Zergling";"Larva";235;1
"Unit";"Zergling";"Larva";235;1
"Unit";"Zergling";"Larva";235;1
"Unit";"Zergling";"Larva";235;1
"Unit";"Zergling";"Larva";235;1
"Upgrade";"ZergMissileWeaponsLevel1";"EvolutionChamber";197;0
"Unit";"Zergling";"Larva";257;1
"Unit";"Zergling";"Larva";257;1
"Unit";"Zergling";"Larva";257;1
"Unit";"Zergling";"Larva";257;1
"Unit";"Zergling";"Larva";257;1
"Unit";"Zergling";"Larva";257;1
"Unit";"Zergling";"Larva";257;1
"Unit";"Zergling";"Larva";257;1
"Unit";"Baneling";"Zergling";257;0
"Unit";"Zergling";"Larva";257;1
"Unit";"Zergling";"Larva";257;1
"Unit";"Zergling";"Larva";257;1
"Unit";"Zergling";"Larva";257;1
"Unit";"Zergling";"Larva";257;1
"Unit";"Zergling";"Larva";257;1
"Unit";"Baneling";"Zergling";257;0
"Unit";"Baneling";"Zergling";257;0
"Unit";"Zergling";"Larva";257;1
"Unit";"Zergling";"Larva";257;1
"Unit";"Baneling";"Zergling";257;0
"Unit";"Baneling";"Zergling";257;0
"Unit";"Baneling";"Zergling";257;0
"Unit";"Zergling";"Larva";257;1
"Unit";"Zergling";"Larva";257;1
"Unit";"Baneling";"Zergling";257;0
"Unit";"Zergling";"Larva";257;1
"Unit";"Zergling";"Larva";257;1
"Unit";"Hydralisk";"Larva";257;2
"Unit";"Hydralisk";"Larva";257;2
"Unit";"Hydralisk";"Larva";257;2
"Unit";"Hydralisk";"Larva";257;2
"Unit";"Hydralisk";"Larva";257;2
"Unit";"Hydralisk";"Larva";257;2
"Unit";"Hydralisk";"Larva";257;2
"Building";"Hatchery";NA;230;0
"Unit";"Hydralisk";"Larva";291;2
"Unit";"Hydralisk";"Larva";291;2
"Unit";"Hydralisk";"Larva";291;2
"Unit";"Hydralisk";"Larva";291;2
"Unit";"Hydralisk";"Larva";291;2
"Unit";"Hydralisk";"Larva";291;2
"Unit";"Hydralisk";"Larva";291;2
"Unit";"Hydralisk";"Larva";291;2
"Upgrade";"ZergMeleeWeaponsLevel2";"EvolutionChamber";235;0
"Unit";"Zergling";"Larva";307;1
"Unit";"Zergling";"Larva";307;1
"Unit";"Zergling";"Larva";307;1
"Unit";"Zergling";"Larva";307;1
"Unit";"Zergling";"Larva";307;1
"Unit";"Zergling";"Larva";307;1
"Unit";"Zergling";"Larva";307;1
"Unit";"Zergling";"Larva";307;1
"Unit";"Zergling";"Larva";307;1
"Unit";"Zergling";"Larva";307;1
"Unit";"Zergling";"Larva";307;1
"Unit";"Zergling";"Larva";307;1
"Unit";"Hydralisk";"Larva";307;2
"Unit";"Hydralisk";"Larva";307;2
"Unit";"Hydralisk";"Larva";307;2
"Unit";"Hydralisk";"Larva";307;2
"Unit";"Hydralisk";"Larva";307;2
"Unit";"Hydralisk";"Larva";307;2
"Unit";"Zergling";"Larva";331;1
"Unit";"Zergling";"Larva";331;1
"Unit";"Zergling";"Larva";331;1
"Unit";"Zergling";"Larva";331;1
"Unit";"Zergling";"Larva";331;1
"Unit";"Zergling";"Larva";331;1
"Unit";"Zergling";"Larva";331;1
"Unit";"Zergling";"Larva";331;1
"Unit";"Zergling";"Larva";331;1
"Unit";"Zergling";"Larva";331;1
"Unit";"Zergling";"Larva";331;1
"Unit";"Zergling";"Larva";331;1
"Unit";"Zergling";"Larva";331;1
"Unit";"Zergling";"Larva";331;1
"Unit";"Zergling";"Larva";331;1
"Unit";"Zergling";"Larva";331;1
"Unit";"Zergling";"Larva";347;1
"Unit";"Zergling";"Larva";347;1
"Unit";"Zergling";"Larva";347;1
"Unit";"Zergling";"Larva";347;1
"Unit";"Zergling";"Larva";347;1
"Unit";"Zergling";"Larva";347;1
"Unit";"Zergling";"Larva";347;1
"Unit";"Zergling";"Larva";347;1
"Unit";"Zergling";"Larva";347;1
"Unit";"Zergling";"Larva";347;1
"Unit";"Zergling";"Larva";347;1
"Unit";"Zergling";"Larva";347;1
"Unit";"Zergling";"Larva";347;1
"Unit";"Zergling";"Larva";347;1
"Unit";"Zergling";"Larva";347;1
"Unit";"Zergling";"Larva";347;1
"Unit";"Zergling";"Larva";347;1
"Unit";"Zergling";"Larva";347;1
"Unit";"Zergling";"Larva";347;1
"Unit";"Zergling";"Larva";347;1
"Unit";"Zergling";"Larva";347;1
"Unit";"Zergling";"Larva";347;1
"Unit";"Zergling";"Larva";349;1
"Unit";"Zergling";"Larva";349;1
"Unit";"Zergling";"Larva";357;1
"Unit";"Zergling";"Larva";357;1
"Unit";"Zergling";"Larva";369;1
"Unit";"Zergling";"Larva";369;1
"Unit";"Hydralisk";"Larva";347;2
"Unit";"Hydralisk";"Larva";347;2
"Unit";"Hydralisk";"Larva";347;2
"Unit";"Hydralisk";"Larva";349;2
"Unit";"Hydralisk";"Larva";349;2
"Unit";"Zergling";"Larva";375;1
"Unit";"Zergling";"Larva";375;1
"Unit";"Hydralisk";"Larva";375;2
"Unit";"Hydralisk";"Larva";375;2
"Unit";"Hydralisk";"Larva";375;2
"Building";"SporeCrawler";NA;391;0
"Building";"SpineCrawler";NA;391;0
"Unit";"Baneling";"Zergling";399;0
"Unit";"Overlord";"Larva";399;0
"Unit";"Overlord";"Larva";399;0
"Unit";"Overlord";"Larva";399;0
"Unit";"Overlord";"Larva";399;0
"Unit";"Overlord";"Larva";399;0
"Unit";"Overlord";"Larva";399;0
"Unit";"Baneling";"Zergling";399;0
"Unit";"Baneling";"Zergling";399;0
"Unit";"Baneling";"Zergling";399;0
"Unit";"Baneling";"Zergling";399;0
"Unit";"Baneling";"Zergling";399;0
"Unit";"Baneling";"Zergling";399;0
"Unit";"Baneling";"Zergling";399;0
"Unit";"Baneling";"Zergling";399;0
"Unit";"Baneling";"Zergling";399;0
"Unit";"Baneling";"Zergling";399;0
"Unit";"Baneling";"Zergling";399;0
"Unit";"Baneling";"Zergling";399;0
"Unit";"Baneling";"Zergling";399;0
"Unit";"Baneling";"Zergling";399;0
"Unit";"Baneling";"Zergling";399;0
"Unit";"Baneling";"Zergling";399;0
"Unit";"Baneling";"Zergling";399;0
"Unit";"Baneling";"Zergling";399;0
"Unit";"Baneling";"Zergling";399;0
"Unit";"Baneling";"Zergling";399;0
"Unit";"Baneling";"Zergling";399;0
"Unit";"Baneling";"Zergling";399;0
"Unit";"Baneling";"Zergling";399;0
"Unit";"Baneling";"Zergling";399;0
"Unit";"Baneling";"Zergling";399;0
"Unit";"Baneling";"Zergling";399;0
"Unit";"Baneling";"Zergling";399;0
"Building";"Spire";NA;391;0
"Unit";"Zergling";"Larva";399;1
"Unit";"Zergling";"Larva";399;1
"Unit";"Zergling";"Larva";399;1
"Unit";"Zergling";"Larva";399;1
"Unit";"Zergling";"Larva";399;1
"Unit";"Zergling";"Larva";399;1
"Unit";"Zergling";"Larva";399;1
"Unit";"Zergling";"Larva";399;1
"Unit";"Zergling";"Larva";399;1
"Unit";"Zergling";"Larva";399;1
"Unit";"Zergling";"Larva";399;1
"Unit";"Zergling";"Larva";399;1
"Unit";"Zergling";"Larva";399;1
"Unit";"Zergling";"Larva";399;1
"Unit";"Zergling";"Larva";399;1
"Unit";"Zergling";"Larva";399;1
"Unit";"Zergling";"Larva";399;1
"Unit";"Zergling";"Larva";399;1
"Unit";"Hydralisk";"Larva";399;2
"Unit";"Hydralisk";"Larva";399;2
"Unit";"Hydralisk";"Larva";399;2
"Unit";"Hydralisk";"Larva";399;2
"Unit";"Hydralisk";"Larva";399;2
"Unit";"Hydralisk";"Larva";399;2
"Unit";"Hydralisk";"Larva";399;2
"Unit";"Hydralisk";"Larva";399;2
"Building";"Extractor";NA;401;0
"Upgrade";"ZergMissileWeaponsLevel2";"EvolutionChamber";399;0
"Unit";"Zergling";"Larva";436;1
"Unit";"Zergling";"Larva";436;1
"Unit";"Zergling";"Larva";436;1
"Unit";"Zergling";"Larva";436;1
"Unit";"Zergling";"Larva";436;1
"Unit";"Zergling";"Larva";436;1
"Unit";"Zergling";"Larva";436;1
"Unit";"Zergling";"Larva";436;1
"Unit";"Zergling";"Larva";436;1
"Unit";"Zergling";"Larva";436;1
"Unit";"Zergling";"Larva";436;1
"Unit";"Zergling";"Larva";436;1
"Unit";"Zergling";"Larva";436;1
"Unit";"Zergling";"Larva";436;1
"Unit";"Zergling";"Larva";436;1
"Unit";"Zergling";"Larva";436;1
"Unit";"Zergling";"Larva";436;1
"Unit";"Zergling";"Larva";436;1
"Unit";"Zergling";"Larva";436;1
"Unit";"Zergling";"Larva";436;1
"Unit";"Zergling";"Larva";436;1
"Unit";"Zergling";"Larva";436;1
"Unit";"Zergling";"Larva";436;1
"Unit";"Zergling";"Larva";436;1
"Unit";"Zergling";"Larva";436;1
"Unit";"Zergling";"Larva";436;1
"Unit";"Zergling";"Larva";436;1
"Unit";"Zergling";"Larva";436;1
"Unit";"Zergling";"Larva";436;1
"Unit";"Zergling";"Larva";436;1
"Unit";"Zergling";"Larva";436;1
"Unit";"Zergling";"Larva";436;1
"Unit";"Zergling";"Larva";436;1
"Unit";"Zergling";"Larva";436;1
"Unit";"Hydralisk";"Larva";436;2
"Unit";"Hydralisk";"Larva";436;2
"Unit";"Hydralisk";"Larva";436;2
"Unit";"Hydralisk";"Larva";436;2
"Unit";"Hydralisk";"Larva";436;2
"Unit";"Hydralisk";"Larva";436;2
"Unit";"Hydralisk";"Larva";436;2
"Unit";"Hydralisk";"Larva";436;2
"Upgrade";"ZergMeleeWeaponsLevel3";"EvolutionChamber";399;0
"Unit";"Baneling";"Zergling";480;0
"Unit";"Baneling";"Zergling";486;0
"Unit";"Baneling";"Zergling";486;0
"Unit";"Baneling";"Zergling";486;0
"Unit";"Baneling";"Zergling";486;0
"Unit";"Baneling";"Zergling";486;0
"Unit";"Baneling";"Zergling";486;0
"Unit";"Baneling";"Zergling";486;0
"Unit";"Baneling";"Zergling";486;0
"Unit";"Baneling";"Zergling";486;0
"Unit";"Baneling";"Zergling";486;0
"Unit";"Baneling";"Zergling";486;0
"Unit";"Baneling";"Zergling";486;0
"Unit";"Baneling";"Zergling";486;0
"Unit";"Baneling";"Zergling";486;0
"Unit";"Baneling";"Zergling";486;0
"Unit";"Baneling";"Zergling";486;0
"Unit";"Baneling";"Zergling";486;0
"Unit";"Baneling";"Zergling";486;0
"Unit";"Baneling";"Zergling";486;0
"Unit";"Baneling";"Zergling";486;0
"Unit";"Baneling";"Zergling";486;0
"Unit";"Hydralisk";"Larva";486;2
"Unit";"Corruptor";"Larva";486;2
"Unit";"Corruptor";"Larva";486;2
"Unit";"Corruptor";"Larva";486;2
"Unit";"Hydralisk";"Larva";486;2
"Unit";"Hydralisk";"Larva";486;2
"Unit";"Hydralisk";"Larva";486;2
"Unit";"Hydralisk";"Larva";488;2
"Unit";"Hydralisk";"Larva";488;2
"Unit";"Hydralisk";"Larva";488;2
"Unit";"Zergling";"Larva";494;1
"Unit";"Zergling";"Larva";494;1
"Unit";"Zergling";"Larva";494;1
"Unit";"Zergling";"Larva";494;1
"Unit";"Zergling";"Larva";494;1
"Unit";"Zergling";"Larva";494;1
"Unit";"Zergling";"Larva";494;1
"Unit";"Zergling";"Larva";494;1
"Unit";"Zergling";"Larva";494;1
"Unit";"Zergling";"Larva";494;1
"Unit";"Zergling";"Larva";494;1
"Unit";"Zergling";"Larva";494;1
"Unit";"Zergling";"Larva";494;1
"Unit";"Zergling";"Larva";494;1
"Unit";"Zergling";"Larva";514;1
"Unit";"Zergling";"Larva";514;1
"Unit";"Zergling";"Larva";514;1
"Unit";"Zergling";"Larva";514;1
"Unit";"Zergling";"Larva";514;1
"Unit";"Zergling";"Larva";514;1
"Unit";"Zergling";"Larva";514;1
"Unit";"Zergling";"Larva";514;1
"Unit";"Hydralisk";"Larva";514;2
"Unit";"Hydralisk";"Larva";520;2
"Unit";"Hydralisk";"Larva";520;2
"Building";"EvolutionChamber";NA;520;0
"Building";"EvolutionChamber";NA;520;0
"Unit";"Hydralisk";"Larva";528;2
"Unit";"Hydralisk";"Larva";530;2
"Unit";"Hydralisk";"Larva";530;2
"Building";"BanelingNest";NA;520;0
"Building";"Hatchery";NA;514;0
"Unit";"Zergling";"Larva";548;1
"Unit";"Zergling";"Larva";548;1
"Unit";"Zergling";"Larva";548;1
"Unit";"Zergling";"Larva";548;1
"Unit";"Zergling";"Larva";548;1
"Unit";"Zergling";"Larva";548;1
"Unit";"Zergling";"Larva";548;1
"Unit";"Zergling";"Larva";548;1
"Building";"LurkerDenMP";NA;514;0
"Unit";"Zergling";"Larva";548;1
"Unit";"Zergling";"Larva";548;1
"Unit";"Zergling";"Larva";548;1
"Unit";"Zergling";"Larva";548;1
"Unit";"Zergling";"Larva";548;1
"Unit";"Zergling";"Larva";548;1
"Unit";"Hydralisk";"Larva";548;2
"Unit";"Hydralisk";"Larva";548;2
"Unit";"Hydralisk";"Larva";548;2
"Unit";"Hydralisk";"Larva";548;2
"Unit";"Hydralisk";"Larva";548;2
"Unit";"Hydralisk";"Larva";548;2
"Unit";"Hydralisk";"Larva";548;2
"Unit";"Hydralisk";"Larva";548;2
"Unit";"Hydralisk";"Larva";548;2
"Unit";"Hydralisk";"Larva";548;2
"Building";"Extractor";NA;578;0
"Unit";"Zergling";"Larva";586;1
"Unit";"Zergling";"Larva";586;1
"Unit";"Zergling";"Larva";586;1
"Unit";"Zergling";"Larva";586;1
"Unit";"Zergling";"Larva";586;1
"Unit";"Zergling";"Larva";586;1
"Unit";"Zergling";"Larva";586;1
"Unit";"Zergling";"Larva";586;1
"Unit";"Hydralisk";"Larva";586;2
"Unit";"Hydralisk";"Larva";586;2
"Unit";"Hydralisk";"Larva";586;2
"Unit";"Zergling";"Larva";590;1
"Unit";"Zergling";"Larva";590;1
"Unit";"Zergling";"Larva";590;1
"Unit";"Zergling";"Larva";590;1
"Unit";"Zergling";"Larva";590;1
"Unit";"Zergling";"Larva";590;1
"Unit";"Zergling";"Larva";590;1
"Unit";"Zergling";"Larva";590;1
"Unit";"Zergling";"Larva";590;1
"Unit";"Zergling";"Larva";590;1
"Unit";"Hydralisk";"Larva";590;2
"Unit";"Hydralisk";"Larva";590;2
"Unit";"Zergling";"Larva";604;1
"Unit";"Zergling";"Larva";604;1
"Unit";"Zergling";"Larva";604;1
"Unit";"Zergling";"Larva";604;1
"Unit";"Hydralisk";"Larva";598;2
"Unit";"Hydralisk";"Larva";598;2
