"type";"unit_name";"on_building";"total_supply";"supply"
"Unit";"Overlord";"Larva";13;0
"Building";"Extractor";NA;17;0
"Unit";"Overlord";"Larva";21;0
"Building";"SpawningPool";NA;19;0
"Building";"Hatchery";NA;17;0
"Unit";"Zergling";"Larva";22;1
"Unit";"Zergling";"Larva";22;1
"Unit";"Zergling";"Larva";23;1
"Unit";"Zergling";"Larva";23;1
"Unit";"Queen";"Hatchery";22;2
"Unit";"Queen";"Hatchery";23;2
"Unit";"Overlord";"Larva";35;0
"Building";"CreepTumorQueen";NA;39;0
"Unit";"Queen";"Hatchery";38;2
"Unit";"Overlord";"Larva";40;0
"Unit";"Overlord";"Larva";43;0
"Building";"CreepTumor";NA;47;0
"Building";"Hatchery";NA;34;0
"Building";"SporeCrawler";NA;49;0
"Building";"SporeCrawler";NA;49;0
"Unit";"Queen";"Hatchery";50;2
"Building";"SporeCrawler";NA;59;0
"Building";"CreepTumorQueen";NA;67;0
"Unit";"Overlord";"Larva";66;0
"Unit";"Overlord";"Larva";67;0
"Building";"Extractor";NA;67;0
"Building";"Extractor";NA;67;0
"Unit";"Overlord";"Larva";68;0
"Unit";"Overlord";"Larva";68;0
"Building";"CreepTumorQueen";NA;69;0
"Building";"Extractor";NA;68;0
"Building";"CreepTumor";NA;77;0
"Building";"CreepTumorQueen";NA;86;0
"Unit";"Zergling";"Larva";86;1
"Unit";"Zergling";"Larva";86;1
"Unit";"Zergling";"Larva";86;1
"Unit";"Zergling";"Larva";86;1
"Unit";"Zergling";"Larva";86;1
"Unit";"Zergling";"Larva";86;1
"Building";"CreepTumor";NA;86;0
"Unit";"Overlord";"Larva";86;0
"Building";"Extractor";NA;86;0
"Building";"CreepTumor";NA;86;0
"Unit";"Overlord";"Larva";86;0
"Building";"Extractor";NA;86;0
"Building";"HydraliskDen";NA;86;0
"Unit";"Overlord";"Larva";98;0
"Unit";"Overlord";"Larva";98;0
"Unit";"Overlord";"Larva";98;0
"Unit";"Overlord";"Larva";98;0
"Unit";"Hydralisk";"Larva";98;2
"Unit";"Hydralisk";"Larva";98;2
"Unit";"Hydralisk";"Larva";98;2
"Unit";"Hydralisk";"Larva";98;2
"Unit";"Hydralisk";"Larva";98;2
"Unit";"Hydralisk";"Larva";98;2
"Unit";"Hydralisk";"Larva";98;2
"Unit";"Hydralisk";"Larva";98;2
"Building";"CreepTumor";NA;119;0
"Unit";"Overlord";"Larva";119;0
"Building";"EvolutionChamber";NA;119;0
"Building";"EvolutionChamber";NA;119;0
"Building";"CreepTumor";NA;124;0
"Unit";"Hydralisk";"Larva";119;2
"Unit";"Hydralisk";"Larva";119;2
"Unit";"Hydralisk";"Larva";119;2
"Unit";"Hydralisk";"Larva";119;2
"Unit";"Hydralisk";"Larva";119;2
"Building";"CreepTumor";NA;124;0
"Unit";"Hydralisk";"Larva";119;2
"Unit";"Overlord";"Larva";124;0
"Building";"Extractor";NA;124;0
"Building";"Extractor";NA;124;0
"Unit";"Hydralisk";"Larva";124;2
"Unit";"Hydralisk";"Larva";124;2
"Unit";"Hydralisk";"Larva";124;2
"Unit";"Hydralisk";"Larva";124;2
"Unit";"Hydralisk";"Larva";124;2
"Building";"CreepTumorQueen";NA;136;0
"Unit";"Overlord";"Larva";124;0
"Building";"CreepTumor";NA;136;0
"Unit";"Hydralisk";"Larva";124;2
"Unit";"Hydralisk";"Larva";124;2
"Unit";"Zergling";"Larva";136;1
"Unit";"Zergling";"Larva";136;1
"Unit";"Zergling";"Larva";136;1
"Unit";"Zergling";"Larva";136;1
"Unit";"Zergling";"Larva";136;1
"Unit";"Zergling";"Larva";136;1
"Unit";"Zergling";"Larva";136;1
"Unit";"Zergling";"Larva";136;1
"Building";"CreepTumor";NA;150;0
"Unit";"Overlord";"Larva";146;0
"Unit";"Hydralisk";"Larva";146;2
"Unit";"Hydralisk";"Larva";146;2
"Unit";"Hydralisk";"Larva";146;2
"Building";"CreepTumor";NA;158;0
"Building";"CreepTumorQueen";NA;158;0
"Building";"CreepTumor";NA;158;0
"Unit";"Overlord";"Larva";158;0
"Upgrade";"EvolveMuscularAugments";"HydraliskDen";124;0
"Building";"CreepTumor";NA;158;0
"Building";"LurkerDenMP";NA;116;0
"Unit";"Zergling";"Larva";158;1
"Unit";"Zergling";"Larva";158;1
"Building";"Hatchery";NA;124;0
"Unit";"Hydralisk";"Larva";158;2
"Unit";"Hydralisk";"Larva";158;2
"Unit";"Hydralisk";"Larva";158;2
"Unit";"Hydralisk";"Larva";158;2
"Unit";"Hydralisk";"Larva";158;2
"Unit";"Hydralisk";"Larva";158;2
"Unit";"Hydralisk";"Larva";158;2
"Unit";"Overlord";"Larva";164;0
"Unit";"Overlord";"Larva";164;0
"Unit";"Zergling";"Larva";164;1
"Unit";"Zergling";"Larva";164;1
"Unit";"Zergling";"Larva";164;1
"Unit";"Zergling";"Larva";164;1
"Unit";"Zergling";"Larva";164;1
"Unit";"Zergling";"Larva";164;1
"Unit";"Zergling";"Larva";164;1
"Unit";"Zergling";"Larva";164;1
"Unit";"Zergling";"Larva";164;1
"Unit";"Zergling";"Larva";164;1
"Building";"CreepTumor";NA;180;0
"Unit";"Hydralisk";"Larva";164;2
"Unit";"Zergling";"Larva";197;1
"Unit";"Zergling";"Larva";197;1
"Unit";"Zergling";"Larva";199;1
"Unit";"Zergling";"Larva";199;1
"Unit";"Zergling";"Larva";200;1
"Unit";"Zergling";"Larva";200;1
"Building";"CreepTumor";NA;200;0
"Building";"CreepTumor";NA;200;0
"Unit";"Overlord";"Larva";200;0
"Unit";"Hydralisk";"Larva";197;2
"Unit";"Hydralisk";"Larva";197;2
"Unit";"Hydralisk";"Larva";197;2
"Unit";"Hydralisk";"Larva";197;2
"Unit";"Hydralisk";"Larva";197;2
"Upgrade";"ZergMissileWeaponsLevel1";"EvolutionChamber";158;0
"Upgrade";"EvolveGroovedSpines";"HydraliskDen";180;0
"Upgrade";"ZergGroundArmorsLevel1";"EvolutionChamber";158;0
"Unit";"Overlord";"Larva";216;0
"Unit";"Overlord";"Larva";216;0
"Unit";"Hydralisk";"Larva";216;2
"Unit";"Hydralisk";"Larva";216;2
"Unit";"Hydralisk";"Larva";216;2
"Unit";"Hydralisk";"Larva";216;2
"Unit";"Hydralisk";"Larva";216;2
"Unit";"Hydralisk";"Larva";216;2
"Unit";"Overlord";"Larva";219;0
"Unit";"Overlord";"Larva";219;0
"Unit";"Overlord";"Larva";219;0
"Building";"Extractor";NA;219;0
"Building";"Extractor";NA;219;0
"Unit";"Hydralisk";"Larva";219;2
"Unit";"Hydralisk";"Larva";219;2
"Unit";"Overlord";"Larva";231;0
"Unit";"Overlord";"Larva";231;0
"Building";"CreepTumor";NA;231;0
"Unit";"Overlord";"Larva";235;0
"Unit";"Hydralisk";"Larva";235;2
"Unit";"Hydralisk";"Larva";235;2
"Unit";"Hydralisk";"Larva";235;2
"Unit";"Hydralisk";"Larva";235;2
"Building";"Hatchery";NA;219;0
"Unit";"Hydralisk";"Larva";243;2
"Unit";"Hydralisk";"Larva";243;2
"Unit";"Hydralisk";"Larva";243;2
"Unit";"Hydralisk";"Larva";243;2
"Unit";"Hydralisk";"Larva";243;2
"Unit";"Hydralisk";"Larva";243;2
"Building";"InfestationPit";NA;235;0
"Unit";"Hydralisk";"Larva";249;2
"Unit";"Hydralisk";"Larva";249;2
"Unit";"Hydralisk";"Larva";249;2
"Unit";"Hydralisk";"Larva";249;2
"Unit";"Hydralisk";"Larva";249;2
"Unit";"Hydralisk";"Larva";249;2
"Unit";"Hydralisk";"Larva";249;2
"Unit";"Hydralisk";"Larva";249;2
"Unit";"Hydralisk";"Larva";249;2
"Unit";"Hydralisk";"Larva";249;2
"Unit";"Hydralisk";"Larva";249;2
"Unit";"Hydralisk";"Larva";249;2
"Unit";"Hydralisk";"Larva";249;2
"Unit";"Hydralisk";"Larva";249;2
"Unit";"Hydralisk";"Larva";249;2
"Unit";"Hydralisk";"Larva";249;2
"Unit";"Hydralisk";"Larva";249;2
"Unit";"Hydralisk";"Larva";249;2
"Unit";"Hydralisk";"Larva";259;2
"Unit";"Hydralisk";"Larva";261;2
"Unit";"Hydralisk";"Larva";261;2
"Building";"CreepTumor";NA;297;0
"Unit";"Hydralisk";"Larva";287;2
"Unit";"Hydralisk";"Larva";287;2
"Unit";"Hydralisk";"Larva";297;2
"Unit";"Hydralisk";"Larva";297;2
"Unit";"Hydralisk";"Larva";307;2
"Unit";"Hydralisk";"Larva";307;2
"Unit";"Hydralisk";"Larva";307;2
"Unit";"Hydralisk";"Larva";307;2
"Upgrade";"ZergGroundArmorsLevel2";"EvolutionChamber";243;0
"Upgrade";"ZergMissileWeaponsLevel2";"EvolutionChamber";246;0
"Unit";"Hydralisk";"Larva";311;2
"Unit";"Hydralisk";"Larva";311;2
"Unit";"Hydralisk";"Larva";311;2
"Unit";"Hydralisk";"Larva";311;2
"Unit";"Hydralisk";"Larva";311;2
"Unit";"Hydralisk";"Larva";311;2
"Unit";"Hydralisk";"Larva";311;2
"Unit";"Hydralisk";"Larva";311;2
"Unit";"Hydralisk";"Larva";311;2
"Unit";"Hydralisk";"Larva";311;2
"Unit";"Hydralisk";"Larva";319;2
"Unit";"Hydralisk";"Larva";319;2
"Unit";"Hydralisk";"Larva";319;2
"Unit";"Hydralisk";"Larva";319;2
"Unit";"Hydralisk";"Larva";319;2
"Unit";"Hydralisk";"Larva";319;2
"Unit";"Hydralisk";"Larva";319;2
"Unit";"Hydralisk";"Larva";345;2
"Unit";"Hydralisk";"Larva";345;2
"Unit";"Hydralisk";"Larva";345;2
"Unit";"Hydralisk";"Larva";345;2
"Unit";"Hydralisk";"Larva";345;2
