"type";"unit_name";"on_building";"total_supply";"supply"
"Unit";"Overlord";"Larva";13;0
"Building";"Extractor";NA;17;0
"Unit";"Overlord";"Larva";22;0
"Building";"SpawningPool";NA;19;0
"Building";"Hatchery";NA;17;0
"Unit";"Queen";"Hatchery";22;2
"Unit";"Queen";"Hatchery";22;2
"Building";"CreepTumorQueen";NA;34;0
"Unit";"Zergling";"Larva";34;1
"Unit";"Zergling";"Larva";34;1
"Unit";"Zergling";"Larva";34;1
"Unit";"Zergling";"Larva";34;1
"Unit";"Overlord";"Larva";35;0
"Unit";"Queen";"Hatchery";34;2
"Building";"SporeCrawler";NA;40;0
"Building";"SporeCrawler";NA;40;0
"Building";"CreepTumorQueen";NA;48;0
"Building";"Hatchery";NA;34;0
"Building";"CreepTumor";NA;50;0
"Building";"Extractor";NA;48;0
"Unit";"Overlord";"Larva";50;0
"Building";"EvolutionChamber";NA;50;0
"Building";"CreepTumor";NA;60;0
"Building";"CreepTumor";NA;60;0
"Building";"SporeCrawler";NA;64;0
"Building";"CreepTumor";NA;69;0
"Building";"BanelingNest";NA;55;0
"Unit";"Overlord";"Larva";64;0
"Unit";"Zergling";"Larva";64;1
"Unit";"Zergling";"Larva";64;1
"Unit";"Zergling";"Larva";64;1
"Unit";"Zergling";"Larva";64;1
"Unit";"Zergling";"Larva";64;1
"Unit";"Zergling";"Larva";64;1
"Building";"CreepTumor";NA;69;0
"Unit";"Zergling";"Larva";69;1
"Unit";"Zergling";"Larva";69;1
"Unit";"Zergling";"Larva";69;1
"Unit";"Zergling";"Larva";69;1
"Unit";"Zergling";"Larva";69;1
"Unit";"Zergling";"Larva";69;1
"Unit";"Overlord";"Larva";69;0
"Unit";"Overlord";"Larva";69;0
"Unit";"Baneling";"Zergling";77;0
"Unit";"Baneling";"Zergling";77;0
"Unit";"Baneling";"Zergling";79;0
"Unit";"Baneling";"Zergling";79;0
"Unit";"Baneling";"Zergling";79;0
"Unit";"Baneling";"Zergling";79;0
"Unit";"Overlord";"Larva";81;0
"Unit";"Zergling";"Larva";81;1
"Unit";"Zergling";"Larva";81;1
"Building";"HydraliskDen";NA;81;0
"Unit";"Zergling";"Larva";81;1
"Unit";"Zergling";"Larva";81;1
"Unit";"Zergling";"Larva";81;1
"Unit";"Zergling";"Larva";81;1
"Unit";"Zergling";"Larva";81;1
"Unit";"Zergling";"Larva";81;1
"Unit";"Zergling";"Larva";81;1
"Unit";"Zergling";"Larva";81;1
"Unit";"Zergling";"Larva";81;1
"Unit";"Zergling";"Larva";81;1
"Building";"Extractor";NA;81;0
"Unit";"Zergling";"Larva";81;1
"Unit";"Zergling";"Larva";81;1
"Building";"Extractor";NA;81;0
"Unit";"Overlord";"Larva";101;0
"Unit";"Overlord";"Larva";101;0
"Building";"Extractor";NA;101;0
"Unit";"Hydralisk";"Larva";101;2
"Unit";"Overlord";"Larva";110;0
"Unit";"Queen";"Hatchery";101;2
"Unit";"Queen";"Hatchery";101;2
"Building";"CreepTumor";NA;125;0
"Unit";"Zergling";"Larva";121;1
"Unit";"Zergling";"Larva";121;1
"Unit";"Zergling";"Larva";121;1
"Unit";"Zergling";"Larva";121;1
"Unit";"Zergling";"Larva";121;1
"Unit";"Zergling";"Larva";121;1
"Unit";"Zergling";"Larva";121;1
"Unit";"Zergling";"Larva";121;1
"Unit";"Zergling";"Larva";121;1
"Unit";"Zergling";"Larva";121;1
"Unit";"Zergling";"Larva";121;1
"Unit";"Zergling";"Larva";121;1
"Unit";"Zergling";"Larva";121;1
"Unit";"Zergling";"Larva";121;1
"Unit";"Zergling";"Larva";125;1
"Unit";"Zergling";"Larva";125;1
"Unit";"Zergling";"Larva";125;1
"Unit";"Zergling";"Larva";125;1
"Unit";"Zergling";"Larva";125;1
"Unit";"Zergling";"Larva";125;1
"Unit";"Baneling";"Zergling";125;0
"Unit";"Baneling";"Zergling";125;0
"Unit";"Baneling";"Zergling";125;0
"Unit";"Baneling";"Zergling";125;0
"Unit";"Baneling";"Zergling";125;0
"Unit";"Baneling";"Zergling";125;0
"Unit";"Baneling";"Zergling";125;0
"Unit";"Baneling";"Zergling";125;0
"Unit";"Baneling";"Zergling";125;0
"Unit";"Baneling";"Zergling";125;0
"Unit";"Baneling";"Zergling";125;0
"Building";"CreepTumor";NA;143;0
"Unit";"Overlord";"Larva";143;0
"Building";"CreepTumorQueen";NA;145;0
"Unit";"Hydralisk";"Larva";145;2
"Unit";"Hydralisk";"Larva";145;2
"Building";"EvolutionChamber";NA;145;0
"Unit";"Hydralisk";"Larva";145;2
"Unit";"Hydralisk";"Larva";145;2
"Unit";"Hydralisk";"Larva";145;2
"Building";"Extractor";NA;145;0
"Building";"CreepTumorQueen";NA;145;0
"Upgrade";"EvolveMuscularAugments";"HydraliskDen";125;0
"Unit";"Hydralisk";"Larva";145;2
"Unit";"Hydralisk";"Larva";145;2
"Unit";"Overlord";"Larva";145;0
"Unit";"Hydralisk";"Larva";145;2
"Unit";"Hydralisk";"Larva";145;2
"Unit";"Hydralisk";"Larva";145;2
"Unit";"Hydralisk";"Larva";145;2
"Unit";"Hydralisk";"Larva";155;2
"Unit";"Hydralisk";"Larva";155;2
"Unit";"Overlord";"Larva";155;0
"Unit";"Overlord";"Larva";155;0
"Unit";"Overlord";"Larva";155;0
"Building";"CreepTumor";NA;163;0
"Unit";"Overlord";"Larva";159;0
"Unit";"Hydralisk";"Larva";155;2
"Building";"CreepTumorQueen";NA;168;0
"Building";"CreepTumor";NA;172;0
"Building";"CreepTumor";NA;172;0
"Unit";"Overlord";"Larva";168;0
"Building";"Hatchery";NA;145;0
"Unit";"Hydralisk";"Larva";168;2
"Unit";"Hydralisk";"Larva";168;2
"Unit";"Hydralisk";"Larva";168;2
"Unit";"Hydralisk";"Larva";168;2
"Unit";"Overlord";"Larva";174;0
"Unit";"Hydralisk";"Larva";174;2
"Unit";"Hydralisk";"Larva";174;2
"Unit";"Overlord";"Larva";174;0
"Building";"SporeCrawler";NA;182;0
"Unit";"Hydralisk";"Larva";182;2
"Unit";"Hydralisk";"Larva";182;2
"Unit";"Hydralisk";"Larva";182;2
"Upgrade";"EvolveGroovedSpines";"HydraliskDen";172;0
"Unit";"Hydralisk";"Larva";184;2
"Unit";"Hydralisk";"Larva";188;2
"Upgrade";"ZergMissileWeaponsLevel1";"EvolutionChamber";155;0
"Unit";"Baneling";"Zergling";194;0
"Unit";"Baneling";"Zergling";194;0
"Unit";"Baneling";"Zergling";194;0
"Unit";"Baneling";"Zergling";194;0
"Unit";"Baneling";"Zergling";194;0
"Unit";"Baneling";"Zergling";194;0
"Unit";"Baneling";"Zergling";194;0
"Unit";"Baneling";"Zergling";194;0
"Unit";"Baneling";"Zergling";194;0
"Unit";"Queen";"Hatchery";194;2
"Unit";"Overlord";"Larva";207;0
"Unit";"Hydralisk";"Larva";207;2
"Unit";"Hydralisk";"Larva";207;2
"Unit";"Hydralisk";"Larva";207;2
"Building";"Extractor";NA;212;0
"Building";"Extractor";NA;212;0
"Unit";"Overlord";"Larva";214;0
"Unit";"Zergling";"Larva";218;1
"Unit";"Zergling";"Larva";218;1
"Unit";"Zergling";"Larva";218;1
"Unit";"Zergling";"Larva";218;1
"Unit";"Zergling";"Larva";218;1
"Unit";"Zergling";"Larva";218;1
"Unit";"Zergling";"Larva";218;1
"Unit";"Zergling";"Larva";218;1
"Unit";"Zergling";"Larva";218;1
"Unit";"Zergling";"Larva";218;1
"Unit";"Zergling";"Larva";218;1
"Unit";"Zergling";"Larva";218;1
"Unit";"Overlord";"Larva";224;0
"Unit";"Zergling";"Larva";224;1
"Unit";"Zergling";"Larva";224;1
"Unit";"Zergling";"Larva";224;1
"Unit";"Zergling";"Larva";224;1
"Unit";"Zergling";"Larva";224;1
"Unit";"Zergling";"Larva";224;1
"Unit";"Zergling";"Larva";224;1
"Unit";"Zergling";"Larva";224;1
"Unit";"Zergling";"Larva";224;1
"Unit";"Zergling";"Larva";224;1
"Unit";"Zergling";"Larva";224;1
"Unit";"Zergling";"Larva";224;1
"Unit";"Zergling";"Larva";230;1
"Unit";"Zergling";"Larva";230;1
"Unit";"Zergling";"Larva";230;1
"Unit";"Zergling";"Larva";230;1
"Unit";"Zergling";"Larva";230;1
"Unit";"Zergling";"Larva";230;1
"Unit";"Zergling";"Larva";240;1
"Unit";"Zergling";"Larva";240;1
"Unit";"Zergling";"Larva";250;1
"Unit";"Zergling";"Larva";250;1
"Unit";"Zergling";"Larva";252;1
"Unit";"Zergling";"Larva";252;1
"Unit";"Zergling";"Larva";252;1
"Unit";"Zergling";"Larva";252;1
"Unit";"Zergling";"Larva";252;1
"Unit";"Zergling";"Larva";252;1
"Unit";"Zergling";"Larva";252;1
"Unit";"Zergling";"Larva";252;1
"Unit";"Zergling";"Larva";252;1
"Unit";"Zergling";"Larva";252;1
"Unit";"Zergling";"Larva";252;1
"Unit";"Zergling";"Larva";252;1
"Unit";"Zergling";"Larva";252;1
"Unit";"Zergling";"Larva";252;1
"Unit";"Baneling";"Zergling";252;0
"Unit";"Baneling";"Zergling";252;0
"Unit";"Baneling";"Zergling";252;0
"Unit";"Baneling";"Zergling";252;0
"Unit";"Baneling";"Zergling";252;0
"Unit";"Baneling";"Zergling";252;0
"Unit";"Baneling";"Zergling";252;0
"Unit";"Baneling";"Zergling";254;0
"Unit";"Baneling";"Zergling";254;0
"Unit";"Baneling";"Zergling";254;0
"Unit";"Zergling";"Larva";260;1
"Unit";"Zergling";"Larva";260;1
"Unit";"Zergling";"Larva";262;1
"Unit";"Zergling";"Larva";262;1
"Unit";"Zergling";"Larva";262;1
"Unit";"Zergling";"Larva";262;1
"Unit";"Zergling";"Larva";262;1
"Unit";"Zergling";"Larva";262;1
"Unit";"Zergling";"Larva";262;1
"Unit";"Zergling";"Larva";262;1
"Unit";"Zergling";"Larva";262;1
"Unit";"Zergling";"Larva";262;1
"Unit";"Overlord";"Larva";276;0
"Building";"LurkerDenMP";NA;212;0
"Building";"CreepTumor";NA;288;0
"Building";"CreepTumor";NA;291;0
"Building";"CreepTumorQueen";NA;291;0
"Building";"CreepTumor";NA;291;0
"Building";"CreepTumorQueen";NA;292;0
"Upgrade";"ZergGroundArmorsLevel1";"EvolutionChamber";218;0
"Building";"CreepTumorQueen";NA;292;0
"Building";"InfestationPit";NA;276;0
"Unit";"Queen";"Hatchery";276;2
"Building";"SpineCrawler";NA;276;0
"Building";"SpineCrawler";NA;276;0
"Building";"SpineCrawler";NA;276;0
"Building";"SpineCrawler";NA;276;0
"Building";"SpineCrawler";NA;278;0
"Building";"SpineCrawler";NA;288;0
"Unit";"Hydralisk";"Larva";296;2
"Unit";"Hydralisk";"Larva";296;2
"Unit";"Hydralisk";"Larva";296;2
"Unit";"Hydralisk";"Larva";296;2
"Unit";"Overlord";"Larva";310;0
"Building";"Hatchery";NA;291;0
"Unit";"Hydralisk";"Larva";310;2
"Unit";"Hydralisk";"Larva";310;2
"Unit";"Hydralisk";"Larva";310;2
"Unit";"Hydralisk";"Larva";310;2
"Unit";"Hydralisk";"Larva";310;2
"Unit";"Hydralisk";"Larva";310;2
"Unit";"Hydralisk";"Larva";310;2
"Unit";"Hydralisk";"Larva";310;2
"Building";"Extractor";NA;310;0
"Unit";"Hydralisk";"Larva";310;2
"Unit";"Hydralisk";"Larva";310;2
"Unit";"Hydralisk";"Larva";310;2
"Unit";"Hydralisk";"Larva";310;2
"Unit";"Hydralisk";"Larva";310;2
"Building";"Extractor";NA;310;0
"Building";"CreepTumor";NA;310;0
"Unit";"Overlord";"Larva";310;0
"Unit";"Overlord";"Larva";310;0
"Unit";"Overlord";"Larva";310;0
"Unit";"Hydralisk";"Larva";310;2
"Unit";"Hydralisk";"Larva";310;2
"Unit";"Hydralisk";"Larva";310;2
"Unit";"Zergling";"Larva";310;1
"Unit";"Zergling";"Larva";310;1
"Unit";"Zergling";"Larva";310;1
"Unit";"Zergling";"Larva";310;1
"Unit";"Zergling";"Larva";310;1
"Unit";"Zergling";"Larva";310;1
"Unit";"Zergling";"Larva";310;1
"Unit";"Zergling";"Larva";310;1
"Unit";"Zergling";"Larva";310;1
"Unit";"Zergling";"Larva";310;1
"Unit";"Zergling";"Larva";312;1
"Unit";"Zergling";"Larva";312;1
"Unit";"Zergling";"Larva";312;1
"Unit";"Zergling";"Larva";312;1
"Unit";"Zergling";"Larva";312;1
"Unit";"Zergling";"Larva";312;1
"Unit";"Zergling";"Larva";312;1
"Unit";"Zergling";"Larva";312;1
"Unit";"Zergling";"Larva";312;1
"Unit";"Zergling";"Larva";312;1
"Unit";"Zergling";"Larva";312;1
"Unit";"Zergling";"Larva";312;1
"Unit";"Zergling";"Larva";312;1
"Unit";"Zergling";"Larva";312;1
"Unit";"Hydralisk";"Larva";336;2
"Unit";"Hydralisk";"Larva";336;2
"Unit";"Hydralisk";"Larva";336;2
"Unit";"Hydralisk";"Larva";336;2
"Building";"CreepTumor";NA;366;0
"Unit";"Baneling";"Zergling";366;0
"Unit";"Baneling";"Zergling";366;0
"Unit";"Baneling";"Zergling";366;0
"Unit";"Baneling";"Zergling";366;0
"Building";"CreepTumorQueen";NA;366;0
"Building";"CreepTumor";NA;366;0
"Building";"CreepTumor";NA;366;0
"Building";"CreepTumor";NA;366;0
"Building";"CreepTumor";NA;367;0
"Building";"CreepTumor";NA;370;0
"Building";"CreepTumor";NA;382;0
"Upgrade";"ZergMeleeWeaponsLevel1";"EvolutionChamber";310;0
"Upgrade";"ZergMissileWeaponsLevel2";"EvolutionChamber";310;0
"Building";"CreepTumor";NA;390;0
"Building";"CreepTumor";NA;390;0
"Building";"CreepTumor";NA;390;0
"Building";"CreepTumor";NA;390;0
"Building";"CreepTumor";NA;390;0
"Unit";"Hydralisk";"Larva";390;2
"Unit";"Hydralisk";"Larva";390;2
"Unit";"Hydralisk";"Larva";390;2
"Unit";"Hydralisk";"Larva";390;2
"Unit";"Hydralisk";"Larva";390;2
"Unit";"Hydralisk";"Larva";390;2
"Unit";"Hydralisk";"Larva";390;2
"Unit";"Hydralisk";"Larva";390;2
"Unit";"Hydralisk";"Larva";390;2
"Unit";"Baneling";"Zergling";390;0
"Building";"CreepTumor";NA;390;0
"Unit";"Baneling";"Zergling";390;0
"Unit";"Baneling";"Zergling";390;0
"Unit";"Baneling";"Zergling";390;0
"Unit";"Baneling";"Zergling";390;0
"Unit";"Baneling";"Zergling";390;0
"Unit";"Baneling";"Zergling";390;0
"Unit";"Baneling";"Zergling";390;0
"Unit";"Baneling";"Zergling";390;0
"Unit";"Baneling";"Zergling";390;0
"Unit";"Baneling";"Zergling";390;0
"Building";"SpineCrawler";NA;390;0
"Unit";"Hydralisk";"Larva";396;2
"Unit";"Hydralisk";"Larva";396;2
"Unit";"Overlord";"Larva";412;0
"Unit";"Overlord";"Larva";412;0
"Unit";"Overlord";"Larva";412;0
"Unit";"Zergling";"Larva";416;1
"Unit";"Zergling";"Larva";416;1
"Unit";"Zergling";"Larva";416;1
"Unit";"Zergling";"Larva";416;1
"Unit";"Zergling";"Larva";416;1
"Unit";"Zergling";"Larva";416;1
"Unit";"Zergling";"Larva";416;1
"Unit";"Zergling";"Larva";416;1
"Unit";"Zergling";"Larva";416;1
"Unit";"Zergling";"Larva";416;1
"Unit";"Zergling";"Larva";416;1
"Unit";"Zergling";"Larva";416;1
"Unit";"Zergling";"Larva";416;1
"Unit";"Zergling";"Larva";416;1
"Unit";"Zergling";"Larva";416;1
"Unit";"Zergling";"Larva";416;1
"Unit";"Zergling";"Larva";416;1
"Unit";"Zergling";"Larva";416;1
"Unit";"Zergling";"Larva";416;1
"Unit";"Zergling";"Larva";416;1
"Unit";"Zergling";"Larva";416;1
"Unit";"Zergling";"Larva";416;1
"Unit";"Zergling";"Larva";416;1
"Unit";"Zergling";"Larva";416;1
"Unit";"Zergling";"Larva";416;1
"Unit";"Zergling";"Larva";416;1
"Unit";"Zergling";"Larva";416;1
"Unit";"Zergling";"Larva";416;1
