"type";"unit_name";"on_building";"total_supply";"supply"
"Unit";"Overlord";"Larva";12;0
"Building";"Extractor";NA;17;0
"Building";"SpawningPool";NA;18;0
"Building";"Hatchery";NA;17;0
"Unit";"Overlord";"Larva";22;0
"Unit";"Zergling";"Larva";23;1
"Unit";"Zergling";"Larva";23;1
"Unit";"Queen";"Hatchery";23;2
"Unit";"Queen";"Hatchery";23;2
"Unit";"Overlord";"Larva";35;0
"Building";"CreepTumorQueen";NA;38;0
"Unit";"Overlord";"Larva";37;0
"Unit";"Queen";"Hatchery";38;2
"Building";"Extractor";NA;43;0
"Building";"Hatchery";NA;34;0
"Unit";"Overlord";"Larva";49;0
"Unit";"Overlord";"Larva";49;0
"Building";"CreepTumor";NA;52;0
"Building";"Extractor";NA;52;0
"Building";"SporeCrawler";NA;55;0
"Building";"SporeCrawler";NA;55;0
"Building";"SporeCrawler";NA;58;0
"Building";"CreepTumor";NA;59;0
"Building";"Extractor";NA;64;0
"Unit";"Overlord";"Larva";66;0
"Unit";"Queen";"Hatchery";59;2
"Building";"EvolutionChamber";NA;66;0
"Unit";"Overlord";"Larva";70;0
"Unit";"Overlord";"Larva";70;0
"Unit";"Overlord";"Larva";72;0
"Building";"RoachWarren";NA;68;0
"Unit";"Overlord";"Larva";78;0
"Building";"HydraliskDen";NA;75;0
"Unit";"Roach";"Larva";78;2
"Unit";"Roach";"Larva";78;2
"Unit";"Roach";"Larva";78;2
"Unit";"Roach";"Larva";78;2
"Unit";"Roach";"Larva";78;2
"Unit";"Roach";"Larva";78;2
"Unit";"Roach";"Larva";78;2
"Unit";"Roach";"Larva";78;2
"Unit";"Overlord";"Larva";78;0
"Unit";"Roach";"Larva";78;2
"Unit";"Roach";"Larva";78;2
"Unit";"Roach";"Larva";78;2
"Unit";"Overlord";"Larva";78;0
"Unit";"Roach";"Larva";78;2
"Unit";"Hydralisk";"Larva";78;2
"Unit";"Roach";"Larva";94;2
"Building";"Extractor";NA;78;0
"Unit";"Overlord";"Larva";100;0
"Building";"Extractor";NA;94;0
"Unit";"Overlord";"Larva";100;0
"Unit";"Hydralisk";"Larva";94;2
"Unit";"Overlord";"Larva";100;0
"Unit";"Hydralisk";"Larva";116;2
"Upgrade";"EvolveGroovedSpines";"HydraliskDen";100;0
"Unit";"Hydralisk";"Larva";116;2
"Unit";"Hydralisk";"Larva";121;2
"Upgrade";"ZergMissileWeaponsLevel1";"EvolutionChamber";78;0
"Building";"CreepTumor";NA;123;0
"Unit";"Hydralisk";"Larva";123;2
"Unit";"Hydralisk";"Larva";123;2
"Unit";"Queen";"Hatchery";123;2
"Building";"CreepTumorQueen";NA;129;0
"Unit";"Hydralisk";"Larva";129;2
"Unit";"Hydralisk";"Larva";129;2
"Building";"CreepTumorQueen";NA;133;0
"Unit";"Overlord";"Larva";129;0
"Unit";"Overlord";"Larva";129;0
"Unit";"Hydralisk";"Larva";129;2
"Unit";"Hydralisk";"Larva";129;2
"Building";"LurkerDenMP";NA;100;0
"Building";"CreepTumor";NA;135;0
"Unit";"Hydralisk";"Larva";135;2
"Unit";"Hydralisk";"Larva";135;2
"Unit";"Hydralisk";"Larva";135;2
"Unit";"Hydralisk";"Larva";135;2
"Building";"CreepTumorQueen";NA;143;0
"Upgrade";"GlialReconstitution";"RoachWarren";123;0
"Unit";"Hydralisk";"Larva";139;2
"Unit";"Hydralisk";"Larva";139;2
"Unit";"Hydralisk";"Larva";139;2
"Unit";"Hydralisk";"Larva";143;2
"Unit";"Hydralisk";"Larva";143;2
"Unit";"Hydralisk";"Larva";143;2
"Building";"Hatchery";NA;123;0
"Unit";"Hydralisk";"Larva";143;2
"Unit";"Hydralisk";"Larva";143;2
"Unit";"Hydralisk";"Larva";143;2
"Building";"CreepTumorQueen";NA;157;0
"Unit";"Hydralisk";"Larva";147;2
"Upgrade";"EvolveMuscularAugments";"HydraliskDen";133;0
"Unit";"Overlord";"Larva";157;0
"Unit";"Overlord";"Larva";157;0
"Unit";"Hydralisk";"Larva";151;2
"Unit";"Hydralisk";"Larva";151;2
"Building";"InfestationPit";NA;151;0
"Unit";"Overlord";"Larva";172;0
"Unit";"Overlord";"Larva";177;0
"Unit";"Overlord";"Larva";180;0
"Unit";"Queen";"Hatchery";172;2
"Building";"Extractor";NA;180;0
"Building";"Extractor";NA;180;0
"Unit";"Zergling";"Larva";182;1
"Unit";"Zergling";"Larva";182;1
"Unit";"Zergling";"Larva";182;1
"Unit";"Zergling";"Larva";182;1
"Unit";"Zergling";"Larva";182;1
"Unit";"Zergling";"Larva";182;1
"Unit";"Zergling";"Larva";182;1
"Unit";"Zergling";"Larva";182;1
"Unit";"Zergling";"Larva";182;1
"Unit";"Zergling";"Larva";182;1
"Unit";"Zergling";"Larva";182;1
"Unit";"Zergling";"Larva";182;1
"Unit";"Zergling";"Larva";182;1
"Unit";"Zergling";"Larva";182;1
"Unit";"Zergling";"Larva";182;1
"Unit";"Zergling";"Larva";182;1
"Unit";"Zergling";"Larva";182;1
"Unit";"Zergling";"Larva";182;1
"Unit";"Zergling";"Larva";182;1
"Unit";"Zergling";"Larva";182;1
"Unit";"Zergling";"Larva";182;1
"Unit";"Zergling";"Larva";182;1
"Unit";"Zergling";"Larva";182;1
"Unit";"Zergling";"Larva";182;1
"Unit";"Zergling";"Larva";182;1
"Unit";"Zergling";"Larva";182;1
"Unit";"Zergling";"Larva";182;1
"Unit";"Zergling";"Larva";182;1
"Unit";"Zergling";"Larva";182;1
"Unit";"Zergling";"Larva";182;1
"Unit";"Zergling";"Larva";182;1
"Unit";"Zergling";"Larva";182;1
"Unit";"Zergling";"Larva";182;1
"Unit";"Zergling";"Larva";182;1
"Upgrade";"ZergMissileWeaponsLevel2";"EvolutionChamber";143;0
"Unit";"Zergling";"Larva";182;1
"Unit";"Zergling";"Larva";182;1
"Unit";"Zergling";"Larva";182;1
"Unit";"Zergling";"Larva";182;1
"Unit";"Zergling";"Larva";182;1
"Unit";"Zergling";"Larva";182;1
"Unit";"Zergling";"Larva";182;1
"Unit";"Zergling";"Larva";182;1
"Unit";"Zergling";"Larva";182;1
"Unit";"Zergling";"Larva";182;1
"Unit";"Zergling";"Larva";182;1
"Unit";"Zergling";"Larva";182;1
"Unit";"Zergling";"Larva";231;1
"Unit";"Zergling";"Larva";231;1
"Unit";"Zergling";"Larva";231;1
"Unit";"Zergling";"Larva";231;1
"Unit";"Zergling";"Larva";231;1
"Unit";"Zergling";"Larva";231;1
"Unit";"Zergling";"Larva";231;1
"Unit";"Zergling";"Larva";231;1
"Unit";"Zergling";"Larva";231;1
"Unit";"Zergling";"Larva";231;1
"Unit";"Zergling";"Larva";231;1
"Unit";"Zergling";"Larva";231;1
"Unit";"Zergling";"Larva";231;1
"Unit";"Zergling";"Larva";231;1
"Building";"Spire";NA;180;0
"Unit";"Hydralisk";"Larva";231;2
"Unit";"Hydralisk";"Larva";231;2
"Unit";"Hydralisk";"Larva";231;2
"Unit";"Hydralisk";"Larva";231;2
"Unit";"Hydralisk";"Larva";231;2
"Unit";"Hydralisk";"Larva";231;2
"Unit";"Hydralisk";"Larva";231;2
"Unit";"Hydralisk";"Larva";231;2
"Unit";"Hydralisk";"Larva";231;2
"Unit";"Hydralisk";"Larva";231;2
"Unit";"Zergling";"Larva";245;1
"Unit";"Zergling";"Larva";245;1
"Unit";"Zergling";"Larva";245;1
"Unit";"Zergling";"Larva";245;1
"Unit";"Zergling";"Larva";245;1
"Unit";"Zergling";"Larva";245;1
"Unit";"Zergling";"Larva";245;1
"Unit";"Zergling";"Larva";245;1
"Unit";"Zergling";"Larva";245;1
"Unit";"Zergling";"Larva";245;1
"Unit";"Zergling";"Larva";265;1
"Unit";"Zergling";"Larva";265;1
"Unit";"Zergling";"Larva";265;1
"Unit";"Zergling";"Larva";265;1
"Unit";"Zergling";"Larva";265;1
"Unit";"Zergling";"Larva";265;1
"Unit";"Zergling";"Larva";265;1
"Unit";"Zergling";"Larva";265;1
"Unit";"Zergling";"Larva";265;1
"Unit";"Zergling";"Larva";265;1
"Unit";"Zergling";"Larva";265;1
"Unit";"Zergling";"Larva";265;1
"Building";"Hatchery";NA;231;0
"Unit";"Zergling";"Larva";277;1
"Unit";"Zergling";"Larva";277;1
"Unit";"Zergling";"Larva";279;1
"Unit";"Zergling";"Larva";279;1
"Unit";"Zergling";"Larva";283;1
"Unit";"Zergling";"Larva";283;1
"Unit";"Zergling";"Larva";283;1
"Unit";"Zergling";"Larva";283;1
"Unit";"Zergling";"Larva";283;1
"Unit";"Zergling";"Larva";283;1
"Unit";"Zergling";"Larva";287;1
"Unit";"Zergling";"Larva";287;1
"Unit";"Corruptor";"Larva";287;2
"Unit";"Corruptor";"Larva";287;2
"Unit";"Corruptor";"Larva";287;2
"Unit";"Queen";"Hatchery";287;2
"Unit";"Corruptor";"Larva";301;2
"Unit";"Corruptor";"Larva";301;2
"Unit";"Corruptor";"Larva";301;2
"Upgrade";"ZergGroundArmorsLevel1";"EvolutionChamber";245;0
"Unit";"Corruptor";"Larva";301;2
"Unit";"Corruptor";"Larva";301;2
"Unit";"Corruptor";"Larva";301;2
"Unit";"Corruptor";"Larva";301;2
"Unit";"Corruptor";"Larva";301;2
"Unit";"Corruptor";"Larva";301;2
"Unit";"Corruptor";"Larva";301;2
"Unit";"Corruptor";"Larva";301;2
"Unit";"Corruptor";"Larva";303;2
"Unit";"Corruptor";"Larva";307;2
"Unit";"Corruptor";"Larva";307;2
"Unit";"Corruptor";"Larva";309;2
"Unit";"Corruptor";"Larva";309;2
"Building";"Extractor";NA;315;0
"Building";"Extractor";NA;315;0
"Unit";"Zergling";"Larva";337;1
"Unit";"Zergling";"Larva";337;1
"Unit";"Zergling";"Larva";337;1
"Unit";"Zergling";"Larva";337;1
"Unit";"Zergling";"Larva";337;1
"Unit";"Zergling";"Larva";337;1
"Unit";"Zergling";"Larva";337;1
"Unit";"Zergling";"Larva";337;1
"Unit";"Zergling";"Larva";337;1
"Unit";"Zergling";"Larva";337;1
"Unit";"Zergling";"Larva";337;1
"Unit";"Zergling";"Larva";337;1
"Unit";"Zergling";"Larva";337;1
"Unit";"Zergling";"Larva";337;1
"Unit";"Zergling";"Larva";337;1
"Unit";"Zergling";"Larva";337;1
"Unit";"Zergling";"Larva";337;1
"Unit";"Zergling";"Larva";337;1
"Unit";"Zergling";"Larva";337;1
"Unit";"Zergling";"Larva";337;1
"Unit";"Zergling";"Larva";337;1
"Unit";"Zergling";"Larva";337;1
"Unit";"Zergling";"Larva";337;1
"Unit";"Zergling";"Larva";337;1
"Unit";"Zergling";"Larva";337;1
"Unit";"Zergling";"Larva";337;1
"Unit";"Zergling";"Larva";337;1
"Unit";"Zergling";"Larva";337;1
"Unit";"Zergling";"Larva";337;1
"Unit";"Zergling";"Larva";337;1
"Building";"EvolutionChamber";NA;341;0
"Unit";"Zergling";"Larva";371;1
"Unit";"Zergling";"Larva";371;1
"Unit";"Zergling";"Larva";371;1
"Unit";"Zergling";"Larva";371;1
"Unit";"Zergling";"Larva";371;1
"Unit";"Zergling";"Larva";371;1
"Unit";"Zergling";"Larva";371;1
"Unit";"Zergling";"Larva";371;1
"Unit";"Zergling";"Larva";371;1
"Unit";"Zergling";"Larva";371;1
"Unit";"Zergling";"Larva";371;1
"Unit";"Zergling";"Larva";371;1
"Unit";"Zergling";"Larva";371;1
"Unit";"Zergling";"Larva";371;1
"Unit";"Zergling";"Larva";371;1
"Unit";"Zergling";"Larva";371;1
"Unit";"Zergling";"Larva";371;1
"Unit";"Zergling";"Larva";371;1
"Unit";"Zergling";"Larva";371;1
"Unit";"Zergling";"Larva";371;1
"Unit";"Overlord";"Larva";391;0
"Unit";"Overlord";"Larva";391;0
