"type";"unit_name";"on_building";"total_supply";"supply"
"Unit";"Overlord";"Larva";12;0
"Building";"Extractor";NA;18;0
"Unit";"Overlord";"Larva";21;0
"Building";"SpawningPool";NA;19;0
"Building";"Hatchery";NA;17;0
"Unit";"Queen";"Hatchery";23;2
"Unit";"Queen";"Hatchery";23;2
"Unit";"Zergling";"Larva";26;1
"Unit";"Zergling";"Larva";26;1
"Unit";"Zergling";"Larva";26;1
"Unit";"Zergling";"Larva";26;1
"Unit";"Overlord";"Larva";30;0
"Unit";"Queen";"Hatchery";32;2
"Unit";"Overlord";"Larva";36;0
"Building";"RoachWarren";NA;32;0
"Building";"CreepTumorQueen";NA;40;0
"Unit";"Overlord";"Larva";37;0
"Unit";"Roach";"Larva";42;2
"Unit";"Roach";"Larva";42;2
"Unit";"Roach";"Larva";42;2
"Unit";"Roach";"Larva";42;2
"Unit";"Roach";"Larva";42;2
"Unit";"Roach";"Larva";42;2
"Unit";"Roach";"Larva";42;2
"Unit";"Overlord";"Larva";56;0
"Building";"SporeCrawler";NA;56;0
"Building";"SporeCrawler";NA;56;0
"Building";"Extractor";NA;63;0
"Unit";"Overlord";"Larva";64;0
"Building";"Extractor";NA;64;0
"Unit";"Overlord";"Larva";69;0
"Unit";"Overlord";"Larva";76;0
"Unit";"Overlord";"Larva";76;0
"Unit";"Zergling";"Larva";79;1
"Unit";"Zergling";"Larva";79;1
"Unit";"Zergling";"Larva";79;1
"Unit";"Zergling";"Larva";79;1
"Unit";"Zergling";"Larva";79;1
"Unit";"Zergling";"Larva";79;1
"Building";"CreepTumorQueen";NA;81;0
"Unit";"Zergling";"Larva";81;1
"Unit";"Zergling";"Larva";81;1
"Unit";"Zergling";"Larva";81;1
"Unit";"Zergling";"Larva";81;1
"Unit";"Zergling";"Larva";81;1
"Unit";"Zergling";"Larva";81;1
"Unit";"Zergling";"Larva";81;1
"Unit";"Zergling";"Larva";81;1
"Unit";"Zergling";"Larva";81;1
"Unit";"Zergling";"Larva";81;1
"Building";"HydraliskDen";NA;81;0
"Building";"Extractor";NA;88;0
"Unit";"Zergling";"Larva";88;1
"Unit";"Zergling";"Larva";88;1
"Unit";"Zergling";"Larva";88;1
"Unit";"Zergling";"Larva";88;1
"Building";"BanelingNest";NA;81;0
"Building";"EvolutionChamber";NA;88;0
"Building";"EvolutionChamber";NA;88;0
"Building";"CreepTumorQueen";NA;106;0
"Building";"CreepTumor";NA;106;0
"Building";"Hatchery";NA;81;0
"Unit";"Hydralisk";"Larva";113;2
"Unit";"Hydralisk";"Larva";113;2
"Unit";"Hydralisk";"Larva";113;2
"Unit";"Hydralisk";"Larva";113;2
"Unit";"Overlord";"Larva";114;0
"Unit";"Overlord";"Larva";115;0
"Building";"CreepTumor";NA;115;0
"Building";"CreepTumorQueen";NA;123;0
"Building";"SporeCrawler";NA;115;0
"Building";"CreepTumorQueen";NA;124;0
"Upgrade";"EvolveMuscularAugments";"HydraliskDen";112;0
"Unit";"Hydralisk";"Larva";123;2
"Unit";"Hydralisk";"Larva";123;2
"Unit";"Hydralisk";"Larva";123;2
"Unit";"Hydralisk";"Larva";123;2
"Unit";"Queen";"Hatchery";115;2
"Unit";"Hydralisk";"Larva";124;2
"Building";"SporeCrawler";NA;133;0
"Unit";"Zergling";"Larva";138;1
"Unit";"Zergling";"Larva";138;1
"Unit";"Zergling";"Larva";138;1
"Unit";"Zergling";"Larva";138;1
"Unit";"Zergling";"Larva";138;1
"Unit";"Zergling";"Larva";138;1
"Unit";"Zergling";"Larva";138;1
"Unit";"Zergling";"Larva";138;1
"Building";"CreepTumor";NA;138;0
"Unit";"Hydralisk";"Larva";138;2
"Unit";"Hydralisk";"Larva";138;2
"Unit";"Hydralisk";"Larva";138;2
"Building";"CreepTumor";NA;138;0
"Unit";"Hydralisk";"Larva";138;2
"Unit";"Hydralisk";"Larva";138;2
"Building";"CreepTumorQueen";NA;138;0
"Unit";"Hydralisk";"Larva";138;2
"Unit";"Hydralisk";"Larva";138;2
"Unit";"Hydralisk";"Larva";138;2
"Unit";"Hydralisk";"Larva";138;2
"Unit";"Hydralisk";"Larva";138;2
"Unit";"Zergling";"Larva";138;1
"Unit";"Zergling";"Larva";138;1
"Unit";"Zergling";"Larva";138;1
"Unit";"Zergling";"Larva";138;1
"Unit";"Zergling";"Larva";138;1
"Unit";"Zergling";"Larva";138;1
"Upgrade";"EvolveGroovedSpines";"HydraliskDen";138;0
"Upgrade";"ZergMeleeWeaponsLevel1";"EvolutionChamber";124;0
"Building";"SpineCrawler";NA;138;0
"Building";"SpineCrawler";NA;138;0
"Unit";"Overlord";"Larva";172;0
"Unit";"Overlord";"Larva";173;0
"Unit";"Overlord";"Larva";174;0
"Building";"CreepTumor";NA;174;0
"Unit";"Zergling";"Larva";174;1
"Unit";"Zergling";"Larva";174;1
"Unit";"Zergling";"Larva";174;1
"Unit";"Zergling";"Larva";174;1
"Building";"SpineCrawler";NA;152;0
"Unit";"Hydralisk";"Larva";172;2
"Unit";"Hydralisk";"Larva";172;2
"Unit";"Hydralisk";"Larva";172;2
"Unit";"Hydralisk";"Larva";172;2
"Building";"SpineCrawler";NA;166;0
"Unit";"Baneling";"Zergling";174;0
"Unit";"Baneling";"Zergling";174;0
"Unit";"Baneling";"Zergling";174;0
"Unit";"Baneling";"Zergling";174;0
"Unit";"Baneling";"Zergling";174;0
"Unit";"Baneling";"Zergling";174;0
"Unit";"Baneling";"Zergling";174;0
"Building";"Extractor";NA;174;0
"Unit";"Baneling";"Zergling";174;0
"Building";"Extractor";NA;174;0
"Unit";"Baneling";"Zergling";178;0
"Unit";"Zergling";"Larva";188;1
"Unit";"Zergling";"Larva";188;1
"Unit";"Zergling";"Larva";188;1
"Unit";"Zergling";"Larva";188;1
"Unit";"Baneling";"Zergling";191;0
"Unit";"Baneling";"Zergling";192;0
"Unit";"Baneling";"Zergling";193;0
"Unit";"Baneling";"Zergling";194;0
"Unit";"Baneling";"Zergling";194;0
"Unit";"Baneling";"Zergling";194;0
"Unit";"Baneling";"Zergling";194;0
"Unit";"Zergling";"Larva";194;1
"Unit";"Zergling";"Larva";194;1
"Unit";"Zergling";"Larva";194;1
"Unit";"Zergling";"Larva";194;1
"Unit";"Zergling";"Larva";194;1
"Unit";"Zergling";"Larva";194;1
"Unit";"Zergling";"Larva";194;1
"Unit";"Zergling";"Larva";194;1
"Unit";"Zergling";"Larva";194;1
"Unit";"Zergling";"Larva";194;1
"Unit";"Zergling";"Larva";194;1
"Unit";"Zergling";"Larva";194;1
"Unit";"Zergling";"Larva";194;1
"Unit";"Zergling";"Larva";194;1
"Building";"CreepTumor";NA;198;0
"Unit";"Zergling";"Larva";196;1
"Unit";"Zergling";"Larva";196;1
"Building";"CreepTumorQueen";NA;198;0
"Building";"CreepTumor";NA;198;0
"Building";"CreepTumor";NA;198;0
"Unit";"Zergling";"Larva";198;1
"Unit";"Zergling";"Larva";198;1
"Unit";"Zergling";"Larva";198;1
"Unit";"Zergling";"Larva";198;1
"Building";"CreepTumor";NA;198;0
"Building";"CreepTumorQueen";NA;214;0
"Unit";"Overlord";"Larva";214;0
"Unit";"Overlord";"Larva";214;0
"Unit";"Overlord";"Larva";214;0
"Unit";"Overlord";"Larva";214;0
"Unit";"Hydralisk";"Larva";214;2
"Unit";"Hydralisk";"Larva";214;2
"Unit";"Hydralisk";"Larva";214;2
"Unit";"Overlord";"Larva";218;0
"Unit";"Overlord";"Larva";218;0
"Upgrade";"ZergGroundArmorsLevel1";"EvolutionChamber";191;0
"Unit";"Zergling";"Larva";226;1
"Unit";"Zergling";"Larva";226;1
"Unit";"Zergling";"Larva";226;1
"Unit";"Zergling";"Larva";226;1
"Unit";"Zergling";"Larva";226;1
"Unit";"Zergling";"Larva";226;1
"Unit";"Zergling";"Larva";226;1
"Unit";"Zergling";"Larva";226;1
"Unit";"Zergling";"Larva";226;1
"Unit";"Zergling";"Larva";226;1
"Unit";"Zergling";"Larva";226;1
"Unit";"Zergling";"Larva";226;1
"Unit";"Zergling";"Larva";226;1
"Unit";"Zergling";"Larva";226;1
"Building";"CreepTumor";NA;226;0
"Building";"CreepTumor";NA;226;0
"Building";"CreepTumor";NA;226;0
"Unit";"Hydralisk";"Larva";226;2
"Unit";"Hydralisk";"Larva";226;2
"Unit";"Hydralisk";"Larva";226;2
"Unit";"Hydralisk";"Larva";226;2
"Unit";"Zergling";"Larva";226;1
"Unit";"Zergling";"Larva";226;1
"Unit";"Zergling";"Larva";226;1
"Unit";"Zergling";"Larva";226;1
"Unit";"Zergling";"Larva";226;1
"Unit";"Zergling";"Larva";226;1
"Unit";"Hydralisk";"Larva";226;2
"Unit";"Hydralisk";"Larva";226;2
"Unit";"Hydralisk";"Larva";226;2
"Unit";"Zergling";"Larva";248;1
"Unit";"Zergling";"Larva";248;1
"Unit";"Zergling";"Larva";248;1
"Unit";"Zergling";"Larva";248;1
"Unit";"Zergling";"Larva";250;1
"Unit";"Zergling";"Larva";250;1
"Unit";"Hydralisk";"Larva";248;2
"Unit";"Hydralisk";"Larva";248;2
"Unit";"Hydralisk";"Larva";248;2
"Unit";"Zergling";"Larva";268;1
"Unit";"Zergling";"Larva";268;1
"Unit";"Zergling";"Larva";268;1
"Unit";"Zergling";"Larva";268;1
"Unit";"Hydralisk";"Larva";268;2
"Unit";"Hydralisk";"Larva";268;2
"Unit";"Hydralisk";"Larva";268;2
"Unit";"Hydralisk";"Larva";268;2
"Building";"CreepTumorQueen";NA;274;0
"Building";"Hatchery";NA;226;0
"Building";"LurkerDenMP";NA;226;0
"Unit";"Hydralisk";"Larva";278;2
"Unit";"Hydralisk";"Larva";278;2
"Unit";"Zergling";"Larva";286;1
"Unit";"Zergling";"Larva";286;1
"Building";"NydusNetwork";NA;274;0
"Unit";"Zergling";"Larva";286;1
"Unit";"Zergling";"Larva";286;1
"Unit";"Zergling";"Larva";286;1
"Unit";"Zergling";"Larva";286;1
"Unit";"Zergling";"Larva";286;1
"Unit";"Zergling";"Larva";286;1
"Unit";"Overlord";"Larva";286;0
"Unit";"Overlord";"Larva";286;0
"Unit";"Overlord";"Larva";286;0
"Unit";"Overlord";"Larva";286;0
"Unit";"Overlord";"Larva";286;0
"Unit";"Overlord";"Larva";286;0
"Unit";"Zergling";"Larva";298;1
"Unit";"Zergling";"Larva";298;1
"Unit";"Zergling";"Larva";298;1
"Unit";"Zergling";"Larva";298;1
"Unit";"Zergling";"Larva";298;1
"Unit";"Zergling";"Larva";298;1
"Upgrade";"ZergMeleeWeaponsLevel2";"EvolutionChamber";262;0
"Unit";"Zergling";"Larva";304;1
"Unit";"Zergling";"Larva";304;1
"Unit";"Zergling";"Larva";304;1
"Unit";"Zergling";"Larva";304;1
"Unit";"Zergling";"Larva";304;1
"Unit";"Zergling";"Larva";304;1
"Unit";"Zergling";"Larva";304;1
"Unit";"Zergling";"Larva";304;1
"Unit";"Zergling";"Larva";304;1
"Unit";"Zergling";"Larva";304;1
"Unit";"Zergling";"Larva";304;1
"Unit";"Zergling";"Larva";304;1
"Unit";"Hydralisk";"Larva";304;2
"Unit";"Hydralisk";"Larva";304;2
"Unit";"Hydralisk";"Larva";304;2
"Unit";"Hydralisk";"Larva";304;2
"Building";"Extractor";NA;304;0
"Building";"NydusCanal";NA;316;0
"Upgrade";"ZergMissileWeaponsLevel1";"EvolutionChamber";298;0
"Unit";"Hydralisk";"Larva";324;2
"Unit";"Hydralisk";"Larva";324;2
"Unit";"Hydralisk";"Larva";324;2
"Unit";"Hydralisk";"Larva";324;2
"Unit";"Hydralisk";"Larva";324;2
"Unit";"Hydralisk";"Larva";324;2
"Unit";"Hydralisk";"Larva";324;2
"Unit";"Hydralisk";"Larva";338;2
"Unit";"Hydralisk";"Larva";338;2
"Building";"HydraliskDen";NA;338;0
"Unit";"Hydralisk";"Larva";342;2
"Unit";"Hydralisk";"Larva";342;2
"Unit";"Hydralisk";"Larva";342;2
"Unit";"Hydralisk";"Larva";342;2
"Unit";"Hydralisk";"Larva";342;2
"Unit";"Hydralisk";"Larva";342;2
"Unit";"Queen";"Hatchery";342;2
"Building";"Extractor";NA;357;0
"Building";"Extractor";NA;357;0
"Building";"LurkerDenMP";NA;338;0
"Unit";"Hydralisk";"Larva";360;2
"Unit";"Hydralisk";"Larva";360;2
"Unit";"Hydralisk";"Larva";360;2
"Unit";"Hydralisk";"Larva";360;2
"Unit";"Hydralisk";"Larva";360;2
"Unit";"Hydralisk";"Larva";360;2
"Building";"InfestationPit";NA;360;0
"Unit";"Hydralisk";"Larva";380;2
"Unit";"Hydralisk";"Larva";380;2
"Unit";"Hydralisk";"Larva";380;2
"Unit";"Hydralisk";"Larva";380;2
"Unit";"Hydralisk";"Larva";380;2
"Unit";"Hydralisk";"Larva";382;2
"Unit";"Hydralisk";"Larva";382;2
"Unit";"Hydralisk";"Larva";382;2
"Unit";"Hydralisk";"Larva";382;2
"Building";"CreepTumor";NA;392;0
"Building";"CreepTumor";NA;392;0
"Building";"CreepTumor";NA;392;0
"Building";"Extractor";NA;392;0
"Building";"Extractor";NA;392;0
"Unit";"Hydralisk";"Larva";405;2
"Unit";"Hydralisk";"Larva";405;2
"Unit";"Hydralisk";"Larva";405;2
"Unit";"Hydralisk";"Larva";405;2
"Unit";"Hydralisk";"Larva";405;2
"Unit";"Hydralisk";"Larva";405;2
"Unit";"Hydralisk";"Larva";405;2
"Building";"SporeCrawler";NA;422;0
"Building";"SporeCrawler";NA;422;0
"Building";"Hatchery";NA;392;0
"Building";"CreepTumor";NA;427;0
"Building";"CreepTumor";NA;427;0
"Building";"CreepTumor";NA;427;0
"Unit";"Hydralisk";"Larva";427;2
"Unit";"Hydralisk";"Larva";427;2
"Upgrade";"ZergMissileWeaponsLevel2";"EvolutionChamber";392;0
"Unit";"Hydralisk";"Larva";427;2
"Unit";"Hydralisk";"Larva";427;2
"Unit";"Hydralisk";"Larva";427;2
"Upgrade";"ZergGroundArmorsLevel2";"EvolutionChamber";392;0
"Unit";"Queen";"Hatchery";427;2
"Unit";"Hydralisk";"Larva";444;2
"Unit";"Hydralisk";"Larva";444;2
"Unit";"Hydralisk";"Larva";444;2
"Unit";"Hydralisk";"Larva";444;2
"Unit";"Hydralisk";"Larva";444;2
"Unit";"Hydralisk";"Larva";444;2
"Unit";"Hydralisk";"Larva";444;2
"Unit";"Hydralisk";"Larva";444;2
"Unit";"Hydralisk";"Larva";444;2
"Unit";"Hydralisk";"Larva";444;2
"Unit";"Hydralisk";"Larva";466;2
"Unit";"Hydralisk";"Larva";466;2
"Unit";"Hydralisk";"Larva";466;2
"Unit";"Hydralisk";"Larva";466;2
"Building";"Hatchery";NA;444;0
"Unit";"Hydralisk";"Larva";474;2
"Unit";"Hydralisk";"Larva";474;2
"Building";"CreepTumor";NA;474;0
"Building";"CreepTumor";NA;474;0
"Building";"CreepTumor";NA;474;0
"Unit";"Hydralisk";"Larva";474;2
"Unit";"Hydralisk";"Larva";474;2
"Unit";"Hydralisk";"Larva";474;2
"Unit";"Hydralisk";"Larva";474;2
"Unit";"Hydralisk";"Larva";474;2
"Unit";"Hydralisk";"Larva";474;2
"Unit";"Hydralisk";"Larva";474;2
"Unit";"Hydralisk";"Larva";474;2
"Unit";"Hydralisk";"Larva";474;2
"Unit";"Hydralisk";"Larva";474;2
