"type";"unit_name";"on_building";"total_supply";"supply"
"Unit";"Overlord";"Larva";12;0
"Building";"Extractor";NA;17;0
"Unit";"Overlord";"Larva";21;0
"Building";"SpawningPool";NA;19;0
"Building";"Hatchery";NA;17;0
"Unit";"Zergling";"Larva";23;1
"Unit";"Zergling";"Larva";23;1
"Unit";"Zergling";"Larva";23;1
"Unit";"Zergling";"Larva";23;1
"Unit";"Queen";"Hatchery";23;2
"Unit";"Queen";"Hatchery";23;2
"Unit";"Overlord";"Larva";37;0
"Unit";"Overlord";"Larva";37;0
"Unit";"Zergling";"Larva";37;1
"Unit";"Zergling";"Larva";37;1
"Unit";"Queen";"Hatchery";36;2
"Building";"CreepTumorQueen";NA;39;0
"Unit";"Overlord";"Larva";39;0
"Unit";"Overlord";"Larva";49;0
"Building";"Hatchery";NA;36;0
"Building";"CreepTumor";NA;50;0
"Building";"SporeCrawler";NA;50;0
"Unit";"Queen";"Hatchery";47;2
"Building";"CreepTumorQueen";NA;51;0
"Building";"Extractor";NA;50;0
"Building";"CreepTumor";NA;56;0
"Building";"RoachWarren";NA;50;0
"Unit";"Overlord";"Larva";59;0
"Building";"CreepTumorQueen";NA;62;0
"Building";"CreepTumor";NA;62;0
"Unit";"Overlord";"Larva";62;0
"Unit";"Overlord";"Larva";62;0
"Unit";"Roach";"Larva";62;2
"Unit";"Roach";"Larva";62;2
"Unit";"Roach";"Larva";62;2
"Unit";"Roach";"Larva";62;2
"Unit";"Roach";"Larva";62;2
"Unit";"Roach";"Larva";62;2
"Unit";"Roach";"Larva";62;2
"Building";"CreepTumor";NA;62;0
"Building";"CreepTumorQueen";NA;62;0
"Unit";"Roach";"Larva";62;2
"Unit";"Roach";"Larva";62;2
"Unit";"Roach";"Larva";62;2
"Unit";"Roach";"Larva";62;2
"Building";"SpineCrawler";NA;62;0
"Unit";"Overlord";"Larva";62;0
"Unit";"Roach";"Larva";76;2
"Unit";"Roach";"Larva";76;2
"Unit";"Roach";"Larva";76;2
"Unit";"Overlord";"Larva";76;0
"Unit";"Roach";"Larva";84;2
"Unit";"Roach";"Larva";84;2
"Unit";"Roach";"Larva";84;2
"Unit";"Roach";"Larva";85;2
"Unit";"Overlord";"Larva";92;0
"Unit";"Roach";"Larva";98;2
"Unit";"Roach";"Larva";98;2
"Unit";"Roach";"Larva";98;2
"Unit";"Roach";"Larva";100;2
"Unit";"Roach";"Larva";100;2
"Unit";"Roach";"Larva";100;2
"Unit";"Roach";"Larva";100;2
"Unit";"Roach";"Larva";100;2
"Unit";"Roach";"Larva";100;2
"Building";"CreepTumor";NA;111;0
"Building";"CreepTumor";NA;122;0
"Unit";"Roach";"Larva";106;2
"Building";"CreepTumor";NA;124;0
"Unit";"Roach";"Larva";106;2
"Building";"CreepTumorQueen";NA;128;0
"Building";"Extractor";NA;111;0
"Unit";"Roach";"Larva";128;2
"Unit";"Roach";"Larva";128;2
"Unit";"Zergling";"Larva";128;1
"Unit";"Zergling";"Larva";128;1
"Building";"Extractor";NA;128;0
"Unit";"Zergling";"Larva";138;1
"Unit";"Zergling";"Larva";138;1
"Unit";"Zergling";"Larva";138;1
"Unit";"Zergling";"Larva";138;1
"Unit";"Zergling";"Larva";138;1
"Unit";"Zergling";"Larva";138;1
"Building";"CreepTumor";NA;141;0
"Building";"CreepTumor";NA;141;0
"Building";"EvolutionChamber";NA;132;0
"Unit";"Overlord";"Larva";141;0
"Unit";"Overlord";"Larva";141;0
"Unit";"Overlord";"Larva";141;0
"Unit";"Overlord";"Larva";141;0
"Building";"CreepTumor";NA;141;0
"Unit";"Overlord";"Larva";141;0
"Building";"CreepTumorQueen";NA;148;0
"Building";"CreepTumor";NA;148;0
"Building";"CreepTumor";NA;148;0
"Unit";"Roach";"Larva";148;2
"Unit";"Roach";"Larva";148;2
"Unit";"Roach";"Larva";148;2
"Unit";"Roach";"Larva";148;2
"Unit";"Zergling";"Larva";150;1
"Unit";"Zergling";"Larva";150;1
"Unit";"Zergling";"Larva";150;1
"Unit";"Zergling";"Larva";150;1
"Unit";"Zergling";"Larva";150;1
"Unit";"Zergling";"Larva";150;1
"Unit";"Zergling";"Larva";150;1
"Unit";"Zergling";"Larva";150;1
"Unit";"Zergling";"Larva";150;1
"Unit";"Zergling";"Larva";150;1
"Building";"CreepTumor";NA;150;0
"Unit";"Zergling";"Larva";150;1
"Unit";"Zergling";"Larva";150;1
"Unit";"Zergling";"Larva";150;1
"Unit";"Zergling";"Larva";150;1
"Unit";"Zergling";"Larva";150;1
"Unit";"Zergling";"Larva";150;1
"Unit";"Zergling";"Larva";150;1
"Unit";"Zergling";"Larva";150;1
"Unit";"Zergling";"Larva";150;1
"Unit";"Zergling";"Larva";150;1
"Unit";"Zergling";"Larva";150;1
"Unit";"Zergling";"Larva";150;1
"Unit";"Zergling";"Larva";150;1
"Unit";"Zergling";"Larva";150;1
"Building";"BanelingNest";NA;148;0
"Unit";"Overlord";"Larva";184;0
"Unit";"Zergling";"Larva";184;1
"Unit";"Zergling";"Larva";184;1
"Unit";"Zergling";"Larva";184;1
"Unit";"Zergling";"Larva";184;1
"Unit";"Zergling";"Larva";184;1
"Unit";"Zergling";"Larva";184;1
"Unit";"Zergling";"Larva";184;1
"Unit";"Zergling";"Larva";184;1
"Unit";"Zergling";"Larva";184;1
"Unit";"Zergling";"Larva";184;1
"Unit";"Zergling";"Larva";184;1
"Unit";"Zergling";"Larva";184;1
"Unit";"Zergling";"Larva";184;1
"Unit";"Zergling";"Larva";184;1
"Unit";"Zergling";"Larva";184;1
"Unit";"Zergling";"Larva";184;1
"Unit";"Zergling";"Larva";184;1
"Unit";"Zergling";"Larva";184;1
"Unit";"Baneling";"Zergling";184;0
"Unit";"Baneling";"Zergling";184;0
"Unit";"Baneling";"Zergling";184;0
"Unit";"Baneling";"Zergling";184;0
"Unit";"Baneling";"Zergling";184;0
"Unit";"Baneling";"Zergling";184;0
"Unit";"Baneling";"Zergling";184;0
"Unit";"Baneling";"Zergling";184;0
"Unit";"Baneling";"Zergling";184;0
"Unit";"Baneling";"Zergling";184;0
"Unit";"Baneling";"Zergling";184;0
"Unit";"Baneling";"Zergling";184;0
"Unit";"Baneling";"Zergling";184;0
"Unit";"Baneling";"Zergling";184;0
"Unit";"Baneling";"Zergling";184;0
"Building";"CreepTumor";NA;184;0
"Building";"CreepTumor";NA;184;0
"Unit";"Overlord";"Larva";184;0
"Unit";"Baneling";"Zergling";202;0
"Building";"Extractor";NA;184;0
"Unit";"Baneling";"Zergling";202;0
"Unit";"Baneling";"Zergling";202;0
"Unit";"Baneling";"Zergling";202;0
"Unit";"Baneling";"Zergling";202;0
"Unit";"Baneling";"Zergling";202;0
"Unit";"Baneling";"Zergling";202;0
"Unit";"Baneling";"Zergling";204;0
"Unit";"Baneling";"Zergling";205;0
"Unit";"Roach";"Larva";207;2
"Unit";"Roach";"Larva";207;2
"Unit";"Roach";"Larva";207;2
"Upgrade";"ZergMissileWeaponsLevel1";"EvolutionChamber";150;0
"Upgrade";"GlialReconstitution";"RoachWarren";184;0
"Unit";"Overlord";"Larva";207;0
"Building";"HydraliskDen";NA;207;0
"Building";"Hatchery";NA;202;0
"Unit";"Overlord";"Larva";216;0
"Unit";"Overlord";"Larva";216;0
"Unit";"Overlord";"Larva";216;0
"Unit";"Hydralisk";"Larva";216;2
"Unit";"Hydralisk";"Larva";216;2
"Unit";"Hydralisk";"Larva";216;2
"Unit";"Hydralisk";"Larva";216;2
"Unit";"Hydralisk";"Larva";216;2
"Unit";"Hydralisk";"Larva";216;2
"Unit";"Hydralisk";"Larva";216;2
"Unit";"Hydralisk";"Larva";216;2
"Unit";"Hydralisk";"Larva";216;2
"Unit";"Hydralisk";"Larva";216;2
"Building";"Extractor";NA;216;0
"Building";"CreepTumor";NA;219;0
"Unit";"Zergling";"Larva";216;1
"Unit";"Zergling";"Larva";216;1
"Unit";"Zergling";"Larva";216;1
"Unit";"Zergling";"Larva";216;1
"Unit";"Zergling";"Larva";216;1
"Unit";"Zergling";"Larva";216;1
"Unit";"Zergling";"Larva";216;1
"Unit";"Zergling";"Larva";216;1
"Unit";"Zergling";"Larva";216;1
"Unit";"Zergling";"Larva";216;1
"Unit";"Zergling";"Larva";216;1
"Unit";"Zergling";"Larva";216;1
"Unit";"Zergling";"Larva";216;1
"Unit";"Zergling";"Larva";216;1
"Unit";"Zergling";"Larva";216;1
"Unit";"Zergling";"Larva";216;1
"Unit";"Zergling";"Larva";216;1
"Unit";"Zergling";"Larva";216;1
"Unit";"Zergling";"Larva";216;1
"Unit";"Zergling";"Larva";216;1
"Building";"CreepTumor";NA;222;0
"Building";"CreepTumor";NA;222;0
"Building";"Extractor";NA;216;0
"Building";"Extractor";NA;216;0
"Unit";"Queen";"Hatchery";216;2
"Upgrade";"EvolveMuscularAugments";"HydraliskDen";216;0
"Unit";"Hydralisk";"Larva";262;2
"Unit";"Hydralisk";"Larva";262;2
"Unit";"Hydralisk";"Larva";262;2
"Unit";"Hydralisk";"Larva";262;2
"Unit";"Hydralisk";"Larva";262;2
"Unit";"Hydralisk";"Larva";262;2
"Unit";"Hydralisk";"Larva";262;2
"Unit";"Zergling";"Larva";265;1
"Unit";"Zergling";"Larva";265;1
"Unit";"Hydralisk";"Larva";262;2
"Unit";"Hydralisk";"Larva";262;2
"Unit";"Overlord";"Larva";265;0
"Unit";"Hydralisk";"Larva";262;2
"Unit";"Overlord";"Larva";265;0
"Unit";"Overlord";"Larva";265;0
"Building";"Hatchery";NA;216;0
"Unit";"Hydralisk";"Larva";291;2
"Unit";"Hydralisk";"Larva";291;2
"Unit";"Hydralisk";"Larva";291;2
"Unit";"Hydralisk";"Larva";291;2
"Unit";"Hydralisk";"Larva";291;2
"Unit";"Hydralisk";"Larva";291;2
"Unit";"Hydralisk";"Larva";291;2
"Unit";"Hydralisk";"Larva";291;2
"Unit";"Hydralisk";"Larva";291;2
"Unit";"Hydralisk";"Larva";291;2
"Unit";"Hydralisk";"Larva";291;2
"Unit";"Hydralisk";"Larva";291;2
"Unit";"Hydralisk";"Larva";291;2
"Unit";"Hydralisk";"Larva";291;2
"Unit";"Hydralisk";"Larva";291;2
"Building";"CreepTumor";NA;309;0
"Building";"CreepTumor";NA;311;0
"Unit";"Zergling";"Larva";309;1
"Unit";"Zergling";"Larva";309;1
"Upgrade";"ZergMissileWeaponsLevel2";"EvolutionChamber";222;0
"Unit";"Zergling";"Larva";316;1
"Unit";"Zergling";"Larva";316;1
"Unit";"Baneling";"Zergling";320;0
"Unit";"Zergling";"Larva";316;1
"Unit";"Zergling";"Larva";316;1
"Unit";"Baneling";"Zergling";320;0
"Unit";"Zergling";"Larva";316;1
"Unit";"Zergling";"Larva";316;1
"Upgrade";"EvolveGroovedSpines";"HydraliskDen";291;0
"Unit";"Zergling";"Larva";334;1
"Unit";"Zergling";"Larva";334;1
"Unit";"Hydralisk";"Larva";334;2
"Unit";"Hydralisk";"Larva";334;2
"Unit";"Hydralisk";"Larva";334;2
"Unit";"Zergling";"Larva";342;1
"Unit";"Zergling";"Larva";342;1
"Unit";"Zergling";"Larva";342;1
"Unit";"Zergling";"Larva";342;1
"Unit";"Zergling";"Larva";342;1
"Unit";"Zergling";"Larva";342;1
"Unit";"Zergling";"Larva";342;1
"Unit";"Zergling";"Larva";342;1
"Unit";"Zergling";"Larva";342;1
"Unit";"Zergling";"Larva";342;1
"Unit";"Zergling";"Larva";342;1
"Unit";"Zergling";"Larva";342;1
"Unit";"Zergling";"Larva";342;1
"Unit";"Zergling";"Larva";342;1
"Unit";"Zergling";"Larva";342;1
"Unit";"Zergling";"Larva";342;1
"Unit";"Zergling";"Larva";342;1
"Unit";"Zergling";"Larva";342;1
"Unit";"Zergling";"Larva";342;1
"Unit";"Zergling";"Larva";342;1
"Unit";"Zergling";"Larva";342;1
"Unit";"Zergling";"Larva";342;1
"Building";"CreepTumor";NA;372;0
"Unit";"Hydralisk";"Larva";372;2
"Unit";"Hydralisk";"Larva";372;2
"Unit";"Hydralisk";"Larva";372;2
"Unit";"Hydralisk";"Larva";372;2
"Unit";"Hydralisk";"Larva";372;2
"Unit";"Hydralisk";"Larva";372;2
"Unit";"Baneling";"Zergling";372;0
"Unit";"Baneling";"Zergling";372;0
"Unit";"Baneling";"Zergling";372;0
"Unit";"Baneling";"Zergling";372;0
"Unit";"Baneling";"Zergling";372;0
"Unit";"Baneling";"Zergling";372;0
"Unit";"Baneling";"Zergling";372;0
"Unit";"Baneling";"Zergling";372;0
"Unit";"Baneling";"Zergling";372;0
"Building";"Extractor";NA;372;0
"Building";"Extractor";NA;372;0
"Unit";"Zergling";"Larva";372;1
"Unit";"Zergling";"Larva";372;1
"Unit";"Zergling";"Larva";372;1
"Unit";"Zergling";"Larva";372;1
"Unit";"Zergling";"Larva";372;1
"Unit";"Zergling";"Larva";372;1
"Unit";"Zergling";"Larva";373;1
"Unit";"Zergling";"Larva";373;1
"Unit";"Zergling";"Larva";373;1
"Unit";"Zergling";"Larva";373;1
"Unit";"Zergling";"Larva";373;1
"Unit";"Zergling";"Larva";373;1
"Unit";"Zergling";"Larva";373;1
"Unit";"Zergling";"Larva";373;1
"Building";"SpineCrawler";NA;375;0
"Building";"SpineCrawler";NA;375;0
"Building";"Hatchery";NA;344;0
"Unit";"Zergling";"Larva";403;1
"Unit";"Zergling";"Larva";403;1
"Unit";"Zergling";"Larva";403;1
"Unit";"Zergling";"Larva";403;1
"Unit";"Zergling";"Larva";403;1
"Unit";"Zergling";"Larva";403;1
"Unit";"Zergling";"Larva";403;1
"Unit";"Zergling";"Larva";403;1
"Unit";"Zergling";"Larva";403;1
"Unit";"Zergling";"Larva";403;1
"Unit";"Zergling";"Larva";403;1
"Unit";"Zergling";"Larva";403;1
"Building";"CreepTumor";NA;403;0
"Unit";"Zergling";"Larva";403;1
"Unit";"Zergling";"Larva";403;1
"Unit";"Zergling";"Larva";403;1
"Unit";"Zergling";"Larva";403;1
"Unit";"Zergling";"Larva";403;1
"Unit";"Zergling";"Larva";403;1
"Unit";"Zergling";"Larva";403;1
"Unit";"Zergling";"Larva";403;1
"Unit";"Zergling";"Larva";403;1
"Unit";"Zergling";"Larva";403;1
"Unit";"Zergling";"Larva";403;1
"Unit";"Zergling";"Larva";403;1
"Unit";"Zergling";"Larva";403;1
"Unit";"Zergling";"Larva";403;1
"Unit";"Overlord";"Larva";403;0
"Building";"Spire";NA;372;0
"Unit";"Baneling";"Zergling";403;0
"Unit";"Baneling";"Zergling";403;0
"Unit";"Baneling";"Zergling";403;0
"Unit";"Baneling";"Zergling";403;0
"Unit";"Baneling";"Zergling";403;0
"Unit";"Baneling";"Zergling";403;0
"Unit";"Baneling";"Zergling";403;0
"Unit";"Baneling";"Zergling";403;0
"Unit";"Baneling";"Zergling";403;0
"Unit";"Baneling";"Zergling";403;0
"Unit";"Baneling";"Zergling";403;0
"Unit";"Baneling";"Zergling";403;0
"Unit";"Baneling";"Zergling";403;0
"Unit";"Baneling";"Zergling";403;0
"Unit";"Baneling";"Zergling";403;0
"Unit";"Baneling";"Zergling";403;0
"Unit";"Baneling";"Zergling";403;0
"Unit";"Baneling";"Zergling";403;0
"Unit";"Baneling";"Zergling";403;0
"Unit";"Baneling";"Zergling";403;0
"Unit";"Baneling";"Zergling";403;0
"Upgrade";"ZergMeleeWeaponsLevel1";"EvolutionChamber";372;0
"Unit";"Mutalisk";"Larva";429;2
"Unit";"Mutalisk";"Larva";429;2
"Unit";"Mutalisk";"Larva";429;2
"Unit";"Mutalisk";"Larva";429;2
"Unit";"Mutalisk";"Larva";429;2
"Unit";"Mutalisk";"Larva";429;2
"Unit";"Mutalisk";"Larva";429;2
"Unit";"Mutalisk";"Larva";429;2
"Unit";"Mutalisk";"Larva";429;2
"Unit";"Mutalisk";"Larva";429;2
"Unit";"Mutalisk";"Larva";429;2
"Unit";"Mutalisk";"Larva";429;2
"Unit";"Mutalisk";"Larva";429;2
"Unit";"Hydralisk";"Larva";429;2
"Unit";"Hydralisk";"Larva";429;2
"Unit";"Hydralisk";"Larva";429;2
"Unit";"Hydralisk";"Larva";429;2
"Unit";"Hydralisk";"Larva";429;2
"Unit";"Hydralisk";"Larva";455;2
"Unit";"Hydralisk";"Larva";455;2
"Unit";"Hydralisk";"Larva";455;2
"Unit";"Hydralisk";"Larva";455;2
"Unit";"Hydralisk";"Larva";455;2
"Building";"CreepTumor";NA;465;0
"Unit";"Baneling";"Zergling";475;0
"Unit";"Baneling";"Zergling";475;0
"Unit";"Baneling";"Zergling";475;0
"Unit";"Baneling";"Zergling";475;0
"Unit";"Baneling";"Zergling";475;0
"Unit";"Baneling";"Zergling";475;0
"Unit";"Baneling";"Zergling";475;0
"Unit";"Baneling";"Zergling";475;0
"Unit";"Baneling";"Zergling";475;0
"Unit";"Baneling";"Zergling";475;0
"Unit";"Baneling";"Zergling";475;0
"Unit";"Baneling";"Zergling";475;0
"Unit";"Baneling";"Zergling";475;0
"Unit";"Baneling";"Zergling";475;0
"Unit";"Baneling";"Zergling";475;0
"Unit";"Hydralisk";"Larva";475;2
"Unit";"Hydralisk";"Larva";475;2
