"type";"unit_name";"on_building";"total_supply";"supply"
"Unit";"Overlord";"Larva";12;0
"Building";"Extractor";NA;18;0
"Unit";"Overlord";"Larva";21;0
"Building";"SpawningPool";NA;19;0
"Building";"Hatchery";NA;17;0
"Unit";"Zergling";"Larva";22;1
"Unit";"Zergling";"Larva";22;1
"Unit";"Zergling";"Larva";22;1
"Unit";"Zergling";"Larva";22;1
"Unit";"Queen";"Hatchery";22;2
"Unit";"Queen";"Hatchery";22;2
"Unit";"Overlord";"Larva";35;0
"Unit";"Overlord";"Larva";39;0
"Unit";"Queen";"Hatchery";39;2
"Building";"Hatchery";NA;29;0
"Unit";"Overlord";"Larva";42;0
"Unit";"Overlord";"Larva";42;0
"Unit";"Overlord";"Larva";46;0
"Building";"CreepTumorQueen";NA;48;0
"Building";"Extractor";NA;48;0
"Unit";"Overlord";"Larva";53;0
"Building";"SporeCrawler";NA;53;0
"Building";"RoachWarren";NA;48;0
"Building";"SporeCrawler";NA;53;0
"Unit";"Overlord";"Larva";55;0
"Building";"CreepTumor";NA;55;0
"Building";"CreepTumorQueen";NA;55;0
"Building";"EvolutionChamber";NA;55;0
"Unit";"Roach";"Larva";55;2
"Unit";"Roach";"Larva";55;2
"Unit";"Roach";"Larva";55;2
"Unit";"Roach";"Larva";56;2
"Unit";"Roach";"Larva";56;2
"Unit";"Roach";"Larva";56;2
"Unit";"Queen";"Hatchery";55;2
"Building";"CreepTumor";NA;62;0
"Unit";"Roach";"Larva";56;2
"Unit";"Roach";"Larva";56;2
"Unit";"Roach";"Larva";65;2
"Unit";"Roach";"Larva";66;2
"Unit";"Roach";"Larva";72;2
"Building";"CreepTumor";NA;76;0
"Unit";"Roach";"Larva";72;2
"Unit";"Overlord";"Larva";74;0
"Unit";"Roach";"Larva";76;2
"Unit";"Roach";"Larva";76;2
"Unit";"Roach";"Larva";78;2
"Unit";"Roach";"Larva";80;2
"Unit";"Overlord";"Larva";80;0
"Unit";"Roach";"Larva";84;2
"Unit";"Roach";"Larva";84;2
"Unit";"Roach";"Larva";84;2
"Building";"CreepTumor";NA;92;0
"Building";"CreepTumor";NA;98;0
"Unit";"Roach";"Larva";98;2
"Unit";"Roach";"Larva";98;2
"Building";"CreepTumorQueen";NA;104;0
"Unit";"Roach";"Larva";103;2
"Upgrade";"GlialReconstitution";"RoachWarren";80;0
"Building";"SporeCrawler";NA;104;0
"Unit";"Overlord";"Larva";104;0
"Unit";"Overlord";"Larva";104;0
"Unit";"Roach";"Larva";113;2
"Unit";"Roach";"Larva";113;2
"Unit";"Roach";"Larva";113;2
"Unit";"Roach";"Larva";113;2
"Unit";"Roach";"Larva";113;2
"Unit";"Roach";"Larva";113;2
"Unit";"Roach";"Larva";113;2
"Unit";"Roach";"Larva";113;2
"Unit";"Overlord";"Larva";113;0
"Unit";"Overlord";"Larva";113;0
"Unit";"Overlord";"Larva";113;0
"Building";"Extractor";NA;129;0
"Building";"HydraliskDen";NA;129;0
"Upgrade";"ZergMissileWeaponsLevel1";"EvolutionChamber";108;0
"Building";"Extractor";NA;141;0
"Building";"Extractor";NA;141;0
"Building";"Extractor";NA;141;0
"Unit";"Roach";"Larva";148;2
"Building";"CreepTumor";NA;152;0
"Building";"CreepTumor";NA;154;0
"Building";"CreepTumorQueen";NA;156;0
"Unit";"Hydralisk";"Larva";154;2
"Unit";"Hydralisk";"Larva";154;2
"Unit";"Hydralisk";"Larva";154;2
"Unit";"Hydralisk";"Larva";154;2
"Unit";"Hydralisk";"Larva";154;2
"Building";"CreepTumorQueen";NA;166;0
"Unit";"Overlord";"Larva";156;0
"Unit";"Overlord";"Larva";156;0
"Unit";"Overlord";"Larva";156;0
"Unit";"Overlord";"Larva";156;0
"Unit";"Overlord";"Larva";156;0
"Unit";"Overlord";"Larva";156;0
"Unit";"Overlord";"Larva";156;0
"Building";"CreepTumorQueen";NA;166;0
"Building";"CreepTumorQueen";NA;166;0
"Unit";"Hydralisk";"Larva";156;2
"Unit";"Hydralisk";"Larva";156;2
"Upgrade";"EvolveGroovedSpines";"HydraliskDen";152;0
"Building";"CreepTumorQueen";NA;166;0
"Unit";"Hydralisk";"Larva";166;2
"Unit";"Hydralisk";"Larva";166;2
"Unit";"Hydralisk";"Larva";166;2
"Unit";"Hydralisk";"Larva";166;2
"Unit";"Hydralisk";"Larva";166;2
"Building";"CreepTumor";NA;170;0
"Building";"Hatchery";NA;152;0
"Building";"CreepTumor";NA;170;0
"Unit";"Roach";"Larva";170;2
"Unit";"Roach";"Larva";170;2
"Unit";"Roach";"Larva";170;2
"Unit";"Roach";"Larva";170;2
"Unit";"Hydralisk";"Larva";170;2
"Unit";"Hydralisk";"Larva";170;2
"Unit";"Hydralisk";"Larva";170;2
"Unit";"Roach";"Larva";180;2
"Unit";"Roach";"Larva";180;2
"Unit";"Roach";"Larva";180;2
"Unit";"Roach";"Larva";180;2
"Unit";"Hydralisk";"Larva";180;2
"Unit";"Roach";"Larva";186;2
"Unit";"Roach";"Larva";188;2
"Unit";"Roach";"Larva";188;2
"Unit";"Hydralisk";"Larva";186;2
"Unit";"Hydralisk";"Larva";188;2
"Unit";"Roach";"Larva";213;2
"Unit";"Roach";"Larva";213;2
"Unit";"Roach";"Larva";213;2
"Unit";"Roach";"Larva";213;2
"Unit";"Hydralisk";"Larva";213;2
"Unit";"Hydralisk";"Larva";213;2
"Unit";"Hydralisk";"Larva";213;2
"Unit";"Hydralisk";"Larva";213;2
"Upgrade";"EvolveMuscularAugments";"HydraliskDen";180;0
"Unit";"Roach";"Larva";217;2
"Unit";"Roach";"Larva";217;2
"Unit";"Hydralisk";"Larva";217;2
"Unit";"Hydralisk";"Larva";217;2
"Building";"CreepTumor";NA;233;0
"Building";"CreepTumor";NA;233;0
"Building";"CreepTumor";NA;233;0
"Building";"CreepTumor";NA;233;0
"Unit";"Overlord";"Larva";233;0
"Unit";"Overlord";"Larva";233;0
"Unit";"Overlord";"Larva";233;0
"Building";"Extractor";NA;233;0
"Building";"Extractor";NA;233;0
"Upgrade";"ZergMissileWeaponsLevel2";"EvolutionChamber";170;0
"Unit";"Roach";"Larva";241;2
"Unit";"Roach";"Larva";241;2
"Unit";"Roach";"Larva";241;2
"Unit";"Roach";"Larva";241;2
"Unit";"Hydralisk";"Larva";241;2
"Unit";"Hydralisk";"Larva";241;2
"Unit";"Hydralisk";"Larva";241;2
"Unit";"Roach";"Larva";249;2
"Unit";"Roach";"Larva";249;2
"Unit";"Roach";"Larva";249;2
"Unit";"Roach";"Larva";249;2
"Unit";"Roach";"Larva";249;2
"Unit";"Roach";"Larva";249;2
"Unit";"Roach";"Larva";249;2
"Unit";"Roach";"Larva";249;2
"Unit";"Hydralisk";"Larva";249;2
"Unit";"Hydralisk";"Larva";249;2
"Unit";"Hydralisk";"Larva";249;2
"Unit";"Hydralisk";"Larva";249;2
"Unit";"Hydralisk";"Larva";249;2
"Unit";"Hydralisk";"Larva";249;2
"Unit";"Hydralisk";"Larva";249;2
"Unit";"Roach";"Larva";255;2
"Unit";"Roach";"Larva";289;2
"Unit";"Roach";"Larva";289;2
"Unit";"Roach";"Larva";289;2
"Unit";"Roach";"Larva";289;2
"Unit";"Roach";"Larva";289;2
"Unit";"Roach";"Larva";289;2
"Unit";"Roach";"Larva";289;2
"Unit";"Hydralisk";"Larva";289;2
"Unit";"Hydralisk";"Larva";289;2
"Unit";"Hydralisk";"Larva";289;2
"Unit";"Hydralisk";"Larva";289;2
"Unit";"Hydralisk";"Larva";289;2
"Unit";"Hydralisk";"Larva";289;2
"Unit";"Hydralisk";"Larva";289;2
"Unit";"Roach";"Larva";289;2
"Unit";"Roach";"Larva";289;2
"Unit";"Roach";"Larva";289;2
"Unit";"Hydralisk";"Larva";289;2
"Unit";"Hydralisk";"Larva";289;2
"Building";"CreepTumor";NA;319;0
"Building";"CreepTumor";NA;319;0
"Building";"CreepTumor";NA;319;0
"Unit";"Roach";"Larva";303;2
"Unit";"Roach";"Larva";303;2
"Building";"CreepTumor";NA;319;0
"Building";"CreepTumor";NA;319;0
"Unit";"Hydralisk";"Larva";303;2
"Unit";"Hydralisk";"Larva";303;2
"Unit";"Roach";"Larva";319;2
"Unit";"Roach";"Larva";319;2
"Unit";"Roach";"Larva";319;2
"Unit";"Hydralisk";"Larva";319;2
"Unit";"Hydralisk";"Larva";319;2
"Unit";"Hydralisk";"Larva";319;2
