"type";"unit_name";"on_building";"total_supply_lag";"supply"
"Building";"Refinery";NA;15;0
"Building";"Barracks";NA;16;0
"Unit";"Reaper";"Barracks";19;1
"Building";"CommandCenter";NA;20;0
"Building";"Factory";NA;20;0
"Building";"Refinery";NA;21;0
"Unit";"Reaper";"Barracks";21;1
"Building";"BarracksReactor";NA;24;0
"Unit";"Hellion";"Factory";25;2
"Building";"Starport";NA;27;0
"Unit";"Hellion";"Factory";28;2
"Upgrade";"SprayTerran";NA;33;0
"Upgrade";"SprayTerran";NA;33;0
