"type";"unit_name";"on_building";"total_supply_lag";"supply"
"Building";"Pylon";NA;14;0
"Building";"Gateway";NA;15;0
"Building";"Assimilator";NA;15;0
"Building";"Assimilator";NA;16;0
"Building";"Gateway";NA;18;0
"Building";"CyberneticsCore";NA;19;0
"Building";"Pylon";NA;21;0
"Unit";"Stalker";"Gateway";22;2
"Unit";"Stalker";"Gateway";24;2
"Building";"Nexus";NA;28;0
"Building";"Pylon";NA;28;0
"Building";"Pylon";NA;28;0
"Building";"TwilightCouncil";NA;29;0
"Unit";"Stalker";"Gateway";29;2
"Unit";"Sentry";"Gateway";31;2
"Building";"Pylon";NA;36;0
"Unit";"Colossus";"Robotics Facility";40;6
"Upgrade";"Charge";"TwilightCouncil";46;0
"Unit";"Stalker";"Gateway";46;2
"Unit";"Stalker";"Gateway";48;2
"Building";"Gateway";NA;54;0
"Building";"Gateway";NA;54;0
"Building";"Pylon";NA;57;0
"Unit";"Zealot";"Gateway";59;2
"Unit";"Zealot";"Gateway";61;2
"Building";"Gateway";NA;65;0
"Building";"TemplarArchive";NA;66;0
"Building";"Assimilator";NA;69;0
"Unit";"Zealot";"Gateway";70;2
"Unit";"Zealot";"Gateway";72;2
"Building";"Assimilator";NA;74;0
"Unit";"Stalker";"Gateway";74;2
"Unit";"Stalker";"Gateway";76;2
"Building";"Pylon";NA;79;0
"Building";"Pylon";NA;79;0
"Building";"Gateway";NA;79;0
"Building";"HighTemplar";NA;80;0
"Building";"HighTemplar";NA;80;0
"Building";"Gateway";NA;80;0
"Building";"HighTemplar";NA;80;0
"Building";"HighTemplar";NA;80;0
"Building";"Gateway";NA;80;0
"Building";"Pylon";NA;80;0
"Unit";"Archon";"High Templar";80;0
"Unit";"Archon";"High Templar";80;0
"Unit";"Zealot";"Gateway";80;2
"Building";"Pylon";NA;82;0
"Building";"Pylon";NA;82;0
"Building";"HighTemplar";NA;82;0
"Building";"HighTemplar";NA;82;0
"Unit";"Archon";"High Templar";82;0
"Unit";"Zealot";"Gateway";82;2
"Unit";"Zealot";"Gateway";84;2
"Unit";"Zealot";"Gateway";86;2
"Building";"Pylon";NA;88;0
"Unit";"Zealot";"Gateway";88;2
"Building";"Pylon";NA;90;0
"Unit";"Zealot";"Gateway";90;2
"Unit";"Zealot";"Gateway";92;2
"Building";"HighTemplar";NA;94;0
"Building";"HighTemplar";NA;94;0
"Unit";"Archon";"High Templar";94;0
"Unit";"Zealot";"Gateway";94;2
"Unit";"Zealot";"Gateway";96;2
"Unit";"Zealot";"Gateway";98;2
"Unit";"Zealot";"Gateway";100;2
"Unit";"Zealot";"Gateway";103;2
"Unit";"Zealot";"Gateway";105;2
"Unit";"Zealot";"Gateway";107;2
"Unit";"Zealot";"Gateway";109;2
"Unit";"Zealot";"Gateway";111;2
"Unit";"Zealot";"Gateway";113;2
"Unit";"Zealot";"Gateway";115;2
"Unit";"Zealot";"Gateway";117;2
"Unit";"Stalker";"Gateway";120;2
"Unit";"Stalker";"Gateway";122;2
"Unit";"Stalker";"Gateway";124;2
"Unit";"Stalker";"Gateway";126;2
"Building";"HighTemplar";NA;128;0
"Building";"HighTemplar";NA;128;0
"Unit";"Archon";"High Templar";128;0
"Building";"HighTemplar";NA;128;0
"Building";"HighTemplar";NA;128;0
"Unit";"Archon";"High Templar";129;0
"Building";"HighTemplar";NA;130;0
"Unit";"Zealot";"Gateway";130;2
"Unit";"Zealot";"Gateway";132;2
"Building";"HighTemplar";NA;134;0
"Unit";"Zealot";"Gateway";134;2
"Unit";"Archon";"High Templar";136;0
"Unit";"Zealot";"Gateway";136;2
"Unit";"Stalker";"Gateway";138;2
"Unit";"Stalker";"Gateway";140;2
"Unit";"Stalker";"Gateway";142;2
"Unit";"Stalker";"Gateway";144;2
"Unit";"Stalker";"Gateway";146;2
"Unit";"Colossus";"Robotics Facility";148;6
"Unit";"Zealot";"Gateway";154;2
"Unit";"Zealot";"Gateway";156;2
"Unit";"Zealot";"Gateway";160;2
"Unit";"Zealot";"Gateway";162;2
"Unit";"Zealot";"Gateway";164;2
"Unit";"Zealot";"Gateway";166;2
"Unit";"Zealot";"Gateway";168;2
"Building";"HighTemplar";NA;171;0
"Building";"HighTemplar";NA;171;0
"Building";"HighTemplar";NA;171;0
"Unit";"Archon";"High Templar";171;0
"Building";"HighTemplar";NA;171;0
"Unit";"Archon";"High Templar";171;0
"Unit";"Zealot";"Gateway";171;2
"Unit";"Zealot";"Gateway";173;2
"Unit";"Zealot";"Gateway";175;2
"Unit";"Zealot";"Gateway";177;2
"Unit";"Zealot";"Gateway";180;2
"Building";"HighTemplar";NA;182;0
"Building";"HighTemplar";NA;182;0
"Unit";"Archon";"High Templar";182;0
"Unit";"Zealot";"Gateway";182;2
"Unit";"Zealot";"Gateway";184;2
"Unit";"Zealot";"Gateway";186;2
"Unit";"Zealot";"Gateway";188;2
"Unit";"Zealot";"Gateway";190;2
"Building";"Nexus";NA;192;0
"Building";"HighTemplar";NA;192;0
"Building";"HighTemplar";NA;192;0
"Unit";"Archon";"High Templar";192;0
"Unit";"Zealot";"Gateway";192;2
"Unit";"Zealot";"Gateway";194;2
"Unit";"Zealot";"Gateway";196;2
"Unit";"Zealot";"Gateway";198;2
"Unit";"Zealot";"Gateway";200;2
"Building";"Pylon";NA;202;0
"Building";"HighTemplar";NA;202;0
"Building";"HighTemplar";NA;202;0
"Unit";"Zealot";"Gateway";202;2
"Unit";"Zealot";"Gateway";204;2
"Unit";"Zealot";"Gateway";206;2
"Unit";"Archon";"High Templar";208;0
"Building";"Pylon";NA;208;0
"Building";"HighTemplar";NA;208;0
"Building";"RoboticsFacility";NA;208;0
"Building";"Pylon";NA;208;0
"Unit";"Zealot";"Gateway";208;2
"Unit";"Stalker";"Gateway";211;2
"Unit";"Stalker";"Gateway";213;2
"Unit";"Stalker";"Gateway";215;2
"Building";"HighTemplar";NA;218;0
"Building";"HighTemplar";NA;218;0
"Unit";"Zealot";"Gateway";218;2
"Unit";"Zealot";"Gateway";220;2
"Unit";"Zealot";"Gateway";222;2
"Unit";"Archon";"High Templar";224;0
"Unit";"Zealot";"Gateway";226;2
"Unit";"Zealot";"Gateway";228;2
"Unit";"Zealot";"Gateway";230;2
"Unit";"Zealot";"Gateway";232;2
"Unit";"Zealot";"Gateway";234;2
"Unit";"Stalker";"Gateway";236;2
"Building";"HighTemplar";NA;238;0
"Building";"HighTemplar";NA;238;0
"Unit";"Archon";"High Templar";238;0
"Building";"HighTemplar";NA;238;0
"Unit";"Zealot";"Gateway";238;2
"Unit";"Zealot";"Gateway";240;2
"Unit";"Archon";"High Templar";243;0
"Unit";"Zealot";"Gateway";243;2
"Unit";"Zealot";"Gateway";245;2
"Unit";"Zealot";"Gateway";247;2
"Upgrade";"SprayProtoss";NA;249;0
"Upgrade";"SprayProtoss";NA;249;0
"Upgrade";"WarpGateResearch";NA;249;0
"Upgrade";"SprayProtoss";NA;249;0
"Upgrade";"SprayProtoss";NA;249;0
