"type";"unit_name";"on_building";"total_supply_lag";"supply"
"Unit";"Overlord";"Larva";14;0
"Building";"Hatchery";NA;17;0
"Building";"SpawningPool";NA;18;0
"Building";"Extractor";NA;19;0
"Unit";"Overlord";"Larva";22;0
"Unit";"Queen";"Hatchery";22;2
"Unit";"Zergling";"Larva";24;1
"Unit";"Zergling";"Larva";25;1
"Unit";"Zergling";"Larva";26;1
"Unit";"Zergling";"Larva";27;1
"Unit";"Queen";"Hatchery";28;2
"Unit";"Zergling";"Larva";30;1
"Unit";"Zergling";"Larva";31;1
"Unit";"Queen";"Hatchery";37;2
"Unit";"Overlord";"Larva";41;0
"Building";"EvolutionChamber";NA;42;0
"Unit";"Zergling";"Larva";43;1
"Unit";"Zergling";"Larva";44;1
"Unit";"Zergling";"Larva";45;1
"Unit";"Zergling";"Larva";46;1
"Unit";"Zergling";"Larva";47;1
"Unit";"Zergling";"Larva";48;1
"Unit";"Zergling";"Larva";49;1
"Unit";"Zergling";"Larva";50;1
"Unit";"Zergling";"Larva";51;1
"Unit";"Zergling";"Larva";52;1
"Unit";"Zergling";"Larva";53;1
"Unit";"Zergling";"Larva";54;1
"Unit";"Zergling";"Larva";55;1
"Unit";"Zergling";"Larva";56;1
"Building";"RoachWarren";NA;57;0
"Unit";"Zergling";"Larva";57;1
"Unit";"Zergling";"Larva";58;1
"Unit";"Zergling";"Larva";59;1
"Unit";"Zergling";"Larva";60;1
"Unit";"Zergling";"Larva";61;1
"Unit";"Zergling";"Larva";62;1
"Unit";"Queen";"Hatchery";63;2
"Unit";"Overlord";"Larva";69;0
"Unit";"Overlord";"Larva";69;0
"Unit";"Queen";"Hatchery";74;2
"Building";"Extractor";NA;80;0
"Building";"Extractor";NA;80;0
"Building";"Hatchery";NA;82;0
"Unit";"Roach";"Larva";86;2
"Unit";"Roach";"Larva";88;2
"Unit";"Roach";"Larva";90;2
"Unit";"Roach";"Larva";92;2
"Unit";"Roach";"Larva";94;2
"Unit";"Overlord";"Larva";97;0
"Unit";"Queen";"Hatchery";97;2
"Unit";"Overlord";"Larva";100;0
"Upgrade";"GlialReconstitution";"RoachWarren";100;0
"Unit";"Roach";"Larva";101;2
"Unit";"Roach";"Larva";103;2
"Unit";"Roach";"Larva";105;2
"Unit";"Overlord";"Larva";107;0
"Unit";"Overlord";"Larva";107;0
"Unit";"Roach";"Larva";108;2
"Unit";"Roach";"Larva";110;2
"Unit";"Roach";"Larva";112;2
"Unit";"Overlord";"Larva";121;0
"Building";"Extractor";NA;121;0
"Unit";"Roach";"Larva";123;2
"Building";"HydraliskDen";NA;134;0
"Building";"Extractor";NA;137;0
"Building";"Extractor";NA;139;0
"Unit";"Overlord";"Larva";139;0
"Unit";"Roach";"Larva";141;2
"Unit";"Roach";"Larva";143;2
"Unit";"Roach";"Larva";145;2
"Unit";"Roach";"Larva";147;2
"Unit";"Overlord";"Larva";149;0
"Building";"Hatchery";NA;149;0
"Unit";"Roach";"Larva";149;2
"Unit";"Overlord";"Larva";151;0
"Unit";"Roach";"Larva";151;2
"Unit";"Roach";"Larva";153;2
"Unit";"Overlord";"Larva";155;0
"Unit";"Overlord";"Larva";155;0
"Unit";"Overlord";"Larva";155;0
"Unit";"Roach";"Larva";155;2
"Unit";"Hydralisk";"Larva";157;2
"Unit";"Hydralisk";"Larva";159;2
"Unit";"Hydralisk";"Larva";161;2
"Unit";"Hydralisk";"Larva";163;2
"Unit";"Hydralisk";"Larva";165;2
"Unit";"Hydralisk";"Larva";167;2
"Unit";"Hydralisk";"Larva";169;2
"Unit";"Hydralisk";"Larva";171;2
"Building";"SporeCrawler";NA;173;0
"Unit";"Hydralisk";"Larva";173;2
"Unit";"Hydralisk";"Larva";175;2
"Unit";"Hydralisk";"Larva";177;2
"Unit";"Hydralisk";"Larva";179;2
"Building";"SporeCrawler";NA;181;0
"Unit";"Hydralisk";"Larva";181;2
"Unit";"Hydralisk";"Larva";183;2
"Unit";"Overlord";"Larva";185;0
"Unit";"Overlord";"Larva";185;0
"Unit";"Hydralisk";"Larva";187;2
"Unit";"Hydralisk";"Larva";189;2
"Unit";"Hydralisk";"Larva";191;2
"Unit";"Hydralisk";"Larva";195;2
"Unit";"Hydralisk";"Larva";197;2
"Building";"SporeCrawler";NA;199;0
"Unit";"Roach";"Larva";199;2
"Unit";"Roach";"Larva";201;2
"Unit";"Roach";"Larva";203;2
"Unit";"Roach";"Larva";205;2
"Unit";"Roach";"Larva";207;2
"Unit";"Roach";"Larva";209;2
"Unit";"Roach";"Larva";211;2
"Unit";"Roach";"Larva";213;2
"Unit";"Roach";"Larva";215;2
"Unit";"Overlord";"Larva";217;0
"Unit";"Overlord";"Larva";217;0
"Unit";"Roach";"Larva";217;2
"Unit";"Roach";"Larva";219;2
"Unit";"Roach";"Larva";221;2
"Unit";"Roach";"Larva";223;2
"Unit";"Roach";"Larva";225;2
"Unit";"Roach";"Larva";227;2
"Unit";"Roach";"Larva";229;2
"Unit";"Hydralisk";"Larva";231;2
"Unit";"Hydralisk";"Larva";233;2
"Unit";"Roach";"Larva";235;2
"Unit";"Roach";"Larva";237;2
"Unit";"Hydralisk";"Larva";239;2
"Unit";"Hydralisk";"Larva";241;2
"Unit";"Hydralisk";"Larva";245;2
"Unit";"Hydralisk";"Larva";247;2
"Unit";"Hydralisk";"Larva";249;2
"Unit";"Hydralisk";"Larva";251;2
"Unit";"Hydralisk";"Larva";253;2
"Unit";"Hydralisk";"Larva";255;2
"Unit";"Hydralisk";"Larva";257;2
"Building";"Hatchery";NA;259;0
"Building";"Extractor";NA;263;0
"Unit";"Overlord";"Larva";263;0
"Unit";"Overlord";"Larva";263;0
"Unit";"Overlord";"Larva";263;0
"Unit";"Overlord";"Larva";263;0
"Unit";"Overlord";"Larva";263;0
"Unit";"Overlord";"Larva";263;0
"Unit";"Hydralisk";"Larva";263;2
"Unit";"Hydralisk";"Larva";265;2
"Unit";"Roach";"Larva";267;2
"Unit";"Hydralisk";"Larva";269;2
"Unit";"Hydralisk";"Larva";271;2
"Unit";"Hydralisk";"Larva";273;2
"Unit";"Hydralisk";"Larva";275;2
"Unit";"Hydralisk";"Larva";277;2
"Unit";"Hydralisk";"Larva";279;2
"Unit";"Roach";"Larva";281;2
"Unit";"Roach";"Larva";283;2
"Unit";"Roach";"Larva";285;2
"Unit";"Roach";"Larva";287;2
"Unit";"Roach";"Larva";289;2
"Unit";"Roach";"Larva";291;2
"Unit";"Roach";"Larva";293;2
"Unit";"Roach";"Larva";295;2
"Unit";"Roach";"Larva";297;2
"Unit";"Roach";"Larva";299;2
"Unit";"Roach";"Larva";301;2
"Unit";"Roach";"Larva";303;2
"Unit";"Roach";"Larva";305;2
"Unit";"Roach";"Larva";307;2
"Unit";"Roach";"Larva";309;2
"Unit";"Roach";"Larva";311;2
"Unit";"Roach";"Larva";313;2
"Unit";"Roach";"Larva";315;2
"Unit";"Roach";"Larva";317;2
"Unit";"Roach";"Larva";319;2
"Unit";"Roach";"Larva";322;2
"Unit";"Roach";"Larva";324;2
"Unit";"Hydralisk";"Larva";326;2
"Unit";"Hydralisk";"Larva";328;2
"Unit";"Hydralisk";"Larva";330;2
"Unit";"Queen";"Hatchery";333;2
"Unit";"Hydralisk";"Larva";335;2
"Unit";"Hydralisk";"Larva";337;2
"Unit";"Roach";"Larva";339;2
"Upgrade";"SprayZerg";NA;341;0
"Upgrade";"SprayZerg";NA;341;0
"Upgrade";"zerglingmovementspeed";NA;341;0
"Upgrade";"SprayZerg";NA;341;0
"Upgrade";"ZergMissileWeaponsLevel1";NA;341;0
"Upgrade";"SprayZerg";NA;341;0
"Upgrade";"SprayZerg";NA;341;0
"Upgrade";"overlordspeed";NA;341;0
"Upgrade";"ZergMissileWeaponsLevel2";NA;341;0
"Upgrade";"SprayZerg";NA;341;0
"Upgrade";"EvolveMuscularAugments";NA;341;0
"Upgrade";"SprayZerg";NA;341;0
"Upgrade";"ZergGroundArmorsLevel1";NA;341;0
"Upgrade";"SprayZerg";NA;341;0
