"type";"unit_name";"on_building";"total_supply_lag";"supply"
"Unit";"Overlord";"Larva";13;0
"Building";"SpawningPool";NA;17;0
"Building";"Hatchery";NA;18;0
"Building";"Extractor";NA;20;0
"Unit";"Queen";"Hatchery";20;2
"Unit";"Zergling";"Larva";22;1
"Unit";"Zergling";"Larva";23;1
"Unit";"Zergling";"Larva";24;1
"Unit";"Zergling";"Larva";25;1
"Unit";"Overlord";"Larva";26;0
"Unit";"Zergling";"Larva";26;1
"Unit";"Zergling";"Larva";27;1
"Unit";"Queen";"Hatchery";29;2
"Unit";"Queen";"Hatchery";32;2
"Building";"CreepTumorQueen";NA;39;0
"Building";"BanelingNest";NA;40;0
"Unit";"Overlord";"Larva";40;0
"Unit";"Zergling";"Larva";41;1
"Unit";"Zergling";"Larva";42;1
"Unit";"Zergling";"Larva";43;1
"Unit";"Zergling";"Larva";44;1
"Building";"CreepTumor";NA;45;0
"Unit";"Zergling";"Larva";45;1
"Unit";"Zergling";"Larva";46;1
"Unit";"Zergling";"Larva";47;1
"Unit";"Zergling";"Larva";48;1
"Unit";"Zergling";"Larva";49;1
"Unit";"Zergling";"Larva";50;1
"Unit";"Zergling";"Larva";51;1
"Unit";"Zergling";"Larva";52;1
"Unit";"Zergling";"Larva";53;1
"Unit";"Zergling";"Larva";54;1
"Unit";"Zergling";"Larva";55;1
"Unit";"Zergling";"Larva";56;1
"Unit";"Overlord";"Larva";57;0
"Building";"CreepTumor";NA;57;0
"Unit";"Overlord";"Larva";57;0
"Building";"CreepTumorQueen";NA;57;0
"Building";"Hatchery";NA;57;0
"Unit";"Baneling";"Zergling";57;0
"Unit";"Baneling";"Zergling";57;0
"Unit";"Baneling";"Zergling";60;0
"Unit";"Baneling";"Zergling";60;0
"Unit";"Zergling";"Larva";63;1
"Unit";"Zergling";"Larva";64;1
"Unit";"Zergling";"Larva";65;1
"Unit";"Zergling";"Larva";66;1
"Unit";"Zergling";"Larva";67;1
"Unit";"Zergling";"Larva";68;1
"Unit";"Zergling";"Larva";69;1
"Unit";"Zergling";"Larva";70;1
"Unit";"Zergling";"Larva";71;1
"Unit";"Zergling";"Larva";72;1
"Unit";"Zergling";"Larva";73;1
"Unit";"Zergling";"Larva";74;1
"Building";"CreepTumor";NA;77;0
"Building";"CreepTumor";NA;77;0
"Unit";"Baneling";"Zergling";80;0
"Unit";"Baneling";"Zergling";80;0
"Unit";"Baneling";"Zergling";80;0
"Building";"Extractor";NA;81;0
"Building";"Extractor";NA;81;0
"Unit";"Overlord";"Larva";81;0
"Building";"EvolutionChamber";NA;82;0
"Building";"RoachWarren";NA;82;0
"Unit";"Zergling";"Larva";85;1
"Unit";"Zergling";"Larva";86;1
"Unit";"Zergling";"Larva";87;1
"Unit";"Zergling";"Larva";88;1
"Unit";"Zergling";"Larva";89;1
"Unit";"Zergling";"Larva";90;1
"Unit";"Zergling";"Larva";91;1
"Unit";"Zergling";"Larva";92;1
"Unit";"Zergling";"Larva";93;1
"Unit";"Zergling";"Larva";94;1
"Unit";"Zergling";"Larva";95;1
"Unit";"Zergling";"Larva";96;1
"Unit";"Zergling";"Larva";97;1
"Unit";"Zergling";"Larva";98;1
"Unit";"Zergling";"Larva";99;1
"Unit";"Zergling";"Larva";100;1
"Unit";"Zergling";"Larva";101;1
"Unit";"Zergling";"Larva";102;1
"Unit";"Zergling";"Larva";103;1
"Unit";"Zergling";"Larva";104;1
"Unit";"Zergling";"Larva";105;1
"Unit";"Zergling";"Larva";106;1
"Unit";"Zergling";"Larva";107;1
"Unit";"Zergling";"Larva";108;1
"Unit";"Zergling";"Larva";109;1
"Unit";"Zergling";"Larva";110;1
"Unit";"Overlord";"Larva";116;0
"Unit";"Overlord";"Larva";116;0
"Building";"Extractor";NA;122;0
"Unit";"Roach";"Larva";124;2
"Unit";"Roach";"Larva";126;2
"Building";"CreepTumor";NA;128;0
"Building";"CreepTumor";NA;128;0
"Unit";"Roach";"Larva";128;2
"Unit";"Roach";"Larva";130;2
"Unit";"Roach";"Larva";132;2
"Unit";"Roach";"Larva";134;2
"Unit";"Overlord";"Larva";139;0
"Building";"CreepTumorQueen";NA;139;0
"Unit";"Roach";"Larva";139;2
"Unit";"Roach";"Larva";141;2
"Unit";"Roach";"Larva";143;2
"Unit";"Overlord";"Larva";145;0
"Unit";"Queen";"Hatchery";146;2
"Building";"CreepTumor";NA;153;0
"Unit";"Overlord";"Larva";153;0
"Building";"CreepTumor";NA;153;0
"Building";"CreepTumor";NA;153;0
"Unit";"Overlord";"Larva";153;0
"Unit";"Roach";"Larva";153;2
"Unit";"Roach";"Larva";155;2
"Unit";"Roach";"Larva";157;2
"Upgrade";"GlialReconstitution";"RoachWarren";159;0
"Unit";"Overlord";"Larva";159;0
"Unit";"Roach";"Larva";159;2
"Unit";"Roach";"Larva";161;2
"Unit";"Roach";"Larva";163;2
"Unit";"Roach";"Larva";165;2
"Unit";"Roach";"Larva";167;2
"Unit";"Roach";"Larva";169;2
"Unit";"Overlord";"Larva";171;0
"Unit";"Overlord";"Larva";171;0
"Unit";"Roach";"Larva";171;2
"Unit";"Roach";"Larva";173;2
"Unit";"Roach";"Larva";175;2
"Unit";"Roach";"Larva";177;2
"Building";"CreepTumor";NA;179;0
"Unit";"Roach";"Larva";179;2
"Unit";"Roach";"Larva";181;2
"Unit";"Roach";"Larva";183;2
"Unit";"Overlord";"Larva";185;0
"Unit";"Overlord";"Larva";185;0
"Building";"Extractor";NA;185;0
"Building";"CreepTumor";NA;185;0
"Building";"CreepTumor";NA;185;0
"Unit";"Roach";"Larva";185;2
"Unit";"Roach";"Larva";187;2
"Unit";"Roach";"Larva";189;2
"Unit";"Zergling";"Larva";191;1
"Unit";"Zergling";"Larva";192;1
"Unit";"Zergling";"Larva";193;1
"Unit";"Zergling";"Larva";194;1
"Unit";"Zergling";"Larva";195;1
"Unit";"Zergling";"Larva";196;1
"Unit";"Zergling";"Larva";197;1
"Unit";"Zergling";"Larva";198;1
"Unit";"Zergling";"Larva";199;1
"Unit";"Zergling";"Larva";200;1
"Unit";"Zergling";"Larva";201;1
"Unit";"Zergling";"Larva";202;1
"Unit";"Roach";"Larva";203;2
"Unit";"Roach";"Larva";205;2
"Unit";"Overlord";"Larva";207;0
"Upgrade";"SprayZerg";NA;207;0
"Upgrade";"SprayZerg";NA;207;0
"Upgrade";"zerglingmovementspeed";NA;207;0
"Upgrade";"SprayZerg";NA;207;0
"Upgrade";"SprayZerg";NA;207;0
"Upgrade";"ZergMissileWeaponsLevel1";NA;207;0
