"type";"unit_name";"on_building";"total_supply_lag";"supply"
"Building";"Extractor";NA;13;0
"Building";"SpawningPool";NA;13;0
"Unit";"Overlord";"Larva";16;0
"Unit";"Queen";"Hatchery";16;2
"Unit";"Zergling";"Larva";18;1
"Unit";"Zergling";"Larva";19;1
"Unit";"Zergling";"Larva";20;1
"Unit";"Zergling";"Larva";21;1
"Unit";"Zergling";"Larva";22;1
"Unit";"Zergling";"Larva";23;1
"Unit";"Zergling";"Larva";24;1
"Unit";"Zergling";"Larva";25;1
"Unit";"Zergling";"Larva";26;1
"Unit";"Zergling";"Larva";27;1
"Building";"BanelingNest";NA;28;0
"Unit";"Zergling";"Larva";28;1
"Unit";"Zergling";"Larva";29;1
"Unit";"Overlord";"Larva";30;0
"Unit";"Zergling";"Larva";30;1
"Unit";"Zergling";"Larva";31;1
"Unit";"Zergling";"Larva";32;1
"Unit";"Zergling";"Larva";33;1
"Unit";"Zergling";"Larva";34;1
"Unit";"Zergling";"Larva";35;1
"Unit";"Zergling";"Larva";36;1
"Unit";"Zergling";"Larva";37;1
"Unit";"Zergling";"Larva";38;1
"Unit";"Zergling";"Larva";39;1
"Unit";"Baneling";"Zergling";40;0
"Unit";"Baneling";"Zergling";40;0
"Unit";"Zergling";"Larva";40;1
"Unit";"Zergling";"Larva";41;1
"Unit";"Zergling";"Larva";42;1
"Unit";"Zergling";"Larva";43;1
"Unit";"Zergling";"Larva";44;1
"Unit";"Zergling";"Larva";45;1
"Unit";"Zergling";"Larva";46;1
"Unit";"Zergling";"Larva";47;1
"Unit";"Zergling";"Larva";48;1
"Unit";"Zergling";"Larva";49;1
"Unit";"Baneling";"Zergling";50;0
"Unit";"Baneling";"Zergling";50;0
"Unit";"Zergling";"Larva";50;1
"Unit";"Zergling";"Larva";51;1
"Unit";"Baneling";"Zergling";52;0
"Unit";"Baneling";"Zergling";52;0
"Unit";"Baneling";"Zergling";52;0
"Unit";"Overlord";"Larva";52;0
"Unit";"Zergling";"Larva";52;1
"Unit";"Zergling";"Larva";53;1
"Unit";"Zergling";"Larva";54;1
"Unit";"Zergling";"Larva";55;1
"Unit";"Baneling";"Zergling";56;0
"Unit";"Baneling";"Zergling";56;0
"Unit";"Zergling";"Larva";56;1
"Unit";"Zergling";"Larva";57;1
"Unit";"Zergling";"Larva";61;1
"Unit";"Zergling";"Larva";62;1
"Building";"Hatchery";NA;63;0
"Unit";"Baneling";"Zergling";63;0
"Unit";"Baneling";"Zergling";63;0
"Unit";"Zergling";"Larva";63;1
"Unit";"Zergling";"Larva";64;1
"Unit";"Zergling";"Larva";65;1
"Unit";"Zergling";"Larva";66;1
"Unit";"Zergling";"Larva";67;1
"Unit";"Zergling";"Larva";68;1
"Unit";"Zergling";"Larva";69;1
"Unit";"Zergling";"Larva";70;1
"Unit";"Zergling";"Larva";71;1
"Unit";"Zergling";"Larva";72;1
"Unit";"Zergling";"Larva";73;1
"Unit";"Zergling";"Larva";74;1
"Unit";"Baneling";"Zergling";75;0
"Unit";"Baneling";"Zergling";75;0
"Unit";"Zergling";"Larva";75;1
"Unit";"Zergling";"Larva";76;1
"Unit";"Zergling";"Larva";77;1
"Unit";"Zergling";"Larva";78;1
"Unit";"Zergling";"Larva";79;1
"Unit";"Zergling";"Larva";80;1
"Unit";"Queen";"Hatchery";81;2
"Unit";"Baneling";"Zergling";83;0
"Unit";"Baneling";"Zergling";96;0
"Unit";"Baneling";"Zergling";96;0
"Unit";"Baneling";"Zergling";96;0
"Unit";"Baneling";"Zergling";96;0
"Unit";"Zergling";"Larva";96;1
"Unit";"Zergling";"Larva";97;1
"Unit";"Zergling";"Larva";98;1
"Unit";"Zergling";"Larva";99;1
"Unit";"Zergling";"Larva";100;1
"Unit";"Zergling";"Larva";101;1
"Unit";"Zergling";"Larva";102;1
"Unit";"Zergling";"Larva";103;1
"Building";"RoachWarren";NA;104;0
"Unit";"Zergling";"Larva";105;1
"Unit";"Zergling";"Larva";106;1
"Unit";"Zergling";"Larva";107;1
"Unit";"Zergling";"Larva";108;1
"Unit";"Zergling";"Larva";109;1
"Unit";"Zergling";"Larva";110;1
"Unit";"Zergling";"Larva";111;1
"Unit";"Zergling";"Larva";112;1
"Unit";"Zergling";"Larva";113;1
"Unit";"Zergling";"Larva";114;1
"Unit";"Overlord";"Larva";115;0
"Unit";"Overlord";"Larva";115;0
"Unit";"Overlord";"Larva";115;0
"Building";"Hatchery";NA;115;0
"Unit";"Roach";"Larva";115;2
"Unit";"Roach";"Larva";117;2
"Unit";"Roach";"Larva";119;2
"Unit";"Roach";"Larva";121;2
"Unit";"Roach";"Larva";123;2
"Unit";"Roach";"Larva";125;2
"Unit";"Roach";"Larva";127;2
"Unit";"Roach";"Larva";129;2
"Unit";"Roach";"Larva";131;2
"Unit";"Roach";"Larva";133;2
"Unit";"Overlord";"Larva";135;0
"Unit";"Roach";"Larva";135;2
"Unit";"Zergling";"Larva";137;1
"Unit";"Zergling";"Larva";138;1
"Unit";"Zergling";"Larva";139;1
"Unit";"Zergling";"Larva";140;1
"Unit";"Zergling";"Larva";141;1
"Unit";"Zergling";"Larva";142;1
"Unit";"Zergling";"Larva";143;1
"Unit";"Zergling";"Larva";144;1
"Unit";"Zergling";"Larva";145;1
"Unit";"Zergling";"Larva";146;1
"Unit";"Zergling";"Larva";147;1
"Unit";"Zergling";"Larva";148;1
"Unit";"Zergling";"Larva";149;1
"Unit";"Zergling";"Larva";150;1
"Unit";"Zergling";"Larva";151;1
"Unit";"Zergling";"Larva";152;1
"Unit";"Zergling";"Larva";153;1
"Unit";"Zergling";"Larva";154;1
"Unit";"Baneling";"Zergling";155;0
"Unit";"Baneling";"Zergling";155;0
"Unit";"Zergling";"Larva";155;1
"Unit";"Zergling";"Larva";156;1
"Unit";"Zergling";"Larva";157;1
"Unit";"Zergling";"Larva";158;1
"Unit";"Overlord";"Larva";159;0
"Unit";"Zergling";"Larva";159;1
"Unit";"Zergling";"Larva";160;1
"Unit";"Zergling";"Larva";161;1
"Unit";"Zergling";"Larva";162;1
"Building";"EvolutionChamber";NA;164;0
"Unit";"Zergling";"Larva";164;1
"Unit";"Zergling";"Larva";165;1
"Unit";"Zergling";"Larva";166;1
"Unit";"Zergling";"Larva";167;1
"Unit";"Zergling";"Larva";168;1
"Unit";"Zergling";"Larva";169;1
"Unit";"Zergling";"Larva";170;1
"Unit";"Zergling";"Larva";171;1
"Unit";"Zergling";"Larva";172;1
"Unit";"Zergling";"Larva";173;1
"Unit";"Zergling";"Larva";174;1
"Unit";"Zergling";"Larva";175;1
"Unit";"Zergling";"Larva";176;1
"Unit";"Zergling";"Larva";177;1
"Unit";"Zergling";"Larva";178;1
"Unit";"Zergling";"Larva";179;1
"Unit";"Zergling";"Larva";180;1
"Unit";"Zergling";"Larva";181;1
"Unit";"Zergling";"Larva";182;1
"Unit";"Zergling";"Larva";183;1
"Unit";"Zergling";"Larva";184;1
"Unit";"Zergling";"Larva";185;1
"Unit";"Queen";"Hatchery";194;2
"Unit";"Roach";"Larva";196;2
"Building";"Extractor";NA;198;0
"Unit";"Roach";"Larva";198;2
"Unit";"Roach";"Larva";200;2
"Unit";"Roach";"Larva";202;2
"Unit";"Roach";"Larva";204;2
"Building";"Extractor";NA;210;0
"Unit";"Overlord";"Larva";234;0
"Building";"Extractor";NA;234;0
"Unit";"Overlord";"Larva";234;0
"Unit";"Overlord";"Larva";234;0
"Unit";"Roach";"Larva";234;2
"Unit";"Overlord";"Larva";236;0
"Unit";"Roach";"Larva";236;2
"Unit";"Roach";"Larva";238;2
"Unit";"Roach";"Larva";240;2
"Unit";"Roach";"Larva";242;2
"Unit";"Roach";"Larva";244;2
"Building";"SpineCrawler";NA;246;0
"Unit";"Roach";"Larva";246;2
"Unit";"Roach";"Larva";248;2
"Unit";"Roach";"Larva";250;2
"Unit";"Roach";"Larva";252;2
"Unit";"Roach";"Larva";254;2
"Unit";"Roach";"Larva";256;2
"Unit";"Roach";"Larva";258;2
"Unit";"Roach";"Larva";260;2
"Unit";"Roach";"Larva";262;2
"Unit";"Roach";"Larva";264;2
"Unit";"Roach";"Larva";266;2
"Unit";"Overlord";"Larva";268;0
"Unit";"Overlord";"Larva";268;0
"Unit";"Overlord";"Larva";268;0
"Unit";"Overlord";"Larva";268;0
"Unit";"Roach";"Larva";268;2
"Unit";"Roach";"Larva";270;2
"Unit";"Overlord";"Larva";272;0
"Unit";"Roach";"Larva";272;2
"Unit";"Roach";"Larva";274;2
"Unit";"Zergling";"Larva";276;1
"Unit";"Zergling";"Larva";277;1
"Unit";"Zergling";"Larva";278;1
"Unit";"Zergling";"Larva";279;1
"Unit";"Zergling";"Larva";280;1
"Unit";"Zergling";"Larva";281;1
"Unit";"Zergling";"Larva";282;1
"Unit";"Zergling";"Larva";283;1
"Unit";"Zergling";"Larva";284;1
"Unit";"Zergling";"Larva";285;1
"Unit";"Roach";"Larva";286;2
"Unit";"Roach";"Larva";288;2
"Unit";"Roach";"Larva";290;2
"Unit";"Roach";"Larva";292;2
"Upgrade";"zerglingmovementspeed";NA;294;0
"Upgrade";"SprayZerg";NA;294;0
"Upgrade";"SprayZerg";NA;294;0
"Upgrade";"SprayZerg";NA;294;0
"Upgrade";"SprayZerg";NA;294;0
"Upgrade";"ZergMissileWeaponsLevel1";NA;294;0
