"type";"unit_name";"on_building";"total_supply_lag";"supply"
"Unit";"Overlord";"Larva";13;0
"Building";"Extractor";NA;17;0
"Building";"SpawningPool";NA;18;0
"Building";"Hatchery";NA;20;0
"Unit";"Zergling";"Larva";21;1
"Unit";"Zergling";"Larva";22;1
"Unit";"Queen";"Hatchery";23;2
"Unit";"Overlord";"Larva";25;0
"Building";"BanelingNest";NA;26;0
"Unit";"Zergling";"Larva";26;1
"Unit";"Zergling";"Larva";27;1
"Unit";"Zergling";"Larva";28;1
"Unit";"Zergling";"Larva";29;1
"Unit";"Zergling";"Larva";30;1
"Unit";"Zergling";"Larva";31;1
"Building";"Hatchery";NA;32;0
"Unit";"Zergling";"Larva";32;1
"Unit";"Zergling";"Larva";33;1
"Unit";"Zergling";"Larva";34;1
"Unit";"Zergling";"Larva";35;1
"Unit";"Zergling";"Larva";36;1
"Unit";"Zergling";"Larva";37;1
"Unit";"Zergling";"Larva";38;1
"Unit";"Zergling";"Larva";39;1
"Unit";"Zergling";"Larva";40;1
"Unit";"Zergling";"Larva";41;1
"Unit";"Baneling";"Zergling";42;0
"Unit";"Baneling";"Zergling";42;0
"Unit";"Zergling";"Larva";42;1
"Unit";"Zergling";"Larva";43;1
"Unit";"Zergling";"Larva";44;1
"Unit";"Zergling";"Larva";45;1
"Unit";"Overlord";"Larva";46;0
"Unit";"Zergling";"Larva";46;1
"Unit";"Zergling";"Larva";47;1
"Unit";"Zergling";"Larva";52;1
"Unit";"Zergling";"Larva";53;1
"Unit";"Baneling";"Zergling";55;0
"Unit";"Baneling";"Zergling";55;0
"Unit";"Zergling";"Larva";55;1
"Unit";"Zergling";"Larva";56;1
"Unit";"Zergling";"Larva";57;1
"Unit";"Zergling";"Larva";58;1
"Unit";"Zergling";"Larva";59;1
"Unit";"Zergling";"Larva";60;1
"Unit";"Zergling";"Larva";62;1
"Unit";"Zergling";"Larva";63;1
"Unit";"Zergling";"Larva";64;1
"Unit";"Zergling";"Larva";65;1
"Unit";"Zergling";"Larva";70;1
"Unit";"Zergling";"Larva";71;1
"Unit";"Zergling";"Larva";72;1
"Unit";"Zergling";"Larva";73;1
"Unit";"Zergling";"Larva";74;1
"Unit";"Zergling";"Larva";75;1
"Unit";"Queen";"Hatchery";76;2
"Unit";"Baneling";"Zergling";78;0
"Unit";"Baneling";"Zergling";78;0
"Unit";"Queen";"Hatchery";78;2
"Unit";"Baneling";"Zergling";80;0
"Unit";"Zergling";"Larva";83;1
"Unit";"Zergling";"Larva";84;1
"Unit";"Overlord";"Larva";85;0
"Unit";"Baneling";"Zergling";85;0
"Unit";"Overlord";"Larva";86;0
"Building";"RoachWarren";NA;92;0
"Unit";"Overlord";"Larva";92;0
"Unit";"Zergling";"Larva";92;1
"Unit";"Zergling";"Larva";93;1
"Unit";"Zergling";"Larva";94;1
"Unit";"Zergling";"Larva";95;1
"Building";"Extractor";NA;103;0
"Building";"Extractor";NA;103;0
"Unit";"Baneling";"Zergling";103;0
"Unit";"Baneling";"Zergling";103;0
"Unit";"Overlord";"Larva";103;0
"Unit";"Overlord";"Larva";105;0
"Building";"EvolutionChamber";NA;106;0
"Unit";"Overlord";"Larva";110;0
"Unit";"Roach";"Larva";110;2
"Unit";"Roach";"Larva";112;2
"Unit";"Roach";"Larva";114;2
"Unit";"Roach";"Larva";116;2
"Unit";"Roach";"Larva";118;2
"Unit";"Roach";"Larva";120;2
"Unit";"Roach";"Larva";122;2
"Unit";"Roach";"Larva";124;2
"Unit";"Roach";"Larva";126;2
"Unit";"Roach";"Larva";128;2
"Unit";"Overlord";"Larva";130;0
"Unit";"Overlord";"Larva";138;0
"Unit";"Overlord";"Larva";142;0
"Building";"Extractor";NA;142;0
"Building";"Extractor";NA;142;0
"Unit";"Roach";"Larva";144;2
"Unit";"Roach";"Larva";146;2
"Upgrade";"GlialReconstitution";"RoachWarren";148;0
"Unit";"Roach";"Larva";151;2
"Unit";"Roach";"Larva";153;2
"Unit";"Roach";"Larva";155;2
"Unit";"Roach";"Larva";157;2
"Unit";"Roach";"Larva";159;2
"Unit";"Roach";"Larva";161;2
"Unit";"Roach";"Larva";163;2
"Unit";"Roach";"Larva";165;2
"Unit";"Roach";"Larva";167;2
"Unit";"Roach";"Larva";169;2
"Unit";"Roach";"Larva";171;2
"Unit";"Roach";"Larva";173;2
"Unit";"Overlord";"Larva";175;0
"Unit";"Overlord";"Larva";175;0
"Unit";"Overlord";"Larva";175;0
"Unit";"Overlord";"Larva";175;0
"Unit";"Overlord";"Larva";175;0
"Unit";"Roach";"Larva";175;2
"Unit";"Roach";"Larva";177;2
"Unit";"Roach";"Larva";179;2
"Unit";"Roach";"Larva";181;2
"Unit";"Roach";"Larva";183;2
"Unit";"Roach";"Larva";185;2
"Unit";"Roach";"Larva";187;2
"Unit";"Roach";"Larva";189;2
"Unit";"Roach";"Larva";191;2
"Unit";"Overlord";"Larva";193;0
"Unit";"Roach";"Larva";193;2
"Unit";"Roach";"Larva";195;2
"Unit";"Roach";"Larva";197;2
"Building";"Hatchery";NA;199;0
"Unit";"Overlord";"Larva";199;0
"Building";"Extractor";NA;199;0
"Unit";"Overlord";"Larva";199;0
"Unit";"Roach";"Larva";199;2
"Unit";"Roach";"Larva";201;2
"Unit";"Roach";"Larva";203;2
"Unit";"Overlord";"Larva";205;0
"Unit";"Overlord";"Larva";205;0
"Unit";"Roach";"Larva";205;2
"Unit";"Roach";"Larva";207;2
"Unit";"Roach";"Larva";209;2
"Unit";"Overlord";"Larva";211;0
"Unit";"Overlord";"Larva";211;0
"Unit";"Roach";"Larva";211;2
"Unit";"Roach";"Larva";213;2
"Unit";"Roach";"Larva";215;2
"Unit";"Roach";"Larva";217;2
"Unit";"Roach";"Larva";219;2
"Unit";"Roach";"Larva";221;2
"Unit";"Roach";"Larva";223;2
"Unit";"Roach";"Larva";225;2
"Unit";"Roach";"Larva";227;2
"Unit";"Roach";"Larva";229;2
"Unit";"Overlord";"Larva";231;0
"Unit";"Roach";"Larva";231;2
"Unit";"Roach";"Larva";233;2
"Unit";"Roach";"Larva";235;2
"Unit";"Roach";"Larva";237;2
"Unit";"Roach";"Larva";239;2
"Unit";"Roach";"Larva";241;2
"Unit";"Roach";"Larva";243;2
"Unit";"Roach";"Larva";245;2
"Unit";"Roach";"Larva";247;2
"Unit";"Roach";"Larva";249;2
"Unit";"Roach";"Larva";251;2
"Unit";"Roach";"Larva";253;2
"Unit";"Roach";"Larva";255;2
"Unit";"Roach";"Larva";257;2
"Unit";"Roach";"Larva";259;2
"Unit";"Roach";"Larva";261;2
"Unit";"Roach";"Larva";263;2
"Unit";"Roach";"Larva";265;2
"Unit";"Roach";"Larva";267;2
"Unit";"Roach";"Larva";269;2
"Unit";"Roach";"Larva";271;2
"Unit";"Roach";"Larva";273;2
"Unit";"Roach";"Larva";275;2
"Unit";"Roach";"Larva";277;2
"Unit";"Roach";"Larva";279;2
"Unit";"Roach";"Larva";281;2
"Unit";"Roach";"Larva";283;2
"Unit";"Roach";"Larva";285;2
"Unit";"Roach";"Larva";287;2
"Unit";"Roach";"Larva";289;2
"Unit";"Roach";"Larva";291;2
"Unit";"Roach";"Larva";293;2
"Unit";"Roach";"Larva";295;2
"Unit";"Roach";"Larva";297;2
"Unit";"Roach";"Larva";299;2
"Unit";"Roach";"Larva";301;2
"Unit";"Roach";"Larva";303;2
"Unit";"Roach";"Larva";305;2
"Unit";"Queen";"Hatchery";307;2
"Unit";"Roach";"Larva";309;2
"Unit";"Roach";"Larva";311;2
"Unit";"Overlord";"Larva";313;0
"Unit";"Roach";"Larva";313;2
"Unit";"Roach";"Larva";315;2
"Unit";"Roach";"Larva";317;2
"Unit";"Roach";"Larva";319;2
"Unit";"Roach";"Larva";321;2
"Unit";"Overlord";"Larva";323;0
"Unit";"Roach";"Larva";323;2
"Unit";"Roach";"Larva";325;2
"Unit";"Roach";"Larva";327;2
"Unit";"Roach";"Larva";329;2
"Unit";"Roach";"Larva";331;2
"Unit";"Roach";"Larva";333;2
"Unit";"Overlord";"Larva";335;0
"Unit";"Roach";"Larva";335;2
"Unit";"Roach";"Larva";337;2
"Unit";"Roach";"Larva";339;2
"Unit";"Roach";"Larva";341;2
"Unit";"Roach";"Larva";343;2
"Unit";"Queen";"Hatchery";345;2
"Building";"InfestationPit";NA;347;0
"Unit";"Roach";"Larva";347;2
"Unit";"Roach";"Larva";349;2
"Unit";"Roach";"Larva";351;2
"Unit";"Roach";"Larva";353;2
"Unit";"Roach";"Larva";355;2
"Unit";"Roach";"Larva";357;2
"Unit";"Roach";"Larva";359;2
"Unit";"Roach";"Larva";361;2
"Unit";"Roach";"Larva";363;2
"Unit";"Roach";"Larva";365;2
"Unit";"Roach";"Larva";367;2
"Unit";"Roach";"Larva";369;2
"Unit";"Roach";"Larva";371;2
"Unit";"Roach";"Larva";373;2
"Unit";"Roach";"Larva";375;2
"Unit";"Roach";"Larva";377;2
"Unit";"Roach";"Larva";379;2
"Unit";"Roach";"Larva";381;2
"Unit";"Roach";"Larva";383;2
"Unit";"Roach";"Larva";385;2
"Unit";"Roach";"Larva";387;2
"Unit";"Roach";"Larva";389;2
"Unit";"Roach";"Larva";391;2
"Unit";"Roach";"Larva";393;2
"Unit";"Roach";"Larva";395;2
"Unit";"Roach";"Larva";399;2
"Building";"Extractor";NA;401;0
"Unit";"Roach";"Larva";401;2
"Unit";"Roach";"Larva";403;2
"Unit";"Roach";"Larva";405;2
"Unit";"Roach";"Larva";407;2
"Unit";"Roach";"Larva";409;2
"Unit";"Roach";"Larva";411;2
"Unit";"Roach";"Larva";413;2
"Unit";"Zergling";"Larva";415;1
"Unit";"Zergling";"Larva";416;1
"Unit";"Zergling";"Larva";417;1
"Unit";"Zergling";"Larva";418;1
"Unit";"Zergling";"Larva";419;1
"Unit";"Zergling";"Larva";420;1
"Unit";"Zergling";"Larva";421;1
"Unit";"Zergling";"Larva";422;1
"Unit";"Roach";"Larva";423;2
"Unit";"Roach";"Larva";425;2
"Unit";"Roach";"Larva";427;2
"Unit";"Roach";"Larva";429;2
"Unit";"Roach";"Larva";431;2
"Unit";"Zergling";"Larva";433;1
"Unit";"Zergling";"Larva";434;1
"Unit";"Zergling";"Larva";435;1
"Unit";"Zergling";"Larva";436;1
"Unit";"Zergling";"Larva";437;1
"Unit";"Zergling";"Larva";438;1
"Unit";"Zergling";"Larva";439;1
"Unit";"Zergling";"Larva";440;1
"Unit";"Zergling";"Larva";441;1
"Unit";"Zergling";"Larva";442;1
"Unit";"Zergling";"Larva";443;1
"Unit";"Zergling";"Larva";444;1
"Unit";"Zergling";"Larva";445;1
"Unit";"Zergling";"Larva";446;1
"Unit";"Roach";"Larva";447;2
"Unit";"Roach";"Larva";449;2
"Unit";"Roach";"Larva";451;2
"Unit";"Baneling";"Zergling";453;0
"Unit";"Baneling";"Zergling";453;0
"Unit";"Baneling";"Zergling";453;0
"Unit";"Baneling";"Zergling";453;0
"Unit";"Baneling";"Zergling";453;0
"Unit";"Baneling";"Zergling";453;0
"Unit";"Baneling";"Zergling";453;0
"Unit";"Baneling";"Zergling";453;0
"Upgrade";"SprayZerg";NA;453;0
"Upgrade";"SprayZerg";NA;453;0
"Upgrade";"SprayZerg";NA;453;0
"Upgrade";"zerglingmovementspeed";NA;453;0
"Upgrade";"SprayZerg";NA;453;0
"Upgrade";"SprayZerg";NA;453;0
"Upgrade";"ZergMissileWeaponsLevel1";NA;453;0
"Upgrade";"SprayZerg";NA;453;0
"Upgrade";"overlordspeed";NA;453;0
"Upgrade";"ZergMissileWeaponsLevel2";NA;453;0
"Upgrade";"ZergGroundArmorsLevel1";NA;453;0
"Upgrade";"CentrificalHooks";NA;453;0
