"type";"unit_name";"on_building";"total_supply";"supply"
"Building";"Pylon";NA;13;0
"Building";"Assimilator";NA;16;0
"Building";"Gateway";NA;15;0
"Building";"Assimilator";NA;21;0
"Building";"Pylon";NA;22;0
"Building";"CyberneticsCore";NA;21;0
"Unit";"Adept";"Gateway";22;2
"Building";"Nexus";NA;20;0
"Building";"TwilightCouncil";NA;23;0
"Unit";"Stalker";"Gateway";24;2
"Unit";"Stalker";"Gateway";29;2
"Building";"RoboticsFacility";NA;29;0
"Unit";"Sentry";"Gateway";34;2
"Building";"ShieldBattery";NA;36;0
"Building";"Pylon";NA;43;0
"Building";"Pylon";NA;44;0
"Building";"Gateway";NA;40;0
"Building";"Gateway";NA;40;0
"Unit";"Immortal";"Robotics Facility";41;4
"Unit";"Sentry";"Gateway";48;2
"Unit";"Sentry";"Gateway";50;2
"Unit";"Stalker";"Gateway";50;2
"Upgrade";"Charge";"TwilightCouncil";40;0
"Building";"Gateway";NA;44;0
"Building";"Gateway";NA;44;0
"Building";"Pylon";NA;54;0
"Building";"Pylon";NA;54;0
"Building";"Gateway";NA;44;0
"Unit";"Zealot";"Gateway";54;2
"Unit";"Zealot";"Gateway";54;2
"Unit";"Zealot";"Gateway";54;2
"Building";"Gateway";NA;48;0
"Building";"Gateway";NA;50;0
"Unit";"Zealot";"Gateway";60;2
"Unit";"Zealot";"Gateway";60;2
"Unit";"Zealot";"Gateway";60;2
"Unit";"Zealot";"Gateway";66;2
"Unit";"Zealot";"Gateway";66;2
"Unit";"Zealot";"Gateway";70;2
"Unit";"Zealot";"Gateway";70;2
"Unit";"Zealot";"Gateway";70;2
"Unit";"Sentry";"Gateway";76;2
"Building";"Pylon";NA;78;0
"Building";"Pylon";NA;78;0
"Unit";"Stalker";"Gateway";78;2
"Unit";"Stalker";"Gateway";78;2
"Unit";"Stalker";"Gateway";78;2
"Unit";"Stalker";"Gateway";78;2
"Unit";"Stalker";"Gateway";78;2
"Unit";"Stalker";"Gateway";78;2
"Unit";"Stalker";"Gateway";78;2
"Unit";"Stalker";"Gateway";78;2
"Unit";"Sentry";"Gateway";94;2
"Unit";"Zealot";"Gateway";94;2
"Unit";"Zealot";"Gateway";94;2
"Unit";"Zealot";"Gateway";94;2
"Unit";"Zealot";"Gateway";94;2
"Unit";"Zealot";"Gateway";94;2
"Unit";"Zealot";"Gateway";94;2
"Unit";"Zealot";"Gateway";94;2
"Building";"Pylon";NA;114;0
"Building";"Assimilator";NA;114;0
"Building";"Pylon";NA;115;0
"Building";"Assimilator";NA;114;0
"Building";"Pylon";NA;115;0
"Building";"ShieldBattery";NA;115;0
"Unit";"Immortal";"Robotics Facility";115;4
"Unit";"Stalker";"Gateway";124;2
"Building";"RoboticsBay";NA;115;0
"Unit";"Stalker";"Gateway";124;2
"Unit";"Stalker";"Gateway";130;2
"Unit";"Stalker";"Gateway";130;2
"Unit";"Stalker";"Gateway";130;2
"Unit";"Stalker";"Gateway";130;2
"Building";"Pylon";NA;132;0
"Building";"Forge";NA;129;0
"Building";"Pylon";NA;138;0
"Building";"Pylon";NA;138;0
"Building";"Pylon";NA;138;0
"Unit";"Stalker";"Gateway";138;2
"Unit";"Stalker";"Gateway";138;2
"Unit";"Stalker";"Gateway";138;2
"Building";"Nexus";NA;130;0
"Building";"Pylon";NA;144;0
"Building";"Pylon";NA;144;0
"Upgrade";"ExtendedThermalLance";"RoboticsBay";130;0
"Unit";"Stalker";"Gateway";146;2
"Unit";"Stalker";"Gateway";146;2
"Unit";"Colossus";"Robotics Facility";138;6
"Unit";"Stalker";"Gateway";161;2
"Unit";"Stalker";"Gateway";161;2
"Unit";"Stalker";"Gateway";161;2
"Building";"Assimilator";NA;160;0
"Building";"Assimilator";NA;160;0
"Unit";"Colossus";"Robotics Facility";152;6
"Unit";"Zealot";"Gateway";170;2
"Unit";"Zealot";"Gateway";176;2
"Building";"ShieldBattery";NA;167;0
"Building";"PhotonCannon";NA;167;0
"Building";"PhotonCannon";NA;167;0
"Upgrade";"ProtossGroundWeaponsLevel1";"Forge";159;0
"Unit";"Zealot";"Gateway";180;2
"Unit";"Zealot";"Gateway";180;2
"Unit";"Zealot";"Gateway";180;2
"Unit";"Zealot";"Gateway";180;2
"Building";"Pylon";NA;180;0
"Building";"DarkShrine";NA;167;0
"Unit";"Colossus";"Robotics Facility";170;6
"Unit";"Zealot";"Gateway";194;2
"Unit";"Zealot";"Gateway";194;2
"Unit";"Zealot";"Gateway";194;2
"Unit";"Zealot";"Gateway";194;2
"Building";"TemplarArchive";NA;180;0
"Unit";"Stalker";"Gateway";202;2
"Unit";"Stalker";"Gateway";202;2
"Unit";"Stalker";"Gateway";202;2
"Unit";"Stalker";"Gateway";202;2
"Unit";"Stalker";"Gateway";202;2
"Unit";"Stalker";"Gateway";202;2
"Unit";"Stalker";"Gateway";202;2
"Unit";"Stalker";"Gateway";202;2
"Building";"Nexus";NA;180;0
"Building";"HighTemplar";NA;218;0
"Building";"HighTemplar";NA;218;0
"Building";"HighTemplar";NA;218;0
"Building";"HighTemplar";NA;218;0
"Building";"HighTemplar";NA;218;0
"Building";"HighTemplar";NA;218;0
"Unit";"Zealot";"Gateway";218;2
"Unit";"Archon";"High Templar";220;0
"Unit";"Archon";"High Templar";220;0
"Unit";"Archon";"High Templar";221;0
"Building";"PhotonCannon";NA;218;0
"Building";"ShieldBattery";NA;218;0
"Building";"PhotonCannon";NA;218;0
"Unit";"Stalker";"Gateway";222;2
"Unit";"Stalker";"Gateway";222;2
"Unit";"Sentry";"Gateway";226;2
"Unit";"Sentry";"Gateway";226;2
"Unit";"Sentry";"Gateway";226;2
"Unit";"Stalker";"Gateway";226;2
"Unit";"Stalker";"Gateway";226;2
"Unit";"Stalker";"Gateway";226;2
"Building";"Assimilator";NA;222;0
"Building";"Assimilator";NA;226;0
"Unit";"Stalker";"Gateway";238;2
"Unit";"Stalker";"Gateway";238;2
"Unit";"Stalker";"Gateway";238;2
"Unit";"Stalker";"Gateway";238;2
"Unit";"Stalker";"Gateway";238;2
"Building";"HighTemplar";NA;251;0
"Building";"HighTemplar";NA;251;0
"Unit";"Stalker";"Gateway";251;2
"Unit";"Stalker";"Gateway";251;2
"Unit";"Stalker";"Gateway";251;2
"Unit";"Stalker";"Gateway";251;2
"Unit";"Stalker";"Gateway";251;2
"Unit";"Archon";"High Templar";261;0
"Unit";"Stalker";"Gateway";261;2
"Unit";"Stalker";"Gateway";261;2
"Unit";"Stalker";"Gateway";261;2
"Unit";"Stalker";"Gateway";261;2
"Unit";"Stalker";"Gateway";261;2
"Unit";"Stalker";"Gateway";261;2
"Unit";"Stalker";"Gateway";273;2
"Unit";"Stalker";"Gateway";273;2
"Unit";"Stalker";"Gateway";273;2
"Unit";"Stalker";"Gateway";273;2
"Unit";"Stalker";"Gateway";273;2
"Unit";"Stalker";"Gateway";283;2
"Unit";"Stalker";"Gateway";283;2
"Upgrade";"ProtossGroundWeaponsLevel2";"Forge";240;0
"Unit";"Stalker";"Gateway";287;2
"Unit";"Colossus";"Robotics Facility";261;6
"Unit";"Stalker";"Gateway";289;2
"Unit";"Stalker";"Gateway";289;2
"Unit";"Stalker";"Gateway";299;2
"Unit";"Stalker";"Gateway";299;2
"Unit";"Stalker";"Gateway";299;2
"Unit";"Stalker";"Gateway";299;2
