"type";"unit_name";"on_building";"total_supply_lag";"supply"
"Building";"Pylon";NA;14;0
"Building";"Gateway";NA;16;0
"Building";"Assimilator";NA;17;0
"Building";"Nexus";NA;20;0
"Building";"CyberneticsCore";NA;20;0
"Building";"Assimilator";NA;21;0
"Building";"Pylon";NA;22;0
"Unit";"Adept";"Gateway";23;2
"Unit";"Adept";"Gateway";28;2
"Building";"Stargate";NA;31;0
"Unit";"Oracle";"Stargate";37;3
"Building";"Gateway";NA;42;0
"Building";"Gateway";NA;42;0
"Building";"Pylon";NA;42;0
"Unit";"Phoenix";"Stargate";44;2
"Building";"Assimilator";NA;48;0
"Building";"Assimilator";NA;48;0
"Building";"Pylon";NA;49;0
"Unit";"Oracle";"Stargate";51;3
"Building";"Pylon";NA;54;0
"Building";"RoboticsFacility";NA;57;0
"Unit";"Adept";"Gateway";57;2
"Unit";"Sentry";"Gateway";59;2
"Building";"Nexus";NA;64;0
"Building";"Pylon";NA;64;0
"Building";"Pylon";NA;66;0
"Building";"Pylon";NA;66;0
"Building";"TwilightCouncil";NA;67;0
"Building";"Forge";NA;67;0
"Unit";"Observer";"Robotics Facility";68;1
"Unit";"Immortal";"Robotics Facility";70;4
"Unit";"Adept";"Gateway";75;2
"Unit";"Adept";"Gateway";78;2
"Unit";"Adept";"Gateway";80;2
"Unit";"Immortal";"Robotics Facility";86;4
"Building";"TemplarArchive";NA;93;0
"Upgrade";"ProtossGroundWeaponsLevel1";"Forge";93;0
"Unit";"Adept";"Gateway";93;2
"Unit";"Sentry";"Gateway";95;2
"Upgrade";"Charge";"TwilightCouncil";97;0
"Building";"Pylon";NA;99;0
"Building";"Gateway";NA;100;0
"Building";"Gateway";NA;100;0
"Unit";"Adept";"Gateway";103;2
"Unit";"Adept";"Gateway";105;2
"Unit";"Adept";"Gateway";108;2
"Unit";"Adept";"Gateway";112;2
"Unit";"Immortal";"Robotics Facility";114;4
"Building";"OracleStasisTrap";NA;118;0
"Building";"Assimilator";NA;118;0
"Building";"ShieldBattery";NA;118;0
"Building";"Assimilator";NA;118;0
"Building";"Gateway";NA;118;0
"Building";"Gateway";NA;118;0
"Building";"Gateway";NA;118;0
"Building";"OracleStasisTrap";NA;118;0
"Building";"RoboticsFacility";NA;118;0
"Unit";"Phoenix";"Stargate";118;2
"Unit";"Zealot";"Gateway";120;2
"Building";"ShieldBattery";NA;122;0
"Building";"ShieldBattery";NA;122;0
"Building";"HighTemplar";NA;122;0
"Building";"HighTemplar";NA;122;0
"Unit";"Zealot";"Gateway";122;2
"Building";"Nexus";NA;124;0
"Building";"Pylon";NA;124;0
"Building";"Pylon";NA;124;0
"Building";"Pylon";NA;124;0
"Unit";"Immortal";"Robotics Facility";124;4
"Building";"HighTemplar";NA;128;0
"Unit";"Immortal";"Robotics Facility";128;4
"Building";"Pylon";NA;132;0
"Building";"PhotonCannon";NA;132;0
"Building";"PhotonCannon";NA;132;0
"Building";"Pylon";NA;132;0
"Building";"PhotonCannon";NA;132;0
"Building";"HighTemplar";NA;132;0
"Unit";"Zealot";"Gateway";132;2
"Unit";"Zealot";"Gateway";134;2
"Unit";"Zealot";"Gateway";136;2
"Unit";"Zealot";"Gateway";138;2
"Unit";"Immortal";"Robotics Facility";140;4
"Unit";"Zealot";"Gateway";144;2
"Unit";"Zealot";"Gateway";146;2
"Unit";"Immortal";"Robotics Facility";148;4
"Building";"HighTemplar";NA;152;0
"Building";"HighTemplar";NA;152;0
"Unit";"Zealot";"Gateway";152;2
"Unit";"Archon";"High Templar";154;0
"Upgrade";"ProtossGroundWeaponsLevel2";"Forge";154;0
"Unit";"Zealot";"Gateway";154;2
"Unit";"Zealot";"Gateway";156;2
"Unit";"Zealot";"Gateway";158;2
"Unit";"Zealot";"Gateway";160;2
"Unit";"Zealot";"Gateway";162;2
"Building";"HighTemplar";NA;167;0
"Unit";"Immortal";"Robotics Facility";167;4
"Unit";"Zealot";"Gateway";171;2
"Unit";"Immortal";"Robotics Facility";173;4
"Unit";"Zealot";"Gateway";177;2
"Unit";"Zealot";"Gateway";179;2
"Unit";"Zealot";"Gateway";181;2
"Unit";"Zealot";"Gateway";183;2
"Unit";"Zealot";"Gateway";185;2
"Unit";"Zealot";"Gateway";187;2
"Building";"Stargate";NA;190;0
"Building";"FleetBeacon";NA;190;0
"Building";"Pylon";NA;190;0
"Building";"Assimilator";NA;190;0
"Building";"Pylon";NA;190;0
"Building";"Assimilator";NA;190;0
"Building";"Pylon";NA;190;0
"Building";"Pylon";NA;190;0
"Building";"Pylon";NA;190;0
"Unit";"Immortal";"Robotics Facility";190;4
"Unit";"Immortal";"Robotics Facility";194;4
"Unit";"Zealot";"Gateway";198;2
"Unit";"Zealot";"Gateway";200;2
"Unit";"Zealot";"Gateway";202;2
"Unit";"Zealot";"Gateway";204;2
"Unit";"Zealot";"Gateway";206;2
"Unit";"Zealot";"Gateway";208;2
"Unit";"Zealot";"Gateway";210;2
"Unit";"Zealot";"Gateway";212;2
"Building";"HighTemplar";NA;218;0
"Building";"HighTemplar";NA;218;0
"Building";"HighTemplar";NA;218;0
"Building";"HighTemplar";NA;218;0
"Building";"HighTemplar";NA;218;0
"Building";"HighTemplar";NA;218;0
"Unit";"Zealot";"Gateway";218;2
"Unit";"Zealot";"Gateway";220;2
"Building";"PhotonCannon";NA;222;0
"Unit";"Archon";"High Templar";223;0
"Unit";"Archon";"High Templar";223;0
"Unit";"Observer";"Robotics Facility";223;1
"Unit";"Observer";"Robotics Facility";224;1
"Unit";"Mothership";"Mothership Core";225;6
"Unit";"Zealot";"Gateway";231;2
"Unit";"Zealot";"Gateway";233;2
"Unit";"Zealot";"Gateway";235;2
"Unit";"Zealot";"Gateway";237;2
"Unit";"Zealot";"Gateway";239;2
"Unit";"Zealot";"Gateway";241;2
"Unit";"Zealot";"Gateway";243;2
"Unit";"Zealot";"Gateway";245;2
"Unit";"Zealot";"Gateway";247;2
"Unit";"Zealot";"Gateway";249;2
"Unit";"Zealot";"Gateway";251;2
"Unit";"Zealot";"Gateway";253;2
"Unit";"Zealot";"Gateway";255;2
"Unit";"Zealot";"Gateway";257;2
"Unit";"Zealot";"Gateway";259;2
"Unit";"Zealot";"Gateway";261;2
"Unit";"Observer";"Robotics Facility";263;1
"Upgrade";"ProtossGroundWeaponsLevel3";"Forge";264;0
"Building";"HighTemplar";NA;264;0
"Building";"HighTemplar";NA;264;0
"Building";"HighTemplar";NA;264;0
"Building";"HighTemplar";NA;264;0
"Building";"HighTemplar";NA;264;0
"Building";"HighTemplar";NA;264;0
"Unit";"Observer";"Robotics Facility";264;1
"Unit";"Zealot";"Gateway";268;2
"Unit";"Zealot";"Gateway";270;2
"Unit";"Tempest";"Stargate";272;4
"Unit";"Tempest";"Stargate";276;4
"Building";"Nexus";NA;280;0
"Building";"HighTemplar";NA;280;0
"Building";"HighTemplar";NA;280;0
"Unit";"Zealot";"Gateway";280;2
"Building";"Pylon";NA;282;0
"Building";"Pylon";NA;282;0
"Unit";"Tempest";"Stargate";282;4
"Unit";"Tempest";"Stargate";286;4
"Unit";"Archon";"High Templar";290;0
"Unit";"Zealot";"Gateway";290;2
"Unit";"Zealot";"Gateway";292;2
"Unit";"Zealot";"Gateway";294;2
"Unit";"Tempest";"Stargate";296;4
"Unit";"Adept";"Gateway";300;2
"Building";"Stargate";NA;302;0
"Unit";"Tempest";"Stargate";302;4
"Building";"PhotonCannon";NA;306;0
"Building";"PhotonCannon";NA;306;0
"Building";"ShieldBattery";NA;306;0
"Unit";"Zealot";"Gateway";306;2
"Unit";"Zealot";"Gateway";308;2
"Unit";"Zealot";"Gateway";310;2
"Unit";"Zealot";"Gateway";312;2
"Unit";"Zealot";"Gateway";314;2
"Unit";"Zealot";"Gateway";316;2
"Unit";"Zealot";"Gateway";318;2
"Building";"DarkShrine";NA;320;0
"Upgrade";"ProtossAirWeaponsLevel1";"CyberneticsCore";320;0
"Upgrade";"ProtossShieldsLevel1";"Forge";320;0
"Unit";"Tempest";"Stargate";320;4
"Unit";"Tempest";"Stargate";324;4
"Unit";"Tempest";"Stargate";328;4
"Building";"Nexus";NA;332;0
"Building";"Pylon";NA;332;0
"Building";"Pylon";NA;332;0
"Unit";"Tempest";"Stargate";332;4
"Building";"PhotonCannon";NA;336;0
"Building";"PhotonCannon";NA;336;0
"Building";"PhotonCannon";NA;336;0
"Building";"DarkTemplar";NA;336;0
"Unit";"Tempest";"Stargate";336;4
"Building";"DarkTemplar";NA;340;0
"Building";"DarkTemplar";NA;340;0
"Building";"DarkTemplar";NA;340;0
"Unit";"Zealot";"Gateway";340;2
"Unit";"Zealot";"Gateway";342;2
"Unit";"Zealot";"Gateway";344;2
"Unit";"Zealot";"Gateway";346;2
"Unit";"Zealot";"Gateway";348;2
"Building";"HighTemplar";NA;350;0
"Building";"HighTemplar";NA;350;0
"Upgrade";"ProtossAirWeaponsLevel2";"CyberneticsCore";350;0
"Building";"Assimilator";NA;350;0
"Building";"Assimilator";NA;350;0
"Building";"HighTemplar";NA;350;0
"Building";"HighTemplar";NA;350;0
"Upgrade";"ProtossShieldsLevel2";"Forge";350;0
"Building";"PhotonCannon";NA;350;0
"Building";"PhotonCannon";NA;350;0
"Building";"PhotonCannon";NA;350;0
"Building";"DarkTemplar";NA;350;0
"Building";"Gateway";NA;350;0
"Unit";"Adept";"Gateway";350;2
"Building";"DarkTemplar";NA;352;0
"Building";"DarkTemplar";NA;352;0
"Unit";"Oracle";"Stargate";352;3
"Unit";"Sentry";"Gateway";355;2
"Building";"Nexus";NA;357;0
"Building";"Pylon";NA;357;0
"Building";"PhotonCannon";NA;357;0
"Building";"PhotonCannon";NA;357;0
"Building";"PhotonCannon";NA;357;0
"Building";"PhotonCannon";NA;357;0
"Building";"ShieldBattery";NA;357;0
"Building";"ShieldBattery";NA;357;0
"Building";"ShieldBattery";NA;357;0
"Building";"Assimilator";NA;357;0
"Building";"Assimilator";NA;357;0
"Upgrade";"ProtossAirWeaponsLevel3";"CyberneticsCore";357;0
"Building";"HighTemplar";NA;357;0
"Building";"HighTemplar";NA;357;0
"Building";"HighTemplar";NA;357;0
"Building";"HighTemplar";NA;357;0
"Unit";"Archon";"High Templar";357;0
"Building";"DarkTemplar";NA;357;0
"Upgrade";"ProtossShieldsLevel3";"Forge";357;0
"Unit";"Observer";"Robotics Facility";357;1
"Building";"DarkTemplar";NA;358;0
"Building";"DarkTemplar";NA;358;0
"Unit";"Mothership";"Mothership Core";358;6
"Unit";"Oracle";"Stargate";364;3
"Building";"HighTemplar";NA;367;0
"Building";"HighTemplar";NA;367;0
"Building";"HighTemplar";NA;367;0
"Building";"HighTemplar";NA;367;0
"Building";"Pylon";NA;367;0
"Building";"Nexus";NA;367;0
"Unit";"Carrier";"Stargate";367;6
"Unit";"Carrier";"Stargate";373;6
"Unit";"Carrier";"Stargate";379;6
"Unit";"Zealot";"Gateway";385;2
"Unit";"Zealot";"Gateway";387;2
"Unit";"Zealot";"Gateway";389;2
"Unit";"Zealot";"Gateway";391;2
"Unit";"Zealot";"Gateway";393;2
"Unit";"Zealot";"Gateway";395;2
"Unit";"Zealot";"Gateway";397;2
"Building";"Assimilator";NA;399;0
"Building";"PhotonCannon";NA;399;0
"Building";"Assimilator";NA;399;0
"Building";"PhotonCannon";NA;399;0
"Building";"PhotonCannon";NA;399;0
"Building";"Stargate";NA;399;0
"Building";"Stargate";NA;399;0
"Unit";"Oracle";"Stargate";399;3
"Building";"Stargate";NA;402;0
"Unit";"Zealot";"Gateway";402;2
"Unit";"Zealot";"Gateway";404;2
"Unit";"Zealot";"Gateway";406;2
"Unit";"Zealot";"Gateway";408;2
"Unit";"Zealot";"Gateway";410;2
"Unit";"Zealot";"Gateway";412;2
"Unit";"Zealot";"Gateway";414;2
"Unit";"Carrier";"Stargate";416;6
"Unit";"Carrier";"Stargate";422;6
"Unit";"Mothership";"Mothership Core";428;6
"Unit";"Carrier";"Stargate";434;6
"Unit";"Carrier";"Stargate";440;6
"Unit";"Carrier";"Stargate";446;6
"Building";"HighTemplar";NA;452;0
"Building";"HighTemplar";NA;452;0
"Building";"HighTemplar";NA;452;0
"Building";"HighTemplar";NA;452;0
"Building";"HighTemplar";NA;452;0
"Building";"HighTemplar";NA;452;0
"Unit";"Zealot";"Gateway";452;2
"Building";"Gateway";NA;454;0
"Building";"Gateway";NA;454;0
"Building";"Gateway";NA;454;0
"Building";"Gateway";NA;454;0
"Building";"Gateway";NA;454;0
"Building";"Gateway";NA;454;0
"Building";"Gateway";NA;454;0
"Building";"Gateway";NA;454;0
"Building";"Gateway";NA;454;0
"Building";"Gateway";NA;454;0
"Building";"Gateway";NA;454;0
"Building";"Gateway";NA;454;0
"Building";"Gateway";NA;454;0
"Building";"Gateway";NA;454;0
"Building";"HighTemplar";NA;454;0
"Building";"HighTemplar";NA;454;0
"Building";"HighTemplar";NA;454;0
"Building";"HighTemplar";NA;454;0
"Building";"HighTemplar";NA;454;0
"Building";"HighTemplar";NA;454;0
"Building";"HighTemplar";NA;454;0
"Upgrade";"SprayProtoss";NA;454;0
"Upgrade";"SprayProtoss";NA;454;0
"Upgrade";"WarpGateResearch";NA;454;0
"Upgrade";"SprayProtoss";NA;454;0
"Upgrade";"SprayProtoss";NA;454;0
"Upgrade";"SprayProtoss";NA;454;0
"Upgrade";"PsiStormTech";NA;454;0
"Upgrade";"SprayProtoss";NA;454;0
"Upgrade";"SprayProtoss";NA;454;0
"Upgrade";"SprayProtoss";NA;454;0
"Upgrade";"SprayProtoss";NA;454;0
"Upgrade";"SprayProtoss";NA;454;0
"Upgrade";"SprayProtoss";NA;454;0
"Upgrade";"SprayProtoss";NA;454;0
"Upgrade";"SprayProtoss";NA;454;0
"Upgrade";"ProtossAirArmorsLevel1";NA;454;0
"Upgrade";"SprayProtoss";NA;454;0
"Upgrade";"CarrierLaunchSpeedUpgrade";NA;454;0
"Upgrade";"ProtossGroundArmorsLevel1";NA;454;0
"Upgrade";"ProtossAirArmorsLevel2";NA;454;0
