"type";"unit_name";"on_building";"total_supply_lag";"supply"
"Building";"Pylon";NA;14;0
"Building";"Gateway";NA;17;0
"Building";"Assimilator";NA;17;0
"Building";"Nexus";NA;20;0
"Building";"CyberneticsCore";NA;20;0
"Building";"Assimilator";NA;21;0
"Building";"Pylon";NA;22;0
"Unit";"Adept";"Gateway";23;2
"Building";"Stargate";NA;25;0
"Unit";"Adept";"Gateway";26;2
"Unit";"Phoenix";"Stargate";33;2
"Unit";"Oracle";"Stargate";37;3
"Building";"Pylon";NA;43;0
"Building";"Gateway";NA;44;0
"Unit";"Oracle";"Stargate";45;3
"Building";"Gateway";NA;48;0
"Building";"Pylon";NA;50;0
"Building";"Assimilator";NA;50;0
"Building";"Assimilator";NA;51;0
"Building";"RoboticsFacility";NA;53;0
"Building";"Pylon";NA;56;0
"Unit";"Adept";"Gateway";57;2
"Unit";"Adept";"Gateway";59;2
"Building";"Nexus";NA;63;0
"Unit";"Observer";"Robotics Facility";63;1
"Building";"Pylon";NA;64;0
"Building";"RoboticsBay";NA;64;0
"Building";"TwilightCouncil";NA;66;0
"Building";"Forge";NA;66;0
"Unit";"Immortal";"Robotics Facility";68;4
"Unit";"Sentry";"Gateway";72;2
"Unit";"Sentry";"Gateway";74;2
"Unit";"Sentry";"Gateway";76;2
"Building";"Pylon";NA;78;0
"Building";"Pylon";NA;78;0
"Building";"Pylon";NA;78;0
"Building";"Pylon";NA;78;0
"Unit";"Immortal";"Robotics Facility";78;4
"Unit";"Adept";"Gateway";83;2
"Unit";"Zealot";"Gateway";85;2
"Unit";"Zealot";"Gateway";87;2
"Building";"Pylon";NA;89;0
"Unit";"Stalker";"Gateway";94;2
"Unit";"Observer";"Robotics Facility";97;1
"Building";"Pylon";NA;98;0
"Unit";"Immortal";"Robotics Facility";99;4
"Unit";"Stalker";"Gateway";103;2
"Unit";"Stalker";"Gateway";105;2
"Unit";"Stalker";"Gateway";107;2
"Building";"Gateway";NA;109;0
"Building";"Gateway";NA;109;0
"Building";"Gateway";NA;109;0
"Building";"ShieldBattery";NA;112;0
"Unit";"Colossus";"Robotics Facility";112;6
"Upgrade";"ProtossGroundWeaponsLevel1";"Forge";119;0
"Building";"Pylon";NA;122;0
"Building";"Pylon";NA;122;0
"Upgrade";"ExtendedThermalLance";"RoboticsBay";122;0
"Building";"RoboticsFacility";NA;122;0
"Building";"PhotonCannon";NA;122;0
"Building";"PhotonCannon";NA;122;0
"Building";"PhotonCannon";NA;122;0
"Unit";"Colossus";"Robotics Facility";122;6
"Building";"Assimilator";NA;128;0
"Building";"Pylon";NA;128;0
"Building";"Assimilator";NA;128;0
"Unit";"Stalker";"Gateway";128;2
"Unit";"Stalker";"Gateway";130;2
"Unit";"Stalker";"Gateway";132;2
"Unit";"Stalker";"Gateway";134;2
"Unit";"Stalker";"Gateway";136;2
"Unit";"Stalker";"Gateway";138;2
"Building";"Gateway";NA;140;0
"Building";"Gateway";NA;140;0
"Unit";"Colossus";"Robotics Facility";140;6
"Building";"Pylon";NA;149;0
"Unit";"Stalker";"Gateway";149;2
"Upgrade";"ProtossGroundWeaponsLevel2";"Forge";151;0
"Unit";"Stalker";"Gateway";151;2
"Unit";"Stalker";"Gateway";153;2
"Unit";"Stalker";"Gateway";155;2
"Unit";"Stalker";"Gateway";157;2
"Unit";"Stalker";"Gateway";159;2
"Unit";"Observer";"Robotics Facility";161;1
"Building";"PhotonCannon";NA;162;0
"Unit";"Stalker";"Gateway";162;2
"Unit";"Stalker";"Gateway";164;2
"Building";"Pylon";NA;166;0
"Building";"Nexus";NA;166;0
"Upgrade";"Charge";"TwilightCouncil";166;0
"Building";"Pylon";NA;166;0
"Unit";"Immortal";"Robotics Facility";166;4
"Unit";"Stalker";"Gateway";170;2
"Unit";"Stalker";"Gateway";172;2
"Unit";"Stalker";"Gateway";174;2
"Unit";"Stalker";"Gateway";176;2
"Unit";"Stalker";"Gateway";178;2
"Unit";"Stalker";"Gateway";180;2
"Unit";"Stalker";"Gateway";182;2
"Unit";"Observer";"Robotics Facility";184;1
"Unit";"Stalker";"Gateway";185;2
"Unit";"Stalker";"Gateway";187;2
"Unit";"Stalker";"Gateway";189;2
"Unit";"Stalker";"Gateway";191;2
"Unit";"Stalker";"Gateway";193;2
"Unit";"Stalker";"Gateway";195;2
"Unit";"Stalker";"Gateway";197;2
"Unit";"Stalker";"Gateway";199;2
"Unit";"Stalker";"Gateway";201;2
"Upgrade";"GraviticDrive";"RoboticsBay";203;0
"Unit";"Stalker";"Gateway";203;2
"Unit";"Stalker";"Gateway";205;2
"Unit";"Stalker";"Gateway";207;2
"Unit";"Stalker";"Gateway";209;2
"Unit";"Stalker";"Gateway";211;2
"Unit";"Stalker";"Gateway";213;2
"Unit";"Stalker";"Gateway";215;2
"Unit";"Stalker";"Gateway";217;2
"Upgrade";"SprayProtoss";NA;219;0
"Upgrade";"SprayProtoss";NA;219;0
"Upgrade";"WarpGateResearch";NA;219;0
"Upgrade";"SprayProtoss";NA;219;0
"Upgrade";"SprayProtoss";NA;219;0
"Upgrade";"SprayProtoss";NA;219;0
"Upgrade";"BlinkTech";NA;219;0
"Upgrade";"SprayProtoss";NA;219;0
"Upgrade";"ObserverGraviticBooster";NA;219;0
"Upgrade";"SprayProtoss";NA;219;0
