"type";"unit_name";"on_building";"total_supply";"supply"
"Building";"Pylon";NA;13;0
"Building";"Forge";NA;15;0
"Building";"Assimilator";NA;20;0
"Building";"PhotonCannon";NA;20;0
"Building";"Assimilator";NA;20;0
"Building";"Gateway";NA;20;0
"Unit";"Zealot";"Gateway";21;2
"Building";"Pylon";NA;22;0
"Building";"CyberneticsCore";NA;22;0
"Building";"Pylon";NA;24;0
"Building";"PhotonCannon";NA;25;0
"Building";"PhotonCannon";NA;25;0
"Building";"ShieldBattery";NA;25;0
