"type";"unit_name";"on_building";"total_supply";"supply"
"Building";"Pylon";NA;13;0
"Building";"Assimilator";NA;16;0
"Building";"Gateway";NA;16;0
"Building";"Pylon";NA;21;0
"Building";"Assimilator";NA;21;0
"Building";"CyberneticsCore";NA;20;0
"Unit";"Adept";"Gateway";22;2
"Building";"Nexus";NA;19;0
"Unit";"Adept";"Gateway";25;2
"Building";"Stargate";NA;24;0
"Building";"Pylon";NA;34;0
"Unit";"Oracle";"Stargate";32;3
"Building";"Assimilator";NA;35;0
"Building";"Assimilator";NA;36;0
"Unit";"Adept";"Gateway";36;2
"Unit";"Phoenix";"Stargate";43;2
"Unit";"Adept";"Gateway";45;2
"Building";"Gateway";NA;42;0
"Building";"Pylon";NA;47;0
"Building";"TwilightCouncil";NA;47;0
"Building";"Gateway";NA;47;0
"Building";"Gateway";NA;47;0
"Unit";"Adept";"Gateway";59;2
"Unit";"Adept";"Gateway";59;2
"Building";"Pylon";NA;57;0
"Building";"TemplarArchive";NA;59;0
"Building";"Pylon";NA;66;0
"Building";"Pylon";NA;66;0
"Building";"HighTemplar";NA;68;0
"Building";"HighTemplar";NA;68;0
"Building";"HighTemplar";NA;68;0
"Building";"Pylon";NA;66;0
"Building";"Pylon";NA;66;0
"Building";"Pylon";NA;68;0
"Building";"RoboticsFacility";NA;65;0
"Unit";"Archon";"High Templar";69;0
"Building";"HighTemplar";NA;70;0
"Unit";"Archon";"High Templar";72;0
"Building";"Nexus";NA;66;0
"Building";"ShieldBattery";NA;70;0
"Unit";"Zealot";"Gateway";76;2
"Unit";"Zealot";"Gateway";76;2
"Unit";"Zealot";"Gateway";76;2
"Unit";"Zealot";"Gateway";76;2
"Building";"Gateway";NA;70;0
"Building";"Gateway";NA;70;0
"Upgrade";"Charge";"TwilightCouncil";66;0
"Building";"Assimilator";NA;84;0
"Building";"Assimilator";NA;84;0
"Unit";"Zealot";"Gateway";87;2
"Unit";"Zealot";"Gateway";87;2
"Unit";"Zealot";"Gateway";87;2
"Unit";"Zealot";"Gateway";87;2
"Building";"Pylon";NA;86;0
"Unit";"Immortal";"Robotics Facility";86;4
"Building";"Gateway";NA;84;0
"Building";"RoboticsFacility";NA;86;0
"Unit";"Zealot";"Gateway";106;2
"Unit";"Zealot";"Gateway";106;2
"Unit";"Zealot";"Gateway";106;2
"Unit";"Zealot";"Gateway";106;2
"Unit";"Zealot";"Gateway";106;2
"Unit";"Zealot";"Gateway";106;2
"Unit";"Zealot";"Gateway";120;2
"Building";"OracleStasisTrap";NA;123;0
"Unit";"Zealot";"Gateway";125;2
"Unit";"Zealot";"Gateway";125;2
"Unit";"Zealot";"Gateway";125;2
"Unit";"Zealot";"Gateway";125;2
"Unit";"Zealot";"Gateway";125;2
"Building";"HighTemplar";NA;135;0
"Building";"HighTemplar";NA;135;0
"Unit";"Immortal";"Robotics Facility";106;4
"Unit";"Immortal";"Robotics Facility";106;4
"Building";"Forge";NA;120;0
"Building";"ShieldBattery";NA;123;0
"Unit";"Zealot";"Gateway";143;2
"Unit";"Zealot";"Gateway";143;2
"Unit";"Zealot";"Gateway";143;2
"Unit";"Zealot";"Gateway";143;2
"Unit";"Zealot";"Gateway";143;2
"Unit";"Immortal";"Robotics Facility";135;4
"Building";"HighTemplar";NA;157;0
"Building";"HighTemplar";NA;157;0
"Building";"HighTemplar";NA;157;0
"Building";"HighTemplar";NA;157;0
"Building";"OracleStasisTrap";NA;161;0
"Building";"HighTemplar";NA;161;0
"Unit";"Archon";"High Templar";161;0
"Unit";"Archon";"High Templar";161;0
"Building";"Pylon";NA;156;0
"Unit";"Immortal";"Robotics Facility";156;4
"Building";"HighTemplar";NA;168;0
"Building";"HighTemplar";NA;168;0
"Building";"PhotonCannon";NA;161;0
"Building";"PhotonCannon";NA;161;0
"Building";"PhotonCannon";NA;161;0
"Unit";"Immortal";"Robotics Facility";157;4
"Building";"Assimilator";NA;164;0
"Building";"Assimilator";NA;164;0
"Building";"Nexus";NA;156;0
"Building";"ShieldBattery";NA;168;0
"Unit";"Immortal";"Robotics Facility";164;4
"Building";"Gateway";NA;164;0
"Building";"Gateway";NA;164;0
"Unit";"Zealot";"Gateway";176;2
"Unit";"Zealot";"Gateway";176;2
"Unit";"Zealot";"Gateway";176;2
"Building";"Gateway";NA;164;0
"Building";"FleetBeacon";NA;172;0
"Unit";"Zealot";"Gateway";185;2
"Unit";"Zealot";"Gateway";185;2
"Unit";"Immortal";"Robotics Facility";172;4
"Building";"Pylon";NA;193;0
"Building";"Pylon";NA;193;0
"Building";"Pylon";NA;193;0
"Building";"Pylon";NA;193;0
"Unit";"Immortal";"Robotics Facility";185;4
"Building";"Pylon";NA;193;0
"Unit";"Zealot";"Gateway";193;2
"Unit";"Zealot";"Gateway";193;2
"Unit";"Zealot";"Gateway";193;2
"Unit";"Zealot";"Gateway";193;2
"Unit";"Zealot";"Gateway";193;2
"Unit";"Zealot";"Gateway";193;2
"Unit";"Zealot";"Gateway";193;2
"Building";"Pylon";NA;193;0
"Building";"PhotonCannon";NA;193;0
"Building";"PhotonCannon";NA;193;0
"Unit";"Observer";"Robotics Facility";193;1
"Unit";"Immortal";"Robotics Facility";193;4
"Unit";"Zealot";"Gateway";212;2
"Upgrade";"ProtossGroundWeaponsLevel1";"Forge";176;0
"Unit";"Zealot";"Gateway";216;2
"Unit";"Zealot";"Gateway";220;2
"Unit";"Zealot";"Gateway";220;2
"Unit";"Zealot";"Gateway";220;2
"Unit";"Zealot";"Gateway";220;2
"Unit";"Zealot";"Gateway";220;2
"Unit";"Zealot";"Gateway";220;2
"Unit";"Zealot";"Gateway";220;2
"Unit";"Zealot";"Gateway";220;2
"Building";"Pylon";NA;212;0
"Building";"Stargate";NA;193;0
"Building";"Stargate";NA;197;0
"Building";"Stargate";NA;211;0
"Building";"Stargate";NA;211;0
"Building";"HighTemplar";NA;236;0
"Building";"HighTemplar";NA;236;0
"Building";"HighTemplar";NA;236;0
"Building";"HighTemplar";NA;236;0
"Unit";"Zealot";"Gateway";236;2
"Unit";"Zealot";"Gateway";236;2
"Unit";"Zealot";"Gateway";236;2
"Unit";"Zealot";"Gateway";236;2
"Unit";"Zealot";"Gateway";236;2
"Building";"HighTemplar";NA;246;0
"Building";"HighTemplar";NA;246;0
"Building";"HighTemplar";NA;246;0
"Building";"HighTemplar";NA;246;0
"Unit";"Zealot";"Gateway";246;2
"Unit";"Zealot";"Gateway";246;2
"Unit";"Zealot";"Gateway";246;2
"Unit";"Zealot";"Gateway";246;2
"Unit";"Zealot";"Gateway";246;2
"Unit";"Zealot";"Gateway";246;2
"Unit";"Archon";"High Templar";258;0
"Unit";"Archon";"High Templar";258;0
"Unit";"Mothership";"Mothership Core";236;6
"Building";"HighTemplar";NA;264;0
"Building";"HighTemplar";NA;264;0
"Building";"HighTemplar";NA;264;0
"Unit";"Observer";"Robotics Facility";258;1
"Unit";"Zealot";"Gateway";265;2
"Building";"PhotonCannon";NA;264;0
"Building";"PhotonCannon";NA;264;0
"Building";"PhotonCannon";NA;264;0
"Building";"ShieldBattery";NA;264;0
"Building";"HighTemplar";NA;267;0
"Building";"HighTemplar";NA;267;0
"Building";"HighTemplar";NA;267;0
"Building";"HighTemplar";NA;267;0
"Building";"HighTemplar";NA;267;0
"Building";"Nexus";NA;258;0
"Building";"HighTemplar";NA;267;0
"Unit";"Archon";"High Templar";267;0
"Unit";"Archon";"High Templar";267;0
"Building";"Assimilator";NA;267;0
"Unit";"Carrier";"Stargate";258;6
"Unit";"Carrier";"Stargate";258;6
"Unit";"Carrier";"Stargate";258;6
"Unit";"Zealot";"Gateway";285;2
"Unit";"Zealot";"Gateway";285;2
"Unit";"Zealot";"Gateway";285;2
"Unit";"Zealot";"Gateway";285;2
"Unit";"Carrier";"Stargate";258;6
"Building";"Assimilator";NA;267;0
"Building";"HighTemplar";NA;299;0
"Unit";"Carrier";"Stargate";267;6
"Building";"PhotonCannon";NA;299;0
"Upgrade";"ProtossAirWeaponsLevel1";"CyberneticsCore";267;0
"Building";"PhotonCannon";NA;299;0
"Unit";"Carrier";"Stargate";267;6
"Unit";"Carrier";"Stargate";279;6
"Unit";"Zealot";"Gateway";317;2
"Unit";"Zealot";"Gateway";317;2
"Unit";"Zealot";"Gateway";317;2
"Unit";"Zealot";"Gateway";317;2
"Unit";"Zealot";"Gateway";317;2
"Unit";"Zealot";"Gateway";317;2
"Unit";"Carrier";"Stargate";299;6
"Building";"PhotonCannon";NA;317;0
"Building";"PhotonCannon";NA;317;0
"Building";"PhotonCannon";NA;317;0
"Building";"HighTemplar";NA;335;0
"Building";"HighTemplar";NA;335;0
"Building";"HighTemplar";NA;335;0
"Building";"HighTemplar";NA;335;0
"Building";"HighTemplar";NA;335;0
"Building";"HighTemplar";NA;335;0
"Building";"HighTemplar";NA;335;0
"Unit";"Archon";"High Templar";335;0
"Unit";"Archon";"High Templar";335;0
"Unit";"Archon";"High Templar";335;0
"Unit";"Carrier";"Stargate";305;6
