"type";"unit_name";"on_building";"total_supply";"supply"
"Building";"Pylon";NA;13;0
"Building";"Assimilator";NA;16;0
"Building";"Gateway";NA;15;0
"Building";"Assimilator";NA;20;0
"Building";"CyberneticsCore";NA;20;0
"Building";"Pylon";NA;21;0
"Unit";"Adept";"Gateway";22;2
"Building";"Nexus";NA;19;0
"Unit";"Adept";"Gateway";24;2
"Building";"Stargate";NA;26;0
"Unit";"Adept";"Gateway";31;2
"Building";"Pylon";NA;40;0
"Unit";"Oracle";"Stargate";36;3
"Building";"Gateway";NA;36;0
"Building";"Assimilator";NA;42;0
"Building";"Assimilator";NA;42;0
"Unit";"Phoenix";"Stargate";46;2
"Building";"Pylon";NA;47;0
"Building";"RoboticsFacility";NA;42;0
"Building";"Forge";NA;49;0
"Building";"TwilightCouncil";NA;49;0
"Building";"Pylon";NA;55;0
"Building";"Pylon";NA;57;0
"Building";"Gateway";NA;57;0
"Unit";"Observer";"Robotics Facility";57;1
"Building";"Gateway";NA;57;0
"Building";"Pylon";NA;59;0
"Building";"TemplarArchive";NA;57;0
"Building";"HighTemplar";NA;60;0
"Building";"HighTemplar";NA;60;0
"Building";"HighTemplar";NA;60;0
"Building";"HighTemplar";NA;60;0
"Building";"Gateway";NA;57;0
"Building";"Pylon";NA;60;0
"Building";"Gateway";NA;57;0
"Unit";"Archon";"High Templar";60;0
"Unit";"Archon";"High Templar";60;0
"Building";"Pylon";NA;60;0
"Upgrade";"Charge";"TwilightCouncil";57;0
"Unit";"Zealot";"Gateway";62;2
"Unit";"Zealot";"Gateway";62;2
"Upgrade";"ProtossGroundWeaponsLevel1";"Forge";57;0
"Unit";"Zealot";"Gateway";70;2
"Unit";"Zealot";"Gateway";70;2
"Unit";"Zealot";"Gateway";70;2
"Unit";"Zealot";"Gateway";70;2
"Unit";"Zealot";"Gateway";70;2
"Unit";"Zealot";"Gateway";70;2
"Unit";"Immortal";"Robotics Facility";60;4
"Building";"Nexus";NA;60;0
"Unit";"Zealot";"Gateway";88;2
"Unit";"Zealot";"Gateway";88;2
"Unit";"Zealot";"Gateway";88;2
"Unit";"Zealot";"Gateway";88;2
"Unit";"Zealot";"Gateway";88;2
"Unit";"Zealot";"Gateway";88;2
"Building";"HighTemplar";NA;104;0
"Building";"HighTemplar";NA;104;0
"Building";"HighTemplar";NA;104;0
"Building";"HighTemplar";NA;104;0
"Unit";"Immortal";"Robotics Facility";88;4
"Unit";"Zealot";"Gateway";111;2
"Unit";"Zealot";"Gateway";111;2
"Building";"Assimilator";NA;104;0
"Building";"Assimilator";NA;104;0
"Building";"ShieldBattery";NA;104;0
"Building";"ShieldBattery";NA;107;0
"Unit";"Immortal";"Robotics Facility";104;4
"Unit";"Zealot";"Gateway";122;2
"Unit";"Zealot";"Gateway";122;2
"Unit";"Zealot";"Gateway";122;2
"Unit";"Zealot";"Gateway";122;2
"Building";"Gateway";NA;115;0
"Building";"Gateway";NA;115;0
"Unit";"Immortal";"Robotics Facility";115;4
"Building";"Pylon";NA;130;0
"Building";"Pylon";NA;130;0
"Building";"HighTemplar";NA;135;0
"Building";"HighTemplar";NA;135;0
"Building";"HighTemplar";NA;135;0
"Building";"HighTemplar";NA;135;0
"Unit";"Zealot";"Gateway";135;2
"Unit";"Zealot";"Gateway";135;2
"Building";"OracleStasisTrap";NA;139;0
"Unit";"Archon";"High Templar";135;0
"Unit";"Archon";"High Templar";137;0
"Building";"OracleStasisTrap";NA;139;0
"Unit";"Zealot";"Gateway";139;2
"Unit";"Zealot";"Gateway";139;2
"Building";"Assimilator";NA;139;0
"Building";"Pylon";NA;139;0
"Building";"Assimilator";NA;139;0
"Building";"Pylon";NA;139;0
"Building";"FleetBeacon";NA;135;0
"Building";"HighTemplar";NA;143;0
"Building";"HighTemplar";NA;143;0
"Building";"HighTemplar";NA;143;0
"Building";"HighTemplar";NA;143;0
"Unit";"Zealot";"Gateway";143;2
"Unit";"Zealot";"Gateway";143;2
"Unit";"Immortal";"Robotics Facility";139;4
"Unit";"Archon";"High Templar";143;0
"Unit";"Archon";"High Templar";143;0
"Unit";"Zealot";"Gateway";151;2
"Unit";"Zealot";"Gateway";151;2
"Building";"Pylon";NA;147;0
"Upgrade";"ProtossGroundWeaponsLevel2";"Forge";130;0
"Building";"HighTemplar";NA;155;0
"Building";"HighTemplar";NA;155;0
"Building";"HighTemplar";NA;155;0
"Building";"Nexus";NA;139;0
"Building";"HighTemplar";NA;155;0
"Building";"Gateway";NA;143;0
"Unit";"Zealot";"Gateway";155;2
"Unit";"Zealot";"Gateway";155;2
"Building";"PhotonCannon";NA;159;0
"Building";"PhotonCannon";NA;159;0
"Building";"Pylon";NA;159;0
"Building";"PhotonCannon";NA;159;0
"Unit";"Zealot";"Gateway";159;2
"Unit";"Zealot";"Gateway";159;2
"Unit";"Zealot";"Gateway";159;2
"Unit";"Zealot";"Gateway";159;2
"Unit";"Zealot";"Gateway";159;2
"Building";"Pylon";NA;159;0
"Building";"PhotonCannon";NA;159;0
"Building";"Pylon";NA;159;0
"Unit";"Zealot";"Gateway";169;2
"Building";"ShieldBattery";NA;159;0
"Unit";"Zealot";"Gateway";169;2
"Building";"ShieldBattery";NA;159;0
"Building";"ShieldBattery";NA;159;0
"Unit";"Immortal";"Robotics Facility";159;4
"Building";"HighTemplar";NA;184;0
"Building";"HighTemplar";NA;184;0
"Building";"HighTemplar";NA;184;0
"Building";"HighTemplar";NA;184;0
"Unit";"Zealot";"Gateway";184;2
"Unit";"Zealot";"Gateway";184;2
"Unit";"Zealot";"Gateway";184;2
"Unit";"Zealot";"Gateway";184;2
"Building";"Gateway";NA;159;0
"Unit";"Archon";"High Templar";192;0
"Unit";"Archon";"High Templar";192;0
"Unit";"Observer";"Robotics Facility";180;1
"Building";"OracleStasisTrap";NA;192;0
"Building";"OracleStasisTrap";NA;193;0
"Building";"PhotonCannon";NA;192;0
"Building";"PhotonCannon";NA;192;0
"Unit";"Zealot";"Gateway";193;2
"Unit";"Zealot";"Gateway";193;2
"Unit";"Zealot";"Gateway";193;2
"Unit";"Zealot";"Gateway";193;2
"Unit";"Oracle";"Stargate";193;3
"Unit";"Zealot";"Gateway";204;2
"Unit";"Zealot";"Gateway";204;2
"Unit";"Zealot";"Gateway";204;2
"Unit";"Zealot";"Gateway";204;2
"Unit";"Zealot";"Gateway";204;2
"Unit";"Immortal";"Robotics Facility";193;4
"Upgrade";"ProtossShieldsLevel1";"Forge";177;0
"Upgrade";"ProtossAirWeaponsLevel1";"CyberneticsCore";177;0
"Building";"Stargate";NA;193;0
"Building";"Stargate";NA;193;0
"Unit";"Zealot";"Gateway";218;2
"Unit";"Zealot";"Gateway";218;2
"Unit";"Zealot";"Gateway";218;2
"Unit";"Zealot";"Gateway";218;2
"Unit";"Zealot";"Gateway";218;2
"Unit";"Zealot";"Gateway";218;2
"Unit";"Zealot";"Gateway";218;2
"Building";"HighTemplar";NA;232;0
"Building";"HighTemplar";NA;232;0
"Building";"HighTemplar";NA;232;0
"Building";"HighTemplar";NA;232;0
"Unit";"Mothership";"Mothership Core";193;6
"Unit";"Archon";"High Templar";238;0
"Unit";"Archon";"High Templar";238;0
"Unit";"Zealot";"Gateway";238;2
"Unit";"Zealot";"Gateway";238;2
"Unit";"Carrier";"Stargate";218;6
"Unit";"Carrier";"Stargate";218;6
"Unit";"Carrier";"Stargate";218;6
"Building";"PhotonCannon";NA;242;0
"Building";"Pylon";NA;264;0
"Building";"Pylon";NA;265;0
"Building";"DarkShrine";NA;265;0
"Unit";"Carrier";"Stargate";264;6
"Building";"Pylon";NA;279;0
"Building";"Assimilator";NA;279;0
"Building";"Pylon";NA;279;0
"Building";"Pylon";NA;279;0
"Building";"Assimilator";NA;279;0
"Unit";"Zealot";"Gateway";285;2
"Unit";"Zealot";"Gateway";285;2
"Unit";"Zealot";"Gateway";285;2
"Unit";"Adept";"Gateway";289;2
"Upgrade";"ProtossAirWeaponsLevel2";"CyberneticsCore";265;0
"Unit";"Zealot";"Gateway";293;2
"Unit";"Zealot";"Gateway";295;2
"Upgrade";"ProtossShieldsLevel2";"Forge";267;0
"Building";"PhotonCannon";NA;285;0
"Building";"PhotonCannon";NA;285;0
"Building";"PhotonCannon";NA;285;0
"Building";"PhotonCannon";NA;285;0
"Building";"ShieldBattery";NA;287;0
"Building";"ShieldBattery";NA;287;0
"Building";"Nexus";NA;279;0
"Unit";"Zealot";"Gateway";297;2
"Unit";"Zealot";"Gateway";297;2
"Unit";"Zealot";"Gateway";297;2
"Unit";"Zealot";"Gateway";297;2
"Unit";"Zealot";"Gateway";297;2
"Unit";"Zealot";"Gateway";297;2
"Unit";"Zealot";"Gateway";297;2
"Building";"Pylon";NA;311;0
"Building";"Pylon";NA;311;0
"Building";"Assimilator";NA;311;0
"Building";"Assimilator";NA;311;0
"Building";"Pylon";NA;311;0
