"type";"unit_name";"on_building";"total_supply";"supply"
"Building";"Pylon";NA;13;0
"Building";"Assimilator";NA;16;0
"Building";"Gateway";NA;15;0
"Building";"Assimilator";NA;19;0
"Building";"CyberneticsCore";NA;19;0
"Building";"Pylon";NA;20;0
"Unit";"Adept";"Gateway";21;2
"Building";"Nexus";NA;19;0
"Unit";"Adept";"Gateway";22;2
"Building";"Stargate";NA;25;0
"Unit";"Adept";"Gateway";30;2
"Building";"Gateway";NA;30;0
"Building";"ShieldBattery";NA;38;0
"Building";"ShieldBattery";NA;38;0
"Unit";"Stalker";"Gateway";38;2
"Building";"Pylon";NA;39;0
"Unit";"Sentry";"Gateway";42;2
"Unit";"Stalker";"Gateway";42;2
"Building";"ShieldBattery";NA;40;0
"Building";"Gateway";NA;40;0
"Unit";"Sentry";"Gateway";46;2
"Unit";"Stalker";"Gateway";46;2
"Building";"ShieldBattery";NA;46;0
"Building";"Pylon";NA;51;0
"Building";"Pylon";NA;51;0
"Unit";"Zealot";"Gateway";51;2
"Unit";"Zealot";"Gateway";51;2
"Unit";"Zealot";"Gateway";51;2
"Building";"Assimilator";NA;51;0
"Building";"Assimilator";NA;51;0
"Building";"TwilightCouncil";NA;51;0
"Building";"Pylon";NA;64;0
"Building";"TemplarArchive";NA;64;0
"Building";"RoboticsFacility";NA;62;0
"Building";"Pylon";NA;68;0
"Building";"Gateway";NA;64;0
"Building";"Pylon";NA;70;0
"Unit";"Oracle";"Stargate";68;3
"Building";"ShieldBattery";NA;75;0
"Upgrade";"Charge";"TwilightCouncil";68;0
"Building";"Nexus";NA;68;0
"Unit";"Immortal";"Robotics Facility";75;4
"Building";"Forge";NA;75;0
"Building";"HighTemplar";NA;79;0
"Building";"HighTemplar";NA;79;0
"Building";"HighTemplar";NA;79;0
"Building";"HighTemplar";NA;79;0
"Building";"Assimilator";NA;76;0
"Building";"Gateway";NA;75;0
"Building";"Gateway";NA;75;0
"Building";"Gateway";NA;76;0
"Building";"Gateway";NA;76;0
"Unit";"Archon";"High Templar";86;0
"Unit";"Archon";"High Templar";86;0
"Building";"Assimilator";NA;83;0
"Building";"Pylon";NA;88;0
"Building";"Pylon";NA;89;0
"Unit";"Immortal";"Robotics Facility";87;4
"Building";"Pylon";NA;94;0
"Building";"Pylon";NA;94;0
"Building";"Pylon";NA;94;0
"Upgrade";"ProtossGroundWeaponsLevel1";"Forge";83;0
"Building";"HighTemplar";NA;98;0
"Building";"HighTemplar";NA;98;0
"Building";"PhotonCannon";NA;94;0
"Unit";"Sentry";"Gateway";99;2
"Unit";"Sentry";"Gateway";99;2
"Building";"HighTemplar";NA;103;0
"Building";"HighTemplar";NA;103;0
"Building";"Pylon";NA;98;0
"Building";"HighTemplar";NA;103;0
"Building";"HighTemplar";NA;103;0
"Unit";"Immortal";"Robotics Facility";98;4
"Building";"Pylon";NA;103;0
"Building";"Pylon";NA;103;0
"Unit";"Zealot";"Gateway";107;2
"Unit";"Zealot";"Gateway";107;2
"Unit";"Zealot";"Gateway";107;2
"Unit";"Zealot";"Gateway";107;2
"Unit";"Zealot";"Gateway";107;2
"Unit";"Zealot";"Gateway";107;2
"Unit";"Zealot";"Gateway";107;2
"Unit";"Zealot";"Gateway";107;2
"Building";"PhotonCannon";NA;107;0
"Unit";"Immortal";"Robotics Facility";103;4
"Building";"PhotonCannon";NA;107;0
"Building";"PhotonCannon";NA;107;0
"Building";"PhotonCannon";NA;107;0
"Building";"PhotonCannon";NA;107;0
"Building";"ShieldBattery";NA;107;0
"Building";"ShieldBattery";NA;107;0
"Building";"Nexus";NA;103;0
"Building";"HighTemplar";NA;127;0
"Building";"HighTemplar";NA;127;0
"Building";"HighTemplar";NA;127;0
"Building";"HighTemplar";NA;127;0
"Building";"HighTemplar";NA;127;0
"Building";"HighTemplar";NA;127;0
"Building";"HighTemplar";NA;127;0
"Building";"HighTemplar";NA;127;0
"Unit";"Archon";"High Templar";127;0
"Unit";"Archon";"High Templar";127;0
"Unit";"Archon";"High Templar";128;0
"Upgrade";"ProtossGroundWeaponsLevel2";"Forge";99;0
"Unit";"Archon";"High Templar";128;0
"Building";"Assimilator";NA;130;0
"Unit";"Zealot";"Gateway";131;2
"Building";"Assimilator";NA;131;0
"Building";"Pylon";NA;131;0
"Building";"HighTemplar";NA;133;0
"Building";"HighTemplar";NA;133;0
"Building";"OracleStasisTrap";NA;137;0
"Building";"HighTemplar";NA;137;0
"Building";"HighTemplar";NA;137;0
"Building";"HighTemplar";NA;137;0
"Unit";"Zealot";"Gateway";137;2
"Building";"FleetBeacon";NA;131;0
"Unit";"Zealot";"Gateway";137;2
"Unit";"Zealot";"Gateway";137;2
"Building";"Pylon";NA;137;0
"Building";"Pylon";NA;137;0
"Building";"PhotonCannon";NA;137;0
"Building";"DarkShrine";NA;131;0
"Building";"PhotonCannon";NA;145;0
"Building";"PhotonCannon";NA;145;0
"Building";"Gateway";NA;145;0
"Building";"HighTemplar";NA;145;0
"Building";"HighTemplar";NA;145;0
"Building";"HighTemplar";NA;145;0
"Building";"Gateway";NA;145;0
"Building";"HighTemplar";NA;145;0
"Building";"HighTemplar";NA;145;0
"Building";"HighTemplar";NA;145;0
"Building";"Gateway";NA;145;0
"Unit";"Observer";"Robotics Facility";145;1
"Building";"Gateway";NA;145;0
"Unit";"Archon";"High Templar";145;0
"Unit";"Archon";"High Templar";145;0
"Upgrade";"ProtossGroundWeaponsLevel3";"Forge";133;0
"Building";"Pylon";NA;146;0
"Building";"RoboticsBay";NA;146;0
"Building";"CyberneticsCore";NA;146;0
"Building";"DarkTemplar";NA;146;0
"Building";"Assimilator";NA;146;0
"Building";"DarkTemplar";NA;146;0
"Building";"DarkTemplar";NA;146;0
"Building";"Pylon";NA;146;0
"Unit";"Zealot";"Gateway";146;2
"Unit";"Zealot";"Gateway";146;2
"Unit";"Zealot";"Gateway";146;2
"Building";"Assimilator";NA;146;0
"Building";"Stargate";NA;146;0
"Building";"Stargate";NA;146;0
"Building";"Stargate";NA;146;0
"Unit";"Mothership";"Mothership Core";146;6
"Building";"Nexus";NA;146;0
"Upgrade";"ProtossAirWeaponsLevel1";"CyberneticsCore";146;0
"Unit";"Zealot";"Gateway";158;2
"Unit";"Zealot";"Gateway";158;2
"Unit";"Zealot";"Gateway";158;2
"Unit";"Zealot";"Gateway";158;2
"Unit";"Zealot";"Gateway";158;2
"Unit";"Zealot";"Gateway";158;2
"Unit";"Zealot";"Gateway";158;2
"Unit";"Zealot";"Gateway";158;2
"Unit";"Carrier";"Stargate";152;6
"Unit";"Carrier";"Stargate";152;6
"Unit";"Carrier";"Stargate";152;6
"Unit";"Carrier";"Stargate";152;6
"Building";"Pylon";NA;192;0
"Building";"Pylon";NA;192;0
"Building";"Pylon";NA;198;0
"Building";"Assimilator";NA;198;0
"Upgrade";"ProtossAirArmorsLevel1";"CyberneticsCore";158;0
"Building";"HighTemplar";NA;198;0
"Building";"HighTemplar";NA;198;0
"Unit";"Zealot";"Gateway";198;2
"Unit";"Zealot";"Gateway";198;2
"Unit";"Zealot";"Gateway";198;2
"Unit";"Carrier";"Stargate";174;6
"Unit";"Carrier";"Stargate";186;6
"Building";"Stargate";NA;198;0
"Building";"Stargate";NA;198;0
"Building";"Nexus";NA;192;0
"Building";"ShieldBattery";NA;204;0
"Unit";"Archon";"High Templar";216;0
"Unit";"Carrier";"Stargate";198;6
"Unit";"Carrier";"Stargate";198;6
"Upgrade";"ProtossAirWeaponsLevel2";"CyberneticsCore";192;0
"Upgrade";"ProtossShieldsLevel1";"Forge";198;0
"Building";"HighTemplar";NA;228;0
"Building";"HighTemplar";NA;228;0
"Building";"HighTemplar";NA;228;0
"Building";"HighTemplar";NA;228;0
"Unit";"Carrier";"Stargate";216;6
"Unit";"Archon";"High Templar";228;0
"Unit";"Archon";"High Templar";228;0
"Building";"HighTemplar";NA;228;0
"Building";"HighTemplar";NA;228;0
"Building";"Pylon";NA;228;0
"Building";"Pylon";NA;234;0
"Building";"Pylon";NA;234;0
"Building";"Nexus";NA;228;0
"Unit";"Mothership";"Mothership Core";228;6
"Upgrade";"ProtossShieldsLevel2";"Forge";228;0
"Upgrade";"ProtossAirArmorsLevel2";"CyberneticsCore";228;0
"Unit";"Carrier";"Stargate";234;6
"Upgrade";"ProtossAirWeaponsLevel3";"CyberneticsCore";228;0
"Building";"PhotonCannon";NA;240;0
"Building";"PhotonCannon";NA;240;0
"Building";"PhotonCannon";NA;240;0
"Building";"PhotonCannon";NA;240;0
"Building";"Assimilator";NA;246;0
