"type";"unit_name";"on_building";"total_supply";"supply"
"Building";"Pylon";NA;13;0
"Building";"Assimilator";NA;15;0
"Building";"Gateway";NA;15;0
"Building";"Pylon";NA;19;0
"Building";"CyberneticsCore";NA;19;0
"Unit";"Zealot";"Gateway";20;2
"Building";"Assimilator";NA;21;0
"Unit";"Zealot";"Gateway";21;2
"Building";"Gateway";NA;20;0
"Building";"Pylon";NA;25;0
"Unit";"Adept";"Gateway";25;2
"Building";"TwilightCouncil";NA;31;0
"Building";"Nexus";NA;28;0
"Building";"RoboticsFacility";NA;32;0
"Building";"Pylon";NA;36;0
"Unit";"Adept";"Gateway";40;2
"Building";"DarkShrine";NA;34;0
"Building";"Gateway";NA;39;0
"Building";"Gateway";NA;39;0
"Building";"Assimilator";NA;44;0
"Building";"DarkTemplar";NA;47;0
"Building";"DarkTemplar";NA;47;0
"Building";"Pylon";NA;45;0
"Building";"DarkTemplar";NA;49;0
"Building";"DarkTemplar";NA;49;0
"Building";"Assimilator";NA;47;0
"Unit";"Zealot";"Gateway";53;2
"Unit";"Zealot";"Gateway";53;2
"Unit";"Zealot";"Gateway";59;2
"Unit";"Zealot";"Gateway";59;2
"Building";"Pylon";NA;63;0
"Building";"DarkTemplar";NA;64;0
"Building";"DarkTemplar";NA;64;0
"Building";"Pylon";NA;63;0
"Building";"DarkTemplar";NA;64;0
"Unit";"Immortal";"Robotics Facility";63;4
"Building";"Gateway";NA;63;0
"Building";"Gateway";NA;63;0
"Building";"Gateway";NA;63;0
"Building";"Gateway";NA;63;0
"Unit";"Sentry";"Gateway";70;2
"Unit";"Zealot";"Gateway";70;2
"Unit";"Zealot";"Gateway";70;2
"Unit";"Zealot";"Gateway";70;2
"Building";"Pylon";NA;69;0
"Unit";"Immortal";"Robotics Facility";64;4
"Building";"Nexus";NA;63;0
"Unit";"Archon";"High Templar";79;0
"Unit";"Sentry";"Gateway";83;2
"Unit";"Sentry";"Gateway";83;2
"Unit";"Sentry";"Gateway";83;2
"Unit";"Zealot";"Gateway";83;2
"Unit";"Zealot";"Gateway";83;2
"Unit";"Zealot";"Gateway";93;2
"Unit";"Zealot";"Gateway";93;2
"Unit";"Zealot";"Gateway";93;2
"Upgrade";"Charge";"TwilightCouncil";64;0
"Unit";"Immortal";"Robotics Facility";79;4
"Unit";"Zealot";"Gateway";105;2
"Unit";"Zealot";"Gateway";105;2
"Unit";"Zealot";"Gateway";105;2
"Unit";"Zealot";"Gateway";105;2
"Unit";"Zealot";"Gateway";105;2
"Building";"Pylon";NA;116;0
"Building";"TemplarArchive";NA;104;0
"Building";"HighTemplar";NA;119;0
"Building";"HighTemplar";NA;119;0
"Building";"HighTemplar";NA;119;0
"Building";"HighTemplar";NA;119;0
"Unit";"Zealot";"Gateway";119;2
"Unit";"Immortal";"Robotics Facility";116;4
"Unit";"Archon";"High Templar";121;0
"Unit";"Archon";"High Templar";122;0
"Building";"ShieldBattery";NA;119;0
"Building";"ShieldBattery";NA;119;0
"Building";"Pylon";NA;128;0
"Building";"Pylon";NA;128;0
"Building";"Pylon";NA;128;0
"Building";"Gateway";NA;119;0
"Unit";"Zealot";"Gateway";130;2
"Unit";"Zealot";"Gateway";130;2
"Unit";"Zealot";"Gateway";130;2
"Unit";"Zealot";"Gateway";130;2
"Unit";"Immortal";"Robotics Facility";128;4
"Unit";"Zealot";"Gateway";141;2
"Building";"Pylon";NA;141;0
"Building";"Pylon";NA;141;0
"Unit";"Observer";"Robotics Facility";141;1
"Building";"Pylon";NA;145;0
"Building";"Forge";NA;141;0
"Building";"Pylon";NA;147;0
"Building";"HighTemplar";NA;148;0
"Building";"HighTemplar";NA;148;0
"Building";"HighTemplar";NA;148;0
"Building";"HighTemplar";NA;148;0
"Unit";"Zealot";"Gateway";148;2
"Unit";"Zealot";"Gateway";148;2
"Unit";"Zealot";"Gateway";148;2
"Unit";"Zealot";"Gateway";148;2
"Unit";"Archon";"High Templar";156;0
"Unit";"Archon";"High Templar";156;0
"Building";"Pylon";NA;148;0
"Building";"Pylon";NA;156;0
"Building";"Pylon";NA;156;0
"Building";"Assimilator";NA;156;0
"Unit";"Immortal";"Robotics Facility";147;4
"Building";"Assimilator";NA;156;0
"Building";"PhotonCannon";NA;156;0
"Building";"PhotonCannon";NA;156;0
"Building";"HighTemplar";NA;160;0
"Building";"HighTemplar";NA;160;0
"Unit";"Zealot";"Gateway";160;2
"Unit";"Zealot";"Gateway";160;2
"Unit";"Zealot";"Gateway";160;2
"Unit";"Zealot";"Gateway";160;2
"Unit";"Immortal";"Robotics Facility";156;4
"Unit";"Archon";"High Templar";160;0
"Building";"HighTemplar";NA;172;0
"Building";"HighTemplar";NA;172;0
"Building";"Nexus";NA;156;0
"Unit";"Zealot";"Gateway";172;2
"Unit";"Zealot";"Gateway";172;2
"Unit";"Zealot";"Gateway";172;2
"Unit";"Zealot";"Gateway";172;2
"Unit";"Zealot";"Gateway";172;2
"Unit";"Archon";"High Templar";172;0
"Unit";"Zealot";"Gateway";182;2
"Unit";"Zealot";"Gateway";182;2
"Unit";"Immortal";"Robotics Facility";160;4
"Building";"PhotonCannon";NA;172;0
"Upgrade";"ProtossGroundWeaponsLevel1";"Forge";156;0
"Unit";"Zealot";"Gateway";190;2
"Unit";"Zealot";"Gateway";190;2
"Unit";"Zealot";"Gateway";190;2
"Unit";"Zealot";"Gateway";190;2
"Unit";"Zealot";"Gateway";190;2
"Unit";"Zealot";"Gateway";190;2
"Building";"HighTemplar";NA;202;0
"Building";"HighTemplar";NA;202;0
"Building";"HighTemplar";NA;202;0
"Building";"HighTemplar";NA;202;0
"Unit";"Zealot";"Gateway";202;2
"Unit";"Zealot";"Gateway";202;2
"Unit";"Zealot";"Gateway";202;2
"Unit";"Zealot";"Gateway";202;2
"Unit";"Zealot";"Gateway";202;2
"Unit";"Archon";"High Templar";202;0
"Unit";"Archon";"High Templar";212;0
"Unit";"Immortal";"Robotics Facility";190;4
"Unit";"Zealot";"Gateway";216;2
"Building";"DarkTemplar";NA;216;0
"Building";"DarkTemplar";NA;216;0
"Unit";"Zealot";"Gateway";216;2
"Unit";"Zealot";"Gateway";216;2
"Unit";"Zealot";"Gateway";222;2
"Unit";"Zealot";"Gateway";222;2
"Unit";"Zealot";"Gateway";222;2
"Unit";"Zealot";"Gateway";222;2
"Unit";"Zealot";"Gateway";230;2
"Unit";"Zealot";"Gateway";232;2
"Unit";"Zealot";"Gateway";232;2
"Unit";"Zealot";"Gateway";232;2
"Unit";"Immortal";"Robotics Facility";216;4
