"type";"unit_name";"on_building";"total_supply";"supply"
"Building";"Pylon";NA;13;0
"Building";"Assimilator";NA;14;0
"Building";"Gateway";NA;16;0
"Building";"Assimilator";NA;20;0
"Building";"CyberneticsCore";NA;20;0
"Building";"Pylon";NA;21;0
"Unit";"Adept";"Gateway";22;2
"Building";"Nexus";NA;19;0
"Building";"Stargate";NA;23;0
"Unit";"Adept";"Gateway";26;2
"Unit";"Oracle";"Stargate";29;3
"Building";"Assimilator";NA;35;0
"Building";"Assimilator";NA;35;0
"Building";"Pylon";NA;42;0
"Building";"RoboticsFacility";NA;37;0
"Building";"TwilightCouncil";NA;44;0
"Building";"Gateway";NA;44;0
"Unit";"Phoenix";"Stargate";46;2
"Building";"Gateway";NA;46;0
"Building";"Pylon";NA;47;0
"Building";"Gateway";NA;46;0
"Building";"TemplarArchive";NA;47;0
"Building";"Pylon";NA;51;0
"Building";"HighTemplar";NA;53;0
"Building";"HighTemplar";NA;53;0
"Building";"HighTemplar";NA;53;0
"Building";"HighTemplar";NA;53;0
"Building";"Pylon";NA;53;0
"Unit";"Archon";"High Templar";53;0
"Unit";"Archon";"High Templar";53;0
"Unit";"Observer";"Robotics Facility";53;1
"Building";"Pylon";NA;54;0
"Building";"Forge";NA;56;0
"Building";"Nexus";NA;53;0
"Building";"Gateway";NA;55;0
"Building";"HighTemplar";NA;64;0
"Building";"HighTemplar";NA;64;0
"Building";"HighTemplar";NA;64;0
"Unit";"Immortal";"Robotics Facility";59;4
"Building";"HighTemplar";NA;65;0
"Unit";"Archon";"High Templar";65;0
"Building";"OracleStasisTrap";NA;71;0
"Building";"ShieldBattery";NA;62;0
"Building";"Assimilator";NA;64;0
"Building";"Gateway";NA;60;0
"Building";"Gateway";NA;60;0
"Building";"Assimilator";NA;65;0
"Building";"Gateway";NA;61;0
"Unit";"Immortal";"Robotics Facility";72;4
"Building";"Pylon";NA;77;0
"Building";"Pylon";NA;78;0
"Building";"Pylon";NA;78;0
"Building";"Pylon";NA;78;0
"Building";"HighTemplar";NA;83;0
"Building";"HighTemplar";NA;83;0
"Building";"HighTemplar";NA;83;0
"Building";"Pylon";NA;83;0
"Unit";"Immortal";"Robotics Facility";79;4
"Unit";"Zealot";"Gateway";86;2
"Building";"HighTemplar";NA;92;0
"Building";"HighTemplar";NA;92;0
"Building";"Gateway";NA;83;0
"Building";"HighTemplar";NA;92;0
"Upgrade";"ProtossGroundWeaponsLevel1";"Forge";76;0
"Building";"Gateway";NA;83;0
"Building";"Pylon";NA;92;0
"Building";"Pylon";NA;92;0
"Unit";"Archon";"High Templar";92;0
"Unit";"Immortal";"Robotics Facility";86;4
"Building";"PhotonCannon";NA;92;0
"Building";"Gateway";NA;86;0
"Building";"Pylon";NA;92;0
"Building";"HighTemplar";NA;96;0
"Building";"HighTemplar";NA;96;0
"Building";"PhotonCannon";NA;92;0
"Building";"PhotonCannon";NA;92;0
"Building";"ShieldBattery";NA;92;0
"Unit";"Observer";"Robotics Facility";92;1
"Unit";"Archon";"High Templar";96;0
"Building";"PhotonCannon";NA;92;0
"Unit";"Zealot";"Gateway";97;2
"Unit";"Zealot";"Gateway";97;2
"Unit";"Zealot";"Gateway";97;2
"Unit";"Zealot";"Gateway";97;2
"Building";"PhotonCannon";NA;92;0
"Building";"PhotonCannon";NA;92;0
"Building";"PhotonCannon";NA;96;0
"Building";"HighTemplar";NA;105;0
"Building";"HighTemplar";NA;105;0
"Building";"PhotonCannon";NA;96;0
"Building";"PhotonCannon";NA;96;0
"Building";"HighTemplar";NA;105;0
"Building";"Pylon";NA;105;0
"Unit";"Archon";"High Templar";105;0
"Unit";"Zealot";"Gateway";105;2
"Unit";"Zealot";"Gateway";105;2
"Unit";"Zealot";"Gateway";105;2
"Unit";"Zealot";"Gateway";105;2
"Unit";"Zealot";"Gateway";105;2
"Unit";"Zealot";"Gateway";105;2
"Unit";"Zealot";"Gateway";105;2
"Unit";"Zealot";"Gateway";105;2
"Building";"OracleStasisTrap";NA;121;0
"Unit";"Observer";"Robotics Facility";105;1
"Building";"HighTemplar";NA;122;0
"Building";"Assimilator";NA;122;0
"Building";"Assimilator";NA;122;0
"Building";"Nexus";NA;105;0
"Unit";"Zealot";"Gateway";122;2
"Unit";"Zealot";"Gateway";122;2
"Unit";"Zealot";"Gateway";122;2
"Building";"ShieldBattery";NA;122;0
"Building";"ShieldBattery";NA;122;0
"Building";"PhotonCannon";NA;122;0
"Building";"PhotonCannon";NA;122;0
"Building";"ShieldBattery";NA;122;0
"Building";"HighTemplar";NA;128;0
"Building";"HighTemplar";NA;128;0
"Building";"HighTemplar";NA;128;0
"Building";"HighTemplar";NA;128;0
"Upgrade";"ProtossGroundWeaponsLevel2";"Forge";97;0
"Unit";"Archon";"High Templar";128;0
"Building";"PhotonCannon";NA;122;0
"Unit";"Archon";"High Templar";128;0
"Building";"Pylon";NA;128;0
"Building";"HighTemplar";NA;128;0
"Building";"HighTemplar";NA;128;0
"Building";"OracleStasisTrap";NA;128;0
"Upgrade";"Charge";"TwilightCouncil";122;0
"Unit";"Observer";"Robotics Facility";128;1
"Unit";"Zealot";"Gateway";128;2
"Unit";"Zealot";"Gateway";128;2
"Unit";"Zealot";"Gateway";128;2
"Unit";"Zealot";"Gateway";128;2
"Unit";"Zealot";"Gateway";128;2
"Unit";"Zealot";"Gateway";128;2
"Unit";"Zealot";"Gateway";128;2
"Unit";"Zealot";"Gateway";128;2
"Unit";"Zealot";"Gateway";128;2
"Building";"FleetBeacon";NA;128;0
"Unit";"Zealot";"Gateway";147;2
"Unit";"Zealot";"Gateway";147;2
"Unit";"Observer";"Robotics Facility";128;1
"Building";"OracleStasisTrap";NA;151;0
"Building";"RoboticsFacility";NA;128;0
"Building";"HighTemplar";NA;152;0
"Building";"HighTemplar";NA;152;0
"Building";"HighTemplar";NA;152;0
"Building";"HighTemplar";NA;152;0
"Building";"HighTemplar";NA;152;0
"Building";"HighTemplar";NA;152;0
"Building";"OracleStasisTrap";NA;155;0
"Unit";"Immortal";"Robotics Facility";151;4
"Building";"OracleStasisTrap";NA;162;0
"Building";"HighTemplar";NA;168;0
"Building";"HighTemplar";NA;168;0
"Unit";"Immortal";"Robotics Facility";155;4
"Building";"Nexus";NA;152;0
"Building";"HighTemplar";NA;175;0
"Building";"HighTemplar";NA;175;0
"Unit";"Archon";"High Templar";175;0
"Building";"Pylon";NA;168;0
"Unit";"Immortal";"Robotics Facility";162;4
"Unit";"Mothership";"Mothership Core";152;6
"Upgrade";"ProtossGroundWeaponsLevel3";"Forge";128;0
"Unit";"Archon";"High Templar";178;0
"Building";"HighTemplar";NA;188;0
"Building";"HighTemplar";NA;188;0
"Unit";"Zealot";"Gateway";191;2
"Unit";"Zealot";"Gateway";191;2
"Unit";"Zealot";"Gateway";191;2
"Unit";"Zealot";"Gateway";191;2
"Unit";"Zealot";"Gateway";191;2
"Upgrade";"ProtossAirWeaponsLevel1";"CyberneticsCore";152;0
"Unit";"Immortal";"Robotics Facility";167;4
"Unit";"Archon";"High Templar";192;0
"Unit";"Stalker";"Gateway";209;2
"Unit";"Stalker";"Gateway";209;2
"Unit";"Stalker";"Gateway";209;2
"Unit";"Archon";"High Templar";211;0
"Unit";"Zealot";"Gateway";215;2
"Unit";"Zealot";"Gateway";215;2
"Unit";"Zealot";"Gateway";215;2
"Unit";"Zealot";"Gateway";215;2
"Unit";"Zealot";"Gateway";215;2
"Unit";"Zealot";"Gateway";215;2
"Unit";"Zealot";"Gateway";215;2
"Building";"Stargate";NA;203;0
"Building";"Stargate";NA;203;0
"Unit";"Zealot";"Gateway";232;2
"Unit";"Zealot";"Gateway";232;2
"Unit";"Zealot";"Gateway";232;2
"Unit";"Zealot";"Gateway";232;2
"Unit";"Zealot";"Gateway";232;2
"Unit";"Zealot";"Gateway";232;2
"Unit";"Immortal";"Robotics Facility";232;4
"Unit";"Zealot";"Gateway";250;2
"Unit";"Zealot";"Gateway";250;2
"Unit";"Zealot";"Gateway";250;2
"Unit";"Zealot";"Gateway";250;2
"Unit";"Zealot";"Gateway";250;2
"Unit";"Zealot";"Gateway";250;2
"Unit";"Zealot";"Gateway";250;2
"Unit";"Zealot";"Gateway";250;2
"Unit";"Zealot";"Gateway";250;2
"Unit";"Tempest";"Stargate";250;4
"Unit";"Tempest";"Stargate";250;4
"Unit";"Tempest";"Stargate";250;4
"Building";"Assimilator";NA;280;0
"Building";"OracleStasisTrap";NA;280;0
"Building";"Assimilator";NA;280;0
"Building";"HighTemplar";NA;280;0
"Building";"OracleStasisTrap";NA;280;0
"Building";"HighTemplar";NA;280;0
"Building";"HighTemplar";NA;280;0
"Building";"HighTemplar";NA;280;0
"Building";"HighTemplar";NA;280;0
"Building";"HighTemplar";NA;280;0
"Building";"PhotonCannon";NA;280;0
"Upgrade";"ProtossShieldsLevel1";"Forge";250;0
"Unit";"Archon";"High Templar";280;0
"Unit";"Archon";"High Templar";280;0
"Building";"Pylon";NA;280;0
"Building";"HighTemplar";NA;280;0
"Upgrade";"ProtossAirWeaponsLevel2";"CyberneticsCore";250;0
"Unit";"Carrier";"Stargate";250;6
"Unit";"Carrier";"Stargate";268;6
"Unit";"Carrier";"Stargate";268;6
"Building";"PhotonCannon";NA;280;0
"Building";"PhotonCannon";NA;282;0
"Building";"Stargate";NA;282;0
"Unit";"Observer";"Robotics Facility";300;1
"Unit";"Carrier";"Stargate";280;6
"Unit";"Observer";"Robotics Facility";308;1
"Building";"HighTemplar";NA;315;0
"Building";"HighTemplar";NA;315;0
"Upgrade";"ProtossShieldsLevel2";"Forge";288;0
"Building";"PhotonCannon";NA;315;0
"Building";"PhotonCannon";NA;315;0
"Unit";"Carrier";"Stargate";305;6
