"type";"unit_name";"on_building";"total_supply";"supply"
"Building";"Pylon";NA;12;0
"Building";"Assimilator";NA;14;0
"Building";"Gateway";NA;16;0
"Building";"Assimilator";NA;20;0
"Building";"CyberneticsCore";NA;20;0
"Building";"Pylon";NA;21;0
"Unit";"Adept";"Gateway";22;2
"Building";"Nexus";NA;20;0
"Unit";"Adept";"Gateway";24;2
"Building";"Stargate";NA;23;0
"Unit";"Oracle";"Stargate";30;3
"Building";"Pylon";NA;36;0
"Building";"Assimilator";NA;38;0
"Building";"Assimilator";NA;41;0
"Unit";"Phoenix";"Stargate";38;2
"Building";"Gateway";NA;37;0
"Building";"Pylon";NA;50;0
"Building";"RoboticsFacility";NA;44;0
"Building";"TwilightCouncil";NA;49;0
"Building";"Pylon";NA;53;0
"Unit";"Zealot";"Gateway";54;2
"Unit";"Zealot";"Gateway";54;2
"Building";"Gateway";NA;51;0
"Building";"Gateway";NA;52;0
"Building";"TemplarArchive";NA;54;0
"Building";"Pylon";NA;58;0
"Unit";"Observer";"Robotics Facility";58;1
"Building";"HighTemplar";NA;58;0
"Building";"HighTemplar";NA;58;0
"Building";"HighTemplar";NA;58;0
"Building";"HighTemplar";NA;58;0
"Building";"Pylon";NA;58;0
"Unit";"Archon";"High Templar";59;0
"Unit";"Archon";"High Templar";59;0
"Building";"Pylon";NA;59;0
"Building";"Forge";NA;58;0
"Upgrade";"Charge";"TwilightCouncil";54;0
"Building";"ShieldBattery";NA;59;0
"Unit";"Zealot";"Gateway";63;2
"Unit";"Zealot";"Gateway";63;2
"Unit";"Zealot";"Gateway";63;2
"Unit";"Zealot";"Gateway";63;2
"Unit";"Immortal";"Robotics Facility";59;4
"Building";"Nexus";NA;58;0
"Building";"RoboticsFacility";NA;59;0
"Unit";"Zealot";"Gateway";79;2
"Unit";"Zealot";"Gateway";79;2
"Unit";"Zealot";"Gateway";79;2
"Unit";"Zealot";"Gateway";79;2
"Unit";"Immortal";"Robotics Facility";73;4
"Building";"HighTemplar";NA;91;0
"Building";"HighTemplar";NA;91;0
"Building";"HighTemplar";NA;91;0
"Building";"HighTemplar";NA;97;0
"Building";"Assimilator";NA;89;0
"Building";"Assimilator";NA;91;0
"Unit";"Immortal";"Robotics Facility";89;4
"Building";"Gateway";NA;95;0
"Building";"Pylon";NA;106;0
"Building";"PhotonCannon";NA;104;0
"Unit";"Sentry";"Gateway";110;2
"Building";"Pylon";NA;107;0
"Building";"Pylon";NA;108;0
"Unit";"Sentry";"Gateway";112;2
"Building";"HighTemplar";NA;112;0
"Building";"Pylon";NA;108;0
"Building";"Gateway";NA;100;0
"Building";"Gateway";NA;104;0
"Building";"Pylon";NA;112;0
"Unit";"Zealot";"Gateway";114;2
"Unit";"Zealot";"Gateway";114;2
"Unit";"Zealot";"Gateway";114;2
"Unit";"Zealot";"Gateway";114;2
"Building";"Gateway";NA;106;0
"Unit";"Immortal";"Robotics Facility";109;4
"Unit";"Immortal";"Robotics Facility";109;4
"Upgrade";"ProtossGroundWeaponsLevel1";"Forge";97;0
"Building";"PhotonCannon";NA;114;0
"Building";"PhotonCannon";NA;118;0
"Building";"ShieldBattery";NA;122;0
"Unit";"Observer";"Robotics Facility";130;1
"Building";"Pylon";NA;130;0
"Building";"FleetBeacon";NA;122;0
"Unit";"Oracle";"Stargate";130;3
"Unit";"Observer";"Robotics Facility";130;1
"Building";"PhotonCannon";NA;131;0
"Building";"PhotonCannon";NA;131;0
"Unit";"Observer";"Robotics Facility";134;1
"Building";"PhotonCannon";NA;134;0
"Unit";"Oracle";"Stargate";134;3
"Building";"PhotonCannon";NA;135;0
"Unit";"Immortal";"Robotics Facility";131;4
"Building";"Nexus";NA;130;0
"Building";"OracleStasisTrap";NA;143;0
"Unit";"Immortal";"Robotics Facility";135;4
"Upgrade";"ProtossGroundWeaponsLevel2";"Forge";130;0
"Unit";"Immortal";"Robotics Facility";139;4
"Building";"Assimilator";NA;143;0
"Building";"Stargate";NA;143;0
"Building";"Stargate";NA;143;0
"Building";"OracleStasisTrap";NA;151;0
"Building";"Pylon";NA;147;0
"Building";"Assimilator";NA;143;0
"Building";"OracleStasisTrap";NA;151;0
"Unit";"Mothership";"Mothership Core";135;6
"Building";"Pylon";NA;151;0
"Building";"PhotonCannon";NA;147;0
"Building";"PhotonCannon";NA;147;0
"Unit";"Zealot";"Gateway";157;2
"Unit";"Zealot";"Gateway";157;2
"Unit";"Zealot";"Gateway";157;2
"Unit";"Zealot";"Gateway";157;2
"Unit";"Zealot";"Gateway";157;2
"Unit";"Zealot";"Gateway";157;2
"Unit";"Zealot";"Gateway";157;2
"Unit";"Zealot";"Gateway";157;2
"Building";"Pylon";NA;157;0
"Building";"Gateway";NA;157;0
"Building";"Gateway";NA;157;0
"Building";"Gateway";NA;157;0
"Building";"Gateway";NA;157;0
"Unit";"Observer";"Robotics Facility";173;1
"Unit";"Carrier";"Stargate";151;6
"Unit";"Carrier";"Stargate";151;6
"Unit";"Carrier";"Stargate";151;6
"Unit";"Zealot";"Gateway";192;2
"Unit";"Zealot";"Gateway";192;2
"Unit";"Zealot";"Gateway";192;2
"Unit";"Zealot";"Gateway";192;2
"Unit";"Zealot";"Gateway";192;2
"Upgrade";"ProtossAirWeaponsLevel1";"CyberneticsCore";173;0
"Upgrade";"ProtossGroundWeaponsLevel3";"Forge";157;0
"Building";"Pylon";NA;202;0
"Building";"Pylon";NA;202;0
"Building";"PhotonCannon";NA;202;0
"Building";"Pylon";NA;202;0
"Building";"PhotonCannon";NA;202;0
"Building";"PhotonCannon";NA;202;0
"Unit";"Carrier";"Stargate";174;6
"Unit";"Carrier";"Stargate";174;6
"Unit";"Carrier";"Stargate";174;6
"Building";"PhotonCannon";NA;202;0
"Building";"PhotonCannon";NA;202;0
"Building";"PhotonCannon";NA;202;0
"Building";"PhotonCannon";NA;202;0
"Building";"Stargate";NA;202;0
"Building";"Stargate";NA;202;0
"Building";"DarkShrine";NA;196;0
"Unit";"Oracle";"Stargate";220;3
"Building";"Pylon";NA;220;0
"Building";"OracleStasisTrap";NA;223;0
"Unit";"Zealot";"Gateway";223;2
"Unit";"Zealot";"Gateway";223;2
"Unit";"Zealot";"Gateway";223;2
"Unit";"Zealot";"Gateway";223;2
"Unit";"Zealot";"Gateway";223;2
"Unit";"Zealot";"Gateway";223;2
"Unit";"Zealot";"Gateway";223;2
"Unit";"Zealot";"Gateway";223;2
"Building";"PhotonCannon";NA;220;0
"Building";"PhotonCannon";NA;220;0
"Building";"PhotonCannon";NA;220;0
"Building";"PhotonCannon";NA;220;0
"Building";"ShieldBattery";NA;220;0
"Building";"PhotonCannon";NA;223;0
"Building";"PhotonCannon";NA;223;0
"Building";"PhotonCannon";NA;223;0
"Unit";"Carrier";"Stargate";220;6
"Unit";"Carrier";"Stargate";220;6
"Building";"Nexus";NA;220;0
"Upgrade";"ProtossShieldsLevel1";"Forge";220;0
"Upgrade";"ProtossAirWeaponsLevel2";"CyberneticsCore";220;0
"Building";"OracleStasisTrap";NA;251;0
"Building";"OracleStasisTrap";NA;251;0
"Building";"PhotonCannon";NA;251;0
"Building";"PhotonCannon";NA;251;0
"Building";"PhotonCannon";NA;251;0
"Building";"PhotonCannon";NA;251;0
"Building";"Pylon";NA;251;0
"Building";"PhotonCannon";NA;251;0
"Building";"Assimilator";NA;251;0
"Building";"PhotonCannon";NA;251;0
"Building";"Assimilator";NA;251;0
"Building";"PhotonCannon";NA;251;0
"Building";"Pylon";NA;251;0
"Building";"PhotonCannon";NA;251;0
"Building";"PhotonCannon";NA;251;0
"Unit";"Zealot";"Gateway";251;2
"Unit";"Zealot";"Gateway";251;2
"Unit";"Zealot";"Gateway";251;2
"Unit";"Zealot";"Gateway";251;2
"Unit";"Zealot";"Gateway";251;2
"Unit";"Zealot";"Gateway";251;2
"Unit";"Zealot";"Gateway";251;2
"Building";"Pylon";NA;265;0
"Building";"HighTemplar";NA;265;0
"Building";"HighTemplar";NA;265;0
"Building";"HighTemplar";NA;265;0
"Building";"HighTemplar";NA;265;0
"Building";"PhotonCannon";NA;265;0
"Building";"Nexus";NA;265;0
"Building";"HighTemplar";NA;265;0
"Building";"HighTemplar";NA;265;0
"Upgrade";"ProtossShieldsLevel2";"Forge";251;0
"Building";"PhotonCannon";NA;265;0
"Building";"PhotonCannon";NA;265;0
"Building";"PhotonCannon";NA;265;0
"Unit";"Oracle";"Stargate";265;3
"Unit";"Carrier";"Stargate";265;6
"Building";"DarkTemplar";NA;268;0
"Unit";"Carrier";"Stargate";265;6
"Unit";"Carrier";"Stargate";265;6
"Unit";"Carrier";"Stargate";265;6
"Building";"DarkTemplar";NA;268;0
"Unit";"Zealot";"Gateway";268;2
"Unit";"Zealot";"Gateway";268;2
"Unit";"Zealot";"Gateway";268;2
"Unit";"Zealot";"Gateway";268;2
"Unit";"Zealot";"Gateway";268;2
"Unit";"Zealot";"Gateway";268;2
"Unit";"Zealot";"Gateway";268;2
"Unit";"Zealot";"Gateway";268;2
"Unit";"Zealot";"Gateway";268;2
"Unit";"Zealot";"Gateway";268;2
"Unit";"Oracle";"Stargate";265;3
"Building";"Assimilator";NA;312;0
"Building";"Assimilator";NA;312;0
"Building";"Pylon";NA;312;0
"Building";"DarkTemplar";NA;315;0
"Unit";"Zealot";"Gateway";315;2
"Unit";"Zealot";"Gateway";315;2
"Unit";"Zealot";"Gateway";315;2
"Unit";"Zealot";"Gateway";315;2
"Unit";"Zealot";"Gateway";315;2
"Unit";"Zealot";"Gateway";315;2
"Unit";"Zealot";"Gateway";315;2
"Unit";"Zealot";"Gateway";315;2
"Unit";"Zealot";"Gateway";315;2
"Unit";"Zealot";"Gateway";315;2
