"type";"unit_name";"on_building";"total_supply_lag";"supply"
"Building";"Pylon";NA;14;0
"Building";"Gateway";NA;16;0
"Building";"Assimilator";NA;17;0
"Building";"Nexus";NA;20;0
"Building";"CyberneticsCore";NA;20;0
"Building";"Assimilator";NA;21;0
"Building";"Pylon";NA;22;0
"Unit";"Adept";"Gateway";23;2
"Building";"Stargate";NA;26;0
"Unit";"Adept";"Gateway";26;2
"Unit";"Adept";"Gateway";33;2
"Unit";"Phoenix";"Stargate";36;2
"Building";"Pylon";NA;42;0
"Building";"TwilightCouncil";NA;42;0
"Building";"Gateway";NA;44;0
"Unit";"Oracle";"Stargate";44;3
"Building";"Gateway";NA;49;0
"Building";"Pylon";NA;49;0
"Building";"Assimilator";NA;50;0
"Building";"Assimilator";NA;50;0
"Building";"Pylon";NA;54;0
"Unit";"Adept";"Gateway";56;2
"Unit";"Adept";"Gateway";58;2
"Building";"Nexus";NA;62;0
"Building";"Pylon";NA;62;0
"Unit";"Adept";"Gateway";62;2
"Unit";"Adept";"Gateway";64;2
"Unit";"Adept";"Gateway";66;2
"Building";"RoboticsFacility";NA;69;0
"Unit";"Sentry";"Gateway";69;2
"Unit";"Sentry";"Gateway";71;2
"Unit";"Sentry";"Gateway";73;2
"Building";"Gateway";NA;75;0
"Building";"Gateway";NA;75;0
"Building";"Gateway";NA;75;0
"Unit";"Immortal";"Robotics Facility";76;4
"Building";"Gateway";NA;80;0
"Building";"Gateway";NA;80;0
"Building";"Pylon";NA;80;0
"Building";"TemplarArchive";NA;80;0
"Upgrade";"Charge";"TwilightCouncil";80;0
"Unit";"Adept";"Gateway";80;2
"Unit";"Sentry";"Gateway";82;2
"Unit";"Zealot";"Gateway";84;2
"Building";"Forge";NA;89;0
"Building";"Pylon";NA;92;0
"Building";"HighTemplar";NA;92;0
"Building";"HighTemplar";NA;92;0
"Building";"Pylon";NA;93;0
"Unit";"Archon";"High Templar";93;0
"Unit";"Zealot";"Gateway";93;2
"Unit";"Zealot";"Gateway";95;2
"Unit";"Zealot";"Gateway";97;2
"Unit";"Zealot";"Gateway";99;2
"Unit";"Adept";"Gateway";101;2
"Unit";"Adept";"Gateway";103;2
"Unit";"Adept";"Gateway";107;2
"Building";"Pylon";NA;109;0
"Unit";"Adept";"Gateway";109;2
"Unit";"Adept";"Gateway";111;2
"Unit";"Adept";"Gateway";116;2
"Unit";"Adept";"Gateway";118;2
"Unit";"Adept";"Gateway";120;2
"Unit";"Adept";"Gateway";122;2
"Building";"Pylon";NA;124;0
"Building";"HighTemplar";NA;124;0
"Building";"HighTemplar";NA;124;0
"Unit";"Archon";"High Templar";124;0
"Unit";"Sentry";"Gateway";124;2
"Unit";"Zealot";"Gateway";126;2
"Unit";"Zealot";"Gateway";128;2
"Unit";"Zealot";"Gateway";130;2
"Unit";"Zealot";"Gateway";132;2
"Unit";"Zealot";"Gateway";134;2
"Building";"Pylon";NA;136;0
"Building";"Assimilator";NA;136;0
"Building";"Assimilator";NA;136;0
"Unit";"Zealot";"Gateway";136;2
"Unit";"Zealot";"Gateway";138;2
"Unit";"Zealot";"Gateway";140;2
"Unit";"Adept";"Gateway";142;2
"Unit";"Adept";"Gateway";144;2
"Unit";"Zealot";"Gateway";146;2
"Building";"Pylon";NA;148;0
"Building";"Pylon";NA;148;0
"Unit";"Zealot";"Gateway";148;2
"Unit";"Zealot";"Gateway";150;2
"Unit";"Zealot";"Gateway";152;2
"Unit";"Zealot";"Gateway";154;2
"Unit";"Zealot";"Gateway";156;2
"Unit";"Zealot";"Gateway";158;2
"Upgrade";"SprayProtoss";NA;160;0
"Upgrade";"SprayProtoss";NA;160;0
"Upgrade";"WarpGateResearch";NA;160;0
"Upgrade";"SprayProtoss";NA;160;0
"Upgrade";"AdeptPiercingAttack";NA;160;0
"Upgrade";"SprayProtoss";NA;160;0
