"type";"unit_name";"on_building";"total_supply";"supply"
"Building";"Pylon";NA;13;0
"Building";"Assimilator";NA;15;0
"Building";"Gateway";NA;16;0
"Building";"Assimilator";NA;20;0
"Building";"Pylon";NA;21;0
"Building";"CyberneticsCore";NA;21;0
"Building";"Nexus";NA;20;0
"Unit";"Adept";"Gateway";22;2
"Unit";"Adept";"Gateway";24;2
"Building";"Stargate";NA;24;0
"Unit";"Phoenix";"Stargate";34;2
"Building";"Assimilator";NA;37;0
"Building";"RoboticsFacility";NA;30;0
"Building";"Assimilator";NA;38;0
"Building";"Pylon";NA;38;0
"Building";"TwilightCouncil";NA;38;0
"Building";"Gateway";NA;42;0
"Building";"Pylon";NA;45;0
"Building";"Gateway";NA;42;0
"Building";"Gateway";NA;43;0
"Building";"TemplarArchive";NA;45;0
"Building";"Pylon";NA;47;0
"Unit";"Observer";"Robotics Facility";47;1
"Building";"HighTemplar";NA;52;0
"Building";"HighTemplar";NA;52;0
"Unit";"Archon";"High Templar";53;0
"Building";"HighTemplar";NA;54;0
"Building";"HighTemplar";NA;54;0
"Unit";"Archon";"High Templar";54;0
"Building";"Pylon";NA;54;0
"Building";"Pylon";NA;54;0
"Building";"Pylon";NA;54;0
"Building";"Pylon";NA;54;0
"Building";"HighTemplar";NA;55;0
"Unit";"Zealot";"Gateway";55;2
"Unit";"Zealot";"Gateway";55;2
"Unit";"Zealot";"Gateway";55;2
"Unit";"Immortal";"Robotics Facility";54;4
"Building";"Forge";NA;55;0
"Building";"HighTemplar";NA;69;0
"Building";"Nexus";NA;54;0
"Unit";"Immortal";"Robotics Facility";55;4
"Unit";"Archon";"High Templar";69;0
"Building";"PhotonCannon";NA;69;0
"Building";"ShieldBattery";NA;69;0
"Building";"Gateway";NA;68;0
"Building";"Gateway";NA;68;0
"Upgrade";"Charge";"TwilightCouncil";55;0
"Building";"Pylon";NA;74;0
"Building";"Gateway";NA;69;0
"Building";"Pylon";NA;75;0
"Unit";"Immortal";"Robotics Facility";70;4
"Unit";"Zealot";"Gateway";85;2
"Unit";"Zealot";"Gateway";85;2
"Unit";"Zealot";"Gateway";85;2
"Unit";"Zealot";"Gateway";85;2
"Upgrade";"ProtossGroundWeaponsLevel1";"Forge";68;0
"Unit";"Immortal";"Robotics Facility";78;4
"Unit";"Zealot";"Gateway";99;2
"Unit";"Zealot";"Gateway";99;2
"Unit";"Zealot";"Gateway";99;2
"Unit";"Zealot";"Gateway";99;2
"Unit";"Zealot";"Gateway";99;2
"Unit";"Zealot";"Gateway";99;2
"Building";"HighTemplar";NA;101;0
"Unit";"Immortal";"Robotics Facility";94;4
"Building";"Assimilator";NA;99;0
"Building";"Assimilator";NA;99;0
"Unit";"Zealot";"Gateway";118;2
"Unit";"Sentry";"Gateway";118;2
"Building";"HighTemplar";NA;122;0
"Building";"HighTemplar";NA;122;0
"Building";"HighTemplar";NA;122;0
"Building";"Gateway";NA;98;0
"Building";"Gateway";NA;99;0
"Building";"Pylon";NA;122;0
"Building";"Pylon";NA;122;0
"Building";"Pylon";NA;122;0
"Building";"Pylon";NA;122;0
"Unit";"Immortal";"Robotics Facility";113;4
"Unit";"Zealot";"Gateway";126;2
"Unit";"Zealot";"Gateway";126;2
"Unit";"Zealot";"Gateway";126;2
"Unit";"Zealot";"Gateway";126;2
"Building";"HighTemplar";NA;137;0
"Building";"HighTemplar";NA;137;0
"Building";"HighTemplar";NA;137;0
"Unit";"Immortal";"Robotics Facility";126;4
"Building";"Nexus";NA;122;0
"Unit";"Zealot";"Gateway";141;2
"Unit";"Zealot";"Gateway";141;2
"Unit";"Zealot";"Gateway";141;2
"Unit";"Zealot";"Gateway";141;2
"Building";"PhotonCannon";NA;136;0
"Upgrade";"ProtossGroundWeaponsLevel2";"Forge";117;0
"Building";"Pylon";NA;141;0
"Building";"RoboticsFacility";NA;134;0
"Unit";"Immortal";"Robotics Facility";136;4
"Building";"Gateway";NA;136;0
"Building";"Gateway";NA;136;0
"Building";"Gateway";NA;136;0
"Building";"HighTemplar";NA;157;0
"Building";"HighTemplar";NA;157;0
"Building";"HighTemplar";NA;157;0
"Building";"HighTemplar";NA;157;0
"Unit";"Zealot";"Gateway";157;2
"Unit";"Zealot";"Gateway";157;2
"Unit";"Zealot";"Gateway";157;2
"Unit";"Observer";"Robotics Facility";149;1
"Building";"Pylon";NA;151;0
"Building";"Assimilator";NA;149;0
"Unit";"Archon";"High Templar";157;0
"Unit";"Archon";"High Templar";157;0
"Building";"Assimilator";NA;152;0
"Building";"PhotonCannon";NA;149;0
"Unit";"Zealot";"Gateway";166;2
"Unit";"Zealot";"Gateway";166;2
"Unit";"Zealot";"Gateway";166;2
"Unit";"Zealot";"Gateway";172;2
"Unit";"Zealot";"Gateway";172;2
"Unit";"Zealot";"Gateway";172;2
"Unit";"Zealot";"Gateway";172;2
"Unit";"Zealot";"Gateway";172;2
"Unit";"Immortal";"Robotics Facility";172;4
"Unit";"Immortal";"Robotics Facility";172;4
"Unit";"Zealot";"Gateway";190;2
"Unit";"Zealot";"Gateway";190;2
"Unit";"Zealot";"Gateway";190;2
"Unit";"Zealot";"Gateway";190;2
"Unit";"Zealot";"Gateway";190;2
"Unit";"Zealot";"Gateway";190;2
"Unit";"Zealot";"Gateway";190;2
"Unit";"Zealot";"Gateway";190;2
"Unit";"Zealot";"Gateway";190;2
"Unit";"Zealot";"Gateway";190;2
"Unit";"Observer";"Robotics Facility";182;1
"Unit";"Observer";"Robotics Facility";186;1
"Unit";"Observer";"Robotics Facility";210;1
"Unit";"Zealot";"Gateway";213;2
"Unit";"Zealot";"Gateway";213;2
"Unit";"Zealot";"Gateway";213;2
"Unit";"Zealot";"Gateway";213;2
"Unit";"Zealot";"Gateway";213;2
"Unit";"Zealot";"Gateway";213;2
"Unit";"Zealot";"Gateway";213;2
"Unit";"Zealot";"Gateway";213;2
"Unit";"Zealot";"Gateway";213;2
"Unit";"Zealot";"Gateway";213;2
"Unit";"Zealot";"Gateway";213;2
"Building";"HighTemplar";NA;235;0
"Unit";"Immortal";"Robotics Facility";210;4
"Upgrade";"ProtossGroundWeaponsLevel3";"Forge";166;0
"Building";"HighTemplar";NA;239;0
"Building";"HighTemplar";NA;239;0
"Building";"HighTemplar";NA;239;0
"Building";"HighTemplar";NA;239;0
"Building";"HighTemplar";NA;239;0
"Building";"HighTemplar";NA;239;0
"Unit";"Archon";"High Templar";239;0
"Unit";"Archon";"High Templar";239;0
"Unit";"Archon";"High Templar";239;0
"Building";"Pylon";NA;239;0
"Building";"Assimilator";NA;239;0
"Unit";"Archon";"High Templar";239;0
"Building";"Assimilator";NA;239;0
"Building";"HighTemplar";NA;239;0
"Building";"HighTemplar";NA;239;0
"Building";"HighTemplar";NA;239;0
"Building";"HighTemplar";NA;239;0
"Unit";"Zealot";"Gateway";239;2
"Unit";"Zealot";"Gateway";239;2
"Unit";"Archon";"High Templar";239;0
"Unit";"Zealot";"Gateway";243;2
"Unit";"Zealot";"Gateway";243;2
"Unit";"Zealot";"Gateway";243;2
"Unit";"Zealot";"Gateway";243;2
"Unit";"Zealot";"Gateway";243;2
"Unit";"Archon";"High Templar";253;0
"Unit";"Immortal";"Robotics Facility";239;4
"Unit";"Immortal";"Robotics Facility";239;4
"Unit";"Archon";"High Templar";253;0
"Building";"Nexus";NA;239;0
"Unit";"Zealot";"Gateway";261;2
"Unit";"Zealot";"Gateway";261;2
"Unit";"Zealot";"Gateway";261;2
"Unit";"Zealot";"Gateway";261;2
"Unit";"Zealot";"Gateway";261;2
"Unit";"Zealot";"Gateway";261;2
"Unit";"Zealot";"Gateway";261;2
"Unit";"Zealot";"Gateway";261;2
"Unit";"Zealot";"Gateway";261;2
"Unit";"Zealot";"Gateway";261;2
"Unit";"Zealot";"Gateway";261;2
"Unit";"Zealot";"Gateway";261;2
