"type";"unit_name";"on_building";"total_supply";"supply"
"Building";"Pylon";NA;13;0
"Building";"Assimilator";NA;16;0
"Building";"Gateway";NA;15;0
"Building";"Pylon";NA;20;0
"Building";"CyberneticsCore";NA;19;0
"Building";"Assimilator";NA;20;0
"Unit";"Adept";"Gateway";21;2
"Building";"Nexus";NA;18;0
"Unit";"Adept";"Gateway";24;2
"Building";"Stargate";NA;26;0
"Unit";"Adept";"Gateway";30;2
"Unit";"Oracle";"Stargate";30;3
"Building";"Gateway";NA;30;0
"Unit";"Phoenix";"Stargate";41;2
"Building";"Assimilator";NA;44;0
"Building";"Assimilator";NA;44;0
"Building";"TwilightCouncil";NA;44;0
"Building";"Pylon";NA;47;0
"Building";"Pylon";NA;47;0
"Building";"RoboticsFacility";NA;47;0
"Building";"Pylon";NA;47;0
"Building";"Pylon";NA;47;0
"Unit";"Zealot";"Gateway";49;2
"Unit";"Zealot";"Gateway";49;2
"Building";"TemplarArchive";NA;47;0
"Building";"Gateway";NA;47;0
"Building";"Gateway";NA;47;0
"Unit";"Zealot";"Gateway";57;2
"Unit";"Zealot";"Gateway";57;2
"Building";"HighTemplar";NA;65;0
"Building";"HighTemplar";NA;65;0
"Building";"HighTemplar";NA;65;0
"Building";"HighTemplar";NA;65;0
"Building";"Pylon";NA;65;0
"Building";"Pylon";NA;65;0
"Unit";"Archon";"High Templar";65;0
"Unit";"Archon";"High Templar";65;0
"Building";"OracleStasisTrap";NA;70;0
"Unit";"Zealot";"Gateway";70;2
"Unit";"Zealot";"Gateway";70;2
"Unit";"Zealot";"Gateway";70;2
"Building";"Nexus";NA;65;0
"Building";"ShieldBattery";NA;70;0
"Building";"Gateway";NA;68;0
"Building";"Gateway";NA;68;0
"Building";"RoboticsFacility";NA;68;0
"Building";"Gateway";NA;68;0
"Building";"Gateway";NA;69;0
"Unit";"Immortal";"Robotics Facility";70;4
"Unit";"Zealot";"Gateway";76;2
"Unit";"Zealot";"Gateway";76;2
"Unit";"Zealot";"Gateway";76;2
"Unit";"Zealot";"Gateway";76;2
"Building";"HighTemplar";NA;88;0
"Building";"HighTemplar";NA;88;0
"Building";"HighTemplar";NA;88;0
"Building";"HighTemplar";NA;88;0
"Unit";"Immortal";"Robotics Facility";88;4
"Unit";"Immortal";"Robotics Facility";88;4
"Building";"Pylon";NA;102;0
"Building";"OracleStasisTrap";NA;105;0
"Building";"HighTemplar";NA;105;0
"Building";"HighTemplar";NA;106;0
"Unit";"Zealot";"Gateway";106;2
"Unit";"Zealot";"Gateway";106;2
"Unit";"Zealot";"Gateway";106;2
"Unit";"Zealot";"Gateway";106;2
"Building";"OracleStasisTrap";NA;106;0
"Unit";"Immortal";"Robotics Facility";94;4
"Building";"Pylon";NA;114;0
"Building";"Pylon";NA;114;0
"Unit";"Immortal";"Robotics Facility";105;4
"Building";"Gateway";NA;102;0
"Upgrade";"Charge";"TwilightCouncil";89;0
"Unit";"Zealot";"Gateway";122;2
"Unit";"Zealot";"Gateway";122;2
"Building";"Gateway";NA;102;0
"Unit";"Zealot";"Gateway";122;2
"Building";"Pylon";NA;118;0
"Unit";"Observer";"Robotics Facility";118;1
"Building";"OracleStasisTrap";NA;129;0
"Building";"Forge";NA;118;0
"Building";"Forge";NA;118;0
"Building";"HighTemplar";NA;129;0
"Building";"HighTemplar";NA;129;0
"Unit";"Immortal";"Robotics Facility";118;4
"Building";"Assimilator";NA;128;0
"Building";"Assimilator";NA;128;0
"Unit";"Archon";"High Templar";131;0
"Unit";"Immortal";"Robotics Facility";131;4
"Building";"HighTemplar";NA;141;0
"Building";"HighTemplar";NA;141;0
"Building";"HighTemplar";NA;141;0
"Building";"HighTemplar";NA;146;0
"Unit";"Zealot";"Gateway";146;2
"Unit";"Zealot";"Gateway";146;2
"Unit";"Archon";"High Templar";146;0
"Unit";"Archon";"High Templar";146;0
"Building";"Pylon";NA;150;0
"Building";"Pylon";NA;150;0
"Building";"Pylon";NA;150;0
"Unit";"Zealot";"Gateway";150;2
"Unit";"Zealot";"Gateway";150;2
"Unit";"Zealot";"Gateway";150;2
"Unit";"Zealot";"Gateway";150;2
"Unit";"Zealot";"Gateway";150;2
"Unit";"Zealot";"Gateway";150;2
"Building";"Pylon";NA;150;0
"Unit";"Zealot";"Gateway";150;2
"Unit";"Zealot";"Gateway";150;2
"Building";"Pylon";NA;150;0
"Building";"Pylon";NA;150;0
"Building";"Assimilator";NA;150;0
"Building";"Assimilator";NA;150;0
"Upgrade";"ProtossGroundWeaponsLevel1";"Forge";141;0
"Unit";"Immortal";"Robotics Facility";150;4
"Unit";"Immortal";"Robotics Facility";150;4
"Building";"FleetBeacon";NA;150;0
"Building";"Stargate";NA;150;0
"Building";"Stargate";NA;150;0
"Unit";"Archon";"High Templar";166;0
"Unit";"Archon";"High Templar";166;0
"Unit";"Observer";"Robotics Facility";166;1
"Building";"HighTemplar";NA;175;0
"Building";"HighTemplar";NA;175;0
"Building";"HighTemplar";NA;175;0
"Building";"HighTemplar";NA;175;0
"Building";"Nexus";NA;150;0
"Unit";"Observer";"Robotics Facility";174;1
"Unit";"Zealot";"Gateway";175;2
"Unit";"Zealot";"Gateway";175;2
"Unit";"Zealot";"Gateway";175;2
"Unit";"Zealot";"Gateway";175;2
"Unit";"Zealot";"Gateway";175;2
"Unit";"Zealot";"Gateway";175;2
"Unit";"Oracle";"Stargate";174;3
"Building";"Pylon";NA;191;0
"Building";"PhotonCannon";NA;191;0
"Building";"PhotonCannon";NA;191;0
"Building";"PhotonCannon";NA;191;0
"Building";"PhotonCannon";NA;193;0
"Building";"PhotonCannon";NA;194;0
"Upgrade";"ProtossGroundArmorsLevel1";"Forge";166;0
"Building";"PhotonCannon";NA;194;0
"Building";"PhotonCannon";NA;197;0
"Building";"ShieldBattery";NA;197;0
"Unit";"Zealot";"Gateway";199;2
"Unit";"Zealot";"Gateway";199;2
"Unit";"Zealot";"Gateway";199;2
"Unit";"Observer";"Robotics Facility";199;1
"Unit";"Zealot";"Gateway";199;2
"Unit";"Zealot";"Gateway";199;2
"Unit";"Zealot";"Gateway";201;2
"Unit";"Zealot";"Gateway";203;2
"Unit";"Zealot";"Gateway";205;2
"Unit";"Zealot";"Gateway";205;2
"Unit";"Zealot";"Gateway";210;2
"Unit";"Immortal";"Robotics Facility";199;4
"Building";"Pylon";NA;224;0
"Building";"PhotonCannon";NA;224;0
"Building";"ShieldBattery";NA;224;0
"Building";"ShieldBattery";NA;224;0
"Unit";"Zealot";"Gateway";224;2
"Unit";"Zealot";"Gateway";224;2
"Unit";"Zealot";"Gateway";224;2
"Unit";"Zealot";"Gateway";224;2
"Unit";"Mothership";"Mothership Core";220;6
"Building";"Nexus";NA;220;0
"Building";"Pylon";NA;232;0
"Building";"Pylon";NA;232;0
"Unit";"Carrier";"Stargate";220;6
"Unit";"Carrier";"Stargate";224;6
"Building";"PhotonCannon";NA;232;0
"Building";"PhotonCannon";NA;232;0
"Building";"PhotonCannon";NA;232;0
"Building";"PhotonCannon";NA;238;0
"Building";"HighTemplar";NA;250;0
"Building";"HighTemplar";NA;250;0
"Building";"OracleStasisTrap";NA;250;0
"Upgrade";"ProtossAirWeaponsLevel1";"CyberneticsCore";224;0
"Building";"Assimilator";NA;250;0
"Building";"OracleStasisTrap";NA;250;0
"Building";"Assimilator";NA;250;0
"Building";"Pylon";NA;250;0
"Building";"PhotonCannon";NA;250;0
"Building";"PhotonCannon";NA;250;0
"Building";"PhotonCannon";NA;250;0
"Building";"PhotonCannon";NA;250;0
"Building";"PhotonCannon";NA;250;0
"Unit";"Carrier";"Stargate";244;6
"Unit";"Carrier";"Stargate";244;6
"Unit";"Immortal";"Robotics Facility";250;4
"Unit";"Immortal";"Robotics Facility";250;4
"Building";"HighTemplar";NA;270;0
"Building";"HighTemplar";NA;270;0
"Building";"HighTemplar";NA;270;0
"Building";"HighTemplar";NA;270;0
"Building";"HighTemplar";NA;270;0
"Unit";"Carrier";"Stargate";250;6
"Unit";"Archon";"High Templar";270;0
"Unit";"Archon";"High Templar";270;0
"Unit";"Carrier";"Stargate";262;6
"Unit";"Carrier";"Stargate";262;6
"Unit";"Archon";"High Templar";288;0
"Unit";"Archon";"High Templar";288;0
"Unit";"Archon";"High Templar";288;0
