"type";"unit_name";"on_building";"total_supply";"supply"
"Building";"Pylon";NA;13;0
"Building";"Assimilator";NA;16;0
"Building";"Gateway";NA;15;0
"Building";"Pylon";NA;22;0
"Building";"Assimilator";NA;21;0
"Building";"CyberneticsCore";NA;21;0
"Building";"Nexus";NA;19;0
"Unit";"Adept";"Gateway";23;2
"Unit";"Adept";"Gateway";27;2
"Building";"TwilightCouncil";NA;24;0
"Unit";"Sentry";"Gateway";32;2
"Building";"Gateway";NA;30;0
"Building";"Gateway";NA;32;0
"Building";"Gateway";NA;34;0
"Unit";"Adept";"Gateway";46;2
"Building";"Pylon";NA;46;0
"Building";"Assimilator";NA;46;0
"Unit";"Adept";"Gateway";49;2
"Unit";"Adept";"Gateway";49;2
"Building";"Assimilator";NA;49;0
"Building";"Pylon";NA;49;0
"Building";"Pylon";NA;49;0
"Building";"Stargate";NA;44;0
"Unit";"Adept";"Gateway";53;2
"Building";"Stargate";NA;45;0
"Unit";"Adept";"Gateway";56;2
"Building";"Pylon";NA;49;0
"Unit";"Adept";"Gateway";60;2
"Unit";"Adept";"Gateway";60;2
"Building";"Nexus";NA;46;0
"Unit";"Phoenix";"Stargate";65;2
"Unit";"Phoenix";"Stargate";65;2
"Building";"Pylon";NA;71;0
"Unit";"Phoenix";"Stargate";67;2
"Unit";"Phoenix";"Stargate";67;2
"Building";"Pylon";NA;76;0
"Unit";"Phoenix";"Stargate";78;2
"Unit";"Phoenix";"Stargate";84;2
"Building";"Pylon";NA;88;0
"Building";"Pylon";NA;88;0
"Unit";"Phoenix";"Stargate";88;2
"Unit";"Adept";"Gateway";101;2
"Unit";"Adept";"Gateway";101;2
"Building";"Assimilator";NA;95;0
"Building";"Assimilator";NA;96;0
"Building";"Gateway";NA;90;0
"Building";"Gateway";NA;91;0
"Building";"Gateway";NA;94;0
"Building";"FleetBeacon";NA;98;0
"Upgrade";"ProtossAirWeaponsLevel1";"CyberneticsCore";85;0
"Unit";"Zealot";"Gateway";110;2
"Unit";"Zealot";"Gateway";112;2
"Unit";"Zealot";"Gateway";112;2
"Unit";"Zealot";"Gateway";112;2
"Unit";"Zealot";"Gateway";112;2
"Unit";"Zealot";"Gateway";112;2
"Unit";"Zealot";"Gateway";112;2
"Upgrade";"Charge";"TwilightCouncil";98;0
"Building";"Pylon";NA;112;0
"Building";"Pylon";NA;127;0
"Unit";"Zealot";"Gateway";127;2
"Unit";"Zealot";"Gateway";127;2
"Unit";"Zealot";"Gateway";127;2
"Unit";"Zealot";"Gateway";127;2
"Unit";"Zealot";"Gateway";127;2
"Unit";"Zealot";"Gateway";127;2
"Building";"Pylon";NA;127;0
"Building";"Pylon";NA;127;0
"Unit";"Zealot";"Gateway";145;2
"Unit";"Carrier";"Stargate";107;6
"Unit";"Carrier";"Stargate";107;6
"Building";"Assimilator";NA;145;0
"Building";"Assimilator";NA;145;0
"Building";"ShieldBattery";NA;145;0
"Unit";"Zealot";"Gateway";160;2
"Unit";"Zealot";"Gateway";160;2
"Unit";"Zealot";"Gateway";160;2
"Building";"Forge";NA;145;0
"Unit";"Phoenix";"Stargate";145;2
"Building";"Stargate";NA;142;0
"Building";"Nexus";NA;127;0
"Building";"Pylon";NA;168;0
"Building";"Pylon";NA;168;0
"Building";"Pylon";NA;168;0
"Building";"Pylon";NA;168;0
"Building";"Pylon";NA;168;0
"Unit";"Phoenix";"Stargate";168;2
"Unit";"Zealot";"Gateway";168;2
"Unit";"Zealot";"Gateway";168;2
"Unit";"Zealot";"Gateway";168;2
"Upgrade";"ProtossAirWeaponsLevel2";"CyberneticsCore";139;0
"Unit";"Carrier";"Stargate";148;6
"Building";"Pylon";NA;176;0
"Building";"TemplarArchive";NA;168;0
"Building";"Pylon";NA;178;0
"Building";"PhotonCannon";NA;178;0
"Building";"PhotonCannon";NA;178;0
"Building";"PhotonCannon";NA;184;0
"Building";"ShieldBattery";NA;184;0
"Building";"PhotonCannon";NA;184;0
"Building";"PhotonCannon";NA;184;0
"Unit";"Carrier";"Stargate";168;6
"Building";"ShieldBattery";NA;184;0
"Building";"PhotonCannon";NA;184;0
"Building";"Nexus";NA;176;0
"Unit";"Mothership";"Mothership Core";176;6
"Building";"HighTemplar";NA;196;0
"Building";"HighTemplar";NA;196;0
"Building";"HighTemplar";NA;196;0
"Building";"HighTemplar";NA;196;0
"Building";"HighTemplar";NA;196;0
"Building";"HighTemplar";NA;196;0
"Building";"HighTemplar";NA;196;0
"Building";"PhotonCannon";NA;190;0
"Unit";"Archon";"High Templar";196;0
"Unit";"Archon";"High Templar";196;0
"Unit";"Archon";"High Templar";196;0
"Building";"PhotonCannon";NA;190;0
"Building";"ShieldBattery";NA;190;0
"Building";"PhotonCannon";NA;190;0
"Upgrade";"ProtossShieldsLevel1";"Forge";178;0
"Unit";"Oracle";"Stargate";190;3
"Unit";"Carrier";"Stargate";184;6
"Unit";"Carrier";"Stargate";184;6
"Unit";"Zealot";"Gateway";211;2
"Unit";"Zealot";"Gateway";211;2
"Unit";"Zealot";"Gateway";211;2
"Unit";"Zealot";"Gateway";211;2
"Unit";"Zealot";"Gateway";211;2
"Unit";"Zealot";"Gateway";211;2
"Building";"RoboticsFacility";NA;199;0
"Unit";"Zealot";"Gateway";223;2
"Unit";"Zealot";"Gateway";223;2
"Unit";"Zealot";"Gateway";223;2
"Unit";"Zealot";"Gateway";223;2
"Unit";"Zealot";"Gateway";223;2
"Unit";"Zealot";"Gateway";223;2
"Unit";"Carrier";"Stargate";196;6
"Building";"HighTemplar";NA;241;0
"Building";"HighTemplar";NA;241;0
"Building";"HighTemplar";NA;241;0
"Building";"HighTemplar";NA;241;0
"Unit";"Carrier";"Stargate";196;6
"Unit";"Observer";"Robotics Facility";235;1
"Building";"HighTemplar";NA;247;0
"Building";"HighTemplar";NA;248;0
"Unit";"Carrier";"Stargate";211;6
"Upgrade";"ProtossAirWeaponsLevel3";"CyberneticsCore";196;0
"Unit";"Archon";"High Templar";248;0
"Unit";"Observer";"Robotics Facility";247;1
"Building";"Assimilator";NA;254;0
"Building";"Assimilator";NA;254;0
"Unit";"Observer";"Robotics Facility";254;1
"Building";"HighTemplar";NA;255;0
"Building";"HighTemplar";NA;255;0
"Building";"HighTemplar";NA;255;0
"Unit";"Zealot";"Gateway";256;2
"Unit";"Zealot";"Gateway";256;2
"Unit";"Zealot";"Gateway";256;2
"Unit";"Archon";"High Templar";255;0
"Unit";"Archon";"High Templar";255;0
"Unit";"Archon";"High Templar";256;0
"Building";"Nexus";NA;235;0
"Unit";"Carrier";"Stargate";235;6
"Unit";"Observer";"Robotics Facility";262;1
"Unit";"Zealot";"Gateway";268;2
"Unit";"Zealot";"Gateway";268;2
"Unit";"Zealot";"Gateway";268;2
"Unit";"Zealot";"Gateway";268;2
"Unit";"Zealot";"Gateway";268;2
"Unit";"Zealot";"Gateway";268;2
"Unit";"Carrier";"Stargate";241;6
"Unit";"Carrier";"Stargate";247;6
"Building";"PhotonCannon";NA;293;0
"Building";"PhotonCannon";NA;293;0
"Building";"PhotonCannon";NA;293;0
"Building";"ShieldBattery";NA;293;0
"Building";"PhotonCannon";NA;293;0
"Building";"PhotonCannon";NA;293;0
"Upgrade";"ProtossAirArmorsLevel1";"CyberneticsCore";262;0
"Building";"ShieldBattery";NA;293;0
"Unit";"Carrier";"Stargate";268;6
"Unit";"Carrier";"Stargate";281;6
