"type";"unit_name";"on_building";"total_supply";"supply"
"Building";"Pylon";NA;13;0
"Building";"Assimilator";NA;16;0
"Building";"Gateway";NA;15;0
"Building";"Assimilator";NA;20;0
"Building";"CyberneticsCore";NA;20;0
"Building";"Pylon";NA;21;0
"Building";"Pylon";NA;22;0
"Unit";"Adept";"Gateway";22;2
"Building";"Nexus";NA;19;0
"Unit";"Adept";"Gateway";27;2
"Building";"Stargate";NA;24;0
"Unit";"Adept";"Gateway";34;2
"Unit";"Oracle";"Stargate";33;3
"Building";"Pylon";NA;42;0
"Unit";"Sentry";"Gateway";42;2
"Building";"Gateway";NA;35;0
"Building";"Gateway";NA;35;0
"Building";"Pylon";NA;43;0
"Unit";"Oracle";"Stargate";42;3
"Building";"ShieldBattery";NA;42;0
"Unit";"Adept";"Gateway";50;2
"Unit";"Adept";"Gateway";50;2
"Unit";"Adept";"Gateway";50;2
"Unit";"Phoenix";"Stargate";50;2
"Building";"Pylon";NA;58;0
"Building";"Assimilator";NA;58;0
"Building";"Assimilator";NA;58;0
"Building";"Forge";NA;58;0
"Building";"Pylon";NA;64;0
"Building";"TwilightCouncil";NA;60;0
"Unit";"Zealot";"Gateway";66;2
"Unit";"Sentry";"Gateway";66;2
"Unit";"Adept";"Gateway";66;2
"Building";"Pylon";NA;66;0
"Building";"Pylon";NA;74;0
"Unit";"Zealot";"Gateway";77;2
"Unit";"Zealot";"Gateway";78;2
"Unit";"Zealot";"Gateway";79;2
"Building";"ShieldBattery";NA;77;0
"Building";"RoboticsFacility";NA;76;0
"Building";"Nexus";NA;66;0
"Building";"TemplarArchive";NA;87;0
"Upgrade";"Charge";"TwilightCouncil";76;0
"Unit";"Zealot";"Gateway";92;2
"Unit";"Zealot";"Gateway";92;2
"Unit";"Zealot";"Gateway";92;2
"Building";"Gateway";NA;87;0
"Building";"Gateway";NA;87;0
"Building";"Gateway";NA;88;0
"Upgrade";"ProtossGroundWeaponsLevel1";"Forge";77;0
"Building";"PhotonCannon";NA;92;0
"Building";"HighTemplar";NA;100;0
"Building";"HighTemplar";NA;100;0
"Building";"HighTemplar";NA;100;0
"Building";"HighTemplar";NA;100;0
"Building";"PhotonCannon";NA;99;0
"Unit";"Archon";"High Templar";100;0
"Unit";"Archon";"High Templar";100;0
"Unit";"Immortal";"Robotics Facility";100;4
"Building";"Pylon";NA;100;0
"Building";"PhotonCannon";NA;100;0
"Building";"ShieldBattery";NA;100;0
"Building";"Assimilator";NA;100;0
"Unit";"Observer";"Robotics Facility";102;1
"Building";"Assimilator";NA;102;0
"Unit";"Zealot";"Gateway";108;2
"Unit";"Zealot";"Gateway";108;2
"Unit";"Zealot";"Gateway";108;2
"Building";"Gateway";NA;103;0
"Building";"Gateway";NA;103;0
"Unit";"Immortal";"Robotics Facility";107;4
"Building";"RoboticsFacility";NA;107;0
"Building";"HighTemplar";NA;118;0
"Building";"HighTemplar";NA;118;0
"Building";"HighTemplar";NA;118;0
"Building";"HighTemplar";NA;118;0
"Building";"Pylon";NA;121;0
"Building";"Pylon";NA;121;0
"Building";"Pylon";NA;121;0
"Building";"Pylon";NA;121;0
"Building";"Assimilator";NA;121;0
"Unit";"Immortal";"Robotics Facility";121;4
"Building";"Assimilator";NA;121;0
"Building";"HighTemplar";NA;122;0
"Building";"HighTemplar";NA;122;0
"Building";"HighTemplar";NA;122;0
"Unit";"Immortal";"Robotics Facility";121;4
"Unit";"Zealot";"Gateway";122;2
"Unit";"Zealot";"Gateway";122;2
"Unit";"Zealot";"Gateway";122;2
"Unit";"Zealot";"Gateway";126;2
"Unit";"Zealot";"Gateway";136;2
"Unit";"Archon";"High Templar";126;0
"Building";"ShieldBattery";NA;122;0
"Building";"ShieldBattery";NA;122;0
"Building";"PhotonCannon";NA;122;0
"Building";"PhotonCannon";NA;122;0
"Building";"HighTemplar";NA;141;0
"Building";"PhotonCannon";NA;122;0
"Upgrade";"ProtossGroundWeaponsLevel2";"Forge";114;0
"Building";"Nexus";NA;121;0
"Unit";"Zealot";"Gateway";143;2
"Unit";"Zealot";"Gateway";143;2
"Unit";"Zealot";"Gateway";143;2
"Building";"Pylon";NA;149;0
"Building";"Pylon";NA;149;0
"Unit";"Immortal";"Robotics Facility";141;4
"Building";"HighTemplar";NA;149;0
"Building";"HighTemplar";NA;149;0
"Building";"HighTemplar";NA;149;0
"Building";"HighTemplar";NA;149;0
"Unit";"Zealot";"Gateway";149;2
"Unit";"Zealot";"Gateway";149;2
"Unit";"Zealot";"Gateway";149;2
"Unit";"Zealot";"Gateway";149;2
"Building";"Gateway";NA;141;0
"Unit";"Zealot";"Gateway";163;2
"Unit";"Zealot";"Gateway";163;2
"Unit";"Zealot";"Gateway";163;2
"Unit";"Zealot";"Gateway";163;2
"Unit";"Zealot";"Gateway";163;2
"Unit";"Zealot";"Gateway";163;2
"Unit";"Zealot";"Gateway";163;2
"Unit";"Immortal";"Robotics Facility";161;4
"Unit";"Oracle";"Stargate";161;3
"Unit";"Immortal";"Robotics Facility";161;4
"Building";"Stargate";NA;163;0
"Building";"FleetBeacon";NA;163;0
"Building";"Pylon";NA;188;0
"Unit";"Zealot";"Gateway";188;2
"Unit";"Zealot";"Gateway";188;2
"Unit";"Zealot";"Gateway";188;2
"Unit";"Zealot";"Gateway";188;2
"Unit";"Zealot";"Gateway";188;2
"Unit";"Zealot";"Gateway";188;2
"Unit";"Zealot";"Gateway";188;2
"Unit";"Zealot";"Gateway";188;2
"Unit";"Zealot";"Gateway";188;2
"Unit";"Immortal";"Robotics Facility";188;4
"Unit";"Zealot";"Gateway";210;2
"Unit";"Zealot";"Gateway";210;2
"Unit";"Zealot";"Gateway";210;2
"Unit";"Zealot";"Gateway";210;2
"Unit";"Zealot";"Gateway";210;2
"Unit";"Zealot";"Gateway";210;2
"Unit";"Zealot";"Gateway";210;2
"Unit";"Zealot";"Gateway";210;2
"Unit";"Zealot";"Gateway";210;2
"Unit";"Tempest";"Stargate";188;4
"Unit";"Tempest";"Stargate";188;4
"Unit";"Zealot";"Gateway";236;2
"Unit";"Zealot";"Gateway";236;2
"Unit";"Zealot";"Gateway";236;2
"Unit";"Zealot";"Gateway";236;2
"Unit";"Zealot";"Gateway";236;2
"Unit";"Observer";"Robotics Facility";236;1
"Building";"HighTemplar";NA;249;0
"Building";"HighTemplar";NA;249;0
"Building";"HighTemplar";NA;249;0
"Building";"HighTemplar";NA;249;0
"Building";"HighTemplar";NA;249;0
"Building";"HighTemplar";NA;249;0
"Building";"HighTemplar";NA;249;0
"Building";"HighTemplar";NA;249;0
"Building";"HighTemplar";NA;249;0
"Upgrade";"ProtossGroundWeaponsLevel3";"Forge";188;0
"Unit";"Archon";"High Templar";250;0
"Unit";"Archon";"High Templar";250;0
"Unit";"Immortal";"Robotics Facility";247;4
"Building";"HighTemplar";NA;256;0
"Building";"HighTemplar";NA;256;0
"Building";"HighTemplar";NA;256;0
"Unit";"Tempest";"Stargate";247;4
"Building";"HighTemplar";NA;256;0
"Unit";"Tempest";"Stargate";247;4
"Unit";"Zealot";"Gateway";261;2
"Unit";"Zealot";"Gateway";261;2
"Unit";"Zealot";"Gateway";261;2
"Unit";"Zealot";"Gateway";261;2
"Unit";"Zealot";"Gateway";261;2
"Unit";"Archon";"High Templar";265;0
"Unit";"Immortal";"Robotics Facility";250;4
"Unit";"Archon";"High Templar";265;0
"Building";"PhotonCannon";NA;256;0
"Unit";"Zealot";"Gateway";283;2
"Unit";"Zealot";"Gateway";283;2
"Unit";"Zealot";"Gateway";283;2
"Unit";"Zealot";"Gateway";283;2
"Unit";"Zealot";"Gateway";283;2
"Unit";"Zealot";"Gateway";283;2
"Unit";"Zealot";"Gateway";283;2
"Unit";"Zealot";"Gateway";283;2
"Unit";"Zealot";"Gateway";283;2
"Unit";"Immortal";"Robotics Facility";283;4
"Building";"HighTemplar";NA;308;0
"Building";"HighTemplar";NA;308;0
"Building";"HighTemplar";NA;308;0
"Unit";"Immortal";"Robotics Facility";283;4
"Unit";"Immortal";"Robotics Facility";301;4
"Building";"PhotonCannon";NA;308;0
"Building";"PhotonCannon";NA;308;0
"Building";"Pylon";NA;316;0
"Unit";"Zealot";"Gateway";320;2
"Unit";"Zealot";"Gateway";320;2
"Unit";"Zealot";"Gateway";320;2
"Unit";"Zealot";"Gateway";320;2
"Unit";"Zealot";"Gateway";320;2
"Unit";"Zealot";"Gateway";320;2
"Building";"Pylon";NA;320;0
"Building";"Pylon";NA;320;0
"Unit";"Zealot";"Gateway";332;2
"Unit";"Zealot";"Gateway";332;2
"Unit";"Zealot";"Gateway";332;2
"Unit";"Zealot";"Gateway";332;2
"Unit";"Zealot";"Gateway";332;2
"Unit";"Zealot";"Gateway";332;2
"Unit";"Zealot";"Gateway";332;2
"Unit";"Zealot";"Gateway";332;2
"Unit";"Zealot";"Gateway";332;2
"Building";"Nexus";NA;315;0
