"type";"unit_name";"on_building";"total_supply";"supply"
"Building";"Pylon";NA;13;0
"Building";"Assimilator";NA;17;0
"Building";"Gateway";NA;15;0
"Building";"CyberneticsCore";NA;20;0
"Building";"Pylon";NA;21;0
"Building";"Assimilator";NA;22;0
"Unit";"Adept";"Gateway";22;2
"Unit";"Adept";"Gateway";24;2
"Building";"Nexus";NA;21;0
"Unit";"Sentry";"Gateway";30;2
"Building";"Gateway";NA;27;0
"Building";"Gateway";NA;28;0
"Building";"ShieldBattery";NA;33;0
"Building";"TwilightCouncil";NA;32;0
"Building";"Pylon";NA;39;0
"Unit";"Sentry";"Gateway";37;2
"Building";"Pylon";NA;41;0
"Unit";"Stalker";"Gateway";49;2
"Unit";"Stalker";"Gateway";49;2
"Unit";"Sentry";"Gateway";54;2
"Building";"Assimilator";NA;48;0
"Building";"Pylon";NA;49;0
"Building";"Assimilator";NA;49;0
"Building";"RoboticsFacility";NA;45;0
"Unit";"Phoenix";"Stargate";53;2
"Building";"Forge";NA;56;0
"Unit";"Immortal";"Robotics Facility";56;4
"Building";"Pylon";NA;62;0
"Building";"Pylon";NA;62;0
"Upgrade";"Charge";"TwilightCouncil";49;0
"Building";"TemplarArchive";NA;68;0
"Building";"Gateway";NA;62;0
"Unit";"Immortal";"Robotics Facility";64;4
"Building";"Gateway";NA;62;0
"Building";"Gateway";NA;64;0
"Building";"HighTemplar";NA;72;0
"Building";"HighTemplar";NA;72;0
"Unit";"Archon";"High Templar";74;0
"Unit";"Phoenix";"Stargate";72;2
"Building";"Pylon";NA;74;0
"Building";"Pylon";NA;79;0
"Unit";"Immortal";"Robotics Facility";74;4
"Upgrade";"ProtossGroundWeaponsLevel1";"Forge";68;0
"Building";"Nexus";NA;68;0
"Building";"HighTemplar";NA;87;0
"Building";"HighTemplar";NA;87;0
"Building";"Assimilator";NA;81;0
"Building";"ShieldBattery";NA;79;0
"Building";"PhotonCannon";NA;79;0
"Building";"Assimilator";NA;81;0
"Unit";"Archon";"High Templar";87;0
"Unit";"Phoenix";"Stargate";87;2
"Unit";"Immortal";"Robotics Facility";81;4
"Building";"Gateway";NA;81;0
"Building";"Gateway";NA;81;0
"Unit";"Stalker";"Gateway";101;2
"Building";"HighTemplar";NA;106;0
"Building";"HighTemplar";NA;106;0
"Building";"PhotonCannon";NA;98;0
"Unit";"Immortal";"Robotics Facility";91;4
"Unit";"Archon";"High Templar";110;0
"Building";"Pylon";NA;110;0
"Building";"Pylon";NA;110;0
"Building";"Pylon";NA;110;0
"Building";"Pylon";NA;110;0
"Building";"HighTemplar";NA;110;0
"Building";"HighTemplar";NA;110;0
"Building";"HighTemplar";NA;110;0
"Building";"HighTemplar";NA;110;0
"Building";"HighTemplar";NA;110;0
"Building";"Pylon";NA;110;0
"Building";"Pylon";NA;110;0
"Building";"HighTemplar";NA;110;0
"Unit";"Zealot";"Gateway";110;2
"Unit";"Zealot";"Gateway";110;2
"Building";"Pylon";NA;110;0
"Unit";"Archon";"High Templar";110;0
"Unit";"Archon";"High Templar";110;0
"Unit";"Archon";"High Templar";110;0
"Unit";"Observer";"Robotics Facility";110;1
"Unit";"Zealot";"Gateway";115;2
"Unit";"Zealot";"Gateway";115;2
"Unit";"Observer";"Robotics Facility";114;1
"Unit";"Zealot";"Gateway";119;2
"Unit";"Zealot";"Gateway";119;2
"Unit";"Zealot";"Gateway";119;2
"Unit";"Zealot";"Gateway";119;2
"Unit";"Zealot";"Gateway";119;2
"Unit";"Zealot";"Gateway";119;2
"Upgrade";"ProtossGroundWeaponsLevel2";"Forge";106;0
"Building";"HighTemplar";NA;132;0
"Building";"HighTemplar";NA;132;0
"Unit";"Zealot";"Gateway";132;2
"Unit";"Zealot";"Gateway";132;2
"Unit";"Zealot";"Gateway";132;2
"Unit";"Zealot";"Gateway";132;2
"Unit";"Zealot";"Gateway";132;2
"Unit";"Archon";"High Templar";132;0
"Building";"Nexus";NA;110;0
"Unit";"Zealot";"Gateway";142;2
"Unit";"Immortal";"Robotics Facility";132;4
"Building";"HighTemplar";NA;148;0
"Building";"HighTemplar";NA;148;0
"Building";"HighTemplar";NA;148;0
"Building";"HighTemplar";NA;148;0
"Building";"HighTemplar";NA;148;0
"Unit";"Zealot";"Gateway";148;2
"Unit";"Zealot";"Gateway";148;2
"Building";"Pylon";NA;144;0
"Unit";"Archon";"High Templar";156;0
"Unit";"Archon";"High Templar";156;0
"Unit";"Immortal";"Robotics Facility";142;4
"Unit";"Zealot";"Gateway";162;2
"Unit";"Zealot";"Gateway";162;2
"Unit";"Zealot";"Gateway";162;2
"Building";"Assimilator";NA;160;0
"Building";"Assimilator";NA;160;0
"Building";"HighTemplar";NA;176;0
"Building";"HighTemplar";NA;176;0
"Building";"HighTemplar";NA;176;0
"Building";"HighTemplar";NA;176;0
"Unit";"Zealot";"Gateway";176;2
"Unit";"Zealot";"Gateway";176;2
"Unit";"Zealot";"Gateway";176;2
"Building";"ShieldBattery";NA;160;0
"Unit";"Zealot";"Gateway";176;2
"Building";"PhotonCannon";NA;160;0
"Building";"PhotonCannon";NA;162;0
"Building";"PhotonCannon";NA;168;0
"Unit";"Immortal";"Robotics Facility";160;4
"Unit";"Zealot";"Gateway";190;2
"Unit";"Zealot";"Gateway";190;2
"Unit";"Zealot";"Gateway";190;2
"Unit";"Zealot";"Gateway";190;2
"Unit";"Archon";"High Templar";190;0
"Unit";"Archon";"High Templar";190;0
"Building";"Pylon";NA;190;0
"Unit";"Immortal";"Robotics Facility";184;4
"Building";"PhotonCannon";NA;190;0
"Building";"PhotonCannon";NA;190;0
"Building";"HighTemplar";NA;202;0
"Building";"HighTemplar";NA;202;0
"Building";"HighTemplar";NA;202;0
"Building";"HighTemplar";NA;202;0
"Building";"ShieldBattery";NA;198;0
"Building";"HighTemplar";NA;202;0
"Building";"PhotonCannon";NA;198;0
"Building";"HighTemplar";NA;202;0
"Unit";"Zealot";"Gateway";202;2
"Unit";"Zealot";"Gateway";202;2
"Building";"PhotonCannon";NA;202;0
"Unit";"Immortal";"Robotics Facility";198;4
"Unit";"Archon";"High Templar";202;0
"Unit";"Archon";"High Templar";202;0
"Building";"Nexus";NA;190;0
"Unit";"Zealot";"Gateway";210;2
"Unit";"Zealot";"Gateway";210;2
"Unit";"Zealot";"Gateway";210;2
"Unit";"Zealot";"Gateway";210;2
"Unit";"Zealot";"Gateway";210;2
"Unit";"Zealot";"Gateway";210;2
"Building";"Stargate";NA;202;0
"Building";"Stargate";NA;202;0
"Building";"Assimilator";NA;210;0
"Unit";"Immortal";"Robotics Facility";202;4
"Building";"Assimilator";NA;210;0
"Unit";"Archon";"High Templar";222;0
