"type";"unit_name";"on_building";"total_supply";"supply"
"Building";"Pylon";NA;14;0
"Building";"Assimilator";NA;16;0
"Building";"Assimilator";NA;16;0
"Building";"Gateway";NA;15;0
"Building";"Pylon";NA;20;0
"Building";"CyberneticsCore";NA;20;0
"Unit";"Adept";"Gateway";22;2
"Building";"Forge";NA;22;0
"Unit";"Sentry";"Gateway";22;2
"Building";"ShieldBattery";NA;22;0
"Building";"PhotonCannon";NA;24;0
