"type";"unit_name";"on_building";"total_supply";"supply"
"Building";"Pylon";NA;13;0
"Building";"Assimilator";NA;16;0
"Building";"Gateway";NA;15;0
"Building";"Assimilator";NA;20;0
"Building";"Pylon";NA;21;0
"Building";"CyberneticsCore";NA;20;0
"Unit";"Adept";"Gateway";21;2
"Building";"Nexus";NA;19;0
"Building";"Stargate";NA;23;0
"Unit";"Adept";"Gateway";26;2
"Unit";"Oracle";"Stargate";30;3
"Building";"Pylon";NA;36;0
"Building";"Pylon";NA;43;0
"Unit";"Phoenix";"Stargate";42;2
"Building";"Assimilator";NA;45;0
"Building";"Assimilator";NA;46;0
"Building";"Pylon";NA;48;0
"Building";"Gateway";NA;43;0
"Building";"Gateway";NA;44;0
"Unit";"Zealot";"Gateway";56;2
"Unit";"Zealot";"Gateway";56;2
"Building";"Pylon";NA;54;0
"Building";"TwilightCouncil";NA;52;0
"Building";"ShieldBattery";NA;54;0
"Building";"RoboticsFacility";NA;52;0
"Building";"Pylon";NA;63;0
"Building";"Pylon";NA;63;0
"Unit";"Sentry";"Gateway";67;2
"Unit";"Sentry";"Gateway";67;2
"Unit";"Stalker";"Gateway";67;2
"Building";"Pylon";NA;65;0
"Building";"OracleStasisTrap";NA;75;0
"Building";"TemplarArchive";NA;65;0
"Unit";"Observer";"Robotics Facility";75;1
"Building";"Pylon";NA;77;0
"Building";"Nexus";NA;63;0
"Building";"HighTemplar";NA;80;0
"Building";"HighTemplar";NA;80;0
"Building";"RoboticsFacility";NA;75;0
"Unit";"Archon";"High Templar";82;0
"Building";"Assimilator";NA;82;0
"Building";"Assimilator";NA;82;0
"Upgrade";"Charge";"TwilightCouncil";71;0
"Building";"OracleStasisTrap";NA;88;0
"Building";"Gateway";NA;79;0
"Unit";"Observer";"Robotics Facility";85;1
"Unit";"Zealot";"Gateway";88;2
"Unit";"Adept";"Gateway";88;2
"Building";"Gateway";NA;80;0
"Building";"Pylon";NA;88;0
"Unit";"Immortal";"Robotics Facility";85;4
"Building";"Pylon";NA;106;0
"Unit";"Zealot";"Gateway";112;2
"Unit";"Zealot";"Gateway";112;2
"Unit";"Zealot";"Gateway";112;2
"Unit";"Zealot";"Gateway";114;2
"Unit";"Zealot";"Gateway";114;2
"Unit";"Immortal";"Robotics Facility";99;4
"Building";"Gateway";NA;104;0
"Building";"Gateway";NA;106;0
"Building";"Gateway";NA;106;0
"Unit";"Zealot";"Gateway";129;2
"Unit";"Zealot";"Gateway";132;2
"Unit";"Zealot";"Gateway";132;2
"Unit";"Zealot";"Gateway";132;2
"Unit";"Zealot";"Gateway";138;2
"Unit";"Zealot";"Gateway";138;2
"Unit";"Zealot";"Gateway";138;2
"Unit";"Zealot";"Gateway";144;2
"Unit";"Zealot";"Gateway";146;2
"Unit";"Zealot";"Gateway";146;2
"Unit";"Zealot";"Gateway";146;2
"Unit";"Immortal";"Robotics Facility";130;4
"Unit";"Immortal";"Robotics Facility";130;4
"Unit";"Stalker";"Gateway";160;2
"Unit";"Stalker";"Gateway";160;2
"Unit";"Stalker";"Gateway";160;2
"Unit";"Stalker";"Gateway";160;2
"Unit";"Stalker";"Gateway";168;2
"Unit";"Immortal";"Robotics Facility";146;4
"Building";"Pylon";NA;170;0
"Building";"HighTemplar";NA;176;0
"Building";"HighTemplar";NA;176;0
"Building";"HighTemplar";NA;176;0
"Building";"HighTemplar";NA;176;0
"Building";"HighTemplar";NA;176;0
"Building";"HighTemplar";NA;176;0
"Unit";"Immortal";"Robotics Facility";160;4
"Unit";"Sentry";"Gateway";176;2
"Unit";"Archon";"High Templar";181;0
"Unit";"Archon";"High Templar";183;0
"Unit";"Archon";"High Templar";183;0
"Unit";"Immortal";"Robotics Facility";170;4
"Building";"HighTemplar";NA;189;0
"Building";"HighTemplar";NA;189;0
"Building";"HighTemplar";NA;191;0
"Building";"HighTemplar";NA;191;0
"Unit";"Immortal";"Robotics Facility";177;4
"Building";"Nexus";NA;170;0
"Building";"HighTemplar";NA;195;0
"Unit";"Zealot";"Gateway";195;2
"Unit";"Zealot";"Gateway";195;2
"Unit";"Zealot";"Gateway";195;2
"Building";"Forge";NA;185;0
"Unit";"Observer";"Robotics Facility";191;1
"Building";"FleetBeacon";NA;189;0
"Building";"Stargate";NA;189;0
"Unit";"Immortal";"Robotics Facility";189;4
"Unit";"Observer";"Robotics Facility";201;1
"Building";"HighTemplar";NA;207;0
"Building";"HighTemplar";NA;207;0
"Building";"HighTemplar";NA;207;0
"Building";"HighTemplar";NA;207;0
"Unit";"Zealot";"Gateway";207;2
"Unit";"Zealot";"Gateway";207;2
"Unit";"Zealot";"Gateway";207;2
"Unit";"Zealot";"Gateway";207;2
"Building";"OracleStasisTrap";NA;217;0
"Building";"HighTemplar";NA;217;0
"Building";"HighTemplar";NA;217;0
"Unit";"Zealot";"Gateway";217;2
"Unit";"Zealot";"Gateway";217;2
"Unit";"Zealot";"Gateway";217;2
"Unit";"Zealot";"Gateway";217;2
"Unit";"Zealot";"Gateway";217;2
"Unit";"Zealot";"Gateway";217;2
"Building";"Assimilator";NA;215;0
"Building";"Assimilator";NA;215;0
"Unit";"Immortal";"Robotics Facility";215;4
"Building";"PhotonCannon";NA;215;0
"Building";"PhotonCannon";NA;215;0
"Building";"PhotonCannon";NA;215;0
"Building";"PhotonCannon";NA;215;0
"Building";"ShieldBattery";NA;217;0
"Building";"PhotonCannon";NA;217;0
"Building";"PhotonCannon";NA;217;0
"Building";"ShieldBattery";NA;217;0
"Unit";"Zealot";"Gateway";235;2
"Unit";"Zealot";"Gateway";235;2
"Unit";"Zealot";"Gateway";235;2
"Unit";"Zealot";"Gateway";235;2
"Unit";"Zealot";"Gateway";235;2
"Building";"OracleStasisTrap";NA;245;0
"Unit";"Immortal";"Robotics Facility";223;4
"Unit";"Immortal";"Robotics Facility";229;4
"Building";"HighTemplar";NA;249;0
"Building";"Pylon";NA;253;0
"Building";"Pylon";NA;253;0
"Unit";"Immortal";"Robotics Facility";249;4
"Building";"Pylon";NA;253;0
"Building";"Pylon";NA;253;0
"Unit";"Immortal";"Robotics Facility";253;4
"Unit";"Immortal";"Robotics Facility";253;4
"Unit";"Tempest";"Stargate";253;4
"Unit";"Tempest";"Stargate";253;4
"Unit";"Zealot";"Gateway";273;2
"Unit";"Zealot";"Gateway";273;2
"Unit";"Zealot";"Gateway";273;2
"Unit";"Zealot";"Gateway";273;2
"Unit";"Zealot";"Gateway";273;2
"Unit";"Zealot";"Gateway";273;2
"Unit";"Zealot";"Gateway";273;2
"Building";"OracleStasisTrap";NA;287;0
"Unit";"Immortal";"Robotics Facility";257;4
"Unit";"Immortal";"Robotics Facility";261;4
"Building";"HighTemplar";NA;295;0
"Building";"HighTemplar";NA;295;0
"Building";"HighTemplar";NA;295;0
"Building";"HighTemplar";NA;295;0
"Building";"HighTemplar";NA;295;0
"Building";"HighTemplar";NA;295;0
"Building";"HighTemplar";NA;295;0
"Building";"HighTemplar";NA;295;0
"Unit";"Tempest";"Stargate";273;4
"Unit";"Tempest";"Stargate";273;4
"Unit";"Archon";"High Templar";303;0
"Unit";"Archon";"High Templar";303;0
"Upgrade";"ProtossAirWeaponsLevel1";"CyberneticsCore";257;0
"Building";"Pylon";NA;303;0
"Building";"HighTemplar";NA;306;0
"Building";"HighTemplar";NA;306;0
"Building";"Pylon";NA;303;0
"Building";"Pylon";NA;306;0
"Unit";"Tempest";"Stargate";295;4
"Unit";"Tempest";"Stargate";295;4
"Unit";"Zealot";"Gateway";314;2
"Unit";"Zealot";"Gateway";314;2
"Unit";"Zealot";"Gateway";314;2
"Unit";"Zealot";"Gateway";314;2
"Unit";"Zealot";"Gateway";314;2
"Unit";"Zealot";"Gateway";314;2
"Unit";"Observer";"Robotics Facility";326;1
"Unit";"Observer";"Robotics Facility";326;1
"Building";"Nexus";NA;303;0
"Building";"Assimilator";NA;328;0
"Building";"HighTemplar";NA;333;0
"Building";"HighTemplar";NA;333;0
"Building";"HighTemplar";NA;333;0
"Building";"PhotonCannon";NA;328;0
"Unit";"Zealot";"Gateway";333;2
"Building";"PhotonCannon";NA;328;0
"Building";"ShieldBattery";NA;329;0
"Unit";"Immortal";"Robotics Facility";326;4
"Building";"Assimilator";NA;330;0
"Unit";"Zealot";"Gateway";339;2
"Unit";"Zealot";"Gateway";339;2
"Unit";"Zealot";"Gateway";339;2
"Unit";"Zealot";"Gateway";339;2
"Building";"PhotonCannon";NA;331;0
"Unit";"Zealot";"Gateway";347;2
"Unit";"Carrier";"Stargate";326;6
"Unit";"Carrier";"Stargate";326;6
"Unit";"Zealot";"Gateway";349;2
"Unit";"Zealot";"Gateway";355;2
"Unit";"Zealot";"Gateway";355;2
"Unit";"Immortal";"Robotics Facility";349;4
"Building";"HighTemplar";NA;367;0
"Building";"HighTemplar";NA;367;0
"Building";"HighTemplar";NA;368;0
"Building";"HighTemplar";NA;375;0
"Building";"HighTemplar";NA;375;0
"Building";"HighTemplar";NA;375;0
"Building";"HighTemplar";NA;376;0
"Building";"HighTemplar";NA;376;0
"Unit";"Archon";"High Templar";376;0
"Unit";"Archon";"High Templar";376;0
"Unit";"Carrier";"Stargate";349;6
"Unit";"Oracle";"Stargate";376;3
"Unit";"Carrier";"Stargate";376;6
"Unit";"Archon";"High Templar";391;0
"Unit";"Archon";"High Templar";391;0
"Building";"HighTemplar";NA;391;0
"Building";"HighTemplar";NA;391;0
"Building";"HighTemplar";NA;391;0
"Building";"HighTemplar";NA;391;0
"Building";"HighTemplar";NA;391;0
"Unit";"Zealot";"Gateway";391;2
"Unit";"Zealot";"Gateway";391;2
"Unit";"Zealot";"Gateway";391;2
"Building";"Nexus";NA;382;0
"Unit";"Carrier";"Stargate";382;6
"Building";"OracleStasisTrap";NA;397;0
"Upgrade";"ProtossAirWeaponsLevel2";"CyberneticsCore";382;0
"Unit";"Stalker";"Gateway";403;2
"Unit";"Stalker";"Gateway";403;2
"Unit";"Stalker";"Gateway";403;2
"Unit";"Stalker";"Gateway";403;2
"Unit";"Stalker";"Gateway";403;2
"Unit";"Stalker";"Gateway";403;2
"Unit";"Stalker";"Gateway";403;2
"Unit";"Stalker";"Gateway";403;2
"Unit";"Zealot";"Gateway";419;2
"Unit";"Zealot";"Gateway";419;2
"Unit";"Zealot";"Gateway";419;2
"Unit";"Zealot";"Gateway";419;2
"Unit";"Zealot";"Gateway";419;2
"Unit";"Zealot";"Gateway";419;2
"Unit";"Zealot";"Gateway";419;2
"Unit";"Zealot";"Gateway";419;2
"Unit";"Zealot";"Gateway";435;2
"Unit";"Zealot";"Gateway";435;2
"Unit";"Zealot";"Gateway";435;2
"Unit";"Zealot";"Gateway";435;2
"Unit";"Zealot";"Gateway";435;2
"Unit";"Zealot";"Gateway";435;2
"Unit";"Zealot";"Gateway";435;2
"Unit";"Zealot";"Gateway";435;2
"Unit";"Observer";"Robotics Facility";435;1
"Unit";"Observer";"Robotics Facility";435;1
"Unit";"Zealot";"Gateway";453;2
"Unit";"Zealot";"Gateway";453;2
"Unit";"Zealot";"Gateway";453;2
"Unit";"Zealot";"Gateway";453;2
"Unit";"Zealot";"Gateway";453;2
"Unit";"Zealot";"Gateway";453;2
"Unit";"Zealot";"Gateway";465;2
"Unit";"Zealot";"Gateway";467;2
"Unit";"Zealot";"Gateway";467;2
"Unit";"Zealot";"Gateway";467;2
"Upgrade";"ProtossGroundWeaponsLevel1";"Forge";419;0
"Unit";"Zealot";"Gateway";473;2
"Unit";"Zealot";"Gateway";473;2
