"type";"unit_name";"on_building";"total_supply";"supply"
"Building";"Pylon";NA;13;0
"Building";"Assimilator";NA;16;0
"Building";"Gateway";NA;15;0
"Building";"Assimilator";NA;19;0
"Building";"CyberneticsCore";NA;19;0
"Building";"Pylon";NA;20;0
"Unit";"Adept";"Gateway";21;2
"Building";"Nexus";NA;19;0
"Unit";"Adept";"Gateway";23;2
"Building";"Stargate";NA;22;0
"Unit";"Adept";"Gateway";28;2
"Unit";"Phoenix";"Stargate";32;2
"Building";"Pylon";NA;42;0
"Unit";"Adept";"Gateway";40;2
"Unit";"Oracle";"Stargate";40;3
"Building";"Assimilator";NA;44;0
"Building";"Assimilator";NA;44;0
"Building";"ShieldBattery";NA;44;0
"Building";"Gateway";NA;42;0
"Building";"TwilightCouncil";NA;52;0
"Unit";"Adept";"Gateway";56;2
"Building";"Pylon";NA;55;0
"Building";"Pylon";NA;55;0
"Building";"RoboticsFacility";NA;52;0
"Unit";"Adept";"Gateway";58;2
"Building";"Gateway";NA;55;0
"Building";"TemplarArchive";NA;56;0
"Building";"Gateway";NA;55;0
"Building";"Pylon";NA;61;0
"Building";"Pylon";NA;61;0
"Upgrade";"Charge";"TwilightCouncil";58;0
"Building";"OracleStasisTrap";NA;65;0
"Building";"OracleStasisTrap";NA;66;0
"Unit";"Immortal";"Robotics Facility";61;4
"Building";"Gateway";NA;61;0
"Building";"HighTemplar";NA;66;0
"Building";"HighTemplar";NA;66;0
"Building";"HighTemplar";NA;66;0
"Building";"HighTemplar";NA;66;0
"Building";"Gateway";NA;61;0
"Unit";"Archon";"High Templar";70;0
"Unit";"Archon";"High Templar";70;0
"Building";"Nexus";NA;61;0
"Building";"Gateway";NA;63;0
"Building";"Gateway";NA;63;0
"Building";"ShieldBattery";NA;66;0
"Building";"Gateway";NA;64;0
"Unit";"Immortal";"Robotics Facility";66;4
"Building";"Gateway";NA;64;0
"Unit";"Zealot";"Gateway";83;2
"Unit";"Zealot";"Gateway";83;2
"Unit";"Zealot";"Gateway";83;2
"Unit";"Zealot";"Gateway";83;2
"Unit";"Observer";"Robotics Facility";82;1
"Building";"Forge";NA;81;0
"Building";"RoboticsFacility";NA;74;0
"Unit";"Zealot";"Gateway";94;2
"Unit";"Zealot";"Gateway";94;2
"Building";"Pylon";NA;101;0
"Building";"Pylon";NA;101;0
"Building";"HighTemplar";NA;105;0
"Building";"HighTemplar";NA;105;0
"Building";"Pylon";NA;105;0
"Building";"Pylon";NA;105;0
"Building";"Pylon";NA;105;0
"Building";"OracleStasisTrap";NA;108;0
"Building";"HighTemplar";NA;108;0
"Building";"HighTemplar";NA;108;0
"Building";"HighTemplar";NA;108;0
"Building";"HighTemplar";NA;108;0
"Unit";"Immortal";"Robotics Facility";104;4
"Unit";"Immortal";"Robotics Facility";104;4
"Building";"Pylon";NA;108;0
"Building";"Assimilator";NA;108;0
"Building";"Assimilator";NA;108;0
"Building";"ShieldBattery";NA;108;0
"Unit";"Zealot";"Gateway";116;2
"Unit";"Zealot";"Gateway";116;2
"Unit";"Zealot";"Gateway";116;2
"Unit";"Zealot";"Gateway";116;2
"Unit";"Zealot";"Gateway";124;2
"Unit";"Zealot";"Gateway";124;2
"Unit";"Zealot";"Gateway";124;2
"Building";"Nexus";NA;105;0
"Unit";"Immortal";"Robotics Facility";108;4
"Unit";"Immortal";"Robotics Facility";112;4
"Upgrade";"ProtossGroundWeaponsLevel1";"Forge";105;0
"Building";"HighTemplar";NA;142;0
"Building";"HighTemplar";NA;142;0
"Building";"HighTemplar";NA;142;0
"Unit";"Zealot";"Gateway";142;2
"Unit";"Zealot";"Gateway";142;2
"Unit";"Zealot";"Gateway";142;2
"Unit";"Zealot";"Gateway";142;2
"Building";"Assimilator";NA;141;0
"Building";"Assimilator";NA;141;0
"Building";"FleetBeacon";NA;130;0
"Building";"Stargate";NA;130;0
"Unit";"Archon";"High Templar";151;0
"Building";"Pylon";NA;151;0
"Building";"Pylon";NA;151;0
"Building";"Pylon";NA;151;0
"Building";"Pylon";NA;151;0
"Building";"Pylon";NA;151;0
"Building";"PhotonCannon";NA;151;0
"Building";"PhotonCannon";NA;151;0
"Building";"PhotonCannon";NA;151;0
"Building";"PhotonCannon";NA;151;0
"Building";"PhotonCannon";NA;151;0
"Building";"PhotonCannon";NA;151;0
"Building";"ShieldBattery";NA;151;0
"Building";"PhotonCannon";NA;151;0
"Building";"ShieldBattery";NA;151;0
"Building";"PhotonCannon";NA;151;0
"Unit";"Zealot";"Gateway";151;2
"Unit";"Zealot";"Gateway";151;2
"Unit";"Zealot";"Gateway";151;2
"Unit";"Zealot";"Gateway";151;2
"Unit";"Zealot";"Gateway";151;2
"Unit";"Zealot";"Gateway";161;2
"Unit";"Zealot";"Gateway";161;2
"Unit";"Zealot";"Gateway";161;2
"Unit";"Zealot";"Gateway";161;2
"Unit";"Zealot";"Gateway";161;2
"Unit";"Zealot";"Gateway";161;2
"Unit";"Carrier";"Stargate";151;6
"Unit";"Carrier";"Stargate";151;6
"Upgrade";"ProtossAirWeaponsLevel1";"CyberneticsCore";151;0
"Upgrade";"ProtossGroundWeaponsLevel2";"Forge";151;0
"Unit";"Mothership";"Mothership Core";151;6
"Building";"HighTemplar";NA;197;0
"Building";"HighTemplar";NA;197;0
"Building";"HighTemplar";NA;197;0
"Building";"HighTemplar";NA;197;0
"Building";"HighTemplar";NA;197;0
"Building";"HighTemplar";NA;197;0
"Building";"Stargate";NA;188;0
"Building";"Pylon";NA;199;0
"Building";"Stargate";NA;188;0
"Building";"PhotonCannon";NA;201;0
"Unit";"Carrier";"Stargate";161;6
"Unit";"Carrier";"Stargate";161;6
"Building";"ShieldBattery";NA;203;0
"Building";"HighTemplar";NA;220;0
"Building";"HighTemplar";NA;220;0
"Unit";"Observer";"Robotics Facility";220;1
"Unit";"Zealot";"Gateway";221;2
"Unit";"Zealot";"Gateway";221;2
"Unit";"Zealot";"Gateway";221;2
"Unit";"Zealot";"Gateway";221;2
"Unit";"Zealot";"Gateway";232;2
"Unit";"Zealot";"Gateway";232;2
"Unit";"Zealot";"Gateway";232;2
"Unit";"Zealot";"Gateway";232;2
"Unit";"Zealot";"Gateway";232;2
"Unit";"Zealot";"Gateway";232;2
"Building";"Pylon";NA;232;0
"Building";"Forge";NA;229;0
"Building";"Stargate";NA;229;0
"Building";"Stargate";NA;229;0
"Unit";"Carrier";"Stargate";221;6
"Unit";"Carrier";"Stargate";221;6
"Building";"Pylon";NA;244;0
"Upgrade";"ProtossAirWeaponsLevel2";"CyberneticsCore";221;0
"Unit";"Zealot";"Gateway";256;2
"Unit";"Zealot";"Gateway";256;2
"Unit";"Zealot";"Gateway";256;2
"Unit";"Zealot";"Gateway";256;2
"Unit";"Zealot";"Gateway";256;2
"Unit";"Immortal";"Robotics Facility";244;4
"Unit";"Immortal";"Robotics Facility";244;4
"Building";"Pylon";NA;256;0
"Unit";"Zealot";"Gateway";274;2
"Unit";"Zealot";"Gateway";276;2
"Unit";"Zealot";"Gateway";276;2
"Unit";"Zealot";"Gateway";276;2
"Unit";"Zealot";"Gateway";276;2
"Unit";"Zealot";"Gateway";276;2
"Unit";"Mothership";"Mothership Core";244;6
"Building";"HighTemplar";NA;292;0
"Building";"HighTemplar";NA;292;0
"Building";"HighTemplar";NA;292;0
"Building";"HighTemplar";NA;292;0
"Building";"HighTemplar";NA;292;0
"Unit";"Carrier";"Stargate";244;6
"Unit";"Carrier";"Stargate";250;6
"Building";"Nexus";NA;256;0
"Unit";"Archon";"High Templar";292;0
"Unit";"Archon";"High Templar";292;0
"Building";"ShieldBattery";NA;286;0
"Building";"PhotonCannon";NA;292;0
"Building";"Gateway";NA;286;0
"Building";"Gateway";NA;286;0
"Building";"Gateway";NA;286;0
"Unit";"Zealot";"Gateway";304;2
"Unit";"Zealot";"Gateway";304;2
"Unit";"Zealot";"Gateway";304;2
"Unit";"Zealot";"Gateway";304;2
"Unit";"Zealot";"Gateway";312;2
"Unit";"Zealot";"Gateway";312;2
"Building";"Assimilator";NA;304;0
"Building";"Assimilator";NA;304;0
"Building";"PhotonCannon";NA;304;0
"Building";"PhotonCannon";NA;304;0
"Building";"PhotonCannon";NA;304;0
"Building";"PhotonCannon";NA;304;0
"Building";"ShieldBattery";NA;304;0
"Building";"Pylon";NA;316;0
"Building";"Pylon";NA;316;0
"Building";"HighTemplar";NA;316;0
"Building";"HighTemplar";NA;316;0
"Building";"HighTemplar";NA;316;0
"Building";"HighTemplar";NA;316;0
"Building";"HighTemplar";NA;316;0
"Building";"HighTemplar";NA;316;0
"Building";"HighTemplar";NA;316;0
"Building";"HighTemplar";NA;316;0
"Unit";"Archon";"High Templar";316;0
"Unit";"Archon";"High Templar";316;0
"Unit";"Archon";"High Templar";316;0
"Unit";"Archon";"High Templar";316;0
"Building";"CyberneticsCore";NA;316;0
"Building";"Pylon";NA;316;0
"Building";"PhotonCannon";NA;316;0
"Building";"PhotonCannon";NA;316;0
"Unit";"Zealot";"Gateway";316;2
"Unit";"Zealot";"Gateway";316;2
"Unit";"Zealot";"Gateway";316;2
"Building";"PhotonCannon";NA;316;0
"Unit";"Zealot";"Gateway";322;2
"Building";"Gateway";NA;316;0
"Unit";"Zealot";"Gateway";324;2
"Unit";"Zealot";"Gateway";324;2
"Unit";"Zealot";"Gateway";324;2
"Unit";"Zealot";"Gateway";324;2
"Unit";"Zealot";"Gateway";324;2
"Unit";"Zealot";"Gateway";324;2
"Unit";"Zealot";"Gateway";324;2
"Unit";"Zealot";"Gateway";324;2
"Unit";"Zealot";"Gateway";340;2
"Unit";"Zealot";"Gateway";340;2
"Building";"HighTemplar";NA;344;0
"Building";"HighTemplar";NA;344;0
"Building";"HighTemplar";NA;344;0
"Building";"HighTemplar";NA;344;0
"Building";"HighTemplar";NA;344;0
"Building";"HighTemplar";NA;344;0
"Building";"DarkShrine";NA;340;0
"Unit";"Archon";"High Templar";344;0
"Unit";"Archon";"High Templar";344;0
"Unit";"Archon";"High Templar";344;0
"Building";"HighTemplar";NA;344;0
"Building";"HighTemplar";NA;344;0
"Unit";"Carrier";"Stargate";340;6
"Unit";"Archon";"High Templar";344;0
"Building";"HighTemplar";NA;350;0
"Upgrade";"ProtossAirWeaponsLevel3";"CyberneticsCore";324;0
"Building";"HighTemplar";NA;350;0
"Building";"HighTemplar";NA;350;0
"Building";"HighTemplar";NA;350;0
"Building";"HighTemplar";NA;350;0
"Building";"HighTemplar";NA;350;0
"Upgrade";"ProtossGroundWeaponsLevel3";"Forge";324;0
"Unit";"Archon";"High Templar";350;0
"Unit";"Carrier";"Stargate";340;6
"Unit";"Carrier";"Stargate";340;6
"Unit";"Stalker";"Gateway";362;2
"Unit";"Stalker";"Gateway";362;2
"Unit";"Stalker";"Gateway";362;2
"Unit";"Stalker";"Gateway";362;2
"Unit";"Stalker";"Gateway";362;2
"Unit";"Stalker";"Gateway";372;2
"Unit";"Stalker";"Gateway";374;2
"Building";"Nexus";NA;344;0
"Building";"DarkTemplar";NA;376;0
"Building";"DarkTemplar";NA;376;0
"Unit";"Stalker";"Gateway";376;2
"Unit";"Stalker";"Gateway";376;2
"Unit";"Stalker";"Gateway";376;2
"Unit";"Stalker";"Gateway";376;2
"Unit";"Stalker";"Gateway";376;2
"Unit";"Stalker";"Gateway";376;2
