"type";"unit_name";"on_building";"total_supply";"supply"
"Building";"Pylon";NA;13;0
"Building";"Assimilator";NA;16;0
"Building";"Gateway";NA;15;0
"Building";"Assimilator";NA;20;0
"Building";"CyberneticsCore";NA;20;0
"Building";"Pylon";NA;21;0
"Unit";"Stalker";"Gateway";22;2
"Building";"Nexus";NA;20;0
"Building";"Pylon";NA;27;0
"Building";"TwilightCouncil";NA;23;0
"Unit";"Adept";"Gateway";26;2
"Building";"Gateway";NA;34;0
"Building";"Pylon";NA;37;0
"Building";"DarkShrine";NA;32;0
"Building";"Gateway";NA;37;0
"Building";"Pylon";NA;41;0
"Building";"Assimilator";NA;41;0
"Building";"DarkTemplar";NA;43;0
"Building";"Assimilator";NA;41;0
"Building";"DarkTemplar";NA;43;0
"Building";"Pylon";NA;42;0
"Building";"Gateway";NA;38;0
"Building";"DarkTemplar";NA;48;0
"Building";"DarkTemplar";NA;50;0
"Unit";"Sentry";"Gateway";56;2
"Unit";"Sentry";"Gateway";56;2
"Unit";"Sentry";"Gateway";56;2
"Unit";"Sentry";"Gateway";56;2
"Building";"Gateway";NA;56;0
"Building";"Gateway";NA;56;0
"Building";"Pylon";NA;64;0
"Building";"Gateway";NA;56;0
"Building";"Pylon";NA;64;0
"Building";"Gateway";NA;56;0
"Building";"Gateway";NA;56;0
"Building";"Pylon";NA;64;0
"Building";"Gateway";NA;56;0
"Building";"DarkTemplar";NA;64;0
"Building";"DarkTemplar";NA;64;0
"Unit";"Zealot";"Gateway";64;2
"Unit";"Zealot";"Gateway";64;2
"Upgrade";"Charge";"TwilightCouncil";56;0
"Unit";"Zealot";"Gateway";68;2
"Unit";"Zealot";"Gateway";68;2
"Unit";"Zealot";"Gateway";68;2
"Unit";"Zealot";"Gateway";68;2
"Unit";"Zealot";"Gateway";68;2
"Unit";"Zealot";"Gateway";68;2
"Unit";"Zealot";"Gateway";68;2
"Unit";"Archon";"High Templar";68;0
"Building";"Pylon";NA;68;0
"Building";"Pylon";NA;68;0
"Unit";"Zealot";"Gateway";82;2
"Building";"Pylon";NA;82;0
"Unit";"Zealot";"Gateway";84;2
"Unit";"Zealot";"Gateway";84;2
"Unit";"Zealot";"Gateway";84;2
"Unit";"Zealot";"Gateway";84;2
"Unit";"Zealot";"Gateway";84;2
"Unit";"Zealot";"Gateway";84;2
"Unit";"Zealot";"Gateway";84;2
"Unit";"Zealot";"Gateway";84;2
"Unit";"Zealot";"Gateway";84;2
"Building";"ShieldBattery";NA;84;0
"Unit";"Zealot";"Gateway";106;2
"Unit";"Zealot";"Gateway";106;2
"Unit";"Zealot";"Gateway";106;2
"Unit";"Zealot";"Gateway";106;2
"Building";"Nexus";NA;84;0
"Building";"RoboticsFacility";NA;104;0
"Unit";"Stalker";"Gateway";118;2
"Building";"RoboticsFacility";NA;104;0
"Unit";"Stalker";"Gateway";118;2
"Unit";"Stalker";"Gateway";118;2
"Unit";"Stalker";"Gateway";118;2
"Unit";"Stalker";"Gateway";118;2
"Unit";"Stalker";"Gateway";118;2
"Unit";"Stalker";"Gateway";118;2
"Unit";"Stalker";"Gateway";135;2
"Building";"Forge";NA;134;0
"Building";"Forge";NA;134;0
"Unit";"Zealot";"Gateway";141;2
"Unit";"Zealot";"Gateway";141;2
"Unit";"Zealot";"Gateway";141;2
"Unit";"Zealot";"Gateway";141;2
"Unit";"Immortal";"Robotics Facility";135;4
"Unit";"Immortal";"Robotics Facility";135;4
"Unit";"Phoenix";"Stargate";138;2
"Unit";"Phoenix";"Stargate";138;2
"Unit";"Observer";"Robotics Facility";161;1
"Building";"Pylon";NA;163;0
"Building";"Pylon";NA;163;0
"Unit";"Immortal";"Robotics Facility";157;4
"Building";"Assimilator";NA;163;0
"Unit";"Zealot";"Gateway";168;2
"Unit";"Zealot";"Gateway";168;2
"Building";"Assimilator";NA;164;0
"Unit";"Zealot";"Gateway";168;2
"Unit";"Zealot";"Gateway";168;2
"Building";"Pylon";NA;168;0
"Unit";"Stalker";"Gateway";178;2
"Unit";"Stalker";"Gateway";178;2
"Unit";"Stalker";"Gateway";178;2
"Building";"TemplarArchive";NA;164;0
"Unit";"Immortal";"Robotics Facility";168;4
"Unit";"Immortal";"Robotics Facility";168;4
"Upgrade";"ProtossGroundArmorsLevel1";"Forge";157;0
"Upgrade";"ProtossGroundWeaponsLevel1";"Forge";157;0
"Building";"Pylon";NA;176;0
"Building";"HighTemplar";NA;193;0
"Building";"HighTemplar";NA;193;0
"Building";"HighTemplar";NA;193;0
"Building";"HighTemplar";NA;193;0
"Building";"HighTemplar";NA;193;0
"Building";"HighTemplar";NA;193;0
"Unit";"Immortal";"Robotics Facility";179;4
"Unit";"Immortal";"Robotics Facility";185;4
"Unit";"Archon";"High Templar";193;0
"Unit";"Archon";"High Templar";193;0
"Unit";"Archon";"High Templar";193;0
"Unit";"Immortal";"Robotics Facility";193;4
"Unit";"Immortal";"Robotics Facility";193;4
"Building";"Pylon";NA;209;0
"Building";"Pylon";NA;209;0
"Building";"Pylon";NA;209;0
"Building";"Pylon";NA;209;0
"Building";"Pylon";NA;209;0
"Building";"DarkTemplar";NA;209;0
"Unit";"Immortal";"Robotics Facility";209;4
"Unit";"Immortal";"Robotics Facility";209;4
"Upgrade";"ProtossGroundArmorsLevel2";"Forge";201;0
"Building";"HighTemplar";NA;209;0
"Building";"HighTemplar";NA;209;0
"Building";"HighTemplar";NA;209;0
"Building";"HighTemplar";NA;209;0
"Building";"HighTemplar";NA;209;0
"Building";"Pylon";NA;217;0
"Building";"Pylon";NA;217;0
"Building";"Nexus";NA;209;0
"Unit";"Immortal";"Robotics Facility";217;4
"Unit";"Zealot";"Gateway";221;2
"Unit";"Zealot";"Gateway";221;2
"Unit";"Zealot";"Gateway";221;2
"Unit";"Zealot";"Gateway";221;2
"Unit";"Zealot";"Gateway";221;2
"Unit";"Zealot";"Gateway";221;2
"Unit";"Zealot";"Gateway";221;2
"Unit";"Immortal";"Robotics Facility";217;4
"Upgrade";"ProtossGroundWeaponsLevel2";"Forge";209;0
"Unit";"Archon";"High Templar";239;0
"Unit";"Archon";"High Templar";239;0
"Building";"Nexus";NA;217;0
"Building";"HighTemplar";NA;239;0
"Building";"HighTemplar";NA;239;0
"Building";"HighTemplar";NA;239;0
"Building";"HighTemplar";NA;239;0
"Building";"HighTemplar";NA;239;0
"Building";"HighTemplar";NA;239;0
"Building";"HighTemplar";NA;239;0
"Unit";"Zealot";"Gateway";239;2
"Unit";"Zealot";"Gateway";239;2
"Unit";"Zealot";"Gateway";239;2
"Unit";"Observer";"Robotics Facility";239;1
"Unit";"Observer";"Robotics Facility";239;1
"Unit";"Archon";"High Templar";249;0
"Unit";"Archon";"High Templar";249;0
"Unit";"Archon";"High Templar";249;0
"Building";"Pylon";NA;249;0
"Unit";"Zealot";"Gateway";250;2
"Unit";"Zealot";"Gateway";250;2
"Unit";"Zealot";"Gateway";250;2
"Unit";"Immortal";"Robotics Facility";245;4
"Unit";"Immortal";"Robotics Facility";250;4
"Unit";"Immortal";"Robotics Facility";256;4
"Building";"HighTemplar";NA;268;0
"Building";"HighTemplar";NA;268;0
"Building";"HighTemplar";NA;268;0
"Building";"HighTemplar";NA;268;0
"Building";"HighTemplar";NA;268;0
"Building";"Assimilator";NA;268;0
"Building";"Assimilator";NA;268;0
"Unit";"Zealot";"Gateway";268;2
"Unit";"Zealot";"Gateway";268;2
"Unit";"Zealot";"Gateway";268;2
"Unit";"Immortal";"Robotics Facility";268;4
"Building";"DarkTemplar";NA;278;0
"Unit";"Zealot";"Gateway";278;2
"Unit";"Zealot";"Gateway";278;2
"Unit";"Zealot";"Gateway";278;2
"Building";"Nexus";NA;264;0
"Unit";"Zealot";"Gateway";278;2
"Unit";"Zealot";"Gateway";286;2
"Building";"HighTemplar";NA;288;0
"Building";"HighTemplar";NA;288;0
"Building";"HighTemplar";NA;288;0
"Unit";"Zealot";"Gateway";288;2
"Unit";"Zealot";"Gateway";288;2
"Unit";"Zealot";"Gateway";288;2
"Unit";"Zealot";"Gateway";288;2
"Unit";"Zealot";"Gateway";288;2
"Unit";"Zealot";"Gateway";288;2
"Unit";"Immortal";"Robotics Facility";288;4
"Unit";"Immortal";"Robotics Facility";288;4
"Building";"Pylon";NA;288;0
"Building";"Pylon";NA;288;0
