"type";"unit_name";"on_building";"total_supply";"supply"
"Building";"Pylon";NA;13;0
"Building";"Assimilator";NA;15;0
"Building";"Gateway";NA;15;0
"Building";"Assimilator";NA;21;0
"Building";"Pylon";NA;21;0
"Building";"CyberneticsCore";NA;21;0
"Unit";"Zealot";"Gateway";22;2
"Building";"Nexus";NA;20;0
"Unit";"Stalker";"Gateway";26;2
"Building";"Gateway";NA;23;0
"Building";"Pylon";NA;35;0
"Building";"Stargate";NA;29;0
"Building";"Pylon";NA;37;0
"Unit";"Sentry";"Gateway";36;2
"Unit";"Sentry";"Gateway";36;2
"Unit";"Oracle";"Stargate";37;3
"Unit";"Adept";"Gateway";54;2
"Unit";"Adept";"Gateway";54;2
"Building";"Assimilator";NA;52;0
"Building";"Assimilator";NA;52;0
"Building";"Pylon";NA;54;0
"Building";"TwilightCouncil";NA;53;0
"Building";"RoboticsFacility";NA;51;0
"Building";"Gateway";NA;51;0
"Unit";"Adept";"Gateway";64;2
"Unit";"Adept";"Gateway";64;2
"Unit";"Observer";"Robotics Facility";68;1
"Building";"Pylon";NA;70;0
"Building";"Pylon";NA;70;0
"Building";"Pylon";NA;70;0
"Building";"Pylon";NA;70;0
"Building";"Pylon";NA;70;0
"Unit";"Zealot";"Gateway";77;2
"Unit";"Zealot";"Gateway";77;2
"Unit";"Zealot";"Gateway";77;2
"Building";"Gateway";NA;70;0
"Unit";"Immortal";"Robotics Facility";71;4
"Building";"Gateway";NA;71;0
"Building";"Gateway";NA;71;0
"Building";"Nexus";NA;70;0
"Unit";"Phoenix";"Stargate";75;2
"Building";"RoboticsFacility";NA;73;0
"Upgrade";"Charge";"TwilightCouncil";71;0
"Building";"Gateway";NA;89;0
"Building";"Gateway";NA;89;0
"Unit";"Immortal";"Robotics Facility";93;4
"Building";"TemplarArchive";NA;93;0
"Unit";"Zealot";"Gateway";105;2
"Building";"Assimilator";NA;103;0
"Unit";"Zealot";"Gateway";105;2
"Unit";"Zealot";"Gateway";105;2
"Unit";"Zealot";"Gateway";105;2
"Unit";"Stalker";"Gateway";105;2
"Unit";"Stalker";"Gateway";105;2
"Unit";"Stalker";"Gateway";105;2
"Building";"Assimilator";NA;105;0
"Unit";"Immortal";"Robotics Facility";103;4
"Unit";"Immortal";"Robotics Facility";103;4
"Building";"Pylon";NA;119;0
"Building";"Pylon";NA;119;0
"Building";"Pylon";NA;119;0
"Building";"Pylon";NA;119;0
"Building";"Pylon";NA;119;0
"Unit";"Zealot";"Gateway";127;2
"Unit";"Zealot";"Gateway";127;2
"Unit";"Zealot";"Gateway";127;2
"Building";"HighTemplar";NA;127;0
"Building";"HighTemplar";NA;127;0
"Building";"HighTemplar";NA;127;0
"Building";"Forge";NA;127;0
"Unit";"Zealot";"Gateway";134;2
"Unit";"Zealot";"Gateway";134;2
"Unit";"Stalker";"Gateway";134;2
"Unit";"Stalker";"Gateway";134;2
"Unit";"Stalker";"Gateway";134;2
"Unit";"Immortal";"Robotics Facility";127;4
"Unit";"Immortal";"Robotics Facility";127;4
"Building";"ShieldBattery";NA;152;0
"Building";"ShieldBattery";NA;152;0
"Unit";"Immortal";"Robotics Facility";152;4
"Unit";"Immortal";"Robotics Facility";152;4
"Building";"Gateway";NA;144;0
"Building";"Gateway";NA;144;0
"Building";"Pylon";NA;152;0
"Building";"Gateway";NA;152;0
"Building";"Pylon";NA;152;0
"Unit";"Zealot";"Gateway";160;2
"Unit";"Zealot";"Gateway";160;2
"Building";"Pylon";NA;160;0
"Unit";"Zealot";"Gateway";160;2
"Unit";"Zealot";"Gateway";160;2
"Unit";"Zealot";"Gateway";160;2
"Building";"Pylon";NA;160;0
"Building";"Pylon";NA;160;0
"Unit";"Zealot";"Gateway";170;2
"Unit";"Zealot";"Gateway";170;2
"Unit";"Immortal";"Robotics Facility";152;4
"Unit";"Zealot";"Gateway";170;2
"Unit";"Zealot";"Gateway";180;2
"Unit";"Zealot";"Gateway";180;2
"Unit";"Immortal";"Robotics Facility";160;4
"Building";"RoboticsBay";NA;160;0
"Unit";"Zealot";"Gateway";188;2
"Unit";"Zealot";"Gateway";188;2
"Unit";"Zealot";"Gateway";188;2
"Upgrade";"ProtossGroundWeaponsLevel1";"Forge";152;0
"Unit";"Zealot";"Gateway";188;2
"Unit";"Zealot";"Gateway";188;2
"Unit";"Stalker";"Gateway";190;2
"Unit";"Stalker";"Gateway";192;2
"Building";"Nexus";NA;160;0
"Unit";"Zealot";"Gateway";202;2
"Unit";"Zealot";"Gateway";202;2
"Unit";"Zealot";"Gateway";202;2
"Unit";"Zealot";"Gateway";202;2
"Unit";"Zealot";"Gateway";202;2
"Unit";"Zealot";"Gateway";202;2
"Unit";"Zealot";"Gateway";202;2
"Unit";"Zealot";"Gateway";202;2
"Unit";"Zealot";"Gateway";202;2
"Unit";"Zealot";"Gateway";202;2
"Unit";"Zealot";"Gateway";202;2
"Building";"DarkShrine";NA;160;0
"Building";"DarkTemplar";NA;224;0
"Building";"DarkTemplar";NA;224;0
"Building";"DarkTemplar";NA;224;0
"Building";"DarkTemplar";NA;224;0
"Building";"DarkTemplar";NA;224;0
"Unit";"Observer";"Robotics Facility";224;1
"Unit";"Observer";"Robotics Facility";224;1
"Unit";"Zealot";"Gateway";226;2
"Unit";"Zealot";"Gateway";226;2
"Unit";"Zealot";"Gateway";226;2
"Unit";"Zealot";"Gateway";226;2
"Unit";"Zealot";"Gateway";226;2
"Unit";"Zealot";"Gateway";226;2
"Building";"DarkTemplar";NA;238;0
"Building";"DarkTemplar";NA;238;0
"Building";"DarkTemplar";NA;238;0
"Building";"DarkTemplar";NA;238;0
"Unit";"Stalker";"Gateway";238;2
"Unit";"Stalker";"Gateway";238;2
"Unit";"Stalker";"Gateway";238;2
"Unit";"Stalker";"Gateway";238;2
"Unit";"Stalker";"Gateway";238;2
"Upgrade";"ProtossGroundWeaponsLevel2";"Forge";224;0
"Building";"Assimilator";NA;248;0
"Unit";"Zealot";"Gateway";248;2
"Unit";"Zealot";"Gateway";248;2
"Unit";"Zealot";"Gateway";248;2
"Unit";"Zealot";"Gateway";248;2
"Unit";"Zealot";"Gateway";248;2
"Unit";"Zealot";"Gateway";248;2
"Unit";"Zealot";"Gateway";248;2
"Unit";"Zealot";"Gateway";248;2
"Unit";"Zealot";"Gateway";248;2
"Building";"Assimilator";NA;248;0
"Unit";"Stalker";"Gateway";266;2
"Unit";"Stalker";"Gateway";266;2
"Unit";"Stalker";"Gateway";266;2
"Unit";"Stalker";"Gateway";266;2
"Unit";"Stalker";"Gateway";266;2
"Unit";"Stalker";"Gateway";266;2
"Unit";"Zealot";"Gateway";266;2
"Unit";"Zealot";"Gateway";266;2
"Unit";"Zealot";"Gateway";266;2
"Unit";"Zealot";"Gateway";266;2
"Unit";"Zealot";"Gateway";266;2
"Building";"DarkTemplar";NA;288;0
"Building";"DarkTemplar";NA;288;0
"Building";"DarkTemplar";NA;288;0
"Building";"DarkTemplar";NA;288;0
"Building";"DarkTemplar";NA;288;0
"Unit";"Zealot";"Gateway";288;2
"Unit";"Zealot";"Gateway";288;2
"Unit";"Colossus";"Robotics Facility";266;6
"Unit";"Colossus";"Robotics Facility";266;6
"Building";"Nexus";NA;266;0
"Unit";"Stalker";"Gateway";304;2
"Unit";"Stalker";"Gateway";304;2
"Unit";"Stalker";"Gateway";304;2
"Unit";"Stalker";"Gateway";304;2
"Unit";"Zealot";"Gateway";312;2
"Unit";"Zealot";"Gateway";312;2
"Unit";"Zealot";"Gateway";312;2
"Unit";"Zealot";"Gateway";312;2
"Unit";"Zealot";"Gateway";312;2
"Upgrade";"ProtossGroundWeaponsLevel3";"Forge";266;0
"Building";"HighTemplar";NA;322;0
"Building";"HighTemplar";NA;322;0
"Building";"HighTemplar";NA;322;0
"Building";"HighTemplar";NA;322;0
"Unit";"Zealot";"Gateway";322;2
"Unit";"Zealot";"Gateway";322;2
"Unit";"Archon";"High Templar";322;0
"Unit";"Archon";"High Templar";322;0
"Building";"Stargate";NA;312;0
"Building";"Stargate";NA;312;0
"Building";"FleetBeacon";NA;312;0
"Unit";"Stalker";"Gateway";326;2
"Unit";"Stalker";"Gateway";326;2
"Unit";"Stalker";"Gateway";326;2
"Unit";"Stalker";"Gateway";326;2
"Unit";"Stalker";"Gateway";326;2
"Unit";"Stalker";"Gateway";326;2
"Unit";"Stalker";"Gateway";326;2
