"type";"unit_name";"on_building";"total_supply";"supply"
"Building";"Pylon";NA;13;0
"Building";"Assimilator";NA;20;0
"Building";"Assimilator";NA;20;0
"Building";"Gateway";NA;19;0
"Building";"Pylon";NA;22;0
"Building";"Nexus";NA;18;0
"Building";"Gateway";NA;20;0
"Building";"CyberneticsCore";NA;23;0
"Unit";"Zealot";"Gateway";23;2
"Unit";"Adept";"Gateway";27;2
"Unit";"Adept";"Gateway";28;2
"Building";"Stargate";NA;33;0
"Unit";"Adept";"Gateway";39;2
"Unit";"Adept";"Gateway";39;2
"Building";"Pylon";NA;41;0
"Building";"Pylon";NA;43;0
"Unit";"Oracle";"Stargate";47;3
"Building";"Assimilator";NA;49;0
"Building";"Assimilator";NA;49;0
"Building";"Pylon";NA;54;0
"Building";"Pylon";NA;56;0
"Unit";"Oracle";"Stargate";49;3
"Building";"RoboticsFacility";NA;51;0
"Building";"Gateway";NA;54;0
"Building";"Gateway";NA;54;0
"Unit";"Sentry";"Gateway";61;2
"Unit";"Sentry";"Gateway";61;2
"Unit";"Phoenix";"Stargate";61;2
"Building";"OracleStasisTrap";NA;73;0
"Building";"Gateway";NA;63;0
"Building";"Gateway";NA;65;0
"Unit";"Immortal";"Robotics Facility";73;4
"Unit";"Zealot";"Gateway";77;2
"Unit";"Zealot";"Gateway";77;2
"Unit";"Zealot";"Gateway";77;2
"Unit";"Zealot";"Gateway";77;2
"Building";"Pylon";NA;77;0
"Building";"Forge";NA;75;0
"Building";"TwilightCouncil";NA;75;0
"Building";"RoboticsFacility";NA;77;0
"Unit";"Immortal";"Robotics Facility";89;4
"Unit";"Sentry";"Gateway";89;2
"Unit";"Sentry";"Gateway";89;2
"Unit";"Sentry";"Gateway";89;2
"Building";"Nexus";NA;77;0
"Building";"OracleStasisTrap";NA;101;0
"Building";"Pylon";NA;101;0
"Building";"Pylon";NA;101;0
"Building";"Pylon";NA;101;0
"Building";"Pylon";NA;101;0
"Unit";"Immortal";"Robotics Facility";89;4
"Building";"Assimilator";NA;101;0
"Building";"Assimilator";NA;101;0
"Unit";"Zealot";"Gateway";108;2
"Unit";"Zealot";"Gateway";108;2
"Unit";"Zealot";"Gateway";108;2
"Unit";"Zealot";"Gateway";108;2
"Unit";"Zealot";"Gateway";108;2
"Building";"Gateway";NA;99;0
"Unit";"Zealot";"Gateway";108;2
"Building";"Gateway";NA;101;0
"Building";"OracleStasisTrap";NA;118;0
"Unit";"Immortal";"Robotics Facility";101;4
"Building";"TemplarArchive";NA;101;0
"Upgrade";"Charge";"TwilightCouncil";93;0
"Unit";"Immortal";"Robotics Facility";105;4
"Upgrade";"ProtossGroundWeaponsLevel1";"Forge";101;0
"Unit";"Zealot";"Gateway";131;2
"Unit";"Zealot";"Gateway";131;2
"Unit";"Zealot";"Gateway";131;2
"Unit";"Zealot";"Gateway";131;2
"Unit";"Zealot";"Gateway";131;2
"Unit";"Zealot";"Gateway";131;2
"Unit";"Immortal";"Robotics Facility";122;4
"Building";"HighTemplar";NA;148;0
"Building";"HighTemplar";NA;148;0
"Unit";"Immortal";"Robotics Facility";127;4
"Unit";"Archon";"High Templar";150;0
"Building";"Pylon";NA;150;0
"Unit";"Zealot";"Gateway";154;2
"Unit";"Zealot";"Gateway";154;2
"Unit";"Zealot";"Gateway";154;2
"Unit";"Zealot";"Gateway";154;2
"Unit";"Zealot";"Gateway";154;2
"Unit";"Zealot";"Gateway";154;2
"Building";"PhotonCannon";NA;150;0
"Building";"PhotonCannon";NA;154;0
"Building";"Pylon";NA;154;0
"Building";"Pylon";NA;154;0
"Unit";"Zealot";"Gateway";166;2
"Unit";"Zealot";"Gateway";166;2
"Unit";"Immortal";"Robotics Facility";154;4
"Building";"Nexus";NA;150;0
"Unit";"Immortal";"Robotics Facility";174;4
"Building";"HighTemplar";NA;181;0
"Building";"HighTemplar";NA;181;0
"Building";"HighTemplar";NA;181;0
"Building";"HighTemplar";NA;181;0
"Building";"HighTemplar";NA;181;0
"Upgrade";"ProtossGroundWeaponsLevel2";"Forge";154;0
"Building";"HighTemplar";NA;181;0
"Building";"HighTemplar";NA;181;0
"Building";"HighTemplar";NA;181;0
"Unit";"Archon";"High Templar";184;0
"Unit";"Archon";"High Templar";184;0
"Unit";"Archon";"High Templar";184;0
"Unit";"Archon";"High Templar";184;0
"Unit";"Immortal";"Robotics Facility";177;4
"Unit";"Immortal";"Robotics Facility";181;4
"Unit";"Zealot";"Gateway";192;2
"Unit";"Zealot";"Gateway";192;2
"Unit";"Zealot";"Gateway";192;2
"Unit";"Zealot";"Gateway";192;2
"Unit";"Zealot";"Gateway";192;2
"Unit";"Zealot";"Gateway";192;2
"Unit";"Zealot";"Gateway";192;2
"Unit";"Zealot";"Gateway";192;2
"Building";"ShieldBattery";NA;192;0
"Building";"ShieldBattery";NA;192;0
"Building";"Gateway";NA;184;0
"Building";"Gateway";NA;188;0
"Unit";"Zealot";"Gateway";212;2
"Unit";"Zealot";"Gateway";212;2
"Unit";"Zealot";"Gateway";212;2
"Unit";"Zealot";"Gateway";212;2
"Unit";"Zealot";"Gateway";212;2
"Unit";"Zealot";"Gateway";212;2
"Unit";"Zealot";"Gateway";212;2
"Unit";"Zealot";"Gateway";212;2
"Building";"Assimilator";NA;210;0
"Unit";"Immortal";"Robotics Facility";188;4
"Building";"Assimilator";NA;210;0
"Building";"HighTemplar";NA;232;0
"Building";"HighTemplar";NA;232;0
"Building";"PhotonCannon";NA;210;0
"Unit";"Immortal";"Robotics Facility";210;4
"Unit";"Zealot";"Gateway";232;2
"Unit";"Zealot";"Gateway";232;2
"Unit";"Zealot";"Gateway";232;2
"Unit";"Zealot";"Gateway";232;2
"Unit";"Zealot";"Gateway";232;2
"Unit";"Zealot";"Gateway";232;2
"Unit";"Immortal";"Robotics Facility";228;4
"Unit";"Zealot";"Gateway";252;2
"Unit";"Zealot";"Gateway";252;2
"Unit";"Zealot";"Gateway";252;2
"Unit";"Zealot";"Gateway";252;2
"Unit";"Zealot";"Gateway";252;2
"Unit";"Zealot";"Gateway";252;2
"Unit";"Zealot";"Gateway";265;2
"Unit";"Zealot";"Gateway";265;2
"Unit";"Zealot";"Gateway";265;2
"Unit";"Zealot";"Gateway";265;2
"Unit";"Immortal";"Robotics Facility";232;4
"Unit";"Immortal";"Robotics Facility";248;4
"Unit";"Observer";"Robotics Facility";273;1
"Unit";"Zealot";"Gateway";284;2
"Unit";"Zealot";"Gateway";284;2
"Unit";"Zealot";"Gateway";284;2
"Unit";"Zealot";"Gateway";284;2
"Unit";"Zealot";"Gateway";284;2
"Unit";"Zealot";"Gateway";284;2
"Unit";"Observer";"Robotics Facility";279;1
"Unit";"Zealot";"Gateway";284;2
"Unit";"Zealot";"Gateway";284;2
"Building";"Pylon";NA;284;0
"Building";"HighTemplar";NA;301;0
"Building";"HighTemplar";NA;301;0
"Unit";"Zealot";"Gateway";301;2
"Unit";"Archon";"High Templar";301;0
"Building";"HighTemplar";NA;301;0
"Building";"HighTemplar";NA;301;0
"Building";"HighTemplar";NA;301;0
"Building";"HighTemplar";NA;301;0
"Building";"HighTemplar";NA;301;0
"Building";"HighTemplar";NA;301;0
"Building";"HighTemplar";NA;301;0
"Upgrade";"ProtossGroundWeaponsLevel3";"Forge";232;0
"Unit";"Archon";"High Templar";303;0
"Unit";"Archon";"High Templar";303;0
"Unit";"Archon";"High Templar";303;0
"Unit";"Observer";"Robotics Facility";301;1
"Unit";"Zealot";"Gateway";304;2
"Unit";"Zealot";"Gateway";304;2
"Unit";"Zealot";"Gateway";304;2
