"type";"unit_name";"on_building";"total_supply";"supply"
"Building";"Pylon";NA;13;0
"Building";"Assimilator";NA;16;0
"Building";"Gateway";NA;15;0
"Building";"Assimilator";NA;20;0
"Building";"CyberneticsCore";NA;20;0
"Building";"Pylon";NA;21;0
"Unit";"Stalker";"Gateway";21;2
"Building";"Nexus";NA;19;0
"Unit";"Stalker";"Gateway";24;2
"Building";"TwilightCouncil";NA;26;0
"Unit";"Stalker";"Gateway";33;2
"Building";"Gateway";NA;35;0
"Building";"Gateway";NA;35;0
"Building";"Pylon";NA;43;0
"Building";"Assimilator";NA;42;0
"Building";"Pylon";NA;44;0
"Unit";"Stalker";"Gateway";47;2
"Unit";"Stalker";"Gateway";47;2
"Unit";"Stalker";"Gateway";47;2
"Building";"Pylon";NA;45;0
"Building";"RoboticsFacility";NA;42;0
"Unit";"Stalker";"Gateway";57;2
"Unit";"Stalker";"Gateway";57;2
"Unit";"Stalker";"Gateway";57;2
"Unit";"Observer";"Robotics Facility";56;1
"Building";"Pylon";NA;63;0
"Unit";"Stalker";"Gateway";65;2
"Unit";"Stalker";"Gateway";65;2
"Unit";"Observer";"Robotics Facility";63;1
"Building";"Pylon";NA;65;0
"Unit";"Observer";"Robotics Facility";72;1
"Building";"Nexus";NA;63;0
"Unit";"Observer";"Robotics Facility";76;1
"Building";"Forge";NA;74;0
"Building";"Forge";NA;74;0
"Building";"Pylon";NA;79;0
"Building";"Pylon";NA;79;0
"Upgrade";"Charge";"TwilightCouncil";72;0
"Unit";"Sentry";"Gateway";83;2
"Unit";"Sentry";"Gateway";83;2
"Unit";"Sentry";"Gateway";83;2
"Building";"Gateway";NA;80;0
"Building";"Gateway";NA;80;0
"Building";"Gateway";NA;80;0
"Building";"Gateway";NA;80;0
"Building";"Assimilator";NA;87;0
"Building";"Gateway";NA;80;0
"Building";"Assimilator";NA;89;0
"Building";"Pylon";NA;91;0
"Unit";"Zealot";"Gateway";98;2
"Unit";"Zealot";"Gateway";98;2
"Unit";"Zealot";"Gateway";98;2
"Unit";"Zealot";"Gateway";98;2
"Unit";"Zealot";"Gateway";98;2
"Unit";"Zealot";"Gateway";98;2
"Unit";"Zealot";"Gateway";98;2
"Unit";"Zealot";"Gateway";98;2
"Unit";"Observer";"Robotics Facility";95;1
"Building";"Assimilator";NA;97;0
"Unit";"Zealot";"Gateway";117;2
"Unit";"Zealot";"Gateway";117;2
"Unit";"Zealot";"Gateway";117;2
"Unit";"Zealot";"Gateway";117;2
"Unit";"Zealot";"Gateway";117;2
"Unit";"Zealot";"Gateway";117;2
"Unit";"Zealot";"Gateway";117;2
"Building";"Pylon";NA;116;0
"Unit";"Zealot";"Gateway";117;2
"Building";"Pylon";NA;117;0
"Upgrade";"ProtossGroundWeaponsLevel1";"Forge";80;0
"Upgrade";"ProtossGroundArmorsLevel1";"Forge";80;0
"Building";"Pylon";NA;117;0
"Unit";"Zealot";"Gateway";135;2
"Unit";"Zealot";"Gateway";135;2
"Unit";"Zealot";"Gateway";135;2
"Unit";"Zealot";"Gateway";135;2
"Unit";"Zealot";"Gateway";135;2
"Unit";"Zealot";"Gateway";135;2
"Unit";"Zealot";"Gateway";147;2
"Unit";"Zealot";"Gateway";147;2
"Building";"Gateway";NA;117;0
"Building";"Gateway";NA;117;0
"Building";"TemplarArchive";NA;135;0
"Building";"HighTemplar";NA;156;0
"Building";"HighTemplar";NA;156;0
"Building";"HighTemplar";NA;156;0
"Building";"HighTemplar";NA;156;0
"Building";"HighTemplar";NA;156;0
"Building";"Pylon";NA;153;0
"Building";"HighTemplar";NA;157;0
"Building";"Pylon";NA;155;0
"Building";"ShieldBattery";NA;158;0
"Unit";"Stalker";"Gateway";158;2
"Unit";"Stalker";"Gateway";158;2
"Building";"ShieldBattery";NA;158;0
"Unit";"Zealot";"Gateway";158;2
"Building";"ShieldBattery";NA;158;0
"Unit";"Zealot";"Gateway";158;2
"Unit";"Zealot";"Gateway";158;2
"Unit";"Zealot";"Gateway";158;2
"Unit";"Zealot";"Gateway";158;2
"Unit";"Zealot";"Gateway";158;2
"Building";"Assimilator";NA;158;0
"Unit";"Zealot";"Gateway";162;2
"Building";"Nexus";NA;153;0
"Unit";"Zealot";"Gateway";174;2
"Building";"Gateway";NA;157;0
"Building";"Gateway";NA;157;0
"Building";"Assimilator";NA;158;0
"Unit";"Observer";"Robotics Facility";158;1
"Building";"Gateway";NA;158;0
"Building";"Gateway";NA;158;0
"Upgrade";"ProtossGroundWeaponsLevel2";"Forge";153;0
"Upgrade";"ProtossGroundArmorsLevel2";"Forge";153;0
"Unit";"Zealot";"Gateway";179;2
"Unit";"Zealot";"Gateway";179;2
"Unit";"Zealot";"Gateway";179;2
"Building";"Stargate";NA;158;0
"Unit";"Stalker";"Gateway";193;2
"Unit";"Stalker";"Gateway";193;2
"Unit";"Stalker";"Gateway";193;2
"Unit";"Stalker";"Gateway";193;2
"Unit";"Zealot";"Gateway";201;2
"Unit";"Zealot";"Gateway";201;2
"Unit";"Zealot";"Gateway";201;2
"Unit";"Zealot";"Gateway";201;2
"Building";"Pylon";NA;189;0
"Building";"Pylon";NA;201;0
"Unit";"Zealot";"Gateway";209;2
"Unit";"Zealot";"Gateway";209;2
"Unit";"Zealot";"Gateway";209;2
"Unit";"Zealot";"Gateway";209;2
"Unit";"Zealot";"Gateway";209;2
"Unit";"Zealot";"Gateway";209;2
"Unit";"Zealot";"Gateway";209;2
"Unit";"Zealot";"Gateway";209;2
"Unit";"Zealot";"Gateway";209;2
"Unit";"Zealot";"Gateway";209;2
"Unit";"Zealot";"Gateway";209;2
"Unit";"Zealot";"Gateway";209;2
"Building";"HighTemplar";NA;227;0
"Building";"HighTemplar";NA;227;0
"Building";"HighTemplar";NA;233;0
"Building";"HighTemplar";NA;233;0
"Building";"HighTemplar";NA;233;0
"Building";"HighTemplar";NA;233;0
"Building";"HighTemplar";NA;233;0
"Building";"HighTemplar";NA;233;0
"Unit";"Archon";"High Templar";233;0
"Unit";"Archon";"High Templar";233;0
"Unit";"Archon";"High Templar";233;0
"Building";"Pylon";NA;233;0
"Building";"Pylon";NA;233;0
"Building";"HighTemplar";NA;233;0
"Building";"HighTemplar";NA;233;0
"Building";"HighTemplar";NA;233;0
"Building";"Pylon";NA;233;0
"Upgrade";"ProtossGroundWeaponsLevel3";"Forge";189;0
"Upgrade";"ProtossGroundArmorsLevel3";"Forge";189;0
"Unit";"Stalker";"Gateway";234;2
"Unit";"Stalker";"Gateway";234;2
"Building";"PhotonCannon";NA;234;0
"Building";"PhotonCannon";NA;234;0
"Building";"PhotonCannon";NA;234;0
"Building";"Pylon";NA;234;0
"Building";"Nexus";NA;233;0
"Unit";"Stalker";"Gateway";238;2
"Unit";"Stalker";"Gateway";238;2
"Unit";"Stalker";"Gateway";238;2
"Unit";"Stalker";"Gateway";238;2
"Building";"FleetBeacon";NA;234;0
"Building";"Stargate";NA;234;0
"Building";"Stargate";NA;234;0
"Upgrade";"ProtossShieldsLevel1";"Forge";234;0
"Building";"HighTemplar";NA;249;0
"Building";"HighTemplar";NA;249;0
"Building";"HighTemplar";NA;249;0
"Unit";"Tempest";"Stargate";246;4
"Unit";"Tempest";"Stargate";246;4
"Unit";"Tempest";"Stargate";246;4
"Building";"HighTemplar";NA;249;0
"Building";"Assimilator";NA;261;0
"Building";"Assimilator";NA;261;0
"Unit";"Tempest";"Stargate";261;4
"Unit";"Tempest";"Stargate";261;4
"Building";"PhotonCannon";NA;261;0
"Building";"PhotonCannon";NA;261;0
"Upgrade";"ProtossAirArmorsLevel1";"CyberneticsCore";249;0
"Building";"PhotonCannon";NA;261;0
"Building";"PhotonCannon";NA;261;0
"Building";"Pylon";NA;261;0
"Building";"PhotonCannon";NA;261;0
"Building";"ShieldBattery";NA;261;0
"Building";"ShieldBattery";NA;261;0
"Building";"RoboticsBay";NA;261;0
"Upgrade";"ProtossShieldsLevel2";"Forge";261;0
"Unit";"Observer";"Robotics Facility";269;1
"Building";"Pylon";NA;270;0
"Building";"RoboticsFacility";NA;269;0
"Building";"CyberneticsCore";NA;270;0
"Unit";"Observer";"Robotics Facility";270;1
"Building";"Stargate";NA;269;0
"Building";"RoboticsFacility";NA;269;0
"Unit";"Oracle";"Stargate";270;3
"Upgrade";"ProtossAirArmorsLevel2";"CyberneticsCore";269;0
"Unit";"Mothership";"Mothership Core";269;6
"Upgrade";"ExtendedThermalLance";"RoboticsBay";270;0
"Upgrade";"ProtossShieldsLevel3";"Forge";269;0
"Unit";"Observer";"Robotics Facility";280;1
"Building";"HighTemplar";NA;281;0
"Building";"HighTemplar";NA;281;0
"Building";"HighTemplar";NA;281;0
"Building";"HighTemplar";NA;281;0
"Unit";"Archon";"High Templar";281;0
"Unit";"Tempest";"Stargate";280;4
"Upgrade";"ProtossAirWeaponsLevel1";"CyberneticsCore";274;0
"Building";"HighTemplar";NA;285;0
"Unit";"Colossus";"Robotics Facility";285;6
"Unit";"Colossus";"Robotics Facility";285;6
"Building";"HighTemplar";NA;297;0
"Unit";"Zealot";"Gateway";297;2
"Unit";"Zealot";"Gateway";297;2
"Unit";"Zealot";"Gateway";297;2
"Unit";"Carrier";"Stargate";281;6
"Unit";"Zealot";"Gateway";297;2
"Unit";"Zealot";"Gateway";297;2
"Unit";"Zealot";"Gateway";297;2
"Unit";"Zealot";"Gateway";297;2
"Unit";"Zealot";"Gateway";297;2
"Unit";"Zealot";"Gateway";297;2
"Unit";"Carrier";"Stargate";281;6
"Unit";"Carrier";"Stargate";281;6
"Unit";"Carrier";"Stargate";285;6
"Upgrade";"ProtossAirWeaponsLevel2";"CyberneticsCore";285;0
"Building";"Pylon";NA;339;0
"Building";"PhotonCannon";NA;339;0
"Building";"PhotonCannon";NA;339;0
"Building";"PhotonCannon";NA;339;0
"Building";"PhotonCannon";NA;339;0
"Building";"PhotonCannon";NA;339;0
"Building";"ShieldBattery";NA;339;0
"Unit";"Carrier";"Stargate";285;6
"Building";"HighTemplar";NA;339;0
"Building";"HighTemplar";NA;345;0
"Unit";"Carrier";"Stargate";297;6
"Building";"Pylon";NA;339;0
"Building";"Pylon";NA;339;0
"Upgrade";"ProtossAirArmorsLevel3";"CyberneticsCore";285;0
"Building";"Pylon";NA;339;0
"Building";"DarkShrine";NA;339;0
"Unit";"Carrier";"Stargate";339;6
"Unit";"Carrier";"Stargate";339;6
"Building";"Assimilator";NA;351;0
"Building";"Assimilator";NA;357;0
"Building";"PhotonCannon";NA;357;0
"Building";"PhotonCannon";NA;357;0
"Building";"Nexus";NA;339;0
"Building";"PhotonCannon";NA;363;0
"Building";"PhotonCannon";NA;363;0
"Building";"PhotonCannon";NA;363;0
"Building";"PhotonCannon";NA;363;0
"Building";"ShieldBattery";NA;363;0
"Building";"ShieldBattery";NA;363;0
"Building";"ShieldBattery";NA;363;0
"Building";"HighTemplar";NA;363;0
"Unit";"Observer";"Robotics Facility";363;1
"Unit";"Tempest";"Stargate";363;4
"Unit";"Tempest";"Stargate";363;4
"Unit";"Tempest";"Stargate";363;4
"Building";"HighTemplar";NA;376;0
"Building";"HighTemplar";NA;376;0
"Building";"HighTemplar";NA;376;0
"Building";"HighTemplar";NA;376;0
"Building";"HighTemplar";NA;376;0
"Building";"HighTemplar";NA;376;0
