"type";"unit_name";"on_building";"total_supply";"supply"
"Building";"Pylon";NA;13;0
"Building";"Assimilator";NA;16;0
"Building";"Gateway";NA;15;0
"Building";"Assimilator";NA;20;0
"Building";"Pylon";NA;20;0
"Building";"CyberneticsCore";NA;20;0
"Unit";"Adept";"Gateway";21;2
"Building";"Nexus";NA;19;0
"Unit";"Stalker";"Gateway";23;2
"Building";"TwilightCouncil";NA;28;0
"Building";"Pylon";NA;37;0
"Building";"ShieldBattery";NA;37;0
"Building";"Gateway";NA;36;0
"Building";"Gateway";NA;37;0
"Unit";"Stalker";"Gateway";42;2
"Unit";"Stalker";"Gateway";42;2
"Unit";"Stalker";"Gateway";42;2
"Building";"Pylon";NA;52;0
"Unit";"Stalker";"Gateway";54;2
"Unit";"Sentry";"Gateway";55;2
"Unit";"Sentry";"Gateway";56;2
"Building";"Assimilator";NA;62;0
"Unit";"Stalker";"Gateway";66;2
"Unit";"Stalker";"Gateway";66;2
"Building";"RoboticsFacility";NA;54;0
"Unit";"Stalker";"Gateway";72;2
"Building";"Nexus";NA;51;0
"Unit";"Stalker";"Gateway";76;2
"Upgrade";"Charge";"TwilightCouncil";64;0
"Unit";"Stalker";"Gateway";85;2
"Unit";"Stalker";"Gateway";85;2
"Building";"Pylon";NA;82;0
"Unit";"Zealot";"Gateway";99;2
"Building";"Pylon";NA;102;0
"Building";"Forge";NA;97;0
"Unit";"Zealot";"Gateway";105;2
"Unit";"Zealot";"Gateway";105;2
"Unit";"Immortal";"Robotics Facility";96;4
"Building";"Pylon";NA;103;0
"Building";"Forge";NA;99;0
"Building";"Pylon";NA;105;0
"Unit";"Zealot";"Gateway";116;2
"Building";"ShieldBattery";NA;104;0
"Building";"ShieldBattery";NA;105;0
"Unit";"Zealot";"Gateway";120;2
"Unit";"Zealot";"Gateway";120;2
"Building";"Gateway";NA;102;0
"Building";"Gateway";NA;102;0
"Unit";"Immortal";"Robotics Facility";113;4
"Unit";"Zealot";"Gateway";129;2
"Unit";"Zealot";"Gateway";129;2
"Unit";"Zealot";"Gateway";129;2
"Unit";"Zealot";"Gateway";129;2
"Unit";"Zealot";"Gateway";129;2
"Building";"Pylon";NA;124;0
"Building";"Pylon";NA;125;0
"Unit";"Zealot";"Gateway";139;2
"Unit";"Zealot";"Gateway";139;2
"Unit";"Zealot";"Gateway";139;2
"Unit";"Zealot";"Gateway";139;2
"Unit";"Zealot";"Gateway";139;2
"Building";"Gateway";NA;125;0
"Building";"Gateway";NA;129;0
"Building";"Gateway";NA;129;0
"Upgrade";"ProtossGroundArmorsLevel1";"Forge";116;0
"Building";"Gateway";NA;131;0
"Unit";"Stalker";"Gateway";151;2
"Unit";"Stalker";"Gateway";151;2
"Unit";"Stalker";"Gateway";151;2
"Unit";"Stalker";"Gateway";151;2
"Unit";"Stalker";"Gateway";151;2
"Unit";"Zealot";"Gateway";161;2
"Unit";"Zealot";"Gateway";161;2
"Unit";"Zealot";"Gateway";165;2
"Upgrade";"ProtossGroundWeaponsLevel1";"Forge";139;0
"Building";"Pylon";NA;165;0
"Unit";"Zealot";"Gateway";167;2
"Unit";"Zealot";"Gateway";169;2
"Unit";"Zealot";"Gateway";169;2
"Unit";"Zealot";"Gateway";169;2
"Unit";"Zealot";"Gateway";169;2
"Unit";"Zealot";"Gateway";169;2
"Unit";"Zealot";"Gateway";169;2
"Unit";"Zealot";"Gateway";169;2
"Building";"Nexus";NA;165;0
"Unit";"Sentry";"Gateway";190;2
"Unit";"Sentry";"Gateway";190;2
"Unit";"Zealot";"Gateway";190;2
"Unit";"Zealot";"Gateway";190;2
"Unit";"Zealot";"Gateway";204;2
"Unit";"Zealot";"Gateway";204;2
"Unit";"Zealot";"Gateway";204;2
"Unit";"Zealot";"Gateway";204;2
"Upgrade";"ProtossGroundArmorsLevel2";"Forge";165;0
"Unit";"Stalker";"Gateway";214;2
"Unit";"Stalker";"Gateway";214;2
"Unit";"Stalker";"Gateway";214;2
"Upgrade";"ProtossGroundWeaponsLevel2";"Forge";190;0
"Building";"Pylon";NA;223;0
"Building";"Pylon";NA;223;0
"Building";"Pylon";NA;224;0
"Unit";"Zealot";"Gateway";225;2
"Unit";"Zealot";"Gateway";225;2
"Unit";"Zealot";"Gateway";225;2
"Unit";"Zealot";"Gateway";225;2
"Unit";"Zealot";"Gateway";225;2
"Unit";"Zealot";"Gateway";225;2
"Unit";"Zealot";"Gateway";225;2
"Unit";"Zealot";"Gateway";225;2
"Unit";"Zealot";"Gateway";225;2
"Unit";"Stalker";"Gateway";244;2
"Unit";"Stalker";"Gateway";244;2
"Unit";"Stalker";"Gateway";244;2
"Unit";"Stalker";"Gateway";244;2
"Unit";"Phoenix";"Stargate";225;2
"Unit";"Adept";"Gateway";255;2
"Unit";"Adept";"Gateway";255;2
"Unit";"Stalker";"Gateway";261;2
"Unit";"Zealot";"Gateway";266;2
"Unit";"Zealot";"Gateway";266;2
"Unit";"Zealot";"Gateway";266;2
"Unit";"Zealot";"Gateway";266;2
"Unit";"Zealot";"Gateway";275;2
"Unit";"Zealot";"Gateway";275;2
"Building";"Nexus";NA;244;0
"Unit";"Zealot";"Gateway";279;2
"Unit";"Zealot";"Gateway";279;2
"Unit";"Zealot";"Gateway";279;2
"Unit";"Zealot";"Gateway";279;2
"Unit";"Zealot";"Gateway";279;2
"Unit";"Zealot";"Gateway";279;2
"Unit";"Zealot";"Gateway";294;2
"Unit";"Zealot";"Gateway";295;2
"Unit";"Zealot";"Gateway";295;2
"Unit";"Zealot";"Gateway";295;2
"Unit";"Stalker";"Gateway";307;2
"Unit";"Sentry";"Gateway";312;2
"Unit";"Sentry";"Gateway";312;2
"Unit";"Sentry";"Gateway";312;2
"Unit";"Sentry";"Gateway";312;2
"Unit";"Stalker";"Gateway";324;2
"Unit";"Stalker";"Gateway";325;2
"Building";"TemplarArchive";NA;306;0
"Building";"HighTemplar";NA;332;0
"Building";"HighTemplar";NA;332;0
"Building";"HighTemplar";NA;332;0
"Building";"HighTemplar";NA;332;0
"Building";"HighTemplar";NA;333;0
"Building";"Pylon";NA;333;0
"Building";"Pylon";NA;333;0
"Unit";"Zealot";"Gateway";334;2
"Unit";"Zealot";"Gateway";334;2
"Unit";"Zealot";"Gateway";334;2
"Unit";"Zealot";"Gateway";334;2
"Unit";"Zealot";"Gateway";334;2
"Unit";"Zealot";"Gateway";334;2
"Unit";"Zealot";"Gateway";334;2
"Unit";"Zealot";"Gateway";334;2
"Building";"Assimilator";NA;333;0
"Building";"Assimilator";NA;333;0
"Building";"Assimilator";NA;333;0
"Building";"Assimilator";NA;333;0
"Unit";"Stalker";"Gateway";350;2
"Unit";"Stalker";"Gateway";350;2
"Unit";"Stalker";"Gateway";350;2
"Unit";"Stalker";"Gateway";350;2
"Unit";"Zealot";"Gateway";358;2
"Building";"Pylon";NA;360;0
"Building";"Pylon";NA;360;0
"Building";"Pylon";NA;360;0
"Building";"Pylon";NA;360;0
"Unit";"Zealot";"Gateway";360;2
"Unit";"Zealot";"Gateway";360;2
"Unit";"Zealot";"Gateway";360;2
"Unit";"Zealot";"Gateway";360;2
"Unit";"Zealot";"Gateway";360;2
"Unit";"Zealot";"Gateway";360;2
"Unit";"Zealot";"Gateway";360;2
"Building";"Pylon";NA;360;0
"Building";"Pylon";NA;360;0
"Unit";"Zealot";"Gateway";375;2
"Unit";"Zealot";"Gateway";375;2
"Building";"Nexus";NA;360;0
"Unit";"Archon";"High Templar";379;0
"Unit";"Zealot";"Gateway";379;2
"Unit";"Zealot";"Gateway";379;2
"Unit";"Zealot";"Gateway";379;2
"Unit";"Zealot";"Gateway";379;2
"Unit";"Archon";"High Templar";379;0
"Unit";"Zealot";"Gateway";379;2
"Unit";"Zealot";"Gateway";379;2
"Building";"HighTemplar";NA;391;0
"Building";"HighTemplar";NA;391;0
"Building";"HighTemplar";NA;391;0
"Building";"HighTemplar";NA;393;0
"Building";"HighTemplar";NA;393;0
"Unit";"Archon";"High Templar";393;0
"Building";"Pylon";NA;393;0
"Unit";"Immortal";"Robotics Facility";393;4
"Building";"Assimilator";NA;395;0
"Building";"HighTemplar";NA;401;0
"Building";"HighTemplar";NA;401;0
"Building";"HighTemplar";NA;401;0
"Building";"HighTemplar";NA;401;0
"Building";"HighTemplar";NA;401;0
"Building";"HighTemplar";NA;401;0
"Building";"HighTemplar";NA;401;0
"Building";"DarkShrine";NA;391;0
"Unit";"Zealot";"Gateway";401;2
"Unit";"Zealot";"Gateway";401;2
"Unit";"Archon";"High Templar";401;0
"Unit";"Archon";"High Templar";401;0
"Unit";"Archon";"High Templar";401;0
"Unit";"Stalker";"Gateway";405;2
"Unit";"Stalker";"Gateway";405;2
"Unit";"Stalker";"Gateway";405;2
"Building";"DarkTemplar";NA;405;0
"Building";"DarkTemplar";NA;405;0
"Unit";"Zealot";"Gateway";411;2
"Unit";"Zealot";"Gateway";411;2
"Building";"Pylon";NA;405;0
"Unit";"Zealot";"Gateway";415;2
"Unit";"Zealot";"Gateway";415;2
"Unit";"Zealot";"Gateway";415;2
"Unit";"Zealot";"Gateway";415;2
"Unit";"Zealot";"Gateway";415;2
"Building";"DarkTemplar";NA;425;0
"Unit";"Immortal";"Robotics Facility";411;4
"Building";"Nexus";NA;401;0
