"type";"unit_name";"on_building";"total_supply";"supply"
"Building";"Pylon";NA;13;0
"Building";"Gateway";NA;14;0
"Building";"Assimilator";NA;16;0
"Building";"Pylon";NA;20;0
"Building";"Assimilator";NA;20;0
"Building";"CyberneticsCore";NA;19;0
"Building";"Nexus";NA;17;0
"Unit";"Stalker";"Gateway";22;2
"Building";"TwilightCouncil";NA;23;0
"Unit";"Stalker";"Gateway";26;2
"Unit";"Stalker";"Gateway";35;2
"Building";"ShieldBattery";NA;35;0
"Building";"ShieldBattery";NA;35;0
"Unit";"Stalker";"Gateway";39;2
"Building";"Gateway";NA;35;0
"Building";"Gateway";NA;35;0
"Building";"Pylon";NA;43;0
"Building";"RoboticsFacility";NA;35;0
"Unit";"Stalker";"Gateway";45;2
"Unit";"Stalker";"Gateway";45;2
"Unit";"Stalker";"Gateway";45;2
"Building";"Pylon";NA;44;0
"Building";"Assimilator";NA;44;0
"Unit";"Stalker";"Gateway";55;2
"Unit";"Stalker";"Gateway";55;2
"Unit";"Observer";"Robotics Facility";54;1
"Building";"Pylon";NA;60;0
"Building";"Pylon";NA;63;0
"Building";"Forge";NA;63;0
"Building";"Forge";NA;63;0
"Unit";"Zealot";"Gateway";63;2
"Unit";"Zealot";"Gateway";63;2
"Unit";"Zealot";"Gateway";63;2
"Building";"Gateway";NA;63;0
"Building";"Gateway";NA;63;0
"Building";"Gateway";NA;63;0
"Building";"Gateway";NA;63;0
"Building";"Gateway";NA;63;0
"Upgrade";"Charge";"TwilightCouncil";63;0
"Building";"Nexus";NA;63;0
"Unit";"Zealot";"Gateway";71;2
"Unit";"Zealot";"Gateway";71;2
"Unit";"Zealot";"Gateway";71;2
"Unit";"Zealot";"Gateway";71;2
"Unit";"Zealot";"Gateway";71;2
"Building";"Pylon";NA;69;0
"Unit";"Sentry";"Gateway";83;2
"Unit";"Sentry";"Gateway";83;2
"Unit";"Sentry";"Gateway";83;2
"Building";"Pylon";NA;71;0
"Building";"Pylon";NA;71;0
"Building";"Pylon";NA;71;0
"Unit";"Immortal";"Robotics Facility";63;4
"Unit";"Stalker";"Gateway";96;2
"Unit";"Stalker";"Gateway";96;2
"Unit";"Stalker";"Gateway";96;2
"Upgrade";"ProtossGroundArmorsLevel1";"Forge";63;0
"Upgrade";"ProtossGroundWeaponsLevel1";"Forge";63;0
"Building";"Pylon";NA;104;0
"Building";"Pylon";NA;104;0
"Unit";"Zealot";"Gateway";107;2
"Unit";"Zealot";"Gateway";107;2
"Unit";"Zealot";"Gateway";107;2
"Unit";"Zealot";"Gateway";107;2
"Unit";"Zealot";"Gateway";117;2
"Unit";"Zealot";"Gateway";117;2
"Unit";"Zealot";"Gateway";117;2
"Unit";"Zealot";"Gateway";117;2
"Unit";"Zealot";"Gateway";117;2
"Unit";"Zealot";"Gateway";117;2
"Unit";"Zealot";"Gateway";117;2
"Unit";"Zealot";"Gateway";117;2
"Unit";"Stalker";"Gateway";140;2
"Unit";"Stalker";"Gateway";140;2
"Unit";"Stalker";"Gateway";140;2
"Unit";"Stalker";"Gateway";140;2
"Unit";"Stalker";"Gateway";140;2
"Unit";"Stalker";"Gateway";140;2
"Unit";"Stalker";"Gateway";140;2
"Unit";"Stalker";"Gateway";140;2
"Unit";"Immortal";"Robotics Facility";137;4
"Building";"Pylon";NA;156;0
"Building";"Pylon";NA;156;0
"Building";"Pylon";NA;156;0
"Upgrade";"ProtossGroundWeaponsLevel2";"Forge";117;0
"Upgrade";"ProtossGroundArmorsLevel2";"Forge";117;0
"Building";"Pylon";NA;156;0
"Building";"Assimilator";NA;161;0
"Building";"Assimilator";NA;161;0
"Building";"Assimilator";NA;161;0
"Building";"RoboticsBay";NA;161;0
"Building";"RoboticsFacility";NA;161;0
"Unit";"Zealot";"Gateway";163;2
"Unit";"Zealot";"Gateway";163;2
"Unit";"Zealot";"Gateway";163;2
"Unit";"Zealot";"Gateway";163;2
"Unit";"Zealot";"Gateway";163;2
"Unit";"Zealot";"Gateway";163;2
"Unit";"Zealot";"Gateway";163;2
"Unit";"Zealot";"Gateway";163;2
"Unit";"Zealot";"Gateway";179;2
"Unit";"Zealot";"Gateway";179;2
"Unit";"Zealot";"Gateway";179;2
"Building";"Pylon";NA;179;0
"Building";"Pylon";NA;179;0
"Unit";"Colossus";"Robotics Facility";179;6
"Building";"Assimilator";NA;179;0
"Building";"Pylon";NA;179;0
"Building";"Pylon";NA;179;0
"Building";"Pylon";NA;185;0
"Unit";"Colossus";"Robotics Facility";179;6
"Unit";"Zealot";"Gateway";197;2
"Unit";"Zealot";"Gateway";197;2
"Unit";"Zealot";"Gateway";197;2
"Unit";"Zealot";"Gateway";197;2
"Unit";"Zealot";"Gateway";197;2
"Unit";"Zealot";"Gateway";197;2
"Upgrade";"ExtendedThermalLance";"RoboticsBay";179;0
"Unit";"Colossus";"Robotics Facility";185;6
"Unit";"Colossus";"Robotics Facility";185;6
"Unit";"Colossus";"Robotics Facility";209;6
"Building";"TemplarArchive";NA;221;0
"Unit";"Observer";"Robotics Facility";221;1
"Building";"Nexus";NA;209;0
"Unit";"Stalker";"Gateway";228;2
"Unit";"Stalker";"Gateway";228;2
"Unit";"Stalker";"Gateway";228;2
"Unit";"Stalker";"Gateway";228;2
"Unit";"Stalker";"Gateway";228;2
"Unit";"Stalker";"Gateway";228;2
"Unit";"Stalker";"Gateway";228;2
"Unit";"Stalker";"Gateway";228;2
"Building";"Nexus";NA;221;0
"Upgrade";"GraviticDrive";"RoboticsBay";227;0
"Unit";"Zealot";"Gateway";244;2
"Unit";"Stalker";"Gateway";244;2
"Unit";"Stalker";"Gateway";244;2
"Unit";"Stalker";"Gateway";244;2
"Unit";"Stalker";"Gateway";244;2
"Unit";"Stalker";"Gateway";244;2
"Unit";"Stalker";"Gateway";244;2
"Unit";"Stalker";"Gateway";244;2
