"type";"unit_name";"on_building";"total_supply";"supply"
"Building";"Pylon";NA;12;0
"Building";"Assimilator";NA;15;0
"Building";"Gateway";NA;14;0
"Building";"Assimilator";NA;18;0
"Building";"CyberneticsCore";NA;18;0
"Building";"Pylon";NA;20;0
"Unit";"Adept";"Gateway";20;2
"Building";"Nexus";NA;17;0
"Unit";"Stalker";"Gateway";22;2
"Building";"Stargate";NA;27;0
"Building";"Pylon";NA;38;0
"Unit";"Oracle";"Stargate";35;3
"Building";"Gateway";NA;37;0
"Building";"Gateway";NA;37;0
"Building";"Pylon";NA;46;0
"Unit";"Stalker";"Gateway";48;2
"Unit";"Oracle";"Stargate";41;3
"Building";"Assimilator";NA;46;0
"Unit";"Stalker";"Gateway";49;2
"Unit";"Stalker";"Gateway";51;2
"Building";"Assimilator";NA;46;0
"Building";"TwilightCouncil";NA;41;0
"Building";"Pylon";NA;49;0
"Unit";"Stalker";"Gateway";61;2
"Unit";"Stalker";"Gateway";61;2
"Unit";"Stalker";"Gateway";61;2
"Unit";"Oracle";"Stargate";61;3
"Building";"Pylon";NA;69;0
"Building";"Pylon";NA;70;0
"Building";"Pylon";NA;73;0
"Unit";"Stalker";"Gateway";75;2
"Unit";"Stalker";"Gateway";79;2
"Unit";"Stalker";"Gateway";79;2
"Building";"Forge";NA;75;0
"Building";"Forge";NA;75;0
"Building";"Nexus";NA;70;0
"Unit";"Stalker";"Gateway";88;2
"Unit";"Stalker";"Gateway";88;2
"Unit";"Stalker";"Gateway";89;2
"Building";"Gateway";NA;85;0
"Building";"OracleStasisTrap";NA;97;0
"Building";"Gateway";NA;85;0
"Unit";"Stalker";"Gateway";102;2
"Unit";"Stalker";"Gateway";102;2
"Unit";"Stalker";"Gateway";102;2
"Building";"Pylon";NA;100;0
"Building";"Assimilator";NA;99;0
"Building";"Assimilator";NA;100;0
"Building";"TemplarArchive";NA;99;0
"Building";"Gateway";NA;97;0
"Building";"Gateway";NA;97;0
"Unit";"Stalker";"Gateway";111;2
"Building";"Gateway";NA;97;0
"Unit";"Stalker";"Gateway";111;2
"Building";"Gateway";NA;98;0
"Upgrade";"ProtossGroundArmorsLevel1";"Forge";95;0
"Upgrade";"ProtossGroundWeaponsLevel1";"Forge";95;0
"Unit";"Zealot";"Gateway";118;2
"Unit";"Zealot";"Gateway";118;2
"Unit";"Zealot";"Gateway";118;2
"Unit";"Zealot";"Gateway";118;2
"Building";"Pylon";NA;115;0
"Building";"Pylon";NA;118;0
"Unit";"Sentry";"Gateway";126;2
"Unit";"Sentry";"Gateway";126;2
"Unit";"Stalker";"Gateway";126;2
"Building";"ShieldBattery";NA;115;0
"Building";"ShieldBattery";NA;115;0
"Building";"Pylon";NA;118;0
"Building";"OracleStasisTrap";NA;132;0
"Building";"Pylon";NA;120;0
"Unit";"Stalker";"Gateway";132;2
"Unit";"Stalker";"Gateway";132;2
"Building";"Pylon";NA;126;0
"Unit";"Stalker";"Gateway";136;2
"Unit";"Stalker";"Gateway";136;2
"Unit";"Zealot";"Gateway";140;2
"Unit";"Zealot";"Gateway";140;2
"Unit";"Zealot";"Gateway";140;2
"Unit";"Zealot";"Gateway";140;2
"Upgrade";"Charge";"TwilightCouncil";111;0
"Unit";"Zealot";"Gateway";148;2
"Unit";"Zealot";"Gateway";148;2
"Unit";"Zealot";"Gateway";152;2
"Building";"OracleStasisTrap";NA;154;0
"Unit";"Zealot";"Gateway";154;2
"Unit";"Zealot";"Gateway";154;2
"Unit";"Zealot";"Gateway";154;2
"Unit";"Stalker";"Gateway";160;2
"Building";"HighTemplar";NA;165;0
"Building";"HighTemplar";NA;165;0
"Unit";"Zealot";"Gateway";166;2
"Unit";"Zealot";"Gateway";166;2
"Unit";"Zealot";"Gateway";166;2
"Building";"Pylon";NA;165;0
"Building";"HighTemplar";NA;172;0
"Building";"HighTemplar";NA;172;0
"Building";"Pylon";NA;166;0
"Building";"Pylon";NA;168;0
"Building";"Pylon";NA;172;0
"Building";"HighTemplar";NA;172;0
"Building";"HighTemplar";NA;172;0
"Unit";"Zealot";"Gateway";172;2
"Unit";"Zealot";"Gateway";172;2
"Unit";"Stalker";"Gateway";176;2
"Unit";"Stalker";"Gateway";176;2
"Upgrade";"ProtossGroundArmorsLevel2";"Forge";132;0
"Upgrade";"ProtossGroundWeaponsLevel2";"Forge";132;0
"Unit";"Stalker";"Gateway";178;2
"Building";"Pylon";NA;176;0
"Unit";"Stalker";"Gateway";182;2
"Unit";"Stalker";"Gateway";182;2
"Unit";"Stalker";"Gateway";182;2
"Unit";"Zealot";"Gateway";188;2
"Unit";"Zealot";"Gateway";190;2
"Unit";"Zealot";"Gateway";190;2
"Unit";"Zealot";"Gateway";190;2
"Unit";"Zealot";"Gateway";190;2
"Unit";"Zealot";"Gateway";190;2
"Building";"Pylon";NA;200;0
"Building";"Pylon";NA;200;0
"Unit";"Stalker";"Gateway";200;2
"Unit";"Stalker";"Gateway";200;2
"Unit";"Stalker";"Gateway";200;2
"Unit";"Stalker";"Gateway";200;2
"Unit";"Zealot";"Gateway";208;2
"Unit";"Zealot";"Gateway";208;2
"Unit";"Zealot";"Gateway";208;2
"Unit";"Zealot";"Gateway";208;2
"Unit";"Zealot";"Gateway";208;2
"Unit";"Zealot";"Gateway";218;2
"Building";"HighTemplar";NA;218;0
"Building";"HighTemplar";NA;218;0
"Building";"HighTemplar";NA;218;0
"Unit";"Zealot";"Gateway";220;2
"Unit";"Zealot";"Gateway";220;2
"Unit";"Zealot";"Gateway";220;2
"Unit";"Zealot";"Gateway";226;2
"Unit";"Zealot";"Gateway";226;2
"Unit";"Archon";"High Templar";230;0
"Unit";"Zealot";"Gateway";230;2
"Unit";"Zealot";"Gateway";230;2
"Unit";"Archon";"High Templar";230;0
"Unit";"Zealot";"Gateway";230;2
"Unit";"Zealot";"Gateway";230;2
"Building";"Pylon";NA;230;0
"Building";"Pylon";NA;230;0
"Building";"Pylon";NA;230;0
"Building";"Pylon";NA;230;0
"Building";"HighTemplar";NA;238;0
"Building";"HighTemplar";NA;238;0
"Upgrade";"ProtossGroundArmorsLevel3";"Forge";202;0
"Building";"HighTemplar";NA;238;0
"Building";"HighTemplar";NA;238;0
"Upgrade";"ProtossGroundWeaponsLevel3";"Forge";208;0
"Unit";"Archon";"High Templar";238;0
"Building";"HighTemplar";NA;238;0
"Building";"HighTemplar";NA;238;0
"Unit";"Zealot";"Gateway";238;2
"Building";"HighTemplar";NA;240;0
"Building";"HighTemplar";NA;240;0
"Building";"Nexus";NA;238;0
"Building";"HighTemplar";NA;244;0
"Building";"HighTemplar";NA;244;0
"Unit";"Archon";"High Templar";245;0
"Unit";"Zealot";"Gateway";245;2
"Unit";"Zealot";"Gateway";245;2
"Unit";"Archon";"High Templar";245;0
"Unit";"Zealot";"Gateway";245;2
"Unit";"Zealot";"Gateway";245;2
"Unit";"Zealot";"Gateway";253;2
"Unit";"Zealot";"Gateway";253;2
"Building";"Pylon";NA;253;0
"Unit";"Zealot";"Gateway";260;2
"Building";"HighTemplar";NA;260;0
"Unit";"Archon";"High Templar";260;0
"Unit";"Archon";"High Templar";260;0
"Building";"HighTemplar";NA;262;0
"Building";"HighTemplar";NA;262;0
"Building";"HighTemplar";NA;262;0
"Building";"HighTemplar";NA;262;0
"Building";"HighTemplar";NA;263;0
"Unit";"Zealot";"Gateway";263;2
"Building";"HighTemplar";NA;265;0
"Unit";"Archon";"High Templar";265;0
"Building";"HighTemplar";NA;265;0
"Unit";"Zealot";"Gateway";265;2
"Unit";"Zealot";"Gateway";265;2
"Building";"HighTemplar";NA;265;0
"Unit";"Zealot";"Gateway";269;2
"Unit";"Zealot";"Gateway";271;2
"Unit";"Zealot";"Gateway";271;2
"Building";"HighTemplar";NA;271;0
"Unit";"Archon";"High Templar";271;0
"Building";"Nexus";NA;265;0
"Building";"HighTemplar";NA;279;0
"Unit";"Zealot";"Gateway";279;2
