"type";"unit_name";"on_building";"total_supply";"supply"
"Building";"Pylon";NA;13;0
"Building";"Assimilator";NA;16;0
"Building";"Gateway";NA;15;0
"Building";"Pylon";NA;20;0
"Building";"CyberneticsCore";NA;20;0
"Building";"Assimilator";NA;20;0
"Unit";"Adept";"Gateway";21;2
"Building";"Nexus";NA;20;0
"Building";"RoboticsFacility";NA;23;0
"Unit";"Stalker";"Gateway";27;2
"Building";"ShieldBattery";NA;29;0
"Unit";"Observer";"Robotics Facility";31;1
"Unit";"Observer";"Robotics Facility";36;1
"Building";"Pylon";NA;38;0
"Unit";"Observer";"Robotics Facility";40;1
"Unit";"Stalker";"Gateway";45;2
"Building";"RoboticsBay";NA;38;0
"Unit";"Stalker";"Gateway";49;2
"Building";"Assimilator";NA;47;0
"Building";"Nexus";NA;38;0
"Building";"Gateway";NA;41;0
"Building";"Gateway";NA;41;0
"Building";"ShieldBattery";NA;49;0
"Unit";"Stalker";"Gateway";61;2
"Building";"Pylon";NA;58;0
"Unit";"Colossus";"Robotics Facility";52;6
"Building";"Pylon";NA;71;0
"Building";"Assimilator";NA;64;0
"Building";"Gateway";NA;58;0
"Building";"Gateway";NA;58;0
"Unit";"Adept";"Gateway";75;2
"Unit";"Adept";"Gateway";76;2
"Building";"TwilightCouncil";NA;72;0
"Building";"Pylon";NA;75;0
"Unit";"Colossus";"Robotics Facility";72;6
"Building";"Gateway";NA;75;0
"Building";"Forge";NA;81;0
"Building";"Forge";NA;81;0
"Building";"Pylon";NA;91;0
"Building";"ShieldBattery";NA;91;0
"Building";"Pylon";NA;93;0
"Building";"Assimilator";NA;93;0
"Unit";"Zealot";"Gateway";98;2
"Unit";"Zealot";"Gateway";98;2
"Unit";"Zealot";"Gateway";98;2
"Unit";"Disruptor";"Robotics Facility";91;3
"Building";"PhotonCannon";NA;96;0
"Building";"Pylon";NA;104;0
"Upgrade";"Charge";"TwilightCouncil";82;0
"Unit";"Zealot";"Gateway";110;2
"Unit";"Zealot";"Gateway";110;2
"Unit";"Zealot";"Gateway";111;2
"Unit";"Zealot";"Gateway";111;2
"Unit";"Zealot";"Gateway";111;2
"Unit";"Zealot";"Gateway";115;2
"Building";"Pylon";NA;110;0
"Unit";"Disruptor";"Robotics Facility";107;3
"Upgrade";"ExtendedThermalLance";"RoboticsBay";91;0
"Building";"ShieldBattery";NA;123;0
"Building";"Pylon";NA;128;0
"Building";"Assimilator";NA;126;0
"Upgrade";"ProtossGroundArmorsLevel1";"Forge";97;0
"Unit";"Disruptor";"Robotics Facility";126;3
"Building";"PhotonCannon";NA;128;0
"Building";"ShieldBattery";NA;128;0
"Upgrade";"ProtossGroundWeaponsLevel1";"Forge";107;0
"Unit";"Stalker";"Gateway";134;2
"Unit";"Stalker";"Gateway";134;2
"Building";"PhotonCannon";NA;133;0
"Building";"Pylon";NA;134;0
"Building";"PhotonCannon";NA;134;0
"Building";"PhotonCannon";NA;134;0
"Building";"Pylon";NA;138;0
"Building";"RoboticsFacility";NA;133;0
"Unit";"Zealot";"Gateway";141;2
"Unit";"Zealot";"Gateway";141;2
"Unit";"Zealot";"Gateway";141;2
"Unit";"Zealot";"Gateway";141;2
"Unit";"Zealot";"Gateway";141;2
"Unit";"Zealot";"Gateway";141;2
"Building";"TemplarArchive";NA;138;0
"Building";"Nexus";NA;130;0
"Unit";"Disruptor";"Robotics Facility";138;3
"Building";"HighTemplar";NA;157;0
"Building";"HighTemplar";NA;157;0
"Building";"HighTemplar";NA;157;0
"Building";"HighTemplar";NA;157;0
"Building";"HighTemplar";NA;157;0
"Building";"HighTemplar";NA;157;0
"Building";"ShieldBattery";NA;153;0
"Building";"ShieldBattery";NA;156;0
"Building";"PhotonCannon";NA;156;0
"Building";"Pylon";NA;157;0
"Unit";"Archon";"High Templar";157;0
"Unit";"Archon";"High Templar";157;0
"Unit";"Archon";"High Templar";157;0
"Building";"Assimilator";NA;157;0
"Building";"Pylon";NA;157;0
"Building";"Assimilator";NA;157;0
"Building";"Gateway";NA;156;0
"Building";"Gateway";NA;156;0
"Unit";"Disruptor";"Robotics Facility";157;3
"Unit";"Disruptor";"Robotics Facility";157;3
"Unit";"Stalker";"Gateway";166;2
"Unit";"Stalker";"Gateway";166;2
"Unit";"Stalker";"Gateway";166;2
"Unit";"Stalker";"Gateway";166;2
"Unit";"Stalker";"Gateway";166;2
"Unit";"Stalker";"Gateway";166;2
"Building";"Pylon";NA;160;0
"Upgrade";"ProtossGroundWeaponsLevel2";"Forge";141;0
"Upgrade";"ProtossGroundArmorsLevel2";"Forge";141;0
"Building";"Pylon";NA;166;0
"Building";"Pylon";NA;166;0
"Unit";"Stalker";"Gateway";178;2
"Unit";"Stalker";"Gateway";178;2
"Unit";"Stalker";"Gateway";178;2
"Unit";"Stalker";"Gateway";178;2
"Unit";"Stalker";"Gateway";178;2
"Unit";"Zealot";"Gateway";188;2
"Unit";"Zealot";"Gateway";188;2
"Unit";"Zealot";"Gateway";188;2
"Unit";"Disruptor";"Robotics Facility";166;3
"Building";"Gateway";NA;166;0
"Building";"Gateway";NA;166;0
"Building";"HighTemplar";NA;197;0
"Building";"HighTemplar";NA;197;0
"Building";"HighTemplar";NA;197;0
"Building";"HighTemplar";NA;197;0
"Building";"HighTemplar";NA;197;0
"Building";"Pylon";NA;197;0
"Building";"PhotonCannon";NA;197;0
"Building";"Pylon";NA;197;0
"Building";"ShieldBattery";NA;197;0
"Building";"PhotonCannon";NA;197;0
"Building";"ShieldBattery";NA;197;0
"Unit";"Stalker";"Gateway";197;2
"Unit";"Stalker";"Gateway";197;2
"Unit";"Stalker";"Gateway";197;2
"Unit";"Stalker";"Gateway";197;2
"Unit";"Zealot";"Gateway";197;2
"Unit";"Zealot";"Gateway";197;2
"Unit";"Zealot";"Gateway";199;2
"Unit";"Zealot";"Gateway";199;2
"Unit";"Zealot";"Gateway";203;2
"Unit";"Zealot";"Gateway";215;2
"Unit";"Zealot";"Gateway";215;2
"Unit";"Zealot";"Gateway";215;2
"Unit";"Zealot";"Gateway";215;2
"Unit";"Zealot";"Gateway";215;2
"Unit";"Zealot";"Gateway";215;2
"Unit";"Zealot";"Gateway";215;2
"Unit";"Zealot";"Gateway";215;2
"Upgrade";"GraviticDrive";"RoboticsBay";197;0
"Unit";"Stalker";"Gateway";231;2
"Unit";"Stalker";"Gateway";231;2
"Unit";"Stalker";"Gateway";231;2
"Unit";"Stalker";"Gateway";231;2
"Unit";"Stalker";"Gateway";231;2
"Unit";"Stalker";"Gateway";231;2
"Unit";"Stalker";"Gateway";231;2
"Unit";"Stalker";"Gateway";231;2
"Upgrade";"ProtossGroundArmorsLevel3";"Forge";197;0
"Upgrade";"ProtossGroundWeaponsLevel3";"Forge";197;0
"Building";"Pylon";NA;247;0
"Building";"HighTemplar";NA;247;0
"Building";"HighTemplar";NA;247;0
"Building";"HighTemplar";NA;248;0
"Building";"HighTemplar";NA;248;0
"Building";"HighTemplar";NA;248;0
"Building";"HighTemplar";NA;248;0
"Building";"HighTemplar";NA;248;0
"Building";"Pylon";NA;248;0
"Building";"Pylon";NA;248;0
"Unit";"Archon";"High Templar";248;0
"Unit";"Archon";"High Templar";248;0
"Building";"Gateway";NA;247;0
"Building";"Gateway";NA;247;0
"Unit";"Stalker";"Gateway";248;2
"Unit";"Stalker";"Gateway";248;2
"Unit";"Stalker";"Gateway";248;2
"Unit";"Zealot";"Gateway";254;2
"Building";"Nexus";NA;247;0
"Unit";"Stalker";"Gateway";256;2
"Unit";"Stalker";"Gateway";256;2
"Unit";"Stalker";"Gateway";256;2
"Unit";"Stalker";"Gateway";256;2
"Building";"PhotonCannon";NA;256;0
"Building";"PhotonCannon";NA;256;0
"Building";"PhotonCannon";NA;256;0
"Building";"ShieldBattery";NA;256;0
"Upgrade";"ProtossShieldsLevel1";"Forge";248;0
"Unit";"Disruptor";"Robotics Facility";256;3
"Unit";"Disruptor";"Robotics Facility";256;3
"Unit";"Zealot";"Gateway";270;2
"Unit";"Zealot";"Gateway";270;2
"Unit";"Zealot";"Gateway";270;2
"Unit";"Zealot";"Gateway";270;2
"Unit";"Zealot";"Gateway";270;2
"Unit";"Zealot";"Gateway";270;2
"Unit";"Zealot";"Gateway";270;2
"Unit";"Zealot";"Gateway";270;2
"Unit";"Zealot";"Gateway";270;2
"Unit";"Zealot";"Gateway";270;2
"Building";"HighTemplar";NA;290;0
"Building";"Pylon";NA;290;0
"Building";"PhotonCannon";NA;290;0
"Building";"PhotonCannon";NA;290;0
"Building";"PhotonCannon";NA;290;0
"Building";"ShieldBattery";NA;290;0
"Building";"PhotonCannon";NA;290;0
"Building";"PhotonCannon";NA;290;0
"Building";"PhotonCannon";NA;290;0
"Building";"Nexus";NA;290;0
"Unit";"Zealot";"Gateway";290;2
"Unit";"Zealot";"Gateway";290;2
"Unit";"Zealot";"Gateway";290;2
"Building";"DarkShrine";NA;290;0
"Unit";"Zealot";"Gateway";290;2
"Unit";"Zealot";"Gateway";290;2
"Unit";"Zealot";"Gateway";290;2
"Unit";"Zealot";"Gateway";290;2
"Unit";"Zealot";"Gateway";290;2
"Unit";"Zealot";"Gateway";290;2
"Unit";"Zealot";"Gateway";290;2
"Unit";"Disruptor";"Robotics Facility";290;3
"Unit";"Disruptor";"Robotics Facility";290;3
