"type";"unit_name";"on_building";"total_supply";"supply"
"Building";"Pylon";NA;13;0
"Building";"Assimilator";NA;16;0
"Building";"Gateway";NA;15;0
"Building";"Assimilator";NA;20;0
"Building";"Pylon";NA;21;0
"Building";"CyberneticsCore";NA;20;0
"Unit";"Stalker";"Gateway";21;2
"Building";"Nexus";NA;19;0
"Unit";"Stalker";"Gateway";26;2
"Building";"RoboticsFacility";NA;26;0
"Unit";"Observer";"Robotics Facility";34;1
"Unit";"Stalker";"Gateway";32;2
"Building";"ShieldBattery";NA;34;0
"Building";"Pylon";NA;37;0
"Unit";"Observer";"Robotics Facility";36;1
"Building";"Assimilator";NA;42;0
"Building";"Gateway";NA;41;0
"Building";"Gateway";NA;41;0
"Building";"Assimilator";NA;45;0
"Building";"Pylon";NA;49;0
"Building";"RoboticsBay";NA;45;0
"Building";"TwilightCouncil";NA;49;0
"Building";"Pylon";NA;52;0
"Unit";"Immortal";"Robotics Facility";50;4
"Building";"Pylon";NA;60;0
"Building";"Pylon";NA;60;0
"Building";"Gateway";NA;55;0
"Building";"Gateway";NA;56;0
"Building";"Gateway";NA;60;0
"Unit";"Zealot";"Gateway";62;2
"Unit";"Zealot";"Gateway";62;2
"Unit";"Colossus";"Robotics Facility";60;6
"Upgrade";"Charge";"TwilightCouncil";60;0
"Unit";"Zealot";"Gateway";73;2
"Unit";"Zealot";"Gateway";73;2
"Unit";"Zealot";"Gateway";73;2
"Unit";"Zealot";"Gateway";73;2
"Unit";"Zealot";"Gateway";73;2
"Unit";"Zealot";"Gateway";73;2
"Building";"Pylon";NA;73;0
"Building";"Pylon";NA;85;0
"Unit";"Sentry";"Gateway";85;2
"Unit";"Sentry";"Gateway";85;2
"Unit";"Sentry";"Gateway";85;2
"Unit";"Sentry";"Gateway";87;2
"Unit";"Sentry";"Gateway";89;2
"Building";"Pylon";NA;85;0
"Unit";"Zealot";"Gateway";95;2
"Upgrade";"ExtendedThermalLance";"RoboticsBay";62;0
"Building";"Nexus";NA;62;0
"Unit";"Stalker";"Gateway";97;2
"Unit";"Stalker";"Gateway";97;2
"Unit";"Stalker";"Gateway";97;2
"Unit";"Colossus";"Robotics Facility";73;6
"Unit";"Zealot";"Gateway";97;2
"Unit";"Zealot";"Gateway";97;2
"Building";"ShieldBattery";NA;95;0
"Building";"ShieldBattery";NA;97;0
"Unit";"Zealot";"Gateway";115;2
"Unit";"Stalker";"Gateway";117;2
"Unit";"Stalker";"Gateway";117;2
"Building";"Assimilator";NA;117;0
"Building";"Assimilator";NA;124;0
"Unit";"Zealot";"Gateway";127;2
"Unit";"Zealot";"Gateway";127;2
"Unit";"Zealot";"Gateway";127;2
"Unit";"Zealot";"Gateway";127;2
"Unit";"Zealot";"Gateway";127;2
"Building";"Forge";NA;126;0
"Building";"Forge";NA;126;0
"Unit";"Zealot";"Gateway";142;2
"Building";"RoboticsFacility";NA;127;0
"Building";"RoboticsFacility";NA;127;0
"Building";"PhotonCannon";NA;140;0
"Building";"Pylon";NA;142;0
"Unit";"Zealot";"Gateway";144;2
"Building";"PhotonCannon";NA;140;0
"Building";"PhotonCannon";NA;142;0
"Building";"CyberneticsCore";NA;140;0
"Unit";"Zealot";"Gateway";146;2
"Unit";"Zealot";"Gateway";146;2
"Unit";"Zealot";"Gateway";146;2
"Unit";"Zealot";"Gateway";146;2
"Building";"PhotonCannon";NA;142;0
"Unit";"Observer";"Robotics Facility";146;1
"Building";"Pylon";NA;146;0
"Unit";"Zealot";"Gateway";154;2
"Unit";"Zealot";"Gateway";157;2
"Unit";"Zealot";"Gateway";157;2
"Unit";"Zealot";"Gateway";157;2
"Building";"RoboticsBay";NA;146;0
"Building";"Pylon";NA;164;0
"Building";"PhotonCannon";NA;164;0
"Building";"Gateway";NA;157;0
"Unit";"Stalker";"Gateway";166;2
"Unit";"Stalker";"Gateway";166;2
"Unit";"Stalker";"Gateway";166;2
"Unit";"Stalker";"Gateway";166;2
"Building";"PhotonCannon";NA;164;0
"Upgrade";"ProtossGroundWeaponsLevel1";"Forge";144;0
"Building";"Gateway";NA;157;0
"Upgrade";"ProtossGroundArmorsLevel1";"Forge";144;0
"Building";"Gateway";NA;157;0
"Building";"PhotonCannon";NA;166;0
"Unit";"Disruptor";"Robotics Facility";164;3
"Unit";"Disruptor";"Robotics Facility";164;3
"Building";"ShieldBattery";NA;166;0
"Building";"ShieldBattery";NA;166;0
"Unit";"Zealot";"Gateway";180;2
"Building";"Gateway";NA;164;0
"Building";"TemplarArchive";NA;166;0
"Unit";"Stalker";"Gateway";182;2
"Unit";"Stalker";"Gateway";184;2
"Unit";"Stalker";"Gateway";185;2
"Unit";"Stalker";"Gateway";185;2
"Unit";"Disruptor";"Robotics Facility";182;3
"Unit";"Disruptor";"Robotics Facility";182;3
"Building";"ShieldBattery";NA;193;0
"Building";"Pylon";NA;201;0
"Unit";"Stalker";"Gateway";201;2
"Unit";"Stalker";"Gateway";201;2
"Unit";"Stalker";"Gateway";205;2
"Unit";"Stalker";"Gateway";205;2
"Unit";"Stalker";"Gateway";205;2
"Unit";"Stalker";"Gateway";205;2
"Unit";"Stalker";"Gateway";205;2
"Building";"Pylon";NA;209;0
"Building";"Pylon";NA;215;0
"Building";"Pylon";NA;215;0
"Building";"Pylon";NA;215;0
"Unit";"Stalker";"Gateway";215;2
"Unit";"Stalker";"Gateway";215;2
"Unit";"Stalker";"Gateway";215;2
"Unit";"Stalker";"Gateway";215;2
"Unit";"Stalker";"Gateway";215;2
"Unit";"Stalker";"Gateway";215;2
"Unit";"Stalker";"Gateway";215;2
"Unit";"Stalker";"Gateway";215;2
"Unit";"Stalker";"Gateway";215;2
"Building";"Pylon";NA;215;0
"Building";"HighTemplar";NA;233;0
"Building";"HighTemplar";NA;233;0
"Building";"HighTemplar";NA;233;0
"Building";"HighTemplar";NA;233;0
"Unit";"Stalker";"Gateway";233;2
"Unit";"Stalker";"Gateway";233;2
"Unit";"Stalker";"Gateway";233;2
"Unit";"Stalker";"Gateway";233;2
"Unit";"Stalker";"Gateway";233;2
"Upgrade";"ProtossGroundWeaponsLevel2";"Forge";201;0
"Upgrade";"ProtossGroundArmorsLevel2";"Forge";201;0
"Building";"Pylon";NA;233;0
"Building";"Pylon";NA;233;0
"Unit";"Archon";"High Templar";243;0
"Unit";"Archon";"High Templar";243;0
"Unit";"Disruptor";"Robotics Facility";233;3
"Unit";"Stalker";"Gateway";246;2
"Unit";"Stalker";"Gateway";246;2
"Unit";"Stalker";"Gateway";246;2
"Unit";"Stalker";"Gateway";246;2
"Unit";"Stalker";"Gateway";246;2
"Unit";"Stalker";"Gateway";256;2
"Unit";"Stalker";"Gateway";256;2
"Unit";"Stalker";"Gateway";256;2
"Unit";"Disruptor";"Robotics Facility";243;3
"Unit";"Stalker";"Gateway";262;2
"Unit";"Zealot";"Gateway";270;2
"Unit";"Zealot";"Gateway";270;2
"Unit";"Zealot";"Gateway";270;2
"Unit";"Zealot";"Gateway";270;2
"Unit";"Zealot";"Gateway";270;2
"Unit";"Zealot";"Gateway";270;2
"Unit";"Zealot";"Gateway";270;2
"Building";"HighTemplar";NA;284;0
"Building";"HighTemplar";NA;284;0
"Building";"HighTemplar";NA;284;0
"Building";"HighTemplar";NA;284;0
"Unit";"Zealot";"Gateway";284;2
"Building";"Pylon";NA;284;0
"Building";"Pylon";NA;284;0
"Unit";"Archon";"High Templar";284;0
"Unit";"Archon";"High Templar";286;0
"Building";"Assimilator";NA;286;0
"Building";"Assimilator";NA;286;0
"Unit";"Stalker";"Gateway";288;2
"Unit";"Stalker";"Gateway";288;2
"Unit";"Stalker";"Gateway";288;2
"Unit";"Stalker";"Gateway";288;2
"Unit";"Stalker";"Gateway";288;2
"Unit";"Stalker";"Gateway";288;2
"Unit";"Stalker";"Gateway";300;2
"Unit";"Stalker";"Gateway";300;2
"Unit";"Stalker";"Gateway";300;2
"Building";"Nexus";NA;284;0
"Unit";"Stalker";"Gateway";306;2
"Unit";"Stalker";"Gateway";306;2
"Unit";"Stalker";"Gateway";306;2
"Unit";"Stalker";"Gateway";306;2
"Unit";"Zealot";"Gateway";314;2
"Unit";"Zealot";"Gateway";314;2
"Unit";"Stalker";"Gateway";318;2
"Unit";"Stalker";"Gateway";318;2
"Unit";"Stalker";"Gateway";318;2
"Unit";"Stalker";"Gateway";318;2
