"type";"unit_name";"on_building";"total_supply";"supply"
"Building";"Pylon";NA;13;0
"Building";"Assimilator";NA;15;0
"Building";"Gateway";NA;15;0
"Building";"Assimilator";NA;21;0
"Building";"Pylon";NA;21;0
"Building";"CyberneticsCore";NA;21;0
"Unit";"Stalker";"Gateway";21;2
"Building";"Nexus";NA;20;0
"Building";"Pylon";NA;26;0
"Unit";"Stalker";"Gateway";23;2
"Building";"ShieldBattery";NA;27;0
"Unit";"Stalker";"Gateway";27;2
"Building";"ShieldBattery";NA;31;0
"Building";"Pylon";NA;32;0
"Building";"ShieldBattery";NA;31;0
"Unit";"Stalker";"Gateway";34;2
"Unit";"Stalker";"Gateway";34;2
"Building";"Assimilator";NA;40;0
"Unit";"Stalker";"Gateway";45;2
"Building";"RoboticsFacility";NA;38;0
"Building";"Pylon";NA;46;0
"Unit";"Zealot";"Gateway";51;2
"Unit";"Adept";"Gateway";55;2
"Unit";"Immortal";"Robotics Facility";51;4
"Building";"Pylon";NA;55;0
"Building";"TwilightCouncil";NA;53;0
"Unit";"Sentry";"Gateway";63;2
"Building";"Pylon";NA;59;0
"Building";"Gateway";NA;53;0
"Building";"Gateway";NA;53;0
"Building";"Gateway";NA;55;0
"Building";"Pylon";NA;65;0
"Unit";"Sentry";"Gateway";65;2
"Unit";"Zealot";"Gateway";65;2
"Unit";"Immortal";"Robotics Facility";59;4
"Building";"Pylon";NA;65;0
"Unit";"Stalker";"Gateway";73;2
"Unit";"Stalker";"Gateway";73;2
"Building";"Pylon";NA;65;0
"Unit";"Sentry";"Gateway";77;2
"Unit";"Zealot";"Gateway";77;2
"Building";"Pylon";NA;77;0
"Unit";"Stalker";"Gateway";81;2
"Unit";"Sentry";"Gateway";81;2
"Unit";"Immortal";"Robotics Facility";65;4
"Unit";"Stalker";"Gateway";93;2
"Unit";"Stalker";"Gateway";93;2
"Unit";"Stalker";"Gateway";97;2
"Unit";"Stalker";"Gateway";97;2
"Building";"ShieldBattery";NA;91;0
"Unit";"Observer";"Robotics Facility";95;1
"Building";"ShieldBattery";NA;91;0
"Unit";"Sentry";"Gateway";101;2
"Unit";"Zealot";"Gateway";106;2
"Building";"Nexus";NA;77;0
"Unit";"Observer";"Robotics Facility";101;1
"Unit";"Zealot";"Gateway";113;2
"Unit";"Zealot";"Gateway";113;2
"Unit";"Zealot";"Gateway";113;2
"Building";"Assimilator";NA;106;0
"Unit";"Observer";"Robotics Facility";110;1
"Unit";"Zealot";"Gateway";124;2
"Unit";"Zealot";"Gateway";124;2
"Unit";"Zealot";"Gateway";124;2
"Building";"Pylon";NA;126;0
"Building";"Assimilator";NA;132;0
"Building";"Pylon";NA;132;0
"Building";"Assimilator";NA;132;0
"Unit";"Zealot";"Gateway";133;2
"Unit";"Zealot";"Gateway";133;2
"Unit";"Zealot";"Gateway";133;2
"Unit";"Immortal";"Robotics Facility";124;4
"Unit";"Zealot";"Gateway";139;2
"Building";"TemplarArchive";NA;132;0
"Upgrade";"Charge";"TwilightCouncil";120;0
"Building";"HighTemplar";NA;150;0
"Building";"Forge";NA;132;0
"Building";"Gateway";NA;132;0
"Building";"Gateway";NA;132;0
"Building";"Pylon";NA;150;0
"Building";"Pylon";NA;151;0
"Building";"HighTemplar";NA;151;0
"Building";"HighTemplar";NA;151;0
"Building";"HighTemplar";NA;151;0
"Building";"Pylon";NA;151;0
"Building";"HighTemplar";NA;151;0
"Building";"HighTemplar";NA;151;0
"Unit";"Zealot";"Gateway";151;2
"Unit";"Zealot";"Gateway";153;2
"Unit";"Zealot";"Gateway";153;2
"Unit";"Zealot";"Gateway";153;2
"Unit";"Immortal";"Robotics Facility";151;4
"Unit";"Zealot";"Gateway";159;2
"Building";"Gateway";NA;151;0
"Building";"Gateway";NA;151;0
"Building";"Gateway";NA;151;0
"Unit";"Zealot";"Gateway";165;2
"Building";"Gateway";NA;151;0
"Unit";"Zealot";"Gateway";165;2
"Unit";"Zealot";"Gateway";165;2
"Unit";"Zealot";"Gateway";165;2
"Unit";"Zealot";"Gateway";165;2
"Unit";"Zealot";"Gateway";175;2
"Unit";"Archon";"High Templar";175;0
"Unit";"Archon";"High Templar";175;0
"Building";"Gateway";NA;159;0
"Building";"HighTemplar";NA;177;0
"Building";"Gateway";NA;159;0
"Building";"HighTemplar";NA;177;0
"Unit";"Zealot";"Gateway";177;2
"Unit";"Zealot";"Gateway";177;2
"Unit";"Zealot";"Gateway";177;2
"Unit";"Zealot";"Gateway";177;2
"Unit";"Zealot";"Gateway";177;2
"Building";"HighTemplar";NA;187;0
"Building";"HighTemplar";NA;187;0
"Building";"HighTemplar";NA;187;0
"Building";"HighTemplar";NA;187;0
"Building";"Forge";NA;187;0
"Unit";"Immortal";"Robotics Facility";187;4
"Building";"Assimilator";NA;187;0
"Building";"Pylon";NA;187;0
"Building";"Assimilator";NA;187;0
"Building";"Pylon";NA;187;0
"Unit";"Observer";"Robotics Facility";187;1
"Building";"RoboticsBay";NA;187;0
"Building";"Pylon";NA;191;0
"Unit";"Stalker";"Gateway";192;2
"Unit";"Stalker";"Gateway";192;2
"Building";"RoboticsFacility";NA;187;0
"Unit";"Stalker";"Gateway";192;2
"Unit";"Stalker";"Gateway";192;2
"Unit";"Zealot";"Gateway";192;2
"Unit";"Zealot";"Gateway";192;2
"Unit";"Zealot";"Gateway";192;2
"Unit";"Zealot";"Gateway";192;2
"Building";"PhotonCannon";NA;191;0
"Building";"Pylon";NA;192;0
"Building";"ShieldBattery";NA;191;0
"Building";"PhotonCannon";NA;191;0
"Building";"PhotonCannon";NA;192;0
"Building";"ShieldBattery";NA;192;0
"Upgrade";"ProtossGroundArmorsLevel1";"Forge";187;0
"Unit";"Colossus";"Robotics Facility";191;6
"Building";"Nexus";NA;187;0
"Building";"HighTemplar";NA;211;0
"Building";"HighTemplar";NA;211;0
"Unit";"Stalker";"Gateway";217;2
"Unit";"Colossus";"Robotics Facility";192;6
"Unit";"Zealot";"Gateway";217;2
"Unit";"Zealot";"Gateway";217;2
"Unit";"Observer";"Robotics Facility";211;1
"Building";"ShieldBattery";NA;211;0
"Building";"ShieldBattery";NA;211;0
"Building";"ShieldBattery";NA;217;0
"Building";"ShieldBattery";NA;217;0
"Upgrade";"ProtossGroundWeaponsLevel1";"Forge";191;0
"Unit";"Colossus";"Robotics Facility";217;6
"Building";"Pylon";NA;238;0
"Building";"Pylon";NA;238;0
"Unit";"Colossus";"Robotics Facility";230;6
"Unit";"Zealot";"Gateway";252;2
"Unit";"Zealot";"Gateway";252;2
"Unit";"Zealot";"Gateway";252;2
"Unit";"Zealot";"Gateway";252;2
"Unit";"Zealot";"Gateway";252;2
"Upgrade";"ExtendedThermalLance";"RoboticsBay";230;0
"Unit";"Zealot";"Gateway";252;2
"Unit";"Zealot";"Gateway";252;2
"Unit";"Zealot";"Gateway";252;2
"Unit";"Zealot";"Gateway";252;2
"Unit";"Stalker";"Gateway";270;2
"Unit";"Stalker";"Gateway";270;2
"Unit";"Stalker";"Gateway";270;2
"Unit";"Zealot";"Gateway";276;2
"Unit";"Zealot";"Gateway";276;2
"Unit";"Zealot";"Gateway";276;2
"Unit";"Zealot";"Gateway";276;2
"Unit";"Zealot";"Gateway";276;2
"Unit";"Zealot";"Gateway";276;2
"Unit";"Zealot";"Gateway";276;2
"Unit";"Zealot";"Gateway";276;2
"Unit";"Zealot";"Gateway";276;2
