"type";"unit_name";"on_building";"total_supply";"supply"
"Building";"Pylon";NA;13;0
"Building";"Assimilator";NA;16;0
"Building";"Gateway";NA;15;0
"Building";"CyberneticsCore";NA;19;0
"Building";"Pylon";NA;20;0
"Building";"Assimilator";NA;20;0
"Unit";"Zealot";"Gateway";20;2
"Unit";"Stalker";"Gateway";20;2
"Building";"Pylon";NA;28;0
"Unit";"Stalker";"Gateway";27;2
"Unit";"Stalker";"Gateway";29;2
"Building";"ShieldBattery";NA;32;0
"Building";"Nexus";NA;27;0
"Unit";"Stalker";"Gateway";36;2
"Building";"Gateway";NA;34;0
"Building";"Gateway";NA;34;0
"Building";"TwilightCouncil";NA;34;0
"Unit";"Stalker";"Gateway";42;2
"Unit";"Stalker";"Gateway";47;2
"Unit";"Stalker";"Gateway";47;2
"Unit";"Stalker";"Gateway";52;2
"Building";"RoboticsFacility";NA;52;0
"Unit";"Stalker";"Gateway";60;2
"Building";"Assimilator";NA;58;0
"Building";"DarkShrine";NA;52;0
"Building";"Assimilator";NA;60;0
"Building";"TemplarArchive";NA;58;0
"Building";"Pylon";NA;62;0
"Building";"Pylon";NA;64;0
"Building";"Pylon";NA;67;0
"Unit";"Observer";"Robotics Facility";68;1
"Building";"DarkTemplar";NA;73;0
"Building";"DarkTemplar";NA;73;0
"Building";"DarkTemplar";NA;73;0
"Building";"Nexus";NA;67;0
"Building";"Gateway";NA;70;0
"Building";"Gateway";NA;70;0
"Building";"Gateway";NA;71;0
"Upgrade";"Charge";"TwilightCouncil";68;0
"Unit";"Zealot";"Gateway";73;2
"Unit";"Zealot";"Gateway";73;2
"Unit";"Zealot";"Gateway";73;2
"Building";"Gateway";NA;73;0
"Building";"Gateway";NA;73;0
"Building";"DarkTemplar";NA;79;0
"Building";"DarkTemplar";NA;79;0
"Building";"Pylon";NA;79;0
"Unit";"Immortal";"Robotics Facility";73;4
"Building";"HighTemplar";NA;85;0
"Building";"HighTemplar";NA;85;0
"Building";"Forge";NA;79;0
"Building";"HighTemplar";NA;85;0
"Building";"Forge";NA;79;0
"Building";"HighTemplar";NA;87;0
"Unit";"Archon";"High Templar";87;0
"Unit";"Immortal";"Robotics Facility";80;4
"Building";"Pylon";NA;90;0
"Unit";"Zealot";"Gateway";100;2
"Unit";"Zealot";"Gateway";100;2
"Unit";"Zealot";"Gateway";100;2
"Unit";"Zealot";"Gateway";100;2
"Unit";"Zealot";"Gateway";100;2
"Unit";"Zealot";"Gateway";100;2
"Unit";"Archon";"High Templar";112;0
"Unit";"Stalker";"Gateway";112;2
"Unit";"Stalker";"Gateway";112;2
"Unit";"Stalker";"Gateway";112;2
"Unit";"Stalker";"Gateway";112;2
"Unit";"Stalker";"Gateway";112;2
"Building";"HighTemplar";NA;125;0
"Building";"HighTemplar";NA;125;0
"Building";"Assimilator";NA;122;0
"Building";"Assimilator";NA;122;0
"Unit";"Sentry";"Gateway";128;2
"Upgrade";"ProtossGroundArmorsLevel1";"Forge";90;0
"Upgrade";"ProtossGroundWeaponsLevel1";"Forge";97;0
"Unit";"Sentry";"Gateway";138;2
"Unit";"Zealot";"Gateway";141;2
"Unit";"Zealot";"Gateway";141;2
"Building";"PhotonCannon";NA;136;0
"Building";"HighTemplar";NA;146;0
"Building";"HighTemplar";NA;146;0
"Building";"Pylon";NA;146;0
"Building";"Pylon";NA;149;0
"Building";"HighTemplar";NA;149;0
"Building";"HighTemplar";NA;149;0
"Building";"Pylon";NA;149;0
"Building";"PhotonCannon";NA;149;0
"Building";"ShieldBattery";NA;149;0
"Unit";"Zealot";"Gateway";154;2
"Unit";"Zealot";"Gateway";154;2
"Unit";"Zealot";"Gateway";154;2
"Unit";"Zealot";"Gateway";154;2
"Building";"PhotonCannon";NA;152;0
"Upgrade";"ProtossGroundArmorsLevel2";"Forge";136;0
"Building";"Pylon";NA;156;0
"Building";"HighTemplar";NA;162;0
"Building";"HighTemplar";NA;162;0
"Building";"HighTemplar";NA;162;0
"Building";"HighTemplar";NA;162;0
"Unit";"Immortal";"Robotics Facility";154;4
"Unit";"Archon";"High Templar";162;0
"Unit";"Archon";"High Templar";162;0
"Unit";"Zealot";"Gateway";166;2
"Unit";"Zealot";"Gateway";166;2
"Building";"Pylon";NA;162;0
"Building";"Pylon";NA;162;0
"Unit";"Zealot";"Gateway";170;2
"Unit";"Zealot";"Gateway";170;2
"Unit";"Zealot";"Gateway";170;2
"Unit";"Zealot";"Gateway";170;2
"Building";"ShieldBattery";NA;162;0
"Building";"HighTemplar";NA;181;0
"Building";"Assimilator";NA;178;0
"Building";"Stargate";NA;170;0
"Building";"Nexus";NA;162;0
"Building";"Assimilator";NA;178;0
"Building";"HighTemplar";NA;181;0
"Building";"Pylon";NA;178;0
"Building";"HighTemplar";NA;181;0
"Upgrade";"ProtossGroundWeaponsLevel2";"Forge";154;0
"Building";"Stargate";NA;178;0
"Building";"PhotonCannon";NA;181;0
"Building";"PhotonCannon";NA;181;0
"Building";"PhotonCannon";NA;181;0
"Building";"PhotonCannon";NA;181;0
"Unit";"Zealot";"Gateway";182;2
"Unit";"Zealot";"Gateway";182;2
"Unit";"Zealot";"Gateway";182;2
"Unit";"Zealot";"Gateway";182;2
"Unit";"Zealot";"Gateway";182;2
"Unit";"Zealot";"Gateway";182;2
"Unit";"Zealot";"Gateway";182;2
"Unit";"Zealot";"Gateway";182;2
"Building";"DarkTemplar";NA;198;0
"Building";"DarkTemplar";NA;198;0
"Building";"DarkTemplar";NA;198;0
"Building";"DarkTemplar";NA;198;0
"Building";"DarkTemplar";NA;198;0
"Building";"DarkTemplar";NA;198;0
"Building";"DarkTemplar";NA;198;0
"Building";"FleetBeacon";NA;182;0
"Building";"Stargate";NA;182;0
"Unit";"Zealot";"Gateway";200;2
"Unit";"Zealot";"Gateway";200;2
"Unit";"Zealot";"Gateway";200;2
"Unit";"Zealot";"Gateway";200;2
"Unit";"Zealot";"Gateway";200;2
"Unit";"Zealot";"Gateway";200;2
"Unit";"Zealot";"Gateway";200;2
"Unit";"Zealot";"Gateway";200;2
"Building";"Pylon";NA;200;0
"Building";"Pylon";NA;216;0
"Building";"Pylon";NA;216;0
"Building";"Pylon";NA;216;0
"Building";"Pylon";NA;216;0
"Building";"HighTemplar";NA;216;0
"Unit";"Tempest";"Stargate";216;4
"Unit";"Tempest";"Stargate";216;4
"Unit";"Tempest";"Stargate";216;4
"Building";"Pylon";NA;216;0
"Building";"PhotonCannon";NA;216;0
"Building";"PhotonCannon";NA;216;0
"Building";"PhotonCannon";NA;216;0
"Building";"Nexus";NA;216;0
"Unit";"Tempest";"Stargate";224;4
"Unit";"Tempest";"Stargate";228;4
"Unit";"Zealot";"Gateway";236;2
"Unit";"Zealot";"Gateway";236;2
"Unit";"Zealot";"Gateway";236;2
"Unit";"Zealot";"Gateway";236;2
"Unit";"Zealot";"Gateway";236;2
"Unit";"Zealot";"Gateway";236;2
"Unit";"Zealot";"Gateway";236;2
"Unit";"Zealot";"Gateway";236;2
"Unit";"Archon";"High Templar";236;0
"Unit";"Zealot";"Gateway";252;2
"Unit";"Zealot";"Gateway";252;2
"Unit";"Zealot";"Gateway";252;2
"Unit";"Zealot";"Gateway";252;2
"Unit";"Zealot";"Gateway";252;2
"Unit";"Zealot";"Gateway";252;2
"Unit";"Zealot";"Gateway";252;2
"Unit";"Zealot";"Gateway";252;2
"Unit";"Carrier";"Stargate";228;6
"Upgrade";"ProtossGroundWeaponsLevel3";"Forge";228;0
"Upgrade";"ProtossGroundArmorsLevel3";"Forge";228;0
"Unit";"Carrier";"Stargate";228;6
"Unit";"Carrier";"Stargate";228;6
"Unit";"Immortal";"Robotics Facility";252;4
"Building";"HighTemplar";NA;290;0
"Building";"HighTemplar";NA;290;0
"Building";"HighTemplar";NA;290;0
"Building";"HighTemplar";NA;290;0
"Building";"HighTemplar";NA;290;0
"Building";"HighTemplar";NA;290;0
"Building";"HighTemplar";NA;290;0
"Building";"HighTemplar";NA;290;0
"Unit";"Archon";"High Templar";290;0
"Unit";"Archon";"High Templar";290;0
"Unit";"Archon";"High Templar";290;0
"Unit";"Archon";"High Templar";290;0
"Unit";"Observer";"Robotics Facility";290;1
