"type";"unit_name";"on_building";"total_supply";"supply"
"Building";"Pylon";NA;13;0
"Building";"Assimilator";NA;16;0
"Building";"Gateway";NA;15;0
"Building";"Assimilator";NA;20;0
"Building";"CyberneticsCore";NA;20;0
"Building";"Pylon";NA;21;0
"Building";"Nexus";NA;19;0
"Unit";"Stalker";"Gateway";22;2
"Building";"TwilightCouncil";NA;23;0
"Unit";"Stalker";"Gateway";24;2
"Unit";"Stalker";"Gateway";33;2
"Building";"Gateway";NA;35;0
"Building";"Assimilator";NA;41;0
"Building";"Gateway";NA;37;0
"Building";"Pylon";NA;43;0
"Building";"Pylon";NA;43;0
"Unit";"Stalker";"Gateway";47;2
"Unit";"Stalker";"Gateway";47;2
"Unit";"Stalker";"Gateway";47;2
"Building";"RoboticsFacility";NA;41;0
"Unit";"Stalker";"Gateway";56;2
"Unit";"Stalker";"Gateway";56;2
"Unit";"Observer";"Robotics Facility";55;1
"Building";"Pylon";NA;56;0
"Building";"Pylon";NA;64;0
"Unit";"Observer";"Robotics Facility";64;1
"Building";"Pylon";NA;66;0
"Unit";"Stalker";"Gateway";71;2
"Unit";"Stalker";"Gateway";71;2
"Unit";"Stalker";"Gateway";71;2
"Unit";"Observer";"Robotics Facility";69;1
"Building";"Pylon";NA;78;0
"Upgrade";"Charge";"TwilightCouncil";63;0
"Building";"Nexus";NA;63;0
"Building";"Pylon";NA;80;0
"Unit";"Sentry";"Gateway";84;2
"Unit";"Sentry";"Gateway";84;2
"Unit";"Sentry";"Gateway";84;2
"Building";"Forge";NA;80;0
"Building";"Forge";NA;80;0
"Unit";"Observer";"Robotics Facility";84;1
"Building";"Pylon";NA;90;0
"Building";"Gateway";NA;82;0
"Building";"Gateway";NA;82;0
"Building";"Assimilator";NA;93;0
"Building";"Assimilator";NA;93;0
"Building";"Assimilator";NA;95;0
"Building";"Gateway";NA;84;0
"Unit";"Zealot";"Gateway";100;2
"Unit";"Zealot";"Gateway";100;2
"Unit";"Zealot";"Gateway";100;2
"Unit";"Zealot";"Gateway";100;2
"Unit";"Zealot";"Gateway";100;2
"Building";"Gateway";NA;84;0
"Building";"Gateway";NA;84;0
"Unit";"Zealot";"Gateway";113;2
"Unit";"Zealot";"Gateway";114;2
"Unit";"Zealot";"Gateway";119;2
"Unit";"Zealot";"Gateway";119;2
"Unit";"Zealot";"Gateway";123;2
"Unit";"Zealot";"Gateway";123;2
"Unit";"Zealot";"Gateway";123;2
"Unit";"Zealot";"Gateway";123;2
"Unit";"Zealot";"Gateway";123;2
"Unit";"Zealot";"Gateway";123;2
"Building";"Pylon";NA;123;0
"Building";"Pylon";NA;123;0
"Unit";"Zealot";"Gateway";135;2
"Unit";"Zealot";"Gateway";135;2
"Building";"Pylon";NA;123;0
"Building";"Pylon";NA;123;0
"Unit";"Zealot";"Gateway";142;2
"Unit";"Zealot";"Gateway";142;2
"Unit";"Zealot";"Gateway";142;2
"Unit";"Zealot";"Gateway";142;2
"Unit";"Zealot";"Gateway";142;2
"Unit";"Zealot";"Gateway";142;2
"Unit";"Zealot";"Gateway";154;2
"Unit";"Zealot";"Gateway";154;2
"Unit";"Immortal";"Robotics Facility";123;4
"Upgrade";"ProtossGroundWeaponsLevel1";"Forge";100;0
"Upgrade";"ProtossGroundArmorsLevel1";"Forge";100;0
"Unit";"Zealot";"Gateway";162;2
"Unit";"Zealot";"Gateway";162;2
"Unit";"Zealot";"Gateway";162;2
"Unit";"Zealot";"Gateway";162;2
"Unit";"Zealot";"Gateway";162;2
"Unit";"Zealot";"Gateway";162;2
"Unit";"Zealot";"Gateway";174;2
"Unit";"Zealot";"Gateway";174;2
"Building";"Pylon";NA;162;0
"Unit";"Immortal";"Robotics Facility";154;4
"Building";"ShieldBattery";NA;162;0
"Building";"ShieldBattery";NA;162;0
"Unit";"Sentry";"Gateway";183;2
"Unit";"Sentry";"Gateway";183;2
"Unit";"Stalker";"Gateway";187;2
"Unit";"Stalker";"Gateway";187;2
"Unit";"Stalker";"Gateway";187;2
"Building";"Gateway";NA;178;0
"Unit";"Zealot";"Gateway";193;2
"Building";"Gateway";NA;178;0
"Unit";"Zealot";"Gateway";193;2
"Building";"TemplarArchive";NA;183;0
"Building";"Gateway";NA;179;0
"Building";"Gateway";NA;179;0
"Building";"HighTemplar";NA;197;0
"Building";"HighTemplar";NA;197;0
"Building";"HighTemplar";NA;197;0
"Building";"HighTemplar";NA;197;0
"Building";"HighTemplar";NA;197;0
"Building";"HighTemplar";NA;197;0
"Building";"Pylon";NA;193;0
"Unit";"Archon";"High Templar";197;0
"Unit";"Zealot";"Gateway";197;2
"Unit";"Archon";"High Templar";197;0
"Unit";"Zealot";"Gateway";197;2
"Unit";"Zealot";"Gateway";197;2
"Unit";"Archon";"High Templar";197;0
"Unit";"Zealot";"Gateway";197;2
"Unit";"Zealot";"Gateway";201;2
"Unit";"Zealot";"Gateway";203;2
"Unit";"Zealot";"Gateway";212;2
"Building";"Pylon";NA;209;0
"Unit";"Zealot";"Gateway";212;2
"Unit";"Zealot";"Gateway";212;2
"Unit";"Zealot";"Gateway";212;2
"Unit";"Zealot";"Gateway";212;2
"Unit";"Zealot";"Gateway";212;2
"Building";"HighTemplar";NA;224;0
"Building";"HighTemplar";NA;224;0
"Building";"HighTemplar";NA;224;0
"Building";"HighTemplar";NA;224;0
"Building";"HighTemplar";NA;224;0
"Building";"HighTemplar";NA;224;0
"Building";"Nexus";NA;193;0
"Upgrade";"ProtossGroundWeaponsLevel2";"Forge";183;0
"Upgrade";"ProtossGroundArmorsLevel2";"Forge";183;0
"Unit";"Zealot";"Gateway";224;2
"Unit";"Zealot";"Gateway";224;2
"Unit";"Zealot";"Gateway";224;2
"Unit";"Zealot";"Gateway";224;2
"Unit";"Stalker";"Gateway";235;2
"Unit";"Stalker";"Gateway";235;2
"Unit";"Stalker";"Gateway";243;2
"Unit";"Stalker";"Gateway";243;2
"Unit";"Stalker";"Gateway";243;2
"Unit";"Stalker";"Gateway";243;2
"Unit";"Stalker";"Gateway";243;2
"Unit";"Stalker";"Gateway";243;2
"Unit";"Stalker";"Gateway";243;2
"Building";"Assimilator";NA;239;0
"Unit";"Stalker";"Gateway";253;2
"Building";"Assimilator";NA;239;0
"Unit";"Zealot";"Gateway";261;2
"Unit";"Zealot";"Gateway";261;2
"Unit";"Zealot";"Gateway";261;2
"Unit";"Zealot";"Gateway";261;2
"Unit";"Zealot";"Gateway";261;2
"Unit";"Zealot";"Gateway";261;2
"Unit";"Zealot";"Gateway";261;2
"Unit";"Zealot";"Gateway";261;2
"Unit";"Zealot";"Gateway";261;2
"Unit";"Zealot";"Gateway";261;2
"Unit";"Zealot";"Gateway";261;2
"Unit";"Zealot";"Gateway";261;2
"Unit";"Stalker";"Gateway";285;2
"Unit";"Stalker";"Gateway";285;2
"Unit";"Stalker";"Gateway";285;2
"Unit";"Stalker";"Gateway";285;2
"Unit";"Stalker";"Gateway";285;2
"Unit";"Stalker";"Gateway";285;2
"Unit";"Stalker";"Gateway";285;2
"Unit";"Stalker";"Gateway";285;2
"Unit";"Immortal";"Robotics Facility";261;4
"Building";"Pylon";NA;301;0
"Building";"Pylon";NA;301;0
"Building";"Pylon";NA;301;0
"Building";"Pylon";NA;305;0
"Unit";"Zealot";"Gateway";305;2
"Unit";"Zealot";"Gateway";305;2
"Unit";"Zealot";"Gateway";305;2
"Unit";"Zealot";"Gateway";305;2
"Unit";"Zealot";"Gateway";305;2
"Unit";"Zealot";"Gateway";305;2
"Unit";"Zealot";"Gateway";305;2
"Building";"HighTemplar";NA;319;0
"Building";"HighTemplar";NA;319;0
"Building";"HighTemplar";NA;319;0
"Upgrade";"ProtossGroundArmorsLevel3";"Forge";239;0
"Building";"HighTemplar";NA;319;0
"Upgrade";"ProtossGroundWeaponsLevel3";"Forge";239;0
"Building";"PhotonCannon";NA;319;0
"Building";"PhotonCannon";NA;319;0
"Building";"PhotonCannon";NA;319;0
"Building";"PhotonCannon";NA;319;0
"Building";"PhotonCannon";NA;319;0
"Building";"ShieldBattery";NA;319;0
"Unit";"Zealot";"Gateway";319;2
"Unit";"Zealot";"Gateway";319;2
"Unit";"Zealot";"Gateway";319;2
"Unit";"Zealot";"Gateway";319;2
"Unit";"Zealot";"Gateway";319;2
"Unit";"Zealot";"Gateway";319;2
"Unit";"Zealot";"Gateway";319;2
"Unit";"Zealot";"Gateway";319;2
"Unit";"Zealot";"Gateway";319;2
"Unit";"Zealot";"Gateway";319;2
"Unit";"Zealot";"Gateway";319;2
"Unit";"Zealot";"Gateway";319;2
