"type";"unit_name";"on_building";"total_supply";"supply"
"Building";"Pylon";NA;13;0
"Building";"Assimilator";NA;16;0
"Building";"Pylon";NA;17;0
"Building";"Gateway";NA;15;0
"Unit";"Zealot";"Gateway";19;2
"Building";"CyberneticsCore";NA;19;0
"Unit";"Stalker";"Gateway";24;2
"Building";"Assimilator";NA;24;0
"Building";"Pylon";NA;28;0
"Unit";"Stalker";"Gateway";27;2
"Building";"Nexus";NA;24;0
"Building";"TwilightCouncil";NA;31;0
"Building";"Gateway";NA;31;0
"Building";"ShieldBattery";NA;33;0
"Building";"Gateway";NA;32;0
"Unit";"Sentry";"Gateway";37;2
"Unit";"Stalker";"Gateway";45;2
"Unit";"Stalker";"Gateway";45;2
"Unit";"Stalker";"Gateway";47;2
"Building";"Assimilator";NA;45;0
"Building";"Assimilator";NA;45;0
"Building";"RoboticsFacility";NA;39;0
"Building";"Pylon";NA;53;0
"Building";"Pylon";NA;53;0
"Unit";"Stalker";"Gateway";55;2
"Unit";"Stalker";"Gateway";57;2
"Building";"Pylon";NA;61;0
"Unit";"Observer";"Robotics Facility";60;1
"Building";"Gateway";NA;55;0
"Building";"Gateway";NA;55;0
"Building";"Pylon";NA;61;0
"Unit";"Stalker";"Gateway";63;2
"Unit";"Stalker";"Gateway";63;2
"Unit";"Stalker";"Gateway";63;2
"Unit";"Stalker";"Gateway";72;2
"Unit";"Stalker";"Gateway";72;2
"Unit";"Stalker";"Gateway";72;2
"Building";"Pylon";NA;70;0
"Unit";"Immortal";"Robotics Facility";70;4
"Upgrade";"Charge";"TwilightCouncil";62;0
"Building";"Pylon";NA;85;0
"Building";"Pylon";NA;86;0
"Unit";"Stalker";"Gateway";88;2
"Unit";"Stalker";"Gateway";88;2
"Unit";"Stalker";"Gateway";88;2
"Unit";"Stalker";"Gateway";88;2
"Building";"Forge";NA;84;0
"Building";"TemplarArchive";NA;84;0
"Building";"Nexus";NA;83;0
"Building";"HighTemplar";NA;101;0
"Building";"HighTemplar";NA;101;0
"Building";"HighTemplar";NA;101;0
"Unit";"Zealot";"Gateway";103;2
"Unit";"Zealot";"Gateway";103;2
"Unit";"Zealot";"Gateway";110;2
"Unit";"Zealot";"Gateway";110;2
"Unit";"Zealot";"Gateway";110;2
"Unit";"Zealot";"Gateway";110;2
"Unit";"Zealot";"Gateway";110;2
"Building";"Pylon";NA;110;0
"Building";"Pylon";NA;110;0
"Building";"Gateway";NA;102;0
"Building";"Gateway";NA;102;0
"Upgrade";"ProtossGroundWeaponsLevel1";"Forge";98;0
"Unit";"Archon";"High Templar";120;0
"Unit";"Zealot";"Gateway";120;2
"Unit";"Zealot";"Gateway";120;2
"Unit";"Zealot";"Gateway";120;2
"Unit";"Zealot";"Gateway";120;2
"Unit";"Stalker";"Gateway";128;2
"Unit";"Zealot";"Gateway";130;2
"Unit";"Zealot";"Gateway";130;2
"Unit";"Zealot";"Gateway";130;2
"Unit";"Zealot";"Gateway";130;2
"Unit";"Zealot";"Gateway";130;2
"Unit";"Zealot";"Gateway";130;2
"Unit";"Immortal";"Robotics Facility";120;4
"Building";"HighTemplar";NA;146;0
"Building";"Assimilator";NA;146;0
"Unit";"Zealot";"Gateway";148;2
"Unit";"Zealot";"Gateway";148;2
"Unit";"Zealot";"Gateway";148;2
"Unit";"Zealot";"Gateway";148;2
"Unit";"Zealot";"Gateway";148;2
"Unit";"Zealot";"Gateway";148;2
"Unit";"Immortal";"Robotics Facility";130;4
"Building";"Assimilator";NA;146;0
"Building";"Gateway";NA;142;0
"Building";"Gateway";NA;146;0
"Building";"Gateway";NA;146;0
"Building";"HighTemplar";NA;165;0
"Building";"HighTemplar";NA;165;0
"Building";"HighTemplar";NA;165;0
"Building";"HighTemplar";NA;165;0
"Building";"HighTemplar";NA;165;0
"Building";"HighTemplar";NA;165;0
"Unit";"Zealot";"Gateway";165;2
"Building";"Gateway";NA;146;0
"Unit";"Immortal";"Robotics Facility";146;4
"Building";"Pylon";NA;165;0
"Unit";"Stalker";"Gateway";175;2
"Unit";"Stalker";"Gateway";175;2
"Unit";"Stalker";"Gateway";175;2
"Unit";"Stalker";"Gateway";175;2
"Building";"Forge";NA;170;0
"Unit";"Zealot";"Gateway";183;2
"Unit";"Zealot";"Gateway";183;2
"Unit";"Zealot";"Gateway";183;2
"Upgrade";"ProtossGroundArmorsLevel1";"Forge";165;0
"Unit";"Zealot";"Gateway";191;2
"Building";"Pylon";NA;189;0
"Building";"Pylon";NA;191;0
"Unit";"Immortal";"Robotics Facility";191;4
"Unit";"Archon";"High Templar";193;0
"Unit";"Archon";"High Templar";193;0
"Unit";"Archon";"High Templar";193;0
"Unit";"Zealot";"Gateway";197;2
"Unit";"Zealot";"Gateway";197;2
"Unit";"Zealot";"Gateway";197;2
"Unit";"Zealot";"Gateway";197;2
"Unit";"Zealot";"Gateway";197;2
"Unit";"Zealot";"Gateway";197;2
"Unit";"Zealot";"Gateway";197;2
"Unit";"Zealot";"Gateway";197;2
"Unit";"Zealot";"Gateway";197;2
"Unit";"Zealot";"Gateway";197;2
"Unit";"Zealot";"Gateway";197;2
"Building";"HighTemplar";NA;219;0
"Building";"HighTemplar";NA;219;0
"Building";"HighTemplar";NA;219;0
"Building";"HighTemplar";NA;219;0
"Building";"HighTemplar";NA;219;0
"Building";"HighTemplar";NA;222;0
"Unit";"Immortal";"Robotics Facility";197;4
"Unit";"Sentry";"Gateway";226;2
"Unit";"Sentry";"Gateway";226;2
"Unit";"Zealot";"Gateway";226;2
"Unit";"Zealot";"Gateway";226;2
"Unit";"Zealot";"Gateway";226;2
"Unit";"Zealot";"Gateway";236;2
"Unit";"Zealot";"Gateway";236;2
"Unit";"Zealot";"Gateway";236;2
"Unit";"Zealot";"Gateway";236;2
"Unit";"Zealot";"Gateway";236;2
"Unit";"Zealot";"Gateway";236;2
"Unit";"Zealot";"Gateway";236;2
"Unit";"Zealot";"Gateway";236;2
"Unit";"Zealot";"Gateway";236;2
"Unit";"Immortal";"Robotics Facility";222;4
"Unit";"Zealot";"Gateway";258;2
"Unit";"Zealot";"Gateway";258;2
"Unit";"Zealot";"Gateway";258;2
"Unit";"Zealot";"Gateway";258;2
"Unit";"Zealot";"Gateway";258;2
"Unit";"Zealot";"Gateway";258;2
"Unit";"Zealot";"Gateway";258;2
"Unit";"Zealot";"Gateway";258;2
"Unit";"Zealot";"Gateway";258;2
"Unit";"Zealot";"Gateway";258;2
"Unit";"Zealot";"Gateway";258;2
"Unit";"Archon";"High Templar";258;0
"Building";"HighTemplar";NA;280;0
"Building";"HighTemplar";NA;280;0
"Building";"HighTemplar";NA;280;0
"Building";"HighTemplar";NA;280;0
"Building";"HighTemplar";NA;280;0
"Building";"HighTemplar";NA;280;0
"Building";"HighTemplar";NA;280;0
"Building";"HighTemplar";NA;280;0
"Unit";"Archon";"High Templar";280;0
"Unit";"Archon";"High Templar";280;0
"Unit";"Zealot";"Gateway";280;2
"Upgrade";"ProtossGroundArmorsLevel2";"Forge";226;0
"Upgrade";"ProtossGroundWeaponsLevel2";"Forge";226;0
"Unit";"Stalker";"Gateway";282;2
"Unit";"Stalker";"Gateway";282;2
"Building";"Pylon";NA;282;0
"Building";"HighTemplar";NA;286;0
"Building";"HighTemplar";NA;286;0
"Unit";"Zealot";"Gateway";286;2
"Unit";"Zealot";"Gateway";286;2
"Unit";"Zealot";"Gateway";286;2
"Unit";"Zealot";"Gateway";286;2
"Unit";"Zealot";"Gateway";286;2
"Unit";"Zealot";"Gateway";286;2
"Unit";"Archon";"High Templar";298;0
"Building";"ShieldBattery";NA;286;0
"Building";"ShieldBattery";NA;286;0
"Unit";"Zealot";"Gateway";298;2
"Unit";"Zealot";"Gateway";298;2
"Unit";"Zealot";"Gateway";298;2
"Unit";"Zealot";"Gateway";298;2
"Unit";"Zealot";"Gateway";298;2
"Unit";"Zealot";"Gateway";298;2
"Unit";"Zealot";"Gateway";298;2
"Unit";"Zealot";"Gateway";298;2
"Unit";"Zealot";"Gateway";298;2
"Unit";"Stalker";"Gateway";316;2
"Unit";"Stalker";"Gateway";318;2
"Unit";"Stalker";"Gateway";318;2
"Unit";"Zealot";"Gateway";318;2
"Unit";"Zealot";"Gateway";318;2
"Unit";"Zealot";"Gateway";318;2
"Unit";"Zealot";"Gateway";318;2
"Unit";"Zealot";"Gateway";330;2
"Unit";"Zealot";"Gateway";330;2
"Unit";"Zealot";"Gateway";330;2
"Unit";"Zealot";"Gateway";330;2
"Unit";"Zealot";"Gateway";330;2
"Unit";"Archon";"High Templar";330;0
"Building";"HighTemplar";NA;340;0
"Building";"HighTemplar";NA;340;0
"Building";"HighTemplar";NA;340;0
"Building";"HighTemplar";NA;340;0
"Building";"HighTemplar";NA;340;0
"Building";"HighTemplar";NA;340;0
"Building";"HighTemplar";NA;340;0
"Building";"HighTemplar";NA;340;0
"Building";"HighTemplar";NA;340;0
"Unit";"Zealot";"Gateway";340;2
"Unit";"Zealot";"Gateway";340;2
