"type";"unit_name";"on_building";"total_supply";"supply"
"Building";"Pylon";NA;13;0
"Building";"Assimilator";NA;16;0
"Building";"Pylon";NA;17;0
"Building";"Gateway";NA;15;0
"Unit";"Zealot";"Gateway";19;2
"Building";"CyberneticsCore";NA;19;0
"Unit";"Stalker";"Gateway";23;2
"Building";"Assimilator";NA;23;0
"Unit";"Stalker";"Gateway";24;2
"Building";"Nexus";NA;23;0
"Unit";"Stalker";"Gateway";29;2
"Building";"RoboticsFacility";NA;27;0
"Building";"Gateway";NA;30;0
"Unit";"Sentry";"Gateway";32;2
"Unit";"Observer";"Robotics Facility";34;1
"Building";"Pylon";NA;41;0
"Building";"ShieldBattery";NA;38;0
"Building";"Gateway";NA;34;0
"Unit";"Observer";"Robotics Facility";43;1
"Unit";"Stalker";"Gateway";46;2
"Unit";"Stalker";"Gateway";46;2
"Building";"Pylon";NA;53;0
"Building";"Pylon";NA;54;0
"Building";"Pylon";NA;55;0
"Unit";"Zealot";"Gateway";55;2
"Unit";"Zealot";"Gateway";55;2
"Unit";"Zealot";"Gateway";55;2
"Building";"TwilightCouncil";NA;53;0
"Unit";"Observer";"Robotics Facility";55;1
"Unit";"Zealot";"Gateway";62;2
"Unit";"Zealot";"Gateway";62;2
"Unit";"Zealot";"Gateway";62;2
"Unit";"Observer";"Robotics Facility";62;1
"Building";"ShieldBattery";NA;62;0
"Building";"Gateway";NA;55;0
"Building";"Gateway";NA;55;0
"Building";"ShieldBattery";NA;62;0
"Unit";"Stalker";"Gateway";70;2
"Building";"Pylon";NA;69;0
"Building";"Pylon";NA;69;0
"Unit";"Zealot";"Gateway";72;2
"Unit";"Zealot";"Gateway";72;2
"Unit";"Zealot";"Gateway";72;2
"Unit";"Zealot";"Gateway";72;2
"Unit";"Immortal";"Robotics Facility";69;4
"Building";"Pylon";NA;72;0
"Unit";"Zealot";"Gateway";84;2
"Unit";"Zealot";"Gateway";84;2
"Unit";"Zealot";"Gateway";84;2
"Unit";"Zealot";"Gateway";84;2
"Upgrade";"Charge";"TwilightCouncil";69;0
"Unit";"Zealot";"Gateway";92;2
"Building";"Pylon";NA;92;0
"Building";"Pylon";NA;92;0
"Building";"Pylon";NA;92;0
"Unit";"Immortal";"Robotics Facility";88;4
"Unit";"Stalker";"Gateway";98;2
"Unit";"Stalker";"Gateway";100;2
"Unit";"Stalker";"Gateway";100;2
"Building";"Gateway";NA;92;0
"Building";"Pylon";NA;100;0
"Unit";"Zealot";"Gateway";108;2
"Unit";"Zealot";"Gateway";108;2
"Unit";"Zealot";"Gateway";112;2
"Unit";"Zealot";"Gateway";112;2
"Unit";"Zealot";"Gateway";112;2
"Building";"Forge";NA;106;0
"Building";"Nexus";NA;98;0
"Unit";"Zealot";"Gateway";118;2
"Unit";"Zealot";"Gateway";118;2
"Unit";"Zealot";"Gateway";118;2
"Unit";"Zealot";"Gateway";118;2
"Unit";"Zealot";"Gateway";118;2
"Unit";"Zealot";"Gateway";133;2
"Unit";"Zealot";"Gateway";134;2
"Unit";"Zealot";"Gateway";134;2
"Unit";"Zealot";"Gateway";134;2
"Unit";"Zealot";"Gateway";134;2
"Unit";"Immortal";"Robotics Facility";118;4
"Building";"Forge";NA;130;0
"Unit";"Sentry";"Gateway";153;2
"Unit";"Sentry";"Gateway";153;2
"Unit";"Zealot";"Gateway";153;2
"Unit";"Zealot";"Gateway";153;2
"Unit";"Zealot";"Gateway";153;2
"Unit";"Zealot";"Gateway";153;2
"Building";"TemplarArchive";NA;134;0
"Building";"Gateway";NA;131;0
"Building";"Gateway";NA;133;0
"Unit";"Immortal";"Robotics Facility";152;4
"Unit";"Zealot";"Gateway";169;2
"Unit";"Zealot";"Gateway";169;2
"Unit";"Zealot";"Gateway";169;2
"Unit";"Zealot";"Gateway";169;2
"Unit";"Zealot";"Gateway";169;2
"Unit";"Zealot";"Gateway";169;2
"Upgrade";"ProtossGroundArmorsLevel1";"Forge";133;0
"Unit";"Zealot";"Gateway";181;2
"Unit";"Zealot";"Gateway";181;2
"Unit";"Zealot";"Gateway";181;2
"Unit";"Zealot";"Gateway";181;2
"Unit";"Zealot";"Gateway";181;2
"Unit";"Zealot";"Gateway";181;2
"Unit";"Immortal";"Robotics Facility";181;4
"Upgrade";"ProtossGroundWeaponsLevel1";"Forge";165;0
"Building";"Assimilator";NA;196;0
"Unit";"Sentry";"Gateway";201;2
"Building";"Assimilator";NA;196;0
"Building";"HighTemplar";NA;201;0
"Building";"HighTemplar";NA;201;0
"Unit";"Zealot";"Gateway";201;2
"Unit";"Zealot";"Gateway";201;2
"Unit";"Zealot";"Gateway";201;2
"Unit";"Zealot";"Gateway";201;2
"Unit";"Zealot";"Gateway";201;2
"Building";"Pylon";NA;201;0
"Building";"Pylon";NA;201;0
"Unit";"Archon";"High Templar";213;0
"Building";"Gateway";NA;196;0
"Building";"Gateway";NA;196;0
"Building";"Assimilator";NA;213;0
"Unit";"Zealot";"Gateway";213;2
"Unit";"Zealot";"Gateway";213;2
"Building";"Assimilator";NA;213;0
"Unit";"Zealot";"Gateway";213;2
"Unit";"Zealot";"Gateway";213;2
"Unit";"Zealot";"Gateway";213;2
"Unit";"Zealot";"Gateway";213;2
"Unit";"Stalker";"Gateway";225;2
"Unit";"Stalker";"Gateway";225;2
"Unit";"Stalker";"Gateway";225;2
"Unit";"Stalker";"Gateway";225;2
"Unit";"Stalker";"Gateway";225;2
"Unit";"Stalker";"Gateway";225;2
"Unit";"Zealot";"Gateway";225;2
"Unit";"Zealot";"Gateway";225;2
"Unit";"Zealot";"Gateway";225;2
"Unit";"Immortal";"Robotics Facility";213;4
"Building";"Nexus";NA;201;0
"Upgrade";"ProtossGroundArmorsLevel2";"Forge";196;0
"Unit";"Zealot";"Gateway";247;2
"Unit";"Zealot";"Gateway";247;2
"Unit";"Zealot";"Gateway";251;2
"Unit";"Zealot";"Gateway";251;2
"Unit";"Zealot";"Gateway";251;2
"Unit";"Zealot";"Gateway";251;2
"Unit";"Zealot";"Gateway";251;2
"Unit";"Zealot";"Gateway";251;2
"Unit";"Zealot";"Gateway";251;2
"Building";"HighTemplar";NA;265;0
"Building";"HighTemplar";NA;265;0
"Building";"Assimilator";NA;265;0
"Building";"Assimilator";NA;265;0
"Unit";"Sentry";"Gateway";273;2
"Unit";"Zealot";"Gateway";273;2
"Unit";"Zealot";"Gateway";273;2
"Unit";"Zealot";"Gateway";273;2
"Unit";"Zealot";"Gateway";273;2
"Unit";"Zealot";"Gateway";273;2
"Unit";"Zealot";"Gateway";273;2
"Unit";"Zealot";"Gateway";273;2
"Unit";"Zealot";"Gateway";273;2
"Unit";"Immortal";"Robotics Facility";268;4
"Building";"HighTemplar";NA;295;0
"Building";"HighTemplar";NA;295;0
"Building";"HighTemplar";NA;295;0
"Building";"HighTemplar";NA;295;0
"Upgrade";"ProtossGroundWeaponsLevel2";"Forge";247;0
"Building";"RoboticsBay";NA;270;0
"Building";"RoboticsFacility";NA;270;0
"Unit";"Zealot";"Gateway";295;2
"Unit";"Zealot";"Gateway";295;2
"Unit";"Zealot";"Gateway";295;2
"Unit";"Immortal";"Robotics Facility";295;4
"Unit";"Colossus";"Robotics Facility";295;6
"Unit";"Zealot";"Gateway";317;2
"Unit";"Zealot";"Gateway";317;2
"Unit";"Zealot";"Gateway";317;2
"Building";"Pylon";NA;311;0
"Unit";"Zealot";"Gateway";323;2
"Unit";"Zealot";"Gateway";323;2
"Unit";"Zealot";"Gateway";323;2
"Upgrade";"ProtossGroundArmorsLevel3";"Forge";273;0
"Unit";"Colossus";"Robotics Facility";309;6
"Building";"Assimilator";NA;329;0
"Building";"Assimilator";NA;329;0
"Unit";"Colossus";"Robotics Facility";311;6
"Building";"Nexus";NA;305;0
"Unit";"Zealot";"Gateway";341;2
"Unit";"Zealot";"Gateway";341;2
"Unit";"Zealot";"Gateway";341;2
"Unit";"Zealot";"Gateway";341;2
"Unit";"Zealot";"Gateway";341;2
"Unit";"Zealot";"Gateway";341;2
"Unit";"Zealot";"Gateway";341;2
"Unit";"Zealot";"Gateway";341;2
"Unit";"Zealot";"Gateway";341;2
"Unit";"Zealot";"Gateway";341;2
"Unit";"Colossus";"Robotics Facility";329;6
"Building";"DarkShrine";NA;323;0
"Unit";"Stalker";"Gateway";367;2
"Unit";"Stalker";"Gateway";367;2
"Unit";"Stalker";"Gateway";367;2
"Unit";"Stalker";"Gateway";367;2
"Unit";"Stalker";"Gateway";367;2
"Unit";"Stalker";"Gateway";367;2
"Upgrade";"ExtendedThermalLance";"RoboticsBay";329;0
"Unit";"Colossus";"Robotics Facility";335;6
"Unit";"Archon";"High Templar";377;0
"Upgrade";"ProtossGroundWeaponsLevel3";"Forge";311;0
"Unit";"Stalker";"Gateway";385;2
"Unit";"Stalker";"Gateway";385;2
"Unit";"Stalker";"Gateway";385;2
"Unit";"Stalker";"Gateway";385;2
"Unit";"Stalker";"Gateway";385;2
"Unit";"Stalker";"Gateway";385;2
"Unit";"Stalker";"Gateway";385;2
"Unit";"Stalker";"Gateway";385;2
"Unit";"Stalker";"Gateway";385;2
"Unit";"Colossus";"Robotics Facility";367;6
"Upgrade";"ProtossShieldsLevel1";"Forge";341;0
"Unit";"Zealot";"Gateway";409;2
"Unit";"Zealot";"Gateway";409;2
"Unit";"Zealot";"Gateway";409;2
"Unit";"Zealot";"Gateway";409;2
"Unit";"Zealot";"Gateway";409;2
"Unit";"Zealot";"Gateway";409;2
"Unit";"Zealot";"Gateway";409;2
"Unit";"Zealot";"Gateway";409;2
"Unit";"Zealot";"Gateway";409;2
"Unit";"Zealot";"Gateway";409;2
"Unit";"Stalker";"Gateway";429;2
"Unit";"Stalker";"Gateway";429;2
"Unit";"Stalker";"Gateway";429;2
"Unit";"Stalker";"Gateway";429;2
"Unit";"Stalker";"Gateway";429;2
"Unit";"Stalker";"Gateway";429;2
"Unit";"Stalker";"Gateway";429;2
"Unit";"Stalker";"Gateway";429;2
"Unit";"Stalker";"Gateway";429;2
"Unit";"Stalker";"Gateway";429;2
