"type";"unit_name";"on_building";"total_supply";"supply"
"Building";"Pylon";NA;13;0
"Building";"Assimilator";NA;16;0
"Building";"Gateway";NA;15;0
"Building";"Pylon";NA;19;0
"Unit";"Zealot";"Gateway";19;2
"Building";"CyberneticsCore";NA;19;0
"Unit";"Adept";"Gateway";19;2
"Building";"Assimilator";NA;23;0
"Unit";"Adept";"Gateway";23;2
"Building";"RoboticsFacility";NA;21;0
"Building";"Nexus";NA;19;0
"Building";"ShieldBattery";NA;23;0
"Building";"ShieldBattery";NA;23;0
"Unit";"Immortal";"Robotics Facility";23;4
"Building";"Pylon";NA;26;0
"Unit";"Observer";"Robotics Facility";26;1
"Unit";"Stalker";"Gateway";31;2
"Unit";"Immortal";"Robotics Facility";35;4
"Unit";"Observer";"Robotics Facility";41;1
"Unit";"Sentry";"Gateway";47;2
"Building";"Pylon";NA;48;0
"Building";"Assimilator";NA;47;0
"Building";"Assimilator";NA;48;0
"Unit";"Observer";"Robotics Facility";48;1
"Building";"RoboticsFacility";NA;41;0
"Unit";"Observer";"Robotics Facility";55;1
"Building";"TwilightCouncil";NA;53;0
"Building";"Gateway";NA;53;0
"Building";"Gateway";NA;53;0
"Building";"Pylon";NA;59;0
"Unit";"Stalker";"Gateway";61;2
"Building";"Gateway";NA;57;0
"Unit";"Stalker";"Gateway";63;2
"Unit";"Observer";"Robotics Facility";65;1
"Unit";"Stalker";"Gateway";65;2
"Unit";"Stalker";"Gateway";65;2
"Unit";"Stalker";"Gateway";65;2
"Building";"Pylon";NA;72;0
"Building";"ShieldBattery";NA;72;0
"Unit";"Phoenix";"Stargate";72;2
"Building";"ShieldBattery";NA;72;0
"Building";"Pylon";NA;72;0
"Building";"Pylon";NA;72;0
"Unit";"Zealot";"Gateway";74;2
"Unit";"Zealot";"Gateway";74;2
"Unit";"Zealot";"Gateway";74;2
"Building";"TemplarArchive";NA;74;0
"Building";"HighTemplar";NA;84;0
"Building";"HighTemplar";NA;84;0
"Building";"Pylon";NA;86;0
"Building";"Gateway";NA;82;0
"Building";"HighTemplar";NA;86;0
"Building";"HighTemplar";NA;86;0
"Unit";"Zealot";"Gateway";86;2
"Building";"Pylon";NA;86;0
"Unit";"Observer";"Robotics Facility";86;1
"Unit";"Stalker";"Gateway";90;2
"Unit";"Stalker";"Gateway";90;2
"Unit";"Stalker";"Gateway";94;2
"Building";"Pylon";NA;89;0
"Building";"Pylon";NA;89;0
"Unit";"Zealot";"Gateway";96;2
"Unit";"Zealot";"Gateway";96;2
"Building";"Gateway";NA;86;0
"Building";"Gateway";NA;86;0
"Unit";"Zealot";"Gateway";100;2
"Unit";"Zealot";"Gateway";100;2
"Unit";"Archon";"High Templar";100;0
"Upgrade";"Charge";"TwilightCouncil";86;0
"Building";"HighTemplar";NA;104;0
"Building";"HighTemplar";NA;104;0
"Building";"HighTemplar";NA;104;0
"Unit";"Zealot";"Gateway";104;2
"Unit";"Zealot";"Gateway";104;2
"Unit";"Zealot";"Gateway";104;2
"Unit";"Zealot";"Gateway";104;2
"Building";"Assimilator";NA;104;0
"Building";"Pylon";NA;104;0
"Building";"Assimilator";NA;104;0
"Building";"RoboticsFacility";NA;104;0
"Building";"Pylon";NA;112;0
"Building";"Pylon";NA;112;0
"Building";"Forge";NA;112;0
"Building";"Forge";NA;112;0
"Unit";"Observer";"Robotics Facility";112;1
"Building";"Nexus";NA;104;0
"Unit";"Adept";"Gateway";113;2
"Unit";"Adept";"Gateway";113;2
"Unit";"Adept";"Gateway";113;2
"Unit";"Adept";"Gateway";113;2
"Unit";"Adept";"Gateway";113;2
"Building";"RoboticsBay";NA;112;0
"Unit";"Immortal";"Robotics Facility";112;4
"Unit";"Colossus";"Robotics Facility";123;6
"Unit";"Colossus";"Robotics Facility";123;6
"Unit";"Archon";"High Templar";141;0
"Unit";"Stalker";"Gateway";141;2
"Unit";"Stalker";"Gateway";141;2
"Unit";"Stalker";"Gateway";145;2
"Unit";"Stalker";"Gateway";145;2
"Unit";"Stalker";"Gateway";145;2
"Unit";"Stalker";"Gateway";145;2
"Unit";"Disruptor";"Robotics Facility";135;3
"Unit";"Stalker";"Gateway";156;2
"Unit";"Stalker";"Gateway";156;2
"Unit";"Colossus";"Robotics Facility";135;6
"Upgrade";"ExtendedThermalLance";"RoboticsBay";129;0
"Unit";"Stalker";"Gateway";170;2
"Unit";"Stalker";"Gateway";170;2
"Unit";"Stalker";"Gateway";176;2
"Unit";"Sentry";"Gateway";176;2
"Unit";"Colossus";"Robotics Facility";145;6
"Building";"HighTemplar";NA;187;0
"Building";"HighTemplar";NA;189;0
"Building";"HighTemplar";NA;189;0
"Unit";"Zealot";"Gateway";189;2
"Unit";"Zealot";"Gateway";189;2
"Building";"PhotonCannon";NA;181;0
"Unit";"Zealot";"Gateway";189;2
"Unit";"Zealot";"Gateway";189;2
"Building";"ShieldBattery";NA;187;0
"Unit";"Zealot";"Gateway";197;2
"Unit";"Zealot";"Gateway";197;2
"Unit";"Zealot";"Gateway";197;2
"Unit";"Zealot";"Gateway";197;2
"Unit";"Zealot";"Gateway";197;2
"Unit";"Zealot";"Gateway";197;2
"Upgrade";"GraviticDrive";"RoboticsBay";189;0
"Upgrade";"ProtossGroundArmorsLevel1";"Forge";174;0
"Upgrade";"ProtossGroundWeaponsLevel1";"Forge";176;0
"Building";"HighTemplar";NA;209;0
"Building";"HighTemplar";NA;209;0
"Building";"Pylon";NA;209;0
"Unit";"Observer";"Robotics Facility";209;1
"Unit";"Observer";"Robotics Facility";209;1
"Building";"HighTemplar";NA;211;0
"Building";"HighTemplar";NA;211;0
"Building";"HighTemplar";NA;211;0
"Unit";"Archon";"High Templar";212;0
"Building";"Gateway";NA;209;0
"Building";"Gateway";NA;209;0
"Unit";"Observer";"Robotics Facility";211;1
"Unit";"Stalker";"Gateway";213;2
"Unit";"Stalker";"Gateway";213;2
"Unit";"Stalker";"Gateway";213;2
"Unit";"Stalker";"Gateway";213;2
"Unit";"Stalker";"Gateway";213;2
"Unit";"Stalker";"Gateway";213;2
"Unit";"Stalker";"Gateway";213;2
"Building";"DarkShrine";NA;209;0
"Unit";"Archon";"High Templar";227;0
"Building";"Nexus";NA;209;0
"Unit";"Stalker";"Gateway";229;2
"Unit";"Stalker";"Gateway";229;2
"Unit";"Stalker";"Gateway";229;2
"Unit";"Stalker";"Gateway";229;2
"Unit";"Stalker";"Gateway";229;2
"Unit";"Stalker";"Gateway";229;2
"Unit";"Stalker";"Gateway";229;2
"Unit";"Immortal";"Robotics Facility";227;4
"Unit";"Immortal";"Robotics Facility";227;4
"Building";"DarkTemplar";NA;251;0
"Building";"DarkTemplar";NA;251;0
"Building";"DarkTemplar";NA;251;0
"Building";"DarkTemplar";NA;251;0
