"type";"unit_name";"on_building";"total_supply_lag";"supply"
"Building";"Pylon";NA;14;0
"Building";"Gateway";NA;16;0
"Building";"Assimilator";NA;17;0
"Building";"Nexus";NA;20;0
"Building";"CyberneticsCore";NA;20;0
"Building";"Assimilator";NA;21;0
"Building";"Pylon";NA;22;0
"Unit";"Stalker";"Gateway";23;2
"Building";"TwilightCouncil";NA;26;0
"Unit";"Stalker";"Gateway";27;2
"Unit";"Stalker";"Gateway";37;2
"Building";"ShieldBattery";NA;40;0
"Building";"Gateway";NA;41;0
"Building";"Gateway";NA;41;0
"Building";"Pylon";NA;43;0
"Unit";"Stalker";"Gateway";43;2
"Building";"RoboticsFacility";NA;46;0
"Building";"Assimilator";NA;55;0
"Building";"Assimilator";NA;55;0
"Unit";"Observer";"Robotics Facility";55;1
"Building";"Nexus";NA;56;0
"Building";"Pylon";NA;56;0
"Building";"Forge";NA;58;0
"Building";"Forge";NA;58;0
"Unit";"Sentry";"Gateway";60;2
"Unit";"Observer";"Robotics Facility";62;1
"Unit";"Stalker";"Gateway";64;2
"Building";"Pylon";NA;68;0
"Upgrade";"Charge";"TwilightCouncil";68;0
"Unit";"Immortal";"Robotics Facility";70;4
"Upgrade";"ProtossGroundWeaponsLevel1";"Forge";74;0
"Unit";"Sentry";"Gateway";76;2
"Building";"Gateway";NA;80;0
"Building";"Gateway";NA;80;0
"Building";"Gateway";NA;80;0
"Building";"Gateway";NA;80;0
"Building";"Gateway";NA;80;0
"Unit";"Immortal";"Robotics Facility";83;4
"Building";"Pylon";NA;87;0
"Unit";"Stalker";"Gateway";90;2
"Unit";"Stalker";"Gateway";92;2
"Unit";"Stalker";"Gateway";94;2
"Building";"Pylon";NA;96;0
"Building";"Pylon";NA;96;0
"Unit";"Immortal";"Robotics Facility";96;4
"Unit";"Zealot";"Gateway";100;2
"Unit";"Zealot";"Gateway";102;2
"Unit";"Zealot";"Gateway";104;2
"Unit";"Zealot";"Gateway";106;2
"Unit";"Zealot";"Gateway";108;2
"Unit";"Zealot";"Gateway";110;2
"Unit";"Zealot";"Gateway";112;2
"Unit";"Zealot";"Gateway";114;2
"Building";"Pylon";NA;116;0
"Building";"Pylon";NA;116;0
"Unit";"Zealot";"Gateway";116;2
"Unit";"Zealot";"Gateway";118;2
"Unit";"Zealot";"Gateway";120;2
"Unit";"Zealot";"Gateway";122;2
"Unit";"Zealot";"Gateway";124;2
"Unit";"Zealot";"Gateway";126;2
"Unit";"Zealot";"Gateway";128;2
"Unit";"Zealot";"Gateway";130;2
"Building";"Pylon";NA;132;0
"Building";"TemplarArchive";NA;132;0
"Unit";"Stalker";"Gateway";132;2
"Unit";"Stalker";"Gateway";134;2
"Building";"Pylon";NA;136;0
"Building";"Pylon";NA;136;0
"Unit";"Stalker";"Gateway";136;2
"Unit";"Stalker";"Gateway";138;2
"Unit";"Stalker";"Gateway";140;2
"Unit";"Stalker";"Gateway";142;2
"Unit";"Stalker";"Gateway";144;2
"Unit";"Zealot";"Gateway";146;2
"Unit";"Zealot";"Gateway";148;2
"Unit";"Zealot";"Gateway";150;2
"Unit";"Zealot";"Gateway";152;2
"Unit";"Zealot";"Gateway";154;2
"Unit";"Zealot";"Gateway";156;2
"Building";"HighTemplar";NA;158;0
"Building";"HighTemplar";NA;158;0
"Building";"HighTemplar";NA;158;0
"Building";"HighTemplar";NA;158;0
"Unit";"Zealot";"Gateway";158;2
"Building";"Assimilator";NA;160;0
"Building";"Assimilator";NA;160;0
"Upgrade";"ProtossGroundWeaponsLevel2";"Forge";163;0
"Unit";"Zealot";"Gateway";163;2
"Unit";"Zealot";"Gateway";165;2
"Unit";"Zealot";"Gateway";167;2
"Unit";"Zealot";"Gateway";169;2
"Building";"Nexus";NA;171;0
"Unit";"Zealot";"Gateway";171;2
"Unit";"Zealot";"Gateway";173;2
"Unit";"Zealot";"Gateway";175;2
"Unit";"Zealot";"Gateway";177;2
"Building";"Pylon";NA;179;0
"Building";"Pylon";NA;179;0
"Unit";"Zealot";"Gateway";179;2
"Unit";"Zealot";"Gateway";181;2
"Unit";"Zealot";"Gateway";183;2
"Unit";"Zealot";"Gateway";185;2
"Unit";"Zealot";"Gateway";187;2
"Building";"Pylon";NA;189;0
"Building";"CyberneticsCore";NA;189;0
"Unit";"Zealot";"Gateway";192;2
"Building";"HighTemplar";NA;194;0
"Building";"HighTemplar";NA;194;0
"Building";"HighTemplar";NA;194;0
"Building";"HighTemplar";NA;194;0
"Building";"HighTemplar";NA;194;0
"Building";"HighTemplar";NA;194;0
"Unit";"Zealot";"Gateway";194;2
"Unit";"Archon";"High Templar";196;0
"Unit";"Archon";"High Templar";196;0
"Unit";"Archon";"High Templar";196;0
"Unit";"Zealot";"Gateway";199;2
"Unit";"Zealot";"Gateway";201;2
"Unit";"Stalker";"Gateway";203;2
"Unit";"Stalker";"Gateway";205;2
"Building";"HighTemplar";NA;207;0
"Building";"HighTemplar";NA;207;0
"Building";"RoboticsFacility";NA;207;0
"Unit";"Zealot";"Gateway";207;2
"Unit";"Zealot";"Gateway";209;2
"Unit";"Zealot";"Gateway";211;2
"Unit";"Zealot";"Gateway";213;2
"Unit";"Zealot";"Gateway";215;2
"Unit";"Zealot";"Gateway";217;2
"Building";"Gateway";NA;219;0
"Building";"Gateway";NA;219;0
"Building";"Nexus";NA;219;0
"Upgrade";"ProtossShieldsLevel1";"Forge";219;0
"Unit";"Zealot";"Gateway";219;2
"Unit";"Zealot";"Gateway";221;2
"Unit";"Zealot";"Gateway";223;2
"Unit";"Zealot";"Gateway";225;2
"Unit";"Zealot";"Gateway";227;2
"Unit";"Zealot";"Gateway";229;2
"Unit";"Zealot";"Gateway";231;2
"Unit";"Zealot";"Gateway";233;2
"Building";"Pylon";NA;235;0
"Building";"Pylon";NA;235;0
"Building";"HighTemplar";NA;235;0
"Building";"HighTemplar";NA;235;0
"Building";"HighTemplar";NA;235;0
"Building";"HighTemplar";NA;235;0
"Building";"HighTemplar";NA;235;0
"Building";"HighTemplar";NA;235;0
"Unit";"Zealot";"Gateway";235;2
"Unit";"Zealot";"Gateway";237;2
"Building";"RoboticsFacility";NA;239;0
"Building";"Pylon";NA;239;0
"Building";"Pylon";NA;239;0
"Building";"Pylon";NA;239;0
"Building";"Pylon";NA;239;0
"Building";"Pylon";NA;239;0
"Building";"HighTemplar";NA;239;0
"Building";"HighTemplar";NA;239;0
"Building";"HighTemplar";NA;239;0
"Building";"HighTemplar";NA;239;0
"Unit";"Zealot";"Gateway";239;2
"Unit";"Zealot";"Gateway";241;2
"Unit";"Zealot";"Gateway";243;2
"Unit";"Zealot";"Gateway";245;2
"Unit";"Zealot";"Gateway";247;2
"Unit";"Zealot";"Gateway";249;2
"Unit";"Immortal";"Robotics Facility";251;4
"Unit";"Zealot";"Gateway";255;2
"Unit";"Zealot";"Gateway";257;2
"Unit";"Zealot";"Gateway";259;2
"Unit";"Zealot";"Gateway";261;2
"Unit";"Zealot";"Gateway";263;2
"Unit";"Zealot";"Gateway";265;2
"Unit";"Zealot";"Gateway";267;2
"Unit";"Zealot";"Gateway";269;2
"Unit";"Zealot";"Gateway";271;2
"Unit";"Zealot";"Gateway";273;2
"Unit";"Immortal";"Robotics Facility";275;4
"Unit";"Archon";"High Templar";279;0
"Unit";"Archon";"High Templar";279;0
"Unit";"Stalker";"Gateway";279;2
"Unit";"Stalker";"Gateway";281;2
"Unit";"Stalker";"Gateway";283;2
"Unit";"Zealot";"Gateway";285;2
"Unit";"Zealot";"Gateway";287;2
"Unit";"Zealot";"Gateway";289;2
"Building";"HighTemplar";NA;291;0
"Building";"HighTemplar";NA;291;0
"Building";"HighTemplar";NA;291;0
"Building";"HighTemplar";NA;291;0
"Building";"Pylon";NA;291;0
"Unit";"Sentry";"Gateway";291;2
"Unit";"Zealot";"Gateway";293;2
"Unit";"Zealot";"Gateway";295;2
"Unit";"Zealot";"Gateway";297;2
"Unit";"Zealot";"Gateway";299;2
"Unit";"Zealot";"Gateway";301;2
"Building";"HighTemplar";NA;303;0
"Building";"HighTemplar";NA;303;0
"Unit";"Zealot";"Gateway";303;2
"Unit";"Zealot";"Gateway";305;2
"Unit";"Zealot";"Gateway";307;2
"Unit";"Zealot";"Gateway";309;2
"Unit";"Stalker";"Gateway";311;2
"Unit";"Stalker";"Gateway";313;2
"Unit";"Stalker";"Gateway";315;2
"Unit";"Zealot";"Gateway";317;2
"Unit";"Observer";"Robotics Facility";319;1
"Unit";"Zealot";"Gateway";320;2
"Unit";"Zealot";"Gateway";322;2
"Unit";"Zealot";"Gateway";324;2
"Unit";"Zealot";"Gateway";326;2
"Unit";"Zealot";"Gateway";328;2
"Unit";"Zealot";"Gateway";330;2
"Unit";"Zealot";"Gateway";332;2
"Unit";"Zealot";"Gateway";334;2
"Unit";"Zealot";"Gateway";336;2
"Unit";"Zealot";"Gateway";338;2
"Upgrade";"SprayProtoss";NA;340;0
"Upgrade";"SprayProtoss";NA;340;0
"Upgrade";"WarpGateResearch";NA;340;0
"Upgrade";"BlinkTech";NA;340;0
"Upgrade";"SprayProtoss";NA;340;0
"Upgrade";"SprayProtoss";NA;340;0
"Upgrade";"ProtossGroundArmorsLevel1";NA;340;0
"Upgrade";"SprayProtoss";NA;340;0
"Upgrade";"PsiStormTech";NA;340;0
"Upgrade";"SprayProtoss";NA;340;0
"Upgrade";"ProtossGroundArmorsLevel2";NA;340;0
"Upgrade";"SprayProtoss";NA;340;0
"Upgrade";"SprayProtoss";NA;340;0
"Upgrade";"ProtossGroundArmorsLevel3";NA;340;0
