"type";"unit_name";"on_building";"total_supply";"supply"
"Building";"Pylon";NA;13;0
"Building";"Assimilator";NA;16;0
"Building";"Gateway";NA;15;0
"Building";"Assimilator";NA;20;0
"Building";"CyberneticsCore";NA;20;0
"Building";"Pylon";NA;21;0
"Unit";"Stalker";"Gateway";22;2
"Building";"Nexus";NA;19;0
"Building";"RoboticsFacility";NA;23;0
"Unit";"Stalker";"Gateway";28;2
"Unit";"Observer";"Robotics Facility";32;1
"Building";"Gateway";NA;31;0
"Unit";"Stalker";"Gateway";36;2
"Unit";"Observer";"Robotics Facility";39;1
"Building";"Pylon";NA;41;0
"Building";"Gateway";NA;33;0
"Building";"ShieldBattery";NA;41;0
"Unit";"Sentry";"Gateway";47;2
"Building";"Pylon";NA;45;0
"Building";"Pylon";NA;46;0
"Building";"TwilightCouncil";NA;42;0
"Unit";"Stalker";"Gateway";50;2
"Unit";"Stalker";"Gateway";50;2
"Unit";"Observer";"Robotics Facility";48;1
"Building";"Assimilator";NA;63;0
"Unit";"Immortal";"Robotics Facility";59;4
"Building";"Pylon";NA;63;0
"Building";"Assimilator";NA;63;0
"Building";"Pylon";NA;64;0
"Building";"Forge";NA;62;0
"Building";"Forge";NA;62;0
"Building";"Nexus";NA;61;0
"Upgrade";"Charge";"TwilightCouncil";62;0
"Building";"Gateway";NA;70;0
"Building";"Gateway";NA;70;0
"Building";"Gateway";NA;70;0
"Building";"Gateway";NA;70;0
"Building";"Pylon";NA;78;0
"Building";"Pylon";NA;80;0
"Unit";"Immortal";"Robotics Facility";74;4
"Building";"Pylon";NA;80;0
"Building";"Gateway";NA;74;0
"Building";"Gateway";NA;74;0
"Building";"TemplarArchive";NA;78;0
"Building";"Assimilator";NA;83;0
"Building";"Assimilator";NA;87;0
"Upgrade";"ProtossGroundWeaponsLevel1";"Forge";71;0
"Upgrade";"ProtossGroundArmorsLevel1";"Forge";72;0
"Building";"HighTemplar";NA;89;0
"Building";"HighTemplar";NA;89;0
"Unit";"Zealot";"Gateway";89;2
"Unit";"Zealot";"Gateway";89;2
"Unit";"Zealot";"Gateway";89;2
"Unit";"Zealot";"Gateway";89;2
"Unit";"Zealot";"Gateway";89;2
"Unit";"Zealot";"Gateway";102;2
"Unit";"Zealot";"Gateway";102;2
"Unit";"Immortal";"Robotics Facility";89;4
"Unit";"Zealot";"Gateway";106;2
"Unit";"Zealot";"Gateway";106;2
"Unit";"Zealot";"Gateway";106;2
"Unit";"Zealot";"Gateway";106;2
"Unit";"Zealot";"Gateway";106;2
"Building";"Pylon";NA;120;0
"Unit";"Zealot";"Gateway";120;2
"Unit";"Zealot";"Gateway";120;2
"Unit";"Zealot";"Gateway";120;2
"Unit";"Zealot";"Gateway";120;2
"Unit";"Zealot";"Gateway";120;2
"Unit";"Zealot";"Gateway";120;2
"Building";"HighTemplar";NA;135;0
"Building";"HighTemplar";NA;135;0
"Building";"HighTemplar";NA;135;0
"Building";"HighTemplar";NA;135;0
"Building";"HighTemplar";NA;135;0
"Building";"HighTemplar";NA;135;0
"Building";"HighTemplar";NA;135;0
"Building";"HighTemplar";NA;135;0
"Unit";"Zealot";"Gateway";135;2
"Building";"Pylon";NA;135;0
"Building";"Pylon";NA;135;0
"Unit";"Sentry";"Gateway";139;2
"Building";"Assimilator";NA;137;0
"Building";"Pylon";NA;139;0
"Unit";"Zealot";"Gateway";141;2
"Unit";"Zealot";"Gateway";141;2
"Unit";"Zealot";"Gateway";141;2
"Unit";"Zealot";"Gateway";141;2
"Unit";"Zealot";"Gateway";141;2
"Unit";"Zealot";"Gateway";141;2
"Unit";"Zealot";"Gateway";141;2
"Unit";"Zealot";"Gateway";141;2
"Upgrade";"ProtossGroundArmorsLevel2";"Forge";120;0
"Building";"Pylon";NA;139;0
"Building";"Pylon";NA;141;0
"Building";"Assimilator";NA;139;0
"Upgrade";"ProtossGroundWeaponsLevel2";"Forge";120;0
"Building";"Pylon";NA;141;0
"Building";"Pylon";NA;141;0
"Building";"Nexus";NA;132;0
"Building";"HighTemplar";NA;157;0
"Unit";"Archon";"High Templar";157;0
"Unit";"Immortal";"Robotics Facility";139;4
"Unit";"Zealot";"Gateway";157;2
"Unit";"Zealot";"Gateway";157;2
"Unit";"Zealot";"Gateway";157;2
"Unit";"Zealot";"Gateway";157;2
"Unit";"Zealot";"Gateway";157;2
"Unit";"Zealot";"Gateway";157;2
"Unit";"Zealot";"Gateway";157;2
"Unit";"Archon";"High Templar";175;0
"Unit";"Archon";"High Templar";175;0
"Unit";"Immortal";"Robotics Facility";175;4
"Unit";"Archon";"High Templar";179;0
"Unit";"Zealot";"Gateway";179;2
"Unit";"Zealot";"Gateway";179;2
"Unit";"Zealot";"Gateway";179;2
"Unit";"Zealot";"Gateway";179;2
"Unit";"Zealot";"Gateway";179;2
"Building";"Gateway";NA;175;0
"Building";"Gateway";NA;175;0
"Unit";"Stalker";"Gateway";189;2
"Unit";"Stalker";"Gateway";189;2
"Building";"Gateway";NA;175;0
"Building";"Gateway";NA;175;0
"Unit";"Stalker";"Gateway";193;2
"Unit";"Stalker";"Gateway";193;2
"Unit";"Stalker";"Gateway";193;2
"Unit";"Stalker";"Gateway";193;2
"Unit";"Stalker";"Gateway";193;2
"Unit";"Stalker";"Gateway";193;2
"Building";"HighTemplar";NA;205;0
"Building";"HighTemplar";NA;205;0
"Building";"HighTemplar";NA;205;0
"Building";"HighTemplar";NA;205;0
"Building";"HighTemplar";NA;205;0
"Unit";"Immortal";"Robotics Facility";193;4
"Unit";"Zealot";"Gateway";206;2
"Unit";"Zealot";"Gateway";206;2
"Unit";"Zealot";"Gateway";206;2
"Unit";"Zealot";"Gateway";206;2
"Unit";"Zealot";"Gateway";206;2
"Unit";"Zealot";"Gateway";206;2
"Building";"Pylon";NA;222;0
"Upgrade";"ProtossGroundWeaponsLevel3";"Forge";175;0
"Upgrade";"ProtossGroundArmorsLevel3";"Forge";175;0
"Unit";"Immortal";"Robotics Facility";206;4
"Unit";"Archon";"High Templar";222;0
"Unit";"Archon";"High Templar";222;0
"Building";"HighTemplar";NA;226;0
"Building";"HighTemplar";NA;226;0
"Building";"HighTemplar";NA;226;0
"Building";"HighTemplar";NA;226;0
"Building";"HighTemplar";NA;226;0
"Building";"HighTemplar";NA;226;0
"Building";"HighTemplar";NA;226;0
"Building";"HighTemplar";NA;226;0
"Building";"HighTemplar";NA;226;0
"Building";"HighTemplar";NA;226;0
"Building";"RoboticsBay";NA;222;0
"Building";"RoboticsFacility";NA;222;0
"Unit";"Archon";"High Templar";226;0
"Unit";"Archon";"High Templar";226;0
"Unit";"Archon";"High Templar";226;0
"Building";"HighTemplar";NA;226;0
"Building";"HighTemplar";NA;226;0
"Unit";"Zealot";"Gateway";226;2
"Unit";"Zealot";"Gateway";226;2
"Unit";"Zealot";"Gateway";226;2
"Unit";"Zealot";"Gateway";226;2
"Unit";"Zealot";"Gateway";226;2
"Building";"Pylon";NA;226;0
"Unit";"Zealot";"Gateway";236;2
"Unit";"Zealot";"Gateway";236;2
"Unit";"Zealot";"Gateway";236;2
"Unit";"Zealot";"Gateway";236;2
"Unit";"Zealot";"Gateway";236;2
"Building";"Pylon";NA;236;0
"Building";"Pylon";NA;236;0
"Unit";"Colossus";"Robotics Facility";226;6
"Unit";"Colossus";"Robotics Facility";226;6
"Building";"Assimilator";NA;236;0
"Building";"Assimilator";NA;236;0
"Unit";"Zealot";"Gateway";258;2
"Unit";"Zealot";"Gateway";258;2
"Unit";"Zealot";"Gateway";258;2
"Unit";"Zealot";"Gateway";258;2
"Unit";"Zealot";"Gateway";258;2
"Unit";"Zealot";"Gateway";258;2
"Unit";"Zealot";"Gateway";258;2
"Building";"Nexus";NA;226;0
"Building";"Nexus";NA;236;0
"Unit";"Zealot";"Gateway";272;2
"Unit";"Zealot";"Gateway";272;2
"Unit";"Zealot";"Gateway";272;2
"Unit";"Zealot";"Gateway";272;2
"Unit";"Zealot";"Gateway";272;2
"Unit";"Zealot";"Gateway";272;2
"Unit";"Zealot";"Gateway";272;2
"Unit";"Zealot";"Gateway";272;2
"Unit";"Zealot";"Gateway";272;2
"Unit";"Zealot";"Gateway";272;2
