"type";"unit_name";"on_building";"total_supply";"supply"
"Building";"Pylon";NA;13;0
"Building";"Assimilator";NA;16;0
"Building";"Gateway";NA;15;0
"Building";"Assimilator";NA;20;0
"Building";"CyberneticsCore";NA;20;0
"Building";"Pylon";NA;21;0
"Building";"Nexus";NA;19;0
"Unit";"Adept";"Gateway";22;2
"Unit";"Adept";"Gateway";24;2
"Building";"RoboticsFacility";NA;24;0
"Unit";"Adept";"Gateway";31;2
"Building";"Pylon";NA;42;0
"Building";"Gateway";NA;37;0
"Building";"Gateway";NA;40;0
"Building";"Pylon";NA;45;0
"Building";"ShieldBattery";NA;44;0
"Building";"Assimilator";NA;46;0
"Building";"Assimilator";NA;46;0
"Unit";"Stalker";"Gateway";47;2
"Unit";"Stalker";"Gateway";48;2
"Building";"Pylon";NA;46;0
"Unit";"Stalker";"Gateway";48;2
"Unit";"Immortal";"Robotics Facility";44;4
"Unit";"Stalker";"Gateway";58;2
"Unit";"Stalker";"Gateway";58;2
"Unit";"Stalker";"Gateway";58;2
"Unit";"Immortal";"Robotics Facility";54;4
"Unit";"Stalker";"Gateway";72;2
"Unit";"Sentry";"Gateway";72;2
"Unit";"Sentry";"Gateway";72;2
"Building";"Forge";NA;64;0
"Building";"RoboticsBay";NA;64;0
"Building";"Pylon";NA;79;0
"Unit";"Observer";"Robotics Facility";79;1
"Building";"Pylon";NA;81;0
"Building";"Pylon";NA;82;0
"Building";"ShieldBattery";NA;81;0
"Building";"Pylon";NA;84;0
"Unit";"Stalker";"Gateway";85;2
"Unit";"Stalker";"Gateway";85;2
"Unit";"Stalker";"Gateway";85;2
"Building";"Nexus";NA;79;0
"Unit";"Colossus";"Robotics Facility";84;6
"Upgrade";"ProtossGroundArmorsLevel1";"Forge";79;0
"Unit";"Phoenix";"Stargate";93;2
"Building";"Forge";NA;91;0
"Building";"TwilightCouncil";NA;91;0
"Unit";"Sentry";"Gateway";106;2
"Unit";"Stalker";"Gateway";106;2
"Upgrade";"ExtendedThermalLance";"RoboticsBay";85;0
"Building";"Gateway";NA;93;0
"Building";"Gateway";NA;94;0
"Building";"Pylon";NA;110;0
"Building";"Gateway";NA;96;0
"Building";"Gateway";NA;96;0
"Unit";"Colossus";"Robotics Facility";96;6
"Unit";"Stalker";"Gateway";114;2
"Unit";"Stalker";"Gateway";114;2
"Unit";"Stalker";"Gateway";114;2
"Building";"Assimilator";NA;113;0
"Building";"Assimilator";NA;114;0
"Unit";"Zealot";"Gateway";126;2
"Unit";"Zealot";"Gateway";126;2
"Unit";"Zealot";"Gateway";126;2
"Unit";"Zealot";"Gateway";126;2
"Building";"Gateway";NA;113;0
"Building";"Gateway";NA;113;0
"Unit";"Zealot";"Gateway";134;2
"Upgrade";"ProtossGroundWeaponsLevel1";"Forge";111;0
"Upgrade";"Charge";"TwilightCouncil";113;0
"Unit";"Zealot";"Gateway";136;2
"Unit";"Zealot";"Gateway";136;2
"Unit";"Zealot";"Gateway";136;2
"Unit";"Zealot";"Gateway";136;2
"Unit";"Zealot";"Gateway";147;2
"Unit";"Zealot";"Gateway";147;2
"Unit";"Zealot";"Gateway";147;2
"Unit";"Zealot";"Gateway";147;2
"Unit";"Zealot";"Gateway";147;2
"Unit";"Zealot";"Gateway";147;2
"Upgrade";"ProtossGroundArmorsLevel2";"Forge";114;0
"Building";"Pylon";NA;160;0
"Building";"Pylon";NA;160;0
"Unit";"Stalker";"Gateway";160;2
"Unit";"Stalker";"Gateway";160;2
"Unit";"Stalker";"Gateway";160;2
"Unit";"Phoenix";"Stargate";160;2
"Building";"TemplarArchive";NA;160;0
"Building";"Pylon";NA;160;0
"Unit";"Stalker";"Gateway";169;2
"Unit";"Stalker";"Gateway";169;2
"Unit";"Stalker";"Gateway";169;2
"Building";"PhotonCannon";NA;160;0
"Building";"PhotonCannon";NA;160;0
"Building";"PhotonCannon";NA;160;0
"Building";"RoboticsFacility";NA;160;0
"Building";"PhotonCannon";NA;160;0
"Building";"ShieldBattery";NA;160;0
"Building";"Pylon";NA;167;0
"Building";"RoboticsFacility";NA;160;0
"Building";"Pylon";NA;169;0
"Building";"Nexus";NA;160;0
"Building";"HighTemplar";NA;175;0
"Building";"HighTemplar";NA;175;0
"Building";"HighTemplar";NA;175;0
"Building";"TemplarArchive";NA;167;0
"Building";"HighTemplar";NA;175;0
"Building";"HighTemplar";NA;175;0
"Unit";"Zealot";"Gateway";177;2
"Unit";"Zealot";"Gateway";177;2
"Unit";"Zealot";"Gateway";177;2
"Unit";"Zealot";"Gateway";177;2
"Upgrade";"ProtossGroundWeaponsLevel2";"Forge";159;0
"Unit";"Immortal";"Robotics Facility";175;4
"Unit";"Immortal";"Robotics Facility";175;4
"Unit";"Archon";"High Templar";189;0
"Unit";"Archon";"High Templar";189;0
"Unit";"Zealot";"Gateway";197;2
"Unit";"Zealot";"Gateway";197;2
"Unit";"Zealot";"Gateway";197;2
"Unit";"Zealot";"Gateway";197;2
"Unit";"Zealot";"Gateway";197;2
"Unit";"Zealot";"Gateway";207;2
"Unit";"Zealot";"Gateway";207;2
"Unit";"Zealot";"Gateway";207;2
"Unit";"Zealot";"Gateway";207;2
"Unit";"Zealot";"Gateway";207;2
"Unit";"Zealot";"Gateway";207;2
"Unit";"Zealot";"Gateway";207;2
"Unit";"Zealot";"Gateway";207;2
"Unit";"Stalker";"Gateway";223;2
"Building";"HighTemplar";NA;225;0
"Building";"HighTemplar";NA;225;0
"Building";"HighTemplar";NA;225;0
"Building";"HighTemplar";NA;225;0
"Building";"HighTemplar";NA;225;0
"Upgrade";"ProtossGroundArmorsLevel3";"Forge";169;0
"Unit";"Zealot";"Gateway";225;2
"Unit";"Zealot";"Gateway";225;2
"Unit";"Zealot";"Gateway";225;2
"Building";"Assimilator";NA;225;0
"Building";"Assimilator";NA;225;0
"Unit";"Zealot";"Gateway";234;2
"Unit";"Zealot";"Gateway";234;2
"Unit";"Zealot";"Gateway";234;2
"Unit";"Colossus";"Robotics Facility";207;6
"Unit";"Archon";"High Templar";234;0
"Unit";"Archon";"High Templar";234;0
"Unit";"Zealot";"Gateway";246;2
"Unit";"Zealot";"Gateway";246;2
"Unit";"Zealot";"Gateway";246;2
"Unit";"Colossus";"Robotics Facility";223;6
"Unit";"Zealot";"Gateway";258;2
"Unit";"Zealot";"Gateway";258;2
"Unit";"Zealot";"Gateway";258;2
"Unit";"Zealot";"Gateway";264;2
"Unit";"Zealot";"Gateway";264;2
"Building";"Gateway";NA;231;0
"Building";"HighTemplar";NA;268;0
"Building";"HighTemplar";NA;268;0
"Unit";"Stalker";"Gateway";268;2
"Unit";"Stalker";"Gateway";268;2
"Unit";"Stalker";"Gateway";268;2
"Unit";"Stalker";"Gateway";268;2
"Unit";"Colossus";"Robotics Facility";234;6
"Unit";"Zealot";"Gateway";283;2
"Unit";"Zealot";"Gateway";283;2
"Unit";"Zealot";"Gateway";283;2
"Unit";"Colossus";"Robotics Facility";252;6
"Building";"HighTemplar";NA;289;0
"Building";"HighTemplar";NA;289;0
"Unit";"Stalker";"Gateway";295;2
"Unit";"Stalker";"Gateway";295;2
"Unit";"Stalker";"Gateway";295;2
"Unit";"Stalker";"Gateway";295;2
"Building";"ShieldBattery";NA;289;0
"Building";"ShieldBattery";NA;289;0
"Unit";"Zealot";"Gateway";303;2
"Unit";"Zealot";"Gateway";303;2
"Unit";"Zealot";"Gateway";303;2
"Unit";"Immortal";"Robotics Facility";289;4
"Unit";"Zealot";"Gateway";313;2
"Unit";"Zealot";"Gateway";313;2
"Unit";"Immortal";"Robotics Facility";295;4
"Unit";"Zealot";"Gateway";313;2
"Unit";"Zealot";"Gateway";313;2
"Upgrade";"ProtossGroundWeaponsLevel3";"Forge";246;0
"Unit";"Stalker";"Gateway";325;2
"Unit";"Stalker";"Gateway";325;2
"Unit";"Stalker";"Gateway";325;2
"Unit";"Stalker";"Gateway";325;2
"Unit";"Immortal";"Robotics Facility";309;4
"Building";"Pylon";NA;325;0
"Building";"Pylon";NA;325;0
"Building";"Pylon";NA;325;0
"Building";"Pylon";NA;325;0
"Building";"Pylon";NA;325;0
"Unit";"Archon";"High Templar";337;0
"Unit";"Zealot";"Gateway";337;2
"Unit";"Zealot";"Gateway";337;2
"Unit";"Zealot";"Gateway";337;2
"Unit";"Zealot";"Gateway";337;2
"Unit";"Zealot";"Gateway";337;2
"Unit";"Zealot";"Gateway";337;2
"Unit";"Zealot";"Gateway";349;2
"Unit";"Zealot";"Gateway";349;2
"Unit";"Zealot";"Gateway";349;2
"Unit";"Zealot";"Gateway";349;2
"Building";"HighTemplar";NA;357;0
"Building";"HighTemplar";NA;357;0
"Building";"HighTemplar";NA;357;0
"Building";"HighTemplar";NA;357;0
"Building";"HighTemplar";NA;357;0
"Unit";"Zealot";"Gateway";357;2
"Unit";"Zealot";"Gateway";357;2
"Unit";"Zealot";"Gateway";357;2
"Unit";"Zealot";"Gateway";357;2
"Unit";"Zealot";"Gateway";357;2
