"type";"unit_name";"on_building";"total_supply";"supply"
"Building";"Pylon";NA;13;0
"Building";"Assimilator";NA;16;0
"Building";"Gateway";NA;14;0
"Building";"Pylon";NA;17;0
"Unit";"Zealot";"Gateway";18;2
"Building";"CyberneticsCore";NA;19;0
"Unit";"Stalker";"Gateway";23;2
"Building";"Pylon";NA;25;0
"Unit";"Stalker";"Gateway";27;2
"Building";"Assimilator";NA;27;0
"Building";"Nexus";NA;25;0
"Building";"TwilightCouncil";NA;31;0
