"type";"unit_name";"on_building";"total_supply";"supply"
"Building";"Pylon";NA;13;0
"Building";"Assimilator";NA;16;0
"Building";"Gateway";NA;15;0
"Building";"Assimilator";NA;20;0
"Building";"CyberneticsCore";NA;20;0
"Building";"Pylon";NA;21;0
"Unit";"Stalker";"Gateway";22;2
"Building";"Nexus";NA;20;0
"Unit";"Stalker";"Gateway";26;2
"Building";"TwilightCouncil";NA;24;0
"Building";"Pylon";NA;28;0
"Unit";"Stalker";"Gateway";35;2
"Building";"Assimilator";NA;41;0
"Building";"Gateway";NA;37;0
"Building";"Gateway";NA;37;0
"Building";"Pylon";NA;47;0
"Building";"Pylon";NA;47;0
"Building";"RoboticsFacility";NA;41;0
"Unit";"Stalker";"Gateway";47;2
"Unit";"Stalker";"Gateway";47;2
"Unit";"Stalker";"Gateway";47;2
"Building";"Pylon";NA;47;0
"Unit";"Observer";"Robotics Facility";47;1
"Unit";"Stalker";"Gateway";60;2
"Unit";"Stalker";"Gateway";60;2
"Unit";"Stalker";"Gateway";60;2
"Building";"Pylon";NA;58;0
"Building";"Forge";NA;55;0
"Building";"Forge";NA;55;0
"Unit";"Observer";"Robotics Facility";58;1
"Unit";"Observer";"Robotics Facility";69;1
"Building";"Nexus";NA;56;0
"Unit";"Sentry";"Gateway";74;2
"Unit";"Sentry";"Gateway";74;2
"Unit";"Sentry";"Gateway";74;2
"Building";"Pylon";NA;72;0
"Upgrade";"Charge";"TwilightCouncil";64;0
"Building";"Gateway";NA;71;0
"Building";"Gateway";NA;71;0
"Building";"Gateway";NA;71;0
"Unit";"Zealot";"Gateway";86;2
"Unit";"Zealot";"Gateway";86;2
"Unit";"Zealot";"Gateway";86;2
"Building";"Gateway";NA;72;0
"Building";"Gateway";NA;72;0
"Upgrade";"ProtossGroundWeaponsLevel1";"Forge";68;0
"Unit";"Zealot";"Gateway";92;2
"Unit";"Zealot";"Gateway";92;2
"Upgrade";"ProtossGroundArmorsLevel1";"Forge";69;0
"Building";"Pylon";NA;96;0
"Building";"Pylon";NA;96;0
"Building";"Pylon";NA;96;0
"Unit";"Zealot";"Gateway";96;2
"Unit";"Zealot";"Gateway";96;2
"Unit";"Zealot";"Gateway";96;2
"Unit";"Zealot";"Gateway";96;2
"Unit";"Zealot";"Gateway";96;2
"Unit";"Zealot";"Gateway";96;2
"Building";"Assimilator";NA;96;0
"Building";"Assimilator";NA;96;0
"Building";"Pylon";NA;96;0
"Unit";"Zealot";"Gateway";116;2
"Unit";"Zealot";"Gateway";116;2
"Unit";"Zealot";"Gateway";116;2
"Unit";"Zealot";"Gateway";116;2
"Building";"Pylon";NA;113;0
"Building";"Pylon";NA;113;0
"Unit";"Zealot";"Gateway";128;2
"Unit";"Zealot";"Gateway";128;2
"Unit";"Zealot";"Gateway";128;2
"Unit";"Zealot";"Gateway";128;2
"Unit";"Zealot";"Gateway";129;2
"Building";"Gateway";NA;112;0
"Building";"Gateway";NA;112;0
"Building";"Pylon";NA;127;0
"Unit";"Zealot";"Gateway";140;2
"Unit";"Stalker";"Gateway";145;2
"Unit";"Stalker";"Gateway";145;2
"Unit";"Stalker";"Gateway";145;2
"Unit";"Stalker";"Gateway";149;2
"Building";"Assimilator";NA;145;0
"Unit";"Zealot";"Gateway";153;2
"Unit";"Zealot";"Gateway";153;2
"Unit";"Zealot";"Gateway";153;2
"Unit";"Zealot";"Gateway";153;2
"Unit";"Zealot";"Gateway";153;2
"Unit";"Zealot";"Gateway";153;2
"Unit";"Zealot";"Gateway";153;2
"Building";"TemplarArchive";NA;143;0
"Unit";"Zealot";"Gateway";157;2
"Unit";"Zealot";"Gateway";167;2
"Upgrade";"ProtossGroundWeaponsLevel2";"Forge";116;0
"Upgrade";"ProtossGroundArmorsLevel2";"Forge";116;0
"Building";"HighTemplar";NA;174;0
"Building";"HighTemplar";NA;174;0
"Building";"HighTemplar";NA;174;0
"Building";"HighTemplar";NA;174;0
"Building";"HighTemplar";NA;174;0
"Building";"HighTemplar";NA;174;0
"Unit";"Sentry";"Gateway";181;2
"Unit";"Sentry";"Gateway";181;2
"Unit";"Zealot";"Gateway";181;2
"Unit";"Zealot";"Gateway";181;2
"Building";"Pylon";NA;178;0
"Building";"Pylon";NA;178;0
"Unit";"Zealot";"Gateway";189;2
"Unit";"Zealot";"Gateway";189;2
"Unit";"Zealot";"Gateway";189;2
"Unit";"Zealot";"Gateway";189;2
"Unit";"Zealot";"Gateway";189;2
"Unit";"Zealot";"Gateway";189;2
"Unit";"Zealot";"Gateway";195;2
"Building";"Pylon";NA;189;0
"Unit";"Zealot";"Gateway";203;2
"Unit";"Zealot";"Gateway";203;2
"Unit";"Stalker";"Gateway";207;2
"Unit";"Stalker";"Gateway";207;2
"Unit";"Stalker";"Gateway";207;2
"Unit";"Stalker";"Gateway";207;2
"Unit";"Stalker";"Gateway";207;2
"Building";"HighTemplar";NA;207;0
"Building";"HighTemplar";NA;207;0
"Unit";"Stalker";"Gateway";217;2
"Unit";"Archon";"High Templar";219;0
"Unit";"Stalker";"Gateway";219;2
"Unit";"Stalker";"Gateway";219;2
"Building";"Nexus";NA;189;0
"Unit";"Archon";"High Templar";223;0
"Unit";"Stalker";"Gateway";223;2
"Unit";"Stalker";"Gateway";223;2
"Unit";"Stalker";"Gateway";223;2
"Unit";"Stalker";"Gateway";223;2
"Unit";"Stalker";"Gateway";223;2
"Unit";"Stalker";"Gateway";223;2
"Unit";"Stalker";"Gateway";223;2
"Unit";"Stalker";"Gateway";223;2
"Unit";"Stalker";"Gateway";223;2
"Unit";"Stalker";"Gateway";223;2
"Upgrade";"ProtossGroundWeaponsLevel3";"Forge";189;0
"Upgrade";"ProtossGroundArmorsLevel3";"Forge";189;0
"Unit";"Zealot";"Gateway";243;2
"Unit";"Zealot";"Gateway";243;2
"Unit";"Zealot";"Gateway";243;2
"Unit";"Zealot";"Gateway";243;2
"Unit";"Zealot";"Gateway";243;2
"Unit";"Zealot";"Gateway";243;2
"Unit";"Zealot";"Gateway";243;2
"Unit";"Zealot";"Gateway";243;2
"Unit";"Zealot";"Gateway";243;2
"Unit";"Zealot";"Gateway";243;2
"Building";"HighTemplar";NA;263;0
"Building";"HighTemplar";NA;263;0
"Building";"HighTemplar";NA;263;0
"Building";"HighTemplar";NA;263;0
"Building";"HighTemplar";NA;263;0
"Building";"HighTemplar";NA;263;0
"Building";"HighTemplar";NA;263;0
"Building";"HighTemplar";NA;263;0
"Building";"HighTemplar";NA;263;0
"Building";"Gateway";NA;263;0
"Building";"Gateway";NA;263;0
"Building";"Gateway";NA;263;0
"Building";"Pylon";NA;263;0
"Building";"HighTemplar";NA;263;0
"Building";"Gateway";NA;263;0
"Building";"Gateway";NA;263;0
"Building";"Gateway";NA;263;0
"Unit";"Archon";"High Templar";263;0
"Unit";"Archon";"High Templar";263;0
"Unit";"Archon";"High Templar";263;0
"Unit";"Archon";"High Templar";263;0
"Unit";"Archon";"High Templar";263;0
"Building";"Gateway";NA;263;0
"Building";"Gateway";NA;263;0
"Building";"Gateway";NA;263;0
"Building";"Gateway";NA;263;0
"Building";"Gateway";NA;263;0
"Building";"Gateway";NA;263;0
"Building";"Pylon";NA;263;0
"Building";"Pylon";NA;263;0
"Building";"Pylon";NA;263;0
"Building";"Pylon";NA;263;0
"Building";"HighTemplar";NA;263;0
"Building";"HighTemplar";NA;263;0
"Building";"HighTemplar";NA;263;0
"Building";"HighTemplar";NA;263;0
"Building";"HighTemplar";NA;263;0
"Building";"HighTemplar";NA;263;0
"Building";"HighTemplar";NA;263;0
"Building";"HighTemplar";NA;263;0
"Building";"HighTemplar";NA;263;0
"Building";"HighTemplar";NA;263;0
"Building";"HighTemplar";NA;263;0
"Unit";"Archon";"High Templar";263;0
"Unit";"Archon";"High Templar";263;0
"Unit";"Zealot";"Gateway";263;2
"Unit";"Archon";"High Templar";263;0
"Unit";"Archon";"High Templar";263;0
"Unit";"Zealot";"Gateway";263;2
"Unit";"Zealot";"Gateway";263;2
"Unit";"Archon";"High Templar";263;0
"Unit";"Archon";"High Templar";263;0
