"type";"unit_name";"on_building";"total_supply";"supply"
"Building";"Pylon";NA;14;0
"Building";"Gateway";NA;15;0
"Building";"Gateway";NA;15;0
"Unit";"Zealot";"Gateway";18;2
"Building";"Pylon";NA;18;0
"Unit";"Zealot";"Gateway";18;2
"Unit";"Zealot";"Gateway";18;2
"Unit";"Zealot";"Gateway";18;2
"Building";"Nexus";NA;18;0
"Building";"Pylon";NA;26;0
"Unit";"Zealot";"Gateway";22;2
"Unit";"Zealot";"Gateway";24;2
"Unit";"Zealot";"Gateway";26;2
"Unit";"Zealot";"Gateway";28;2
