"type";"unit_name";"on_building";"total_supply";"supply"
"Building";"Pylon";NA;13;0
"Building";"Assimilator";NA;16;0
"Building";"Gateway";NA;15;0
"Building";"Assimilator";NA;19;0
"Building";"CyberneticsCore";NA;19;0
"Building";"Pylon";NA;20;0
"Unit";"Adept";"Gateway";21;2
"Building";"Nexus";NA;19;0
"Unit";"Adept";"Gateway";25;2
"Building";"Stargate";NA;22;0
"Unit";"Stalker";"Gateway";27;2
"Unit";"Oracle";"Stargate";30;3
"Unit";"Phoenix";"Stargate";36;2
"Building";"Pylon";NA;41;0
"Building";"Gateway";NA;36;0
"Building";"Gateway";NA;36;0
"Unit";"Phoenix";"Stargate";46;2
"Building";"ShieldBattery";NA;46;0
"Building";"Forge";NA;45;0
"Building";"TwilightCouncil";NA;46;0
"Building";"Pylon";NA;55;0
"Building";"Pylon";NA;55;0
"Unit";"Sentry";"Gateway";57;2
"Unit";"Sentry";"Gateway";57;2
"Unit";"Sentry";"Gateway";57;2
"Building";"OracleStasisTrap";NA;64;0
"Building";"ShieldBattery";NA;55;0
"Building";"Nexus";NA;54;0
"Building";"Assimilator";NA;64;0
"Unit";"Zealot";"Gateway";66;2
"Unit";"Zealot";"Gateway";66;2
"Unit";"Zealot";"Gateway";66;2
"Unit";"Phoenix";"Stargate";64;2
"Building";"Gateway";NA;55;0
"Building";"Pylon";NA;66;0
"Building";"Gateway";NA;57;0
"Building";"Pylon";NA;66;0
"Building";"Gateway";NA;57;0
"Building";"Gateway";NA;57;0
"Building";"Gateway";NA;57;0
"Upgrade";"Charge";"TwilightCouncil";55;0
"Unit";"Zealot";"Gateway";80;2
"Unit";"Zealot";"Gateway";80;2
"Unit";"Zealot";"Gateway";80;2
"Unit";"Zealot";"Gateway";80;2
"Unit";"Zealot";"Gateway";80;2
"Unit";"Phoenix";"Stargate";76;2
"Upgrade";"ProtossGroundArmorsLevel1";"Forge";55;0
"Unit";"Zealot";"Gateway";95;2
"Unit";"Zealot";"Gateway";95;2
"Unit";"Zealot";"Gateway";95;2
"Building";"Pylon";NA;94;0
"Building";"Pylon";NA;94;0
"Unit";"Zealot";"Gateway";102;2
"Unit";"Zealot";"Gateway";102;2
"Unit";"Zealot";"Gateway";102;2
"Unit";"Zealot";"Gateway";102;2
"Unit";"Zealot";"Gateway";110;2
"Unit";"Zealot";"Gateway";110;2
"Unit";"Zealot";"Gateway";110;2
"Unit";"Zealot";"Gateway";110;2
"Unit";"Zealot";"Gateway";118;2
"Unit";"Zealot";"Gateway";118;2
"Unit";"Zealot";"Gateway";119;2
"Unit";"Zealot";"Gateway";119;2
"Unit";"Zealot";"Gateway";120;2
"Unit";"Zealot";"Gateway";120;2
"Unit";"Stalker";"Gateway";135;2
"Unit";"Stalker";"Gateway";135;2
"Unit";"Stalker";"Gateway";135;2
"Unit";"Zealot";"Gateway";141;2
"Unit";"Zealot";"Gateway";141;2
"Unit";"Zealot";"Gateway";141;2
"Unit";"Zealot";"Gateway";141;2
"Unit";"Zealot";"Gateway";141;2
"Building";"Pylon";NA;151;0
"Building";"Nexus";NA;121;0
"Building";"Pylon";NA;154;0
"Unit";"Zealot";"Gateway";154;2
"Unit";"Zealot";"Gateway";154;2
"Unit";"Zealot";"Gateway";154;2
"Unit";"Zealot";"Gateway";154;2
"Unit";"Zealot";"Gateway";154;2
"Unit";"Zealot";"Gateway";154;2
"Unit";"Zealot";"Gateway";154;2
"Unit";"Zealot";"Gateway";154;2
"Unit";"Phoenix";"Stargate";154;2
"Upgrade";"ProtossGroundWeaponsLevel1";"Forge";135;0
"Building";"RoboticsFacility";NA;154;0
"Unit";"Stalker";"Gateway";179;2
"Unit";"Stalker";"Gateway";179;2
"Unit";"Stalker";"Gateway";179;2
"Unit";"Stalker";"Gateway";179;2
"Unit";"Stalker";"Gateway";179;2
"Unit";"Stalker";"Gateway";179;2
"Unit";"Stalker";"Gateway";179;2
"Unit";"Zealot";"Gateway";197;2
"Unit";"Zealot";"Gateway";197;2
"Unit";"Zealot";"Gateway";197;2
"Unit";"Zealot";"Gateway";197;2
"Unit";"Zealot";"Gateway";197;2
"Unit";"Phoenix";"Stargate";193;2
"Building";"Assimilator";NA;195;0
"Building";"Assimilator";NA;195;0
"Building";"Assimilator";NA;195;0
"Building";"Assimilator";NA;196;0
"Building";"Assimilator";NA;197;0
"Building";"TemplarArchive";NA;195;0
"Building";"Pylon";NA;209;0
"Building";"Pylon";NA;210;0
"Building";"Pylon";NA;210;0
"Unit";"Zealot";"Gateway";210;2
"Building";"Forge";NA;209;0
"Building";"Pylon";NA;210;0
"Building";"Pylon";NA;210;0
"Building";"Pylon";NA;210;0
"Building";"Pylon";NA;210;0
"Building";"Pylon";NA;210;0
"Unit";"Zealot";"Gateway";214;2
"Unit";"Zealot";"Gateway";214;2
"Unit";"Zealot";"Gateway";214;2
"Unit";"Zealot";"Gateway";214;2
"Unit";"Zealot";"Gateway";214;2
"Unit";"Zealot";"Gateway";214;2
"Unit";"Zealot";"Gateway";214;2
"Unit";"Zealot";"Gateway";228;2
"Unit";"Immortal";"Robotics Facility";210;4
"Unit";"Zealot";"Gateway";234;2
"Unit";"Zealot";"Gateway";234;2
"Unit";"Zealot";"Gateway";234;2
"Unit";"Zealot";"Gateway";234;2
"Unit";"Zealot";"Gateway";234;2
"Unit";"Zealot";"Gateway";234;2
"Unit";"Zealot";"Gateway";234;2
"Unit";"Zealot";"Gateway";248;2
"Unit";"Zealot";"Gateway";252;2
"Unit";"Zealot";"Gateway";252;2
"Unit";"Zealot";"Gateway";252;2
"Unit";"Zealot";"Gateway";252;2
"Unit";"Zealot";"Gateway";252;2
"Unit";"Zealot";"Gateway";252;2
"Unit";"Zealot";"Gateway";252;2
"Building";"Gateway";NA;228;0
"Building";"Gateway";NA;228;0
"Building";"Gateway";NA;228;0
"Building";"Gateway";NA;228;0
"Unit";"Zealot";"Gateway";266;2
"Building";"HighTemplar";NA;273;0
"Building";"HighTemplar";NA;273;0
"Building";"HighTemplar";NA;273;0
"Building";"HighTemplar";NA;273;0
"Building";"HighTemplar";NA;273;0
"Building";"HighTemplar";NA;273;0
"Building";"HighTemplar";NA;273;0
"Building";"HighTemplar";NA;273;0
"Building";"HighTemplar";NA;274;0
"Building";"HighTemplar";NA;274;0
"Building";"HighTemplar";NA;274;0
"Building";"HighTemplar";NA;274;0
"Unit";"Archon";"High Templar";274;0
"Unit";"Archon";"High Templar";274;0
"Unit";"Archon";"High Templar";274;0
"Unit";"Archon";"High Templar";274;0
"Unit";"Archon";"High Templar";276;0
"Unit";"Archon";"High Templar";276;0
"Upgrade";"ProtossGroundWeaponsLevel2";"Forge";252;0
"Upgrade";"ProtossGroundArmorsLevel2";"Forge";252;0
"Building";"HighTemplar";NA;276;0
"Building";"HighTemplar";NA;276;0
"Building";"HighTemplar";NA;276;0
"Building";"HighTemplar";NA;276;0
"Building";"HighTemplar";NA;276;0
"Unit";"Zealot";"Gateway";276;2
"Unit";"Zealot";"Gateway";276;2
"Unit";"Zealot";"Gateway";276;2
"Unit";"Zealot";"Gateway";276;2
"Unit";"Zealot";"Gateway";276;2
"Unit";"Zealot";"Gateway";276;2
"Unit";"Zealot";"Gateway";276;2
"Building";"Pylon";NA;276;0
"Building";"Pylon";NA;276;0
"Unit";"Stalker";"Gateway";294;2
"Unit";"Stalker";"Gateway";294;2
"Unit";"Stalker";"Gateway";294;2
"Unit";"Stalker";"Gateway";294;2
"Unit";"Stalker";"Gateway";294;2
"Unit";"Stalker";"Gateway";294;2
"Building";"Pylon";NA;294;0
"Unit";"Zealot";"Gateway";308;2
"Unit";"Zealot";"Gateway";308;2
"Unit";"Zealot";"Gateway";308;2
"Unit";"Zealot";"Gateway";308;2
"Unit";"Zealot";"Gateway";308;2
"Unit";"Zealot";"Gateway";308;2
"Unit";"Zealot";"Gateway";308;2
"Unit";"Zealot";"Gateway";322;2
"Unit";"Zealot";"Gateway";322;2
"Unit";"Zealot";"Gateway";322;2
"Unit";"Zealot";"Gateway";322;2
"Unit";"Zealot";"Gateway";322;2
"Unit";"Zealot";"Gateway";322;2
"Unit";"Zealot";"Gateway";322;2
"Unit";"Zealot";"Gateway";322;2
"Building";"Nexus";NA;294;0
