"type";"unit_name";"on_building";"total_supply_lag"
"Building";"Refinery";NA;15
"Building";"Barracks";NA;16
"Unit";"Reaper";"Barracks";19
"Building";"CommandCenter";NA;20
"Building";"Factory";NA;20
"Building";"BarracksReactor";NA;20
"Building";"Refinery";NA;21
"Building";"Starport";NA;23
"Unit";"Hellion";"Factory";23
"Unit";"Hellion";"Factory";25
"Building";"BarracksTechLab";NA;28
"Unit";"Hellion";"Factory";29
"Unit";"Hellion";"Factory";33
"Building";"BarracksTechLab";NA;37
"Unit";"Marine";"Barracks";40
"Unit";"Banshee";"Starport";41
"Building";"CommandCenter";NA;46
"Unit";"Marine";"Barracks";48
"Building";"FactoryReactor";NA;49
"Building";"Barracks";NA;49
"Building";"Barracks";NA;50
"Upgrade";"Stimpack";"TechLab";50
"Unit";"Marine";"Barracks";52
"Unit";"Raven";"Starport";53
"Building";"EngineeringBay";NA;56
"Building";"EngineeringBay";NA;56
"Unit";"Marine";"Barracks";59
"Building";"EngineeringBay";NA;61
"Building";"FactoryReactor";NA;61
"Unit";"Marine";"Barracks";61
"Building";"Barracks";NA;66
"Building";"StarportReactor";NA;67
"Building";"Barracks";NA;68
"Building";"Refinery";NA;68
"Unit";"Marine";"Barracks";68
"Unit";"Marine";"Barracks";69
"Unit";"Marine";"Barracks";70
"Building";"Refinery";NA;71
"Unit";"Marine";"Barracks";71
"Unit";"Marine";"Barracks";74
"Upgrade";"TerranInfantryWeaponsLevel1";"EngineeringBay";75
"Unit";"Marine";"Barracks";75
"Unit";"Marine";"Barracks";76
"Unit";"Marine";"Barracks";77
"Unit";"Marine";"Barracks";78
"Unit";"Marine";"Barracks";81
"Unit";"Medivac";"Starport";82
"Unit";"Marine";"Barracks";86
"Unit";"Marine";"Barracks";87
"Unit";"Marine";"Barracks";89
"Unit";"Marine";"Barracks";90
"Building";"BarracksReactor";NA;93
"Unit";"Marine";"Barracks";93
"Unit";"Medivac";"Starport";94
"Unit";"Marine";"Barracks";96
"Unit";"Marine";"Barracks";97
"Unit";"Medivac";"Starport";100
"Building";"Refinery";NA;102
"Building";"Refinery";NA;103
"Unit";"Marine";"Barracks";105
"Unit";"Marine";"Barracks";106
"Unit";"Marine";"Barracks";107
"Unit";"Marine";"Barracks";108
"Unit";"Marine";"Barracks";109
"Unit";"Marine";"Barracks";110
"Building";"Factory";NA;111
"Unit";"Marine";"Barracks";112
"Unit";"Marine";"Barracks";113
"Unit";"Marine";"Barracks";114
"Unit";"Medivac";"Starport";117
"Unit";"Medivac";"Starport";119
"Unit";"Marine";"Barracks";121
"Unit";"Marine";"Barracks";122
"Unit";"Marine";"Barracks";123
"Unit";"Marine";"Barracks";124
"Unit";"Marine";"Barracks";125
"Unit";"Marine";"Barracks";126
"Unit";"Marine";"Barracks";128
"Unit";"Marine";"Barracks";129
"Unit";"Marine";"Barracks";130
"Building";"Armory";NA;132
"Unit";"Marine";"Barracks";132
"Unit";"Marine";"Barracks";133
"Unit";"Marine";"Barracks";134
"Unit";"Marine";"Barracks";135
"Unit";"Marine";"Barracks";136
"Unit";"Marine";"Barracks";137
"Unit";"Medivac";"Starport";140
"Building";"FactoryTechLab";NA;143
"Unit";"Marine";"Barracks";145
"Unit";"Marine";"Barracks";146
"Unit";"Marine";"Barracks";147
"Unit";"Marine";"Barracks";148
"Unit";"Marine";"Barracks";149
"Unit";"Marine";"Barracks";151
"Unit";"Marine";"Barracks";152
"Unit";"Marine";"Barracks";153
"Unit";"Marine";"Barracks";154
"Unit";"Marine";"Barracks";155
"Unit";"Marine";"Barracks";156
"Unit";"Marine";"Barracks";157
"Unit";"Medivac";"Starport";161
"Unit";"Medivac";"Starport";163
"Unit";"Marine";"Barracks";165
"Unit";"Marine";"Barracks";166
"Unit";"Marine";"Barracks";167
"Unit";"Marine";"Barracks";168
"Unit";"Marine";"Barracks";169
"Unit";"Marine";"Barracks";170
"Unit";"Marine";"Barracks";171
"Unit";"Marine";"Barracks";172
"Unit";"Marine";"Barracks";173
"Upgrade";"TerranVehicleWeaponsLevel1";"Armory";174
"Upgrade";"TerranInfantryWeaponsLevel2";"EngineeringBay";174
"Unit";"Marine";"Barracks";174
"Unit";"Marine";"Barracks";175
"Unit";"Marine";"Barracks";176
"Unit";"Marine";"Barracks";177
"Unit";"Marine";"Barracks";178
"Unit";"Marine";"Barracks";179
"Unit";"Marine";"Barracks";180
"Unit";"Marine";"Barracks";181
"Unit";"Marine";"Barracks";182
"Unit";"Medivac";"Starport";183
"Unit";"Medivac";"Starport";185
"Unit";"Marine";"Barracks";187
"Unit";"Marine";"Barracks";188
"Unit";"Marine";"Barracks";189
"Unit";"Marine";"Barracks";190
"Unit";"Marine";"Barracks";191
"Unit";"Marine";"Barracks";192
"Unit";"Marine";"Barracks";193
"Unit";"Marine";"Barracks";194
"Unit";"Marine";"Barracks";195
"Unit";"Marine";"Barracks";196
"Unit";"Marine";"Barracks";197
"Unit";"Marine";"Barracks";198
"Unit";"Marine";"Barracks";199
"Unit";"Marine";"Barracks";200
"Unit";"Marine";"Barracks";201
"Unit";"Marine";"Barracks";202
"Unit";"Marine";"Barracks";203
"Unit";"Marine";"Barracks";204
"Unit";"Medivac";"Starport";205
"Unit";"Marine";"Barracks";207
"Building";"MissileTurret";NA;208
"Unit";"Marine";"Barracks";208
"Unit";"Marine";"Barracks";209
"Unit";"Marine";"Barracks";210
"Unit";"Marine";"Barracks";211
"Unit";"Marine";"Barracks";212
"Unit";"Marine";"Barracks";213
"Unit";"Marine";"Barracks";214
"Unit";"Marine";"Barracks";215
"Unit";"Marine";"Barracks";216
"Building";"CommandCenter";NA;217
"Unit";"Marine";"Barracks";217
"Unit";"Marine";"Barracks";218
"Unit";"Marine";"Barracks";219
"Unit";"Marine";"Barracks";220
"Unit";"Marine";"Barracks";221
"Unit";"Marine";"Barracks";222
"Unit";"Marine";"Barracks";223
"Unit";"Marine";"Barracks";224
"Unit";"Marine";"Barracks";225
"Unit";"Marine";"Barracks";226
"Unit";"Marine";"Barracks";227
"Unit";"Marine";"Barracks";228
"Unit";"Marine";"Barracks";229
"Unit";"Marine";"Barracks";230
"Unit";"Marine";"Barracks";231
"Unit";"Medivac";"Starport";232
"Unit";"Medivac";"Starport";234
"Unit";"Marine";"Barracks";236
"Unit";"Marine";"Barracks";237
"Unit";"Marine";"Barracks";238
"Building";"MissileTurret";NA;239
"Unit";"Marine";"Barracks";239
"Unit";"Marine";"Barracks";240
"Unit";"Marine";"Barracks";241
"Upgrade";"TerranVehicleWeaponsLevel2";"Armory";242
"Unit";"Marine";"Barracks";242
"Unit";"Marine";"Barracks";243
"Unit";"Marine";"Barracks";244
"Building";"Refinery";NA;245
"Building";"Refinery";NA;245
"Unit";"Medivac";"Starport";245
"Unit";"Medivac";"Starport";247
"Unit";"Marine";"Barracks";249
"Unit";"Marine";"Barracks";250
"Unit";"Marine";"Barracks";251
"Unit";"Marine";"Barracks";252
"Unit";"Marine";"Barracks";253
"Unit";"Marine";"Barracks";254
"Unit";"Marine";"Barracks";255
"Unit";"Marine";"Barracks";256
"Unit";"Marine";"Barracks";257
"Upgrade";"SprayTerran";NA;258
"Upgrade";"SprayTerran";NA;258
"Upgrade";"SprayTerran";NA;258
"Upgrade";"SprayTerran";NA;258
"Upgrade";"TerranInfantryArmorsLevel1";NA;258
"Upgrade";"ShieldWall";NA;258
"Upgrade";"SprayTerran";NA;258
"Upgrade";"SprayTerran";NA;258
"Upgrade";"TerranInfantryArmorsLevel2";NA;258
"Upgrade";"SprayTerran";NA;258
"Upgrade";"SprayTerran";NA;258
"Upgrade";"SprayTerran";NA;258
"Upgrade";"SprayTerran";NA;258
"Upgrade";"SprayTerran";NA;258
