"type";"unit_name";"on_building";"total_supply_lag";"supply"
"Building";"Refinery";NA;15;0
"Building";"Barracks";NA;16;0
"Unit";"Reaper";"Barracks";19;1
"Building";"CommandCenter";NA;20;0
"Building";"Factory";NA;20;0
"Building";"BarracksReactor";NA;21;0
"Building";"Refinery";NA;22;0
"Building";"Starport";NA;24;0
"Unit";"Marine";"Barracks";24;1
"Unit";"Marine";"Barracks";25;1
"Unit";"Marine";"Barracks";28;1
"Unit";"Marine";"Barracks";29;1
"Unit";"Marine";"Barracks";31;1
"Unit";"Marine";"Barracks";32;1
"Unit";"Medivac";"Starport";33;2
"Unit";"Marine";"Barracks";37;1
"Unit";"Marine";"Barracks";38;1
"Unit";"Marine";"Barracks";43;1
"Unit";"Marine";"Barracks";44;1
"Building";"Barracks";NA;45;0
"Building";"Barracks";NA;46;0
"Building";"EngineeringBay";NA;47;0
"Building";"FactoryTechLab";NA;47;0
"Building";"StarportTechLab";NA;47;0
"Unit";"Marine";"Barracks";49;1
"Unit";"Marine";"Barracks";50;1
"Unit";"Marine";"Barracks";53;1
"Unit";"Marine";"Barracks";54;1
"Unit";"Marine";"Barracks";59;1
"Unit";"Marine";"Barracks";60;1
"Unit";"Marauder";"Barracks";61;2
"Unit";"Marauder";"Barracks";63;2
"Building";"StarportReactor";NA;65;0
"Building";"FactoryReactor";NA;65;0
"Upgrade";"TerranInfantryWeaponsLevel1";"EngineeringBay";66;0
"Unit";"Marauder";"Barracks";69;2
"Unit";"Marauder";"Barracks";71;2
"Unit";"Marine";"Barracks";73;1
"Unit";"Marine";"Barracks";74;1
"Upgrade";"Stimpack";"TechLab";76;0
"Unit";"Medivac";"Starport";76;2
"Unit";"Medivac";"Starport";78;2
"Building";"CommandCenter";NA;80;0
"Unit";"Marauder";"Barracks";80;2
"Unit";"Marauder";"Barracks";82;2
"Building";"Refinery";NA;84;0
"Building";"Refinery";NA;84;0
"Unit";"Marine";"Barracks";84;1
"Unit";"Marine";"Barracks";85;1
"Unit";"Marauder";"Barracks";87;2
"Unit";"Marauder";"Barracks";89;2
"Building";"Barracks";NA;91;0
"Building";"Barracks";NA;91;0
"Unit";"Medivac";"Starport";92;2
"Unit";"Marine";"Barracks";94;1
"Unit";"Marine";"Barracks";95;1
"Unit";"Marauder";"Barracks";96;2
"Unit";"Marauder";"Barracks";98;2
"Building";"MissileTurret";NA;102;0
"Unit";"Marine";"Barracks";104;1
"Unit";"Marauder";"Barracks";105;2
"Unit";"Marine";"Barracks";107;1
"Unit";"Marine";"Barracks";108;1
"Building";"BarracksTechLab";NA;110;0
"Building";"Starport";NA;110;0
"Building";"BarracksTechLab";NA;110;0
"Unit";"Marauder";"Barracks";110;2
"Unit";"Marine";"Barracks";112;1
"Unit";"Marine";"Barracks";113;1
"Unit";"Marine";"Barracks";114;1
"Unit";"Liberator";"Starport";115;3
"Unit";"Marauder";"Barracks";121;2
"Unit";"Marauder";"Barracks";123;2
"Unit";"Liberator";"Starport";125;3
"Unit";"Marauder";"Barracks";128;2
"Unit";"Marauder";"Barracks";130;2
"Unit";"Marauder";"Barracks";132;2
"Unit";"Marauder";"Barracks";134;2
"Unit";"Marauder";"Barracks";136;2
"Building";"GhostAcademy";NA;138;0
"Building";"Refinery";NA;141;0
"Unit";"Marine";"Barracks";141;1
"Unit";"Marine";"Barracks";142;1
"Unit";"Marauder";"Barracks";143;2
"Unit";"Marauder";"Barracks";145;2
"Unit";"Marauder";"Barracks";148;2
"Unit";"Marauder";"Barracks";150;2
"Unit";"Marauder";"Barracks";152;2
"Unit";"Marauder";"Barracks";154;2
"Unit";"Marauder";"Barracks";156;2
"Unit";"Ghost";"Barracks";158;2
"Unit";"Marine";"Barracks";160;1
"Unit";"Marine";"Barracks";161;1
"Unit";"Ghost";"Barracks";162;2
"Unit";"Marine";"Barracks";164;1
"Unit";"Marine";"Barracks";168;1
"Unit";"Marine";"Barracks";169;1
"Unit";"Marauder";"Barracks";171;2
"Unit";"Marauder";"Barracks";175;2
"Unit";"Marauder";"Barracks";177;2
"Unit";"Marauder";"Barracks";179;2
"Unit";"Marauder";"Barracks";181;2
"Unit";"Marauder";"Barracks";183;2
"Unit";"Marauder";"Barracks";185;2
"Unit";"Marauder";"Barracks";187;2
"Unit";"Marauder";"Barracks";189;2
"Unit";"Marine";"Barracks";191;1
"Unit";"Marine";"Barracks";192;1
"Unit";"Marauder";"Barracks";193;2
"Unit";"Marauder";"Barracks";195;2
"Unit";"Marine";"Barracks";197;1
"Unit";"Marine";"Barracks";198;1
"Unit";"Marine";"Barracks";199;1
"Unit";"Marine";"Barracks";200;1
"Building";"Armory";NA;201;0
"Building";"Barracks";NA;201;0
"Unit";"Marine";"Barracks";201;1
"Building";"Barracks";NA;202;0
"Building";"EngineeringBay";NA;202;0
"Unit";"Marauder";"Barracks";202;2
"Unit";"Marine";"Barracks";204;1
"Unit";"Marine";"Barracks";205;1
"Unit";"Marine";"Barracks";206;1
"Unit";"Liberator";"Starport";207;3
"Unit";"Marine";"Barracks";210;1
"Building";"CommandCenter";NA;211;0
"Unit";"Marine";"Barracks";211;1
"Unit";"Marine";"Barracks";212;1
"Unit";"Marine";"Barracks";213;1
"Unit";"Marine";"Barracks";214;1
"Unit";"Marauder";"Barracks";215;2
"Unit";"Liberator";"Starport";217;3
"Unit";"Liberator";"Starport";220;3
"Unit";"Marauder";"Barracks";223;2
"Unit";"Marine";"Barracks";225;1
"Unit";"Marauder";"Barracks";226;2
"Unit";"Marine";"Barracks";228;1
"Unit";"Marine";"Barracks";229;1
"Unit";"Marine";"Barracks";230;1
"Unit";"Marine";"Barracks";231;1
"Unit";"Marine";"Barracks";232;1
"Unit";"Liberator";"Starport";233;3
"Unit";"Marine";"Barracks";236;1
"Unit";"Liberator";"Starport";237;3
"Unit";"Marauder";"Barracks";240;2
"Unit";"Marauder";"Barracks";242;2
"Unit";"Marine";"Barracks";244;1
"Unit";"Marauder";"Barracks";245;2
"Unit";"Marauder";"Barracks";247;2
"Unit";"Marine";"Barracks";249;1
"Unit";"Marine";"Barracks";250;1
"Unit";"Marine";"Barracks";251;1
"Unit";"Ghost";"Barracks";252;2
"Unit";"Marine";"Barracks";254;1
"Unit";"Marauder";"Barracks";255;2
"Unit";"Marauder";"Barracks";257;2
"Unit";"Marauder";"Barracks";259;2
"Unit";"Marine";"Barracks";261;1
"Unit";"Marine";"Barracks";262;1
"Unit";"Marine";"Barracks";263;1
"Upgrade";"TerranInfantryWeaponsLevel2";"EngineeringBay";264;0
"Unit";"Marine";"Barracks";264;1
"Unit";"Liberator";"Starport";265;3
"Unit";"Marauder";"Barracks";268;2
"Unit";"Marine";"Barracks";270;1
"Unit";"Liberator";"Starport";271;3
"Unit";"Marauder";"Barracks";274;2
"Unit";"Marine";"Barracks";276;1
"Unit";"Marauder";"Barracks";277;2
"Building";"Refinery";NA;279;0
"Building";"Refinery";NA;279;0
"Unit";"Marine";"Barracks";279;1
"Unit";"Marauder";"Barracks";280;2
"Unit";"Marine";"Barracks";282;1
"Unit";"Marauder";"Barracks";283;2
"Unit";"Marine";"Barracks";285;1
"Unit";"Marauder";"Barracks";286;2
"Unit";"Liberator";"Starport";288;3
"Unit";"Marine";"Barracks";291;1
"Unit";"Marine";"Barracks";292;1
"Unit";"Marine";"Barracks";293;1
"Unit";"Marine";"Barracks";294;1
"Unit";"Marine";"Barracks";295;1
"Building";"Refinery";NA;296;0
"Unit";"Marine";"Barracks";296;1
"Unit";"Liberator";"Starport";297;3
"Unit";"Marine";"Barracks";300;1
"Unit";"Marine";"Barracks";301;1
"Unit";"Marauder";"Barracks";302;2
"Unit";"Marine";"Barracks";304;1
"Unit";"Marine";"Barracks";305;1
"Unit";"Marauder";"Barracks";306;2
"Unit";"Marine";"Barracks";308;1
"Unit";"Marine";"Barracks";309;1
"Unit";"Liberator";"Starport";310;3
"Unit";"Liberator";"Starport";313;3
"Unit";"Marine";"Barracks";316;1
"Unit";"Marine";"Barracks";317;1
"Unit";"Marine";"Barracks";318;1
"Unit";"Marine";"Barracks";319;1
"Unit";"Marauder";"Barracks";320;2
"Unit";"Marine";"Barracks";322;1
"Unit";"Marauder";"Barracks";323;2
"Unit";"Marine";"Barracks";325;1
"Unit";"Liberator";"Starport";326;3
"Unit";"Liberator";"Starport";329;3
"Unit";"Marine";"Barracks";332;1
"Unit";"Marine";"Barracks";333;1
"Unit";"Marine";"Barracks";334;1
"Unit";"Marine";"Barracks";335;1
"Unit";"Marauder";"Barracks";336;2
"Unit";"Marauder";"Barracks";338;2
"Unit";"Marauder";"Barracks";340;2
"Unit";"Marine";"Barracks";342;1
"Unit";"Marine";"Barracks";343;1
"Unit";"Liberator";"Starport";344;3
"Unit";"Liberator";"Starport";347;3
"Unit";"Marine";"Barracks";350;1
"Unit";"Marine";"Barracks";351;1
"Unit";"Marine";"Barracks";352;1
"Unit";"Marauder";"Barracks";353;2
"Unit";"Marauder";"Barracks";355;2
"Unit";"Marine";"Barracks";357;1
"Unit";"Marine";"Barracks";358;1
"Unit";"Marine";"Barracks";359;1
"Unit";"Marine";"Barracks";360;1
"Unit";"Marine";"Barracks";361;1
"Unit";"Marine";"Barracks";362;1
"Unit";"Marauder";"Barracks";363;2
"Unit";"Marauder";"Barracks";365;2
"Unit";"Marauder";"Barracks";367;2
"Unit";"Marauder";"Barracks";369;2
"Unit";"Marine";"Barracks";371;1
"Unit";"Marine";"Barracks";372;1
"Unit";"Medivac";"Starport";373;2
"Unit";"Medivac";"Starport";375;2
"Unit";"Ghost";"Barracks";377;2
"Unit";"Ghost";"Barracks";379;2
"Unit";"Marine";"Barracks";381;1
"Unit";"Marine";"Barracks";382;1
"Unit";"Marine";"Barracks";383;1
"Unit";"Marine";"Barracks";384;1
"Unit";"Marauder";"Barracks";385;2
"Unit";"Marine";"Barracks";387;1
"Unit";"Marine";"Barracks";388;1
"Unit";"Marine";"Barracks";389;1
"Unit";"Marauder";"Barracks";390;2
"Unit";"Marauder";"Barracks";392;2
"Unit";"Marine";"Barracks";394;1
"Unit";"Marauder";"Barracks";395;2
"Unit";"Marine";"Barracks";397;1
"Upgrade";"SprayTerran";NA;398;0
"Upgrade";"SprayTerran";NA;398;0
"Upgrade";"SprayTerran";NA;398;0
"Upgrade";"ShieldWall";NA;398;0
"Upgrade";"SprayTerran";NA;398;0
"Upgrade";"TerranInfantryArmorsLevel1";NA;398;0
"Upgrade";"PunisherGrenades";NA;398;0
"Upgrade";"SprayTerran";NA;398;0
"Upgrade";"SprayTerran";NA;398;0
"Upgrade";"TerranInfantryArmorsLevel2";NA;398;0
