"type";"unit_name";"on_building";"total_supply_lag";"supply"
"Unit";"Overlord";"Larva";13;0
"Building";"Hatchery";NA;17;0
"Building";"Extractor";NA;19;0
"Building";"SpawningPool";NA;19;0
"Unit";"Overlord";"Larva";22;0
"Unit";"Queen";"Hatchery";23;2
"Unit";"Zergling";"Larva";25;1
"Unit";"Zergling";"Larva";26;1
"Unit";"Queen";"Hatchery";27;2
"Building";"Hatchery";NA;34;0
"Building";"EvolutionChamber";NA;35;0
"Unit";"Overlord";"Larva";38;0
"Unit";"Zergling";"Larva";38;1
"Unit";"Zergling";"Larva";39;1
"Unit";"Overlord";"Larva";48;0
"Building";"CreepTumorQueen";NA;48;0
"Unit";"Queen";"Hatchery";48;2
"Unit";"Overlord";"Larva";51;0
"Unit";"Overlord";"Larva";51;0
"Building";"CreepTumor";NA;55;0
"Building";"Extractor";NA;58;0
"Unit";"Overlord";"Larva";62;0
"Building";"Extractor";NA;62;0
"Building";"RoachWarren";NA;70;0
"Unit";"Zergling";"Larva";70;1
"Unit";"Zergling";"Larva";71;1
"Unit";"Zergling";"Larva";72;1
"Unit";"Zergling";"Larva";73;1
"Unit";"Zergling";"Larva";74;1
"Unit";"Zergling";"Larva";75;1
"Unit";"Overlord";"Larva";76;0
"Building";"Extractor";NA;79;0
"Building";"CreepTumor";NA;79;0
"Building";"Extractor";NA;83;0
"Building";"Extractor";NA;83;0
"Building";"EvolutionChamber";NA;91;0
"Unit";"Overlord";"Larva";95;0
"Unit";"Overlord";"Larva";95;0
"Unit";"Roach";"Larva";95;2
"Unit";"Roach";"Larva";97;2
"Unit";"Roach";"Larva";99;2
"Unit";"Roach";"Larva";101;2
"Building";"Hatchery";NA;103;0
"Unit";"Roach";"Larva";103;2
"Upgrade";"GlialReconstitution";"RoachWarren";105;0
"Unit";"Roach";"Larva";105;2
"Unit";"Roach";"Larva";107;2
"Unit";"Roach";"Larva";109;2
"Unit";"Roach";"Larva";111;2
"Unit";"Roach";"Larva";113;2
"Unit";"Roach";"Larva";115;2
"Unit";"Roach";"Larva";117;2
"Unit";"Roach";"Larva";119;2
"Unit";"Roach";"Larva";121;2
"Unit";"Roach";"Larva";123;2
"Unit";"Roach";"Larva";125;2
"Unit";"Overlord";"Larva";127;0
"Unit";"Overlord";"Larva";127;0
"Unit";"Overlord";"Larva";127;0
"Upgrade";"Burrow";"Hatchery";127;0
"Unit";"Roach";"Larva";127;2
"Unit";"Overlord";"Larva";129;0
"Unit";"Overlord";"Larva";129;0
"Unit";"Roach";"Larva";129;2
"Unit";"Roach";"Larva";131;2
"Unit";"Roach";"Larva";133;2
"Unit";"Roach";"Larva";135;2
"Unit";"Roach";"Larva";137;2
"Unit";"Roach";"Larva";139;2
"Unit";"Roach";"Larva";141;2
"Unit";"Roach";"Larva";143;2
"Unit";"Roach";"Larva";145;2
"Unit";"Roach";"Larva";147;2
"Unit";"Roach";"Larva";149;2
"Unit";"Roach";"Larva";151;2
"Unit";"Roach";"Larva";153;2
"Unit";"Roach";"Larva";155;2
"Unit";"Roach";"Larva";157;2
"Unit";"Roach";"Larva";159;2
"Unit";"Roach";"Larva";161;2
"Unit";"Overlord";"Larva";163;0
"Unit";"Roach";"Larva";163;2
"Unit";"Roach";"Larva";165;2
"Unit";"Roach";"Larva";167;2
"Unit";"Roach";"Larva";169;2
"Unit";"Overlord";"Larva";171;0
"Upgrade";"TunnelingClaws";"RoachWarren";171;0
"Unit";"Overlord";"Larva";171;0
"Unit";"Overlord";"Larva";171;0
"Unit";"Roach";"Larva";171;2
"Unit";"Roach";"Larva";173;2
"Unit";"Roach";"Larva";175;2
"Unit";"Roach";"Larva";177;2
"Unit";"Roach";"Larva";179;2
"Unit";"Roach";"Larva";181;2
"Unit";"Overlord";"Larva";183;0
"Building";"HydraliskDen";NA;183;0
"Unit";"Roach";"Larva";183;2
"Unit";"Roach";"Larva";185;2
"Unit";"Roach";"Larva";187;2
"Unit";"Roach";"Larva";189;2
"Unit";"Roach";"Larva";191;2
"Unit";"Roach";"Larva";193;2
"Unit";"Roach";"Larva";195;2
"Unit";"Roach";"Larva";197;2
"Unit";"Roach";"Larva";199;2
"Unit";"Roach";"Larva";201;2
"Unit";"Roach";"Larva";203;2
"Unit";"Roach";"Larva";205;2
"Unit";"Roach";"Larva";207;2
"Unit";"Overlord";"Larva";213;0
"Unit";"Overlord";"Larva";213;0
"Unit";"Overlord";"Larva";213;0
"Unit";"Hydralisk";"Larva";213;2
"Unit";"Hydralisk";"Larva";215;2
"Unit";"Hydralisk";"Larva";217;2
"Unit";"Hydralisk";"Larva";219;2
"Unit";"Hydralisk";"Larva";221;2
"Unit";"Hydralisk";"Larva";223;2
"Unit";"Hydralisk";"Larva";225;2
"Unit";"Hydralisk";"Larva";227;2
"Unit";"Hydralisk";"Larva";229;2
"Unit";"Hydralisk";"Larva";231;2
"Unit";"Hydralisk";"Larva";233;2
"Unit";"Hydralisk";"Larva";235;2
"Unit";"Hydralisk";"Larva";237;2
"Unit";"Roach";"Larva";239;2
"Unit";"Roach";"Larva";241;2
"Unit";"Roach";"Larva";243;2
"Unit";"Roach";"Larva";245;2
"Unit";"Roach";"Larva";247;2
"Unit";"Roach";"Larva";249;2
"Unit";"Roach";"Larva";251;2
"Unit";"Roach";"Larva";253;2
"Unit";"Roach";"Larva";255;2
"Unit";"Roach";"Larva";257;2
"Unit";"Hydralisk";"Larva";259;2
"Unit";"Hydralisk";"Larva";261;2
"Unit";"Hydralisk";"Larva";263;2
"Unit";"Hydralisk";"Larva";265;2
"Building";"InfestationPit";NA;267;0
"Unit";"Hydralisk";"Larva";267;2
"Unit";"Hydralisk";"Larva";269;2
"Unit";"Hydralisk";"Larva";271;2
"Unit";"Hydralisk";"Larva";273;2
"Unit";"Roach";"Larva";275;2
"Unit";"Roach";"Larva";277;2
"Unit";"Roach";"Larva";279;2
"Unit";"Roach";"Larva";281;2
"Unit";"Roach";"Larva";283;2
"Unit";"Roach";"Larva";285;2
"Unit";"Roach";"Larva";287;2
"Unit";"Roach";"Larva";289;2
"Unit";"Roach";"Larva";291;2
"Building";"SpineCrawler";NA;293;0
"Building";"SpineCrawler";NA;293;0
"Unit";"Roach";"Larva";293;2
"Unit";"Roach";"Larva";295;2
"Unit";"Roach";"Larva";297;2
"Unit";"Roach";"Larva";299;2
"Unit";"Roach";"Larva";301;2
"Unit";"Roach";"Larva";303;2
"Unit";"Roach";"Larva";305;2
"Unit";"Roach";"Larva";307;2
"Unit";"Roach";"Larva";309;2
"Unit";"Roach";"Larva";311;2
"Unit";"Roach";"Larva";313;2
"Unit";"Roach";"Larva";315;2
"Unit";"Roach";"Larva";317;2
"Upgrade";"SprayZerg";NA;319;0
"Upgrade";"SprayZerg";NA;319;0
"Upgrade";"SprayZerg";NA;319;0
"Upgrade";"zerglingmovementspeed";NA;319;0
"Upgrade";"SprayZerg";NA;319;0
"Upgrade";"SprayZerg";NA;319;0
"Upgrade";"ZergMissileWeaponsLevel1";NA;319;0
"Upgrade";"SprayZerg";NA;319;0
"Upgrade";"ZergGroundArmorsLevel1";NA;319;0
"Upgrade";"ZergMissileWeaponsLevel2";NA;319;0
