"type";"unit_name";"on_building";"total_supply_lag";"supply"
"Unit";"Overlord";"Larva";13;0
"Building";"SpawningPool";NA;18;0
"Building";"Hatchery";NA;19;0
"Unit";"Queen";"Hatchery";21;2
"Building";"Hatchery";NA;24;0
"Unit";"Zergling";"Larva";24;1
"Unit";"Zergling";"Larva";25;1
"Unit";"Overlord";"Larva";26;0
"Unit";"Queen";"Hatchery";26;2
"Unit";"Queen";"Hatchery";32;2
"Building";"CreepTumorQueen";NA;40;0
"Building";"Extractor";NA;40;0
"Building";"Extractor";NA;40;0
"Unit";"Overlord";"Larva";41;0
"Building";"EvolutionChamber";NA;43;0
"Building";"EvolutionChamber";NA;43;0
"Building";"RoachWarren";NA;43;0
"Building";"CreepTumor";NA;47;0
"Unit";"Overlord";"Larva";51;0
"Building";"CreepTumor";NA;60;0
"Unit";"Overlord";"Larva";65;0
"Unit";"Overlord";"Larva";68;0
"Building";"Extractor";NA;74;0
"Building";"Extractor";NA;74;0
"Unit";"Overlord";"Larva";74;0
"Building";"Extractor";NA;80;0
"Unit";"Overlord";"Larva";82;0
"Unit";"Zergling";"Larva";83;1
"Unit";"Zergling";"Larva";84;1
"Unit";"Zergling";"Larva";85;1
"Unit";"Zergling";"Larva";86;1
"Unit";"Zergling";"Larva";87;1
"Unit";"Zergling";"Larva";88;1
"Unit";"Zergling";"Larva";89;1
"Unit";"Zergling";"Larva";90;1
"Unit";"Zergling";"Larva";91;1
"Unit";"Zergling";"Larva";92;1
"Unit";"Zergling";"Larva";93;1
"Unit";"Zergling";"Larva";94;1
"Unit";"Zergling";"Larva";95;1
"Unit";"Zergling";"Larva";96;1
"Unit";"Zergling";"Larva";97;1
"Unit";"Zergling";"Larva";98;1
"Unit";"Zergling";"Larva";99;1
"Unit";"Zergling";"Larva";100;1
"Unit";"Zergling";"Larva";101;1
"Unit";"Zergling";"Larva";102;1
"Unit";"Zergling";"Larva";103;1
"Unit";"Zergling";"Larva";104;1
"Unit";"Zergling";"Larva";105;1
"Unit";"Zergling";"Larva";106;1
"Unit";"Zergling";"Larva";107;1
"Unit";"Zergling";"Larva";108;1
"Unit";"Zergling";"Larva";109;1
"Unit";"Zergling";"Larva";110;1
"Unit";"Overlord";"Larva";111;0
"Building";"Hatchery";NA;111;0
"Unit";"Zergling";"Larva";111;1
"Unit";"Zergling";"Larva";112;1
"Unit";"Zergling";"Larva";113;1
"Unit";"Zergling";"Larva";114;1
"Unit";"Zergling";"Larva";115;1
"Unit";"Zergling";"Larva";116;1
"Unit";"Zergling";"Larva";117;1
"Unit";"Zergling";"Larva";118;1
"Unit";"Zergling";"Larva";119;1
"Unit";"Zergling";"Larva";120;1
"Unit";"Zergling";"Larva";121;1
"Unit";"Zergling";"Larva";122;1
"Unit";"Overlord";"Larva";123;0
"Unit";"Overlord";"Larva";123;0
"Unit";"Zergling";"Larva";123;1
"Unit";"Zergling";"Larva";124;1
"Unit";"Zergling";"Larva";125;1
"Unit";"Zergling";"Larva";126;1
"Unit";"Zergling";"Larva";127;1
"Unit";"Zergling";"Larva";128;1
"Unit";"Zergling";"Larva";129;1
"Unit";"Zergling";"Larva";130;1
"Unit";"Zergling";"Larva";131;1
"Unit";"Zergling";"Larva";132;1
"Unit";"Zergling";"Larva";133;1
"Unit";"Zergling";"Larva";134;1
"Unit";"Zergling";"Larva";135;1
"Unit";"Zergling";"Larva";136;1
"Unit";"Overlord";"Larva";137;0
"Unit";"Zergling";"Larva";137;1
"Unit";"Zergling";"Larva";138;1
"Unit";"Zergling";"Larva";139;1
"Unit";"Zergling";"Larva";140;1
"Unit";"Zergling";"Larva";141;1
"Unit";"Zergling";"Larva";142;1
"Unit";"Zergling";"Larva";143;1
"Unit";"Zergling";"Larva";144;1
"Unit";"Zergling";"Larva";145;1
"Unit";"Zergling";"Larva";146;1
"Unit";"Zergling";"Larva";147;1
"Unit";"Zergling";"Larva";148;1
"Unit";"Zergling";"Larva";149;1
"Unit";"Zergling";"Larva";150;1
"Unit";"Zergling";"Larva";151;1
"Unit";"Zergling";"Larva";152;1
"Unit";"Zergling";"Larva";153;1
"Unit";"Zergling";"Larva";154;1
"Unit";"Zergling";"Larva";155;1
"Unit";"Zergling";"Larva";156;1
"Unit";"Zergling";"Larva";159;1
"Unit";"Zergling";"Larva";160;1
"Building";"Spire";NA;161;0
"Unit";"Zergling";"Larva";161;1
"Unit";"Zergling";"Larva";162;1
"Unit";"Zergling";"Larva";163;1
"Unit";"Zergling";"Larva";164;1
"Building";"InfestationPit";NA;165;0
"Unit";"Zergling";"Larva";165;1
"Unit";"Zergling";"Larva";166;1
"Unit";"Zergling";"Larva";167;1
"Unit";"Zergling";"Larva";168;1
"Unit";"Overlord";"Larva";169;0
"Building";"Hatchery";NA;169;0
"Unit";"Overlord";"Larva";169;0
"Building";"BanelingNest";NA;169;0
"Unit";"Zergling";"Larva";169;1
"Unit";"Zergling";"Larva";170;1
"Unit";"Zergling";"Larva";171;1
"Unit";"Zergling";"Larva";172;1
"Unit";"Zergling";"Larva";173;1
"Unit";"Zergling";"Larva";174;1
"Unit";"Zergling";"Larva";175;1
"Unit";"Zergling";"Larva";176;1
"Unit";"Zergling";"Larva";177;1
"Unit";"Zergling";"Larva";178;1
"Unit";"Zergling";"Larva";179;1
"Unit";"Zergling";"Larva";180;1
"Unit";"Zergling";"Larva";181;1
"Unit";"Zergling";"Larva";182;1
"Unit";"Zergling";"Larva";183;1
"Unit";"Zergling";"Larva";184;1
"Unit";"Zergling";"Larva";185;1
"Unit";"Zergling";"Larva";186;1
"Unit";"Zergling";"Larva";187;1
"Unit";"Zergling";"Larva";188;1
"Unit";"Zergling";"Larva";189;1
"Unit";"Zergling";"Larva";190;1
"Unit";"Zergling";"Larva";191;1
"Unit";"Zergling";"Larva";192;1
"Unit";"Zergling";"Larva";193;1
"Unit";"Zergling";"Larva";194;1
"Unit";"Zergling";"Larva";195;1
"Unit";"Zergling";"Larva";196;1
"Unit";"Zergling";"Larva";197;1
"Unit";"Zergling";"Larva";198;1
"Unit";"Overlord";"Larva";199;0
"Unit";"Overlord";"Larva";199;0
"Unit";"Zergling";"Larva";199;1
"Unit";"Zergling";"Larva";200;1
"Unit";"Zergling";"Larva";201;1
"Unit";"Zergling";"Larva";202;1
"Unit";"Zergling";"Larva";203;1
"Unit";"Zergling";"Larva";204;1
"Unit";"Zergling";"Larva";205;1
"Unit";"Zergling";"Larva";206;1
"Unit";"Zergling";"Larva";207;1
"Unit";"Zergling";"Larva";208;1
"Unit";"Zergling";"Larva";209;1
"Unit";"Zergling";"Larva";210;1
"Unit";"Overlord";"Larva";211;0
"Unit";"Baneling";"Zergling";222;0
"Unit";"Baneling";"Zergling";222;0
"Unit";"Baneling";"Zergling";222;0
"Unit";"Baneling";"Zergling";222;0
"Unit";"Baneling";"Zergling";222;0
"Unit";"Overlord";"Larva";222;0
"Unit";"Queen";"Hatchery";222;2
"Unit";"Overlord";"Larva";226;0
"Unit";"Mutalisk";"Larva";226;2
"Unit";"Mutalisk";"Larva";228;2
"Unit";"Mutalisk";"Larva";230;2
"Unit";"Mutalisk";"Larva";232;2
"Unit";"Mutalisk";"Larva";234;2
"Unit";"Mutalisk";"Larva";236;2
"Unit";"Mutalisk";"Larva";238;2
"Unit";"Mutalisk";"Larva";240;2
"Unit";"Mutalisk";"Larva";242;2
"Unit";"Mutalisk";"Larva";244;2
"Unit";"Mutalisk";"Larva";246;2
"Unit";"Mutalisk";"Larva";248;2
"Unit";"Zergling";"Larva";250;1
"Unit";"Zergling";"Larva";251;1
"Unit";"Zergling";"Larva";252;1
"Unit";"Zergling";"Larva";253;1
"Unit";"Zergling";"Larva";254;1
"Unit";"Zergling";"Larva";255;1
"Unit";"Zergling";"Larva";256;1
"Unit";"Zergling";"Larva";257;1
"Unit";"Zergling";"Larva";258;1
"Unit";"Zergling";"Larva";259;1
"Building";"UltraliskCavern";NA;260;0
"Unit";"Zergling";"Larva";260;1
"Unit";"Zergling";"Larva";261;1
"Unit";"Zergling";"Larva";262;1
"Unit";"Zergling";"Larva";263;1
"Unit";"Zergling";"Larva";264;1
"Unit";"Zergling";"Larva";265;1
"Unit";"Zergling";"Larva";266;1
"Unit";"Zergling";"Larva";267;1
"Unit";"Zergling";"Larva";268;1
"Unit";"Zergling";"Larva";269;1
"Unit";"Zergling";"Larva";270;1
"Unit";"Zergling";"Larva";271;1
"Unit";"Zergling";"Larva";272;1
"Unit";"Zergling";"Larva";273;1
"Unit";"Zergling";"Larva";274;1
"Unit";"Zergling";"Larva";275;1
"Unit";"Zergling";"Larva";276;1
"Unit";"Zergling";"Larva";277;1
"Building";"Extractor";NA;278;0
"Unit";"Zergling";"Larva";278;1
"Unit";"Zergling";"Larva";279;1
"Building";"Extractor";NA;280;0
"Unit";"Zergling";"Larva";280;1
"Unit";"Zergling";"Larva";281;1
"Unit";"Zergling";"Larva";282;1
"Unit";"Zergling";"Larva";283;1
"Unit";"Overlord";"Larva";284;0
"Unit";"Baneling";"Zergling";284;0
"Unit";"Baneling";"Zergling";284;0
"Unit";"Baneling";"Zergling";284;0
"Unit";"Baneling";"Zergling";284;0
"Unit";"Baneling";"Zergling";284;0
"Unit";"Baneling";"Zergling";284;0
"Unit";"Baneling";"Zergling";284;0
"Unit";"Baneling";"Zergling";284;0
"Unit";"Baneling";"Zergling";284;0
"Unit";"Baneling";"Zergling";284;0
"Unit";"Baneling";"Zergling";284;0
"Unit";"Baneling";"Zergling";284;0
"Unit";"Baneling";"Zergling";284;0
"Unit";"Baneling";"Zergling";284;0
"Unit";"Overlord";"Larva";284;0
"Unit";"Baneling";"Zergling";284;0
"Unit";"Baneling";"Zergling";284;0
"Unit";"Baneling";"Zergling";284;0
"Unit";"Baneling";"Zergling";284;0
"Unit";"Zergling";"Larva";284;1
"Unit";"Zergling";"Larva";285;1
"Unit";"Zergling";"Larva";286;1
"Unit";"Zergling";"Larva";287;1
"Unit";"Zergling";"Larva";288;1
"Unit";"Zergling";"Larva";289;1
"Unit";"Zergling";"Larva";290;1
"Unit";"Zergling";"Larva";291;1
"Unit";"Zergling";"Larva";292;1
"Unit";"Zergling";"Larva";293;1
"Unit";"Zergling";"Larva";294;1
"Unit";"Zergling";"Larva";295;1
"Unit";"Zergling";"Larva";296;1
"Unit";"Zergling";"Larva";297;1
"Unit";"Zergling";"Larva";298;1
"Unit";"Zergling";"Larva";299;1
"Unit";"Zergling";"Larva";300;1
"Unit";"Zergling";"Larva";301;1
"Unit";"Baneling";"Zergling";302;0
"Unit";"Baneling";"Zergling";302;0
"Unit";"Baneling";"Zergling";302;0
"Unit";"Baneling";"Zergling";302;0
"Unit";"Baneling";"Zergling";302;0
"Unit";"Overlord";"Larva";302;0
"Unit";"Overlord";"Larva";302;0
"Unit";"Zergling";"Larva";302;1
"Unit";"Zergling";"Larva";303;1
"Unit";"Zergling";"Larva";304;1
"Unit";"Zergling";"Larva";305;1
"Unit";"Zergling";"Larva";306;1
"Unit";"Zergling";"Larva";307;1
"Unit";"Zergling";"Larva";308;1
"Unit";"Zergling";"Larva";309;1
"Unit";"Zergling";"Larva";310;1
"Unit";"Zergling";"Larva";311;1
"Unit";"Zergling";"Larva";312;1
"Unit";"Zergling";"Larva";313;1
"Unit";"Zergling";"Larva";314;1
"Unit";"Zergling";"Larva";315;1
"Unit";"Zergling";"Larva";316;1
"Unit";"Zergling";"Larva";317;1
"Unit";"Zergling";"Larva";318;1
"Unit";"Zergling";"Larva";319;1
"Unit";"Zergling";"Larva";320;1
"Unit";"Zergling";"Larva";321;1
"Unit";"Zergling";"Larva";322;1
"Unit";"Zergling";"Larva";323;1
"Unit";"Zergling";"Larva";324;1
"Unit";"Zergling";"Larva";325;1
"Unit";"Zergling";"Larva";326;1
"Unit";"Zergling";"Larva";327;1
"Unit";"Zergling";"Larva";328;1
"Unit";"Zergling";"Larva";329;1
"Unit";"Zergling";"Larva";330;1
"Unit";"Zergling";"Larva";331;1
"Unit";"Zergling";"Larva";332;1
"Unit";"Zergling";"Larva";333;1
"Building";"Hatchery";NA;334;0
"Unit";"Zergling";"Larva";340;1
"Unit";"Zergling";"Larva";341;1
"Unit";"Zergling";"Larva";342;1
"Unit";"Zergling";"Larva";343;1
"Unit";"Zergling";"Larva";344;1
"Unit";"Zergling";"Larva";345;1
"Unit";"Zergling";"Larva";346;1
"Unit";"Zergling";"Larva";347;1
"Unit";"Zergling";"Larva";348;1
"Unit";"Zergling";"Larva";349;1
"Upgrade";"ChitinousPlating";"UltraliskCavern";350;0
"Unit";"Ultralisk";"Larva";350;6
"Unit";"Ultralisk";"Larva";356;6
"Unit";"Ultralisk";"Larva";362;6
"Unit";"Ultralisk";"Larva";368;6
"Unit";"Ultralisk";"Larva";374;6
"Unit";"Zergling";"Larva";380;1
"Unit";"Zergling";"Larva";381;1
"Unit";"Zergling";"Larva";382;1
"Unit";"Zergling";"Larva";383;1
"Unit";"Zergling";"Larva";384;1
"Unit";"Zergling";"Larva";385;1
"Unit";"Zergling";"Larva";386;1
"Unit";"Zergling";"Larva";387;1
"Unit";"Zergling";"Larva";388;1
"Unit";"Zergling";"Larva";389;1
"Unit";"Zergling";"Larva";390;1
"Unit";"Zergling";"Larva";391;1
"Unit";"Zergling";"Larva";392;1
"Unit";"Zergling";"Larva";393;1
"Unit";"Zergling";"Larva";394;1
"Unit";"Zergling";"Larva";395;1
"Unit";"Zergling";"Larva";396;1
"Unit";"Zergling";"Larva";397;1
"Unit";"Zergling";"Larva";398;1
"Unit";"Zergling";"Larva";399;1
"Unit";"Zergling";"Larva";400;1
"Unit";"Zergling";"Larva";401;1
"Unit";"Zergling";"Larva";402;1
"Unit";"Zergling";"Larva";403;1
"Building";"Hatchery";NA;404;0
"Unit";"Baneling";"Zergling";404;0
"Unit";"Baneling";"Zergling";404;0
"Unit";"Baneling";"Zergling";404;0
"Unit";"Baneling";"Zergling";404;0
"Unit";"Baneling";"Zergling";404;0
"Unit";"Baneling";"Zergling";404;0
"Unit";"Baneling";"Zergling";404;0
"Unit";"Baneling";"Zergling";404;0
"Unit";"Baneling";"Zergling";404;0
"Unit";"Baneling";"Zergling";404;0
"Unit";"Baneling";"Zergling";404;0
"Unit";"Baneling";"Zergling";404;0
"Unit";"Baneling";"Zergling";404;0
"Unit";"Baneling";"Zergling";404;0
"Building";"SpineCrawler";NA;404;0
"Building";"Extractor";NA;404;0
"Building";"SpineCrawler";NA;404;0
"Unit";"Ultralisk";"Larva";404;6
"Unit";"Ultralisk";"Larva";410;6
"Unit";"Zergling";"Larva";416;1
"Unit";"Zergling";"Larva";417;1
"Unit";"Zergling";"Larva";418;1
"Unit";"Zergling";"Larva";419;1
"Unit";"Zergling";"Larva";420;1
"Unit";"Zergling";"Larva";421;1
"Unit";"Zergling";"Larva";422;1
"Unit";"Zergling";"Larva";423;1
"Unit";"Zergling";"Larva";424;1
"Unit";"Zergling";"Larva";425;1
"Unit";"Zergling";"Larva";426;1
"Unit";"Zergling";"Larva";427;1
"Unit";"Zergling";"Larva";428;1
"Unit";"Zergling";"Larva";429;1
"Unit";"Zergling";"Larva";430;1
"Unit";"Zergling";"Larva";431;1
"Unit";"Zergling";"Larva";432;1
"Unit";"Zergling";"Larva";433;1
"Unit";"Zergling";"Larva";434;1
"Unit";"Zergling";"Larva";435;1
"Unit";"Zergling";"Larva";436;1
"Unit";"Zergling";"Larva";437;1
"Unit";"Zergling";"Larva";438;1
"Unit";"Zergling";"Larva";439;1
"Unit";"Zergling";"Larva";440;1
"Unit";"Zergling";"Larva";441;1
"Unit";"Zergling";"Larva";442;1
"Unit";"Zergling";"Larva";443;1
"Unit";"Zergling";"Larva";444;1
"Unit";"Zergling";"Larva";445;1
"Unit";"Zergling";"Larva";446;1
"Unit";"Zergling";"Larva";447;1
"Unit";"Zergling";"Larva";448;1
"Unit";"Zergling";"Larva";449;1
"Unit";"Zergling";"Larva";450;1
"Unit";"Zergling";"Larva";451;1
"Unit";"Zergling";"Larva";452;1
"Unit";"Zergling";"Larva";453;1
"Unit";"Zergling";"Larva";454;1
"Unit";"Zergling";"Larva";455;1
"Unit";"Zergling";"Larva";456;1
"Unit";"Zergling";"Larva";457;1
"Unit";"Zergling";"Larva";458;1
"Unit";"Zergling";"Larva";459;1
"Unit";"Ultralisk";"Larva";460;6
"Unit";"Ultralisk";"Larva";466;6
"Unit";"Ultralisk";"Larva";472;6
"Unit";"Zergling";"Larva";478;1
"Unit";"Zergling";"Larva";479;1
"Unit";"Zergling";"Larva";480;1
"Unit";"Zergling";"Larva";481;1
"Unit";"Zergling";"Larva";482;1
"Unit";"Zergling";"Larva";483;1
"Unit";"Baneling";"Zergling";484;0
"Unit";"Baneling";"Zergling";484;0
"Unit";"Baneling";"Zergling";484;0
"Unit";"Baneling";"Zergling";484;0
"Unit";"Baneling";"Zergling";484;0
"Unit";"Baneling";"Zergling";484;0
"Unit";"Baneling";"Zergling";484;0
"Unit";"Baneling";"Zergling";484;0
"Unit";"Baneling";"Zergling";484;0
"Unit";"Baneling";"Zergling";484;0
"Unit";"Baneling";"Zergling";484;0
"Unit";"Baneling";"Zergling";484;0
"Unit";"Baneling";"Zergling";484;0
"Unit";"Zergling";"Larva";484;1
"Unit";"Zergling";"Larva";485;1
"Unit";"Zergling";"Larva";486;1
"Unit";"Zergling";"Larva";487;1
"Unit";"Zergling";"Larva";488;1
"Unit";"Zergling";"Larva";489;1
"Unit";"Baneling";"Zergling";490;0
"Unit";"Baneling";"Zergling";490;0
"Unit";"Baneling";"Zergling";490;0
"Unit";"Baneling";"Zergling";490;0
"Unit";"Baneling";"Zergling";490;0
"Unit";"Baneling";"Zergling";490;0
"Unit";"Baneling";"Zergling";490;0
"Unit";"Baneling";"Zergling";490;0
"Upgrade";"SprayZerg";NA;490;0
"Upgrade";"SprayZerg";NA;490;0
"Upgrade";"SprayZerg";NA;490;0
"Upgrade";"SprayZerg";NA;490;0
"Upgrade";"SprayZerg";NA;490;0
"Upgrade";"zerglingmovementspeed";NA;490;0
"Upgrade";"ZergMeleeWeaponsLevel1";NA;490;0
"Upgrade";"ZergGroundArmorsLevel1";NA;490;0
"Upgrade";"SprayZerg";NA;490;0
"Upgrade";"SprayZerg";NA;490;0
"Upgrade";"SprayZerg";NA;490;0
"Upgrade";"ZergMeleeWeaponsLevel2";NA;490;0
"Upgrade";"ZergGroundArmorsLevel2";NA;490;0
"Upgrade";"CentrificalHooks";NA;490;0
"Upgrade";"SprayZerg";NA;490;0
"Upgrade";"SprayZerg";NA;490;0
"Upgrade";"SprayZerg";NA;490;0
"Upgrade";"zerglingattackspeed";NA;490;0
"Upgrade";"SprayZerg";NA;490;0
"Upgrade";"ZergGroundArmorsLevel3";NA;490;0
