"type";"unit_name";"on_building";"total_supply_lag";"supply"
"Building";"Pylon";NA;14;0
"Building";"Forge";NA;16;0
"Building";"Pylon";NA;18;0
"Building";"Pylon";NA;18;0
"Building";"Pylon";NA;18;0
"Building";"Pylon";NA;18;0
"Building";"PhotonCannon";NA;19;0
"Building";"PhotonCannon";NA;19;0
"Building";"Pylon";NA;19;0
