"type";"unit_name";"on_building";"total_supply";"supply"
"Building";"Pylon";NA;13;0
"Building";"Assimilator";NA;16;0
"Building";"Assimilator";NA;17;0
"Building";"Gateway";NA;15;0
"Unit";"Zealot";"Gateway";20;2
"Building";"CyberneticsCore";NA;21;0
"Building";"Pylon";NA;23;0
"Unit";"Stalker";"Gateway";23;2
