"type";"unit_name";"on_building";"total_supply";"supply"
"Building";"Pylon";NA;13;0
"Building";"Forge";NA;14;0
"Building";"Pylon";NA;15;0
"Building";"Pylon";NA;15;0
"Building";"PhotonCannon";NA;15;0
"Building";"PhotonCannon";NA;15;0
"Building";"PhotonCannon";NA;15;0
"Building";"Gateway";NA;15;0
"Unit";"Zealot";"Gateway";15;2
"Building";"Pylon";NA;15;0
"Building";"PhotonCannon";NA;15;0
"Building";"PhotonCannon";NA;15;0
