"type";"unit_name";"on_building";"total_supply";"supply"
"Building";"Pylon";NA;13;0
"Building";"Assimilator";NA;15;0
"Building";"Gateway";NA;14;0
"Building";"Assimilator";NA;18;0
"Building";"Gateway";NA;18;0
"Building";"Pylon";NA;20;0
"Building";"CyberneticsCore";NA;19;0
"Unit";"Adept";"Gateway";22;2
"Unit";"Adept";"Gateway";22;2
"Building";"Pylon";NA;28;0
"Unit";"Stalker";"Gateway";28;2
"Building";"Stargate";NA;23;0
"Building";"ShieldBattery";NA;28;0
