"type";"unit_name";"on_building";"total_supply";"supply"
"Building";"Pylon";NA;13;0
"Building";"Assimilator";NA;16;0
"Building";"Assimilator";NA;17;0
"Building";"Gateway";NA;14;0
"Unit";"Zealot";"Gateway";18;2
"Unit";"Zealot";"Gateway";21;2
"Building";"CyberneticsCore";NA;19;0
