"type";"unit_name";"on_building";"total_supply";"supply"
"Building";"Pylon";NA;14;0
"Building";"Gateway";NA;15;0
"Building";"Forge";NA;16;0
"Building";"Assimilator";NA;16;0
"Building";"Assimilator";NA;16;0
"Building";"Pylon";NA;16;0
"Building";"PhotonCannon";NA;16;0
"Unit";"Zealot";"Gateway";16;2
"Building";"Pylon";NA;16;0
"Building";"PhotonCannon";NA;18;0
"Building";"Assimilator";NA;18;0
"Building";"Assimilator";NA;19;0
