"type";"unit_name";"on_building";"total_supply_lag";"supply"
"Building";"Refinery";NA;15;0
"Building";"Barracks";NA;16;0
"Building";"Refinery";NA;17;0
"Unit";"Reaper";"Barracks";19;1
"Building";"Factory";NA;20;0
"Unit";"Reaper";"Barracks";21;1
"Building";"Starport";NA;23;0
"Unit";"Cyclone";"Factory";24;3
"Building";"BarracksTechLab";NA;28;0
"Unit";"Banshee";"Starport";29;3
"Building";"BarracksReactor";NA;32;0
"Building";"CommandCenter";NA;32;0
"Building";"FactoryTechLab";NA;32;0
"Unit";"Raven";"Starport";35;2
"Unit";"Marine";"Barracks";37;1
"Unit";"Marine";"Barracks";38;1
"Unit";"Marine";"Barracks";40;1
"Unit";"Marine";"Barracks";41;1
"Building";"Barracks";NA;42;0
"Building";"Barracks";NA;43;0
"Unit";"Marine";"Barracks";43;1
"Unit";"Marine";"Barracks";44;1
"Unit";"Marine";"Barracks";47;1
"Building";"StarportReactor";NA;48;0
"Building";"EngineeringBay";NA;51;0
"Unit";"Marine";"Barracks";51;1
"Unit";"Marine";"Barracks";52;1
"Unit";"Marine";"Barracks";53;1
"Upgrade";"Stimpack";"TechLab";56;0
"Unit";"Marine";"Barracks";57;1
"Unit";"Marine";"Barracks";58;1
"Unit";"Marine";"Barracks";59;1
"Building";"Refinery";NA;60;0
"Building";"StarportReactor";NA;60;0
"Unit";"Marine";"Barracks";60;1
"Unit";"Marine";"Barracks";61;1
"Unit";"Marine";"Barracks";62;1
"Unit";"Marine";"Barracks";64;1
"Unit";"Marine";"Barracks";65;1
"Unit";"Marine";"Barracks";67;1
"Unit";"Marine";"Barracks";68;1
"Unit";"Marine";"Barracks";71;1
"Unit";"Marine";"Barracks";72;1
"Unit";"Marine";"Barracks";73;1
"Upgrade";"TerranInfantryWeaponsLevel1";"EngineeringBay";74;0
"Unit";"Marine";"Barracks";74;1
"Unit";"Marine";"Barracks";77;1
"Unit";"Medivac";"Starport";78;2
"Unit";"Marine";"Barracks";80;1
"Unit";"Marine";"Barracks";81;1
"Unit";"Marine";"Barracks";82;1
"Building";"Refinery";NA;83;0
"Unit";"Medivac";"Starport";83;2
"Unit";"Marine";"Barracks";87;1
"Unit";"Marine";"Barracks";88;1
"Unit";"Marine";"Barracks";89;1
"Unit";"Marine";"Barracks";90;1
"Unit";"Marine";"Barracks";91;1
"Unit";"Marine";"Barracks";94;1
"Unit";"Marine";"Barracks";95;1
"Unit";"Marine";"Barracks";96;1
"Unit";"Marine";"Barracks";97;1
"Unit";"Marine";"Barracks";98;1
"Unit";"Marine";"Barracks";99;1
"Unit";"Marine";"Barracks";102;1
"Unit";"Marine";"Barracks";103;1
"Unit";"Marine";"Barracks";104;1
"Unit";"Marine";"Barracks";105;1
"Building";"CommandCenter";NA;106;0
"Unit";"Medivac";"Starport";106;2
"Unit";"Medivac";"Starport";108;2
"Unit";"Marine";"Barracks";112;1
"Unit";"Marine";"Barracks";113;1
"Unit";"Marine";"Barracks";114;1
"Unit";"Marine";"Barracks";115;1
"Unit";"Marine";"Barracks";116;1
"Unit";"Medivac";"Starport";118;2
"Unit";"Medivac";"Starport";120;2
"Unit";"Marine";"Barracks";122;1
"Unit";"Marine";"Barracks";123;1
"Unit";"Marine";"Barracks";124;1
"Unit";"Marine";"Barracks";125;1
"Unit";"Marine";"Barracks";126;1
"Building";"EngineeringBay";NA;128;0
"Building";"Barracks";NA;128;0
"Building";"Armory";NA;128;0
"Building";"Barracks";NA;129;0
"Unit";"Medivac";"Starport";129;2
"Unit";"Marine";"Barracks";131;1
"Unit";"Marine";"Barracks";132;1
"Unit";"Marine";"Barracks";134;1
"Unit";"Marine";"Barracks";135;1
"Unit";"Marine";"Barracks";136;1
"Unit";"Marine";"Barracks";137;1
"Unit";"Marine";"Barracks";138;1
"Building";"BarracksReactor";NA;139;0
"Building";"BarracksReactor";NA;139;0
"Unit";"Marine";"Barracks";142;1
"Unit";"Marine";"Barracks";144;1
"Unit";"Marine";"Barracks";145;1
"Unit";"Marine";"Barracks";146;1
"Unit";"Marine";"Barracks";147;1
"Unit";"Marine";"Barracks";148;1
"Unit";"Medivac";"Starport";149;2
"Unit";"Medivac";"Starport";151;2
"Unit";"Marine";"Barracks";153;1
"Building";"Refinery";NA;154;0
"Unit";"Marine";"Barracks";154;1
"Unit";"Marine";"Barracks";155;1
"Unit";"Marine";"Barracks";156;1
"Building";"Refinery";NA;157;0
"Unit";"Marine";"Barracks";157;1
"Upgrade";"TerranInfantryWeaponsLevel2";"EngineeringBay";158;0
"Unit";"Marine";"Barracks";158;1
"Unit";"Marine";"Barracks";159;1
"Building";"SensorTower";NA;160;0
"Unit";"Marine";"Barracks";160;1
"Unit";"Marine";"Barracks";161;1
"Building";"MissileTurret";NA;162;0
"Unit";"Marine";"Barracks";162;1
"Unit";"Marine";"Barracks";163;1
"Unit";"Marine";"Barracks";164;1
"Unit";"Marine";"Barracks";165;1
"Unit";"Marine";"Barracks";166;1
"Unit";"Marine";"Barracks";167;1
"Unit";"Marine";"Barracks";168;1
"Unit";"Marine";"Barracks";169;1
"Unit";"Marine";"Barracks";170;1
"Unit";"Marine";"Barracks";171;1
"Unit";"Marine";"Barracks";172;1
"Unit";"Marine";"Barracks";173;1
"Unit";"Marine";"Barracks";174;1
"Unit";"Marine";"Barracks";175;1
"Unit";"Marine";"Barracks";176;1
"Unit";"Marine";"Barracks";177;1
"Unit";"Marine";"Barracks";178;1
"Unit";"Marine";"Barracks";179;1
"Unit";"Marine";"Barracks";180;1
"Unit";"Marine";"Barracks";181;1
"Unit";"Marine";"Barracks";182;1
"Unit";"Marine";"Barracks";183;1
"Unit";"Marine";"Barracks";184;1
"Unit";"Medivac";"Starport";185;2
"Unit";"Medivac";"Starport";187;2
"Unit";"Marine";"Barracks";189;1
"Unit";"Marine";"Barracks";190;1
"Unit";"Marine";"Barracks";191;1
"Unit";"Marine";"Barracks";192;1
"Building";"MissileTurret";NA;193;0
"Unit";"Marine";"Barracks";193;1
"Unit";"Marine";"Barracks";194;1
"Building";"MissileTurret";NA;195;0
"Unit";"Marine";"Barracks";195;1
"Unit";"Marine";"Barracks";196;1
"Unit";"Marine";"Barracks";197;1
"Unit";"Marine";"Barracks";198;1
"Upgrade";"TerranVehicleWeaponsLevel1";"Armory";199;0
"Unit";"Medivac";"Starport";199;2
"Unit";"Marine";"Barracks";201;1
"Unit";"Marine";"Barracks";202;1
"Unit";"Marine";"Barracks";203;1
"Unit";"Marine";"Barracks";204;1
"Unit";"Marine";"Barracks";205;1
"Unit";"Marine";"Barracks";206;1
"Unit";"Marine";"Barracks";207;1
"Unit";"Marine";"Barracks";208;1
"Unit";"Marine";"Barracks";209;1
"Unit";"Marine";"Barracks";210;1
"Building";"MissileTurret";NA;211;0
"Unit";"Medivac";"Starport";211;2
"Unit";"Marine";"Barracks";213;1
"Unit";"Marine";"Barracks";214;1
"Unit";"Marine";"Barracks";215;1
"Unit";"Marine";"Barracks";216;1
"Unit";"Marine";"Barracks";217;1
"Unit";"Marine";"Barracks";218;1
"Unit";"Marine";"Barracks";219;1
"Unit";"Marine";"Barracks";220;1
"Unit";"Marine";"Barracks";221;1
"Unit";"Marine";"Barracks";222;1
"Unit";"Marine";"Barracks";223;1
"Unit";"Marine";"Barracks";224;1
"Unit";"Marine";"Barracks";225;1
"Unit";"Marine";"Barracks";226;1
"Unit";"Medivac";"Starport";227;2
"Unit";"Medivac";"Starport";229;2
"Unit";"Marine";"Barracks";231;1
"Unit";"Marine";"Barracks";232;1
"Unit";"Marine";"Barracks";236;1
"Unit";"Marine";"Barracks";237;1
"Unit";"Marine";"Barracks";238;1
"Unit";"Marine";"Barracks";239;1
"Upgrade";"SprayTerran";NA;240;0
"Upgrade";"BansheeCloak";NA;240;0
"Upgrade";"SprayTerran";NA;240;0
"Upgrade";"SprayTerran";NA;240;0
"Upgrade";"ShieldWall";NA;240;0
"Upgrade";"SprayTerran";NA;240;0
"Upgrade";"TerranInfantryArmorsLevel1";NA;240;0
"Upgrade";"TerranInfantryArmorsLevel2";NA;240;0
