"type";"unit_name";"on_building";"total_supply";"supply"
"Building";"Pylon";NA;13;0
"Building";"Assimilator";NA;16;0
"Building";"Assimilator";NA;17;0
"Building";"Gateway";NA;15;0
"Building";"Pylon";NA;20;0
"Building";"CyberneticsCore";NA;20;0
"Building";"Gateway";NA;20;0
"Unit";"Adept";"Gateway";22;2
"Unit";"Stalker";"Gateway";23;2
"Building";"Pylon";NA;23;0
"Building";"Stargate";NA;23;0
"Unit";"Stalker";"Gateway";28;2
"Unit";"Stalker";"Gateway";28;2
