"type";"unit_name";"on_building";"total_supply";"supply"
"Building";"Pylon";NA;13;0
"Building";"Assimilator";NA;17;0
"Building";"Gateway";NA;15;0
"Unit";"Zealot";"Gateway";18;2
"Unit";"Zealot";"Gateway";20;2
"Building";"Assimilator";NA;23;0
"Building";"CyberneticsCore";NA;23;0
"Building";"Pylon";NA;23;0
"Unit";"Stalker";"Gateway";23;2
"Unit";"Stalker";"Gateway";24;2
"Unit";"Stalker";"Gateway";27;2
"Building";"Gateway";NA;26;0
