"type";"unit_name";"on_building";"total_supply";"supply"
"Building";"Pylon";NA;13;0
"Building";"Assimilator";NA;15;0
"Building";"Assimilator";NA;16;0
"Building";"Gateway";NA;15;0
"Building";"Pylon";NA;20;0
"Building";"CyberneticsCore";NA;19;0
"Building";"Gateway";NA;18;0
"Unit";"Adept";"Gateway";21;2
"Unit";"Adept";"Gateway";21;2
"Building";"Stargate";NA;27;0
"Unit";"Stalker";"Gateway";28;2
"Building";"Nexus";NA;28;0
"Building";"Pylon";NA;30;0
"Building";"Pylon";NA;30;0
"Unit";"Oracle";"Stargate";30;3
"Unit";"Stalker";"Gateway";38;2
"Unit";"Stalker";"Gateway";38;2
"Building";"ShieldBattery";NA;31;0
"Building";"RoboticsFacility";NA;30;0
"Building";"OracleStasisTrap";NA;44;0
"Building";"Pylon";NA;44;0
"Unit";"Stalker";"Gateway";47;2
"Unit";"Stalker";"Gateway";47;2
"Building";"Forge";NA;44;0
"Building";"Assimilator";NA;47;0
"Building";"Assimilator";NA;47;0
"Building";"TwilightCouncil";NA;53;0
"Building";"PhotonCannon";NA;53;0
"Unit";"Stalker";"Gateway";60;2
"Unit";"Stalker";"Gateway";61;2
"Unit";"Observer";"Robotics Facility";63;1
"Building";"Pylon";NA;70;0
"Building";"Nexus";NA;57;0
"Building";"Pylon";NA;70;0
"Building";"Assimilator";NA;72;0
"Building";"Pylon";NA;72;0
"Building";"Assimilator";NA;72;0
"Building";"Gateway";NA;67;0
"Building";"Gateway";NA;68;0
"Unit";"Stalker";"Gateway";74;2
"Unit";"Stalker";"Gateway";74;2
"Building";"Gateway";NA;70;0
"Unit";"Immortal";"Robotics Facility";70;4
"Upgrade";"ProtossGroundWeaponsLevel1";"Forge";66;0
"Unit";"Stalker";"Gateway";86;2
"Building";"PhotonCannon";NA;84;0
"Building";"PhotonCannon";NA;85;0
"Building";"TemplarArchive";NA;90;0
"Building";"HighTemplar";NA;101;0
"Building";"HighTemplar";NA;101;0
"Building";"HighTemplar";NA;101;0
"Building";"HighTemplar";NA;101;0
"Building";"HighTemplar";NA;101;0
"Unit";"Observer";"Robotics Facility";97;1
"Building";"Gateway";NA;92;0
"Building";"Gateway";NA;92;0
"Building";"Pylon";NA;105;0
"Building";"HighTemplar";NA;110;0
"Building";"HighTemplar";NA;110;0
"Building";"HighTemplar";NA;110;0
"Building";"Pylon";NA;108;0
"Building";"Pylon";NA;110;0
"Unit";"Observer";"Robotics Facility";110;1
"Building";"Pylon";NA;111;0
"Building";"HighTemplar";NA;112;0
"Building";"HighTemplar";NA;112;0
"Building";"HighTemplar";NA;112;0
"Building";"HighTemplar";NA;112;0
"Building";"Pylon";NA;111;0
"Building";"Pylon";NA;111;0
"Upgrade";"ProtossGroundWeaponsLevel2";"Forge";93;0
"Building";"Assimilator";NA;111;0
"Building";"Nexus";NA;105;0
"Upgrade";"Charge";"TwilightCouncil";105;0
"Building";"ShieldBattery";NA;111;0
"Unit";"Archon";"High Templar";114;0
"Unit";"Archon";"High Templar";114;0
"Unit";"Archon";"High Templar";114;0
"Unit";"Archon";"High Templar";114;0
"Unit";"Archon";"High Templar";114;0
"Building";"ShieldBattery";NA;111;0
"Building";"Pylon";NA;114;0
"Unit";"Archon";"High Templar";114;0
"Unit";"Zealot";"Gateway";114;2
"Unit";"Zealot";"Gateway";114;2
"Unit";"Zealot";"Gateway";114;2
"Unit";"Zealot";"Gateway";120;2
"Unit";"Zealot";"Gateway";120;2
"Unit";"Zealot";"Gateway";120;2
"Unit";"Zealot";"Gateway";120;2
"Unit";"Immortal";"Robotics Facility";114;4
"Building";"HighTemplar";NA;131;0
"Building";"HighTemplar";NA;131;0
"Building";"HighTemplar";NA;131;0
"Building";"Assimilator";NA;120;0
"Building";"HighTemplar";NA;138;0
"Unit";"Archon";"High Templar";138;0
"Building";"Assimilator";NA;131;0
"Building";"FleetBeacon";NA;114;0
"Building";"PhotonCannon";NA;130;0
"Building";"Assimilator";NA;131;0
"Unit";"Sentry";"Gateway";138;2
"Unit";"Zealot";"Gateway";138;2
"Unit";"Zealot";"Gateway";138;2
"Building";"PhotonCannon";NA;131;0
"Unit";"Archon";"High Templar";138;0
"Building";"PhotonCannon";NA;131;0
"Unit";"Immortal";"Robotics Facility";131;4
"Building";"Pylon";NA;148;0
"Building";"PhotonCannon";NA;144;0
"Building";"Gateway";NA;138;0
"Building";"Gateway";NA;138;0
"Unit";"Oracle";"Stargate";144;3
"Building";"Forge";NA;144;0
"Building";"Nexus";NA;129;0
"Building";"Gateway";NA;138;0
"Unit";"Zealot";"Gateway";151;2
"Unit";"Zealot";"Gateway";151;2
"Unit";"Zealot";"Gateway";151;2
"Unit";"Zealot";"Gateway";151;2
"Unit";"Zealot";"Gateway";151;2
"Unit";"Zealot";"Gateway";151;2
"Unit";"Zealot";"Gateway";151;2
"Unit";"Zealot";"Gateway";151;2
"Unit";"Immortal";"Robotics Facility";148;4
"Upgrade";"ProtossGroundWeaponsLevel3";"Forge";120;0
"Building";"HighTemplar";NA;171;0
"Building";"HighTemplar";NA;171;0
"Building";"Forge";NA;167;0
"Building";"HighTemplar";NA;171;0
"Unit";"Mothership";"Mothership Core";167;6
"Unit";"Observer";"Robotics Facility";171;1
"Building";"HighTemplar";NA;178;0
"Unit";"Archon";"High Templar";178;0
"Unit";"Phoenix";"Stargate";171;2
"Upgrade";"ProtossGroundArmorsLevel1";"Forge";171;0
"Unit";"Archon";"High Templar";180;0
"Building";"PhotonCannon";NA;178;0
"Building";"PhotonCannon";NA;180;0
"Building";"PhotonCannon";NA;180;0
"Building";"Stargate";NA;178;0
"Building";"ShieldBattery";NA;180;0
"Building";"ShieldBattery";NA;180;0
"Building";"Stargate";NA;178;0
"Unit";"Phoenix";"Stargate";180;2
"Building";"Stargate";NA;178;0
"Upgrade";"ProtossShieldsLevel1";"Forge";171;0
"Upgrade";"ProtossAirWeaponsLevel1";"CyberneticsCore";171;0
"Unit";"Phoenix";"Stargate";180;2
"Building";"HighTemplar";NA;184;0
"Building";"HighTemplar";NA;184;0
"Building";"HighTemplar";NA;184;0
"Building";"HighTemplar";NA;184;0
"Building";"HighTemplar";NA;184;0
"Building";"HighTemplar";NA;184;0
"Building";"HighTemplar";NA;184;0
"Unit";"Zealot";"Gateway";184;2
"Unit";"Zealot";"Gateway";184;2
"Unit";"Zealot";"Gateway";188;2
"Unit";"Stalker";"Gateway";190;2
"Unit";"Stalker";"Gateway";190;2
"Unit";"Stalker";"Gateway";194;2
"Unit";"Stalker";"Gateway";194;2
"Unit";"Stalker";"Gateway";194;2
"Unit";"Stalker";"Gateway";194;2
"Unit";"Archon";"High Templar";190;0
"Unit";"Stalker";"Gateway";194;2
"Unit";"Stalker";"Gateway";194;2
"Unit";"Stalker";"Gateway";194;2
"Unit";"Archon";"High Templar";190;0
"Unit";"Stalker";"Gateway";194;2
"Unit";"Archon";"High Templar";190;0
"Unit";"Carrier";"Stargate";184;6
"Unit";"Carrier";"Stargate";184;6
"Unit";"Carrier";"Stargate";184;6
"Unit";"Carrier";"Stargate";184;6
"Upgrade";"ProtossGroundArmorsLevel2";"Forge";184;0
"Upgrade";"ProtossShieldsLevel2";"Forge";184;0
"Unit";"Zealot";"Gateway";234;2
"Unit";"Zealot";"Gateway";234;2
"Unit";"Zealot";"Gateway";234;2
"Unit";"Zealot";"Gateway";234;2
"Unit";"Zealot";"Gateway";234;2
"Unit";"Zealot";"Gateway";234;2
"Unit";"Zealot";"Gateway";234;2
"Unit";"Zealot";"Gateway";234;2
"Unit";"Zealot";"Gateway";234;2
"Building";"HighTemplar";NA;255;0
"Building";"HighTemplar";NA;255;0
"Building";"HighTemplar";NA;255;0
"Building";"HighTemplar";NA;255;0
"Building";"HighTemplar";NA;255;0
"Building";"HighTemplar";NA;255;0
"Unit";"Carrier";"Stargate";210;6
"Unit";"Carrier";"Stargate";210;6
