"type";"unit_name";"on_building";"total_supply";"supply"
"Building";"Pylon";NA;13;0
"Building";"Assimilator";NA;16;0
"Building";"Assimilator";NA;17;0
"Building";"Gateway";NA;15;0
"Building";"Gateway";NA;18;0
"Building";"Pylon";NA;21;0
"Building";"CyberneticsCore";NA;19;0
"Unit";"Stalker";"Gateway";22;2
"Unit";"Stalker";"Gateway";22;2
"Building";"Pylon";NA;24;0
"Unit";"Stalker";"Gateway";30;2
"Building";"TwilightCouncil";NA;30;0
"Building";"Pylon";NA;32;0
"Unit";"Stalker";"Gateway";31;2
"Building";"Pylon";NA;32;0
"Unit";"Stalker";"Gateway";40;2
"Unit";"Stalker";"Gateway";40;2
"Building";"ShieldBattery";NA;39;0
"Unit";"Stalker";"Gateway";45;2
"Unit";"Stalker";"Gateway";45;2
"Building";"Nexus";NA;39;0
"Building";"RoboticsFacility";NA;44;0
"Unit";"Stalker";"Gateway";50;2
"Unit";"Stalker";"Gateway";55;2
"Unit";"Observer";"Robotics Facility";51;1
"Building";"Gateway";NA;48;0
"Building";"Assimilator";NA;61;0
"Unit";"Stalker";"Gateway";62;2
"Unit";"Stalker";"Gateway";62;2
"Building";"Pylon";NA;61;0
"Building";"Assimilator";NA;61;0
"Unit";"Stalker";"Gateway";68;2
"Unit";"Stalker";"Gateway";68;2
"Building";"ShieldBattery";NA;66;0
"Unit";"Immortal";"Robotics Facility";62;4
"Unit";"Sentry";"Gateway";73;2
"Building";"Pylon";NA;68;0
"Building";"Pylon";NA;73;0
"Building";"ShieldBattery";NA;68;0
"Building";"Pylon";NA;73;0
"Unit";"Sentry";"Gateway";82;2
"Building";"Pylon";NA;85;0
"Building";"RoboticsBay";NA;80;0
"Upgrade";"Charge";"TwilightCouncil";73;0
"Unit";"Immortal";"Robotics Facility";82;4
"Unit";"Stalker";"Gateway";92;2
"Unit";"Stalker";"Gateway";92;2
"Unit";"Stalker";"Gateway";92;2
"Building";"Forge";NA;86;0
"Unit";"Disruptor";"Robotics Facility";87;3
"Unit";"Phoenix";"Stargate";92;2
"Building";"Nexus";NA;85;0
"Building";"RoboticsFacility";NA;87;0
"Building";"PhotonCannon";NA;98;0
"Unit";"Disruptor";"Robotics Facility";99;3
"Unit";"Disruptor";"Robotics Facility";103;3
"Building";"Assimilator";NA;106;0
"Building";"PhotonCannon";NA;106;0
"Unit";"Phoenix";"Stargate";107;2
"Building";"ShieldBattery";NA;106;0
"Building";"Assimilator";NA;107;0
"Building";"Pylon";NA;116;0
"Unit";"Disruptor";"Robotics Facility";109;3
"Building";"Pylon";NA;119;0
"Unit";"Disruptor";"Robotics Facility";113;3
"Unit";"Stalker";"Gateway";129;2
"Unit";"Stalker";"Gateway";129;2
"Unit";"Disruptor";"Robotics Facility";122;3
"Unit";"Disruptor";"Robotics Facility";122;3
"Upgrade";"ProtossGroundWeaponsLevel1";"Forge";107;0
"Building";"PhotonCannon";NA;133;0
"Building";"Pylon";NA;142;0
"Unit";"Disruptor";"Robotics Facility";135;3
"Building";"Pylon";NA;143;0
"Unit";"Disruptor";"Robotics Facility";135;3
"Building";"Pylon";NA;143;0
"Building";"Gateway";NA;135;0
"Building";"Gateway";NA;136;0
"Building";"Gateway";NA;136;0
"Building";"Gateway";NA;142;0
"Building";"TemplarArchive";NA;143;0
"Building";"Gateway";NA;142;0
"Building";"HighTemplar";NA;149;0
"Building";"HighTemplar";NA;149;0
"Building";"Pylon";NA;149;0
"Unit";"Zealot";"Gateway";149;2
"Unit";"Zealot";"Gateway";149;2
"Unit";"Archon";"High Templar";149;0
"Building";"PhotonCannon";NA;149;0
"Unit";"Phoenix";"Stargate";149;2
"Building";"HighTemplar";NA;157;0
"Building";"HighTemplar";NA;157;0
"Unit";"Zealot";"Gateway";157;2
"Unit";"Zealot";"Gateway";158;2
"Building";"Pylon";NA;155;0
"Unit";"Disruptor";"Robotics Facility";149;3
"Unit";"Disruptor";"Robotics Facility";149;3
"Building";"Pylon";NA;155;0
"Building";"Pylon";NA;155;0
"Unit";"Archon";"High Templar";162;0
"Building";"PhotonCannon";NA;155;0
"Building";"ShieldBattery";NA;155;0
"Unit";"Zealot";"Gateway";171;2
"Unit";"Zealot";"Gateway";171;2
"Unit";"Zealot";"Gateway";171;2
"Unit";"Phoenix";"Stargate";157;2
"Building";"Pylon";NA;168;0
"Building";"Pylon";NA;168;0
"Building";"Pylon";NA;169;0
"Unit";"Zealot";"Gateway";180;2
"Unit";"Zealot";"Gateway";180;2
"Building";"PhotonCannon";NA;171;0
"Upgrade";"ProtossGroundWeaponsLevel2";"Forge";149;0
"Building";"PhotonCannon";NA;180;0
"Building";"Nexus";NA;155;0
"Unit";"Zealot";"Gateway";184;2
"Unit";"Zealot";"Gateway";184;2
"Unit";"Zealot";"Gateway";184;2
"Unit";"Zealot";"Gateway";184;2
"Building";"PhotonCannon";NA;184;0
"Unit";"Zealot";"Gateway";184;2
"Unit";"Zealot";"Gateway";184;2
"Building";"Pylon";NA;190;0
"Building";"Pylon";NA;196;0
"Unit";"Stalker";"Gateway";199;2
"Unit";"Stalker";"Gateway";199;2
"Building";"Pylon";NA;196;0
"Building";"Pylon";NA;197;0
"Building";"HighTemplar";NA;203;0
"Building";"HighTemplar";NA;203;0
"Building";"HighTemplar";NA;203;0
"Building";"HighTemplar";NA;203;0
"Unit";"Stalker";"Gateway";204;2
"Unit";"Archon";"High Templar";203;0
"Building";"PhotonCannon";NA;199;0
"Unit";"Archon";"High Templar";204;0
"Building";"PhotonCannon";NA;199;0
"Building";"Pylon";NA;203;0
"Building";"Assimilator";NA;203;0
"Building";"Assimilator";NA;203;0
"Building";"PhotonCannon";NA;203;0
"Building";"PhotonCannon";NA;203;0
"Building";"PhotonCannon";NA;203;0
"Building";"HighTemplar";NA;207;0
"Building";"HighTemplar";NA;207;0
"Building";"HighTemplar";NA;207;0
"Building";"HighTemplar";NA;207;0
"Building";"HighTemplar";NA;207;0
"Building";"HighTemplar";NA;207;0
"Unit";"Archon";"High Templar";207;0
"Unit";"Archon";"High Templar";207;0
"Unit";"Archon";"High Templar";207;0
"Unit";"Observer";"Robotics Facility";207;1
"Unit";"Observer";"Robotics Facility";207;1
"Unit";"Stalker";"Gateway";207;2
"Building";"Pylon";NA;207;0
"Building";"Gateway";NA;206;0
"Building";"Gateway";NA;206;0
"Building";"Gateway";NA;206;0
"Building";"Gateway";NA;206;0
"Building";"HighTemplar";NA;211;0
"Building";"HighTemplar";NA;211;0
"Building";"HighTemplar";NA;211;0
"Building";"HighTemplar";NA;211;0
"Building";"HighTemplar";NA;211;0
"Building";"HighTemplar";NA;211;0
"Unit";"Archon";"High Templar";212;0
"Unit";"Archon";"High Templar";212;0
"Unit";"Archon";"High Templar";212;0
"Unit";"Immortal";"Robotics Facility";207;4
"Unit";"Zealot";"Gateway";217;2
"Building";"ShieldBattery";NA;211;0
"Building";"PhotonCannon";NA;212;0
"Unit";"Zealot";"Gateway";222;2
"Unit";"Zealot";"Gateway";223;2
"Unit";"Zealot";"Gateway";223;2
"Unit";"Zealot";"Gateway";223;2
"Unit";"Zealot";"Gateway";224;2
"Unit";"Zealot";"Gateway";224;2
"Unit";"Zealot";"Gateway";224;2
"Unit";"Zealot";"Gateway";224;2
