"type";"unit_name";"on_building";"total_supply";"supply"
"Building";"Pylon";NA;13;0
"Building";"Assimilator";NA;16;0
"Building";"Gateway";NA;14;0
"Building";"Assimilator";NA;17;0
"Building";"Pylon";NA;20;0
"Building";"CyberneticsCore";NA;19;0
"Building";"Gateway";NA;18;0
"Unit";"Adept";"Gateway";21;2
"Unit";"Adept";"Gateway";22;2
"Building";"Pylon";NA;23;0
"Building";"Pylon";NA;27;0
"Unit";"Stalker";"Gateway";27;2
