"type";"unit_name";"on_building";"total_supply";"supply"
"Building";"Pylon";NA;13;0
"Building";"Assimilator";NA;15;0
"Building";"Pylon";NA;16;0
"Building";"Gateway";NA;15;0
"Building";"Gateway";NA;17;0
"Building";"Gateway";NA;17;0
"Building";"CyberneticsCore";NA;17;0
"Building";"Assimilator";NA;18;0
"Unit";"Adept";"Gateway";19;2
"Unit";"Adept";"Gateway";19;2
"Building";"Pylon";NA;21;0
"Unit";"Adept";"Gateway";22;2
"Unit";"Adept";"Gateway";22;2
"Unit";"Stalker";"Gateway";26;2
