"type";"unit_name";"on_building";"total_supply";"supply"
"Building";"Pylon";NA;13;0
"Building";"Assimilator";NA;16;0
"Building";"Assimilator";NA;16;0
"Building";"Gateway";NA;15;0
"Unit";"Zealot";"Gateway";18;2
"Building";"Pylon";NA;18;0
"Building";"Gateway";NA;17;0
"Building";"CyberneticsCore";NA;20;0
