"type";"unit_name";"on_building";"total_supply";"supply"
"Building";"Pylon";NA;13;0
"Building";"Forge";NA;16;0
"Building";"Pylon";NA;18;0
"Building";"Pylon";NA;18;0
"Building";"Pylon";NA;18;0
"Building";"Pylon";NA;18;0
"Building";"PhotonCannon";NA;18;0
"Building";"Pylon";NA;18;0
