"type";"unit_name";"on_building";"total_supply_lag";"supply"
"Unit";"Overlord";"Larva";13;0
"Building";"SpawningPool";NA;16;0
"Building";"Extractor";NA;18;0
"Building";"Hatchery";NA;19;0
"Unit";"Zergling";"Larva";19;1
"Unit";"Zergling";"Larva";20;1
"Unit";"Zergling";"Larva";21;1
"Unit";"Zergling";"Larva";22;1
"Unit";"Zergling";"Larva";23;1
"Unit";"Zergling";"Larva";24;1
"Unit";"Queen";"Hatchery";25;2
"Unit";"Overlord";"Larva";27;0
"Unit";"Queen";"Hatchery";32;2
"Unit";"Queen";"Hatchery";34;2
"Unit";"Overlord";"Larva";41;0
"Building";"CreepTumorQueen";NA;42;0
"Building";"Hatchery";NA;43;0
"Building";"CreepTumor";NA;51;0
"Unit";"Overlord";"Larva";51;0
"Building";"EvolutionChamber";NA;51;0
"Building";"CreepTumorQueen";NA;52;0
"Unit";"Overlord";"Larva";52;0
"Unit";"Queen";"Hatchery";52;2
"Unit";"Queen";"Hatchery";57;2
"Unit";"Overlord";"Larva";60;0
"Building";"CreepTumor";NA;60;0
"Unit";"Overlord";"Larva";60;0
"Unit";"Overlord";"Larva";62;0
"Unit";"Queen";"Hatchery";67;2
"Building";"CreepTumor";NA;69;0
"Unit";"Queen";"Hatchery";69;2
"Building";"SporeCrawler";NA;71;0
"Building";"SporeCrawler";NA;72;0
"Building";"CreepTumorQueen";NA;74;0
"Building";"SporeCrawler";NA;75;0
"Building";"CreepTumor";NA;75;0
"Building";"CreepTumorQueen";NA;78;0
"Building";"CreepTumor";NA;82;0
"Building";"Extractor";NA;85;0
"Building";"CreepTumor";NA;88;0
"Building";"CreepTumorQueen";NA;90;0
"Building";"Extractor";NA;92;0
"Building";"Extractor";NA;92;0
"Unit";"Zergling";"Larva";92;1
"Unit";"Zergling";"Larva";93;1
"Unit";"Zergling";"Larva";94;1
"Unit";"Zergling";"Larva";95;1
"Unit";"Zergling";"Larva";96;1
"Unit";"Zergling";"Larva";97;1
"Unit";"Overlord";"Larva";99;0
"Building";"Extractor";NA;99;0
"Building";"Extractor";NA;100;0
"Building";"Spire";NA;103;0
"Unit";"Zergling";"Larva";104;1
"Unit";"Zergling";"Larva";105;1
"Unit";"Zergling";"Larva";106;1
"Unit";"Zergling";"Larva";107;1
"Unit";"Zergling";"Larva";108;1
"Unit";"Zergling";"Larva";109;1
"Unit";"Zergling";"Larva";110;1
"Unit";"Zergling";"Larva";111;1
"Unit";"Zergling";"Larva";112;1
"Unit";"Zergling";"Larva";113;1
"Unit";"Zergling";"Larva";114;1
"Unit";"Zergling";"Larva";115;1
"Unit";"Zergling";"Larva";116;1
"Unit";"Zergling";"Larva";117;1
"Unit";"Zergling";"Larva";118;1
"Unit";"Zergling";"Larva";119;1
"Unit";"Zergling";"Larva";120;1
"Unit";"Zergling";"Larva";121;1
"Unit";"Zergling";"Larva";122;1
"Unit";"Zergling";"Larva";123;1
"Unit";"Zergling";"Larva";124;1
"Unit";"Zergling";"Larva";125;1
"Unit";"Zergling";"Larva";126;1
"Unit";"Zergling";"Larva";127;1
"Unit";"Zergling";"Larva";128;1
"Unit";"Zergling";"Larva";129;1
"Unit";"Zergling";"Larva";130;1
"Unit";"Zergling";"Larva";131;1
"Unit";"Zergling";"Larva";132;1
"Unit";"Zergling";"Larva";133;1
"Unit";"Zergling";"Larva";134;1
"Unit";"Zergling";"Larva";135;1
"Unit";"Zergling";"Larva";136;1
"Unit";"Zergling";"Larva";137;1
"Unit";"Overlord";"Larva";147;0
"Building";"CreepTumor";NA;147;0
"Unit";"Overlord";"Larva";147;0
"Unit";"Overlord";"Larva";147;0
"Unit";"Overlord";"Larva";147;0
"Building";"CreepTumor";NA;150;0
"Building";"CreepTumor";NA;150;0
"Unit";"Mutalisk";"Larva";150;2
"Unit";"Mutalisk";"Larva";152;2
"Unit";"Mutalisk";"Larva";154;2
"Unit";"Mutalisk";"Larva";156;2
"Unit";"Mutalisk";"Larva";158;2
"Unit";"Mutalisk";"Larva";160;2
"Unit";"Mutalisk";"Larva";162;2
"Building";"Hatchery";NA;164;0
"Building";"Hatchery";NA;164;0
"Unit";"Mutalisk";"Larva";164;2
"Unit";"Mutalisk";"Larva";166;2
"Unit";"Zergling";"Larva";168;1
"Unit";"Zergling";"Larva";169;1
"Unit";"Zergling";"Larva";170;1
"Unit";"Zergling";"Larva";171;1
"Unit";"Zergling";"Larva";172;1
"Unit";"Zergling";"Larva";173;1
"Unit";"Zergling";"Larva";174;1
"Unit";"Zergling";"Larva";175;1
"Unit";"Zergling";"Larva";176;1
"Unit";"Zergling";"Larva";177;1
"Unit";"Zergling";"Larva";178;1
"Unit";"Zergling";"Larva";179;1
"Unit";"Mutalisk";"Larva";183;2
"Building";"BanelingNest";NA;185;0
"Unit";"Mutalisk";"Larva";185;2
"Unit";"Overlord";"Larva";187;0
"Unit";"Overlord";"Larva";187;0
"Building";"CreepTumor";NA;187;0
"Building";"CreepTumor";NA;187;0
"Building";"CreepTumor";NA;187;0
"Unit";"Overlord";"Larva";187;0
"Building";"CreepTumor";NA;187;0
"Unit";"Overlord";"Larva";187;0
"Unit";"Overlord";"Larva";187;0
"Unit";"Overlord";"Larva";187;0
"Building";"CreepTumorQueen";NA;187;0
"Unit";"Zergling";"Larva";187;1
"Unit";"Zergling";"Larva";188;1
"Building";"CreepTumorQueen";NA;189;0
"Unit";"Zergling";"Larva";189;1
"Unit";"Zergling";"Larva";190;1
"Unit";"Zergling";"Larva";191;1
"Unit";"Zergling";"Larva";192;1
"Unit";"Zergling";"Larva";193;1
"Unit";"Zergling";"Larva";194;1
"Unit";"Zergling";"Larva";195;1
"Unit";"Zergling";"Larva";196;1
"Building";"CreepTumorQueen";NA;197;0
"Building";"CreepTumorQueen";NA;197;0
"Unit";"Mutalisk";"Larva";198;2
"Unit";"Zergling";"Larva";200;1
"Unit";"Zergling";"Larva";201;1
"Unit";"Zergling";"Larva";202;1
"Unit";"Zergling";"Larva";203;1
"Unit";"Zergling";"Larva";204;1
"Unit";"Zergling";"Larva";205;1
"Unit";"Zergling";"Larva";206;1
"Unit";"Zergling";"Larva";207;1
"Building";"CreepTumorQueen";NA;208;0
"Unit";"Mutalisk";"Larva";208;2
"Unit";"Mutalisk";"Larva";210;2
"Unit";"Mutalisk";"Larva";212;2
"Unit";"Mutalisk";"Larva";214;2
"Unit";"Mutalisk";"Larva";216;2
"Unit";"Mutalisk";"Larva";218;2
"Unit";"Mutalisk";"Larva";220;2
"Unit";"Zergling";"Larva";222;1
"Unit";"Zergling";"Larva";223;1
"Unit";"Zergling";"Larva";224;1
"Unit";"Zergling";"Larva";225;1
"Unit";"Zergling";"Larva";226;1
"Unit";"Zergling";"Larva";227;1
"Unit";"Zergling";"Larva";228;1
"Unit";"Zergling";"Larva";229;1
"Unit";"Zergling";"Larva";230;1
"Unit";"Zergling";"Larva";231;1
"Unit";"Zergling";"Larva";232;1
"Unit";"Zergling";"Larva";233;1
"Unit";"Zergling";"Larva";234;1
"Unit";"Zergling";"Larva";235;1
"Unit";"Zergling";"Larva";236;1
"Unit";"Zergling";"Larva";237;1
"Building";"CreepTumor";NA;238;0
"Unit";"Zergling";"Larva";238;1
"Unit";"Zergling";"Larva";239;1
"Unit";"Zergling";"Larva";240;1
"Unit";"Zergling";"Larva";241;1
"Building";"CreepTumor";NA;242;0
"Building";"CreepTumor";NA;242;0
"Building";"CreepTumor";NA;242;0
"Unit";"Zergling";"Larva";249;1
"Unit";"Zergling";"Larva";250;1
"Unit";"Zergling";"Larva";251;1
"Unit";"Zergling";"Larva";252;1
"Building";"Extractor";NA;253;0
"Building";"CreepTumor";NA;253;0
"Building";"CreepTumor";NA;253;0
"Building";"CreepTumor";NA;253;0
"Unit";"Zergling";"Larva";253;1
"Unit";"Zergling";"Larva";254;1
"Unit";"Zergling";"Larva";255;1
"Unit";"Zergling";"Larva";256;1
"Unit";"Zergling";"Larva";257;1
"Unit";"Zergling";"Larva";258;1
"Building";"CreepTumorQueen";NA;259;0
"Unit";"Zergling";"Larva";259;1
"Unit";"Zergling";"Larva";260;1
"Unit";"Baneling";"Zergling";261;0
"Unit";"Baneling";"Zergling";261;0
"Unit";"Baneling";"Zergling";261;0
"Unit";"Baneling";"Zergling";261;0
"Unit";"Baneling";"Zergling";261;0
"Unit";"Baneling";"Zergling";261;0
"Unit";"Overlord";"Larva";261;0
"Unit";"Zergling";"Larva";261;1
"Unit";"Zergling";"Larva";262;1
"Building";"CreepTumor";NA;263;0
"Unit";"Zergling";"Larva";263;1
"Unit";"Zergling";"Larva";264;1
"Unit";"Zergling";"Larva";265;1
"Unit";"Zergling";"Larva";266;1
"Unit";"Zergling";"Larva";267;1
"Unit";"Zergling";"Larva";268;1
"Unit";"Overlord";"Larva";271;0
"Unit";"Overlord";"Larva";271;0
"Unit";"Overlord";"Larva";271;0
"Unit";"Zergling";"Larva";271;1
"Unit";"Zergling";"Larva";272;1
"Unit";"Mutalisk";"Larva";273;2
"Unit";"Mutalisk";"Larva";275;2
"Unit";"Mutalisk";"Larva";277;2
"Building";"CreepTumor";NA;286;0
"Unit";"Zergling";"Larva";286;1
"Unit";"Zergling";"Larva";287;1
"Unit";"Zergling";"Larva";288;1
"Unit";"Zergling";"Larva";289;1
"Unit";"Zergling";"Larva";290;1
"Unit";"Zergling";"Larva";291;1
"Unit";"Zergling";"Larva";292;1
"Unit";"Zergling";"Larva";293;1
"Unit";"Zergling";"Larva";294;1
"Unit";"Zergling";"Larva";295;1
"Unit";"Zergling";"Larva";296;1
"Unit";"Zergling";"Larva";297;1
"Unit";"Zergling";"Larva";298;1
"Unit";"Zergling";"Larva";299;1
"Unit";"Baneling";"Zergling";300;0
"Unit";"Baneling";"Zergling";300;0
"Unit";"Baneling";"Zergling";300;0
"Unit";"Baneling";"Zergling";300;0
"Unit";"Baneling";"Zergling";300;0
"Unit";"Baneling";"Zergling";300;0
"Unit";"Baneling";"Zergling";300;0
"Unit";"Baneling";"Zergling";300;0
"Unit";"Baneling";"Zergling";300;0
"Unit";"Baneling";"Zergling";300;0
"Unit";"Baneling";"Zergling";300;0
"Unit";"Baneling";"Zergling";300;0
"Unit";"Baneling";"Zergling";300;0
"Unit";"Zergling";"Larva";300;1
"Unit";"Zergling";"Larva";301;1
"Unit";"Zergling";"Larva";302;1
"Unit";"Zergling";"Larva";303;1
"Unit";"Zergling";"Larva";304;1
"Unit";"Zergling";"Larva";305;1
"Unit";"Zergling";"Larva";306;1
"Unit";"Zergling";"Larva";307;1
"Unit";"Baneling";"Zergling";308;0
"Unit";"Baneling";"Zergling";308;0
"Unit";"Baneling";"Zergling";308;0
"Unit";"Baneling";"Zergling";308;0
"Unit";"Baneling";"Zergling";308;0
"Unit";"Zergling";"Larva";308;1
"Unit";"Zergling";"Larva";309;1
"Unit";"Zergling";"Larva";310;1
"Unit";"Zergling";"Larva";311;1
"Unit";"Zergling";"Larva";312;1
"Unit";"Zergling";"Larva";313;1
"Unit";"Zergling";"Larva";314;1
"Unit";"Zergling";"Larva";315;1
"Unit";"Zergling";"Larva";316;1
"Unit";"Zergling";"Larva";317;1
"Unit";"Zergling";"Larva";318;1
"Unit";"Zergling";"Larva";319;1
"Unit";"Overlord";"Larva";320;0
"Unit";"Overlord";"Larva";320;0
"Unit";"Overlord";"Larva";320;0
"Unit";"Overlord";"Larva";320;0
"Unit";"Overlord";"Larva";320;0
"Building";"CreepTumor";NA;320;0
"Unit";"Baneling";"Zergling";320;0
"Unit";"Baneling";"Zergling";320;0
"Unit";"Baneling";"Zergling";320;0
"Unit";"Baneling";"Zergling";320;0
"Unit";"Baneling";"Zergling";320;0
"Unit";"Baneling";"Zergling";320;0
"Unit";"Baneling";"Zergling";320;0
"Unit";"Baneling";"Zergling";320;0
"Unit";"Baneling";"Zergling";320;0
"Building";"Hatchery";NA;320;0
"Unit";"Baneling";"Zergling";320;0
"Unit";"Baneling";"Zergling";320;0
"Unit";"Baneling";"Zergling";320;0
"Unit";"Baneling";"Zergling";320;0
"Unit";"Baneling";"Zergling";320;0
"Unit";"Baneling";"Zergling";320;0
"Unit";"Baneling";"Zergling";320;0
"Unit";"Baneling";"Zergling";320;0
"Unit";"Zergling";"Larva";320;1
"Unit";"Zergling";"Larva";321;1
"Unit";"Zergling";"Larva";322;1
"Unit";"Zergling";"Larva";323;1
"Unit";"Zergling";"Larva";324;1
"Unit";"Zergling";"Larva";325;1
"Unit";"Zergling";"Larva";326;1
"Unit";"Zergling";"Larva";327;1
"Unit";"Zergling";"Larva";328;1
"Unit";"Zergling";"Larva";329;1
"Unit";"Zergling";"Larva";330;1
"Unit";"Zergling";"Larva";331;1
"Unit";"Zergling";"Larva";332;1
"Unit";"Zergling";"Larva";333;1
"Unit";"Zergling";"Larva";334;1
"Unit";"Zergling";"Larva";335;1
"Unit";"Zergling";"Larva";336;1
"Unit";"Zergling";"Larva";337;1
"Unit";"Baneling";"Zergling";338;0
"Unit";"Baneling";"Zergling";338;0
"Unit";"Baneling";"Zergling";338;0
"Unit";"Baneling";"Zergling";338;0
"Unit";"Baneling";"Zergling";338;0
"Unit";"Baneling";"Zergling";338;0
"Unit";"Baneling";"Zergling";338;0
"Unit";"Baneling";"Zergling";338;0
"Unit";"Baneling";"Zergling";338;0
"Unit";"Baneling";"Zergling";338;0
"Unit";"Baneling";"Zergling";338;0
"Unit";"Baneling";"Zergling";338;0
"Unit";"Baneling";"Zergling";338;0
"Unit";"Baneling";"Zergling";338;0
"Unit";"Baneling";"Zergling";338;0
"Unit";"Baneling";"Zergling";338;0
"Unit";"Baneling";"Zergling";338;0
"Unit";"Zergling";"Larva";338;1
"Unit";"Zergling";"Larva";339;1
"Unit";"Zergling";"Larva";340;1
"Unit";"Zergling";"Larva";341;1
"Unit";"Zergling";"Larva";342;1
"Unit";"Zergling";"Larva";343;1
"Unit";"Zergling";"Larva";344;1
"Unit";"Zergling";"Larva";345;1
"Unit";"Zergling";"Larva";346;1
"Unit";"Zergling";"Larva";347;1
"Building";"CreepTumorQueen";NA;348;0
"Building";"CreepTumorQueen";NA;348;0
"Building";"CreepTumorQueen";NA;348;0
"Unit";"Zergling";"Larva";348;1
"Unit";"Zergling";"Larva";349;1
"Unit";"Zergling";"Larva";350;1
"Unit";"Zergling";"Larva";351;1
"Unit";"Zergling";"Larva";352;1
"Unit";"Zergling";"Larva";353;1
"Unit";"Zergling";"Larva";354;1
"Unit";"Zergling";"Larva";355;1
"Unit";"Zergling";"Larva";356;1
"Unit";"Zergling";"Larva";357;1
"Unit";"Zergling";"Larva";358;1
"Unit";"Zergling";"Larva";359;1
"Unit";"Zergling";"Larva";360;1
"Unit";"Zergling";"Larva";361;1
"Unit";"Zergling";"Larva";362;1
"Unit";"Zergling";"Larva";363;1
"Unit";"Zergling";"Larva";364;1
"Unit";"Zergling";"Larva";365;1
"Unit";"Zergling";"Larva";366;1
"Unit";"Zergling";"Larva";367;1
"Unit";"Zergling";"Larva";368;1
"Unit";"Zergling";"Larva";369;1
"Unit";"Zergling";"Larva";370;1
"Unit";"Zergling";"Larva";371;1
"Unit";"Zergling";"Larva";372;1
"Unit";"Zergling";"Larva";373;1
"Unit";"Zergling";"Larva";374;1
"Unit";"Zergling";"Larva";375;1
"Unit";"Zergling";"Larva";376;1
"Unit";"Zergling";"Larva";377;1
"Unit";"Zergling";"Larva";378;1
"Unit";"Zergling";"Larva";379;1
"Unit";"Zergling";"Larva";380;1
"Unit";"Zergling";"Larva";381;1
"Unit";"Zergling";"Larva";382;1
"Unit";"Zergling";"Larva";383;1
"Unit";"Zergling";"Larva";384;1
"Unit";"Zergling";"Larva";385;1
"Unit";"Zergling";"Larva";386;1
"Unit";"Zergling";"Larva";387;1
"Unit";"Zergling";"Larva";388;1
"Unit";"Zergling";"Larva";389;1
"Unit";"Zergling";"Larva";390;1
"Unit";"Zergling";"Larva";391;1
"Unit";"Mutalisk";"Larva";392;2
"Unit";"Mutalisk";"Larva";394;2
"Unit";"Mutalisk";"Larva";396;2
"Unit";"Mutalisk";"Larva";398;2
"Unit";"Mutalisk";"Larva";400;2
"Unit";"Mutalisk";"Larva";402;2
"Unit";"Mutalisk";"Larva";404;2
"Unit";"Mutalisk";"Larva";406;2
"Unit";"Zergling";"Larva";408;1
"Unit";"Zergling";"Larva";409;1
"Unit";"Zergling";"Larva";410;1
"Unit";"Zergling";"Larva";411;1
"Unit";"Zergling";"Larva";412;1
"Unit";"Zergling";"Larva";413;1
"Building";"CreepTumor";NA;414;0
"Building";"CreepTumor";NA;414;0
"Building";"CreepTumor";NA;414;0
"Building";"CreepTumorQueen";NA;414;0
"Unit";"Zergling";"Larva";414;1
"Unit";"Zergling";"Larva";415;1
"Unit";"Zergling";"Larva";416;1
"Unit";"Zergling";"Larva";417;1
"Unit";"Baneling";"Zergling";419;0
"Unit";"Baneling";"Zergling";419;0
"Unit";"Baneling";"Zergling";419;0
"Unit";"Baneling";"Zergling";419;0
"Unit";"Baneling";"Zergling";419;0
"Unit";"Baneling";"Zergling";419;0
"Unit";"Baneling";"Zergling";419;0
"Unit";"Baneling";"Zergling";419;0
"Unit";"Baneling";"Zergling";419;0
"Unit";"Zergling";"Larva";419;1
"Unit";"Zergling";"Larva";420;1
"Unit";"Zergling";"Larva";421;1
"Unit";"Zergling";"Larva";422;1
"Unit";"Zergling";"Larva";423;1
"Unit";"Zergling";"Larva";424;1
"Unit";"Zergling";"Larva";425;1
"Unit";"Zergling";"Larva";426;1
"Unit";"Zergling";"Larva";427;1
"Unit";"Zergling";"Larva";428;1
"Unit";"Zergling";"Larva";429;1
"Unit";"Zergling";"Larva";430;1
"Unit";"Zergling";"Larva";431;1
"Unit";"Zergling";"Larva";432;1
"Unit";"Zergling";"Larva";433;1
"Unit";"Zergling";"Larva";434;1
"Unit";"Zergling";"Larva";435;1
"Unit";"Zergling";"Larva";436;1
"Unit";"Zergling";"Larva";437;1
"Unit";"Zergling";"Larva";438;1
"Unit";"Zergling";"Larva";439;1
"Unit";"Zergling";"Larva";440;1
"Unit";"Zergling";"Larva";441;1
"Unit";"Zergling";"Larva";442;1
"Unit";"Zergling";"Larva";443;1
"Unit";"Zergling";"Larva";444;1
"Unit";"Zergling";"Larva";445;1
"Unit";"Zergling";"Larva";446;1
"Unit";"Zergling";"Larva";447;1
"Unit";"Zergling";"Larva";448;1
"Unit";"Zergling";"Larva";449;1
"Unit";"Zergling";"Larva";450;1
"Unit";"Overlord";"Larva";451;0
"Unit";"Overlord";"Larva";451;0
"Unit";"Zergling";"Larva";451;1
"Unit";"Zergling";"Larva";452;1
"Unit";"Mutalisk";"Larva";453;2
"Unit";"Mutalisk";"Larva";455;2
"Unit";"Mutalisk";"Larva";457;2
"Unit";"Mutalisk";"Larva";459;2
"Unit";"Mutalisk";"Larva";461;2
"Unit";"Mutalisk";"Larva";463;2
"Unit";"Mutalisk";"Larva";465;2
"Unit";"Zergling";"Larva";467;1
"Unit";"Zergling";"Larva";468;1
"Unit";"Zergling";"Larva";469;1
"Unit";"Zergling";"Larva";470;1
"Unit";"Zergling";"Larva";471;1
"Unit";"Zergling";"Larva";472;1
"Unit";"Zergling";"Larva";473;1
"Unit";"Zergling";"Larva";474;1
"Unit";"Zergling";"Larva";475;1
"Unit";"Zergling";"Larva";476;1
"Unit";"Zergling";"Larva";477;1
"Unit";"Zergling";"Larva";478;1
"Unit";"Zergling";"Larva";479;1
"Unit";"Zergling";"Larva";480;1
"Unit";"Zergling";"Larva";481;1
"Unit";"Zergling";"Larva";482;1
"Unit";"Zergling";"Larva";483;1
"Unit";"Zergling";"Larva";484;1
"Unit";"Zergling";"Larva";485;1
"Unit";"Zergling";"Larva";486;1
"Unit";"Zergling";"Larva";487;1
"Unit";"Zergling";"Larva";488;1
"Unit";"Zergling";"Larva";489;1
"Unit";"Zergling";"Larva";490;1
"Unit";"Zergling";"Larva";491;1
"Unit";"Zergling";"Larva";492;1
"Building";"CreepTumor";NA;493;0
"Building";"CreepTumor";NA;493;0
"Building";"CreepTumor";NA;493;0
"Building";"CreepTumor";NA;493;0
"Building";"CreepTumor";NA;493;0
"Building";"CreepTumorQueen";NA;493;0
"Unit";"Overlord";"Larva";493;0
"Building";"CreepTumorQueen";NA;493;0
"Unit";"Baneling";"Zergling";493;0
"Unit";"Baneling";"Zergling";493;0
"Building";"CreepTumorQueen";NA;493;0
"Unit";"Baneling";"Zergling";493;0
"Unit";"Baneling";"Zergling";493;0
"Unit";"Baneling";"Zergling";493;0
"Unit";"Baneling";"Zergling";493;0
"Unit";"Baneling";"Zergling";493;0
"Unit";"Baneling";"Zergling";493;0
"Unit";"Baneling";"Zergling";493;0
"Unit";"Baneling";"Zergling";493;0
"Unit";"Baneling";"Zergling";493;0
"Unit";"Baneling";"Zergling";493;0
"Building";"CreepTumorQueen";NA;493;0
"Building";"CreepTumorQueen";NA;493;0
"Unit";"Overlord";"Larva";493;0
"Building";"CreepTumorQueen";NA;493;0
"Building";"CreepTumor";NA;493;0
"Unit";"Zergling";"Larva";493;1
"Unit";"Zergling";"Larva";494;1
"Unit";"Zergling";"Larva";495;1
"Unit";"Zergling";"Larva";496;1
"Unit";"Overlord";"Larva";497;0
"Unit";"Baneling";"Zergling";497;0
"Unit";"Baneling";"Zergling";497;0
"Unit";"Baneling";"Zergling";497;0
"Unit";"Baneling";"Zergling";497;0
"Unit";"Baneling";"Zergling";497;0
"Unit";"Baneling";"Zergling";497;0
"Unit";"Baneling";"Zergling";497;0
"Unit";"Baneling";"Zergling";497;0
"Unit";"Zergling";"Larva";497;1
"Unit";"Zergling";"Larva";498;1
"Unit";"Zergling";"Larva";499;1
"Unit";"Zergling";"Larva";500;1
"Unit";"Zergling";"Larva";501;1
"Unit";"Zergling";"Larva";502;1
"Unit";"Zergling";"Larva";503;1
"Unit";"Zergling";"Larva";504;1
"Unit";"Zergling";"Larva";505;1
"Unit";"Zergling";"Larva";506;1
"Unit";"Zergling";"Larva";507;1
"Unit";"Zergling";"Larva";508;1
"Unit";"Zergling";"Larva";509;1
"Unit";"Zergling";"Larva";510;1
"Unit";"Zergling";"Larva";511;1
"Unit";"Zergling";"Larva";512;1
"Unit";"Zergling";"Larva";513;1
"Unit";"Zergling";"Larva";514;1
"Unit";"Zergling";"Larva";515;1
"Unit";"Zergling";"Larva";516;1
"Unit";"Zergling";"Larva";517;1
"Unit";"Zergling";"Larva";518;1
"Unit";"Zergling";"Larva";519;1
"Unit";"Zergling";"Larva";520;1
"Building";"CreepTumor";NA;521;0
"Building";"CreepTumor";NA;521;0
"Building";"CreepTumor";NA;521;0
"Building";"CreepTumor";NA;521;0
"Building";"CreepTumor";NA;521;0
"Building";"CreepTumor";NA;521;0
"Building";"CreepTumor";NA;521;0
"Building";"CreepTumor";NA;521;0
"Building";"CreepTumor";NA;521;0
"Building";"CreepTumor";NA;521;0
"Unit";"Baneling";"Zergling";521;0
"Unit";"Baneling";"Zergling";521;0
"Unit";"Baneling";"Zergling";521;0
"Unit";"Baneling";"Zergling";521;0
"Unit";"Baneling";"Zergling";521;0
"Unit";"Baneling";"Zergling";521;0
"Unit";"Baneling";"Zergling";521;0
"Unit";"Baneling";"Zergling";521;0
"Unit";"Baneling";"Zergling";521;0
"Unit";"Baneling";"Zergling";521;0
"Unit";"Baneling";"Zergling";521;0
"Unit";"Baneling";"Zergling";521;0
"Unit";"Baneling";"Zergling";521;0
"Unit";"Baneling";"Zergling";521;0
"Unit";"Baneling";"Zergling";521;0
"Unit";"Baneling";"Zergling";521;0
"Building";"CreepTumor";NA;521;0
"Building";"Hatchery";NA;521;0
"Building";"InfestationPit";NA;521;0
"Unit";"Zergling";"Larva";521;1
"Unit";"Zergling";"Larva";522;1
"Building";"Extractor";NA;523;0
"Unit";"Zergling";"Larva";523;1
"Unit";"Zergling";"Larva";524;1
"Unit";"Zergling";"Larva";525;1
"Unit";"Zergling";"Larva";526;1
"Building";"CreepTumor";NA;527;0
"Building";"CreepTumor";NA;527;0
"Building";"CreepTumor";NA;527;0
"Building";"CreepTumor";NA;527;0
"Unit";"Baneling";"Zergling";527;0
"Unit";"Baneling";"Zergling";527;0
"Unit";"Baneling";"Zergling";527;0
"Unit";"Baneling";"Zergling";527;0
"Unit";"Baneling";"Zergling";527;0
"Unit";"Baneling";"Zergling";527;0
"Unit";"Baneling";"Zergling";527;0
"Unit";"Baneling";"Zergling";527;0
"Unit";"Baneling";"Zergling";527;0
"Unit";"Baneling";"Zergling";527;0
"Unit";"Baneling";"Zergling";527;0
"Unit";"Baneling";"Zergling";527;0
"Unit";"Baneling";"Zergling";527;0
"Unit";"Baneling";"Zergling";527;0
"Unit";"Baneling";"Zergling";527;0
"Building";"Hatchery";NA;527;0
"Unit";"Zergling";"Larva";527;1
"Unit";"Zergling";"Larva";528;1
"Unit";"Zergling";"Larva";529;1
"Unit";"Zergling";"Larva";530;1
"Unit";"Zergling";"Larva";531;1
"Unit";"Zergling";"Larva";532;1
"Unit";"Zergling";"Larva";533;1
"Unit";"Zergling";"Larva";534;1
"Unit";"Zergling";"Larva";535;1
"Unit";"Zergling";"Larva";536;1
"Unit";"Zergling";"Larva";537;1
"Unit";"Zergling";"Larva";538;1
"Unit";"Zergling";"Larva";539;1
"Unit";"Zergling";"Larva";540;1
"Unit";"Zergling";"Larva";541;1
"Unit";"Zergling";"Larva";542;1
"Unit";"Zergling";"Larva";543;1
"Unit";"Zergling";"Larva";544;1
"Unit";"Zergling";"Larva";545;1
"Unit";"Zergling";"Larva";546;1
"Unit";"Zergling";"Larva";547;1
"Unit";"Zergling";"Larva";548;1
"Unit";"Zergling";"Larva";549;1
"Unit";"Zergling";"Larva";550;1
"Unit";"Zergling";"Larva";551;1
"Unit";"Zergling";"Larva";552;1
"Unit";"Zergling";"Larva";553;1
"Unit";"Zergling";"Larva";554;1
"Unit";"Zergling";"Larva";555;1
"Unit";"Zergling";"Larva";556;1
"Unit";"Zergling";"Larva";557;1
"Unit";"Zergling";"Larva";558;1
"Unit";"Zergling";"Larva";559;1
"Unit";"Zergling";"Larva";560;1
"Unit";"Zergling";"Larva";561;1
"Unit";"Zergling";"Larva";562;1
"Unit";"Zergling";"Larva";563;1
"Unit";"Zergling";"Larva";564;1
"Unit";"Zergling";"Larva";565;1
"Unit";"Zergling";"Larva";566;1
"Unit";"Zergling";"Larva";567;1
"Unit";"Zergling";"Larva";568;1
"Unit";"Zergling";"Larva";569;1
"Unit";"Zergling";"Larva";570;1
"Unit";"Zergling";"Larva";571;1
"Unit";"Zergling";"Larva";572;1
"Unit";"Zergling";"Larva";573;1
"Unit";"Zergling";"Larva";574;1
"Unit";"Zergling";"Larva";575;1
"Unit";"Zergling";"Larva";576;1
"Unit";"Zergling";"Larva";577;1
"Unit";"Zergling";"Larva";578;1
"Unit";"Zergling";"Larva";579;1
"Unit";"Zergling";"Larva";580;1
"Unit";"Zergling";"Larva";581;1
"Unit";"Zergling";"Larva";582;1
"Unit";"Zergling";"Larva";583;1
"Unit";"Zergling";"Larva";584;1
"Unit";"Zergling";"Larva";585;1
"Unit";"Zergling";"Larva";586;1
"Unit";"Zergling";"Larva";587;1
"Unit";"Zergling";"Larva";588;1
"Unit";"Zergling";"Larva";589;1
"Unit";"Zergling";"Larva";590;1
"Unit";"Zergling";"Larva";591;1
"Unit";"Zergling";"Larva";592;1
"Unit";"Zergling";"Larva";593;1
"Unit";"Zergling";"Larva";594;1
"Unit";"Zergling";"Larva";595;1
"Unit";"Zergling";"Larva";596;1
"Unit";"Zergling";"Larva";597;1
"Unit";"Zergling";"Larva";598;1
"Unit";"Zergling";"Larva";599;1
"Unit";"Zergling";"Larva";600;1
"Unit";"Mutalisk";"Larva";601;2
"Unit";"Mutalisk";"Larva";603;2
"Unit";"Mutalisk";"Larva";605;2
"Unit";"Mutalisk";"Larva";607;2
"Unit";"Mutalisk";"Larva";609;2
"Unit";"Mutalisk";"Larva";611;2
"Unit";"Mutalisk";"Larva";613;2
"Unit";"Mutalisk";"Larva";615;2
"Unit";"Mutalisk";"Larva";617;2
"Unit";"Mutalisk";"Larva";619;2
"Unit";"Mutalisk";"Larva";621;2
"Unit";"Zergling";"Larva";623;1
"Unit";"Zergling";"Larva";624;1
"Unit";"Zergling";"Larva";625;1
"Unit";"Zergling";"Larva";626;1
"Unit";"Zergling";"Larva";627;1
"Unit";"Zergling";"Larva";628;1
"Unit";"Zergling";"Larva";629;1
"Unit";"Zergling";"Larva";630;1
"Unit";"Zergling";"Larva";631;1
"Unit";"Zergling";"Larva";632;1
"Unit";"Zergling";"Larva";633;1
"Unit";"Zergling";"Larva";634;1
"Unit";"Zergling";"Larva";635;1
"Unit";"Zergling";"Larva";636;1
"Unit";"Zergling";"Larva";637;1
"Unit";"Zergling";"Larva";638;1
"Unit";"Zergling";"Larva";639;1
"Unit";"Zergling";"Larva";640;1
"Unit";"Zergling";"Larva";641;1
"Unit";"Zergling";"Larva";642;1
"Unit";"Zergling";"Larva";643;1
"Unit";"Zergling";"Larva";644;1
"Unit";"Zergling";"Larva";645;1
"Unit";"Zergling";"Larva";646;1
"Unit";"Zergling";"Larva";647;1
"Unit";"Zergling";"Larva";648;1
"Unit";"Zergling";"Larva";649;1
"Unit";"Zergling";"Larva";650;1
"Unit";"Baneling";"Zergling";652;0
"Unit";"Baneling";"Zergling";652;0
"Unit";"Baneling";"Zergling";652;0
"Unit";"Baneling";"Zergling";652;0
"Unit";"Baneling";"Zergling";652;0
"Unit";"Baneling";"Zergling";652;0
"Unit";"Baneling";"Zergling";652;0
"Unit";"Baneling";"Zergling";652;0
"Unit";"Baneling";"Zergling";652;0
"Unit";"Baneling";"Zergling";652;0
"Building";"CreepTumor";NA;652;0
"Unit";"Zergling";"Larva";652;1
"Unit";"Zergling";"Larva";653;1
"Unit";"Zergling";"Larva";654;1
"Unit";"Zergling";"Larva";655;1
"Unit";"Zergling";"Larva";656;1
"Unit";"Zergling";"Larva";657;1
"Unit";"Zergling";"Larva";658;1
"Unit";"Zergling";"Larva";659;1
"Unit";"Zergling";"Larva";660;1
"Unit";"Zergling";"Larva";661;1
"Unit";"Zergling";"Larva";662;1
"Unit";"Zergling";"Larva";663;1
"Unit";"Zergling";"Larva";664;1
"Unit";"Zergling";"Larva";665;1
"Unit";"Baneling";"Zergling";667;0
"Unit";"Baneling";"Zergling";667;0
"Unit";"Baneling";"Zergling";667;0
"Unit";"Baneling";"Zergling";667;0
"Unit";"Baneling";"Zergling";667;0
"Unit";"Baneling";"Zergling";667;0
"Unit";"Baneling";"Zergling";667;0
"Unit";"Zergling";"Larva";667;1
"Unit";"Zergling";"Larva";668;1
"Unit";"Zergling";"Larva";669;1
"Unit";"Zergling";"Larva";670;1
"Unit";"Zergling";"Larva";671;1
"Unit";"Zergling";"Larva";672;1
"Unit";"Zergling";"Larva";673;1
"Unit";"Zergling";"Larva";674;1
"Unit";"Zergling";"Larva";675;1
"Unit";"Zergling";"Larva";676;1
"Unit";"Zergling";"Larva";677;1
"Unit";"Zergling";"Larva";678;1
"Unit";"Zergling";"Larva";679;1
"Unit";"Zergling";"Larva";680;1
"Unit";"Zergling";"Larva";681;1
"Unit";"Zergling";"Larva";682;1
"Unit";"Zergling";"Larva";683;1
"Unit";"Zergling";"Larva";684;1
"Unit";"Baneling";"Zergling";685;0
"Unit";"Baneling";"Zergling";685;0
"Unit";"Baneling";"Zergling";685;0
"Unit";"Baneling";"Zergling";685;0
"Unit";"Baneling";"Zergling";685;0
"Unit";"Baneling";"Zergling";685;0
"Unit";"Baneling";"Zergling";685;0
"Unit";"Baneling";"Zergling";685;0
"Unit";"Baneling";"Zergling";685;0
"Unit";"Baneling";"Zergling";685;0
"Unit";"Baneling";"Zergling";685;0
"Unit";"Baneling";"Zergling";685;0
"Unit";"Baneling";"Zergling";685;0
"Unit";"Baneling";"Zergling";685;0
"Unit";"Baneling";"Zergling";685;0
"Unit";"Zergling";"Larva";685;1
"Unit";"Zergling";"Larva";686;1
"Unit";"Zergling";"Larva";687;1
"Unit";"Zergling";"Larva";688;1
"Unit";"Zergling";"Larva";689;1
"Unit";"Zergling";"Larva";690;1
"Unit";"Zergling";"Larva";691;1
"Unit";"Zergling";"Larva";692;1
"Unit";"Zergling";"Larva";693;1
"Unit";"Zergling";"Larva";694;1
"Unit";"Zergling";"Larva";695;1
"Unit";"Zergling";"Larva";696;1
"Unit";"Zergling";"Larva";697;1
"Unit";"Zergling";"Larva";698;1
"Unit";"Zergling";"Larva";699;1
"Unit";"Zergling";"Larva";700;1
"Unit";"Zergling";"Larva";701;1
"Unit";"Zergling";"Larva";702;1
"Unit";"Zergling";"Larva";703;1
"Unit";"Zergling";"Larva";704;1
"Unit";"Baneling";"Zergling";705;0
"Unit";"Baneling";"Zergling";705;0
"Unit";"Baneling";"Zergling";705;0
"Unit";"Baneling";"Zergling";705;0
"Unit";"Baneling";"Zergling";705;0
"Unit";"Baneling";"Zergling";705;0
"Unit";"Baneling";"Zergling";705;0
"Unit";"Baneling";"Zergling";705;0
"Unit";"Baneling";"Zergling";705;0
"Unit";"Baneling";"Zergling";705;0
"Unit";"Baneling";"Zergling";705;0
"Unit";"Baneling";"Zergling";705;0
"Unit";"Baneling";"Zergling";705;0
"Unit";"Baneling";"Zergling";705;0
"Unit";"Baneling";"Zergling";705;0
"Unit";"Baneling";"Zergling";705;0
"Unit";"Baneling";"Zergling";705;0
"Unit";"Zergling";"Larva";705;1
"Unit";"Zergling";"Larva";706;1
"Unit";"Zergling";"Larva";707;1
"Unit";"Zergling";"Larva";708;1
"Unit";"Zergling";"Larva";709;1
"Unit";"Zergling";"Larva";710;1
"Unit";"Zergling";"Larva";711;1
"Unit";"Zergling";"Larva";712;1
"Unit";"Zergling";"Larva";713;1
"Unit";"Zergling";"Larva";714;1
"Unit";"Zergling";"Larva";715;1
"Unit";"Zergling";"Larva";716;1
"Unit";"Zergling";"Larva";717;1
"Unit";"Zergling";"Larva";718;1
"Unit";"Zergling";"Larva";719;1
"Unit";"Zergling";"Larva";720;1
"Unit";"Zergling";"Larva";721;1
"Unit";"Zergling";"Larva";722;1
"Unit";"Zergling";"Larva";723;1
"Unit";"Zergling";"Larva";724;1
"Unit";"Zergling";"Larva";725;1
"Unit";"Zergling";"Larva";726;1
"Unit";"Zergling";"Larva";727;1
"Unit";"Zergling";"Larva";728;1
"Unit";"Zergling";"Larva";729;1
"Unit";"Zergling";"Larva";730;1
"Unit";"Zergling";"Larva";731;1
"Unit";"Zergling";"Larva";732;1
"Unit";"Zergling";"Larva";733;1
"Unit";"Zergling";"Larva";734;1
"Unit";"Zergling";"Larva";735;1
"Unit";"Zergling";"Larva";736;1
"Unit";"Zergling";"Larva";737;1
"Unit";"Zergling";"Larva";738;1
"Unit";"Zergling";"Larva";739;1
"Unit";"Zergling";"Larva";740;1
"Unit";"Zergling";"Larva";741;1
"Unit";"Zergling";"Larva";742;1
"Unit";"Zergling";"Larva";743;1
"Unit";"Zergling";"Larva";744;1
"Unit";"Zergling";"Larva";745;1
"Unit";"Zergling";"Larva";746;1
"Unit";"Zergling";"Larva";747;1
"Unit";"Zergling";"Larva";748;1
"Unit";"Baneling";"Zergling";749;0
"Unit";"Baneling";"Zergling";749;0
"Unit";"Baneling";"Zergling";749;0
"Unit";"Baneling";"Zergling";749;0
"Unit";"Baneling";"Zergling";749;0
"Unit";"Baneling";"Zergling";749;0
"Unit";"Baneling";"Zergling";749;0
"Unit";"Baneling";"Zergling";749;0
"Unit";"Baneling";"Zergling";749;0
"Unit";"Baneling";"Zergling";749;0
"Unit";"Baneling";"Zergling";749;0
"Unit";"Baneling";"Zergling";749;0
"Unit";"Baneling";"Zergling";749;0
"Unit";"Baneling";"Zergling";749;0
"Unit";"Baneling";"Zergling";749;0
"Unit";"Baneling";"Zergling";749;0
"Unit";"Baneling";"Zergling";749;0
"Unit";"Baneling";"Zergling";749;0
"Unit";"Baneling";"Zergling";749;0
"Unit";"Baneling";"Zergling";749;0
"Unit";"Baneling";"Zergling";749;0
"Unit";"Zergling";"Larva";749;1
"Unit";"Zergling";"Larva";750;1
"Unit";"Zergling";"Larva";751;1
"Unit";"Zergling";"Larva";752;1
"Unit";"Zergling";"Larva";753;1
"Unit";"Zergling";"Larva";754;1
"Unit";"Zergling";"Larva";755;1
"Unit";"Zergling";"Larva";756;1
"Unit";"Zergling";"Larva";757;1
"Unit";"Zergling";"Larva";758;1
"Unit";"Zergling";"Larva";759;1
"Unit";"Zergling";"Larva";760;1
"Unit";"Zergling";"Larva";761;1
"Unit";"Zergling";"Larva";762;1
"Unit";"Zergling";"Larva";763;1
"Unit";"Zergling";"Larva";764;1
"Unit";"Zergling";"Larva";765;1
"Unit";"Zergling";"Larva";766;1
"Unit";"Zergling";"Larva";767;1
"Unit";"Zergling";"Larva";768;1
"Unit";"Zergling";"Larva";769;1
"Unit";"Zergling";"Larva";770;1
"Unit";"Zergling";"Larva";771;1
"Unit";"Zergling";"Larva";772;1
"Unit";"Zergling";"Larva";773;1
"Unit";"Zergling";"Larva";774;1
"Unit";"Baneling";"Zergling";775;0
"Unit";"Baneling";"Zergling";775;0
"Unit";"Baneling";"Zergling";775;0
"Unit";"Baneling";"Zergling";775;0
"Unit";"Baneling";"Zergling";775;0
"Unit";"Baneling";"Zergling";775;0
"Unit";"Baneling";"Zergling";775;0
"Unit";"Baneling";"Zergling";775;0
"Unit";"Baneling";"Zergling";775;0
"Unit";"Baneling";"Zergling";775;0
"Unit";"Baneling";"Zergling";775;0
"Unit";"Baneling";"Zergling";775;0
"Building";"Hatchery";NA;775;0
"Unit";"Zergling";"Larva";775;1
"Unit";"Zergling";"Larva";776;1
"Unit";"Zergling";"Larva";777;1
"Unit";"Zergling";"Larva";778;1
"Unit";"Zergling";"Larva";779;1
"Unit";"Zergling";"Larva";780;1
"Unit";"Zergling";"Larva";781;1
"Unit";"Zergling";"Larva";782;1
"Unit";"Zergling";"Larva";783;1
"Unit";"Zergling";"Larva";784;1
"Unit";"Zergling";"Larva";785;1
"Unit";"Zergling";"Larva";786;1
"Unit";"Zergling";"Larva";787;1
"Unit";"Zergling";"Larva";788;1
"Unit";"Zergling";"Larva";789;1
"Unit";"Zergling";"Larva";790;1
"Unit";"Zergling";"Larva";791;1
"Unit";"Zergling";"Larva";792;1
"Unit";"Zergling";"Larva";793;1
"Unit";"Zergling";"Larva";794;1
"Unit";"Zergling";"Larva";795;1
"Unit";"Zergling";"Larva";796;1
"Unit";"Zergling";"Larva";797;1
"Unit";"Zergling";"Larva";798;1
"Unit";"Zergling";"Larva";799;1
"Unit";"Zergling";"Larva";800;1
"Unit";"Zergling";"Larva";801;1
"Unit";"Zergling";"Larva";802;1
"Unit";"Zergling";"Larva";803;1
"Unit";"Zergling";"Larva";804;1
"Unit";"Zergling";"Larva";805;1
"Unit";"Zergling";"Larva";806;1
"Unit";"Zergling";"Larva";807;1
"Unit";"Zergling";"Larva";808;1
"Unit";"Zergling";"Larva";809;1
"Unit";"Zergling";"Larva";810;1
"Building";"UltraliskCavern";NA;811;0
"Unit";"Zergling";"Larva";811;1
"Unit";"Zergling";"Larva";812;1
"Building";"CreepTumor";NA;813;0
"Unit";"Zergling";"Larva";813;1
"Unit";"Zergling";"Larva";814;1
"Unit";"Zergling";"Larva";815;1
"Unit";"Zergling";"Larva";816;1
"Unit";"Zergling";"Larva";817;1
"Unit";"Zergling";"Larva";818;1
"Unit";"Zergling";"Larva";819;1
"Unit";"Zergling";"Larva";820;1
"Unit";"Zergling";"Larva";821;1
"Unit";"Zergling";"Larva";822;1
"Unit";"Zergling";"Larva";823;1
"Unit";"Zergling";"Larva";824;1
"Unit";"Zergling";"Larva";825;1
"Unit";"Zergling";"Larva";826;1
"Unit";"Zergling";"Larva";827;1
"Unit";"Zergling";"Larva";828;1
"Unit";"Zergling";"Larva";829;1
"Unit";"Zergling";"Larva";830;1
"Unit";"Zergling";"Larva";831;1
"Unit";"Zergling";"Larva";832;1
"Unit";"Zergling";"Larva";833;1
"Unit";"Zergling";"Larva";834;1
"Unit";"Zergling";"Larva";835;1
"Unit";"Zergling";"Larva";836;1
"Unit";"Zergling";"Larva";837;1
"Unit";"Zergling";"Larva";838;1
"Unit";"Zergling";"Larva";839;1
"Unit";"Zergling";"Larva";840;1
"Unit";"Zergling";"Larva";841;1
"Unit";"Zergling";"Larva";842;1
"Unit";"Zergling";"Larva";843;1
"Unit";"Zergling";"Larva";844;1
"Unit";"Zergling";"Larva";845;1
"Unit";"Zergling";"Larva";846;1
"Unit";"Zergling";"Larva";847;1
"Unit";"Zergling";"Larva";848;1
"Unit";"Zergling";"Larva";849;1
"Unit";"Zergling";"Larva";850;1
"Unit";"Baneling";"Zergling";851;0
"Unit";"Baneling";"Zergling";851;0
"Unit";"Baneling";"Zergling";851;0
"Unit";"Baneling";"Zergling";851;0
"Unit";"Baneling";"Zergling";851;0
"Unit";"Baneling";"Zergling";851;0
"Unit";"Baneling";"Zergling";851;0
"Unit";"Baneling";"Zergling";851;0
"Unit";"Baneling";"Zergling";851;0
"Unit";"Baneling";"Zergling";851;0
"Unit";"Baneling";"Zergling";851;0
"Unit";"Baneling";"Zergling";851;0
"Unit";"Baneling";"Zergling";851;0
"Unit";"Baneling";"Zergling";851;0
"Unit";"Baneling";"Zergling";851;0
"Unit";"Baneling";"Zergling";851;0
"Unit";"Baneling";"Zergling";851;0
"Unit";"Baneling";"Zergling";851;0
"Unit";"Baneling";"Zergling";851;0
"Unit";"Baneling";"Zergling";851;0
"Unit";"Baneling";"Zergling";851;0
"Unit";"Baneling";"Zergling";851;0
"Unit";"Baneling";"Zergling";851;0
"Unit";"Baneling";"Zergling";851;0
"Unit";"Baneling";"Zergling";851;0
"Unit";"Baneling";"Zergling";851;0
"Unit";"Baneling";"Zergling";851;0
"Unit";"Baneling";"Zergling";851;0
"Unit";"Baneling";"Zergling";851;0
"Unit";"Baneling";"Zergling";851;0
"Unit";"Baneling";"Zergling";851;0
"Unit";"Baneling";"Zergling";851;0
"Unit";"Baneling";"Zergling";851;0
"Unit";"Baneling";"Zergling";851;0
"Unit";"Baneling";"Zergling";851;0
"Unit";"Baneling";"Zergling";851;0
"Unit";"Baneling";"Zergling";851;0
"Unit";"Baneling";"Zergling";851;0
"Building";"CreepTumor";NA;851;0
"Building";"CreepTumor";NA;851;0
"Building";"CreepTumor";NA;851;0
"Building";"CreepTumor";NA;851;0
"Upgrade";"SprayZerg";NA;851;0
"Upgrade";"SprayZerg";NA;851;0
"Upgrade";"zerglingmovementspeed";NA;851;0
"Upgrade";"SprayZerg";NA;851;0
"Upgrade";"SprayZerg";NA;851;0
"Upgrade";"ZergGroundArmorsLevel1";NA;851;0
"Upgrade";"SprayZerg";NA;851;0
"Upgrade";"SprayZerg";NA;851;0
"Upgrade";"SprayZerg";NA;851;0
"Upgrade";"SprayZerg";NA;851;0
"Upgrade";"ZergMeleeWeaponsLevel1";NA;851;0
"Upgrade";"CentrificalHooks";NA;851;0
"Upgrade";"SprayZerg";NA;851;0
"Upgrade";"ZergFlyerWeaponsLevel1";NA;851;0
"Upgrade";"ZergGroundArmorsLevel2";NA;851;0
"Upgrade";"SprayZerg";NA;851;0
"Upgrade";"overlordspeed";NA;851;0
"Upgrade";"SprayZerg";NA;851;0
"Upgrade";"ZergMeleeWeaponsLevel2";NA;851;0
"Upgrade";"SprayZerg";NA;851;0
"Upgrade";"SprayZerg";NA;851;0
"Upgrade";"SprayZerg";NA;851;0
"Upgrade";"ZergFlyerWeaponsLevel2";NA;851;0
"Upgrade";"SprayZerg";NA;851;0
"Upgrade";"SprayZerg";NA;851;0
"Upgrade";"zerglingattackspeed";NA;851;0
"Upgrade";"SprayZerg";NA;851;0
