"type";"unit_name";"on_building";"total_supply_lag";"supply"
"Unit";"Overlord";"Larva";13;0
"Building";"SpawningPool";NA;17;0
"Building";"Hatchery";NA;19;0
"Unit";"Queen";"Hatchery";19;2
"Unit";"Zergling";"Larva";21;1
"Unit";"Zergling";"Larva";22;1
"Unit";"Zergling";"Larva";23;1
"Unit";"Zergling";"Larva";24;1
"Unit";"Overlord";"Larva";25;0
"Building";"Hatchery";NA;26;0
"Building";"CreepTumorQueen";NA;27;0
"Unit";"Queen";"Hatchery";27;2
"Building";"Extractor";NA;29;0
"Unit";"Queen";"Hatchery";31;2
"Unit";"Queen";"Hatchery";39;2
"Building";"CreepTumor";NA;41;0
"Unit";"Overlord";"Larva";42;0
"Building";"CreepTumorQueen";NA;42;0
"Unit";"Queen";"Hatchery";42;2
"Building";"CreepTumorQueen";NA;44;0
"Building";"CreepTumorQueen";NA;44;0
"Unit";"Overlord";"Larva";49;0
"Unit";"Zergling";"Larva";49;1
"Unit";"Zergling";"Larva";50;1
"Unit";"Zergling";"Larva";51;1
"Unit";"Zergling";"Larva";52;1
"Unit";"Zergling";"Larva";53;1
"Unit";"Zergling";"Larva";54;1
"Unit";"Zergling";"Larva";55;1
"Unit";"Zergling";"Larva";56;1
"Unit";"Zergling";"Larva";57;1
"Unit";"Zergling";"Larva";58;1
"Unit";"Zergling";"Larva";59;1
"Unit";"Zergling";"Larva";60;1
"Unit";"Zergling";"Larva";61;1
"Unit";"Zergling";"Larva";62;1
"Unit";"Zergling";"Larva";63;1
"Unit";"Zergling";"Larva";64;1
"Building";"CreepTumorQueen";NA;65;0
"Building";"CreepTumorQueen";NA;65;0
"Unit";"Zergling";"Larva";65;1
"Unit";"Zergling";"Larva";66;1
"Unit";"Zergling";"Larva";67;1
"Unit";"Zergling";"Larva";68;1
"Unit";"Zergling";"Larva";69;1
"Unit";"Zergling";"Larva";70;1
"Unit";"Zergling";"Larva";71;1
"Unit";"Zergling";"Larva";72;1
"Unit";"Zergling";"Larva";73;1
"Unit";"Zergling";"Larva";74;1
"Unit";"Overlord";"Larva";75;0
"Building";"RoachWarren";NA;75;0
"Unit";"Overlord";"Larva";75;0
"Unit";"Overlord";"Larva";80;0
"Building";"CreepTumor";NA;80;0
"Building";"CreepTumor";NA;80;0
"Building";"CreepTumor";NA;80;0
"Unit";"Zergling";"Larva";80;1
"Unit";"Zergling";"Larva";81;1
"Unit";"Zergling";"Larva";82;1
"Unit";"Zergling";"Larva";83;1
"Unit";"Zergling";"Larva";84;1
"Unit";"Zergling";"Larva";85;1
"Unit";"Zergling";"Larva";86;1
"Unit";"Zergling";"Larva";87;1
"Unit";"Zergling";"Larva";88;1
"Unit";"Zergling";"Larva";89;1
"Unit";"Zergling";"Larva";90;1
"Unit";"Zergling";"Larva";91;1
"Unit";"Zergling";"Larva";92;1
"Unit";"Zergling";"Larva";93;1
"Unit";"Zergling";"Larva";94;1
"Unit";"Zergling";"Larva";95;1
"Unit";"Zergling";"Larva";96;1
"Unit";"Zergling";"Larva";97;1
"Unit";"Zergling";"Larva";98;1
"Unit";"Zergling";"Larva";99;1
"Unit";"Zergling";"Larva";100;1
"Unit";"Zergling";"Larva";101;1
"Unit";"Zergling";"Larva";102;1
"Unit";"Zergling";"Larva";103;1
"Building";"CreepTumor";NA;110;0
"Building";"CreepTumor";NA;110;0
"Building";"CreepTumor";NA;110;0
"Building";"CreepTumor";NA;110;0
"Building";"CreepTumor";NA;110;0
"Building";"Extractor";NA;110;0
"Building";"Extractor";NA;113;0
"Building";"CreepTumorQueen";NA;116;0
"Building";"SporeCrawler";NA;116;0
"Building";"SporeCrawler";NA;116;0
"Building";"SpineCrawler";NA;116;0
"Unit";"Overlord";"Larva";116;0
"Unit";"Overlord";"Larva";116;0
"Unit";"Overlord";"Larva";116;0
"Building";"CreepTumor";NA;122;0
"Building";"CreepTumor";NA;122;0
"Building";"CreepTumor";NA;122;0
"Building";"CreepTumor";NA;122;0
"Building";"Hatchery";NA;122;0
"Building";"CreepTumorQueen";NA;122;0
"Building";"CreepTumor";NA;122;0
"Building";"CreepTumor";NA;122;0
"Building";"CreepTumorQueen";NA;133;0
"Building";"CreepTumorQueen";NA;133;0
"Unit";"Overlord";"Larva";133;0
"Unit";"Overlord";"Larva";133;0
"Building";"Extractor";NA;135;0
"Building";"EvolutionChamber";NA;136;0
"Building";"EvolutionChamber";NA;138;0
"Building";"Extractor";NA;140;0
"Building";"Extractor";NA;143;0
"Building";"BanelingNest";NA;149;0
"Building";"SporeCrawler";NA;149;0
"Upgrade";"GlialReconstitution";"RoachWarren";149;0
"Building";"SpineCrawler";NA;149;0
"Building";"InfestationPit";NA;149;0
"Unit";"Queen";"Hatchery";165;2
"Building";"CreepTumor";NA;167;0
"Building";"CreepTumor";NA;167;0
"Building";"CreepTumor";NA;167;0
"Building";"CreepTumor";NA;167;0
"Building";"CreepTumor";NA;167;0
"Building";"CreepTumor";NA;167;0
"Building";"CreepTumor";NA;167;0
"Building";"CreepTumor";NA;167;0
"Building";"CreepTumor";NA;167;0
"Building";"CreepTumorQueen";NA;167;0
"Building";"CreepTumorQueen";NA;167;0
"Building";"CreepTumorQueen";NA;167;0
"Building";"CreepTumorQueen";NA;167;0
"Unit";"Zergling";"Larva";167;1
"Unit";"Zergling";"Larva";168;1
"Unit";"Zergling";"Larva";169;1
"Unit";"Zergling";"Larva";170;1
"Unit";"Zergling";"Larva";171;1
"Unit";"Zergling";"Larva";172;1
"Unit";"Zergling";"Larva";173;1
"Unit";"Zergling";"Larva";174;1
"Unit";"Zergling";"Larva";175;1
"Unit";"Zergling";"Larva";176;1
"Unit";"Zergling";"Larva";177;1
"Unit";"Zergling";"Larva";178;1
"Unit";"Zergling";"Larva";179;1
"Unit";"Zergling";"Larva";180;1
"Unit";"Zergling";"Larva";181;1
"Unit";"Zergling";"Larva";182;1
"Unit";"Zergling";"Larva";183;1
"Unit";"Zergling";"Larva";184;1
"Unit";"Zergling";"Larva";185;1
"Unit";"Zergling";"Larva";186;1
"Building";"CreepTumorQueen";NA;187;0
"Unit";"Baneling";"Zergling";187;0
"Unit";"Baneling";"Zergling";187;0
"Unit";"Baneling";"Zergling";187;0
"Unit";"Baneling";"Zergling";187;0
"Unit";"Baneling";"Zergling";187;0
"Unit";"Baneling";"Zergling";187;0
"Unit";"Baneling";"Zergling";187;0
"Unit";"Baneling";"Zergling";187;0
"Unit";"Baneling";"Zergling";187;0
"Unit";"Baneling";"Zergling";187;0
"Unit";"Baneling";"Zergling";187;0
"Unit";"Baneling";"Zergling";187;0
"Unit";"Baneling";"Zergling";187;0
"Unit";"Baneling";"Zergling";187;0
"Unit";"Baneling";"Zergling";187;0
"Unit";"Baneling";"Zergling";187;0
"Unit";"Baneling";"Zergling";187;0
"Unit";"Baneling";"Zergling";187;0
"Unit";"Baneling";"Zergling";187;0
"Unit";"Baneling";"Zergling";187;0
"Unit";"Baneling";"Zergling";187;0
"Unit";"Baneling";"Zergling";187;0
"Unit";"Baneling";"Zergling";187;0
"Unit";"Overlord";"Larva";190;0
"Unit";"Overlord";"Larva";190;0
"Unit";"Overlord";"Larva";190;0
"Unit";"Overlord";"Larva";190;0
"Unit";"Overlord";"Larva";190;0
"Building";"Extractor";NA;190;0
"Unit";"Zergling";"Larva";190;1
"Unit";"Zergling";"Larva";191;1
"Unit";"Zergling";"Larva";192;1
"Unit";"Zergling";"Larva";193;1
"Unit";"Zergling";"Larva";194;1
"Unit";"Zergling";"Larva";195;1
"Unit";"Zergling";"Larva";196;1
"Unit";"Zergling";"Larva";197;1
"Unit";"Zergling";"Larva";198;1
"Unit";"Zergling";"Larva";199;1
"Building";"Hatchery";NA;200;0
"Building";"Extractor";NA;200;0
"Unit";"Overlord";"Larva";200;0
"Unit";"Overlord";"Larva";200;0
"Building";"CreepTumor";NA;200;0
"Building";"CreepTumor";NA;200;0
"Building";"CreepTumor";NA;200;0
"Building";"CreepTumor";NA;200;0
"Building";"CreepTumor";NA;200;0
"Building";"CreepTumor";NA;200;0
"Building";"CreepTumor";NA;200;0
"Unit";"Infestor";"Larva";200;2
"Unit";"Infestor";"Larva";202;2
"Unit";"Infestor";"Larva";204;2
"Unit";"Infestor";"Larva";206;2
"Unit";"Infestor";"Larva";208;2
"Unit";"Infestor";"Larva";210;2
"Unit";"Infestor";"Larva";212;2
"Unit";"Infestor";"Larva";214;2
"Unit";"Overlord";"Larva";216;0
"Unit";"Overlord";"Larva";216;0
"Unit";"Overlord";"Larva";216;0
"Building";"CreepTumorQueen";NA;226;0
"Building";"CreepTumorQueen";NA;226;0
"Building";"CreepTumorQueen";NA;226;0
"Upgrade";"Burrow";"Hatchery";226;0
"Unit";"Baneling";"Zergling";226;0
"Unit";"Baneling";"Zergling";226;0
"Unit";"Baneling";"Zergling";226;0
"Unit";"Baneling";"Zergling";226;0
"Unit";"Baneling";"Zergling";226;0
"Unit";"Baneling";"Zergling";226;0
"Unit";"Baneling";"Zergling";226;0
"Unit";"Baneling";"Zergling";226;0
"Unit";"Baneling";"Zergling";226;0
"Unit";"Baneling";"Zergling";226;0
"Unit";"Baneling";"Zergling";226;0
"Unit";"Baneling";"Zergling";226;0
"Unit";"Baneling";"Zergling";226;0
"Unit";"Baneling";"Zergling";226;0
"Building";"Extractor";NA;228;0
"Building";"Extractor";NA;232;0
"Unit";"Zergling";"Larva";232;1
"Unit";"Zergling";"Larva";233;1
"Unit";"Zergling";"Larva";234;1
"Unit";"Zergling";"Larva";235;1
"Unit";"Zergling";"Larva";236;1
"Unit";"Zergling";"Larva";237;1
"Unit";"Zergling";"Larva";238;1
"Unit";"Zergling";"Larva";239;1
"Unit";"Zergling";"Larva";240;1
"Unit";"Zergling";"Larva";241;1
"Unit";"Zergling";"Larva";242;1
"Unit";"Zergling";"Larva";243;1
"Unit";"Zergling";"Larva";244;1
"Unit";"Zergling";"Larva";245;1
"Unit";"Zergling";"Larva";246;1
"Unit";"Zergling";"Larva";247;1
"Unit";"Zergling";"Larva";248;1
"Unit";"Zergling";"Larva";249;1
"Unit";"Zergling";"Larva";250;1
"Unit";"Zergling";"Larva";251;1
"Unit";"Zergling";"Larva";252;1
"Unit";"Zergling";"Larva";253;1
"Unit";"Zergling";"Larva";254;1
"Unit";"Zergling";"Larva";255;1
"Unit";"Zergling";"Larva";256;1
"Unit";"Zergling";"Larva";257;1
"Building";"CreepTumor";NA;258;0
"Building";"CreepTumor";NA;258;0
"Building";"CreepTumor";NA;258;0
"Building";"CreepTumor";NA;258;0
"Building";"CreepTumorQueen";NA;258;0
"Building";"CreepTumorQueen";NA;258;0
"Building";"CreepTumor";NA;258;0
"Building";"CreepTumor";NA;258;0
"Building";"UltraliskCavern";NA;258;0
"Unit";"Overlord";"Larva";258;0
"Unit";"Overlord";"Larva";258;0
"Building";"Hatchery";NA;258;0
"Building";"CreepTumor";NA;258;0
"Building";"CreepTumor";NA;258;0
"Building";"CreepTumor";NA;258;0
"Building";"CreepTumor";NA;258;0
"Building";"CreepTumor";NA;258;0
"Building";"CreepTumor";NA;258;0
"Building";"CreepTumor";NA;258;0
"Building";"CreepTumor";NA;258;0
"Building";"Hatchery";NA;258;0
"Building";"CreepTumor";NA;258;0
"Building";"CreepTumor";NA;258;0
"Building";"CreepTumorQueen";NA;258;0
"Building";"CreepTumor";NA;258;0
"Building";"Hatchery";NA;258;0
"Building";"CreepTumorQueen";NA;258;0
"Building";"Hatchery";NA;258;0
"Building";"CreepTumor";NA;258;0
"Building";"CreepTumor";NA;258;0
"Building";"CreepTumorQueen";NA;258;0
"Building";"CreepTumor";NA;258;0
"Building";"CreepTumor";NA;258;0
"Building";"CreepTumor";NA;258;0
"Building";"CreepTumor";NA;258;0
"Building";"CreepTumor";NA;258;0
"Building";"Hatchery";NA;258;0
"Building";"Hatchery";NA;258;0
"Building";"Spire";NA;258;0
"Building";"UltraliskCavern";NA;258;0
"Unit";"Zergling";"Larva";258;1
"Unit";"Zergling";"Larva";259;1
"Unit";"Zergling";"Larva";260;1
"Unit";"Zergling";"Larva";261;1
"Unit";"Zergling";"Larva";262;1
"Unit";"Zergling";"Larva";263;1
"Unit";"Zergling";"Larva";264;1
"Unit";"Zergling";"Larva";265;1
"Unit";"Zergling";"Larva";266;1
"Unit";"Zergling";"Larva";267;1
"Unit";"Zergling";"Larva";268;1
"Unit";"Zergling";"Larva";269;1
"Unit";"Zergling";"Larva";270;1
"Unit";"Zergling";"Larva";271;1
"Unit";"Zergling";"Larva";272;1
"Unit";"Zergling";"Larva";273;1
"Unit";"Zergling";"Larva";274;1
"Unit";"Zergling";"Larva";275;1
"Unit";"Zergling";"Larva";276;1
"Unit";"Zergling";"Larva";277;1
"Unit";"Zergling";"Larva";278;1
"Unit";"Zergling";"Larva";279;1
"Unit";"Zergling";"Larva";280;1
"Unit";"Zergling";"Larva";281;1
"Unit";"Zergling";"Larva";282;1
"Unit";"Zergling";"Larva";283;1
"Unit";"Zergling";"Larva";284;1
"Unit";"Zergling";"Larva";285;1
"Unit";"Zergling";"Larva";286;1
"Unit";"Zergling";"Larva";287;1
"Unit";"Zergling";"Larva";288;1
"Unit";"Zergling";"Larva";289;1
"Unit";"Zergling";"Larva";290;1
"Unit";"Zergling";"Larva";291;1
"Unit";"Zergling";"Larva";292;1
"Unit";"Zergling";"Larva";293;1
"Unit";"Zergling";"Larva";294;1
"Unit";"Zergling";"Larva";295;1
"Unit";"Zergling";"Larva";296;1
"Unit";"Zergling";"Larva";297;1
"Unit";"Zergling";"Larva";298;1
"Unit";"Zergling";"Larva";299;1
"Unit";"Zergling";"Larva";300;1
"Unit";"Zergling";"Larva";301;1
"Unit";"Zergling";"Larva";302;1
"Unit";"Zergling";"Larva";303;1
"Unit";"Zergling";"Larva";304;1
"Unit";"Zergling";"Larva";305;1
"Unit";"Zergling";"Larva";306;1
"Unit";"Zergling";"Larva";307;1
"Unit";"Zergling";"Larva";308;1
"Unit";"Zergling";"Larva";309;1
"Unit";"Baneling";"Zergling";310;0
"Unit";"Baneling";"Zergling";310;0
"Unit";"Baneling";"Zergling";310;0
"Unit";"Baneling";"Zergling";310;0
"Unit";"Baneling";"Zergling";310;0
"Unit";"Baneling";"Zergling";310;0
"Unit";"Baneling";"Zergling";310;0
"Unit";"Baneling";"Zergling";310;0
"Unit";"Baneling";"Zergling";310;0
"Unit";"Baneling";"Zergling";310;0
"Unit";"Baneling";"Zergling";310;0
"Unit";"Baneling";"Zergling";310;0
"Unit";"Baneling";"Zergling";310;0
"Unit";"Baneling";"Zergling";310;0
"Unit";"Baneling";"Zergling";310;0
"Unit";"Baneling";"Zergling";310;0
"Unit";"Baneling";"Zergling";310;0
"Unit";"Baneling";"Zergling";310;0
"Unit";"Baneling";"Zergling";310;0
"Unit";"Baneling";"Zergling";310;0
"Unit";"Baneling";"Zergling";310;0
"Unit";"Baneling";"Zergling";310;0
"Unit";"Baneling";"Zergling";310;0
"Unit";"Baneling";"Zergling";310;0
"Unit";"Baneling";"Zergling";310;0
"Unit";"Baneling";"Zergling";310;0
"Unit";"Baneling";"Zergling";310;0
"Unit";"Baneling";"Zergling";310;0
"Unit";"Baneling";"Zergling";310;0
"Unit";"Baneling";"Zergling";310;0
"Unit";"Baneling";"Zergling";310;0
"Unit";"Baneling";"Zergling";310;0
"Unit";"Baneling";"Zergling";310;0
"Unit";"Baneling";"Zergling";310;0
"Unit";"Baneling";"Zergling";310;0
"Unit";"Baneling";"Zergling";310;0
"Unit";"Baneling";"Zergling";310;0
"Unit";"Baneling";"Zergling";310;0
"Unit";"Baneling";"Zergling";310;0
"Unit";"Baneling";"Zergling";310;0
"Unit";"Baneling";"Zergling";310;0
"Unit";"Baneling";"Zergling";310;0
"Unit";"Baneling";"Zergling";310;0
"Unit";"Baneling";"Zergling";310;0
"Unit";"Baneling";"Zergling";310;0
"Unit";"Baneling";"Zergling";310;0
"Unit";"Baneling";"Zergling";310;0
"Unit";"Baneling";"Zergling";310;0
"Unit";"Baneling";"Zergling";310;0
"Unit";"Baneling";"Zergling";310;0
"Unit";"Baneling";"Zergling";310;0
"Unit";"Baneling";"Zergling";310;0
"Building";"SporeCrawler";NA;310;0
"Building";"SporeCrawler";NA;310;0
"Unit";"Mutalisk";"Larva";310;2
"Unit";"Mutalisk";"Larva";312;2
"Unit";"Mutalisk";"Larva";314;2
"Unit";"Mutalisk";"Larva";316;2
"Unit";"Mutalisk";"Larva";318;2
"Unit";"Mutalisk";"Larva";320;2
"Unit";"Mutalisk";"Larva";322;2
"Unit";"Mutalisk";"Larva";324;2
"Unit";"Mutalisk";"Larva";326;2
"Unit";"Mutalisk";"Larva";328;2
"Unit";"Mutalisk";"Larva";330;2
"Unit";"Mutalisk";"Larva";332;2
"Unit";"Mutalisk";"Larva";334;2
"Unit";"Mutalisk";"Larva";336;2
"Unit";"Mutalisk";"Larva";338;2
"Unit";"Mutalisk";"Larva";340;2
"Unit";"Mutalisk";"Larva";342;2
"Unit";"Mutalisk";"Larva";344;2
"Unit";"Mutalisk";"Larva";346;2
"Unit";"Mutalisk";"Larva";348;2
"Unit";"Mutalisk";"Larva";350;2
"Unit";"Mutalisk";"Larva";352;2
"Unit";"Zergling";"Larva";354;1
"Unit";"Zergling";"Larva";355;1
"Unit";"Zergling";"Larva";356;1
"Unit";"Zergling";"Larva";357;1
"Unit";"Zergling";"Larva";358;1
"Unit";"Zergling";"Larva";359;1
"Unit";"Zergling";"Larva";360;1
"Unit";"Zergling";"Larva";361;1
"Unit";"Zergling";"Larva";362;1
"Unit";"Zergling";"Larva";363;1
"Unit";"Zergling";"Larva";364;1
"Unit";"Zergling";"Larva";365;1
"Unit";"Zergling";"Larva";366;1
"Unit";"Zergling";"Larva";367;1
"Unit";"Zergling";"Larva";368;1
"Unit";"Zergling";"Larva";369;1
"Unit";"Zergling";"Larva";370;1
"Unit";"Zergling";"Larva";371;1
"Unit";"Zergling";"Larva";372;1
"Unit";"Zergling";"Larva";373;1
"Unit";"Zergling";"Larva";374;1
"Unit";"Zergling";"Larva";375;1
"Unit";"Zergling";"Larva";376;1
"Unit";"Zergling";"Larva";377;1
"Unit";"Zergling";"Larva";378;1
"Unit";"Zergling";"Larva";379;1
"Unit";"Zergling";"Larva";380;1
"Unit";"Zergling";"Larva";381;1
"Unit";"Zergling";"Larva";382;1
"Unit";"Zergling";"Larva";383;1
"Unit";"Zergling";"Larva";384;1
"Unit";"Zergling";"Larva";385;1
"Unit";"Zergling";"Larva";386;1
"Unit";"Zergling";"Larva";387;1
"Unit";"Zergling";"Larva";388;1
"Unit";"Zergling";"Larva";389;1
"Building";"Extractor";NA;390;0
"Building";"Extractor";NA;390;0
"Upgrade";"SprayZerg";NA;390;0
"Upgrade";"SprayZerg";NA;390;0
"Upgrade";"SprayZerg";NA;390;0
"Upgrade";"SprayZerg";NA;390;0
"Upgrade";"zerglingmovementspeed";NA;390;0
"Upgrade";"SprayZerg";NA;390;0
"Upgrade";"overlordspeed";NA;390;0
"Upgrade";"SprayZerg";NA;390;0
"Upgrade";"SprayZerg";NA;390;0
"Upgrade";"InfestorEnergyUpgrade";NA;390;0
"Upgrade";"ZergMeleeWeaponsLevel1";NA;390;0
"Upgrade";"ZergGroundArmorsLevel1";NA;390;0
"Upgrade";"CentrificalHooks";NA;390;0
"Upgrade";"SprayZerg";NA;390;0
"Upgrade";"SprayZerg";NA;390;0
"Upgrade";"SprayZerg";NA;390;0
"Upgrade";"SprayZerg";NA;390;0
"Upgrade";"SprayZerg";NA;390;0
"Upgrade";"SprayZerg";NA;390;0
"Upgrade";"SprayZerg";NA;390;0
"Upgrade";"SprayZerg";NA;390;0
"Upgrade";"ZergMeleeWeaponsLevel2";NA;390;0
"Upgrade";"SprayZerg";NA;390;0
"Upgrade";"SprayZerg";NA;390;0
"Upgrade";"SprayZerg";NA;390;0
"Upgrade";"SprayZerg";NA;390;0
"Upgrade";"SprayZerg";NA;390;0
"Upgrade";"SprayZerg";NA;390;0
"Upgrade";"zerglingattackspeed";NA;390;0
"Upgrade";"ZergGroundArmorsLevel2";NA;390;0
