"type";"unit_name";"on_building";"total_supply_lag"
"Unit";"Overlord";"Larva";13
"Building";"Hatchery";NA;17
"Building";"Extractor";NA;19
"Building";"SpawningPool";NA;19
"Unit";"Overlord";"Larva";22
"Unit";"Zergling";"Larva";22
"Unit";"Zergling";"Larva";23
"Unit";"Zergling";"Larva";24
"Unit";"Zergling";"Larva";25
"Unit";"Queen";"Hatchery";26
"Unit";"Queen";"Hatchery";28
"Unit";"Overlord";"Larva";36
"Unit";"Queen";"Hatchery";36
"Unit";"Queen";"Hatchery";38
"Building";"CreepTumorQueen";NA;45
"Building";"CreepTumorQueen";NA;45
"Unit";"Overlord";"Larva";45
"Building";"Hatchery";NA;49
"Building";"CreepTumor";NA;49
"Building";"CreepTumor";NA;49
"Building";"CreepTumorQueen";NA;49
"Unit";"Overlord";"Larva";54
"Unit";"Queen";"Hatchery";54
"Building";"CreepTumor";NA;63
"Building";"CreepTumor";NA;63
"Building";"Extractor";NA;65
"Building";"EvolutionChamber";NA;65
"Unit";"Queen";"Hatchery";65
"Building";"EvolutionChamber";NA;67
"Unit";"Overlord";"Larva";67
"Unit";"Overlord";"Larva";67
"Building";"CreepTumorQueen";NA;70
"Building";"CreepTumor";NA;70
"Building";"CreepTumor";NA;70
"Building";"CreepTumor";NA;70
"Unit";"Queen";"Hatchery";70
"Building";"CreepTumorQueen";NA;72
"Unit";"Overlord";"Larva";72
"Unit";"Zergling";"Larva";72
"Unit";"Zergling";"Larva";73
"Unit";"Zergling";"Larva";74
"Unit";"Zergling";"Larva";75
"Unit";"Zergling";"Larva";76
"Unit";"Zergling";"Larva";77
"Unit";"Zergling";"Larva";78
"Unit";"Zergling";"Larva";79
"Unit";"Zergling";"Larva";80
"Unit";"Zergling";"Larva";81
"Building";"BanelingNest";NA;84
"Unit";"Zergling";"Larva";85
"Unit";"Zergling";"Larva";86
"Unit";"Zergling";"Larva";87
"Unit";"Zergling";"Larva";88
"Unit";"Zergling";"Larva";89
"Unit";"Zergling";"Larva";90
"Building";"CreepTumor";NA;91
"Unit";"Queen";"Hatchery";91
"Building";"CreepTumor";NA;93
"Building";"CreepTumorQueen";NA;93
"Building";"CreepTumor";NA;93
"Unit";"Zergling";"Larva";93
"Unit";"Zergling";"Larva";94
"Unit";"Zergling";"Larva";95
"Unit";"Zergling";"Larva";96
"Unit";"Zergling";"Larva";97
"Unit";"Zergling";"Larva";98
"Unit";"Zergling";"Larva";99
"Unit";"Zergling";"Larva";100
"Unit";"Zergling";"Larva";101
"Unit";"Zergling";"Larva";102
"Building";"CreepTumor";NA;111
"Building";"CreepTumorQueen";NA;111
"Building";"Extractor";NA;111
"Building";"CreepTumorQueen";NA;111
"Building";"CreepTumorQueen";NA;111
"Building";"Extractor";NA;111
"Building";"Hatchery";NA;111
"Building";"CreepTumor";NA;111
"Building";"CreepTumor";NA;111
"Building";"CreepTumor";NA;111
"Unit";"Baneling";"Zergling";111
"Unit";"Baneling";"Zergling";111
"Unit";"Baneling";"Zergling";111
"Unit";"Baneling";"Zergling";111
"Unit";"Baneling";"Zergling";111
"Unit";"Baneling";"Zergling";111
"Unit";"Baneling";"Zergling";111
"Unit";"Baneling";"Zergling";111
"Unit";"Zergling";"Larva";111
"Unit";"Zergling";"Larva";112
"Unit";"Zergling";"Larva";113
"Unit";"Zergling";"Larva";114
"Unit";"Zergling";"Larva";115
"Unit";"Zergling";"Larva";116
"Unit";"Zergling";"Larva";117
"Unit";"Zergling";"Larva";118
"Unit";"Overlord";"Larva";121
"Unit";"Overlord";"Larva";121
"Unit";"Zergling";"Larva";136
"Unit";"Zergling";"Larva";137
"Unit";"Zergling";"Larva";138
"Unit";"Zergling";"Larva";139
"Unit";"Zergling";"Larva";140
"Unit";"Zergling";"Larva";141
"Unit";"Zergling";"Larva";142
"Unit";"Zergling";"Larva";143
"Unit";"Zergling";"Larva";144
"Unit";"Zergling";"Larva";145
"Building";"HydraliskDen";NA;146
"Unit";"Queen";"Hatchery";146
"Unit";"Zergling";"Larva";148
"Unit";"Zergling";"Larva";149
"Unit";"Zergling";"Larva";150
"Unit";"Zergling";"Larva";151
"Unit";"Zergling";"Larva";152
"Unit";"Zergling";"Larva";153
"Unit";"Baneling";"Zergling";154
"Unit";"Baneling";"Zergling";154
"Unit";"Baneling";"Zergling";154
"Unit";"Zergling";"Larva";154
"Unit";"Zergling";"Larva";155
"Unit";"Zergling";"Larva";156
"Unit";"Zergling";"Larva";157
"Unit";"Zergling";"Larva";158
"Unit";"Zergling";"Larva";159
"Unit";"Zergling";"Larva";160
"Unit";"Zergling";"Larva";161
"Unit";"Zergling";"Larva";162
"Unit";"Zergling";"Larva";163
"Unit";"Zergling";"Larva";164
"Unit";"Zergling";"Larva";165
"Unit";"Zergling";"Larva";166
"Unit";"Zergling";"Larva";167
"Unit";"Zergling";"Larva";168
"Unit";"Zergling";"Larva";169
"Unit";"Zergling";"Larva";170
"Unit";"Zergling";"Larva";171
"Unit";"Zergling";"Larva";172
"Unit";"Zergling";"Larva";173
"Unit";"Zergling";"Larva";174
"Unit";"Zergling";"Larva";175
"Unit";"Zergling";"Larva";176
"Unit";"Zergling";"Larva";177
"Unit";"Zergling";"Larva";178
"Unit";"Zergling";"Larva";179
"Unit";"Zergling";"Larva";180
"Unit";"Zergling";"Larva";181
"Unit";"Hydralisk";"Larva";182
"Unit";"Hydralisk";"Larva";184
"Unit";"Zergling";"Larva";186
"Unit";"Zergling";"Larva";187
"Unit";"Zergling";"Larva";188
"Unit";"Zergling";"Larva";189
"Unit";"Zergling";"Larva";190
"Unit";"Zergling";"Larva";191
"Unit";"Zergling";"Larva";192
"Unit";"Zergling";"Larva";193
"Unit";"Zergling";"Larva";194
"Unit";"Zergling";"Larva";195
"Building";"Extractor";NA;196
"Unit";"Hydralisk";"Larva";196
"Building";"Hatchery";NA;198
"Building";"CreepTumor";NA;198
"Building";"CreepTumor";NA;198
"Unit";"Hydralisk";"Larva";198
"Unit";"Hydralisk";"Larva";200
"Unit";"Zergling";"Larva";202
"Unit";"Zergling";"Larva";203
"Building";"CreepTumor";NA;204
"Building";"CreepTumor";NA;204
"Building";"CreepTumor";NA;204
"Building";"CreepTumorQueen";NA;204
"Unit";"Zergling";"Larva";204
"Unit";"Zergling";"Larva";205
"Unit";"Zergling";"Larva";206
"Unit";"Zergling";"Larva";207
"Unit";"Zergling";"Larva";208
"Unit";"Zergling";"Larva";209
"Unit";"Zergling";"Larva";210
"Unit";"Zergling";"Larva";211
"Unit";"Zergling";"Larva";212
"Unit";"Zergling";"Larva";213
"Unit";"Zergling";"Larva";214
"Unit";"Zergling";"Larva";215
"Unit";"Zergling";"Larva";216
"Unit";"Zergling";"Larva";217
"Unit";"Zergling";"Larva";218
"Unit";"Zergling";"Larva";219
"Unit";"Zergling";"Larva";220
"Unit";"Zergling";"Larva";221
"Unit";"Zergling";"Larva";222
"Unit";"Zergling";"Larva";223
"Building";"SporeCrawler";NA;227
"Unit";"Hydralisk";"Larva";227
"Unit";"Hydralisk";"Larva";229
"Unit";"Hydralisk";"Larva";231
"Unit";"Overlord";"Larva";233
"Unit";"Overlord";"Larva";233
"Unit";"Overlord";"Larva";233
"Unit";"Overlord";"Larva";233
"Unit";"Overlord";"Larva";233
"Unit";"Overlord";"Larva";233
"Unit";"Baneling";"Zergling";233
"Unit";"Baneling";"Zergling";233
"Unit";"Baneling";"Zergling";233
"Unit";"Baneling";"Zergling";233
"Unit";"Baneling";"Zergling";233
"Unit";"Baneling";"Zergling";233
"Unit";"Baneling";"Zergling";233
"Unit";"Baneling";"Zergling";233
"Unit";"Baneling";"Zergling";233
"Unit";"Baneling";"Zergling";233
"Unit";"Baneling";"Zergling";233
"Unit";"Baneling";"Zergling";233
"Unit";"Baneling";"Zergling";233
"Unit";"Baneling";"Zergling";233
"Unit";"Baneling";"Zergling";233
"Unit";"Zergling";"Larva";233
"Unit";"Zergling";"Larva";234
"Unit";"Zergling";"Larva";235
"Unit";"Zergling";"Larva";236
"Unit";"Zergling";"Larva";237
"Unit";"Zergling";"Larva";238
"Unit";"Zergling";"Larva";239
"Unit";"Zergling";"Larva";240
"Unit";"Zergling";"Larva";241
"Unit";"Zergling";"Larva";242
"Unit";"Zergling";"Larva";243
"Unit";"Zergling";"Larva";244
"Unit";"Zergling";"Larva";245
"Unit";"Zergling";"Larva";246
"Unit";"Zergling";"Larva";247
"Unit";"Zergling";"Larva";248
"Unit";"Zergling";"Larva";249
"Unit";"Zergling";"Larva";250
"Unit";"Zergling";"Larva";251
"Unit";"Zergling";"Larva";252
"Unit";"Zergling";"Larva";253
"Unit";"Zergling";"Larva";254
"Building";"CreepTumor";NA;255
"Building";"CreepTumor";NA;255
"Building";"CreepTumor";NA;255
"Building";"CreepTumor";NA;255
"Building";"CreepTumor";NA;255
"Unit";"Zergling";"Larva";255
"Unit";"Zergling";"Larva";256
"Unit";"Zergling";"Larva";257
"Unit";"Zergling";"Larva";258
"Unit";"Zergling";"Larva";259
"Unit";"Zergling";"Larva";260
"Unit";"Zergling";"Larva";261
"Unit";"Zergling";"Larva";262
"Unit";"Zergling";"Larva";263
"Unit";"Zergling";"Larva";264
"Unit";"Zergling";"Larva";265
"Unit";"Zergling";"Larva";266
"Unit";"Zergling";"Larva";267
"Unit";"Zergling";"Larva";268
"Unit";"Zergling";"Larva";269
"Unit";"Zergling";"Larva";270
"Unit";"Zergling";"Larva";271
"Unit";"Zergling";"Larva";272
"Building";"CreepTumor";NA;273
"Unit";"Zergling";"Larva";273
"Unit";"Zergling";"Larva";274
"Unit";"Zergling";"Larva";275
"Unit";"Zergling";"Larva";276
"Unit";"Baneling";"Zergling";277
"Unit";"Baneling";"Zergling";277
"Unit";"Baneling";"Zergling";277
"Unit";"Overlord";"Larva";280
"Unit";"Zergling";"Larva";280
"Unit";"Zergling";"Larva";281
"Unit";"Zergling";"Larva";282
"Unit";"Zergling";"Larva";283
"Unit";"Zergling";"Larva";284
"Unit";"Zergling";"Larva";285
"Unit";"Zergling";"Larva";286
"Unit";"Zergling";"Larva";287
"Unit";"Zergling";"Larva";288
"Unit";"Zergling";"Larva";289
"Unit";"Zergling";"Larva";290
"Unit";"Zergling";"Larva";291
"Unit";"Zergling";"Larva";292
"Unit";"Zergling";"Larva";293
"Unit";"Zergling";"Larva";294
"Unit";"Zergling";"Larva";295
"Unit";"Baneling";"Zergling";296
"Unit";"Baneling";"Zergling";296
"Unit";"Baneling";"Zergling";296
"Unit";"Baneling";"Zergling";296
"Unit";"Baneling";"Zergling";296
"Unit";"Baneling";"Zergling";296
"Unit";"Zergling";"Larva";296
"Unit";"Zergling";"Larva";297
"Unit";"Zergling";"Larva";298
"Unit";"Zergling";"Larva";299
"Unit";"Zergling";"Larva";300
"Unit";"Zergling";"Larva";301
"Unit";"Zergling";"Larva";302
"Unit";"Zergling";"Larva";303
"Unit";"Zergling";"Larva";304
"Unit";"Zergling";"Larva";305
"Unit";"Zergling";"Larva";306
"Unit";"Zergling";"Larva";307
"Unit";"Zergling";"Larva";308
"Unit";"Zergling";"Larva";309
"Unit";"Zergling";"Larva";310
"Unit";"Zergling";"Larva";311
"Unit";"Zergling";"Larva";312
"Unit";"Zergling";"Larva";313
"Unit";"Zergling";"Larva";314
"Unit";"Zergling";"Larva";315
"Unit";"Zergling";"Larva";316
"Unit";"Zergling";"Larva";317
"Unit";"Zergling";"Larva";325
"Unit";"Zergling";"Larva";326
"Unit";"Zergling";"Larva";327
"Unit";"Zergling";"Larva";328
"Building";"InfestationPit";NA;329
"Unit";"Zergling";"Larva";329
"Unit";"Zergling";"Larva";330
"Unit";"Zergling";"Larva";331
"Unit";"Zergling";"Larva";332
"Unit";"Zergling";"Larva";333
"Unit";"Zergling";"Larva";334
"Unit";"Zergling";"Larva";335
"Unit";"Zergling";"Larva";336
"Unit";"Zergling";"Larva";337
"Unit";"Zergling";"Larva";338
"Unit";"Zergling";"Larva";339
"Unit";"Zergling";"Larva";340
"Unit";"Zergling";"Larva";341
"Unit";"Zergling";"Larva";342
"Unit";"Baneling";"Zergling";343
"Unit";"Baneling";"Zergling";343
"Unit";"Baneling";"Zergling";343
"Unit";"Baneling";"Zergling";343
"Unit";"Baneling";"Zergling";343
"Unit";"Baneling";"Zergling";343
"Unit";"Baneling";"Zergling";343
"Unit";"Baneling";"Zergling";343
"Unit";"Baneling";"Zergling";343
"Building";"Hatchery";NA;343
"Unit";"Baneling";"Zergling";343
"Unit";"Baneling";"Zergling";343
"Unit";"Baneling";"Zergling";343
"Unit";"Baneling";"Zergling";343
"Unit";"Baneling";"Zergling";343
"Unit";"Baneling";"Zergling";343
"Unit";"Baneling";"Zergling";343
"Building";"CreepTumor";NA;343
"Building";"CreepTumor";NA;343
"Building";"CreepTumor";NA;343
"Building";"CreepTumor";NA;343
"Unit";"Zergling";"Larva";343
"Unit";"Zergling";"Larva";344
"Unit";"Zergling";"Larva";345
"Unit";"Zergling";"Larva";346
"Unit";"Zergling";"Larva";347
"Unit";"Zergling";"Larva";348
"Unit";"Zergling";"Larva";349
"Unit";"Zergling";"Larva";350
"Unit";"Zergling";"Larva";351
"Unit";"Zergling";"Larva";352
"Unit";"Zergling";"Larva";353
"Unit";"Zergling";"Larva";354
"Unit";"Zergling";"Larva";355
"Unit";"Zergling";"Larva";356
"Unit";"Zergling";"Larva";357
"Unit";"Zergling";"Larva";358
"Unit";"Zergling";"Larva";359
"Unit";"Zergling";"Larva";360
"Unit";"Zergling";"Larva";361
"Unit";"Zergling";"Larva";362
"Unit";"Zergling";"Larva";363
"Unit";"Zergling";"Larva";364
"Unit";"Zergling";"Larva";365
"Unit";"Zergling";"Larva";366
"Unit";"Zergling";"Larva";367
"Unit";"Zergling";"Larva";368
"Unit";"Zergling";"Larva";369
"Unit";"Zergling";"Larva";370
"Unit";"Zergling";"Larva";371
"Unit";"Zergling";"Larva";372
"Unit";"Zergling";"Larva";373
"Unit";"Zergling";"Larva";374
"Unit";"Zergling";"Larva";375
"Unit";"Zergling";"Larva";376
"Unit";"Zergling";"Larva";377
"Unit";"Zergling";"Larva";378
"Unit";"Zergling";"Larva";379
"Unit";"Zergling";"Larva";380
"Unit";"Zergling";"Larva";381
"Unit";"Zergling";"Larva";382
"Unit";"Zergling";"Larva";383
"Unit";"Zergling";"Larva";384
"Unit";"Zergling";"Larva";385
"Unit";"Zergling";"Larva";386
"Unit";"Zergling";"Larva";387
"Unit";"Zergling";"Larva";388
"Unit";"Zergling";"Larva";389
"Unit";"Zergling";"Larva";390
"Unit";"Baneling";"Zergling";391
"Unit";"Baneling";"Zergling";391
"Unit";"Baneling";"Zergling";391
"Unit";"Baneling";"Zergling";391
"Unit";"Baneling";"Zergling";391
"Unit";"Baneling";"Zergling";391
"Unit";"Baneling";"Zergling";391
"Unit";"Baneling";"Zergling";391
"Unit";"Baneling";"Zergling";391
"Unit";"Baneling";"Zergling";391
"Unit";"Baneling";"Zergling";391
"Unit";"Baneling";"Zergling";391
"Unit";"Zergling";"Larva";391
"Unit";"Zergling";"Larva";392
"Unit";"Zergling";"Larva";393
"Unit";"Zergling";"Larva";394
"Unit";"Zergling";"Larva";395
"Unit";"Zergling";"Larva";396
"Unit";"Hydralisk";"Larva";397
"Unit";"Hydralisk";"Larva";399
"Unit";"Hydralisk";"Larva";401
"Unit";"Hydralisk";"Larva";403
"Unit";"Hydralisk";"Larva";405
"Unit";"Hydralisk";"Larva";407
"Unit";"Hydralisk";"Larva";409
"Unit";"Hydralisk";"Larva";411
"Unit";"Hydralisk";"Larva";413
"Unit";"Zergling";"Larva";415
"Unit";"Zergling";"Larva";416
"Unit";"Zergling";"Larva";417
"Unit";"Zergling";"Larva";418
"Unit";"Zergling";"Larva";419
"Unit";"Zergling";"Larva";420
"Unit";"Zergling";"Larva";421
"Unit";"Zergling";"Larva";422
"Unit";"Zergling";"Larva";423
"Unit";"Zergling";"Larva";424
"Unit";"Zergling";"Larva";425
"Unit";"Zergling";"Larva";426
"Unit";"Zergling";"Larva";427
"Unit";"Zergling";"Larva";428
"Unit";"Zergling";"Larva";429
"Unit";"Zergling";"Larva";430
"Unit";"Hydralisk";"Larva";431
"Unit";"Hydralisk";"Larva";433
"Unit";"Hydralisk";"Larva";435
"Unit";"Hydralisk";"Larva";437
"Unit";"Hydralisk";"Larva";439
"Unit";"Hydralisk";"Larva";441
"Unit";"Hydralisk";"Larva";443
"Unit";"Hydralisk";"Larva";445
"Unit";"Hydralisk";"Larva";447
"Unit";"Hydralisk";"Larva";449
"Unit";"Hydralisk";"Larva";451
"Unit";"Hydralisk";"Larva";453
"Unit";"Zergling";"Larva";455
"Unit";"Zergling";"Larva";456
"Unit";"Zergling";"Larva";457
"Unit";"Zergling";"Larva";458
"Unit";"Zergling";"Larva";459
"Unit";"Zergling";"Larva";460
"Unit";"Zergling";"Larva";461
"Unit";"Zergling";"Larva";462
"Unit";"Zergling";"Larva";463
"Unit";"Zergling";"Larva";464
"Unit";"Zergling";"Larva";465
"Unit";"Zergling";"Larva";466
"Unit";"Zergling";"Larva";467
"Unit";"Zergling";"Larva";468
"Unit";"Zergling";"Larva";469
"Unit";"Zergling";"Larva";470
"Unit";"Zergling";"Larva";471
"Unit";"Zergling";"Larva";472
"Unit";"Zergling";"Larva";473
"Unit";"Zergling";"Larva";474
"Unit";"Zergling";"Larva";475
"Unit";"Zergling";"Larva";476
"Unit";"Zergling";"Larva";477
"Unit";"Zergling";"Larva";478
"Unit";"Zergling";"Larva";479
"Unit";"Zergling";"Larva";480
"Unit";"Zergling";"Larva";481
"Unit";"Zergling";"Larva";482
"Unit";"Zergling";"Larva";483
"Unit";"Zergling";"Larva";484
"Unit";"Zergling";"Larva";485
"Unit";"Zergling";"Larva";486
"Unit";"Zergling";"Larva";487
"Unit";"Zergling";"Larva";488
"Unit";"Zergling";"Larva";489
"Unit";"Zergling";"Larva";490
"Unit";"Zergling";"Larva";491
"Unit";"Zergling";"Larva";492
"Unit";"Zergling";"Larva";493
"Unit";"Zergling";"Larva";494
"Unit";"Zergling";"Larva";495
"Unit";"Zergling";"Larva";496
"Unit";"Zergling";"Larva";497
"Unit";"Zergling";"Larva";498
"Unit";"Zergling";"Larva";499
"Unit";"Zergling";"Larva";500
"Unit";"Zergling";"Larva";501
"Unit";"Zergling";"Larva";502
"Unit";"Zergling";"Larva";503
"Unit";"Zergling";"Larva";504
"Unit";"Baneling";"Zergling";505
"Unit";"Baneling";"Zergling";505
"Unit";"Baneling";"Zergling";505
"Unit";"Baneling";"Zergling";505
"Unit";"Baneling";"Zergling";505
"Unit";"Baneling";"Zergling";505
"Unit";"Baneling";"Zergling";505
"Unit";"Baneling";"Zergling";505
"Unit";"Baneling";"Zergling";505
"Unit";"Baneling";"Zergling";505
"Unit";"Baneling";"Zergling";505
"Unit";"Baneling";"Zergling";505
"Unit";"Baneling";"Zergling";505
"Unit";"Baneling";"Zergling";505
"Unit";"Zergling";"Larva";505
"Unit";"Zergling";"Larva";506
"Unit";"Zergling";"Larva";507
"Unit";"Zergling";"Larva";508
"Unit";"Zergling";"Larva";509
"Unit";"Zergling";"Larva";510
"Unit";"Zergling";"Larva";511
"Unit";"Zergling";"Larva";512
"Unit";"Zergling";"Larva";513
"Unit";"Zergling";"Larva";514
"Unit";"Baneling";"Zergling";515
"Unit";"Baneling";"Zergling";515
"Unit";"Baneling";"Zergling";515
"Unit";"Zergling";"Larva";515
"Unit";"Zergling";"Larva";516
"Unit";"Zergling";"Larva";517
"Unit";"Zergling";"Larva";518
"Unit";"Zergling";"Larva";519
"Unit";"Zergling";"Larva";520
"Unit";"Zergling";"Larva";521
"Unit";"Zergling";"Larva";522
"Unit";"Zergling";"Larva";523
"Unit";"Zergling";"Larva";524
"Unit";"Zergling";"Larva";525
"Unit";"Zergling";"Larva";526
"Unit";"Zergling";"Larva";527
"Unit";"Zergling";"Larva";528
"Unit";"Zergling";"Larva";529
"Unit";"Zergling";"Larva";530
"Building";"CreepTumor";NA;531
"Building";"CreepTumor";NA;531
"Unit";"Zergling";"Larva";531
"Unit";"Zergling";"Larva";532
"Unit";"Zergling";"Larva";533
"Unit";"Zergling";"Larva";534
"Unit";"Zergling";"Larva";535
"Unit";"Zergling";"Larva";536
"Unit";"Zergling";"Larva";537
"Unit";"Zergling";"Larva";538
"Unit";"Zergling";"Larva";539
"Unit";"Zergling";"Larva";540
"Unit";"Zergling";"Larva";541
"Unit";"Zergling";"Larva";542
"Unit";"Zergling";"Larva";543
"Unit";"Zergling";"Larva";544
"Unit";"Zergling";"Larva";545
"Unit";"Zergling";"Larva";546
"Unit";"Zergling";"Larva";547
"Unit";"Zergling";"Larva";548
"Unit";"Zergling";"Larva";549
"Unit";"Zergling";"Larva";550
"Unit";"Zergling";"Larva";551
"Unit";"Zergling";"Larva";552
"Unit";"Zergling";"Larva";553
"Unit";"Zergling";"Larva";554
"Unit";"Zergling";"Larva";555
"Unit";"Zergling";"Larva";556
"Unit";"Zergling";"Larva";557
"Unit";"Zergling";"Larva";558
"Unit";"Baneling";"Zergling";559
"Unit";"Baneling";"Zergling";559
"Unit";"Baneling";"Zergling";559
"Unit";"Baneling";"Zergling";559
"Unit";"Baneling";"Zergling";559
"Unit";"Baneling";"Zergling";559
"Unit";"Baneling";"Zergling";559
"Unit";"Baneling";"Zergling";559
"Unit";"Baneling";"Zergling";559
"Unit";"Baneling";"Zergling";559
"Unit";"Baneling";"Zergling";559
"Unit";"Baneling";"Zergling";559
"Unit";"Baneling";"Zergling";559
"Unit";"Baneling";"Zergling";559
"Building";"Extractor";NA;563
"Upgrade";"SprayZerg";NA;563
"Upgrade";"SprayZerg";NA;563
"Upgrade";"zerglingmovementspeed";NA;563
"Upgrade";"SprayZerg";NA;563
"Upgrade";"SprayZerg";NA;563
"Upgrade";"SprayZerg";NA;563
"Upgrade";"ZergMeleeWeaponsLevel1";NA;563
"Upgrade";"ZergGroundArmorsLevel1";NA;563
"Upgrade";"SprayZerg";NA;563
"Upgrade";"SprayZerg";NA;563
"Upgrade";"CentrificalHooks";NA;563
"Upgrade";"EvolveMuscularAugments";NA;563
"Upgrade";"SprayZerg";NA;563
"Upgrade";"overlordspeed";NA;563
"Upgrade";"ZergMeleeWeaponsLevel2";NA;563
"Upgrade";"ZergGroundArmorsLevel2";NA;563
"Upgrade";"SprayZerg";NA;563
"Upgrade";"SprayZerg";NA;563
"Upgrade";"ZergMissileWeaponsLevel1";NA;563
