"type";"unit_name";"on_building";"total_supply_lag";"supply"
"Unit";"Overlord";"Larva";13;0
"Building";"Extractor";NA;17;0
"Building";"SpawningPool";NA;18;0
"Building";"Hatchery";NA;20;0
"Unit";"Queen";"Hatchery";21;2
"Unit";"Zergling";"Larva";23;1
"Unit";"Zergling";"Larva";24;1
"Unit";"Overlord";"Larva";25;0
"Unit";"Queen";"Hatchery";28;2
"Unit";"Queen";"Hatchery";31;2
"Unit";"Overlord";"Larva";35;0
"Building";"CreepTumorQueen";NA;42;0
"Building";"Hatchery";NA;42;0
"Unit";"Overlord";"Larva";47;0
"Building";"CreepTumor";NA;49;0
"Unit";"Overlord";"Larva";49;0
"Building";"CreepTumorQueen";NA;49;0
"Building";"RoachWarren";NA;49;0
"Unit";"Queen";"Hatchery";49;2
"Unit";"Queen";"Hatchery";51;2
"Building";"EvolutionChamber";NA;55;0
"Building";"CreepTumor";NA;58;0
"Unit";"Zergling";"Larva";58;1
"Unit";"Zergling";"Larva";59;1
"Unit";"Zergling";"Larva";60;1
"Unit";"Zergling";"Larva";61;1
"Building";"CreepTumor";NA;62;0
"Unit";"Zergling";"Larva";62;1
"Unit";"Zergling";"Larva";63;1
"Unit";"Overlord";"Larva";64;0
"Building";"Extractor";NA;66;0
"Building";"Extractor";NA;69;0
"Unit";"Overlord";"Larva";70;0
"Building";"CreepTumor";NA;72;0
"Unit";"Overlord";"Larva";72;0
"Unit";"Roach";"Larva";72;2
"Unit";"Roach";"Larva";74;2
"Building";"CreepTumor";NA;76;0
"Unit";"Roach";"Larva";76;2
"Unit";"Queen";"Hatchery";81;2
"Unit";"Overlord";"Larva";85;0
"Building";"CreepTumor";NA;85;0
"Unit";"Overlord";"Larva";86;0
"Unit";"Roach";"Larva";88;2
"Unit";"Roach";"Larva";90;2
"Unit";"Roach";"Larva";92;2
"Building";"SporeCrawler";NA;94;0
"Building";"SporeCrawler";NA;94;0
"Building";"SporeCrawler";NA;94;0
"Building";"Extractor";NA;98;0
"Building";"Extractor";NA;98;0
"Building";"CreepTumor";NA;98;0
"Building";"CreepTumor";NA;98;0
"Building";"CreepTumorQueen";NA;98;0
"Unit";"Overlord";"Larva";98;0
"Unit";"Zergling";"Larva";98;1
"Unit";"Zergling";"Larva";99;1
"Unit";"Zergling";"Larva";100;1
"Unit";"Zergling";"Larva";101;1
"Unit";"Zergling";"Larva";102;1
"Unit";"Zergling";"Larva";103;1
"Unit";"Zergling";"Larva";104;1
"Unit";"Zergling";"Larva";105;1
"Unit";"Overlord";"Larva";106;0
"Building";"Extractor";NA;112;0
"Upgrade";"GlialReconstitution";"RoachWarren";113;0
"Building";"CreepTumor";NA;113;0
"Building";"Spire";NA;113;0
"Building";"CreepTumor";NA;122;0
"Building";"CreepTumor";NA;122;0
"Unit";"Overlord";"Larva";144;0
"Unit";"Mutalisk";"Larva";144;2
"Unit";"Mutalisk";"Larva";146;2
"Unit";"Mutalisk";"Larva";148;2
"Unit";"Mutalisk";"Larva";150;2
"Unit";"Mutalisk";"Larva";152;2
"Unit";"Mutalisk";"Larva";154;2
"Unit";"Overlord";"Larva";156;0
"Unit";"Mutalisk";"Larva";156;2
"Unit";"Overlord";"Larva";158;0
"Unit";"Overlord";"Larva";158;0
"Building";"InfestationPit";NA;158;0
"Building";"CreepTumor";NA;158;0
"Building";"Hatchery";NA;158;0
"Building";"CreepTumor";NA;158;0
"Unit";"Overlord";"Larva";158;0
"Unit";"Overlord";"Larva";158;0
"Unit";"Roach";"Larva";158;2
"Unit";"Roach";"Larva";160;2
"Unit";"Roach";"Larva";162;2
"Unit";"Roach";"Larva";164;2
"Unit";"Roach";"Larva";166;2
"Unit";"Roach";"Larva";168;2
"Building";"CreepTumorQueen";NA;170;0
"Building";"CreepTumorQueen";NA;170;0
"Building";"CreepTumorQueen";NA;170;0
"Unit";"Overlord";"Larva";172;0
"Unit";"Overlord";"Larva";172;0
"Building";"EvolutionChamber";NA;173;0
"Unit";"Overlord";"Larva";173;0
"Building";"CreepTumor";NA;173;0
"Building";"CreepTumor";NA;173;0
"Building";"CreepTumor";NA;173;0
"Unit";"Overlord";"Larva";173;0
"Building";"HydraliskDen";NA;173;0
"Building";"CreepTumor";NA;178;0
"Building";"CreepTumor";NA;178;0
"Building";"Extractor";NA;182;0
"Building";"Extractor";NA;182;0
"Unit";"Roach";"Larva";183;2
"Unit";"Roach";"Larva";185;2
"Unit";"Roach";"Larva";187;2
"Unit";"Roach";"Larva";189;2
"Building";"CreepTumor";NA;191;0
"Building";"SporeCrawler";NA;193;0
"Building";"BanelingNest";NA;194;0
"Building";"CreepTumorQueen";NA;194;0
"Unit";"Zergling";"Larva";194;1
"Unit";"Zergling";"Larva";195;1
"Unit";"Zergling";"Larva";196;1
"Unit";"Zergling";"Larva";197;1
"Unit";"Zergling";"Larva";198;1
"Unit";"Zergling";"Larva";199;1
"Unit";"Zergling";"Larva";200;1
"Unit";"Zergling";"Larva";201;1
"Unit";"Zergling";"Larva";202;1
"Unit";"Zergling";"Larva";203;1
"Unit";"Zergling";"Larva";204;1
"Unit";"Zergling";"Larva";205;1
"Unit";"Zergling";"Larva";206;1
"Unit";"Zergling";"Larva";207;1
"Unit";"Overlord";"Larva";208;0
"Unit";"Overlord";"Larva";208;0
"Building";"CreepTumor";NA;208;0
"Building";"CreepTumorQueen";NA;208;0
"Building";"CreepTumor";NA;208;0
"Building";"CreepTumorQueen";NA;208;0
"Unit";"Overlord";"Larva";208;0
"Unit";"Overlord";"Larva";208;0
"Unit";"Overlord";"Larva";208;0
"Building";"Hatchery";NA;208;0
"Building";"CreepTumorQueen";NA;208;0
"Building";"CreepTumorQueen";NA;212;0
"Building";"CreepTumorQueen";NA;212;0
"Building";"CreepTumorQueen";NA;215;0
"Unit";"Roach";"Larva";215;2
"Unit";"Roach";"Larva";217;2
"Unit";"Roach";"Larva";219;2
"Unit";"Zergling";"Larva";221;1
"Unit";"Zergling";"Larva";222;1
"Unit";"Zergling";"Larva";223;1
"Unit";"Zergling";"Larva";224;1
"Unit";"Roach";"Larva";225;2
"Unit";"Roach";"Larva";227;2
"Unit";"Baneling";"Zergling";229;0
"Unit";"Zergling";"Larva";229;1
"Unit";"Zergling";"Larva";230;1
"Unit";"Zergling";"Larva";231;1
"Unit";"Zergling";"Larva";232;1
"Building";"CreepTumor";NA;233;0
"Building";"CreepTumorQueen";NA;233;0
"Building";"EvolutionChamber";NA;236;0
"Unit";"Hydralisk";"Larva";236;2
"Unit";"Hydralisk";"Larva";238;2
"Unit";"Hydralisk";"Larva";240;2
"Unit";"Hydralisk";"Larva";242;2
"Unit";"Hydralisk";"Larva";244;2
"Unit";"Hydralisk";"Larva";246;2
"Unit";"Hydralisk";"Larva";248;2
"Unit";"Zergling";"Larva";250;1
"Unit";"Zergling";"Larva";251;1
"Unit";"Zergling";"Larva";252;1
"Unit";"Zergling";"Larva";253;1
"Building";"Hatchery";NA;254;0
"Building";"CreepTumorQueen";NA;254;0
"Unit";"Zergling";"Larva";254;1
"Unit";"Zergling";"Larva";255;1
"Unit";"Zergling";"Larva";256;1
"Unit";"Zergling";"Larva";257;1
"Unit";"Zergling";"Larva";258;1
"Unit";"Zergling";"Larva";259;1
"Unit";"Zergling";"Larva";260;1
"Unit";"Zergling";"Larva";261;1
"Unit";"Zergling";"Larva";262;1
"Unit";"Zergling";"Larva";263;1
"Unit";"Zergling";"Larva";264;1
"Unit";"Zergling";"Larva";265;1
"Unit";"Zergling";"Larva";266;1
"Unit";"Zergling";"Larva";267;1
"Unit";"Zergling";"Larva";268;1
"Unit";"Zergling";"Larva";269;1
"Unit";"Zergling";"Larva";270;1
"Unit";"Zergling";"Larva";271;1
"Unit";"Zergling";"Larva";272;1
"Unit";"Zergling";"Larva";273;1
"Unit";"Zergling";"Larva";274;1
"Unit";"Zergling";"Larva";275;1
"Unit";"Zergling";"Larva";276;1
"Unit";"Zergling";"Larva";277;1
"Unit";"Zergling";"Larva";278;1
"Unit";"Zergling";"Larva";279;1
"Unit";"Zergling";"Larva";280;1
"Unit";"Zergling";"Larva";281;1
"Building";"CreepTumor";NA;282;0
"Unit";"Baneling";"Zergling";282;0
"Unit";"Baneling";"Zergling";282;0
"Unit";"Baneling";"Zergling";282;0
"Unit";"Baneling";"Zergling";282;0
"Unit";"Baneling";"Zergling";282;0
"Unit";"Baneling";"Zergling";282;0
"Unit";"Baneling";"Zergling";282;0
"Unit";"Baneling";"Zergling";282;0
"Unit";"Baneling";"Zergling";282;0
"Unit";"Baneling";"Zergling";282;0
"Unit";"Baneling";"Zergling";282;0
"Unit";"Baneling";"Zergling";282;0
"Unit";"Baneling";"Zergling";282;0
"Unit";"Baneling";"Zergling";282;0
"Unit";"Baneling";"Zergling";282;0
"Unit";"Baneling";"Zergling";282;0
"Unit";"Baneling";"Zergling";282;0
"Unit";"Baneling";"Zergling";282;0
"Unit";"Zergling";"Larva";282;1
"Unit";"Zergling";"Larva";283;1
"Building";"CreepTumor";NA;284;0
"Building";"CreepTumor";NA;284;0
"Unit";"Zergling";"Larva";284;1
"Unit";"Zergling";"Larva";285;1
"Unit";"Zergling";"Larva";286;1
"Unit";"Zergling";"Larva";287;1
"Unit";"Zergling";"Larva";288;1
"Unit";"Zergling";"Larva";289;1
"Unit";"Zergling";"Larva";290;1
"Unit";"Zergling";"Larva";291;1
"Unit";"Baneling";"Zergling";292;0
"Unit";"Baneling";"Zergling";292;0
"Unit";"Baneling";"Zergling";292;0
"Unit";"Baneling";"Zergling";292;0
"Unit";"Baneling";"Zergling";292;0
"Unit";"Baneling";"Zergling";292;0
"Unit";"Baneling";"Zergling";292;0
"Unit";"Baneling";"Zergling";292;0
"Unit";"Baneling";"Zergling";292;0
"Unit";"Baneling";"Zergling";292;0
"Unit";"Baneling";"Zergling";292;0
"Unit";"Baneling";"Zergling";292;0
"Unit";"Baneling";"Zergling";292;0
"Unit";"Baneling";"Zergling";292;0
"Unit";"Baneling";"Zergling";292;0
"Unit";"Baneling";"Zergling";292;0
"Unit";"Zergling";"Larva";292;1
"Unit";"Zergling";"Larva";293;1
"Unit";"Zergling";"Larva";294;1
"Unit";"Zergling";"Larva";295;1
"Unit";"Zergling";"Larva";296;1
"Unit";"Zergling";"Larva";297;1
"Unit";"Zergling";"Larva";298;1
"Unit";"Zergling";"Larva";299;1
"Unit";"Zergling";"Larva";300;1
"Unit";"Zergling";"Larva";301;1
"Unit";"Zergling";"Larva";302;1
"Unit";"Zergling";"Larva";303;1
"Unit";"Zergling";"Larva";304;1
"Unit";"Zergling";"Larva";305;1
"Unit";"Zergling";"Larva";306;1
"Unit";"Zergling";"Larva";307;1
"Unit";"Zergling";"Larva";308;1
"Unit";"Zergling";"Larva";309;1
"Unit";"Zergling";"Larva";310;1
"Unit";"Zergling";"Larva";311;1
"Unit";"Zergling";"Larva";312;1
"Unit";"Zergling";"Larva";313;1
"Building";"SporeCrawler";NA;314;0
"Building";"SporeCrawler";NA;314;0
"Building";"SpineCrawler";NA;314;0
"Building";"SpineCrawler";NA;314;0
"Building";"CreepTumor";NA;314;0
"Building";"CreepTumor";NA;314;0
"Unit";"Hydralisk";"Larva";314;2
"Unit";"Hydralisk";"Larva";316;2
"Unit";"Hydralisk";"Larva";318;2
"Unit";"Hydralisk";"Larva";320;2
"Unit";"Hydralisk";"Larva";322;2
"Unit";"Hydralisk";"Larva";324;2
"Unit";"Hydralisk";"Larva";326;2
"Building";"SpineCrawler";NA;328;0
"Unit";"Zergling";"Larva";328;1
"Unit";"Zergling";"Larva";329;1
"Unit";"Zergling";"Larva";330;1
"Unit";"Zergling";"Larva";331;1
"Unit";"Zergling";"Larva";332;1
"Unit";"Zergling";"Larva";333;1
"Unit";"Zergling";"Larva";334;1
"Unit";"Zergling";"Larva";335;1
"Unit";"Zergling";"Larva";336;1
"Unit";"Zergling";"Larva";337;1
"Unit";"Zergling";"Larva";338;1
"Unit";"Zergling";"Larva";339;1
"Unit";"Zergling";"Larva";340;1
"Unit";"Zergling";"Larva";341;1
"Unit";"Zergling";"Larva";342;1
"Unit";"Zergling";"Larva";343;1
"Unit";"Zergling";"Larva";344;1
"Unit";"Zergling";"Larva";345;1
"Unit";"Zergling";"Larva";346;1
"Unit";"Zergling";"Larva";347;1
"Unit";"Baneling";"Zergling";348;0
"Unit";"Baneling";"Zergling";348;0
"Unit";"Baneling";"Zergling";348;0
"Unit";"Baneling";"Zergling";348;0
"Unit";"Baneling";"Zergling";348;0
"Unit";"Baneling";"Zergling";348;0
"Unit";"Baneling";"Zergling";348;0
"Unit";"Baneling";"Zergling";348;0
"Unit";"Baneling";"Zergling";348;0
"Unit";"Baneling";"Zergling";348;0
"Unit";"Baneling";"Zergling";348;0
"Unit";"Baneling";"Zergling";348;0
"Unit";"Baneling";"Zergling";348;0
"Unit";"Baneling";"Zergling";348;0
"Unit";"Baneling";"Zergling";348;0
"Unit";"Baneling";"Zergling";348;0
"Unit";"Baneling";"Zergling";348;0
"Unit";"Baneling";"Zergling";348;0
"Unit";"Baneling";"Zergling";348;0
"Unit";"Baneling";"Zergling";348;0
"Unit";"Baneling";"Zergling";348;0
"Unit";"Baneling";"Zergling";348;0
"Unit";"Baneling";"Zergling";348;0
"Unit";"Baneling";"Zergling";348;0
"Unit";"Baneling";"Zergling";348;0
"Unit";"Baneling";"Zergling";348;0
"Unit";"Baneling";"Zergling";348;0
"Unit";"Baneling";"Zergling";348;0
"Unit";"Baneling";"Zergling";348;0
"Unit";"Baneling";"Zergling";348;0
"Unit";"Baneling";"Zergling";348;0
"Unit";"Hydralisk";"Larva";348;2
"Unit";"Hydralisk";"Larva";350;2
"Unit";"Hydralisk";"Larva";352;2
"Unit";"Hydralisk";"Larva";354;2
"Unit";"Hydralisk";"Larva";356;2
"Unit";"Hydralisk";"Larva";358;2
"Unit";"Zergling";"Larva";360;1
"Unit";"Zergling";"Larva";361;1
"Unit";"Zergling";"Larva";362;1
"Unit";"Zergling";"Larva";363;1
"Unit";"Zergling";"Larva";364;1
"Unit";"Zergling";"Larva";365;1
"Unit";"Zergling";"Larva";366;1
"Unit";"Zergling";"Larva";367;1
"Unit";"Zergling";"Larva";368;1
"Unit";"Zergling";"Larva";369;1
"Unit";"Zergling";"Larva";370;1
"Unit";"Zergling";"Larva";371;1
"Unit";"Zergling";"Larva";372;1
"Unit";"Zergling";"Larva";373;1
"Unit";"Zergling";"Larva";374;1
"Unit";"Zergling";"Larva";375;1
"Unit";"Zergling";"Larva";376;1
"Unit";"Zergling";"Larva";377;1
"Unit";"Zergling";"Larva";378;1
"Unit";"Zergling";"Larva";379;1
"Unit";"Zergling";"Larva";380;1
"Unit";"Zergling";"Larva";381;1
"Unit";"Zergling";"Larva";382;1
"Unit";"Zergling";"Larva";383;1
"Unit";"Zergling";"Larva";384;1
"Unit";"Zergling";"Larva";385;1
"Unit";"Zergling";"Larva";386;1
"Unit";"Zergling";"Larva";387;1
"Unit";"Zergling";"Larva";388;1
"Unit";"Zergling";"Larva";389;1
"Unit";"Zergling";"Larva";390;1
"Unit";"Zergling";"Larva";391;1
"Unit";"Zergling";"Larva";392;1
"Unit";"Zergling";"Larva";393;1
"Unit";"Overlord";"Larva";394;0
"Unit";"Overlord";"Larva";394;0
"Unit";"Overlord";"Larva";394;0
"Unit";"Overlord";"Larva";394;0
"Unit";"Overlord";"Larva";394;0
"Unit";"Overlord";"Larva";394;0
"Unit";"Baneling";"Zergling";394;0
"Unit";"Baneling";"Zergling";394;0
"Unit";"Baneling";"Zergling";394;0
"Unit";"Baneling";"Zergling";394;0
"Unit";"Baneling";"Zergling";394;0
"Unit";"Baneling";"Zergling";394;0
"Unit";"Baneling";"Zergling";394;0
"Unit";"Baneling";"Zergling";394;0
"Unit";"Baneling";"Zergling";394;0
"Unit";"Baneling";"Zergling";394;0
"Unit";"Baneling";"Zergling";394;0
"Unit";"Baneling";"Zergling";394;0
"Unit";"Baneling";"Zergling";394;0
"Unit";"Baneling";"Zergling";394;0
"Unit";"Baneling";"Zergling";394;0
"Unit";"Baneling";"Zergling";394;0
"Unit";"Viper";"Larva";394;3
"Unit";"Viper";"Larva";397;3
"Unit";"Viper";"Larva";400;3
"Unit";"Zergling";"Larva";403;1
"Unit";"Zergling";"Larva";404;1
"Unit";"Zergling";"Larva";405;1
"Unit";"Zergling";"Larva";406;1
"Unit";"Zergling";"Larva";407;1
"Unit";"Zergling";"Larva";408;1
"Unit";"Zergling";"Larva";409;1
"Unit";"Zergling";"Larva";410;1
"Unit";"Zergling";"Larva";411;1
"Unit";"Zergling";"Larva";412;1
"Unit";"Zergling";"Larva";413;1
"Unit";"Zergling";"Larva";414;1
"Unit";"Zergling";"Larva";415;1
"Unit";"Zergling";"Larva";416;1
"Unit";"Zergling";"Larva";417;1
"Unit";"Zergling";"Larva";418;1
"Unit";"Zergling";"Larva";419;1
"Unit";"Zergling";"Larva";420;1
"Building";"Hatchery";NA;421;0
"Building";"CreepTumorQueen";NA;421;0
"Unit";"Corruptor";"Larva";421;2
"Unit";"Corruptor";"Larva";423;2
"Unit";"Corruptor";"Larva";425;2
"Unit";"Corruptor";"Larva";427;2
"Unit";"Corruptor";"Larva";429;2
"Unit";"Corruptor";"Larva";431;2
"Building";"CreepTumorQueen";NA;433;0
"Building";"CreepTumorQueen";NA;433;0
"Building";"CreepTumorQueen";NA;433;0
"Building";"Hatchery";NA;433;0
"Unit";"Zergling";"Larva";433;1
"Unit";"Zergling";"Larva";434;1
"Unit";"Zergling";"Larva";435;1
"Unit";"Zergling";"Larva";436;1
"Unit";"Zergling";"Larva";437;1
"Unit";"Zergling";"Larva";438;1
"Unit";"Zergling";"Larva";439;1
"Unit";"Zergling";"Larva";440;1
"Unit";"Zergling";"Larva";441;1
"Unit";"Zergling";"Larva";442;1
"Unit";"Zergling";"Larva";443;1
"Unit";"Zergling";"Larva";444;1
"Unit";"Zergling";"Larva";445;1
"Unit";"Zergling";"Larva";446;1
"Building";"CreepTumor";NA;447;0
"Building";"CreepTumor";NA;447;0
"Building";"CreepTumor";NA;447;0
"Building";"CreepTumor";NA;447;0
"Building";"CreepTumor";NA;447;0
"Unit";"Baneling";"Zergling";447;0
"Unit";"Baneling";"Zergling";447;0
"Unit";"Baneling";"Zergling";447;0
"Unit";"Baneling";"Zergling";447;0
"Unit";"Baneling";"Zergling";447;0
"Unit";"Baneling";"Zergling";447;0
"Unit";"Baneling";"Zergling";447;0
"Unit";"Baneling";"Zergling";447;0
"Unit";"Baneling";"Zergling";447;0
"Unit";"Baneling";"Zergling";447;0
"Unit";"Baneling";"Zergling";447;0
"Building";"CreepTumor";NA;447;0
"Building";"CreepTumor";NA;447;0
"Building";"CreepTumor";NA;447;0
"Building";"CreepTumor";NA;447;0
"Building";"CreepTumor";NA;447;0
"Building";"Hatchery";NA;447;0
"Building";"CreepTumor";NA;447;0
"Unit";"Zergling";"Larva";447;1
"Unit";"Zergling";"Larva";448;1
"Unit";"Zergling";"Larva";449;1
"Unit";"Zergling";"Larva";450;1
"Unit";"Zergling";"Larva";451;1
"Unit";"Zergling";"Larva";452;1
"Unit";"Baneling";"Zergling";453;0
"Unit";"Baneling";"Zergling";453;0
"Unit";"Baneling";"Zergling";453;0
"Unit";"Baneling";"Zergling";453;0
"Unit";"Baneling";"Zergling";453;0
"Unit";"Baneling";"Zergling";453;0
"Unit";"Baneling";"Zergling";453;0
"Unit";"Baneling";"Zergling";453;0
"Unit";"Baneling";"Zergling";453;0
"Unit";"Corruptor";"Larva";453;2
"Unit";"Corruptor";"Larva";455;2
"Unit";"Corruptor";"Larva";457;2
"Unit";"Corruptor";"Larva";459;2
"Unit";"Zergling";"Larva";461;1
"Unit";"Zergling";"Larva";462;1
"Unit";"Zergling";"Larva";463;1
"Unit";"Zergling";"Larva";464;1
"Unit";"Zergling";"Larva";465;1
"Unit";"Zergling";"Larva";466;1
"Unit";"Zergling";"Larva";467;1
"Unit";"Zergling";"Larva";468;1
"Unit";"Zergling";"Larva";469;1
"Unit";"Zergling";"Larva";470;1
"Unit";"Zergling";"Larva";471;1
"Unit";"Zergling";"Larva";472;1
"Unit";"Zergling";"Larva";473;1
"Unit";"Zergling";"Larva";474;1
"Unit";"Zergling";"Larva";475;1
"Unit";"Zergling";"Larva";476;1
"Unit";"Zergling";"Larva";477;1
"Unit";"Zergling";"Larva";478;1
"Unit";"Zergling";"Larva";479;1
"Unit";"Zergling";"Larva";480;1
"Unit";"Zergling";"Larva";481;1
"Unit";"Zergling";"Larva";482;1
"Unit";"Zergling";"Larva";483;1
"Unit";"Zergling";"Larva";484;1
"Unit";"Zergling";"Larva";485;1
"Unit";"Zergling";"Larva";486;1
"Unit";"Zergling";"Larva";487;1
"Unit";"Zergling";"Larva";488;1
"Unit";"Zergling";"Larva";489;1
"Unit";"Zergling";"Larva";490;1
"Unit";"Zergling";"Larva";491;1
"Unit";"Zergling";"Larva";492;1
"Unit";"Corruptor";"Larva";493;2
"Unit";"Corruptor";"Larva";495;2
"Unit";"Corruptor";"Larva";497;2
"Unit";"Corruptor";"Larva";499;2
"Unit";"Corruptor";"Larva";501;2
"Unit";"Zergling";"Larva";503;1
"Unit";"Zergling";"Larva";504;1
"Unit";"Zergling";"Larva";505;1
"Unit";"Zergling";"Larva";506;1
"Unit";"Zergling";"Larva";507;1
"Unit";"Zergling";"Larva";508;1
"Unit";"Zergling";"Larva";509;1
"Unit";"Zergling";"Larva";510;1
"Unit";"Zergling";"Larva";511;1
"Unit";"Zergling";"Larva";512;1
"Unit";"Zergling";"Larva";513;1
"Unit";"Zergling";"Larva";514;1
"Unit";"Zergling";"Larva";515;1
"Unit";"Zergling";"Larva";516;1
"Unit";"Zergling";"Larva";517;1
"Unit";"Zergling";"Larva";518;1
"Unit";"Corruptor";"Larva";519;2
"Unit";"Corruptor";"Larva";521;2
"Unit";"Corruptor";"Larva";523;2
"Unit";"Corruptor";"Larva";525;2
"Unit";"Corruptor";"Larva";527;2
"Unit";"Corruptor";"Larva";529;2
"Unit";"Corruptor";"Larva";531;2
"Unit";"Hydralisk";"Larva";533;2
"Unit";"Zergling";"Larva";535;1
"Unit";"Zergling";"Larva";536;1
"Unit";"Zergling";"Larva";545;1
"Unit";"Zergling";"Larva";546;1
"Unit";"Hydralisk";"Larva";559;2
"Unit";"Hydralisk";"Larva";561;2
"Unit";"Hydralisk";"Larva";563;2
"Unit";"Hydralisk";"Larva";565;2
"Unit";"Hydralisk";"Larva";567;2
"Unit";"Hydralisk";"Larva";569;2
"Unit";"Hydralisk";"Larva";575;2
"Unit";"Hydralisk";"Larva";577;2
"Unit";"Zergling";"Larva";579;1
"Unit";"Zergling";"Larva";580;1
"Unit";"Zergling";"Larva";581;1
"Unit";"Zergling";"Larva";582;1
"Unit";"Zergling";"Larva";583;1
"Unit";"Zergling";"Larva";584;1
"Unit";"Zergling";"Larva";585;1
"Unit";"Zergling";"Larva";586;1
"Unit";"Zergling";"Larva";587;1
"Unit";"Zergling";"Larva";588;1
"Unit";"Zergling";"Larva";589;1
"Unit";"Zergling";"Larva";590;1
"Unit";"Zergling";"Larva";591;1
"Unit";"Zergling";"Larva";592;1
"Unit";"Zergling";"Larva";593;1
"Unit";"Zergling";"Larva";594;1
"Unit";"Zergling";"Larva";595;1
"Unit";"Zergling";"Larva";596;1
"Unit";"Zergling";"Larva";597;1
"Unit";"Zergling";"Larva";598;1
"Unit";"Zergling";"Larva";599;1
"Unit";"Zergling";"Larva";600;1
"Unit";"Zergling";"Larva";601;1
"Unit";"Zergling";"Larva";602;1
"Unit";"Zergling";"Larva";603;1
"Unit";"Zergling";"Larva";604;1
"Unit";"Zergling";"Larva";605;1
"Unit";"Zergling";"Larva";606;1
"Unit";"Zergling";"Larva";607;1
"Unit";"Zergling";"Larva";608;1
"Unit";"Zergling";"Larva";609;1
"Unit";"Zergling";"Larva";610;1
"Unit";"Baneling";"Zergling";611;0
"Unit";"Baneling";"Zergling";611;0
"Unit";"Baneling";"Zergling";611;0
"Unit";"Baneling";"Zergling";611;0
"Unit";"Baneling";"Zergling";611;0
"Unit";"Baneling";"Zergling";611;0
"Unit";"Baneling";"Zergling";611;0
"Unit";"Baneling";"Zergling";611;0
"Unit";"Baneling";"Zergling";611;0
"Unit";"Baneling";"Zergling";611;0
"Unit";"Baneling";"Zergling";611;0
"Unit";"Baneling";"Zergling";611;0
"Unit";"Baneling";"Zergling";611;0
"Unit";"Baneling";"Zergling";611;0
"Unit";"Hydralisk";"Larva";611;2
"Unit";"Hydralisk";"Larva";613;2
"Unit";"Hydralisk";"Larva";615;2
"Unit";"Hydralisk";"Larva";617;2
"Unit";"Hydralisk";"Larva";619;2
"Unit";"Hydralisk";"Larva";621;2
"Unit";"Hydralisk";"Larva";623;2
"Unit";"Hydralisk";"Larva";625;2
"Unit";"Hydralisk";"Larva";627;2
"Unit";"Hydralisk";"Larva";629;2
"Upgrade";"SprayZerg";NA;631;0
"Upgrade";"SprayZerg";NA;631;0
"Upgrade";"zerglingmovementspeed";NA;631;0
"Upgrade";"SprayZerg";NA;631;0
"Upgrade";"overlordspeed";NA;631;0
"Upgrade";"SprayZerg";NA;631;0
"Upgrade";"SprayZerg";NA;631;0
"Upgrade";"SprayZerg";NA;631;0
"Upgrade";"SprayZerg";NA;631;0
"Upgrade";"ZergMissileWeaponsLevel1";NA;631;0
"Upgrade";"SprayZerg";NA;631;0
"Upgrade";"EvolveMuscularAugments";NA;631;0
"Upgrade";"SprayZerg";NA;631;0
"Upgrade";"ZergFlyerWeaponsLevel1";NA;631;0
"Upgrade";"ZergMeleeWeaponsLevel1";NA;631;0
"Upgrade";"CentrificalHooks";NA;631;0
"Upgrade";"SprayZerg";NA;631;0
"Upgrade";"ZergGroundArmorsLevel1";NA;631;0
"Upgrade";"ZergMeleeWeaponsLevel2";NA;631;0
"Upgrade";"ZergMissileWeaponsLevel2";NA;631;0
"Upgrade";"SprayZerg";NA;631;0
"Upgrade";"SprayZerg";NA;631;0
"Upgrade";"SprayZerg";NA;631;0
"Upgrade";"SprayZerg";NA;631;0
"Upgrade";"SprayZerg";NA;631;0
"Upgrade";"SprayZerg";NA;631;0
"Upgrade";"ZergGroundArmorsLevel2";NA;631;0
"Upgrade";"ZergMissileWeaponsLevel3";NA;631;0
"Upgrade";"ZergMeleeWeaponsLevel3";NA;631;0
