"type";"unit_name";"on_building";"total_supply_lag";"supply"
"Unit";"Overlord";"Larva";13;0
"Building";"SpawningPool";NA;17;0
"Building";"Hatchery";NA;18;0
"Building";"Extractor";NA;20;0
"Unit";"Queen";"Hatchery";21;2
"Unit";"Zergling";"Larva";23;1
"Unit";"Zergling";"Larva";24;1
"Unit";"Overlord";"Larva";25;0
"Unit";"Queen";"Hatchery";27;2
"Unit";"Queen";"Hatchery";30;2
"Unit";"Overlord";"Larva";40;0
"Building";"CreepTumorQueen";NA;40;0
"Unit";"Zergling";"Larva";41;1
"Unit";"Zergling";"Larva";42;1
"Unit";"Zergling";"Larva";43;1
"Unit";"Zergling";"Larva";44;1
"Unit";"Zergling";"Larva";45;1
"Unit";"Zergling";"Larva";46;1
"Unit";"Overlord";"Larva";47;0
"Building";"CreepTumor";NA;50;0
"Building";"CreepTumorQueen";NA;52;0
"Building";"Hatchery";NA;55;0
"Unit";"Queen";"Hatchery";57;2
"Unit";"Queen";"Hatchery";59;2
"Building";"CreepTumor";NA;61;0
"Unit";"Overlord";"Larva";61;0
"Unit";"Zergling";"Larva";61;1
"Unit";"Zergling";"Larva";62;1
"Building";"CreepTumor";NA;63;0
"Unit";"Overlord";"Larva";63;0
"Building";"CreepTumor";NA;69;0
"Unit";"Queen";"Hatchery";70;2
"Building";"CreepTumor";NA;72;0
"Building";"CreepTumorQueen";NA;73;0
"Building";"EvolutionChamber";NA;74;0
"Building";"EvolutionChamber";NA;74;0
"Building";"RoachWarren";NA;74;0
"Building";"Extractor";NA;74;0
"Unit";"Overlord";"Larva";80;0
"Building";"CreepTumor";NA;80;0
"Unit";"Queen";"Hatchery";80;2
"Unit";"Overlord";"Larva";83;0
"Unit";"Overlord";"Larva";83;0
"Building";"CreepTumorQueen";NA;83;0
"Unit";"Queen";"Hatchery";83;2
"Building";"CreepTumor";NA;85;0
"Unit";"Zergling";"Larva";85;1
"Unit";"Zergling";"Larva";86;1
"Unit";"Zergling";"Larva";87;1
"Unit";"Zergling";"Larva";88;1
"Unit";"Zergling";"Larva";89;1
"Unit";"Zergling";"Larva";90;1
"Unit";"Zergling";"Larva";91;1
"Unit";"Zergling";"Larva";92;1
"Unit";"Zergling";"Larva";93;1
"Unit";"Zergling";"Larva";94;1
"Unit";"Roach";"Larva";95;2
"Unit";"Roach";"Larva";97;2
"Unit";"Roach";"Larva";99;2
"Unit";"Zergling";"Larva";101;1
"Unit";"Zergling";"Larva";102;1
"Unit";"Zergling";"Larva";103;1
"Unit";"Zergling";"Larva";104;1
"Unit";"Zergling";"Larva";105;1
"Unit";"Zergling";"Larva";106;1
"Unit";"Zergling";"Larva";107;1
"Unit";"Zergling";"Larva";108;1
"Unit";"Roach";"Larva";109;2
"Unit";"Queen";"Hatchery";117;2
"Unit";"Queen";"Hatchery";119;2
"Unit";"Roach";"Larva";121;2
"Unit";"Roach";"Larva";123;2
"Unit";"Roach";"Larva";125;2
"Unit";"Roach";"Larva";127;2
"Unit";"Roach";"Larva";129;2
"Unit";"Roach";"Larva";131;2
"Building";"CreepTumor";NA;133;0
"Building";"Hatchery";NA;133;0
"Building";"CreepTumor";NA;133;0
"Building";"CreepTumor";NA;133;0
"Unit";"Roach";"Larva";133;2
"Unit";"Roach";"Larva";135;2
"Unit";"Roach";"Larva";137;2
"Unit";"Queen";"Hatchery";142;2
"Building";"Extractor";NA;145;0
"Building";"CreepTumor";NA;146;0
"Building";"Extractor";NA;148;0
"Building";"CreepTumor";NA;150;0
"Unit";"Overlord";"Larva";158;0
"Unit";"Overlord";"Larva";158;0
"Building";"CreepTumor";NA;158;0
"Building";"InfestationPit";NA;158;0
"Building";"Extractor";NA;158;0
"Building";"Extractor";NA;158;0
"Unit";"Overlord";"Larva";158;0
"Unit";"Overlord";"Larva";158;0
"Unit";"Overlord";"Larva";158;0
"Unit";"Roach";"Larva";158;2
"Unit";"Roach";"Larva";160;2
"Unit";"Roach";"Larva";162;2
"Unit";"Roach";"Larva";164;2
"Unit";"Roach";"Larva";166;2
"Unit";"Roach";"Larva";168;2
"Unit";"Roach";"Larva";170;2
"Unit";"Roach";"Larva";172;2
"Unit";"Roach";"Larva";174;2
"Unit";"Roach";"Larva";176;2
"Building";"SporeCrawler";NA;178;0
"Unit";"Roach";"Larva";178;2
"Unit";"Roach";"Larva";180;2
"Unit";"Queen";"Hatchery";182;2
"Unit";"Queen";"Hatchery";184;2
"Unit";"Queen";"Hatchery";186;2
"Building";"CreepTumor";NA;194;0
"Unit";"Overlord";"Larva";207;0
"Unit";"Overlord";"Larva";207;0
"Unit";"Overlord";"Larva";207;0
"Upgrade";"GlialReconstitution";"RoachWarren";207;0
"Unit";"Infestor";"Larva";207;2
"Unit";"Infestor";"Larva";209;2
"Unit";"Infestor";"Larva";211;2
"Building";"CreepTumorQueen";NA;213;0
"Building";"CreepTumor";NA;213;0
"Unit";"Infestor";"Larva";213;2
"Unit";"Roach";"Larva";215;2
"Unit";"Roach";"Larva";217;2
"Unit";"Roach";"Larva";219;2
"Unit";"Roach";"Larva";221;2
"Unit";"Roach";"Larva";223;2
"Building";"CreepTumorQueen";NA;225;0
"Unit";"Roach";"Larva";225;2
"Unit";"Roach";"Larva";227;2
"Unit";"Roach";"Larva";229;2
"Unit";"Roach";"Larva";231;2
"Unit";"Roach";"Larva";233;2
"Unit";"Roach";"Larva";235;2
"Unit";"Roach";"Larva";237;2
"Unit";"Roach";"Larva";239;2
"Unit";"Overlord";"Larva";241;0
"Unit";"Overlord";"Larva";241;0
"Building";"CreepTumorQueen";NA;241;0
"Unit";"Overlord";"Larva";241;0
"Building";"CreepTumorQueen";NA;241;0
"Unit";"Overlord";"Larva";241;0
"Building";"CreepTumor";NA;241;0
"Building";"Hatchery";NA;241;0
"Unit";"Roach";"Larva";241;2
"Unit";"Roach";"Larva";243;2
"Unit";"Roach";"Larva";245;2
"Unit";"Roach";"Larva";247;2
"Unit";"Roach";"Larva";249;2
"Unit";"Roach";"Larva";251;2
"Unit";"Roach";"Larva";253;2
"Unit";"Roach";"Larva";255;2
"Building";"CreepTumorQueen";NA;257;0
"Building";"CreepTumorQueen";NA;257;0
"Building";"CreepTumorQueen";NA;257;0
"Building";"CreepTumorQueen";NA;257;0
"Unit";"Roach";"Larva";257;2
"Unit";"Roach";"Larva";259;2
"Unit";"Roach";"Larva";261;2
"Unit";"Roach";"Larva";263;2
"Unit";"Roach";"Larva";265;2
"Unit";"Roach";"Larva";267;2
"Upgrade";"Burrow";"Hatchery";269;0
"Unit";"Roach";"Larva";269;2
"Unit";"Roach";"Larva";271;2
"Unit";"Roach";"Larva";273;2
"Unit";"Roach";"Larva";275;2
"Unit";"Roach";"Larva";277;2
"Unit";"Roach";"Larva";279;2
"Unit";"Roach";"Larva";281;2
"Building";"CreepTumor";NA;289;0
"Building";"CreepTumor";NA;289;0
"Building";"CreepTumor";NA;289;0
"Building";"CreepTumor";NA;289;0
"Building";"CreepTumor";NA;289;0
"Unit";"Roach";"Larva";289;2
"Unit";"Roach";"Larva";291;2
"Unit";"Roach";"Larva";293;2
"Unit";"Roach";"Larva";295;2
"Unit";"Roach";"Larva";297;2
"Unit";"Roach";"Larva";299;2
"Unit";"Roach";"Larva";301;2
"Building";"CreepTumor";NA;303;0
"Unit";"Roach";"Larva";303;2
"Unit";"Roach";"Larva";305;2
"Unit";"Roach";"Larva";307;2
"Unit";"Roach";"Larva";309;2
"Building";"CreepTumor";NA;311;0
"Unit";"Roach";"Larva";311;2
"Unit";"Roach";"Larva";313;2
"Unit";"Roach";"Larva";315;2
"Unit";"Roach";"Larva";317;2
"Unit";"Roach";"Larva";319;2
"Unit";"Roach";"Larva";321;2
"Unit";"Roach";"Larva";323;2
"Unit";"Roach";"Larva";325;2
"Unit";"Roach";"Larva";327;2
"Unit";"Roach";"Larva";329;2
"Unit";"Roach";"Larva";331;2
"Unit";"Roach";"Larva";333;2
"Unit";"Roach";"Larva";335;2
"Unit";"Roach";"Larva";337;2
"Unit";"Roach";"Larva";339;2
"Unit";"Roach";"Larva";341;2
"Unit";"Roach";"Larva";343;2
"Unit";"Roach";"Larva";345;2
"Unit";"Roach";"Larva";347;2
"Unit";"Roach";"Larva";349;2
"Unit";"Roach";"Larva";351;2
"Unit";"Roach";"Larva";353;2
"Unit";"Roach";"Larva";355;2
"Unit";"Roach";"Larva";357;2
"Unit";"Roach";"Larva";359;2
"Unit";"Roach";"Larva";361;2
"Unit";"Roach";"Larva";363;2
"Unit";"Roach";"Larva";365;2
"Unit";"Roach";"Larva";367;2
"Unit";"Roach";"Larva";369;2
"Unit";"Roach";"Larva";371;2
"Unit";"Roach";"Larva";373;2
"Unit";"Infestor";"Larva";375;2
"Unit";"Infestor";"Larva";377;2
"Building";"CreepTumor";NA;381;0
"Building";"CreepTumor";NA;381;0
"Building";"CreepTumor";NA;381;0
"Building";"CreepTumor";NA;381;0
"Building";"CreepTumor";NA;381;0
"Building";"CreepTumor";NA;381;0
"Building";"CreepTumor";NA;383;0
"Building";"Extractor";NA;384;0
"Building";"Extractor";NA;385;0
"Building";"CreepTumor";NA;388;0
"Unit";"Queen";"Hatchery";388;2
"Unit";"Queen";"Hatchery";390;2
"Building";"Hatchery";NA;392;0
"Unit";"Roach";"Larva";392;2
"Unit";"Roach";"Larva";394;2
"Unit";"Roach";"Larva";396;2
"Unit";"Roach";"Larva";398;2
"Unit";"Overlord";"Larva";400;0
"Unit";"Overlord";"Larva";400;0
"Building";"CreepTumor";NA;400;0
"Building";"CreepTumorQueen";NA;405;0
"Building";"Spire";NA;405;0
"Unit";"Overlord";"Larva";405;0
"Building";"CreepTumorQueen";NA;405;0
"Building";"CreepTumor";NA;405;0
"Unit";"Roach";"Larva";405;2
"Unit";"Roach";"Larva";407;2
"Unit";"Roach";"Larva";409;2
"Unit";"Roach";"Larva";411;2
"Unit";"Roach";"Larva";413;2
"Unit";"Overlord";"Larva";415;0
"Unit";"Overlord";"Larva";415;0
"Unit";"Roach";"Larva";415;2
"Unit";"Roach";"Larva";417;2
"Unit";"Roach";"Larva";419;2
"Unit";"Roach";"Larva";421;2
"Building";"CreepTumor";NA;423;0
"Building";"CreepTumorQueen";NA;423;0
"Unit";"Roach";"Larva";423;2
"Unit";"Roach";"Larva";425;2
"Unit";"Roach";"Larva";427;2
"Building";"SporeCrawler";NA;429;0
"Building";"SpawningPool";NA;429;0
"Unit";"Roach";"Larva";429;2
"Unit";"Roach";"Larva";431;2
"Unit";"Roach";"Larva";433;2
"Unit";"Roach";"Larva";435;2
"Unit";"Roach";"Larva";437;2
"Unit";"Roach";"Larva";439;2
"Unit";"Roach";"Larva";441;2
"Unit";"Roach";"Larva";443;2
"Unit";"Roach";"Larva";445;2
"Unit";"Roach";"Larva";447;2
"Unit";"Roach";"Larva";449;2
"Unit";"Roach";"Larva";451;2
"Building";"CreepTumor";NA;453;0
"Unit";"Roach";"Larva";453;2
"Unit";"Roach";"Larva";455;2
"Unit";"Roach";"Larva";457;2
"Unit";"Roach";"Larva";459;2
"Unit";"Roach";"Larva";461;2
"Unit";"Roach";"Larva";463;2
"Unit";"Roach";"Larva";465;2
"Unit";"Roach";"Larva";467;2
"Unit";"Roach";"Larva";469;2
"Unit";"Roach";"Larva";471;2
"Unit";"Roach";"Larva";473;2
"Unit";"Roach";"Larva";475;2
"Unit";"Roach";"Larva";477;2
"Unit";"Roach";"Larva";479;2
"Unit";"Roach";"Larva";481;2
"Unit";"Roach";"Larva";483;2
"Unit";"Roach";"Larva";485;2
"Unit";"Roach";"Larva";487;2
"Unit";"Roach";"Larva";489;2
"Unit";"Roach";"Larva";491;2
"Unit";"Roach";"Larva";493;2
"Unit";"Roach";"Larva";495;2
"Unit";"Roach";"Larva";497;2
"Unit";"Roach";"Larva";499;2
"Unit";"Roach";"Larva";501;2
"Unit";"Roach";"Larva";503;2
"Unit";"Roach";"Larva";505;2
"Unit";"Roach";"Larva";507;2
"Unit";"Roach";"Larva";509;2
"Unit";"Roach";"Larva";511;2
"Unit";"Roach";"Larva";513;2
"Unit";"Roach";"Larva";515;2
"Unit";"Roach";"Larva";517;2
"Unit";"Roach";"Larva";519;2
"Unit";"Roach";"Larva";521;2
"Unit";"Roach";"Larva";523;2
"Unit";"Roach";"Larva";525;2
"Unit";"Infestor";"Larva";527;2
"Unit";"Infestor";"Larva";529;2
"Building";"Hatchery";NA;531;0
"Building";"CreepTumor";NA;531;0
"Building";"CreepTumor";NA;531;0
"Building";"CreepTumorQueen";NA;531;0
"Building";"CreepTumorQueen";NA;531;0
"Building";"CreepTumorQueen";NA;531;0
"Building";"CreepTumorQueen";NA;531;0
"Building";"Hatchery";NA;531;0
"Unit";"Infestor";"Larva";531;2
"Building";"CreepTumor";NA;533;0
"Building";"CreepTumorQueen";NA;533;0
"Building";"CreepTumorQueen";NA;533;0
"Building";"CreepTumor";NA;533;0
"Building";"CreepTumor";NA;533;0
"Building";"CreepTumorQueen";NA;533;0
"Building";"CreepTumor";NA;533;0
"Unit";"Infestor";"Larva";533;2
"Building";"CreepTumor";NA;535;0
"Building";"CreepTumor";NA;535;0
"Building";"CreepTumor";NA;535;0
"Unit";"Roach";"Larva";535;2
"Unit";"Roach";"Larva";537;2
"Unit";"Roach";"Larva";539;2
"Building";"CreepTumorQueen";NA;541;0
"Building";"CreepTumorQueen";NA;541;0
"Building";"CreepTumorQueen";NA;541;0
"Unit";"Roach";"Larva";541;2
"Unit";"Roach";"Larva";543;2
"Unit";"Roach";"Larva";545;2
"Unit";"Roach";"Larva";547;2
"Unit";"Roach";"Larva";549;2
"Building";"CreepTumorQueen";NA;551;0
"Building";"CreepTumor";NA;551;0
"Building";"CreepTumorQueen";NA;551;0
"Unit";"Roach";"Larva";551;2
"Unit";"Roach";"Larva";553;2
"Unit";"Roach";"Larva";555;2
"Building";"CreepTumor";NA;557;0
"Building";"CreepTumor";NA;557;0
"Unit";"Roach";"Larva";557;2
"Unit";"Roach";"Larva";559;2
"Unit";"Roach";"Larva";561;2
"Unit";"Roach";"Larva";563;2
"Unit";"Roach";"Larva";565;2
"Unit";"Roach";"Larva";567;2
"Building";"CreepTumor";NA;569;0
"Unit";"Corruptor";"Larva";569;2
"Unit";"Corruptor";"Larva";571;2
"Unit";"Corruptor";"Larva";573;2
"Building";"Extractor";NA;575;0
"Unit";"Corruptor";"Larva";575;2
"Building";"CreepTumor";NA;577;0
"Building";"CreepTumor";NA;577;0
"Building";"CreepTumor";NA;577;0
"Unit";"Queen";"Hatchery";577;2
"Unit";"Queen";"Hatchery";579;2
"Building";"CreepTumor";NA;581;0
"Building";"CreepTumor";NA;581;0
"Building";"CreepTumor";NA;581;0
"Unit";"Queen";"Hatchery";581;2
"Building";"Hatchery";NA;583;0
"Building";"Extractor";NA;586;0
"Building";"CreepTumor";NA;586;0
"Unit";"Corruptor";"Larva";586;2
"Unit";"Roach";"Larva";588;2
"Unit";"Roach";"Larva";590;2
"Unit";"Roach";"Larva";592;2
"Unit";"Roach";"Larva";594;2
"Unit";"Roach";"Larva";596;2
"Unit";"Roach";"Larva";598;2
"Unit";"Roach";"Larva";600;2
"Unit";"Roach";"Larva";602;2
"Unit";"Roach";"Larva";604;2
"Unit";"Roach";"Larva";606;2
"Unit";"Roach";"Larva";608;2
"Building";"CreepTumor";NA;610;0
"Building";"SporeCrawler";NA;610;0
"Unit";"Roach";"Larva";610;2
"Unit";"Roach";"Larva";612;2
"Unit";"Roach";"Larva";614;2
"Unit";"Roach";"Larva";616;2
"Unit";"Roach";"Larva";618;2
"Unit";"Roach";"Larva";620;2
"Unit";"Roach";"Larva";622;2
"Unit";"Roach";"Larva";624;2
"Unit";"Roach";"Larva";626;2
"Unit";"Queen";"Hatchery";628;2
"Unit";"Queen";"Hatchery";630;2
"Unit";"Queen";"Hatchery";632;2
"Unit";"Queen";"Hatchery";634;2
"Unit";"Roach";"Larva";636;2
"Unit";"Roach";"Larva";638;2
"Unit";"Roach";"Larva";640;2
"Unit";"Roach";"Larva";642;2
"Unit";"Roach";"Larva";644;2
"Unit";"Roach";"Larva";646;2
"Unit";"Roach";"Larva";648;2
"Building";"Extractor";NA;650;0
"Unit";"Queen";"Hatchery";650;2
"Unit";"Queen";"Hatchery";652;2
"Unit";"Queen";"Hatchery";654;2
"Unit";"Queen";"Hatchery";656;2
"Building";"CreepTumor";NA;658;0
"Building";"CreepTumor";NA;658;0
"Building";"Hatchery";NA;658;0
"Unit";"Roach";"Larva";658;2
"Building";"Hatchery";NA;660;0
"Building";"SporeCrawler";NA;660;0
"Building";"SporeCrawler";NA;660;0
"Building";"CreepTumor";NA;660;0
"Building";"CreepTumor";NA;660;0
"Building";"CreepTumor";NA;660;0
"Building";"SporeCrawler";NA;660;0
"Building";"SporeCrawler";NA;660;0
"Unit";"Roach";"Larva";660;2
"Unit";"Roach";"Larva";662;2
"Building";"SporeCrawler";NA;664;0
"Building";"CreepTumorQueen";NA;664;0
"Building";"Extractor";NA;665;0
"Building";"CreepTumorQueen";NA;665;0
"Building";"SporeCrawler";NA;668;0
"Building";"SporeCrawler";NA;668;0
"Building";"Extractor";NA;668;0
"Upgrade";"SprayZerg";NA;668;0
"Upgrade";"SprayZerg";NA;668;0
"Upgrade";"zerglingmovementspeed";NA;668;0
"Upgrade";"SprayZerg";NA;668;0
"Upgrade";"SprayZerg";NA;668;0
"Upgrade";"SprayZerg";NA;668;0
"Upgrade";"SprayZerg";NA;668;0
"Upgrade";"ZergGroundArmorsLevel1";NA;668;0
"Upgrade";"SprayZerg";NA;668;0
"Upgrade";"ZergMissileWeaponsLevel1";NA;668;0
"Upgrade";"SprayZerg";NA;668;0
"Upgrade";"ZergGroundArmorsLevel2";NA;668;0
"Upgrade";"SprayZerg";NA;668;0
"Upgrade";"SprayZerg";NA;668;0
"Upgrade";"ZergMissileWeaponsLevel2";NA;668;0
"Upgrade";"SprayZerg";NA;668;0
"Upgrade";"SprayZerg";NA;668;0
"Upgrade";"ZergGroundArmorsLevel3";NA;668;0
"Upgrade";"ZergMissileWeaponsLevel3";NA;668;0
"Upgrade";"SprayZerg";NA;668;0
"Upgrade";"SprayZerg";NA;668;0
"Upgrade";"SprayZerg";NA;668;0
"Upgrade";"SprayZerg";NA;668;0
"Upgrade";"SprayZerg";NA;668;0
"Upgrade";"SprayZerg";NA;668;0
"Upgrade";"SprayZerg";NA;668;0
"Upgrade";"SprayZerg";NA;668;0
"Upgrade";"SprayZerg";NA;668;0
"Upgrade";"SprayZerg";NA;668;0
