"type";"unit_name";"on_building";"total_supply_lag";"supply"
"Unit";"Overlord";"Larva";13;0
"Building";"Hatchery";NA;17;0
"Building";"Extractor";NA;19;0
"Building";"SpawningPool";NA;19;0
"Unit";"Overlord";"Larva";22;0
"Unit";"Queen";"Hatchery";23;2
"Unit";"Zergling";"Larva";25;1
"Unit";"Zergling";"Larva";26;1
"Unit";"Queen";"Hatchery";27;2
"Unit";"Zergling";"Larva";29;1
"Unit";"Zergling";"Larva";30;1
"Building";"Extractor";NA;37;0
"Unit";"Queen";"Hatchery";37;2
"Unit";"Queen";"Hatchery";39;2
"Unit";"Overlord";"Larva";41;0
"Unit";"Overlord";"Larva";42;0
"Building";"CreepTumorQueen";NA;51;0
"Building";"CreepTumorQueen";NA;51;0
"Building";"Hatchery";NA;51;0
"Unit";"Overlord";"Larva";53;0
"Unit";"Zergling";"Larva";53;1
"Unit";"Zergling";"Larva";54;1
"Building";"CreepTumor";NA;56;0
"Building";"CreepTumorQueen";NA;56;0
"Unit";"Queen";"Hatchery";57;2
"Building";"EvolutionChamber";NA;67;0
"Unit";"Queen";"Hatchery";67;2
"Building";"CreepTumor";NA;69;0
"Building";"CreepTumor";NA;69;0
"Building";"CreepTumor";NA;69;0
"Unit";"Overlord";"Larva";69;0
"Unit";"Overlord";"Larva";69;0
"Building";"SpineCrawler";NA;70;0
"Building";"CreepTumorQueen";NA;71;0
"Building";"CreepTumorQueen";NA;71;0
"Building";"CreepTumorQueen";NA;71;0
"Unit";"Overlord";"Larva";73;0
"Unit";"Overlord";"Larva";73;0
"Unit";"Zergling";"Larva";76;1
"Unit";"Zergling";"Larva";77;1
"Unit";"Zergling";"Larva";78;1
"Unit";"Zergling";"Larva";79;1
"Building";"SporeCrawler";NA;80;0
"Unit";"Zergling";"Larva";80;1
"Unit";"Zergling";"Larva";81;1
"Building";"CreepTumor";NA;82;0
"Unit";"Zergling";"Larva";82;1
"Unit";"Zergling";"Larva";83;1
"Unit";"Zergling";"Larva";84;1
"Unit";"Zergling";"Larva";85;1
"Unit";"Zergling";"Larva";86;1
"Unit";"Zergling";"Larva";87;1
"Unit";"Zergling";"Larva";88;1
"Unit";"Zergling";"Larva";89;1
"Unit";"Zergling";"Larva";90;1
"Unit";"Zergling";"Larva";91;1
"Unit";"Zergling";"Larva";92;1
"Unit";"Zergling";"Larva";93;1
"Unit";"Zergling";"Larva";94;1
"Unit";"Zergling";"Larva";95;1
"Unit";"Zergling";"Larva";96;1
"Unit";"Zergling";"Larva";97;1
"Unit";"Zergling";"Larva";98;1
"Unit";"Zergling";"Larva";99;1
"Unit";"Queen";"Hatchery";100;2
"Unit";"Zergling";"Larva";102;1
"Unit";"Zergling";"Larva";103;1
"Unit";"Queen";"Hatchery";104;2
"Unit";"Zergling";"Larva";106;1
"Unit";"Zergling";"Larva";107;1
"Unit";"Zergling";"Larva";108;1
"Unit";"Zergling";"Larva";109;1
"Building";"CreepTumor";NA;110;0
"Building";"CreepTumor";NA;110;0
"Building";"CreepTumor";NA;110;0
"Building";"CreepTumor";NA;110;0
"Unit";"Overlord";"Larva";110;0
"Building";"EvolutionChamber";NA;110;0
"Unit";"Overlord";"Larva";110;0
"Building";"CreepTumor";NA;124;0
"Building";"CreepTumor";NA;124;0
"Building";"CreepTumor";NA;124;0
"Building";"SporeCrawler";NA;124;0
"Building";"CreepTumorQueen";NA;124;0
"Building";"Extractor";NA;127;0
"Building";"CreepTumor";NA;127;0
"Building";"Extractor";NA;127;0
"Building";"Hatchery";NA;127;0
"Building";"Extractor";NA;127;0
"Building";"CreepTumorQueen";NA;127;0
"Building";"CreepTumorQueen";NA;127;0
"Building";"CreepTumorQueen";NA;127;0
"Building";"Extractor";NA;127;0
"Building";"RoachWarren";NA;130;0
"Building";"CreepTumorQueen";NA;131;0
"Building";"CreepTumorQueen";NA;131;0
"Building";"CreepTumor";NA;131;0
"Building";"CreepTumor";NA;134;0
"Building";"CreepTumor";NA;136;0
"Building";"CreepTumor";NA;136;0
"Building";"CreepTumorQueen";NA;137;0
"Unit";"Overlord";"Larva";137;0
"Unit";"Zergling";"Larva";139;1
"Unit";"Zergling";"Larva";140;1
"Unit";"Zergling";"Larva";141;1
"Unit";"Zergling";"Larva";142;1
"Unit";"Zergling";"Larva";143;1
"Unit";"Zergling";"Larva";144;1
"Unit";"Zergling";"Larva";145;1
"Unit";"Zergling";"Larva";146;1
"Building";"Spire";NA;147;0
"Building";"HydraliskDen";NA;147;0
"Unit";"Zergling";"Larva";147;1
"Unit";"Zergling";"Larva";148;1
"Unit";"Zergling";"Larva";149;1
"Unit";"Zergling";"Larva";150;1
"Unit";"Zergling";"Larva";151;1
"Unit";"Zergling";"Larva";152;1
"Unit";"Zergling";"Larva";153;1
"Unit";"Zergling";"Larva";154;1
"Unit";"Zergling";"Larva";155;1
"Unit";"Zergling";"Larva";156;1
"Unit";"Zergling";"Larva";157;1
"Unit";"Zergling";"Larva";158;1
"Unit";"Zergling";"Larva";159;1
"Unit";"Zergling";"Larva";160;1
"Unit";"Zergling";"Larva";161;1
"Unit";"Zergling";"Larva";162;1
"Unit";"Zergling";"Larva";163;1
"Unit";"Zergling";"Larva";164;1
"Unit";"Zergling";"Larva";165;1
"Unit";"Zergling";"Larva";166;1
"Building";"CreepTumor";NA;167;0
"Building";"CreepTumor";NA;167;0
"Building";"CreepTumor";NA;167;0
"Building";"CreepTumor";NA;167;0
"Building";"CreepTumor";NA;167;0
"Building";"CreepTumor";NA;167;0
"Building";"CreepTumor";NA;168;0
"Building";"CreepTumor";NA;168;0
"Building";"CreepTumor";NA;170;0
"Building";"CreepTumor";NA;170;0
"Unit";"Overlord";"Larva";170;0
"Unit";"Overlord";"Larva";170;0
"Building";"CreepTumorQueen";NA;171;0
"Building";"InfestationPit";NA;171;0
"Unit";"Overlord";"Larva";171;0
"Building";"CreepTumor";NA;171;0
"Building";"CreepTumor";NA;171;0
"Building";"CreepTumorQueen";NA;171;0
"Building";"CreepTumor";NA;171;0
"Building";"CreepTumor";NA;171;0
"Building";"CreepTumor";NA;171;0
"Upgrade";"GlialReconstitution";"RoachWarren";171;0
"Unit";"Overlord";"Larva";171;0
"Building";"Extractor";NA;171;0
"Unit";"Hydralisk";"Larva";171;2
"Unit";"Hydralisk";"Larva";173;2
"Unit";"Hydralisk";"Larva";175;2
"Unit";"Hydralisk";"Larva";177;2
"Unit";"Hydralisk";"Larva";179;2
"Unit";"Overlord";"Larva";181;0
"Unit";"Mutalisk";"Larva";192;2
"Unit";"Mutalisk";"Larva";194;2
"Unit";"Mutalisk";"Larva";196;2
"Unit";"Mutalisk";"Larva";198;2
"Unit";"Mutalisk";"Larva";200;2
"Unit";"Mutalisk";"Larva";202;2
"Unit";"Hydralisk";"Larva";209;2
"Unit";"Hydralisk";"Larva";211;2
"Building";"CreepTumor";NA;213;0
"Building";"CreepTumor";NA;213;0
"Building";"CreepTumor";NA;213;0
"Building";"CreepTumor";NA;213;0
"Building";"CreepTumor";NA;213;0
"Building";"CreepTumor";NA;213;0
"Unit";"Hydralisk";"Larva";213;2
"Building";"CreepTumor";NA;215;0
"Building";"CreepTumor";NA;215;0
"Building";"CreepTumor";NA;215;0
"Unit";"Hydralisk";"Larva";219;2
"Unit";"Hydralisk";"Larva";221;2
"Unit";"Hydralisk";"Larva";223;2
"Unit";"Hydralisk";"Larva";225;2
"Unit";"Hydralisk";"Larva";227;2
"Unit";"Hydralisk";"Larva";229;2
"Building";"CreepTumor";NA;231;0
"Unit";"Hydralisk";"Larva";231;2
"Unit";"Hydralisk";"Larva";233;2
"Unit";"Zergling";"Larva";235;1
"Unit";"Zergling";"Larva";236;1
"Unit";"Hydralisk";"Larva";237;2
"Unit";"Hydralisk";"Larva";239;2
"Unit";"Hydralisk";"Larva";241;2
"Unit";"Hydralisk";"Larva";243;2
"Unit";"Zergling";"Larva";245;1
"Unit";"Zergling";"Larva";246;1
"Unit";"Zergling";"Larva";247;1
"Unit";"Zergling";"Larva";248;1
"Unit";"Zergling";"Larva";249;1
"Unit";"Zergling";"Larva";250;1
"Unit";"Zergling";"Larva";251;1
"Unit";"Zergling";"Larva";252;1
"Unit";"Zergling";"Larva";253;1
"Unit";"Zergling";"Larva";254;1
"Unit";"Hydralisk";"Larva";255;2
"Unit";"Overlord";"Larva";257;0
"Unit";"Overlord";"Larva";257;0
"Unit";"Overlord";"Larva";257;0
"Unit";"Overlord";"Larva";257;0
"Unit";"Overlord";"Larva";257;0
"Unit";"Overlord";"Larva";257;0
"Unit";"Hydralisk";"Larva";257;2
"Unit";"Hydralisk";"Larva";259;2
"Unit";"Hydralisk";"Larva";261;2
"Unit";"Hydralisk";"Larva";263;2
"Unit";"Roach";"Larva";265;2
"Unit";"Roach";"Larva";267;2
"Unit";"Roach";"Larva";269;2
"Unit";"Roach";"Larva";271;2
"Unit";"Roach";"Larva";273;2
"Unit";"Roach";"Larva";275;2
"Unit";"Roach";"Larva";277;2
"Unit";"Roach";"Larva";279;2
"Unit";"Roach";"Larva";281;2
"Unit";"Roach";"Larva";283;2
"Unit";"Roach";"Larva";285;2
"Unit";"Roach";"Larva";287;2
"Unit";"Roach";"Larva";289;2
"Unit";"Roach";"Larva";291;2
"Unit";"Roach";"Larva";293;2
"Unit";"Roach";"Larva";295;2
"Unit";"Roach";"Larva";297;2
"Unit";"Roach";"Larva";299;2
"Unit";"Roach";"Larva";301;2
"Unit";"Roach";"Larva";303;2
"Unit";"Viper";"Larva";305;3
"Unit";"Viper";"Larva";308;3
"Unit";"Viper";"Larva";311;3
"Unit";"Viper";"Larva";314;3
"Building";"Hatchery";NA;317;0
"Building";"CreepTumorQueen";NA;319;0
"Building";"Extractor";NA;319;0
"Building";"CreepTumorQueen";NA;319;0
"Unit";"Hydralisk";"Larva";319;2
"Unit";"Hydralisk";"Larva";321;2
"Unit";"Hydralisk";"Larva";323;2
"Building";"CreepTumorQueen";NA;325;0
"Building";"CreepTumorQueen";NA;325;0
"Building";"CreepTumorQueen";NA;325;0
"Unit";"Hydralisk";"Larva";325;2
"Unit";"Hydralisk";"Larva";327;2
"Unit";"Roach";"Larva";329;2
"Unit";"Roach";"Larva";331;2
"Unit";"Roach";"Larva";333;2
"Unit";"Roach";"Larva";335;2
"Unit";"Roach";"Larva";337;2
"Unit";"Roach";"Larva";339;2
"Unit";"Roach";"Larva";341;2
"Unit";"Roach";"Larva";343;2
"Unit";"Roach";"Larva";345;2
"Unit";"Roach";"Larva";347;2
"Unit";"Roach";"Larva";349;2
"Unit";"Roach";"Larva";351;2
"Unit";"Hydralisk";"Larva";353;2
"Unit";"Hydralisk";"Larva";355;2
"Unit";"Hydralisk";"Larva";357;2
"Unit";"Overlord";"Larva";359;0
"Unit";"Hydralisk";"Larva";359;2
"Unit";"Hydralisk";"Larva";361;2
"Unit";"Overlord";"Larva";363;0
"Unit";"Overlord";"Larva";363;0
"Unit";"Hydralisk";"Larva";363;2
"Unit";"Hydralisk";"Larva";365;2
"Unit";"Hydralisk";"Larva";367;2
"Unit";"Hydralisk";"Larva";369;2
"Unit";"Hydralisk";"Larva";371;2
"Unit";"Hydralisk";"Larva";373;2
"Unit";"Hydralisk";"Larva";375;2
"Unit";"Hydralisk";"Larva";377;2
"Building";"Extractor";NA;379;0
"Unit";"Hydralisk";"Larva";379;2
"Building";"Hatchery";NA;381;0
"Unit";"Hydralisk";"Larva";381;2
"Unit";"Hydralisk";"Larva";383;2
"Building";"CreepTumor";NA;385;0
"Unit";"Viper";"Larva";385;3
"Unit";"Viper";"Larva";388;3
"Unit";"Zergling";"Larva";391;1
"Unit";"Zergling";"Larva";392;1
"Unit";"Zergling";"Larva";393;1
"Unit";"Zergling";"Larva";394;1
"Unit";"Zergling";"Larva";395;1
"Unit";"Zergling";"Larva";396;1
"Unit";"Zergling";"Larva";397;1
"Unit";"Zergling";"Larva";398;1
"Unit";"Zergling";"Larva";399;1
"Unit";"Zergling";"Larva";400;1
"Unit";"Roach";"Larva";401;2
"Unit";"Roach";"Larva";403;2
"Unit";"Roach";"Larva";405;2
"Unit";"Roach";"Larva";407;2
"Unit";"Roach";"Larva";409;2
"Unit";"Roach";"Larva";411;2
"Unit";"Roach";"Larva";413;2
"Unit";"Roach";"Larva";415;2
"Unit";"Roach";"Larva";417;2
"Unit";"Roach";"Larva";419;2
"Unit";"Hydralisk";"Larva";421;2
"Unit";"Hydralisk";"Larva";423;2
"Unit";"Hydralisk";"Larva";425;2
"Unit";"Hydralisk";"Larva";427;2
"Unit";"Hydralisk";"Larva";429;2
"Unit";"Hydralisk";"Larva";431;2
"Unit";"Hydralisk";"Larva";433;2
"Unit";"Hydralisk";"Larva";435;2
"Unit";"Roach";"Larva";437;2
"Unit";"Roach";"Larva";439;2
"Unit";"Roach";"Larva";441;2
"Unit";"Roach";"Larva";443;2
"Unit";"Roach";"Larva";445;2
"Unit";"Roach";"Larva";447;2
"Building";"Hatchery";NA;449;0
"Unit";"Roach";"Larva";449;2
"Building";"CreepTumorQueen";NA;451;0
"Building";"CreepTumorQueen";NA;451;0
"Unit";"Roach";"Larva";451;2
"Building";"CreepTumorQueen";NA;453;0
"Unit";"Roach";"Larva";453;2
"Unit";"Roach";"Larva";455;2
"Building";"CreepTumorQueen";NA;457;0
"Unit";"Roach";"Larva";457;2
"Unit";"Roach";"Larva";459;2
"Building";"CreepTumorQueen";NA;461;0
"Unit";"Roach";"Larva";461;2
"Unit";"Roach";"Larva";463;2
"Unit";"Roach";"Larva";465;2
"Unit";"Roach";"Larva";467;2
"Unit";"Roach";"Larva";469;2
"Unit";"Roach";"Larva";471;2
"Unit";"Roach";"Larva";473;2
"Unit";"Roach";"Larva";475;2
"Unit";"Roach";"Larva";477;2
"Unit";"Roach";"Larva";479;2
"Unit";"Hydralisk";"Larva";481;2
"Unit";"Hydralisk";"Larva";483;2
"Unit";"Hydralisk";"Larva";485;2
"Unit";"Hydralisk";"Larva";487;2
"Unit";"Hydralisk";"Larva";489;2
"Building";"Extractor";NA;491;0
"Building";"CreepTumor";NA;491;0
"Building";"CreepTumor";NA;491;0
"Building";"CreepTumor";NA;491;0
"Building";"CreepTumorQueen";NA;491;0
"Unit";"Hydralisk";"Larva";491;2
"Unit";"Hydralisk";"Larva";493;2
"Unit";"Hydralisk";"Larva";495;2
"Building";"CreepTumorQueen";NA;497;0
"Building";"CreepTumorQueen";NA;497;0
"Building";"CreepTumorQueen";NA;497;0
"Building";"CreepTumorQueen";NA;497;0
"Unit";"Hydralisk";"Larva";497;2
"Unit";"Roach";"Larva";499;2
"Building";"CreepTumor";NA;501;0
"Building";"CreepTumorQueen";NA;501;0
"Building";"CreepTumorQueen";NA;501;0
"Unit";"Hydralisk";"Larva";501;2
"Unit";"Hydralisk";"Larva";503;2
"Unit";"Hydralisk";"Larva";505;2
"Unit";"Hydralisk";"Larva";507;2
"Building";"CreepTumorQueen";NA;509;0
"Building";"CreepTumorQueen";NA;509;0
"Unit";"Hydralisk";"Larva";509;2
"Unit";"Hydralisk";"Larva";511;2
"Unit";"Hydralisk";"Larva";513;2
"Unit";"Hydralisk";"Larva";515;2
"Unit";"Hydralisk";"Larva";517;2
"Unit";"Hydralisk";"Larva";519;2
"Building";"CreepTumorQueen";NA;521;0
"Building";"CreepTumorQueen";NA;521;0
"Upgrade";"SprayZerg";NA;521;0
"Upgrade";"SprayZerg";NA;521;0
"Upgrade";"zerglingmovementspeed";NA;521;0
"Upgrade";"SprayZerg";NA;521;0
"Upgrade";"SprayZerg";NA;521;0
"Upgrade";"SprayZerg";NA;521;0
"Upgrade";"ZergGroundArmorsLevel1";NA;521;0
"Upgrade";"SprayZerg";NA;521;0
"Upgrade";"ZergMeleeWeaponsLevel1";NA;521;0
"Upgrade";"ZergMissileWeaponsLevel1";NA;521;0
"Upgrade";"SprayZerg";NA;521;0
"Upgrade";"SprayZerg";NA;521;0
"Upgrade";"SprayZerg";NA;521;0
"Upgrade";"overlordspeed";NA;521;0
"Upgrade";"ZergMissileWeaponsLevel2";NA;521;0
"Upgrade";"SprayZerg";NA;521;0
"Upgrade";"SprayZerg";NA;521;0
"Upgrade";"SprayZerg";NA;521;0
