"type";"unit_name";"on_building";"total_supply_lag";"supply"
"Unit";"Overlord";"Larva";13;0
"Building";"SpawningPool";NA;17;0
"Building";"Hatchery";NA;19;0
"Building";"Extractor";NA;21;0
"Unit";"Queen";"Hatchery";22;2
"Unit";"Zergling";"Larva";24;1
"Unit";"Zergling";"Larva";25;1
"Unit";"Overlord";"Larva";26;0
"Building";"RoachWarren";NA;26;0
"Unit";"Queen";"Hatchery";26;2
"Unit";"Overlord";"Larva";29;0
"Unit";"Roach";"Larva";29;2
"Unit";"Roach";"Larva";31;2
"Building";"CreepTumorQueen";NA;33;0
"Unit";"Roach";"Larva";33;2
"Unit";"Roach";"Larva";35;2
"Unit";"Roach";"Larva";37;2
"Unit";"Roach";"Larva";39;2
"Unit";"Overlord";"Larva";43;0
"Building";"CreepTumor";NA;48;0
"Unit";"Overlord";"Larva";48;0
"Unit";"Roach";"Larva";54;2
"Unit";"Overlord";"Larva";56;0
"Building";"Extractor";NA;58;0
"Building";"CreepTumor";NA;58;0
"Unit";"Queen";"Hatchery";64;2
"Building";"Hatchery";NA;67;0
"Building";"CreepTumor";NA;69;0
"Building";"EvolutionChamber";NA;71;0
"Building";"Extractor";NA;76;0
"Unit";"Queen";"Hatchery";76;2
"Unit";"Zergling";"Larva";78;1
"Unit";"Zergling";"Larva";79;1
"Unit";"Zergling";"Larva";80;1
"Unit";"Zergling";"Larva";81;1
"Unit";"Zergling";"Larva";82;1
"Unit";"Zergling";"Larva";83;1
"Unit";"Zergling";"Larva";84;1
"Unit";"Zergling";"Larva";85;1
"Unit";"Zergling";"Larva";86;1
"Unit";"Zergling";"Larva";87;1
"Building";"CreepTumor";NA;89;0
"Building";"SporeCrawler";NA;89;0
"Building";"CreepTumorQueen";NA;93;0
"Building";"SporeCrawler";NA;93;0
"Unit";"Queen";"Hatchery";93;2
"Unit";"Overlord";"Larva";95;0
"Building";"Extractor";NA;96;0
"Unit";"Roach";"Larva";96;2
"Unit";"Roach";"Larva";98;2
"Unit";"Zergling";"Larva";100;1
"Unit";"Zergling";"Larva";101;1
"Unit";"Zergling";"Larva";102;1
"Unit";"Zergling";"Larva";103;1
"Unit";"Zergling";"Larva";104;1
"Unit";"Zergling";"Larva";105;1
"Unit";"Zergling";"Larva";106;1
"Unit";"Zergling";"Larva";107;1
"Unit";"Zergling";"Larva";108;1
"Unit";"Zergling";"Larva";109;1
"Unit";"Overlord";"Larva";110;0
"Unit";"Roach";"Larva";110;2
"Upgrade";"GlialReconstitution";"RoachWarren";112;0
"Unit";"Roach";"Larva";112;2
"Unit";"Roach";"Larva";114;2
"Unit";"Roach";"Larva";116;2
"Unit";"Overlord";"Larva";118;0
"Unit";"Overlord";"Larva";118;0
"Building";"Hatchery";NA;118;0
"Building";"CreepTumor";NA;123;0
"Building";"CreepTumor";NA;123;0
"Building";"CreepTumorQueen";NA;123;0
"Building";"EvolutionChamber";NA;128;0
"Building";"CreepTumorQueen";NA;128;0
"Building";"BanelingNest";NA;130;0
"Building";"HydraliskDen";NA;130;0
"Building";"CreepTumor";NA;132;0
"Building";"CreepTumor";NA;132;0
"Building";"CreepTumor";NA;135;0
"Unit";"Zergling";"Larva";138;1
"Unit";"Zergling";"Larva";139;1
"Unit";"Zergling";"Larva";140;1
"Unit";"Zergling";"Larva";141;1
"Unit";"Zergling";"Larva";142;1
"Unit";"Zergling";"Larva";143;1
"Building";"CreepTumor";NA;144;0
"Building";"Hatchery";NA;144;0
"Unit";"Overlord";"Larva";144;0
"Building";"CreepTumor";NA;144;0
"Building";"CreepTumor";NA;144;0
"Unit";"Overlord";"Larva";144;0
"Unit";"Overlord";"Larva";144;0
"Building";"CreepTumorQueen";NA;144;0
"Building";"CreepTumorQueen";NA;144;0
"Building";"CreepTumorQueen";NA;144;0
"Building";"Extractor";NA;144;0
"Building";"Extractor";NA;144;0
"Unit";"Queen";"Hatchery";144;2
"Unit";"Hydralisk";"Larva";146;2
"Unit";"Hydralisk";"Larva";148;2
"Unit";"Overlord";"Larva";150;0
"Unit";"Hydralisk";"Larva";150;2
"Unit";"Hydralisk";"Larva";152;2
"Building";"CreepTumor";NA;154;0
"Building";"CreepTumor";NA;154;0
"Unit";"Hydralisk";"Larva";154;2
"Unit";"Hydralisk";"Larva";156;2
"Building";"CreepTumor";NA;158;0
"Building";"CreepTumor";NA;158;0
"Building";"CreepTumor";NA;158;0
"Unit";"Hydralisk";"Larva";158;2
"Unit";"Hydralisk";"Larva";160;2
"Unit";"Hydralisk";"Larva";162;2
"Unit";"Hydralisk";"Larva";164;2
"Unit";"Hydralisk";"Larva";166;2
"Unit";"Overlord";"Larva";168;0
"Unit";"Hydralisk";"Larva";168;2
"Building";"CreepTumor";NA;172;0
"Building";"CreepTumor";NA;172;0
"Building";"CreepTumor";NA;172;0
"Building";"CreepTumor";NA;172;0
"Building";"CreepTumor";NA;175;0
"Building";"CreepTumor";NA;175;0
"Unit";"Hydralisk";"Larva";175;2
"Unit";"Hydralisk";"Larva";177;2
"Unit";"Baneling";"Zergling";179;0
"Unit";"Baneling";"Zergling";179;0
"Unit";"Baneling";"Zergling";179;0
"Unit";"Baneling";"Zergling";179;0
"Building";"CreepTumorQueen";NA;179;0
"Unit";"Hydralisk";"Larva";186;2
"Unit";"Hydralisk";"Larva";188;2
"Unit";"Hydralisk";"Larva";190;2
"Unit";"Hydralisk";"Larva";192;2
"Unit";"Hydralisk";"Larva";194;2
"Building";"SporeCrawler";NA;196;0
"Building";"InfestationPit";NA;196;0
"Unit";"Overlord";"Larva";196;0
"Unit";"Zergling";"Larva";196;1
"Unit";"Zergling";"Larva";197;1
"Unit";"Zergling";"Larva";198;1
"Unit";"Zergling";"Larva";199;1
"Building";"CreepTumor";NA;200;0
"Building";"CreepTumor";NA;200;0
"Building";"CreepTumor";NA;200;0
"Building";"CreepTumor";NA;200;0
"Building";"CreepTumor";NA;200;0
"Unit";"Baneling";"Zergling";200;0
"Unit";"Baneling";"Zergling";200;0
"Unit";"Baneling";"Zergling";200;0
"Unit";"Baneling";"Zergling";200;0
"Unit";"Baneling";"Zergling";200;0
"Unit";"Baneling";"Zergling";200;0
"Unit";"Baneling";"Zergling";200;0
"Unit";"Baneling";"Zergling";200;0
"Unit";"Baneling";"Zergling";200;0
"Unit";"Overlord";"Larva";200;0
"Building";"CreepTumorQueen";NA;200;0
"Building";"CreepTumorQueen";NA;200;0
"Unit";"Zergling";"Larva";200;1
"Unit";"Zergling";"Larva";201;1
"Unit";"Zergling";"Larva";202;1
"Unit";"Zergling";"Larva";203;1
"Unit";"Zergling";"Larva";204;1
"Unit";"Zergling";"Larva";205;1
"Unit";"Zergling";"Larva";206;1
"Unit";"Zergling";"Larva";207;1
"Unit";"Zergling";"Larva";208;1
"Unit";"Zergling";"Larva";209;1
"Unit";"Zergling";"Larva";210;1
"Unit";"Zergling";"Larva";211;1
"Unit";"Zergling";"Larva";212;1
"Unit";"Zergling";"Larva";213;1
"Unit";"Zergling";"Larva";214;1
"Unit";"Zergling";"Larva";215;1
"Unit";"Zergling";"Larva";216;1
"Unit";"Zergling";"Larva";217;1
"Unit";"Zergling";"Larva";218;1
"Unit";"Zergling";"Larva";219;1
"Building";"CreepTumorQueen";NA;220;0
"Building";"CreepTumorQueen";NA;220;0
"Unit";"Overlord";"Larva";220;0
"Unit";"Overlord";"Larva";220;0
"Building";"CreepTumor";NA;220;0
"Unit";"Zergling";"Larva";220;1
"Unit";"Zergling";"Larva";221;1
"Unit";"Zergling";"Larva";222;1
"Unit";"Zergling";"Larva";223;1
"Unit";"Zergling";"Larva";224;1
"Unit";"Zergling";"Larva";225;1
"Unit";"Zergling";"Larva";226;1
"Unit";"Zergling";"Larva";227;1
"Unit";"Zergling";"Larva";228;1
"Unit";"Zergling";"Larva";229;1
"Unit";"Zergling";"Larva";230;1
"Unit";"Zergling";"Larva";231;1
"Unit";"Zergling";"Larva";232;1
"Unit";"Zergling";"Larva";233;1
"Unit";"Zergling";"Larva";234;1
"Unit";"Zergling";"Larva";235;1
"Unit";"Zergling";"Larva";236;1
"Unit";"Zergling";"Larva";237;1
"Unit";"Zergling";"Larva";238;1
"Unit";"Zergling";"Larva";239;1
"Unit";"Zergling";"Larva";240;1
"Unit";"Zergling";"Larva";241;1
"Unit";"Zergling";"Larva";242;1
"Unit";"Zergling";"Larva";243;1
"Unit";"Zergling";"Larva";244;1
"Unit";"Zergling";"Larva";245;1
"Unit";"Zergling";"Larva";246;1
"Unit";"Zergling";"Larva";247;1
"Unit";"Zergling";"Larva";248;1
"Unit";"Zergling";"Larva";249;1
"Unit";"Baneling";"Zergling";250;0
"Unit";"Baneling";"Zergling";250;0
"Unit";"Baneling";"Zergling";250;0
"Unit";"Baneling";"Zergling";250;0
"Unit";"Baneling";"Zergling";250;0
"Unit";"Baneling";"Zergling";250;0
"Unit";"Baneling";"Zergling";250;0
"Unit";"Baneling";"Zergling";250;0
"Unit";"Baneling";"Zergling";250;0
"Unit";"Baneling";"Zergling";250;0
"Unit";"Baneling";"Zergling";250;0
"Unit";"Baneling";"Zergling";250;0
"Unit";"Baneling";"Zergling";250;0
"Building";"CreepTumor";NA;250;0
"Building";"CreepTumor";NA;250;0
"Unit";"Zergling";"Larva";250;1
"Unit";"Zergling";"Larva";251;1
"Unit";"Zergling";"Larva";252;1
"Unit";"Zergling";"Larva";253;1
"Unit";"Zergling";"Larva";254;1
"Unit";"Zergling";"Larva";255;1
"Building";"CreepTumor";NA;256;0
"Building";"CreepTumor";NA;256;0
"Unit";"Zergling";"Larva";257;1
"Unit";"Zergling";"Larva";258;1
"Unit";"Zergling";"Larva";259;1
"Unit";"Zergling";"Larva";260;1
"Unit";"Baneling";"Zergling";261;0
"Unit";"Baneling";"Zergling";261;0
"Unit";"Baneling";"Zergling";261;0
"Building";"Hatchery";NA;261;0
"Unit";"Zergling";"Larva";261;1
"Unit";"Zergling";"Larva";262;1
"Unit";"Zergling";"Larva";263;1
"Unit";"Zergling";"Larva";264;1
"Unit";"Zergling";"Larva";265;1
"Unit";"Zergling";"Larva";266;1
"Unit";"Zergling";"Larva";267;1
"Unit";"Zergling";"Larva";268;1
"Unit";"Zergling";"Larva";269;1
"Unit";"Zergling";"Larva";270;1
"Unit";"Zergling";"Larva";271;1
"Unit";"Zergling";"Larva";272;1
"Unit";"Zergling";"Larva";273;1
"Unit";"Zergling";"Larva";274;1
"Unit";"Zergling";"Larva";275;1
"Unit";"Zergling";"Larva";276;1
"Unit";"Zergling";"Larva";277;1
"Unit";"Zergling";"Larva";278;1
"Unit";"Zergling";"Larva";279;1
"Unit";"Zergling";"Larva";280;1
"Unit";"Zergling";"Larva";281;1
"Unit";"Zergling";"Larva";282;1
"Unit";"Zergling";"Larva";283;1
"Unit";"Zergling";"Larva";284;1
"Unit";"Zergling";"Larva";285;1
"Unit";"Zergling";"Larva";286;1
"Unit";"Zergling";"Larva";287;1
"Unit";"Zergling";"Larva";288;1
"Unit";"Zergling";"Larva";289;1
"Unit";"Zergling";"Larva";290;1
"Unit";"Zergling";"Larva";291;1
"Unit";"Zergling";"Larva";292;1
"Unit";"Zergling";"Larva";293;1
"Unit";"Zergling";"Larva";294;1
"Unit";"Overlord";"Larva";295;0
"Unit";"Overlord";"Larva";297;0
"Building";"CreepTumor";NA;297;0
"Building";"CreepTumor";NA;297;0
"Building";"CreepTumor";NA;297;0
"Building";"CreepTumor";NA;297;0
"Building";"CreepTumor";NA;297;0
"Building";"CreepTumor";NA;297;0
"Building";"CreepTumor";NA;297;0
"Building";"UltraliskCavern";NA;297;0
"Unit";"Hydralisk";"Larva";297;2
"Unit";"Hydralisk";"Larva";299;2
"Unit";"Roach";"Larva";301;2
"Unit";"Zergling";"Larva";303;1
"Unit";"Zergling";"Larva";304;1
"Unit";"Zergling";"Larva";305;1
"Unit";"Zergling";"Larva";306;1
"Unit";"Zergling";"Larva";307;1
"Unit";"Zergling";"Larva";308;1
"Unit";"Zergling";"Larva";309;1
"Unit";"Zergling";"Larva";310;1
"Unit";"Zergling";"Larva";311;1
"Unit";"Zergling";"Larva";312;1
"Unit";"Zergling";"Larva";313;1
"Unit";"Zergling";"Larva";314;1
"Unit";"Zergling";"Larva";315;1
"Unit";"Zergling";"Larva";316;1
"Unit";"Zergling";"Larva";317;1
"Unit";"Zergling";"Larva";318;1
"Unit";"Zergling";"Larva";319;1
"Unit";"Zergling";"Larva";320;1
"Unit";"Zergling";"Larva";321;1
"Unit";"Zergling";"Larva";322;1
"Building";"SporeCrawler";NA;323;0
"Unit";"Overlord";"Larva";326;0
"Building";"CreepTumor";NA;331;0
"Building";"CreepTumor";NA;331;0
"Building";"CreepTumor";NA;331;0
"Building";"CreepTumor";NA;331;0
"Building";"CreepTumor";NA;331;0
"Building";"CreepTumor";NA;331;0
"Building";"CreepTumor";NA;331;0
"Building";"CreepTumor";NA;331;0
"Building";"CreepTumor";NA;331;0
"Building";"CreepTumor";NA;331;0
"Unit";"Baneling";"Zergling";331;0
"Unit";"Baneling";"Zergling";331;0
"Unit";"Baneling";"Zergling";331;0
"Unit";"Baneling";"Zergling";331;0
"Unit";"Baneling";"Zergling";331;0
"Unit";"Baneling";"Zergling";331;0
"Unit";"Baneling";"Zergling";331;0
"Unit";"Baneling";"Zergling";331;0
"Unit";"Baneling";"Zergling";331;0
"Unit";"Baneling";"Zergling";331;0
"Unit";"Baneling";"Zergling";331;0
"Unit";"Baneling";"Zergling";331;0
"Unit";"Baneling";"Zergling";331;0
"Unit";"Baneling";"Zergling";331;0
"Unit";"Baneling";"Zergling";331;0
"Unit";"Baneling";"Zergling";331;0
"Unit";"Baneling";"Zergling";331;0
"Unit";"Baneling";"Zergling";331;0
"Unit";"Baneling";"Zergling";331;0
"Unit";"Baneling";"Zergling";331;0
"Unit";"Baneling";"Zergling";331;0
"Unit";"Baneling";"Zergling";331;0
"Unit";"Baneling";"Zergling";331;0
"Unit";"Baneling";"Zergling";331;0
"Unit";"Queen";"Hatchery";331;2
"Unit";"Viper";"Larva";333;3
"Unit";"Viper";"Larva";336;3
"Unit";"Zergling";"Larva";339;1
"Unit";"Zergling";"Larva";340;1
"Unit";"Zergling";"Larva";341;1
"Unit";"Zergling";"Larva";342;1
"Unit";"Zergling";"Larva";343;1
"Unit";"Zergling";"Larva";344;1
"Unit";"Zergling";"Larva";345;1
"Unit";"Zergling";"Larva";346;1
"Unit";"Zergling";"Larva";347;1
"Unit";"Zergling";"Larva";348;1
"Unit";"Zergling";"Larva";349;1
"Unit";"Zergling";"Larva";350;1
"Unit";"Zergling";"Larva";351;1
"Unit";"Zergling";"Larva";352;1
"Unit";"Zergling";"Larva";353;1
"Unit";"Zergling";"Larva";354;1
"Unit";"Zergling";"Larva";355;1
"Unit";"Zergling";"Larva";356;1
"Unit";"Zergling";"Larva";357;1
"Unit";"Zergling";"Larva";358;1
"Unit";"Zergling";"Larva";359;1
"Unit";"Zergling";"Larva";360;1
"Unit";"Zergling";"Larva";361;1
"Unit";"Zergling";"Larva";362;1
"Unit";"Zergling";"Larva";363;1
"Unit";"Zergling";"Larva";364;1
"Unit";"Zergling";"Larva";365;1
"Unit";"Zergling";"Larva";366;1
"Unit";"Zergling";"Larva";367;1
"Unit";"Zergling";"Larva";368;1
"Unit";"Zergling";"Larva";369;1
"Unit";"Zergling";"Larva";370;1
"Unit";"Zergling";"Larva";371;1
"Unit";"Zergling";"Larva";372;1
"Unit";"Zergling";"Larva";373;1
"Unit";"Zergling";"Larva";374;1
"Unit";"Zergling";"Larva";375;1
"Unit";"Zergling";"Larva";376;1
"Unit";"Zergling";"Larva";377;1
"Unit";"Zergling";"Larva";378;1
"Unit";"Zergling";"Larva";379;1
"Unit";"Zergling";"Larva";380;1
"Unit";"Zergling";"Larva";381;1
"Unit";"Zergling";"Larva";382;1
"Unit";"Zergling";"Larva";383;1
"Unit";"Zergling";"Larva";384;1
"Unit";"Zergling";"Larva";385;1
"Unit";"Zergling";"Larva";386;1
"Unit";"Zergling";"Larva";387;1
"Unit";"Zergling";"Larva";388;1
"Upgrade";"ChitinousPlating";"UltraliskCavern";389;0
"Unit";"Zergling";"Larva";389;1
"Unit";"Zergling";"Larva";390;1
"Unit";"Zergling";"Larva";391;1
"Unit";"Zergling";"Larva";392;1
"Unit";"Ultralisk";"Larva";393;6
"Unit";"Ultralisk";"Larva";399;6
"Unit";"Baneling";"Zergling";405;0
"Unit";"Baneling";"Zergling";405;0
"Unit";"Baneling";"Zergling";405;0
"Unit";"Baneling";"Zergling";405;0
"Unit";"Baneling";"Zergling";405;0
"Unit";"Zergling";"Larva";405;1
"Unit";"Zergling";"Larva";406;1
"Unit";"Zergling";"Larva";407;1
"Unit";"Zergling";"Larva";408;1
"Unit";"Zergling";"Larva";409;1
"Unit";"Zergling";"Larva";410;1
"Unit";"Zergling";"Larva";411;1
"Unit";"Zergling";"Larva";412;1
"Unit";"Zergling";"Larva";413;1
"Unit";"Zergling";"Larva";414;1
"Unit";"Zergling";"Larva";415;1
"Unit";"Zergling";"Larva";416;1
"Unit";"Zergling";"Larva";417;1
"Unit";"Zergling";"Larva";418;1
"Unit";"Zergling";"Larva";419;1
"Unit";"Zergling";"Larva";420;1
"Unit";"Zergling";"Larva";421;1
"Unit";"Zergling";"Larva";422;1
"Unit";"Zergling";"Larva";423;1
"Unit";"Zergling";"Larva";424;1
"Unit";"Zergling";"Larva";425;1
"Unit";"Zergling";"Larva";426;1
"Unit";"Zergling";"Larva";427;1
"Unit";"Zergling";"Larva";428;1
"Unit";"Baneling";"Zergling";429;0
"Unit";"Baneling";"Zergling";429;0
"Unit";"Baneling";"Zergling";429;0
"Unit";"Baneling";"Zergling";429;0
"Unit";"Baneling";"Zergling";429;0
"Unit";"Baneling";"Zergling";429;0
"Unit";"Baneling";"Zergling";429;0
"Unit";"Baneling";"Zergling";429;0
"Unit";"Zergling";"Larva";429;1
"Unit";"Zergling";"Larva";430;1
"Unit";"Zergling";"Larva";431;1
"Unit";"Zergling";"Larva";432;1
"Unit";"Zergling";"Larva";433;1
"Unit";"Zergling";"Larva";434;1
"Unit";"Zergling";"Larva";435;1
"Unit";"Zergling";"Larva";436;1
"Unit";"Zergling";"Larva";437;1
"Unit";"Zergling";"Larva";438;1
"Unit";"Baneling";"Zergling";439;0
"Unit";"Baneling";"Zergling";439;0
"Unit";"Baneling";"Zergling";439;0
"Unit";"Baneling";"Zergling";439;0
"Unit";"Baneling";"Zergling";439;0
"Unit";"Baneling";"Zergling";439;0
"Unit";"Ultralisk";"Larva";439;6
"Unit";"Zergling";"Larva";445;1
"Unit";"Zergling";"Larva";446;1
"Unit";"Zergling";"Larva";447;1
"Unit";"Zergling";"Larva";448;1
"Unit";"Zergling";"Larva";449;1
"Unit";"Zergling";"Larva";450;1
"Unit";"Zergling";"Larva";451;1
"Unit";"Zergling";"Larva";452;1
"Unit";"Zergling";"Larva";453;1
"Unit";"Zergling";"Larva";454;1
"Unit";"Zergling";"Larva";455;1
"Unit";"Zergling";"Larva";456;1
"Unit";"Zergling";"Larva";457;1
"Unit";"Zergling";"Larva";458;1
"Unit";"Zergling";"Larva";459;1
"Unit";"Zergling";"Larva";460;1
"Unit";"Zergling";"Larva";461;1
"Unit";"Zergling";"Larva";462;1
"Unit";"Zergling";"Larva";463;1
"Unit";"Zergling";"Larva";464;1
"Unit";"Zergling";"Larva";465;1
"Unit";"Zergling";"Larva";466;1
"Unit";"Zergling";"Larva";467;1
"Unit";"Zergling";"Larva";468;1
"Unit";"Ultralisk";"Larva";469;6
"Unit";"Ultralisk";"Larva";475;6
"Unit";"Ultralisk";"Larva";481;6
"Unit";"Ultralisk";"Larva";487;6
"Unit";"Zergling";"Larva";493;1
"Unit";"Zergling";"Larva";494;1
"Unit";"Zergling";"Larva";495;1
"Unit";"Zergling";"Larva";496;1
"Unit";"Viper";"Larva";497;3
"Building";"CreepTumor";NA;500;0
"Building";"CreepTumorQueen";NA;500;0
"Building";"CreepTumor";NA;500;0
"Building";"CreepTumorQueen";NA;500;0
"Building";"CreepTumor";NA;500;0
"Building";"CreepTumorQueen";NA;500;0
"Building";"CreepTumor";NA;500;0
"Building";"CreepTumorQueen";NA;500;0
"Building";"CreepTumorQueen";NA;500;0
"Building";"CreepTumor";NA;500;0
"Building";"CreepTumor";NA;500;0
"Building";"CreepTumorQueen";NA;500;0
"Building";"CreepTumorQueen";NA;500;0
"Building";"Hatchery";NA;500;0
"Building";"CreepTumorQueen";NA;500;0
"Unit";"Zergling";"Larva";500;1
"Unit";"Zergling";"Larva";501;1
"Unit";"Zergling";"Larva";502;1
"Unit";"Zergling";"Larva";503;1
"Unit";"Zergling";"Larva";504;1
"Unit";"Zergling";"Larva";505;1
"Unit";"Zergling";"Larva";506;1
"Unit";"Zergling";"Larva";507;1
"Building";"Spire";NA;508;0
"Unit";"Zergling";"Larva";508;1
"Unit";"Zergling";"Larva";509;1
"Unit";"Zergling";"Larva";510;1
"Unit";"Zergling";"Larva";511;1
"Unit";"Overlord";"Larva";512;0
"Unit";"Overlord";"Larva";512;0
"Building";"EvolutionChamber";NA;512;0
"Building";"EvolutionChamber";NA;512;0
"Building";"CreepTumor";NA;512;0
"Building";"CreepTumor";NA;512;0
"Building";"CreepTumor";NA;512;0
"Building";"CreepTumor";NA;512;0
"Building";"CreepTumor";NA;512;0
"Building";"CreepTumor";NA;512;0
"Unit";"Baneling";"Zergling";512;0
"Unit";"Baneling";"Zergling";512;0
"Unit";"Baneling";"Zergling";512;0
"Unit";"Baneling";"Zergling";512;0
"Unit";"Baneling";"Zergling";512;0
"Unit";"Baneling";"Zergling";512;0
"Unit";"Baneling";"Zergling";512;0
"Unit";"Baneling";"Zergling";512;0
"Unit";"Baneling";"Zergling";512;0
"Unit";"Baneling";"Zergling";512;0
"Unit";"Baneling";"Zergling";512;0
"Unit";"Baneling";"Zergling";512;0
"Unit";"Baneling";"Zergling";512;0
"Unit";"Baneling";"Zergling";512;0
"Unit";"Baneling";"Zergling";512;0
"Unit";"Baneling";"Zergling";512;0
"Building";"CreepTumor";NA;512;0
"Building";"CreepTumor";NA;512;0
"Unit";"Overlord";"Larva";512;0
"Unit";"Overlord";"Larva";512;0
"Building";"CreepTumor";NA;512;0
"Unit";"Overlord";"Larva";512;0
"Building";"CreepTumor";NA;512;0
"Unit";"Overlord";"Larva";512;0
"Unit";"Overlord";"Larva";512;0
"Building";"CreepTumor";NA;512;0
"Building";"CreepTumor";NA;512;0
"Building";"CreepTumor";NA;512;0
"Building";"CreepTumorQueen";NA;512;0
"Unit";"Zergling";"Larva";512;1
"Unit";"Zergling";"Larva";513;1
"Unit";"Zergling";"Larva";514;1
"Unit";"Zergling";"Larva";515;1
"Unit";"Zergling";"Larva";516;1
"Unit";"Zergling";"Larva";517;1
"Unit";"Zergling";"Larva";518;1
"Unit";"Zergling";"Larva";519;1
"Unit";"Zergling";"Larva";520;1
"Unit";"Zergling";"Larva";521;1
"Unit";"Zergling";"Larva";522;1
"Unit";"Zergling";"Larva";523;1
"Unit";"Zergling";"Larva";524;1
"Unit";"Zergling";"Larva";525;1
"Unit";"Zergling";"Larva";526;1
"Unit";"Zergling";"Larva";527;1
"Unit";"Zergling";"Larva";528;1
"Unit";"Zergling";"Larva";529;1
"Unit";"Zergling";"Larva";530;1
"Unit";"Zergling";"Larva";531;1
"Unit";"Zergling";"Larva";532;1
"Unit";"Zergling";"Larva";533;1
"Unit";"Zergling";"Larva";534;1
"Unit";"Zergling";"Larva";535;1
"Unit";"Zergling";"Larva";536;1
"Unit";"Zergling";"Larva";537;1
"Unit";"Zergling";"Larva";538;1
"Unit";"Zergling";"Larva";539;1
"Unit";"Zergling";"Larva";540;1
"Unit";"Zergling";"Larva";541;1
"Unit";"Zergling";"Larva";542;1
"Unit";"Zergling";"Larva";543;1
"Unit";"Zergling";"Larva";544;1
"Unit";"Zergling";"Larva";545;1
"Unit";"Zergling";"Larva";546;1
"Unit";"Zergling";"Larva";547;1
"Building";"CreepTumor";NA;548;0
"Building";"CreepTumor";NA;548;0
"Unit";"Zergling";"Larva";548;1
"Unit";"Zergling";"Larva";549;1
"Unit";"Zergling";"Larva";550;1
"Unit";"Zergling";"Larva";551;1
"Unit";"Zergling";"Larva";552;1
"Unit";"Zergling";"Larva";553;1
"Unit";"Zergling";"Larva";554;1
"Unit";"Zergling";"Larva";555;1
"Unit";"Zergling";"Larva";556;1
"Unit";"Zergling";"Larva";557;1
"Unit";"Zergling";"Larva";558;1
"Unit";"Zergling";"Larva";559;1
"Unit";"Zergling";"Larva";560;1
"Unit";"Zergling";"Larva";561;1
"Unit";"Zergling";"Larva";562;1
"Unit";"Zergling";"Larva";563;1
"Unit";"Zergling";"Larva";564;1
"Unit";"Zergling";"Larva";565;1
"Building";"CreepTumor";NA;566;0
"Building";"CreepTumor";NA;566;0
"Building";"CreepTumor";NA;566;0
"Building";"CreepTumor";NA;566;0
"Building";"CreepTumor";NA;566;0
"Building";"CreepTumor";NA;566;0
"Building";"CreepTumor";NA;566;0
"Building";"CreepTumor";NA;566;0
"Building";"CreepTumor";NA;566;0
"Building";"CreepTumor";NA;566;0
"Unit";"Zergling";"Larva";568;1
"Unit";"Zergling";"Larva";569;1
"Unit";"Zergling";"Larva";570;1
"Unit";"Zergling";"Larva";571;1
"Unit";"Zergling";"Larva";572;1
"Unit";"Zergling";"Larva";573;1
"Unit";"Zergling";"Larva";574;1
"Unit";"Zergling";"Larva";575;1
"Unit";"Zergling";"Larva";576;1
"Unit";"Zergling";"Larva";577;1
"Unit";"Zergling";"Larva";578;1
"Unit";"Zergling";"Larva";579;1
"Unit";"Zergling";"Larva";580;1
"Unit";"Zergling";"Larva";581;1
"Unit";"Zergling";"Larva";582;1
"Unit";"Zergling";"Larva";583;1
"Unit";"Zergling";"Larva";584;1
"Unit";"Zergling";"Larva";585;1
"Unit";"Zergling";"Larva";586;1
"Unit";"Zergling";"Larva";587;1
"Unit";"Zergling";"Larva";588;1
"Unit";"Zergling";"Larva";589;1
"Unit";"Zergling";"Larva";590;1
"Unit";"Zergling";"Larva";591;1
"Unit";"Zergling";"Larva";592;1
"Unit";"Zergling";"Larva";593;1
"Unit";"Zergling";"Larva";594;1
"Unit";"Zergling";"Larva";595;1
"Unit";"Zergling";"Larva";596;1
"Unit";"Zergling";"Larva";597;1
"Unit";"Zergling";"Larva";598;1
"Unit";"Zergling";"Larva";599;1
"Unit";"Zergling";"Larva";600;1
"Unit";"Zergling";"Larva";601;1
"Unit";"Zergling";"Larva";602;1
"Unit";"Zergling";"Larva";603;1
"Unit";"Zergling";"Larva";604;1
"Unit";"Zergling";"Larva";605;1
"Unit";"Zergling";"Larva";606;1
"Unit";"Zergling";"Larva";607;1
"Unit";"Zergling";"Larva";608;1
"Unit";"Zergling";"Larva";609;1
"Unit";"Zergling";"Larva";610;1
"Unit";"Zergling";"Larva";611;1
"Unit";"Zergling";"Larva";612;1
"Unit";"Zergling";"Larva";613;1
"Unit";"Zergling";"Larva";614;1
"Unit";"Zergling";"Larva";615;1
"Unit";"Zergling";"Larva";616;1
"Unit";"Zergling";"Larva";617;1
"Unit";"Zergling";"Larva";618;1
"Unit";"Zergling";"Larva";619;1
"Unit";"Zergling";"Larva";620;1
"Unit";"Zergling";"Larva";621;1
"Unit";"Zergling";"Larva";622;1
"Unit";"Zergling";"Larva";623;1
"Unit";"Zergling";"Larva";624;1
"Unit";"Zergling";"Larva";625;1
"Unit";"Zergling";"Larva";626;1
"Unit";"Zergling";"Larva";627;1
"Unit";"Zergling";"Larva";628;1
"Unit";"Zergling";"Larva";629;1
"Upgrade";"SprayZerg";NA;630;0
"Upgrade";"SprayZerg";NA;630;0
"Upgrade";"SprayZerg";NA;630;0
"Upgrade";"SprayZerg";NA;630;0
"Upgrade";"zerglingmovementspeed";NA;630;0
"Upgrade";"SprayZerg";NA;630;0
"Upgrade";"ZergGroundArmorsLevel1";NA;630;0
"Upgrade";"SprayZerg";NA;630;0
"Upgrade";"SprayZerg";NA;630;0
"Upgrade";"EvolveMuscularAugments";NA;630;0
"Upgrade";"SprayZerg";NA;630;0
"Upgrade";"CentrificalHooks";NA;630;0
"Upgrade";"ZergMeleeWeaponsLevel1";NA;630;0
"Upgrade";"ZergGroundArmorsLevel2";NA;630;0
"Upgrade";"SprayZerg";NA;630;0
"Upgrade";"SprayZerg";NA;630;0
"Upgrade";"ZergMeleeWeaponsLevel2";NA;630;0
"Upgrade";"zerglingattackspeed";NA;630;0
"Upgrade";"SprayZerg";NA;630;0
"Upgrade";"SprayZerg";NA;630;0
