"type";"unit_name";"on_building";"total_supply_lag";"supply"
"Building";"Pylon";NA;14;0
"Building";"Gateway";NA;16;0
"Building";"Assimilator";NA;17;0
"Building";"Nexus";NA;20;0
"Building";"CyberneticsCore";NA;20;0
"Building";"Assimilator";NA;21;0
"Building";"Pylon";NA;22;0
"Unit";"Adept";"Gateway";23;2
"Building";"Stargate";NA;26;0
"Unit";"Adept";"Gateway";27;2
"Unit";"Oracle";"Stargate";33;3
"Unit";"Adept";"Gateway";36;2
"Building";"TwilightCouncil";NA;43;0
"Building";"Gateway";NA;44;0
"Unit";"Phoenix";"Stargate";44;2
"Building";"Pylon";NA;47;0
"Building";"Gateway";NA;47;0
"Building";"Pylon";NA;47;0
"Building";"Pylon";NA;51;0
"Building";"Assimilator";NA;52;0
"Unit";"Adept";"Gateway";53;2
"Unit";"Adept";"Gateway";55;2
"Unit";"Adept";"Gateway";59;2
"Unit";"Adept";"Gateway";61;2
"Unit";"Adept";"Gateway";63;2
"Building";"Nexus";NA;65;0
"Building";"Pylon";NA;65;0
"Unit";"Adept";"Gateway";67;2
"Building";"Pylon";NA;69;0
"Unit";"Adept";"Gateway";69;2
"Unit";"Adept";"Gateway";71;2
"Building";"Assimilator";NA;75;0
"Building";"Forge";NA;75;0
"Building";"RoboticsFacility";NA;75;0
"Unit";"Adept";"Gateway";78;2
"Unit";"Adept";"Gateway";80;2
"Unit";"Adept";"Gateway";82;2
"Building";"OracleStasisTrap";NA;86;0
"Building";"TemplarArchive";NA;87;0
"Building";"Gateway";NA;90;0
"Building";"Gateway";NA;90;0
"Building";"Gateway";NA;90;0
"Building";"Gateway";NA;90;0
"Unit";"Adept";"Gateway";90;2
"Unit";"Adept";"Gateway";92;2
"Unit";"Adept";"Gateway";94;2
"Upgrade";"ProtossGroundWeaponsLevel1";"Forge";96;0
"Unit";"Zealot";"Gateway";99;2
"Unit";"Zealot";"Gateway";101;2
"Unit";"Zealot";"Gateway";103;2
"Building";"Pylon";NA;105;0
"Upgrade";"Charge";"TwilightCouncil";105;0
"Building";"Pylon";NA;108;0
"Building";"HighTemplar";NA;108;0
"Building";"HighTemplar";NA;108;0
"Building";"HighTemplar";NA;108;0
"Unit";"Zealot";"Gateway";108;2
"Unit";"Zealot";"Gateway";110;2
"Unit";"Zealot";"Gateway";112;2
"Building";"Assimilator";NA;114;0
"Building";"Assimilator";NA;114;0
"Building";"PhotonCannon";NA;114;0
"Building";"Pylon";NA;117;0
"Unit";"Observer";"Robotics Facility";117;1
"Building";"HighTemplar";NA;118;0
"Building";"Gateway";NA;121;0
"Building";"Gateway";NA;121;0
"Building";"Gateway";NA;121;0
"Unit";"Immortal";"Robotics Facility";121;4
"Unit";"Zealot";"Gateway";125;2
"Unit";"Zealot";"Gateway";127;2
"Unit";"Zealot";"Gateway";129;2
"Unit";"Zealot";"Gateway";131;2
"Unit";"Zealot";"Gateway";133;2
"Building";"Pylon";NA;135;0
"Unit";"Zealot";"Gateway";135;2
"Unit";"Zealot";"Gateway";137;2
"Upgrade";"ProtossGroundWeaponsLevel2";"Forge";139;0
"Building";"Pylon";NA;139;0
"Building";"Pylon";NA;139;0
"Building";"Pylon";NA;139;0
"Building";"Pylon";NA;139;0
"Building";"Pylon";NA;139;0
"Unit";"Immortal";"Robotics Facility";139;4
"Building";"HighTemplar";NA;143;0
"Building";"HighTemplar";NA;143;0
"Building";"HighTemplar";NA;143;0
"Building";"HighTemplar";NA;143;0
"Unit";"Archon";"High Templar";146;0
"Unit";"Archon";"High Templar";146;0
"Building";"Nexus";NA;146;0
"Unit";"Zealot";"Gateway";146;2
"Unit";"Zealot";"Gateway";148;2
"Unit";"Zealot";"Gateway";150;2
"Unit";"Zealot";"Gateway";152;2
"Building";"HighTemplar";NA;154;0
"Building";"HighTemplar";NA;154;0
"Unit";"Archon";"High Templar";154;0
"Unit";"Immortal";"Robotics Facility";154;4
"Building";"HighTemplar";NA;158;0
"Building";"HighTemplar";NA;158;0
"Unit";"Zealot";"Gateway";158;2
"Unit";"Zealot";"Gateway";160;2
"Unit";"Zealot";"Gateway";162;2
"Unit";"Zealot";"Gateway";164;2
"Unit";"Zealot";"Gateway";166;2
"Unit";"Zealot";"Gateway";168;2
"Unit";"Archon";"High Templar";170;0
"Building";"PhotonCannon";NA;170;0
"Building";"HighTemplar";NA;170;0
"Building";"HighTemplar";NA;170;0
"Unit";"Zealot";"Gateway";170;2
"Unit";"Zealot";"Gateway";172;2
"Unit";"Zealot";"Gateway";174;2
"Unit";"Zealot";"Gateway";176;2
"Unit";"Zealot";"Gateway";178;2
"Unit";"Zealot";"Gateway";180;2
"Unit";"Archon";"High Templar";182;0
"Unit";"Zealot";"Gateway";182;2
"Unit";"Zealot";"Gateway";184;2
"Unit";"Immortal";"Robotics Facility";186;4
"Building";"HighTemplar";NA;190;0
"Building";"HighTemplar";NA;190;0
"Unit";"Zealot";"Gateway";190;2
"Unit";"Zealot";"Gateway";192;2
"Unit";"Zealot";"Gateway";194;2
"Unit";"Zealot";"Gateway";196;2
"Unit";"Zealot";"Gateway";198;2
"Unit";"Zealot";"Gateway";200;2
"Unit";"Zealot";"Gateway";202;2
"Unit";"Zealot";"Gateway";204;2
"Unit";"Immortal";"Robotics Facility";206;4
"Building";"Nexus";NA;210;0
"Building";"Pylon";NA;210;0
"Building";"HighTemplar";NA;210;0
"Building";"HighTemplar";NA;210;0
"Building";"HighTemplar";NA;210;0
"Building";"HighTemplar";NA;210;0
"Unit";"Archon";"High Templar";210;0
"Unit";"Archon";"High Templar";210;0
"Unit";"Zealot";"Gateway";210;2
"Unit";"Zealot";"Gateway";212;2
"Unit";"Zealot";"Gateway";214;2
"Unit";"Zealot";"Gateway";216;2
"Unit";"Zealot";"Gateway";218;2
"Unit";"Zealot";"Gateway";220;2
"Unit";"Archon";"High Templar";222;0
"Unit";"Zealot";"Gateway";222;2
"Unit";"Zealot";"Gateway";224;2
"Unit";"Zealot";"Gateway";226;2
"Unit";"Zealot";"Gateway";228;2
"Unit";"Zealot";"Gateway";230;2
"Upgrade";"ProtossGroundWeaponsLevel3";"Forge";232;0
"Unit";"Zealot";"Gateway";232;2
"Unit";"Zealot";"Gateway";234;2
"Unit";"Zealot";"Gateway";236;2
"Unit";"Zealot";"Gateway";238;2
"Building";"Assimilator";NA;240;0
"Unit";"Immortal";"Robotics Facility";240;4
"Building";"Assimilator";NA;244;0
"Building";"HighTemplar";NA;244;0
"Building";"HighTemplar";NA;244;0
"Building";"HighTemplar";NA;244;0
"Building";"HighTemplar";NA;244;0
"Unit";"Zealot";"Gateway";244;2
"Unit";"Zealot";"Gateway";246;2
"Unit";"Zealot";"Gateway";248;2
"Unit";"Zealot";"Gateway";250;2
"Unit";"Zealot";"Gateway";252;2
"Unit";"Immortal";"Robotics Facility";254;4
"Unit";"Zealot";"Gateway";258;2
"Unit";"Zealot";"Gateway";260;2
"Unit";"Zealot";"Gateway";262;2
"Unit";"Zealot";"Gateway";264;2
"Unit";"Zealot";"Gateway";266;2
"Unit";"Zealot";"Gateway";268;2
"Unit";"Zealot";"Gateway";270;2
"Unit";"Zealot";"Gateway";272;2
"Unit";"Zealot";"Gateway";274;2
"Unit";"Immortal";"Robotics Facility";276;4
"Building";"HighTemplar";NA;280;0
"Building";"HighTemplar";NA;280;0
"Building";"HighTemplar";NA;280;0
"Building";"HighTemplar";NA;280;0
"Building";"HighTemplar";NA;280;0
"Building";"HighTemplar";NA;280;0
"Building";"HighTemplar";NA;280;0
"Building";"HighTemplar";NA;280;0
"Unit";"Zealot";"Gateway";280;2
"Unit";"Zealot";"Gateway";282;2
"Unit";"Immortal";"Robotics Facility";284;4
"Building";"HighTemplar";NA;288;0
"Building";"HighTemplar";NA;288;0
"Building";"HighTemplar";NA;288;0
"Building";"HighTemplar";NA;288;0
"Unit";"Zealot";"Gateway";288;2
"Unit";"Zealot";"Gateway";290;2
"Unit";"Zealot";"Gateway";292;2
"Unit";"Zealot";"Gateway";294;2
"Unit";"Archon";"High Templar";296;0
"Unit";"Zealot";"Gateway";296;2
"Building";"HighTemplar";NA;298;0
"Building";"HighTemplar";NA;298;0
"Unit";"Zealot";"Gateway";298;2
"Unit";"Zealot";"Gateway";300;2
"Unit";"Archon";"High Templar";302;0
"Building";"HighTemplar";NA;302;0
"Building";"HighTemplar";NA;302;0
"Unit";"Archon";"High Templar";302;0
"Building";"Nexus";NA;302;0
"Unit";"Zealot";"Gateway";302;2
"Unit";"Zealot";"Gateway";304;2
"Unit";"Zealot";"Gateway";306;2
"Unit";"Zealot";"Gateway";308;2
"Unit";"Zealot";"Gateway";310;2
"Unit";"Archon";"High Templar";312;0
"Unit";"Zealot";"Gateway";312;2
"Unit";"Zealot";"Gateway";314;2
"Unit";"Archon";"High Templar";316;0
"Unit";"Zealot";"Gateway";316;2
"Unit";"Zealot";"Gateway";318;2
"Building";"HighTemplar";NA;320;0
"Building";"HighTemplar";NA;320;0
"Building";"HighTemplar";NA;320;0
"Building";"HighTemplar";NA;320;0
"Building";"Assimilator";NA;320;0
"Building";"Assimilator";NA;320;0
"Building";"Pylon";NA;320;0
"Unit";"Zealot";"Gateway";320;2
"Unit";"Zealot";"Gateway";322;2
"Unit";"Zealot";"Gateway";324;2
"Unit";"Zealot";"Gateway";326;2
"Building";"HighTemplar";NA;328;0
"Building";"HighTemplar";NA;328;0
"Unit";"Archon";"High Templar";328;0
"Building";"HighTemplar";NA;328;0
"Building";"HighTemplar";NA;328;0
"Unit";"Zealot";"Gateway";328;2
"Unit";"Zealot";"Gateway";330;2
"Unit";"Zealot";"Gateway";332;2
"Unit";"Zealot";"Gateway";334;2
"Unit";"Zealot";"Gateway";336;2
"Unit";"Archon";"High Templar";338;0
"Building";"PhotonCannon";NA;338;0
"Building";"Pylon";NA;338;0
"Unit";"Observer";"Robotics Facility";338;1
"Unit";"Zealot";"Gateway";339;2
"Unit";"Zealot";"Gateway";341;2
"Building";"Pylon";NA;343;0
"Building";"HighTemplar";NA;343;0
"Building";"HighTemplar";NA;343;0
"Building";"HighTemplar";NA;343;0
"Building";"HighTemplar";NA;343;0
"Unit";"Archon";"High Templar";343;0
"Unit";"Archon";"High Templar";343;0
"Unit";"Zealot";"Gateway";343;2
"Unit";"Zealot";"Gateway";345;2
"Unit";"Zealot";"Gateway";347;2
"Unit";"Zealot";"Gateway";349;2
"Unit";"Zealot";"Gateway";351;2
"Building";"Assimilator";NA;353;0
"Upgrade";"SprayProtoss";NA;353;0
"Upgrade";"SprayProtoss";NA;353;0
"Upgrade";"WarpGateResearch";NA;353;0
"Upgrade";"SprayProtoss";NA;353;0
"Upgrade";"AdeptPiercingAttack";NA;353;0
"Upgrade";"SprayProtoss";NA;353;0
"Upgrade";"PsiStormTech";NA;353;0
"Upgrade";"SprayProtoss";NA;353;0
"Upgrade";"SprayProtoss";NA;353;0
"Upgrade";"SprayProtoss";NA;353;0
"Upgrade";"SprayProtoss";NA;353;0
"Upgrade";"SprayProtoss";NA;353;0
"Upgrade";"SprayProtoss";NA;353;0
"Upgrade";"SprayProtoss";NA;353;0
"Upgrade";"SprayProtoss";NA;353;0
