"type";"unit_name";"on_building";"total_supply";"supply"
"Building";"Pylon";NA;15;0
"Building";"Pylon";NA;15;0
"Building";"Gateway";NA;15;0
"Building";"Gateway";NA;15;0
"Building";"Gateway";NA;15;0
"Unit";"Zealot";"Gateway";15;2
"Unit";"Zealot";"Gateway";15;2
"Building";"Pylon";NA;15;0
"Unit";"Zealot";"Gateway";15;2
"Building";"Pylon";NA;19;0
"Unit";"Zealot";"Gateway";15;2
