"type";"unit_name";"on_building";"total_supply";"supply"
"Building";"Pylon";NA;13;0
"Building";"Assimilator";NA;16;0
"Building";"Assimilator";NA;17;0
"Building";"Gateway";NA;15;0
"Building";"Pylon";NA;21;0
"Building";"Gateway";NA;19;0
"Building";"CyberneticsCore";NA;20;0
"Building";"Pylon";NA;24;0
"Unit";"Stalker";"Gateway";23;2
"Unit";"Stalker";"Gateway";23;2
"Unit";"Sentry";"Gateway";28;2
"Unit";"Stalker";"Gateway";28;2
"Building";"RoboticsFacility";NA;29;0
"Building";"ShieldBattery";NA;34;0
"Building";"Nexus";NA;28;0
"Building";"ShieldBattery";NA;35;0
"Unit";"Phoenix";"Stargate";36;2
"Unit";"Observer";"Robotics Facility";36;1
"Building";"TwilightCouncil";NA;36;0
"Unit";"Observer";"Robotics Facility";44;1
"Building";"Forge";NA;48;0
"Building";"Pylon";NA;55;0
"Building";"Gateway";NA;53;0
"Building";"Gateway";NA;53;0
"Unit";"Zealot";"Gateway";55;2
"Unit";"Zealot";"Gateway";55;2
"Building";"Gateway";NA;53;0
"Building";"Gateway";NA;55;0
"Upgrade";"Charge";"TwilightCouncil";51;0
"Building";"Gateway";NA;55;0
"Building";"Pylon";NA;59;0
"Building";"Assimilator";NA;59;0
"Building";"Gateway";NA;55;0
"Unit";"Zealot";"Gateway";60;2
"Unit";"Zealot";"Gateway";60;2
"Unit";"Zealot";"Gateway";60;2
"Unit";"Zealot";"Gateway";60;2
"Building";"Pylon";NA;59;0
"Unit";"Zealot";"Gateway";68;2
"Unit";"Zealot";"Gateway";68;2
"Unit";"Zealot";"Gateway";72;2
"Unit";"Zealot";"Gateway";72;2
"Building";"TemplarArchive";NA;60;0
"Building";"Nexus";NA;55;0
"Upgrade";"ProtossGroundWeaponsLevel1";"Forge";55;0
"Building";"HighTemplar";NA;78;0
"Building";"HighTemplar";NA;78;0
"Building";"HighTemplar";NA;78;0
"Building";"HighTemplar";NA;78;0
"Unit";"Zealot";"Gateway";78;2
"Unit";"Zealot";"Gateway";78;2
"Unit";"Zealot";"Gateway";78;2
"Building";"Pylon";NA;76;0
"Unit";"Zealot";"Gateway";85;2
"Unit";"Archon";"High Templar";84;0
"Unit";"Archon";"High Templar";84;0
"Building";"Pylon";NA;84;0
"Building";"Pylon";NA;85;0
"Unit";"Zealot";"Gateway";87;2
"Unit";"Zealot";"Gateway";87;2
"Unit";"Zealot";"Gateway";87;2
"Unit";"Zealot";"Gateway";88;2
"Unit";"Zealot";"Gateway";98;2
"Unit";"Zealot";"Gateway";98;2
"Unit";"Zealot";"Gateway";98;2
"Unit";"Zealot";"Gateway";98;2
"Unit";"Zealot";"Gateway";98;2
"Unit";"Zealot";"Gateway";98;2
"Unit";"Zealot";"Gateway";113;2
"Unit";"Zealot";"Gateway";113;2
"Unit";"Zealot";"Gateway";113;2
"Unit";"Zealot";"Gateway";113;2
"Unit";"Zealot";"Gateway";113;2
"Building";"Pylon";NA;112;0
"Building";"Pylon";NA;112;0
"Unit";"Zealot";"Gateway";123;2
"Unit";"Zealot";"Gateway";123;2
"Building";"Assimilator";NA;112;0
"Unit";"Zealot";"Gateway";128;2
"Unit";"Zealot";"Gateway";128;2
"Unit";"Zealot";"Gateway";128;2
"Unit";"Zealot";"Gateway";128;2
"Unit";"Zealot";"Gateway";128;2
"Unit";"Zealot";"Gateway";128;2
"Unit";"Zealot";"Gateway";140;2
"Unit";"Zealot";"Gateway";140;2
"Upgrade";"ProtossGroundWeaponsLevel2";"Forge";98;0
"Unit";"Zealot";"Gateway";144;2
"Unit";"Zealot";"Gateway";144;2
"Unit";"Zealot";"Gateway";144;2
"Unit";"Zealot";"Gateway";144;2
"Unit";"Zealot";"Gateway";144;2
"Unit";"Zealot";"Gateway";144;2
"Unit";"Zealot";"Gateway";144;2
"Unit";"Zealot";"Gateway";144;2
"Unit";"Immortal";"Robotics Facility";140;4
"Building";"HighTemplar";NA;165;0
"Building";"HighTemplar";NA;165;0
"Building";"HighTemplar";NA;165;0
"Building";"HighTemplar";NA;165;0
"Unit";"Zealot";"Gateway";165;2
"Unit";"Zealot";"Gateway";165;2
"Unit";"Zealot";"Gateway";165;2
"Unit";"Zealot";"Gateway";165;2
"Unit";"Immortal";"Robotics Facility";146;4
"Unit";"Archon";"High Templar";178;0
"Unit";"Archon";"High Templar";178;0
"Unit";"Immortal";"Robotics Facility";165;4
"Building";"PhotonCannon";NA;178;0
"Building";"Assimilator";NA;178;0
"Building";"Assimilator";NA;178;0
"Building";"PhotonCannon";NA;178;0
"Building";"ShieldBattery";NA;178;0
"Building";"PhotonCannon";NA;178;0
"Building";"Pylon";NA;178;0
"Building";"Pylon";NA;178;0
"Building";"HighTemplar";NA;182;0
"Building";"HighTemplar";NA;182;0
"Building";"HighTemplar";NA;183;0
"Building";"HighTemplar";NA;183;0
"Building";"HighTemplar";NA;183;0
"Building";"HighTemplar";NA;183;0
"Unit";"Zealot";"Gateway";183;2
"Unit";"Zealot";"Gateway";183;2
"Unit";"Archon";"High Templar";183;0
"Unit";"Archon";"High Templar";183;0
"Unit";"Archon";"High Templar";183;0
"Unit";"Immortal";"Robotics Facility";178;4
"Building";"Pylon";NA;187;0
"Building";"Pylon";NA;187;0
"Unit";"Zealot";"Gateway";191;2
"Unit";"Zealot";"Gateway";191;2
"Unit";"Zealot";"Gateway";191;2
"Unit";"Zealot";"Gateway";191;2
"Unit";"Zealot";"Gateway";191;2
"Unit";"Zealot";"Gateway";191;2
"Unit";"Zealot";"Gateway";191;2
"Unit";"Zealot";"Gateway";191;2
"Upgrade";"ProtossGroundWeaponsLevel3";"Forge";165;0
"Unit";"Zealot";"Gateway";207;2
"Unit";"Zealot";"Gateway";207;2
"Unit";"Zealot";"Gateway";207;2
"Unit";"Zealot";"Gateway";207;2
"Unit";"Zealot";"Gateway";207;2
"Unit";"Zealot";"Gateway";207;2
"Unit";"Zealot";"Gateway";207;2
"Building";"Pylon";NA;207;0
"Building";"Pylon";NA;207;0
