"type";"unit_name";"on_building";"total_supply";"supply"
"Building";"Pylon";NA;13;0
"Building";"Assimilator";NA;15;0
"Building";"Pylon";NA;17;0
"Building";"Gateway";NA;15;0
"Building";"Assimilator";NA;18;0
"Building";"CyberneticsCore";NA;18;0
"Building";"Gateway";NA;18;0
"Building";"Gateway";NA;18;0
"Unit";"Adept";"Gateway";20;2
"Unit";"Adept";"Gateway";20;2
"Building";"Pylon";NA;25;0
"Unit";"Adept";"Gateway";21;2
"Unit";"Adept";"Gateway";21;2
