"type";"unit_name";"on_building";"total_supply";"supply"
"Building";"Pylon";NA;13;0
"Building";"Gateway";NA;15;0
"Building";"Assimilator";NA;17;0
"Building";"Assimilator";NA;18;0
"Building";"Gateway";NA;17;0
"Building";"Pylon";NA;20;0
"Building";"CyberneticsCore";NA;19;0
"Unit";"Sentry";"Gateway";22;2
"Unit";"Stalker";"Gateway";22;2
"Building";"Pylon";NA;22;0
"Unit";"Stalker";"Gateway";25;2
"Unit";"Stalker";"Gateway";25;2
"Unit";"Phoenix";"Stargate";32;2
"Building";"ShieldBattery";NA;32;0
"Building";"RoboticsFacility";NA;32;0
"Unit";"Sentry";"Gateway";34;2
"Building";"Nexus";NA;28;0
"Unit";"Sentry";"Gateway";34;2
"Unit";"Stalker";"Gateway";42;2
"Unit";"Stalker";"Gateway";42;2
"Unit";"Observer";"Robotics Facility";40;1
"Building";"TwilightCouncil";NA;47;0
"Building";"Pylon";NA;52;0
"Building";"Pylon";NA;52;0
"Unit";"Immortal";"Robotics Facility";50;4
"Unit";"Phoenix";"Stargate";52;2
"Unit";"Immortal";"Robotics Facility";56;4
"Building";"Pylon";NA;62;0
"Building";"Forge";NA;62;0
"Unit";"Phoenix";"Stargate";65;2
"Building";"TemplarArchive";NA;69;0
"Building";"Assimilator";NA;73;0
"Building";"Assimilator";NA;73;0
"Building";"Nexus";NA;62;0
"Building";"Gateway";NA;70;0
"Building";"Gateway";NA;70;0
"Building";"Gateway";NA;70;0
"Building";"Gateway";NA;71;0
"Unit";"Phoenix";"Stargate";77;2
"Building";"Pylon";NA;77;0
"Building";"Gateway";NA;73;0
"Unit";"Phoenix";"Stargate";77;2
"Building";"Gateway";NA;74;0
"Building";"HighTemplar";NA;90;0
"Building";"HighTemplar";NA;90;0
"Unit";"Zealot";"Gateway";90;2
"Building";"Stargate";NA;77;0
"Unit";"Zealot";"Gateway";90;2
"Unit";"Zealot";"Gateway";90;2
"Unit";"Zealot";"Gateway";90;2
"Unit";"Zealot";"Gateway";90;2
"Unit";"Zealot";"Gateway";90;2
"Building";"Stargate";NA;77;0
"Unit";"Archon";"High Templar";91;0
"Upgrade";"ProtossGroundWeaponsLevel1";"Forge";74;0
"Building";"Pylon";NA;103;0
"Building";"Assimilator";NA;103;0
"Building";"Assimilator";NA;103;0
"Unit";"Phoenix";"Stargate";103;2
"Building";"HighTemplar";NA;108;0
"Building";"Pylon";NA;105;0
"Building";"Pylon";NA;106;0
"Building";"Pylon";NA;106;0
"Building";"Pylon";NA;106;0
"Building";"HighTemplar";NA;111;0
"Unit";"Zealot";"Gateway";111;2
"Unit";"Zealot";"Gateway";111;2
"Unit";"Zealot";"Gateway";111;2
"Unit";"Immortal";"Robotics Facility";104;4
"Building";"Pylon";NA;108;0
"Unit";"Archon";"High Templar";111;0
"Upgrade";"Charge";"TwilightCouncil";87;0
"Unit";"Phoenix";"Stargate";110;2
"Unit";"Phoenix";"Stargate";110;2
"Building";"HighTemplar";NA;125;0
"Building";"HighTemplar";NA;125;0
"Building";"HighTemplar";NA;125;0
"Building";"Pylon";NA;125;0
"Building";"HighTemplar";NA;125;0
"Unit";"Zealot";"Gateway";125;2
"Unit";"Zealot";"Gateway";125;2
"Unit";"Zealot";"Gateway";125;2
"Unit";"Zealot";"Gateway";125;2
"Unit";"Archon";"High Templar";125;0
"Unit";"Archon";"High Templar";125;0
"Building";"Pylon";NA;133;0
"Building";"Pylon";NA;133;0
"Building";"Gateway";NA;125;0
"Building";"Pylon";NA;133;0
"Building";"Gateway";NA;125;0
"Building";"Pylon";NA;133;0
"Building";"Gateway";NA;125;0
"Building";"Pylon";NA;134;0
"Building";"HighTemplar";NA;138;0
"Building";"HighTemplar";NA;138;0
"Building";"HighTemplar";NA;138;0
"Building";"HighTemplar";NA;138;0
"Building";"HighTemplar";NA;138;0
"Unit";"Zealot";"Gateway";138;2
"Unit";"Zealot";"Gateway";138;2
"Unit";"Zealot";"Gateway";138;2
"Unit";"Archon";"High Templar";138;0
"Unit";"Archon";"High Templar";138;0
"Building";"PhotonCannon";NA;136;0
"Building";"PhotonCannon";NA;136;0
"Unit";"Phoenix";"Stargate";138;2
"Unit";"Zealot";"Gateway";149;2
"Unit";"Zealot";"Gateway";149;2
"Unit";"Zealot";"Gateway";149;2
"Unit";"Zealot";"Gateway";149;2
"Unit";"Zealot";"Gateway";149;2
"Unit";"Zealot";"Gateway";149;2
"Building";"ShieldBattery";NA;144;0
"Building";"Nexus";NA;135;0
"Unit";"Zealot";"Gateway";161;2
"Unit";"Zealot";"Gateway";161;2
"Unit";"Zealot";"Gateway";161;2
"Unit";"Phoenix";"Stargate";149;2
"Unit";"Phoenix";"Stargate";149;2
"Upgrade";"ProtossGroundWeaponsLevel2";"Forge";134;0
"Unit";"Zealot";"Gateway";177;2
"Unit";"Zealot";"Gateway";177;2
"Unit";"Zealot";"Gateway";177;2
"Unit";"Zealot";"Gateway";177;2
"Unit";"Zealot";"Gateway";177;2
"Unit";"Zealot";"Gateway";177;2
"Unit";"Zealot";"Gateway";177;2
"Unit";"Zealot";"Gateway";177;2
"Unit";"Zealot";"Gateway";177;2
"Unit";"Zealot";"Gateway";177;2
"Unit";"Zealot";"Gateway";177;2
"Unit";"Phoenix";"Stargate";177;2
"Building";"HighTemplar";NA;201;0
"Building";"HighTemplar";NA;201;0
"Building";"HighTemplar";NA;201;0
"Building";"HighTemplar";NA;201;0
"Building";"HighTemplar";NA;201;0
"Building";"HighTemplar";NA;201;0
"Unit";"Zealot";"Gateway";201;2
"Unit";"Zealot";"Gateway";201;2
"Unit";"Zealot";"Gateway";201;2
"Unit";"Zealot";"Gateway";201;2
"Unit";"Zealot";"Gateway";201;2
"Unit";"Archon";"High Templar";201;0
"Unit";"Archon";"High Templar";201;0
"Unit";"Archon";"High Templar";201;0
"Unit";"Phoenix";"Stargate";201;2
"Unit";"Phoenix";"Stargate";201;2
"Building";"Assimilator";NA;211;0
"Unit";"Immortal";"Robotics Facility";201;4
"Unit";"Phoenix";"Stargate";211;2
"Unit";"Phoenix";"Stargate";211;2
"Unit";"Zealot";"Gateway";227;2
"Unit";"Zealot";"Gateway";227;2
"Unit";"Zealot";"Gateway";227;2
"Unit";"Zealot";"Gateway";227;2
"Unit";"Zealot";"Gateway";227;2
"Unit";"Zealot";"Gateway";227;2
"Unit";"Zealot";"Gateway";227;2
"Unit";"Phoenix";"Stargate";223;2
"Building";"HighTemplar";NA;245;0
"Building";"HighTemplar";NA;245;0
"Building";"HighTemplar";NA;245;0
"Building";"HighTemplar";NA;245;0
"Building";"HighTemplar";NA;245;0
"Building";"HighTemplar";NA;245;0
"Unit";"Phoenix";"Stargate";243;2
"Unit";"Phoenix";"Stargate";243;2
"Unit";"Zealot";"Gateway";245;2
"Unit";"Zealot";"Gateway";245;2
"Unit";"Zealot";"Gateway";245;2
"Unit";"Zealot";"Gateway";245;2
"Unit";"Zealot";"Gateway";245;2
"Unit";"Archon";"High Templar";245;0
"Unit";"Archon";"High Templar";245;0
"Unit";"Archon";"High Templar";259;0
"Building";"Pylon";NA;259;0
"Building";"Nexus";NA;241;0
"Building";"PhotonCannon";NA;259;0
"Building";"HighTemplar";NA;264;0
"Building";"HighTemplar";NA;264;0
"Building";"HighTemplar";NA;265;0
"Building";"HighTemplar";NA;265;0
"Unit";"Zealot";"Gateway";265;2
"Unit";"Zealot";"Gateway";265;2
"Unit";"Zealot";"Gateway";265;2
"Unit";"Zealot";"Gateway";265;2
"Unit";"Zealot";"Gateway";265;2
"Unit";"Zealot";"Gateway";265;2
"Unit";"Archon";"High Templar";265;0
"Unit";"Archon";"High Templar";265;0
"Unit";"Zealot";"Gateway";277;2
"Unit";"Zealot";"Gateway";277;2
"Unit";"Zealot";"Gateway";277;2
"Unit";"Zealot";"Gateway";277;2
"Unit";"Zealot";"Gateway";277;2
"Unit";"Zealot";"Gateway";277;2
"Unit";"Zealot";"Gateway";277;2
"Unit";"Phoenix";"Stargate";277;2
"Unit";"Phoenix";"Stargate";277;2
"Unit";"Immortal";"Robotics Facility";277;4
"Unit";"Zealot";"Gateway";299;2
"Unit";"Zealot";"Gateway";299;2
"Unit";"Zealot";"Gateway";299;2
"Unit";"Zealot";"Gateway";299;2
"Unit";"Zealot";"Gateway";299;2
"Unit";"Zealot";"Gateway";299;2
"Unit";"Zealot";"Gateway";299;2
"Unit";"Zealot";"Gateway";299;2
"Unit";"Zealot";"Gateway";299;2
"Unit";"Zealot";"Gateway";299;2
"Unit";"Zealot";"Gateway";299;2
"Building";"HighTemplar";NA;321;0
"Building";"HighTemplar";NA;321;0
"Building";"HighTemplar";NA;321;0
"Building";"HighTemplar";NA;321;0
"Building";"HighTemplar";NA;321;0
"Building";"HighTemplar";NA;321;0
"Building";"HighTemplar";NA;321;0
"Building";"HighTemplar";NA;321;0
"Unit";"Zealot";"Gateway";321;2
"Unit";"Zealot";"Gateway";321;2
"Unit";"Zealot";"Gateway";321;2
"Unit";"Archon";"High Templar";321;0
"Unit";"Archon";"High Templar";321;0
"Unit";"Archon";"High Templar";321;0
"Unit";"Archon";"High Templar";321;0
"Building";"Assimilator";NA;321;0
