"type";"unit_name";"on_building";"total_supply";"supply"
"Building";"Pylon";NA;13;0
"Building";"Assimilator";NA;15;0
"Building";"Gateway";NA;15;0
"Building";"Assimilator";NA;17;0
"Building";"Gateway";NA;17;0
"Building";"Pylon";NA;19;0
"Building";"CyberneticsCore";NA;18;0
"Unit";"Adept";"Gateway";20;2
"Unit";"Adept";"Gateway";20;2
"Building";"Pylon";NA;21;0
"Building";"Stargate";NA;21;0
"Unit";"Stalker";"Gateway";25;2
"Unit";"Stalker";"Gateway";25;2
"Building";"Pylon";NA;26;0
